[{"job_id": "100003009052060", "location_code": "hk", "company": "eMotionLab Limited", "job_title": "Account Servicing Manager/ Project Manager", "description": "If you are a\u00a0Account Servicing Manager (AM) / Project Manager (PM)\u00a0who aspire to plan, oversee and lead meaningful storytelling video projects from ideation to completion,\n\nWe should meet!\n\nWe are looking for high caliber talents to join our\u00a0growing team\u00a0\n... in our\u00a0new spacious office\n\u2026 and to chill out with us in our\u00a0amazing balcony!\n\nAM Responsibilities:\n\nTo develop and maintain good relationship with potential and current clients\nTo accurately identify client needs and provide professional advice\nTo build and maintain harmonized agency-client relationship at all levels\nPrepare and present engaging creative proposal with creative team\nPreparing pricing proposal that engage business while also profitable\n\nPM Responsibilities:\n\nTo manage and utilize resources effectively\u00a0and keep track of multiple works and project status to ensure timely delivery\nTo carry out all duties in planning, coordination, organization and implementation of productions and projects\nTo develop excellent communication with all parties involved (the creative, production team & the client)\nTo coordinate on logistical arrangement for productions\n\nJob Requirements:\n\nUniversity graduate and relevant working experience in agency\nUnderstanding of design, production, motion graphic and animation fundamentals\nWith active network in CG animation, motion graphic & multimedia production industry is an advantage, but not essential\nGood communication and interpersonal skills\nExcellent communication in both written and oral presentations (English and Chinese).\nWell-organized, detail minded and able to work independently\nProficiency in English, Mandarin and Cantonese\nAble to work under pressure\nFresh graduates\u00a0/ candidates with less experience can be considered as Account Servicing Executive/ Production assistant\n\nInterested candidates please include your current and expected salary, website/ samples of your work in your application.\n\nPlease include\u00a0[Account Servicing Manager/ Project Manager]\u00a0in the subject line.\n\nPersonal data collected will be handled strict confidence for recruitment related purpose only.\n", "employment_types": ["Full Time"], "selling_points": ["Account Servicing Manager/ Project Manager", "Convenient location", "5 days work and dynamic working environment"], "locations": ["Wong Tai Sin Area"], "categories": ["Media & Advertising", "Account Servicing", "Strategic Planning", "Design", "Multi-media"], "post_time": "2022-01-17T02:01:19Z", "salary": {"currency": null, "max": null, "min": null, "period": "monthly", "term": null}, "salary_visible": false, "title_keywords": ["project manager", "manager"], "responsibilities": ["implementation", "maintain good relationship", "develop", "communication", "coordinate", "maintain", "coordination", "planning"], "requirements": {"degrees": ["university graduate"], "majors": [], "languages": ["cantonese", "english", "chinese", "mandarin"], "language_level": ["excellent", "proficiency"], "hard_skills": ["cg", "multimedia", "presentations"], "soft_skills": ["oral", "work independently", "well-organized", "communication", "communication and interpersonal skills", "active", "work under pressure"], "languages_combined": [{"language": "cantonese", "language_level": ["proficiency"]}, {"language": "english", "language_level": ["excellent", "proficiency"]}, {"language": "chinese", "language_level": ["excellent"]}, {"language": "mandarin", "language_level": ["proficiency"]}]}, "experience_required": {"duration": [], "field": ["agency", "relevant working experience", "account servicing"]}}, {"job_id": "100003009053143", "location_code": "hk", "company": "Omnicom Media Group", "job_title": "Account Manager (Content and Social)", "description": "Job Responsibilities :\n\nExecute all aspects of digital media campaign executions across different channels\nPerform digital media planning, buying across all products and platforms in the market\nPerform fundamental support for pitch, proposal and projects on a local, national and international basis\nProvide in-\u00addepth analysis to get insights using all obtainable analytics tools.\nAssist Senior Account Manager to achieve all campaign objectives through close monitoring and frequent optimisations.\nProvide clients servicing and answer enquires for corporate clients, advertising agencies and resellers at both local and regional level.\nDeliver accurate updates on campaigns to clients on both overall business and daily campaign performance\nBuild strong, long-term client relationships and maintain frequent contact\n\n\n\nRequirements:\n\n2 years or above experience in a media agency and/or digital marketing related fields.\n\nExperience for working in 4As agency is preferable\nExperience in operating digital advertising platform, (such as\u00a0Facebook, Google, DBM, The Trade Desk...etc) is preferable\nExperience in handling China Related Media platforms (such as\u00a0Baidu, Wechat, Weibo, 360...etc) is preferable\nAble to communicate in Cantonese, English & Mandarin.\nProficient in Chinese language (Simplified & Traditional) and fluent in English.\nStrong interpersonal skills with great attention to details.\nMulti-tasking and able to work under pressure to meet deadlines & business targets.\nPassionate about the Internet and latest online advertising technologies.\n\nBenefits:\n\n5 days Work + Bank Holidays\nCompetitive Remuneration Package & Performance Bonus\nMedical and Dental Insurance after passing probation\nOvertime Meal and Transportation allowance\nProfessional Training in digital marketing & related Technology\nFast track career progression in this growing industry\nEnergetic, Fun, Young, Fast-paced environment", "employment_types": ["Full Time", "Permanent"], "selling_points": ["Free Shuttle Bus & Free Breakfast", "Birthday, Family Day & Self-Love Day Leave", "5-Day Work Week"], "locations": ["Pok Fu Lam"], "categories": ["Media & Advertising", "Account Servicing", "Creative / Design", "Others"], "post_time": "2022-01-17T06:11:49Z", "salary": {"currency": null, "max": null, "min": null, "period": "monthly", "term": null}, "salary_visible": false, "title_keywords": ["account manager"], "responsibilities": ["analytics tools", "advertising", "analysis", "monitoring", "maintain", "contact", "planning"], "requirements": {"degrees": [], "majors": [], "languages": ["cantonese", "english", "chinese", "mandarin"], "language_level": ["fluent", "proficient"], "hard_skills": ["facebook", "wechat"], "soft_skills": ["multi-tasking", "interpersonal skills", "attention to details", "meet deadlines", "passionate about", "work under pressure"], "languages_combined": [{"language": "cantonese", "language_level": []}, {"language": "english", "language_level": ["fluent", "proficient"]}, {"language": "chinese", "language_level": ["fluent", "proficient"]}, {"language": "mandarin", "language_level": []}]}, "experience_required": {"duration": ["2 years"], "field": ["advertising", "agency", "related", "digital marketing", "digital", "media"]}}, {"job_id": "100003009045962", "location_code": "hk", "company": "Tag Worldwide Asia Limited", "job_title": "Senior Account Manager", "description": "To become a digital expertise in our Company, you will enjoy our attractive benefits:\n\nCompetitive remuneration package\nPerformance Bonus\nMedical Insurance\n5-day work per week\nFlexi-working hour\nGeneral Holiday, Annual Leave, Family Care Leave and Anniversary Leave\nCasual wear in office\nFriendly working environment\n\n\u00a0\u00a0The Job\n\nStrong analytical skills to consolidate data from numerous digital advertising platforms, analyze various metrics, and to convert them into strategies and action plans\nCommunicate with client on campaign performance, insight and recommendation\nDemonstrate to clients how digital advertising and web analytics can reach their marketing objectives towards business goal\nAttentive to details, execute and optimize various digital media channels (i.e. Facebook, Google, Yahoo, LinkedIn Programmatics DSP), including but not limited to search engine marketing, display ad, social media marketing, conversion tracking and web analysis.\nCollaborate with internal teams to manage and monitor for search engine marketing and social media campaign, to deliver results and KPIs\nKeep up-to-date with platform knowledge and industry news\nAble to work independently, under pressure and to work on multiple projects with tight schedule\n\n\u00a0The Person\n\nDegree in Business, Marketing, IT or related discipline\u00a0\n2 years' experience in online business incl. Search Engine Marketing, Social Media Marketing, Web Analytic\u00a0and account management; Candidate with less experience may be considered as Executive;\nKnowledge of the Search Engine Marketing in Search engines like Google and Yahoo is preferable\nSolid understanding of the current technologies available for online advertising e,g, Search Engine Marketing, Display Advertising, Social Media Marketing, Programmatics, Website development, etc.\nAttentive to details, good with figures and strong analytical skills\nStrong passion for the Internet/Digital environment, result-oriented, proactive and independent\nAble to work collaboratively across teams as a good team player, with client-centric mindset\nGood command of written, spoken English and Chinese, knowledge of Mandarin is preferable\nAble to work independently, under pressure and to work on multiple projects with tight schedule\n\nCandidate with less experience will be considered as Digital Advertising Executive. Fresh graduates are also welcome if you possess knowledge in digital analytics, ad platforms like Google, Facebook, Bing, etc.\n\nPlease send your application with full resume stating\u00a0your present and expected salary\u00a0to the Company by clicking\u00a0on the\u00a0\"Apply now\".\u00a0Please also quote the\u00a0reference number\u00a0of the applied position in the subject field.", "employment_types": ["Full Time", "Permanent"], "selling_points": ["Account management", "Shopper marketing", "5-day work with good benefits, birthday leave"], "locations": ["Wan Chai"], "categories": ["Media & Advertising", "Account Servicing"], "post_time": "2022-01-13T09:28:19Z", "salary": {"currency": null, "max": null, "min": null, "period": "monthly", "term": null}, "salary_visible": false, "title_keywords": ["senior account manager"], "responsibilities": [], "requirements": {"degrees": [], "majors": [], "languages": [], "language_level": [], "hard_skills": [], "soft_skills": [], "languages_combined": []}, "experience_required": {"duration": [], "field": []}}, {"job_id": "100003009046294", "location_code": "hk", "company": "XGD Media Limited", "job_title": "Advertising Account Executive / Account Manager / Sales Manager", "description": "Stepworks is a wholehearted independent branding firm, based in Hong Kong.\u00a0\n\nWe have a strong track record helping ambitious organisations of every type create positive change with our brand building skills, in HK and all over the world.\n\nOn our multicultural team you\u2019ll meet caring people who are really good at building brands that deliver valuable competitive advantages for our clients. We love what we do and encourage one another to be kind, understanding, and compassionate in our thoughts and actions.\u00a0\n\nAs our account manager (or senior account manager if you\u2019re more experienced) you will help lead the clients under your care, maintaining consistently high standards in the work delivered, underpinned by a deep understanding of brand building discipline and industry best practices.\n\nMore on our wholehearted approach to brand building at www.stepworks.co\n\nResponsibilities\n\n\nTake a leadership role for the clients under your care\nUnderstand your customers\u2019 businesses objectives in order to support their brand building goals\nDeep understanding of brand building discipline and industry best practices\nDeliverables on brief with high degree of client satisfaction\nDraft effective proposals\u00a0\nAchieve revenue targets\nMaintain consistently high standards in the work delivered\nEffective delegation and oversight of the team involved in your projects\nEfficiently manage day-to-day operations for a portfolio of clients\nPrepare desktop research, proposals, presentations, schedules, quotations, invoices\nMaintain healthy working relationships with clients and colleagues\u00a0\u00a0\n\nCapabilities\u00a0\u00a0\n\nA wholehearted attitude to life\nFluent spoken and written Cantonese and English is a must. Mandarin is a plus\nAt least 5 years creative agency account management experience, serving B2B and B2C multinational clients\nEnthusiastic about your profession with a passion for the art and science of brand branding \u2013 design, marketing, digital and print\nProactive, outgoing, professional, extremely detail oriented, with superb organisational skills\u00a0\nEager to positively contribute to a healthy team work environment\nGet in touch\n\nIf you feel this role may be good for you, please email our Head of Account Servicing, Shadow Wong with your r\u00e9sum\u00e9, stating expected salary. We\u2019ll treat your information confidentially.\n\nWe look forward to hearing from you.\u00a0", "employment_types": ["Full Time", "Permanent"], "selling_points": ["Fresh Graduates welcome.", "Proactive & Entrepreneurial", "Competitive Salary & Great Commission Scheme"], "locations": ["Central"], "categories": ["Media & Advertising", "Account Servicing", "Media Buying", "Sales, CS & Business Devpt", "Account Servicing"], "post_time": "2022-01-13T10:21:02Z", "salary": {"currency": null, "max": null, "min": null, "period": "monthly", "term": null}, "salary_visible": false, "title_keywords": ["account executive", "account manager", "sales manager"], "responsibilities": ["management", "invoices", "maintaining", "schedules", "day-to-day operations", "presentations", "design", "maintain", "working relationships"], "requirements": {"degrees": ["degree"], "majors": [], "languages": ["cantonese", "english", "mandarin"], "language_level": ["fluent"], "hard_skills": ["plus", "presentations"], "soft_skills": ["outgoing", "proactive", "independent", "passion for", "detail oriented", "deep", "organisational skills", "enthusiastic", "creative", "leadership", "positive"], "languages_combined": [{"language": "cantonese", "language_level": ["fluent"]}, {"language": "english", "language_level": ["fluent"]}, {"language": "mandarin", "language_level": []}]}, "experience_required": {"duration": ["at least 5 years"], "field": ["agency", "account management"]}}, {"job_id": "100003009045109", "location_code": "hk", "company": "Xenyo Limited", "job_title": "Digital Project Manager,  Account Executive ( SAAS, Digital Agency )", "description": "\u5982\u6709\u898b\u5230\u4ee5\u4e0b\u4eba\u58eb\uff0c\u8acb\u8fc5\u901f\u806f\u7e6b\uff01\n\n\u6a02\u610f\u63a5\u53d7\u6311\u6230\u3001\u52c7\u65bc\u627f\u64d4\u8cac\u4efb\u3001\n\n\u4e0d\u754f\u5de5\u4f5c\u8271\u8f9b\u3001\u5805\u6301\u5275\u4f5c\u512a\u79c0\u4f5c\u54c1\uff01\n\n\u5982\u679c\u662f\u60a8\uff0c\u6211\u5011\u5718\u968a\u6210\u54e1\u5f88\u9700\u8981\u4f60\u5354\u52a9\u5e36\u9818\u53ca\u5171\u540c\u6210\u9577\uff01\n\n\u66fe\u7d93apply \u904e\u6b61\u8fce\u518dapply\n\n\u8acb\u7528\u5c11\u5c11\u6642\u9593\u4ffe\u6211\u5730\u4e86\u89e3\u4f60\uff0c\u6709\u54a9\u80fd\u529b\u540c\u62b1\u8ca0\uff0c\u5982\u679c\u4f60\u5c0d\u6211\u5730\u516c\u53f8\u6709\u8208\u8da3\uff0c\u8acb\u56de\u7b54\u4ee5\u4e0b\u554f\u984c\n\n\u300c\u4f60\u8a8d\u70ba\u5728\u4e8b\u696d\u4e0a\u6210\u529f\u61c9\u5177\u5099\u7684\u4e94\u500b\u689d\u4ef6\u53ca\u9700\u8981\u505a\u7684\u4e94\u4ef6\u4e8b\u300d\n\n\u8acb\u56de\u7b54\u6b64\u554f\u984c\u9023\u540c\u4f60\u7684Expected salary\uff0cResume \u53caPortfolio Email\u7d66\u6211\u5011\u3002\uff08\u4e0d\u8981\u900f\u904ejobsdb \u5167\u90e8\u7533\u8acb\uff0c\u8acb\u76f4\u63a5email \u7d66\u6211\u5011)\n\u6211\u5011\u6703\u614e\u91cd\u8003\u616e\u6bcf\u4e00\u4f4d\u6c42\u8077\u8005\u3002\n\n\u6240\u4ee5\u9700\u8981\u6709\u624d\u80fd\u7684\u4f60\u4e00\u8d77\u5171\u540c\u6210\u9577!\n\n\n\u6211\u5730\u7406\u5ff5\uff1a\u76e1\u529b\u5e6b\u5ba2\u6236\u89e3\u6c7a\u96e3\u984c\uff0c\u8ffd\u6c42\u5275\u4f5c\u8207\u6311\u6230\uff0c\u5805\u6301\u935b\u934a\u81ea\u5df1\u7684\u80fd\u529b\n\u5de5\u4f5c\u5167\u5bb9\uff1a\u5f71\u7247\u88fd\u4f5c\uff0c\u7db2\u9801\u8a2d\u8a08\uff0c\u8a2d\u8a08\uff0c\u52d5\u756b\u88fd\u4f5c\u53ca\u7db2\u4e0a\u5ba3\u50b3\uff0c\u53e6\u5916\u6709\u81ea\u5df1\u7684\u5f71\u7247channel\n\u5c0d\u6bcf\u500b\u4f19\u4f34\u671f\u671b\uff1a\u6301\u7e8c\u5b78\u7fd2\uff0c\u6301\u7e8c\u9032\u6b65\uff0c\u6210\u70ba\u9818\u5c0e\u8005\n\n------------------\u00a0------------------\u00a0------------------\u00a0------------------\u00a0------------------\n\n\u53ef\u7533\u8acb\u8077\u4f4d\n\nJob Responsibilities & Requirement\n\nAccount\u00a0Executive /\u00a0Sales\n\n\n\u6703\u4e0d\u5b9a\u6642\u5de5\u4f5c\uff08\u5982\u9700\u5354\u52a9\u8d95\u51fa\u8857\u65e2Campaign/\u5ee3\u544a/\u62cd\u651d)\n\u9700\u8981cold call / warm call\n\u64f4\u5c55\u4eba\u8108\u53ca\u95dc\u4fc2\uff0c\u5982\u52a0\u5165\u5546\u6703\u53ca\u53c3\u8207\u4e0d\u540c\u6d3b\u52d5\n\u505aQuotation/Proposal\nCopywriting\n\u8ddf\u5ba2, \u8ddfProject\n\u9700\u5354\u52a9\u516c\u53f8\u4e0d\u540c\u7684fb/youtube channel \u4e0a\u5275\u4f5c\n\u66fe\u65bc\u88fd\u4f5c\uff0f\u5ee3\u544a\u516c\u53f8\u5de5\u4f5c\u6216\u6709\u76f8\u95dc\u7d93\u9a57\u512a\u5148\n\u4e94\u5929\u5de5\u4f5c\uff0c\u6709\u6642\u8d95\u5de5\u4f5c\u9700\u8981OT\n\u6709\u51fa\u93e1\u6a5f\u6703\uff0c\u6210\u70ba\u7db2\u7d05 (Optional)\n\n\u6709\u8208\u8da3\u8acb\u6e2c\u8a66\u6027\u683c\uff0c\u8a71\u6211\u77e5\u4f60\u4fc2\u54a9\u985e\u578b\u4eba\u58eb\uff0d https://www.arealme.com/16types/zh/\n\nCreative Copywriting\n\n\n\u9700\u5beb\u4e2d\u6587\u53ca\u82f1\u6587\nSocial Media \u4e0a\u5275\u4f5c\n\u9700\u5beb\u5287\u672c\n\u9762\u8a66\u9700\u8981\u4f5c\u4e00\u500b\u5beb\u4f5c\u6e2c\u8a66\n\u6709\u76f8\u95dc\u7d93\u9a57\n\n\n\nSenior Secretary / Administrative\n\n\u4e3b\u52d5\u7a4d\u6975\uff0c\u76e1\u8cac\n\u8655\u7406\u7e41\u7463\u5de5\u4f5c\uff0c\u7cfb\u7d71\u5316\n\u5167\u90e8\u884c\u653f\u5de5\u4f5c\n\u90fd\u6703\u8981\u8ddf\u5ba2\uff0c\u8ddfProject\uff0c\u9593\u4e2d\u898b\u5ba2\uff0c\u5ba2\u6236\u7ba1\u7406\ngoogle adwords \u7ba1\u7406\uff0c\u5514\u8b58\u8981\u5b78\n\u6587\u66f8\u5de5\u4f5c\uff0cResearch\uff0c\u505aProposal\uff0cQuotation\uff0cInvoice\uff0cTender\n\u6700\u5c11\u4e00\u5e74\u76f8\u95dc\u5de5\u4f5c\u7d93\u9a57\n------------------\u00a0------------------\u00a0------------------\u00a0------------------\u00a0------------------\n\nOur channel:\nhttps://www.youtube.com/channel/UCyLVZIEw2jawOLSxM4571JQ\nhttps://www.youtube.com/channel/UC8Az3jqRPwwMpY8eJ1bsYMg\n\nOur Website: www.beeline-pro.com\n\nAddress: Room 20C, Cheung Hing Shing Centre, 23 Sha Tsui Road, Tsuen Wan, N.T., Hong Kong\n\n\nAny interested parties please send e-mail with\u00a0Expected salary\uff0cResume and Portfolio(Proposal) to\u00a0recruit @beeline-pro.com\u00a0for further detail.\n\nPersonal data collected will be used for recruitment purpose only\n\n***Application without Portfolio/ Expected salary will NOT get response***", "employment_types": ["Full Time"], "selling_points": ["pref. Agency experience", "Proactive & good communicator", "Good Business and Tech Mix"], "locations": ["Kwun Tong Area"], "categories": ["Media & Advertising", "Account Servicing", "Sales, CS & Business Devpt", "Business Development", "Information Technology (IT)", "IT Project Management / Team Lead"], "post_time": "2022-01-13T07:11:06Z", "salary": {"currency": null, "max": null, "min": null, "period": "monthly", "term": null}, "salary_visible": false, "title_keywords": ["account executive", "project manager"], "responsibilities": [], "requirements": {"degrees": [], "majors": [], "languages": [], "language_level": [], "hard_skills": ["adwords", "wan"], "soft_skills": ["creative"], "languages_combined": []}, "experience_required": {"duration": [], "field": []}}, {"job_id": "100003009049943", "location_code": "hk", "company": "Hina Technology Co., Limited", "job_title": "Digital Executive /Specialist", "description": "Responsibilities:\n\nManage and support day to day activities on loyalty program\u2019s set up and operations for earning and redemption\nAssist implementation of targeted member communications, online and offline marketing promotions as and when it is required\nPromotion execution for HK and overseas market when it is required\nWorks effectively and independently with the clients and the third parties on the daily operations and execution of marketing campaigns\nCoordinate with IT team to a different system update to maintain the daily process\nCompile reports and co-ordinate with different parties for project implementation\nOngoing relationship management with partners, clients and internal teams\nSupport research and analysis of market trend/industry insight\u00a0\nHandle administrative tasks including record maintenance, report generation, stock management and follow-up\n\nRequirements:\n\nDegree in Marketing or equivalent discipline\nMinimum 3 years working experience in the field of client focus position, with agency account servicing background will be an added advantage\nStrong time management abilities; able to manage multiple projects at a time\nExcellent analytic and problem-solving skills\nAbility to effectively interact with all levels of an organisation\nTo be proactive and can-do attitude\nAn open mind to get on board on the other projects when the company need\nFamiliar with HTML editing is an advantage\nExcellent command of written and spoken English and Chinese\nCollinson offers attractive remuneration, benefit packages and excellent development and advancement opportunities. Benefit includes:\n\n15 to 18 days Annual Leave\nFull Paid Leave (14 weeks Maternity / 5 days Paternity)\nReferral Bonus\nOn the job training\nFree Priority Pass Membership (unlimited Airport Lounge access)\nCollinson offers attractive remuneration, benefit packages and excellent development and advancement opportunities. Please send full resume (MS word) with latest and expected salary by clicking Apply Now.\n\nYou may lose the chance of an interview if you don\u2019t provide the above required information. (Please note that only those short-listed will receive a reply). Learn more about Collinson at\u00a0https://www.collinsongroup.com/en.", "employment_types": ["Full Time", "Permanent"], "selling_points": ["Expert in Google Ads and performance channels", "Meal, traffic and communication allowance", "Great Exposure and Career Development"], "locations": ["Causeway Bay"], "categories": ["Media & Advertising", "Account Servicing", "Sales, CS & Business Devpt", "Account Servicing", "Marketing / Public Relations", "Digital Marketing"], "post_time": "2022-01-15T19:11:39Z", "salary": {"currency": null, "max": null, "min": null, "period": "monthly", "term": null}, "salary_visible": false, "title_keywords": ["specialist", "digital executive"], "responsibilities": ["management", "stock management", "maintenance", "compile reports", "co-ordinate with", "operations", "system update", "analysis", "coordinate with", "implementation", "teams", "daily operations", "maintain", "marketing promotions", "marketing campaigns", "administrative tasks", "report"], "requirements": {"degrees": ["degree"], "majors": ["marketing"], "languages": ["english", "chinese"], "language_level": ["excellent"], "hard_skills": ["problem-solving skills", "focus", "html", "ms word"], "soft_skills": ["proactive", "can-do attitude", "organisation", "problem-solving skills", "focus", "time management"], "languages_combined": [{"language": "english", "language_level": ["excellent"]}, {"language": "chinese", "language_level": ["excellent"]}]}, "experience_required": {"duration": ["minimum 3 years"], "field": ["agency", "account servicing"]}}, {"job_id": "100003009046513", "location_code": "hk", "company": "Alien Creation Limited", "job_title": "Senior Account Executive", "description": "Position Overview:\n\nThis role is operationally responsible for managing the shopper marketing (print management and creative production) requirements for a large Consumer Health client, and support the broader account regionally where required.\n\nThe candidate is responsible for the financial and people management, building a professional working relationship with client contacts and ultimately ensuring that a first class service is delivered. He/she will represent Tag in the eyes of the client, and deliver the KPI\u2019s on a daily basis.\n\nHe/she is in charge of coordinating the activities of the team in order to achieve the strategic aims of both the clients and Tag.\n\nIn conjunction with the central support team and Strategic Sourcing team, he/she will have to ensure that the most appropriate supplier is selected, best costings and time-scales for each job are set and that benchmarking is accurate. In addition to print management requirements, the candidate is responsible for managing all creative production activities for the account.\n\nKey Responsibilities:\n\n\nDevelop excellent relationships with day to day clients\nResponsible for major campaign management and operational problem resolution\nIdentify opportunities for business growth and further value add for the client; highlight to Line Manager\nGain a good understanding of the client's business and share this knowledge with all team members\nProduction and analysis of monthly management reports\nSupport in the production and analysis of management information and KPI's for the global contract leads and the client\nActively participate in the contract review process\nPerformance management of direct reports (including absence management)\nEnsure effective two-way communication with direct reports\nCoach and develop direct reports\nProvide technical input and advice on print projects\nOversee (and assist with) the procurement of print (in particular Point of Sales Material), delivering on time, to specification, to quality and to contractual targets\nManagement of campaigns and creative production components\nDevelop strong relationships with suppliers\nImplement and use management information systems\nEnsure best practice in conjunction with wider Tag operations group\n\nKey Requirements:\n\n\nBachelor Degree or equivalent in related field\nAt least 5 years of experience in a related field, with exposure in production setting and background in POSM, displays, supplier and stakeholder managements\nPrior experience in an agency is desirable\nShopper marketing and significant print industry experience in either purchasing or production management; strong POSM knowledge is essential\nExcellent communication and interpersonal skills,\nStrong commercial awareness, ability to plan and negotiate\nDynamic, yet detail-oriented outlook\nSelf motivated, able to work under minimum supervision\nCapable of developing and implementing plans and strategy\nAble to manage and motivate the team\nFluent in both written and spoken Cantonese, strong English communication skills\n\nWe offer competitive remuneration package and fringe benefits to the successful candidate. In addition, you will have an opportunity to work in a reputable company with excellent career exposure.\n\nInterested parties please send us your\u00a0full resume with expected salary and availability\u00a0by clicking \"Apply Now\"\n\n(All information provided will be treated in strict confidence and used solely for recruitment purpose).", "employment_types": ["Full Time"], "selling_points": ["Propose creative ideas", "Build relationships with clients", "Provide professional services"], "locations": ["Kwun Tong"], "categories": ["Media & Advertising", "Account Servicing", "Marketing / Public Relations", "Marketing - Brand / Product Management", "Sales, CS & Business Devpt", "Account Servicing"], "post_time": "2022-01-13T12:47:00Z", "salary": {"currency": null, "max": null, "min": null, "period": "monthly", "term": null}, "salary_visible": false, "title_keywords": ["senior account executive"], "responsibilities": ["management", "operations", "analysis", "review", "quality", "systems", "develop", "resolution", "communication", "management reports", "reports", "campaign management"], "requirements": {"degrees": ["degree", "bachelor"], "majors": [], "languages": ["cantonese", "english"], "language_level": ["fluent"], "hard_skills": ["dynamic", "outlook"], "soft_skills": ["communication skills", "capable", "detail-oriented", "self motivated", "dynamic", "communication and interpersonal skills"], "languages_combined": [{"language": "cantonese", "language_level": ["fluent"]}, {"language": "english", "language_level": []}]}, "experience_required": {"duration": ["at least 5 years"], "field": ["management", "related", "agency", "print", "purchasing", "marketing"]}}, {"job_id": "100003009049786", "location_code": "hk", "company": "Asia Media Search Limited", "job_title": "Assistant Partnership Manager", "description": "We are currently searching for an ambitious\u00a0Account Executive / Account Manager / Sales Manager with a strong interest in the outdoor advertising industry. You will find yourself in a fun working environment with opportunities to interact with multiple major brands while helping the company to achieve company sales targets. We value your opinions and you will be constantly challenged to think outside of the box to generate new ideas across multiple channels.\u00a0\n\nResponsibilities:\n\nSolicit new businesses for the Company\u2019s outdoor media sales\nEnsure our service commitments are fulfilled and meet customers' requirements\nAchieve company assigned sales target\nFollow up on campaign logistics and provide post campaign services to clients\nFrequently report newest market intelligence to Company\u00a0\u00a0\n\n\u00a0Desired Skills/Qualifications:\n\nUniversity graduate is preferred\nFresh Graduates welcome\nProactive & Entrepreneurial - eager to help the company grow!\nIndependent, organized and able to deliver under pressure\u00a0\nExcellent communication/interpersonal skills\n\nGood account servicing and management skill\u00a0\nProficient in Chinese (Cantonese & Mandarin) and English\u00a0\nFresh graduates or candidates with less experience will be considered for junior positions\u00a0\n\nIf you are an awesome person and most importantly, you want to build something you can call your own, it is time you join our extremely passionate founding team and apply now!\u00a0\n\nWe offer a competitive package with attractive commission schemes with many additional benefits. All personal data provided by job applications will be used strictly for recruitment purposes only.\u00a0\n\nTo apply: Please email us\u00a0with your CV and salary expectations.\u00a0", "employment_types": ["Full Time"], "selling_points": ["International loyalty marketing agency", "Excellent exposure to big accounts & career dev", "Manage and coordinate with redemption partners"], "locations": ["Others"], "categories": ["Media & Advertising", "Account Servicing", "Marketing / Public Relations", "Marketing - Marketing Communication", "Sales, CS & Business Devpt", "Account Servicing"], "post_time": "2022-01-15T03:50:36Z", "salary": {"currency": null, "max": null, "min": null, "period": "monthly", "term": null}, "salary_visible": false, "title_keywords": ["manager", "assistant"], "responsibilities": ["management", "advertising", "ideas", "sales target", "communication", "logistics", "report"], "requirements": {"degrees": ["university graduate"], "majors": [], "languages": ["cantonese", "english", "chinese", "mandarin"], "language_level": ["proficient"], "hard_skills": ["fun"], "soft_skills": ["passionate", "organized", "independent", "under pressure", "communication", "interpersonal skills", "proactive"], "languages_combined": [{"language": "cantonese", "language_level": ["proficient"]}, {"language": "english", "language_level": ["proficient"]}, {"language": "chinese", "language_level": ["proficient"]}, {"language": "mandarin", "language_level": ["proficient"]}]}, "experience_required": {"duration": [], "field": []}}, {"job_id": "100003009047989", "location_code": "hk", "company": "IPG Mediabrands (HK) Limited", "job_title": "Media Buyer / Senior Buyer (Buying & Operation Team)", "description": "Xenyo, a leading digital agency is looking to add various roles to our team. The candidates will be responsible to deliver outstanding service to multiple clients to achieve their online business goals.\n\nThe candidates will be our client's main point of contact with Xenyo during pre-sale or project phase and therefore the candidate must possess the skill set and personality to be valued as a solutions provider and expert to our clients.\n\nResponsibilities:\n\nUnderstand client's business requirements, provide suggestions and articulate to development team.\nLead the proposal process, project estimates, solutions collaboration and contribute to pitches\nAssign project work and tasks to project teams\nBe responsible for project profitability & quality\nBuild and maintain long-term relationships with clients\n\nRequirements:\n\nDiploma or above, preferably in business, marketing or I.T.\nPref. agency experience\nMinimum 3\u00a0year\u00a0work experience, preferably from a digital /creative agency or as a business analyst / Project Manager\nBe technical enough to understand development restrictions and industry best practices.\nCan understand requirements quickly and offer ideas and solutions on the spot.\nAble to handle multi-tasks and independent in a fast-paced environment\nKeep learning latest Internet Marketing and business trends to be able to provide the best solutions to clients.\nA good team player with great interpersonal skills\nDetail-minded, proactive and creative\nFluent in\u00a0spoken English & Chinese\nPlease forward your CV with Expected Salary. All data collected will be kept strictly confidential and will be used for recruitment purposes only.", "employment_types": ["Full Time"], "selling_points": [], "locations": ["Quarry Bay"], "categories": ["Media & Advertising", "Account Servicing", "Media Buying", "Marketing / Public Relations", "Marketing - Marketing Communication"], "post_time": "2022-01-14T04:40:43Z", "salary": {"currency": null, "max": null, "min": null, "period": "monthly", "term": null}, "salary_visible": false, "title_keywords": [], "responsibilities": ["quality", "maintain", "teams"], "requirements": {"degrees": ["diploma or above"], "majors": ["business", "marketing"], "languages": ["english", "chinese"], "language_level": ["fluent"], "hard_skills": [], "soft_skills": ["detail-minded", "good team player", "proactive", "independent", "multi-tasks", "fast-paced environment", "learning", "interpersonal skills", "creative"], "languages_combined": [{"language": "english", "language_level": ["fluent"]}, {"language": "chinese", "language_level": ["fluent"]}]}, "experience_required": {"duration": ["minimum 3 year"], "field": ["agency", "digital", "business"]}}, {"job_id": "100003009043237", "location_code": "hk", "company": "MEology Limited", "job_title": "MEology \u2013 Account Manager / Senior Account Executive", "description": "Job Responsibilities:\n\nThis role will serve one of the regional clients in HiNA. This regional client is a listed company group, which also holds a leading role in the industry. Client is currently operating in Hong Kong, Singapore, Malaysia and other countries in SEA market. This role will have opportunities to work in both branding and performance campaigns in web and app, which provides extensive exposure in different media channels.\n\nWork in a team to plan cross-channel paid media campaigns.\nManage digital campaigns across different paid media channels such as Google Ads, Facebook Ads and Apple Search Ads.\nMonitor and analyze campaign performance and derive insights for optimization.\nPrepare performance review presentations and reports.\nCommunicate and deliver findings to client with actionable recommendations to clients.\nWork with Account Manager to provide professional advice.\nServe as one of the main contacts of client support and contribute to the development of media strategies.\n\nJob Requirements:\n\nUniversity degree in business, marketing, advertising, communications, or a related field.\n1-3 years of hands-on experience in digital channels as SEM and Google Ads. Agency background is preferred.\nRelevant certifications of Google Ads.\nWell organized and have strong quantitative/analytical skills.\nEffective communication and problem-solving skills.\nWilling to work in start-up environment.\nPassionate in Digital Marketing.\nFluent in English and Cantonese.\nProficiency in Word, Excel and PowerPoint.\n\nWe offer 5 days work and attractive compensation package to suitable candidates. Interested parties, please send your full resume including your present & expected salary\u00a0", "employment_types": ["Full Time"], "selling_points": ["Work in digital marketing industry", "Competitive compensation", "Fun and flexible working environment"], "locations": ["Lai Chi Kok"], "categories": ["Media & Advertising", "Account Servicing"], "post_time": "2022-01-12T10:19:19Z", "salary": {"currency": null, "max": null, "min": null, "period": "monthly", "term": null}, "salary_visible": false, "title_keywords": ["senior account executive", "account manager"], "responsibilities": ["review", "monitor", "presentations", "media channels", "reports", "digital campaigns", "plan", "facebook"], "requirements": {"degrees": ["university degree"], "majors": ["business", "communications", "marketing"], "languages": ["cantonese", "english"], "language_level": ["fluent"], "hard_skills": ["excel", "word", "powerpoint", "analytical skills", "sem", "problem-solving skills"], "soft_skills": ["passionate", "well organized", "analytical skills", "communication", "hands-on", "problem-solving skills"], "languages_combined": [{"language": "cantonese", "language_level": ["fluent"]}, {"language": "english", "language_level": ["fluent"]}]}, "experience_required": {"duration": ["1-3 years"], "field": ["digital"]}}, {"job_id": "100003009041577", "location_code": "hk", "company": "Digitas Hong Kong Limited", "job_title": "Digital Media Executive", "description": "Responsibilities\u00a0\u00a0\n\n\nPropose creative ideas into integrated digital marketing campaign for developing strategies and new clients\nAnalyze information on market trends, business and competitive activities for marketing report\nPrepare\u00a0social media AD performance report and present to clients once per month\nBuild relationships and maintain constant contact with key clients and marketers\nProvide professional services to major accounts\nBe motivated to take challenges and master multiple tasks in account servicing and project management in a timely and professional manner\nReliable management skill and need to manage the\u00a0production team\n\nExperience on social media is preferred\n\nRequirements\n\n\nHigher Diploma or above in Business, Advertising, Marketing, Communications, Information system, E-commerce, project management or related discipline\n2 years solid experience, experience in E-business will be an advantage\nExcellent communication, interpersonal and negotiation skills is a must\nCreative brainstorming, ambitious; self-starter; proactive and aggressive\nProficiency in MS office application\nPassionate and knowledgeable about digital marketing or advertising is preferred\nFresh graduates are welcome (Candidates with less experience will be considered as account executive)\n\nBenefits We Offer\n\n\n5-Day Work\nFlexible Working Hours\nOvertime Meal and Transportation allowance\nEducation Fund\nFree snacks and Drinks\u00a0\nFun, young and joyful environment with lots of social activities e.g. sport games, retreat, festivals\u2019 celebrations etc.\n\n* Personal data collected will be used for recruitment purpose only *", "employment_types": ["Full Time", "Permanent"], "selling_points": ["World's 3rd largest integrated Communication Group", "Attractive salary and benefits; energetic culture", "Spacious, Stylish office with an outdoor balcony"], "locations": ["Kwun Tong"], "categories": ["Media & Advertising", "Account Servicing", "Media Buying", "Marketing / Public Relations", "Digital Marketing"], "post_time": "2022-01-12T04:03:41Z", "salary": {"currency": null, "max": null, "min": null, "period": "monthly", "term": null}, "salary_visible": false, "title_keywords": ["executive"], "responsibilities": ["social media", "creative ideas", "management", "professional manner", "developing", "project management", "maintain", "digital marketing", "contact", "report"], "requirements": {"degrees": ["higher diploma or above"], "majors": ["e-commerce", "project management", "business", "marketing", "communications"], "languages": [], "language_level": [], "hard_skills": ["project management", "ms office", "information system", "e-commerce"], "soft_skills": ["passionate", "proactive", "communication", "project management", "negotiation skills", "creative", "interpersonal"], "languages_combined": []}, "experience_required": {"duration": ["2 years"], "field": ["business"]}}, {"job_id": "100003009048990", "location_code": "hk", "company": "Zenith Integrated Communications Limited", "job_title": "Senior Manager/Manager", "description": "What we do\n\nProvide digital marketing solutions to clients with a focus on social media, from idea generation, execution to evaluation\nCreate content and solutions that matter not only to clients, but more importantly, to consumers\nPioneer and partner with clients in the journey of digital transformation\n\nWhat we\u2019d like to see\n\n1.5- 3 years of account service experience in Advertising, Media, Marketing or related disciplines, preferably on projects with digital solutions\nCreative and passionate in digital and social media solutions that help provide value to brands\nComfortable interacting with clients of all levels and industry backgrounds\nBuild trust with people and know when to compromise or confront when necessary\nWilling to think big but at the same time be practical and get things done\nAbility to identify clients\u2019 needs and match them with our digital solutions\nProficiency in English and Chinese, Mandarin is a plus\n\nWhat we offer\n\nCompetitive compensation with clear advancement opportunities\u00a0\nOpportunities to initiate new ideas and make things happen\nA chance to create real business solutions\nA collaborative and flexible working environment\n\nWhat YOU would experience\n\nFast-paced working environment\nDirect feedback from clients, managers, and peers\nExciting projects and a rewarding career\n\nDon\u2019t forget to check out our website at www.meology.hk", "employment_types": ["Full Time"], "selling_points": [], "locations": ["Kwun Tong"], "categories": ["Media & Advertising", "Account Servicing", "Marketing / Public Relations", "Marketing - Brand / Product Management", "Public Relations - Copy-writing"], "post_time": "2022-01-14T07:50:50Z", "salary": {"currency": null, "max": null, "min": null, "period": "monthly", "term": null}, "salary_visible": false, "title_keywords": ["senior manager", "manager"], "responsibilities": ["social media", "advertising", "digital marketing", "evaluation"], "requirements": {"degrees": [], "majors": [], "languages": ["english", "chinese", "mandarin"], "language_level": ["proficiency"], "hard_skills": ["focus", "plus"], "soft_skills": ["passionate", "focus", "creative"], "languages_combined": [{"language": "english", "language_level": ["proficiency"]}, {"language": "chinese", "language_level": ["proficiency"]}, {"language": "mandarin", "language_level": []}]}, "experience_required": {"duration": ["5- 3 years"], "field": ["advertising", "related", "marketing", "digital", "media"]}}, {"job_id": "100003009049957", "location_code": "hk", "company": "Hina Technology Co., Limited", "job_title": "Business Development Manager", "description": "Responsibilities:\n\n\nAccount Servicing and new business pitching\nPropose and implement PR campaigns, including brand promotion, product launches, media luncheons, social media campaigns, KOL campaigns, product promotion, advertising activities, sponsorship line ups, etc\u2026\nAssist the Team Head on preparing all PR materials, including pitching proposals, press material write ups, KOL management, social media copy writing, content editing, proofreading etc\u2026\nCoach and supervise junior staff in execution of all PR campaigns and retainer projects\nMedia Pitching to enhance media exposure for various client projects\nBuild and maintain a good relationship with media (both online and offline), KOLs and Artist Management\nCo-ordinate with external and internal parties to ensure the smooth execution of PR and marketing campaigns\nSupport on reports, admin works, and maintaining filing systems, and any other ad-hoc tasks assigned by senior management\n\n\u00a0Requirements:\n\n\nDegree holder preferably in Communications, Journalism or related discipline\n5 years\u2019 agency experience in PR agency is a must; candidate with less experience would also considered as Manager\nSolid hands on experience in Media Pitching, KOL pitching, social media content development and/or digital media buying\nGood communication, presentation and interpersonal skills\nProficiency in written and spoken English and Chinese\nExcellent project management skills and enthusiastic multi-tasker with a can do attitude and passion for PR industry\u00a0\n\nWe offer excellent career opportunity, benefits and generous compensations.\u00a0 Please apply in strict confidence with expected salary by email.", "employment_types": ["Full Time", "Permanent"], "selling_points": ["2+ years relevant experience", "Meal, traffic and communication allowance", "Great Exposure and Career Development"], "locations": ["Causeway Bay"], "categories": ["Media & Advertising", "Account Servicing", "Sales, CS & Business Devpt", "Account Servicing", "Marketing / Public Relations", "Digital Marketing"], "post_time": "2022-01-15T19:11:40Z", "salary": {"currency": null, "max": null, "min": null, "period": "monthly", "term": null}, "salary_visible": false, "title_keywords": ["business development manager"], "responsibilities": ["social media", "management", "advertising", "social media campaigns", "maintaining", "co-ordinate with", "ad-hoc tasks", "systems", "good relationship", "proofreading", "maintain", "reports", "marketing campaigns", "editing", "internal parties", "senior management"], "requirements": {"degrees": ["degree holder"], "majors": ["journalism", "communications"], "languages": ["english", "chinese"], "language_level": ["proficiency"], "hard_skills": ["project management"], "soft_skills": ["passion for", "project management skills", "communication", "hands on", "interpersonal skills", "enthusiastic", "presentation"], "languages_combined": [{"language": "english", "language_level": ["proficiency"]}, {"language": "chinese", "language_level": ["proficiency"]}]}, "experience_required": {"duration": ["5 years"], "field": ["social media", "pr", "content development", "agency", "digital media", "media"]}}, {"job_id": "100003009043231", "location_code": "hk", "company": "MEology Limited", "job_title": "MEology \u2013 Account Manager / Senior Account Executive (Performance Marketing)", "description": "Job Responsibilities:\n\nProspect and identify new business opportunities to drive sales revenue.\nDevelop digital strategies and plan for clients to achieve their goals and directions.\nLeverage company\u2019s competitive advantages in sales pitches.\nPresent in pre-sales meetings and maintain client relationships after deal closed.\nParticipate in networking events and trade shows.\nWork with internal operations team to ensure plans are well executed according to clients\u2019 requirements and meeting their expectations.\n\nJob Requirements:\n\n\u00a0University degree in business, marketing, advertising, communications, or a related field.\n\u00a02+ years of sales experience in digital channels in agency, publishers, vendors or consulting firms in the field.\nFamiliar with Google Ads, Facebook advertising or programmatic buy is a plus.\nEffective communication and presentation skills.\nProven track record of success in meeting revenue goals.\nWilling to work in start-up environment.\nPassionate in Digital Marketing.\nFluent in English and Cantonese.\nProficiency in Word, Excel and PowerPoint.\n\nWe offer 5 day work and attractive compensation package to suitable candidates. Interested parties, please send your full resume including your present & expected salary.\u00a0", "employment_types": ["Full Time"], "selling_points": ["Work in digital marketing industry", "Competitive compensation", "Fun and flexible working environment"], "locations": ["Lai Chi Kok"], "categories": ["Media & Advertising", "Account Servicing"], "post_time": "2022-01-12T10:18:54Z", "salary": {"currency": null, "max": null, "min": null, "period": "monthly", "term": null}, "salary_visible": false, "title_keywords": ["senior account executive", "account manager"], "responsibilities": ["operations", "business opportunities", "develop", "maintain", "plan", "plans", "digital strategies", "drive sales"], "requirements": {"degrees": ["university degree"], "majors": ["business", "communications", "marketing"], "languages": ["cantonese", "english"], "language_level": ["fluent"], "hard_skills": ["excel", "plus", "word", "powerpoint", "facebook"], "soft_skills": ["communication", "presentation skills", "passionate"], "languages_combined": [{"language": "cantonese", "language_level": ["fluent"]}, {"language": "english", "language_level": ["fluent"]}]}, "experience_required": {"duration": ["2+ years"], "field": ["agency", "digital", "consulting firms"]}}, {"job_id": "100003009045012", "location_code": "hk", "company": "Adtactics Marketing International Limited", "job_title": "Account Manager / Assistant Account Manager", "description": "What we do\n\nProvide digital marketing solutions to clients with a focus on social media and e-commerce, from idea generation, execution, evaluation and optimisation\nDrive performance marketing by preparing analytical reports and dashboard with insights and suggestions for monitoring and optimisation\nTranslate performance data to content strategy and media tactics\nCreate content and solutions that matter not only to clients, but more importantly, to consumers\nPioneer and partner with clients in the journey of digital transformation\n\nWhat we\u2019d like to see\n\n2- 3 years of account service experience in Advertising, Media, Marketing or related disciplines, preferably on projects with digital solutions and optimisation\nCreative and passionate in digital and social media solutions that help provide value to brands\nHappy to work with numbers and analytics\nComfortable interacting with clients of all levels and industry backgrounds\nBuild trust with people and know when to compromise or confront when necessary\nWilling to think big but at the same time be practical and get things done\nAbility to identify clients\u2019 needs and match them with our digital solutions\nProficiency in English and Chinese, Mandarin is a plus\n\nWhat we offer\n\nCompetitive compensation with clear advancement opportunities\u00a0\nOpportunities to initiate new ideas and make things happen\nA chance to create real business solutions\nA collaborative and flexible working environment\n\nWhat YOU would experience\n\nFast-paced working environment\nDirect feedback from clients, managers, and peers\nExciting projects and a rewarding career\n\nDon\u2019t forget to check out our website at www.meology.hk", "employment_types": ["Full Time"], "selling_points": ["Manage digital marketing campaigns and accounts", "Equip solid knowledge of Google Ads, SEM, Social", "Serve with good portfolio of public sector clients"], "locations": ["Kwun Tong"], "categories": ["Media & Advertising", "Account Servicing", "Marketing / Public Relations", "Management", "Digital Marketing"], "post_time": "2022-01-13T06:53:49Z", "salary": {"currency": "HKD", "max": 29999, "min": 20000, "period": "monthly", "term": null}, "salary_visible": true, "title_keywords": ["account manager", "assistant account manager"], "responsibilities": ["social media", "advertising", "data", "monitoring", "digital marketing", "reports", "evaluation"], "requirements": {"degrees": [], "majors": [], "languages": ["english", "chinese", "mandarin"], "language_level": ["proficiency"], "hard_skills": ["focus", "plus", "e-commerce"], "soft_skills": ["passionate", "focus", "creative"], "languages_combined": [{"language": "english", "language_level": ["proficiency"]}, {"language": "chinese", "language_level": ["proficiency"]}, {"language": "mandarin", "language_level": []}]}, "experience_required": {"duration": ["2- 3 years"], "field": ["advertising", "related", "marketing", "digital", "media"]}}, {"job_id": "100003009043622", "location_code": "hk", "company": "Burson-Marsteller (Hong Kong) Limited", "job_title": "PR Account Manager", "description": "Responsibilities\n\nFollow up with digital marketing service orders - Search Engine Marketing (SEM) / Social Media Marketing/ Programmatic campaigns;\nPrepare proposal, budget and execution plan for marketing campaigns;\nImplement and execute digital, search, display and social media campaigns;\nDeliver excellent pre-sales & after-sales service to both existing and new clients;\nEstablish and maintain strong relationships with business partners and clients;\nAdopt consultative approach to customers on their digital marketing & advertising strategies with big data research and analysis;\nResponsible for the strategic development and day-to-day operation of the corporate social media and other online channels.\n\nRequirements\n\nHigher Diploma / Degree holders in Marketing, Business Administration, Public Relations, Information Management & Technology, E-Commerce, Computer Science, Engineering, or equivalent discipline;\nExperience in at least 3 years is welcomed;\nStrong knowledge in Google Adwords and Google Analytics;\u00a0\nExperience in digital marketing and emerging digital technology, social trends and insights;\nGood interpersonal and communication skills;\nProactive, self-motivated and able to work independently;\nProficient in using MS Word, Excel and PowerPoint;\nGood written and spoken in English and Chinese including both Cantonese and Mandarin.\n\n\n\nAdTactics offers an attractive remuneration package, including 5 days\u2019 work, performance bonus, bank holidays, and wedding leaves to right candidates.\u00a0For interested\u00a0parties please send a cover letter stating your current salary and expected salary with Resume to us.\u00a0", "employment_types": ["Full Time"], "selling_points": ["4-6 years of experience in an international agency", "Experienced in MNC and China global company", "Strong in APAC media relations"], "locations": ["Quarry Bay"], "categories": ["Media & Advertising", "Account Servicing", "Marketing / Public Relations", "Public Relations - Copy-writing", "Public Relations - General / Support"], "post_time": "2022-01-13T00:53:55Z", "salary": {"currency": null, "max": null, "min": null, "period": "monthly", "term": null}, "salary_visible": false, "title_keywords": ["account manager"], "responsibilities": ["social media", "online channels", "advertising", "social media campaigns", "analysis", "budget", "big data", "after-sales service", "maintain", "digital marketing", "sem", "plan", "marketing campaigns", "day-to-day operation"], "requirements": {"degrees": ["diploma", "degree"], "majors": ["business administration", "engineering", "e-commerce", "marketing", "computer science"], "languages": ["cantonese", "english", "chinese", "mandarin"], "language_level": ["good"], "hard_skills": ["google analytics", "excel", "e-commerce", "adwords", "powerpoint", "ms word"], "soft_skills": ["communication skills", "self-motivated", "work independently", "proactive", "interpersonal"], "languages_combined": [{"language": "cantonese", "language_level": ["good"]}, {"language": "english", "language_level": ["good"]}, {"language": "chinese", "language_level": ["good"]}, {"language": "mandarin", "language_level": ["good"]}]}, "experience_required": {"duration": ["at least 3 years"], "field": ["digital", "digital marketing"]}}, {"job_id": "100003009037379", "location_code": "hk", "company": "\u7d93\u6fdf\u4e00\u9031 EDigest", "job_title": "Account Executive(Business & Finance)", "description": "Provide secretarial and administrative support to Sales Team\nF.7 graduate or equivalent qualification preferred\n3 years' working experience in related field\nGood communication skills in Cantonese, English and Mandarin\nProficient in MS office and Chinese word processing\nAble to work independently, detail-minded and well-organized\nWorking location in Causeway Bay\n\nPlease apply, quoting the appropriate reference number, with details of your qualifications and experience, expected salary and a contact telephone number to The\u00a0Senior Manager, Personnel Department, Television Broadcasts Limited, TVB City, 77 Chun Choi Street, Tseung Kwan O Industrial Estate, Tseung Kwan O, Kowloon or email to us via Recruitment Centre.\n\nApplications received are solely for selection purpose.\u00a0 Those not invited for an interview within 4 weeks may consider their applications unsuccessful and their applications will be filed for another 3 months for future selection.\u00a0 Afterwards, all applications would be destroyed.", "employment_types": ["Full Time", "Permanent"], "selling_points": ["Client Servicing", "Project Management", "Prepare campaign reports & competitive analysis"], "locations": ["Kwun Tong"], "categories": ["Media & Advertising", "Account Servicing", "Marketing / Public Relations", "Marketing - General / Support", "Digital Marketing"], "post_time": "2022-01-12T23:26:07Z", "salary": {"currency": null, "max": null, "min": null, "period": null, "term": null}, "salary_visible": false, "title_keywords": [], "responsibilities": ["administrative support", "communication", "recruitment", "sales team", "contact"], "requirements": {"degrees": [], "majors": [], "languages": ["cantonese", "english", "chinese", "mandarin"], "language_level": ["proficient", "good"], "hard_skills": ["chinese word processing", "ms office"], "soft_skills": ["detail-minded", "communication skills", "work independently", "well-organized"], "languages_combined": [{"language": "cantonese", "language_level": ["good"]}, {"language": "english", "language_level": ["good"]}, {"language": "chinese", "language_level": ["proficient"]}, {"language": "mandarin", "language_level": ["good"]}]}, "experience_required": {"duration": ["3 years"], "field": ["related", "recruitment"]}}, {"job_id": "100003009038406", "location_code": "hk", "company": "DDB Worldwide Limited", "job_title": "Account Co-ordinator", "description": "\u00a0Role:\n\nPlan and recommend content strategies and ideas for client\u2019s social media marketing campaigns\nManage a small team and maintain job done in good quality\u00a0\nAs day to day client key contact, meeting and liaising with clients to discuss briefs, requirements and project progress\nIn liaison with animators,photographers,\u00a0programmers, writers, video producers, KOLs\u00a0and artists on project basis\nQuality control on\u00a0social media copywriting, media plan, proposals, scripts and\u00a0analytic reports in Chinese or English\n\nRequirement:\u00a0\n\n*immediate available preferred\n\nDegree/higher diploma/diploma in communication / marketing / language or related disciplines\n3+ year of working experience preferably in agency environment, less experience will be considered as Senior Executive\nGood writing and presentation skill in Chinese and English , excellent English writing skills will be an advantage\nPassionate in digital,\u00a0social media and digital PR\u00a0\nAble to adapt changes in fast pace environment\u00a0\nPositive attitude at work\u00a0\nGood communication skill, responsible, punctual, good team-player, detail-minded, able to work under pressure\u00a0", "employment_types": ["Full Time", "Permanent"], "selling_points": ["Good communication skills", "Willing to learn", "Proactive problem solver"], "locations": ["Not Specified"], "categories": ["Media & Advertising", "Account Servicing", "Marketing / Public Relations", "Marketing - Direct Marketing"], "post_time": "2022-01-11T06:48:12Z", "salary": {"currency": null, "max": null, "min": null, "period": "monthly", "term": null}, "salary_visible": false, "title_keywords": [], "responsibilities": ["social media", "ideas", "quality", "liaising with", "project progress", "communication", "maintain", "reports", "contact", "marketing campaigns", "plan", "quality control", "work under pressure"], "requirements": {"degrees": ["diploma", "degree"], "majors": ["related disciplines", "marketing"], "languages": ["english", "chinese"], "language_level": ["advantage", "excellent", "good"], "hard_skills": ["small", "presentation skill", "writing skills", "animators"], "soft_skills": ["presentation skill", "passionate", "detail-minded", "responsible", "team-player", "communication skill", "writing skills", "communication", "positive attitude", "work under pressure"], "languages_combined": [{"language": "english", "language_level": ["advantage", "excellent", "good"]}, {"language": "chinese", "language_level": ["advantage", "excellent", "good"]}]}, "experience_required": {"duration": ["3+ year"], "field": ["agency"]}}, {"job_id": "100003009040808", "location_code": "hk", "company": "VS Media Limited", "job_title": "Account Executive (Campaign)", "description": "Curiosity. Vision. Drive. Integrity. At BCW (Burson Cohn & Wolfe), we\u2019re an integrated communications agency of thinkers, futurists, technologists and makers who come together to create powerful connections spanning every industry, discipline and culture on the planet. Here in APAC, BCW follows a people-first strategy where we focus on recruiting and retaining the best talent, upskilling our team, and instilling a culture of learning, collaboration, winning and having fun.\n\nAs an Account Manager, you are expected to support day-to-day client activities and provide guidance to junior team members through ongoing counsel and effective delegation. You will contribute to BCW\u2019s performance by managing client relationships and integrated communication (IC) programs, satisfying and delighting clients, helping, generate new business and growing existing accounts.\u00a0 You are required to support our corporate strategy and your practice or office to help ensure superior client service, a winning culture and profitability.\n\nCORE JOB RESPONSIBILITIES\n\nStay current on your clients\u2019 businesses, industries and competitors and use your knowledge to develop comprehensive, strategic and integrated communications programs that complement the client\u2019s business objectives and deliver results\nAct as a day-to-day client leader and maintain a clear and consistent communication channel between the client and the account team\nBe actively involved and oversee quality implementation for one or a group of accounts within time and budget constraints\nHave strong verbal and written communication skills including development of various types of materials such as Q&A, key messages, holding statements, press releases etc.\nBe able to support the senior managers and leaders in resolving client issues\nMaintain a strong rapport with journalists/bloggers/media members who cover your clients\u2019 industries and businesses to optimize channels.\u00a0\nHelp develop media strategies, write pitch letters and respond to media queries\nStay updated on social media channels, trends and analytical tools and make recommendations to strengthen our capabilities\nSupport the Directors and other senior leaders to identify new business opportunities within existing and potential clients\nBe proactive during new business brainstorms and take ownership of portions of new business proposals under the guidance of Directors and senior leaders\nManage client relationships and be the client\u2019s key contact, counselor and strategic thinker\n\nJOB REQUIREMENTS\n\nWith 4-6 years of experience in working in an international agency environment\nExperienced in MNC and China global company is an advantage\nExperienced in handling regional/global technology and media\nProficiency in English and Mandarin is a must", "employment_types": ["Full Time", "Permanent"], "selling_points": ["Digital Media, Campaign, Advertisement", "Account Servicing", "Social media, Influencer landscape,"], "locations": ["Kwun Tong"], "categories": ["Media & Advertising", "Account Servicing", "Media Buying", "Strategic Planning"], "post_time": "2022-01-12T03:23:52Z", "salary": {"currency": null, "max": null, "min": null, "period": "monthly", "term": null}, "salary_visible": false, "title_keywords": ["account executive"], "responsibilities": ["make recommendations", "social media", "guidance", "business opportunities", "budget", "quality", "implementation", "letters", "develop", "communication", "maintain", "contact"], "requirements": {"degrees": [], "majors": [], "languages": ["english", "mandarin"], "language_level": ["proficiency"], "hard_skills": [], "soft_skills": [], "languages_combined": [{"language": "english", "language_level": ["proficiency"]}, {"language": "mandarin", "language_level": ["proficiency"]}]}, "experience_required": {"duration": ["4-6 years"], "field": ["agency"]}}, {"job_id": "100003009037973", "location_code": "hk", "company": "Cheil Hong Kong Limited", "job_title": "Senior Account Executive (Integrated Marketing Communication)", "description": "Benefits:\n\n5 days Work + Bank Holidays\nFull Medical Coverage\nSales Incentive\nBirthday Leave, Wedding Leave\nTraining Subsidy\nProfessional training in digital marketing\nFast track career progression in this growing industry\n\nResponsibilities include:\n\nIdentify new clients and perform outbound call selling on our digital marketing consultancy service via phone;\nHandle enquiries and provide service information to corporate clients in a professional manner;\nProvide support to Business Development Team.\n\nRequirements:\n\nPassionate to digital marketing;\nDiploma or above; education background in marketing/ advertising or related discipline will be an advantage;\nPossessing at least 1 year of working experience is preferred;\nExperience in call center/ B2B customer service is an advantage;\nProficient in both written and oral Chinese and English;\nExcellent organizational and communication skills;\nHigh level of customer centric mentality; able to work in a fast-paced environment;\nOutstanding candidates will be promoted to Sales Manager after completing on-the-job-training programme.\n\nTo Apply:\n\nFor more information about You Find Ltd., please visit\u00a0www.youfind.hk\nWe offer attractive package to the right candidate. Interested parties please send your application by clicking \"Apply Now\".\nAll information received will be used for recruitment purpose only and will be kept in strict confidential.\n\nYouFind is an Equal Opportunity Employer and prohibits discrimination and harassment of any kind. All employment decisions at YouFind are based on business needs, job requirements and individual qualifications, without regard to race; family status; gender; disability status or any other status protected by the laws or regulations in Hong Kong.", "employment_types": ["Full Time"], "selling_points": ["5 days work week", "2~3 years of working experience", "Immediately available is highly preferable"], "locations": ["Sheung Wan"], "categories": ["Media & Advertising", "Account Servicing", "Strategic Planning", "Marketing / Public Relations", "Marketing - Marketing Communication"], "post_time": "2022-01-11T04:27:58Z", "salary": {"currency": null, "max": null, "min": null, "period": "monthly", "term": null}, "salary_visible": false, "title_keywords": ["senior account executive"], "responsibilities": [], "requirements": {"degrees": [], "majors": [], "languages": [], "language_level": [], "hard_skills": [], "soft_skills": [], "languages_combined": []}, "experience_required": {"duration": [], "field": []}}, {"job_id": "100003009042908", "location_code": "hk", "company": "Most Kwai Chung Limited", "job_title": "Account Officer / Account Assistant (Account Servicing)", "description": "The role is to work on client\u2019s advertising projects in our leading business and finance channel \u7d93\u6fdf\u4e00\u9031.\n\nJob Description:\n\nFollow up on advertising leads, prepare advertising contract, work schedule and post-campaign evaluations\nWork closely with clients to launch media placement, advertising and special projects our channels;\nPrepare sales deck, and client proposals\nClient Servicing: Have the sensitivity to understand clients\u2019 marketing needs and able to propose appropriate solutions;\nProject Management: Manage clients\u2019 projects including define deliverables, prepare project schedules, resources planning, coordinating internal resources, campaign launch, etc.\nPrepare campaign reports, and competitive analysis\nWork on different brand marketing and client advertising projects assigned.\nRequirements:\n\n1-2 years experience in client servicing. Knowledge on banking and finance brands, either agency side or in-house digital marketing will be an advantage\nWell-organized, attention to details and follow through execution.\nMulti-tasking and strong project management skills are important in this role.\nSelf-motivated showing strong sense of ownership and able to work under pressure;\nGood excel skills and data analysis skills, and also able to prepare quality powerpoints and reports will be a plus.\nPresentable with good communication skills in both English and Chinese\nExperience in either client side, client servicing, digital projects, or digital media will be an advantage.\nFamiliar with banking, insurance, investment areas will be a plus\nFresh grad will be considered for the Account Executive role.\nFor job applications, please send in your resume, HKDSE and academic result to us.\n", "employment_types": ["Full Time", "Permanent"], "selling_points": ["Managing various advertising campaigns", "Fresh graduate are also welcome", "Immediately available is an advantage"], "locations": ["Kwai Hing"], "categories": ["Media & Advertising", "Account Servicing", "Marketing / Public Relations", "Marketing - Brand / Product Management", "Sales, CS & Business Devpt", "Account Servicing"], "post_time": "2022-01-12T09:12:26Z", "salary": {"currency": null, "max": null, "min": null, "period": "monthly", "term": null}, "salary_visible": false, "title_keywords": ["officer", "account assistant"], "responsibilities": ["advertising", "schedules", "analysis", "prepare sales", "project management", "reports", "schedule", "client proposals", "planning"], "requirements": {"degrees": ["hkdse"], "majors": [], "languages": ["english", "chinese"], "language_level": ["good"], "hard_skills": ["project management", "analysis", "excel", "plus"], "soft_skills": ["communication skills", "self-motivated", "project management skills", "well-organized", "presentable", "multi-tasking", "attention to details", "work under pressure"], "languages_combined": [{"language": "english", "language_level": ["good"]}, {"language": "chinese", "language_level": ["good"]}]}, "experience_required": {"duration": ["1-2 years"], "field": ["digital", "digital media"]}}, {"job_id": "100003009041983", "location_code": "hk", "company": "Guru Online", "job_title": "Senior Account Executive", "description": "Job Description:\nDay to day client contact at equivalent client role level\nWorking with client projects and responds to queries or forward queries to the appropriate person for response\nKeep tracking of potential issue on problem solving these where possible or accelerating them upwards for early resolution\nEffective handling of all client account administration including compilating of work in progress reports, contact reports and job no.\nFormulating day to day cost estimates\nWork with account team to ensure that the information is accurate\nWork across all agency teams as appropriate to projects\nRequirements of the candidate:\nCompletion secondary education or above with at least 1 year working experience\nGood communication skills - oral & written\nA proactive problem solver, who always wants to strive for better solutions\nA responsible team player, who is willing to learn\n\u2028Good interpersonal skill and able to work under pressure\nImmediate available is preferable\nBenefits:\nHealth Insurance\nMPF\nAnnual Leave\nBirthday Leave\nShuttle Bus to/from work\nInterest parties, please send CV with expected salary by clicking \"Apply Now\"\n\nPersonal data collected will be used for recruitment purposes only", "employment_types": ["Full Time", "Permanent"], "selling_points": ["Manage digital campaign projects", "Flexible working style", "Fun, Young working environment"], "locations": ["Kwun Tong"], "categories": ["Media & Advertising", "Account Servicing", "Strategic Planning", "Marketing / Public Relations", "Digital Marketing"], "post_time": "2022-01-12T04:59:49Z", "salary": {"currency": null, "max": null, "min": null, "period": "monthly", "term": null}, "salary_visible": false, "title_keywords": ["senior account executive"], "responsibilities": ["tracking", "cost", "progress reports", "teams", "resolution", "reports", "contact", "administration"], "requirements": {"degrees": ["secondary education"], "majors": [], "languages": [], "language_level": [], "hard_skills": [], "soft_skills": ["communication skills", "oral", "problem solver", "responsible", "willing to learn", "interpersonal skill", "team player", "proactive", "work under pressure"], "languages_combined": []}, "experience_required": {"duration": ["at least 1 year"], "field": ["education"]}}, {"job_id": "100003009041899", "location_code": "hk", "company": "Digit Pepper Limited", "job_title": "Digital Account Executive / Senior Account Executive (E-commerce and Digital Marketing Specialist)", "description": "Our client, an international loyalty marketing agency, is looking for an Assistant Partnership Manager to join their growing team in Hong Kong.\n\nIn this role, you will be responsible for:\n\nManage and oversee the loyalty programme\u2019s accrual operations\nHandle multiple loyalty partners and maintain constant dialogue and relationship with programme partners\nProactively manage client relationship and overall account deliverables\nWorks effectively and independently with the clients and the third parties on the daily operations and execution of marketing campaigns\nLead and drive a small team and ensure projects are delivered with high quality and timeliness. Provide mentorship and coaching for subordinates.\nActively take part in internal team management and work closely with peer level managers on ideas exchange and generation. Be part of internal leadership.\nConduct research and analysis, provide market/industry insight on an on-going basis\nHandle ad-hoc projects as and be open-minded to get on board on other projects when required by the company\n\nTo be considered, you must have:\n\nDegree holder, preferably in Business or Marketing relating disciplines\nMinimum 4 years working experience in the field of project management /content management.\nExperience in managing a team of partner and client relationship managers/operations staff\nExperience from Retail / F&B / FMCG/ Finance is a definite plus.\nExperience in agency account management will be an added advantage\nExcellent project management skills, negotiation skills and detail oriented\nEnergetic, self-motivated and persistent in achieving results; ability to perform multi-task and meet tight deadline\nExcellent communication and interpersonal skills. Good in English, Cantonese and Mandarin, both written\u00a0and spoken.\nGood command of MS Office, including Excel and Powerpoint\n\nIf you are aggressive, willing to face new challenges and passionate about eCommerce and digital marketing, here is the opportunity for you to advance your career in an international environment.\u00a0 Simply APPLY NOW!\n\nAll information collected is for recruitment purpose only and will be treated in the strictest of confidence. (HKEA#66094)", "employment_types": ["Full Time", "Permanent"], "selling_points": [], "locations": ["Quarry Bay"], "categories": ["Media & Advertising", "Account Servicing", "Creative / Design", "Strategic Planning"], "post_time": "2022-01-12T04:36:57Z", "salary": {"currency": null, "max": null, "min": null, "period": "monthly", "term": null}, "salary_visible": false, "title_keywords": ["digital marketing specialist", "account executive", "senior account executive"], "responsibilities": ["management", "ideas", "operations", "analysis", "quality", "communication", "project management", "daily operations", "maintain", "digital marketing", "accrual", "marketing campaigns", "recruitment", "ad-hoc projects", "managing a team", "conduct research"], "requirements": {"degrees": ["degree holder"], "majors": ["business", "marketing"], "languages": ["cantonese", "english", "mandarin"], "language_level": ["good"], "hard_skills": ["small", "excel", "plus", "analysis", "powerpoint", "project management", "ms office", "exchange"], "soft_skills": ["self-motivated", "independently", "multi-task", "confidence", "responsible", "open-minded", "project management skills", "detail oriented", "persistent", "project management", "negotiation skills", "communication and interpersonal skills", "meet tight deadline", "energetic", "leadership", "passionate about"], "languages_combined": [{"language": "cantonese", "language_level": ["good"]}, {"language": "english", "language_level": ["good"]}, {"language": "mandarin", "language_level": ["good"]}]}, "experience_required": {"duration": ["minimum 4 years"], "field": ["management", "fmcg", "agency", "finance", "project management", "f&b", "managing a team", "retail", "account management"]}}, {"job_id": "100003009038004", "location_code": "hk", "company": "Bingo Communications Company Limited", "job_title": "Account Executive / Senior Account Executive", "description": "Qualifications and Requirements:\n\n1-3 year of working experience in media buying / planning\u00a0\u00a0\nUniversity graduated in Business, Marketing, Advertising, Communications, Mathematics or related field will be an advantage\nFluent in English and Chinese, both written and spoken language skills; \u00a0\u00a0\nPassion for advertising / media\nA good team player with good communication skills and self-motivated;\nWell organized multi-tasker and able to work under pressure\nGood PC Skills, especially in Excel, PowerPoint & internet operations\nImmediately availability is preferred\n\nJob Scope:\n\nLiaise with both offline and digital media vendors on buying cost\nOptimization of media budget and provide the best value / solution for client;\nParticipate in implementing an integrated offline and digital advertising campaign from material co-ordination, booking, post campaign reporting / evaluation to monthly billing\nKeep monitoring the advertising market change, client\u2019s competitors move and the transformation of media consumption behavior\nCoodination with local and regional markets and reporting\nBuilding relationships with different working partners internally and externally\nInitiate \u201cout-of-box\u201d ideas to your client\n\nWe offer 5 days\u2019 work week, good salary package with MPF and Medical Plan with Dental Care and staff training for development.\u00a0 Interested applicants should submit resumes with expected salary and date of availability to us.\n\nFor further information about IPG Mediabrands, please visit:\u00a0http://www.ipgmediabrands.com/\n\n", "employment_types": ["Full Time"], "selling_points": [], "locations": ["Kwun Tong"], "categories": ["Media & Advertising", "Account Servicing", "Marketing / Public Relations", "Public Relations - Event Management", "Digital Marketing"], "post_time": "2022-01-11T04:31:52Z", "salary": {"currency": null, "max": null, "min": null, "period": "monthly", "term": null}, "salary_visible": false, "title_keywords": ["account executive", "senior account executive"], "responsibilities": ["reporting", "cost", "advertising", "ideas", "operations", "budget", "monitoring", "communication", "planning", "booking", "evaluation", "liaise with", "work under pressure"], "requirements": {"degrees": [], "majors": [], "languages": ["english", "chinese"], "language_level": ["fluent"], "hard_skills": ["excel", "pc skills", "powerpoint"], "soft_skills": ["communication skills", "good team player", "self-motivated", "passion for", "well organized", "work under pressure"], "languages_combined": [{"language": "english", "language_level": ["fluent"]}, {"language": "chinese", "language_level": ["fluent"]}]}, "experience_required": {"duration": ["1-3 year"], "field": ["media buying", "planning"]}}, {"job_id": "100003009046647", "location_code": "hk", "company": "Firebean Limited", "job_title": "PR & Social Media Executive (5 days work)", "description": "We are a creative agency providing a wide range of advertising services. With our expertise in creative communications, social media content creation, art and design work, to stand out our client\u2019s brand in the commercial world.\n\nYou will become an integral part of the team, cooperate with some key international and local brands and be responsible for managing various advertising campaigns.\n\nResponsibilities\nImplement marketing plans, promotion campaigns, KOLs campaigns, events, social media campaigns etc;\nResponsible for day-to-day client activities and delivery of works;\nMaintain excellent and long-term relationship with clients, working partners and KOLs/celebrities;\nUnderstand client\u2019s business & objectives and input strategically to develop creative briefs;\nCoordinate with different parties to execute various advertising projects.\n\nRequirements\n\nBachelor Degree in Sales & Marketing /\u00a0Digital Marketing / Communications / Advertising / Public Relations or related disciplines;\n1-2 years working experience in Digital Marketing or Marketing industry;\nFresh graduate are also welcome;\nWilling to coordinate with various parties;\nStrong communication, presentation, and interpersonal skills;\nFluent in spoken and written English, Chinese, and Putonghua;\nImmediately availability is preferred.\n\nWe offer a 5-day week of work, group medical insurance coverage & birthday leave.\n\nInterested parties, please send your detailed resume with the expected salary via Apply Now.\n\nThis role is located and based in Hong Kong. Candidates must be eligible to work in Hong Kong.", "employment_types": ["Full Time"], "selling_points": ["Copywriting in various social media", "Follow up on integrated marketing events", "1 year relevant working experience"], "locations": ["Wan Chai"], "categories": ["Media & Advertising", "Account Servicing", "Editorial / Journalism", "Marketing / Public Relations", "Public Relations - Copy-writing"], "post_time": "2022-01-13T18:54:01Z", "salary": {"currency": null, "max": null, "min": null, "period": "monthly", "term": null}, "salary_visible": false, "title_keywords": ["social media executive"], "responsibilities": ["advertising", "social media campaigns", "marketing plans", "coordinate with", "develop", "promotion campaigns", "maintain"], "requirements": {"degrees": ["degree", "bachelor", "fresh graduate"], "majors": ["related disciplines", "marketing", "digital marketing", "communications"], "languages": ["putonghua", "english", "chinese"], "language_level": ["fluent"], "hard_skills": [], "soft_skills": ["communication", "interpersonal skills", "presentation"], "languages_combined": [{"language": "putonghua", "language_level": ["fluent"]}, {"language": "english", "language_level": ["fluent"]}, {"language": "chinese", "language_level": ["fluent"]}]}, "experience_required": {"duration": ["1-2 years"], "field": ["marketing", "digital marketing"]}}, {"job_id": "100003009039989", "location_code": "hk", "company": "Sunny Interactive Company Limited", "job_title": "Senior Account Executive / Account Manager / Senior Account Manager (5 Days Work)", "description": "What You Will Be Doing:\n\n\nManage digital campaign\u00a0projects\u00a0for clients\nWork closely with vendors / internal teams to plan, develop, execute and implement digital marketing campaign projects;\nManage and analyze clients' digital performance\u00a0 from different industries (Beauty, Banking, Travel, FMCG, NGO, other media agencies,\u00a0etc.);\nStudy and document client\u2019s requirements and provide suggestions / solutions based on client\u2019s inquiries;\nCommunicate and solve problem during project period with clients;\nWrite up reports for clients about monthly updates, campaign effectiveness, marketing outcomes, data insights, competitor analysis, etc.\n\n\u00a0What You Need for this Position:\n\n\nDegree or above in Business, Advertising, Marketing, Journalism, Media, Public Relations, Communications, Information system, E-commerce,\u00a0project management or related discipline;\n1-2 years solid experience in accounts servicing, preferably in\u00a0managing online advertising and social media projects;\nFluent in written Chinese and English and\u00a0spoken Mandarin, English and Cantonese;\nExcellent communication, interpersonal and negotiation skills is a must;\nMature, attention to details and ability to work under tight timeline and multi-task independently;\nAgency experiences are preferred;\nProficiency in MS office application;\n\n\u00a0Benefits We Offer:\n\n\u00a05 days\u2019\u00a0work\nQuarterly Performance Bonus\nMedical Coverage including Dental\nFlexible Working Hours\nOvertime\u00a0Meal\u00a0and Transportation allowance\nBirthday, Wedding, Graduation and other special leaves\nFun, young and joyful environment\u00a0\n\n\u00a0Be a GURU, be our next great hire.\u00a0APPLY NOW!\n\n*All information will be treated as confidential and used solely for recruitment purposes.", "employment_types": ["Full Time", "Permanent"], "selling_points": [], "locations": ["Lai Chi Kok"], "categories": ["Media & Advertising", "Account Servicing", "Design", "Graphics", "Multi-media"], "post_time": "2022-01-11T17:22:32Z", "salary": {"currency": null, "max": null, "min": null, "period": "monthly", "term": null}, "salary_visible": false, "title_keywords": ["senior account manager", "senior account executive", "account manager"], "responsibilities": ["social media", "advertising", "data", "analysis", "teams", "develop", "communication", "project management", "digital marketing", "reports", "plan", "banking", "client\u2019s requirements", "online advertising"], "requirements": {"degrees": ["degree or above"], "majors": ["e-commerce", "journalism", "project management", "business", "marketing", "communications"], "languages": ["cantonese", "english", "chinese", "mandarin"], "language_level": ["fluent"], "hard_skills": ["e-commerce", "analysis", "information system", "project management", "ms office"], "soft_skills": ["independently", "multi-task", "mature", "communication", "project management", "negotiation skills", "attention to details", "interpersonal"], "languages_combined": [{"language": "cantonese", "language_level": ["fluent"]}, {"language": "english", "language_level": ["fluent"]}, {"language": "chinese", "language_level": ["fluent"]}, {"language": "mandarin", "language_level": ["fluent"]}]}, "experience_required": {"duration": ["1-2 years"], "field": ["agency", "social media", "advertising"]}}, {"job_id": "100003009039613", "location_code": "hk", "company": "Shepherd Communications Limited", "job_title": "Senior Account Manager", "description": "What you get:\u00a0\n\nJob security:\u00a0 Part of Publicis Groupe - world's 3rd largest, fully\u00a0integrated communications group\u00a0with offices across 100 countries, employing over 80,000 staffs globally\nExcellent office environment - conveniently located, spacious, stylish office with an outdoor terrace for some fresh air\nLearning opportunity:\u00a0 Chance to work with, and learn the management philosophies from a well-structured organisation\nBirthday leave\n5-day work-week\nGroup medical & life insurance coverage\nFun & energetic company culture\n\nThe Digital Executive will work closely supporting the PPC business with the day-to-day management of paid search campaigns. This person will report directly to the Digital Manager and is responsible for tracking, analyzing and executing paid search strategies, ensuring that all deliverables are executed on time and produce a high standard of quality for all client deliverables. The Digital Executive will acquire in-depth paid search knowledge, while utilizing the creativity, attention to detail and analytical skills needed to grow a career within the agency.\n\nResponsibilities\n\nHolistic SEM program management including keywords development, ad creative and strategy, trafficking recommendations, optimizing program towards key business goals and reporting\nActively participating in meetings and proactively documenting takeaways and next steps\nAssimilating data from multiple sources, compiling the information and drawing actionable conclusions that can be measured and reported\nBid strategy optimization and testing. Daily checks on program KPIs, thresholds and campaign budget caps. Ongoing management of budget and pacing.\nTranslating campaign/client goals into SEM tactics and effectively executing those tactics against the client\u2019s strategy\nImplementing Paid Search best practices, providing refinement and optimization recommendations and proactively identifying campaign execution issues\nMonitoring emerging industry trends and summarizing them for internal and external stakeholders\nLeveraging and developing proficiencies with SEM platforms, tools and resources\nDeveloping campaign ad copy (text-based titles and descriptions or feed-based images) and tagging traffic or creative elements to sites per creative rotation instructions\nHelp develop performance forecasts, budget allocations and providing data-based rationale for these recommendations\nCollaborating with both clients and internal cross-channel colleagues by providing reporting as requested in a concise and timely fashion\nFostering relationship with internal teams, external partners and clients\n\nCompetencies\n\nFresh graduates with a relevant degree such with a concentration such as Business Systems Management and Information Management, with the passion and interest in the digital media business\n1 or more years of paid search experience, with knowledge of bid management platforms a plus\nStrong ability to work closely with your team to problem solve, prioritize tasks, and manage time effectively\nA detail-oriented approach and a desire to achieve objectives accurately\nSolid quantitative and research skills, and proven data interpretation capability\nFamiliarity with the digital advertising space and a passion for growing that interest into a career\nStrong communication skills \u2013 you\u2019re clear and thorough, yet concise\nA passion for building relationships and a desire to contribute to team building and event planning\nExudes confidence and won\u2019t hesitate to connect with\u00a0colleagues\u00a0throughout the organization to get the job done right\nCandidates with more experience may be considered as Digital Specialist\u00a0\n\n\nAll information collected will be solely used for recruitment purposes only.", "employment_types": ["Full Time", "Permanent"], "selling_points": ["Lead & coach a small team of account executives", "Help business partners achieve business objectives", "Support overall business development"], "locations": ["Sai Ying Pun"], "categories": ["Media & Advertising", "Account Servicing", "Strategic Planning", "Marketing / Public Relations", "Digital Marketing"], "post_time": "2022-01-11T10:13:17Z", "salary": {"currency": null, "max": null, "min": null, "period": "monthly", "term": null}, "salary_visible": false, "title_keywords": ["senior account manager"], "responsibilities": ["business goals", "data", "budget", "quality", "communication", "advertising", "teams", "developing", "testing", "day-to-day management", "develop", "kpis", "report", "reporting", "management", "monitoring", "executing", "tracking", "systems", "recruitment", "sem", "insurance", "planning"], "requirements": {"degrees": ["degree"], "majors": ["business"], "languages": [], "language_level": [], "hard_skills": ["sem", "plus", "fun", "analytical skills"], "soft_skills": ["communication skills", "confidence", "creative", "responsible", "research skills", "problem solve", "passion for", "timely", "prioritize", "analytical skills", "detail-oriented", "clear", "learning", "thorough", "organisation", "structured", "attention to detail", "energetic"], "languages_combined": []}, "experience_required": {"duration": [], "field": ["digital", "management"]}}, {"job_id": "100003009048795", "location_code": "hk", "company": "now TV", "job_title": "Senior Marketing Executive, Hong Kong", "description": "Requirements:\n\nBachelor degree\u00a0in\u00a0Advertising,\u00a0Mass\u00a0Communication,\u00a0Marketing or related disciplines;\n1 - 2\u00a0year\u00a0of relevant\u00a0work\u00a0experience\u00a0with proven capabilities of being strategic and creative in handling digital marketing campaigns;\n\u00a0A natural user of social media and forums as well as natural player of mobile games\n\u00a0Passionate and familiar with various online media platforms;\nGood marketing sense, multi-tasking and good management;\nPresentable, independent, proactive and creative;\n\u00a0A good team player, able and flexible to work with people of different cultures;\n\nResponsibilities:\n\n- Help develop integrated digital marketing solutions for clients, including but not limited to social \u00a0media maintenance, creative campaign, video campaign, website production, O2O solution, media \u00a0placement, Social CRM, etc.\n\n- Formulate insightful strategies and creative ideas to meet clients\u2019 objectives, ensure successful \u00a0execution, flow and end-result.\n\n- Prepare documents to pitch clients, e.g. marketing plan, schedule, budget etc.;\n\n- Present ideas to clients together with the Project Management Team, if necessary;\n\n- Explore and assimilate the latest digital marketing trends and develop knowledge management \u00a0 \u00a0database for internal and external training\n\n- Assist in key client project management and coordinate communication with both internal and \u00a0external parties.\n\nWe offer performance bonus, medical coverage, bank holidays, and wedding leaves to right candidates. Interested parties please send a cover letter stating your expected salary, resume and\u00a0a full set of your portfolio\u00a0to\u00a0Mr. Yeung.\u00a0\n\n*All information will be treated as confidential and used solely for recruitment purposes.", "employment_types": ["Full Time", "Permanent"], "selling_points": [], "locations": ["Kowloon Bay"], "categories": ["Media & Advertising", "Account Servicing", "Strategic Planning", "Marketing / Public Relations", "Digital Marketing"], "post_time": "2022-01-14T07:17:57Z", "salary": {"currency": null, "max": null, "min": null, "period": null, "term": null}, "salary_visible": false, "title_keywords": ["senior marketing executive"], "responsibilities": ["creative ideas", "management", "ideas", "maintenance", "budget", "external parties", "website", "develop", "coordinate", "marketing plan", "project management", "communication", "digital marketing", "schedule", "database", "prepare documents"], "requirements": {"degrees": ["degree", "bachelor"], "majors": ["related disciplines", "marketing"], "languages": [], "language_level": [], "hard_skills": ["mobile"], "soft_skills": ["passionate", "flexible", "good team player", "proactive", "marketing sense", "independent", "presentable", "communication", "multi-tasking", "creative"], "languages_combined": []}, "experience_required": {"duration": ["1 - 2 year"], "field": ["digital marketing"]}}, {"job_id": "100003009043010", "location_code": "hk", "company": "Mediacom Limited", "job_title": "MediaCom | Senior Manager", "description": "Responsibilities:\n\nResponsible to do the copywriting in various social media platforms\nAssist in preparing analytic reports and proposal\nResponsible to follow up on integrated marketing events\nHighly involve in customer servicing, social media marketing and account servicing management\nCreation and development of presentation materials for marketing and communications\nCreative, self-motivated, responsible, polite, able to work independently and under pressure\n\n\n\nRequirements:\n\nUniversity degree in Journalism / Public Relations / Marketing\u00a0etc.\nGood command of written and spoken English and Chinese\nStrong Media Connections preferably in lifestyle\nActive on social media platforms\nHard-working, able to multi-task, work under pressure and meet deadlines\u00a0\nAble to handle projects independently\nDetail-minded, mature, outgoing, good interpersonal skills and flexible to work\u00a0\n\n\n\nSalaries are subjected to working performance and skills possessed.\n\nTips: Have a look at our website first!\n\nhttp://www.firebean.net\n\nIf you are the perfect fit for Firebean, please email your resume, profile and expect salary by clicking \"Apply Now\" We look forward to meeting you.\n\nAll applications received will be used strictly for selection purposes only.", "employment_types": ["Full Time", "Permanent"], "selling_points": [], "locations": ["Quarry Bay"], "categories": ["Media & Advertising", "Account Servicing", "Media Buying", "Strategic Planning"], "post_time": "2022-01-12T09:31:31Z", "salary": {"currency": null, "max": null, "min": null, "period": "monthly", "term": null}, "salary_visible": false, "title_keywords": ["senior manager"], "responsibilities": ["marketing events", "management", "social media", "social media platforms", "reports"], "requirements": {"degrees": ["university degree"], "majors": ["journalism", "marketing"], "languages": ["english", "chinese"], "language_level": ["good command"], "hard_skills": [], "soft_skills": ["detail-minded", "outgoing", "flexible", "independently", "multi-task", "mature", "hard-working", "interpersonal skills", "meet deadlines", "active", "work under pressure"], "languages_combined": [{"language": "english", "language_level": ["good command"]}, {"language": "chinese", "language_level": ["good command"]}]}, "experience_required": {"duration": [], "field": []}}, {"job_id": "100003009042591", "location_code": "hk", "company": "ESD Services Limited (ESDlife)", "job_title": "Account Manager (Digital Media Advertising)", "description": "Responsibilities:\n\n\nCheck and ensure the accuracy and quality of every design layout and artwork.\u00a0Proofreading of POP materials before they are online and print.\nWork closely with design team and responsible for account management and ensure client\u2019s requirements and expectation are satisfied.\nResponsible for cost estimate, planning and project management for a broad range of multinational accounts\nTo develop effective advertising campaign, print or online promotional materials, public communications and program\nTo develop company's own products and business, assist on project management, marketing and sale campaign\n\nRequirements:\n\n2+ years working experiences in advertising agency, customer services or project management\nPassion on design related aspects (print or online) and ready for implementing your creativity.\nEnergetic, presentable, independent, self-confident with innovative thinking\nSelf-motivated, hardworking, multitasking, detail-minded, pleasant personality and a good team player with excellent communication skills\nStrong problem solving skills and time management, able to work under pressure & meet tight deadline\nExperience working\u00a0in digital\u00a0agency / online marketing is an advantage\n\nInterested applicants please provide your resume, availability with expected salary for application enquiry.\n\nPersonal data collected will be used for recruitment purpose only.\u00a0", "employment_types": ["Full Time", "Permanent"], "selling_points": [], "locations": ["Hung Hom"], "categories": ["Media & Advertising", "Account Servicing", "Strategic Planning", "Sales, CS & Business Devpt", "Business Development"], "post_time": "2022-01-12T08:06:03Z", "salary": {"currency": null, "max": null, "min": null, "period": "monthly", "term": null}, "salary_visible": false, "title_keywords": ["account manager"], "responsibilities": ["pop materials", "management", "cost", "advertising", "quality", "design", "develop", "project management", "proofreading", "promotional materials", "client\u2019s requirements", "planning"], "requirements": {"degrees": [], "majors": [], "languages": [], "language_level": [], "hard_skills": ["project management", "problem solving skills"], "soft_skills": ["confident", "detail-minded", "self-motivated", "good team player", "independent", "communication skills", "presentable", "innovative", "project management", "pleasant", "time management", "meet tight deadline", "problem solving skills", "energetic", "hardworking", "work under pressure"], "languages_combined": []}, "experience_required": {"duration": ["2+ years"], "field": ["agency", "customer services", "project management", "marketing", "advertising agency", "digital"]}}, {"job_id": "100003009038113", "location_code": "hk", "company": "Velvet Limited", "job_title": "Account Executive", "description": "Job Responsibilities:\n\nLead & coach a small team of account executives and senior account executives \u00a0\nResponsible for day to day project administration in a meticulous and timely manner\nDevelop thorough understanding of the brands and apply relevant knowledge to meet or exceed clients\u2019 expectation\nPrepare budget summary and follow through project campaigns\nManage campaigns deliverables and coordinate with the creative team to implement the best class of advertising campaigns\nBring in new business\n\n\u00a0Qualifications, Skills and Other Requirement\n\nDegree or above in business, advertising, marketing, communications, journalism, e-commerce, project management or related discipline\nWith minimum 6 years relevant experience\u00a0\nExcellent communication in both written and oral presentations (English and Chinese)\nDetail-minded, well-organised, a good team leader and a strong sense of responsibility\nDemonstrate a positive attitude with ability to get things done\n\nAttractive salary &\u00a05-day work per week. Interested parties please email full CV with both\u00a0present & expected salary\u00a0by clicking \"APPLY NOW\".", "employment_types": ["Full Time"], "selling_points": ["Fresh Graduates are also welcome", "Basic knowledge of social media, online marketing", "Immediately available is highly preferred"], "locations": ["Kwun Tong"], "categories": ["Media & Advertising", "Account Servicing", "Sales, CS & Business Devpt", "Account Servicing", "Sales Administration"], "post_time": "2022-01-11T05:15:47Z", "salary": {"currency": null, "max": null, "min": null, "period": "monthly", "term": null}, "salary_visible": false, "title_keywords": ["account executive"], "responsibilities": ["advertising", "budget", "coordinate with", "presentations", "develop", "communication", "project management", "project administration", "advertising campaigns"], "requirements": {"degrees": ["degree or above"], "majors": ["e-commerce", "journalism", "project management", "business", "marketing", "communications"], "languages": ["english", "chinese"], "language_level": ["excellent"], "hard_skills": ["small", "project management", "presentations", "e-commerce"], "soft_skills": ["detail-minded", "meticulous", "oral", "responsible", "sense of responsibility", "timely", "communication", "project management", "positive attitude", "thorough", "well-organised", "good team leader", "creative"], "languages_combined": [{"language": "english", "language_level": ["excellent"]}, {"language": "chinese", "language_level": ["excellent"]}]}, "experience_required": {"duration": ["minimum 6 years"], "field": ["relevant experience"]}}, {"job_id": "100003009048394", "location_code": "hk", "company": "AIA Hong Kong and Macau", "job_title": "CS Business Development, Agency Distribution, Principal (Senior Manager)", "description": "Your New Role\n\nAs a member of our now TV marketing team, you will assist in marketing to achieve business targets and objectives.\u00a0 Major duties include but not limited to:\n\nPlan, implement and manage execution of marketing program and offer by working closely with cross-functional departments to encourage contract renewal and revenue protection.\nAssist line manager to launch out new service from planning, preparation to service rollout.\nWork for online subscription and self-subscription platform such as TV portal subscription or website subscription to generate revenue to the company.\nPrepare program evaluation of each campaign and measure campaign effectiveness.\nAssist in analyzing customer portfolio and updating regular reports to monitor the targeted segments.\nSupport and prepare, marketing collaterals for the responsible market segment.\nWork closely with product team, sales channels and various marketing team.\n\nWhat makes you succeed\n\nUniversity graduate in Marketing, Business Administration or related discipline\nAt least 4-5\u00a0years experience in marketing, preferrable with some working experiences in telecommunication, banking or pay TV industry.\nStrong business sense with analytical abilities.\nAble to work independently and under tight schedule\nGood project management and communication skills\nGood command of written and spoken English and Chinese", "employment_types": ["Full Time"], "selling_points": ["Experience in Business Development for agencies", "People management experience", "Strategic planning and critical thinking"], "locations": ["Quarry Bay"], "categories": ["Media & Advertising", "Account Servicing", "Sales, CS & Business Devpt", "Sales - Sales Management"], "post_time": "2022-01-14T06:27:55Z", "salary": {"currency": null, "max": null, "min": null, "period": "monthly", "term": null}, "salary_visible": false, "title_keywords": ["senior manager"], "responsibilities": ["administration", "marketing collaterals", "monitor", "website", "banking", "communication", "project management", "reports", "schedule", "plan", "evaluation", "planning"], "requirements": {"degrees": ["university graduate"], "majors": ["marketing", "business administration"], "languages": ["english", "chinese"], "language_level": ["good command"], "hard_skills": ["project management"], "soft_skills": ["communication skills", "work independently", "responsible", "business sense", "project management"], "languages_combined": [{"language": "english", "language_level": ["good command"]}, {"language": "chinese", "language_level": ["good command"]}]}, "experience_required": {"duration": ["at least 4-5 years"], "field": ["marketing", "banking"]}}, {"job_id": "100003009048553", "location_code": "hk", "company": "ProJob21.com Limited", "job_title": "Growth Marketing Manager/ Assistant Manager (DTC e-Commerce)", "description": "Overview of job\n\nMediaCom is an agency of GroupM, the world\u2019s largest media investment company and are a part of WPP. In fact, we are responsible for one in every three ads you see globally. We are currently looking for a\u00a0Senior Manager\u00a0to join us. In this role, you will be responsible for servicing clients of international brands at regional level, providing integrated media strategy plans as well as managing campaign executions and reporting. You will be working closely with few local markets in APAC, and to provide them guidance and to shape local media recommendations. You will also assist team leader in mentoring junior staff and collaborating with cross functional teams within the Company offices and the WPP network.\n\nAt GroupM APAC, our people are our strength, which is why fostering a culture of diversity and inclusion is important to us.\n\nReporting of the role\n\nThis role reports to: Regional Business Director\n\n3 best things about the job:\n\nYou will work on various accounts which will challenge your critical thinking & creative ideations\nWork side-by-side with few key markets in APAC and guide and educate to ensure consistent and high-quality media recommendation. Bridge communications with some of the HQ offices in US, UK & Paris offices\nJoin the winning team that is proud of the work they deliver while enjoying what we do\n\nIn this role, your goals will be:\n\nIn 3 months:\n\nCompleted inductions with internal teams and develop a rock-solid chemistry with key stakeholders, including the clients and local markets;\nBecome fully up-to-speed with the APAC media landscape in general, and competitor media landscape specifically to the travel industry;\nUnderstand the clients\u2019 business and brand situation, and the way of working and communication flow with local teams and agency partners;\nCompleted all the tools training (if not familiar with the systems already) and understand how MediaCom develops communication planning;\nProvided constructive feedback about the day-to-day job duty of junior members of the team\n\nIn 6 months:\n\nHave a full understanding of all key accounts and their performance and ad operations requirements;\nAlready established trusted relationship with client management and custodianship;\nDemonstrated ability to evaluate and provide constructive feedback to local teams in shaping their strategies and media recommendations;\nDemonstrated creativity and innovative mindset in client\u2019s briefs and problem solving.\n\n\u00a0In 12 months:\n\nGot into a strong habit of delivering excellent work with accuracy;\nManaged the full annual planning proposal for your key accounts;\nSuccessfully work on, or lead, cross-functional teams with clients, internal teams, and media owners;\nWorked in close collaboration with the team on future communication directives for your assigned client to address the dynamic media development, with a focus on innovation;\nBecome an invaluable partner to your clients.\n\nWhat your day job looks like:\n\nOversee campaign strategy, planning, implementation, and reporting;\nWork closely with local markets in guiding on planning and execution;\nDevelop and maintain strong relationships with clients, agency partners and vendors;\nSet expectations and manage delivery on multiple projects at the same time;\nSupervise implementation team on deliverables, provide suggestions to problem solve issues;\nSupervise a team comprised of 2-3 junior team members.\n\nMinimum qualifications:\n\n6+ years account planning, media communications planning, brand strategy, or marketing experience\nExperience in working on regional capacity is preferred but not a must\nYou\u2019ll be comfortable taking action on follow-ups by doing the nuts and bolts work yourself and leading by example\nDemonstrate strategic & critical thinking and effective problem-solving skills\nStrong quantitative & qualitative analytical skills especially in the area of assessing consumer insights, media landscape & media metrics\nExperience in TV planning is a plus\nYou enjoy working in, and managing multi-cultural teams where English is not the first language\nExcellent communication skills\nFluent written and spoken English and Chinese is a must\nAbility to work effectively and collaboratively with other teams/business units\nNatural curiosity and dynamism\nEnjoy challenging the status quo and push through new ideas\n\nAbout MediaCom\n\nWe believe in People First, Better Results.\n\nMediaCom unleashes brands\u2019 growth by helping them See the Bigger Picture. This means that we apply our unique \u2018Systems Thinking\u2019 philosophy and technology to all marketing levers: media, message and data. As a result, we design communication strategies that deliver short term results and help brands build for the future.\n\nAs part of WPP, the world's largest marketing communications services group, and GroupM, WPP\u2019s consolidated media investment management arm, we have access to the richest data, most robust benchmarks and most advanced capabilities in the market. This helps us provide comprehensive solutions to all marketing challenges.\n\nOur success is underpinned by our long-standing \u2018People First, Better Results\u2019 belief. We know that by investing in our people\u2019s whole-person wellbeing, careers and capabilities, we will help grow our clients\u2019 businesses.\n\nIn 2020 this approach led MediaCom to be crowned Global Media Network of the Year by Eurobest and Festival of Media Global, in addition to being the most awarded agency at the WARC Media Awards.\n\nMediaCom is one of the world\u2019s leading media communications specialists, with billings of US$17.6 billion (Source: COMvergence, 2020), employing 8,000 people in 125 offices across 100 countries. Its global client roster includes adidas, Coca-Cola (TCCC), Dell, Groupe PSA, Hasbro, Mars, NBC Universal, P&G, Richemont, Shell, Sony, Uber and Walgreens Boots Alliance.\n\nTo find out more about MediaCom visit us here:\u00a0 www.mediacom.com", "employment_types": ["Permanent"], "selling_points": [], "locations": ["Not Specified"], "categories": ["Media & Advertising", "Account Servicing", "Marketing / Public Relations", "Digital Marketing", "E-commerce", "Marketing - Brand / Product Management"], "post_time": "2022-01-14T07:03:43Z", "salary": {"currency": null, "max": null, "min": null, "period": "monthly", "term": null}, "salary_visible": false, "title_keywords": ["assistant manager", "marketing manager"], "responsibilities": ["ideas", "data", "operations", "quality", "design", "communication", "maintain", "plans", "communications with", "billings", "teams", "implementation", "develop", "reports", "guidance", "reporting", "management", "consumer insights", "cross-functional teams", "systems", "evaluate", "multiple projects", "planning"], "requirements": {"degrees": [], "majors": [], "languages": ["english", "chinese"], "language_level": ["fluent"], "hard_skills": ["plus", "analytical skills", "problem solving", "dynamic", "problem-solving skills", "focus"], "soft_skills": ["work effectively", "communication skills", "advanced", "responsible", "problem solve", "enjoy working", "unique", "innovative", "communication", "problem solving", "analytical skills", "dynamic", "robust", "comprehensive", "problem-solving skills", "focus", "creative", "constructive"], "languages_combined": [{"language": "english", "language_level": ["fluent"]}, {"language": "chinese", "language_level": ["fluent"]}]}, "experience_required": {"duration": ["6+ years"], "field": ["marketing", "brand", "media", "planning"]}}, {"job_id": "100003009044842", "location_code": "hk", "company": "HSBC Group", "job_title": "Senior Mortgage Service Officer - Wealth & Personal Banking", "description": "Bring your career aspirations to life with AIA!\n\nLead and manage sub-ordinates to develop and execute strategies and build relationships with agency to meet and exceed sales targets\n\nRoles and responsibilities:\n\nAgency Activities Management\n\nHelp formulate sales strategies and execute the plans\n\nSupport and push CS business by ensuring efficient support is delivered to front line\n\nKeep abreast of market development and provide effective promotional programme for agency to increase awareness within the agency channels\n\nProvide help desk at agency offices, if applicable\n\nPerform any other duties and projects as assigned\n\nPeople Management\n\nProvide coaching, training and development to the team\n\nAllocation of proper resources to support the team and agency\n\nMinimum Job requirements:\n\nUniversity graduate with minimum 10 years sales experience of which 6-8 years in supervisory/managerial positions\n\nGood product knowledge\n\nGood communication skills\n\nAble to manage a project/event independently\n\nGood command of English and Chinese\n\nTactful interpersonal relationship\n\nGood presentation and team building skills\n\nSelf-motivated and customer orientated\n\nPreferably IIQE (paper 1,2,3 & 4) licensed\n\nEnsure team members who perform regulated activities have obtained the relevant licenses and fulfilled the licensing requirements\n\nBuild a career with us as we help our customers and the community live healthier, longer, better lives.\n\nYou must provide all requested information, including Personal Data, to be considered for this career opportunity. Failure to provide such information may influence the processing and outcome of your application. You are responsible for ensuring that the information you submit is accurate and up-to-date.", "employment_types": ["Full Time"], "selling_points": ["Impact on the Business/Function", "Customers / Stakeholders", "Operational Effectiveness & Control"], "locations": ["Kowloon City"], "categories": ["Media & Advertising", "Account Servicing", "Banking / Finance", "Asset Management"], "post_time": "2022-01-13T06:26:53Z", "salary": {"currency": null, "max": null, "min": null, "period": "monthly", "term": null}, "salary_visible": false, "title_keywords": ["officer", "personal"], "responsibilities": ["plans", "management", "any other duties", "support the team"], "requirements": {"degrees": ["university graduate"], "majors": [], "languages": ["english", "chinese"], "language_level": ["good command"], "hard_skills": ["iiqe", "processing"], "soft_skills": ["communication skills", "self-motivated", "independently", "responsible", "presentation", "accurate", "tactful", "interpersonal"], "languages_combined": [{"language": "english", "language_level": ["good command"]}, {"language": "chinese", "language_level": ["good command"]}]}, "experience_required": {"duration": ["minimum 10 years", "6-8 years"], "field": ["managerial", "supervisory"]}}, {"job_id": "100003009042259", "location_code": "hk", "company": "PHD Limited", "job_title": "Regional Performance Specialist, ASP HUB (Advertising & Media Field)", "description": "Responsibility:\n\nHandle multiple client projects such as video production, influencer activation, social media management, and other digital marketing campaigns;\nProvide creative inputs in social media content and campaign planning;\nManage timeline to ensure smooth project execution;\nPrepare proposals and support new clients pitching;\nLiaise with and provide creative briefings to vendors, designers, internal and external parties;\nMonitor project implementation and performance against KPIs;\nCompile regular and post-campaign reports for project performance evaluations;\nStay alert to industry happenings and able to share insights;\u00a0\n\nRequirement:\u00a0\n\nDegree in Media, Marketing, Communications or related discipline;\nMinimum 1 year experience on digital/social media management or other relevant work experience;\nDemonstrate strong communication and presentation skills;\nFamiliar with the social media & influencer landscape and practices in Hong Kong;\u00a0\nProficiency in written and spoken English and Chinese;\u00a0\nProactive, passionate, and a detail-minded team player;\nGood multi-tasking skills, willing to work under pressure and tight schedules;\nExperience working with social listening and social media management tools is a plus; \u00a0\nImmediate availability is highly preferred;\nCandidate with more experience will be considered as Senior Account Executive;\n\nAll personal data collected will be kept confidential and used for recruitment purpose only.", "employment_types": ["Full Time", "Permanent"], "selling_points": ["Fun and Energetic Team Culture", "Birthday, Family Day & Self-Love Day Leave", "5-Day Work Week"], "locations": ["Pok Fu Lam"], "categories": ["Media & Advertising", "Account Servicing", "Strategic Planning", "Others"], "post_time": "2022-01-12T06:46:03Z", "salary": {"currency": null, "max": null, "min": null, "period": "monthly", "term": null}, "salary_visible": false, "title_keywords": ["performance specialist"], "responsibilities": ["social media", "management", "video production", "digital marketing campaigns", "internal and external parties", "monitor", "implementation", "social media content", "reports", "liaise with", "kpis", "planning"], "requirements": {"degrees": ["degree"], "majors": ["marketing", "communications"], "languages": ["english", "chinese"], "language_level": ["proficiency"], "hard_skills": ["plus"], "soft_skills": ["detail-minded", "passionate", "communication", "presentation skills", "multi-tasking skills", "team player", "proactive", "work under pressure"], "languages_combined": [{"language": "english", "language_level": ["proficiency"]}, {"language": "chinese", "language_level": ["proficiency"]}]}, "experience_required": {"duration": ["minimum 1 year"], "field": ["digital", "management", "social media"]}}, {"job_id": "100003009038338", "location_code": "hk", "company": "PHD Limited", "job_title": "Planning Manager (Advertising & Media Field)", "description": "NY Sustainable Designer home d\u00e9cor business\nAgile Culture & Robust Business Expansion\nChampion Digital Marketing initiatives\nThe Role\n\nJoin a fun and high-achieving small team and be part of the global strategic hub to drive business and sustainability values for a beautifully designed and environmental-friendly New York home d\u00e9cor brand\nThe team is on a mission to make a material difference to do good for the people and the planet, engage artisans from around the world to support local communities\nWith ambition to map out the exciting journey to grow the business in the region, this is an expansion hire in Hong Kong\nYou will be the go-to Digital Marketing / Growth Hacker, helping to optimize the customer web experience while enforcing the identity of the brand by continuously improving the content, design, and UX of the website and social media presence\nYou will also work together with tech, marketing/external agencies, product, and operations to drive traffic to the website and promote the products; strategize and track CRM programs and creative campaigns to acquire new customers\nBenefits: flexible hours, chic working space, 20 days+ leave\n\nThe Person\n\nDegree holder with about 3-5 years\u2019 experience as a Digital Marketer ideally for e-commerce business\nPassionate about home d\u00e9cor/sustainable wellness living\nSelf-starter with high standards and attention to details\nAnalytical and creative, with experience managing cross-functional partners and multiple stakeholders\nHigh caliber candidates at digital agency who are business savvy are encouraged to apply\nFluent in written and speaking Chinese (Both Cantonese and Putonghua) and English\nEarly availability preferred\n\nInterested candidates, please email your update resume (in MS WORD format) with current and expected salary to us soonest.\n\nAlso come visit ProJOB21 www.ProJob21.com to discover other exciting career opportunities!\n\nAll information received will be kept in strict confidence and used for employment-related purposes only.", "employment_types": ["Full Time", "Permanent"], "selling_points": ["Free Shuttle Bus & Free Breakfast", "Birthday, Family Day & Self-Love Day Leave", "5-Day Work Week"], "locations": ["Pok Fu Lam"], "categories": ["Media & Advertising", "Account Servicing", "Strategic Planning", "Others"], "post_time": "2022-01-11T06:35:04Z", "salary": {"currency": null, "max": null, "min": null, "period": "monthly", "term": null}, "salary_visible": false, "title_keywords": ["manager"], "responsibilities": ["social media", "operations", "website", "design", "digital marketing"], "requirements": {"degrees": [], "majors": [], "languages": [], "language_level": [], "hard_skills": ["small", "agile", "fun", "web experience", "make", "go"], "soft_skills": ["creative", "friendly", "agile", "robust"], "languages_combined": []}, "experience_required": {"duration": [], "field": ["social media", "digital marketing", "brand", "design"]}}, {"job_id": "100003009042725", "location_code": "hk", "company": "She Communications Ltd", "job_title": "Executive  / Senior Executive, Digital & Social Media", "description": "Digital Advertising\n\nMonitor and optimize performance for digital media campaigns (SEM, programmatic, social, etc) in a daily manner\nAnalyze weekly/monthly/seasonal performance data to generate insights and take actions to maximize online conversions\nManage media agency for in-depth optimization on sales acquisition and leads generation performance\n\nDigital Campaigns\n\n\nAssist in the planning and executions of brand campaign, social media promotions and product launch campaigns\nHandle the productions of various digital marketing materials such as website, display ads, social posts, eDM, animation, videos, etc and develop ad content copywriting\nResponsible for campaign fulfilment to eligible customers\nPerform ad hoc assignment or other related duties as assigned\nMonitor campaign budget and expenses\nPrepare post-campaign report and provide recommendations based on the insights\n\nDigital Partnerships\n\n\nExplore and develop new partnerships to extend AXA's presence in the market\nGrow and maintain relationship with existing partners to grow the business, build product awareness and generating leads\n\nJob Requirements:\n\nUniversity graduate or equivalent\nMinimum 3 years' experience in digital marketing, preferably in insurance, banking, financial institutions or advertising agency\nExperience in paid search and digital advertising knowledge is preferred\nGood understanding on digital advertising tools such as Google Analytics, Google Adwords, Facebook Business Manager, and other web/app analytics, etc\nGood command of English & Chinese with strong interpersonal and problem solving skills\nStrong numeric and analytical skill, and good business senses\nAttention to details, self-initiative and result-oriented\nA good team player, be proactive and with can-do spirit. Have a strong sense of ownership & accountability\nGood project management experience\nProficiency in MS Office (Word, Excel, PowerPoint) and computer literacy", "employment_types": ["Full Time", "Permanent"], "selling_points": ["Social media savvy", "Creative & passionate", "Energetic & has a good sense in trending topics"], "locations": ["Sheung Wan"], "categories": ["Media & Advertising", "Account Servicing", "Marketing / Public Relations", "Public Relations - Copy-writing", "Digital Marketing"], "post_time": "2022-01-12T08:32:31Z", "salary": {"currency": null, "max": null, "min": null, "period": "monthly", "term": null}, "salary_visible": false, "title_keywords": ["senior executive", "executive"], "responsibilities": ["data", "budget", "website", "maintain", "facebook", "advertising", "ad hoc assignment", "expenses", "monitor", "develop", "digital campaigns", "banking", "report", "social media", "edm", "digital marketing", "provide recommendations", "project management", "sem", "insurance", "animation", "planning"], "requirements": {"degrees": ["university graduate"], "majors": [], "languages": ["english", "chinese"], "language_level": ["good command"], "hard_skills": ["google analytics", "analytical skill", "excel", "web", "adwords", "word", "powerpoint", "project management", "sem", "facebook", "problem solving skills", "ms office"], "soft_skills": ["result-oriented", "analytical skill", "good team player", "responsible", "accountability", "project management", "computer literacy", "self-initiative", "attention to details", "can-do", "problem solving skills", "proactive", "interpersonal"], "languages_combined": [{"language": "english", "language_level": ["good command"]}, {"language": "chinese", "language_level": ["good command"]}]}, "experience_required": {"duration": ["minimum 3 years"], "field": ["advertising", "project management", "digital marketing", "advertising agency", "banking", "digital", "financial institutions", "insurance"]}}, {"job_id": "100003009034515", "location_code": "hk", "company": "\u4e00\u5a92\u9ad4\u5ee3\u544a\u7b56\u5283\u6709\u9650\u516c\u53f8", "job_title": "Account Manager \u2013 Hong Kong", "description": "Responsibilities\u00a0\n\nResponsible for day-to-day account management, particularly on project execution to ensure delivery and quality control.\u00a0 Also to serve as key contact person with clients at operation level.\nDevelop and maintain close and effective client relationships.\nAssist in the co-ordination, writing and verbal briefing of internal and external resources as required.\nWork with the Creative/Media to deliver high quality project deliverables within budget and on schedule and post campaign follow up\nProvide updates to budgets and help team leader/members to ensure timing plans are fully up to date.\nEffectively delegate specific tasks based on Brief requirements.\nSupport on ad hoc projects\u00a0\n\nRequirements\u00a0\n\nUniversity degree holder, preferably in Marketing/ Communication/ New Media/ Advertising related discipline\n2~3 years of account management experience in agency or related fields\nAble to work under tight deadlines\nAble to work long hours and under pressure\nStrong aptitude for building \u201cpartner\u201d relationships with clients and colleagues\nAct as a team player, passionate and cheerful characters with innovative thinking and pleasant personality to serve our clients\nExcellent listening, communication and presentation skills\nFluent in English, Cantonese and Mandarin is a must\nAbility to manage several projects at once\nImmediate availability is highly preferred\n\nData collected will be used for recruitment purposes only. Personal data provided by job applicants will be used strictly in accordance with the Personal Data (Privacy) Ordinance.", "employment_types": ["Full Time", "Permanent"], "selling_points": [], "locations": ["Ngau Tau Kok"], "categories": ["Media & Advertising", "Account Servicing", "Marketing / Public Relations", "Public Relations - Event Management", "Photography / Video"], "post_time": "2022-01-10T03:33:32Z", "salary": {"currency": null, "max": null, "min": null, "period": "monthly", "term": null}, "salary_visible": false, "title_keywords": ["account manager"], "responsibilities": ["budgets", "management", "project deliverables", "budget", "quality", "develop", "maintain", "ad hoc projects", "contact", "quality control", "schedule", "plans"], "requirements": {"degrees": ["university degree"], "majors": ["marketing"], "languages": ["cantonese", "english", "mandarin"], "language_level": ["fluent"], "hard_skills": [], "soft_skills": ["passionate", "cheerful", "under pressure", "pleasant", "communication", "presentation skills", "team player", "innovative"], "languages_combined": [{"language": "cantonese", "language_level": ["fluent"]}, {"language": "english", "language_level": ["fluent"]}, {"language": "mandarin", "language_level": ["fluent"]}]}, "experience_required": {"duration": ["2~3 years"], "field": ["agency", "account management", "related"]}}, {"job_id": "100003009034624", "location_code": "hk", "company": "GroupM Limited", "job_title": "GroupM | Media Planner/ Senior Planner", "description": "F.6 or above\nIndependent with creative mind\nWilling to work irregular hours and under pressure\nVideo Production training preferred\nProficient in written & spoken English & Chinese as well as Mandarin", "employment_types": ["Full Time", "Permanent"], "selling_points": [], "locations": ["Quarry Bay"], "categories": ["Media & Advertising", "Account Servicing", "Media Buying"], "post_time": "2022-01-10T03:49:28Z", "salary": {"currency": null, "max": null, "min": null, "period": "monthly", "term": null}, "salary_visible": false, "title_keywords": [], "responsibilities": ["video production"], "requirements": {"degrees": [], "majors": [], "languages": ["english", "chinese", "mandarin"], "language_level": ["proficient"], "hard_skills": [], "soft_skills": ["creative", "independent", "under pressure"], "languages_combined": [{"language": "english", "language_level": ["proficient"]}, {"language": "chinese", "language_level": ["proficient"]}, {"language": "mandarin", "language_level": ["proficient"]}]}, "experience_required": {"duration": [], "field": []}}, {"job_id": "100003009042316", "location_code": "hk", "company": "Havas Worldwide Hong Kong Limited", "job_title": "Media Executive / Media Planner", "description": "Job Responsibilities :\n\nAssist the team leader in planning international marketing, both online and offline and help to service multi-national clients across a range of markets in APAC.\nPrepare evaluation of media opportunities, keep tracks of market trends by using industry tools and other research methods\nWork closely with media and digital planners, understand campaign objectives and implementation needs\nPrepare media plans, budget summaries, campaign follow ups and reports regularly\n\nJob Requirements\u00a0\u00a0:\n\nUniversity degree in business, marketing, advertising, communications, or a related field\n0-2 years of media planning/buying experience (Fresh graduate welcome)\u00a0\nMust be well organized and have strong quantitative/analytical skills\nAttentive to detail\nFluent written and spoken English and Chinese is a must\nProficiency in Word, Excel and PowerPoint\nWe offer 5-day work week, birthday and other special leaves, staff training, good salary package with MPF and Medical Coverage.\u00a0Interested parties please apply with full resume stating availability, current and expected salaries by clicking \"APPLY NOW\"\u00a0.\n\nFurther information about Havas Group is available on the company\u2019s website: havasgroup.com\n\nDue to high volume of applications, only eligible or matching candidates will be contacted by us. All personal data received will only be used for recruitment purpose and will be destroyed after the position is filled.", "employment_types": ["Full Time"], "selling_points": ["Fluent written and spoken English and Chinese", "Attentive to detail & well organized", "5-Day Work Week, Work Life Balance"], "locations": ["Kwun Tong"], "categories": ["Media & Advertising", "Account Servicing", "Strategic Planning", "Others"], "post_time": "2022-01-12T06:59:26Z", "salary": {"currency": null, "max": null, "min": null, "period": "monthly", "term": null}, "salary_visible": false, "title_keywords": ["executive"], "responsibilities": ["budget", "implementation", "reports", "evaluation", "plans", "planning"], "requirements": {"degrees": ["university degree", "fresh graduate"], "majors": ["business", "communications", "marketing"], "languages": ["english", "chinese"], "language_level": ["fluent"], "hard_skills": ["excel", "word", "powerpoint", "analytical skills"], "soft_skills": ["attentive to detail", "well organized", "analytical skills"], "languages_combined": [{"language": "english", "language_level": ["fluent"]}, {"language": "chinese", "language_level": ["fluent"]}]}, "experience_required": {"duration": ["0-2 years"], "field": ["media", "planning"]}}, {"job_id": "100003009037528", "location_code": "hk", "company": "Digitas Hong Kong Limited", "job_title": "Digital Media Specialist", "description": "The ASP HUB is the Centre of Excellence regional team, executing client's digital acquisition campaigns for 11 markets in Asia.\n\nWe work closely with local PHD and our clients to deliver campaign performance. We continuously share learning's to fast-track initiatives across markets, and we take pride in sharing our knowledge to improve client performance and agency capabilities.\n\nThe advantage of working in the regional team is that you have exposure to multiple markets, working closely with different departments internally and externally (e.g. marketing, product, data & analytics).\n\nWe have a very collaborate approach within the team; everyone\u2019s role and personal approach is critical to our success, especially as the team continues to grow. We invest in everyone\u2019s development, with a clear progression path tailored to support everyone to become industry leaders.\n\nResponsibilities:\n\nExecution strategy for multiple products, looking at previous campaign performance and market insights.\nSetup and execution of performance campaigns across SEM, Social and Display/Programmatic\nOn-going optimization to achieve client\u2019s KPI target\nEffectively manage campaign budget spend by implementing relevant bidding strategies and keeping track of budget pacing, updating the strategy, and troubleshoot accordingly\nProactively identity initiatives and opportunities for your market, aligned against local market KPIs\nLead the coordination, preparation, and execute multi-channel strategies\nProactively supply solutions to troubleshoot any account issues when budget and bid pacing, including major volume or cost shifts.\nProduce and develop reports on monthly campaign performance, audiences, creative analysis, and cross channel attribution - update client performance reports, analyse and format data, supply insights and commentary.\nLead the preparation and rationale of paid media recommendations, new tactics, and annual plan presentations for your given market/s\nProduce case studies and best practices on campaigns that best utilized data/research products, including insights from 3rd Party Sources.\nLead the communication and maintain effective relationships within team, business units and client\n\nExperience required:\n\n2+ years hands on experience in digital paid media operations and customer acquisition campaigns\nExpert with Google Marketing Platform (e.g. SA360, DV360, Campaign Manager), Facebook Ads Manager and Programmatic platforms\nOutstanding analytical, decision-making, and problem-solving skills; sharp attention to detail.\nA strong desire to learn and passion for both performance marketing and analytics\nAble to produce high quality work within a fast paced, dynamic environment\nUnderstanding of web analytic metrics\nDevelops knowledge of client\u2019s business, competition and latest industry news and trends\nDigital savvy, with specific proficiency at MS Suite: Excel, Word, PowerPoint\nExcellent verbal and written communication skills in Cantonese and English\n\nWorking Location: client office in Olympic, with occasional requirements to work from PHD office in Cyberport\n\nWe offer a 5-day work of week, group medical & life insurance coverage to the right candidate. Interested parties please send your application letter and resume with current and expected salary\u00a0by clicking the \"Apply Now\" button.\n\nAll information collected will be used for recruitment only and treated in strict confidence. We will retain the personal data of unsuccessful applicants for future recruitment purpose for a maximum period of 2 years.", "employment_types": ["Full Time", "Permanent"], "selling_points": ["Worlds 3rd largest integrated Communication Group", "Attractive salary & benefits; energetic culture", "Spacious, stylish office with an outdoor balcony"], "locations": ["Kwun Tong"], "categories": ["Media & Advertising", "Account Servicing", "Marketing / Public Relations", "Digital Marketing"], "post_time": "2022-01-11T03:02:43Z", "salary": {"currency": null, "max": null, "min": null, "period": "monthly", "term": null}, "salary_visible": false, "title_keywords": ["specialist"], "responsibilities": ["performance reports", "data", "operations", "budget", "quality", "communication", "maintain", "troubleshoot", "plan", "facebook", "collaborate", "presentations", "develop", "reports", "kpis", "setup", "cost", "executing", "analysis", "sem", "coordination", "execution strategy", "analyse"], "requirements": {"degrees": [], "majors": [], "languages": ["cantonese", "english"], "language_level": ["excellent"], "hard_skills": ["excel", "web", "problem-solving skills", "analysis", "word", "presentations", "powerpoint", "dynamic", "sem", "execution strategy", "facebook"], "soft_skills": ["communication skills", "dynamic environment", "passion for", "clear", "communication", "learning", "hands on", "troubleshoot", "coordination", "attention to detail", "problem-solving skills", "creative"], "languages_combined": [{"language": "cantonese", "language_level": ["excellent"]}, {"language": "english", "language_level": ["excellent"]}]}, "experience_required": {"duration": ["2+ years"], "field": ["digital", "media"]}}, {"job_id": "100003009043352", "location_code": "hk", "company": "Morgan McKinley", "job_title": "Digital Media Planner, APAC - Luxury Brand (MNC) - 25k", "description": "WHAT YOU WILL BE WORKING ON:\nBuild strong, long-term client relationships and maintain frequent contact;\nPerform fundamental support for pitch, proposal and projects on a local and international basis;\nFormulate and execute marketing strategy to drive e-Commerce business on online platforms;\nCoordinate with internal team to execute digital marketing campaigns including creative copywriting, media evaluation, campaign trafficking, media buy, optimizing and reporting;\nPlan and execute digital marketing campaigns including SEO/SEM, social media and display advertising to increase sales and brand awareness;\nPlan and manage advertising cost and marketing budget to obtain ROI optimization;\nMaintain social media presence for brands across multiple digital channels like Facebook, Instagram\u2026etc;\nMonitor performance daily and execute optimisation strategies;\nExplore and identify new channel expansion opportunities to reach potential customers;\nPerform analysis on the marketing results to optimize customer experience across multiple channels: offline to online and vice versa;\nYOUR SKILLSET AND BACKGROUND:\nHands-on experience in Google Ads, Facebook Manager or any other relevant tools\nComfortable with numbers.\nYou are hands-on, details oriented and organized\nYou are a team player and able to communicate effectively and build solid relationships with clients and colleagues\nYou are curious at heart and like to take ownership of something to make it better day to day basis with a demonstrated ability to build positive relationships with peers\n\u201cCan do\u201d attitude and disciplined and proactive approach to work\n\n\n\nInterested parties please email detail resume with recent portfolio, current and expected salary to\u00a0recruit(@)digitpepper.com\nPersonal data collected will be used for recruitment purpose only", "employment_types": ["Full Time", "Permanent"], "selling_points": ["2 years media planning/ digital advertising exp", "Immediately available is preferred", "Top tier Luxury brand"], "locations": ["Not Specified"], "categories": ["Media & Advertising", "Account Servicing", "Media Buying", "Marketing / Public Relations", "Digital Marketing"], "post_time": "2022-01-12T10:57:38Z", "salary": {"currency": "HKD", "max": 24999, "min": 20000, "period": "monthly", "term": null}, "salary_visible": true, "title_keywords": [], "responsibilities": ["reporting", "social media", "cost", "seo", "advertising", "digital marketing campaigns", "monitor performance", "budget", "coordinate with", "analysis", "maintain", "contact", "plan", "evaluation", "sem", "facebook"], "requirements": {"degrees": [], "majors": [], "languages": [], "language_level": [], "hard_skills": ["seo", "e-commerce", "analysis", "make", "sem", "facebook"], "soft_skills": ["organized", "proactive", "hands-on", "team player", "creative", "positive"], "languages_combined": []}, "experience_required": {"duration": [], "field": ["marketing"]}}, {"job_id": "100003009042790", "location_code": "hk", "company": "Sing Tao Management Services Limited", "job_title": "Account Executive / Senior Account Executive (Advertising Solution)", "description": "The Role Encompasses:\n\nLead the communication planning process for campaigns which includes:\n\nMaintaining good relationship and manage expectation with clients.\nDiscussion and understanding of the brief with client and agency partners.\nDevelop the communication strategy; guiding through to execution to ensure the integrity of the strategy lands in implementation.\nCampaign presentation.\nTo develop competitive/category analysis and provide actionable learnings that are relevant to the brand(s).\nTo lead planning team, to gather market intelligence on post-campaign results, consumer insights, media landscape and competitive activity.\nCascade new skill sets required to implement and drive innovation amongst planners/ executives.\n\n\u00a0We are looking for:\n\nMinimum 4 years + experienced in Media Agency\nFamiliar with Targeting Strategies in AD Network\nStrong knowledge in Programmatic / SEM / Social buying and optimisation\nExperience leading a team and natural ability to develop relationship with your team members\nCantonese and English are a must for this role\nHolding a Bachelor\u2019s Degree or above\n\nWorking Location: Cyberport (\u6578\u78bc\u6e2f), Hong Kong:\n\n\nWe offer a 5-day work of week, group medical & life insurance coverage, free shuttle bus to the right candidate. Interested parties please send your application letter and resume with current and expected salary by clicking the \"Apply Now\" button.\u00a0\u00a0\n\nAll information collected will be used for recruitment only and treated in strict confidence. We will retain the personal data of unsuccessful applicants for future recruitment purpose for a maximum period of 2 years.", "employment_types": ["Full Time", "Permanent"], "selling_points": [], "locations": ["Tseung Kwan O"], "categories": ["Media & Advertising", "Account Servicing", "Creative / Design", "Sales, CS & Business Devpt", "Others"], "post_time": "2022-01-12T08:50:43Z", "salary": {"currency": null, "max": null, "min": null, "period": "monthly", "term": null}, "salary_visible": false, "title_keywords": ["account executive", "senior account executive"], "responsibilities": ["consumer insights", "maintaining", "analysis", "planning process", "implementation", "develop", "communication", "good relationship", "sem", "planning"], "requirements": {"degrees": ["degree or above", "bachelor"], "majors": [], "languages": ["cantonese", "english"], "language_level": [], "hard_skills": ["analysis", "sem"], "soft_skills": ["communication", "integrity", "presentation"], "languages_combined": [{"language": "cantonese", "language_level": []}, {"language": "english", "language_level": []}]}, "experience_required": {"duration": [], "field": ["team"]}}, {"job_id": "100003009039645", "location_code": "hk", "company": "Carat Media Services Hong Kong Limited", "job_title": "Associate Media Manager/ Media Manager", "description": "Responsibilities:\n- Lead social campaign strategy and planning, from idea to execution\n- Ensure optimal media performance through KPI development and assessment\n- Measure, optimize and reporting on paid campaigns to achieve traffic and sales boost and increase ROI\n- Create, edit and promote social media content in various formats, eg. feeds, videos, photos, etc\u00a0\n- Assist operation of all social media platforms including Facebook, Instagram, WeChat, Weibo, YouTube, etc\n- Keep track of all trending topics and create instant content with creatives across different platforms\n- Stay alert to ad-hoc happenings during off-office hours and react with quick response\n- Take action to all changes in trends and drive engagement to online platforms\n\nRequirements:\n- Degree holder preferably in Journalism, Communication or related, experience in online environment would be a distinct advantage\n- At least 2 years relevant experience in related field is preferred\n- Social media savvy who can act quick with ad-hoc happenings\n- Creative and has a good sense in beauty, fashion, entertainment and lifestyle trends\n- Proficient in photo and video editing software (Photoshop, Premiere Pro, Final Cut Pro) is highly preferred\n- Excellent written communication skills in Chinese, good experience in Chinese and English copywriting is a plus\u00a0\n- Candidates who have experience in ecommerce is an advantage\n- Highly responsive and self-motivated, capable to work under pressure and tight deadlines\n- A team player with excellent interpersonal skills and communications skills\n\nInterested parties please send full C.V. and expected salary to Ms\u00a0Lo via email", "employment_types": ["Full Time", "Permanent"], "selling_points": ["media planning", "integrated marketing", "marketing strategy"], "locations": ["Quarry Bay"], "categories": ["Media & Advertising", "Account Servicing", "Strategic Planning", "Others"], "post_time": "2022-01-11T10:19:43Z", "salary": {"currency": null, "max": null, "min": null, "period": "monthly", "term": null}, "salary_visible": false, "title_keywords": ["associate", "manager"], "responsibilities": ["ad-hoc", "reporting", "social media platforms", "social media content", "facebook", "planning"], "requirements": {"degrees": ["degree holder"], "majors": ["journalism"], "languages": ["english", "chinese"], "language_level": ["excellent", "good"], "hard_skills": ["final cut pro", "plus", "video editing", "premiere pro", "photoshop"], "soft_skills": ["communication skills", "self-motivated", "capable", "communication", "interpersonal skills", "team player", "creative", "responsive", "work under pressure"], "languages_combined": [{"language": "english", "language_level": ["excellent", "good"]}, {"language": "chinese", "language_level": ["excellent", "good"]}]}, "experience_required": {"duration": ["at least 2 years"], "field": ["related", "copywriting", "relevant experience", "ecommerce"]}}, {"job_id": "100003009025318", "location_code": "hk", "company": "Money Plaza Hong Kong Limited", "job_title": "Marketing Executive/ Account Executive", "description": "Job Description:\n\nPrepare proposals for marketing campaigns.\nPlan, execute and coordinate campaigns.\nHandle clients\u2019 enquiries.\nHandle day to day liaison matters with clients and stakeholders.\n\nRequirements:\n\nUniversity graduated in Communications/ Marketing or related field.\nMin. 2 years of working experience in marketing, advertising agency or related field.\nExperience in event management is a plus.\nBe proactive, curious, passionate, and attention to details.\nHave strong problem solving, excellent organizational and presentation skill.\nMulti-tasking, can work independently with tight timeline.\nProficient in both English and Chinese.\nCandidate with less experience will be considered as Account Executive.\n\nWe offer attractive 5-day remuneration package to the right candidate.\u00a0 Please send us your detailed resume with current salary, expected salary and date of availability by email.\n\n\u00a0\n", "employment_types": ["Full Time", "Permanent", "Contract"], "selling_points": ["Great Exposure in Fintech and digital marketing", "Dynamic and Friendly Work Environment", "5 work days and preformance bonus"], "locations": ["Tsuen Wan Area"], "categories": ["Media & Advertising", "Account Servicing", "Marketing / Public Relations", "Digital Marketing", "E-commerce", "Marketing - Brand / Product Management"], "post_time": "2022-01-10T02:51:15Z", "salary": {"currency": null, "max": null, "min": null, "period": "monthly", "term": null}, "salary_visible": false, "title_keywords": ["account executive", "marketing executive"], "responsibilities": ["coordinate", "marketing campaigns", "plan"], "requirements": {"degrees": [], "majors": [], "languages": ["english", "chinese"], "language_level": ["proficient"], "hard_skills": ["problem solving", "plus", "presentation skill"], "soft_skills": ["passionate", "presentation skill", "work independently", "organizational", "problem solving", "multi-tasking", "attention to details", "proactive"], "languages_combined": [{"language": "english", "language_level": ["proficient"]}, {"language": "chinese", "language_level": ["proficient"]}]}, "experience_required": {"duration": ["2 years"], "field": ["related", "management", "marketing", "advertising agency"]}}, {"job_id": "100003009037224", "location_code": "hk", "company": "RFI Asia Limited", "job_title": "Group Account Director, Integrated Marketing", "description": "Planning\n\n\n\nAssist the Manager to develop media strategy, channel/ platform recommendations and prepare the detailed media flow-plan;\nLeverage available planning tools and liaise with media owners for proposals;\nEngage clients on day to day operations, media trend updates and various campaign reports on local/regional/global levels.\n\nBuying\n\n\n\nNegotiate with media owners for better rates and value adds;\nBook ads - both managed service and self-service across various platforms;\nLiaise with media vendors & creative agencies for material submission;\nDigital ad ops (campaign set up on self-serve platforms, tagging of ads and client's site, ensure ads are properly served and tags are firing);\nGlobal ops (adhering and following globally set parameters and campaign execution processes while also guiding others);\nOversee all performance across channels (Search, Social, Programmatic etc.);\nMonitor and optimize performance during campaign period across platforms such as Google Adwords, Facebook, LinkedIn etc.\nWeekly digital reporting, end of campaign reporting and reconciliation of final costs for finance billings.\n\nQualifications\n\n\n1 - 3 years' of digital media experience\nMeticulous, good with numbers and able to organise and prioritise tasks and work under tight timelines\nResilient to change and willing to keen to learn new skills\nStrong communication skills, both written and verbal, with internal and external parties\nReady to take up initiatives and ownership of projects\nPlay well with others and are a team player\nGood command of English and Chinese", "employment_types": ["Full Time", "Permanent", "Contract"], "selling_points": ["Bold marketing team seeks new portfolio lead", "Digital marketing retainers + IMC campaigns", "Key business driver + strategy and team leader"], "locations": ["Southern Area"], "categories": ["Media & Advertising", "Account Servicing", "Strategic Planning", "Marketing / Public Relations", "Digital Marketing"], "post_time": "2022-01-11T02:07:23Z", "salary": {"currency": null, "max": null, "min": null, "period": "monthly", "term": null}, "salary_visible": false, "title_keywords": ["account director"], "responsibilities": ["reporting", "day to day operations", "billings", "internal and external parties", "monitor", "develop", "communication", "reports", "plan", "liaise with", "facebook", "costs", "planning"], "requirements": {"degrees": [], "majors": [], "languages": ["english", "chinese"], "language_level": ["good command"], "hard_skills": ["adwords", "facebook"], "soft_skills": ["meticulous", "communication skills", "keen", "prioritise", "team player", "creative", "detailed"], "languages_combined": [{"language": "english", "language_level": ["good command"]}, {"language": "chinese", "language_level": ["good command"]}]}, "experience_required": {"duration": ["1 - 3 years"], "field": ["digital media"]}}, {"job_id": "100003009042903", "location_code": "hk", "company": "MRRM Publishing Ltd", "job_title": "Assistant Sales Manager / Senior Sales Executive", "description": "Wepro180 is a technology focused digital vertical media platform formed by a group of IT experts and digital media talents.\nWepro180 differs from conventional technology publishers as it transforms professional knowledge and information into easily comprehensible entertaining bit-size infotainment.\nAggregating a large number of audience who share similar interest, advertising on wepro180 is highly accurate and effective.\n\nhttps://wepro180.com/\n\nA member of Edvance International Holdings Limited (Stock code: 1410.HK)\u00a0\n\n\nResponsibilities:\n\nCreating, managing and converting new business opportunities and relationships;\nResponsible for client pitching, quotation, resource planning, time and cost control;\nStudy and document client\u2019s requirements and provide suggestions / solutions based on client\u2019s requirements;\nKnowledge on SEO and SEM would be an advantage;\nParticipating in pitch presentations;\nReport business progress to internal management team regularly\n\nDesired Skills & Experience:\n\n3 years or above relevant experience in Digital Marketing ; or Equivalent;\nDegree in Communication / Information System / Interactive Media / Computer Science / Marketing is preferred;\nExtensive experience in web and mobile production is preferable;\nHave strong presentation skills;\nGood team player who is at ease in a multi-cultural environment;\nGood command in both written and spoken English and Cantonese;\nLess experience would be considered as Sales Executive;\nWorking experience in Digital Agency is preferred.\n\nOur Offer:\n\nBirthday Leave\nDiscretionary Bonus\nLife & Medical Insurance\nMarriage Leave and Paternity Leave\nStaff Award\nMonthly Mobile\u00a0bill\u00a0allowance\nEmployee Wellness Programs\nTraining and Development Programs\nMPF \u2013 Company Voluntary Contribution\nNewborn Gratuity", "employment_types": ["Full Time"], "selling_points": [], "locations": ["Wan Chai"], "categories": ["Media & Advertising", "Account Servicing", "Others", "Sales, CS & Business Devpt", "Others"], "post_time": "2022-01-12T09:11:25Z", "salary": {"currency": null, "max": null, "min": null, "period": "monthly", "term": null}, "salary_visible": false, "title_keywords": ["assistant sales manager", "senior sales executive"], "responsibilities": ["management team", "advertising", "seo", "development programs", "mpf", "business opportunities", "quotation", "presentations", "communication", "digital marketing", "cost control", "sem", "client\u2019s requirements", "insurance", "report", "planning"], "requirements": {"degrees": ["degree"], "majors": ["marketing", "computer science"], "languages": ["cantonese", "english"], "language_level": ["good command"], "hard_skills": ["ease", "seo", "web", "information system", "presentations", "mobile", "sem", "code"], "soft_skills": ["good team player", "focused", "responsible", "communication", "presentation skills", "accurate", "extensive"], "languages_combined": [{"language": "cantonese", "language_level": ["good command"]}, {"language": "english", "language_level": ["good command"]}]}, "experience_required": {"duration": ["3 years"], "field": ["agency", "digital", "relevant experience", "digital marketing"]}}, {"job_id": "100003009036653", "location_code": "hk", "company": "Vibes Limited", "job_title": "Account Executive", "description": "Responsibilities:\n\nGenerate advertising revenue by promoting multimedia services mainly on digital, print and event\nEstablish and maintain positive relationship with current and potential clients\nWork together with marketing and business services teams to develop advertising solutions for clients, also closely work together with designers for advertising production\n\nRequirements:\n\nDegree / Higher Diploma / Associate Degree holders\n1 - 2 years\u2019 experience, preferably in print and online media\nGood communication skills, presentable, sales-driven and able to work under pressure\nPC literate, with good command of English and Chinese\nWorking location: Tsang Kwan O Industrial Estate\n\n(Fresh graduates are welcome and candidate with more experience will be considered as\u00a0Senior Account Executive)\n\n\nInterested parties please\u00a0click \u201cApply Now\"\u00a0to submit your complete resume with\u00a0employment history and expected salary or by\u00a0post to\u00a0Human Resources Department, 3/F, Sing Tao News Corporation Building, 7 Chun Cheong Street, Tseung Kwan O Industrial Estate, Tseung Kwan O, New Territories, Hong Kong.\n\nWe are an equal opportunity employer and welcome applications from all qualified candidates. Information provided will be treated in strict confidence and only be used for recruitment related purpose. Applicant who is not invited for an interview within 6 weeks may consider their application not successful. All personal data of unsuccessful applicants will be destroyed within 6 months.\n\nwww.singtaonewscorp.com", "employment_types": ["Full Time", "Permanent"], "selling_points": [], "locations": ["Kowloon Bay"], "categories": ["Media & Advertising", "Account Servicing"], "post_time": "2022-01-10T11:45:21Z", "salary": {"currency": null, "max": null, "min": null, "period": "monthly", "term": null}, "salary_visible": false, "title_keywords": ["account executive"], "responsibilities": ["teams", "maintain", "advertising", "develop"], "requirements": {"degrees": ["associate degree", "diploma", "degree"], "majors": [], "languages": ["english", "chinese"], "language_level": ["good command"], "hard_skills": ["pc literate"], "soft_skills": ["work under pressure", "communication skills", "driven", "presentable"], "languages_combined": [{"language": "english", "language_level": ["good command"]}, {"language": "chinese", "language_level": ["good command"]}]}, "experience_required": {"duration": ["1 - 2 years"], "field": ["print", "media"]}}, {"job_id": "100003009038857", "location_code": "hk", "company": "Now TV", "job_title": "Corporate Account Manager", "description": "Responsibilities\n\nServe as a media strategist across all applicable company accounts and projects\nDevelop strategic, innovative and integrated communication recommendation with full understanding on consumer consumption behaviour across different touch points to fulfil clients\u2019 business objectives\nManage and develop the media team in delivering high quality of services from providing recommendation to post campaign analysis\nSupport departmental business development with occasional new business pitches and client presentations\nPerform ad-hoc consumer, market, and/or industry research to inform strategic rationale and build an information repository for Carat\nProvide forward-thinking recommendations for the vision, practice, and growth of the Media department\nManage individual projects on an as-need basis with professionalism, organization, and high quality of service\nAbility to be self-motivated, entrepreneurial, and organized across multiple projects with various internal teams, clients and deadlines\nAbility to apply tactical knowledge into strategic recommendations for a variety of industries and business situations\nDesire to push innovation with a sound business mind and passion for ongoing education of strategic practice in the convergent media industry\n\nRequirements\n\nAt least 5 years of experience in media planning in an agency environment\nExperience in working on integrated marketing programs, with an understanding of how digital can build off of other media channels a plus\nExperience in full-cycle planning from consumer insights, to marketing strategy, to data analytics is a plus\nGood relationship built with media vendors\nProficiency in the full suite of Microsoft Office tools\nFluent, persuasive, and concise English presentation and writing skills\nPositive \u201ccan-do\u201d attitude\nCantonese and good command of English\n\nWe offer 5 days work and attractive compensation package to suitable candidates. Interested parties, please send your full resume including your date of available,\u00a0present & expected salary to us.\n\nPlease note that only short-listed applicants will be notified. All information provided will be treated in strictly confidential and used solely for recruitment purpose.", "employment_types": ["Full Time"], "selling_points": [], "locations": ["Kowloon Bay"], "categories": ["Media & Advertising", "Account Servicing", "Sales, CS & Business Devpt", "Account Servicing", "Direct Sales"], "post_time": "2022-01-11T07:56:43Z", "salary": {"currency": null, "max": null, "min": null, "period": "monthly", "term": null}, "salary_visible": false, "title_keywords": ["account manager"], "responsibilities": ["ad-hoc", "analysis", "company accounts", "quality", "teams", "presentations", "develop", "multiple projects", "integrated communication"], "requirements": {"degrees": [], "majors": [], "languages": ["cantonese", "english"], "language_level": ["good command", "fluent"], "hard_skills": ["data analytics", "plus", "writing skills", "microsoft office"], "soft_skills": ["persuasive", "writing skills", "can-do", "presentation", "positive"], "languages_combined": [{"language": "cantonese", "language_level": ["good command"]}, {"language": "english", "language_level": ["good command", "fluent"]}]}, "experience_required": {"duration": ["at least 5 years"], "field": ["agency", "marketing", "digital", "media", "planning"]}}, {"job_id": "100003009041981", "location_code": "hk", "company": "Guru Online", "job_title": "Senior Social Media Executive", "description": "Job Description:\n\n\u3002Explore and develop new business opportunities to meet sales target\n\u3002Prepare proposals, sales and presentation materials to client\n\u3002Follow up new or potential clients\u2019 inquires\n\u3002Coordinate with other teams to ensure smooth operations\n\n\nRequirements:\n\n\u3002Degree holder in Communication, Marketing, Business Administration, Journalism or related discipline are preferred\n\u3002At least 3 years media\u00a0sales experience on print, digital,or product\n\u3002Extensive network with local corporate clients or retail merchants\n\u3002Knowledge of social media trend is preferable\n\u3002Cheerful, initiative and well organized\n\u3002Excellent spoken and written English and Chinese\n\u3002Strong network in certain industry is highly preferred\n\u3002Candidates with\u00a0less experience would be considered as Senior Sales Executive\n\n\n\n\u00a0Interested candidate please provide full resume with latest and expected salary.\n\n\u00a0Personal data collected will be used for recruitment purpose only.", "employment_types": ["Full Time", "Permanent"], "selling_points": ["Work with local and regional brands", "Provide strategic social media advice", "Fun, Young working environment"], "locations": ["Kwun Tong"], "categories": ["Media & Advertising", "Account Servicing", "Marketing / Public Relations", "Marketing - Brand / Product Management", "Marketing - Marketing Communication"], "post_time": "2022-01-12T04:59:48Z", "salary": {"currency": null, "max": null, "min": null, "period": "monthly", "term": null}, "salary_visible": false, "title_keywords": ["social media executive"], "responsibilities": ["develop new business", "sales target", "coordinate with", "teams", "ensure smooth operations"], "requirements": {"degrees": ["degree holder"], "majors": ["journalism", "marketing", "business administration"], "languages": ["english", "chinese"], "language_level": ["excellent"], "hard_skills": [], "soft_skills": ["cheerful", "well organized", "communication", "extensive", "initiative"], "languages_combined": [{"language": "english", "language_level": ["excellent"]}, {"language": "chinese", "language_level": ["excellent"]}]}, "experience_required": {"duration": ["at least 3 years"], "field": ["digital", "print", "media sales"]}}, {"job_id": "100003009046218", "location_code": "hk", "company": "Sing Tao Management Services Limited", "job_title": "\u793e\u4ea4\u5a92\u9ad4\u7de8\u8f2f Social Media Specialist (New Media Business)", "description": "Job Description\n\n0-1 year of experience (fresh graduates are welcomed)\nProficient in Cantonese and English\nStrong in communication and interpretation\nGreat passion in advertising\nIndependent, proactive, energetic, organised and attention to details\nWilling to work long hours\u00a0and capable of working under tight schedule\nWe offer 5 days work and fringe benefits. Interested parties, please click \"Apply Now\" and send your CV with expected salary to us.\n\nPersonal data collected will be used for recruitment purposes only.", "employment_types": ["Full Time", "Permanent"], "selling_points": [], "locations": ["Tseung Kwan O"], "categories": ["Media & Advertising", "Account Servicing", "Editorial / Journalism", "Photography / Video"], "post_time": "2022-01-13T09:59:53Z", "salary": {"currency": null, "max": null, "min": null, "period": "monthly", "term": null}, "salary_visible": false, "title_keywords": ["social media specialist"], "responsibilities": ["communication", "advertising", "schedule"], "requirements": {"degrees": [], "majors": [], "languages": ["cantonese", "english"], "language_level": ["proficient"], "hard_skills": [], "soft_skills": ["proactive", "independent", "capable", "passion in", "communication", "attention to details", "organised", "energetic"], "languages_combined": [{"language": "cantonese", "language_level": ["proficient"]}, {"language": "english", "language_level": ["proficient"]}]}, "experience_required": {"duration": ["0-1 year"], "field": []}}, {"job_id": "100003009034054", "location_code": "hk", "company": "EY Mtel Solutions Limited", "job_title": "Project Executive / Project Manager", "description": "To cope with business needs, we are looking for high caliber candidates to provide integrated advertising solutions to help our clients to enhance promotion effectiveness, with strong focus in expanding the NowTV advertising market.\u00a0\u00a0\u00a0\n\nThe Job\n\nSell integrated advertising solutions to new customers to achieve sales goals\nMedia planning,\u00a0proposal\u00a0development,\u00a0event management,\u00a0production follow-up, and provision of professional\u00a0account\u00a0services\nBuild, grow and maintain long term relationships with targeted clients and business partners\u00a0\n\nThe Person\n\nMin 2 years working experience in media / advertising sales, TVC experience a definite advantage\nProven Sales Track Record is a must\nAggressive, result-oriented, able to work under pressure\nPresentable, strong in communication and negotiation skills\nGood command of both written and spoken English and Chinese/Mandarin", "employment_types": ["Full Time", "Permanent"], "selling_points": ["Experience in mobile/digital agency", "Presentable and posses good communication skills", "1-2 years relevant working experience"], "locations": ["Kwun Tong"], "categories": ["Media & Advertising", "Account Servicing", "Information Technology (IT)", "IT Project Management / Team Lead", "Technical / Functional Consulting"], "post_time": "2022-01-10T02:30:50Z", "salary": {"currency": null, "max": null, "min": null, "period": "monthly", "term": null}, "salary_visible": false, "title_keywords": ["project manager", "project executive"], "responsibilities": ["management", "maintain", "advertising", "planning"], "requirements": {"degrees": [], "majors": [], "languages": ["english", "chinese", "mandarin"], "language_level": ["good command"], "hard_skills": [], "soft_skills": ["presentable", "communication", "negotiation skills", "result-oriented", "work under pressure"], "languages_combined": [{"language": "english", "language_level": ["good command"]}, {"language": "chinese", "language_level": ["good command"]}, {"language": "mandarin", "language_level": ["good command"]}]}, "experience_required": {"duration": ["min 2 years"], "field": ["advertising sales", "media"]}}, {"job_id": "100003009034314", "location_code": "hk", "company": "EternityX Marketing Technology Limited", "job_title": "Digital Marketing- Senior/ Account Executive", "description": "What You Will Be Doing:\n\n\nWork closely with internal teams to deliver outstanding account servicing;\nWork with local and regional brands to continuously achieve social media success;\nHandle multiple projects simultaneously and manage various accounts in a \u00a0timely and professional manner;\nProvide strategic social media advice and guidance to ensure clients\u2019 objectives are met and exceed clients\u2019 expectations;\nTake pride in representing your clients via managing their social networks in Facebook etc.\n\n\u00a0What You Need for this Position:\n\n\nDegree holder or above with major in Communications, Marketing, Journalism, PR, Arts or related disciplines;\n1-2 solid experience in account servicing, with social media marketing experience is a plus;\nGood command of Chinese and English;\u00a0\nA natural presenter with excellent communication and analytical skills;\nA passionate believer in social media;\nAble to work under pressure and tight deadlines;\nFresh graduates are welcome.\n\n\u00a0Benefits We Offer:\n\n\u00a05 days\u2019\u00a0work\nQuarterly Performance Bonus\nMedical Coverage including Dental\nFlexible Working Hours\nOvertime\u00a0Meal\u00a0and Transportation allowance\nBirthday, Wedding, Graduation and other special leaves\nFun, young and joyful environment\u00a0\n\n\u00a0Be a GURU, be our next great hire.\u00a0APPLY NOW!\n\n*All information will be treated as confidential and used solely for recruitment purposes.", "employment_types": ["Full Time", "Permanent"], "selling_points": ["Uncapped Quarterly Commission + Performance Bonus", "Opportunity To Work In A Multi-Cultural Team", "Professional Training in China & Global Digi. Mkt"], "locations": ["Sheung Wan"], "categories": ["Media & Advertising", "Account Servicing", "Marketing / Public Relations", "Marketing - General / Support", "Digital Marketing"], "post_time": "2022-01-10T03:09:03Z", "salary": {"currency": null, "max": null, "min": null, "period": "monthly", "term": null}, "salary_visible": false, "title_keywords": ["account executive", "digital marketing"], "responsibilities": ["guidance", "social media", "teams", "professional manner", "communication", "multiple projects", "facebook", "work under pressure"], "requirements": {"degrees": ["degree holder"], "majors": ["journalism", "related disciplines", "marketing", "communications"], "languages": ["english", "chinese"], "language_level": ["good command"], "hard_skills": ["facebook", "plus", "analytical skills"], "soft_skills": ["passionate", "presenter", "timely", "analytical skills", "communication", "work under pressure"], "languages_combined": [{"language": "english", "language_level": ["good command"]}, {"language": "chinese", "language_level": ["good command"]}]}, "experience_required": {"duration": [], "field": ["social media", "marketing", "account servicing"]}}, {"job_id": "100003009043249", "location_code": "hk", "company": "AXA Hong Kong", "job_title": "Officer / Assistant Officer, Brand and Advertising (Marketing)", "description": "\u8077\u8cac\uff1a\n\n\u8ca0\u8cac\u516c\u53f8\u65d7\u4e0b\u793e\u4ea4\u5a92\u9ad4\u904b\u4f5c\uff08Facebook\u3001Instagram\u3001YouTube\uff09\uff1b\n\n\u64b0\u5beb\u6587\u5b57\u53ca\u8a2d\u8a08\u5716\u7247\uff0c\u88fd\u4f5c\u5e16\u5b50\u64f4\u95ca\u8b80\u8005\u7fa4\uff1b\n\u7dca\u8cbc\u793e\u6703\u6642\u4e8b\u71b1\u8a71\u3001\u7db2\u7d61\u65b0\u805e\u3001\u6f6e\u6d41\u8cc7\u8a0a\uff0c\u8a02\u7acb\u5167\u5bb9\u65b9\u5411\u53ca\u8207\u8b80\u8005\u4e92\u52d5\uff1b\n\u6587\u5b57\u7de8\u8f2f\u5de5\u4f5c\uff1b\n\u65e5\u591c\u66f4\u81f3\u665a\u4e0a12\u6642\uff0c\u9808\u8f2a\u73ed\u5de5\u4f5c\uff08\u500b\u5225\u5468\u516d\u65e5\u6216\u5047\u671f\u9808\u4e0a\u73ed\uff0c\u7de8\u66f4\u5236\uff09\u3002\n\n\u8981\u6c42\uff1a\n\n\u719f\u6089\u7db2\u7d61\u8da8\u52e2\uff1b\n\u4e3b\u52d5\u3001\u6562\u65bc\u5275\u65b0\uff1b\u7406\u89e3\u529b\u5f37\u3001\u80fd\u878d\u6703\u8cab\u901a\uff1b\n\u826f\u597d\u4e2d\u6587\u66f8\u5beb\u53ca\u6e9d\u901a\u80fd\u529b\uff1b\n\u5177\u5718\u968a\u7cbe\u795e\uff0c\u80fd\u8207\u4e0d\u540c\u7684\u4f19\u4f34\u5408\u4f5c\uff1b\u5177\u5927\u5c08\u6216\u4ee5\u4e0a\u5b78\u6b77\uff0c\u76f8\u95dc\u5b78\u79d1\u6216\u5de5\u4f5c\u7d93\u9a57\u8005\u512a\u5148\uff1b\u5177\u57fa\u672c\u5716\u50cf\u8655\u7406\u6280\u80fd\uff0c\u5982Photoshop\u3001Illustrator\u3001Adobe Premiere\u512a\u5148\u3002\n\u5de5\u4f5c\u5730\u9ede\uff1a\u5c07\u8ecd\u6fb3\u5de5\u696d\u90a8\n\n\u6c42\u8077\u8005\u8acb\u8a73\u9644\u500b\u4eba\u5c65\u6b77\u53ca\u8981\u6c42\u5f85\u9047\uff0c\u5bc4\u9999\u6e2f\u65b0\u754c\u5c07\u8ecd\u6fb3\u5de5\u696d\u90a8\u99ff\u660c\u8857\u4e03\u865f\u661f\u5cf6\u65b0\u805e\u96c6\u5718\u5927\u5ec83\u6a13\u4eba\u529b\u8cc7\u6e90\u90e8\u6536\uff0c\u4fe1\u5c01\u9762\u8acb\u8a3b\u660e\u7533\u8acb\u8077\u4f4d\u6216\u6309\u201cApply Now\u201d\u63d0\u4ea4\u7533\u8acb\u3002\n\n\u672c\u516c\u53f8\u70ba\u516c\u5e73\u6a5f\u6703\u50f1\u4e3b\uff0c\u6b61\u8fce\u6240\u6709\u5408\u8cc7\u683c\u7684\u5019\u9078\u4eba\u7533\u8acb\u3002\u6240\u63d0\u4f9b\u7684\u4fe1\u606f\u5c07\u56b4\u683c\u4fdd\u5bc6\uff0c\u50c5\u7528\u65bc\u62db\u8058\u76f8\u95dc\u7528\u9014\u3002\u82e5\u672a\u80fd\u65bc 6 \u9031\u5167\u7372\u9080\u51fa\u5e2d\u9762\u8a66\u7684\u7533\u8acb\u8005\u6703\u81ea\u52d5\u843d\u9078\uff0c\u53e6\u6240\u6709\u843d\u9078\u7684\u7533\u8acb\u8005\u7684\u6240\u6709\u500b\u4eba\u8cc7\u6599\u5c07\u57286\u500b\u6708\u5167\u92b7\u6bc0\u3002\n\nwww.singtaonewscorp.com", "employment_types": ["Full Time", "Permanent"], "selling_points": ["entry level for Corporate Marketing role", "exposure to all advertising & branding activities", "Good working environment & culture"], "locations": ["Southern Area"], "categories": ["Media & Advertising", "Account Servicing", "Marketing / Public Relations", "Marketing - General / Support", "Others"], "post_time": "2022-01-12T10:21:29Z", "salary": {"currency": null, "max": null, "min": null, "period": "monthly", "term": null}, "salary_visible": false, "title_keywords": ["assistant officer", "officer"], "responsibilities": [], "requirements": {"degrees": [], "majors": [], "languages": [], "language_level": [], "hard_skills": [], "soft_skills": [], "languages_combined": []}, "experience_required": {"duration": [], "field": []}}, {"job_id": "100003009028534", "location_code": "hk", "company": "Art Map Limited", "job_title": "Social Media Executive/ Account Servicing Executive (Digital Marketing)", "description": "Job Responsibilities:\n\nThis Officer / Assistant Officer will support Senior Manager and the team in launching advertising campaigns:\n\nAssist in developing and implementing effective integrated advertising campaigns\n\nWork closely with advertising and media agencies to ensure successful execution of marketing strategies\n\nLiaise with internal parties for materials approval\n\nAssist the team on the launch communication\n\nStay alert on competitive activities and keep the team updated\n\nAct as a brand custodian to ensure the communications are in line and consistent across the entire company\n\nPerform daily administrative works and assist in maintaining and process invoices\n\nJob Requirements:\n\nUniversity graduate, in Marketing, Public Relations, Communications, Business Admin or related disciplines\n\n1-2 years' experience in marketing/ advertising/ branding preferred. Fresh graduates are also welcomed.\n\nProficiency in MS Office (Excel, Word and especially Powerpoint), basic Adobe Illustration and Photoshop skills will be a bonus\n\nStrong presentation, analytical, communication and interpersonal skills, with attention to details and high sensitivity\n\nSelf-motivated, good team player with entrepreneurial spirit\n\nStrong writing skills in both English and Chinese\n\nExcellent command spoken English and Chinese\n\n(Candidates with less experience will be considered as Assistant Officer)\n", "employment_types": ["Full Time", "Permanent"], "selling_points": ["Assist Social Media platforms", "Provide daily support to the gallery operation", "At least 1 year of marketing and practical exp."], "locations": ["Not Specified"], "categories": ["Media & Advertising", "Account Servicing", "Editorial / Journalism", "Marketing / Public Relations", "Digital Marketing"], "post_time": "2022-01-10T06:34:03Z", "salary": {"currency": null, "max": null, "min": null, "period": "monthly", "term": null}, "salary_visible": false, "title_keywords": ["executive", "digital marketing", "social media executive"], "responsibilities": ["advertising", "marketing strategies", "maintaining", "invoices", "developing", "communication", "liaise with", "advertising campaigns", "internal parties"], "requirements": {"degrees": ["university graduate"], "majors": ["business", "related disciplines", "marketing", "communications"], "languages": ["english", "chinese"], "language_level": ["excellent"], "hard_skills": ["excel", "basic", "word", "powerpoint", "writing skills", "adobe", "photoshop", "illustration", "ms office"], "soft_skills": ["self-motivated", "good team player", "sensitivity", "writing skills", "communication and interpersonal skills", "attention to details", "presentation"], "languages_combined": [{"language": "english", "language_level": ["excellent"]}, {"language": "chinese", "language_level": ["excellent"]}]}, "experience_required": {"duration": ["1-2 years"], "field": ["marketing", "advertising"]}}, {"job_id": "100003009036523", "location_code": "hk", "company": "Nesta (Hong Kong) Limited", "job_title": "Account Manager / Senior Account Manager (Digital Media Sales ) 35-50K", "description": "Social Media Executive/ Account Servicing Executive (Digital Marketing)\n\u2022\u00a0\u00a0 \u00a0Social Media\n\u2022\u00a0\u00a0 \u00a0Marketing Executive\n\u2022\u00a0\u00a0 \u00a0Project Management\n\nThis candidate will have various exposure and connection to different\u00a0brands connection, especially Art & Gallery industry. The candidate will support many meaningful projects.\u00a0\n\nJob duty:\nAssist Social Media platforms, including but not limit to Facebook, Instagram content creation\u00a0n\n\u00a0Assist online video production and related online marketing campaigny\nAccount servicing - communication between clients & vendors\n\n\u00a0Generating reports on campaign effectiveness in social media sites and collect marketing intelligence\n\nProvide daily support to the gallery operation and administration works\nAsist with exhibition openings and different art events(e.g., Art fair)\nManage social media platform and event promotion\nProvide technical support and coordinate with the preparation of exhibition, e.g. artworks display, installation, storage, and dismantlement\nManage and organize the inventory\n\n\nRequirements:\nDegree holder of a recognized qualification in Journalism, Advertising, Marketing digital, Fine Art, Cultural Studies and/or a related discipline\nPassionate in marketing &/ digital,\u00a0publishing and art/cultural industry\nKnowledge of Photoshop, Adobe,\u00a0Excel, and Google documents strongly preferred\nGood at both written and spoken English and Chinese\nAbility of problem solving and multi-tasking is requested\nStrong administration ability, well-organized and able to work independently\nFamiliar with website development and maintenance as well as online platform\u00a0\u00a0\nStrong interest in Contemporary Art\nAt least 1 year of marketing and practical experience in social media platforms/ online marketing \u00a0\u00a0\u00a0\u00a0\u00a0\u00a0\u00a0\u00a0\u00a0\u00a0\u00a0\u00a0\u00a0\u00a0\u00a0\u00a0\u00a0\u00a0\u00a0\u00a0\u00a0\u00a0\u00a0\u00a0\u00a0\u00a0\u00a0\u00a0\u00a0\u00a0\u00a0\u00a0\u00a0\u00a0\u00a0\u00a0\u00a0\u00a0\u00a0\u00a0\u00a0\u00a0\u00a0\u00a0\u00a0\u00a0\u00a0\u00a0\u00a0\u00a0\u00a0\u00a0\u00a0\n\u00a0Preference will be given to a team player with passion for arts and the ability to work effectively and individually. The appointee will report to the Business Development Executive.\u00a0\nInterested parties please apply in strict confidence with complete resume,\u00a0compensation history (printed copy),\u00a0expected salary\u00a0to our email by clicking \"Apply Now\"\u00a0 or by post to Human Resources Department, Art Map Limited, Room 602, 6/F, Winfull Commercial Building, 172-176 Wing Lok Street, Sheung Wan, Hong Kong.\u00a0\nWe are an equal opportunity employer and welcome applications from all qualified candidates. Information provided will be treated in strict confidence and only be used for recruitment related purpose. Applicant who is not invited for an interview within 6 weeks may consider their application not successful. All personal data of unsuccessful applicants will be destroyed within 6 months.", "employment_types": ["Full Time", "Permanent"], "selling_points": ["Finance, Beauty & Fashion, Lifestyle", "Advertising Agency or Media Experience Wanted!", "Uncapped Commission + Attractive Basic Salary"], "locations": ["Not Specified"], "categories": ["Media & Advertising", "Account Servicing", "Print Media", "Sales, CS & Business Devpt", "Sales - Sales Management"], "post_time": "2022-01-10T10:51:10Z", "salary": {"currency": "HKD", "max": 54999, "min": 35000, "period": "monthly", "term": null}, "salary_visible": true, "title_keywords": ["senior account manager", "account manager", "sales"], "responsibilities": ["social media", "installation", "advertising", "maintenance", "video production", "technical support", "inventory", "social media platforms", "coordinate with", "website", "communication", "project management", "digital marketing", "reports", "facebook", "report", "administration"], "requirements": {"degrees": ["degree holder"], "majors": ["journalism", "marketing", "fine art"], "languages": ["english", "chinese"], "language_level": ["good"], "hard_skills": ["excel", "maintenance", "problem solving", "project management", "adobe", "facebook", "photoshop"], "soft_skills": ["passionate", "work effectively", "work independently", "passion for", "well-organized", "communication", "project management", "multi-tasking", "problem solving", "team player"], "languages_combined": [{"language": "english", "language_level": ["good"]}, {"language": "chinese", "language_level": ["good"]}]}, "experience_required": {"duration": ["at least 1 year"], "field": ["social media", "marketing"]}}, {"job_id": "100003009033948", "location_code": "hk", "company": "GroupM Limited", "job_title": "GroupM | Planning Supervisor", "description": "Our client is a fast growing company specializing in digital media industry. They are now seeking for a high caliber to join their team as Account Manager or Senior\u00a0Account Manager.\n\nResponsibilities\u00a0\n\nSell digital advertising and marketing services to clients\nIdentify and implement sales opportunities with targeted potential clients\nParticipate in tailor made strategic planning for different advertising or marketing solutions on company platform\n\nRequirements\n\nMinimum 2 years existing account management or new business sales experiences gained in Digital Media /Publisher\nAggressive and determined to meet sales & other business targets\nExperience in handling clients from F&B, Beauty & Fashion, Traveling and Lifestyle is preferred\nCandidates with less experience may be considered as Account Manager\nHigh Basic Salary + Uncapped Commission", "employment_types": ["Full Time", "Permanent"], "selling_points": [], "locations": ["Quarry Bay"], "categories": ["Media & Advertising", "Account Servicing", "Media Buying", "Strategic Planning"], "post_time": "2022-01-10T02:14:42Z", "salary": {"currency": null, "max": null, "min": null, "period": "monthly", "term": null}, "salary_visible": false, "title_keywords": ["supervisor"], "responsibilities": ["advertising", "strategic planning"], "requirements": {"degrees": [], "majors": [], "languages": [], "language_level": [], "hard_skills": ["publisher", "basic"], "soft_skills": ["determined"], "languages_combined": []}, "experience_required": {"duration": ["minimum 2 years"], "field": ["f&b", "digital media", "business", "beauty", "account management"]}}, {"job_id": "100003009042571", "location_code": "hk", "company": "Blue Chip Group Limited", "job_title": "Sales Manager for Fast Growing Media Agency", "description": "Job Description and Responsibilities\n- Research and assess local and global market for potential partnership opportunities\n- Plan, pitch and present\u00a0media revenue opportunities\n-\u00a0Explore new media channel opportunities\u00a0\n- Develop new business\n- Identify client business needs and proactively develop advertising solutions to meet objectives\n- Meet challenging objectives in a high profile, competitive marketplace\n- Other projects as assigned by the MD\n- Travelling often to meet with vendors across the regions\n\nRequirements\n- 1-5 years of experience in a media agency/media owner\u00a0role will be highly preferred\n- Undergraduate degree in related field or a combination of related education and work experience\n- Highly self-motivated, resourceful, enthusiastic, start-up personality\n- Creative thinker and problem solver\n- Ability to handle multiple priorities and simultaneous projects\n- Excellent presentation and communication skills\n- Fluent in English and Chinese\n- Speaking Korean would be a great asset", "employment_types": ["Full Time", "Part Time", "Permanent", "Temporary", "Internship"], "selling_points": [], "locations": ["Tsim Sha Tsui"], "categories": ["Media & Advertising", "Account Servicing", "Others", "Sales, CS & Business Devpt", "Business Development"], "post_time": "2022-01-12T08:02:43Z", "salary": {"currency": null, "max": null, "min": null, "period": "monthly", "term": null}, "salary_visible": false, "title_keywords": ["sales manager"], "responsibilities": ["develop new business", "advertising", "plan", "develop"], "requirements": {"degrees": ["degree"], "majors": [], "languages": ["english", "chinese", "korean"], "language_level": ["fluent"], "hard_skills": [], "soft_skills": ["communication skills", "self-motivated", "problem solver", "resourceful", "enthusiastic", "creative", "presentation"], "languages_combined": [{"language": "english", "language_level": ["fluent"]}, {"language": "chinese", "language_level": ["fluent"]}, {"language": "korean", "language_level": []}]}, "experience_required": {"duration": ["1-5 years"], "field": ["agency", "media", "related", "education"]}}, {"job_id": "100003009046433", "location_code": "hk", "company": "Medialink Entertainment Limited", "job_title": "Licensing Manager", "description": "Job Introduction\nAs a Licensing Manager, you will be responsible for identifying product opportunities, selling licenses to suitable partners and maintaining commercial relationships within allocated categories.\u00a0\n\nRole Responsibilities\n\nSupervise Licensing for Anime in Hong Kong and SEA\nSelling licenses to suitable partners\nFormulate strategic licensing strategies to maximize business opportunities\nManage existing key licensees & develop new licensees to achieve sales targets\nSupport team to achieve sales targets e.g. Brand presentation, Creative, Deal Memo, Sales Plan, Contract Review, AR, Launch & Marketing plan, Royalty report, Approval\nCoordination among oversea offices to support development business in oversea territories\nIdentify, pitch and secure new licensees that enhance the category growth in a substantial manner\u00a0\nHandle ad-hoc projects\n\nRequirements\n\nEnthusiasmand knowledge in Japanese Anime is an advantage\nBachelor degree, relevant business administration, commercial marketing, or similar consumer targeting experience\nMinimum 5 years experience in sales and marketing or related field\nSubstantial experience within Anime industry management\nProactive, well-organized, and attentive to details\nStrong negotiation, communications and interpersonal skills\nExcellent command in English and Chinese (including Mandarin)\nGood command in Japanese is preferred\nLess experience will be considered as an Executive\n\nWe offer 5-days work week, medical scheme, discretionary bonus, performance bonus and good career prospect to the right candidates. Interested parties, please send full resume with present & expected salaries & date availability to HR Department by \u201cApply Now\u201d\u00a0", "employment_types": ["Full Time"], "selling_points": ["Characters Licensing", "Experience in sales and marketing and retail", "Enthusiasm and knowledge in Japanese Anime"], "locations": ["Tsim Sha Tsui"], "categories": ["Media & Advertising", "Account Servicing", "Sales, CS & Business Devpt", "Account Servicing"], "post_time": "2022-01-13T11:07:34Z", "salary": {"currency": null, "max": null, "min": null, "period": "monthly", "term": null}, "salary_visible": false, "title_keywords": ["manager"], "responsibilities": ["ar", "memo", "business opportunities", "review", "develop", "marketing plan", "plan", "coordination", "ad-hoc projects", "report"], "requirements": {"degrees": ["degree", "bachelor"], "majors": ["marketing", "business administration"], "languages": ["japanese", "english", "chinese", "mandarin"], "language_level": ["advantage", "excellent", "good command"], "hard_skills": [], "soft_skills": ["negotiation", "attentive to details", "well-organized", "interpersonal skills", "proactive"], "languages_combined": [{"language": "japanese", "language_level": ["advantage", "good command"]}, {"language": "english", "language_level": ["excellent"]}, {"language": "chinese", "language_level": ["excellent"]}, {"language": "mandarin", "language_level": ["excellent"]}]}, "experience_required": {"duration": ["minimum 5 years"], "field": ["management", "business administration", "related", "commercial", "marketing"]}}, {"job_id": "100003009037981", "location_code": "hk", "company": "IPG Mediabrands (HK) Limited", "job_title": "Media Executive (Buying & Operation Team)", "description": "As one of the leading marketing agencies in Hong Kong, we are looking for an Account Manager who will need to \u2013\u00a0\n\nHandle client inquiries related to video / creative projects, online / offline event\u00a0and other marketing projects/campaigns\nClosely work with internal team and external vendors to manage\u00a0various\u00a0projects.\nHave solid knowledge on managing online / offline event management and production projects.\nBe willing to work with irregular work schedules if necessary.\nHave strong organizational and time management skills, ability to meet tight deadlines and work well under pressure.\nHave experiences in managing/producing live streaming / virtual events will be an advantage\nUnderstand the needs of your customers and be able to respond effectively with a plan of how to meet the requirement\nMeet with customers/clients face to face or over the phone and present project proposal and company experience\nMaintain client relationships and introduce other services to the client whenever appropriate\n\nYou should also have the below soft skills:\n\nQualifications and skills: 2 or more years of recent advertising sales, account management and/or project experience \u2013 ideally in creative marketing production agency environment in Hong Kong.\nExceptional communication and presentation skills, and ability to translate technical and business benefits to decision makers\nStakeholder management skills and proven ability to negotiate\nExperience working to and exceeding targets\nA deep understanding of the marketing campaign and project, from creative development, project planning to execution\nSelf-motivated, detail-oriented, and comfortable working independently\nInterested parties please send full resume with expected salary to us.\u00a0\n\nFor more information,\u00a0Please visit our group website:\u00a0www.onemediagroup.asia\nOr service websites: www.studioone.com.hk, www.onemedia.hk\u00a0\n\nPersonal data will be used for recruitment purpose only.\n\njobsDB will send your application for review directly to\nOne Media Group\n\n", "employment_types": ["Full Time"], "selling_points": [], "locations": ["Quarry Bay"], "categories": ["Media & Advertising", "Account Servicing", "Media Buying", "Marketing / Public Relations", "Marketing - Marketing Communication"], "post_time": "2022-01-11T04:28:56Z", "salary": {"currency": null, "max": null, "min": null, "period": "monthly", "term": null}, "salary_visible": false, "title_keywords": ["executive"], "responsibilities": ["management", "advertising", "schedules", "marketing projects", "maintain", "plan"], "requirements": {"degrees": [], "majors": [], "languages": [], "language_level": [], "hard_skills": [], "soft_skills": ["meet tight deadlines", "under pressure", "time management skills", "organizational", "creative"], "languages_combined": []}, "experience_required": {"duration": [], "field": ["advertising sales", "agency", "marketing", "account management"]}}, {"job_id": "100003009041326", "location_code": "hk", "company": "In Express-Sisters Group Limited", "job_title": "Sales Manager / Assistant Sales Manager", "description": "Advertising Sales Department (HKCNE)\nTo be responsible for developing sales account and products for airtime advertising to achieve business target and driving for sales and profitability; performing account servicing including advertisement scheduling, tailor made advertisement campaign and coordination of TV advertisement production; procuring market information and competitors\u2019 activities; procuring market information and competitor\u2019s activities, solicit new business for the Company\u2019s outdoor media\nForm 7 or above with minimum with minimum 3 years relevant working experience in media sales is preferred\nProficient in PC applications and MS Office including Excel, Word, PowerPoint and Outlook\nGood command of both spoken and written English & Chinese\nConscious in Global News with passionate interest in TV advertising industry\nIndependent, diligent and able to work under pressure\n\nWe offer 5-day work week, competitive remuneration packages and advancement opportunities. Interested parties, please write with full resume to\u00a0Director, Human Resources,\u00a0Human Resources Department, i-CABLE Communications Limited, 4/F Cable TV Tower, 9 Hoi Shing Road Tsuen Wan, N.T. or fax to 2112 7841 or via Apply Now (Please quote reference number and position applied for). For other information, please visit our website\u00a0http://www.i-cable.com.\n\nYour application may be forwarded to any\u00a0affiliate companies\u00a0and successful applicant may be seconded to work at any office as assigned.\u00a0 The information received will be used for consideration of employment only and all personal data supplied will be destroyed within 3 months.\n\nWe are an equal opportunity employer.", "employment_types": ["Full Time"], "selling_points": ["DSE or above / Degree holder preferable", "3 years of media sales experience", "Very competitive remuneration and benefits package"], "locations": ["Not Specified"], "categories": ["Media & Advertising", "Account Servicing", "Sales, CS & Business Devpt", "Account Servicing", "Channel / Distribution"], "post_time": "2022-01-12T04:05:51Z", "salary": {"currency": null, "max": null, "min": null, "period": "monthly", "term": null}, "salary_visible": false, "title_keywords": ["assistant sales manager", "sales manager"], "responsibilities": ["market information", "advertising", "developing", "scheduling", "coordination", "work under pressure"], "requirements": {"degrees": [], "majors": [], "languages": ["english", "chinese"], "language_level": ["good command"], "hard_skills": ["excel", "word", "powerpoint", "pc applications", "outlook", "ms office"], "soft_skills": ["passionate", "independent", "responsible", "diligent", "coordination", "work under pressure"], "languages_combined": [{"language": "english", "language_level": ["good command"]}, {"language": "chinese", "language_level": ["good command"]}]}, "experience_required": {"duration": ["minimum 3 years"], "field": ["relevant working experience", "media sales"]}}, {"job_id": "100003009039808", "location_code": "hk", "company": "Social Galaxy Limited", "job_title": "Marketing Executive / Business Assistant (Event / Online Ad)", "description": "Account servicing, follow up ad production and assist business director on work\nWork experience in online marketing, social media will be preferred\nExperience in copywriting and/or creating content for social media platforms\nGood communication skills, event and PR experience will be preferred\nAble to meet tight deadlines and work\u00a0independently\u00a0under pressure\u00a0in fast paced environment\nGood command of both written and spoken English and Chinese\nResponsible for planning, executing and evaluating all online marketing strategies to enhance company visibility and awareness; manage and maintain all digital channels to optimize brand image and produce comprehensive social media campaigns\nExperience of using Facebook Ad Manager / Google Ad Manager is preferable\nImmediate available is preferable\n\nJob Requirements:\u00a0\n\nHigh Diploma or above\nAt least 1 \u2013 2 years of working experience, media experience preferably\nInterest in Advertising, especially Media field\nProficient in MS office applications including Word, Excel and Outlook\nUse of Powerpoint is a must\nAttentive to details and good communication skills\nPatience and work under pressure\u00a0\n\nInterested parties please send us your updated resume and application letter together with your expected salary. All information collected will be used for recruitment related purpose only.", "employment_types": ["Full Time"], "selling_points": [], "locations": ["Kwun Tong"], "categories": ["Media & Advertising", "Account Servicing", "Marketing / Public Relations", "Public Relations - Event Management", "Sales, CS & Business Devpt", "Tele-sales (Telemarketing)"], "post_time": "2022-01-11T11:34:26Z", "salary": {"currency": null, "max": null, "min": null, "period": "monthly", "term": null}, "salary_visible": false, "title_keywords": ["assistant", "marketing executive"], "responsibilities": ["social media", "marketing strategies", "advertising", "social media campaigns", "work under pressure", "social media platforms", "communication", "maintain", "executing", "facebook", "planning"], "requirements": {"degrees": ["high diploma or above"], "majors": [], "languages": ["english", "chinese"], "language_level": ["good command"], "hard_skills": ["excel", "word", "powerpoint", "outlook", "facebook", "ms office"], "soft_skills": ["communication skills", "meet tight deadlines", "work independently", "under pressure", "responsible", "attentive to details", "comprehensive", "patience", "work under pressure"], "languages_combined": [{"language": "english", "language_level": ["good command"]}, {"language": "chinese", "language_level": ["good command"]}]}, "experience_required": {"duration": ["2 years"], "field": ["social media", "pr", "marketing", "copywriting", "media"]}}, {"job_id": "100003009035235", "location_code": "hk", "company": "3 Screens Strategic Advisors Limited", "job_title": "Digital Account Managers", "description": "The Digital Specialist will work closely supporting the PPC business with the day-to-day management of paid search campaigns. This person will report directly to the Digital Manager and is responsible for tracking, analyzing and executing paid search strategies, ensuring that all deliverables are executed on time and produce a high standard of quality for all client deliverables. The Digital Specialist will acquire in-depth paid search knowledge, while utilizing the creativity, attention to detail and analytical skills needed to grow a career within the agency.\n\nResponsibilities\n\nHolistic SEM program management including keywords development, ad creative and strategy, trafficking recommendations, optimizing program towards key business goals and reporting\nActively participating in meetings and proactively documenting takeaways and next steps\nAssimilating data from multiple sources, compiling the information and drawing actionable conclusions that can be measured and reported\nBid strategy optimization and testing. Daily checks on program KPIs, thresholds and campaign budget caps. Ongoing management of budget and pacing.\nTranslating campaign/client goals into SEM tactics and effectively executing those tactics against the client\u2019s strategy\nImplementing Paid Search best practices, providing refinement and optimization recommendations and proactively identifying campaign execution issues\nMonitoring emerging industry trends and summarizing them for internal and external stakeholders\nLeveraging and developing proficiencies with SEM platforms, tools and resources\nDeveloping campaign ad copy (text-based titles and descriptions or feed-based images) and tagging traffic or creative elements to sites per creative rotation instructions\nHelp develop performance forecasts, budget allocations and providing data-based rationale for these recommendations\nCollaborating with both clients and internal cross-channel colleagues by providing reporting as requested in a concise and timely fashion\nFostering relationship with internal teams, external partners and clients\n\nCompetencies\n\n1 to 2 years of paid search experience, with knowledge of bid management platforms a plus\nStrong ability to work closely with your team to problem solve, prioritize tasks, and manage time effectively\nA detail-oriented approach and a desire to achieve objectives accurately\nSolid quantitative and research skills, and proven data interpretation capability\nFamiliarity with the digital advertising space and a passion for growing that interest into a career\nStrong communication skills \u2013 you\u2019re clear and thorough, yet concise\nA passion for building relationships and a desire to contribute to team building and event planning\nExudes confidence and won\u2019t hesitate to connect with\ncolleagues\nthroughout the organization to get the job done right\ncandidates with less experience will be considered as Digital Executive\n\nAll information collected will be solely used for recruitment purposes only.", "employment_types": ["Full Time", "Permanent"], "selling_points": [], "locations": ["Central"], "categories": ["Media & Advertising", "Account Servicing", "Professional Services", "Business Consultancy", "Marketing / Public Relations", "Digital Marketing"], "post_time": "2022-01-10T06:27:48Z", "salary": {"currency": "HKD", "max": 34999, "min": 20000, "period": "monthly", "term": null}, "salary_visible": true, "title_keywords": [], "responsibilities": ["business goals", "data", "budget", "quality", "communication", "advertising", "teams", "developing", "testing", "day-to-day management", "develop", "kpis", "report", "reporting", "management", "monitoring", "executing", "tracking", "recruitment", "sem", "planning"], "requirements": {"degrees": [], "majors": [], "languages": [], "language_level": [], "hard_skills": ["plus", "sem", "analytical skills"], "soft_skills": ["communication skills", "confidence", "research skills", "responsible", "passion for", "problem solve", "timely", "prioritize", "analytical skills", "detail-oriented", "clear", "thorough", "attention to detail", "creative"], "languages_combined": []}, "experience_required": {"duration": ["1 to 2 years"], "field": ["digital", "management"]}}, {"job_id": "100003009042088", "location_code": "hk", "company": "Osmium Consulting Group Limited", "job_title": "CRM Specialist", "description": "We are a digital native business consultancy looking for a Digital Account Managers with the ambition to becoming a strategic digital business consultant who can help businesses master digital communications to achieve business success.\n\nHow you can contribute\n\nEstablish courteous and productive working relationship with clients.\nPlan and manage\u00a0the implementation of digital marketing executions across channels such as display ad, social media ad/post, paid search, SEO, eCommerce website, email automation\nAble to set priorities and lead multiple projects and manage deadlines\n\n\nWho you are \u00a0\n\nA digital native\nPersonable, not afraid to speak out and think outside the box\nPassionate, curious with strong business sense\nExperience managing international accounts/clients\n4As or management consultancy experience is appreciated\nMinimum\u00a03-year\u00a0working experience in Digital Marketing or related fields\nGood\u00a0understanding\u00a0of the strategic importance and executional know-how of various digital marketing channels across Paid, Owned and Earned.\nProactive, meticulous, organised with good sense of urgency and can-do attitude\nGood with words and not afraid of numbers\nNative English/Cantonese, fluency in Mandarin is a plus\nCandidates with less experience will be considered as Digital Account Executive\n\nRewards & benefits\n\nDiscretionary bonus\nOrganised and collaborative individual is awarded with WFH privileged.\n\nImmediate availability is highly preferred.", "employment_types": ["Full Time", "Permanent"], "selling_points": ["Cryptocurrency", "Extremely Good Benefits", "Work From Home"], "locations": ["Central"], "categories": ["Media & Advertising", "Account Servicing", "Information Technology (IT)", "Others", "Marketing / Public Relations", "Digital Marketing"], "post_time": "2022-01-12T06:01:19Z", "salary": {"currency": null, "max": null, "min": null, "period": "monthly", "term": null}, "salary_visible": false, "title_keywords": ["specialist"], "responsibilities": ["social media", "management", "seo", "implementation", "website", "digital marketing", "plan", "multiple projects"], "requirements": {"degrees": ["master"], "majors": ["business", "communications"], "languages": ["cantonese", "english", "mandarin"], "language_level": ["fluency", "native"], "hard_skills": ["plus", "seo", "words"], "soft_skills": ["productive", "passionate", "courteous", "personable", "meticulous", "business sense", "urgency", "can-do attitude", "organised", "proactive"], "languages_combined": [{"language": "cantonese", "language_level": ["native"]}, {"language": "english", "language_level": ["native"]}, {"language": "mandarin", "language_level": ["fluency", "native"]}]}, "experience_required": {"duration": ["minimum 3-year"], "field": ["related", "digital", "management", "digital marketing"]}}, {"job_id": "100003009035226", "location_code": "hk", "company": "3 Screens Strategic Advisors Limited", "job_title": "Digital Account Executives", "description": "Responsibilities:\n\n\n\nPlan on marketing strategy, from idea generation to campaign execution to drive growth.\nWork closely with the creative team in delivering marketing material, provide strategic social media advice and guidance.\nSupport partners\u2019 marketing campaigns in a timely and professional manner\nMonitor marketing performance to identify new business opportunities.\u00a0\nBuild strong client relationships with partners for customer success and satisfaction\nSupport on ad hoc projects\n\n\n\n\nRequirements:\n\nPassionate in digital marketing and FinTech\nMin. of 3 years experience in digital marketing, agency background with account servicing experience will be preferred\nGood understanding in digital marketing and keep abreast of the trend\nExperience in content marketing and copywriting is highly desirable\nKnowledge on and good communication in campaign management\nAggressive, self-motivated and result oriented\nAble to multi-tasks with excellent time management skills\nFluent in Cantonese and English\nCandidate with more experience will be considered for Senior Marketing Executive\n\n\n", "employment_types": ["Full Time", "Permanent"], "selling_points": [], "locations": ["Central"], "categories": ["Media & Advertising", "Account Servicing", "Professional Services", "Business Consultancy", "Marketing / Public Relations", "Digital Marketing"], "post_time": "2022-01-10T06:27:18Z", "salary": {"currency": "HKD", "max": 19999, "min": 14000, "period": "monthly", "term": null}, "salary_visible": true, "title_keywords": [], "responsibilities": ["guidance", "social media", "business opportunities", "professional manner", "monitor", "ad hoc projects", "plan", "marketing campaigns", "marketing material"], "requirements": {"degrees": [], "majors": [], "languages": ["cantonese", "english"], "language_level": ["fluent"], "hard_skills": [], "soft_skills": ["passionate", "self-motivated", "multi-tasks", "time management skills", "communication", "result oriented"], "languages_combined": [{"language": "cantonese", "language_level": ["fluent"]}, {"language": "english", "language_level": ["fluent"]}]}, "experience_required": {"duration": ["of 3 years"], "field": ["agency", "account servicing", "marketing", "digital marketing", "copywriting"]}}, {"job_id": "100003009037377", "location_code": "hk", "company": "Sedgwick Richardson (Hong Kong) Ltd", "job_title": "Project Manager (ESG and Financial Reports)", "description": "Highlights :\nRemote Working\nCrypto\u00a0\nGreat Benefits\u00a0\n\nResponsibilities :\n\nPropose, design, and launch CRM campaigns and workflows in collaboration with Product, User Acquisition, Marketing, and Tech teams\nMap user journeys and optimize campaigns for funnel conversion\nDrive platform retention, loyalty, engagement, and usage metrics for the Crypto.com products and services (e.g. DAU/MAU, purchases )\nSupport analysis and enhancement of CRM campaigns\nExecute A/B tests and own analysis of results to ensure maximum impact and effectiveness\nDevise ways to improve usage of the CRM platform by automatic basic, everyday tasks\nPulling reports from the CRM platform into data visualization tools\nMeeting with other stakeholders and teams to analyse industry trends and tailor CRM campaigns to meet business objectives\nAssess and plan data points to integrate with CRM platform\n\nRequirements :\nBA/BS degree in Business Administration, Mathematics, Statistics, Information System, Computer Science, Business Analytics, Data Science or relevant field\nMinimum of 3 years experience in e-commerce business\nExpertise and proven experience in CRM software ( e.g. Braze, Hubspot, Salesforce, Marketo )\nAbility to integrate CRM platform with internal data visualization platforms and customer data platforms ( CDPs )\nStrong experience with Google Analytics and Google Tag Manager, including analytics, tag implementation, conversion tracking\nExcellent skills in MS Office suite of programs\nExcellent command of English, both written and verbally\nProficiency in building email templates via HTML\nProficiency in SQL or Python and other programming languages\nExperience in copywriting and / or design a plus\nStrong understanding of cryptocurrency / blockchain industries including non-fungible tokens\nA strong eye for detail and precision\nSelf-directed learning attitude and strong sense of ownership\nQuick-thinking to respond to ever-changing and volatile market conditions", "employment_types": ["Full Time"], "selling_points": [], "locations": ["Central"], "categories": ["Media & Advertising", "Account Servicing", "Professional Services", "Business Analysis / Data Analysis", "Sciences, Lab, R&D", "Research & Development (R&D)"], "post_time": "2022-01-11T02:38:59Z", "salary": {"currency": null, "max": null, "min": null, "period": "monthly", "term": null}, "salary_visible": false, "title_keywords": ["project manager"], "responsibilities": [], "requirements": {"degrees": [], "majors": [], "languages": [], "language_level": [], "hard_skills": [], "soft_skills": [], "languages_combined": []}, "experience_required": {"duration": [], "field": []}}, {"job_id": "100003009037903", "location_code": "hk", "company": "PHD Limited", "job_title": "Digital Operation Executive (Advertising & Media Field)", "description": "We are a digital native business consultancy looking for a Digital Account Executives with the ambition to becoming a strategic digital business consultant who can help businesses master digital communications to achieve business success.\n\nHow you can contribute\n\nEstablish courteous and productive working relationship with clients.\nPlan and manage\u00a0the implementation of digital marketing executions across channels such as display ad, social media ad/post, paid search, SEO, eCommerce website, email automation\nManage outsourcing partners in the production of digital marketing deliverables\nBalancing multiple projects and deadlines\n\n\n\nWho you are\n\nA digital native\nPersonable, not afraid to speak out\nPassionate, curious with strong business sense\nMinimum\u00a01-year\u00a0working experience in Digital Marketing or related fields\nEager to learn the strategic importance and executional know-how of various digital marketing channels across Paid, Owned and Earned\nProactive, meticulous, organised with good sense of urgency and can-do attitude\nGood with words and not afraid of numbers\nNative English/Cantonese, fluency in Mandarin is a plus\n\n\nRewards & benefits\n\nDiscretionary bonus\nMedical benefits\nOrganised and collaborative individual is awarded with WFH privileged.\n\nImmediate availability is highly preferred.", "employment_types": ["Full Time", "Permanent"], "selling_points": ["Free Shuttle Bus & Free Breakfast", "Birthday, Family Day & Self-Love Day Leave", "5-Day Work Week"], "locations": ["Pok Fu Lam"], "categories": ["Media & Advertising", "Account Servicing", "Media Buying", "Others"], "post_time": "2022-01-11T04:11:59Z", "salary": {"currency": null, "max": null, "min": null, "period": "monthly", "term": null}, "salary_visible": false, "title_keywords": ["operation executive"], "responsibilities": ["social media", "seo", "implementation", "website", "digital marketing", "plan", "multiple projects"], "requirements": {"degrees": ["master"], "majors": ["business", "communications"], "languages": ["cantonese", "english", "mandarin"], "language_level": ["fluency", "native"], "hard_skills": ["plus", "seo", "words"], "soft_skills": ["productive", "passionate", "courteous", "personable", "meticulous", "business sense", "urgency", "can-do attitude", "eager to learn", "organised", "proactive"], "languages_combined": [{"language": "cantonese", "language_level": ["native"]}, {"language": "english", "language_level": ["native"]}, {"language": "mandarin", "language_level": ["fluency", "native"]}]}, "experience_required": {"duration": ["minimum 1-year"], "field": ["related", "digital marketing"]}}, {"job_id": "100003009036532", "location_code": "hk", "company": "DASH", "job_title": "PROJECT MANAGER / SR. PROJECT EXECUTIVE", "description": "Responsibilities:\n\nResponsible for day-to-day project management and serve as key person\u00a0between client, multi-function teams and internal work counterparts\nPresentable and possess good communication skills\nProvide consultation and recommendations for the customers in different\u00a0digital solutions\nMust be detail-minded, efficient and able to work under pressure\nResponsibilities include briefing, project management, time and cost\u00a0control, market landscape analysis and understanding of client\u2019s business\u00a0and needs\nGood team player who is at ease in a multi-cultural environment\n\nRequirements:\n\n\nTo qualify for the role you must have:\n\nDegree holder, preferably in IT or\u00a0related discipline\nA minimum of\u00a01-2\u00a0years experience of account servicing / project management\u00a0\nExperience in digital agency / consulting company will be an advantage\nHolder of Project Management Professional (PMP) and Professional Scrum Master (PSM) will be an advantage\nStrong analytical, time management and people skills\nFluent written and spoken English and Chinese is a must\n\nWhat working at EY offers:\n\nSupport, coaching and feedback from some of the most engaging colleagues around\nOpportunities to develop new skills and progress your career\nThe freedom and flexibility to handle your role in a way that\u2019s right for you\n\nIf you can confidently demonstrate that you meet the criteria above, please contact us as soon as possible.\n\nJoin us in building a better working world.\n\nApply now.", "employment_types": ["Full Time", "Permanent"], "selling_points": [], "locations": ["Lai Chi Kok"], "categories": ["Media & Advertising", "Account Servicing"], "post_time": "2022-01-10T10:54:35Z", "salary": {"currency": null, "max": null, "min": null, "period": "monthly", "term": null}, "salary_visible": false, "title_keywords": ["project manager", "project executive"], "responsibilities": ["analysis", "teams", "communication", "project management", "cost control", "work under pressure"], "requirements": {"degrees": ["master", "degree holder"], "majors": ["project management", "it"], "languages": ["english", "chinese"], "language_level": ["fluent"], "hard_skills": ["project management", "pmp", "project management professional"], "soft_skills": ["project management", "time management"], "languages_combined": [{"language": "english", "language_level": ["fluent"]}, {"language": "chinese", "language_level": ["fluent"]}]}, "experience_required": {"duration": ["minimum of 1-2 years"], "field": ["consulting", "agency", "account servicing", "project management", "digital"]}}, {"job_id": "100003009037414", "location_code": "hk", "company": "New iMedia Solutions Limited", "job_title": "Digital Performance Executive / Specialist | Digital Advertising | SEM | (Department Expansion)", "description": "Job Responsibilities:\n\nExecute all aspects of digital media campaign executions across different channels\nPerform digital media planning, buying across all products and platforms in the market\nPerform fundamental support for pitch, proposal and projects on a local, national and international basis\nProvide in-\u00addepth analysis to get insights using all obtainable analytics tools.\nAssist Senior Account Manager to achieve all campaign objectives through close monitoring and frequent optimisations.\nProvide clients servicing and answer enquires for corporate clients, advertising agencies and resellers at both local and regional level.\nDeliver accurate updates on campaigns to clients on both overall business and daily campaign performance\nBuild strong, long-term client relationships and maintain frequent contact\n\nRequirements:\n\nFresh graduate are also welcomed\nExperience in operating digital advertising platform, (such as\u00a0Facebook, Google, DBM, The Trade Desk...etc) is preferable\nExperience in handling China Related Media platforms (such as\u00a0Baidu, Wechat, Weibo, 360...etc) is preferable\nAble to communicate in Cantonese, English & Mandarin.\nProficient in Chinese language (Simplified & Traditional) and fluent in English.\nStrong interpersonal skills with great attention to details.\nMulti-tasking and able to work under pressure to meet deadlines & business targets.\nPassionate about the Internet and latest online advertising technologies", "employment_types": ["Full Time"], "selling_points": ["Flexi-Hour, Monthly Early Friday-off & Incentive", "Young & Energetic Talent with Passion in Digital", "Digital Performance & Strategies"], "locations": ["Kwun Tong"], "categories": ["Media & Advertising", "Account Servicing", "Media Buying", "Marketing / Public Relations", "Digital Marketing"], "post_time": "2022-01-11T02:44:49Z", "salary": {"currency": null, "max": null, "min": null, "period": "monthly", "term": null}, "salary_visible": false, "title_keywords": ["specialist", "performance executive"], "responsibilities": ["analytics tools", "advertising", "analysis", "monitoring", "maintain", "contact", "planning"], "requirements": {"degrees": ["fresh graduate"], "majors": [], "languages": ["cantonese", "english", "chinese", "mandarin"], "language_level": ["fluent", "proficient"], "hard_skills": ["facebook", "wechat"], "soft_skills": ["multi-tasking", "interpersonal skills", "attention to details", "meet deadlines", "passionate about", "work under pressure"], "languages_combined": [{"language": "cantonese", "language_level": []}, {"language": "english", "language_level": ["fluent", "proficient"]}, {"language": "chinese", "language_level": ["fluent", "proficient"]}, {"language": "mandarin", "language_level": []}]}, "experience_required": {"duration": [], "field": ["related", "digital", "advertising", "media"]}}, {"job_id": "100003009038333", "location_code": "hk", "company": "Optimum Media Direction", "job_title": "Media Executive (Advertising & Media Field)", "description": "job description\n\n\n\nTo handle project from concept and communication development to completion\nTo participate project in field of offline to online\u00a0\nWork with team to plan, implement and coordinate Marketing and advertising campaign projects\nManage\u00a0copywriting\u00a0including advertising and marketing communication, proposal write-up and related correspondences\u00a0\n\nrequirements\n\nstrong\u00a0analytics\u00a0and\u00a0strategic thinking\u00a0\ndegree / Higher Diploma in Communication, Marketing or related disciplines\ngreat interest on internet, marketing and advertising field\ncurious with everything online\nrich experience in editorial / publication is a plus\ngood Chinese copywriting skill\nproficiency in Microsoft office applications and Chinese word processing\nself-motivated, responsible,\u00a0able to work independently and under pressure and tight deadline\n\nInterested candidates, please send resume with\u00a0expected salaries*,\u00a0availability date* through jobsDB system", "employment_types": ["Full Time", "Permanent"], "selling_points": ["Free Shuttle Bus & Free Breakfast", "Birthday, Family Day & Self-Love Day Leave", "5-Day Work Week"], "locations": ["Pok Fu Lam"], "categories": ["Media & Advertising", "Account Servicing", "Media Buying", "Others"], "post_time": "2022-01-11T06:34:00Z", "salary": {"currency": null, "max": null, "min": null, "period": "monthly", "term": null}, "salary_visible": false, "title_keywords": ["executive"], "responsibilities": ["communication", "advertising", "coordinate", "plan"], "requirements": {"degrees": ["diploma", "degree"], "majors": ["related disciplines", "marketing"], "languages": ["chinese"], "language_level": ["proficiency", "good"], "hard_skills": ["plus", "chinese word processing", "microsoft office"], "soft_skills": ["self-motivated", "work independently", "under pressure", "strategic thinking", "responsible", "communication"], "languages_combined": [{"language": "chinese", "language_level": ["proficiency", "good"]}]}, "experience_required": {"duration": [], "field": ["editorial"]}}, {"job_id": "100003009033949", "location_code": "hk", "company": "GroupM Limited", "job_title": "Xaxis | Programmatic Trading Specialist", "description": "GroupM, the world\u2019s largest media investment company and are a part of WPP. In fact, we are responsible for one in every three ads you see globally. We are currently looking for a\u00a0Planning\u00a0Supervisor\u00a0to join us.\n\nAt GroupM, our people are our strength, which is why fostering a culture of diversity and inclusion is important to us.\n\n\u00a0\nDescription\n\n3 best things about the job:\n\nOpportunity to learn advanced integrated media planning skills from the experienced team lead\nOpportunity to learn advanced planning approach with heavily digital focus operation and advanced digital solution\nWork with young and energetic team\n\nMeasures of success\n\nIn three months:\n\nBecome familiar with all relevant media and finance systems, and the team processes\nProvided support to the team as well as build knowledge of the media landscape & skillsets\n\n\u00a0In six months:\n\nMaster client reporting and tracking of booked media\nStarted to build relationships with the key decision makers within the client and agency organizations\n\nIn 12 months:\n\nConfidence and precision in updating integrated media schedules and participate to construct a holistic campaign\nBe the person whom the client goes to for day- to-day activities. Able to propose ideas and activities to answer identified challenges\n\nWhat your day job looks like at GroupM:\n\nContribute to overall media strategy development. This will include the ability to understand and interpret briefs and the application of insights to develop marketing and communications solutions\nUnderstand the client\u2019s market position to achieve optimal negotiation for clients\nEnsure regular reporting is delivered on time and accurately\nEnsure that campaigns are tracked and measured based on agreed KPIs and media efficiencies\nDevelop and build relationships with clients, acting as first point of contact on account requirements\nDevelop strong working relationship with key agency and media partners. This will include acting as the first point of contact for operational issues\nKeep current on media trends, identify and implement local media initiatives\n\nMinimum qualifications:\n\nDegree relating to marketing or business will be preferable and you have been working with media and communication planning for several years\n4 years of experience in media agency, including client-side or media owner capacity\nYou are a team player with good interpersonal skills and you thrive in an energetic and fast paced environment.\nAn affinity for numbers and experience in Excel is highly desired.\nExperience working with multiple stakeholders, e.g. suppliers, advertising/marketing agencies, media owners and internal specialist resources\nCompetent in communications planning, media planning and buying across all platforms with a good understanding and working knowledge of both traditional and new media\nStrong analytical mind, good flair of creativity and with an eye for details\nStrong communication and presentation skills\nCandidate with more experience will be considered as Assistant Manager/ Manager\n\n\u00a0More about GroupM\n\nGroupM leads and shapes media markets by delivering performance enhancing media products and services, powered by data and technology. Our global network agencies and businesses enable our people to work collaboratively across borders with the best in class, providing them the opportunity to accelerate their progress and development. We are not limited by teams or geographies; our scale and diverse range of clients lets us be more adventurous with our business and talent. We give our talent the space, support and tools to innovate and grow.\n\nDiscover more about GroupM at\u00a0www.groupm.com\nFollow @GroupMAPAC on Twitter\nFollow GroupM on LinkedIn -\u00a0https://www.linkedin.com/company/groupm\n\nAbout Hong Kong\n\nHong Kong SAR\u2019s small yet highly dynamic and efficient media market allows us to operate with agility. Its internet and digital penetration continues to grow year-on-year, and has the highest smartphone penetration in Asia Pacific at 87%, while tablet ownership clocks in at 57%. Hong Kong SAR\u2019s digital market boasts a healthy mix of local, regional and global players, providing new opportunities in the media space.\n\nIf you want a future in media and communications, and believe in Hong Kong SAR\u2019s belief of \u201cwork hard, play hard\u201d, there is clearly no place more vibrant, challenging and exciting than Hong Kong SAR, where opportunities for you to innovate and grow are unparalleled.\n\nGroupM is an equal opportunity employer. We view everyone as an individual and we understand that inclusion is more than just diversity \u2013 it\u2019s about belonging. We celebrate the fact that everyone is unique and that\u2019s what makes us so good at what we do. We pride ourselves on being a company that embraces difference and truly represents the global clients we work with.", "employment_types": ["Full Time", "Permanent"], "selling_points": [], "locations": ["Quarry Bay"], "categories": ["Media & Advertising", "Account Servicing", "Media Buying", "Others"], "post_time": "2022-01-10T02:14:42Z", "salary": {"currency": null, "max": null, "min": null, "period": "monthly", "term": null}, "salary_visible": false, "title_keywords": ["specialist"], "responsibilities": ["reporting", "ideas", "advertising", "data", "schedules", "systems", "teams", "develop", "communication", "planning", "contact", "kpis", "tracking"], "requirements": {"degrees": ["degree", "master"], "majors": ["business", "marketing"], "languages": [], "language_level": [], "hard_skills": ["small", "excel", "no", "dynamic", "finance systems", "focus"], "soft_skills": ["efficient", "planning skills", "confidence", "advanced", "responsible", "negotiation", "competent", "unique", "communication", "diverse", "presentation skills", "team player", "interpersonal skills", "analytical mind", "dynamic", "focus", "energetic"], "languages_combined": []}, "experience_required": {"duration": ["4 years"], "field": ["agency", "media"]}}, {"job_id": "100003009037411", "location_code": "hk", "company": "New iMedia Solutions Limited", "job_title": "Content Writer", "description": "Design & decoration magazine is looking for a\n\nSales Manager / Assistant Sales Manager\n\n\n\nDSE or above / Degree holder preferable\nMinimum 3 years of media sales experience (Candidates with less sales experience will be considered a lower position.)\nHonest and committed\nPresentable, out-going personality, self-motivated with strong sense of responsibility\nMay need to work overtime\n\nWe offer very competitive remuneration and benefits package for the right candidate.\n\nPlease send your application with one-page cv and expected income to:\n\n\u00a0In Express-Sisters Group Limited", "employment_types": ["Full Time"], "selling_points": ["Digital Content Writing, SEO Writing", "Good command in Chi & Eng writing", "14 days Leave, Flexi-hour"], "locations": ["Kwun Tong"], "categories": ["Media & Advertising", "Account Servicing", "Sales, CS & Business Devpt", "Business Development", "Marketing / Public Relations", "Digital Marketing"], "post_time": "2022-01-11T02:44:14Z", "salary": {"currency": null, "max": null, "min": null, "period": "monthly", "term": null}, "salary_visible": false, "title_keywords": ["content writer"], "responsibilities": ["design"], "requirements": {"degrees": ["dse", "degree holder"], "majors": [], "languages": [], "language_level": [], "hard_skills": [], "soft_skills": ["self-motivated", "work overtime", "sense of responsibility", "presentable", "committed", "honest"], "languages_combined": []}, "experience_required": {"duration": ["minimum 3 years"], "field": ["media sales"]}}, {"job_id": "100003009035366", "location_code": "hk", "company": "TBWA Hong Kong", "job_title": "SOCIAL STRATEGIST", "description": "\u00a0Job Responsibilities:\u00a0\n\nAssist the team in developing and implementing an integrated on/off advertising campaign\nHelp on competitive data generation, analysis and presentation\nPrepare evaluation of media opportunities, keep tracks of market trends by using industry tools and other research methods\nPrepare media plan, budget summary and campaign follow up\nActively participate in brain-storming for big ideas and consumer insights\nMaintain and strengthen relationships with industry partners.\n\n\u00a0Job Requirements:\u00a0\n\nUniversity degree in business, marketing, advertising, communications, or a related field\n0-1 year of media planning/buying experience preferably (fresh graduates are also welcomed)\nMust be well organized and have strong quantitative/analytical skills\nAble to build relationship internally and externally\nAbility to manage multi-task well in a fast-paced environment and a team player.\nMust be numerate and have strong attention to detail\nPassionate about building a career in advertising field\nFluent written and spoken English and Chinese is a must\nProficiency in Word, Excel and PowerPoint\n\nWorking Location: Cyberport (\u6578\u78bc\u6e2f), Hong Kong\n\nWe offer a 5-day week of work, group medical & life insurance coverage and free shuttle bus to the right candidate. Interested parties please send your application letter and resume to click the \"Apply Now\" at the bottom.\n\nAll information collected will be used for recruitment only and treated in strict confidence. We will retain the personal data of unsuccessful applicants for future recruitment purpose for a maximum period of 2 years.", "employment_types": ["Full Time", "Permanent"], "selling_points": ["2-3 year experience in an integrated agency", "Manage social media pages & content planning", "Spoken and written Cantonese & English"], "locations": ["Quarry Bay"], "categories": ["Media & Advertising", "Account Servicing", "Marketing / Public Relations", "Digital Marketing"], "post_time": "2022-01-10T06:56:19Z", "salary": {"currency": null, "max": null, "min": null, "period": "monthly", "term": null}, "salary_visible": false, "title_keywords": [], "responsibilities": ["advertising", "ideas", "consumer insights", "data", "analysis", "budget", "developing", "maintain", "plan", "evaluation"], "requirements": {"degrees": ["university degree"], "majors": ["business", "communications", "marketing"], "languages": ["english", "chinese"], "language_level": ["fluent"], "hard_skills": ["excel", "word", "powerpoint", "analytical skills"], "soft_skills": ["multi-task", "fast-paced environment", "well organized", "analytical skills", "attention to detail", "team player", "passionate about"], "languages_combined": [{"language": "english", "language_level": ["fluent"]}, {"language": "chinese", "language_level": ["fluent"]}]}, "experience_required": {"duration": ["0-1 year"], "field": ["media", "planning"]}}, {"job_id": "100003009038331", "location_code": "hk", "company": "Optimum Media Direction", "job_title": "Digital Manager (Advertising & Media Field)", "description": "Being a crucial member of the team, the successful candidate will be responsible for implementing media placements, liaising with client, creative agency, and media vendor to make campaign GO LIVES. We also aim to provide best services and value to our client.\nTraining on negotiation process and usage on proprietary tools will be provided. This entry-level opportunity will kick-start your career in media and provide a platform to partner with the world\u2019s leading consumer brands.\n\nQualifications and Requirements:\n\nPassion for advertising / media\nForm 7 / Diploma / University graduated in any discipline;\nFluent in English and Chinese, both written and spoken language skills; \u00a0\u00a0\nDetail oriented, organised and sensitive to numbers;\nA good team player with good communication skills and self-motivated;\n\nJob Scope:\n\nLiaise with both traditional and digital media vendors on buying cost\nOptimisation of media budget and provide the best value / solution for client;\nParticipate in implementing an integrated traditional and digital advertising campaign from material co-ordination, booking, post campaign reporting / evaluation to monthly billing\nKeep monitoring the advertising market change, client\u2019s competitors move and the transformation of media consumption behavior\nInitiate \u201cout-of-box\u201d ideas to your client\n\nWe offer 5 days\u2019 work week, good salary package with MPF and Medical Plan with Dental Care and staff training for development.\u00a0 Interested applicants should submit resumes with expected salary and date of availability to our email address\u00a0(please indicate the relevant job position: Media Executive Buying & Operation Team)\n\nFor further information about IPG Mediabrands, please visit:\u00a0http://www.ipgmediabrands.com/\n\n", "employment_types": ["Full Time", "Permanent"], "selling_points": ["Free Shuttle Bus & Free Breakfast", "Birthday, Family Day & Self-Love Day Leave", "5-Day Work Week"], "locations": ["Pok Fu Lam"], "categories": ["Media & Advertising", "Account Servicing", "Strategic Planning", "Others"], "post_time": "2022-01-11T06:33:19Z", "salary": {"currency": null, "max": null, "min": null, "period": "monthly", "term": null}, "salary_visible": false, "title_keywords": ["manager"], "responsibilities": ["reporting", "cost", "advertising", "ideas", "budget", "monitoring", "liaising with", "communication", "booking", "evaluation", "liaise with", "negotiation process"], "requirements": {"degrees": ["diploma"], "majors": [], "languages": ["english", "chinese"], "language_level": ["fluent"], "hard_skills": ["make", "go", "vendor"], "soft_skills": ["communication skills", "good team player", "self-motivated", "negotiation", "responsible", "passion for", "detail oriented", "organised", "sensitive to numbers", "creative"], "languages_combined": [{"language": "english", "language_level": ["fluent"]}, {"language": "chinese", "language_level": ["fluent"]}]}, "experience_required": {"duration": [], "field": []}}, {"job_id": "100003009043420", "location_code": "hk", "company": "", "job_title": "\u53ef\u6263\u7a05\u5f37\u7a4d\u91d1\u8a08\u5283\u5c08\u54e1 MPF Service Manager", "description": "Support social team in social planning and social strategy development\nWork closely with Business Team, Creative Team, Strategy Team, etc to come up with social media strategy and content plan that fit clients\u2019 need\nManage day-to-day social media content\nMeasure content performance with analytic tools and compile weekly and monthly performance reports\nPerform daily community management to respond to enquiries on clients\u2019 social pages\nCarry out influencer identification, outreach, and management for collaborated content\nSkills & Experience\n\n\n2-3 years\u2019 experience in an integrated agency setting\u00a0\nPassionate about social media and digital marketing\nExperience in managing social media pages, content planning and deliver accurate performance reports\nKnowledge in paid social (Facebook ads, Instagram ads, etc)\nFluency in spoken and written Cantonese and English\nExperience in working with bank, financial and hospitality clients will be preferred\n\nIf you are interested, we want to hear from you.\u00a0 Please apply with your cv indicating current and expected salary.\n\nTBWA\u00a0is an equal opportunity employer\u00a0and\u00a0does not discriminate on the basis of race, colour, religion, creed, gender, sexual orientation, age, gender identity, marital status, citizenship,\u00a0disability, genetic information or veteran status or any other basis prohibited by federal, state, or local law.\n\nPosition: Social Strategist\nDepartment: Strategic Planning\nReports to: Head of Strategy\nJob Location: Hong Kong SAR\nJob Type: Full-Time/Regular\nDocument required: CV indicating your current and expected salary", "employment_types": ["Full Time", "Permanent"], "selling_points": ["Attractive Compensation & free overseas trip", "Fast Track Promotion to Management Level", "5-day work, bank holidays, 20-day Annual Leave"], "locations": ["Others"], "categories": ["Media & Advertising", "Account Servicing", "Manufacturing", "Others", "Merchandising & Purchasing", "Procurement / Purchasing / Sourcing"], "post_time": "2022-01-15T19:11:32Z", "salary": {"currency": "HKD", "max": 29999, "min": 20000, "period": "monthly", "term": null}, "salary_visible": true, "title_keywords": ["manager"], "responsibilities": ["social media", "management", "strategic planning", "performance reports", "social media content", "digital marketing", "plan", "reports", "facebook", "planning"], "requirements": {"degrees": [], "majors": [], "languages": ["cantonese", "english"], "language_level": ["fluency"], "hard_skills": ["facebook"], "soft_skills": ["creative", "accurate", "passionate about"], "languages_combined": [{"language": "cantonese", "language_level": ["fluency"]}, {"language": "english", "language_level": ["fluency"]}]}, "experience_required": {"duration": ["2-3 years"], "field": ["agency", "social media", "financial", "planning"]}}, {"job_id": "100003009031369", "location_code": "hk", "company": "Hakuhodo Hong Kong Ltd", "job_title": "Account Manager / Senior Account Manager", "description": "Job Role:\n\nThe Digital Manager supervises all day to day planning/\u200bclient service activity.\u200b\u00a0 Reporting to the Business Director, the Digital Manager work in providing digital planning recommendations to the client.\u200b The Manager oversees preparation of digital strategy and media plans and supervises media plan implementation.\u200b The Manager is also in charge of supervising the Planners/\u200bSenior Planners in executing media plans.\u200b\n\n\nKey Responsibilities:\n\nMaintain day-to-day contact for all clients to execute requests flawlessly while adhering to clients\u2019 strategic direction.\nCoordinate and execute workflow between planning, operations and buying.\nIntelligence gathering of research, analysis and other strategic support materials. Translate/interpret data into clear and succinct information and relevant insights.\nSeek out new opportunities to grow clients business and provide necessary Point of View and rationale.\nLead internal and external status meetings/calls.\nThe role may involve performing additional media agency duties as required.\n\nKey Requirements:\n\nAt least 5-6 years of digital industry work experience. \u00a0\nCollege degree preferably in Marketing.\nProficiency in Microsoft Office\nExcellent written and verbal communication skills\nExperience in digital buying/planning\nAbility to manage tight deadlines while multitasking\nExperience/background in digital buying/planning.\nKnowledge of Display, Mobile, SEM/SEO, Social Media, Programmatic, Social Listening and content marketing.\nWorking Location: Cyberport (\u6578\u78bc\u6e2f), Hong Kong\nWe offer a 5-day week of work, group medical & life insurance coverage and free shuttle bus to the right candidate. Interested parties please send your application letter and resume with your current and expected salary by clicking \u201cApply Now\u201d button.\nAll information collected will be used for recruitment only and treated in strict confidence. We will retain the personal data of unsuccessful applicants for future recruitment purpose for a maximum period of 2 years.", "employment_types": ["Full Time", "Part Time", "Permanent"], "selling_points": ["3+yrs account servicing exp in advertising agency", "Presentable, good leadership, communication skills", "FMCG/Banking & Finance/Personal Care accounts exp"], "locations": ["North Point"], "categories": ["Media & Advertising", "Account Servicing", "Strategic Planning", "Others"], "post_time": "2022-01-07T09:16:06Z", "salary": {"currency": null, "max": null, "min": null, "period": "monthly", "term": null}, "salary_visible": false, "title_keywords": ["senior account manager", "account manager"], "responsibilities": ["data", "operations", "analysis", "coordinate", "maintain", "contact", "planning"], "requirements": {"degrees": ["degree"], "majors": ["marketing"], "languages": [], "language_level": [], "hard_skills": ["mobile", "seo", "sem", "microsoft office"], "soft_skills": ["communication skills"], "languages_combined": []}, "experience_required": {"duration": ["at least 5-6 years"], "field": ["digital", "digital industry", "planning"]}}, {"job_id": "100003007966041", "location_code": "hk", "company": "Shepherd Communications Limited", "job_title": "Social Media Manager", "description": "Manulife is No.\u00a01\u00a0in MPF Market Share as well as the Best Service Provider in Hong Kong.\n\n\u00a0A tailor-made program is offered to high calibers like you to join our profession.\u00a0\n\nOffer:\n\nSpecial package tailor-made for right person according to qualification and experience\nFast Track promotion program to Management Level within 6 months\nProfessional and ongoing training programs to enhance products and marketing knowledge\nHigh Monthly and Annual Performance bonus\nMedical and Life Insurance, low interest mortgage scheme\nFree overseas trip recognition\u00a0\n\nRequirements:\n\nHong Kong Resident\nDegree Holder\nFluency in Cantonese, proficiency in Putonghua is a plus\nMinimum 3 years of working experience\nAggressive person, endeavor to start up own business with strong commitment to succeed\n\n\nOnly short-listed candidates will be contacted.\u00a0 All applicant information is treated confidentially; personal data collection is only for recruitment selection purposes.", "employment_types": ["Full Time", "Permanent"], "selling_points": ["Account Servicing", "Online Marketing", "Digital Agency"], "locations": ["Sai Ying Pun"], "categories": ["Media & Advertising", "Account Servicing", "Strategic Planning", "Marketing / Public Relations", "Digital Marketing"], "post_time": "2022-01-10T03:47:36Z", "salary": {"currency": null, "max": null, "min": null, "period": "monthly", "term": null}, "salary_visible": false, "title_keywords": ["manager"], "responsibilities": ["management", "mpf", "recruitment", "personal data", "insurance"], "requirements": {"degrees": ["degree holder"], "majors": [], "languages": ["cantonese", "putonghua"], "language_level": ["fluency", "proficiency"], "hard_skills": ["no", "scheme", "plus"], "soft_skills": [], "languages_combined": [{"language": "cantonese", "language_level": ["fluency", "proficiency"]}, {"language": "putonghua", "language_level": ["proficiency"]}]}, "experience_required": {"duration": ["minimum 3 years"], "field": []}}, {"job_id": "100003009034918", "location_code": "hk", "company": "The Garage Limited", "job_title": "Digital Strategist", "description": "\nJob Requirements:\n\n\u2022 University graduated\n\u2022 3-5 years account servicing experience in integrated Advertising Agency\n\u2022 Preferable with relevant experience in beauty care or FMCG products\n\u2022 Passionate, proactive, self & team motivated\n\u2022 Detail-minded, good interpersonal and leadership skills\n\u2022 Proficiency in English & Chinese, both Spoken & Written\n\u2022 Able to work independently and under pressure\n\u2022 Capable of working in a fast-paced working environment\n\nJob Responsibilities:\n\n\u2022 Leading roll outs of integrated advertising campaign for beauty care products\n\u2022 Coordinate with various internal and external parties to implement the best class of advertising campaigns as a team\n\u2022 Sound strategic and planning skills for the implementation of communication\n\u2022 Understanding client\u2019s needs and providing client with professional consultation and suitable solution\n\u2022 Cultivate and maintain good relationship with key client\n\u2022 Manage client\u2019s expectation and budget\n\u2022 Coach, supervise and motivate subordinates in daily operations\n\u00a0\n", "employment_types": ["Full Time"], "selling_points": ["Plan and implement marketing campaigns", "Manage digital campaign projects", "Prepare proposals and reports"], "locations": ["Kowloon Bay"], "categories": ["Media & Advertising", "Account Servicing", "Marketing / Public Relations", "Others", "Digital Marketing"], "post_time": "2022-01-10T04:38:54Z", "salary": {"currency": null, "max": null, "min": null, "period": "monthly", "term": null}, "salary_visible": false, "title_keywords": [], "responsibilities": ["advertising", "internal and external parties", "coordinate with", "implementation", "budget", "maintain good relationship", "communication", "daily operations", "advertising campaigns", "planning"], "requirements": {"degrees": [], "majors": [], "languages": ["english", "chinese"], "language_level": ["proficiency"], "hard_skills": [], "soft_skills": ["passionate", "detail-minded", "work independently", "under pressure", "capable", "leadership skills", "motivated", "proactive", "interpersonal"], "languages_combined": [{"language": "english", "language_level": ["proficiency"]}, {"language": "chinese", "language_level": ["proficiency"]}]}, "experience_required": {"duration": ["3-5 years"], "field": ["fmcg", "account servicing", "relevant experience", "beauty", "advertising agency"]}}, {"job_id": "100003009037223", "location_code": "hk", "company": "RFI Asia Limited", "job_title": "Social Media Marketing Intern (full-time only)", "description": "Trainee / Business Development Manager (Income $30,000Up + High Bonus & Incentives)\nWe are now recruiting a\u00a0Trainee / Business Development Manager with high calibre and intelligence to join this fast-growing industry. \u00a0\nSuccessful candidate will be offered a 6 months fast track promotion which including attractive packages, comprehensive on-the-job training and all professional financial knowledge and skills.\nThis is an entry point that leads you to a management position as soon as 6 months!\u00a0\u00a0\nWe Offer :\u00a0\n\u2022 Fast-track promotion program to management level within 6 months\u00a0\n\u2022 5 days work, 20 days annual leave and bank holidays\u00a0\n\u2022 Medical & life insurance, provident fund and low interest mortgage Insurance benefit\u00a0\n\u2022 Professional training program (Pre-job and on-job training for promotion to management level) excellent career path to management with the market leader\u00a0\n\u2022 Monthly income $30,000 up + high monthly and annual performance bonus\u00a0\u00a0\u00a0\n\u2022 Management overrides, overseas trips and incentives\u00a0\u00a0\n\u2022 Client Base Provided\nRequirements :\n\u2022 Degree holder preferred / F.5 or above with management experience\u00a0\n\u2022 3 Years or more working experience, fresh graduate or new in industry will also be considered\n\u2022 Sales driven, self-motivated and customer oriented\n\u2022 Finance related experience is not necessary, but solid management skill is an absolute advantage\u00a0\n\u2022 Fluent in Cantonese\u00a0\u00a0\n\u2022 Strong desire for a successful career\u00a0\n\u2022 Valid HKID holder for working in Hong Kong\nJob Descriptions\u00a0:\u00a0\n\u2022 Deliver professional financial planning to individual clients on life and medical protection, risk management, savings planning, investment planning, retirement planning and MPF etc.\u00a0\n\u2022 Provide professional service to corporate clients on MPF, group medical plan and business insurance\u00a0\n\u2022 Maintain ongoing client relationship and develop an affluent client base\u00a0\n\u2022 Provide team management and attempt planning strategies for building team\n\u2022 Welcome candidates changing from Telecom sales, Aviation (airline industry), food & beverages industry to join\nInterested Candidate please send your detailed CV to us or contact Ms Chiu at mobile: 9735-6840.\n\n\n*Only shortlisted candidates will be notified.\u00a0 All data collected will be used for recruitment purposes only and will be used strictly confidential.", "employment_types": ["Internship"], "selling_points": ["Fast-track digital marketing internship", "Grow quickly to become a Social Media Executive", "Recent graduates encouraged!"], "locations": ["Southern Area"], "categories": ["Media & Advertising", "Account Servicing", "Media Buying", "Marketing / Public Relations", "Digital Marketing"], "post_time": "2022-01-11T02:07:05Z", "salary": {"currency": "HKD", "max": 13999, "min": 8000, "period": "monthly", "term": null}, "salary_visible": true, "title_keywords": ["intern"], "responsibilities": [], "requirements": {"degrees": [], "majors": [], "languages": [], "language_level": [], "hard_skills": [], "soft_skills": [], "languages_combined": []}, "experience_required": {"duration": [], "field": []}}, {"job_id": "100003009035493", "location_code": "hk", "company": "Carat Media Services Hong Kong Limited", "job_title": "Media Executive (Fresh graduate welcome)", "description": "ABOUT SEDGWICK RICHARDSON\n\nWe\u2019re a regional team of strategists, designers and sustainability specialists who are passionate about building brands that have a positive impact on our world.\n\nTogether, we Build Belief in the Future.\n\nThe Role\n\nWe are looking for an articulate, driven and highly organised Project Manager to join our Greater China team, working with our Associate Account Director and Sustainability Director\u00a0 on corporate and ESG publishing projects for leading listed companies. These include both printed and digital sustainability and financial reports.\n\nWorking with the account servicing team and our creative studio, you will assist in delivering high quality and inspiring projects on time and on budget, while maintaining professional and proactive service to our clients.\n\n\n\nAbout You\n\nAt least 3 years of experience working in reporting (print and digital) or publishing within an agency environment\nDetail focused and take pride in delivering great work\nProven project management skills, including scoping out new projects and contributing to proposals\nExperience in managing external vendors\nGood spoken and written English, Cantonese. Putonghua would be a big plus", "employment_types": ["Full Time", "Permanent"], "selling_points": ["Prepare implementational buying briefs", "Prepare competitive analysis", "Quality check spot plans"], "locations": ["Quarry Bay"], "categories": ["Media & Advertising", "Account Servicing", "Strategic Planning", "Others"], "post_time": "2022-01-10T07:25:18Z", "salary": {"currency": null, "max": null, "min": null, "period": "monthly", "term": null}, "salary_visible": false, "title_keywords": ["executive"], "responsibilities": ["reporting", "financial reports", "maintaining", "budget", "quality", "project management"], "requirements": {"degrees": [], "majors": [], "languages": ["cantonese", "putonghua", "english"], "language_level": ["good"], "hard_skills": ["project management", "plus"], "soft_skills": ["passionate about", "proactive", "focused", "project management skills", "inspiring", "organised", "articulate", "creative", "driven", "positive"], "languages_combined": [{"language": "cantonese", "language_level": ["good"]}, {"language": "putonghua", "language_level": []}, {"language": "english", "language_level": ["good"]}]}, "experience_required": {"duration": ["at least 3 years"], "field": ["agency", "digital", "print", "publishing"]}}, {"job_id": "100003009038140", "location_code": "hk", "company": "Executive One", "job_title": "Part Time - Marketing Assistant \u591a\u5a92\u9ad4\u904b\u71df(HK$65-85/hr)", "description": "The Role\n\nReporting to the Digital Marketing Director, this position requires a candidate who has a passion for digital media and Ad-Tech industry. You will be growing quickly, learning how the ecosystem of digital media and data operates in the Hong Kong market from the one of the biggest agencies in the region.\n\n\n\nResponsibilities\n\nAd Trafficking, including 3rd party ad serving (Google Campaign Manager), website tracking, brand safety and associated technologies.\nConversion Tag tracking for different digital platform.\nGathering data through various third party platforms and analytics tools.\nData management including dashboards.\nData QA and analysis on media/performance trends, identify insights for campaign strategy/ planning.\n\nKey Requirements\n\nPreferably 1-2 years experience with digital marketing agency.\u00a0 Fresh graduate will also be considered.\nUnderstanding of Digital Media buying, including IO, DSP, Social Media, Search.\nStrong analytical skills, highly numerate and comfortable with data processing and interpretation.\nGood team player with excellent time-management and strong organizational skills to handle multiple projects.\nWork under pressure and meet tight deadline.\nGood in communications skills.\nExcellent command of English and Cantonese; written and spoken\nStrong attention to detail and problem-solving skills\nEagerness to learn and collaborate with others\nOpenness to change and willingness to work through challenges\nProficiency in Microsoft Office (Words, Excel and PowerPoint) is a must.\nA bachelor's degree, preferably with combined studies in Information Systems and Media, or related business field.\n\nWorking Location: Cyberport (\u6578\u78bc\u6e2f), Hong Kong\u00a0\n\nWe offer a 5-day work of week, group medical & life insurance coverage to the right candidate. Interested parties please send your application letter and resume with current and expected salary\u00a0by clicking the \"Apply Now\" button.\n\nAll information collected will be used for recruitment only and treated in strict confidence. We will retain the personal data of unsuccessful applicants for future recruitment purpose for a maximum period of 2 years.", "employment_types": ["Full Time", "Part Time", "Permanent", "Temporary", "Contract", "Internship"], "selling_points": ["Proven experience in Facebook / Digital Marketing", "Passionate about Digital Marketing Trends", "Proficiency in photo and video editing software"], "locations": ["Wan Chai"], "categories": ["Media & Advertising", "Account Servicing", "Others", "Student / Fresh Graduate / No Experience", "Marketing / Public Relations", "Digital Marketing"], "post_time": "2022-01-11T05:29:12Z", "salary": {"currency": null, "max": null, "min": null, "period": "hourly", "term": null}, "salary_visible": false, "title_keywords": ["marketing assistant", "hr"], "responsibilities": ["analytics tools", "management", "data", "analysis", "website", "digital platform", "planning", "third party", "tracking"], "requirements": {"degrees": ["degree", "bachelor", "fresh graduate"], "majors": ["business"], "languages": ["cantonese", "english"], "language_level": ["excellent"], "hard_skills": ["excel", "io", "words", "microsoft office", "powerpoint", "analytical skills", "problem-solving skills", "processing"], "soft_skills": ["organizational skills", "good team player", "analytical skills", "willingness to work", "meet tight deadline", "attention to detail", "problem-solving skills", "work under pressure"], "languages_combined": [{"language": "cantonese", "language_level": ["excellent"]}, {"language": "english", "language_level": ["excellent"]}]}, "experience_required": {"duration": ["1-2 years"], "field": ["agency", "digital marketing"]}}, {"job_id": "100003009037376", "location_code": "hk", "company": "Asia One HK Limited", "job_title": "Customer Service", "description": "Responsibilities\u00a0\n\n\nWorking with the Media Planners to support the Business Director on account management on a day to day basis.\nBeing part of team in creating / generating communication ideas.\nCompiling reviews on competitive activities and market research on media consumptions.\nCommunicate with different parties, including clients and vendors, during the planning process.\u00a0\u00a0\nCollate monthly plan updates with buying team or different creative teams on executions.\u00a0\n\n\u00a0Requirements\n\n\nTertiary education or above\nWell organized multi-tasker\nPositive \u201ccan-do\u201d attitude\nGood team player\nInterested in different technologies\nDetail-minded and able to work under pressure.\nEnthusiastic and keen to learn about media in Hong Kong\nGood English and interpersonal communication\nGood PC skill , especially excel, PowerPoint and internet operation, proficiency in the full suite of Microsoft Office tools\n\nWe offer 5 days work and attractive compensation package to suitable candidates. Interested parties, please send your full resume including your present & expected salary to us by email.\n\nPlease note that only short-listed applicants will be notified. All information provided will be treated in strictly confidential and used solely for recruitment purpose.", "employment_types": ["Full Time"], "selling_points": ["Performance Bonus", "Development opportunities", "Flexible working"], "locations": ["Kowloon Bay"], "categories": ["Media & Advertising", "Account Servicing", "Sales, CS & Business Devpt", "Customer Service - Supervisor / Officer", "Marketing / Public Relations", "Marketing - General / Support"], "post_time": "2022-01-11T02:38:46Z", "salary": {"currency": null, "max": null, "min": null, "period": "monthly", "term": null}, "salary_visible": false, "title_keywords": ["customer service"], "responsibilities": ["communicate with", "management", "ideas", "planning process", "teams", "market research", "communication", "plan"], "requirements": {"degrees": [], "majors": [], "languages": ["english"], "language_level": ["good"], "hard_skills": ["powerpoint", "excel", "pc skill", "microsoft office"], "soft_skills": ["detail-minded", "good team player", "keen", "interested in", "well organized", "communication", "can-do", "enthusiastic", "interpersonal", "positive", "work under pressure"], "languages_combined": [{"language": "english", "language_level": ["good"]}]}, "experience_required": {"duration": [], "field": []}}, {"job_id": "100003009035207", "location_code": "hk", "company": "3 Screens Strategic Advisors Limited", "job_title": "Digital Business Director", "description": "\u8077\u52d9\u7db1\u9818\n\n\u7ba1\u7406\u5b98\u65b9\u7db2\u7ad9\u548c\u793e\u4ea4\u5a92\u9ad4\u5e73\u81fa\uff08Facebook\uff0cInstagram\uff0cYouTube\u7b49\uff09;\n\u8ca0\u8cac\u7c21\u55ae\u6d77\u5831\u8a2d\u8a08\u548c\u5f8c\u671f\u88fd\u4f5c\n\u5354\u52a9\u7de8\u8f2f\u548c\u63a8\u9001\u6587\u7ae0\u4ee5\u53ca\u767c\u4f48\u5230\u5927\u9678\u5a92\u9ad4\u5e73\u81fa\uff08\u5fae\u4fe1\u516c\u773e\u865f\u3001\u5fae\u535a\u3001\u5c0f\u7d05\u66f8\u7b49\uff09\n\u7121\u9700\u9032\u884c\u4efb\u4f55\u92b7\u552e\u5de5\u4f5c\n\n\u00a0\u8cc7\u6b77\u8981\u6c42\n\n\u719f\u6089\u4f7f\u7528\u7167\u7247\u548c\u8996\u983b\u7de8\u8f2f\u8edf\u9ad4\uff0c\u5177\u5099\u651d\u5f71\u7d93\u9a57\u70ba\u4f73;\n\u7cbe\u901a\u6587\u66f8\u8655\u7406\uff0c\u6587\u7b46\u6d41\u66a2;\n\u80fd\u66f8\u5beb\u53ca\u64cd\u6d41\u5229\u5ee3\u6771\u8a71\uff0c\u00a0\u82f1\u8a9e\u548c\u666e\u901a\u8a71;\n\u5177\u5099\u826f\u597d\u7684\u4eba\u969b\u6e9d\u901a\u3001\u5718\u968a\u5408\u4f5c\u3001\u7d44\u7e54\u5206\u6790\u80fd\u529b;\n\u719f\u8b58\u570b\u5167\u7db2\u7ad9\u6587\u5316\u3001\u64c1\u6709\u500b\u4eba\u535a\u5ba2\u6216\u7de8\u5beb\u535a\u5ba2\u5167\u5bb9\u7684\u7d93\u9a57\u512a\u5148\u8003\u616e;", "employment_types": ["Full Time", "Permanent"], "selling_points": [], "locations": ["Central"], "categories": ["Media & Advertising", "Account Servicing", "Professional Services", "Business Consultancy", "Marketing / Public Relations", "Digital Marketing"], "post_time": "2022-01-10T06:26:02Z", "salary": {"currency": "HKD", "max": 69999, "min": 55000, "period": "monthly", "term": null}, "salary_visible": true, "title_keywords": ["director"], "responsibilities": [], "requirements": {"degrees": [], "majors": [], "languages": [], "language_level": [], "hard_skills": [], "soft_skills": [], "languages_combined": []}, "experience_required": {"duration": [], "field": []}}, {"job_id": "100003009032685", "location_code": "hk", "company": "Bigazines Consulting Limited", "job_title": "Marketing/ Account Executive/ Business Manager (Five Days Work)", "description": "Xaxis is seeking for a Programmatic Trading Specialist to join the Programmatic Trading team in Hong Kong.\n\nThe Programmatic Trading team is at the heart of all Xaxis activity and is pivotal to the success of each programmatic advertising campaign that is executed. You will be someone who has a positive attitude and is a dedicated individual who thrives on challenges.\n\nDescription\n\nXaxis is seeking for a Programmatic Trading Specialist to join the Programmatic Trading team in Hong Kong. The Programmatic Trading team is at the heart of all Xaxis activity and is pivotal to the success of each programmatic advertising campaign that is executed. You will be someone who has a positive attitude and is a dedicated individual who thrives on challenges.\n\nThe team works closely with all other teams within the Xaxis family from Client Development and Ad Operations to Data and Product. We are looking for someone with a positive attitude, enthusiastic and is flexible with embracing changes and new challenges.\n\nReporting of the role\n\nThis role reports to the Associate Director, Programmatic Trading.\n\n3 best things about the job:\n\nIt\u2019s a great work environment - You will collaborate with a group of quick witted, humorous, diverse and extremely dedicated colleagues who are all passionate about programmatic and making advertising welcome.\nOpinions and ideas are highly encouraged, and everyone has a voice at Xaxis. Ambition is expected and passion is admired. We are always open to new ways of thinking from everyone, especially those that will contribute to the overall success of Xaxis.\nIt is never static. You are empowered to create your own balance and be proactive. There is always something new to learn, new challenges to overcome, and new technology to embrace everyday.\n\n\nMeasures of success \u2013\u00a0\n\nIn three months, you would:\n\nGain an in depth understanding of the programmatic landscape\nBe trained on the various Xaxis platforms and tools\nContribute to the day-to-day operations of the Xaxis Programmatic Trading team and take ownership of simple campaign set ups, campaign monitoring and basic optimization\n\nIn six months, you would:\n\nDevelop relationships and earn trust with Client Development and Operations teams\nManage and be responsible for branding campaigns from start to completion\nIncorporate and recommend other aspects of the Xaxis business including audience planning and insights, Xaxis products and Xaxis Marketplace as part of the overall campaign execution.\n\nIn 12 months, you would:\n\nBe responsible and confidently manage campaigns of all KPIs from start to completion\nBe a trusted advisor to Xaxis HK team and support their activity\nTest and learn, share and seek different optimization tactics and knowledge share with the wider trading team\n\nResponsibilities of the role:\u00a0\n\nSupport the Programmatic Trading Team in executing campaigns with Client Development Team and Ad Operations\u00a0Team closely\nOversee day-to-day optimization and monitoring of campaigns, and ensure optimal delivery and performance, report any anomalies to Programmatic Trading Manager.\nDevelop basic yield optimization strategies by monitoring campaign performance and identifying opportunities to optimize, improve ROI and pitch for incremental revenue\nDeploy testing methodologies on campaigns under the direction of Associate Director, Programmatic Trading\nAnalyze data from ad serving providers like Campaign Manager, Sizmek as well as conversion tracking to map the complete consumer journey\nInvolve to advise/consult with Xaxis HK team regarding inventory performance and forecasting, campaign performance, insights and suggestions.\nAssist in preparing post campaign analysis report along with the Analytics team\n\n\nWhat you will need:\n\n3 years of Professional experience with digital marketing agency, ad network or other digital media company\nKnowledge along with a passion for digital\nResult-oriented with strong communication and analytical skills\nAbility to work both independently and under supervision once objectives have been set\nAbility to work within a fast-paced deadline driven environment\nExperience managing digital ad campaigns, - display, video, mobile or paid search\nApplied knowledge of 3rd party ad serving, website tracking and associated technologies\nUnderstanding of programmatic buying, including DSPs/SSPs, RTB, ad exchanges, DMPs, audience targeting will be a bonus\nGood command in written and spoken English and Cantonese\nProficiency in Microsoft Excel and PowerPoint\nCantonese speaking is a must\nCandidate with les experience may considered as Programmatic Trader\n\nAbout Xaxis\n\nXaxis is a global digital media platform that programmatically connects advertisers to audiences across all addressable channels. Through the expert use of proprietary data and advertising technology along with unparalleled media relationships, Xaxis delivers results for over 2,800 clients in 40 markets across North America, Europe, Asia Pacific, Latin America and the Middle East. Advertisers working with Xaxis achieve exceptionally high return on advertising spend through the company\u2019s proprietary media products, as well as through its wholly-owned specialist companies, Light Reaction, Bannerconnect, and ActionX.\u00a0 For more information, visit\u00a0www.xaxis.com.\n\n\n\nAbout Hong Kong\n\nHong Kong SAR\u2019s small yet highly dynamic and efficient media market allows us to operate with agility. Its internet and digital penetration continues to grow year-on-year, and has the highest smartphone penetration in Asia Pacific at 87%, while tablet ownership clocks in at 57%. Hong Kong SAR\u2019s digital market boasts a healthy mix of local, regional and global players, providing new opportunities in the media space.\n\nIf you want a future in media and communications, and believe in Hong Kong SAR\u2019s belief of \u201cwork hard, play hard\u201d, there is clearly no place more vibrant, challenging and exciting than Hong Kong SAR, where opportunities for you to innovate and grow are unparalleled.\n\nGroupM is an equal opportunity employer. We view everyone as an individual and we understand that inclusion is more than just diversity \u2013 it\u2019s about belonging. We celebrate the fact that everyone is unique and that\u2019s what makes us so good at what we do. We pride ourselves on being a company that embraces difference and truly represents the global clients we work with.", "employment_types": ["Full Time", "Part Time", "Permanent", "Internship"], "selling_points": ["Good understanding of Internet & Social Marketing", "Strong communication skills, & quick response", "Business development, bridging between IT & Client"], "locations": ["Kwai Hing"], "categories": ["Media & Advertising", "Account Servicing", "Sales, CS & Business Devpt", "Business Development", "Marketing / Public Relations", "Digital Marketing"], "post_time": "2022-01-07T14:36:05Z", "salary": {"currency": null, "max": null, "min": null, "period": "monthly", "term": null}, "salary_visible": false, "title_keywords": ["account executive", "manager"], "responsibilities": ["collaborate with", "ideas", "data", "analysis report", "operations", "inventory", "day-to-day operations", "website", "communication", "deploy", "advertising", "teams", "develop", "testing", "reports", "analyze data", "kpis", "forecasting", "report", "reporting", "monitoring", "executing", "digital marketing", "tracking", "planning"], "requirements": {"degrees": [], "majors": [], "languages": ["cantonese", "english"], "language_level": ["good command"], "hard_skills": ["simple", "small", "no", "basic", "analysis", "powerpoint", "analytical skills", "microsoft excel", "mobile", "dynamic"], "soft_skills": ["flexible", "efficient", "independently", "responsible", "passion for", "driven", "unique", "analytical skills", "positive attitude", "diverse", "communication", "dynamic", "enthusiastic", "proactive", "result-oriented", "passionate about"], "languages_combined": [{"language": "cantonese", "language_level": ["good command"]}, {"language": "english", "language_level": ["good command"]}]}, "experience_required": {"duration": ["3 years"], "field": ["video", "agency", "digital media", "digital marketing", "digital"]}}, {"job_id": "100003009034063", "location_code": "hk", "company": "Webs s'up Production Company Limited", "job_title": "Digital Sales and Marketing Executive", "description": "We are a digital native business consultancy looking for a seasoned Digital Business\u00a0Director\u00a0to help us build and expand our business who values flatter and more flexible boutique working environment.\n\n\n\nHow you can contribute\n\n\nIdentify and nurture new businesses\nLead/support pitch/proposal development\nResponsible for company-level P&L\nManage and mentor a team\u00a0account directors/managers\nEnrich company workflow and process\nStrengthen company's offering in creative, data and marketing technology\nServe as a billable consultant on strategy only or consulting assignments\nLead and build relationship with client's senior management\nAnticipate and mitigate client's problems with your team\nAchieve client's KPIs through the application of creativity, data insight and applicable marketing technology\nOversee the implementation of digital marketing executions across channels such as display ad, social media ad/post, paid search, SEO, eCommerce website, email automation\n\n\nWho you are \u00a0\n\n\nA digital native\nCurious with strong buisness sense\nExperience managing interantional accounts/clients\n4As or management consultancy experience is appreciated\nMinimum 10-year\u00a0working experience in Digital Marketing or related fields\nThorough understanding of the strategic importance and executional know-how of various digital marketing channels across Paid, Owned and Earned.\nKeen sense of evolving digital trends and where things are heading\nGood with words and not afraid of numbers\nNative English/Cantonese, fluency in Mandarin is a plus\n\nRewards & benefits\n\n\nNew business bonus\nOrganised and collaborative individual is awarded with WFH privileged.\nLong term staff who demonstrated the skills and commitment to build and expand the 3 Screens team may be offered stock option and/or account/company level profit-sharing.\n\n\nAbout 3 Screens\n\nLocated in Soho, we are a 12 year old boutique digital native business consultancy looking to scale in the next 3 years. We enable businesses to master digital communications in order to achieve business success.", "employment_types": ["Full Time", "Permanent"], "selling_points": ["Five-day work week in Kowloon Bay Office", "Open-minded and young working environment", "Competitive salary with attractive Talent Benefits"], "locations": ["Kowloon Bay"], "categories": ["Media & Advertising", "Account Servicing", "Sales, CS & Business Devpt", "Account Servicing", "Marketing / Public Relations", "Digital Marketing"], "post_time": "2022-01-10T02:34:00Z", "salary": {"currency": null, "max": null, "min": null, "period": "monthly", "term": null}, "salary_visible": false, "title_keywords": ["sales and marketing executive"], "responsibilities": ["social media", "management", "seo", "consulting", "data", "implementation", "p&l", "website", "digital marketing", "kpis", "senior management"], "requirements": {"degrees": [], "majors": [], "languages": ["cantonese", "english", "mandarin"], "language_level": ["fluency", "native"], "hard_skills": ["plus", "seo", "words"], "soft_skills": ["flexible", "responsible", "keen", "thorough", "creative"], "languages_combined": [{"language": "cantonese", "language_level": ["native"]}, {"language": "english", "language_level": ["native"]}, {"language": "mandarin", "language_level": ["fluency", "native"]}]}, "experience_required": {"duration": ["minimum 10-year"], "field": ["related", "management", "digital marketing"]}}, {"job_id": "100003009029167", "location_code": "hk", "company": "EP Marketing", "job_title": "Account Manager / Account Executive", "description": "Job Responsibilities\n\nLead & coach a small team of account executives\nWork with local and regional brands to continuously achieve social media success;\nTo participate in client's yearly digital & social communication plan\nPrepare media plan, budget summary and campaign follow up\nActively participate in brain-storming for big ideas and consumer insights\nTo manage campaigns deliverables and coordinate with the project team, creative team & digital team to implement the best class of digital campaigns\n\nQualifications, Skills and Other Requirement\n\nDegree or above in Business, Advertising, Marketing, Communications, Journalism, E-commerce, Project Management, PR or related discipline;\nAt least 6 years experience working in account servicing, experience in digital or social media marketing is a plus\nGood knowledge or experience in HTML, Search Engine Marketing and SEO is an advantage\nDetail-minded, well-organised and a good team leader\nSelf-motivated with strong sense of responsibility\nCandidates with less experience will be considered as Senior Account Executive\n\nAttractive salary & 5-day work per week. Interested parties please email full CV by clicking \u201cAPPLY NOW\u201d.\u00a0 Please clearly state the\u00a0Present & Expected Salary\u00a0in your resume.\n\nAll personal data collected will be kept confidential and used for recruitment purpose only.", "employment_types": ["Full Time", "Permanent"], "selling_points": [], "locations": ["Causeway Bay"], "categories": ["Media & Advertising", "Account Servicing", "Marketing / Public Relations", "Marketing - General / Support", "Sales, CS & Business Devpt", "Account Servicing"], "post_time": "2022-01-07T09:41:19Z", "salary": {"currency": null, "max": null, "min": null, "period": "monthly", "term": null}, "salary_visible": false, "title_keywords": ["account executive", "account manager"], "responsibilities": ["social media", "ideas", "consumer insights", "advertising", "seo", "budget", "coordinate with", "communication", "project management", "plan", "digital campaigns"], "requirements": {"degrees": ["degree or above"], "majors": ["e-commerce", "journalism", "project management", "business", "marketing", "communications"], "languages": [], "language_level": [], "hard_skills": ["small", "plus", "seo", "e-commerce", "html", "project management"], "soft_skills": ["detail-minded", "self-motivated", "sense of responsibility", "communication", "project management", "well-organised", "good team leader", "creative"], "languages_combined": []}, "experience_required": {"duration": ["at least 6 years"], "field": ["digital", "marketing", "social media", "account servicing"]}}, {"job_id": "100003009030806", "location_code": "hk", "company": "Metta Communications Limited", "job_title": "Account Director", "description": "We\u2019re recruiting fresh minds and fresh ideas with big ambitions. New rising stars looking to begin their career in marketing.\n\nInterns join the company as Junior Associates, earning hands-on, real-world experience,\u00a0working alongside award-winning experts.\u00a0Ideal candidates are hungry to learn and excel. They are committed to delivering a job well done, which will require a detailed and curious mind, tons of energy, professional maturity, and positive work attitude.\n\nThis is a 3-month intensive program for recent graduates or those seeking to become a social media specialist. Upon successful completion, we will offer a long-term contract and promote this role to Social Media Executive.\n\nRequirements:\n\nImpress us with how much you love and understand social media\u00a0\nSurprise us with your understanding of the digital marketing world and any related skills\nWow us with your professionalism, presentation and communication skills, and strong work ethic\n\n\nWe are looking for candidates who seek a long-term career opportunity. The salary for interns is HK$8,000 per month. A salary increase will be offered when successfully promoted to\u00a0Social Media Executive.\n\nAspiring designers with skills in Adobe Photoshop, Illustrator and After Effects may apply for Creative Internship.\n\nAll internships require full-time availability from Monday through Friday.", "employment_types": ["Full Time", "Permanent"], "selling_points": ["5+ years' experience in creative agency", "Client management and engagement", "Excellent communication and presentation skills"], "locations": ["Sai Wan"], "categories": ["Media & Advertising", "Account Servicing", "Strategic Planning", "Marketing / Public Relations", "Marketing - Brand / Product Management"], "post_time": "2022-01-07T08:21:42Z", "salary": {"currency": null, "max": null, "min": null, "period": "monthly", "term": null}, "salary_visible": false, "title_keywords": ["account director"], "responsibilities": ["communication", "social media", "ideas", "digital marketing"], "requirements": {"degrees": [], "majors": [], "languages": [], "language_level": [], "hard_skills": ["excel", "adobe photoshop", "illustrator", "after effects"], "soft_skills": ["communication skills", "ideal", "committed", "hands-on", "work ethic", "creative", "positive work attitude", "presentation", "detailed"], "languages_combined": []}, "experience_required": {"duration": [], "field": []}}, {"job_id": "100003009025700", "location_code": "hk", "company": "Grayling China Ltd", "job_title": "Social Account Executive", "description": "JOB HIGHLIGHTS/ RESPONSIBILITIES\n- Develop and maintain strong relationships with new and existing partners and channels\n- Present company projects and products to potential clients\n- Conduct Research on the potential customers using social media\n- Strong commitment to team goal setting\n\nQUALIFICATIONS &\u00a0REQUIREMENTS\n- Associate Degree/Diploma Holder or above\n- With a Minimum of 1-year working experience in the advertising/ PR/ marketing / eMarketing industry\n- Outgoing, Assertive personality & Willing to learn.\n- Good understanding of Branding, Social Media and Internet Marketing\n- Good team member and self-management\n- Independent, Aggressive, Responsible, Result Oriented & Able to work under pressure.\n- Strong business mind & marketing sense.\n- Good communication skills, Presentable & quick response\n- Candidates with Advertising/ PR Selling Background have the prior advantage\n\nFresh graduates are also welcome. Those with fewer experienced candidates may be considered as\u00a0Account and Research Assistant\u00a0\n\n", "employment_types": ["Full Time"], "selling_points": [], "locations": ["Wan Chai"], "categories": ["Media & Advertising", "Account Servicing"], "post_time": "2022-01-06T06:27:41Z", "salary": {"currency": null, "max": null, "min": null, "period": "monthly", "term": null}, "salary_visible": false, "title_keywords": ["account executive"], "responsibilities": ["social media", "maintain", "conduct research", "develop"], "requirements": {"degrees": ["diploma holder", "associate degree"], "majors": [], "languages": [], "language_level": [], "hard_skills": [], "soft_skills": ["outgoing", "communication skills", "independent", "marketing sense", "responsible", "assertive", "willing to learn", "presentable", "result oriented", "team member", "work under pressure"], "languages_combined": []}, "experience_required": {"duration": ["minimum of 1-year"], "field": ["pr", "marketing", "advertising"]}}, {"job_id": "100003009031690", "location_code": "hk", "company": "TFI Digital Media Limited", "job_title": "Project Manager / Project Executive / Account Servicing (Live Event & Video Production)", "description": "Responsibilities\n\nAct as the link between China/U.S.\u2019s editorial, technical & advertising team and global brand advertisers to follow through details of advertising programs\nMonitor, facilitate and co-ordinate the process of advertising campaigns to ensure seamless and smooth execution\nAnalyze data and work out monthly reports to keep customers well informed the progress of activities and results\nHandle documentation on advertising proposal, presentation materials, sales update and forecast\n\nDesired Skills and Experience\n\n1-3 years of advertising experience preferable\nBachelor\u2019s degree in marketing or related field\nGood organizational and time management skills\nExcellent communication and problem solving skills\nAbility to analyze data and recommend solutions\nAbility to work independently in a fast-paced environment\nGood verbal and written communication skills in Mandarin and English\n\nLess experience / qualification will be considered as Account Executive\n\nWe offer an excellent remuneration package including medical scheme, MPF scheme, public holidays, and discretionary bonus to the right candidate. Please send your detailed resume indicating expected salary by clicking \u201cApply Now\u201d button to the attention of Ms. Hazel Pone.\n\n(Data collected will be used for recruitment purpose only.)", "employment_types": ["Full Time", "Permanent"], "selling_points": ["Project Management, Video Solution, Live Event", "Technology Driven, Fast Growth Industry", "5-day work, Kowloon Tong, Dynamic working team"], "locations": ["Others"], "categories": ["Media & Advertising", "Account Servicing", "Production", "Information Technology (IT)", "Others"], "post_time": "2022-01-07T10:32:22Z", "salary": {"currency": null, "max": null, "min": null, "period": "monthly", "term": null}, "salary_visible": false, "title_keywords": ["project manager", "project executive"], "responsibilities": ["management", "documentation", "advertising", "monthly reports", "monitor", "communication", "forecast", "analyze data", "advertising campaigns"], "requirements": {"degrees": ["degree", "bachelor"], "majors": ["marketing"], "languages": ["english", "mandarin"], "language_level": ["good"], "hard_skills": ["documentation", "problem solving skills"], "soft_skills": ["communication skills", "work independently", "time management skills", "organizational", "fast-paced environment", "communication", "ability to analyze", "smooth", "problem solving skills", "presentation"], "languages_combined": [{"language": "english", "language_level": ["good"]}, {"language": "mandarin", "language_level": ["good"]}]}, "experience_required": {"duration": ["1-3 years"], "field": ["advertising"]}}, {"job_id": "100003009038160", "location_code": "hk", "company": "Executive One", "job_title": "\u884c\u653f\u79d8\u66f8Administrative Secretary", "description": "Overall Purpose of an Account Director at Metta - We Are Social\n\nYou will work as team lead with client groups and teams to successfully plan and deliver services in one or more of our core service areas: Consultancy, Research and Insight, and Engagement.\n\nWe look to you to work very closely with internal teams and clients to deliver the best solutions that Metta - We Are Social can offer. You will have the responsibility, together with the wider Management Team, for developing and driving forward existing business, building and developing your client relationships, demonstrating real \u2018thought\u2019 leadership and helping bring new business into the agency. We expect you to work with us on staff development, team structures, forward planning and financial forecasting, whilst achieving profitability and revenue targets. You will also be expected to lead teams and projects as needed.\n\nWe also expect you to keep abreast of the industry for emerging trends and creative practices, educating not only your own team but also the wider team at Metta - We Are Social. We also look to you to continually keep your clients updated and engaged with relevant industry practices.\n\nSome of the key duties will include:\n\nManagement of strategic and long-term planning of client accounts\nManagement of day to day client activity and inter-agency projects, including scheduling and management of client-facing meetings\nAct as a partner to clients in developing business solutions and providing ideas that solve marketing problems\nEnsuring that all activity follows sign off processes\nStatus and other reporting internally and externally\nDay to day team management both task management and ensuring that your team members develop their skills, helping them to reach their goals\nFinancial management of all of your accounts\nEndeavour to increase revenues in existing client business\nActive involvement in new business pitching and preparation\nProactive development and planning of creative campaigns and answering creative briefs relevant to both existing clients and new business prospects, and helping ensure that the outputs generate the best possible results\nClearly defining client requirements while overseeing the execution of the creative idea from the client brief\nRegular monitoring of the client and their reputation in on and off line media\nRegular monitoring of competitor brands in on and off line media\nConducting research as required for new business and campaign planning\n\nQualifications and Experience\n\nMinimum 5 \u00a0years\u2019 work experience in an advertising, PR, or online marketing agency or similar field\nWell-versed in and committed to producing leading-edge social media communications and content\nExcellent written Chinese and English communication and presentation skills.\nAbility to work independently on a project or in a collaborative team environment\nMust have outstanding organisational skills and the ability to handle\u00a0multiple projects\u00a0simultaneously while working under pressure of deadlines\nDemonstrated critical thinking and problem solving abilities\nBachelor\u2019s degree in advertising, marketing, graphics, web development communications or related area", "employment_types": ["Full Time", "Part Time", "Permanent", "Temporary", "Contract", "Internship", "Freelance"], "selling_points": ["Proven experience in Facebook / Digital Marketing", "Passionate about Digital Marketing Trends", "Proficiency in photo and video editing software"], "locations": ["Wan Chai"], "categories": ["Media & Advertising", "Account Servicing", "Others", "Student / Fresh Graduate / No Experience", "Marketing / Public Relations", "Digital Marketing"], "post_time": "2022-01-11T05:43:09Z", "salary": {"currency": null, "max": null, "min": null, "period": "hourly", "term": null}, "salary_visible": false, "title_keywords": ["secretary"], "responsibilities": ["graphics", "management team", "management", "reporting", "ideas", "advertising", "social media", "monitoring", "teams", "developing", "develop", "communication", "scheduling", "plan", "multiple projects", "forecasting", "planning"], "requirements": {"degrees": ["degree", "bachelor"], "majors": ["marketing", "communications"], "languages": ["english", "chinese"], "language_level": ["excellent"], "hard_skills": ["problem solving", "web development", "graphics"], "soft_skills": ["work independently", "proactive", "under pressure", "creative", "collaborative", "communication", "committed", "presentation skills", "organisational skills", "problem solving", "active", "leadership", "client-facing"], "languages_combined": [{"language": "english", "language_level": ["excellent"]}, {"language": "chinese", "language_level": ["excellent"]}]}, "experience_required": {"duration": [], "field": ["agency", "pr", "marketing", "advertising"]}}, {"job_id": "100003009036775", "location_code": "hk", "company": "Austen Capital Partners Holding Limited", "job_title": "Executive Assistant", "description": "Reports to: \u00a0 \u00a0\u00a0\u00a0\u00a0\u00a0\u00a0\u00a0\u00a0\u00a0 Social Account Director (Hong Kong)\nLocation: \u00a0\u00a0\u00a0\u00a0 \u00a0\u00a0\u00a0\u00a0\u00a0\u00a0\u00a0\u00a0\u00a0 Grayling Hong Kong (Wan Chai)\nDirect reports: \u00a0\u00a0\u00a0\u00a0\u00a0 Social Account Manager (Hong Kong)\nSalary: \u00a0\u00a0\u00a0\u00a0\u00a0\u00a0\u00a0\u00a0\u00a0\u00a0\u00a0\u00a0\u00a0\u00a0\u00a0\u00a0\u00a0\u00a0 Competitive\n\nRole\n\nWe are looking for a driven, hard-working and highly organised Social Media Account Executive to join the social media team at Grayling, working solely on one of the company\u2019s biggest and most important clients. The successful candidate will be an enthusiastic team player, with incredible attention-to-detail and can spot a typo a mile off, exceptional copy-writing skills and switched on to the latest social media trends and innovations.\u00a0\n\nThe client is a world-leading technology brand, producing high-quality mobile phones and other premium lifestyle products. Our role is to manage the client\u2019s global social media channels, across Facebook, Instagram, Twitter, YouTube and LinkedIn.\n\nThe successful candidate will join a dedicated social media team, with day-to-day responsibilities including management of influencer collaborations, reporting and live content creation at client and industry events, and community management of an engaged global audience.\n\nThis is a unique, full-on role for an ambitious, motivated candidate with a positive, can-do attitude, who loves social media and engaging with audiences, and who\u2019s looking to work in a fast-paced and exciting environment for one of the world\u2019s most high-profile technology brands and loves all things social media. It is an excellent opportunity to be a team player and learn insight and strategy, proposal brainstorming and creation, and presentation skills.\n\n\n\nSkills, Experience and Qualifications\n\nIdeally already has 6-12 months+ social media experience at an agency or well-known brand, with a focus on community management and social content creation\nStrong knowledge and confident use of social media platforms, such as Facebook, Twitter, Instagram, YouTube and LinkedIn (knowledge of TikTok or other latest social trends are an advantage)\nExcellent organisation skills, including time management\nImpeccable attention-to-detail with ability to spot typos easily, and takes absolute pride in the quality of their written work particularly in regards to public social community management\nExcellent English written skills for creating engaging social media copy\nMandarin Chinese written and verbal skills a must for client communication\nStrong computer skills (PowerPoint, Excel, Word), with basic Photoshop skills a bonus\nConfident use of social media advertising platforms (e.g. Ad Manager) is an advantage\nExcellent communication skills via telephone, social platforms, e-mail, etc \u2013 the ability to empathise and respond appropriately to customer enquiries on social media is essential\nAnalytical thinker, capable of learning fast and quickly adapting to new tools and platforms\nExperience of influencer relations/campaign management is an advantage\nExperience with social media listening tools is a huge plus\nCurious: a desire to learn, improve, apply new knowledge and develop\nProactive, quick working and self-motivated team player\nAccountabilities\n\nDevelopment of social media content calendars across Facebook, Twitter, Instagram, Youtube and LinkedIn with the support of the account manager.\nContent scheduling and posting across channels \u2013 including posting content from approved content calendars and posting ad hoc content, as requested by the client\nWorking with the team to help manage influencer collaborations \u2013 including identifying influencers to work with, developing creative ideas for the collaboration, liaison with influencers and their agents to arrange activity and measurement and reporting of campaign success\nReport creation and management \u2013 including weekly and monthly activity reporting, regular client updates and analysis of data to optimise future activity\nProposal research and support \u2013 including desktop research, social listening insights and reports, sourcing for best practice case studies, brainstorming\nCommunity management of social media channels \u2013 including proactive and reactive engagement with fans, responding to customer service enquiries, identifying and engaging with superfans and building rapport with those core fans, and identifying and selecting the best user-generated content for re-sharing.\u00a0", "employment_types": ["Full Time", "Part Time", "Permanent"], "selling_points": ["Oversee office administration", "Provide secretarial support", "Co-ordinate internal and external meetings"], "locations": ["Tsim Sha Tsui"], "categories": ["Admin & HR", "Personal / Executive Assistant", "Media & Advertising", "Account Servicing", "Professional Services", "Company Secretary"], "post_time": "2022-01-10T14:03:10Z", "salary": {"currency": null, "max": null, "min": null, "period": "monthly", "term": null}, "salary_visible": false, "title_keywords": ["executive assistant"], "responsibilities": ["data", "social media platforms", "quality", "communication", "customer service", "social media content", "facebook", "advertising", "ad hoc", "measurement", "developing", "develop", "reports", "report", "social media", "management", "reporting", "customer enquiries", "scheduling", "campaign management", "creative ideas", "analysis"], "requirements": {"degrees": [], "majors": [], "languages": ["mandarin chinese", "english"], "language_level": ["excellent"], "hard_skills": ["excel", "plus", "basic", "analysis", "word", "writing skills", "powerpoint", "mobile", "computer skills", "facebook", "focus", "wan", "photoshop"], "soft_skills": ["capable", "can-do attitude", "writing skills", "communication", "customer service", "hard-working", "focus", "team player", "time management", "confident", "creative", "communication skills", "unique", "enthusiastic", "driven", "positive", "self-motivated", "presentation skills", "motivated", "learning", "organisation", "organised", "proactive"], "languages_combined": [{"language": "mandarin chinese", "language_level": []}, {"language": "english", "language_level": ["excellent"]}]}, "experience_required": {"duration": [], "field": ["social media", "management", "brand", "agency", "content creation"]}}, {"job_id": "100003009021261", "location_code": "hk", "company": "IPG Mediabrands (HK) Limited", "job_title": "Digital Manager / Assistant Digital Manager", "description": "KEL LI ART GALLERY(Top 10 wedding photographer) combines photojournalism & aesthetics in wedding photography. Yes wedding is a happy and fun industry, that's why we smile a lot! Life's meaningless if you can't do what you love. Isn't it?\n\n\nJob\n\nTaking good care of potential clients to actual clients\nHandling daily enquiry\nMeeting clients\nSocial media management\nCoordinate with vendors and partners\nAdministrative work\n\n\n\nRequirements\n\nPhotography lover\nFriendly & outgoing\nGood command of English & Chinese\nSelf-motivated, disciplined and hardworking\nEnjoy working in wedding industry\nKnowledge in digital marketing\n\n\nExperience in customer service is a must. Interested candidates please send your resume.", "employment_types": ["Full Time"], "selling_points": [], "locations": ["Quarry Bay"], "categories": ["Media & Advertising", "Account Servicing", "Strategic Planning", "Marketing / Public Relations", "Marketing - Marketing Communication"], "post_time": "2022-01-05T03:28:59Z", "salary": {"currency": null, "max": null, "min": null, "period": "monthly", "term": null}, "salary_visible": false, "title_keywords": ["manager", "assistant"], "responsibilities": ["social media", "management", "administrative work", "coordinate with", "customer service", "digital marketing"], "requirements": {"degrees": [], "majors": [], "languages": ["english", "chinese"], "language_level": ["good command"], "hard_skills": ["fun"], "soft_skills": ["outgoing", "self-motivated", "enjoy working", "customer service", "friendly", "hardworking"], "languages_combined": [{"language": "english", "language_level": ["good command"]}, {"language": "chinese", "language_level": ["good command"]}]}, "experience_required": {"duration": [], "field": ["customer service"]}}, {"job_id": "100003009033223", "location_code": "hk", "company": "Vpon HK Limited", "job_title": "Senior/ Business Executive", "description": "TFI is a technology company who is a leading one-stop video solutions provider based in Hong Kong, with global footprints. We focuses on enterprise solutions with Video Technology, Machine Learning and Big Data Analytics.\u00a0\u00a0As a pioneer in video technology, TFI strives to empower its clients to take up business transformation journey, creates remarkable business value to drive business growth.\n\nWe are expanding and looking for candidates who have technical background and interested in a client facing role to support\u00a0a\u00a0high quality live streaming and web conferencing solution (www.hermeslive.com).\n\n**We offer training for potential candidate to pick up technical knowledge and operations\nOur clients: https://www.tfidm.com/hk/en/clients\n\n\n\nWhat you will do\n\nProject planning, account servicing,\u00a0resource management, change management and delivery of multiple projects.\nEstablishing live streaming opportunity with potential client, stimulate business and sales activities.\nCoordinate and arrange online live streaming event solution design and production in outside venues (e.g. conference room, exhibition hall and other performing venues) or in-house studio, including:\nArrange site-surveys with clients, external producers and camera crew, event venue owner, IT network technicians, Internet Service Provider (ISP) and other related parties.\nLiaise with related parties to prepare graphic design and media assets, equipment logistics and requirement and production/ programme rundown.\nPrepare production plan, solution design and technical operation documents.\nMonitor, record, document and evaluate the performance and output qualities of online live streaming events during/after rehearsals and outside broadcast productions.\nPerform system backup and post-production work such as content editing and transcoding recorded live feed into video archive if necessary.\nAssist in-house product development of HERMES Live (http://www.hermeslive.com)\u00a0a broadcast quality online live streaming technology product) on areas such as requirement formulation, product testing and quality control.\nIrregular and outdoor work may be required.\n\nWhat you need for this position\n\nDegree or above in Technical Arts, Broadcasting, Digital Media, Computer Science or other related disciplines\nExperience in Digital Media / Broadcast / Production Industry / Project Management and/or Technical Roles\nGood problem solving skills and communication skills\nExperience and knowledge of modern multimedia, show control technologies, computer programming, networking, AV equipment and/or 3D graphics would be an advantage\n\nInterested applicants please send full CV with expected salary and availability to us.\n\nFor better understanding of our company, you can visit our\u00a0Website\u00a0or connect us at\u00a0LinkedIn\n\n\nCompany Location: Kowloon Tong\nBenefits: Medical Allowance, Birthday and Childcare Leave", "employment_types": ["Full Time", "Permanent"], "selling_points": ["3 years of online media/ agency sales exp.", "Strong self-motivation", "Excellent communication and project coordination"], "locations": ["Quarry Bay"], "categories": ["Media & Advertising", "Account Servicing", "Sales, CS & Business Devpt", "Business Development", "E-commerce", "Business Development"], "post_time": "2022-01-08T17:13:09Z", "salary": {"currency": null, "max": null, "min": null, "period": "monthly", "term": null}, "salary_visible": false, "title_keywords": ["business executive"], "responsibilities": ["quality", "big data"], "requirements": {"degrees": [], "majors": [], "languages": [], "language_level": [], "hard_skills": ["data analytics", "web conferencing"], "soft_skills": ["interested in", "learning"], "languages_combined": []}, "experience_required": {"duration": [], "field": []}}, {"job_id": "100003009023681", "location_code": "hk", "company": "Pigture Creations Limited", "job_title": "Account Manager / Senior Account Executive", "description": "\u5de5\u4f5c\u7bc4\u570d\uff1a\n\n\u5fae\u4fe1\u7fa4\u3001\u516c\u773e\u865f\u3001Facebook\u3001IG \u7dda\u4e0a\u5e73\u53f0\u7ba1\u7406\nMicrosoft office\u3001\u77ed\u7247\u88fd\u4f5c\u3001\u6d77\u5831\u8a2d\u8a08\n\u884c\u653f\u4fdd\u55ae\u7ba1\u7406\u5165\u8077\u884c\u653f\u6d3b\u52d5\n\u7c4c\u8fa6\u57f9\u8a13\u3001\u62db\u52df\u3001\u516c\u958b\u6d3b\u52d5\n\u5718\u968a\u696d\u7e3e\u5831\u544a\u8ffd\u8e2a\u6210\u54e1\u696d\u7e3e/\u734e\u9805\n\n\n\u8cc7\u6b77:\n\n\u719f\u6089\u4f7f\u7528\u7167\u7247\u548c\u8996\u983b\u7de8\u8f2f\u8edf\u9ad4\uff0c\u5177\u5099\u651d\u5f71\u7d93\u9a57\u70ba\u4f73;\n\u7cbe\u901a\u6587\u66f8\u8655\u7406\uff0c\u6587\u7b46\u6d41\u66a2;\n\u80fd\u66f8\u5beb\u53ca\u64cd\u6d41\u5229\u5ee3\u6771\u8a71\uff0c\u00a0\u82f1\u8a9e\u548c\u666e\u901a\u8a71;\n\u6b61\u8fce\u65b0\u7562\u696d\u751f\u61c9\u5fb5\n\n\u5de5\u4f5c\u6642\u9593\uff1a\n\n\u661f\u671f\u4e00\u81f3\u4e94 9:30-17:30\n\u9999\u6e2f\u6cd5\u5b9a\u7bc0\u5047\u65e5\u4f11\u606f\n\u5f85\u9047\uff1a\n\n$65-$85/\u5c0f\u6642\uff08\u8996\u4e4e\u5de5\u4f5c\u7d93\u9a57\u800c\u5b9a\uff09\n\u5982\u5c0d\u8077\u4f4d\u6709\u8208\u8da3\u8acb\"APPLY\"", "employment_types": ["Full Time", "Permanent"], "selling_points": ["Work in digital marketing industry", "Competitive compensation", "Fun and flexible working environment"], "locations": ["Tsuen Wan Area"], "categories": ["Media & Advertising", "Account Servicing", "Creative / Design", "Photography / Video"], "post_time": "2022-01-05T09:27:49Z", "salary": {"currency": null, "max": null, "min": null, "period": "monthly", "term": null}, "salary_visible": false, "title_keywords": ["senior account executive", "account manager"], "responsibilities": [], "requirements": {"degrees": [], "majors": [], "languages": [], "language_level": [], "hard_skills": [], "soft_skills": [], "languages_combined": []}, "experience_required": {"duration": [], "field": []}}, {"job_id": "100003009025397", "location_code": "hk", "company": "EternityX Marketing Technology Limited", "job_title": "Digital Marketing- Senior/ Account Executive", "description": "About Us\n\n\nHi, we are [\u2018mediPr], a young, dynamic and fast-growing medical communications agency. We help pharmaceutical companies, clinics, and other medical organisations with event management, content creation, and video production.\u00a0\n\nWe are growing, and looking for a self-motivated account manager to join our team. In return, we offer an excellent commission system.\u00a0\n\nJob Overview\n\nInterested to join our young and growing team? We are looking for a bright personality who is customer focused and with a strong sense of responsibility. You enjoy the challenge of finding business opportunities with existing and new clients, you are keen to meet business targets, and you thrive when you can communicate and work with your colleagues to deliver a product within budget, scope, and timelines.\u00a0\n\nResponsibilities and Duties\n\nB2B sales;\nGenerate sales strategies and achieve sales targets;\nDevelop and explore business and marketing opportunities within the pharmaceutical and medical devices industry as well as clinics and healthcare organisations;\nMaintain a good relationship with existing and new clients within the pharmaceutical and medical devices industries as well as with healthcare providers;\nProject management, liaise with internal team members to ensure project deliverables are of high quality and met within budget and timelines.\n\nQualifications\n\nYou hold a bachelor\u2019s degree, or higher. Candidates with prior sales or accounts experience within the pharmaceutical industry or for a medical communications agency are preferred.\n\nPersonal Characteristics and Skills Required\n\nYou are proactive and punctual with customer-focused attitude, problem-solving mentality, and a strong sense of responsibility and business acumen;\nYou are self-motivated with the ability to work independently and in a team environment;\nYou are outgoing and persuasive with good communication and presentation skills;\nYou are a permanent resident of Hong Kong, native in Cantonese, proficient in English. Spoken Mandarin is a positive.\n\nWhat we Offer\n\nAn excellent and competitive package consisting of basic salary plus tiered commission;\nAn opportunity to grow and help grow. We are growing the company, the successful candidate is offered an option to grow with us;\nA five-day workweek with an excellent work-life balance.\u00a0\n\nReporting Line\n\nThe successful incumbent will report to the Director of\u00a0[\u2018mediPr].\n\nProcess\n\nPlease submit your resume, cover letter, and current and desired salary. Candidates who do not hear back from Company within two (2) weeks after submission of the documents may consider their application to be unsuccessful.\u00a0", "employment_types": ["Full Time", "Permanent"], "selling_points": ["Uncapped Quarterly Commission + Performance Bonus", "Opportunity To Work In A Multi-Cultural Team", "Professional Training in China & Global Digi. Mkt"], "locations": ["Sheung Wan"], "categories": ["Media & Advertising", "Account Servicing", "Marketing / Public Relations", "Marketing - General / Support", "Digital Marketing"], "post_time": "2022-01-06T04:22:01Z", "salary": {"currency": null, "max": null, "min": null, "period": "monthly", "term": null}, "salary_visible": false, "title_keywords": ["account executive", "digital marketing"], "responsibilities": [], "requirements": {"degrees": [], "majors": [], "languages": [], "language_level": [], "hard_skills": [], "soft_skills": [], "languages_combined": []}, "experience_required": {"duration": [], "field": []}}, {"job_id": "100003009021363", "location_code": "hk", "company": "Cheil Hong Kong Limited", "job_title": "Account Executive / Senior Account Executive (ATL & digital advertising)", "description": "Responsibilities\n\nProvide personal assistance to CEO as required\nAssist with record keeping, payment and accounting services\nManage\u00a0correspondence and\u00a0schedule appointments\n\nRequirements\n\nHard-working\nPrior experience is an advantage but not a necessity\nManagement accounting knowledge and experience required\nExcellent in Microsoft Office (MS Word, Excel, PowerPoint)\nWell-organized, self-motivated and able to work independently\nExcellent command of verbal and written English and Chinese (Mandarin a plus)\n\nJob Offer\n\nAttractive package", "employment_types": ["Full Time"], "selling_points": ["At least 1 year experience", "Digital & ATL marketing", "More experience can be considered as SAE"], "locations": ["Sheung Wan"], "categories": ["Media & Advertising", "Account Servicing", "Others", "Marketing / Public Relations", "Marketing - General / Support"], "post_time": "2022-01-05T03:45:31Z", "salary": {"currency": null, "max": null, "min": null, "period": "monthly", "term": null}, "salary_visible": false, "title_keywords": ["account executive", "senior account executive"], "responsibilities": ["payment", "schedule"], "requirements": {"degrees": [], "majors": [], "languages": ["english", "chinese", "mandarin"], "language_level": ["excellent"], "hard_skills": ["excel", "plus", "microsoft office", "powerpoint", "ms word"], "soft_skills": ["self-motivated", "hard-working", "well-organized", "work independently"], "languages_combined": [{"language": "english", "language_level": ["excellent"]}, {"language": "chinese", "language_level": ["excellent"]}, {"language": "mandarin", "language_level": ["excellent"]}]}, "experience_required": {"duration": [], "field": ["management accounting"]}}, {"job_id": "100003009025180", "location_code": "hk", "company": "Wave Insight Limited", "job_title": "Account Manager / Senior Sales Manager (Media Advertising)", "description": "Responsibilities\u00a0\u00a0\n\n\nPropose creative ideas into integrated digital marketing campaign for developing strategies and new clients\nAnalyze information on market trends, business and competitive activities for marketing report\nPrepare\u00a0social media AD performance report and present to clients once per month\nBuild relationships and maintain constant contact with key clients and marketers\nProvide professional services to major accounts\nBe motivated to take challenges and master multiple tasks in account servicing and project management in a timely and professional manner\nReliable management skill and need to manage the\u00a0production team\nManagement experience is preferred\u00a0\n\nRequirements\n\n\nHigher Diploma or above in Business, Advertising, Marketing, Communications, Information system, E-commerce, project management or related discipline\n2 years solid experience, experience in E-business will be an advantage\nExcellent communication, interpersonal and negotiation skills is a must\nCreative brainstorming, ambitious; self-starter; proactive and aggressive\nProficiency in MS office application\nPassionate and knowledgeable about digital marketing or advertising is preferred\nFresh graduates are welcome (Candidates with less experience will be considered as account executive)\n\nBenefits We Offer\n\n\n5-Day Work\nFlexible Working Hours\nOvertime Meal and Transportation allowance\nEducation Fund\nFree snacks and Drinks\u00a0\nFun, young and joyful environment with lots of social activities e.g. sport games, retreat, festivals\u2019 celebrations etc.\n\n* Personal data collected will be used for recruitment purpose only *", "employment_types": ["Full Time"], "selling_points": [], "locations": ["Kwun Tong"], "categories": ["Media & Advertising", "Account Servicing", "Strategic Planning", "Sales, CS & Business Devpt", "Account Servicing"], "post_time": "2022-01-06T03:44:13Z", "salary": {"currency": null, "max": null, "min": null, "period": "monthly", "term": null}, "salary_visible": false, "title_keywords": ["senior sales manager", "account manager"], "responsibilities": ["social media", "creative ideas", "management", "professional manner", "developing", "project management", "maintain", "digital marketing", "contact", "report"], "requirements": {"degrees": ["higher diploma or above"], "majors": ["e-commerce", "project management", "business", "marketing", "communications"], "languages": [], "language_level": [], "hard_skills": ["project management", "ms office", "information system", "e-commerce"], "soft_skills": ["passionate", "proactive", "communication", "project management", "negotiation skills", "creative", "interpersonal"], "languages_combined": []}, "experience_required": {"duration": ["2 years"], "field": ["business"]}}, {"job_id": "100003009029157", "location_code": "hk", "company": "Bliss Concepts Limited", "job_title": "Project Manager / Assistant Project Manager", "description": "We\u2019re Webs S\u2019 up, a digital consultancy with a singular mission \u2013 We Enhance Engagement.\u00a0\n\nJoin us to become a Webs S\u2019 up family member!\nYou will be entitled to a competitive salary and attractive staff benefits including:\n\nAnnual leave, paid sick leave, compensation leave, marriage leave, maternity leave, paternity leave and compassionate leave\nFive-day work week in Kowloon Bay Office\nComprehensive medical and dental coverage\nProfessional training and career advancement opportunities\nFriendly working environment\u00a0and work-life balance culture\nWhat do you need to do?\nIdentify new business opportunities including clients & customers to grow the sales\nRun sales and marketing operations, including price strategy, online campaigns and content management\nPlan and execute online advertising and retargeting\nResearch and support in marketing content production for an email newsletter and other social media channels\nHandle social media postings, communicate with influencers and promoting our brand and products\nProvide operational support in marketing and sales promotional campaigns to drive business and product awareness for other online platforms through self-owned platforms as well as online channels\nAssist in ad hoc duties when required\nWhat do you need to have?\nDegree holder in Digital Marketing/ e-commerce/ Advertising/ Business or related disciplines\n1-2 years working experience (Digital Marketing / Web Analytics)\nKnowledge of Digital Platforms (Web Analytics tools in Google is an advantage)\nPositive working attitude, independent, efficient, punctual, and well organized\nGood command of written and spoken English & Chinese; Mandarin is a must\nFamiliar with Microsoft Word, Excel, PowerPoint and Web savvy\nReady to join us? Apply now to submit your resume & expected salary to us!\n(Personal data will be used for Webs s\u2019 up Production Limited recruitment purposes only. We will retain the applications of candidates for no more than 12 months.)", "employment_types": ["Full Time", "Permanent"], "selling_points": ["5-day Work", "Creative Media and IP Industry", "Experience in Media/Marketing/Business Development"], "locations": ["Tin Hau"], "categories": ["Media & Advertising", "Account Servicing", "Sales, CS & Business Devpt", "Business Development"], "post_time": "2022-01-07T04:07:15Z", "salary": {"currency": null, "max": null, "min": null, "period": "monthly", "term": null}, "salary_visible": false, "title_keywords": ["project manager", "assistant project manager"], "responsibilities": [], "requirements": {"degrees": [], "majors": [], "languages": [], "language_level": [], "hard_skills": [], "soft_skills": [], "languages_combined": []}, "experience_required": {"duration": [], "field": []}}, {"job_id": "100003009025363", "location_code": "hk", "company": "VS Media Limited", "job_title": "Account Executive (Digital Media)", "description": "We thirst for more creative blood to join our growing team!\nWe value employee experience. We encourage Vponers to embrace an agile mindset and adapt to the high-speed business world.\n\nWhen Opportunity Knocks \u2013 Are You Ready to Step Through the Door?\n\nGet ready to meet dynamic business needs and changes in digital advertising, data, and internet industry.\nWhat you will be working on:\nAchieving\u00a0sales targets through developing and managing partner sales activities\nPitching clients with Vpon\u2019s local and cross-border programmatic advertising solutions, data analytic tools and business intelligent platforms\nHandling enquires from not only HK market, but also from markets where Vpon has regional offices, including Taiwan, Japan, Korea and South East Asia\nAchieving advertising and data targets through developing and managing partner sales activities\nProviding strategic advices to enable data-driven marketing capabilities\nProviding professional sales consultation and product presentation\nDeveloping strong client relationship and ensure successful relationship progression for potential business growth\nWorking with cross functional teams on project management, delivery, optimizations, changes and campaign set-up\n\nWhat can make you stand out in a competitive pool:\n\n\n3-5 years of digital or online media sales / agency sales experience\nStrong self-motivation and commitment to achieve sales target\nAble to work independently and work under pressure\nExcellent communication, project coordination, budgeting and planning skills\nless experienced candidates may be considered as Senior/ Business Executive", "employment_types": ["Full Time", "Permanent"], "selling_points": ["Digital Media, Media Buy", "Account Servicing, Project Management", "Advertising"], "locations": ["Kwun Tong"], "categories": ["Media & Advertising", "Account Servicing", "Media Buying", "Others"], "post_time": "2022-01-06T04:14:08Z", "salary": {"currency": null, "max": null, "min": null, "period": "monthly", "term": null}, "salary_visible": false, "title_keywords": ["account executive"], "responsibilities": ["sales activities", "advertising", "project coordination", "data", "budgeting", "sales target", "teams", "developing", "communication", "project management", "planning", "work under pressure"], "requirements": {"degrees": [], "majors": [], "languages": [], "language_level": [], "hard_skills": ["project management", "make", "dynamic", "agile"], "soft_skills": ["planning skills", "work independently", "agile", "driven", "communication", "project management", "dynamic", "self-motivation", "coordination", "creative", "presentation", "work under pressure"], "languages_combined": []}, "experience_required": {"duration": ["3-5 years"], "field": ["agency", "digital", "media sales"]}}, {"job_id": "100003009027689", "location_code": "hk", "company": "Go In Marketing", "job_title": "Ecommerce & Marketing Executive", "description": "Qualifications\uff1a\nTake a leadership role for the clients under your care\nUnderstand your customers\u2019 businesses objectives in order to support their brand building goals\nDeep understanding of brand building discipline and industry best practices\nDeliverables on brief with high degree of client satisfaction\nDraft effective proposals\u00a0\nAchieve revenue targets\nMaintain consistently high standards in the work delivered\nEffective delegation and oversight of the team involved in your projects\nEfficiently manage day-to-day operations for a portfolio of clients\nPrepare desktop research, proposals, presentations, schedules, quotations, invoices\nMaintain healthy working relationships with clients and colleagues\u00a0\u00a0\nRequirements:\n\nUniversity degree, preferably in Marketing / Communication / Advertising or related discipline\nPassionate and proactive team player with pleasant personality\nSelf-starter and able to adapt to a fast-paced environment with tight deadline\nOrganized and attention to details\nGood communication and written skills in English, Cantonese and Mandarin\nExperience in 4As creative agencies and/or digital agencies will be a definite advantage", "employment_types": ["Full Time"], "selling_points": ["Fresh graduates are welcome", "Five-day work week", "Knowledge of Mailchimp& Google Analytics is a plus"], "locations": ["Lai Chi Kok"], "categories": ["Media & Advertising", "Account Servicing", "Marketing / Public Relations", "Digital Marketing", "E-commerce", "Marketing - Brand / Product Management"], "post_time": "2022-01-07T06:03:56Z", "salary": {"currency": null, "max": null, "min": null, "period": "monthly", "term": null}, "salary_visible": false, "title_keywords": ["marketing executive"], "responsibilities": ["advertising", "invoices", "schedules", "day-to-day operations", "presentations", "communication", "maintain", "working relationships"], "requirements": {"degrees": ["university degree", "degree"], "majors": ["marketing"], "languages": ["cantonese", "english", "mandarin"], "language_level": ["good"], "hard_skills": ["presentations"], "soft_skills": ["passionate", "organized", "creative", "fast-paced environment", "deep", "pleasant", "communication", "attention to details", "team player", "proactive", "leadership"], "languages_combined": [{"language": "cantonese", "language_level": ["good"]}, {"language": "english", "language_level": ["good"]}, {"language": "mandarin", "language_level": ["good"]}]}, "experience_required": {"duration": [], "field": ["digital"]}}]