[{"job_id": "100003009053712", "location_code": "hk", "company": "Iyuno Hong Kong Limited", "job_title": "Audio Video Editor | Media Technician | Transform Operator | 1+ yr exp", "description": "Job Overview\nThe Media Technician / Media Transform Operator is responsible for potential audio/video editing for client delivery, proxy file creation for subtitle and caption file creation, and media specs identification and troubleshooting\nPrinciple Duties & Responsibilities\nEncode audio/video assets from any available source asset to specification using the prescribed workflows and equipment\nPerform audio/video editing, layback and standards conversion using the prescribed workflows and equipment\nPerform delivery of assets via accelerated digital delivery mechanisms using the prescribed workflows and equipment\nMaintain an up to the minute accurate account of production and task status in our job management systems\nMust be able to demonstrate:\nDemonstrate the ability to multitask\nDemonstrate the ability to detect audio video errors\nUnderstanding of encoders and transcoders\nUnderstanding of \u201cNon Linear Editors\u201d\nUnderstanding of digital file transport services\n\u00a0Requirements\nAudio/Video certifications/degrees preferred or equivocal work experience\nSubject to proficiency test related to digital media\nKnowledge and experience in Adobe Premiere, Photoshop\nShift duty is required\nApplication Interested parties please send your application with full CV including current and expected salary and availability by clicking below icon\u00a0\"Apply Now\".\nAll personal information will be treated strictly confidential and solely for recruitment purpose.", "employment_types": ["Full Time", "Temporary", "Contract"], "selling_points": [], "locations": ["Kowloon Bay"], "categories": ["Media & Advertising", "Production", "Broadcasting - TV / Radio", "Photography / Video"], "post_time": "2022-01-17T07:23:39Z", "salary": {"currency": null, "max": null, "min": null, "period": "monthly", "term": null}, "salary_visible": false, "title_keywords": ["operator", "technician", "video editor"], "responsibilities": ["management", "systems", "video editing", "maintain", "audio"], "requirements": {"degrees": [], "majors": [], "languages": [], "language_level": [], "hard_skills": ["adobe premiere", "photoshop"], "soft_skills": [], "languages_combined": []}, "experience_required": {"duration": [], "field": ["video"]}}, {"job_id": "100003009054849", "location_code": "hk", "company": "Manner Production Limited", "job_title": "Director \u5c0e\u6f14", "description": "Job Highlights\n\nFun, young, and joyful working environment\nCreate ideas & improve designs for Manner Group\nCoordinate with art and creative team\n\nResponsibilities:\n\nCopywriting or creating content and script for social media platforms\nHandle production and sales project and creative, pre-production, on location shooting and post-production;\nWork with Director and Production team to make sure project on time and within budget;\nTime management, able to meet tight deadlines and work independently under pressure in fast paced environment;\nKeep the team in a good production atmosphere\nRequirements:\n\nThree to five years of the production company or producer experience is preferred;\nAble to plan independently, to coordinate, organize, and screen projects, and be familiar with the program production process;\nWork experience in online marketing, social media group will be preferred;\nKnowledge of production software; after Effects, Photoshop and Illustrator etc.;\nHave a passion for the Internet or film industry, with enthusiasm, initiative, team awareness and coordination and strong resistance;\nWork with Production Team\n\n\u8077\u4f4d\u8981\u6c42:\n\n\u81f3\u5c11\u4e09\u81f3\u4e94\u5e74\u4ee5\u4e0a\u88fd\u4f5c\u516c\u53f8\u5275\u4f5c\u7d93\u9a57; \u7368\u7acb\u7d71\u7c4c\uff0c\u5275\u4f5c\u5f71\u7247\u5305\u62ec\u524d\u4e2d\u5f8c\u671f\u88fd\u4f5c\uff1b\u7be9\u9078\u9805\u76ee; \u719f\u6089\u88fd\u4f5c\u6d41\u7a0b\uff0c\u6709\u8c50\u5bcc\u5f71\u8996\u88fd\u4f5c\uff0c\u51dd\u805a\u5718\u968a\uff0c\u6709\u61c9\u8b8a\u80fd\u529b\u8655\u7406\u7a81\u767c\u5371\u6a5f\uff0c\u5354\u4f5c\u5287\u672c\u548c\u62cd\u651d\u8981\u6c42\u7b56\u5283\u62cd\u651d.\n\nTo apply, please send us your resume / CV to us.\u00a0Personal data collected will be used for recruitment purposes only.", "employment_types": ["Full Time"], "selling_points": ["Work with Manner creative team", "Opportunity to work with production team and KOLs", "Harmonious and funny working environment"], "locations": ["Causeway Bay"], "categories": ["Media & Advertising", "Production", "Editorial / Journalism", "Broadcasting - TV / Radio"], "post_time": "2022-01-17T12:15:57Z", "salary": {"currency": null, "max": null, "min": null, "period": "monthly", "term": null}, "salary_visible": false, "title_keywords": ["director"], "responsibilities": ["pre-production", "management", "social media platforms", "budget"], "requirements": {"degrees": [], "majors": [], "languages": [], "language_level": [], "hard_skills": ["after effects", "illustrator", "photoshop"], "soft_skills": ["independently", "initiative", "coordination", "passion for"], "languages_combined": []}, "experience_required": {"duration": ["three to five years"], "field": ["social media", "marketing"]}}, {"job_id": "100003009045783", "location_code": "hk", "company": "\u96fb\u8996\u5ee3\u64ad\u6709\u9650\u516c\u53f8 (TVB)", "job_title": "\u52a9\u7406\u7de8\u5c0e \u2013 \u6232\u5287\uff08\u5408\u7d04\uff09", "description": "Tape Library Department\nTo be responsible for\u00a0handling library material; assisting in data processing, archive management and managing all type of media; assisting to solve music copyright enquiries and the digitization project; performing ad-hoc tasks assigned by supervisor\nForm 5 or above with minimum 1 year relevant working experience\nGood command of both spoken and written English & Chinese\nFamiliar with Chinese word processing is a must\nAble to work independently on roster duty and work under pressure in a fast-paced\nKnowledge of Microsoft Office and copyright\nKnowledge in music and library relevant matters are preferred\nImmediate available is highly preferable\nWe offer 5-day work week, competitive remuneration packages and advancement opportunities. Interested parties, please write with full resume to Director, Human Resources, Human Resources Department, i-CABLE Communications Limited, 4/F Cable TV Tower, 9 Hoi Shing Road Tsuen Wan, N.T. or fax to 2112 7841 or via Apply Now (Please quote reference number and position applied for). For other information, please visit our website http://www.i-cable.com.\n\nYour application may be forwarded to any affiliate companies\u00a0and successful applicant may be seconded to work at any office as assigned.\u00a0 The information received will be used for consideration of employment only and all personal data supplied will be destroyed within 3 months.\n\nWe are an equal opportunity employer.", "employment_types": ["Full Time", "Contract"], "selling_points": [], "locations": ["Others"], "categories": ["Media & Advertising", "Production", "Broadcasting - TV / Radio", "Photography / Video"], "post_time": "2022-01-17T02:51:06Z", "salary": {"currency": null, "max": null, "min": null, "period": "monthly", "term": null}, "salary_visible": false, "title_keywords": [], "responsibilities": ["work under pressure", "management", "ad-hoc tasks", "data processing"], "requirements": {"degrees": ["form 5 or above"], "majors": [], "languages": ["english", "chinese"], "language_level": ["good command"], "hard_skills": ["processing", "chinese word processing", "microsoft office"], "soft_skills": ["work independently", "responsible", "work under pressure"], "languages_combined": [{"language": "english", "language_level": ["good command"]}, {"language": "chinese", "language_level": ["good command"]}]}, "experience_required": {"duration": ["minimum 1 year"], "field": ["relevant working experience"]}}, {"job_id": "100003009054167", "location_code": "hk", "company": "i-CABLE Communications Limited", "job_title": "Assistant Librarian", "description": "\u57f7\u884c\u524d\u671f\u88fd\u4f5c\u5982\uff1a\u7de8\u6392\u62cd\u651d\u7a0b\u5e8f\uff0c\u7d71\u7c4c\u62cd\u651d\u6240\u9700\u7684\u8cc7\u6e90\uff0c\u5982\u5834\u5730\u3001 \u6f14\u54e1\u3001\u670d\u88dd\u3001\u5316\u599d\u7b49\n\u5354\u52a9\u62cd\u651d\u5de5\u4f5c\u53ca\u8a18\u9304\u6709\u95dc\u8cc7\u6599\n\u53c3\u8207\u5f8c\u671f\u88fd\u4f5c\u5982\u526a\u63a5\u3001\u914d\u97f3\u7b49\n\u4e2d\u4e94\u7562\u696d\u800c\u5177\u5099\u5169\u81f3\u4e09\u5e74\u5de5\u4f5c\u7d93\u9a57\u6216\u5177\u5099\u5927\u5b78\u6216\u5927\u5c08\u7a0b\u5ea6\n\u5177\u826f\u597d\u7d44\u7e54\u80fd\u529b\u53ca\u4eba\u969b\u6280\u5de7\n\u80fd\u64cd\u6d41\u5229\u5ee3\u6771\u8a71\n\u9858\u610f\u4e0d\u5b9a\u6642\u5de5\u4f5c\n\n\u8acb\u8a73\u8ff0\u8cc7\u6b77\u53ca\u7d93\u9a57\u3001\u73fe\u6642\u53ca\u8981\u6c42\u85aa\u91d1\u3001\u806f\u7d61\u96fb\u8a71\uff0c\u4e26\u8a3b\u660e\u8077\u4f4d\u7de8\u865f\uff0c\u5bc4\u9999\u6e2f\u4e5d\u9f8d\u5c07\u8ecd\u6fb3\u5de5\u696d\u90a8\u99ff\u624d\u885777\u865f\u96fb\u8996\u5ee3\u64ad\u57ce\uff0c\u96fb\u8996\u5ee3\u64ad\u6709\u9650\u516c\u53f8\uff0c\u4eba\u4e8b\u79d1\u9ad8\u7d1a\u7d93\u7406\u6536\u3002\n\n\u7533\u8acb\u4eba\u6240\u63d0\u4f9b\u7684\u8cc7\u6599\u7d55\u5c0d\u4fdd\u5bc6\uff0c\u4e26\u53ea\u4f5c\u8077\u4f4d\u7504\u9078\u7528\u9014\u3002\u672a\u7372\u53d6\u9304\u7684\u7533\u8acb\u4eba\uff0c\u5176\u8cc7\u6599\u6703\u65bc\u56db\u661f\u671f\u5f8c\u5b58\u6a94\uff0c\u96c6\u5718\u5167\u5982\u6709\u5176\u4ed6\u8077\u4f4d\u7a7a\u7f3a\u6642\uff0c\u672c\u516c\u53f8\u6703\u63a8\u85a6\u5408\u9069\u7533\u8acb\u4eba\u4e88\u4ee5\u8003\u616e\u3002\u7533\u8acb\u4eba\u7684\u8cc7\u6599\u53ea\u6703\u4fdd\u5b58\u4e09\u500b\u6708\uff0c\u671f\u6eff\u92b7\u6bc0\u3002", "employment_types": ["Full Time", "Permanent"], "selling_points": [], "locations": ["Tsuen Wan Area"], "categories": ["Media & Advertising", "Production", "Editorial / Journalism", "Broadcasting - TV / Radio"], "post_time": "2022-01-17T08:38:32Z", "salary": {"currency": null, "max": null, "min": null, "period": null, "term": null}, "salary_visible": false, "title_keywords": ["assistant"], "responsibilities": [], "requirements": {"degrees": [], "majors": [], "languages": [], "language_level": [], "hard_skills": [], "soft_skills": [], "languages_combined": []}, "experience_required": {"duration": [], "field": []}}, {"job_id": "100003009054398", "location_code": "hk", "company": "i-CABLE Communications Limited", "job_title": "Media Librarian", "description": "Responsible for data input and website video editing\nSecondary school graduate or above, no relevant experience is required\nKnowledge of Photoshop, After Effects, Motion, FCPX is preferable\nFamiliar with Chinese word processing, at least 25 w.p.m.\nNight shift and rotated rest day are required\n(Those with more experience will be considered as Video Editor)\n\n\nApplication Method\n\n\nWe offer 5-day work week, free shuttle bus, free parking and fringe benefits including medical scheme, discretionary bonus and public holidays\u00a0to the right candidate. Interested parties, please send full resume with expected salary to ORIENTAL HUMAN RESOURCES LIMITED\u00a0by\u00a0clicking \"Apply now\" ;\u00a0or fax to 3600 1900 ( Please quote reference on the application letter )\n\n\nPersonal Information Collection Statement\n\nPersonal data collected will be treated in accordance with our Personal Data Policy and handled in strict confidence by authorized personnel for recruitment related purpose only.\u00a0 \u00a0 \u00a0\n\u00a0 \u00a0 \u00a0 \u00a0 \u00a0 \u00a0\n\n\u00a0 \u00a0 \u00a0 \u00a0 \u00a0 \u00a0 \u00a0 \u00a0 \u00a0 \u00a0 \u00a0 \u00a0 \u00a0 \u00a0 \u00a0 \u00a0 \u00a0 \u00a0 \u00a0 \u00a0 \u00a0 \u00a0 \u00a0 \u00a0 \u00a0 \u00a0 \u00a0\u00a0on.cc\n\n", "employment_types": ["Full Time", "Permanent"], "selling_points": [], "locations": ["Tsuen Wan Area"], "categories": ["Media & Advertising", "Production", "Editorial / Journalism", "Broadcasting - TV / Radio"], "post_time": "2022-01-17T09:22:04Z", "salary": {"currency": null, "max": null, "min": null, "period": null, "term": null}, "salary_visible": false, "title_keywords": [], "responsibilities": ["video editing", "data input", "website"], "requirements": {"degrees": [], "majors": [], "languages": ["chinese"], "language_level": [], "hard_skills": ["no", "chinese word processing", "scheme", "video editing", "after effects", "photoshop"], "soft_skills": ["responsible"], "languages_combined": [{"language": "chinese", "language_level": []}]}, "experience_required": {"duration": [], "field": ["editor", "video", "relevant experience"]}}, {"job_id": "100003009010878", "location_code": "hk", "company": "Television Broadcasts Limited (TVB)", "job_title": "Principal Subeditor (Pearl)", "description": "TVB News is inviting applications for a Principal Sub-Editor position for the English (Pearl) news desk.\n\n\nResponsibilities\n\n\nEdit and re-write local news stories and features\nWrite international news stories with voice over (based on wired stories)\nSupport the managing editor in editorial operations\nRequirements\n\nUniversity degree holder with at least 10 years\u2019 solid experience\nExcellent command of written and spoken English\nKnowledge of Cantonese not essential but would be an advantage\nShift duty is required \u00a0\nPlease send the application, quoting the appropriate reference number, with details of your qualifications and experience, expected salary and a contact telephone number to The Senior\u00a0Manager, Personnel Department,\u00a0Television Broadcasts Limited, TVB City, 77 Chun Choi Street, Tseung Kwan O Industrial Estate, Tseung Kwan O, Kowloon or email to us via Recruitment Centre.\n\n\nApplications received are solely for selection purpose. Those not invited for an interview within 4 weeks may consider their applications unsuccessful and their applications will be filed for another 3 months for future selection. Afterwards, all applications would be destroyed.", "employment_types": ["Full Time", "Permanent"], "selling_points": [], "locations": ["Others"], "categories": ["Media & Advertising", "Editorial / Journalism", "Broadcasting - TV / Radio"], "post_time": "2022-01-17T06:29:22Z", "salary": {"currency": null, "max": null, "min": null, "period": "monthly", "term": null}, "salary_visible": false, "title_keywords": [], "responsibilities": ["operations"], "requirements": {"degrees": ["university degree"], "majors": [], "languages": ["cantonese", "english"], "language_level": ["advantage", "excellent"], "hard_skills": [], "soft_skills": [], "languages_combined": [{"language": "cantonese", "language_level": ["advantage"]}, {"language": "english", "language_level": ["excellent"]}]}, "experience_required": {"duration": ["at least 10 years"], "field": ["recruitment"]}}, {"job_id": "100003009051586", "location_code": "hk", "company": "Medialink Entertainment Limited", "job_title": "Distribution Manager - Content", "description": "\u300c\u6bba\u624b\u597d\u523a\u6fc0\u5440\uff01\u5572\u6bba\u4eba\u5834\u9762\u9ede\u62cd\u35ce\uff1f\u300d\u00a0\n\n\u300c\u767d\u8272\u5f37\u4eba\u597d\u5c08\u696d\u5440\uff01\u5572\u624b\u8853\u5481\u771f\u5605\u2026\u300d\u00a0\n\n\u300c\u958b\u5fc3\u901f\u905e\u597d\u597d\u7747\u5440\uff01\u5927\u5c0f\u59d0\u771f\u4eba\u4fc2\u54aa\u90fd\u4fc2\u5481\u35ce\u2026.\u300d\u00a0\n\n\u4f60\u60f3\u5514\u60f3\u90fd\u53c3\u8207\u5176\u4e2d\uff0c\u6210\u70ba\u6211\u54cb\u9020\u5922\u8005\u5605\u4e00\u4efd\u5b50\u5462\uff1f\u800c\u5bb6\u6a5f\u6703\u553b\u5587\uff01\uff01\n\n\u5275\u85dd\u5c55\u624d\uff0c\u8aa0\u5fb5\u6232\u5287\u7d44\u52a9\u7406\u7de8\u5c0e\uff0c\u6b61\u8fce\u6709\u5fd7\u6295\u8eab\u96fb\u8996\u5287\u88fd\u4f5c\u884c\u5217\uff0c\u5fd7\u9858\u6210\u70ba\u7de8\u5c0e\u3001\u76e3\u88fd\u7684\u6709\u70ba\u9752\u5e74\u61c9\u5fb5\uff0c\u6211\u5011\u6703\u63d0\u4f9b\u5c08\u696d\u5728\u8077\u57f9\u8a13\uff0c\u66f4\u6709\u661f\u7d1a\u5c0e\u5e2b\u5206\u4eab\u62cd\u651d\u5fc3\u5f97\u3002\n\n\u5165\u8077\u9996\u8981\u689d\u4ef6\u8981\u71b1\u611b\u770b\u5287\u96c6\uff0c\u4e0d\u6015\u8271\u8f9b\uff0c\u80af\u535a\u80af\u6371\u3002\n\n\u300c\u96fb\u8996\u5922\u5de5\u5834\u300d\u6b63\u7b49\u8457\u4f60\u3002\n\n\u5de5\u4f5c\u7bc4\u7587\uff1a\n\n\u53c3\u8207\u96fb\u8996\u5287\u6574\u500b\u88fd\u4f5c\u904e\u7a0b\uff0c\u7531\u7c4c\u5099\u81f3\u5287\u96c6\u5b8c\u6210\uff0c\u7de8\u6392\u62cd\u651d\u7a0b\u5e8f\uff0c\u5b89\u6392\u6f14\u54e1\u3001\u8cc7\u6e90\u3001\u526a\u63a5\u3001\u914d\u97f3\u7b49\u7b49\u3002\n\n\u5165\u8077\u8981\u6c42\uff1a\n\n\u4e2d\u5b78\u7562\u696d\u6216\u4ee5\u4e0a\u7a0b\u5ea6\n\u5177\u5099\u826f\u597d\u7d44\u7e54\u80fd\u529b\u53ca\u6e9d\u901a\u6280\u5de7\n\u80fd\u64cd\u6d41\u5229\u5ee3\u6771\u8a71\n\u9858\u610f\u4e0d\u5b9a\u6642\u5de5\u4f5c\n\n\u8acb\u8a73\u8ff0\u8cc7\u6b77\u53ca\u7d93\u9a57\u3001\u73fe\u6642\u53ca\u8981\u6c42\u85aa\u91d1\u3001\u806f\u7d61\u96fb\u8a71\uff0c\u4e26\u8a3b\u660e\u8077\u4f4d\u7de8\u865f\uff0c\u5bc4\u9999\u6e2f\u4e5d\u9f8d\u5c07\u8ecd\u6fb3\u5de5\u696d\u90a8\u99ff\u624d\u885777\u865f\u96fb\u8996\u5ee3\u64ad\u57ce\uff0c\u96fb\u8996\u5ee3\u64ad\u6709\u9650\u516c\u53f8\uff0c\u4eba\u4e8b\u79d1\u9ad8\u7d1a\u7d93\u7406\u6536\u3002\n\n\u7533\u8acb\u4eba\u6240\u63d0\u4f9b\u7684\u8cc7\u6599\u7d55\u5c0d\u4fdd\u5bc6\uff0c\u4e26\u53ea\u4f5c\u8077\u4f4d\u7504\u9078\u7528\u9014\u3002\u672a\u7372\u53d6\u9304\u7684\u7533\u8acb\u4eba\uff0c\u5176\u8cc7\u6599\u6703\u65bc\u56db\u661f\u671f\u5f8c\u5b58\u6a94\uff0c\u96c6\u5718\u5167\u5982\u6709\u5176\u4ed6\u8077\u4f4d\u7a7a\u7f3a\u6642\uff0c\u672c\u516c\u53f8\u6703\u63a8\u85a6\u5408\u9069\u7533\u8acb\u4eba\u4e88\u4ee5\u8003\u616e\u3002\u7533\u8acb\u4eba\u7684\u8cc7\u6599\u53ea\u6703\u4fdd\u5b58\u4e09\u500b\u6708\uff0c\u671f\u6eff\u92b7\u6bc0\u3002", "employment_types": ["Full Time"], "selling_points": ["Min 3 years exp in media / content distribution", "Enthusiasm in Japanese Animation & Drama Series", "Familiar w/ international & Asian content markets"], "locations": ["Tsim Sha Tsui"], "categories": ["Media & Advertising", "Media Buying", "Production", "Broadcasting - TV / Radio"], "post_time": "2022-01-16T13:01:09Z", "salary": {"currency": null, "max": null, "min": null, "period": "monthly", "term": null}, "salary_visible": false, "title_keywords": ["manager"], "responsibilities": [], "requirements": {"degrees": [], "majors": [], "languages": [], "language_level": [], "hard_skills": [], "soft_skills": [], "languages_combined": []}, "experience_required": {"duration": [], "field": []}}, {"job_id": "100003009054086", "location_code": "hk", "company": "i-CABLE Communications Limited", "job_title": "Senior Visual Designer", "description": "We are Leading live streaming company in the world. Now we are looking for:\n\nEntertainment Talent Manager\n\nResponsibilities:\n\nPerform end-to-end recruitment of live streamer and KOL including sourcing, CV screening, interviewing, etc.\n\nAssist in streamers management, training, communication, coordination and casting\nMonitor, measure and review streamers\u2019 and KOL\u2019s performance timely\nCoordinating and liaising with marketing and operation teams for sales campaign\nConsolidate and prepare various streamers\u2019 and KOL\u2019s performance analytics reports and presentations for management review\nProvide on-site support during events or company promotions\n\nRequirements:\n\n1-2 years' relevant work experience in business development or similar field preferred\nSounds knowledgeable in entertainment trend and live streaming business\nSensitive on marketing trend and numbers\nExcellent communication and interpersonal skills with positive and \u201ccan-do\u201d attitudes\nAble to work independent, under pressure and adopt fast pace environment\nGood command in both written and spoken English, Chinese and Mandarin\nImmediate available will be an advantage\n\n\nWe Offer:\n\n\u00a0Basic Salary with Commission Package\nAttractive bonus or project bonus (depends on performance)\nFriendly and professional working environment\nExcellent career path\nWell-structured on-job training program\u00a0\n\nWelcome young, energetic and strong motivation candidates!\u00a0", "employment_types": ["Full Time", "Permanent"], "selling_points": [], "locations": ["Tsuen Wan Area"], "categories": ["Design", "Graphics", "Media & Advertising", "Editorial / Journalism", "Broadcasting - TV / Radio"], "post_time": "2022-01-17T08:21:10Z", "salary": {"currency": null, "max": null, "min": null, "period": null, "term": null}, "salary_visible": false, "title_keywords": ["designer"], "responsibilities": ["management", "cv screening", "review", "monitor", "liaising with", "teams", "presentations", "communication", "recruitment", "reports", "coordination", "management review"], "requirements": {"degrees": [], "majors": [], "languages": ["english", "chinese", "mandarin"], "language_level": ["good command"], "hard_skills": [], "soft_skills": ["independent", "under pressure", "communication and interpersonal skills", "can-do", "sensitive", "positive"], "languages_combined": [{"language": "english", "language_level": ["good command"]}, {"language": "chinese", "language_level": ["good command"]}, {"language": "mandarin", "language_level": ["good command"]}]}, "experience_required": {"duration": ["1-2 years"], "field": ["business development"]}}, {"job_id": "100003009049322", "location_code": "hk", "company": "Phoenix Satellite Television Co Ltd", "job_title": "Audio Operator", "description": "Key responsibilities\n\nContent Acquisition \u2013 Now TV Team:\n\nResponsible for the important role of \u00a0Asian content acquisition, primarily drama series, across Now TV and its affiliates\u2019 media services in Hong Kong.\nHeads up a team to manage all aspects of content acquisition and management including research, negotiation, contract drafting, viewership tracking, financial analysis and contract database maintenance.\nManage the programming and scheduling of exclusive Asian drama linear channels and on-demand services to ensure that they are popular with customers.\u00a0\nCollaborate with internal stakeholders such as Marketing, Product, Legal, Finance and Overseas business teams to align budgets and forecasts, programming plans, marketing and promotional activities as well as to drive content \u00a0engagement across all customer touchpoints.\nMonitor industry trends to drive strategic content decisions, formulate business plans and develop content strategies for both internal and external stakeholders.\n\nQualifications\n\nUniversity degree required with 8+ years of relevant work experience in the media industry or content acquisition / distribution fields and with 3+ years of supervisory experience.\nExperience in negotiations and ability to manage legal agreements and contracts.\u00a0\nRelevant knowledge of Asian drama market and industry trends.\nAbility to learn in fast-paced environment, prioritizing and balancing multiple projects and deadlines simultaneously.\nGreat interpersonal skills, business judgment, proven strategic thinking and problem solving skills.\nExcellent verbal and written communication skills\u00a0in Cantonese/ Mandarin/ English.\nPreferred proficiency in a foreign language such as \u00a0Japanese/Korean but not required.", "employment_types": ["Full Time", "Permanent"], "selling_points": [], "locations": ["Tai Po Area"], "categories": ["Media & Advertising", "Production", "Others", "Broadcasting - TV / Radio"], "post_time": "2022-01-14T08:28:18Z", "salary": {"currency": null, "max": null, "min": null, "period": null, "term": null}, "salary_visible": false, "title_keywords": ["operator"], "responsibilities": ["collaborate with", "budgets", "management", "maintenance", "contracts", "teams", "monitor", "business plans", "develop", "financial analysis", "scheduling", "communication", "promotional activities", "database", "plans", "multiple projects", "tracking"], "requirements": {"degrees": ["university degree"], "majors": [], "languages": ["cantonese", "english", "mandarin", "japanese", "korean"], "language_level": ["excellent", "proficiency"], "hard_skills": ["financial analysis", "programming", "problem solving skills", "maintenance"], "soft_skills": ["communication skills", "negotiation", "responsible", "strategic thinking", "fast-paced environment", "interpersonal skills", "problem solving skills", "prioritizing"], "languages_combined": [{"language": "cantonese", "language_level": ["excellent"]}, {"language": "english", "language_level": ["excellent"]}, {"language": "mandarin", "language_level": ["excellent"]}, {"language": "japanese", "language_level": ["proficiency"]}, {"language": "korean", "language_level": ["proficiency"]}]}, "experience_required": {"duration": ["8+ years", "3+ years"], "field": ["media", "legal", "supervisory experience"]}}, {"job_id": "100003009049329", "location_code": "hk", "company": "Phoenix Satellite Television Co Ltd", "job_title": "PRODUCER", "description": "Commercial Radio Interactive, a division of Commercial Radio Productions Limited and the digital arm of Commercial Radio, are looking for a passionate and energetic\u00a0System Administrator to join our IT team and develop his/her career under the guidance of our experienced senior staff.\n\n\n\nJob Duties\n\nInstalling, configuring, and maintaining Internet systems/services\nPerforming Linux (mainly)/Windows system administration\nDeveloping scripts for system automation\nDesign System Architecture and work with Application Development Team for overall solution\nResponsible for the whole network architecture maintenance, optimization, security, and troubleshooting\nConsistently working on system performance monitoring, tuning and enhancement\nCreating and maintaining technical documentation\n\nJob Requirements\n\n\nHands on experience in Linux/Unix production environment is MUST\nHands on experience on all of the following :\nLoad balancer LVS or HAProxy setup and configuration\nApache / Nginx / Tomcat / Jetty configuration and tuning\nMySQL DB setup, master/slave with no downtime synchronization setup\nDistributed Filesystem (CEPH / Swift / Hadoop)\nHigh availability and large scale service configuration\nVMWare vCenter management/Hyper-V management\nBash / Perl / Python scripting\nDNS, DHCP, FTP, Email\nFirewall, Switch, VPN, TCP/IP Networking\nZabbix / Cacti / Munin / Nagios or other monitoring tools\nAWS / Google VM & service deployment\nLive audio/video streaming support is an advance\nDegree holder in IT or related disciplines\nAt least 3 years experience in system administrator or support role.\nGood problem solving skills, pay attention to details and good communication skills\nResponsible, self motivated, work independently, and process tasks without supervision.\nWilling to work at non office hour for urgent production service support & maintenance.\nCandidate with more experience will be considered for the position of Senior System Administrator\n\nOffice location: Kowloon Tong\n\nApplication Procedure:\n\nWe offer attractive remuneration package, competitive salary, medical scheme and life insurance to the right candidate. Interested candidates, please submit application letter with full resume, present and expected salary by clicking \u201cApply Now\u201d (Please quote the job reference number on the e-mail subject line).\n\nAll information received will be kept in strict confidence and only for employment-related purpose. Only short listed candidates will be invited for interview.", "employment_types": ["Full Time", "Permanent"], "selling_points": [], "locations": ["Tai Po Area"], "categories": ["Media & Advertising", "Creative / Design", "Production", "Broadcasting - TV / Radio"], "post_time": "2022-01-14T08:28:20Z", "salary": {"currency": null, "max": null, "min": null, "period": null, "term": null}, "salary_visible": false, "title_keywords": ["producer"], "responsibilities": ["maintaining", "maintenance", "systems", "monitoring", "developing", "design", "troubleshooting", "configuring", "installing", "documentation", "application development", "architecture", "administration"], "requirements": {"degrees": ["degree holder", "master"], "majors": ["related disciplines", "it"], "languages": [], "language_level": [], "hard_skills": ["hyper-v", "no", "vmware", "tcp", "vpn", "firewall", "perl", "aws", "python", "linux", "apache", "dns", "maintenance", "switch", "bash", "ip", "deployment", "swift", "problem solving skills"], "soft_skills": ["communication skills", "work independently", "responsible", "self motivated", "hands on", "attention to details", "problem solving skills"], "languages_combined": []}, "experience_required": {"duration": ["at least 3 years"], "field": []}}, {"job_id": "100003009039822", "location_code": "hk", "company": "ViuTV", "job_title": "Production Assistant", "description": "Responsibilities :\n\nPrepare proposals and perform industry research to evaluate various negotiating positions and strategies for Content Licensing deals with new and existing clients\nAnalyze and assess results from clients and compare with market and industry data to formulate new business initiatives and business models\nParticipate in deal negotiations with clients\nUnderstand the trends in technology, digital media, content protection and consumer viewing habits\nManage and monitor the deal approval process\nPerform leadership and strategic planning on complicated deal structures, new windowing initiatives impacting Content Distribution\nBe a key and initial point of contact for members of the sales team, directing deal proposals from initiation to finalization\nResponsible for regional distribution on Animation, Drama series and Live movies\nHandle ad-hoc projects involving budget, forecast and deal track\nRequirement :\n\nMinimum 3 years solid experience in media / content distribution\nExposure in content production is a plus\nFamiliar with international and Asian content markets, major and independent program producers / distributors and Asian broadcasters\nGood command of written and spoken English and Chinese (including Mandarin)\nEnthusiasm in Japanese Animation and Drama Series is an advantage\nStrong analytical skills, sales-oriented, attention to details with strong work ethics\nProactive, independent, good team player with good working attitude\nWe offer 5-day work week, medical scheme, dental plan, discretionary bonus, and good career prospect to the right candidate. Interested parties, please send full resume with present & expected salaries and date availability to HR & Admin Department by \u201cApply Now\u201d below.\n", "employment_types": ["Full Time"], "selling_points": ["Assist Producer in all aspects of production", "Ensure a smooth production operations", "1 year of relevant experience"], "locations": ["Kowloon Bay"], "categories": ["Media & Advertising", "Creative / Design", "Production", "Broadcasting - TV / Radio"], "post_time": "2022-01-11T11:40:46Z", "salary": {"currency": null, "max": null, "min": null, "period": "monthly", "term": null}, "salary_visible": false, "title_keywords": ["production assistant"], "responsibilities": ["business initiatives", "strategic planning", "data", "budget", "monitor", "evaluate", "sales team", "contact", "forecast", "ad-hoc projects", "animation"], "requirements": {"degrees": [], "majors": [], "languages": ["japanese", "english", "chinese", "mandarin"], "language_level": ["advantage", "good command"], "hard_skills": ["plus", "analytical skills"], "soft_skills": ["good working attitude", "good team player", "independent", "analytical skills", "attention to details", "proactive"], "languages_combined": [{"language": "japanese", "language_level": ["advantage"]}, {"language": "english", "language_level": ["good command"]}, {"language": "chinese", "language_level": ["good command"]}, {"language": "mandarin", "language_level": ["good command"]}]}, "experience_required": {"duration": ["minimum 3 years"], "field": ["media"]}}, {"job_id": "100003009049290", "location_code": "hk", "company": "now TV", "job_title": "Senior Content Development Executive / Content Development Executive", "description": "On-Air Promotion\u00a0Department\nTo be responsible for producing on-air promos; following up with non-linear editing and post production work; providing creative ideas on all promotional campaigns and projects; initiating motion graphic design for promotion video\u00a0\nProficient in After Effects, Illustrator, Final Cut Pro, Maya, 3Ds Max and Photoshop\u00a0\nUniversity graduate with minimum 2 years experience in TV or creative industry\nGood command of both spoken and written English and Chinese\nAlert to deadlines with Can-do attitude\nGood interpersonal and communication skills\n\nWe offer 5-day work week, competitive remuneration packages and advancement opportunities. Interested parties, please write with full resume to Director, Human Resources, Human Resources Department, i-CABLE Communications Limited, 4/F Cable TV Tower, 9 Hoi Shing Road Tsuen Wan, N.T. or fax to 2112 7841 or via Apply Now (Please quote reference number and position applied for). For other information, please visit our website http://www.i-cable.com.\n\nYour application may be forwarded to any affiliate companies and successful applicant may be seconded to work at any office as assigned.\u00a0 The information received will be used for consideration of employment only and all personal data supplied will be destroyed within 3 months.\n\n\nWe are an equal opportunity employer.", "employment_types": ["Full Time", "Permanent"], "selling_points": ["Content Acquisition", "OTT", "Performance Bonus, Medical benefit, 5day work week"], "locations": ["Kowloon Bay"], "categories": ["Media & Advertising", "Production", "Strategic Planning", "Broadcasting - TV / Radio"], "post_time": "2022-01-14T08:23:38Z", "salary": {"currency": null, "max": null, "min": null, "period": null, "term": null}, "salary_visible": false, "title_keywords": ["executive"], "responsibilities": ["communication", "editing", "creative ideas", "motion graphic design"], "requirements": {"degrees": ["university graduate"], "majors": [], "languages": ["english", "chinese"], "language_level": ["good command"], "hard_skills": ["final cut pro", "maya", "3ds max", "illustrator", "after effects", "photoshop"], "soft_skills": ["communication skills", "responsible", "can-do attitude", "creative", "interpersonal"], "languages_combined": [{"language": "english", "language_level": ["good command"]}, {"language": "chinese", "language_level": ["good command"]}]}, "experience_required": {"duration": ["minimum 2 years"], "field": []}}, {"job_id": "100003009049328", "location_code": "hk", "company": "Phoenix Satellite Television Co Ltd", "job_title": "PROGRAMME DIRECTOR", "description": "Responsibilities:\u00a0\n\nResponsible for operating audio equipments in 24 hours news live studio and post production audio suite.\u00a0\n\n\u00a0Requirements:\u00a0\n\nF.5 or above.\nPrefer 2 years\u2019 experience of news live studio is an advantage.\nSelf-motivated and able to work independently.\nAble to work 24-hour shift duties.\nExcellent command of written and spoken English and Chinese.\n\nFor more details of our company, please visit our website at http://www.ifeng.com/\n\nWe offer attractive remuneration package to the right candidate. Interested parties please click \u201cApply Now\u201d to submit applications or send applications with detailed resume stating career history, present & expected salary and date available to Human Resources Department, Phoenix Satellite Television Co. Ltd. via fax: 2200 8620.\n\n\u00a0Personal data collected will be used for recruitment purpose only. Applicants not hearing from us within 6 weeks may consider their applications unsuccessful and all related information will be destroyed after 6 months.", "employment_types": ["Full Time", "Permanent"], "selling_points": [], "locations": ["Tai Po Area"], "categories": ["Media & Advertising", "Production", "Others", "Broadcasting - TV / Radio"], "post_time": "2022-01-14T08:28:20Z", "salary": {"currency": null, "max": null, "min": null, "period": null, "term": null}, "salary_visible": false, "title_keywords": ["director"], "responsibilities": ["audio"], "requirements": {"degrees": [], "majors": [], "languages": ["english", "chinese"], "language_level": ["excellent"], "hard_skills": [], "soft_skills": ["self-motivated", "work independently"], "languages_combined": [{"language": "english", "language_level": ["excellent"]}, {"language": "chinese", "language_level": ["excellent"]}]}, "experience_required": {"duration": ["2 years"], "field": []}}, {"job_id": "100003009049327", "location_code": "hk", "company": "Phoenix Satellite Television Co Ltd", "job_title": "Programme Editor", "description": "Description\nAssist in managing the online marketing channels and social media platforms (YouTube, Facebook, Telegram, Twitter)\nHave a certain understanding of international current affairs, financial information and social development trends\nformulate in-depth content promotion strategies and implementation, including setting directions, content creation, interacting with audiences, promotion, etc\nPerform miscellaneous assignments and assist in ad-hoc projects\nParticipate in planning iSun TV's original financial programs and content\n\n\u00a0Requirements\n\nBachelor Degree in Marketing or related disciplines\n2+ years\u2019 experience in Marketing\nGood written and spoken communication skills in English and Chinese/Mandarin\nStrong sense of responsibility, well organized with exceptional problem-solving skill\nA good team player with strong communication and interpersonal skills\nAbility to introduce new ideas and projects", "employment_types": ["Full Time", "Permanent"], "selling_points": [], "locations": ["Tai Po Area"], "categories": ["Media & Advertising", "Production", "Others", "Broadcasting - TV / Radio"], "post_time": "2022-01-14T08:28:19Z", "salary": {"currency": null, "max": null, "min": null, "period": null, "term": null}, "salary_visible": false, "title_keywords": ["editor"], "responsibilities": ["social media platforms", "implementation", "facebook", "ad-hoc projects", "planning"], "requirements": {"degrees": ["degree", "bachelor"], "majors": ["related disciplines", "marketing"], "languages": ["english", "chinese", "mandarin"], "language_level": ["good"], "hard_skills": ["problem-solving"], "soft_skills": ["communication skills", "good team player", "sense of responsibility", "problem-solving", "well organized", "communication and interpersonal skills"], "languages_combined": [{"language": "english", "language_level": ["good"]}, {"language": "chinese", "language_level": ["good"]}, {"language": "mandarin", "language_level": ["good"]}]}, "experience_required": {"duration": ["2+ years"], "field": ["marketing"]}}, {"job_id": "100003009049324", "location_code": "hk", "company": "Phoenix Satellite Television Co Ltd", "job_title": "Technical Director", "description": "Responsibilities:\n\nResponsible for the production of non-news programmes.\n\nRequirements:\n\n\nDegree/ Diploma holder in Journalism / Communication, with at least 4 years experience in TV production\nExperience in live variety show /outside broadcast /studio recording and filming are welcomed.\nKnowledge and experience in the field of digital media is a plus\nProficient in using Final Cut Pro, DaVinci, After effects and Photoshop\nCreative, presentable and good in communication.\nSelf-motivated and able to work independently under tight schedule.\nExcellent command of written and spoken English and Chinese, proficiency in Putonghua is a MUST.\nImmediate available is an advantage.\nCandidates with less experience will be considered for the post of Associate Producer.\n\nFor more details of our company, please visit our website at http://www.ifeng.com\n\nWe offer attractive remuneration package to the right candidate. Interested parties please click \u201cApply Now\u201d to submit applications or send applications with detailed resume stating career history, present & expected salary and date available to Human Resources Department, Phoenix Satellite Television Co. Ltd. via fax: 2200 8620.\n\n\u00a0Personal data collected will be used for recruitment purpose only. Applicants not hearing from us within 6 weeks may consider their applications unsuccessful and all related information will be destroyed after 6 months.", "employment_types": ["Full Time", "Permanent"], "selling_points": [], "locations": ["Tai Po Area"], "categories": ["Media & Advertising", "Production", "Others", "Broadcasting - TV / Radio"], "post_time": "2022-01-14T08:28:18Z", "salary": {"currency": null, "max": null, "min": null, "period": null, "term": null}, "salary_visible": false, "title_keywords": ["director"], "responsibilities": [], "requirements": {"degrees": ["diploma holder", "degree"], "majors": ["journalism"], "languages": ["putonghua", "english", "chinese"], "language_level": ["excellent", "proficiency"], "hard_skills": ["final cut pro", "after effects", "plus", "photoshop"], "soft_skills": ["self-motivated", "work independently", "presentable", "communication", "creative"], "languages_combined": [{"language": "putonghua", "language_level": ["proficiency", "excellent"]}, {"language": "english", "language_level": ["proficiency", "excellent"]}, {"language": "chinese", "language_level": ["proficiency", "excellent"]}]}, "experience_required": {"duration": ["at least 4 years"], "field": ["digital media", "tv production"]}}, {"job_id": "100003009049323", "location_code": "hk", "company": "Phoenix Satellite Television Co Ltd", "job_title": "\u5207\u63db\u53f0\u64cd\u4f5c\u54e1 VISION SWITCHER", "description": "Your New Role:\n\nAssist Producer in all aspects of production\nCoordinate with internal and external parties to ensure a smooth production operations\n\nWhat makes you succeed:\u00a0\n\n\nDegree or diploma holder, preferably in Mass Media Communications, Graphic Design or related disciplines\n1 year of relevant experience\nProficient in Premiere, After Effect and Final Cut Pro\nCreative mind with strong conceptual and execution skills\nDetail-minded, a good team player\nGood communication skills and able to work under pressure and meet tight deadlines\n\nWant to be one of us?\n\nIf you have the desire to create an exciting and rewarding career, please send us your resume immediately, quoting the reference number, your present and expected salary to\u00a0Human Resources Department by clicking \"Apply Now\".\n\n\nFor more information on other job opportunities of PCCW, please visit our website at\u00a0http://www.pccw.com/Careers/Job+Opportunities+%26+Application/Current+Opportunities?language=en_US\nPCCW is an equal opportunity employer and welcomes applications from all qualified candidates. Information provided will be treated in strict confidence and will only be used for recruitment-related purposes. Personal data provided by job applicants will be used strictly in accordance with the employer\u2019s\u00a0privacy statement\u00a0(www.pccw.com/privacy-statement/index.page), a copy of which will be provided immediately upon request.", "employment_types": ["Full Time", "Permanent"], "selling_points": [], "locations": ["Tai Po Area"], "categories": ["Media & Advertising", "Broadcasting - TV / Radio"], "post_time": "2022-01-14T08:28:18Z", "salary": {"currency": null, "max": null, "min": null, "period": null, "term": null}, "salary_visible": false, "title_keywords": [], "responsibilities": ["operations", "graphic design", "internal and external parties", "coordinate with", "website", "communication", "recruitment", "personal data", "work under pressure"], "requirements": {"degrees": ["diploma holder", "degree"], "majors": ["related disciplines", "graphic design", "mass media", "communications"], "languages": [], "language_level": [], "hard_skills": ["final cut pro", "after effect", "premiere"], "soft_skills": ["detail-minded", "communication skills", "good team player", "meet tight deadlines", "confidence", "smooth", "creative", "work under pressure"], "languages_combined": []}, "experience_required": {"duration": ["1 year"], "field": ["relevant experience"]}}, {"job_id": "100003009040127", "location_code": "hk", "company": "i-CABLE Communications Limited", "job_title": "Senior Account Executive - Advertising Sales", "description": "Your New Role\n\nResponsible for content acquisition for linear channel and on-demand services, including content sourcing from local and international content providers, deal negotiation and contract execution.\nCoordinate with content providers and internal stakeholders on all operational aspects as required, including day-to-day functions such as material delivery, dubbing, subtitling, encoding, scheduling,compliance, quality assurance and on-air promotion/ marketing support etc.\nEnsure all programme and promotional materials meet launch specifications and delivery timeline.\nResponsible for content curation and preparing metadata. Plan and manage programme schedule and monthly highlights to ensure services meet marketing objectives.\nMaintain programming log to keep track of on-air dates, length of exhibition period, license period, contract expiry date etc. as required for the services.\nGenerate usage and viewership reports for analysis and reporting purposes.\n\nWhat makes you succeed\n\nUniversity graduate in any discipline and 2 years\u2019 relevant experience is preferred\u00a0\nExperience in program scheduling in TV industry is a definite advantage\nPassionate about children and educational content and interested in new media development\nAble to work under pressure and meet tight deadlines\nDetail-minded, well organized and good sense of priority\nProficiency in MS Office and Chinese word processing\nGood command in both spoken & written English and Chinese", "employment_types": ["Full Time", "Permanent"], "selling_points": [], "locations": ["Tsuen Wan Area"], "categories": ["Media & Advertising", "Account Servicing", "Sales, CS & Business Devpt", "Business Development", "Broadcasting - TV / Radio"], "post_time": "2022-01-12T01:33:09Z", "salary": {"currency": null, "max": null, "min": null, "period": null, "term": null}, "salary_visible": false, "title_keywords": ["senior account executive", "sales"], "responsibilities": ["reporting", "analysis", "compliance", "coordinate with", "quality", "scheduling", "promotional materials", "specifications", "schedule", "plan", "maintain", "reports", "work under pressure"], "requirements": {"degrees": ["university graduate"], "majors": [], "languages": ["english", "chinese"], "language_level": ["proficiency", "good command"], "hard_skills": ["analysis", "chinese word processing", "programming", "ms office"], "soft_skills": ["detail-minded", "meet tight deadlines", "negotiation", "responsible", "interested in", "well organized", "passionate about", "work under pressure"], "languages_combined": [{"language": "english", "language_level": ["good command"]}, {"language": "chinese", "language_level": ["proficiency", "good command"]}]}, "experience_required": {"duration": ["2 years"], "field": ["relevant experience"]}}, {"job_id": "100003009039821", "location_code": "hk", "company": "ViuTV", "job_title": "Research Writer", "description": "Responsibilities:\u00a0\n\nResponsible for the production of TV programmes, especially live newscast.\n\nRequirements:\n\n\nCertificate/Diploma/Degree holder in Journalism/Communication, with 5 years relevant working experience in programme production.\nExperienced in handling live newscast and programme\nWorking at digital media platform is an advantage.\nKnowledge in editing\nSelf-motivated, creative and independent.\nAble to work 24-hour shift duties.\nGood command of written and spoken English and Chinese, proficiency in Putonghua is an advantage.\n\nFor more details of our company, please visit our website at http://www.ifeng.com\n\nWe offer attractive remuneration package to the right candidate. Interested parties please click \u201cApply Now\u201d to submit applications or send applications with detailed resume stating career history, present & expected salary and date available to Human Resources Department, Phoenix Satellite Television Co. Ltd. via fax: 2200 8620.\n\n\u00a0Personal data collected will be used for recruitment purpose only. Applicants not hearing from us within 6 weeks may consider their applications unsuccessful and all related information will be destroyed after 6 months.", "employment_types": ["Full Time"], "selling_points": ["Producing top quality TV Programmes", "1 to 3 years experience in TV production", "Good script writing skills"], "locations": ["Kowloon Bay"], "categories": ["Media & Advertising", "Creative / Design", "Production", "Broadcasting - TV / Radio"], "post_time": "2022-01-11T11:39:56Z", "salary": {"currency": null, "max": null, "min": null, "period": "monthly", "term": null}, "salary_visible": false, "title_keywords": [], "responsibilities": [], "requirements": {"degrees": ["certificate", "diploma", "degree holder"], "majors": ["journalism"], "languages": ["putonghua", "english", "chinese"], "language_level": ["advantage", "proficiency", "good command"], "hard_skills": [], "soft_skills": ["communication", "self-motivated", "creative", "independent"], "languages_combined": [{"language": "putonghua", "language_level": ["proficiency", "advantage", "good command"]}, {"language": "english", "language_level": ["proficiency", "advantage", "good command"]}, {"language": "chinese", "language_level": ["proficiency", "advantage", "good command"]}]}, "experience_required": {"duration": ["5 years"], "field": ["relevant working experience"]}}, {"job_id": "100003009049326", "location_code": "hk", "company": "Phoenix Satellite Television Co Ltd", "job_title": "EFP Technician \u5916\u666f\u63a1\u8a2a\u6280\u8853\u54e1", "description": "Responsibilities:\n\nResponsible in editing news and current affairs programmes.\n\nRequirements:\n\n\n3 - 5 years\u2019 experience in editing news and current affairs programmes.\nBe a good team player, work independently under tight schedule.\nAble to work 24-hour shift duties.\nGood command of written and spoken English, Chinese and Putonghua.\n\nFor more details of our company, please visit our website at http://www.ifeng.com/\n\n\nWe offer attractive remuneration package to the right candidate. Interested parties please click \u201cApply Now\u201d to submit applications or send applications with detailed resume stating career history, present & expected salary and date available to Human Resources Department, Phoenix Satellite Television Co. Ltd. via fax: 2200 8620.\n\n\u00a0Personal data collected will be used for recruitment purpose only. Applicants not hearing from us within 6 weeks may consider their applications unsuccessful and all related information will be destroyed after 6 months.", "employment_types": ["Full Time", "Permanent"], "selling_points": [], "locations": ["Tai Po Area"], "categories": ["Media & Advertising", "Production", "Others", "Broadcasting - TV / Radio"], "post_time": "2022-01-14T08:28:19Z", "salary": {"currency": null, "max": null, "min": null, "period": null, "term": null}, "salary_visible": false, "title_keywords": ["technician"], "responsibilities": ["editing"], "requirements": {"degrees": [], "majors": [], "languages": ["putonghua", "english", "chinese"], "language_level": ["good command"], "hard_skills": [], "soft_skills": ["good team player", "work independently"], "languages_combined": [{"language": "putonghua", "language_level": ["good command"]}, {"language": "english", "language_level": ["good command"]}, {"language": "chinese", "language_level": ["good command"]}]}, "experience_required": {"duration": ["3 - 5 years"], "field": ["editing"]}}, {"job_id": "100003009039830", "location_code": "hk", "company": "ViuTV", "job_title": "Assistant /  Production Administrator", "description": "\u8077\u52d9\u7bc4\u570d\uff1a\n\n\u8ca0\u8cac\u9818\u5c0e\u9304\u5f71\u5ee0\u65e5\u5e38\u6280\u8853\u64cd\u4f5c\n\n\u5165\u8077\u8981\u6c42\uff1a\n\n\u4e2d\u4e94\u4ee5\u4e0a\u7a0b\u5ea6\u4e26\u67095\u5e74\u6216\u4ee5\u4e0a\u76f8\u95dc\u5de5\u4f5c\u7d93\u9a57\n\u5177\u6709\u9304\u5f71\u5ee0\u5404\u7a2e\u57fa\u672c\u5668\u6750\u64cd\u4f5c\u77e5\u8b58\u8005\u00a0\n\u6ce8\u91cd\u5718\u968a\u5408\u4f5c\u4e26\u80fd\u65bc\u58d3\u529b\u4e0b\u7368\u7acb\u5de5\u4f5c\n\u80fd\u592024\u5c0f\u6642\u8f2a\u73ed\u5de5\u4f5c\n\u80fd\u8b1b\u7cb5\u8a9e\u3001\u666e\u901a\u8a71\u3001\u82f1\u8a9e\uff0c\u5177\u5099\u826f\u597d\u53e3\u8a9e\u53ca\u66f8\u5beb\u80fd\u529b\n\nResponsibilities:\n\nIn charge of daily studio technical operations.\n\nRequirements:\n\nForm 5 or above with over 5 years relevant working experience.\nKnowledge of general studio equipment.\nA good team player, independent and able to work under pressure.\nAble to work 24-hour shift duties.\nGood command of written and spoken English and Chinese, proficiency in Putonghua is an advantage.\n\nFor more details of our company, please visit our website at http://www.ifeng.com/\n\nWe offer attractive remuneration package to the right candidate. Interested parties please click \u201cApply Now\u201d to submit applications or send applications with detailed resume stating career history, present & expected salary and date available to Human Resources Department, Phoenix Satellite Television Co. Ltd. via fax: 2200 8620.\n\n\u00a0Personal data collected will be used for recruitment purpose only. Applicants not hearing from us within 6 weeks may consider their applications unsuccessful and all related information will be destroyed after 6 months.", "employment_types": ["Full Time", "Permanent"], "selling_points": ["Provide administrative and clerical support", "Facilities and manpower arrangements", "Organize appointment and coordinate meeting"], "locations": ["Kowloon Bay"], "categories": ["Media & Advertising", "Production", "Broadcasting - TV / Radio"], "post_time": "2022-01-11T11:44:41Z", "salary": {"currency": null, "max": null, "min": null, "period": null, "term": null}, "salary_visible": false, "title_keywords": ["administrator", "assistant"], "responsibilities": ["operations"], "requirements": {"degrees": ["form 5 or above"], "majors": [], "languages": ["putonghua", "english", "chinese"], "language_level": ["advantage", "proficiency", "good command"], "hard_skills": [], "soft_skills": ["good team player", "independent", "work under pressure"], "languages_combined": [{"language": "putonghua", "language_level": ["proficiency", "advantage", "good command"]}, {"language": "english", "language_level": ["proficiency", "advantage", "good command"]}, {"language": "chinese", "language_level": ["proficiency", "advantage", "good command"]}]}, "experience_required": {"duration": ["5 years"], "field": ["relevant working experience"]}}, {"job_id": "100003009044493", "location_code": "hk", "company": "Phoenix Satellite Television Co Ltd", "job_title": "PUBLIC RELATIONS OFFICER", "description": "\u8077\u52d9\u7bc4\u570d\uff1a\n\n\u5354\u52a9\u651d\u5f71\u5ee0\u5207\u63db\u53f0\u65e5\u5e38\u64cd\u4f5c\u3002\n\n\u00a0\u5165\u8077\u8981\u6c42\uff1a\n\n\u4e2d\u4e94\u7562\u696d\u6216\u4ee5\u4e0a\u5b78\u6b77\uff1b\n\u5177\u5099\u4e00\u81f3\u5169\u5e74\u76f8\u95dc\u7d93\u9a57\uff1b\n\u5177\u5718\u968a\u5408\u4f5c\u7cbe\u795e\u3001\u80fd\u7368\u7acb\u53ca\u5728\u58d3\u529b\u4e0b\u5de5\u4f5c\uff1b\n\u980824\u5c0f\u6642\u8f2a\u73ed\u5de5\u4f5c\uff1b\n\u826f\u597d\u7684\u4e2d\u82f1\u6587\u8b80\u5beb\u80fd\u529b\u53ca\u64cd\u6d41\u5229\u666e\u901a\u8a71\n\nResponsibilities:\n\nProvide comprehensive support to daily studio vision mixer operations.\n\nRequirements:\n\nForm 5 or above with 1-2 years relevant working experience.\nA good team player, independent and able to work under pressure.\nAble to work 24-hour shift duties.\nGood command of written and spoken English and Chinese, proficiency in Putonghua is an advantage.\n\nFor more details of our company, please visit our website at http://www.ifeng.com/\n\nWe offer attractive remuneration package to the right candidate. Interested parties please click \u201cApply Now\u201d to submit applications or send applications with detailed resume stating career history, present & expected salary and date available to Human Resources Department, Phoenix Satellite Television Co. Ltd. via fax: 2200 8620.\n\n\u00a0Personal data collected will be used for recruitment purpose only. Applicants not hearing from us within 6 weeks may consider their applications unsuccessful and all related information will be destroyed after 6 months.", "employment_types": ["Full Time", "Permanent"], "selling_points": [], "locations": ["Tai Po Area"], "categories": ["Media & Advertising", "Broadcasting - TV / Radio"], "post_time": "2022-01-13T04:20:42Z", "salary": {"currency": null, "max": null, "min": null, "period": null, "term": null}, "salary_visible": false, "title_keywords": ["officer"], "responsibilities": ["operations"], "requirements": {"degrees": ["form 5 or above"], "majors": [], "languages": ["putonghua", "english", "chinese"], "language_level": ["advantage", "proficiency", "good command"], "hard_skills": [], "soft_skills": ["good team player", "independent", "work under pressure"], "languages_combined": [{"language": "putonghua", "language_level": ["proficiency", "advantage", "good command"]}, {"language": "english", "language_level": ["proficiency", "advantage", "good command"]}, {"language": "chinese", "language_level": ["proficiency", "advantage", "good command"]}]}, "experience_required": {"duration": ["1-2 years"], "field": ["relevant working experience"]}}, {"job_id": "100003009049325", "location_code": "hk", "company": "Phoenix Satellite Television Co Ltd", "job_title": "EFP Cameraman", "description": "Your New Role:\n\n\nThe successful candidate will take on the challenge of formulating and producing top quality TV Programmes.\n\nWhat makes you succeed:\u00a0\n\n\nDegree / Diploma holder in any disciplines, preferably in TV Production / Mass Communications\n1 to 3 years experience in TV production\u00a0\nGood script writing skills\nOutgoing, creative and energetic\nA good team player\nPossess good communication skills and able to work under tight schedules and irregular hours\nExcellent in written and spoken English, Cantonese and Putonghua is a MUST\n\nWant to be one of us?\n\nIf you have the desire to create an exciting and rewarding career, please send us your resume immediately, quoting the reference number, your present and expected salary to\u00a0Human Resources Department by clicking \"Apply Now\".\n\n\nFor more information on other job opportunities of PCCW, please visit our website at\u00a0http://www.pccw.com/Careers/Job+Opportunities+%26+Application/Current+Opportunities?language=en_US\nPCCW is an equal opportunity employer and welcomes applications from all qualified candidates. Information provided will be treated in strict confidence and will only be used for recruitment-related purposes. Personal data provided by job applicants will be used strictly in accordance with the employer\u2019s\u00a0privacy statement\u00a0(www.pccw.com/privacy-statement/index.page), a copy of which will be provided immediately upon request.", "employment_types": ["Full Time", "Permanent"], "selling_points": [], "locations": ["Tai Po Area"], "categories": ["Media & Advertising", "Production", "Broadcasting - TV / Radio", "Photography / Video"], "post_time": "2022-01-14T08:28:19Z", "salary": {"currency": null, "max": null, "min": null, "period": null, "term": null}, "salary_visible": false, "title_keywords": [], "responsibilities": ["schedules", "quality", "website", "communication", "recruitment", "personal data"], "requirements": {"degrees": ["diploma holder", "degree"], "majors": ["any disciplines", "communications"], "languages": ["cantonese", "putonghua", "english"], "language_level": ["excellent"], "hard_skills": ["writing skills"], "soft_skills": ["outgoing", "communication skills", "good team player", "confidence", "creative", "writing skills", "energetic"], "languages_combined": [{"language": "cantonese", "language_level": ["excellent"]}, {"language": "putonghua", "language_level": ["excellent"]}, {"language": "english", "language_level": ["excellent"]}]}, "experience_required": {"duration": ["1 to 3 years"], "field": ["tv production"]}}, {"job_id": "100003009049303", "location_code": "hk", "company": "Commercial Radio Productions Ltd", "job_title": "IT Support Engineer (Kowloon Tong)", "description": "Responsibilities:\n\nTechnical support for location shooting and news covering including audio, lighting and signal transmission etc.\n\nRequirements:\n\nSecondary education or above with 3 years\u2019 relevant work experience\nGood command of written and spoken English, Chinese and Putonghua\nKnowledge in PC and Internet\nShift duty and overseas travel required\nProactive and a team player\nRelevant experience in TV industry is preferred\n\nFor more details of our company, please visit our website at http://www.ifeng.com/\n\nWe offer attractive remuneration package to the right candidate. Interested parties please click \u201cApply Now\u201d to submit applications or send applications with detailed resume stating career history, present & expected salary and date available to Human Resources Department, Phoenix Satellite Television Co. Ltd. via fax: 2200 8620.\n\nPersonal data collected will be used for recruitment purpose only. Applicants not hearing from us within 6 weeks may consider their applications unsuccessful and all related information will be destroyed after 6 months.", "employment_types": ["Full Time", "Permanent"], "selling_points": ["Provide IT Helpdesk services for in-house end-user", "Setup and provide IT support for Live stream event", "Hands-on experience in Linux/Windows is a MUST"], "locations": ["Not Specified"], "categories": ["Information Technology (IT)", "Support", "Network & System", "Media & Advertising", "Broadcasting - TV / Radio"], "post_time": "2022-01-14T08:24:37Z", "salary": {"currency": null, "max": null, "min": null, "period": "monthly", "term": null}, "salary_visible": false, "title_keywords": ["it support engineer"], "responsibilities": ["technical support", "audio"], "requirements": {"degrees": ["secondary education"], "majors": [], "languages": ["putonghua", "english", "chinese"], "language_level": ["good command"], "hard_skills": ["pc"], "soft_skills": ["team player", "proactive"], "languages_combined": [{"language": "putonghua", "language_level": ["good command"]}, {"language": "english", "language_level": ["good command"]}, {"language": "chinese", "language_level": ["good command"]}]}, "experience_required": {"duration": ["3 years"], "field": ["relevant experience", "education"]}}, {"job_id": "100003009049321", "location_code": "hk", "company": "Phoenix Satellite Television Co Ltd", "job_title": "Technical Operator", "description": "Your New Role\u00a0\n\n\nProvide administrative and clerical support to the department\nLiaise with different parties for on-air promotion production and planning; facilities and man-power arrangements, work out production and post-production details\nUpdate and maintain database of the department\u00a0\nOrganize appointment and coordinate meeting schedule\nPrepare correspondences, accounting reports and presentation materials\nAssist in ad-hoc duties as assigned\n\nWhat makes you succeed\n\n\nF.7 or DSE / Diploma or above with at least 1 years working experience in secretarial / administrative support\nExperience in TV / Media / Wardrobe / Make-up is an advantage\nPositive working attitude and detail minded\nWilling to work overtime and under pressure\nProficiency in MS Office such as Excel, Word, PowerPoint and Chinese Word Processing\nExcellent command of spoken and written English & Chinese\nImmediate available is highly preferred\n\nWant to be one of us?\n\nWe offer attractive & competitive salary and benefits, an exciting work environment and excellent career development opportunities. If you have the desire for an exciting and rewarding career, please send us your resume, stating your present and expected salary to Human Resources Department\u00a0by clicking \"Apply Now\".\u00a0\u00a0\n\nFor more information on other job opportunities of PCCW, please visit our website at<http://www.pccw.com/Careers/Job+Opportunities+&+Application/Current+Opportunities?language=en_US>\u00a0\u00a0\n\nPCCW is an equal opportunity employer and welcomes applications from all qualified candidates. Information provided will be treated in strict confidence and will only be used for recruitment-related purposes. Personal data provided by job applicants will be used strictly in accordance with the employer personal data policies (http://www.pccw.com/staticfiles/PCCWCorpsite/Terms%20of%20Use/Privacy%20Policy%20Statement/(PCCW)%20HR%20Privacy%20Policy%20Statement%20(version%20-%20Nov%202017).pdf), a copy of which will be provided immediately upon request.", "employment_types": ["Full Time", "Permanent"], "selling_points": [], "locations": ["Tai Po Area"], "categories": ["Media & Advertising", "Production", "Others", "Broadcasting - TV / Radio"], "post_time": "2022-01-14T08:28:17Z", "salary": {"currency": null, "max": null, "min": null, "period": null, "term": null}, "salary_visible": false, "title_keywords": ["operator"], "responsibilities": ["ad-hoc duties", "administrative support", "coordinate", "maintain", "reports", "schedule", "database", "administrative and clerical support", "liaise with", "planning"], "requirements": {"degrees": ["diploma or above", "dse"], "majors": [], "languages": ["english", "chinese"], "language_level": ["proficiency", "excellent"], "hard_skills": ["excel", "chinese word processing", "word", "powerpoint", "make", "ms office"], "soft_skills": ["work overtime", "under pressure", "positive working attitude", "ad-hoc duties", "presentation"], "languages_combined": [{"language": "english", "language_level": ["excellent"]}, {"language": "chinese", "language_level": ["proficiency", "excellent"]}]}, "experience_required": {"duration": ["at least 1 years"], "field": ["secretarial", "administrative", "media"]}}, {"job_id": "100003009042996", "location_code": "hk", "company": "Phoenix Satellite Television Co Ltd", "job_title": "Broadcast Operator \u5ee3\u64ad\u904b\u4f5c\u6280\u8853\u54e1", "description": "Responsibilities:\n\nLocation planning, shooting, lighting setup, live broadcasting signal transmission.\n\nRequirements:\n\n3 years\u2019 work experience in news and features shooting\nGood command of written and spoken English, Chinese and Putonghua\nKnowledge in PC\nShift duty and overseas travel required\nProactive and a team player\nRelevant experience in TV industry is preferred\n\nFor more details of our company, please visit our website at http://www.ifeng.com/\n\nWe offer attractive remuneration package to the right candidate. Interested parties please click \u201cApply Now\u201d to submit applications or send applications with detailed resume stating career history, present & expected salary and date available to Human Resources Department, Phoenix Satellite Television Co. Ltd. via fax: 2200 8620.\n\nPersonal data collected will be used for recruitment purpose only. Applicants not hearing from us within 6 weeks may consider their applications unsuccessful and all related information will be destroyed after 6 months.", "employment_types": ["Full Time", "Permanent"], "selling_points": [], "locations": ["Tai Po Area"], "categories": ["Media & Advertising", "Others", "Broadcasting - TV / Radio"], "post_time": "2022-01-12T09:27:38Z", "salary": {"currency": null, "max": null, "min": null, "period": null, "term": null}, "salary_visible": false, "title_keywords": ["operator"], "responsibilities": ["setup", "planning"], "requirements": {"degrees": [], "majors": [], "languages": ["putonghua", "english", "chinese"], "language_level": ["good command"], "hard_skills": ["pc"], "soft_skills": ["team player", "proactive"], "languages_combined": [{"language": "putonghua", "language_level": ["good command"]}, {"language": "english", "language_level": ["good command"]}, {"language": "chinese", "language_level": ["good command"]}]}, "experience_required": {"duration": ["3 years"], "field": ["relevant experience"]}}, {"job_id": "100003009039803", "location_code": "hk", "company": "now TV", "job_title": "Finance Reporter \u2013 Features", "description": "Commercial Radio Interactive, a division of Commercial Radio Productions Limited and the digital arm of Commercial Radio, are looking for a passionate and energetic\u00a0System Engineer to join our IT team and develop his/her career under the guidance of our experienced senior staff.\n\n\n\nJob Duties\n\nProvide IT Helpdesk services for in-house end-users\nSetup and provide IT support for Live streaming event\nInstall, configure, and maintain internal systems/services\nPerform Linux/Windows system administration\nCreate and maintain technical documentation\nJob Requirements\n\n\nHigher Diploma or Degree holder in Computer Science or related disciplines of Tertiary Education\nMinimum 1 year solid experiences in system administration and technical support\u00a0\nHands-on experience in Linux/Windows is a MUST\nHolder of RHCT/RHCE, LPI, MCSA, MCSE is an advantage\nHands-on experience in VMWare is an advantage\nGood problem solving skills , pay attention to details and good communication skills\nResponsible, self motivated, work independently, and process tasks without supervision\nWilling to work at non office hour for urgent production service support & maintenance.\nFresh graduates are also welcome\n\nOffice location: Kowloon Tong\n\nApplication Procedure:\n\nWe offer attractive remuneration package, competitive salary, medical scheme and life insurance to the right candidate. Interested candidates, please submit application letter with full resume, present and expected salary by clicking \u201cApply Now\u201d (Please quote the job reference number on the e-mail subject line).\n\nAll information received will be kept in strict confidence and only for employment-related purpose. Only short listed candidates will be invited for interview.", "employment_types": ["Full Time", "Permanent"], "selling_points": ["Program production", "Property, technology and other features", "Financial news reporting"], "locations": ["Wan Chai"], "categories": ["Media & Advertising", "Editorial / Journalism", "Broadcasting - TV / Radio"], "post_time": "2022-01-11T11:28:53Z", "salary": {"currency": null, "max": null, "min": null, "period": null, "term": null}, "salary_visible": false, "title_keywords": ["reporter"], "responsibilities": ["maintain", "documentation", "internal systems", "setup", "administration"], "requirements": {"degrees": ["diploma", "degree holder"], "majors": ["related disciplines", "computer science"], "languages": [], "language_level": [], "hard_skills": ["linux", "mcse", "vmware", "maintenance", "mcsa", "problem solving skills"], "soft_skills": ["communication skills", "work independently", "responsible", "self motivated", "hands-on", "attention to details", "problem solving skills"], "languages_combined": []}, "experience_required": {"duration": ["minimum 1 year"], "field": ["administration"]}}, {"job_id": "100003009055232", "location_code": "hk", "company": "ORIENTAL HUMAN RESOURCES LIMITED", "job_title": "Video Editor Trainee", "description": "Responsible for data input and website video editing\nSecondary school graduate or above, no relevant experience is required\nKnowledge of Photoshop, After Effects, Motion, FCPX is preferable\nFamiliar with Chinese word processing, at least 25 w.p.m.\nNight shift and rotated rest day are required\n(Those with more experience will be considered as Video Editor)\n\n\nApplication Method\n\n\nWe offer 5-day work week, free shuttle bus, free parking and fringe benefits including medical scheme, discretionary bonus and public holidays\u00a0to the right candidate. Interested parties, please send full resume with expected salary to ORIENTAL HUMAN RESOURCES LIMITED\u00a0by\u00a0clicking \"Apply now\" ;\u00a0or fax to 3600 1900 ( Please quote reference on the application letter )\n\n\nPersonal Information Collection Statement\n\nPersonal data collected will be treated in accordance with our Personal Data Policy and handled in strict confidence by authorized personnel for recruitment related purpose only.\u00a0 \u00a0 \u00a0\n\u00a0 \u00a0 \u00a0 \u00a0 \u00a0 \u00a0\n\n\u00a0 \u00a0 \u00a0 \u00a0 \u00a0 \u00a0 \u00a0 \u00a0 \u00a0 \u00a0 \u00a0 \u00a0 \u00a0 \u00a0 \u00a0 \u00a0 \u00a0 \u00a0 \u00a0 \u00a0 \u00a0 \u00a0 \u00a0 \u00a0 \u00a0 \u00a0 \u00a0\u00a0on.cc\n\n", "employment_types": ["Full Time"], "selling_points": [], "locations": ["Tai Po Area"], "categories": ["Media & Advertising", "Production", "Broadcasting - TV / Radio", "Photography / Video"], "post_time": "2022-01-18T01:53:16Z", "salary": {"currency": null, "max": null, "min": null, "period": "monthly", "term": null}, "salary_visible": false, "title_keywords": ["trainee", "video editor"], "responsibilities": ["video editing", "data input", "website"], "requirements": {"degrees": [], "majors": [], "languages": ["chinese"], "language_level": [], "hard_skills": ["no", "chinese word processing", "scheme", "video editing", "after effects", "photoshop"], "soft_skills": ["responsible"], "languages_combined": [{"language": "chinese", "language_level": []}]}, "experience_required": {"duration": [], "field": ["editor", "video", "relevant experience"]}}, {"job_id": "100003009056325", "location_code": "hk", "company": "Asia Innovations HK Limited", "job_title": "Entertainment Talent Manager", "description": "We are Leading live streaming company in the world. Now we are looking for:\n\nEntertainment Talent Manager\n\nResponsibilities:\n\nPerform end-to-end recruitment of live streamer and KOL including sourcing, CV screening, interviewing, etc.\n\nAssist in streamers management, training, communication, coordination and casting\nMonitor, measure and review streamers\u2019 and KOL\u2019s performance timely\nCoordinating and liaising with marketing and operation teams for sales campaign\nConsolidate and prepare various streamers\u2019 and KOL\u2019s performance analytics reports and presentations for management review\nProvide on-site support during events or company promotions\n\nRequirements:\n\n1-2 years' relevant work experience in business development or similar field preferred\nSounds knowledgeable in entertainment trend and live streaming business\nSensitive on marketing trend and numbers\nExcellent communication and interpersonal skills with positive and \u201ccan-do\u201d attitudes\nAble to work independent, under pressure and adopt fast pace environment\nGood command in both written and spoken English, Chinese and Mandarin\nImmediate available will be an advantage\n\n\nWe Offer:\n\n\u00a0Basic Salary with Commission Package\nAttractive bonus or project bonus (depends on performance)\nFriendly and professional working environment\nExcellent career path\nWell-structured on-job training program\u00a0\n\nWelcome young, energetic and strong motivation candidates!\u00a0", "employment_types": ["Full Time"], "selling_points": [], "locations": ["Tsim Sha Tsui"], "categories": ["Sales, CS & Business Devpt", "Business Development", "Others", "Entertainment - Artists / Singers / Musicians", "Media & Advertising", "Broadcasting - TV / Radio"], "post_time": "2022-01-18T03:57:54Z", "salary": {"currency": null, "max": null, "min": null, "period": "monthly", "term": null}, "salary_visible": false, "title_keywords": ["manager"], "responsibilities": ["management", "cv screening", "review", "monitor", "liaising with", "teams", "presentations", "communication", "recruitment", "reports", "coordination", "management review"], "requirements": {"degrees": [], "majors": [], "languages": ["english", "chinese", "mandarin"], "language_level": ["good command"], "hard_skills": [], "soft_skills": ["independent", "under pressure", "communication and interpersonal skills", "can-do", "sensitive", "positive"], "languages_combined": [{"language": "english", "language_level": ["good command"]}, {"language": "chinese", "language_level": ["good command"]}, {"language": "mandarin", "language_level": ["good command"]}]}, "experience_required": {"duration": ["1-2 years"], "field": ["business development"]}}, {"job_id": "100003009056174", "location_code": "hk", "company": "PCCW Media (NowTV)", "job_title": "Senior Content Development Manager / Content Development Manager (Content Acquisition)", "description": "Key responsibilities\n\nContent Acquisition \u2013 Now TV Team:\n\nResponsible for the important role of \u00a0Asian content acquisition, primarily drama series, across Now TV and its affiliates\u2019 media services in Hong Kong.\nHeads up a team to manage all aspects of content acquisition and management including research, negotiation, contract drafting, viewership tracking, financial analysis and contract database maintenance.\nManage the programming and scheduling of exclusive Asian drama linear channels and on-demand services to ensure that they are popular with customers.\u00a0\nCollaborate with internal stakeholders such as Marketing, Product, Legal, Finance and Overseas business teams to align budgets and forecasts, programming plans, marketing and promotional activities as well as to drive content \u00a0engagement across all customer touchpoints.\nMonitor industry trends to drive strategic content decisions, formulate business plans and develop content strategies for both internal and external stakeholders.\n\nQualifications\n\nUniversity degree required with 8+ years of relevant work experience in the media industry or content acquisition / distribution fields and with 3+ years of supervisory experience.\nExperience in negotiations and ability to manage legal agreements and contracts.\u00a0\nRelevant knowledge of Asian drama market and industry trends.\nAbility to learn in fast-paced environment, prioritizing and balancing multiple projects and deadlines simultaneously.\nGreat interpersonal skills, business judgment, proven strategic thinking and problem solving skills.\nExcellent verbal and written communication skills\u00a0in Cantonese/ Mandarin/ English.\nPreferred proficiency in a foreign language such as \u00a0Japanese/Korean but not required.", "employment_types": ["Full Time"], "selling_points": ["Asian content acquisition, Primarily drama series", "Content acquisition and management", "Performance bonus, Medical benefit, 5day work week"], "locations": ["Kowloon Bay"], "categories": ["Media & Advertising", "Media Buying", "Strategic Planning", "Broadcasting - TV / Radio"], "post_time": "2022-01-18T03:28:48Z", "salary": {"currency": null, "max": null, "min": null, "period": "monthly", "term": null}, "salary_visible": false, "title_keywords": ["manager"], "responsibilities": ["collaborate with", "budgets", "management", "maintenance", "contracts", "teams", "monitor", "business plans", "develop", "financial analysis", "scheduling", "communication", "promotional activities", "database", "plans", "multiple projects", "tracking"], "requirements": {"degrees": ["university degree"], "majors": [], "languages": ["cantonese", "english", "mandarin", "japanese", "korean"], "language_level": ["excellent", "proficiency"], "hard_skills": ["financial analysis", "programming", "problem solving skills", "maintenance"], "soft_skills": ["communication skills", "negotiation", "responsible", "strategic thinking", "fast-paced environment", "interpersonal skills", "problem solving skills", "prioritizing"], "languages_combined": [{"language": "cantonese", "language_level": ["excellent"]}, {"language": "english", "language_level": ["excellent"]}, {"language": "mandarin", "language_level": ["excellent"]}, {"language": "japanese", "language_level": ["proficiency"]}, {"language": "korean", "language_level": ["proficiency"]}]}, "experience_required": {"duration": ["8+ years", "3+ years"], "field": ["media", "legal", "supervisory experience"]}}, {"job_id": "100003009055899", "location_code": "hk", "company": "Metro Broadcast Corporation Ltd", "job_title": "Sales Support Officer (Ref#: SSO)", "description": "Job requirements:\n\nDegree holder in Marketing, Business Administration or related disciplines\nMinimum 1-2 years' experience in digital marketing, media advertising or related field\nAttention to details, able to work under tight timeline and multi-task independently\nWell-organized and a good team player\nProficiency in MS Office applications (Word, Excel, Powerpoint)\nGood command of spoken and written English and Chinese\nLess related experience will be considered as junior position\nImmediate available is highly preferable\n\n\u00a0Job description:\n\nAssist sales team to handle sales orders including order processing, account servicing and documentation work\nAssist sales team to plan, organize and monitor sales campaigns\nWork closely with New Media to coordinate content update of digital platforms\nPrepare post-campaign reports with analysis of campaign effectiveness, data insights and project outcomes.\nHandle ad-hoc tasks assigned by Management\u00a0\nIf you are interested and have the required qualification, please send your full resume together with expected salary in confidence to the HR & Admin. Dept., Metro Broadcast Corp. Ltd., Basement 2, Site 6, Whampoa Garden, Hunghom, Kln.\n\n\nAll information provided will be treated in strict confidence and be used solely for consideration of your application. Personal data of unsuccessful applicants will be destroyed after the recruitment exercise. (Please quote our reference no. for the position applied on the envelop)", "employment_types": ["Full Time", "Permanent"], "selling_points": [], "locations": ["Hung Hom"], "categories": ["Marketing / Public Relations", "Marketing - General / Support", "Media & Advertising", "Broadcasting - TV / Radio", "Sales, CS & Business Devpt", "Account Servicing"], "post_time": "2022-01-18T03:03:56Z", "salary": {"currency": null, "max": null, "min": null, "period": null, "term": null}, "salary_visible": false, "title_keywords": ["sales support officer"], "responsibilities": ["management", "data", "analysis", "ad-hoc tasks", "monitor", "hr", "coordinate", "sales team", "reports", "order processing", "plan", "documentation", "recruitment", "personal data"], "requirements": {"degrees": ["degree holder"], "majors": ["related disciplines", "marketing", "business administration"], "languages": ["english", "chinese"], "language_level": ["good command"], "hard_skills": ["excel", "word", "powerpoint", "ms office"], "soft_skills": ["good team player", "independently", "multi-task", "well-organized", "attention to details"], "languages_combined": [{"language": "english", "language_level": ["good command"]}, {"language": "chinese", "language_level": ["good command"]}]}, "experience_required": {"duration": ["minimum 1-2 years"], "field": ["related", "advertising", "digital marketing", "media"]}}, {"job_id": "100003009056558", "location_code": "hk", "company": "Commercial Radio Productions Ltd", "job_title": "System Administrator - Linux (Kowloon Tong)", "description": "Commercial Radio Interactive, a division of Commercial Radio Productions Limited and the digital arm of Commercial Radio, are looking for a passionate and energetic\u00a0System Administrator to join our IT team and develop his/her career under the guidance of our experienced senior staff.\n\n\n\nJob Duties\n\nInstalling, configuring, and maintaining Internet systems/services\nPerforming Linux (mainly)/Windows system administration\nDeveloping scripts for system automation\nDesign System Architecture and work with Application Development Team for overall solution\nResponsible for the whole network architecture maintenance, optimization, security, and troubleshooting\nConsistently working on system performance monitoring, tuning and enhancement\nCreating and maintaining technical documentation\n\nJob Requirements\n\n\nHands on experience in Linux/Unix production environment is MUST\nHands on experience on all of the following :\nLoad balancer LVS or HAProxy setup and configuration\nApache / Nginx / Tomcat / Jetty configuration and tuning\nMySQL DB setup, master/slave with no downtime synchronization setup\nDistributed Filesystem (CEPH / Swift / Hadoop)\nHigh availability and large scale service configuration\nVMWare vCenter management/Hyper-V management\nBash / Perl / Python scripting\nDNS, DHCP, FTP, Email\nFirewall, Switch, VPN, TCP/IP Networking\nZabbix / Cacti / Munin / Nagios or other monitoring tools\nAWS / Google VM & service deployment\nLive audio/video streaming support is an advance\nDegree holder in IT or related disciplines\nAt least 3 years experience in system administrator or support role.\nGood problem solving skills, pay attention to details and good communication skills\nResponsible, self motivated, work independently, and process tasks without supervision.\nWilling to work at non office hour for urgent production service support & maintenance.\nCandidate with more experience will be considered for the position of Senior System Administrator\n\nOffice location: Kowloon Tong\n\nApplication Procedure:\n\nWe offer attractive remuneration package, competitive salary, medical scheme and life insurance to the right candidate. Interested candidates, please submit application letter with full resume, present and expected salary by clicking \u201cApply Now\u201d (Please quote the job reference number on the e-mail subject line).\n\nAll information received will be kept in strict confidence and only for employment-related purpose. Only short listed candidates will be invited for interview.", "employment_types": ["Full Time", "Permanent"], "selling_points": ["Hands on experience in Linux/Unix production", "At least 3 years experience in system admin", "Degree holder in IT or related disciplines"], "locations": ["Not Specified"], "categories": ["Information Technology (IT)", "Support", "Network & System", "Media & Advertising", "Broadcasting - TV / Radio"], "post_time": "2022-01-18T04:48:52Z", "salary": {"currency": null, "max": null, "min": null, "period": "monthly", "term": null}, "salary_visible": false, "title_keywords": ["system administrator"], "responsibilities": ["maintaining", "maintenance", "systems", "monitoring", "developing", "design", "troubleshooting", "configuring", "installing", "documentation", "application development", "architecture", "administration"], "requirements": {"degrees": ["degree holder", "master"], "majors": ["related disciplines", "it"], "languages": [], "language_level": [], "hard_skills": ["hyper-v", "no", "vmware", "tcp", "vpn", "firewall", "perl", "aws", "python", "linux", "apache", "dns", "maintenance", "switch", "bash", "ip", "deployment", "swift", "problem solving skills"], "soft_skills": ["communication skills", "work independently", "responsible", "self motivated", "hands on", "attention to details", "problem solving skills"], "languages_combined": []}, "experience_required": {"duration": ["at least 3 years"], "field": []}}, {"job_id": "100003009045569", "location_code": "hk", "company": "Sun Television Cybernetworks Enterprise Limited", "job_title": "Marketing Executive", "description": "Description\nAssist in managing the online marketing channels and social media platforms (YouTube, Facebook, Telegram, Twitter)\nHave a certain understanding of international current affairs, financial information and social development trends\nformulate in-depth content promotion strategies and implementation, including setting directions, content creation, interacting with audiences, promotion, etc\nPerform miscellaneous assignments and assist in ad-hoc projects\nParticipate in planning iSun TV's original financial programs and content\n\n\u00a0Requirements\n\nBachelor Degree in Marketing or related disciplines\n2+ years\u2019 experience in Marketing\nGood written and spoken communication skills in English and Chinese/Mandarin\nStrong sense of responsibility, well organized with exceptional problem-solving skill\nA good team player with strong communication and interpersonal skills\nAbility to introduce new ideas and projects", "employment_types": ["Full Time", "Permanent"], "selling_points": [], "locations": ["Siu Sai Wan"], "categories": ["Media & Advertising", "Broadcasting - TV / Radio", "Marketing / Public Relations", "Digital Marketing"], "post_time": "2022-01-13T08:05:52Z", "salary": {"currency": null, "max": null, "min": null, "period": "monthly", "term": null}, "salary_visible": false, "title_keywords": ["marketing executive"], "responsibilities": ["social media platforms", "implementation", "facebook", "ad-hoc projects", "planning"], "requirements": {"degrees": ["degree", "bachelor"], "majors": ["related disciplines", "marketing"], "languages": ["english", "chinese", "mandarin"], "language_level": ["good"], "hard_skills": ["problem-solving"], "soft_skills": ["communication skills", "good team player", "sense of responsibility", "problem-solving", "well organized", "communication and interpersonal skills"], "languages_combined": [{"language": "english", "language_level": ["good"]}, {"language": "chinese", "language_level": ["good"]}, {"language": "mandarin", "language_level": ["good"]}]}, "experience_required": {"duration": ["2+ years"], "field": ["marketing"]}}, {"job_id": "100003009032658", "location_code": "hk", "company": "Telus International AI Inc.", "job_title": "Media Search Analyst-Cantonese language(HK)", "description": "Responsibilities:\n\nWork with professional Broadcast system and Master Control for Digital TV.\nPrepare and inspect on-air schedules and materials according to procedures.\nHandle program transmission operations, pre-recorded playout and live broadcast to ensure broadcast safely.\nMonitor and manipulate incoming and outgoing TV signals traffic and support satellite, live streaming and base-band feed receptions according to bookings.\nPrepare operational report for logistic and follow-up purposes.\n\nRequirements:\n\n\nForm 5/DSE graduates or above, preferably in computing/engineering related disciplines. Fresh graduates will also be considered.\nUnderstanding of broadcast operations, with experience on using different kinds of automation system is an advantage.\nTeam player and detail-oriented at work.\nAble to work in shift hours, including overnight shift.\nExcellent command of written and spoken English and Chinese, proficiency in Putonghua, MS Word and Excel.\n\n\u8077\u8cac\uff1a\n\n\u00a0\u00a0\u00a0\u00a0\u00a0\u00a0 \u8655\u7406\u5c08\u696d\u6578\u78bc\u96fb\u8996\u5ee3\u64ad\u7cfb\u7d71\u548c\u4e2d\u592e\u4fe1\u865f\u7e3d\u63a7\u5de5\u4f5c\u3002\n\u00a0\u00a0\u00a0\u00a0\u00a0\u00a0 \u6309\u7a0b\u5e8f\u6aa2\u6536\u7bc0\u76ee\u64ad\u51fa\u6392\u7a0b\u53ca\u5ee3\u64ad\u6750\u6599\u3002\n\u00a0\u00a0\u00a0\u00a0\u00a0\u00a0 \u8655\u7406\u7bc0\u76ee\u64ad\u653e\uff0c\u5305\u62ec\u9810\u9304\u548c\u73fe\u5834\u76f4\u64ad\uff0c\u4fdd\u969c\u64ad\u51fa\u5b89\u5168\u3002\n\u00a0\u00a0\u00a0\u00a0\u00a0\u00a0 \u76e3\u5bdf\u548c\u64cd\u63a7\u4fe1\u865f\u9032\u51fa\uff0c\u6839\u64da\u9810\u8a02\u652f\u6301\u885b\u661f\u3001\u5be6\u6642/\u78bc\u6d41\u5a92\u9ad4\u994b\u9001\u63a5\u6536\u3002\n\u00a0\u00a0\u00a0\u00a0\u00a0\u00a0 \u70ba\u5f8c\u52e4\u548c\u7ba1\u7406\u6e96\u5099\u904b\u71df\u5831\u544a\u3002\n\u8981\u6c42\uff1a\n\u00a0\u00a0\u00a0\u00a0\u00a0\u00a0 \u9999\u6e2f\u4e2d\u5b78\u6703\u8003/\u6587\u6191\u8a66\u7562\u696d\u6216\u4ee5\u4e0a\u5b78\u6b77\uff0c\u4ee5\u96fb\u8166/\u5de5\u7a0b\u6216\u76f8\u95dc\u5b78\u79d1\u70ba\u4f73\u3002\u61c9\u5c46\u7562\u696d\u751f\u4e5f\u6703\u8003\u616e\u3002\n\u00a0\u00a0\u00a0\u00a0\u00a0\u00a0 \u4e86\u89e3\u5ee3\u64ad\u904b\u4f5c\uff0c\u6709\u4f7f\u7528\u4e0d\u540c\u985e\u578b\u81ea\u52d5\u5316\u7cfb\u7d71\u7d93\u9a57\u8005\u512a\u5148\u3002\n\u00a0\u00a0\u00a0\u00a0\u00a0\u00a0 \u6ce8\u91cd\u5718\u968a\u5408\u4f5c\u53ca\u5de5\u4f5c\u7d30\u7bc0\u3002\n\u00a0\u00a0\u00a0\u00a0\u00a0\u00a0 \u80fd\u5920\u8f2a\u73ed\u5de5\u4f5c\uff0c\u5305\u62ec\u591c\u73ed\u3002\n\u00a0\u00a0\u00a0\u00a0\u00a0\u00a0 \u512a\u79c0\u4e2d\u82f1\u6587\u66f8\u9762\u548c\u53e3\u8a9e\u80fd\u529b\uff0c\u719f\u7df4\u666e\u901a\u8a71\uff0c\u901a\u66c9MS Word\u3001Excel\u904b\u4f5c\nFor more details of our company, please visit our website at http://www.ifeng.com/\n\n\n\nWe offer attractive remuneration package to the right candidate. Interested parties please click \u201cApply Now\u201d to submit applications or send applications with detailed resume stating career history, present & expected salary and date available to Human Resources Department, Phoenix Satellite Television Co. Ltd. via fax: 2200 8620.\n\n\u00a0Personal data collected will be used for recruitment purpose only. Applicants not hearing from us within 6 weeks may consider their applications unsuccessful and all related information will be destroyed after 6 months.", "employment_types": ["Part Time", "Temporary", "Contract", "Freelance"], "selling_points": ["Work from home", "Freelance", "Media"], "locations": ["Central & Western Area"], "categories": ["Information Technology (IT)", "IT - Webmaster / SEO", "Marketing / Public Relations", "Marketing - Market Research", "Media & Advertising", "Broadcasting - TV / Radio"], "post_time": "2022-01-10T06:28:52Z", "salary": {"currency": "HKD", "max": 134, "min": 75, "period": "hourly", "term": null}, "salary_visible": true, "title_keywords": ["analyst"], "responsibilities": ["control", "schedules", "operations", "procedures", "monitor", "report"], "requirements": {"degrees": ["form 5", "dse"], "majors": ["related disciplines", "engineering"], "languages": ["putonghua", "english", "chinese"], "language_level": ["excellent", "proficiency"], "hard_skills": ["excel", "ms word"], "soft_skills": ["team player", "detail-oriented"], "languages_combined": [{"language": "putonghua", "language_level": ["proficiency", "excellent"]}, {"language": "english", "language_level": ["proficiency", "excellent"]}, {"language": "chinese", "language_level": ["proficiency", "excellent"]}]}, "experience_required": {"duration": [], "field": []}}, {"job_id": "100003009039816", "location_code": "hk", "company": "PCCW Media Limited", "job_title": "Business Analysis Officer", "description": "Your New Role:\n\n\nProgram production including property, technology and other features\nFinancial news reporting / On air presentation for Now Business News Channel\nSocial media content production\nWhat makes you succeed:\u00a0\u00a0\n\n\nDegree holder in Journalism/ Finance/ Economics or related discipline\nFamiliar with and sensitive to financial news and current affairs\nProficiency in Chinese word processing is a must\nTeam player\nGood communication skills\nSelf-motivated and able to work under pressure and tight timeline\nShift duty is required\n\n\nWe offer attractive & competitive salary and benefits, an exciting work environment and excellent career development opportunities.\u00a0If you have the desire for an exciting and rewarding career, please send us your resume,\u00a0stating your present and expected salary to Human Resources Department by clicking \"Apply Now\"\u00a0\n\nFor more information on other job opportunities of PCCW, please visit our website at\u00a0http://www.pccw.com/Careers/Job+Opportunities+%26+Application/Current+Opportunities?language=en_US\nPCCW is an equal opportunity employer and welcomes applications from all qualified candidates. Information provided will be treated in strict confidence and will only be used for recruitment-related purposes. Personal data provided by job applicants will be used strictly in accordance with the employer\u2019s\u00a0privacy statement\u00a0(www.pccw.com/privacy-statement/index.page), a copy of which will be provided immediately upon request.\u00a0", "employment_types": ["Full Time", "Permanent"], "selling_points": ["Conduct analysis on channel performance", "Prepare monthly statements to content partners", "Define user requirement for system enhancement"], "locations": ["Kowloon Bay"], "categories": ["Accounting", "Accounting Clerk / Supervisor", "Media & Advertising", "Broadcasting - TV / Radio"], "post_time": "2022-01-11T11:36:37Z", "salary": {"currency": null, "max": null, "min": null, "period": null, "term": null}, "salary_visible": false, "title_keywords": ["officer"], "responsibilities": ["communication", "reporting", "social media content", "work under pressure"], "requirements": {"degrees": ["degree holder"], "majors": ["journalism", "finance", "economics"], "languages": ["chinese"], "language_level": ["proficiency"], "hard_skills": ["chinese word processing"], "soft_skills": ["communication skills", "self-motivated", "sensitive to", "team player", "presentation", "work under pressure"], "languages_combined": [{"language": "chinese", "language_level": ["proficiency"]}]}, "experience_required": {"duration": [], "field": []}}, {"job_id": "100003009044605", "location_code": "hk", "company": "Phoenix Satellite Television Co Ltd", "job_title": "JUNIOR GRAPHIC DESIGNER (CONTRACT)", "description": "The Job:\u00a0\n\nThe successful candidate will have the responsibilities to :\u00a0\n\nPreview, vet and approve programme, commercials and promotional materials to ensure content compliance of all media business with the applicable industry regulations & standards and\u00a0 consistency with the company brand image\nConduct market analyses to keep abreast of the key regulatory changes in Hong Kong and worldwide\nThe Person:\u00a0\u00a0\n\nDegree holder in Communication, Media Studies or other related discipline\n1-2 years compliance experience in TV or media industry\nSelf-motivated, independent and detail minded\nEnthusiasm in and appreciation of content, television and movie industry\nGood command of spoken and written English and Chinese\u00a0\nWe offer attractive and competitive salary and benefits, an exciting work environment and excellent career development opportunities.\u00a0If you have the desire for an exciting and rewarding career, please send us your resume,\u00a0stating your present and expected salary to Human Resources Department by\u00a0 clicking \"Apply Now\".\n\n\n\nFor more information on other job opportunities of PCCW, please visit our website at\u00a0<http://www.pccw.com/Careers/Job+Opportunities+&+Application/Current+Opportunities?language=en_US>\n\nPCCW is an equal opportunity employer and welcomes applications from all qualified candidates. Information provided will be treated in strict confidence and will only be used for recruitment-related purposes. Personal data provided by job applicants will be used strictly in accordance with the employer personal data policies (http://www.pccw.com/staticfiles/PCCWCorpsite/Terms%20of%20Use/Privacy%20Policy%20Statement/(PCCW)%20HR%20Privacy%20Policy%20Statement%20(version%20-%20Nov%202017).pdf), a copy of which will be provided immediately upon request.", "employment_types": ["Contract"], "selling_points": [], "locations": ["Tai Po Area"], "categories": ["Media & Advertising", "Broadcasting - TV / Radio"], "post_time": "2022-01-13T04:49:25Z", "salary": {"currency": null, "max": null, "min": null, "period": null, "term": null}, "salary_visible": false, "title_keywords": ["junior graphic designer"], "responsibilities": ["regulations", "compliance", "promotional materials"], "requirements": {"degrees": ["degree holder"], "majors": [], "languages": ["english", "chinese"], "language_level": ["good command"], "hard_skills": [], "soft_skills": ["communication", "self-motivated", "independent"], "languages_combined": [{"language": "english", "language_level": ["good command"]}, {"language": "chinese", "language_level": ["good command"]}]}, "experience_required": {"duration": ["1-2 years"], "field": ["compliance", "media"]}}, {"job_id": "100003009034184", "location_code": "hk", "company": "The Hong Kong Jockey Club", "job_title": "Senior Audio & Visual Engineer", "description": "Responsibilities:\n\nAssist the Public Relations Department in managing the daily operations of the department.\nResponsible for maintaining official company accounts on social media.\nDevelop press releases in Chinese and English and coordinate with other departments in preparation of the corporate publications.\nBuild rapport and communication with related regulatory bodies and influential groups, etc.\nDevise and implement corporate communications strategies and organize corporate promotional events and media functions.\nBuild and maintain relationship with local and overseas press on all publicity-related activities.\n\nRequirements:\n\nUniversity graduate with at least 2 years experience in similar capacity preferably in sizable organizations and / or television industry.\nExtensive experience in corporate PR and media relations with good communication skill.\nProactive, enthusiastic and able to work independently and tight time frames.\nFamiliar with MS word, Excel and proficiency in Chinese Word Processing is a must.\nKnowledge in social media interface (Facebook, Twitter, Weibo, Wechat).\nSolid experience\u00a0in managing and creating content for social media platforms.\nProficient in Premiere Pro,\u00a0Photoshop and After Effect would be an advantage.\nExcellent command of written and spoken English and Chinese, proficiency in Putonghua is an advantage.\n\nFor more details of our company, please visit our website at\u00a0http://www.ifeng.com/\n\n\n\nWe offer attractive remuneration package to the right candidate. Interested parties please send applications with detailed resume stating career history, present & expected salary and date available to Human Resources Department, Phoenix Satellite Television Co. Ltd. via e-mail: phxhr@phoenixtv. com or via fax: 2200 8620.\n\nPersonal data collected will be used for recruitment purpose only.\u00a0 Applicants not hearing from us within 6 weeks may consider their applications unsuccessful and all related information will be destroyed after 6 months.", "employment_types": ["Full Time"], "selling_points": ["Supervise front-line operations team", "Supervise the AV system implementation", "7 years of experience"], "locations": ["Causeway Bay"], "categories": ["Media & Advertising", "Production", "Broadcasting - TV / Radio", "Photography / Video"], "post_time": "2022-01-10T02:54:58Z", "salary": {"currency": null, "max": null, "min": null, "period": null, "term": null}, "salary_visible": false, "title_keywords": ["engineer"], "responsibilities": ["social media", "maintaining", "company accounts", "coordinate with", "develop", "communication", "daily operations", "maintain"], "requirements": {"degrees": ["university graduate"], "majors": [], "languages": ["putonghua", "english", "chinese"], "language_level": ["advantage", "proficiency", "excellent"], "hard_skills": ["excel", "chinese word processing", "wechat", "premiere pro", "photoshop", "facebook", "after effect", "ms word"], "soft_skills": ["work independently", "communication skill", "enthusiastic", "proactive", "extensive"], "languages_combined": [{"language": "putonghua", "language_level": ["proficiency", "advantage", "excellent"]}, {"language": "english", "language_level": ["proficiency", "advantage", "excellent"]}, {"language": "chinese", "language_level": ["proficiency", "advantage", "excellent"]}]}, "experience_required": {"duration": ["at least 2 years"], "field": ["social media", "pr", "media"]}}, {"job_id": "100003009036572", "location_code": "hk", "company": "HK01 Company Limited", "job_title": "\u8a18\u8005 - \u5a1b\u6a02 (\u901a\u5bb5\u66f4)", "description": "Work from Home - Hong Kong\n\nMedia Search Analyst - An exciting work from home opportunity related to Music, Video App Store and HomePod! We offer a flexible schedule of up to 20 hours per week completing tasks in a web-based evaluation tool.\n\nThe Role:\u00a0\n\nEvaluation of online task types related to Music, Video, App Store and HomePod to help improve the overall quality and relevance of online content and research.\n\nWhat are the main requirements for the job?\n\nFluency in English & Cantonese is essential\nYou must be living in Hong Kong for a minimum of 1 year\nApple user - Your email address must be associated with an Apple ID\nExperience/know-how of Apple products is mandatory\nAll candidates will need to pass online evaluations to demonstrate capability of reading and applying the guidelines.\n\n\u00a0Benefits & Perks:\n\nFlexible hours to work around home life\nBetter Work-Life balance\nRemote work & location independence\nPositive environmental impact\nIndependent contractor role\n\nWhat\u2019s next?\u00a0\n\nDon\u2019t Delay! Submit your application through the following link and a member of our\n\nrecruitment team will review your application:\n\nhttps://e-recruit.sap.lionbridge.com/sap(bD1lbiZjPTEwMCZkPW1pbg==)/bc/bsp/sap/unrg_appl/application.do?param=cGluc3RfZ3VpZD1FQkJGQzY1NjdFNDA2RUYxQTg0NzAwMTU1RDAwQUMwOQ%3d%3d&amp%3bsap-client=100&amp%3bsap-client=100&amp%3bsap-language=EN&amp%3brcfcontext=GR&rcfcontext=GR\n\nWant to know more? Please visit:\n\nhttps://jobs.telusinternational.com/en_US/careers/PipelineDetail/Media-Search-Analyst-Hong-Kong-Cantonese-language/24930\n\n", "employment_types": ["Full Time", "Permanent"], "selling_points": ["\u8ca0\u8cac\u672c\u5730\u53ca\u570b\u969b\u5a1b\u6a02\u65b0\u805e\u63a1\u8a2a\u5de5\u4f5c", "\u8ca0\u8cac\u5a1b\u6a02\u65b0\u805e\u8996\u983b\u88fd\u4f5c", "\u9700\u8f2a\u66f4\u7576\u503c\u53ca\u901a\u5bb5\u5de5\u4f5c"], "locations": ["Tsuen Wan Area"], "categories": ["Media & Advertising", "Others", "Editorial / Journalism", "Broadcasting - TV / Radio"], "post_time": "2022-01-10T11:07:05Z", "salary": {"currency": null, "max": null, "min": null, "period": "monthly", "term": null}, "salary_visible": false, "title_keywords": ["\u8a18\u8005"], "responsibilities": ["guidelines", "quality", "schedule", "evaluation"], "requirements": {"degrees": [], "majors": [], "languages": ["cantonese", "english"], "language_level": ["fluency"], "hard_skills": ["id", "web"], "soft_skills": ["flexible"], "languages_combined": [{"language": "cantonese", "language_level": ["fluency"]}, {"language": "english", "language_level": ["fluency"]}]}, "experience_required": {"duration": [], "field": []}}, {"job_id": "100003009041735", "location_code": "hk", "company": "Phoenix Satellite Television Co Ltd", "job_title": "GRAPHIC PRODUCER", "description": "Your New Role:\n\n\nAs member of the Finance team in PCCW Media, you will conduct analysis on our channel performance, liaise with various content partners on financial issues, be responsible for managing content system and preparing monthly statements to content partners. Your key role would be working with IT, operation and marketing teams to define user requirement for system enhancement to support billing of new services/channels and conduct user acceptance test. You will manage AP, prepare respective accounting entries in month end closing and support the team in other ad hoc analysis.\n\n\nWhat makes you succeed:\n\n\nDegree holder, preferably in Accounting, business or IT background\nAt least 2 years relevant experience\nHighly proficient in Microsoft Excel. Prior experience in handling Oracle accounting and billing system is an advantage\nNumerical, analytical and self-motivated\nImmediate available is highly preferred\n\nWant to be one of us?\n\nWe offer attractive & competitive salary and benefits, an exciting work environment and excellent career development opportunities.\u00a0If you have the desire for an exciting and rewarding career, please send us your resume,\u00a0stating your present and expected salary to Human Resources Department by clicking \"Apply Now\"\u00a0\u00a0\n\nFor more information on other job opportunities of PCCW, please visit our website at\nhttp://www.pccw.com/Careers/Job+Opportunities+%26+Application/Current+Opportunities?language=en_US\n\nPCCW is an equal opportunity employer and welcomes applications from all qualified candidates. Information provided will be treated in strict confidence and will only be used for recruitment-related purposes. Personal data provided by job applicants will be used strictly in accordance with the employer personal data policies (http://www.pccw.com/staticfiles/PCCWCorpsite/Terms%20of%20Use/Privacy%20Policy%20Statement/(PCCW)%20HR%20Privacy%20Policy%20Statement%20(version%20-%20Nov%202017).pdf), a copy of which will be provided immediately upon request.", "employment_types": ["Full Time", "Permanent"], "selling_points": [], "locations": ["Tai Po Area"], "categories": ["Media & Advertising", "Broadcasting - TV / Radio"], "post_time": "2022-01-12T04:17:03Z", "salary": {"currency": null, "max": null, "min": null, "period": null, "term": null}, "salary_visible": false, "title_keywords": ["producer"], "responsibilities": ["ap", "user requirement", "month end closing", "ad hoc", "analysis", "teams", "finance team", "liaise with", "support the team"], "requirements": {"degrees": ["degree holder"], "majors": ["business", "accounting", "it"], "languages": [], "language_level": [], "hard_skills": ["ap", "analysis", "microsoft excel", "billing system", "oracle"], "soft_skills": ["self-motivated", "responsible"], "languages_combined": []}, "experience_required": {"duration": ["at least 2 years"], "field": ["billing", "accounting", "relevant experience"]}}, {"job_id": "100003009037547", "location_code": "hk", "company": "Commercial Radio Productions Ltd", "job_title": "Programmer (Mobile Application Development)", "description": "Your New Role\n\n\nMonitor all incoming signal such as microwave link, satellite reception etc.\nCarry out system routine check\nProvide support in broadcast system setup and maintenance\n\nWhat makes you succeed\n\n\nDegree or Higher Diploma in Electronic Engineering or related disciplines\nMinimum 1 year relevant working experience in TV or Broadcast industry\nTeam player with good communication and coordination skills\u00a0\nAble to work independently\nShift duty including overnight shift is required\nCandidate with less experience will be considered for Assistant Broadcast Engineer or Technician\n\nWant to be one of us?\n\nWe offer attractive & competitive salary and benefits, an exciting work environment and excellent career development opportunities. If you have the desire for an exciting and rewarding career, please send us your resume, quoting the reference number, stating your present and expected salary to\u00a0Human Resources Department by clicking \"Apply Now\"\n\nFor more information on other job opportunities of PCCW, please visit our website at\u00a0\nhttp://www.pccw.com/Careers/Job+Opportunities+%26+Application/Current+Opportunities?language=en_US\n\nPCCW is an equal opportunity employer and welcomes applications from all qualified candidates. Information provided will be treated in strict confidence and will only be used for recruitment-related purposes. Personal data provided by job applicants will be used strictly in accordance with the employer personal data policies (http://www.pccw.com/staticfiles/PCCWCorpsite/Terms%20of%20Use/Privacy%20Policy%20Statement/(PCCW)%20HR%20Privacy%20Policy%20Statement%20(version%20-%20Nov%202017).pdf), a copy of which will be provided immediately upon request.", "employment_types": ["Full Time", "Permanent"], "selling_points": ["University graduate in Computer Science or related", "iOS Mobile development", "Spirit of Commercial Radio & friendly team culture"], "locations": ["Not Specified"], "categories": ["Information Technology (IT)", "Application Specialist - Software", "Software Development", "Media & Advertising", "Broadcasting - TV / Radio"], "post_time": "2022-01-11T03:05:21Z", "salary": {"currency": null, "max": null, "min": null, "period": "monthly", "term": null}, "salary_visible": false, "title_keywords": ["programmer"], "responsibilities": ["provide support", "maintenance", "monitor", "communication", "coordination", "setup"], "requirements": {"degrees": ["diploma", "degree"], "majors": ["related disciplines", "engineering"], "languages": [], "language_level": [], "hard_skills": ["signal", "maintenance"], "soft_skills": ["communication", "team player", "coordination skills", "work independently"], "languages_combined": []}, "experience_required": {"duration": ["minimum 1 year"], "field": ["relevant working experience"]}}, {"job_id": "100003009028820", "location_code": "hk", "company": "The Hong Kong Jockey Club", "job_title": "Audio & Visual Operations Support Manager (Technical Support)", "description": "\u4e3b\u8981\u8077\u8cac\n\n\u5f9e\u591a\u89d2\u5ea6\u767c\u6398\u8da3\u805e\u3001\u641c\u96c6\u8cc7\u6599\u53ca\u64b0\u5beb\u6587\u7ae0\n\u8ca0\u8cac\u672c\u5730\u53ca\u570b\u969b\u5a1b\u6a02\u65b0\u805e\u63a1\u8a2a\u5de5\u4f5c\n\u8ca0\u8cac\u5a1b\u6a02\u65b0\u805e\u8996\u983b\u88fd\u4f5c\n\n\u5165\u8077\u8981\u6c42\n\n\u6301\u5927\u5b78\u5b78\u4f4d\u6216\u4ee5\u4e0a\u5b78\u6b77\uff0c\u4e3b\u4fee\u5b78\u79d1\u4e0d\u62d8\n\u719f\u6089\u5404\u5730\u5a1b\u6a02\u8cc7\u8a0a\u6700\u65b0\u52d5\u614b\n\u64c1\u6709\u88fd\u4f5c\u53ca\u62cd\u651d\u5f71\u7247\u548c\u7d93\u71df\u793e\u4ea4\u5e73\u53f0\u7d93\u9a57\u66f4\u4f73\n\u5177\u65b0\u805e\u89f8\u89ba\u8207\u5224\u65b7\u529b\u3001\u61c9\u8b8a\u529b\u9ad8\u3001\u7a4d\u6975\u4e3b\u52d5\uff0c\u53ca\u64c5\u9577\u8207\u4eba\u6e9d\u901a\n\u5c0d\u5468\u908a\u4e8b\u7269\u6709\u597d\u5947\u5fc3\uff0c\u80fd\u5f9e\u4e0d\u540c\u6e20\u9053\u767c\u6398\u65b0\u9bae\u4e8b\u7269\n\u9700\u8f2a\u66f4\u7576\u503c\u53ca\u901a\u5bb5\u5de5\u4f5c\n\u61c9\u5fb5\u8005\u8acb\u5728\u5c65\u6b77\u8868\u4e2d\u9644\u4e0a\u76f8\u95dc\u4e4b\u500b\u4eba\u4f5c\u54c1\n\n\u8acb\u65bc\u6c42\u8077\u4fe1\u8a3b\u660e\u6b32\u61c9\u5fb5\u4e4b\u8077\u4f4d\u3002\u6211\u5011\u6703\u70ba\u5408\u9069\u7684\u4eba\u9078\u63d0\u4f9b\u512a\u539a\u7684\u85aa\u916c\u5f85\u9047\u53ca\u798f\u5229(\u5305\u62ec\u4e94\u5929\u5de5\u4f5c\u5468)\u3002\u61c9\u5fb5\u8005\u8acb\u6309\u300cApply Now\u300d\u6309\u9215\u4e26\u63d0\u4f9b\u5c65\u6b77\u3001\u73fe\u6642\u53ca\u8981\u6c42\u7684\u85aa\u916c\u5f85\u9047\u7b49\u8cc7\u6599\u4f5c\u8077\u4f4d\u7533\u8acb\u3002\n\n\u6240\u6709\u6536\u96c6\u7684\u500b\u4eba\u8cc7\u6599\u90fd\u6703\u56b4\u683c\u4fdd\u5bc6\u4e26\u53ea\u4f5c\u62db\u8058\u7528\u9014\u30023\u500b\u6708\u5167\u672a\u7372\u9762\u8a66\u901a\u77e5\u7684\u7533\u8acb\u8005\uff0c\u53ef\u8996\u5176\u7533\u8acb\u70ba\u4e0d\u6210\u529f\u8ad6\u3002\u53e6\u4e00\u65b9\u9762\uff0c\u5c65\u6b77\u4ea6\u53ef\u80fd\u6839\u64da\u516c\u53f8\u96c6\u5718\u7684\u5167\u90e8\u9700\u8981\uff0c\u9032\u884c\u5167\u90e8\u8f49\u79fb\u3002\u672a\u7372\u63a5\u7d0d\u7684\u7533\u8acb\u8cc7\u6599\u5c07\u6703\u572812\u500b\u6708\u5167\u92b7\u6bc0\u3002", "employment_types": ["Full Time"], "selling_points": ["Race Day", "Non Race Day", "Contract preparation and execution experience"], "locations": ["Causeway Bay"], "categories": ["Media & Advertising", "Production", "Broadcasting - TV / Radio"], "post_time": "2022-01-10T02:59:23Z", "salary": {"currency": null, "max": null, "min": null, "period": null, "term": null}, "salary_visible": false, "title_keywords": ["technical support", "operations", "manager"], "responsibilities": [], "requirements": {"degrees": [], "majors": [], "languages": [], "language_level": [], "hard_skills": [], "soft_skills": [], "languages_combined": []}, "experience_required": {"duration": [], "field": []}}, {"job_id": "100003009029881", "location_code": "hk", "company": "Metro Broadcast Corporation Ltd", "job_title": "Programme Assistant (Ref: MF)", "description": "\u00a0Responsibilities:\n\nDesign high quality television broadcast video graphics.\nCreate and implement design concepts with 2D & 3D computer software.\nWork closely with the creative team in design & production.\n\nRequirements:\n\nAt least 1 year experience in broadcast design or graphic design.\nProficient with all major Adobe software (Photoshop, Illustrator & After Effects) and 3D software (3D Max, Maya).\nInnovative with excellent conceptual creativity.\nAble to work independently under tight deadlines.\nWilling to work on 24-hour shift and proficiency in Putonghua is an advantage.\nWorking on On-Air Promo graphics experience is an advantage.\nStrong 3D skill is an advantage.\nFresh graduates are also welcomed.\n\nFor more details of our company, please visit our website at http://www.ifeng.com\n\n\n\nWe offer attractive remuneration package to the right candidate. Interested parties please send applications with detailed resume stating career history, present & expected salary and date available to Human Resources Department, Phoenix Satellite Television Co. Ltd. via e-mail: phxhr@phoenixtv. com or via fax: 2200 8620.\n\nPersonal data collected will be used for recruitment purpose only.\u00a0 Applicants not hearing from us within 6 weeks may consider their applications unsuccessful and all related information will be destroyed after 6 months.", "employment_types": ["Full Time", "Permanent"], "selling_points": [], "locations": ["Hung Hom"], "categories": ["Media & Advertising", "Production", "Broadcasting - TV / Radio"], "post_time": "2022-01-07T06:21:46Z", "salary": {"currency": null, "max": null, "min": null, "period": null, "term": null}, "salary_visible": false, "title_keywords": ["assistant"], "responsibilities": ["graphics", "design concepts", "software", "quality", "design"], "requirements": {"degrees": [], "majors": [], "languages": ["putonghua"], "language_level": ["advantage", "proficiency"], "hard_skills": ["graphics", "3d software", "maya", "illustrator", "after effects", "adobe software", "max", "photoshop"], "soft_skills": ["work independently", "innovative"], "languages_combined": [{"language": "putonghua", "language_level": ["advantage", "proficiency"]}]}, "experience_required": {"duration": ["at least 1 year"], "field": ["graphic design", "design"]}}, {"job_id": "100003009033328", "location_code": "hk", "company": "Asia Innovations HK Limited", "job_title": "Entertainment Talent Manager", "description": "The Department\n\nThe Customer and International Business Development Division (C&I) is responsible for providing quality wagering experience to local and overseas customers of The Hong Kong Jockey Club. It operates 88 Race Meetings a year, 37 Simulcasts days, a thrice-weekly Mark 6 Draw, 7X24 Digital Channels, 7X24 Football Betting Services on over 11,000 different leagues per year. The ultimate aim is to provide an impressive total customer experience leading to sustainable turnover growth in a responsible manner.\n\nThe Broadcasting Operations team is responsible for live coverage of horse racing in Hong Kong, production of related promotional video, formatting betting and racing-related information into TV graphic displays and documentaries for on-air at TV stations as well as display on the giant display screens and closed-circuit TV network at the racecourses.\u00a0 The Chinese Telecast Section in Broadcasting Operations is responsible for producing and packaging racing television programs, both for local broadcasting by terrestrial free-to-air television, pay cable television, overseas simulcasting operations of which betting on Hong Kong\u2019s horse racing is operated.\n\n\n\nYou will:\n\n\nSupervise front-line operations team to ensure smooth operations of Club\u2019s TV Production systems and racecourse AV systems\nPerform quality control and monitoring to ensure Club\u2019s programme signals are complied with broadcasting standard for both local and overseas live transmission\nOversee all operational issues and contingency planning of AV / TV systems, and performs system fall-back & recovery when required\nEnsure the efficiency and quality of video and audio signal transmissions for both overseas race simulcasting and local television/online broadcasting\nLiaise with internal and external clients on AV system design\nSupervise the AV system implementation to ensure the completion on time and within budget\nMaintain and/or develop expertise in audio and video concepts and technologies, as well as other skillsets required within the professional AV industry\nInitial and edit project\u00a0 documentation for tendering and procurement process\nAssist the line manager in any projects as assigned\nEnsures compliance with Responsible Gambling Policy (RGP) and all stipulated legal requirements pertaining to wagering, thereby protecting the integrity of the Club\u2019s business\nUndertakes other duties as assigned by Line Manager\n\nYou should have:\n\n\n\u00a0\u00a0\u00a0\u00a0\u00a0\u00a0\u00a0\u00a0 A Bachelor degree or higher diploma in Communication/Visual Arts with major in AV Engineering or TV production or related disciplines\n\u00a0\u00a0\u00a0\u00a0\u00a0\u00a0\u00a0\u00a0 A minimum of 7 years\u2019 experience with AV Consultant or system integrator or a TV Station and venue AV system design & development\n\u00a0\u00a0\u00a0\u00a0\u00a0\u00a0\u00a0\u00a0 Experience in AV industry managerial role with strong leadership skill\n\u00a0\u00a0\u00a0\u00a0\u00a0\u00a0\u00a0\u00a0 Good sense of trends and the initiative to stay up-to-date, be self-motivated, proactive and able to work independently and willing to work under pressure\n\u00a0\u00a0\u00a0\u00a0\u00a0\u00a0\u00a0\u00a0 Good communication skills, fluency in both spoken and written English and Chinese\n\u00a0\u00a0\u00a0\u00a0\u00a0\u00a0\u00a0\u00a0 Ability to work independently and in a team environment\u00a0\u00a0\u00a0\u00a0\u00a0\u00a0\u00a0\u00a0\u00a0\u00a0\u00a0\n\u00a0\u00a0\u00a0\u00a0\u00a0\u00a0\u00a0\u00a0 Willingness to work long and irregular hours including Sunday and public holiday\n\nTerms of employment\nThe level of appointment will be commensurate with qualification and experience.\u00a0 A contract employment will be offered to the successful candidate. Contract renewal will be subject to mutual agreement between the Club and the individual.\u00a0\n\n\nHow to Apply\nPlease send your resume, complete with expected salary and job reference by clicking \"Apply Now\" button or to:\nThe Human Resources Department\nThe Hong Kong Jockey Club\n1 Sports Road, Happy Valley\nHong Kong\n\nWe are an equal opportunity employer. Personal data provided by job applicants will be used strictly in accordance with the Club's notice to employees and prospective employees relating to the Personal Data (Privacy) Ordinance. A copy of which will be provided immediately upon request.", "employment_types": ["Full Time"], "selling_points": [], "locations": ["Tsim Sha Tsui"], "categories": ["Sales, CS & Business Devpt", "Business Development", "Others", "Entertainment - Artists / Singers / Musicians", "Media & Advertising", "Broadcasting - TV / Radio"], "post_time": "2022-01-09T08:50:23Z", "salary": {"currency": null, "max": null, "min": null, "period": "monthly", "term": null}, "salary_visible": false, "title_keywords": ["manager"], "responsibilities": ["operations", "budget", "quality", "tendering", "communication", "maintain", "liaise with", "personal data", "work under pressure", "other duties", "promotional video", "compliance", "implementation", "develop", "visual", "audio", "monitoring", "ensure smooth operations", "documentation", "systems", "system design", "formatting", "quality control", "planning"], "requirements": {"degrees": ["diploma", "degree", "bachelor"], "majors": ["related disciplines", "engineering"], "languages": ["english", "chinese"], "language_level": ["fluency", "good"], "hard_skills": ["av system", "documentation", "signal"], "soft_skills": ["communication skills", "self-motivated", "work independently", "responsible", "integrity", "willingness to work", "communication", "smooth", "leadership skill", "proactive", "initiative", "work under pressure"], "languages_combined": [{"language": "english", "language_level": ["fluency", "good"]}, {"language": "chinese", "language_level": ["fluency", "good"]}]}, "experience_required": {"duration": ["minimum of 7 years"], "field": ["development", "business development", "managerial", "system design"]}}, {"job_id": "100003009031278", "location_code": "hk", "company": "The Vine Church Limited", "job_title": "Videographer", "description": "Responsibilities:\n\nDesign high quality television broadcast video graphics\u00a0for news;\nWorking on On-Air Promo graphics;\nCreate and implement design concepts with 2D & 3D computer software;\nWork closely with the creative team in design & production.\n\nRequirements:\n\nAt least 3-year experience in broadcast design or graphic design;\nProficient with all major Adobe software (Photoshop, Illustrator & After Effects) and 3D software (Cinema4D);\nInnovative with excellent conceptual creativity;\nAble to work independently under tight deadlines;\nProficiency in Putonghua is an advantage;\nStrong 3D skill is an advantage;\nKnowledge of Unreal Engine is an advantage;\nLess experience will be considered as graphic designer.\n\n\n\nFor more details of our company, please visit our website at http://www.ifeng.com/\n\nWe offer attractive remuneration package to the right candidate. Interested parties please send applications with detailed resume stating career history, present & expected salary and date available to Human Resources Department, Phoenix Satellite Television Co. Ltd. via e-mail: phxhr@ phoenixtv.com or via fax: 2200 8620.\n\nPersonal data collected will be used for recruitment purpose only.\u00a0 Applicants not hearing from us within 6 weeks may consider their applications unsuccessful and all related information will be destroyed after 6 months.", "employment_types": ["Full Time"], "selling_points": [], "locations": ["Wan Chai"], "categories": ["Media & Advertising", "Production", "Broadcasting - TV / Radio", "Photography / Video"], "post_time": "2022-01-07T09:07:46Z", "salary": {"currency": null, "max": null, "min": null, "period": "monthly", "term": null}, "salary_visible": false, "title_keywords": ["videographer"], "responsibilities": ["graphics", "design concepts", "software", "quality", "design"], "requirements": {"degrees": [], "majors": [], "languages": ["putonghua"], "language_level": ["advantage", "proficiency"], "hard_skills": ["3d software", "illustrator", "after effects", "adobe software", "photoshop"], "soft_skills": ["work independently", "innovative"], "languages_combined": [{"language": "putonghua", "language_level": ["proficiency", "advantage"]}]}, "experience_required": {"duration": ["at least 3-year"], "field": ["graphic design", "graphic", "designer", "design"]}}, {"job_id": "100003009031233", "location_code": "hk", "company": "Cinedigit Sound Ltd", "job_title": "Junior Recording Engineer", "description": "Commercial Radio Interactive, a division of Commercial Radio Productions Limited and the digital arm of Commercial Radio, are looking for a passionate and energetic Programmer to join our IT team and develop his/her career under the guidance of our experienced senior developers.\n\n\n\nJob Duties\n\nResponsible for iOS mobile application development, enhancement, maintenance and testing\nParticipate in multiple projects simultaneously\nJob Requirements\n\n\nUniversity graduate in Computer Science or related disciplines\nExperience in iOS Mobile development\nProficient in\u00a0Swift, Objective-C, C / C++ for iOS developer\nExperience in Android application development is a plus\nExperience in network programming is a plus\nGood understanding of algorithms\nGood team player with strong interpersonal and communication skills\nWilling to learn and have a strong sense of responsibility\nFresh graduate will also be considered\n\nOffice location: Kowloon Tong\n\nApplication Procedure:\n\nWe offer attractive remuneration package, competitive salary, medical scheme and life insurance to the right candidate. Interested candidates, please submit application letter with full resume, present and expected salary by clicking \u201cApply Now\u201d (Please quote the job reference number on the e-mail subject line).\n\nAll information received will be kept in strict confidence and only for employment-related purpose. Only short listed candidates will be invited for interview.", "employment_types": ["Full Time", "Permanent"], "selling_points": [], "locations": ["Tseung Kwan O"], "categories": ["Media & Advertising", "Broadcasting - TV / Radio"], "post_time": "2022-01-07T09:05:16Z", "salary": {"currency": null, "max": null, "min": null, "period": "monthly", "term": null}, "salary_visible": false, "title_keywords": ["engineer", "junior"], "responsibilities": ["multiple projects", "application development", "maintenance", "testing"], "requirements": {"degrees": ["university graduate", "fresh graduate"], "majors": ["related disciplines", "computer science"], "languages": [], "language_level": [], "hard_skills": ["plus", "c++", "objective-c", "mobile", "c", "programming", "swift", "android"], "soft_skills": ["communication skills", "good team player", "sense of responsibility", "willing to learn", "interpersonal"], "languages_combined": []}, "experience_required": {"duration": [], "field": ["development", "application development", "programming"]}}, {"job_id": "100003009031952", "location_code": "hk", "company": "i-CABLE Communications Limited", "job_title": "Studio Technician", "description": "News Department\n\nTo be responsible for delivering of daily newscasts at video-wall set and covering live events; identifying and reflecting issues related to on-air presentation; maintaining professional\u00a0on-air presentation quality; anchoring breaking news and talk shows; participating in dubbing for acquisition programmes; researching on current news topics, gathering news, writing and translating packages\nUniversity graduate\u00a0with minimum 1 year relevant working experience in newspaper or broadcasting industry\nGood command of both spoken and written English & Chinese; fluent in Putonghua is an advantage\nGood communication skills, presentable, energetic and able to work under pressure\n\nWe offer competitive remuneration packages and advancement opportunities. Interested parties, please write with full resume to Director, Human Resources, Human Resources Department, i-CABLE Communications Limited, 4th Floor, Cable TV Tower, 9 Hoi Shing Road, Tsuen Wan, Hong Kong or fax to 2112 7841 or via Apply Now (Please quote reference number and position applied for). For other information, please visit our website http://www.i-cable.com.\n\nYour application may be forwarded to any affiliate companies and successful applicant may be seconded to work at any office as assigned. The information received will be used for consideration of employment only and all personal data supplied will be destroyed within 3 months.\n\nWe are an equal opportunity employer.", "employment_types": ["Full Time", "Permanent"], "selling_points": [], "locations": ["Tsuen Wan Area"], "categories": ["Media & Advertising", "Production", "Broadcasting - TV / Radio", "Photography / Video"], "post_time": "2022-01-07T10:01:24Z", "salary": {"currency": null, "max": null, "min": null, "period": null, "term": null}, "salary_visible": false, "title_keywords": ["technician"], "responsibilities": ["communication", "quality", "maintaining", "work under pressure"], "requirements": {"degrees": ["university graduate"], "majors": [], "languages": ["putonghua", "english", "chinese"], "language_level": ["advantage", "good command", "fluent"], "hard_skills": [], "soft_skills": ["communication skills", "responsible", "presentable", "energetic", "presentation", "work under pressure"], "languages_combined": [{"language": "putonghua", "language_level": ["fluent", "advantage"]}, {"language": "english", "language_level": ["good command"]}, {"language": "chinese", "language_level": ["good command"]}]}, "experience_required": {"duration": ["minimum 1 year"], "field": ["relevant working experience", "newspaper"]}}, {"job_id": "100003009026353", "location_code": "hk", "company": "Our Hong Kong Foundation Limited", "job_title": "Assistant Officer, Creative & Production", "description": "We are Leading live streaming company in the world. Now we are looking for:\n\nEntertainment Talent Manager\n\nResponsibilities:\n\nPerform end-to-end recruitment of live streamer and KOL including sourcing, CV screening, interviewing, etc.\n\nAssist in streamers management, training, communication, coordination and casting\nMonitor, measure and review streamers\u2019 and KOL\u2019s performance timely\nCoordinating and liaising with marketing and operation teams for sales campaign\nConsolidate and prepare various streamers\u2019 and KOL\u2019s performance analytics reports and presentations for management review\nProvide on-site support during events or company promotions\n\nRequirements:\n\n1-2 years' relevant work experience in business development or similar field preferred\nSounds knowledgeable in entertainment trend and live streaming business\nSensitive on marketing trend and numbers\nExcellent communication and interpersonal skills with positive and \u201ccan-do\u201d attitudes\nAble to work independent, under pressure and adopt fast pace environment\nGood command in both written and spoken English, Chinese and Mandarin\nImmediate available will be an advantage\n\n\nWe Offer:\n\n\u00a0Basic Salary with Commission Package\nAttractive bonus or project bonus (depends on performance)\nFriendly and professional working environment\nExcellent career path\nWell-structured on-job training program\u00a0\n\nWelcome young, energetic and strong motivation candidates!\u00a0", "employment_types": ["Full Time", "Permanent"], "selling_points": ["Experienced in video and photo shooting", "Responsible for live-streaming broadcast", "Fresh Grad / Minimum two years relevant experience"], "locations": ["Wan Chai"], "categories": ["Media & Advertising", "Production", "Broadcasting - TV / Radio", "Photography / Video"], "post_time": "2022-01-06T10:35:56Z", "salary": {"currency": null, "max": null, "min": null, "period": "monthly", "term": null}, "salary_visible": false, "title_keywords": ["assistant officer", "creative"], "responsibilities": ["management", "cv screening", "review", "monitor", "liaising with", "teams", "presentations", "communication", "recruitment", "reports", "coordination", "management review"], "requirements": {"degrees": [], "majors": [], "languages": ["english", "chinese", "mandarin"], "language_level": ["good command"], "hard_skills": [], "soft_skills": ["independent", "under pressure", "communication and interpersonal skills", "can-do", "sensitive", "positive"], "languages_combined": [{"language": "english", "language_level": ["good command"]}, {"language": "chinese", "language_level": ["good command"]}, {"language": "mandarin", "language_level": ["good command"]}]}, "experience_required": {"duration": ["1-2 years"], "field": ["business development"]}}, {"job_id": "100003009030819", "location_code": "hk", "company": "i-CABLE Communications Limited", "job_title": "Assistant Programme Officer - Dubbing and Subtitling", "description": "We are currently looking to hire a full time Videographer who reports directly to the Head of Creative Arts.\u00a0\u00a0\u00a0The primary role and responsibilities are as follows:\n\n\nWork with the Head of Creative Arts, the Creative Arts team and teams across the organisation to produce and create short-to-medium form videos for The Vine Church and Branches of Hope.\nVideo scope including but not limited to: weekly Vine News, event/campaign/initiative promotion, community stories & testimonies, digital shorts, internal & external ministry materials.\nAlong with fellow videographer, be responsible for all aspects of video production:Collaborate with\u00a0Pastoral team to produce digital video content\nConceptualise and storyboard according to creative briefs. Work with communication officer/copywriter and relevant stakeholders on script.\nPlanning of video during pre-production period\nLight, record audio, direct and shoot the video during production\nEdit, audio-mix, animate and other post-production process to ready final video\nCollaborate with Pastoral team to produce digital video content\nResponsible for managing The Vine\u2019s YouTube & Vimeo channel, uploading\u00a0weekly video and audio sermon podcasts.\nMay be required to work on Sundays.\n\nJob Requirements:\n\n3\u00a0years of experience working as video production and videography.\u00a0Candidates with less experience will be considered as Associate Videographer.\nProficient\u00a0in\u00a0the full spectrum of the video production process including camera operation, lighting and audio capture.\nProficiency in Premiere Pro, Final Cut, After Effects. (Knowledge in Photoshop is highly preferred).\nKnowledge in running livestream a plus.\nFluency in written and spoken English.\nPossess creative storytelling talent, marketing mindset, and a good eye for aesthetics.\nA good team player with a strong self-learning drive and resourcefulness.\nMust have a show-reel.\nHow to Apply:\n\nInterested parties please send application with full CV with your current and expected salary by clicking \"Apply Now\".\u00a0Candidates who apply without a show-reel will not be considered.\n\nPersonal data provided by job applicants will be strictly used for recruitment purpose.", "employment_types": ["Full Time", "Permanent"], "selling_points": [], "locations": ["Tsuen Wan Area"], "categories": ["Media & Advertising", "Creative / Design", "Broadcasting - TV / Radio", "Professional Services", "Translation"], "post_time": "2022-01-07T08:23:58Z", "salary": {"currency": null, "max": null, "min": null, "period": null, "term": null}, "salary_visible": false, "title_keywords": ["officer", "assistant"], "responsibilities": ["collaborate with", "production process", "video production", "teams", "communication", "pre-production", "audio", "planning"], "requirements": {"degrees": [], "majors": [], "languages": ["english"], "language_level": ["fluency"], "hard_skills": ["after effects", "plus", "premiere pro", "photoshop"], "soft_skills": ["good team player", "creative", "learning"], "languages_combined": [{"language": "english", "language_level": ["fluency"]}]}, "experience_required": {"duration": ["3 years"], "field": ["video production"]}}, {"job_id": "100003009021370", "location_code": "hk", "company": "Niksun Limited", "job_title": "PRODUCTION ASSISTANT", "description": "The Junior Recording Engineer will provide start-to-finish audio engineering services in order to create and deliver audio recordings for Film, TV, Multimedia clients. The ideal candidate will be a highly motivated, self-starting individual who can work independently as well as within an established team.\n\nDuties & Responsibilities:\n\n. Record VO, lip-sync dialogue to client specifications\n. Flag any recording issues during sessions to avoid pickups and/or retakes\n. Work with scheduler and directors to maintain established production schedule\n. Monitor quality of all audio deliverables to maintain consistency\n. Analyze and resolve work problems proactively when possible\n. Performs other related duties, as assigned\n\nAble to demonstrate:\n\n. Good communication and interpersonal skills\n. Flexible and adaptable to new workflows\n. Good technical understanding\n. Ability to work to tight deadlines and under pressure\n. Ability to work independently and on own initiative\n. Ability to be an excellent team player\n\nQualifications and Experience\n\n. 0-2 years related experience dialogue recording,\n. Experience with Mac environment, ProTools is a MUST,\n. Ability to perform quality audio recordings for both low and high end dubbing projects,\n. Ability to identify and solve technical problems with equipment when possible,\n. Fresh grad major in Audio and related subject is also welcome to apply\n\nInterested parties please send resume with possible starting date and expected salary.\n\n", "employment_types": ["Full Time", "Permanent"], "selling_points": [], "locations": ["Eastern Area"], "categories": ["Media & Advertising", "Creative / Design", "Production", "Broadcasting - TV / Radio"], "post_time": "2022-01-05T03:46:23Z", "salary": {"currency": null, "max": null, "min": null, "period": "monthly", "term": null}, "salary_visible": false, "title_keywords": ["production assistant"], "responsibilities": ["monitor", "quality", "communication", "maintain", "specifications", "schedule", "solve technical problems", "audio"], "requirements": {"degrees": [], "majors": [], "languages": [], "language_level": [], "hard_skills": ["mac environment", "multimedia"], "soft_skills": ["flexible", "work independently", "under pressure", "adaptable", "motivated", "communication and interpersonal skills", "team player", "initiative", "ideal"], "languages_combined": []}, "experience_required": {"duration": ["0-2 years"], "field": ["related"]}}, {"job_id": "100003009031923", "location_code": "hk", "company": "i-CABLE Communications Limited", "job_title": "Junior Audioman", "description": "The Department\nThe Customer and International Business Development Division (C&I) is responsible for providing quality wagering experience marketing, and CRM to local and overseas customers of The Hong Kong Jockey Club. The ultimate aim is to provide an impressive total customer experience leading to sustainable turnover growth in a responsible manner.\n\nThe Job\nYou will:\n\nEnsure front-line technical support in pre-raceday set-up of video camera system between HV and ST video patrol room, support in Mark Six live Draw, 7 x 12 Channel JC video playout system for OCBBs, Technical support for Telecast / Infotainment TV program productions / playout, and set-up of special equipment to enhance live TV program production; support the Club\u2019s functions or activities (Corporate and C&I functions) and the necessary equipment and resources\nAssure the technical performance of Racecourse IDS (RCIDS) and the large video screens\nWork with IT to maintain uninterrupted RCIDS network reliability\nExecute agreed plans and designs for the enhancement of RCIDS / Telecast systems to sustain continuous improvement on capacity and capability to align with the business needs\nAct as the internal advisor on assessing AV consultant report and product evaluation; prepare technical requirements and tender documents for AV systems\nAssist the AV Operations Manager (TS) in the co-ordination of Club\u2019s projects (SCTC, RCIDS, Live Horse Tracking system) in areas of live TV production / display system design and implementation\nProvide technical set-up support to the Club\u2019s functions or activities (event marketing and in-house functions) by ascertaining the programme is well packaged and the necessary equipment and operational resources are well organised.\nAssist in maintaining an effective work team by training staff in operational skills, technical domain knowledge and acquiring hands-on experience at various operational positions through job rotation for team members. This facilitates coverage for absenteeism of on-site operation staff.\nResearch on and conduct implementation of new A&V technologies and ensure all systems / equipment are constantly in good working order with the aim of improving operations and broadcasting services. The equipment is capable to support the new activities / initiatives.\nUndertake other duties as assigned by AV Operations Manager (TS).\n\nAbout You\nYou should have:\n\nA bachelor degree or higher diploma in Electronic / TV Multi-media Engineering. A post-graduate degree in management and relevant discipline a plus\nAt least 7 years of relevant working experience\nFamiliarity with TV production system design and post-production workflow. And proficient knowledge in the latest technologies in broadcasting industry\nProficiency in written and spoken Chinese and English\nSharp reflexes, a strong sense of initiative and a high sense of responsibility in handling on-site environment, including incident management in ad hoc on-site situations. Ability to cope with pressure is necessary\nStrong project and cost management ability\nTechnical writing / Drawing skills such as AutoCAD, RFP and evaluation criteria, equipment and demonstration and test report\nContract preparation and execution experience\n\nTerms of employment\nThe level of appointment will be commensurate with qualifications and experience.\n\nHow to Apply\nPlease send your resume, complete with expected salary and job reference by clicking the Apply Now button or to:\nFax: 2576-1987\nMail: The Human Resources Department, The Hong Kong Jockey Club, 1 Sports Road, Happy Valley, Hong Kong\n\n\nWe are an equal opportunity employer. Personal data provided by job applicants will be used strictly in accordance with the Club's notice to employees and prospective employees relating to the Personal Data (Privacy) Ordinance. A copy of which will be provided immediately upon request.", "employment_types": ["Full Time", "Permanent"], "selling_points": [], "locations": ["Tsuen Wan Area"], "categories": ["Media & Advertising", "Production", "Broadcasting - TV / Radio", "Photography / Video"], "post_time": "2022-01-07T09:58:34Z", "salary": {"currency": null, "max": null, "min": null, "period": null, "term": null}, "salary_visible": false, "title_keywords": ["junior"], "responsibilities": ["tracking", "management", "ad hoc", "cost", "maintaining", "tender documents", "technical support", "operations", "other duties", "systems", "quality", "implementation", "maintain", "system design", "evaluation", "plans", "personal data", "report"], "requirements": {"degrees": ["diploma", "degree", "bachelor"], "majors": ["engineering"], "languages": ["english", "chinese"], "language_level": ["proficiency"], "hard_skills": ["plus", "system design", "autocad"], "soft_skills": ["capable", "responsible", "high sense of responsibility", "hands-on", "organised", "initiative"], "languages_combined": [{"language": "english", "language_level": ["proficiency"]}, {"language": "chinese", "language_level": ["proficiency"]}]}, "experience_required": {"duration": ["at least 7 years"], "field": ["training", "business development", "relevant working experience", "marketing", "team"]}}, {"job_id": "100003009031412", "location_code": "hk", "company": "i-CABLE Communications Limited", "job_title": "Senior Visual Effect Producer", "description": "Broadcasting & Engineering Operations Department\nTo\u00a0be responsible for\u00a0assisting in operating studio equipment as assigned, such as camera, video switcher, video server; providing comprehensive support to daily operation and outdoor broadcast event if any\nDiploma\u00a0holder or above in Electronic / Communication engineering / Film, Television and Photography or related disciplines\u00a0 with relevant working experience is an advantage\nBasic knowledge in PC applications\nShift duty is required\n\nWe offer 5-day work week, competitive remuneration packages and advancement opportunities. Interested parties, please write with full resume to Director, Human Resources, Human Resources Department, i-CABLE Communications Limited, 4/F Cable TV Tower, 9 Hoi Shing Road Tsuen Wan, N.T. or fax to 2112 7841 or via Apply Now (Please quote reference number and position applied for). For other information, please visit our website http://www.i-cable.com.\n\nYour application may be forwarded to any affiliate companies and successful applicant may be seconded to work at any office as assigned.\u00a0 The information received will be used for consideration of employment only and all personal data supplied will be destroyed within 3 months.\n\nWe are an equal opportunity employer.", "employment_types": ["Full Time", "Permanent"], "selling_points": [], "locations": ["Tsuen Wan Area"], "categories": ["Design", "Graphics", "Media & Advertising", "Editorial / Journalism", "Broadcasting - TV / Radio"], "post_time": "2022-01-07T09:18:25Z", "salary": {"currency": null, "max": null, "min": null, "period": null, "term": null}, "salary_visible": false, "title_keywords": ["producer"], "responsibilities": ["communication", "operations", "daily operation"], "requirements": {"degrees": ["diploma holder"], "majors": ["related disciplines", "engineering"], "languages": [], "language_level": [], "hard_skills": ["server", "basic", "pc applications"], "soft_skills": ["communication", "comprehensive", "responsible"], "languages_combined": []}, "experience_required": {"duration": [], "field": ["related", "relevant working experience", "engineering"]}}, {"job_id": "100003009025836", "location_code": "hk", "company": "Phoenix Satellite Television Co Ltd", "job_title": "PRODUCER (ON AIR PROMOTIONS)\t                         (REF: P-OAP-DB)", "description": "Responsibilities:\n\nResponsible for live-streaming broadcast setup and operation control\nResponsible for video shoot and photo shoot including camera operation, lighting set up and audio recording\nResponsible for video editing and photo retouch\nSupport creative & production team to handle in house production\n\nRequirements:\n\nHigher Diploma or above in Multimedia, Graphic Design or related discipline\nMinimum two years relevant experience\nExperienced in video and photo shooting, live-streaming broadcast and virtual event\nPassionate about video production\nProficiency in audiovisual and graphic software e.g. Premiere Pro, AE, AI and Lightroom\nAbility to perform well under pressure and meet deadlines\nOptimistic and detail oriented, work under pressure, open to all ideas\n\n\nInterested parties please send:\n\nFull resume;\nCover letter;\nCopies of academic transcripts (including\u00a0public examination results if applicable);\nPresent and expected salary;\nAvailability\n\n\nBy clicking 'Apply Now' or by post to: Our Hong Kong Foundation Limited, 11/F, Fortis Tower, 77-79 Gloucester Road, Wan Chai, Hong Kong. Applicants who are not invited to an interview within two months from the date of this advertisement should consider their applications unsuccessful.\u00a0\n\nAll information provided by applicants will be handled with strictest confidence and will be solely used for the purpose of recruitment.", "employment_types": ["Full Time", "Permanent"], "selling_points": [], "locations": ["Tai Po Area"], "categories": ["Media & Advertising", "Broadcasting - TV / Radio"], "post_time": "2022-01-06T06:34:16Z", "salary": {"currency": null, "max": null, "min": null, "period": null, "term": null}, "salary_visible": false, "title_keywords": ["producer"], "responsibilities": ["control", "video editing", "photo retouch", "audio", "setup"], "requirements": {"degrees": ["higher diploma or above"], "majors": ["graphic design"], "languages": [], "language_level": [], "hard_skills": ["premiere pro", "multimedia", "ai"], "soft_skills": ["passionate about", "detail oriented", "meet deadlines", "perform well under pressure", "work under pressure"], "languages_combined": []}, "experience_required": {"duration": ["minimum two years"], "field": ["relevant experience"]}}, {"job_id": "100003009021067", "location_code": "hk", "company": "Multi Channel Network Limited", "job_title": "Live Stream KOL Manager \u7db2\u7d05\u7ba1\u7406\u53ca\u62d3\u5c55\u7d93\u7406", "description": "To be responsible for checking, translating and interpretation for various programmes from English to Chinese or vice versa; cooperating with various department, channels and vendors to ensure the smooth operation for the on-air programmes; performing ad hoc projects or assignments as assigned\nUniversity graduate in Translation or related disciplines\u00a0 with relevant working experience in translation, script rewriting, dubbing or subtitling is preferred\nExcellent command of both written and spoken English and Chinese; Fluent in foreign language ia an advantage\nProficient in MS Office and Chinese word-processsing is a must\nExcellent interpersonal, communication skills and able to work under pressure in a fast-paces environment\nStrong passion in TV and Media industry\nShift duty is required\nFresh graduate\u00a0will also be considered\n\nWe offer 5-day work week, competitive remuneration packages and advancement opportunities. Interested parties, please write with full resume to Director, Human Resources, Human Resources Department, i-CABLE Communications Limited, 4/F Cable TV Tower, 9 Hoi Shing Road Tsuen Wan, N.T. or fax to 2112 7841 or via Apply Now (Please quote reference number and position applied for). For other information, please visit our website http://www.i-cable.com.\n\nYour application may be forwarded to any affiliate companies\u00a0and successful applicant may be seconded to work at any office as assigned.\u00a0 The information received will be used for consideration of employment only and all personal data supplied will be destroyed within 3 months.\n\nWe are an equal opportunity employer.", "employment_types": ["Full Time", "Permanent"], "selling_points": ["Asia Leading KOL Company", "3 years experience in Media or Entertainment", "Target Global Market"], "locations": ["Lai Chi Kok"], "categories": ["Others", "Entertainment - Artists / Singers / Musicians", "Media & Advertising", "Print Media", "Broadcasting - TV / Radio"], "post_time": "2022-01-05T02:59:25Z", "salary": {"currency": "HKD", "max": 24999, "min": 17000, "period": "monthly", "term": null}, "salary_visible": true, "title_keywords": ["manager"], "responsibilities": ["communication", "ad hoc projects", "checking", "work under pressure"], "requirements": {"degrees": ["university graduate", "fresh graduate"], "majors": ["related disciplines"], "languages": ["english", "chinese"], "language_level": ["excellent", "proficient"], "hard_skills": ["translation", "word", "ms office"], "soft_skills": ["communication skills", "responsible", "passion in", "smooth", "interpersonal", "work under pressure"], "languages_combined": [{"language": "english", "language_level": ["excellent"]}, {"language": "chinese", "language_level": ["excellent", "proficient"]}]}, "experience_required": {"duration": [], "field": ["related", "relevant working experience"]}}, {"job_id": "100003009021371", "location_code": "hk", "company": "Niksun Limited", "job_title": "VIDEO CAMERAMAN", "description": "Broadcasting & Engineering Operations Department\u00a0\nTo\u00a0be responsible for\u00a0providing quality audio control and judgment in studio and field production; providing operation support in studio, field and OB production coverage; solving daily operation problems and providing front-line maintenance support\nDiploma\u00a0holder or above in Film, Television and Photography or related disciplines\u00a0 with relevant working experience is an advantage\nBasic knowledge in PC applications\nShift duty is required\n\nWe offer 5-day work week, competitive remuneration packages and advancement opportunities. Interested parties, please write with full resume to\u00a0Director, Human Resources, Human Resources Department, i-CABLE Communications Limited, 4/F Cable TV Tower, 9 Hoi Shing Road Tsuen Wan, N.T. or fax to 2112 7841 or via Apply Now (Please quote reference number and position applied for). For other information, please visit our website http://www.i-cable.com.\n\nYour application may be forwarded to any affiliate companies and successful applicant may be seconded to work at any office as assigned.\u00a0 The information received will be used for consideration of employment only and all personal data supplied will be destroyed within 3 months.\n\nWe are an equal opportunity employer.", "employment_types": ["Full Time"], "selling_points": [], "locations": ["Eastern Area"], "categories": ["Media & Advertising", "Production", "Broadcasting - TV / Radio", "Photography / Video"], "post_time": "2022-01-05T03:46:50Z", "salary": {"currency": null, "max": null, "min": null, "period": "monthly", "term": null}, "salary_visible": false, "title_keywords": [], "responsibilities": ["control", "operations", "maintenance support", "daily operation", "quality", "audio"], "requirements": {"degrees": ["diploma holder"], "majors": ["related disciplines"], "languages": [], "language_level": [], "hard_skills": ["maintenance", "basic", "operation support", "pc applications"], "soft_skills": ["responsible"], "languages_combined": []}, "experience_required": {"duration": [], "field": ["related", "relevant working experience"]}}, {"job_id": "100003009024747", "location_code": "hk", "company": "Hong Kong Cyberport Management Co Ltd", "job_title": "Videographer and Video Editor (Ref# VVE220106J)", "description": "On-Air Promotion\u00a0Department\nTo be responsible for producing on-air promos; following up with non-linear editing and post production work; providing creative ideas on all promotional campaigns and projects; initiating motion graphic design for promotion video\u00a0\nProficient in After Effects, Illustrator, Final Cut Pro, Maya, 3Ds Max and Photoshop\u00a0\nUniversity graduate with minimum 2 years experience in TV or creative industry\nGood command of both spoken and written English and Chinese\nAlert to deadlines with Can-do attitude\nGood interpersonal and communication skills\n\nWe offer 5-day work week, competitive remuneration packages and advancement opportunities. Interested parties, please write with full resume to Director, Human Resources, Human Resources Department, i-CABLE Communications Limited, 4/F Cable TV Tower, 9 Hoi Shing Road Tsuen Wan, N.T. or fax to 2112 7841 or via Apply Now (Please quote reference number and position applied for). For other information, please visit our website http://www.i-cable.com.\n\nYour application may be forwarded to any affiliate companies and successful applicant may be seconded to work at any office as assigned.\u00a0 The information received will be used for consideration of employment only and all personal data supplied will be destroyed within 3 months.\n\n\nWe are an equal opportunity employer.", "employment_types": ["Full Time", "Permanent", "Contract"], "selling_points": ["Promotion video, event highlights, interviews, etc", "Lighting, sound, backdrops, and special needs", "Editing, graphics, effects, music select, etc."], "locations": ["Pok Fu Lam"], "categories": ["Media & Advertising", "Production", "Broadcasting - TV / Radio", "Photography / Video"], "post_time": "2022-01-06T02:24:14Z", "salary": {"currency": null, "max": null, "min": null, "period": "monthly", "term": null}, "salary_visible": false, "title_keywords": ["videographer", "video editor"], "responsibilities": ["communication", "editing", "creative ideas", "motion graphic design"], "requirements": {"degrees": ["university graduate"], "majors": [], "languages": ["english", "chinese"], "language_level": ["good command"], "hard_skills": ["final cut pro", "maya", "3ds max", "illustrator", "after effects", "photoshop"], "soft_skills": ["communication skills", "responsible", "can-do attitude", "creative", "interpersonal"], "languages_combined": [{"language": "english", "language_level": ["good command"]}, {"language": "chinese", "language_level": ["good command"]}]}, "experience_required": {"duration": ["minimum 2 years"], "field": []}}, {"job_id": "100003009025423", "location_code": "hk", "company": "Salon Films (H.K.) Limited", "job_title": "Project Coordinator", "description": "Job Description :\n\nAssist Producer in all preparation work of TV commercial and Production video production\nWill gradually develop to be a Producer / Director\nOn the job training will be provided\n\nRequirements :\n\nMinimum HKCEE 5 subject pass (included English Syl. B and Chinese)\u00a0\nProficiency in MS Word, PowerPoint, Excel and Chinese Word Processing, Photoshop & Photo/Video Shooting Skill\nVideo Editing Skill is Preferred\nRelevant working experience is preferred but not a must\u00a0\nExcellent Interpersonal Skill and Communication abilities in both English, Cantonese and Mandarin\nWilling to work in overseas and mainland China\u00a0\nHardworking and be able to work under pressure\u00a0\nMature, Reliable and Outgoing\u00a0\n\nA Competitive package and promising career prospect will be offered to the right candidate. Interested parties please send your full resume, stating the date of availability, present and expected salary.\n\n\nAll Applications will be treated in strict confidence and personal data collected will be used for recruitment purpose only. Applications who are not invited for interview within 8 weeks may consider their applications unsuccessful. All personal data of unsuccessful candidates will be destroyed after 6 months.", "employment_types": ["Full Time"], "selling_points": ["Project and event planning and implementation", "Coordinate on logistical arrangement", "Assist in pitching for events & perform admin duty"], "locations": ["To Kwa Wan"], "categories": ["Media & Advertising", "Broadcasting - TV / Radio"], "post_time": "2022-01-06T04:28:25Z", "salary": {"currency": null, "max": null, "min": null, "period": "monthly", "term": null}, "salary_visible": false, "title_keywords": ["project coordinator"], "responsibilities": ["video production", "develop"], "requirements": {"degrees": [], "majors": [], "languages": ["cantonese", "english", "chinese", "mandarin"], "language_level": ["proficiency", "excellent"], "hard_skills": ["excel", "chinese word processing", "ms word", "powerpoint", "video editing", "photoshop"], "soft_skills": ["outgoing", "mature", "interpersonal skill", "communication", "reliable", "hardworking", "work under pressure"], "languages_combined": [{"language": "cantonese", "language_level": ["excellent"]}, {"language": "english", "language_level": ["excellent"]}, {"language": "chinese", "language_level": ["proficiency"]}, {"language": "mandarin", "language_level": ["excellent"]}]}, "experience_required": {"duration": [], "field": ["relevant working experience"]}}, {"job_id": "100003009020554", "location_code": "hk", "company": "One Click Go Live Limited", "job_title": "Full Stack Software Developer", "description": "Responsibilities:\u00a0\n\n\u00a0\u00a0\u00a0\u00a0\u00a0\u00a0\u00a0\u00a0 Production of On-Air Promotions, Corporate Video and Sales tape.\u00a0\n\nRequirements:\u00a0\n\nCertificate/Diploma/Degree holder in Journalism / Communication, with 5 years relevant working experience;\nSolid experience in directing shoots and proficiency in non-linear editing skill (e.g. Apple Final Cut Pro);\nCreative with good knowledge of video graphic design;\nAble to work independently under tight schedule;\nExcellent command of written and spoken English and Chinese, proficiency in Putonghua is an advantage; and\nCandidates with more experience will be considered for senior position.\u00a0\n\nFor more details of our company, please visit our website at http://www.ifeng.com/\n\n\n\nWe offer attractive remuneration package to the right candidate. Interested parties please send applications with detailed resume stating career history, present & expected salary and date available to Human Resources Department, Phoenix Satellite Television Co. Ltd. via fax: 2200 8620.\n\nPersonal data collected will be used for recruitment purpose only.\u00a0 Applicants not hearing from us within 6 weeks may consider their applications unsuccessful and all related information will be destroyed after 6 months.", "employment_types": ["Full Time", "Permanent"], "selling_points": ["Software Development with cutting-edge technology", "Fresh graduate", "Career growth"], "locations": ["Others"], "categories": ["Media & Advertising", "Broadcasting - TV / Radio", "Information Technology (IT)", "Mobile / Wireless Communications"], "post_time": "2022-01-04T15:39:00Z", "salary": {"currency": null, "max": null, "min": null, "period": "monthly", "term": null}, "salary_visible": false, "title_keywords": ["developer"], "responsibilities": [], "requirements": {"degrees": ["certificate", "diploma", "degree holder"], "majors": ["journalism"], "languages": ["putonghua", "english", "chinese"], "language_level": ["advantage", "excellent", "proficiency"], "hard_skills": ["final cut pro"], "soft_skills": ["communication", "work independently", "creative"], "languages_combined": [{"language": "putonghua", "language_level": ["proficiency", "advantage", "excellent"]}, {"language": "english", "language_level": ["proficiency", "advantage", "excellent"]}, {"language": "chinese", "language_level": ["proficiency", "advantage", "excellent"]}]}, "experience_required": {"duration": ["5 years"], "field": ["editing", "relevant working experience"]}}, {"job_id": "100003009023157", "location_code": "hk", "company": "Television Broadcasts Limited\u96fb\u8996\u5ee3\u64ad\u6709\u9650\u516c\u53f8(TVB)", "job_title": "\u5a1b\u6a02\u65b0\u805e\u8a18\u8005 (\u5408\u7d04)", "description": "One Click Go Live Limited (\u201cONE CLICK GO LIVE\u201d)\u00a0is a live streaming technology company focuses on enterprise broadcast-grade video live streaming solutions with offerings including live streaming platforms, products and services.\u00a0ONE CLICK GO LIVE enables corporates to conduct professional live streaming through one single button \u2013 ONE CLICK GO LIVE, delivering a seamless user experience in combination with patented technologies.\n\nServing over 300 corporates for over 9,000 live streaming events,\u00a0ONE CLICK GO LIVE leverages its technical expertise while corporates focus on generating growth and revenue with video content.\u00a0\n\nOur successful cases:\u00a0www.oneclickgolive.com\n\nWe are looking for candidate(s) who is/are interested to join our fast growing team.\u00a0 Training will be offered for potential candidate(s).\n\n\nJob responsibility:\n\nDevelop high-quality, robust, scalable and supportable video-related software systems and cloud-based services in an Agile development environment\nDevelop sufficient automated tests to assure product quality\nResearch into new technologies as necessary\nCollaborate with the team members and work with product team in enhancing product features\n\n\u00a0Job requirement:\n\nBachelor degree or above in Computer Science or related disciplines\n1-3 years relevant experience\nProficient in Javascript, Python, Golang, Java, Kotlin, C/C++\nExperience with a common relational or NoSQL database\nKnowledge or experience in Docker, Kubernetes, cloud computing on AWS/GCP/Azure/AliCloud, VueJS, OTT video streaming will be an advantage\nFast learner and good team player\nGood communication and interpersonal skills\nFresh graduates are welcome to apply\nInterested applicants please send us full CV with current and expected salary and availability.\n\nBenefits : Medical Allowance, Birthday and Childcare Leave\u00a0\n\nThe information provided will be treated in strict confidence and used only for consideration of application for relevant/similar post(s).\u00a0 All personal data of unsuccessful applicants will be destroyed within 6 months.", "employment_types": ["Full Time", "Contract"], "selling_points": [], "locations": ["Tseung Kwan O"], "categories": ["Media & Advertising", "Production", "Editorial / Journalism", "Broadcasting - TV / Radio"], "post_time": "2022-01-05T20:32:10Z", "salary": {"currency": null, "max": null, "min": null, "period": "monthly", "term": null}, "salary_visible": false, "title_keywords": ["\u5a1b\u6a02\u65b0\u805e\u8a18\u8005"], "responsibilities": ["collaborate with", "software", "systems", "quality", "agile development", "develop"], "requirements": {"degrees": ["degree or above", "bachelor"], "majors": ["related disciplines", "computer science"], "languages": [], "language_level": [], "hard_skills": ["java", "azure", "c++", "aws", "c", "javascript", "python", "kotlin"], "soft_skills": ["good team player", "communication and interpersonal skills", "fast learner"], "languages_combined": []}, "experience_required": {"duration": ["1-3 years"], "field": ["video", "relevant experience", "database"]}}, {"job_id": "100003009025771", "location_code": "hk", "company": "Phoenix Satellite Television Co Ltd", "job_title": "\u65b0\u805e\u4e3b\u7de8", "description": "\u00b7\u00a0\u5927\u5b78\u7a0b\u5ea6\uff0c\u66fe\u4fee\u8b80\u50b3\u7406\u5b78\u6709\u95dc\u8ab2\u7a0b\u66f4\u4f73\n\u00b7\u00a0\u61c2\u4e2d\u6587\u8f38\u5165\u6cd5\u00a0\n\u00b7\u00a0\u53e3\u9f52\u4f36\u4fd0\u3001\u4e3b\u52d5\u53ca\u6027\u683c\u958b\u6717\n\u00b7\u00a0\u80fd\u64cd\u6d41\u5229\u97d3\u8a9e\u3001\u65e5\u8a9e\u3001\u82f1\u8a9e\u6216\u666e\u901a\u8a71\u8005\u53ef\u7372\u512a\u5148\u8003\u616e\n\u00b7\u00a0\u9858\u610f\u6236\u5916\u53ca\u4e0d\u5b9a\u6642\u5de5\u4f5c\n\u00b7\u00a0\u61c2\u526a\u7247\u66f4\u4f73\n\n\u8acb\u8a73\u8ff0\u8cc7\u6b77\u53ca\u7d93\u9a57\u3001\u73fe\u6642\u53ca\u8981\u6c42\u85aa\u91d1\u3001\u806f\u7d61\u96fb\u8a71\uff0c\u4e26\u8a3b\u660e\u8077\u4f4d\u7de8\u865f\uff0c\u5bc4\u9999\u6e2f\u4e5d\u9f8d\u5c07\u8ecd\u6fb3\u5de5\u696d\u90a8\u99ff\u624d\u885777\u865f\u96fb\u8996\u5ee3\u64ad\u57ce\uff0c\u96fb\u8996\u5ee3\u64ad\u6709\u9650\u516c\u53f8\uff0c\u4eba\u4e8b\u79d1\u9ad8\u7d1a\u7d93\u7406\u6536\u3002\n\n\u7533\u8acb\u4eba\u6240\u63d0\u4f9b\u7684\u8cc7\u6599\u7d55\u5c0d\u4fdd\u5bc6\uff0c\u4e26\u53ea\u4f5c\u8077\u4f4d\u7504\u9078\u7528\u9014\u3002\u672a\u7372\u53d6\u9304\u7684\u7533\u8acb\u4eba\uff0c\u5176\u8cc7\u6599\u6703\u65bc\u56db\u661f\u671f\u5f8c\u5b58\u6a94\uff0c\u96c6\u5718\u5167\u5982\u6709\u5176\u4ed6\u8077\u4f4d\u7a7a\u7f3a\u6642\uff0c\u672c\u516c\u53f8\u6703\u63a8\u85a6\u5408\u9069\u7533\u8acb\u4eba\u4e88\u4ee5\u8003\u616e\u3002\u7533\u8acb\u4eba\u7684\u8cc7\u6599\u53ea\u6703\u4fdd\u5b58\u4e09\u500b\u6708\uff0c\u671f\u6eff\u92b7\u6bc0\u3002", "employment_types": ["Full Time"], "selling_points": [], "locations": ["Tai Po Area"], "categories": ["Media & Advertising", "Others", "Editorial / Journalism", "Broadcasting - TV / Radio"], "post_time": "2022-01-06T06:27:24Z", "salary": {"currency": null, "max": null, "min": null, "period": null, "term": null}, "salary_visible": false, "title_keywords": [], "responsibilities": [], "requirements": {"degrees": [], "majors": [], "languages": [], "language_level": [], "hard_skills": [], "soft_skills": [], "languages_combined": []}, "experience_required": {"duration": [], "field": []}}, {"job_id": "100003009029793", "location_code": "hk", "company": "Phoenix Satellite Television Co Ltd", "job_title": "Legal Counsel", "description": "\u8077\u8cac\uff1a\n\n\u00a0\u00a0\u00a0\u00a0\u00a0\u00a0\u00a0 \u8ca0\u8cac\u65b0\u805e\u8cc7\u8a0a\u985e\u96fb\u8996\u7bc0\u76ee\u4e4b\u7de8\u6392\u3001\u88fd\u4f5c\u53ca\u64ad\u51fa\n\u00a0\u00a0\u00a0\u00a0\u00a0\u00a0\u00a0 \u4e3b\u5c0e\u7bc0\u76ee\u5275\u610f\u3001\u9078\u984c\u8ddf\u9032\uff0c\u7b56\u5283\u5927\u578b\u65b0\u805e\u76f4\u64ad\n\u00a0\u00a0\u00a0\u00a0\u00a0\u00a0\u00a0 \u8ca0\u8cac\u6709\u95dc\u7bc0\u76ee\u4e8b\u52d9\u7684\u8de8\u90e8\u9580\u6e9d\u901a\u4ee5\u53ca\u5c0d\u5916\u806f\u7d61\n\u00a0\u00a0\u00a0\u00a0\u00a0\u00a0\u00a0 \u53c3\u8207\u516c\u53f8\u65b0\u5a92\u9ad4\u5e73\u53f0\u7684\u5167\u5bb9\u5275\u4f5c\u4e26\u63d0\u4f9b\u65b0\u7406\u5ff5\n\n\u00a0\u5165\u8077\u8981\u6c42\uff1a\n\n\u00a0\u00a0\u00a0\u00a0\u00a0\u00a0\u00a0 \u5927\u5b78\u672c\u79d1\u6216\u4ee5\u4e0a\u5b78\u6b77\uff0c\u8ca1\u7d93\u3001\u65b0\u805e\u7b49\u76f8\u95dc\u5c08\u696d\u512a\u5148\n\u00a0\u00a0\u00a0\u00a0\u00a0\u00a0\u00a0 \u5177\u50995\u5e74\u6216\u4ee5\u4e0a\u8ca1\u7d93\u3001\u65b0\u805e\u7de8\u8f2f\u6216\u63a1\u8a2a\u7d93\u9a57\uff0c\u6709\u96fb\u8996\u7bc0\u76ee\u88fd\u4f5c\u6216\u65b0\u5a92\u9ad4\u7d93\u9a57\u00a0 \u8005\u512a\u5148\n\u00a0\u00a0\u00a0\u00a0\u00a0\u00a0\u00a0 \u826f\u597d\u7684\u65b0\u805e\u7d20\u990a\uff0c\u65b0\u805e\u654f\u611f\u6027\u5f37\uff0c\u77ad\u89e3\u5169\u5cb8\u56db\u5730\u7684\u91cd\u5927\u65b0\u805e\u4e8b\u4ef6\u548c\u65b0\u805e\u80cc\u666f\n\u00a0\u00a0\u00a0\u00a0\u00a0\u00a0\u00a0 \u826f\u597d\u7684\u4e2d\u82f1\u6587\u8b80\u5beb\u80fd\u529b\uff0c\u5305\u62ec\u666e\u901a\u8a71\u53ca\u7cb5\u8a9e\uff0c\u4e2d\u6587\u6587\u5b57\u529f\u5e95\u624e\u5be6\n\u00a0\u00a0\u00a0\u00a0\u00a0\u00a0\u00a0 \u5177\u6709\u57fa\u672c\u7684\u8996\u983b\u526a\u8f2f\u6280\u5de7\n\u00a0\u00a0\u00a0\u00a0\u00a0\u00a0\u00a0 \u80fd\u9069\u61c9\u7dca\u5f35\u7e41\u5fd9\u7684\u5de5\u4f5c\u74b0\u5883\u3001\u6297\u58d3\u6027\u5f37\uff0c\u6709\u5f37\u70c8\u7684\u5718\u968a\u5408\u4f5c\u7cbe\u795e\n\u00a0\u00a0\u00a0\u00a0\u00a0\u00a0\u00a0 \u9700\u8f2a\u73ed\u5de5\u4f5c\n\u00a0\u00a0\u00a0\u00a0\u00a0\u00a0\u00a0 \u8cc7\u6b77\u8f03\u6dfa\u8005\u4ea6\u53ef\u7372\u8003\u616e\u70ba\u526f\u65b0\u805e\u4e3b\u7de8\n\u5de5\u4f5c\u5730\u9ede\uff1a\u9999\u6e2f", "employment_types": ["Full Time", "Permanent"], "selling_points": [], "locations": ["Tai Po Area"], "categories": ["Media & Advertising", "Broadcasting - TV / Radio"], "post_time": "2022-01-07T06:11:05Z", "salary": {"currency": null, "max": null, "min": null, "period": null, "term": null}, "salary_visible": false, "title_keywords": ["legal counsel"], "responsibilities": [], "requirements": {"degrees": [], "majors": [], "languages": [], "language_level": [], "hard_skills": [], "soft_skills": [], "languages_combined": []}, "experience_required": {"duration": [], "field": []}}, {"job_id": "100003009018497", "location_code": "hk", "company": "OpenExchange", "job_title": "Senior Video Specialist", "description": "Responsibilities:\n\nProvide legal and compliance support to various business units within the Group\nDraft, review and negotiate a range of documents including agreements, compliance documentation, stock exchange announcements, annual reports etc.\nIdentify legal issues under any contract, document, applicable laws and regulations (including listing rules) and the related legal risk(s)\nConduct legal research and investigate on cases involving legal issues / disputes\nLiaise and work closely with other in-house legal colleagues and external lawyers on all legal assignments\nHandle trademarks, copyrights and other intellectual property matters\nHandle ad-hoc assignments by the management\n\nRequirements:\n\nHong Kong qualified solicitor with at least 5 years\u2019 post qualified experience\nSelf-motivated, capable of handling matter independently and proactively\nStrong business acumen and analytical skill\nGood communication and interpersonal skills at all levels\nPrevious working experience gained in television, film production and other media related legal matters will be an advantage\nExcellent command of both written and spoken English, Cantonese and Mandarin\n\n\nFor more details of our company, please visit our website at http://www.ifeng.com/\n\n\n\nWe offer attractive remuneration package to the right candidate. Interested parties please send applications with detailed resume stating career history, present & expected salary and date available to Human Resources Department, Phoenix Satellite Television Co. Ltd. via e-mail: phxhr @phoenixtv.com or via fax: 2200 8620.\n\nPersonal data collected will be used for recruitment purpose only.\u00a0 Applicants not hearing from us within 6 weeks may consider their applications unsuccessful and all related information will be destroyed after 6 months.", "employment_types": ["Full Time", "Permanent", "Contract", "Freelance"], "selling_points": [], "locations": ["Kwai Hing"], "categories": ["Media & Advertising", "Broadcasting - TV / Radio"], "post_time": "2022-01-04T03:56:52Z", "salary": {"currency": null, "max": null, "min": null, "period": "monthly", "term": null}, "salary_visible": false, "title_keywords": ["specialist"], "responsibilities": ["compliance documentation", "regulations", "liaise", "management", "ad-hoc assignments", "review", "compliance", "reports", "listing"], "requirements": {"degrees": [], "majors": [], "languages": ["cantonese", "english", "mandarin"], "language_level": ["excellent"], "hard_skills": ["analytical skill", "acumen"], "soft_skills": ["self-motivated", "independently", "analytical skill", "capable", "communication and interpersonal skills", "business acumen"], "languages_combined": [{"language": "cantonese", "language_level": ["excellent"]}, {"language": "english", "language_level": ["excellent"]}, {"language": "mandarin", "language_level": ["excellent"]}]}, "experience_required": {"duration": ["at least 5 years"], "field": ["related", "media", "legal"]}}, {"job_id": "100003009020750", "location_code": "hk", "company": "ORIENTAL HUMAN RESOURCES LIMITED", "job_title": "Video Editor Trainee", "description": "Atomy is from Korea and making our network with all the world through e-commerce.\nAtomy Hong Kong Branch has\u00a0opened in 2020.\u00a0\nWe are currently planing to recruit and\u00a0plan a long-term development in Hong Kong\u00a0\n\nWelcome to join us to explore and develop Atomy Hong Kong.\n\n[Videographer-----Full Time ]\n\n\u00a0Key tasks:\n\n- An internal position, nothing related to product selling\n\n- Handle\u00a0sound, recording, video equipment during company seminar and activities\n\n- Perform video shooting for our seminar and activities\n\n- Basic Video editing\n\n- Developing and implementing product advertising, and member\u00a0activities recording\n\n\u00a0Must-have skills and qualities:\n\n- Working experience over 1 year in related field\n\n-\u00a0Advanced knowledge of computer systems, familiar with After Effect, Premiere Pro, Adobe Photoshop, Illustrator software\n\n- Knowledge of sound and recording equipment on live broadcast events like seminar\n\n- Native Cantonese speaking\n\n\u00a0Relevant skills\n\n- Korean proficiency is a plus\n\n- Ability of\u00a0on-the-spot live broadcast is a plus", "employment_types": ["Full Time"], "selling_points": [], "locations": ["Tai Po Area"], "categories": ["Media & Advertising", "Production", "Broadcasting - TV / Radio", "Photography / Video"], "post_time": "2022-01-05T01:55:25Z", "salary": {"currency": null, "max": null, "min": null, "period": "monthly", "term": null}, "salary_visible": false, "title_keywords": ["trainee", "video editor"], "responsibilities": ["advertising", "software", "developing", "computer systems", "develop", "video editing", "video shooting", "plan"], "requirements": {"degrees": [], "majors": [], "languages": ["cantonese", "korean"], "language_level": ["native", "proficiency"], "hard_skills": ["plus", "basic", "e-commerce", "adobe photoshop", "computer systems", "illustrator", "video editing", "premiere pro", "after effect"], "soft_skills": ["advanced"], "languages_combined": [{"language": "cantonese", "language_level": ["native"]}, {"language": "korean", "language_level": ["proficiency"]}]}, "experience_required": {"duration": ["1 year"], "field": ["related"]}}, {"job_id": "100003009026106", "location_code": "hk", "company": "ConnectedGroup Limited", "job_title": "Senior Content Editor, Racing", "description": "Job Responsibilities:\nPerform end-to-end recruitment of live streamer and KOL including screening, approaching, interviewing and closing\nAssist in streamers management, training, communication, coordination and casting\nMaintain a good relationship with streamers and KOL\nMonitor, measure and review streamers\u2019 and KOL\u2019s performance timely\nConsolidate and prepare various streamers\u2019 and KOL\u2019s performance analytics reports and presentations for management review\nCooperate with various internal teams to implement streamers\u2019 and KOL\u2019s promotion and interview with media\nCoordinate with social media platform and arrange broadcast activities for streamers and KOL to increase social media presence\nCooperate with various internal teams to organize offline activities and arrange streamers and KOL to participate\nPerform other ad-hoc projects if necessary\n\n\u00a0Requirements:\n\nMinimum 3 years work experience in Media, Entertainment, Broadcasting industry or related disciplines\nExcellent skill in communication, interpersonal and social networking\nFluency in written and spoken\u00a0Cantonese, Putonghua\u00a0and English\nFamiliar with Social Media Platform\nGood presentation and negotiation skills, flexible and be able to work under pressure\nResponsible, strong execution, team player, well-organized, equipped with aesthetic sense\nExperience in Model Management, Artist Management, or any media related disciplines would be an advantage\nImmediate available is highly preferred", "employment_types": ["Full Time", "Permanent"], "selling_points": ["Racing domain specialist", "Stable work environment", "Attractive total package"], "locations": ["Not Specified"], "categories": ["Media & Advertising", "Others", "Editorial / Journalism", "Broadcasting - TV / Radio"], "post_time": "2022-01-06T07:20:36Z", "salary": {"currency": null, "max": null, "min": null, "period": "monthly", "term": null}, "salary_visible": false, "title_keywords": ["content editor"], "responsibilities": ["social media", "management", "review", "monitor", "teams", "presentations", "coordinate with", "communication", "good relationship", "maintain", "recruitment", "reports", "coordination", "ad-hoc projects", "cooperate with", "management review"], "requirements": {"degrees": [], "majors": [], "languages": ["cantonese", "putonghua", "english"], "language_level": ["fluency"], "hard_skills": [], "soft_skills": ["flexible", "responsible", "well-organized", "communication", "negotiation skills", "team player", "interpersonal", "presentation", "work under pressure"], "languages_combined": [{"language": "cantonese", "language_level": ["fluency"]}, {"language": "putonghua", "language_level": ["fluency"]}, {"language": "english", "language_level": ["fluency"]}]}, "experience_required": {"duration": ["minimum 3 years"], "field": ["related", "management", "media"]}}, {"job_id": "100003009028977", "location_code": "hk", "company": "Commercial Radio Productions Ltd", "job_title": "IT Support Engineer (Kowloon Tong)", "description": "Your New Role:\n\nPlaying a business analyst role in modernization and development of business support systems that support evolving business requirements of Company\u2019s media business\nUnderstanding user requirements from business counterparts, formulating/analyzing solutions put forward by technical teams or vendors\nWorking with various stakeholders to design and agree on the operation flow and making sure systems developed can support that effectively\nManaging the development of ordering, subscription, billing and payment system to ensure on-time and quality delivery\nConducting end user training and providing support to users\nCollaborating with users to set up / configure the system / data so as to support marketing policies / offers\nProviding production support to ensure subscription and subscription/billing accuracy; and handling production faults reported by users or customers\n\nWhat makes you succeed:\n\nUniversity Degree in Computer Science, Information System, Statistics or related disciplines\nMinimum 1 year experience preferably in a business analyst or IT related role\nImplementation experience in web-based applications, consumer subscription is a plus\nAttention to details.\u00a0 Strong analytical skill and numerical sense, ability to deal with large quantity of data with high accuracy and tight timeline\nKnowledge in New Media/TV business, Internet, Telecommunication and Mobile technology is a plus\nKnowledge of UX and web technologies such as HTML5/CSS/Javascript/Web Service\nGood interpersonal and presentation skill\nIndependent, self-initiated and self-motivated\nHands-on experience with Excel, Access, database management software and statistical tools\nGood written and oral communications in English/Chinese\nCandidates with less experience or fresh graduates are also welcome to apply for more junior position\n\nWant to be one of us?\u00a0\n\nIf you have the desire to create an exciting and rewarding career, please send us your resume immediately, quoting the reference number, your present and expected salary to\u00a0Human Resources Department by fax, post or clicking \"Apply Now\".\n\nPost:\u00a0\u00a0\u00a0\u00a06/F, Goldin Financial Global Centre, 17 Kai Cheung Road, Kowloon Bay\nFax:\u00a0\u00a0\u00a0\u00a0 (852) 2827 8322\n\nFor more information on other job opportunities of PCCW, please visit our website at\u00a0http://www.pccw.com/Careers/Job+Opportunities+%26+Application/Current+Opportunities?language=en_US\nPCCW is an equal opportunity employer and welcomes applications from all qualified candidates. Information provided will be treated in strict confidence and will only be used for recruitment-related purposes. Personal data provided by job applicants will be used strictly in accordance with the employer\u2019s\u00a0privacy statement\u00a0(www.pccw.com/privacy-statement/index.page), a copy of which will be provided immediately upon request.", "employment_types": ["Full Time", "Permanent"], "selling_points": ["Provide IT Helpdesk services for in-house end-user", "Setup and provide IT support for Live stream event", "Hands-on experience in Linux/Windows is a MUST"], "locations": ["Not Specified"], "categories": ["Information Technology (IT)", "Support", "Network & System", "Media & Advertising", "Broadcasting - TV / Radio"], "post_time": "2022-01-07T03:44:37Z", "salary": {"currency": null, "max": null, "min": null, "period": "monthly", "term": null}, "salary_visible": false, "title_keywords": ["it support engineer"], "responsibilities": ["management", "software", "data", "policies", "systems", "quality", "teams", "design", "implementation", "website", "payment", "recruitment", "providing support", "database", "personal data"], "requirements": {"degrees": ["university degree"], "majors": ["related disciplines", "statistics", "computer science"], "languages": ["english", "chinese"], "language_level": ["good"], "hard_skills": ["presentation skill", "excel", "plus", "analytical skill", "web", "information system", "mobile", "web-based applications", "javascript", "css", "web technologies"], "soft_skills": ["presentation skill", "analytical skill", "self-motivated", "independent", "oral", "confidence", "hands-on", "attention to details", "interpersonal"], "languages_combined": [{"language": "english", "language_level": ["good"]}, {"language": "chinese", "language_level": ["good"]}]}, "experience_required": {"duration": ["minimum 1 year"], "field": ["related", "database management", "business", "it"]}}, {"job_id": "100003009021427", "location_code": "hk", "company": "Zebra Strategic Outsource Solution Ltd", "job_title": "Junior / Senior Video Producer", "description": "Job Description :\n\nResponsible for Video Shooting and Lighting\u00a0\nShooting for TV Commercial , Documentary, Training Video, Corporate Video, Construction Site, Interview , Outdoor Event, Public Event where inside and outside of Hong Kong\u00a0\nCommunicate, Meeting and Site Visit with Client\u00a0\nAd-hoc duties assigned by Producer / Director\nRequirements:\u00a0\n\nMinimum HKCEE 5 subject pass (included English Syl.B and Chinese); Diploma or Certificate in Film/ Media or related field\nMinimum 5 years or above experience in Video Cameraman\nExcellent Interpersonal Skill and Communication abilities in both English and Cantonese\nWilling to work in overseas and mainland China\nHardworking and be able to work under pressure and tight deadline\nImmediately available is preferable\u00a0\nA Competitive package and promising career prospect will be offered to the right candidate. Interested parties please send your full resume, stating the date of availability, present and expected salary.\n\nAll Applications will be treated in strict confidence and personal data collected will be used for recruitment purpose only. Applications who are not invited for interview within 8 weeks may consider their applications unsuccessful. All personal data of unsuccessful candidates will be destroyed after 6 months.", "employment_types": ["Full Time", "Contract"], "selling_points": [], "locations": ["Kowloon Bay"], "categories": ["Media & Advertising", "Others", "Broadcasting - TV / Radio", "Photography / Video"], "post_time": "2022-01-05T03:56:45Z", "salary": {"currency": null, "max": null, "min": null, "period": "monthly", "term": null}, "salary_visible": false, "title_keywords": ["video producer", "junior"], "responsibilities": ["video shooting", "ad-hoc duties"], "requirements": {"degrees": ["certificate", "diploma"], "majors": [], "languages": ["cantonese", "english", "chinese"], "language_level": ["excellent"], "hard_skills": [], "soft_skills": ["communication", "work under pressure", "hardworking", "interpersonal skill"], "languages_combined": [{"language": "cantonese", "language_level": ["excellent"]}, {"language": "english", "language_level": ["excellent"]}, {"language": "chinese", "language_level": []}]}, "experience_required": {"duration": ["minimum 5 years"], "field": ["video"]}}, {"job_id": "100003009023507", "location_code": "hk", "company": "Now TV", "job_title": "Business Analyst", "description": "The Videographer and Video Editor is a part of the Technology Centre team in Cyberport that oversees video production, live streaming production, and photography. The Videographer and Video Editor is primarily responsible for the capture and editing of all produced videos.\n\nThe Videographer and Video Editor ensures safe-working practices, provides necessary production management for ensuring properly executed video production and final product, and facilitates repair and maintenance of the video equipment. Key to this is a strong work ethic centered on excellent organizational skills and the ability to develop and maintain positive, collaborative relationships and communications with all parties.\n\nKey Responsibilities\n\nWorking in an in-house video production team to create and produce video contents for various usage including promotion video, event highlights, interviews, and live streaming\nAttends required production meetings\nDetermines the necessary technical supports, such as lighting, sound, backdrops, and special needs, necessary for the video productions in advance of production dates\nOversees and implements production preparation for all video shoots\nWorks with Technology Center team for support of pre-production activities such as scout locations, write technical and instructional content\nComplete post-production activities such as editing, graphics, special effects, music selection, media conversion and duplication\nFollow final review and approval processes to ensure content quality and editorial and branding compliance\nMonitors the condition of equipment including camera, lighting, sound, and rigging equipment; reports to center manager for the repair and replacement; performs preventive maintenance on equipment\nAssist Technology Centre team with tasks not related to video as may be necessary\nAdditional duties as assigned by the Technology Center Manager\n\n\u00a0Requirements\n\nBachelor\u2019s degree or equivalent experience in digital and multi-media, including videography and video editing, or related field and a minimum of 5 years of experience working in video production and multi-media field\nProficient in video production equipment including video cameras, microphone, and lightings\nExtensive editing knowledge using Final Cut Pro / Adobe Premiere Pro\nGood knowledge using motion graphics tools such as Adobe After Effects to enhance video footage and standalone videos for social media\nKnowledge using graphic editing tools such as Adobe Photoshop and Adobe Illustrator is a plus\nProactively stay on top of video marketing trends and news, to inform future growth strategies and opportunities\nKnowledge in live streaming production workflow, platform, and equipment\nManage multiple projects simultaneously while meeting tight deadlines and brand requirements\n\nThe position is on a renewable 2-year fixed-term contract (subject to performance and operational needs).\n\nWe offer competitive package to the right candidate. Interested party please click\u00a0Apply Now\u00a0to apply on or before\u00a014 January 2022\u00a0in confidence with full resume in Word document, stating present and expected salary, and available date\u00a0and quote the reference.\u00a0\n\nApplicants who do not hear from us by\u00a028 January 2022\u00a0may assume that their applications are unsuccessful.\n\nFurther information about the Cyberport is available at\u00a0http://www.cyberport.hk", "employment_types": ["Full Time"], "selling_points": ["Understanding user requirements", "Conducting end user training", "Knowledge in New Media/TV business"], "locations": ["Kowloon Bay"], "categories": ["Information Technology (IT)", "Product Management / Business Analyst", "Media & Advertising", "Broadcasting - TV / Radio"], "post_time": "2022-01-05T08:58:18Z", "salary": {"currency": null, "max": null, "min": null, "period": "monthly", "term": null}, "salary_visible": false, "title_keywords": ["business analyst"], "responsibilities": ["graphics", "technical supports", "maintenance", "video production", "additional duties", "review", "quality", "compliance", "repair", "reports", "contents", "pre-production", "editing"], "requirements": {"degrees": ["degree", "bachelor"], "majors": [], "languages": [], "language_level": [], "hard_skills": ["final cut pro", "graphics", "plus", "inform", "adobe photoshop", "adobe after effects", "video editing", "adobe premiere pro", "adobe illustrator"], "soft_skills": ["manage multiple projects simultaneously", "meeting tight deadlines", "extensive"], "languages_combined": []}, "experience_required": {"duration": ["minimum of 5 years"], "field": ["video", "related", "video production", "digital", "editing", "media"]}}, {"job_id": "100003009025934", "location_code": "hk", "company": "Phoenix Satellite Television Co Ltd", "job_title": "DEPUTY FINANCE EDITOR/ ANCHOR", "description": "Project Coordinator\n\nResponsibilities:\n\n-\u00a0\u00a0\u00a0\u00a0\u00a0\u00a0\u00a0\u00a0\u00a0\u00a0\u00a0\u00a0\u00a0 Carry out all duties in planning, coordination, organization and implementation of project and event\n\n-\u00a0\u00a0\u00a0\u00a0\u00a0\u00a0\u00a0\u00a0\u00a0\u00a0\u00a0\u00a0\u00a0 Coordinate on logistical arrangement and to provide onsite support for all kinds of events\n\n-\u00a0\u00a0\u00a0\u00a0\u00a0\u00a0\u00a0\u00a0\u00a0\u00a0\u00a0\u00a0\u00a0 Keep track of multiple works and project status to ensure timely delivery\n\n-\u00a0\u00a0\u00a0\u00a0\u00a0\u00a0\u00a0\u00a0\u00a0\u00a0\u00a0\u00a0\u00a0 Assist to pitch commercial sponsors or government subsidy for events\n\n-\u00a0\u00a0\u00a0\u00a0\u00a0\u00a0\u00a0\u00a0\u00a0\u00a0\u00a0\u00a0\u00a0 Document, monitor and review the project progress and prepare reports and proposal\n\n-\u00a0\u00a0\u00a0\u00a0\u00a0\u00a0\u00a0\u00a0\u00a0\u00a0\u00a0\u00a0\u00a0 Assist to manage the smooth operation of the office\n\n-\u00a0\u00a0\u00a0\u00a0\u00a0\u00a0\u00a0\u00a0\u00a0\u00a0\u00a0\u00a0\u00a0 Perform administration and logistic duties\n\n-\u00a0\u00a0\u00a0\u00a0\u00a0\u00a0\u00a0\u00a0\u00a0\u00a0\u00a0\u00a0\u00a0 Perform other duties when required\n\nRequirements:\n\n-\u00a0\u00a0\u00a0\u00a0\u00a0\u00a0\u00a0\u00a0\u00a0\u00a0\u00a0\u00a0\u00a0 Degree holder or post-secondary education is preferable\n\n-\u00a0\u00a0\u00a0\u00a0\u00a0\u00a0\u00a0\u00a0\u00a0\u00a0\u00a0\u00a0\u00a0 One year working experience but fresh graduate will also be considered\n\n-\u00a0\u00a0\u00a0\u00a0\u00a0\u00a0\u00a0\u00a0\u00a0\u00a0\u00a0\u00a0\u00a0 Experience in administrative and office operation\n\n-\u00a0\u00a0\u00a0\u00a0\u00a0\u00a0\u00a0\u00a0\u00a0\u00a0\u00a0\u00a0\u00a0 Good command of written and spoken Chinese and English\n\n-\u00a0\u00a0\u00a0\u00a0\u00a0\u00a0\u00a0\u00a0\u00a0\u00a0\u00a0\u00a0\u00a0 Fluent in spoken Cantonese is a must\n\n-\u00a0\u00a0\u00a0\u00a0\u00a0\u00a0\u00a0\u00a0\u00a0\u00a0\u00a0\u00a0\u00a0 Experience in NGO projects is an advantage\n\n-\u00a0\u00a0\u00a0\u00a0\u00a0\u00a0\u00a0\u00a0\u00a0\u00a0\u00a0\u00a0\u00a0 Ability to work independently but also work as a team; strong communication skills and can work under pressure and tight schedule\n\n-\u00a0\u00a0\u00a0\u00a0\u00a0\u00a0\u00a0\u00a0\u00a0\u00a0\u00a0\u00a0\u00a0 Able to work under flexible hours\n\n-\u00a0\u00a0\u00a0\u00a0\u00a0\u00a0\u00a0\u00a0\u00a0\u00a0\u00a0\u00a0\u00a0 Pleasant and outgoing character\n\nWe offer 5-day work, competitive salary and fringe benefits to the right candidate. Interested parties are invited to send your full resume with current and expected salary.\u00a0 All applications will be treated in strict confidential and used for recruitment purpose only.", "employment_types": ["Full Time", "Permanent"], "selling_points": [], "locations": ["Tai Po Area"], "categories": ["Media & Advertising", "Broadcasting - TV / Radio"], "post_time": "2022-01-06T06:49:18Z", "salary": {"currency": null, "max": null, "min": null, "period": null, "term": null}, "salary_visible": false, "title_keywords": ["editor", "anchor"], "responsibilities": ["administration", "perform other duties", "review", "monitor", "implementation", "project progress", "coordinate", "coordination", "prepare reports", "planning"], "requirements": {"degrees": ["secondary education", "fresh graduate", "degree holder"], "majors": [], "languages": ["cantonese", "english", "chinese"], "language_level": ["good command", "fluent"], "hard_skills": [], "soft_skills": ["flexible", "communication skills", "work independently", "outgoing", "work as a team", "pleasant", "work under pressure"], "languages_combined": [{"language": "cantonese", "language_level": ["fluent"]}, {"language": "english", "language_level": ["good command"]}, {"language": "chinese", "language_level": ["good command"]}]}, "experience_required": {"duration": ["one year"], "field": ["operation", "administrative"]}}, {"job_id": "100003009024695", "location_code": "hk", "company": "Phoenix Satellite Television Co Ltd", "job_title": "SUB-EDITOR", "description": "Responsibilities:\n\nProofread and edit financial related stories and select topic.\nLiase with guests for the finance program.\nAnchoring and hosting daily finance program.\n\nRequirements:\n\nUniversity graduate in Journalism, Communications or Business related.\nMinimum 3 years editorial / journalistic experience, TV experience is preferred.\nFamiliar and sensitive to Finance news / International affairs.\nAccurate, detail-minded and able to work under pressure.\nAble to react tactfully to emergency circumstances.\nExcellent command of written and spoken English and Chinese, proficiency in Cantonese is a MUST.\n\n\n\nWe offer attractive remuneration package to the right candidate. Interested parties please send applications with detailed resume stating career history, present & expected salary and date available to Human Resources Department, Phoenix Satellite Television Co. Ltd. via e-mail: phxhr@ phoenixtv.com or via fax: 2200 8620.\n\nPersonal data collected will be used for recruitment purpose only.\u00a0 Applicants not hearing from us within 6 weeks may consider their applications unsuccessful and all related information will be destroyed after 6 months.", "employment_types": ["Full Time", "Permanent"], "selling_points": [], "locations": ["Tai Po Area"], "categories": ["Media & Advertising", "Others", "Editorial / Journalism", "Broadcasting - TV / Radio"], "post_time": "2022-01-06T02:14:22Z", "salary": {"currency": null, "max": null, "min": null, "period": null, "term": null}, "salary_visible": false, "title_keywords": ["editor"], "responsibilities": [], "requirements": {"degrees": ["university graduate"], "majors": ["journalism", "business", "communications"], "languages": ["cantonese", "english", "chinese"], "language_level": ["excellent", "proficiency"], "hard_skills": ["react"], "soft_skills": ["detail-minded", "sensitive to", "accurate", "work under pressure"], "languages_combined": [{"language": "cantonese", "language_level": ["proficiency", "excellent"]}, {"language": "english", "language_level": ["proficiency", "excellent"]}, {"language": "chinese", "language_level": ["proficiency", "excellent"]}]}, "experience_required": {"duration": ["minimum 3 years"], "field": ["editorial", "journalistic"]}}, {"job_id": "100003009016422", "location_code": "hk", "company": "now TV", "job_title": "Reporter (English News)", "description": "Job Description\n\n- Responsible for shooting all kinds of video projects, including events, social media videos, online streaming videos, corporate videos, construction videos, TVCs, etc.\n- Assist in video editing, and other ad hoc production duties\n- Equipment maintenance\n\n\nRequirements:\n\n- Higher diploma or above in TV / Video Production / Journalism or related areas\n- At least 1 year working experience in video production\n- Strong in video shooting and camera operation\n- Strong knowledge of DSLR and video cameras\n- Good knowledge in lighting and audio recording equipment\n- Basic knowledge in Adobe Premiere pro and good knowledge in After Effects, Photoshop and Illustrator\n- Self-motivated, responsible and a good team player\n- Able to travel overseas", "employment_types": ["Full Time", "Permanent"], "selling_points": ["Conducting interviews, reporting", "English News", "Will consider fresh graduates"], "locations": ["Wan Chai"], "categories": ["Media & Advertising", "Editorial / Journalism", "Broadcasting - TV / Radio"], "post_time": "2022-01-03T09:03:15Z", "salary": {"currency": null, "max": null, "min": null, "period": null, "term": null}, "salary_visible": false, "title_keywords": ["reporter"], "responsibilities": ["video editing", "social media", "ad hoc", "maintenance"], "requirements": {"degrees": ["higher diploma or above"], "majors": ["journalism"], "languages": [], "language_level": [], "hard_skills": ["basic", "illustrator", "adobe premiere pro", "after effects", "photoshop"], "soft_skills": ["good team player", "self-motivated", "responsible"], "languages_combined": []}, "experience_required": {"duration": ["at least 1 year"], "field": ["video production"]}}, {"job_id": "100003009017019", "location_code": "hk", "company": "The New Office Limited", "job_title": "Videographer / Junior Cameraman", "description": "Network Projects Department\n\nTo be responsible for planning and designing the CATV network design on Coaxial Network, Fiber Optic Network and GPON Network;\nHigher Diploma in Electronic Engineering, Telecommunications or related disciplines with minimum 2 years working experience, with exposure in CATV and telecommunication field is preferred\nIn-depth knowledge in television and telecommunication standard and specification\nGood command of both spoken and written English & Chinese\nStrong analytical skills and self-driven in problem solving\n\nWe offer 5-day work week, competitive remuneration packages and advancement opportunities. Interested parties, please write with full resume to\u00a0Director, Human Resources,\u00a0Human Resources Department, i-CABLE Communications Limited, 4/F Cable TV Tower, 9 Hoi Shing Road Tsuen Wan, N.T. or fax to 2112 7841\u00a0or\u00a0Apply Now\u00a0(Please quote reference number and position applied for).\u00a0 For other information, please visit our website\u00a0http://www.i-cable.com.\n\nYour application may be forwarded to any company within Wharf Group and successful applicant may be seconded to work at any office as assigned. The information received will be used for consideration of employment only and all personal data supplied will be destroyed within 3 months.\n\nWe are an equal opportunity employer.", "employment_types": ["Full Time"], "selling_points": [], "locations": ["Tsuen Wan Area"], "categories": ["Media & Advertising", "Production", "Broadcasting - TV / Radio", "Photography / Video"], "post_time": "2022-01-03T10:30:07Z", "salary": {"currency": null, "max": null, "min": null, "period": "monthly", "term": null}, "salary_visible": false, "title_keywords": ["videographer", "junior"], "responsibilities": ["designing", "design", "planning"], "requirements": {"degrees": ["diploma"], "majors": ["related disciplines", "engineering"], "languages": ["english", "chinese"], "language_level": ["good command"], "hard_skills": ["problem solving", "analytical skills"], "soft_skills": ["problem solving", "driven", "responsible", "analytical skills"], "languages_combined": [{"language": "english", "language_level": ["good command"]}, {"language": "chinese", "language_level": ["good command"]}]}, "experience_required": {"duration": ["minimum 2 years"], "field": ["telecommunications", "engineering", "related"]}}, {"job_id": "100003009031115", "location_code": "hk", "company": "i-CABLE Communications Limited", "job_title": "Designer - Network", "description": "Under the direction of the Head of Production in APAC, the Multimedia Video Specialist provides a wide range of technical services to assist in delivering innovative, seamless, and quality Livestream and broadcasting solutions for clients in the finance industry. The incumbent is also expected to work in an environment in which technical supervision is not available and he/she is the primary source for technical support for clients. Work is typically performed in a combination of studio, control room, and office environment. Interruptions are expected to occur often and the incumbent must be able to prioritize work.\n\nDuties and Responsibilities\n- Provide support on pre-production, onsite production, and post video production for the Livestream broadcast\n- Manage a range of audio & video scenarios within a studio environment\n- Set up video and lighting, video shoot, audio recording, mixing, and related production activities\n- Act as a technical and creative resource assisting in video production\n- Contribute to technical or content ideas to assist in achieving desirable outcomes for the video project\n- Support video conferencing services to include the operation of control bridge\n- Prepare, set up, and test all studio equipment prior to broadcast\n- Lead on the maintenance of multimedia related requirements and software\n- Perform accessibility training and quality assurance\n- Coordinate multiple projects with frequently adjusted priorities\n- Other production-based tasks as needed\n\nQualifications\n- Bachelor\u2019s or Associate\u2019s degree or two years of college-level course work in electronic/multi-media production, graphic design, or related area\n- Individuals who do not meet the above education requirement but have relevant experience in the studio, production, and live broadcast environment can also be considered\n- Three to five years of recent experience in creating video content using tools such as Vmix or Tricaster is a must\n- Proficiency in Premiere, Photoshop, QuickTime, and other Adobe products\n- Strong ability to communicate and work with non-technical clients and translate content into multimedia products in formats including but not limited to video, audio, graphics, and digital animations\n- Demonstrate ability to work as part of a project team\n- Ability to work in a high paced environment\n- Able to adapt and respond quickly to constantly changing technology\n- Strong verbal communication skills\n- Proficiency in English and Mandarin", "employment_types": ["Full Time", "Permanent"], "selling_points": [], "locations": ["Tsuen Wan Area"], "categories": ["Design", "Others", "Engineering", "Electrical / Electronics", "Media & Advertising", "Broadcasting - TV / Radio"], "post_time": "2022-01-07T08:59:44Z", "salary": {"currency": null, "max": null, "min": null, "period": "monthly", "term": null}, "salary_visible": false, "title_keywords": ["designer"], "responsibilities": ["graphics", "provide support", "control", "ideas", "control room", "maintenance", "software", "technical support", "video production", "graphic design", "quality", "coordinate", "communication", "animations", "pre-production", "audio", "high paced environment", "multiple projects"], "requirements": {"degrees": ["degree", "bachelor"], "majors": ["graphic design"], "languages": ["english", "mandarin"], "language_level": ["proficiency"], "hard_skills": ["graphics", "maintenance", "premiere", "adobe", "multimedia", "photoshop"], "soft_skills": ["communication skills", "innovative", "creative", "able to prioritize"], "languages_combined": [{"language": "english", "language_level": ["proficiency"]}, {"language": "mandarin", "language_level": ["proficiency"]}]}, "experience_required": {"duration": ["three to five years"], "field": ["video", "relevant experience", "education"]}}, {"job_id": "100003009016485", "location_code": "hk", "company": "ViuTV", "job_title": "\u5916\u666f\u651d\u5f71\u5e2b / \u521d\u7d1a\u5916\u666f\u651d\u5f71\u5e2b", "description": "\u4e3b\u8981\u8077\u8cac\uff1a\n\n\u8ca0\u8cac\u64cd\u4f5c\u96fb\u8996\u62cd\u651d\u4e4b\u5404\u7a2e\u624b\u63d0\u651d\u5f71\u6a5f\uff0c\u5176\u4e2d\u5305\u62ec\uff1aSony PXW, A7S; Canon MK II, MK III, MK IV; GoPro Hero \u7b49\n\u6839\u64da\u5c0e\u6f14\u8981\u6c42\u62cd\u651d\u4e0d\u540c\u985e\u578b\u7684\u96fb\u8996\u7bc0\u76ee\n\u8207\u71c8\u5149\u53ca\u6536\u97f3\u5de5\u4f5c\u4eba\u54e1\u5408\u4f5c\u63d0\u4f9b\u6700\u4f73\u8996\u807d\u6548\u679c\n\u9700\u8f2a\u73ed\u5de5\u4f5c\u53ca\u914d\u5408\u4e0d\u5b9a\u6642\u4e0a\u4e0b\u73ed\u6642\u9593\uff0c\u5305\u62ec\u5728\u5468\u672b\u53ca\u5047\u65e5\u5de5\u4f5c\n\u6709\u9700\u8981\u6703\u5b89\u6392\u5916\u57e0\u62cd\u651d\n\n\u5165\u8077\u8981\u6c42:\n\n\u5177\u5c08\u696d\u62cd\u651d\u5de5\u4f5c\u7d93\u9a57\uff0c\u66fe\u65bc\u5236\u4f5c\u516c\u53f8\u6216\u96fb\u8996\u53f0\u5de5\u4f5c\u66f4\u4f73\n\u4e2d\u5b78\u7a0b\u5ea6\uff0c\u5982\u6709\u76f8\u95dc\u5b78\u6b77\u6216\u5c0a\u696d\u8cc7\u683c\u66f4\u4f73\n\u80fd\u55ae\u7368\u5de5\u4f5c\n\u5916\u666f\u55ae\u6a5f\u4f5c\u696d\u64cd\u4f5c\uff0c\u719f\u6089\u96fb\u8996\u71c8\u5149\u64cd\u4f5c\u8005\u512a\u5148\n\u826f\u597d\u6e9d\u901a\u80fd\u529b\uff0c\u5177\u5718\u968a\u7cbe\u795e\u53ca\u80fd\u65bc\u58d3\u529b\u4e0b\u5de5\u4f5c\n\u56e0\u61c9\u4e0d\u540c\u7d93\u9a57\uff0c\u61c9\u5fb5\u8005\u6703\u88ab\u8003\u616e\u70ba\u4e0d\u540c\u7d1a\u5225\u5d17\u4f4d\n\n\u7533\u8acb\u65b9\u6cd5:\n\n\u5de5\u4f5c\u5c65\u6b77\u53ef\u6309 \"Apply Now\" \u50b3\u9001\u00a0\u6216\n\u90f5\u5bc4\u81f3 \u00a0\u00a0\u00a0\u00a0\u4e5d\u9f8d\u7063\u5553\u7965\u905317\u865f\u9ad8\u9280\u91d1\u878d\u570b\u969b\u4e2d\u5fc36 \u6a13 \u6216\n\u50b3\u771f\u81f3\u00a0\u00a0\u00a0\u00a0\u00a0(852) 2827 8322\n\n\u96fb\u8a0a\u76c8\u79d1\u70ba\u5e73\u7b49\u6a5f\u6703\u50f1\u4e3b\uff0c\u6b61\u8fce\u6240\u6709\u5408\u8cc7\u683c\u4eba\u58eb\u7533\u8acb\u5404\u9805\u8077\u4f4d\uff0c\u7533\u8acb\u4eba\u6240\u63d0\u4f9b\u7684\u8cc7\u6599\u7d55\u5c0d\u4fdd\u5bc6\uff0c\u4e26\u53ea\u4f5c\u8207\u62db\u8058\u6709\u95dc\u7684\u7528\u9014\u3002\u5728\u4f7f\u7528\u6c42\u8077\u8005\u6240\u63d0\u4f9b\u7684\u500b\u4eba\u8cc7\u6599\u6642\uff0c\u50f1\u4e3b\u6703\u56b4\u683c\u9075\u5b88\u5176\u500b\u4eba\u8cc7\u6599\u653f\u7b56\u7684\u898f\u5b9a\uff0c\u4e26\u5728\u6536\u5230\u6709\u95dc\u8981\u6c42\u5f8c\uff0c\u6703\u96a8\u5373\u63d0\u4f9b\u4e00\u4efd\u6709\u95dc\u653f\u7b56\u7684\u8907\u672c\u3002\n\n\u79c1\u96b1\u8072\u660e", "employment_types": ["Full Time"], "selling_points": ["\u8ca0\u8cac\u64cd\u4f5c\u96fb\u8996\u62cd\u651d\u4e4b\u5404\u7a2e\u624b\u63d0\u651d\u5f71\u6a5f", "\u62cd\u651d\u4e0d\u540c\u985e\u578b\u7684\u96fb\u8996\u7bc0\u76ee", "\u9700\u8f2a\u73ed\u5de5\u4f5c"], "locations": ["Kowloon Bay"], "categories": ["Media & Advertising", "Production", "Broadcasting - TV / Radio", "Photography / Video"], "post_time": "2022-01-03T09:11:46Z", "salary": {"currency": null, "max": null, "min": null, "period": null, "term": null}, "salary_visible": false, "title_keywords": [], "responsibilities": [], "requirements": {"degrees": [], "majors": [], "languages": [], "language_level": [], "hard_skills": [], "soft_skills": [], "languages_combined": []}, "experience_required": {"duration": [], "field": []}}, {"job_id": "100003009020551", "location_code": "hk", "company": "One Click Go Live Limited", "job_title": "System Administrator", "description": "One Click Go Live Limited (\u201cONE CLICK GO LIVE\u201d)\u00a0is a live streaming technology company focuses on enterprise broadcast-grade video live streaming solutions with offerings including live streaming platforms, products and services.\u00a0ONE CLICK GO LIVE enables corporates to conduct professional live streaming through one single button \u2013 ONE CLICK GO LIVE, delivering a seamless user experience in combination with patented technologies.\n\nServing over 300 corporates for over 9,000 live streaming events,\u00a0ONE CLICK GO LIVE leverages its technical expertise while corporates focus on generating growth and revenue with video content.\u00a0\n\nOur successful cases:\u00a0www.oneclickgolive.com\n\nWe are looking for candidate(s) who is/are interested to join our fast growing team.\u00a0 Training will be offered for potential candidate(s).\n\n\nJob responsibility:\n\nTo install, maintain and support the IT infrastructure, security, networking, server computers and messaging systems;\nManage Internal IT systems (i.e. web, email, applications and server, etc.);\u00a0\nResponsible for the installation, administration, maintenance, configuration and support the smooth running of the enterprise network;\nManage infrastructure projects in a quality and timely manner;\nManage system databases and servers to ensure smooth on-going operation and up-time according to service standards.\u00a0 Plan and perform database version upgrades;\nPerform regular network scanning, analysis and threat identification;\nManage and maintain documentation of all IT assets and ensure all processes & procedure are compliant with the company policies;\nManage service transition and release to production process to ensure network infrastructure setup and its components are complied with enterprise technical standard;\nDesign, deploy, and administer the network infrastructure and supporting systems;\nTo assist and provide support to solve end user's technical problems including but not limited to any hardware, software and network systems (Operating System, MS Office suite, antivirus, email- client, office printing system, networking, etc.) ;\nProvide off-hours operational support for emergency maintenance and deployment events when necessary;\n\n\u00a0Job requirement:\n\nDiploma or Degree holders in Computer Science, Information Technology, or related discipline\n\nAt least 3-5 years' working experience in server administration and server networking or performing in system support role\nExposure in Live audio/video streaming support will be an advantage\nSound knowledge and technical skills and Microsoft Windows\u00a0\nSolid experience in Windows Server platform, Active directory, Group Policy, VMare, Networking, Firewall, switch and router\nExperience with MacOS will have an added advantage\nWilling to provide ad hoc support in non-office hours, if required\nStrong problem solving and good interpersonal skills\nInterested applicants please send us full CV with current and expected salary and availability.\n\nBenefits : Medical Allowance, Birthday and Childcare Leave\u00a0\n\nThe information provided will be treated in strict confidence and used only for consideration of application for relevant/similar post(s).\u00a0 All personal data of unsuccessful applicants will be destroyed within 6 months.", "employment_types": ["Full Time", "Permanent"], "selling_points": ["Perform server maintenance, administration,back up", "Strong problem solving and interpersonal skills", "3-5 years experience in System Administration"], "locations": ["Others"], "categories": ["Media & Advertising", "Broadcasting - TV / Radio", "Information Technology (IT)", "Mobile / Wireless Communications"], "post_time": "2022-01-04T15:27:04Z", "salary": {"currency": null, "max": null, "min": null, "period": "monthly", "term": null}, "salary_visible": false, "title_keywords": ["system administrator"], "responsibilities": ["operational support", "production process", "software", "quality", "design", "service standards", "maintain", "plan", "database", "deploy", "administration", "scanning", "it infrastructure", "configuration", "infrastructure", "setup", "network infrastructure", "installation", "provide support", "upgrades", "maintenance", "policies", "analysis", "systems", "hardware", "databases", "maintain documentation"], "requirements": {"degrees": ["diploma", "degree"], "majors": ["computer science", "information technology"], "languages": [], "language_level": [], "hard_skills": ["active directory", "server administration", "switch", "vmare", "router", "problem solving", "firewall", "server", "windows server"], "soft_skills": ["technical skills", "active", "interpersonal skills", "problem solving"], "languages_combined": []}, "experience_required": {"duration": ["at least 3-5 years"], "field": ["server networking", "system support", "server administration"]}}, {"job_id": "100003009020002", "location_code": "hk", "company": "MegaHub Limited", "job_title": "Financial Anchor", "description": "Responsibilities:\n\nPresent on camera in Cantonese for quality finance video content and live broadcast on social media platform (e.g. Facebook/ YouTube).\nDevelop ideas and concepts and collaborate with the production team for shooting and video editing.\nHost financial live broadcast, interview financial experts\nResearch local and international financial news\nPlan, create, optimize and manage content and implement on social media platform\u00a0with marketing team.\n\nRequirements:\n\nBachelor degree or above, Major in Finance, Economics, Journalism, Media, Communication, Business Management or any relevant discipline.\nMinimum 2-3 years of journalism/ broadcasting experience.\nPresentable and interested in stock market\nExcellent command in written & spoken Mandarin, Cantonese and English.\nCreative, good communication skills, team spirit and work enthusiasm.\nExcellent sense of storytelling and production workflow.\nImmediately available is preferred.\n\nTo know more about us, please visit our website: https://www.megahubhk.com/\n\nWe offer 5-day work week, flexible working hours and good career development opportunities in a young and dynamic environment.\u00a0 Interested parties, please send your resume and stating your current & expected salary to MegaHub Limited by clicking \"Apply Now\".\n(Personal data collected will be used for recruitment purpose only)\n\n\n", "employment_types": ["Full Time"], "selling_points": ["Fin-tech Co./ 5-day work/ flexible work & lunch hr", "Young & energetic Co./ good career development", "Broadcasting, planning financial feature stories"], "locations": ["Wan Chai"], "categories": ["Media & Advertising", "Creative / Design", "Strategic Planning", "Broadcasting - TV / Radio"], "post_time": "2022-01-04T09:40:13Z", "salary": {"currency": null, "max": null, "min": null, "period": "monthly", "term": null}, "salary_visible": false, "title_keywords": ["anchor"], "responsibilities": ["collaborate with", "social media", "ideas", "quality", "develop", "video editing", "plan", "facebook"], "requirements": {"degrees": ["degree or above", "bachelor"], "majors": ["journalism", "finance", "economics", "business"], "languages": ["cantonese", "english", "mandarin"], "language_level": ["excellent"], "hard_skills": ["business management"], "soft_skills": ["communication skills", "team spirit", "interested in", "presentable", "communication", "creative"], "languages_combined": [{"language": "cantonese", "language_level": ["excellent"]}, {"language": "english", "language_level": ["excellent"]}, {"language": "mandarin", "language_level": ["excellent"]}]}, "experience_required": {"duration": ["minimum 2-3 years"], "field": []}}, {"job_id": "100003009016418", "location_code": "hk", "company": "now TV", "job_title": "Anchor / Reporter", "description": "Your New Role\n\nResponsible for anchoring daily newscasts and hosting various news programs\n\nWhat makes you succeed\n\nDegree holder in Journalism / Finance / Economics or related disciplines\nFamiliar with and sensitive to current affairs and financial news\nGood communication skills and presentable\nTeam player, self-motivated and able to work under pressure and tight timeline\nExcellent command of written and spoken Chinese and English, Putonghua is an advantage\nShift duty is required\n\nWant to be one of us?\n\nWe offer attractive & competitive salary and benefits, an exciting work environment and excellent career development opportunities. If you have the desire for an exciting and rewarding career, please send us your resume, quoting the reference number, stating your present and expected salary to now Business News Channel\u00a0by post, fax or clicking \"Apply Now\":\n\nPost: 3/F, Telecom House, 3 Gloucester Road, Wan Chai, Hong Kong\n\nFax: 2511 9686\n\nFor more information on other job opportunities of PCCW, please visit our website at\u00a0\nhttp://www.pccw.com/Careers/Job+Opportunities+%26+Application/Current+Opportunities?language=en_US\n\nPCCW is an equal opportunity employer and welcomes applications from all qualified candidates. Information provided will be treated in strict confidence and will only be used for recruitment-related purposes. Personal data provided by job applicants will be used strictly in accordance with the employer personal data policies (http://www.pccw.com/staticfiles/PCCWCorpsite/Terms%20of%20Use/Privacy%20Policy%20Statement/(PCCW)%20HR%20Privacy%20Policy%20Statement%20(version%20-%20Nov%202017).pdf), a copy of which will be provided immediately upon request.\n", "employment_types": ["Full Time", "Permanent"], "selling_points": ["Present daily newscasts on TV", "Sensitive to current affairs & financial news", "Presentable"], "locations": ["Wan Chai"], "categories": ["Media & Advertising", "Editorial / Journalism", "Broadcasting - TV / Radio"], "post_time": "2022-01-03T09:02:33Z", "salary": {"currency": null, "max": null, "min": null, "period": null, "term": null}, "salary_visible": false, "title_keywords": ["reporter", "anchor"], "responsibilities": ["communication", "work under pressure"], "requirements": {"degrees": ["degree holder"], "majors": ["journalism", "finance", "related disciplines", "economics"], "languages": ["putonghua", "english", "chinese"], "language_level": ["advantage", "excellent"], "hard_skills": [], "soft_skills": ["communication skills", "self-motivated", "responsible", "presentable", "sensitive to", "team player", "work under pressure"], "languages_combined": [{"language": "putonghua", "language_level": ["advantage", "excellent"]}, {"language": "english", "language_level": ["excellent"]}, {"language": "chinese", "language_level": ["excellent"]}]}, "experience_required": {"duration": [], "field": []}}, {"job_id": "100003009013297", "location_code": "hk", "company": "Strategist Publishing Limited", "job_title": "Studio Assistant", "description": "Commercial Radio Interactive, a division of Commercial Radio Productions Limited and the digital arm of Commercial Radio, are looking for a passionate and energetic\u00a0System Engineer to join our IT team and develop his/her career under the guidance of our experienced senior staff.\n\n\n\nJob Duties\n\nProvide IT Helpdesk services for in-house end-users\nSetup and provide IT support for Live streaming event\nInstall, configure, and maintain internal systems/services\nPerform Linux/Windows system administration\nCreate and maintain technical documentation\nJob Requirements\n\n\nHigher Diploma or Degree holder in Computer Science or related disciplines of Tertiary Education\nMinimum 1 year solid experiences in system administration and technical support\u00a0\nHands-on experience in Linux/Windows is a MUST\nHolder of RHCT/RHCE, LPI, MCSA, MCSE is an advantage\nHands-on experience in VMWare is an advantage\nGood problem solving skills , pay attention to details and good communication skills\nResponsible, self motivated, work independently, and process tasks without supervision\nWilling to work at non office hour for urgent production service support & maintenance.\nFresh graduates are also welcome\n\nOffice location: Kowloon Tong\n\nApplication Procedure:\n\nWe offer attractive remuneration package, competitive salary, medical scheme and life insurance to the right candidate. Interested candidates, please submit application letter with full resume, present and expected salary by clicking \u201cApply Now\u201d (Please quote the job reference number on the e-mail subject line).\n\nAll information received will be kept in strict confidence and only for employment-related purpose. Only short listed candidates will be invited for interview.", "employment_types": ["Full Time"], "selling_points": [], "locations": ["Central"], "categories": ["Media & Advertising", "Broadcasting - TV / Radio"], "post_time": "2022-01-03T02:01:43Z", "salary": {"currency": "HKD", "max": 16999, "min": 14000, "period": "monthly", "term": null}, "salary_visible": true, "title_keywords": ["assistant"], "responsibilities": ["maintain", "documentation", "internal systems", "setup", "administration"], "requirements": {"degrees": ["diploma", "degree holder"], "majors": ["related disciplines", "computer science"], "languages": [], "language_level": [], "hard_skills": ["linux", "mcse", "vmware", "maintenance", "mcsa", "problem solving skills"], "soft_skills": ["communication skills", "work independently", "responsible", "self motivated", "hands-on", "attention to details", "problem solving skills"], "languages_combined": []}, "experience_required": {"duration": ["minimum 1 year"], "field": ["administration"]}}, {"job_id": "100003009016495", "location_code": "hk", "company": "ViuTV", "job_title": "Junior Audio Engineer", "description": "\n\n\u53d7\u8058\u54e1\u5de5\u5c07\u7372\u59d4\u6d3e\u65bc MOOV (Hong Kong) Limited \u5de5\u4f5c\u3002\n\n\u4e3b\u8981\u8077\u8cac\n\n\u62cd\u651d\u5f71\u7247\u65bc\u793e\u4ea4\u5a92\u9ad4\u767c\u4f48\n\u62cd\u651d\u6b4c\u624b\u8a2a\u554f\u53ca\u5275\u610f\u5f71\u7247\n\u62cd\u651d\u97f3\u6a02\u8868\u6f14\u76f4\u64ad\u7bc0\u76ee\n\u8ca0\u8cac\u526a\u63a5\u5f71\u7247\u65bc\u793e\u4ea4\u5a92\u9ad4\u767c\u4f48\n\u526a\u63a5\u6b4c\u624b\u8a2a\u554f\u53ca\u5275\u610f\u5f71\u7247\n\u5f8c\u671f\u8996\u8a0a\u6548\u679c\n\n\u5165\u8077\u8981\u6c42\n\n2-3\u5e74\u4ee5\u4e0a\u5c08\u696d\u62cd\u651d, \u5c08\u696d\u526a\u63a5\u5de5\u4f5c\u7d93\u9a57\uff0c\u719f\u7df4\u638c\u63e1premiere, after effect, cs &ai \uff0c\u66fe\u65bc\u5236\u4f5c\u516c\u53f8\u6216\u7db2\u4e0a\u5a92\u9ad4\u5de5\u4f5c\u66f4\u4f73\n\u4e2d\u5b78\u7a0b\u5ea6\uff0c\u5982\u6709\u76f8\u95dc\u5b78\u6b77\u6216\u5c08\u696d\u8cc7\u683c\u66f4\u4f73\n\u80fd\u55ae\u7368\u5de5\u4f5c \u5916\u666f\u55ae\u6a5f\u4f5c\u696d\u64cd\u4f5c\uff0c\u719f\u6089\u71c8\u5149\u64cd\u4f5c\u8005\u512a\u5148\n\u826f\u597d\u6e9d\u901a\u80fd\u529b\uff0c\u5177\u5718\u968a\u7cbe\u795e\u53ca\u80fd\u65bc\u58d3\u529b\u4e0b\u5de5\u4f5c\n\nThis position will be under the employment of Zebra Strategic Outsource Solution Ltd.\n\nTo find out more about Zebra, visit us at\u00a0www.zebragroup.com\n\nAll personal data collected will be kept in strict confidence and would only be used for recruitment purpose.", "employment_types": ["Full Time", "Permanent"], "selling_points": ["Responsible for audio post production work", "Proficiency in  ProTools Software", "Have a good sense in audio mixing and balance"], "locations": ["Kowloon Bay"], "categories": ["Media & Advertising", "Production", "Engineering", "Telecommunication / Wireless / Radio", "Broadcasting - TV / Radio"], "post_time": "2022-01-03T09:12:26Z", "salary": {"currency": null, "max": null, "min": null, "period": null, "term": null}, "salary_visible": false, "title_keywords": ["engineer", "junior"], "responsibilities": ["personal data", "recruitment"], "requirements": {"degrees": [], "majors": [], "languages": [], "language_level": [], "hard_skills": ["after effect", "ai"], "soft_skills": ["confidence"], "languages_combined": []}, "experience_required": {"duration": [], "field": []}}, {"job_id": "100003009018063", "location_code": "hk", "company": "All's Well Media Company Limited", "job_title": "Program Officer / Senior Program Officer", "description": "Your New Role\u00a0\n\n\nResponsible for audio post production work\n\nWhat makes you succeed\n\n\nF.7 / DSE or IVE graduates with a minimum of 2 years\u2019 relevant experience\nProficiencyin \u00a0ProTools Software (latest version)\nGood knowledge of Sound Recording, Effects and Plugins\nHave a good sense in Music and TV programs audio mixing and balance\nShift duty and work on public holidays are required\nFresh graduate or candidate with less experience will also be considered\n\nWant to be one of us?\n\nWe offer attractive & competitive salary and benefits, an exciting work environment and excellent career development opportunities. If you have the desire for an exciting and rewarding career, please send us your resume, stating your present and expected salary to Human Resources Department\u00a0by post, fax or clicking \"Apply Now\".\u00a0\u00a0\n\nPost :\u00a06/F, Goldin Financial Global Centre, 17 Kai Cheung Road, Kowloon Bay\u00a0\nFax :\u00a0 2827 8322\u00a0\u00a0\n\nFor more information on other job opportunities of PCCW, please visit our website at<http://www.pccw.com/Careers/Job+Opportunities+&+Application/Current+Opportunities?language=en_US>\u00a0\u00a0\n\nPCCW is an equal opportunity employer and welcomes applications from all qualified candidates. Information provided will be treated in strict confidence and will only be used for recruitment-related purposes. Personal data provided by job applicants will be used strictly in accordance with the employer personal data policies (http://www.pccw.com/staticfiles/PCCWCorpsite/Terms%20of%20Use/Privacy%20Policy%20Statement/(PCCW)%20HR%20Privacy%20Policy%20Statement%20(version%20-%20Nov%202017).pdf), a copy of which will be provided immediately upon request.", "employment_types": ["Full Time"], "selling_points": ["Program Scheduling", "Assist in program research", "Write program highlights and synopsis"], "locations": ["Wong Tai Sin Area"], "categories": ["Media & Advertising", "Others", "Broadcasting - TV / Radio"], "post_time": "2022-01-04T02:48:13Z", "salary": {"currency": null, "max": null, "min": null, "period": "monthly", "term": null}, "salary_visible": false, "title_keywords": ["officer"], "responsibilities": ["audio", "software"], "requirements": {"degrees": ["fresh graduate", "dse"], "majors": [], "languages": [], "language_level": [], "hard_skills": [], "soft_skills": ["responsible"], "languages_combined": []}, "experience_required": {"duration": ["minimum of 2 years"], "field": ["relevant experience"]}}, {"job_id": "100003009016441", "location_code": "hk", "company": "PCCW Media", "job_title": "Librarian", "description": "Job Descriptions:\n\nTo be responsible for producing programs, on air promos and online platform\nWork closely with research writers, motion graphic designers, production crew, talents and related parties\nResponsible for initiating the creative process from idea conceptualization to creative proposal\n\nRequirements:\n\nDegree or Diploma holder in Film & TV/ Creative Media / Visual Communication or equivalent\n2 years or above related working experiences, preferably work experience with TV Stations or advertising productions\nProficiency in non-linear editing(Final Cut Pro/Premiere) is a must, preferably with shooting experience\nKnowledge of motion graphic skills is an advantage such as After Effect, Photoshop, etc.\nKnowledge of video/DSLR camera operation\nFamiliar with social media and digital space\nFluent in written & spoken English and Chinese, proficiency in Putonghua is an advantage\nCreative, self-motivated, good communication and organization skill\nWilling to work on irregular hours and able to work under pressure to meet tight deadline\n\nInterested parties please send full resume and expected salary by clicking \"APPLY NOW\".\n\nFor more details of our company, please visit our website at www.nowbaogumovies.com\n\nFB: Now\u7206\u8c37\u53f0\n\n(Data collected will be used for recruitment purposes only.)", "employment_types": ["Full Time"], "selling_points": ["Index news footage", "Update library database", "Strong computer literacy"], "locations": ["Wan Chai"], "categories": ["Media & Advertising", "Broadcasting - TV / Radio"], "post_time": "2022-01-03T09:04:31Z", "salary": {"currency": null, "max": null, "min": null, "period": "monthly", "term": null}, "salary_visible": false, "title_keywords": [], "responsibilities": ["motion graphic"], "requirements": {"degrees": ["diploma holder", "degree"], "majors": ["creative media"], "languages": ["putonghua", "english", "chinese"], "language_level": ["advantage", "proficiency", "fluent"], "hard_skills": ["visual communication", "after effect", "premiere", "photoshop"], "soft_skills": ["self-motivated", "organization skill", "communication", "meet tight deadline", "creative", "work under pressure"], "languages_combined": [{"language": "putonghua", "language_level": ["proficiency", "fluent"]}, {"language": "english", "language_level": ["advantage", "fluent"]}, {"language": "chinese", "language_level": ["advantage", "fluent"]}]}, "experience_required": {"duration": ["2 years"], "field": ["related", "advertising"]}}, {"job_id": "100003009016397", "location_code": "hk", "company": "now TV", "job_title": "Sub-editor / Translator (International News)", "description": "Your New Role:\n\nTo index news footage and update the library database.\u00a0\n\nWhat makes you succeed:\u00a0\n\nUniversity graduate with relevant experience in library\nGood command of both written and spoken English and Chinese\nStrong computer literacy in MS applications including Chinese word processing\nWilling to work on shift\n\nWant to be one of us?\n\nWe offer attractive & competitive salary and benefits, an exciting work environment and excellent career development opportunities.\u00a0If you have the desire for an exciting and rewarding career, please send us your resume,\u00a0stating your present and expected salary to Human Resources Department by clicking \"Apply Now\"\u00a0\n\nFor more information on other job opportunities of PCCW, please visit our website at\u00a0http://www.pccw.com/Careers/Job+Opportunities+%26+Application/Current+Opportunities?language=en_US\nPCCW is an equal opportunity employer and welcomes applications from all qualified candidates. Information provided will be treated in strict confidence and will only be used for recruitment-related purposes. Personal data provided by job applicants will be used strictly in accordance with the employer\u2019s\u00a0privacy statement\u00a0(www.pccw.com/privacy-statement/index.page), a copy of which will be provided immediately upon request.", "employment_types": ["Full Time", "Permanent"], "selling_points": ["Translating and writing international news", "Sensitive to news and current affairs", "Good translation and writing skills"], "locations": ["Wan Chai"], "categories": ["Media & Advertising", "Editorial / Journalism", "Broadcasting - TV / Radio"], "post_time": "2022-01-03T09:00:34Z", "salary": {"currency": null, "max": null, "min": null, "period": null, "term": null}, "salary_visible": false, "title_keywords": ["editor", "translator"], "responsibilities": ["database"], "requirements": {"degrees": ["university graduate"], "majors": [], "languages": ["english", "chinese"], "language_level": ["good command"], "hard_skills": ["chinese word processing", "ms applications"], "soft_skills": ["computer literacy"], "languages_combined": [{"language": "english", "language_level": ["good command"]}, {"language": "chinese", "language_level": ["good command"]}]}, "experience_required": {"duration": [], "field": ["relevant experience"]}}, {"job_id": "100003009017025", "location_code": "hk", "company": "Commercial Radio Productions Ltd", "job_title": "Senior Multimedia Designer/ Multimedia Designer", "description": "Duties include\n\n\nFive day work in Central\nSupport the operation of real-time broadcasting studio\nHandling enquiry on social media\nEdit posts on social media\nClerical work\n\n\u00a0Requirements\n\n\nDSE/Form 7 or above\n\nGood teamwork skills\n\nWilling to learn\n\nBasic desktop computer skills\n\nComprehensive training will be provided\n\nApplicants with no working experiences will also be considered.", "employment_types": ["Full Time"], "selling_points": ["Minimum 2 yrs working experience in Digital Design", "Proficiency in Photoshop, Illustrator, Dreamweaver", "Understanding of UI/UX principles, web design"], "locations": ["Not Specified"], "categories": ["Design", "Multi-media", "Web Designer", "Media & Advertising", "Broadcasting - TV / Radio"], "post_time": "2022-01-03T10:22:34Z", "salary": {"currency": null, "max": null, "min": null, "period": "monthly", "term": null}, "salary_visible": false, "title_keywords": ["multimedia designer"], "responsibilities": ["social media"], "requirements": {"degrees": ["dse"], "majors": [], "languages": [], "language_level": [], "hard_skills": ["computer skills", "no", "basic"], "soft_skills": ["comprehensive", "teamwork", "willing to learn"], "languages_combined": []}, "experience_required": {"duration": [], "field": []}}, {"job_id": "100003009010704", "location_code": "hk", "company": "EC Healthcare", "job_title": "Videographer / Video Specialist / Video Editor", "description": "Job Descriptions:\n\nResponsible for the daily operations of Program Scheduling including issuing program schedules, playlist, EPG \u2026etc , and coordination with other related sections\nAssist in program research, program materials delivery, strategic program planning and program acquisition\nWrite program highlights and synopsis\nAssist in social media channel promotion\n\nRequirements:\n\nUniversity Graduate with 1 \u2013 2 years\u2019 experience in TV, Film or Media industry;\nProficient in Chinese and English, fluent in Mandarin\nStrong interest in TV & Films\nGood at details and having great patience at work\nWeb savvy and familiar with Photoshop & Microsoft office\nAn independent, detail-minded team player\nCandidate with more experience will be considered as Senior Program Officer.\n\nInterested parties please send full resume and expected salary by clicking \"APPLY NOW\".\n\nFor more details of our company, please visit our website at www.nowbaogumovies.com\n\nFB: Now\u7206\u8c37\u53f0\n\n(The personal data provided will only be used for recruitment and employment-related purposes. All personal data provided will be treated in strict confidence.\u00a0Information on unsuccessful candidates will normally be destroyed after 12 months from the date of application.)\n", "employment_types": ["Full Time"], "selling_points": ["Produce diversified video content", "Shoot and perform post-production", "Engage in the whole video production process"], "locations": ["Mong Kok"], "categories": ["Media & Advertising", "Production", "Broadcasting - TV / Radio", "Photography / Video"], "post_time": "2021-12-31T04:31:05Z", "salary": {"currency": null, "max": null, "min": null, "period": "monthly", "term": null}, "salary_visible": false, "title_keywords": ["specialist", "videographer", "video editor"], "responsibilities": ["social media", "schedules", "coordination with", "scheduling", "daily operations", "planning"], "requirements": {"degrees": ["university graduate"], "majors": [], "languages": ["english", "chinese", "mandarin"], "language_level": ["fluent", "proficient"], "hard_skills": ["microsoft office", "web savvy", "photoshop"], "soft_skills": ["detail-minded", "team player", "independent", "patience"], "languages_combined": [{"language": "english", "language_level": ["proficient"]}, {"language": "chinese", "language_level": ["fluent", "proficient"]}, {"language": "mandarin", "language_level": ["fluent", "proficient"]}]}, "experience_required": {"duration": ["2 years"], "field": ["media"]}}, {"job_id": "100003009013137", "location_code": "hk", "company": "PCCW Media (NowTV)", "job_title": "Senior Content Development Manager / Content Development Manager (Content Acquisition)", "description": "Launched in 1997, the China Daily Hong Kong Edition offers a unique local perspective that has become essential reading for decision-makers, including HKSAR government officials, CEOs and senior executives, scholars and academics in Hong Kong and Macau.\n\nThe China Daily Hong Kong Edition is recognized by both the newspaper industry and readers for its exceptional journalism and outstanding reporting. China Daily was a frequent winner at the most recent \u201cHong Kong News Awards\u201d organized by the Newspaper Society of Hong Kong. Since 2010, The Hong Kong Edition has been honored every year at the \u201cHong Kong News Awards\u201d, winning a current total of 84 awards.\n\n\u521b\u520a\u4e8e1997\u5e74\uff0c\u300a\u4e2d\u56fd\u65e5\u62a5\u9999\u6e2f\u7248\u300b\u4ee5\u5176\u672c\u5730\u5316\u3001\u72ec\u7279\u7684\u62a5\u9053\u89c6\u89d2\u6210\u4e3a\u9999\u6e2f\u3001\u6fb3\u95e8\u548c\u90e8\u5206\u4e9a\u6d32\u56fd\u5bb6\u548c\u5730\u533a\u9ad8\u7aef\u8bfb\u8005\u7684\u91cd\u8981\u8bfb\u7269\u3002 \u8bfb\u8005\u5305\u62ec\u9999\u6e2f\u7279\u522b\u884c\u653f\u533a\u653f\u5e9c\u5b98\u5458\u3001\u91d1\u878d\u673a\u6784\u548c\u8de8\u56fd\u4f01\u4e1aCEO\u3001\u9ad8\u7ea7\u7ba1\u7406\u4eba\u5458\u3001\u5916\u4ea4\u5b98\u5458\u3001\u667a\u5e93\u548c\u5b66\u8005\u7b49\u3002\n\n\u300a\u4e2d\u56fd\u65e5\u62a5\u9999\u6e2f\u7248\u300b\u591a\u6b21\u5728\u7531\u9999\u6e2f\u62a5\u4e1a\u516c\u4f1a\u4e3b\u529e\u7684\u300c\u9999\u6e2f\u6700\u4f73\u65b0\u95fb\u5956\u300d\u8bc4\u9009\u6d3b\u52a8\u4e2d\u83b7\u5956\uff0c\u4ee5\u4e13\u4e1a\u7684\u62a5\u9053\u5b34\u5f97\u62a5\u4e1a\u540c\u884c\u548c\u5404\u4f4d\u8bfb\u8005\u7684\u8ba4\u53ef\u3002 \u81ea2010\u5e74\u4ee5 \u6765\uff0c\u9999\u6e2f\u7248\u5df2\u8fde\u7eed\u83b7\u5f9784\u9879\u300c\u9999\u6e2f\u6700\u4f73\u65b0\u95fb\u5956\u300d\u3002\n\nIn order to manage the development and its integrated revenue growth across China Daily media products, we are now looking for qualified candidates in Hong Kong to fill the following position:\n\nResponsibilities:-\n\nCover HK and Greater Bay Area news, produce videos and content for both the newspaper and digital edition\nPitch story ideas, feature writing, conduct interviews and related research on topics to provide context\nBuild contacts & strengthen the knowledge and networking in assigned beats\nHave the creativity to write engagingly, to propose suitable projects that are attractive for print and online viewers\nMaintain close contact with news desk about work-related information and story progress.\nBe a good team player and work with other colleagues such as photographer, videographers and designers to initiate small group projects\nFollow China Daily style in writing copies and help spot and prevent errors\nWork on weekend or in emergency situations when required\nAssist with ad-hoc assignments the department is responsible for.\nRequirements:-\nBachelor Degree or above in Journalism or media communication or related disciplines from a reputable university.\nAt least 2 years\u2019 experience in news media preferably English news media. Candidate with more experience can be considered as Senior Multimedia Reporter.\nFamiliar with public affairs and economy of Hong Kong and Chinese Mainland\nKeen understanding of Hong Kong's governance structure & the role of functional constituencies\nFamiliar with social media networks, such as Facebook\nProficiency in both written and spoken English and Chinese.Clarity of expression in written English is essential.\nGood command of reporting and writing skills with strong news sense and able to turn stories around quickly\nAn organized & logical thinker who can interact proactively with the Data Journalism Team\nDetail-minded with high sense of responsibility, able to work independently and under pressure\nOutgoing personality, energetic, with good interpersonal skills\n\nWe offer successful candidates attractive salary and comprehensive benefits. Interested parties should send their full resumes, stating their current and expected salaries, to Human Resources Department, China Daily Hong Kong Ltd., Room 1818 Hing Wai Centre, 7 Tin Wan Praya Road, Aberdeen, Hong Kong, or email by clicking \"Apply Now\". (Personal Information collected will be used for recruitment purpose only)", "employment_types": ["Full Time"], "selling_points": ["Asian content acquisition, Primarily drama series", "Content acquisition and management", "Performance bonus, Medical benefit, 5day work week"], "locations": ["Kowloon Bay"], "categories": ["Media & Advertising", "Media Buying", "Strategic Planning", "Broadcasting - TV / Radio"], "post_time": "2022-01-03T01:30:35Z", "salary": {"currency": null, "max": null, "min": null, "period": "monthly", "term": null}, "salary_visible": false, "title_keywords": ["manager"], "responsibilities": ["ad-hoc assignments", "maintain", "ideas", "contact"], "requirements": {"degrees": ["degree or above", "bachelor"], "majors": ["journalism", "related disciplines"], "languages": ["english", "chinese"], "language_level": ["proficiency"], "hard_skills": ["facebook", "multimedia", "writing skills"], "soft_skills": ["detail-minded", "organized", "work independently", "outgoing personality", "under pressure", "keen", "high sense of responsibility", "writing skills", "communication", "interpersonal skills", "energetic"], "languages_combined": [{"language": "english", "language_level": ["proficiency"]}, {"language": "chinese", "language_level": ["proficiency"]}]}, "experience_required": {"duration": ["at least 2 years"], "field": ["reporter", "media"]}}, {"job_id": "100003005900459", "location_code": "hk", "company": "Wowwowtank Co Ltd", "job_title": "Videographer/Photographer/Editor", "description": "Your New Role:\n\n\nResponsible for translating and writing international news\n\nWhat makes you succeed:\u00a0\u00a0\n\n\nDegree holder in Journalism or related discipline\nFamiliar with and sensitive to international news and current affairs\nGood translation and writing skills\nExcellent command of written and spoken Chinese and English, Putonghua is an advantage\nProficiency in Chinese word processing is a must\nSelf-motivated and able to work under pressure and tight timeline\nTeam Player with good communication skills\nShift duty is required\nWe offer attractive & competitive salary and benefits, an exciting work environment and excellent career development opportunities.\u00a0If you have the desire for an exciting and rewarding career, please send us your resume,\u00a0stating your present and expected salary to Human Resources Department by clicking \"Apply Now\"\u00a0\n\nFor more information on other job opportunities of PCCW, please visit our website at\u00a0http://www.pccw.com/Careers/Job+Opportunities+%26+Application/Current+Opportunities?language=en_US\nPCCW is an equal opportunity employer and welcomes applications from all qualified candidates. Information provided will be treated in strict confidence and will only be used for recruitment-related purposes. Personal data provided by job applicants will be used strictly in accordance with the employer\u2019s\u00a0privacy statement\u00a0(www.pccw.com/privacy-statement/index.page), a copy of which will be provided immediately upon request.\u00a0", "employment_types": ["Full Time"], "selling_points": ["Love video editing. Love Advertising", "3 years experience minimum", "Creative. Fast. Hardworking"], "locations": ["Quarry Bay"], "categories": ["Design", "Multi-media", "Media & Advertising", "Broadcasting - TV / Radio", "Photography / Video"], "post_time": "2021-12-31T05:06:50Z", "salary": {"currency": "HKD", "max": 13999, "min": 11000, "period": "monthly", "term": null}, "salary_visible": true, "title_keywords": ["editor", "videographer", "photographer"], "responsibilities": ["communication", "work under pressure"], "requirements": {"degrees": ["degree holder"], "majors": ["journalism"], "languages": ["putonghua", "english", "chinese"], "language_level": ["advantage", "excellent", "proficiency"], "hard_skills": ["translation", "chinese word processing", "writing skills"], "soft_skills": ["communication skills", "self-motivated", "responsible", "writing skills", "sensitive to", "team player", "work under pressure"], "languages_combined": [{"language": "putonghua", "language_level": ["advantage", "excellent"]}, {"language": "english", "language_level": ["excellent"]}, {"language": "chinese", "language_level": ["excellent", "proficiency"]}]}, "experience_required": {"duration": [], "field": []}}, {"job_id": "100003009016428", "location_code": "hk", "company": "PCCW Media", "job_title": "Junior / Graphic Designer", "description": "Commercial Radio Interactive, a division of Commercial Radio Productions Limited and the digital arm of Commercial Radio,\u00a0are looking for a passionate and energetic Multimedia Designer to join our team and develop his/her career under the guidance of our experienced senior designer.\n\nJob Responsibilities\n\n\u2022\u00a0Work closely with Project and Marketing teams to design all digital marketing materials, including website layout, digital web banners, and eDM\n\u2022\u00a0Create visual, video, animation and other graphic design content for social media\n\u2022\u00a0Assist in ad-hoc online advertising and digital projects as assigned\n\nJob Requirements\n\n\u2022\u00a0Minimum 2 years working experience in Graphic Design, Digital Multimedia Design, Creative Media, Advertising or related disciplines\n\u2022\u00a0Proficiency in Photoshop, Illustrator, Dreamweaver and After Effect is an advantage\n\u2022\u00a0Understanding of UI/UX principles and proficient on using web design comp tools such as Adobe Sketch, XD.\n\u2022\u00a0Knowledge of front-end wireframe, responsive web design & prototyping development using HTML5 & CSS.\n\u2022\u00a0Creative, passionate about design / advertising and have a good sense of art direction\n\u2022\u00a0Responsible, self-motivated, willing to learn new skills, able to work under pressure and tight deadlines\n\u2022\u00a0Knowledge of social media, photo shooting, video editing is an advantage\n\u2022 Portfolio in pdf is required for application\n\nLocation: 3 Broadcast Drive, Kowloon, Hong Kong\n\nApplication Procedure:\n\nWe offer attractive remuneration package, competitive salary, medical scheme and life insurance to the right candidate. Interested candidates, please submit application letter with full resume, present and expected salary by clicking \u201cApply Now\u201d (Please quote the job reference number on the e-mail subject line).\n\nAll information received will be kept in strict confidence and only for employment-related purpose. Only short listed candidates will be invited for interview.", "employment_types": ["Full Time"], "selling_points": ["Create news graphics", "Create news motion graphics", "Strong creative and graphic sense"], "locations": ["Wan Chai"], "categories": ["Media & Advertising", "Creative / Design", "Design", "Graphics", "Broadcasting - TV / Radio"], "post_time": "2022-01-03T09:03:56Z", "salary": {"currency": null, "max": null, "min": null, "period": "monthly", "term": null}, "salary_visible": false, "title_keywords": ["graphic designer", "junior"], "responsibilities": ["ad-hoc", "social media", "edm", "graphic design", "teams", "website", "design", "banners", "digital marketing", "visual", "online advertising", "animation"], "requirements": {"degrees": [], "majors": [], "languages": [], "language_level": [], "hard_skills": ["web design", "illustrator", "video editing", "adobe", "multimedia", "dreamweaver", "css", "after effect", "photoshop"], "soft_skills": ["self-motivated", "responsible", "willing to learn", "creative", "responsive", "passionate about", "work under pressure"], "languages_combined": []}, "experience_required": {"duration": ["minimum 2 years"], "field": ["advertising", "related", "graphic design", "design", "digital", "media"]}}, {"job_id": "100003008997406", "location_code": "hk", "company": "Television Broadcasts Ltd", "job_title": "Production Director", "description": "Your New Role:\n\nResponsible for designing and creating news graphics and motion graphics for Now News / Business News Channels\u00a0\n\nWhat makes you succeed:\u00a0\n\nDegree or diploma holder in Multi-media or Graphic Design\n2 years\u2019 relevant experience in media industry specializes in Graphic Creation\nExtensive experience in graphic design process from concept to production for still graphics and motion graphics\nStrong computer literacy in Macintosh or PC applications e.g. C4D, 3D Max or Mayer, After Effect, Photoshop and Illustrator\nStrong creative and graphic sense with deep interest in TV industry\nGood communication skills\nAble to work independently and meet tight deadlines\nWilling to work irregular hours\nFresh graduates will be considered as Junior Graphic Designer\n\nWant to be one of us?\n\nWe offer attractive & competitive salary and benefits, an exciting work environment and excellent career development opportunities.\u00a0If you have the desire for an exciting and rewarding career, please send us your resume,\u00a0stating your present and expected salary to Human Resources Department by clicking \"Apply Now\"\u00a0\n\nFor more information on other job opportunities of PCCW, please visit our website at\u00a0http://www.pccw.com/Careers/Job+Opportunities+%26+Application/Current+Opportunities?language=en_US\nPCCW is an equal opportunity employer and welcomes applications from all qualified candidates. Information provided will be treated in strict confidence and will only be used for recruitment-related purposes. Personal data provided by job applicants will be used strictly in accordance with the employer\u2019s\u00a0privacy statement\u00a0(www.pccw.com/privacy-statement/index.page), a copy of which will be provided immediately upon request.", "employment_types": ["Full Time"], "selling_points": [], "locations": ["Tseung Kwan O"], "categories": ["Media & Advertising", "Production", "Others", "Broadcasting - TV / Radio"], "post_time": "2021-12-29T07:13:46Z", "salary": {"currency": null, "max": null, "min": null, "period": "monthly", "term": null}, "salary_visible": false, "title_keywords": ["director"], "responsibilities": ["graphics", "graphic design", "communication", "motion graphics", "designing"], "requirements": {"degrees": ["diploma holder", "degree"], "majors": ["graphic design"], "languages": [], "language_level": [], "hard_skills": ["graphics", "c4d", "illustrator", "pc applications", "max", "after effect", "photoshop"], "soft_skills": ["communication skills", "work independently", "meet tight deadlines", "responsible", "deep", "computer literacy", "creative", "extensive"], "languages_combined": []}, "experience_required": {"duration": ["2 years"], "field": ["graphic design", "graphic", "relevant experience", "media"]}}, {"job_id": "100003008997408", "location_code": "hk", "company": "Television Broadcasts Limited (TVB)", "job_title": "Reporter (Jade)", "description": "Job Duties:\n\nDevelop creative ideas and concepts with marketing team members\nProduce diversified video content for multiple platforms including but not limited to social, print, corporate, and creative campaigns\nRecord, mix and post produce audio recordings\nCreate motion graphic design, including insert subtitles and aftereffects to the videos\nShoot and perform post-production of high quality, compelling content\nEnsure videos are well-edited, color / sound graded and produced according to brand guidelines\nEngage in the whole video production process;\nCoordinate production tasks including camera shooting, video editing, color correcting and color grading etc\nAmend, revise or redevelop adverts or campaign videos in response to feedback from the marketing team, management and market feedback\nAd-hoc duties as assigned\n\nRequirements:\n\nCertificate/Diploma/Degree holder in Film/ Creative Media/ Multimedia Design/ Motion Graphics/ Animation or related field\nMinimum 2 years of solid experience in video shooting, editing and production\nGood communication & interpersonal skills\nFamiliar with websites and social media platforms like Facebook, Instagram and YouTube\nFresh graduates will be considered", "employment_types": ["Full Time", "Permanent"], "selling_points": [], "locations": ["Others"], "categories": ["Media & Advertising", "Editorial / Journalism", "Broadcasting - TV / Radio"], "post_time": "2021-12-29T07:11:37Z", "salary": {"currency": null, "max": null, "min": null, "period": "monthly", "term": null}, "salary_visible": false, "title_keywords": ["reporter"], "responsibilities": ["management", "video production", "quality", "coordinate", "video editing", "brand guidelines", "ad-hoc duties", "audio", "develop creative ideas", "motion graphic design"], "requirements": {"degrees": ["certificate", "diploma", "degree holder"], "majors": ["multimedia design", "creative media", "motion graphics", "animation"], "languages": [], "language_level": [], "hard_skills": ["graphics", "facebook", "multimedia"], "soft_skills": ["communication", "creative", "interpersonal skills"], "languages_combined": []}, "experience_required": {"duration": ["minimum 2 years"], "field": ["editing", "video shooting"]}}, {"job_id": "100003009011381", "location_code": "hk", "company": "Phoenix Satellite Television Co Ltd", "job_title": "DEPUTY NEWS EDITOR\t                          (REF: DNE-HKC-DB)", "description": "About the jobTVB, the leading TV station in Hong Kong and the world\u2019s number one distributor of Chinese Programme, marks the successful transformation of TVB from a traditional television station to a company amalgamating three different platforms - broadcast TV, online TV and social media.\n\nJob Description\n\nDirect and produce on-air presentation of newscasts\nCoordinate with News Editor in production of newscasts\nF.5/DSE with good command in both written and spoken Cantonese and English, Putonghua is preferable\nRelevant experience of TV production is preferable\nWilling to work shift duty and overnight\nPlease send the application, quoting the appropriate reference number, with details of your qualifications and experience, expected salary and a contact telephone number to The Senior Manager, Personnel Department, Television Broadcasts Limited, TVB City, 77 Chun Choi Street, Tseung Kwan O Industrial Estate, Tseung Kwan O, Kowloon\u00a0or APPLY NOW", "employment_types": ["Full Time", "Permanent"], "selling_points": [], "locations": ["Tai Po Area"], "categories": ["Media & Advertising", "Broadcasting - TV / Radio"], "post_time": "2021-12-31T07:04:01Z", "salary": {"currency": null, "max": null, "min": null, "period": null, "term": null}, "salary_visible": false, "title_keywords": ["deputy news editor"], "responsibilities": ["social media", "coordinate with", "contact"], "requirements": {"degrees": ["dse"], "majors": [], "languages": ["cantonese", "putonghua", "english", "chinese"], "language_level": ["good command"], "hard_skills": [], "soft_skills": ["presentation"], "languages_combined": [{"language": "cantonese", "language_level": ["good command"]}, {"language": "putonghua", "language_level": ["good command"]}, {"language": "english", "language_level": ["good command"]}, {"language": "chinese", "language_level": []}]}, "experience_required": {"duration": [], "field": ["relevant experience", "tv production"]}}, {"job_id": "100003009010906", "location_code": "hk", "company": "Salon Films (H.K.) Limited", "job_title": "FILM & MEDIA MANAGEMENT ACCOUNTANT", "description": "Role Description\u00a0\n\nThe position of Audio Engineer will be responsible for conducting dubbing sessions, mixing and combining dubbing recorded files (recorded voice, music, effect, etc.).\n\n\n\n\nSpecific Responsibilities\n\nEnsure reception of premix files\nConduct and record dubbing sessions with voice talents\nGive feedback on dubbing aspects in order to improve mixing output standards\nFull-mix assigned dubbed programs and see to completion\nCoordinate with Senior Audio Engineers, and Studio Coordinator\nAny other tasks which are deemed important to ensure required standards for the dubbing program\nRequirements\n\n\nDemonstrate a proficient level of professional skill and/or knowledge in audio engineering and studio recording techniques, and post audio mixing, specifically in\n\nrecording ARD, Dubbing and/ or animation\nMac environment, ProTools audio software and hardware, including peripheral equipment as compressors, microphones, AD Converters\naudio and session formats and specifications (.wav, .mp3, .ptf, .omf, etc.)\nProvide professional and quality audio recordings for both low and high-end dubbing projects\nWilling to work overtime / shift schedule\nImmediately available\n2 year production work experience\nApplication Interested parties please send your application with full CV including current and expected salary and availability by clicking below icon\u00a0\"Apply Now\".\n\nAll personal information will be treated strictly confidential and solely for recruitment purpose.", "employment_types": ["Full Time"], "selling_points": ["Process filming production accounts", "Provide timely production planning scenarios", "Ovesee job production forecast and actual report"], "locations": ["To Kwa Wan"], "categories": ["Media & Advertising", "Broadcasting - TV / Radio"], "post_time": "2021-12-31T05:36:45Z", "salary": {"currency": null, "max": null, "min": null, "period": "monthly", "term": null}, "salary_visible": false, "title_keywords": ["accountant"], "responsibilities": ["other tasks", "audio", "coordinate with", "give feedback"], "requirements": {"degrees": [], "majors": [], "languages": [], "language_level": [], "hard_skills": ["hardware", "mac environment"], "soft_skills": ["work overtime"], "languages_combined": []}, "experience_required": {"duration": ["2 year"], "field": []}}, {"job_id": "100003008997416", "location_code": "hk", "company": "Television Broadcasts Limited (TVB)", "job_title": "News Anchor/Reporter", "description": "We are looking for an enthusiastic Reporter (Jade) with sharp news sense.\u00a0\n\nRequirements:\n\nUniversity graduate\nAt least two years of relevant job experience\nExcellent command of written and spoken Cantonese and English\nDemonstrate high integrity, morality and proactive attitude\nShift duty is required\nApplicant with more experience will be considered as Senior / Principal Reporter\nPlease send the application, quoting the appropriate reference number, with details of your qualifications and experience, expected salary and a contact telephone number to The Senior\u00a0Manager, Personnel Department,\u00a0Television Broadcasts Limited, TVB City, 77 Chun Choi Street, Tseung Kwan O Industrial Estate, Tseung Kwan O, Kowloon or email to us via Recruitment Centre.\n\n\nApplications received are solely for selection purpose. Those not invited for an interview within 4 weeks may consider their applications unsuccessful and their applications will be filed for another 3 months for future selection. Afterwards, all applications would be destroyed.", "employment_types": ["Full Time", "Permanent"], "selling_points": [], "locations": ["Others"], "categories": ["Media & Advertising", "Editorial / Journalism", "Broadcasting - TV / Radio"], "post_time": "2021-12-29T16:11:09Z", "salary": {"currency": null, "max": null, "min": null, "period": "monthly", "term": null}, "salary_visible": false, "title_keywords": ["reporter", "anchor"], "responsibilities": ["recruitment", "contact"], "requirements": {"degrees": ["university graduate"], "majors": [], "languages": ["cantonese", "english"], "language_level": ["excellent"], "hard_skills": ["jade"], "soft_skills": ["proactive", "integrity", "enthusiastic"], "languages_combined": [{"language": "cantonese", "language_level": ["excellent"]}, {"language": "english", "language_level": ["excellent"]}]}, "experience_required": {"duration": ["at least two years"], "field": ["reporter", "recruitment"]}}, {"job_id": "100003009007545", "location_code": "hk", "company": "ORIENTAL HUMAN RESOURCES LIMITED", "job_title": "\u8996\u983b\u7522\u7d93\u8a18\u8005", "description": "Responsibilities:\u00a0\n\nTranslate international/financial news from English to Chinese;\nWrite, edit and update news stories; and\nArrange rundown for newscast.\u00a0\n\nRequirements:\u00a0\n\nDegree holder with at least 3 years editorial / journalistic experience in Media.\nHands on experience in news translation from English to Chinese.\nAble to work shift duties.\nFamiliar with MS word, Excel and proficiency in Chinese Word Processing is a must.\nExcellent command of written and spoken English and Chinese, proficiency in Cantonese is a MUST.\nCandidates with more experience will be considered for the position of News Editor.\u00a0\n\nFor more details of our company, please visit our website at http://www.ifeng.com/\n\n\n\nWe offer attractive remuneration package to the right candidate. Interested parties please send applications with detailed resume stating career history, present & expected salary and date available to Human Resources Department, Phoenix Satellite Television Co. Ltd. via e-mail: phxhr@ phoenixtv.com or via fax: 2200 8620.\u00a0\n\nPersonal data collected will be used for recruitment purpose only.\u00a0 Applicants not hearing from us within 6 weeks may consider their applications unsuccessful and all related information will be destroyed after 6 months.", "employment_types": ["Full Time"], "selling_points": [], "locations": ["Tai Po Area"], "categories": ["Banking / Finance", "Others", "Media & Advertising", "Editorial / Journalism", "Broadcasting - TV / Radio"], "post_time": "2021-12-30T03:20:54Z", "salary": {"currency": null, "max": null, "min": null, "period": "monthly", "term": null}, "salary_visible": false, "title_keywords": [], "responsibilities": [], "requirements": {"degrees": ["degree holder"], "majors": [], "languages": ["cantonese", "english", "chinese"], "language_level": ["proficiency", "excellent"], "hard_skills": ["translation", "chinese word processing", "excel", "ms word"], "soft_skills": ["hands on"], "languages_combined": [{"language": "cantonese", "language_level": ["proficiency", "excellent"]}, {"language": "english", "language_level": ["proficiency", "excellent"]}, {"language": "chinese", "language_level": ["proficiency", "excellent"]}]}, "experience_required": {"duration": ["at least 3 years"], "field": ["editor", "editorial", "media", "journalistic"]}}, {"job_id": "100003008997417", "location_code": "hk", "company": "Television Broadcasts Limited (TVB)", "job_title": "Anchor", "description": "A WELL-ESTABLISHED FILM/VIDEO/MULTIMEDIA COMPANY SEEKING HIGH CALIBRE CANDIDATE FOR:\n\nFILM & MEDIA MANAGEMENT ACCOUNTANT\n\nJob Description:\n\nPrepare analysis of tender received and quotation submitted\nProcess filming production accounts from end to end in production accounting\nPartner with producers and production teams to create and manage production schedules and budgets\nProvide and present clear, accurate and timely production planning scenarios and analysis to both producers and production teams during the life cycle of a production\nMonitor the progress of various production jobs\nPrepare accurate, detailed and weekly cost reports, cash flows and headcount forecasts\nOversee and deliver job production forecast and actual report comparisons of production budgets\nOther ad-hoc tasks as assigned\n\nJob Requirements:\n\nDegree in Accounting or related discipline\nHolder of recognized professional accounting qualification or finalist, such as ACCA or HKICPA is a plus\n3-5 years relevant experience in management accounting\nAble to work independently and under pressure\nProactive team player with a meticulous and strong analytical mind\nStrong interpersonal and communication skills, well-organized and able to prioritize different requests from various stakeholders, and willingness to learn and accept new responsibilities & challenges\nExperience in system development or implementation\nNeed to work with production team in shooting location when necessary\nWilling to work long hours under tough condition\nProficiency in PC applications such as Excel, Word, Outlook, and PowerPoint, etc.\nExperience in filming industry is preferred\nImmediate\u00a0available is preferred.\u00a0\nHolding driving licence will be an advantage\nLess experience will be considered assistant management accountant\n\nWe offer 5-day work with attractive salary and fringe benefits package including medical insurance, training and education.\u00a0 Interested parties are invited to send your full resume with current and expected salary.\u00a0 All applications will be treated in strict confidential and used for recruitment purpose only.", "employment_types": ["Full Time", "Permanent"], "selling_points": [], "locations": ["Others"], "categories": ["Media & Advertising", "Editorial / Journalism", "Broadcasting - TV / Radio"], "post_time": "2021-12-29T07:20:34Z", "salary": {"currency": null, "max": null, "min": null, "period": "monthly", "term": null}, "salary_visible": false, "title_keywords": ["anchor"], "responsibilities": ["budgets", "cost", "schedules", "analysis", "quotation", "teams", "production planning", "monitor", "ad-hoc tasks", "reports", "tender", "forecast", "report"], "requirements": {"degrees": ["degree"], "majors": ["accounting"], "languages": [], "language_level": [], "hard_skills": ["excel", "acca", "plus", "word", "powerpoint", "pc applications", "outlook", "hkicpa"], "soft_skills": ["meticulous", "work independently", "communication skills", "under pressure", "able to prioritize", "well-organized", "analytical mind", "team player", "proactive", "interpersonal"], "languages_combined": []}, "experience_required": {"duration": ["3-5 years"], "field": ["management accounting", "management", "relevant experience", "system development"]}}, {"job_id": "100003009004596", "location_code": "hk", "company": "Havas Worldwide Hong Kong Limited", "job_title": "Programmatic Executive / Programmatic Trader", "description": "Requirements:\u00a0\n\nGenerate news stories, material sourcing and other ad hoc projects\u00a0\nUniversity degree holder, preferably in Journalism/Communications\u00a0\u00a0\nAt least 1-2 years\u2019 work experience in relevant field\u00a0\nSound knowledge of public and current affairs\u00a0\nExcellent command of written and spoken Cantonese, English and Mandarin\u00a0\nMeet deadline and work under pressure\u00a0\nWork overnight, weekends and holidays\u00a0\nPlease send the application, quoting the appropriate reference number, with details of your qualifications and experience, expected salary and a contact telephone number to The Senior\u00a0Manager, Personnel Department,\u00a0Television Broadcasts Limited, TVB City, 77 Chun Choi Street, Tseung Kwan O Industrial Estate, Tseung Kwan O, Kowloon or email to us via Recruitment Centre.\n\n\nApplications received are solely for selection purpose. Those not invited for an interview within 4 weeks may consider their applications unsuccessful and their applications will be filed for another 3 months for future selection. Afterwards, all applications would be destroyed.", "employment_types": ["Full Time", "Permanent"], "selling_points": ["1+ year experience in programmatic & paid social", "Hands-on experience with key DSPs (DV360, TTD)", "Excellent verbal and written skills"], "locations": ["Kwun Tong"], "categories": ["Media & Advertising", "Strategic Planning", "Others", "Broadcasting - TV / Radio"], "post_time": "2021-12-29T02:44:50Z", "salary": {"currency": null, "max": null, "min": null, "period": "monthly", "term": null}, "salary_visible": false, "title_keywords": ["executive"], "responsibilities": ["recruitment", "ad hoc projects", "contact", "work under pressure"], "requirements": {"degrees": ["university degree"], "majors": ["journalism", "communications"], "languages": ["cantonese", "english", "mandarin"], "language_level": ["excellent"], "hard_skills": [], "soft_skills": ["work under pressure"], "languages_combined": [{"language": "cantonese", "language_level": ["excellent"]}, {"language": "english", "language_level": ["excellent"]}, {"language": "mandarin", "language_level": ["excellent"]}]}, "experience_required": {"duration": ["at least 1-2 years"], "field": ["recruitment"]}}, {"job_id": "100003009002273", "location_code": "hk", "company": "She Communications Ltd", "job_title": "Photographer / Videographer", "description": "Responsibilities\n\nPresent News stories to audiences in a professional way\nResearch local and international current events\nInterview guest\nGenerate and report feature stories and weather reports\n\nRequirements\n\nUniversity degree holder\nSound knowledge and strong interest in current affairs\nExcellent command of written and spoken Cantonese, English, and Mandarin\nComfortable yet professional presence on camera\nAble to work under stressful conditions\nShift duty required\nPlease send the application, quoting the appropriate reference number, with details of your qualifications and experience, expected salary and a contact telephone number to The Senior\u00a0Manager, Personnel Department,\u00a0Television Broadcasts Limited, TVB City, 77 Chun Choi Street, Tseung Kwan O Industrial Estate, Tseung Kwan O, Kowloon or email to us via Recruitment Centre.\n\n\nApplications received are solely for selection purpose. Those not invited for an interview within 4 weeks may consider their applications unsuccessful and their applications will be filed for another 3 months for future selection. Afterwards, all applications would be destroyed.", "employment_types": ["Full Time", "Permanent"], "selling_points": ["Responsible for video, photo shooting and editing", "Responsible for live-streaming broadcast", "Research, develop creative idea and design mock up"], "locations": ["Sheung Wan"], "categories": ["Media & Advertising", "Production", "Broadcasting - TV / Radio", "Photography / Video"], "post_time": "2021-12-28T04:24:07Z", "salary": {"currency": null, "max": null, "min": null, "period": "monthly", "term": null}, "salary_visible": false, "title_keywords": ["videographer", "photographer"], "responsibilities": ["reports", "report"], "requirements": {"degrees": ["university degree"], "majors": [], "languages": ["cantonese", "english", "mandarin"], "language_level": ["excellent"], "hard_skills": [], "soft_skills": [], "languages_combined": [{"language": "cantonese", "language_level": ["excellent"]}, {"language": "english", "language_level": ["excellent"]}, {"language": "mandarin", "language_level": ["excellent"]}]}, "experience_required": {"duration": [], "field": ["recruitment"]}}, {"job_id": "100003009006388", "location_code": "hk", "company": "Television Broadcasts Ltd", "job_title": "\u5b57\u5e55\u64cd\u4f5c\u54e1", "description": "\u00a0\n\u8ca0\u8cac\u96fb\u8996\u7bc0\u76ee\u5b57\u5e55\u64cd\u4f5c\n\u4e2d\u4e94\u6216\u4ee5\u4e0a\u7a0b\u5ea6\n\u719f\u6089\u96fb\u8166\u4e2d\u6587\u8f38\u5165\u6cd5\n\u9700\u8981\u8f2a\u73ed\n\n\nPlease send the application, quoting the appropriate reference number, with details of your qualifications and experience, expected salary and a contact telephone number to The Senior Manager, Personnel Department, Television Broadcasts Limited, TVB City, 77 Chun Choi Street, Tseung Kwan O Industrial Estate, Tseung Kwan O, Kowloon\u00a0or APPLY NOW", "employment_types": ["Full Time", "Permanent", "Temporary"], "selling_points": [], "locations": ["Tseung Kwan O"], "categories": ["Media & Advertising", "Production", "Others", "Broadcasting - TV / Radio"], "post_time": "2021-12-29T16:11:11Z", "salary": {"currency": null, "max": null, "min": null, "period": "monthly", "term": null}, "salary_visible": false, "title_keywords": [], "responsibilities": ["contact"], "requirements": {"degrees": [], "majors": [], "languages": [], "language_level": [], "hard_skills": [], "soft_skills": [], "languages_combined": []}, "experience_required": {"duration": [], "field": []}}, {"job_id": "100003009006893", "location_code": "hk", "company": "Phoenix Satellite Television Co Ltd", "job_title": "PROGRAMME ACQUISITION EXECUTIVE", "description": "Responsibilities:\u00a0\n\nAssist in sourcing and buying programmes from global distributors\nHandling screeners, screening and evaluating programmes, proofreading contracts, following up with distributors on material delivery.\nResponsible for administrative work for the department, especially those related to programme acquisition process.\nUndertake programmes research through multiple sources, both inside and outside TV industry.\n\nRequirements:\n\nDiploma/Degree holder, 2 years relevant working experience in TV industry preferable.\nDetail oriented, organized, good social skills and strong problem solving ability.\nSelf-motivated, hard-working and able to work independently.\nFamiliar with MS Word, Excel, PowerPoint and proficiency in Chinese Word Processing is a must.\nExcellent command of written and spoken English and Chinese,\u00a0proficiency in Putonghua is a MUST.\nCandidates with less experience will be considered for the position of Assistant Programme Acquisition Executive.\n\nFor more details of our company, please visit our website at\u00a0http://www.ifeng.com\n\nWe offer attractive remuneration package to the right candidate.\u00a0Interested parties please click \u201cApply Now\u201d to submit applications or send applications with detailed resume stating career history, present & expected salary and date available to Human Resources Department, Phoenix Satellite Television Co. Ltd. via fax:\u00a02200 8620.\u00a0\n\nPersonal data collected will be used for recruitment purpose only.\u00a0 Applicants not hearing from us within 6 weeks may consider their applications unsuccessful and all related information will be destroyed after 6 months.", "employment_types": ["Full Time", "Permanent"], "selling_points": [], "locations": ["Tai Po Area"], "categories": ["Media & Advertising", "Media Buying", "Others", "Broadcasting - TV / Radio"], "post_time": "2021-12-29T11:41:17Z", "salary": {"currency": null, "max": null, "min": null, "period": null, "term": null}, "salary_visible": false, "title_keywords": ["executive"], "responsibilities": ["contracts", "proofreading", "administrative work"], "requirements": {"degrees": ["diploma", "degree holder"], "majors": [], "languages": ["putonghua", "english", "chinese"], "language_level": ["proficiency", "excellent"], "hard_skills": ["excel", "chinese word processing", "powerpoint", "problem solving", "ms word"], "soft_skills": ["organized", "self-motivated", "work independently", "detail oriented", "problem solving", "hard-working"], "languages_combined": [{"language": "putonghua", "language_level": ["proficiency", "excellent"]}, {"language": "english", "language_level": ["proficiency", "excellent"]}, {"language": "chinese", "language_level": ["proficiency", "excellent"]}]}, "experience_required": {"duration": ["2 years"], "field": ["relevant working experience"]}}, {"job_id": "100003009002254", "location_code": "hk", "company": "HK01 Company Limited", "job_title": "\u8a18\u8005 (\u958b\u7f50)", "description": "\u00a0\n\nDirect and produce News related documentaries and features\n\nF.5/DSE or above with 1-2 years' relevant experience\n\nProficiency in non-linear editing tools\u00a0\u00a0\n\nCreative sense of thinking is a must\n\nGood command of both written and spoken Chinese and English\n\nWilling to work on shift duty and overnight\n\n\nPlease send the application, quoting the appropriate reference number, with details of your qualifications and experience, expected salary and a contact telephone number to The Senior Manager, Personnel Department, Television Broadcasts Limited, TVB City, 77 Chun Choi Street, Tseung Kwan O Industrial Estate, Tseung Kwan O, Kowloon\u00a0or APPLY NOW", "employment_types": ["Full Time", "Permanent"], "selling_points": ["\u69cb\u601d\u5167\u5bb9\u53ca\u64b0\u5beb\u5171\u9cf4\u6587\u7ae0", "1\u5e74\u4ee5\u4e0a\u7d93\u9a57\uff0c\u5177\u5099\u57fa\u672c\u64b0\u6587\u6280\u5de7\uff0c\u61c2\u5f97\u97d3\u8a9e\u66f4\u4f73", "\u63d0\u4f9b\u8077\u696d\u767c\u5c55\u6a5f\u6703\uff0c\u53ca\u6709\u7af6\u722d\u529b\u7684\u85aa\u916c"], "locations": ["Tsuen Wan Area"], "categories": ["Media & Advertising", "Others", "Editorial / Journalism", "Broadcasting - TV / Radio"], "post_time": "2021-12-28T04:20:50Z", "salary": {"currency": null, "max": null, "min": null, "period": "monthly", "term": null}, "salary_visible": false, "title_keywords": ["\u8a18\u8005"], "responsibilities": ["editing", "contact"], "requirements": {"degrees": ["dse"], "majors": [], "languages": ["english", "chinese"], "language_level": ["good command"], "hard_skills": [], "soft_skills": ["creative"], "languages_combined": [{"language": "english", "language_level": ["good command"]}, {"language": "chinese", "language_level": ["good command"]}]}, "experience_required": {"duration": ["1-2 years"], "field": ["relevant experience"]}}, {"job_id": "100003008997418", "location_code": "hk", "company": "Television Broadcasts Ltd", "job_title": "Visual Director/Program Director (Documentary)", "description": "Responsibilities:\n\nWork closely with Producers to produce videos in accordance to work schedule\nMaintain good communication with both internal and external parties including clients, third-party contractors and vendors, to ensure a balanced-mix of creativity and usability for the planning and execution of video production\nCoordination of on-location video shooting and post-production including Video Editing, Dubbing and Subtitling\nHandle all video production logistic and to ensure delivery quality output on time\nMay be required to work irregular hours, or need to work outdoors\nOverseas travel may be required\n\nRequirements:\n\nDiploma/Degree holder in video production or related discipline\nAt least 2 years experience solid working in TV industry, Creative Media, Video Production Agency/Video Production House is an advantage\nStrong proficiency in video software including Final Cut Pro, After Effect, Photoshop & Illustrator will be an advantage, as well as hardware like cameras, lighting set up and sound equipment\nFamiliar with various HD, 5D Mark II, Sony A7S II camera operation\nGood command of written and spoken Chinese and English\nFamiliar with PC / Mac application, MS Office and Proficiency in Chinese Word Processing\nCreative with passion, Positive-thinking, Self-motivated, Teamworks oriented\nHard-working, attention to detail, organized, strong sense of responsibility, strong problem solving ability, pleasant personality\n\nHow to Apply:\n\nInterested parties please email detail resume and stating your present and expected salary to Human Resources Department. Applicants should also provide work samples or Link with recent portfolio.\n\nAll information provided by applicants will be treated in strict confidence and used only for recruitment purposes.", "employment_types": ["Full Time", "Permanent"], "selling_points": [], "locations": ["Tseung Kwan O"], "categories": ["Media & Advertising", "Production", "Others", "Broadcasting - TV / Radio"], "post_time": "2021-12-28T12:03:19Z", "salary": {"currency": null, "max": null, "min": null, "period": "monthly", "term": null}, "salary_visible": false, "title_keywords": ["director"], "responsibilities": ["video production", "internal and external parties", "quality", "maintain good communication", "video editing", "video shooting", "schedule", "coordination", "planning"], "requirements": {"degrees": ["diploma", "degree holder"], "majors": [], "languages": ["english", "chinese"], "language_level": ["proficiency", "good command"], "hard_skills": ["final cut pro", "chinese word processing", "illustrator", "problem solving", "hardware", "pc", "ms office", "after effect", "photoshop"], "soft_skills": ["organized", "self-motivated", "sense of responsibility", "pleasant", "problem solving", "hard-working", "attention to detail", "creative", "positive"], "languages_combined": [{"language": "english", "language_level": ["good command"]}, {"language": "chinese", "language_level": ["proficiency", "good command"]}]}, "experience_required": {"duration": ["at least 2 years"], "field": ["video production", "agency", "media"]}}, {"job_id": "100003009000482", "location_code": "hk", "company": "Xebec Media Limited", "job_title": "Assistant Producer / \u52a9\u7406\u7de8\u5c0e", "description": "SCOPE OF ROLE\n\nThe position is exciting for those willing to play an integral role in the programmatic environment, solving operational and strategic issues on behalf of clients relating to digital RTB campaigns e.g. Programmatic Trading, Paid Social\n\nThe ideal candidate possesses the ingredients of analytical curiosity, attention to detail; team focused mindset and thrives to work in a dynamic environment.\n\nROLE & PRIMARY RESPONSIBILITIES\n\nPrimary duties & responsibilities\n\nCollaborate with account team and other cross-functional teams in developing Programmatic elements of strategies/media plans.\nCollaborate with publishers to source, evaluate and implement deals that provide our clients with high quality inventory opportunities.\nSupport internal product development and educational initiatives to internal & external account team.\nOperational: Manage Campaign, following our trading desk processes (Briefing platform, creative upload, strategies set up,\u2026)\nOptimization: Campaign metrics monitoring and optimizations toward our client goals (Branding, traffic, acquisitions, \u2026) and KPIs.\nReporting and analytics: Updating the media planning team on campaign delivery, taking decision and making recommendations\nFollow up on new technology and offer in the market to maintain competitively among other players\nRequirements\n\n1+ years of relevant career experience in programmatic & paid social campaigns at an agency, DSP or Ad Network strongly is strongly preferred.\nHands-on experience with key DSPs (DV360, TTD, Yahoo), & Paid social platform (Facebook, LinkedIn, Twitter) across multi-market and large-scale campaigns.\nEffective at juggling multiple, competing priorities and working in a fast-paced, open environment\nExcellent verbal and written skills\nWillingness to work collaboratively in a team setting\nConceptual thinker with strong analytical skills\nExceptional organizational skills and detail-oriented mindset\nCandidate with lower qualification or less experience will be considered as Programmatic Executive\nWe offer 5-day work week, birthday and other special leaves, staff training, good salary package with MPF and Medical Coverage.\u00a0Interested parties please apply with full resume stating availability, current and expected salaries by clicking \"APPLY NOW\".\n\nFurther information about Havas\u00a0Hong Kong\u00a0is available on the company\u2019s website:\n\nhttps://hk.havas.com/\n\n\u00a0\nDue to high volume of applications, only eligible or matching candidates will be contacted by us. All personal data received will only be used for recruitment purpose and will be destroyed after the position is filled.\n", "employment_types": ["Full Time"], "selling_points": ["2 years relevant working experience", "Assist Producer in all aspects of production", "Camera Operation"], "locations": ["Kwun Tong"], "categories": ["Media & Advertising", "Broadcasting - TV / Radio", "Photography / Video"], "post_time": "2021-12-26T05:11:34Z", "salary": {"currency": null, "max": null, "min": null, "period": "monthly", "term": null}, "salary_visible": false, "title_keywords": ["producer", "assistant"], "responsibilities": ["collaborate with", "reporting", "inventory", "monitoring", "quality", "developing", "evaluate", "maintain", "kpis", "plans", "cross-functional teams", "planning"], "requirements": {"degrees": [], "majors": [], "languages": [], "language_level": [], "hard_skills": ["facebook", "analytical skills"], "soft_skills": ["organizational skills", "detail-oriented", "analytical skills", "hands-on", "willingness to work"], "languages_combined": []}, "experience_required": {"duration": ["1+ years"], "field": ["agency"]}}, {"job_id": "100003008997414", "location_code": "hk", "company": "Television Broadcasts Limited (TVB)", "job_title": "Subeditor/Senior Subeditor/Principal Subeditor", "description": "Edit and package local and foreign news items\nExcellent news judgment\nUniversity graduate in Journalism or Translation\nGood command of both written and spoken Chinese and English\nShift duty is required\nApplicant with more experience will be considered as Senior Subeditor/ Principal Subeditor\n\nPlease apply, quoting the appropriate reference number, with details of your qualifications and experience, expected salary and a contact telephone number to The Senior Manager, Personnel Department, Television Broadcasts Limited, TVB City, 77 Chun Choi Street, Tseung Kwan O Industrial Estate, Tseung Kwan O, Kowloon or email to us via Recruitment Centre.\n\nApplications received are solely for selection purpose.\u00a0 Those not invited for an interview within 4 weeks may consider their applications unsuccessful and their applications will be filed for another 3 months for future selection.\u00a0 Afterwards, all applications would be destroyed.", "employment_types": ["Full Time", "Permanent"], "selling_points": [], "locations": ["Not Specified"], "categories": ["Media & Advertising", "Production", "Editorial / Journalism", "Broadcasting - TV / Radio"], "post_time": "2021-12-29T16:11:09Z", "salary": {"currency": null, "max": null, "min": null, "period": "monthly", "term": null}, "salary_visible": false, "title_keywords": [], "responsibilities": ["recruitment", "contact"], "requirements": {"degrees": ["university graduate"], "majors": ["journalism"], "languages": ["english", "chinese"], "language_level": ["good command"], "hard_skills": ["translation"], "soft_skills": [], "languages_combined": [{"language": "english", "language_level": ["good command"]}, {"language": "chinese", "language_level": ["good command"]}]}, "experience_required": {"duration": [], "field": ["recruitment"]}}, {"job_id": "100003009006883", "location_code": "hk", "company": "Phoenix Satellite Television Co Ltd", "job_title": "PROGRAMME DISTRIBUTION EXECUTIVE", "description": "Responsibilities:\n- Work closely with design & marketing team to complete high quality of varies genre of photography & videography\n- Responsible for video shoot and photo shoot including camera operation, lighting set up and audio recording\n- Responsible for audio visual equipment for video / photo shoot, and equipment maintenance\n- Responsible for live-streaming broadcast set up and operation control\n- Research, develop creative idea and design visual mockup to company standard\n- Responsible for photo re-touch\n-\u00a0Responsible for offline video editing\n- Manage raw material and file storage in a good format\n- Ensure photos / videos are in high standard quality and complete filming within time frame\n\nRequirements:\n- At least 2 years relevant working experience in photo / video production\n- Proficient of video camera, also familiar with wide range of photo / filming equipment (lights, audio & gimbal)\n- Knowledge of video editing is a must\n- Knowledge of photo shoot is an advantage\n- Able to work independently and under pressure\n- Self-motivated, well-organized and a good team player\n- Ability to multi-task and produce good content in tight schedule\n- Online portfolio is a must\n\nInterested parties please send full C.V. and expected salary to Ms Lo via email\u00a0\n", "employment_types": ["Full Time", "Permanent"], "selling_points": [], "locations": ["Tai Po Area"], "categories": ["Media & Advertising", "Editorial / Journalism", "Broadcasting - TV / Radio", "Sales, CS & Business Devpt", "Account Servicing"], "post_time": "2021-12-29T11:36:34Z", "salary": {"currency": null, "max": null, "min": null, "period": null, "term": null}, "salary_visible": false, "title_keywords": ["executive"], "responsibilities": ["control", "maintenance", "file storage", "quality", "design", "develop", "video editing", "visual", "audio"], "requirements": {"degrees": [], "majors": [], "languages": [], "language_level": [], "hard_skills": ["video editing"], "soft_skills": ["good team player", "work independently", "under pressure", "self-motivated", "multi-task", "well-organized"], "languages_combined": []}, "experience_required": {"duration": ["at least 2 years"], "field": ["video production", "photo", "relevant working experience"]}}]