[{"job_id": "100003009054207", "location_code": "hk", "company": "Mindmad Creation Limited", "job_title": "Graphic Designer (Stage/ Graphic Design)", "description": "Requirements:\n\nPost-secondary (Diploma/Certificate) in Art, Design, Graphic, Advertising or other related disciplines\nAt least 2~3 years of commercial graphic design experience;\nA design portfolio is a must - Fluent in Adobe Creative Suite\u00a0\nProficient in Adobe Illustrator, Photoshop and InDesign;\nFluent in Adobe CS, in particular, Photoshop, Illustrator and InDesign. Knowledge and experience in Cinema 4D, After Effects and Premiere Pro a bonus.\nCreative, detail-minded, responsible with constant innovation and work dynamic\nProficient in PhotoShop and Illustrator, venue decoration familiar with MAC would be an advantage\nGood command of written and spoken English & Chinese (Mandarin & Cantonese)\nFresh Graduates are welcome to apply\u00a0\nGood communication skills with customers\nImmediate available is preferred\nHave a positive and passionate approach with a can-do attitude.\nMeticulous planning and organizational skills.\n\nJob Descriptions:\n\nCreate graphic design & layout for various design projects\nCollaborate with team to deliver innovative creative concepts that meet client business objectives\nDevelop effective, brand-appropriate marketing and promotional layouts for digital and print media\nKnowledge in Output process\nCreative, strong sense\u00a0at\u00a0good typography, layout, good color\u00a0and\u00a0marketing sense\nSelf-motivating, creative, energetic, a positive attitude with strong interpersonal skills, able to work independently and as an integral part of the team, share ideas openly and work towards the common goal of the team\nMust be open to new ideas and enjoy working with a creative team\nStrong sense of responsibility, attention to details and a good team player, creative, energetic and independent with excellent critical thinking and interpersonal skills\nCommunicate and collaborate closely with internal clients and stakeholders to facilitate the creative process\nDevelop creative ideas and concepts, often in partnership with other creative team members.\nBeing a problem solver and have a creative mindset\nAssist in planning and implementation of marketing activities, public relations, events management, online marketing and loyalty marketing;\nLiaise and maintain good relationship with strategic partners and tenants for coordinating effective marketing collaborations;\u00a0\nWork closely with internal and external parties to achieve marketing goals;\u00a0\nParticipate in ad hoc projects as assigned;\u00a0\nSelf-motivated & independent, responsible and able to work under tight schedule and pressure.\nHandle idea and project related to art with creativity\nOversee profitability, deliverables, timelines and budgets\nMotion graphic, and video editing skills is a huge plus\u00a0\nProduce clear and concise verbal and written communications.\nCommunicate with internal parties on the design requirement for projects ( e.g. leaflets and printed materials design and publishing. )\nProducing graphic layout and production output", "employment_types": ["Full Time", "Permanent"], "selling_points": [], "locations": ["Quarry Bay"], "categories": ["Media & Advertising", "Creative / Design", "Design", "Graphics", "Marketing / Public Relations", "Marketing - General / Support"], "post_time": "2022-01-17T08:49:12Z", "salary": {"currency": null, "max": null, "min": null, "period": "monthly", "term": null}, "salary_visible": false, "title_keywords": ["graphic designer"], "responsibilities": ["collaborate with", "liaise", "ideas", "graphic layout", "internal and external parties", "design", "video editing", "collaborate", "implementation", "develop", "maintain good relationship", "schedule", "communicate with internal parties", "develop creative ideas", "management", "leaflets", "motion graphic", "budgets", "graphic design", "facilitate the creative process", "ad hoc projects", "planning"], "requirements": {"degrees": ["certificate", "diploma"], "majors": ["related disciplines", "art", "design"], "languages": ["cantonese", "english", "chinese", "mandarin"], "language_level": ["good command"], "hard_skills": ["indesign", "illustrator", "adobe illustrator", "after effects", "dynamic", "premiere pro", "adobe cs", "adobe creative suite", "photoshop"], "soft_skills": ["detail-minded", "communication skills", "passionate", "meticulous", "organizational skills", "responsible", "can-do attitude", "dynamic", "creative", "positive"], "languages_combined": [{"language": "cantonese", "language_level": ["good command"]}, {"language": "english", "language_level": ["good command"]}, {"language": "chinese", "language_level": ["good command"]}, {"language": "mandarin", "language_level": ["good command"]}]}, "experience_required": {"duration": ["at least 2~3 years"], "field": ["commercial", "graphic design"]}}, {"job_id": "100003009056137", "location_code": "hk", "company": "Always Marketing Holdings Limited", "job_title": "Associate Art Director/Art Director", "description": "Always Marketing Holdings Limited\n\n\u00a0We are a strategy-driven marketing agency, we offer integration of creativity and technology applications to deliver unique communications and experiential marketing solutions.\n\nTo cope with the rapid expansion of the company, we are recruiting talents for the following position:\n\n\u00a0Associate Art Director / Art Director\n\n\u00a0Job Highlights\n\n\u00a0Art direction and graphic design initiative\n\nDevelop & implement digital technology ideas\nMarketing campaigns ideas recommendation\n\nResponsibilities:\n\nWork as part of a creative team to develop concepts, visual elements, creative solution and executions\nDevelop layout and artwork in various platforms, including print ads, TVC and video production, digital media etc.\nContinually explore the new trend in creative, design and digital marketing\nClient presentation and cooperation with vendors and third parties\n\nRequirements:\n\nDiploma or above in Design / Multimedia / Animation or related discipline\nCreative and conceptual thinker\nAbility to explain complex ideas to internal and external partners including communicate creative concepts in presentations to clients\nProficiency in Photoshop and Illustrator in Mac environment and Microsoft Office, knowledge in multimedia will be an added advantage\nFresh graduate or 1 year experience for Assistant Art Director position / 2-3 years\u2019 experience for Art Director position\n\nWe offer competitive\u00a0package to right candidates.\u00a0If you have the enthusiasm and ambition to develop career in the marketing industry, and enjoy working in a company with fun and dynamic culture, please apply by sending\u00a0your resume with expected salary and\u00a0portfolio/ reference work.\n\nPersonal data collected will be used for recruitment purpose only.\u00a0\n\nAdditional Information\n\nCareer Level - Middle\n\nJob Type - Full Time, Permanent\n\nOffice location \u2013 Fortress Hill, Hong Kong\n\n\u00a0Candidate who is interested in the post please send the resume to the below email address.", "employment_types": ["Full Time"], "selling_points": [], "locations": ["North Point"], "categories": ["Media & Advertising", "Creative / Design"], "post_time": "2022-01-18T03:22:50Z", "salary": {"currency": "HKD", "max": 34999, "min": 20000, "period": "monthly", "term": null}, "salary_visible": true, "title_keywords": ["art director", "associate"], "responsibilities": ["develop layout", "video production", "design", "develop concepts", "digital marketing", "visual"], "requirements": {"degrees": ["fresh graduate", "diploma or above"], "majors": ["art", "animation", "design"], "languages": [], "language_level": [], "hard_skills": ["mac environment", "microsoft office", "illustrator", "presentations", "multimedia", "photoshop"], "soft_skills": ["creative"], "languages_combined": []}, "experience_required": {"duration": ["2-3 years", "1 year"], "field": ["art director"]}}, {"job_id": "100003009056096", "location_code": "hk", "company": "Purple Cow Communications Ltd", "job_title": "Graphic Designer / Art Director / Senior Art Director (FMCG)", "description": "The Job \u00a0\n\nResponsible for developing and executing creative projects for 360 Marketing Campaign\nExecute design projects from ideas to finished products independently\nFollow through project from concept development, artwork design and production independently and within tight timeline\n\n\nThe Person \u00a0\n\nPolytechnic or T.I. Students studying in Graphic Design, Commercial Arts or related disciplines are welcomed\nAt least 5 years solid design experience working in Advertising agency or Graphic House; Less experience will treat it as Art Director and Graphic Designer\nExcellent creative sense and strong passion for design\nSelf motivated and capable of handling and supervising projects independently from concept design to project completion;\nHighly proficient in Macintosh softwares e.g. Photoshop, Illustrator & Premiere etc. from layout presentation to artwork output & production\nKnowledge in video production\u00a0would be an advantage\n\n\nWe offer 5-day work week and attractive remuneration package to qualified candidates. Interested parties please send your resume, portfolio, latest and expected salary\u00a0 by clicking \u2018Apply Now\u2019.\n\n\nPersonal data collected would be used for recruitment purpose only.", "employment_types": ["Full Time", "Permanent"], "selling_points": ["Award winning creative agency", "5 days work, Happy working environment", "Medical Insurance + Year-end Bonus"], "locations": ["Kowloon Bay"], "categories": ["Media & Advertising", "Creative / Design", "Production", "Design", "Graphics"], "post_time": "2022-01-18T03:17:03Z", "salary": {"currency": null, "max": null, "min": null, "period": "monthly", "term": null}, "salary_visible": false, "title_keywords": ["art director", "senior art director", "graphic designer"], "responsibilities": ["executing", "developing", "design", "ideas"], "requirements": {"degrees": [], "majors": [], "languages": [], "language_level": [], "hard_skills": ["illustrator", "premiere", "photoshop"], "soft_skills": ["independently", "capable", "passion for", "self motivated", "creative", "presentation"], "languages_combined": []}, "experience_required": {"duration": ["at least 5 years"], "field": ["art director", "designer", "design", "graphic", "it", "advertising agency"]}}, {"job_id": "100003009054970", "location_code": "hk", "company": "Beeline Pro Limited", "job_title": "\u61f8\u8cde\u512a\u79c0\u4f19\u4f34 Designer\uff0fArt Director\uff0fMotion Graphic\uff0fProduction Assistant (Full Time / Part Time)", "description": "\u5982\u6709\u898b\u5230\u4ee5\u4e0b\u4eba\u58eb\uff0c\u8acb\u8fc5\u901f\u806f\u7e6b\uff01\n\n\u6a02\u610f\u63a5\u53d7\u6311\u6230\u3001\u52c7\u65bc\u627f\u64d4\u8cac\u4efb\u3001\n\n\u4e0d\u754f\u5de5\u4f5c\u8271\u8f9b\u3001\u5805\u6301\u5275\u4f5c\u512a\u79c0\u4f5c\u54c1\uff01\n\n\u5982\u679c\u662f\u60a8\uff0c\u6211\u5011\u5718\u968a\u6210\u54e1\u5f88\u9700\u8981\u4f60\u5354\u52a9\u5e36\u9818\u53ca\u5171\u540c\u6210\u9577\uff01\n\n\u66fe\u7d93apply \u904e\u6b61\u8fce\u518dapply\n\n\u8acb\u7528\u5c11\u5c11\u6642\u9593\u4ffe\u6211\u5730\u4e86\u89e3\u4f60\uff0c\u6709\u54a9\u80fd\u529b\u540c\u62b1\u8ca0\uff0c\u5982\u679c\u4f60\u5c0d\u6211\u5730\u516c\u53f8\u6709\u8208\u8da3\uff0c\u8acb\u56de\u7b54\u4ee5\u4e0b\u554f\u984c\n\n\u300c\u4f60\u8a8d\u70ba\u5728\u672a\u4f86\u4e8b\u696d\u4e0a\u6210\u529f\u61c9\u5177\u5099\u7684\u4e94\u500b\u689d\u4ef6\u53ca\u9700\u8981\u505a\u7684\u4e94\u4ef6\u4e8b\u300d\n\n\u8acb\u56de\u7b54\u6b64\u554f\u984c\u9023\u540c\u4f60\u7684Expected salary\uff0cResume \u53caPortfolio Email\u7d66\u6211\u5011\u3002\uff08\u4e0d\u8981\u900f\u904ejobsdb \u5167\u90e8\u7533\u8acb\uff0c\u8acb\u76f4\u63a5email \u7d66\u6211\u5011)\n\u6211\u5011\u6703\u614e\u91cd\u8003\u616e\u6bcf\u4e00\u4f4d\u6c42\u8077\u8005\u3002\n\n\u9700\u8981\u6709\u624d\u80fd\u7684\u4f60\u4e00\u8d77\u5171\u540c\u6210\u9577!\n\n\n\u6211\u5730\u7406\u5ff5\uff1a\u76e1\u529b\u5e6b\u5ba2\u6236\u89e3\u6c7a\u96e3\u984c\uff0c\u8ffd\u6c42\u5275\u4f5c\u8207\u6311\u6230\uff0c\u5805\u6301\u935b\u934a\u81ea\u5df1\u7684\u80fd\u529b\n\u5de5\u4f5c\u5167\u5bb9\uff1a\u5f71\u7247\u88fd\u4f5c\uff0c\u7db2\u9801\u8a2d\u8a08\uff0c\u8a2d\u8a08\uff0c\u52d5\u756b\u88fd\u4f5c\u53ca\u7db2\u4e0a\u5ba3\u50b3\uff0c\u53e6\u5916\u6709\u81ea\u5df1\u7684\u5f71\u7247channel\n\u5c0d\u6bcf\u500b\u4f19\u4f34\u671f\u671b\uff1a\u6301\u7e8c\u5b78\u7fd2\uff0c\u6301\u7e8c\u9032\u6b65\n\n------------------\u00a0------------------\u00a0------------------\u00a0------------------\u00a0------------------\n\nGraphic Design / Art Director (Full Time/ Part Time)\n\n\n\u54c1\u724c\u5f62\u50cf\u8a2d\u8a08\uff0f\u7db2\u9801\u8a2d\u8a08\uff0f\u5e73\u9762\u8a2d\u8a08\uff0f\u7f8e\u8853\u6307\u5c0e\n\u66fe\u65bcDesign House / Production House \u76f8\u95dc\u5de5\u4f5c\u7d93\u9a57\u4e00\u5e74\u6216\u4ee5\u4e0a\u512a\u5148\n\nVideo Editor & Videographer & PA\n\n\u57f7\u884c\u529b\u5f37\n\u5f71\u7247\u88fd\u4f5c\uff0c\u7531\u524d\u671f\u5275\u4f5c\u53ca\u7c4c\u5099(\u6435\u6f14\u54e1\uff0f\u666f\uff0fprops)\uff0c\u5230\u73fe\u5834\u62cd\u651d\u53ca\u5f8c\u671f\u526a\u63a5\n\u5de5\u4f5c\u7bc4\u570d 60%\u5f8c\u671f\uff0c30%\u524d\u671f\uff0c10%\u62cd\u651d\n\u9700\u9577\u6642\u9593\u5de5\u4f5c\uff0c\u6371\u5f97\uff0c\u6709\u8cac\u4efb\u5fc3\n\u9700\u8981Teamwork \u5de5\u4f5c\uff0c\u500b\u4eba\u4e3b\u7fa9\u597d\u5f37\uff0c\u5514\u63a5\u53d7\u4eba\u610f\u898b\u65e2\u4eba\u5514\u5ca9\n\u7528 Davinci\uff0fFinal Cut Pro X\uff0fAfter Effect\n\u6709\u526a\u63a5\uff0c\u62cd\u651d\u7d93\u9a57\u512a\u5148\n\n\n\n\nMotion Graphic Designer\u00a0 (Full Time / Part Time)\n\n\n\u5de5\u4f5c\u5167\u5bb9\u4e3b\u8981 motion graphic \u53ca VFX\n\n\u300c\u719f\u300d\u7528After Effect / Photoshop / Illustrator\n\u61c2\u756b\u5716\n\u826f\u597d\u53e3\u8aaa\u6e9d\u901a\u548c\u8868\u9054\u80fd\u529b\n\u76f8\u95dc\u9ad8\u7d1a\u6587\u6191\u4ee5\u4e0a\u7a0b\u5ea6\n\n\u00a0------------------\u00a0------------------\u00a0------------------\u00a0------------------\u00a0------------------\n\nOur channel:\nhttps://www.youtube.com/channel/UCyLVZIEw2jawOLSxM4571JQ\nhttps://www.youtube.com/channel/UC8Az3jqRPwwMpY8eJ1bsYMg\n\nOur Website: www.beeline-pro.com\n\nAddress: Room 20C, Cheung Hing Shing Centre, 23 Sha Tsui Road, Tsuen Wan, N.T., Hong Kong\n\n\nAny interested parties please send e-mail with\u00a0Expected salary\uff0cResume and Portfolio to\u00a0recruit @beeline-pro.com\u00a0for further detail.\n\nPersonal data collected will be used for recruitment purpose only\n\n***Application without Portfolio/ Expected salary will NOT get response***", "employment_types": ["Full Time", "Part Time", "Permanent", "Contract", "Internship", "Freelance"], "selling_points": [], "locations": ["Tsuen Wan Area"], "categories": ["Media & Advertising", "Creative / Design", "Production", "Photography / Video"], "post_time": "2022-01-17T16:21:45Z", "salary": {"currency": null, "max": null, "min": null, "period": "monthly", "term": null}, "salary_visible": false, "title_keywords": ["assistant"], "responsibilities": ["graphic design", "motion graphic", "website"], "requirements": {"degrees": [], "majors": [], "languages": [], "language_level": [], "hard_skills": ["wan", "illustrator", "photoshop"], "soft_skills": [], "languages_combined": []}, "experience_required": {"duration": [], "field": []}}, {"job_id": "100003009055766", "location_code": "hk", "company": "", "job_title": "Digital Marketing Executive (Graphics & Copy)", "description": "Requirements\n\nHigher Diploma / Associate Degree / Degree holder in Multimedia, Creative Media, Digital Marketing Communications or other related disciplines\n1-2 years social media / digital marketing experience is a plus\nBringing creative ideas to multiple categories including Layout and Copy in various social media platforms, and online/offline campaigns\nBanners, Online Promotion Layouts, image retouch and other graphics design\nCuriosity to learn new things, not afraid of taking challenges and initiatives, ask questions and implement strategies\nGood command of English & Chinese\nFresh graduate will also be considered\nImmediately available is preferred\n\nJob Description\n\nHandling daily updates of Chinese and English social media and online platforms (graphics / videos and copy)\nPlan and design creative graphic and Copy in various eCommerce social media platform\nDesigning materials (banner, icon, premium etc) to optimize UI of various platforms\nManaging Social Media advertisement and executing online marketing campaigns of Google Ads and other promotion tools\nDevelop and execute E-Marketing ideas in a strategic way\nOther ad hoc assignments\n\u00a0\n\nOur IG : https://www.instagram.com/etopiahkofficial/\n\nInterested candidates, please contact us at 23593358 for company details before applying.", "employment_types": ["Full Time", "Permanent"], "selling_points": ["Manage & Create daily social media ads & posts", "Develop & execute E-Marketing ideas strategically", "Create & Design Graphics & Copy for Social Media"], "locations": ["Kwun Tong"], "categories": ["Media & Advertising", "Creative / Design", "Design", "Multi-media", "Marketing / Public Relations", "Marketing - Direct Marketing"], "post_time": "2022-01-18T02:55:52Z", "salary": {"currency": null, "max": null, "min": null, "period": "monthly", "term": null}, "salary_visible": false, "title_keywords": ["digital marketing executive"], "responsibilities": ["graphics", "social media", "ideas", "design", "develop", "executing", "ad hoc assignments", "plan", "designing", "marketing campaigns", "ui"], "requirements": {"degrees": ["associate degree", "diploma", "fresh graduate", "degree holder"], "majors": ["related disciplines", "creative media", "digital marketing", "communications"], "languages": ["english", "chinese"], "language_level": ["good command"], "hard_skills": ["graphics", "plus", "multimedia"], "soft_skills": ["creative"], "languages_combined": [{"language": "english", "language_level": ["good command"]}, {"language": "chinese", "language_level": ["good command"]}]}, "experience_required": {"duration": ["1-2 years"], "field": ["social media", "digital marketing"]}}, {"job_id": "100003009054404", "location_code": "hk", "company": "KREW LIMITED", "job_title": "Associate Creative Director (Art-Based) / Assistant Digital Creative Director", "description": "Company Background\n\nKREW Digital\u00a0is the\u00a0No.1\u00a0Social Media Agency and Content Marketing Agency recognized by Marketing Magazine*. We won the\u00a0Agency of the Year 2021 (6 Gold, 6 Local Hero, 3 Bronze).\u00a0KREW is a fast-growing digital agency, mainly focusing on social media, digital campaigns and content marketing. Our team is formed by veterans of first-tier digital agencies, consultancies and the mass media. Our client list includes some of the most respected and admired names in Hong Kong and worldwide, including leading property developer, hospitality group, luxury retailer and world-class travelware brand.\n\nWith self-developed tool \"KREWatch\", its analytic approach help craft persona insight for our creative ideas, it's the core reason for us to win Marketing Excellence Awards in Categories of Retail Marketing and Loyalty Marketing.\u00a0\n\nTo cope with our expansion, we would like to invite high-calibre talents to join our energetic team for an exciting career in digital marketing.\n\nThe ideal candidate will formulate online / digital / social media / content marketing strategies for our clients by planning and executing digital marketing campaigns. Candidate will also plan and launch digital advertisements and create content. He / she will also be able to monitor clients\u2019 social media presences.\n\n*KREW is the Gold Winner of Social Media Agency of the Year 2021 and Content Marketing Agency of the Year 2021 organized by Marketing Magazine.\u00a0\n\nFollow Us\u00a0\n\n\u25baW:\u00a0https://www.krewdigital.com/\u00a0\n\u25baF:\u00a0https://www.facebook.com/krewdigital/\n\u25baL:\u00a0https://www.linkedin.com/company/krewdigital/\n\n\nRequirements\n\nDirectly report to Directors to lead creative team for digital and social media strategy.\nIn charge of overseeing digital creative direction and quality control of all projects.\u00a0\nWork closely with account servicing and creative to in charge of proposals and ad hoc projects.\nVeteran in digital and social media advertising and creative industry.\u00a0\nCraft ideas with award-winning approach.\u00a0\n\nQualifications\n\nDiploma holder or above in Graphic / Multimedia Design\n3 to 5 year Digital Agency background in well-known 4As/web/multi-media/interactive fields is a plus\nPresentable and good command of Cantonese and English\nProficiency in HTML, AI, AE, PS, PR\nExperience on handling Finance, Banking, Insurance, Shopping Malls is a plus\nCreative, Can-Do attitude, Proactive, independent and a good team leader and player\nCapable in manage multiple projects to meet tight deadlines\nStrong Sense of belongings to the projects of client and team\n\nInterested parties please send CV to us!", "employment_types": ["Full Time"], "selling_points": ["3 - 5 year ex. 4As agency background is a plus", "Creative. Digital marketing & social media veteran", "Stunning agency office environment"], "locations": ["Tsuen Wan Area"], "categories": ["Media & Advertising", "Creative / Design", "Design", "Graphics", "Multi-media"], "post_time": "2022-01-17T09:23:31Z", "salary": {"currency": null, "max": null, "min": null, "period": "monthly", "term": null}, "salary_visible": false, "title_keywords": ["creative director", "associate", "assistant"], "responsibilities": ["multimedia design", "ideas", "plan", "facebook", "advertising", "digital marketing campaigns", "monitor", "manage multiple projects", "digital campaigns", "banking", "report", "social media", "marketing strategies", "digital marketing", "executing", "creative ideas", "advertisements", "ad hoc projects", "quality control", "insurance", "planning"], "requirements": {"degrees": ["diploma holder"], "majors": ["multimedia design"], "languages": ["cantonese", "english"], "language_level": ["good command"], "hard_skills": ["no", "plus", "web", "ai", "html", "reason", "multimedia", "facebook"], "soft_skills": ["organized", "meet tight deadlines", "proactive", "independent", "creative", "capable", "can-do attitude", "world-class", "presentable", "good team leader", "energetic", "ideal"], "languages_combined": [{"language": "cantonese", "language_level": ["good command"]}, {"language": "english", "language_level": ["good command"]}]}, "experience_required": {"duration": [], "field": ["finance", "insurance", "banking"]}}, {"job_id": "100003009053141", "location_code": "hk", "company": "Harmonic Scene Limited", "job_title": "Multimedia Designer (5-Day Work)", "description": "We're looking for talents to join our a high-calibre creative team to create digital solution for our client.\n\nResponsibility:\n\n\nDevelop UI layout and interaction design for a variety of digital solutions\nTo create stunning design and forward-thinking user experience with analytically data and creative mindset.\nEffectively communicate research findings, conceptual ideas and detail design rationale both verbally and visually\n\nRequirements:\n\n\nExperienced in web design (PC & Mobile responsive) / mobile app design with a demonstrated portfolio\nConceptual thinking in both visual and interactive visual\nStrong communication skills to interface with clients and internal project team\nCreative, strong design sense, good responsibility, attention to details and good team player\nKnowledge of relevant industry tools specifically Adobe XD, Adobe Photoshop & Adobe Illustrator\nImmediate\u00a0available\u00a0is\u00a0highly\u00a0preferred\nDiploma, associate degree or bachelor\u2019s degree in related disciplines\nFresh graduates will also be considered\n\nWe offer\n\n\nHappy and dynamic working environment\nMedical Scheme\nBeing part of a young team striving for excellence\nOpportunities to participate in fun and exciting company events year-round\nComplimentary food and drinks in the workplace\nWork life balance\nBank holiday\nLife Insurance\nPerformance Bonus", "employment_types": ["Full Time", "Permanent"], "selling_points": [], "locations": ["Kwai Hing"], "categories": ["Media & Advertising", "Creative / Design", "Design", "Graphics", "Multi-media"], "post_time": "2022-01-17T06:04:33Z", "salary": {"currency": null, "max": null, "min": null, "period": "monthly", "term": null}, "salary_visible": false, "title_keywords": ["multimedia designer"], "responsibilities": ["ideas", "data", "user experience", "design", "develop", "ui"], "requirements": {"degrees": ["associate degree", "diploma", "degree", "bachelor"], "majors": ["related disciplines"], "languages": [], "language_level": [], "hard_skills": ["web design", "adobe xd", "adobe photoshop", "adobe illustrator", "mobile", "pc"], "soft_skills": ["communication skills", "good team player", "attention to details", "creative", "responsive"], "languages_combined": []}, "experience_required": {"duration": [], "field": []}}, {"job_id": "100003009054029", "location_code": "hk", "company": "Shepherd Communications Limited", "job_title": "Senior Graphic Designer", "description": "Key Responsibilities\n\nCreate graphic and multimedia design from concept to finished artwork development in print and digital communications.\nMonitor the design and production quality of marketing materials.\nWork closely with Marketing and Creative and Game Departments.\n\nRequirements\n\nDiploma or Degree holder in Multimedia/ Creative Media/ Design or related disciplines.\nMinimum 3 years' solid experience in Multimedia Design/ Advertising/ Graphic Design and Printing Production.\nCreative, excellent drawing and concept skills.\nProficiency in Creative Cloud (Photoshop, Illustrator, InDesign, After Effect, Premiere Pro, HTML5, etc.) and Maya on Mac environment.\nStrong sense of responsibility and work independently.\nKnowledge of Web Design, Animation and Video Production is an advantage.\n\nInterested parties please submit your detailed CV (with current and expected salary) by clicking \"Apply Now\".\u00a0\u00a0\n\nData collected will be used for recruitment purpose only.", "employment_types": ["Full Time", "Permanent"], "selling_points": ["Senior Graphic Designer", "Graphic design", "Motion Graphics"], "locations": ["Sai Ying Pun"], "categories": ["Media & Advertising", "Creative / Design", "Design", "Graphics", "Multi-media"], "post_time": "2022-01-17T09:16:34Z", "salary": {"currency": null, "max": null, "min": null, "period": "monthly", "term": null}, "salary_visible": false, "title_keywords": ["senior graphic designer"], "responsibilities": ["multimedia design", "artwork development", "quality", "monitor", "design", "marketing materials"], "requirements": {"degrees": ["diploma", "degree holder"], "majors": ["related disciplines", "creative media", "design"], "languages": [], "language_level": [], "hard_skills": ["web design", "maya", "mac environment", "indesign", "illustrator", "multimedia", "premiere pro", "after effect", "photoshop"], "soft_skills": ["work independently", "creative", "sense of responsibility"], "languages_combined": []}, "experience_required": {"duration": ["minimum 3 years"], "field": ["graphic design", "advertising", "design"]}}, {"job_id": "100003009051406", "location_code": "hk", "company": "Hardchi Creative", "job_title": "Associate Art Director / Art Director", "description": "Job Responsibilities\n\n\nResponsible for graphic design from concept creative to final artwork.\nWide range of graphic design jobs including Advertising, Corporate Identity, digital games & moving images.\nDevelop 2D layouts for Animation, AR & VR Games.\nGenerate idea and create storyboard for TVC, Micro Films, Corporate Video & Animation.\nQualifications, Skills and Other Requirement\n\n\nDiploma in Graphic Design or related discipline.\n4 years solid experience;\u00a0at least 2 years in the same capacity.\nHighly Proficiency in Adobe Illustrator and vector graphics. Knowledge of Adobe Photoshop in output standard.\nExcellent in Graphic Design, perfectionist in design details.\nAccuracy in output - online and printing.\nKnowledge in 2D animation and film editing (After Effect or\u00a0Adobe Premiere).\nUnderstanding digital marketing, content marketing, SEO,\u00a0UI and UX, and mobile responsive is a bonus.\nExcellent work attitude,\u00a0highly responsible and able to\u00a0handle multiple projects.\nAble to complete project under tight deadlines.\nAttractive salary & 5-day work per week. Interested parties please email full CV with Present & Expected Salary by clicking \u201cAPPLY NOW\u201d.\n\n\nAll personal data collected will be kept confidential and used for recruitment purpose only.\n\n", "employment_types": ["Full Time"], "selling_points": [], "locations": ["Lai Chi Kok"], "categories": ["Media & Advertising", "Creative / Design"], "post_time": "2022-01-17T02:26:28Z", "salary": {"currency": null, "max": null, "min": null, "period": "monthly", "term": null}, "salary_visible": false, "title_keywords": ["art director", "associate"], "responsibilities": ["graphics", "advertising", "ar", "seo", "graphic design", "design", "develop", "digital marketing", "multiple projects", "editing", "ui", "animation"], "requirements": {"degrees": ["diploma"], "majors": ["graphic design"], "languages": [], "language_level": [], "hard_skills": ["graphics", "seo", "ar", "adobe photoshop", "adobe illustrator", "mobile", "adobe premiere", "after effect"], "soft_skills": ["creative", "responsive", "responsible"], "languages_combined": []}, "experience_required": {"duration": ["4 years"], "field": []}}, {"job_id": "100003009053004", "location_code": "hk", "company": "Passionation (Hong Kong) Limited", "job_title": "Multimedia/Content Designer (Lifestyle and Trending)", "description": "Responsibilities:\nProvide strong conceptual thinking as well as visual crafting\nHandle and create visual content for clients\nGenerate clear ideas and concepts, either working alone or with team members.\nProduce sketches, storyboards, roughs to visualise ideas\nTake work from concept to final execution within tight deadlines\nOversee photography/motion shoots and briefing of illustrations/graphics/animations\nPresent completed ideas to clients/team members\nStay on top of all trends and maintain best practices\nStrong creative sense in social media platforms\u00a0\nCapable of developing award winning campaigns\nRequirements:\n\n1-3 years\u2019 experience in advertising, digital agency or related discipline\nCapable of generating creative ideas and concepts independently and with team members\nExperienced with integrated communications\nGood sense of art direction, graphic sense, skills on layout presentation and artwork production\nExperienced in multimedia design\nSelf-motivated, detail-minded, and able to work under pressure\u00a0\nProficient use of Photoshop, Illustrator or other visual design tools\nGood command of English and Chinese\nImmediate available is preferable\nWe offer a 5-day week of work, group medical insurance coverage & birthday leave.\n\nInterested parties, please send your detailed resume with the expected salary via Apply Now.", "employment_types": ["Full Time"], "selling_points": ["Min. 1 year of related working experience", "Able to work creatively in videos & images", "Good communication skill in Cantonese and English"], "locations": ["Quarry Bay"], "categories": ["Media & Advertising", "Creative / Design", "Production", "Photography / Video"], "post_time": "2022-01-17T05:02:10Z", "salary": {"currency": null, "max": null, "min": null, "period": "monthly", "term": null}, "salary_visible": false, "title_keywords": ["designer"], "responsibilities": ["graphics", "ideas", "social media platforms", "developing", "sketches", "maintain", "animations", "visual", "storyboards"], "requirements": {"degrees": [], "majors": [], "languages": ["english", "chinese"], "language_level": ["good command"], "hard_skills": ["visual design", "illustrator", "multimedia", "photoshop"], "soft_skills": ["detail-minded", "self-motivated", "independently", "capable", "creative", "presentation", "work under pressure"], "languages_combined": [{"language": "english", "language_level": ["good command"]}, {"language": "chinese", "language_level": ["good command"]}]}, "experience_required": {"duration": ["1-3 years"], "field": ["agency", "digital", "advertising", "related"]}}, {"job_id": "100003009055357", "location_code": "hk", "company": "S&S Hospitality Limited", "job_title": "Social Media Content Creator", "description": "\u00a0Job Highlights:\n\n\nPlanning\u00a0and\u00a0creating\u00a0content\u00a0of\u00a0video\u00a0projects,\u00a0like\u00a0post-treatment\u00a0experience\u00a0of\u00a0patients\u00a0and\u00a0KOLs,\u00a0introduction\u00a0of\u00a0clinical\u00a0service,\u00a0etc.\nResponsible\u00a0for\u00a0all\u00a0aspects\u00a0of\u00a0video\u00a0production\u00a0including\u00a0pre-production,\u00a0shooting,\u00a0editing,\u00a0subtitling\u00a0and\u00a0post-production\u00a0\nPublishing\u00a0in\u00a0various\u00a0channels\u00a0including\u00a0social\u00a0media,\u00a0website\u00a0and\u00a0internal\u00a0training\n\n\u00a0Job Duties:\n\nDevelop creative ideas and concepts with\u00a0marketing team members\nProduce diversified video content for multiple platforms including but not limited to social, print, corporate, and creative campaigns\nRecord, mix and post produce audio recordings\nSet and adjust the lighting during shooting\nInsert subtitles and aftereffects to the videos\nShoot and perform post-production of high quality, compelling content\nEnsure videos are well-edited, color / sound graded and produced according to brand guidelines\nAmend, revise or redevelop adverts or campaign videos in response to feedback from the marketing team and management\u00a0\nAd-hoc duties as assigned from time to time\n\n\u00a0Requirements:\n\nCertificate/Diploma/Degree holder in Film/ Creative Media/ Multimedia Design/ Motion Graphics/ Animation or related field\nMinimum 2 years of solid experience in video shooting, editing and production\nGood communication & interpersonal skills\n\u00a0Benefits:\n\nYoung and dynamic marketing team\n5-day work per week\nMedical insurance\nAnnual leave\nAnnual discretionary bonus\nSpecial offer of eye treatment for staff and family\n\n\u00a0Skills:\n\nAdobe Premiere / After Effects / Photoshop / Illustrator\n*Please provide your portfolio to demonstrate some work that you have done before*\n\n\n*Please include a recent photo and your expected salary in the CV for the application*\n\n\u8acb\u900f\u904e\"Apply Now\"\u905e\u4ea4\u5c65\u6b77\u3001\u4f5c\u54c1\u96c6\uff08\u6216\u9023\u7d50\uff09\u3001\u73fe\u6642\u53ca\u8981\u6c42\u7684\u85aa\u916c\u5f85\u9047\u7b49\u8cc7\u6599\u3002\n", "employment_types": ["Full Time", "Permanent"], "selling_points": ["Manage social media channels strategies", "Develop campaigns to engage customers", "Create content for social media that drives brand"], "locations": ["Tsim Sha Tsui"], "categories": ["Media & Advertising", "Creative / Design", "Photography / Video", "Marketing / Public Relations", "Digital Marketing"], "post_time": "2022-01-18T02:17:52Z", "salary": {"currency": null, "max": null, "min": null, "period": "monthly", "term": null}, "salary_visible": false, "title_keywords": [], "responsibilities": ["management", "quality", "brand guidelines", "ad-hoc duties", "audio", "develop creative ideas"], "requirements": {"degrees": ["certificate", "diploma", "degree holder"], "majors": ["multimedia design", "creative media", "motion graphics", "animation"], "languages": [], "language_level": [], "hard_skills": ["graphics", "multimedia"], "soft_skills": ["communication", "creative", "interpersonal skills"], "languages_combined": []}, "experience_required": {"duration": ["minimum 2 years"], "field": ["editing", "video shooting"]}}, {"job_id": "100003008964815", "location_code": "hk", "company": "eMotionLab Limited", "job_title": "Creative Copywriter/ Strategist", "description": "Job Responsibilities\n\nUnderstand clients\u2019 needs and deliver creative and innovative business solutions;\nSharp creative mind, collaborate with Account Management team to pitching/developing new ideas to clients\nIdentify market opportunities and potential strategic partnerships to capture new business and to expand market share\nContribute to the development of projects and responsible for researching, planning, executing, and preparing creative briefs in line with project needs & goals\nElevate the creative concept, design, and execution of various formats of contents\nAssist in developing overall corporate branding and marketing strategy\n\nJob Requirements\n\nBachelor\u2019s degree on Marketing, Multimedia,, Communications, or related disciplines;\nAt least 1 years\u2019 experience in digital marketing agency\nExcellent command in\u00a0Cantonese, English and Mandarin ;\nProficient in MS PowerPoint and Excel;\nMultimedia experience is preferred;\nExcellent communication and analytical skills;\nCorporately presentable and business savvy\nAble to work under pressure and tight deadlines;\nExcellent attention to detail, work independently, flexible and willing to learn;", "employment_types": ["Full Time"], "selling_points": ["Creative Copywriter/ Strategist", "Aspire to innovate", "5 days work and dynamic working environment"], "locations": ["Wong Tai Sin Area"], "categories": ["Media & Advertising", "Creative / Design", "Production", "Design", "Multi-media"], "post_time": "2022-01-17T02:04:37Z", "salary": {"currency": null, "max": null, "min": null, "period": "monthly", "term": null}, "salary_visible": false, "title_keywords": ["creative copywriter"], "responsibilities": ["collaborate with", "management team", "developing", "design", "developing new ideas", "executing", "contents", "planning"], "requirements": {"degrees": ["degree", "bachelor"], "majors": ["related disciplines", "marketing", "communications"], "languages": ["cantonese", "english", "mandarin"], "language_level": ["excellent"], "hard_skills": ["excel", "ms powerpoint", "multimedia", "analytical skills"], "soft_skills": ["flexible", "work independently", "willing to learn", "presentable", "communication", "analytical skills", "attention to detail", "work under pressure"], "languages_combined": [{"language": "cantonese", "language_level": ["excellent"]}, {"language": "english", "language_level": ["excellent"]}, {"language": "mandarin", "language_level": ["excellent"]}]}, "experience_required": {"duration": ["at least 1 years"], "field": ["agency", "digital marketing"]}}, {"job_id": "100003009053165", "location_code": "hk", "company": "\u5708\u50b3\u5a92\u6709\u9650\u516c\u53f8", "job_title": "Multimedia Reporter \u591a\u5a92\u9ad4\u8a18\u8005 / Video Editor \u526a\u7247 \u300a\u6e2f\u4eba\u8b1b\u5730\u300b - \uff08\u591a\u540d\uff09(5 days)", "description": "We are seeking applicants who are enthusiastic, experienced in content creation for the group\u2019s restaurants and bars.\n\nRESPONSIBILITIES\n\n\nMust be self-motivated and able to work independently\nPrepare copy and content calendar for social media posts\nProduce edited photography and short videos\nSet up accounts on social media platforms for new outlets\nResearch latest digital innovations to introduce to company activities\nPresent social media strategic plan and influencer campaign to expand digital reach\nLiaise with marketing team to align brand strategy\nProduce professional social media collaterals with design team\nAnalyze and compile monthly reports on growth tracking, promotion results and guests\u2019 reviews\nManage daily engagement with audiences, respond and react to enquiries and feedback\u00a0\n\nREQUIREMENTS\n\nStrong interpersonal and communication skills\nAble to deliver high quality video, photography\nPost production and editing of video and photography\nExperience in designing brand content for web, desktop and mobile\nCreative thinker, articulate and persuasive\nGood, creative and confident writer, high attention to detail in correct spelling and punctuation\nProficient in Adobe Photoshop, Illustrator, After Effects and Premier Pro\nDegree holder (or similar) in Videography, photography or equivalent experience in the creative or graphic design field\nMinimum 2 years\u2019 experience in managing social media accounts\nAbility to multitask several creative projects\nExcellent creative skills and a great eye for detail\nFluent in English, written and spoken, is essential, Cantonese and Mandarin is an advantage\nCreative, enthusiastic, proactive approach to all social media activities\n\nInterested applicants, please forward your resume together with the expected salary\u00a0by clicking \"Apply Now\"\n\nPersonal information collected is for recruitment purposes only.\u00a0", "employment_types": ["Full Time"], "selling_points": [], "locations": ["Lai Chi Kok"], "categories": ["Media & Advertising", "Creative / Design", "Editorial / Journalism", "Photography / Video"], "post_time": "2022-01-17T06:11:10Z", "salary": {"currency": null, "max": null, "min": null, "period": "monthly", "term": null}, "salary_visible": false, "title_keywords": ["reporter", "video editor"], "responsibilities": ["social media", "monthly reports", "social media platforms", "design", "plan", "liaise with", "tracking"], "requirements": {"degrees": ["degree holder"], "majors": ["graphic design"], "languages": ["cantonese", "english", "mandarin"], "language_level": ["advantage", "fluent"], "hard_skills": ["web", "adobe photoshop", "illustrator", "mobile", "after effects"], "soft_skills": ["confident", "communication skills", "proactive", "persuasive", "enthusiastic", "attention to detail", "eye for detail", "articulate", "ability to multitask", "creative", "interpersonal"], "languages_combined": [{"language": "cantonese", "language_level": ["fluent"]}, {"language": "english", "language_level": ["fluent"]}, {"language": "mandarin", "language_level": ["advantage", "fluent"]}]}, "experience_required": {"duration": ["minimum 2 years"], "field": ["graphic design", "social media", "brand"]}}, {"job_id": "100003009052064", "location_code": "hk", "company": "Eagle Sky Media Limited", "job_title": "Digital Marketing Officer (Advertising Agency , Digital Marketing, Social media)", "description": "1. Multimedia Reporter \u591a\u5a92\u9ad4\u8a18\u8005\n\n\u8077\u8cac\uff1a\n\n\n\u64b0\u5beb\u65b0\u805e\u3001\u6642\u8a55\u3001\u5c08\u984c\u53ca\u591a\u5a92\u9ad4\u88fd\u4f5c\u7684\u5167\u5bb9\n\u4e3b\u52d5\u767c\u6398\u672c\u5730\u6642\u653f\u3001\u5169\u5cb8\u3001\u570b\u969b\u95dc\u4fc2\u4ee5\u53ca\u6b63\u80fd\u91cf\u5c08\u984c\n\u9700\u8981\u9032\u884c\u6236\u5167\u6216\u6236\u5916\u63a1\u8a2a\u5de5\u4f5c\uff0c\u6216\u6709\u9700\u8981\u6642\u5230\u5916\u5730\u5de5\u4f5c\n\u5165\u8077\u8981\u6c42\uff1a\n\n\n\u5927\u5c08\u6216\u4ee5\u4e0a\u5b78\u6b77\u7a0b\u5ea6\u512a\u5148\uff0c\u5b78\u79d1\u80cc\u666f\u4e0d\u62d8\n\u5177\u63a1\u8a2a\u6216\u7de8\u8f2f\u5de5\u4f5c\u7d93\u9a57\uff0c\u6216\u65b0\u5a92\u9ad4\u76f8\u95dc\u5de5\u4f5c\u7d93\u9a57\u512a\u5148\uff0c\u525b\u7562\u696d\u8005\u4ea6\u6703\u8003\u616e\n\u5c0d\u6642\u653f\u3001\u5169\u5cb8\u3001\u793e\u6703\u3001\u7d93\u6fdf\u3001\u5916\u4ea4\u3001\u570b\u969b\u95dc\u4fc2\u7b49\u8b70\u984c\u6709\u8a8d\u8b58\uff0c\u4e26\u5177\u6709\u76f8\u95dc\u5206\u6790\u80fd\u529b\n\u61c2\u5169\u6587\u4e09\u8a9e\uff0c\u4e2d\u82f1\u6587\u66f8\u5beb\u80fd\u529b\u8f03\u4f73\u8005\u7372\u512a\u5148\u8003\u616e\n\u5177\u8996\u983b\u88fd\u4f5c\u77e5\u8b58\u6216\u7d93\u9a57\u8005\u512a\u5148\n\u5c0d\u65b0\u5a92\u9ad4\u5de5\u4f5c\u6709\u71b1\u8aa0\uff0c\u6709\u5275\u610f\uff0c\u6027\u683c\u7a4d\u6975\u4e3b\u52d5\uff0c\u6709\u62da\u640f\u7cbe\u795e\uff0c\u64c5\u9577\u8207\u4eba\u6e9d\u901a\n\u4e94\u5929\u5de5\u4f5c\uff0c\u9700\u8f2a\u73ed\n\n2. Video Editor \u526a\u7247\n\n\u00a0\u00a0\u00a0\u00a0\u00a0\u00a0\u00a0\u00a0\u00a0\u00a0\u00a0 \u8077\u8cac\uff1a\n\n\n\u8ca0\u8cac\u65b0\u805e\u5f71\u7247\u526a\u63a5\u53ca\u5f8c\u671f\u88fd\u4f5c\n\n\u5165\u8077\u8981\u6c42\uff1a\n\n\n\u5c0d\u65b0\u805e\u5f71\u7247\u526a\u63a5\u6709\u8208\u8da3\uff0c\u64c1\u76f8\u95dc\u5de5\u4f5c\u7d93\u9a57\u8005\u512a\u5148\u8003\u616e\n\u9700\u719f\u6089\u500b\u4eba\u96fb\u8166\u53caMac\u6a5f\u61c9\u7528\u7a0b\u5f0f\u64cd\u4f5c\n\u651d\u5f71\u53ca\u526a\u7247\u5169\u7a2e\u6280\u80fd\u4ff1\u5099\u8005\uff0c\u7372\u512a\u5148\u8003\u616e\n\u826f\u597d\u6e9d\u901a\u6280\u5de7\uff0c\u559c\u6b61\u5718\u968a\u5de5\u4f5c\uff0c\u52e4\u596e\u597d\u5b78\uff0c\u559c\u6b61\u5275\u65b0\uff0c\u5c0d\u5de5\u4f5c\u6709\u8cac\u4efb\u611f\n\u4e94\u5929\u5de5\u4f5c\uff0c\u9700\u8f2a\u73ed\n\n\u6709\u610f\u8005\u8acb\u628a\u81ea\u5df1\u904e\u53bb\u62cd\u651d\u6216\u526a\u63a5\u7684\u4f5c\u54c1\u9023\u7d50\uff0c\u4e26\u9644\u4e0a\u5c65\u6b77\u53ca\u85aa\u91d1\u8981\u6c42\uff0c\u6309 \"Apply Now\" \u6309\u9215\u7533\u8acb\uff1b \u6216\u90f5\u5bc4\u81f3\u672c\u516c\u53f8\u4eba\u529b\u8cc7\u6e90\u90e8\uff0c\u5730\u5740:\u4e5d\u9f8d\u8354\u679d\u89d2\u9577\u9806\u88577\u865f\u897f\u9813\u4e2d\u5fc33305-7\u5ba4\uff0c\u4fe1\u5c01\u9762\u8acb\u8a3b\u660e\u300c\u61c9\u5fb5\u591a\u5a92\u9ad4\u8a18\u8005\u300d / \u300c\u61c9\u5fb5\u526a\u7247\u300d\u3002", "employment_types": ["Full Time", "Permanent"], "selling_points": ["CONTENT Marketing", "Advertising Agency", "designer"], "locations": ["Tsuen Wan Area"], "categories": ["Media & Advertising", "Creative / Design", "Design", "Graphics", "Marketing / Public Relations", "Public Relations - Copy-writing"], "post_time": "2022-01-17T08:45:18Z", "salary": {"currency": null, "max": null, "min": null, "period": "monthly", "term": null}, "salary_visible": false, "title_keywords": ["digital marketing officer", "digital marketing"], "responsibilities": [], "requirements": {"degrees": [], "majors": [], "languages": [], "language_level": [], "hard_skills": ["multimedia"], "soft_skills": [], "languages_combined": []}, "experience_required": {"duration": [], "field": []}}, {"job_id": "100003009053480", "location_code": "hk", "company": "Untitled Limited", "job_title": "Senior 3D Designer (5 days work)", "description": "If you are a\u00a0Copywriter who aspire to to give life and new meanings to what matters now with words for brands, corporates and even government agencies & public organizations...\u00a0\nWe should meet!\n\nWe are looking for high caliber talents to join our growing team\n... in our new spacious office\n\u2026 and to chill out with us in our amazing balcony!\n\nThe Ideal candidate shall have the following qualities:\n\ngood language and written skills\npresentable and good interpersonal skills\nhave an eye for detail and interest in new advertising trends and techniques\nPassionate, Motivated and Proactive Working Attitude\nBe able to meet tight schedule\nwork well in a team\n\n*\u00a0Fresh graduates are welcomed to apply\n\nInterested candidates please include your current and expected salary, website/ samples of your work in your application.\n\nPlease include [Creative Copywriter/ Strategist] in the subject line.\n\nPersonal data collected will be handled strict confidence for recruitment related purpose only.", "employment_types": ["Full Time"], "selling_points": ["Five-day work week", "Double pay", "Performance bonus"], "locations": ["Quarry Bay"], "categories": ["Media & Advertising", "Creative / Design", "Design", "Graphics", "Visual Merchandising"], "post_time": "2022-01-17T07:02:15Z", "salary": {"currency": null, "max": null, "min": null, "period": "monthly", "term": null}, "salary_visible": false, "title_keywords": ["senior 3d designer"], "responsibilities": ["advertising", "schedule"], "requirements": {"degrees": [], "majors": [], "languages": [], "language_level": [], "hard_skills": ["chill", "words"], "soft_skills": ["passionate", "presentable", "motivated", "interpersonal skills", "eye for detail", "proactive", "ideal"], "languages_combined": []}, "experience_required": {"duration": [], "field": []}}, {"job_id": "100003009051362", "location_code": "hk", "company": "Raze Technology Limited", "job_title": "Art Director", "description": "Responsibilities:\nSocial media management including content development & consumer engagement\nCommunicate and extent good relationships with on-line media, KOL, vendors & platform partners\nAnalyze market trends and explore new marketing techniques & business opportunities\nParticipate and support internal teams for different marketing campaign and operation needs\nPrepare marketing proposal for client\nPrepare regular reports for management review\nParticipate & support in all new business initiatives and all ad hoc projects\nGood content writer\nStrong Creative Designer is much preferred\n\nRequirements:\n\nDegree holder in Marketing / Communication / Multi-media Design preferred\nMin. 2 years\u2019 experienced in marketing\nExcellent interpersonal, presentation and communication skills\nProficient in MS Word, Excel, PowerPoint and Chinese Word Processing\nFluency in written and spoken Chinese and English\nExperience in CMS (Wordpress) ,graphic design tools (Adobe Photoshop and Adobe Illustrator)\nDetail-minded, tech-savvy, outgoing, and flexible to work\nHard-working, willing to learn and able to handle multi-task, work under pressure and meet deadlines\nCandidate with more experienced will be considered as Senior Marketing Executive", "employment_types": ["Full Time", "Permanent", "Contract", "Freelance"], "selling_points": [], "locations": ["Southern Area"], "categories": ["Media & Advertising", "Creative / Design", "Design", "Graphics", "Multi-media"], "post_time": "2022-01-15T11:12:04Z", "salary": {"currency": null, "max": null, "min": null, "period": "monthly", "term": null}, "salary_visible": false, "title_keywords": ["art director"], "responsibilities": ["social media", "management", "business initiatives", "business opportunities", "review", "teams", "regular reports for management", "ad hoc projects"], "requirements": {"degrees": ["degree holder"], "majors": ["marketing", "design"], "languages": ["english", "chinese"], "language_level": ["fluency", "proficient"], "hard_skills": ["excel", "chinese word processing", "adobe photoshop", "powerpoint", "adobe illustrator", "wordpress", "ms word"], "soft_skills": ["detail-minded", "communication skills", "outgoing", "flexible", "multi-task", "willing to learn", "communication", "hard-working", "meet deadlines", "interpersonal", "presentation", "work under pressure"], "languages_combined": [{"language": "english", "language_level": ["fluency"]}, {"language": "chinese", "language_level": ["fluency", "proficient"]}]}, "experience_required": {"duration": [], "field": ["graphic design"]}}, {"job_id": "100003009053572", "location_code": "hk", "company": "ANKH \u6a5f\u80fd\u518d\u751f \u75db\u75c7\u5065\u5eb7\u96c6\u5718", "job_title": "Producer / Videographer", "description": "Requirements:\n\n\n2 years minimum experience in event production / exhibition field / shopping mall decorations\nCompetency in adobe illustrator / Photoshop / 3D studio max, Auto CAD\nPreparing studies, layouts, and construction drawing.\nSeasonal-Decoration, Event Design experience will be an absolute advantage\nExhibition, or environmental design qualification in degree or diploma level\nFresh Graduate will be considered\nAble to handle projects from concept design through to completion\nMust be a team player and willing to work overtime, self initiative & motivated, strong sense of responsibitity and able to work under pressure\n\n\nWe offer attractive package to the right candidate.\n\nInterested parties please send full resume with salary expected, to Fax No. 3426 9709\n\nhttp://www.facebook.com/pages/untitled-limited/336303970488", "employment_types": ["Full Time"], "selling_points": ["video production, video shooting and editing", "3 years related experiences", "Candidates must provide Portfolio"], "locations": ["Tsim Sha Tsui"], "categories": ["Media & Advertising", "Creative / Design", "Design", "Multi-media", "Photography / Video"], "post_time": "2022-01-17T07:10:45Z", "salary": {"currency": null, "max": null, "min": null, "period": "monthly", "term": null}, "salary_visible": false, "title_keywords": ["producer", "videographer"], "responsibilities": ["design", "work under pressure"], "requirements": {"degrees": ["diploma", "degree", "fresh graduate"], "majors": ["design"], "languages": [], "language_level": [], "hard_skills": ["max", "auto cad", "photoshop", "adobe illustrator"], "soft_skills": ["work overtime", "motivated", "team player", "initiative", "work under pressure"], "languages_combined": []}, "experience_required": {"duration": ["2 years"], "field": ["design"]}}, {"job_id": "100003009053082", "location_code": "hk", "company": "BDO Financial Services Limited", "job_title": "UX/UI Designer", "description": "The Role\nThe Art Director is required to work hand-in-hand with Head of Marketing, primarily to generate the original idea, lead the art direction and present campaigns to top management, secondly to groom and coach the juniors, help manage the execution and production.\n\nResponsibilities\n\nInterpret a creative brief and turn it into a compelling story;\nProduce innovative ideas for campaigns in line with the creative brief provided;\nTranslate marketing campaign \u2018Big Idea\u2019 into visual brand identity of our clients;\nProduce key visuals for pitches and marketing campaign;\nTranslate a briefing into a visual statement using presentation tools such as PowerPoint, Google slide or Keynote;\nAble to develop visual concepts which adhere to any brand style guideline and restrictions provided;\nWork resourcefully, offer variety of alternative solutions to creative problems;\nThe ability to present your work clearly and confidently in front of internal stakeholders;\nHands-on working is needed, be ready to jump in with the highest level of design quality.\n\nRequirements\n\nStrong conceptual skills with a passion for big ideas;\nHungry to produce high quality work;\nSolid technical art direction with a keen eye for detail;\nBe interested in popular culture, social media and be up to date with current advertising trends and techniques;\nExcellent command of English (native level would be an advantage) and Cantonese is required, both spoken and written;\nMinimum 5 years of art directing and design work experience;\nAbility to shift priorities and navigate between competing deadlines while managing multiple projects of varying sizes, topic and type;\nInnovative, energetic and proactive, proven self-starter and a strong team player;\nExceptional art/design and verbal communication skills, presentation skills and organisational skills;\nRegional experience is an advantage.\n\nWe offer the right candidate attractive remuneration package and outstanding prospects for career advancement and development.\u00a0 The right candidate will progress career in a forward thinking and dynamic business with exciting growth plans.\u00a0 If you are qualified and interested, please send your full resume with current & expected salary and availability by clicking \"APPLY \".\n\nAll information collected will be treated as strictly confidential and used for recruitment purposes only. (Only shortlisted candidates will be notified)", "employment_types": ["Full Time", "Permanent"], "selling_points": ["Listed Company", "Exp from advertising / creative / branding agency", "Westernize team culture"], "locations": ["Not Specified"], "categories": ["Media & Advertising", "Creative / Design", "Marketing / Public Relations", "Digital Marketing", "Information Technology (IT)", "UI/UX Designer"], "post_time": "2022-01-17T05:41:29Z", "salary": {"currency": null, "max": null, "min": null, "period": "monthly", "term": null}, "salary_visible": false, "title_keywords": ["ui designer"], "responsibilities": ["ideas", "key visuals", "quality", "design", "develop", "visual"], "requirements": {"degrees": [], "majors": [], "languages": ["cantonese", "english"], "language_level": ["native", "excellent", "advantage"], "hard_skills": [], "soft_skills": ["communication skills", "proactive", "passion for", "keen", "interested in", "energetic", "presentation skills", "organisational skills", "eye for detail", "team player", "innovative"], "languages_combined": [{"language": "cantonese", "language_level": ["native", "excellent", "advantage"]}, {"language": "english", "language_level": ["native", "excellent", "advantage"]}]}, "experience_required": {"duration": ["minimum 5 years"], "field": ["design"]}}, {"job_id": "100003009053140", "location_code": "hk", "company": "ORIENTAL HUMAN RESOURCES LIMITED", "job_title": "Reporter Trainee - Entertainment News", "description": "Job Description:\n\nResponsible in video production, video shooting and editing\nEnsure videos are well-edited, color / sound graded and produced according to brand guidelines\nMaterial preparation for shooting including products, scenes, lightings, props and backgrounds\nRecord, mix and post produce audio recordings\nCreate motion graphic design, including insert subtitles and aftereffects to the videos\nCollaborate with Creative and Marketing team\nPerform other ad-hoc tasks as assigned\n\nRequirements:\n\nDiploma in Film\u00a0/\u00a0Television Production / Video Production / Multimedia or related discipline\n3 years above related experiences\nProficient in video shooting and editing including software likes Premiere, Photoshop, After Effects is necessary\nStrong visual storytelling skills, and interpersonal & communication skills\nKnowledge of Graphic Design\nCreative, eager to learn, self-initiative & motivated, responsible, supportive\nAble\u00a0to work under pressure, independently, collaboratively and under tight schedule\nImmediately available is highly preferred\nCandidate without Portfolio (job reference / link) will\u00a0NOT\u00a0be\u00a0considered\n\nWe offer competitive salary package and fringe benefits to the right candidate.\u00a0\n\nInterested parties please send cover letter and full resume with current and expected salary to\u00a0Human Resources Department\u00a0by clicking 'APPLY NOW'.\u00a0\n\nFor more information, please visit our website https://www.ankh.com.hk\n\nPersonal data collected will be used for recruitment purpose only.", "employment_types": ["Full Time"], "selling_points": [], "locations": ["Tai Po Area"], "categories": ["Media & Advertising", "Creative / Design", "Others", "Editorial / Journalism"], "post_time": "2022-01-17T08:34:57Z", "salary": {"currency": null, "max": null, "min": null, "period": "monthly", "term": null}, "salary_visible": false, "title_keywords": ["reporter", "trainee"], "responsibilities": ["audio", "collaborate with", "video production", "ad-hoc tasks", "video shooting", "brand guidelines", "editing", "motion graphic design"], "requirements": {"degrees": ["diploma"], "majors": [], "languages": [], "language_level": [], "hard_skills": ["after effects", "multimedia", "premiere", "photoshop"], "soft_skills": ["communication skills", "supportive", "independently", "responsible", "eager to learn", "motivated", "self-initiative", "creative", "interpersonal", "work under pressure"], "languages_combined": []}, "experience_required": {"duration": ["3 years"], "field": ["related"]}}, {"job_id": "100003009052933", "location_code": "hk", "company": "Passionation (Hong Kong) Limited", "job_title": "Editor (Lifestyle and Trending)", "description": "Our client is a listed company and established a global presence with a variety of businesses around the world.\u00a0 Reporting to Head and Creative Director, candidate will take the ownership and be the go-to person of the website and mobile app.\n\nKey Responsibilities:\u00a0\n\nRedesign the current the website and build a new app from scratch for new business direction and enhanced backend technology\nDeliver CRO, UX, and UI ideas and solutions\u00a0to optimize the results and performance\nDrive A/B tests to improve conversion funnels and user engagement\nEnsure the highest standard and keep improving the design based on new business requirements and changes\n\nKey Requirements:\n\n\nDegree holder in Multimedia Design, Arts, Visual Arts or any related disciplines\nMinimum 3 years\u2019 relevant working experience, preferably gained in\u00a0advertising / creative / branding agency with UX/UI focused experience\u00a0\nProficient in Adobe Creative Suite, Photoshop, Illustrator and InDesign\nHands-on experience in UX design software such as Adobe XD, InVision and UXPin. Knowledge and experience in After Effects and Premiere Pro a bonus\nGood command of both written and spoken English and Chinese\nStrong sense of responsibility, self-motivated, eager to learn and a good team player\nPortfolio is required for application\nCandidate with more experience will be considered as Senior UX/UI Designer\u00a0\n\nInterested parties please send your application with full career history, current & expected salary and portfolio by clicking Apply Now button. Applications will be treated in strict confidence. Personal data collected will be used for recruitment purposes only.", "employment_types": ["Full Time"], "selling_points": ["Min. 1 year of working experience in Editorial", "Creative and excellent online knowledge", "Good communications skills in Cantonese & English"], "locations": ["Quarry Bay"], "categories": ["Media & Advertising", "Creative / Design", "Editorial / Journalism", "Photography / Video"], "post_time": "2022-01-17T04:38:55Z", "salary": {"currency": null, "max": null, "min": null, "period": "monthly", "term": null}, "salary_visible": false, "title_keywords": ["editor"], "responsibilities": ["ui", "ideas", "website", "design"], "requirements": {"degrees": ["degree holder"], "majors": ["multimedia design", "related disciplines"], "languages": ["english", "chinese"], "language_level": ["good command"], "hard_skills": ["adobe xd", "indesign", "illustrator", "after effects", "multimedia", "premiere pro", "adobe creative suite", "photoshop"], "soft_skills": ["self-motivated", "good team player", "focused", "sense of responsibility", "eager to learn", "hands-on", "creative"], "languages_combined": [{"language": "english", "language_level": ["good command"]}, {"language": "chinese", "language_level": ["good command"]}]}, "experience_required": {"duration": ["minimum 3 years"], "field": ["designer", "advertising", "agency", "relevant working experience", "design"]}}, {"job_id": "100003009051313", "location_code": "hk", "company": "Miramar Hotel and Investment Company, Limited", "job_title": "Designer", "description": "Responsibilities:\n\nCreate quality and engaging social media contents for \u653f\u7b56\u2027\u6b63\u5bdfFacebook, YouTube and Instagram\nContribute creative ideas and conduct interviews for video projects\nCollaborate with videographers/editors in production\nAdministrate social media platforms\nDevelop, implement and evaluate digital marketing strategy\nMonitor the social media trend\n\nRequirements:\n\nDegree holder in Journalism, New media, Digital Marketing, Public Policy or relevant disciplines\nMinimum of 2 years of relevant experience\nStrong interest or knowledge in digital content marketing and public affairs\nRelevant media and digital agency experience is an advantage\nKnowledge of editing software and/or online marketing tools is an advantage\nAnchoring or program hosting experience is an advantage\nSelf-motivated and detail-oriented, able to work under pressure and juggle among tasks\nCandidates with more than 5 years' relevant experience will be considered as Senior Officer\nFresh graduates will be considered as Assistant Officer\n\nInterested parties please send:\n\nFull resume;\nCover letter;\nCopies of academic transcripts (including\u00a0public examination results if applicable);\nPresent and expected salary;\nAvailability\n\nBy clicking 'Apply Now' or by post to: Our Hong Kong Foundation Limited, 19/F, Nan Fung Tower, 88 Connaught Road Central, Hong Kong. Applicants who are not invited to an interview within two months from the date of this advertisement should consider their applications unsuccessful.\u00a0\n\nAll information provided by applicants will be handled with strictest confidence and will be solely used for the purpose of recruitment.", "employment_types": ["Full Time", "Permanent"], "selling_points": [], "locations": ["Tsim Sha Tsui"], "categories": ["Media & Advertising", "Creative / Design", "Design", "Graphics", "Multi-media"], "post_time": "2022-01-15T08:04:11Z", "salary": {"currency": null, "max": null, "min": null, "period": "monthly", "term": null}, "salary_visible": false, "title_keywords": ["designer"], "responsibilities": ["collaborate with", "social media", "creative ideas", "social media platforms", "quality", "monitor", "develop", "evaluate", "digital marketing", "contents"], "requirements": {"degrees": ["degree holder"], "majors": ["journalism", "digital marketing", "public policy"], "languages": [], "language_level": [], "hard_skills": [], "soft_skills": ["work under pressure", "self-motivated", "detail-oriented"], "languages_combined": []}, "experience_required": {"duration": ["5 years", "minimum of 2 years"], "field": ["agency", "digital", "relevant experience", "media"]}}, {"job_id": "100003009054128", "location_code": "hk", "company": "The Hong Kong Jockey Club", "job_title": "Part-time Customer Digital Experience Development Assistant", "description": "Responsibilities:\n\n\nTo participate in seasonal projects in HR Department\nTo assist in event and campaign planning in Marketing Department\nTo perform ad-hoc duties if required\n\n\nRequirements:\n\n\nDSE & Higher Diploma & University graduates in any disciplines, & no relevant working experience candidates are also welcomed\nGood work attitude and team players\nSelf-motivated and creative candidates\nStrong interpersonal skills and communication skills (Cantonese, English and Mandarin)\n\n\nWorking Day (Successful candidates will be assigned for only one of the following days):\n\n16th February, 2022 (Wed); or\n22nd February, 2022 (Tue); or\n23rd February, 2022 (Wed); or\n2nd March, 2022 (Wed); or\n8th March, 2022 (Tue); or\n18th March, 2022 (Fri); or\n25th March, 2022 (Fri)\n\n\nWorking Hours: 10:30am \u2013 6pm\nJob Salary: $2,000 / one day contract\n\nDirect employment, salary, MPF and contract will be paid and issued by Quality People Resources Limited.\n\nInterested parties, please submit your application by:\n\nClicking \u201cApply Now\u201d; or\nThrough \"Joboffer\" app; or\nWhatsApp 92886650 (https://wa.me/message/M24M4MRDAA34E1).", "employment_types": ["Part Time"], "selling_points": ["The Hong Kong Jockey Club", "HK$73.5 per hour", "Digital product and mobile application operation"], "locations": ["Wan Chai Area"], "categories": ["Media & Advertising", "Creative / Design"], "post_time": "2022-01-17T08:31:17Z", "salary": {"currency": null, "max": null, "min": null, "period": "hourly", "term": null}, "salary_visible": false, "title_keywords": ["assistant"], "responsibilities": ["hr", "ad-hoc duties", "planning"], "requirements": {"degrees": ["diploma", "dse"], "majors": ["any disciplines"], "languages": ["cantonese", "english", "mandarin"], "language_level": [], "hard_skills": ["no"], "soft_skills": ["communication skills", "self-motivated", "creative", "interpersonal skills"], "languages_combined": [{"language": "cantonese", "language_level": []}, {"language": "english", "language_level": []}, {"language": "mandarin", "language_level": []}]}, "experience_required": {"duration": [], "field": ["relevant working experience"]}}, {"job_id": "100003009056107", "location_code": "hk", "company": "The Ad Region Ltd", "job_title": "Senior Project Executive", "description": "The Job\n\nCreate innovative solutions for Group and Business Units from concept generation, layout design and final artwork production including F&B photo shooting art direction, mall campaign setup idea, hotel sophisticated layout designs and corporate communicating materials to convey the distinctive messages\nDesign and execute all the assigned design tasks from research, concept generation, layout design and final artwork production in a wide range of media platforms\nWork with supervisor and other teammates to adhere to user\u2019s requests and meet deadlines to retain the company brand consistency and the specific promotions\nLiaise and follow up with printing companies and suppliers to ensure the timely delivery\nThe Requirement\n\nHigher diploma or above in Graphic Design or related disciplines\n2 years or above experience in design/advertising and/or digital campaign\nExperience in graphic, multimedia design, layout and typography\nKnowledge on Adobe Suite and video editing software i.e. Illustrator, Photoshop, InDesign, Premiere & Aftereffect etc.\nGood team player, willing to learn, open-minded, independent and responsible\n\nAttractive remuneration would be offered to the right candidates.\nPlease send your application with portfolio and expected salary to\u00a0Human Resources Manager:\n\nBy WhatsApp: 6388-3034 or\nBy Fax: 2722-5555\n\nPersonal data collected will be used for recruitment purpose only.\u00a0 We are an equal opportunity employer.", "employment_types": ["Full Time"], "selling_points": [], "locations": ["North Point"], "categories": ["Media & Advertising", "Account Servicing", "Creative / Design", "Production"], "post_time": "2022-01-18T03:19:37Z", "salary": {"currency": null, "max": null, "min": null, "period": "monthly", "term": null}, "salary_visible": false, "title_keywords": ["senior project executive"], "responsibilities": ["liaise", "artwork production", "layout design", "design", "brand consistency", "setup"], "requirements": {"degrees": ["higher diploma or above"], "majors": ["related disciplines", "graphic design"], "languages": [], "language_level": [], "hard_skills": ["indesign", "illustrator", "premiere", "video editing", "whatsapp", "adobe", "multimedia", "photoshop"], "soft_skills": ["good team player", "independent", "responsible", "open-minded", "willing to learn"], "languages_combined": []}, "experience_required": {"duration": ["2 years"], "field": ["digital", "graphic", "advertising", "design"]}}, {"job_id": "100003009037383", "location_code": "hk", "company": "\u7d93\u6fdf\u4e00\u9031 EDigest", "job_title": "Social Media Executive/Digital Content Executive (Business & Finance)", "description": "The Department\nThe Customer Digital Experience Department is responsible for leading and managing development projects of digital wagering experience and customer service digital transformation.\u00a0 Besides project management, its scope includes content requirement definition, user-interface and user experience design, as well as the look and feel based on customer insights and product requirements.\n\nThe Job\nYou will\u00a0\u00a0\n\nassist in design and deliver the best possible digital customer experience across the Club\u2019s range of digital channels\nparticipate in and provide assistance in the testing stage of different digital related projects\nprovide\u00a0administrative support for the department including preparing management reports and consolidating customer enquiries for product development roadmap establishment\n\nAbout You\nYou should have\u00a0\n\nminimum Level 2 or equivalent in 5 subjects including English Language in HKDSE\nknowledge of using digital product and mobile application operation\nknowledge in Adobe Creative Suite, Sketch, inVision Studio, Figma or other design software will be an advantage\ndetails orientated and self-motivated, mindset with sense of responsibilities\n\n\nTerms of Employment\n\nPay-rate:\nHK$73.5 per hour\n\nWorking Schedule: 10:00am-6:00pm (2-3 days per week / Monday to Friday)\u00a0\n*Actual working hours would depend on operational needs.\n\nWorking Location\u00a0\nHappy Valley / Shatin\n\nHow to Apply\nPlease send your resume and job reference by clicking the Apply Now button or to:\nFax: 2881-7966\nMail: The Human Resources Department,\u00a0\u00a0\u00a0\u00a0\u00a0\u00a0\u00a0\u00a0\n\u00a0\u00a0\u00a0\u00a0\u00a0\u00a0\u00a0\u00a0\u00a0 The Hong Kong Jockey Club,\u00a0\u00a0\u00a0\u00a0\u00a0\n\u00a0\u00a0\u00a0\u00a0\u00a0\u00a0\u00a0\u00a0\u00a0 1 Sports Road, Happy Valley,\n\u00a0\u00a0\u00a0\u00a0\u00a0\u00a0\u00a0\u00a0\u00a0 Hong Kong\n\nFind out more about the remarkable opportunity today. Visit our website at www.hkjc.com now.\n\nWe are an equal opportunity employer.\n\nPersonal data collected will be used for recruitment purposes only.", "employment_types": ["Full Time", "Permanent"], "selling_points": ["Content development & data analysis", "Experience in social media marketing field", "Great development opportunity, competitive package"], "locations": ["Kwun Tong"], "categories": ["Media & Advertising", "Creative / Design", "Others", "Editorial / Journalism"], "post_time": "2022-01-16T21:50:10Z", "salary": {"currency": null, "max": null, "min": null, "period": null, "term": null}, "salary_visible": false, "title_keywords": ["digital content executive", "social media executive"], "responsibilities": ["software", "customer enquiries", "customer insights", "user experience", "design", "testing", "project management", "management reports", "customer service", "schedule", "provide administrative support", "provide assistance"], "requirements": {"degrees": ["hkdse"], "majors": [], "languages": ["english"], "language_level": [], "hard_skills": ["project management", "management reports", "mobile", "adobe creative suite"], "soft_skills": ["self-motivated", "responsible", "project management", "customer service", "creative", "sense of responsibilities"], "languages_combined": [{"language": "english", "language_level": []}]}, "experience_required": {"duration": [], "field": ["design", "project management", "customer service", "digital", "development projects"]}}, {"job_id": "100003009051426", "location_code": "hk", "company": "ACT Company", "job_title": "Social Media Specialist \u793e\u4ea4\u5a92\u9ad4 x Wealth Management \u8ca1\u5bcc\u7ba1\u740615K-30K", "description": "Responsibilities :\n\nTo independently plan & manage project series in HK and overseas\nTo provide high quality client servicing\nTo co-work with team members for a smooth executive\nTravel is a necessary\n\n\u00a0Job Requirement :\n\nUniversity graduates with at least 3-4 years\u2019 experience\u00a0\nKnowledge in event marketing and advertising production is a must\nStrong organizational, communication & interpersonal skill\nSelf-driven, aggressive and creative\nGood spoken & written English, Cantonese & Mandarin\nAble to work under pressure and to meet tight deadlines", "employment_types": ["Full Time", "Part Time", "Permanent", "Temporary", "Contract", "Internship", "Freelance"], "selling_points": ["\u7db2\u7d61\u71df\u92b7", "Instagram Facebook \u5c0f\u7de8", "Financial Planning"], "locations": ["Kwun Tong"], "categories": ["Media & Advertising", "Creative / Design", "Editorial / Journalism", "Marketing / Public Relations", "Marketing - Direct Marketing"], "post_time": "2022-01-15T16:19:32Z", "salary": {"currency": "HKD", "max": 29999, "min": 14000, "period": "monthly", "term": null}, "salary_visible": true, "title_keywords": ["wealth management", "social media specialist"], "responsibilities": ["quality", "plan"], "requirements": {"degrees": [], "majors": [], "languages": ["cantonese", "english", "mandarin"], "language_level": ["good"], "hard_skills": [], "soft_skills": ["meet tight deadlines", "organizational", "interpersonal skill", "communication", "creative", "driven", "work under pressure"], "languages_combined": [{"language": "cantonese", "language_level": ["good"]}, {"language": "english", "language_level": ["good"]}, {"language": "mandarin", "language_level": ["good"]}]}, "experience_required": {"duration": ["at least 3-4 years"], "field": []}}, {"job_id": "100003009053143", "location_code": "hk", "company": "Omnicom Media Group", "job_title": "Account Manager (Content and Social)", "description": "This position is suitable for those who have experience in social media platforms management, including FB, IG, Youtube and Linkedin. Fresh graduates who are familiar with social trends will be considered.\n\nJob Nature:\u00a0\u00a0\n\nFully responsible for social media activities (e.g. FB, IG, Youtube, Linkedin), on content development and execution, data analysis, strategy for growth etc.\nCreate core content that fit the channel nature\nHandle multiple projects simultaneously and manage various accounts/ campaigns in a timely and professional manner\nAnalyze data and insights to guide strategy and implementation of solutions\nTo manage campaigns deliverables and coordinate with the internal parties to implement digital campaigns\n\nCharacters / Qualifications:\u00a0\n\nDegree holder, 1+ years experience in social media marketing field. Candidates with more than 3 years experience will be considered for manager title.\nExperience in business/ and finance platform management will be an advantage\nDigitally savvy with strong interest in social trends\nDerive strong satisfaction in creating high engagement and viral content that fit our brands\nCheerful and creative, with marketing sense and data driven mind\nStrong communication skills and ability to influence counterparts/stakeholders at various levels\nSelf-motivated showing strong sense of ownership and able to work under pressure\n\nWe offer competitive salary and benefits package (5 days work, 14 days AL up, birthday leave, medical & dental insurance) with great opportunity for career development to the successful candidate.\n\nPlease send your detailed resume and expected salary to us by clicking \"Apply Now\" (please put position applied on subject line)", "employment_types": ["Full Time", "Permanent"], "selling_points": ["Free Shuttle Bus & Free Breakfast", "Birthday, Family Day & Self-Love Day Leave", "5-Day Work Week"], "locations": ["Pok Fu Lam"], "categories": ["Media & Advertising", "Account Servicing", "Creative / Design", "Others"], "post_time": "2022-01-17T06:11:49Z", "salary": {"currency": null, "max": null, "min": null, "period": "monthly", "term": null}, "salary_visible": false, "title_keywords": ["account manager"], "responsibilities": ["social media", "management", "data", "social media platforms", "professional manner", "implementation", "coordinate with", "data analysis", "communication", "digital campaigns", "career development", "analyze data", "multiple projects", "insurance", "internal parties", "work under pressure"], "requirements": {"degrees": ["degree holder"], "majors": ["marketing"], "languages": [], "language_level": [], "hard_skills": ["analysis"], "soft_skills": ["communication skills", "self-motivated", "cheerful", "marketing sense", "responsible", "timely", "detailed", "creative", "driven", "work under pressure"], "languages_combined": []}, "experience_required": {"duration": ["3 years", "1+ years"], "field": ["social media", "management", "finance", "business", "marketing"]}}, {"job_id": "100003009052857", "location_code": "hk", "company": "Passionation (Hong Kong) Limited", "job_title": "Senior Editor (Lifestyle and Trending)", "description": "Primary Responsibilities\n\nIn charge of content development for a brand-new content platform, including articles, social media feeds, and video development, reaching agreed KPIs\nDrive, involve and participate in developing new content and programs that can build up the new platform\u2019s brand in the market\nLiaise with bloggers, influencers, guest editors, designers, and photographers for content development\nResearch topics, conduct interviews and content write up, especially on lifestyle and trendy topic\nRe-edit trendy topics and 3rd party contents for social usage\nAssist in daily channel content posting\nWork closely with local and regional team across departments\n\nSpecification and Requirement (Eligibility)\n\nBachelor's Degree and minimum 1 year of working experience in editorial. Fresh graduate will also be considered.\nGood knowledge in social media and story-telling skills\nExperience in fashion, beauty and lifestyle content is an advantage\nCreative and excellent digital and online knowledge\nAttentive to details and open minded\nGood communications skills in Cantonese, Mandarin, English and strong writing skills\u00a0", "employment_types": ["Full Time"], "selling_points": ["Min. 3 years of working experience in Editorial", "Experience in Fashion & Lifestyle content", "Good knowledge in social media and story-telling"], "locations": ["Quarry Bay"], "categories": ["Media & Advertising", "Creative / Design", "Editorial / Journalism", "Photography / Video"], "post_time": "2022-01-17T04:25:55Z", "salary": {"currency": null, "max": null, "min": null, "period": "monthly", "term": null}, "salary_visible": false, "title_keywords": ["senior editor"], "responsibilities": ["social media", "developing", "team across", "contents", "liaise with", "kpis"], "requirements": {"degrees": ["degree", "bachelor", "fresh graduate"], "majors": [], "languages": ["cantonese", "english", "mandarin"], "language_level": ["good"], "hard_skills": ["writing skills"], "soft_skills": ["creative", "open minded", "attentive to details", "writing skills"], "languages_combined": [{"language": "cantonese", "language_level": ["good"]}, {"language": "english", "language_level": ["good"]}, {"language": "mandarin", "language_level": ["good"]}]}, "experience_required": {"duration": ["minimum 1 year"], "field": ["editorial", "beauty"]}}, {"job_id": "100003009056562", "location_code": "hk", "company": "Plotio Financial Group Limited", "job_title": "Web Designer / UIUX Designer (5 Days Work)", "description": "We're looking for talents to join our a high-calibre creative team to create digital solution for our client.\n\nResponsibility:\n\n\nDevelop UI layout and interaction design for a variety of digital solutions\nTo create stunning design and forward-thinking user experience with analytically data and creative mindset.\nEffectively communicate research findings, conceptual ideas and detail design rationale both verbally and visually\n\nRequirements:\n\n\nExperienced in web design (PC & Mobile responsive) / mobile app design with a demonstrated portfolio\nConceptual thinking in both visual and interactive visual\nStrong communication skills to interface with clients and internal project team\nCreative, strong design sense, good responsibility, attention to details and good team player\nKnowledge of relevant industry tools specifically Adobe XD, Adobe Photoshop & Adobe Illustrator\nImmediate\u00a0available\u00a0is\u00a0highly\u00a0preferred\nDiploma, associate degree or bachelor\u2019s degree in related disciplines\nFresh graduates will also be considered\n\nWe offer\n\n\nHappy and dynamic working environment\nMedical Scheme\nBeing part of a young team striving for excellence\nOpportunities to participate in fun and exciting company events year-round\nComplimentary food and drinks in the workplace\nWork life balance\nBank holiday\nLife Insurance\nPerformance Bonus", "employment_types": ["Full Time"], "selling_points": ["Performance Bonus", "Medical Scheme", "Life Insurance"], "locations": ["Tsim Sha Tsui"], "categories": ["Media & Advertising", "Creative / Design"], "post_time": "2022-01-18T04:50:38Z", "salary": {"currency": null, "max": null, "min": null, "period": "monthly", "term": null}, "salary_visible": false, "title_keywords": ["designer"], "responsibilities": ["ideas", "data", "user experience", "design", "develop", "ui"], "requirements": {"degrees": ["associate degree", "diploma", "degree", "bachelor"], "majors": ["related disciplines"], "languages": [], "language_level": [], "hard_skills": ["web design", "adobe xd", "adobe photoshop", "adobe illustrator", "mobile", "pc"], "soft_skills": ["communication skills", "good team player", "attention to details", "creative", "responsive"], "languages_combined": []}, "experience_required": {"duration": [], "field": []}}, {"job_id": "100003009054242", "location_code": "hk", "company": "C-Mer Dennis Lam & Partners Eye Center", "job_title": "\u651d\u5f71\u53ca\u5f71\u7247\u526a\u63a5\u5e2b / Video producer / Videographer / Video Editor", "description": "\u00a0Job Highlights:\n\n\nPlanning\u00a0and\u00a0creating\u00a0content\u00a0of\u00a0video\u00a0projects,\u00a0like\u00a0post-treatment\u00a0experience\u00a0of\u00a0patients\u00a0and\u00a0KOLs,\u00a0introduction\u00a0of\u00a0clinical\u00a0service,\u00a0etc.\nResponsible\u00a0for\u00a0all\u00a0aspects\u00a0of\u00a0video\u00a0production\u00a0including\u00a0pre-production,\u00a0shooting,\u00a0editing,\u00a0subtitling\u00a0and\u00a0post-production\u00a0\nPublishing\u00a0in\u00a0various\u00a0channels\u00a0including\u00a0social\u00a0media,\u00a0website\u00a0and\u00a0internal\u00a0training\n\n\u00a0Job Duties:\n\nDevelop creative ideas and concepts with\u00a0marketing team members\nProduce diversified video content for multiple platforms including but not limited to social, print, corporate, and creative campaigns\nRecord, mix and post produce audio recordings\nSet and adjust the lighting during shooting\nInsert subtitles and aftereffects to the videos\nShoot and perform post-production of high quality, compelling content\nEnsure videos are well-edited, color / sound graded and produced according to brand guidelines\nAmend, revise or redevelop adverts or campaign videos in response to feedback from the marketing team and management\u00a0\nAd-hoc duties as assigned from time to time\n\n\u00a0Requirements:\n\nCertificate/Diploma/Degree holder in Film/ Creative Media/ Multimedia Design/ Motion Graphics/ Animation or related field\nMinimum 2 years of solid experience in video shooting, editing and production\nGood communication & interpersonal skills\n\u00a0Benefits:\n\nYoung and dynamic marketing team\n5-day work per week\nMedical insurance\nAnnual leave\nAnnual discretionary bonus\nSpecial offer of eye treatment for staff and family\n\n\u00a0Skills:\n\nAdobe Premiere / After Effects / Photoshop / Illustrator\n*Please provide your portfolio to demonstrate some work that you have done before*\n\n\n*Please include a recent photo and your expected salary in the CV for the application*\n\n\u8acb\u900f\u904e\"Apply Now\"\u905e\u4ea4\u5c65\u6b77\u3001\u4f5c\u54c1\u96c6\uff08\u6216\u9023\u7d50\uff09\u3001\u73fe\u6642\u53ca\u8981\u6c42\u7684\u85aa\u916c\u5f85\u9047\u7b49\u8cc7\u6599\u3002\n", "employment_types": ["Full Time", "Permanent"], "selling_points": ["Working location: Central", "Young and dynamic marketing team", "5-day work per week"], "locations": ["Central"], "categories": ["Media & Advertising", "Creative / Design", "Production", "Photography / Video"], "post_time": "2022-01-17T08:55:42Z", "salary": {"currency": null, "max": null, "min": null, "period": "monthly", "term": null}, "salary_visible": false, "title_keywords": ["videographer", "video producer", "video editor"], "responsibilities": ["management", "quality", "brand guidelines", "ad-hoc duties", "audio", "develop creative ideas"], "requirements": {"degrees": ["certificate", "diploma", "degree holder"], "majors": ["multimedia design", "creative media", "motion graphics", "animation"], "languages": [], "language_level": [], "hard_skills": ["graphics", "multimedia"], "soft_skills": ["communication", "creative", "interpersonal skills"], "languages_combined": []}, "experience_required": {"duration": ["minimum 2 years"], "field": ["editing", "video shooting"]}}, {"job_id": "100003009056594", "location_code": "hk", "company": "Social Big Data Limited", "job_title": "Creative Copywriter/ Strategist (Digital Marketing)", "description": "Job Responsibilities\n\nUnderstand clients\u2019 needs and deliver creative and innovative business solutions;\nSharp creative mind, collaborate with Account Management team to pitching/developing new ideas to clients\nIdentify market opportunities and potential strategic partnerships to capture new business and to expand market share\nContribute to the development of projects and responsible for researching, planning, executing, and preparing creative briefs in line with project needs & goals\nElevate the creative concept, design, and execution of various formats of contents\nAssist in developing overall corporate branding and marketing strategy\n\nJob Requirements\n\nBachelor\u2019s degree on Marketing, Multimedia,, Communications, or related disciplines;\nAt least 1 years\u2019 experience in digital marketing agency\nExcellent command in\u00a0Cantonese, English and Mandarin ;\nProficient in MS PowerPoint and Excel;\nMultimedia experience is preferred;\nExcellent communication and analytical skills;\nCorporately presentable and business savvy\nAble to work under pressure and tight deadlines;\nExcellent attention to detail, work independently, flexible and willing to learn;", "employment_types": ["Full Time"], "selling_points": ["Deliver innovative business solutions to clients", "Elevate creative concept, design, and execution", "Planning, executing, and preparing creative briefs"], "locations": ["Kwun Tong"], "categories": ["Media & Advertising", "Creative / Design", "Strategic Planning", "Marketing / Public Relations", "Digital Marketing"], "post_time": "2022-01-18T04:56:59Z", "salary": {"currency": null, "max": null, "min": null, "period": "monthly", "term": null}, "salary_visible": false, "title_keywords": ["creative copywriter", "digital marketing"], "responsibilities": ["collaborate with", "management team", "developing", "design", "developing new ideas", "executing", "contents", "planning"], "requirements": {"degrees": ["degree", "bachelor"], "majors": ["related disciplines", "marketing", "communications"], "languages": ["cantonese", "english", "mandarin"], "language_level": ["excellent"], "hard_skills": ["excel", "ms powerpoint", "multimedia", "analytical skills"], "soft_skills": ["flexible", "work independently", "willing to learn", "presentable", "communication", "analytical skills", "attention to detail", "work under pressure"], "languages_combined": [{"language": "cantonese", "language_level": ["excellent"]}, {"language": "english", "language_level": ["excellent"]}, {"language": "mandarin", "language_level": ["excellent"]}]}, "experience_required": {"duration": ["at least 1 years"], "field": ["agency", "digital marketing"]}}, {"job_id": "100003009052142", "location_code": "hk", "company": "eMotionLab Limited", "job_title": "Producer / Creative Assistant / Production Assistant", "description": "If you are a\u00a0Producer who aspire to plan, oversee and lead meaningful storytelling video projects from ideation to completion,\n\nWe should meet!\n\nWe are looking for high caliber talents to join our\u00a0growing team\u00a0\n... in our\u00a0new spacious office\n\u2026 and to chill out with us in our\u00a0amazing balcony!\n\nResponsibilities:\n\nTo manage and utilize resources effectively and keep track of multiple works and project status to ensure timely delivery\nTo carry out all duties in planning, coordination, organization and implementation of productions and projects\nTo develop excellent communication with all parties involved (the creative, production team & the client)\nTo coordinate on logistical arrangement for productions\n\nJob Requirements:\n\nSolid experience in video with vfx production\nUnderstanding of design, production, motion graphic and animation fundamentals\nWith active network in CG animation, motion graphic & multimedia production industry is an advantage, but not essential\nGood communication and interpersonal skills\nWell-organized, detail minded and able to work independently\nProficiency in English, Mandarin and Cantonese\nAble to work under pressure\nFresh graduates / candidate with less experience can be considered as creative assistant / production assistant\n\nInterested candidates please include your current and expected salary, website/ samples of your work in your application.\n\nPlease include\u00a0[Producer / Creative Assistant / Production Assistant]\u00a0in the subject line.\n\nPersonal data collected will be handled strict confidence for recruitment related purpose only.\n", "employment_types": ["Full Time"], "selling_points": ["Producer / Creative Assistant", "Aspire to innovate", "5 days work and dynamic working environment"], "locations": ["Wong Tai Sin Area"], "categories": ["Media & Advertising", "Creative / Design", "Design", "Multi-media"], "post_time": "2022-01-17T02:15:55Z", "salary": {"currency": null, "max": null, "min": null, "period": "monthly", "term": null}, "salary_visible": false, "title_keywords": ["producer", "production assistant", "creative", "assistant"], "responsibilities": ["implementation", "develop", "communication", "coordinate", "coordination", "planning"], "requirements": {"degrees": [], "majors": [], "languages": ["cantonese", "english", "mandarin"], "language_level": ["proficiency"], "hard_skills": ["cg", "multimedia"], "soft_skills": ["work independently", "creative", "well-organized", "communication and interpersonal skills", "active", "work under pressure"], "languages_combined": [{"language": "cantonese", "language_level": ["proficiency"]}, {"language": "english", "language_level": ["proficiency"]}, {"language": "mandarin", "language_level": ["proficiency"]}]}, "experience_required": {"duration": [], "field": ["video"]}}, {"job_id": "100003009055434", "location_code": "hk", "company": "Our Hong Kong Foundation Limited", "job_title": "Officer / Senior officer (Social Media)", "description": "Responsibilities:\n\nCreate quality and engaging social media contents for \u653f\u7b56\u2027\u6b63\u5bdfFacebook, YouTube and Instagram\nContribute creative ideas and conduct interviews for video projects\nCollaborate with videographers/editors in production\nAdministrate social media platforms\nDevelop, implement and evaluate digital marketing strategy\nMonitor the social media trend\n\nRequirements:\n\nDegree holder in Journalism, New media, Digital Marketing, Public Policy or relevant disciplines\nMinimum of 2 years of relevant experience\nStrong interest or knowledge in digital content marketing and public affairs\nRelevant media and digital agency experience is an advantage\nKnowledge of editing software and/or online marketing tools is an advantage\nAnchoring or program hosting experience is an advantage\nSelf-motivated and detail-oriented, able to work under pressure and juggle among tasks\nCandidates with more than 5 years' relevant experience will be considered as Senior Officer\nFresh graduates will be considered as Assistant Officer\n\nInterested parties please send:\n\nFull resume;\nCover letter;\nCopies of academic transcripts (including\u00a0public examination results if applicable);\nPresent and expected salary;\nAvailability\n\nBy clicking 'Apply Now' or by post to: Our Hong Kong Foundation Limited, 19/F, Nan Fung Tower, 88 Connaught Road Central, Hong Kong. Applicants who are not invited to an interview within two months from the date of this advertisement should consider their applications unsuccessful.\u00a0\n\nAll information provided by applicants will be handled with strictest confidence and will be solely used for the purpose of recruitment.", "employment_types": ["Full Time", "Permanent"], "selling_points": ["Create quality & engaging content for social media", "Familiar with social media platforms", "Growing platform with development opportunities"], "locations": ["Central & Western Area"], "categories": ["Media & Advertising", "Creative / Design", "Marketing / Public Relations", "Marketing - Marketing Communication", "Digital Marketing"], "post_time": "2022-01-18T02:34:47Z", "salary": {"currency": null, "max": null, "min": null, "period": "monthly", "term": null}, "salary_visible": false, "title_keywords": ["officer", "senior officer"], "responsibilities": ["collaborate with", "social media", "creative ideas", "social media platforms", "quality", "monitor", "develop", "evaluate", "digital marketing", "contents"], "requirements": {"degrees": ["degree holder"], "majors": ["journalism", "digital marketing", "public policy"], "languages": [], "language_level": [], "hard_skills": [], "soft_skills": ["work under pressure", "self-motivated", "detail-oriented"], "languages_combined": []}, "experience_required": {"duration": ["5 years", "minimum of 2 years"], "field": ["agency", "digital", "relevant experience", "media"]}}, {"job_id": "100003009056557", "location_code": "hk", "company": "Quality People Resources Limited", "job_title": "Temporary Project Assistant ($2,000 / day) (\u591a\u540d)", "description": "Responsibilities:\n\n\nTo participate in seasonal projects in HR Department\nTo assist in event and campaign planning in Marketing Department\nTo perform ad-hoc duties if required\n\n\nRequirements:\n\n\nDSE & Higher Diploma & University graduates in any disciplines, & no relevant working experience candidates are also welcomed\nGood work attitude and team players\nSelf-motivated and creative candidates\nStrong interpersonal skills and communication skills (Cantonese, English and Mandarin)\n\n\nWorking Day (Successful candidates will be assigned for only one of the following days):\n\n16th February, 2022 (Wed); or\n22nd February, 2022 (Tue); or\n23rd February, 2022 (Wed); or\n2nd March, 2022 (Wed); or\n8th March, 2022 (Tue); or\n18th March, 2022 (Fri); or\n25th March, 2022 (Fri)\n\n\nWorking Hours: 10:30am \u2013 6pm\nJob Salary: $2,000 / one day contract\n\nDirect employment, salary, MPF and contract will be paid and issued by Quality People Resources Limited.\n\nInterested parties, please submit your application by:\n\nClicking \u201cApply Now\u201d; or\nThrough \"Joboffer\" app; or\nWhatsApp 92886650 (https://wa.me/message/M24M4MRDAA34E1).", "employment_types": ["Full Time", "Part Time", "Permanent", "Temporary", "Contract", "Internship", "Freelance"], "selling_points": [], "locations": ["Yau Ma Tei"], "categories": ["Media & Advertising", "Creative / Design", "Editorial / Journalism", "Marketing / Public Relations", "Public Relations - Event Management"], "post_time": "2022-01-18T04:48:46Z", "salary": {"currency": "HKD", "max": 369, "min": 185, "period": "hourly", "term": null}, "salary_visible": true, "title_keywords": ["project assistant"], "responsibilities": ["hr", "ad-hoc duties", "planning"], "requirements": {"degrees": ["diploma", "dse"], "majors": ["any disciplines"], "languages": ["cantonese", "english", "mandarin"], "language_level": [], "hard_skills": ["no"], "soft_skills": ["communication skills", "self-motivated", "creative", "interpersonal skills"], "languages_combined": [{"language": "cantonese", "language_level": []}, {"language": "english", "language_level": []}, {"language": "mandarin", "language_level": []}]}, "experience_required": {"duration": [], "field": ["relevant working experience"]}}, {"job_id": "100003009048690", "location_code": "hk", "company": "North Viet Catering Group Limited", "job_title": "Graphic Designer", "description": "#\u975e\u4e00\u822c\u6253\u5de5\u65b9\u5f0f\n#\u597d\u73a9+\u6536\u5165\n\n\n\u00a0\u8aa0\u9080\u597d\u52d5\u5e74\u8f15\u4eba\u52a0\u5165\u00a0\n\n\u00a0Digital Marketing Specialist x Financial Planning 15K-30K\n\n\u73fe\u8aa0\u9080\u5f8c\u751f\u6709\u76f8\u95dc\u7d93\u9a57\u4eba\u58eb\u53c3\u8207\uff01\u597d\u73a9\u53ef\u767c\u5c55\uff01\n\n\u8b58\u5e73\u9762\u8a2d\u8a08\uff0c\u6709\u7ba1\u7406IG\u6216FB\u7d93\u9a57\u512a\u5148\n\n\u5de5\u4f5c\u7bc4\u7587\uff1a\n\n\u8ca0\u8cac Instagram Facebook\u00a0\u7db2\u7d61\u71df\u92b7\n\n\u5b9a\u671fUpdate\u53ca\u5206\u4eab\u5de5\u4f5c\u65e5\u5e38/\u7406\u8ca1\u6559\u5b78/\u8cc7\u8a0a\n\n\u984c\u6750\u4e3b\u8981\u4ee5\uff1a\u65e5\u5e38\u751f\u6d3b / \u6295\u8cc7 / \u7406\u8ca1\n\n\u4e00\u822c\u6587\u66f8\u8655\u7406\u5de5\u4f5c\n\n\u5b78\u7fd2\u7406\u8ca1\u7b56\u5283\u77e5\u8b58\uff0c\u5132\u84c4\u3001\u5f37\u7a4d\u91d1\u3001\u6295\u8cc7\u7b49\u91d1\u878d\u77e5\u8b58\n\n\u8207\u516c\u53f8\u4e0d\u540c\u5ba2\u6236\u806f\u7e6b\uff0c \u5354\u52a9\u88fd\u4f5c\u7db2\u7d61\u71df\u92b7\u76f8\u95dc\u7684\u7814\u7a76\uff0c\u63d0\u4f9b\u8ddf\u9032\u670d\u52d9\n\n\u798f\u5229\uff1a\n\n\u53e6\u4eab\u8c50\u539a\u4f63\u91d1\uff0c\u6bcf\u6708\u734e\u91d1\u53ca\u5e74\u5c3e\u82b1\u7d05\n\u5c08\u5c6c\u5168\u65b9\u4f4d\u6709\u6548\u57f9\u8a13\n\u5728\u8077\u92b7\u552e\u53ca\u7522\u54c1\u57f9\u8a13\n\u516c\u5e73\u6649\u5347\u5236\u5ea6\n\u89c0\u5858\u7532\u7d1a\u5546\u5834\u5beb\u5b57\u6a13\u5de5\u4f5c\n\u5730\u65b9\u5bec\u8eba\uff0c\u64c1\u6709\u8212\u9069\u4f11\u606f\u7a7a\u9593\n\u6642\u9593\u81ea\u4e3b\uff0c\u81ea\u6211\u5b89\u6392\u653e\u5047\u6642\u9593\uff0c\u4e0d\u8a2d\u5927\u5047\u65e5\u6578\n\u65c5\u884c\u734e\u8cde\uff0c\u5982\u9054\u6a19\u8005\u53ef\u4ee5\u4e00\u5e74\u53bb\u4e00\u6b21\u4e9e\u6d32\u8207\u6b50\u6d32\uff08\u6a5f\u7968\uff0b\u9152\u5e97)\u00a0\n\n\u8981\u6c42\uff1a\n\n\u4e2d\u5b78\u7562\u696d\u53ca\u4e94\u79d1\u5408\u683c\n\u6709\u826f\u597d\u7684\u4eba\u969b\u95dc\u4fc2\uff0c\u597d\u52d5\uff0c\u6709\u5275\u610f\n\u611b\u6e9d\u901a\uff0c\u4e3b\u52d5\uff0c\u6562\u65bc\u63a5\u53d7\u6311\u6230\n\u7d93\u9a57\u4e0d\u62d8\uff0c\u6b61\u8fce\u7562\u696d\u5927\u5b78\u751f\n\n*******\u6709\u610f\u8005\u8acb\u7acb\u523b\u9ede\u64caApply Now\u4ee5\u5b89\u6392\u9762\u8a66\u00a0**********", "employment_types": ["Full Time", "Permanent"], "selling_points": [], "locations": ["Chai Wan"], "categories": ["Media & Advertising", "Creative / Design", "Design", "Graphics", "Hospitality / F & B", "Food & Beverage"], "post_time": "2022-01-14T07:02:53Z", "salary": {"currency": null, "max": null, "min": null, "period": "monthly", "term": null}, "salary_visible": false, "title_keywords": ["graphic designer"], "responsibilities": ["facebook", "digital marketing", "planning"], "requirements": {"degrees": [], "majors": [], "languages": [], "language_level": [], "hard_skills": ["facebook"], "soft_skills": [], "languages_combined": []}, "experience_required": {"duration": [], "field": []}}, {"job_id": "100003009047548", "location_code": "hk", "company": "Online Marketing Genius Company Limited", "job_title": "Graphic Designer / Multimedia Designer", "description": "ABOUT THE ROLE\n\nThe role of Account Managers is to keep the customer \u2013 and the agency \u2014 satisfied. Your role will be to handle a handful of Social and marketing accounts and serve as the primary point of agency contact for clients. Your job is to communicate both good and bad news to a client with tact and aplomb, answer questions, and make certain they receive what they asked for as part of their agency contractual agreement.\n\nIt\u2019s a challenging role requiring a careful balance between the client\u2019s needs, wants and priorities, and the agency\u2019s bottom line. You will play a crucial role in client retention as well as potentially bringing in new business as part of an existing client referral process.\n\nAccount Manager must develop an understanding of:\n\nThe client\u2019s business model\nThe marketplace and factors affecting sales\nAdvertising techniques from creative, research and media outreach\n\nThe ideal Account Manager knows when to push and when to let things simmer.\u00a0The Account Manager\u2019s job duties include having a\u00a0strong but non-aggressive leadership style, as they ultimately control the agencies use of time and resources, and then present the product deliverables to the client satisfaction while maintaining agency\u2019s work integrity.\n\nJob Responsibilities:\n\nOverall management of the client relationship\nWork with project supervisors, content planners and creative team members to provide integrated solutions to client\u2019s marketing and media needs.\nManagement of the day-to-day client activities and delivery of work\nManagement of the strategic and longer-term planning of the overall client account\nDelivery of small and large creative campaigns\nWork closely with project managers to ensure your projects are suitably resourced\nOversee social profile management inc. calendars of activity and ensure that it remains aligned to the wider strategy\nEnsure that agency process in being followed\nEnsure excellence across all deliverables\nFinancial management and oversight of your account and projects\nThoroughly understands the development of advertising and is able to dig for more information.\nTo understand and participate in the creative process.\nTo manage financial process effectively and profitably.\nCommercial sense and sensitive to numbers and profitability\nand ROI for each project is highly essential.\n\nYou need to be:\n\nConfident and interested in all the areas laid out below:\n\nClient Account Management\nFinancial Management\nProject Management\nIndustry Knowledge and Expertise\nPlanning and Organization\nEffective Communication Skills\nAccountability\n\nJob Requirements:\n\nUniversity degree in business, marketing, advertising, communications, or a related field.\n3 to 4 years of 4As, digital agency, social media agency experience preferably.\nAbility to manage multi-task well in a fast-paced environment.\nAbility to develop strong relationship, both internally and externally, and feel comfortable interacting with people from different disciplines, countries and cultures.\nMust be well organized and have strong quantitative/analytical skills.\nMust be numerate and have strong attention to detail.\nInterest in learning new trends and developments in marketing, media, advertising and digital.\nImportantly, must be passionate about building a career in advertising, social and content field.\nOn trend with the latest popular culture both local and internationally.\nFluent written and spoken English and Chinese (Cantonese) is a must.\nProficiency in Word, Excel and PowerPoint.\nImmediate availability is preferred.\n\nWorking Location: Cyberport (\u6578\u78bc\u6e2f), Hong Kong\n\nWe offer a 5-day week of work, group medical & life insurance coverage, free shuttle bus to the right candidate. Interested parties please send your application letter and resume with current and expected salary by clicking the \u201cApply Now\u201d button.\n\nAll information collected will be used for recruitment only and treated in strict confidence. We will retain the personal data of unsuccessful applicants for future recruitment purpose for a maximum period of 2 years.", "employment_types": ["Full Time", "Permanent"], "selling_points": ["Highly creative, able to manage different styles", "5-day work, flexible working hour", "Medical benefit and year-end bonus"], "locations": ["Kwai Hing"], "categories": ["Media & Advertising", "Creative / Design", "Design", "Graphics", "Multi-media"], "post_time": "2022-01-14T03:26:25Z", "salary": {"currency": null, "max": null, "min": null, "period": "monthly", "term": null}, "salary_visible": false, "title_keywords": ["multimedia designer", "graphic designer"], "responsibilities": ["project management", "management", "advertising", "planning"], "requirements": {"degrees": ["university degree"], "majors": ["business", "communications", "marketing"], "languages": ["cantonese", "english", "chinese"], "language_level": ["fluent"], "hard_skills": ["excel", "word", "powerpoint", "analytical skills"], "soft_skills": ["communication skills", "multi-task", "accountability", "fast-paced environment", "well organized", "analytical skills", "learning", "attention to detail", "passionate about"], "languages_combined": [{"language": "cantonese", "language_level": ["fluent"]}, {"language": "english", "language_level": ["fluent"]}, {"language": "chinese", "language_level": ["fluent"]}]}, "experience_required": {"duration": ["3 to 4 years"], "field": ["agency", "digital", "social media agency"]}}, {"job_id": "100003009052758", "location_code": "hk", "company": "Verbatim (Hong Kong) Limited", "job_title": "Digital Marketing Executive ( 5 Days work )", "description": "Primary Responsibilities\n\nIn charge of content and business development for a brand-new content platform, including articles, social media feeds, and video development, reaching agreed KPIs\nDrive, involve and participate in developing new content and programs that can build up the new platform\u2019s brand in the market\nLiaise with bloggers, influencers, guest editors, designers, and photographers for content development\nResearch topics, conduct interview and content write up, especially on lifestyle and trending topic\nRe-edit trending topics and 3rd party content for social use\nAssist in daily channel content posting\nCoach juniors to deliver good quality content timely\nWork closely with local and regional team from different departments\n\nSpecification and Requirement (Eligibility)\n\nBachelor's Degree and minimum 3 years of working experience in editorial\nGood knowledge in social media and story-telling skills\nExperience in fashion, beauty and lifestyle content is an advantage\nCreative and excellent digital and online knowledge\nAttentive to details and open minded\nGood communications skills in Cantonese, Mandarin, English, and strong writing skills\u00a0", "employment_types": ["Full Time"], "selling_points": [], "locations": ["Tsim Sha Tsui"], "categories": ["Media & Advertising", "Creative / Design"], "post_time": "2022-01-17T03:57:27Z", "salary": {"currency": null, "max": null, "min": null, "period": "monthly", "term": null}, "salary_visible": false, "title_keywords": ["digital marketing executive"], "responsibilities": ["social media", "quality", "developing", "liaise with", "kpis"], "requirements": {"degrees": ["degree", "bachelor"], "majors": [], "languages": ["cantonese", "english", "mandarin"], "language_level": ["good"], "hard_skills": ["writing skills"], "soft_skills": ["creative", "open minded", "attentive to details", "writing skills"], "languages_combined": [{"language": "cantonese", "language_level": ["good"]}, {"language": "english", "language_level": ["good"]}, {"language": "mandarin", "language_level": ["good"]}]}, "experience_required": {"duration": ["minimum 3 years"], "field": ["editorial", "beauty"]}}, {"job_id": "100003009044084", "location_code": "hk", "company": "Zoo", "job_title": "Senior Art Director", "description": "Zeek is a smart logistics startup that provides diversified products including SaaS solutions, same day / instant delivery for food and parcel, meeting all kinds of logistics needs in the market. We are looking for talents to:\n\n\u00a0Responsibilities:\n\nReport to Marketing Director on Public Relations, Communication, Event and Press Release related matters, working with different target B2B(Business) / B2R(Rider) / B2C(Customer) segments and business product team;\nSupport global communications, market research and content creation;\nDevelop content framework and content calendar with Digital Marketing Manager;\nRoll out regional corporate communications, media relationship content creation and CSR initiatives in HQ and local markets ensure consistency;\nOversee all external and internal communication on our website, product description, sales kits, social media, app store, advertising;\nBuild and maintain relationships with key target media and manage crises and issues if needed. In a long run, we aim to achieve positive media coverage for Zeek in the region;\nWork closely with internal stakeholders and external partners to ensure communication channels are well deployed and monitored;\nEnsure accurate measurement and reporting of PR and content efforts to demonstrate how the effort ties back to the overall business and marketing goals.\u00a0\n\n\u00a0Requirements\n\nBachelor\u2019s degree in Marketing, Communications or Business Administration;\u00a0\nMinimum 5 years of experience in public relations, content development and / or related fields, preferably with both APAC regional and Hong Kong experiences;\nExperience in the Technology, Start-Up or Logistics industries will be an advantage;\nStrong network of media in Hong Kong, focusing. Candidate with knowledge and network in APAC is an advantage;\nStrong communicator with exceptional attention to detail, excellent written and verbal in English and Chinese. Mandarin Chinese or other Asian language is a plus;\nCandidates with less experience will be considered as\u00a0Marketing & Public Relations Manager", "employment_types": ["Full Time", "Permanent"], "selling_points": [], "locations": ["Kwun Tong"], "categories": ["Media & Advertising", "Creative / Design", "Design", "Others", "Marketing / Public Relations", "Digital Marketing"], "post_time": "2022-01-13T02:59:55Z", "salary": {"currency": null, "max": null, "min": null, "period": "monthly", "term": null}, "salary_visible": false, "title_keywords": ["senior art director"], "responsibilities": ["maintain relationships", "social media", "reporting", "advertising", "measurement", "market research", "website", "develop", "communication", "digital marketing", "report"], "requirements": {"degrees": ["degree", "bachelor"], "majors": ["marketing", "business administration", "communications"], "languages": ["mandarin chinese", "english", "chinese"], "language_level": ["excellent"], "hard_skills": ["plus"], "soft_skills": ["communicator", "attention to detail"], "languages_combined": [{"language": "mandarin chinese", "language_level": []}, {"language": "english", "language_level": ["excellent"]}, {"language": "chinese", "language_level": ["excellent"]}]}, "experience_required": {"duration": ["minimum 5 years"], "field": ["public relations", "content development", "related", "marketing", "logistics"]}}, {"job_id": "100003009050884", "location_code": "hk", "company": "Sun Cupid Technology (HK) Ltd", "job_title": "Web Design/Creative Director", "description": "If you are a\u00a0Motion Designer who aspire to give new meanings to what matters now with your visual stories,\nWe should meet!\n\nWe are looking for high caliber talents to join our growing team\u00a0\n... in our new spacious office\n\u2026 and to chill out with us in our amazing balcony!\n\nJob Responsibilities:\n\nMotion design and/or 2D&3D animation design developments and production\nParticipate in projects from conceptualisation to the finished products\n\nRequirements:\n\n2 - 5 years working experience in the industry\nFresh graduates and potential candidates will fewer experience will be considered as junior motion designer/animator\nExcellent sense in motion and strong animation skills\nProficient in Adobe AfterEffect, Photoshop, Illustrator & Editing Skills\nKnowledge in 2D and/or 3D animation, having both is an advantage.\nPassionate, Motivated and Proactive Working Attitude\nBe able to meet tight schedule\nPleasant and presentable, and enjoy working in a cozy and friendly environment\nInterested candidates please include your current and expected salary, website/ samples of your work in your application.\n\nPlease include [Senior/ Junior Motion Designer/ Animator] in the subject line.\n\nPersonal data collected will be handled strict confidence for recruitment related purpose only.", "employment_types": ["Full Time", "Permanent"], "selling_points": [], "locations": ["Lai Chi Kok"], "categories": ["Media & Advertising", "Creative / Design", "Marketing / Public Relations", "Marketing - Market Research", "Digital Marketing"], "post_time": "2022-01-14T11:38:57Z", "salary": {"currency": null, "max": null, "min": null, "period": "monthly", "term": null}, "salary_visible": false, "title_keywords": ["creative director"], "responsibilities": ["animation", "design"], "requirements": {"degrees": [], "majors": [], "languages": [], "language_level": [], "hard_skills": ["adobe", "illustrator", "photoshop"], "soft_skills": ["passionate", "enjoy working", "presentable", "pleasant", "motivated", "friendly", "proactive"], "languages_combined": []}, "experience_required": {"duration": ["2 - 5 years"], "field": ["designer"]}}, {"job_id": "100003009044056", "location_code": "hk", "company": "Goodbye Dear Company Limited", "job_title": "Creative Content Writer / Copywriter", "description": "Responsibilities\n\nDesign menu, promotion material, poster for both offline and online platform;\nProduce printing material & visual for outlets;\nProduct photo shooting & retouch for design works;\nPrepare artwork for IG & Facebook thread;\nAssist management to update company website, IG & Facebook of various brands;\nProvide support to distribute printing material;\nOccasionally outing may be required\nRequirements\n\nDiploma in graphic design or related disciplines\nMinimum 3 years relevant experience, solid experience in F&B industry is a must\nKnowledge in Web Site design & editing and Photography will be a definite advantage\nProficient in\u00a0Illustrator, Photoshop & MS Office is a must\nSelf-motivated, independent, well-organized and detail-minded\n\nWe offer\u00a0competitive\u00a0remuneration package for suitable candidates.\u00a0For interested parties, please click \"Apply Now\" to apply with your\u00a0resume\u00a0and\u00a0expected\u00a0salary.\u00a0\u00a0\n\nAll personal data collected will be used for recruitment purpose only and will be kept strictly confidential. Only short-listed candidates will be notified.", "employment_types": ["Full Time"], "selling_points": [], "locations": ["Kwun Tong"], "categories": ["Media & Advertising", "Creative / Design", "Marketing / Public Relations", "Marketing - Brand / Product Management", "Public Relations - Copy-writing"], "post_time": "2022-01-13T02:55:48Z", "salary": {"currency": null, "max": null, "min": null, "period": "monthly", "term": null}, "salary_visible": false, "title_keywords": ["copywriter", "content writer", "creative"], "responsibilities": ["management", "provide support", "product photo shooting", "design", "visual", "facebook", "company website"], "requirements": {"degrees": ["diploma"], "majors": ["related disciplines", "graphic design"], "languages": [], "language_level": [], "hard_skills": ["ms office", "illustrator", "web", "photoshop"], "soft_skills": ["detail-minded", "self-motivated", "independent", "well-organized"], "languages_combined": []}, "experience_required": {"duration": ["minimum 3 years"], "field": ["f&b", "relevant experience"]}}, {"job_id": "100003009051305", "location_code": "hk", "company": "Miramar Hotel and Investment Company, Limited", "job_title": "Senior Multimedia Designer / Multimedia Designer (social media focus)", "description": "Responsibilities\n\n\n\u00a0 Provide creative design and production supports\n\u00a0 Designing visuals for branding materials, online banners, packaging and other marketing materials, etc\n\u00a0 Handle ad hoc assignments as required\n\nRequirements\n\n\u00a0 Degree or diploma in design or related discipline\n\u00a0 Experience in Adobe AI and Photoshop\n\u00a0 Knowledge in photography and video editing will be advantage\n\u00a0 Self-motivated, creative and able to work independently\n\u00a0 Welcome students and fresh grad\n\u00a0 Immediate available would be in a high priority", "employment_types": ["Full Time", "Permanent"], "selling_points": [], "locations": ["Tsim Sha Tsui"], "categories": ["Media & Advertising", "Creative / Design", "Design", "Multi-media", "Photography / Video"], "post_time": "2022-01-15T07:54:02Z", "salary": {"currency": null, "max": null, "min": null, "period": "monthly", "term": null}, "salary_visible": false, "title_keywords": ["multimedia designer"], "responsibilities": ["design", "banners", "ad hoc assignments", "designing", "marketing materials"], "requirements": {"degrees": ["diploma", "degree"], "majors": ["design"], "languages": [], "language_level": [], "hard_skills": ["video editing", "adobe", "photoshop", "ai"], "soft_skills": ["self-motivated", "creative", "work independently"], "languages_combined": []}, "experience_required": {"duration": [], "field": []}}, {"job_id": "100003009054948", "location_code": "hk", "company": "Pearl Lam Galleries Limited", "job_title": "PR & Communications Executive / Manager", "description": "Job Duties:\n\n\nTo contribute creative ideas and innovative multimedia solutions, develop and produce e-learning packages, animated, audio and visual videos, interactive video games and animated PowerPoint presentation, etc.;\nTo write scripts, design and produce the department\u2019s training and presentation materials in diversified visual content including photo and video shooting, editing and retouching with a view to achieving better audio and visual appeal to audiences;\nTo handle graphic design and artwork output for departmental publications and e-cards, etc.\nEmployment Terms\n\n\nWork Hours: 8.8 hours a day between 0900 and 1800, Monday to Friday, off on Sat, Sun and Public Holidays\n\nSalary: HK$20,000 per month\nWork Location: Shamshuipo\n\nCandidates Requirement:\n\nHave bachelor degree/higher diploma in Creative Writing for Film, TV and New Media, or Creative/Digital Media, or Multimedia Technologies and Innovation or similar subjects from a local university/institute, or equivalent;\n\nLevel 3 or above in Chinese Language and English Language in HKDSE or HKCEE, or equivalent;\nProficient in scriptwriting, operating AV equipment and various computer software related to digital and image-sound media, photo and video editing and production including Windows 10, Microsoft Office 2016, Adobe Premier, Adobe Audition, Adobe After Effects, Adobe Illustrator, Adobe InDesign, Adobe Animate CC, Adobe Captivate 2019, Flash, Digital Animation and PhotoShop; and\nPossess some working experiences in scriptwriting and producing interactive video games and PowerPoint with audio and visual effects;\nHave at least one dose of Covid-19 vaccine.\nHow to Apply:\n\nInterested candidates please send in your CV (including all grades attained in public exam) stating clearly your academic qualifications with working experience, and earliest date available.\n\nPlease state ref no: JB-RVD-0117 as header in your application\n\nAll personal information collected will be solely for use in recruitment and will be kept in strict confidentiality\n\nWe apologize that only shortlisted candidates will be contacted for interviews", "employment_types": ["Full Time"], "selling_points": ["Young and good knowledge in social media platforms", "Excellent written English & Chinese", "Proficiency in Mac OS, MS Office, Adobe Pr/Ai/Ps"], "locations": ["Central & Western Area"], "categories": ["Media & Advertising", "Creative / Design", "Design", "Multi-media", "Marketing / Public Relations", "Marketing - General / Support"], "post_time": "2022-01-17T14:54:35Z", "salary": {"currency": null, "max": null, "min": null, "period": "monthly", "term": null}, "salary_visible": false, "title_keywords": ["executive", "manager"], "responsibilities": ["sat", "retouching", "creative ideas", "editing", "graphic design", "design", "develop", "video shooting", "visual", "audio", "artwork output"], "requirements": {"degrees": [], "majors": [], "languages": [], "language_level": [], "hard_skills": [], "soft_skills": [], "languages_combined": []}, "experience_required": {"duration": [], "field": []}}, {"job_id": "100003009044246", "location_code": "hk", "company": "Total Brand Activation Hong Kong Limited", "job_title": "Art Director (Job Ref. No: DES05)", "description": "Job Description\n\n\nCopywriting for NUU Mobile will lead the strategic storytelling responsibility in creating original, culturally vibrant, brand engagement: from top level campaign concepts, to arrange media advertising, and everything in between.\nPlay an instrumental role in shaping the expression of the NUU Mobile brand.\nBring ideas to life and convey our marketing messages to our target audiences.\nExecute and shepherd concepts from conception and executive buy-in through all stages of creative development, production and post-production\u2014ensuring faithful execution, quality, and brand consistency all the way.\nSeek to push the brand and our marketing practice into new media, experimenting, testing and tracking.\nQualifications\n\nDegree in Fine Arts, Communication Design, Advertising or equivalent practical experience.\n5+ years of writing and creative direction experience at a creative agency;\nExceptional conceptual and written storytelling talent;\nProven experience developing strategically grounded, creative ideas across digital and traditional media, for major consumer brands;\nA strong and diverse portfolio of original advertising and brand engagement work, including digital, video, and new media;\nExpert understanding of creative considerations across print, website, mobile, online advertising, social media, video, and so on;\nAbility to thoughtfully and persuasively articulate creative concepts to cross-functional teams;\nProficiency in creative and productivity applications: Photoshop, InDesign, Keynote/PowerPoint/Google Slides;\nExperience in technology, consumer technology or consumer lifestyle categories;\nTravelling is required and will stay in USA at least 6 months per year.", "employment_types": ["Full Time", "Permanent"], "selling_points": ["Strong creative vision", "Proficiency with design software", "Interest in social and cultural trends & fashions"], "locations": ["Not Specified"], "categories": ["Media & Advertising", "Creative / Design", "Design", "Multi-media", "Marketing / Public Relations", "Public Relations - Event Management"], "post_time": "2022-01-13T03:31:31Z", "salary": {"currency": null, "max": null, "min": null, "period": null, "term": null}, "salary_visible": false, "title_keywords": ["art director"], "responsibilities": ["social media", "creative ideas", "advertising", "ideas", "quality", "developing", "design", "testing", "communication", "website", "brand consistency", "online advertising", "cross-functional teams", "tracking"], "requirements": {"degrees": ["degree"], "majors": ["fine arts", "design"], "languages": [], "language_level": [], "hard_skills": ["mobile", "indesign", "powerpoint", "photoshop"], "soft_skills": ["communication", "diverse", "articulate", "creative", "instrumental"], "languages_combined": []}, "experience_required": {"duration": ["5+ years"], "field": ["advertising", "agency", "developing", "design", "writing", "digital", "media"]}}, {"job_id": "100003009043932", "location_code": "hk", "company": "Fimmick Limited", "job_title": "Senior Graphic Designer / Graphic Designer", "description": "The Job\n\nProvide\u00a0creative solutions and mockups that meet the brand standards by translating concepts into digital and/ or print formats\nCreate\u00a0graphics, animations, and special effects, as well as edit\u00a0graphic design, photos retouching, audio, and video using Adobe Creative Suite\nDraw\u00a0storyboards for advertisements, video games, FB, IG and website etc.\nDesign\u00a0and execute\u00a0all the assigned design tasks from research, concept generation, layout design and final artwork production in a wide range of media platforms\nWork\u00a0closely with the photographers and designers to brainstorm creative concepts. Liaise and follow up with marketing team to ensure the timely delivery\nThe Requirement\n\nHigher diploma or above in Graphic/Multimedia Design or related disciplines\n5 years or above experience in design/advertising agency and/or digital campaign\nExperience in\u00a0graphic, multimedia design, layout, typography, photo/video shooting and editing\nStrong understanding of latest design trends and digital optimization technology\nKnowledge on Adobe Creative Suite \u2013 includes Photoshop, Illustrator, Indesign, Flash, Dreamweaver and several other programs\u00a0\nGood team player, multi-tasking, willing to learn, open-minded, independent and responsible\nCandidate with less experience will be considered as Multimedia Designer\n\nAttractive remuneration would be offered to the right candidates.\nPlease send your application with portfolio and expected salary to\u00a0Human Resources Manager:\n\nBy WhatsApp: 6388-3034 or\nBy Fax: 2722-5555\n\nPersonal data collected will be used for recruitment purpose only.\u00a0 We are an equal opportunity employer.", "employment_types": ["Full Time", "Permanent"], "selling_points": ["Execute top-quality design", "2+ years interactive design experience", "Develop digital storyboards and animation"], "locations": ["Kwun Tong"], "categories": ["Media & Advertising", "Creative / Design", "Design", "Graphics", "Multi-media"], "post_time": "2022-01-13T02:30:11Z", "salary": {"currency": null, "max": null, "min": null, "period": "monthly", "term": null}, "salary_visible": false, "title_keywords": ["senior graphic designer", "graphic designer"], "responsibilities": ["graphics", "retouching", "liaise", "advertisements", "graphic design", "artwork production", "layout design", "website", "design", "animations", "audio", "storyboards"], "requirements": {"degrees": ["higher diploma or above"], "majors": ["multimedia design", "related disciplines"], "languages": [], "language_level": [], "hard_skills": ["indesign", "illustrator", "whatsapp", "multimedia", "flash", "dreamweaver", "adobe creative suite", "photoshop"], "soft_skills": ["good team player", "independent", "responsible", "open-minded", "willing to learn", "multi-tasking", "creative"], "languages_combined": []}, "experience_required": {"duration": ["5 years"], "field": ["photo", "designer", "design", "graphic", "video shooting", "advertising agency", "digital", "editing"]}}, {"job_id": "100003009042738", "location_code": "hk", "company": "Chan Tsang Wong Chu & Mee", "job_title": "Assistant Art Director", "description": "Position overview:\n\nThe role of Communications\u00a0Executive / Manager\u00a0will be responsible for\u00a0managing and updating all our social media channels, PR and providing assist to Website. \u00a0As an independent and pro-active problem solver, this person will help to build the company\u2019s brand image and awareness as well as to expand client base and sales.\n\nYou will also be involving in design / graphics of evite, e-catalogue, video and photo shooting of events and art fairs / exhibition co-ordination works.\n\nAs one of the world's leading\u00a0contemporary\u00a0art galleries located in Hong Kong's Central district, we look for a candidate with a pleasant demeanor, and is able to multi-task under pressure. \u00a0Passion and/or experience in art scene would be highly advantageous. \u00a0A detail-oriented, fast-paced individual would surely thrive in this cultural environment.\n\nOur gallery in Shanghai is looking for the same position also.\n\nWorking Days: Mon-Sat\n\nWorking Hours: 10:00-19:00 (with one hour lunch time)\n\nResponsibilities include:\n\nPlan and set up company pages within various internal and external social media channels to increase visibility of the company\u2019s social content, build brand awareness and customer loyalty.\nCreate original, creative and engaging content for all social media channels.\nPlan and arrange social media contents following gallery\u2019s exhibition schedule.\nPlan and organize social media marketing campaigns, online advertising and events for customer engagement, customer service initiatives and drive new customers.\nWork with external parties for joint different exhibition news and announcements, content distribution, influencer marketing, etc\u2026\nEdit videos and images for social media updates\n\nRequirement skills/attributes include:\n\n1\u00a0years\u2019 experience in-house and hands on social media planning, development and operation for worldwide markets, NO FRESH GRAD\nKnowledge of website update, social media platforms including Facebook, Twitter, Google+, Pinterest, Instagram, Youtube, LinkedIn, Weibo, Wechat & Renren\u2026 etc.\nCopywriting or editorial experience in online media, PR, social media is strongly preferred;\nExcellent in written English & Chinese (Traditional & Simplified Chinese)\nProficiency in Apple Mac, Word, Adobe Photoshop, Illustrator, Premier\nGood typing skills in English and Chinese - accuracy and presentation is required\nExcellent writing and communication skills\nHighly organized & efficient with an ability to work across an organization\nDress Code - BLACK\n\nPlease send your CV under\u00a0subject \u201cApplication to the post of Communications\u00a0Executive / Manager\u201d for interview arrangement.", "employment_types": ["Full Time"], "selling_points": [], "locations": ["Central"], "categories": ["Media & Advertising", "Creative / Design"], "post_time": "2022-01-12T08:35:34Z", "salary": {"currency": null, "max": null, "min": null, "period": "monthly", "term": null}, "salary_visible": false, "title_keywords": ["art director", "assistant"], "responsibilities": ["social media", "external parties", "edit videos", "contents", "customer service", "schedule", "marketing campaigns", "plan", "online advertising"], "requirements": {"degrees": [], "majors": [], "languages": ["english", "chinese"], "language_level": ["excellent", "good"], "hard_skills": ["no", "adobe photoshop", "word", "illustrator", "wechat", "typing", "code", "facebook"], "soft_skills": ["efficient", "organized", "communication skills", "hands on", "presentation"], "languages_combined": [{"language": "english", "language_level": ["excellent", "good"]}, {"language": "chinese", "language_level": ["excellent", "good"]}]}, "experience_required": {"duration": ["1 years"], "field": ["social media", "pr", "development", "editorial", "operation", "copywriting", "media", "planning"]}}, {"job_id": "100003009049329", "location_code": "hk", "company": "Phoenix Satellite Television Co Ltd", "job_title": "PRODUCER", "description": "CTWCM is a renowned advertising agency in Hong Kong and is now looking for high caliber talents to join us to cope with our expansion.\n\nPlease visit our website for more information- www.ctwcm.com\n\nAssistant Art Director\n\nJob Descriptions:\n\nWork closely with Creative team on advertising and creative projects\nAble to generate concept ideas for different types of clients\nFollow through projects from concept ideas, layout development to final production with support of the creative team\n\n\u00a0Requirements:\n\n1- 2 years experience in design/ advertising field\nDiploma or above in advertising, design institute or equivalent\nGood sense of art direction across different media including TV, print, outdoor and online channels\nSelf- motivated with strong creative sense\nAble to execute projects from ideas to finished products independently\nProficient in AI,\u00a0In-Design, Photoshop and other design softwares in Mac platform.\nFamiliar with ouput and print production\nFamiliar with video editing\nKnowledge in website/ digital development is a plus\nGood presentation, communication and negotiation skills\nPleasant personality, independent and willing to work overtime. Able to meet tight deadlines under pressure\n\nInterested parties please send your portfolio in PDF format or website link, resume, expected salary and availability\u00a0\n* Application without portfolio will not be considered.", "employment_types": ["Full Time", "Permanent"], "selling_points": [], "locations": ["Tai Po Area"], "categories": ["Media & Advertising", "Creative / Design", "Production", "Broadcasting - TV / Radio"], "post_time": "2022-01-14T08:28:20Z", "salary": {"currency": null, "max": null, "min": null, "period": null, "term": null}, "salary_visible": false, "title_keywords": ["producer"], "responsibilities": ["advertising", "ideas"], "requirements": {"degrees": ["diploma or above"], "majors": ["design"], "languages": [], "language_level": [], "hard_skills": ["plus", "design softwares", "ai", "video editing", "in-design", "photoshop"], "soft_skills": ["work overtime", "independently", "independent", "meet tight deadlines", "under pressure", "pleasant", "communication", "negotiation skills", "motivated", "creative", "presentation"], "languages_combined": []}, "experience_required": {"duration": ["1- 2 years"], "field": ["advertising", "design"]}}, {"job_id": "100003009047193", "location_code": "hk", "company": "Alges Asia Pacific Limited", "job_title": "Assistant Graphic Designer", "description": "Job Duties\n\n-\u00a0 \u00a0 \u00a0 \u00a0Responsible for graphic design and artwork production for printing, advertising & promotion purposes\n-\u00a0\u00a0\u00a0\u00a0\u00a0\u00a0 Support the sales / marketing team to develop graphic design in annual report, brochure, leaflet etc.\n-\u00a0\u00a0\u00a0\u00a0\u00a0\u00a0 Communicate with sales team and project management team in order to cope with design requirements of different jobs\n-\u00a0\u00a0\u00a0\u00a0\u00a0\u00a0 Provide useful and constructive proposal for company project design\n-\u00a0\u00a0\u00a0\u00a0\u00a0\u00a0 Ad-hoc duties when required\n\nJob requirement\n\n-\u00a0\u00a0\u00a0\u00a0\u00a0\u00a0 Diploma or above in Graphic Design or other related disciplines\n-\u00a0\u00a0\u00a0\u00a0\u00a0\u00a0 1-2 years relevant working experience; Candidate with less experience shall be considered for the junior positions; Fresh graduates will be considered as Trainee\n-\u00a0\u00a0\u00a0\u00a0\u00a0\u00a0 Proficiency in Design related software, such as Adobe InDesign, Illustrator and Photoshop, MS Office etc.\n-\u00a0\u00a0\u00a0\u00a0\u00a0\u00a0 Able to work independently, hardworking, creative, self-motivated and responsible\n-\u00a0\u00a0\u00a0\u00a0\u00a0\u00a0 Good organizational and interpersonal skills\n\nAttractive remuneration package will be offered to the right candidate. Interested parties, please send us your resume with current and expected salary (with reference number quoted)\u00a0by clicking \"APPLY NOW\".\n\nPersonal data collected would be used for recruitment purpose only.", "employment_types": ["Full Time"], "selling_points": [], "locations": ["Kowloon Bay"], "categories": ["Media & Advertising", "Creative / Design", "Design", "Graphics", "Building & Construction", "Building / Construction / QS"], "post_time": "2022-01-14T02:33:10Z", "salary": {"currency": null, "max": null, "min": null, "period": "monthly", "term": null}, "salary_visible": false, "title_keywords": ["assistant", "graphic designer"], "responsibilities": ["communicate with", "advertising", "graphic design", "artwork production", "leaflet", "design", "develop", "project management", "sales team", "ad-hoc duties", "report"], "requirements": {"degrees": ["diploma or above"], "majors": ["related disciplines", "graphic design"], "languages": [], "language_level": [], "hard_skills": ["ms office", "adobe indesign", "illustrator", "photoshop"], "soft_skills": ["work independently", "self-motivated", "responsible", "organizational", "interpersonal skills", "creative", "hardworking"], "languages_combined": []}, "experience_required": {"duration": ["1-2 years"], "field": ["relevant working experience"]}}, {"job_id": "100003009048927", "location_code": "hk", "company": "Eagle Sky Media Limited", "job_title": "Digital Marketing Officer (Advertising Agency , Digital Marketing, Social media)", "description": "Responsibilities:\n\nResponsible for the production of non-news programmes.\n\nRequirements:\n\n\nDegree/ Diploma holder in Journalism / Communication, with at least 4 years experience in TV production\nExperience in live variety show /outside broadcast /studio recording and filming are welcomed.\nKnowledge and experience in the field of digital media is a plus\nProficient in using Final Cut Pro, DaVinci, After effects and Photoshop\nCreative, presentable and good in communication.\nSelf-motivated and able to work independently under tight schedule.\nExcellent command of written and spoken English and Chinese, proficiency in Putonghua is a MUST.\nImmediate available is an advantage.\nCandidates with less experience will be considered for the post of Associate Producer.\n\nFor more details of our company, please visit our website at http://www.ifeng.com\n\nWe offer attractive remuneration package to the right candidate. Interested parties please click \u201cApply Now\u201d to submit applications or send applications with detailed resume stating career history, present & expected salary and date available to Human Resources Department, Phoenix Satellite Television Co. Ltd. via fax: 2200 8620.\n\n\u00a0Personal data collected will be used for recruitment purpose only. Applicants not hearing from us within 6 weeks may consider their applications unsuccessful and all related information will be destroyed after 6 months.", "employment_types": ["Full Time", "Permanent"], "selling_points": ["Socail media management", "Advertising Agency", "designer"], "locations": ["Tsuen Wan Area"], "categories": ["Media & Advertising", "Creative / Design", "Design", "Graphics", "Marketing / Public Relations", "Public Relations - Copy-writing"], "post_time": "2022-01-14T07:43:38Z", "salary": {"currency": null, "max": null, "min": null, "period": "monthly", "term": null}, "salary_visible": false, "title_keywords": ["digital marketing officer", "digital marketing"], "responsibilities": [], "requirements": {"degrees": ["diploma holder", "degree"], "majors": ["journalism"], "languages": ["putonghua", "english", "chinese"], "language_level": ["excellent", "proficiency"], "hard_skills": ["final cut pro", "after effects", "plus", "photoshop"], "soft_skills": ["self-motivated", "work independently", "presentable", "communication", "creative"], "languages_combined": [{"language": "putonghua", "language_level": ["proficiency", "excellent"]}, {"language": "english", "language_level": ["proficiency", "excellent"]}, {"language": "chinese", "language_level": ["proficiency", "excellent"]}]}, "experience_required": {"duration": ["at least 4 years"], "field": ["digital media", "tv production"]}}, {"job_id": "100003009050187", "location_code": "hk", "company": "PressLogic Limited", "job_title": "Video Editor / Cameraman", "description": "Responsibilities:\nSocial media management including content development & consumer engagement\nCommunicate and extent good relationships with on-line media, KOL, vendors & platform partners\nAnalyze market trends and explore new marketing techniques & business opportunities\nParticipate and support internal teams for different marketing campaign and operation needs\nPrepare marketing proposal for client\nPrepare regular reports for management review\nParticipate & support in all new business initiatives and all ad hoc projects\nGood content writer\nStrong Creative Designer is much preferred\n\nRequirements:\n\nDegree holder in Marketing / Communication / Multi-media Design preferred\nMin. 2 years\u2019 experienced in marketing\nExcellent interpersonal, presentation and communication skills\nProficient in MS Word, Excel, PowerPoint and Chinese Word Processing\nFluency in written and spoken Chinese and English\nExperience in CMS (Wordpress) ,graphic design tools (Adobe Photoshop and Adobe Illustrator)\nDetail-minded, tech-savvy, outgoing, and flexible to work\nHard-working, willing to learn and able to handle multi-task, work under pressure and meet deadlines\nCandidate with more experienced will be considered as Senior Marketing Executive", "employment_types": ["Full Time", "Permanent"], "selling_points": ["Birthday Leave & Anniversary Leave", "Shooting and video editing", "Minimum 3 years relative experience"], "locations": ["Lai Chi Kok"], "categories": ["Media & Advertising", "Creative / Design", "Production", "Photography / Video"], "post_time": "2022-01-14T09:55:03Z", "salary": {"currency": null, "max": null, "min": null, "period": "monthly", "term": null}, "salary_visible": false, "title_keywords": ["video editor"], "responsibilities": ["social media", "management", "business initiatives", "business opportunities", "review", "teams", "regular reports for management", "ad hoc projects"], "requirements": {"degrees": ["degree holder"], "majors": ["marketing", "design"], "languages": ["english", "chinese"], "language_level": ["fluency", "proficient"], "hard_skills": ["excel", "chinese word processing", "adobe photoshop", "powerpoint", "adobe illustrator", "wordpress", "ms word"], "soft_skills": ["detail-minded", "communication skills", "outgoing", "flexible", "multi-task", "willing to learn", "communication", "hard-working", "meet deadlines", "interpersonal", "presentation", "work under pressure"], "languages_combined": [{"language": "english", "language_level": ["fluency"]}, {"language": "chinese", "language_level": ["fluency", "proficient"]}]}, "experience_required": {"duration": [], "field": ["graphic design"]}}, {"job_id": "100003009053778", "location_code": "hk", "company": "eMotionLab Limited", "job_title": "Business Development Manager/ Executive", "description": "This position requires the ability to collaborate with the video producers and autonomously work on video content so that it is delivered in a timely manner. With a focus on Hong Kong, the video editor should also be conscious of PressLogic aesthetics/branding and past/current content outside of the local landscape.\n\nResponsibilities:\n\nResponsible for shooting and video editing\nSupport for maintaining steady flow of content\nHandle video editing and assisting in production\nCommunicating with other editors/ reporters in brainstorming and developing new ideas\nTo assist in ad hoc assignments and projects\n\nRequirements:\n\nMinimum 3 years relative experience\nExperience with lighting and shooting on DSLRs and other HD cameras\nProficient in video editing software, e.g. Final Cut Pro, AE, Premiere, Audition, Photoshop / Illustrator\u00a0\nLive broadcasting experience is a plus\nFamiliar with social media tools\u2019 (e.g. Instagram, Facebook) format and style is a plus\nMotion Graphic skills is a plus\nAbility to problem solve and multitask in a fast-paced environment\nCreative, independent, detail-minded and open to new idea\nA good team-player able to work independently under tight schedules\nGood command of both written and spoken English\nWe Offer:\n\n5 Days Work\nFlexible Working Hour\nBirthday Leave & Anniversary Leave\nMedical Coverage\nFun, Young and Joyful Office Environment\nInterested parties please send detailed resume with 1.) EXPECTED SALARY 2.) AVAILABILITY 3.) WORK REFERENCE to HR Department by clicking 'Apply Now'.\n\nFor company information, please refer to the website http://www.presslogic.com/.\n\nAll information received will be kept in strict confidence and only for employment-related purpose.", "employment_types": ["Full Time"], "selling_points": ["2 - 5 years agency experience", "Convenient Work location", "5 days work and dynamic working environment"], "locations": ["Wong Tai Sin Area"], "categories": ["Media & Advertising", "Account Servicing", "Creative / Design", "Sales, CS & Business Devpt", "Business Development"], "post_time": "2022-01-17T07:30:43Z", "salary": {"currency": null, "max": null, "min": null, "period": "monthly", "term": null}, "salary_visible": false, "title_keywords": ["business development manager", "executive"], "responsibilities": ["maintaining", "video editing", "developing new ideas", "communicating with", "ad hoc assignments"], "requirements": {"degrees": [], "majors": [], "languages": ["english"], "language_level": ["good command"], "hard_skills": ["final cut pro", "plus", "illustrator", "premiere", "video editing", "facebook", "photoshop"], "soft_skills": ["detail-minded", "work independently", "independent", "problem solve", "fast-paced environment", "team-player", "multitask", "creative"], "languages_combined": [{"language": "english", "language_level": ["good command"]}]}, "experience_required": {"duration": ["minimum 3 years"], "field": []}}, {"job_id": "100003009050080", "location_code": "hk", "company": "Stepworks Co Ltd", "job_title": "Web and graphic designer", "description": "We are looking for a high caliber\u00a0\n\nBusiness Development Manager/ Executive\n\nto join our growing team\u00a0\n... in our spacious office\n\u2026 and to chill out with us on our amazing balcony!\n\n\nResponsibilities\n\nIdentify strategies to target new & high value accounts\nPrepare and present impressive pitches to actively promote our services to existing clients and new customers\nTo build and develop lasting business relationships through trusted advisory role\nTo handle client and project management, inclusive of obtaining client's project requirement, design briefing and presentation, preparation of quotation and costing sheet, and to obtain contract confirmation\nRequirements\n\nUniversity graduate in advertising/ marketing/ communications or languages or related disciplines\n2 - 5 years agency experience\nA self-starter with excellent communication, presentation and negotiation skills\nTarget-oriented, aggressive, patient, self-motivated, mature, responsible, able to work as a good team player\nCreative, strong marketing sense, organized and responsible\nFluent in written and spoken English and Chinese is essential\nCandidates with less working experience will be considered as Business Development Executive\n\nInterested parties are invited to send us your full resume with current and expected salary in your application.\n\nPlease include [Business Development Manager/ Executive] in the subject line.\n\nPersonal data collected will be handled with strict confidence for recruitment related purposes only.", "employment_types": ["Full Time", "Permanent"], "selling_points": ["Over 5 years relevant experience", "Enjoy working in a team environment", "5-day work week"], "locations": ["Central"], "categories": ["Media & Advertising", "Creative / Design", "Design", "Graphics", "Web Designer"], "post_time": "2022-01-14T09:45:11Z", "salary": {"currency": null, "max": null, "min": null, "period": "monthly", "term": null}, "salary_visible": false, "title_keywords": ["graphic designer"], "responsibilities": ["project management", "quotation", "design", "develop"], "requirements": {"degrees": ["university graduate"], "majors": ["related disciplines", "marketing", "communications"], "languages": ["english", "chinese"], "language_level": ["fluent"], "hard_skills": [], "soft_skills": ["organized", "self-motivated", "good team player", "marketing sense", "responsible", "mature", "communication", "negotiation skills", "patient", "creative", "presentation"], "languages_combined": [{"language": "english", "language_level": ["fluent"]}, {"language": "chinese", "language_level": ["fluent"]}]}, "experience_required": {"duration": ["2 - 5 years"], "field": ["agency", "business development"]}}, {"job_id": "100003009046440", "location_code": "hk", "company": "PressLogic Limited", "job_title": "Graphic Designer", "description": "IMPORTANT PLEASE NOTE: We want to see your best work. For fast attention please link prominently to an online portfolio of no more than ten examples of your best work. Thanks :)\n\nWant a challenge creating outstanding brands and websites?\u00a0\n\nStepworks is a wholehearted independent branding firm, based in Hong Kong. Superb design underpins our work, which is enhanced by next level digital.\n\nWe have a strong track record helping organisations create positive change with our brand building skills, in HK and worldwide.\n\nOn our multicultural team you\u2019ll meet caring people who are really good at building brands that deliver valuable competitive advantages for our clients.\n\nMore on our wholehearted approach to brand building at www.stepworks.co\n\nResponsibilities\n\n\nWork on a range of creative brand building projects for respected organisations\nDesign websites underpinned by a good UX and UI foundation\u00a0\nExpress brand-led ideas using graphic and motion graphics\nProactively take responsibility of the quality of work under your care\nProduce deliverables on brief to a world-class standard with high degree of client satisfaction\nMaintain healthy working relationships\nUnderstand evolving industry best practices in digital, web and brand building\nCapabilities\u00a0\n\nOver 5 years relevant experience\nA strong sense of design aesthetics, artistic talent and creativity\nBe fluent and confident in English and Cantonese\nExpertise across the Adobe Creative SuiteExpertise across the Adobe Creative Suite, Figma or other web prototyping tools, and motion graphic software for web\nGood communication skills and superb organisation and time management skills\nBe experienced in production processes for digital and print\nOther creative skills like illustration, music/audio etc, will be considered a bonus\nEnjoy working in a team environment and be wholehearted\nRewards\n\nFlexible working arrangements\nCompetitive salary, profit sharing and opportunity for growth\nGreat culture working on projects that create positive change\nCaring team who look after each other\nTraining and support for your ambitions\u00a0\nA high credibility gig in your resume\nSounds good?\n\n\nEmail your portfolio, r\u00e9sum\u00e9 and expected salary. We\u2019ll treat it all in confidence.\n\nDon\u2019t forget to link to your portfolio!", "employment_types": ["Full Time", "Permanent"], "selling_points": ["Birthday Leave & Work Anniversary Leave", "Fun, young and joyful office environment", "Social Media Graphic Design - Branding Development"], "locations": ["Lai Chi Kok"], "categories": ["Media & Advertising", "Creative / Design", "Design", "Graphics", "Web Designer"], "post_time": "2022-01-13T11:11:32Z", "salary": {"currency": null, "max": null, "min": null, "period": "monthly", "term": null}, "salary_visible": false, "title_keywords": ["graphic designer"], "responsibilities": ["management", "ideas", "software", "quality", "motion graphic", "design", "communication", "motion graphics", "maintain", "working relationships", "audio", "ui"], "requirements": {"degrees": ["degree"], "majors": [], "languages": ["cantonese", "english"], "language_level": ["fluent"], "hard_skills": ["graphics", "no", "web", "adobe", "illustration", "adobe creative suite"], "soft_skills": ["confident", "communication skills", "flexible", "confidence", "independent", "time management skills", "enjoy working", "organisation", "creative", "positive", "world-class"], "languages_combined": [{"language": "cantonese", "language_level": ["fluent"]}, {"language": "english", "language_level": ["fluent"]}]}, "experience_required": {"duration": ["5 years"], "field": ["relevant experience"]}}, {"job_id": "100003009044441", "location_code": "hk", "company": "Oasis Brand Communications Company Limited", "job_title": "Designer", "description": "A well established International Sales company located in Tsim Sha Tsui East are seeking for a high caliber candidate to join our group.\n\nDigital Marketing Executive ( 5 Days work )\n\n\nResponsibilities:\n\n\nDevelop content strategy across all platforms including website and social media\nRegularly create and schedule posts and advertisements on Social Media platforms\nHandle customers enquiries on the social media platforms\nPerform copy-writing, editing and proofreading for digital and print materials\nPlan and execute online advertising and re-targeting channels such as SEM, Facebook, Instagram, etc.\nCreate and design content in forms of videos, photos and other multimedia formats and to be used on social media platforms including Facebook, Instagram and Website etc.\nPromote successful purchase through Search Engine Optimization, Search Engine Marketing, Social Media Marketing\nSophisticated in Google Ads, Facebook ads, YouTube ads spending, etc.\u2026\nAssist in building up new online store and manage daily operation\nPlanning for seasonal and thematic promotion activities\nAssist in preparing marcom support for effective execution of corporate brand image, e.g. materials translation, POP and merchandising, advertising visuals, marketing support in the exhibition and roadshow\n\nRequirements:\n\n\nHigher Diploma or above in Marketing, Digital Media, Advertising or related disciplines\nStrong and passionate in digital marketing and social media management\nMinimum 3 years relevant experience in digital marketing, social media, or other marketing related fields\nHands-on knowledge of managing social media platforms like Facebook, Instagram\nExperience in setting up and managing online shops is a plus\nExperience or have knowledge in Google Analytics, SEO & SEM is definitely an advantage\nCapable of using Adobe Illustrator, Photoshop and Video Editing softwares\nComputer proficiency in Microsoft Office, Word, Excel and PowerPoint is essential\nGood command of English, Chinese and Mandarin\nGood interpersonal and analytical skills, self-motivated, organized and detail-minded\n\n\u00a0Remuneration:\u00a0\n\nSalary : Negotiation\nPlease state your expected salary on your application letter\nInterest parties please send email for enquiry of application\n", "employment_types": ["Full Time"], "selling_points": ["all-rounded design knowledge", "fresh graduate will be considered", "willing to work overnight & holiday"], "locations": ["Kwun Tong"], "categories": ["Media & Advertising", "Creative / Design", "Design", "Graphics", "Others"], "post_time": "2022-01-13T04:04:50Z", "salary": {"currency": null, "max": null, "min": null, "period": "monthly", "term": null}, "salary_visible": false, "title_keywords": ["designer"], "responsibilities": ["social media", "advertising", "advertisements", "social media platforms", "daily operation", "website", "merchandising", "develop", "purchase", "proofreading", "schedule", "plan", "sem", "facebook", "editing", "online advertising", "design content", "planning"], "requirements": {"degrees": ["higher diploma or above"], "majors": ["related disciplines", "marketing"], "languages": ["english", "chinese", "mandarin"], "language_level": ["good command"], "hard_skills": ["google analytics", "plus", "excel", "seo", "microsoft office", "word", "powerpoint", "adobe illustrator", "video editing", "analytical skills", "sem", "facebook", "photoshop"], "soft_skills": ["passionate", "organized", "self-motivated", "detail-minded", "capable", "negotiation", "analytical skills", "hands-on", "interpersonal"], "languages_combined": [{"language": "english", "language_level": ["good command"]}, {"language": "chinese", "language_level": ["good command"]}, {"language": "mandarin", "language_level": ["good command"]}]}, "experience_required": {"duration": ["minimum 3 years"], "field": ["social media", "related", "marketing", "relevant experience", "digital marketing"]}}, {"job_id": "100003009049628", "location_code": "hk", "company": "TecPal Limited", "job_title": "UX / UI Designer", "description": "Responsibilities:\n\nCreate optimized social media graphic design for branding development and daily content in different topic\nResponsible for concept development, visualization and hands on design for key visual, social media posts and promotion collateral, etc\nWork closely with editorial team to ensure concept's achievability and present accurately\u00a0\nAdjust and revise on project goals and design style accordingly as required from time to time\nFollow through project from concept development, executing layouts, artwork design independently\nStaying abreast of current marketing trends among digital, social media platform to develop a cutting edge among the advertisement industry\nSupport any ad-hoc job tasks assigned, including but not limited to client ad related tasks\n\nRequirements:\n\nDegree in multimedia design / graphic design or other relative disciplines\nAt least 3 years of experience in marketing design\nExperience in create optimized social media design is preferred\nFamiliar with social media operations is preferred\nGood verbal and written communications in English and Chinese\nCapable of drawing storyboards\u00a0\nWith website design experience is a plus\nAdvance users of Photoshop, illustrator, and video editing tools\nStrong sense in aesthetics design\n\nWe Offer:\n\n5 Days work\nFlexible Working Hour\nBirthday Leave & Work Anniversary Leave\u00a0\nMedical Coverage\nFun, young and joyful office environment\u00a0\n\nInterested candidates, please email full resume with 1.) EXPECTED SALARY 2.) AVAILABILITY 3.)\u00a0WORK REFERENCE\u00a0 to the HR department by clicking 'Apply Now'.\n\nFor company information, please refer to the website http://www.presslogic.com/.\n\nAll information received will be kept in strict confidence and only for employment-related purposes.", "employment_types": ["Full Time"], "selling_points": ["Multicultural Workplace", "15-day Annual Leave", "Excellent Career Development"], "locations": ["Hung Hom"], "categories": ["Media & Advertising", "Creative / Design", "Design", "Web Designer", "Information Technology (IT)", "UI/UX Designer"], "post_time": "2022-01-14T08:59:43Z", "salary": {"currency": null, "max": null, "min": null, "period": "monthly", "term": null}, "salary_visible": false, "title_keywords": ["ui designer"], "responsibilities": ["ad-hoc", "social media", "visualization", "graphic design", "design", "develop", "executing", "visual"], "requirements": {"degrees": ["degree"], "majors": ["multimedia design", "graphic design"], "languages": ["english", "chinese"], "language_level": ["good"], "hard_skills": ["plus", "illustrator", "video editing", "multimedia", "photoshop"], "soft_skills": ["capable"], "languages_combined": [{"language": "english", "language_level": ["good"]}, {"language": "chinese", "language_level": ["good"]}]}, "experience_required": {"duration": ["at least 3 years"], "field": ["social media", "marketing", "design"]}}, {"job_id": "100003009048955", "location_code": "hk", "company": "M plus design & architecture consultancy (HongKong) limited", "job_title": "Advanced 3D Designer", "description": "Job Responsibilities\n\nDevelop creative content strategy to meet client's marketing needs;\nCreate contents on digital platforms, including Facebook, Instagram, Weibo etc.;\nTo ensure all copy and information is accurate and meets commercial standard;\nResearch online behaviours and trends of the target audience\nMonitor and report SEO performance and metrics, using web analytics tools and dashboards\nKeeping updated with industry trends\nSupport the Business Manager on strategic projects as assigned\n\nJob Requirements:\n\nMinimum 1 years copywriting experience in writing;\nAble to write excellent and stylish Cantonese;\nCreative, willing to learn, self-initiative & motivated, responsible, supportive and able to work under pressure, independently and over time;\nGood team player with excellent interpersonal and communication skills\nStay updated on creative trends *Immediate availability is preferred", "employment_types": ["Full Time", "Permanent", "Contract"], "selling_points": ["Retail Experiential Design (VM, Pop Up etc) Exp", "Strong in 3D Max-V-Ray, AutoCAD, PS", "Creative Thinking and Design Sense"], "locations": ["Central"], "categories": ["Media & Advertising", "Creative / Design", "Design", "Interior", "Visual Merchandising"], "post_time": "2022-01-14T07:47:32Z", "salary": {"currency": "HKD", "max": 24999, "min": 20000, "period": "monthly", "term": null}, "salary_visible": true, "title_keywords": ["designer"], "responsibilities": ["analytics tools", "seo", "creative content", "monitor", "develop", "contents", "facebook", "report"], "requirements": {"degrees": [], "majors": [], "languages": ["cantonese"], "language_level": ["excellent"], "hard_skills": [], "soft_skills": ["communication skills", "supportive", "independently", "good team player", "responsible", "willing to learn", "motivated", "self-initiative", "creative", "interpersonal", "work under pressure"], "languages_combined": [{"language": "cantonese", "language_level": ["excellent"]}]}, "experience_required": {"duration": ["minimum 1 years"], "field": ["copywriting", "writing"]}}, {"job_id": "100003009034637", "location_code": "hk", "company": "Frengers Communications Limited", "job_title": "(not just an) Assistant Art Director / Art Director / Senior Art Director", "description": "Benefits:\n\n5 days Work + Bank Holidays\nFull Medical Coverage\nPerformance Bonus\nBirthday Leave, Wedding Leave\nTraining Subsidy\nOvertime Meal and Transportation allowance\nProfessional Training + Good Career Prospect in the Growing Digital Marketing Industry\n\nResponsibilities include:\n\nResponsible for artworks and design for digital marketing including banner display, video, campaign and website;\nInvolve in pitching for new projects;\nWorking with our online marketing team, implement and roll out online marketing strategy with the use of Facebook and other social media platforms.\n\nRequirements :\n\nHigher diploma or above in Graphic/ Multimedia Design or related disciplines;\nPossessing 2 years of working experience in Graphic Design, Advertising or Website Design ; experience in digital marketing agencies is preferred.\nPossessing experience in pitching;\nUnderstanding on branding / art direction is a plus;\nGood team player with effective interpersonal and communication skills;\nAble to work with tight deadlines and under pressure;\nInternet savvy, keen interest in internet marketing and social media.\nCandidate with more experience may be considered for Senior role.\n\nTo Apply:\n\nFor more information about You Find Ltd., please visit www.youfind.hk.\nWe offer attractive package to the right candidate. Interested parties please send your application together with Current Salary, Expected Salary & Availability by clicking \"Apply Now\".\nAll information received will be used for recruitment purpose only and will be kept in strict confidential.\n\nYouFind is an Equal Opportunity Employer and prohibits discrimination and harassment of any kind. All employment decisions at YouFind are based on business needs, job requirements and individual qualifications, without regard to race; family status; gender; disability status or any other status protected by the laws or regulations in Hong Kong.", "employment_types": ["Full Time"], "selling_points": [], "locations": ["Kwun Tong"], "categories": ["Media & Advertising", "Creative / Design", "Others", "Design", "Graphics"], "post_time": "2022-01-10T03:50:54Z", "salary": {"currency": null, "max": null, "min": null, "period": "monthly", "term": null}, "salary_visible": false, "title_keywords": ["art director", "senior art director", "assistant"], "responsibilities": [], "requirements": {"degrees": [], "majors": [], "languages": [], "language_level": [], "hard_skills": [], "soft_skills": [], "languages_combined": []}, "experience_required": {"duration": [], "field": []}}, {"job_id": "100003009049007", "location_code": "hk", "company": "M plus design & architecture consultancy (HongKong) limited", "job_title": "Senior 3D Designer", "description": "Responsibilities:\n\n\nCreate innovative user experiences and user interfaces for mobile apps and smart home devices\nIntegrate design features, wireframes, sketches, flow diagrams, style guides and user research into the product development process\nCollaborate with product development and engineering team\nStay up-to-date with the latest UX/UI design trends, tools, best practices\nRequirements:\n\nDiploma or above in Visual Design, interactive Design or similar disciplines\nMore than 3 years of related work experience\nGood knowledge of UX design techniques\nProficiency in Sketch and/or Adobe CS\nGood command in written and spoken English\nSelf-starter, independent and well-organized\nCome and join us in a multi-cultural, dynamic and stable work environment, experience the opportunity to develop your career and to work in different exciting projects in an nicely decorated office.\n\nWe are an Equal Opportunity Employer. Interested parties, please send us your job application, the position you apply, together with Current and Expected Salary. We look forward to your application.", "employment_types": ["Full Time", "Permanent", "Contract"], "selling_points": ["Retail Experiential Design (VM, Pop Up etc) Exp", "Strong in 3D Max-V-Ray, AutoCAD, PS", "Creative Thinking and Design Sense"], "locations": ["Central"], "categories": ["Media & Advertising", "Creative / Design", "Design", "Interior", "Visual Merchandising"], "post_time": "2022-01-14T07:54:20Z", "salary": {"currency": "HKD", "max": 34999, "min": 30000, "period": "monthly", "term": null}, "salary_visible": true, "title_keywords": ["senior 3d designer"], "responsibilities": ["collaborate with", "sketches", "design", "design trends", "ui"], "requirements": {"degrees": ["diploma or above"], "majors": ["design"], "languages": ["english"], "language_level": ["good command"], "hard_skills": ["visual design", "adobe cs"], "soft_skills": ["independent", "well-organized"], "languages_combined": [{"language": "english", "language_level": ["good command"]}]}, "experience_required": {"duration": ["3 years"], "field": ["related"]}}, {"job_id": "100003009046347", "location_code": "hk", "company": "H&W Technology Service Limited", "job_title": "Digital Marketing Specialist (Social Media/ FSI/ Fintech)", "description": "TBA Hong Kong is driven by innovation and design. We\u2019re searching for an experienced art director to work with our Creative Directors to conceptualize experiential and through-the-line campaigns, apply expert art direction to the visual elements of creative projects, and inspire the agency\u2019s clients to be creatively progressive, through the application of fresh and inventive visual work.\n\nThe ideal art director will bring a mix of artistic, marketing, and business expertise to the position, promoting our company and that of our valued clients. We are looking for an experienced manager, who can inspire and be inspired by others to take our creative efforts to the next level. The ideal candidate will have a natural eye for design and a passion for delivering dynamic ideas that connect with any audience.\n\nDuties and Responsibilities:\n\nWorking from a brief to generate ideas to present to the client\nWork with the entire creative team to establish a unified brand understanding and voice for the company, helming a creative audit to elevate our innovation\nConceptualize campaign vision, harnessing original graphics, copy, content websites, social media, and other marketing materials\nWorking with specialists, such as video editors, 3D designers and photographers, to work on projects\nSupervise and mentor a team of graphic designers\nPresenting final layouts, storyboards, and illustrations, encouraging members to provide feedback, and responding to internal commentary and requests\nPresent to clients or oversee presentation of final concepts and coordinate production and dissemination for cross-organizational use\nAble to work on several projects at one time\n\nThe Person:\n\nHonest, open and not afraid to speak openly about their thoughts and ideas\nBachelor\u2019s degree in fine art, graphic design, or similar discipline\nAt least 3 years experience as an art director or designer within an agency is desired, with a strong desire to deliver \u2018best in class\u2019 creative work and be a creative leader.\nProficiency with design software, such as Adobe Creative Suite\nA strong command of branding principles, experiential design, consumer engagement and digital media, and an understanding of how they need to work together in developing on-brand, on-target solutions.\nExceptional capability with typography, layout, and prototyping\nWeb development and/or mobile development experience\nExperience with photography and video production and editing\nHave excellent interpersonal and communication skills and work well in a team.\nStrong creative vision with an understanding of business objectives\nhave an interest in social and cultural trends and fashions.\nhave a good understanding of exhibition, events, and digital campaigns.\nAbility to present and sell ideas effectively, and communicate our expertise and work both internally and externally.\nIf this sounds like you, then click\u00a0\"Apply Now\"\u00a0or\u00a0send us email\u00a0to forward your full resume with current & expected salary and job reference number to join us.\n\nAll personal data provided by job applicants will be used strictly in accordance with Company\u2019s personal data policies, a copy of which will be provided upon request.", "employment_types": ["Full Time", "Permanent"], "selling_points": ["2yrs+ exp. in digital / content marketing", "Exp. in Financial field &/ global market preferred", "Knowledge in social media & website content"], "locations": ["Hung Hom"], "categories": ["Media & Advertising", "Creative / Design", "Marketing / Public Relations", "Public Relations - Copy-writing", "Digital Marketing"], "post_time": "2022-01-13T10:37:58Z", "salary": {"currency": null, "max": null, "min": null, "period": "monthly", "term": null}, "salary_visible": false, "title_keywords": ["digital marketing specialist"], "responsibilities": ["graphics", "social media", "ideas", "audit", "coordinate", "marketing materials", "storyboards"], "requirements": {"degrees": ["degree", "bachelor"], "majors": ["graphic design", "fine art"], "languages": [], "language_level": [], "hard_skills": ["mobile", "web development", "adobe creative suite"], "soft_skills": ["communication skills", "creative", "interpersonal", "honest"], "languages_combined": []}, "experience_required": {"duration": ["at least 3 years"], "field": ["art director", "designer", "agency", "development", "video production", "editing"]}}, {"job_id": "100003009047519", "location_code": "hk", "company": "HKBN Enterprise Solutions HK Limited", "job_title": "Senior Officer - Marketing Communications (Copywriting)", "description": "Job Responsibilities:\n\nWork closely with other department to execute the creative strategy in Brand Experience and new pitch projects\nExecute top-quality design from concept to delivery complying with brand standards in execution of marketing materials\nDevelop digital storyboards and animation as demanded\nIntegrate visually and enhance creative concept, architecture, UI and navigation design for web sites, online advertising and mobile\n\nRequirements:\n\nHigher Diploma holder preferably in Art, Design, Digital or related disciplines\n2+ years graphic design experience, strong creative portfolio in design, motion graphics and video in brand experience\nExperience in effective strategic brainstorming, campaign design and development\nHigh Proficiency in Photoshop, Illustrator and After Effect etc.\nKnowledge in 2D animation & Final Cut Pro is a plus\nPassion for new technologies and emerging trends\nGood communication skill\n\nBenefits:\n\nStaff Training\nFive-day work per week\nTeam Building Activities\nBirthday Leave, General Holiday and Medical Allowance\n\nWe offer attractive remuneration package, commensurate with candidates\u2019 qualification and experience. Interested parties, please send your application letter, detailed CV including date of availability and current and expected salary by clicking \"APPLY NOW\". Only short-listed candidates will be notified for an interview All information received will be kept in STRICT CONFIDENCE and only for employment related purpose.\n\nFor more information about Fimmick, please visit our website www.fimmick.com.", "employment_types": ["Full Time", "Permanent"], "selling_points": ["Experienced in creating content for various media", "Excellent in Chinese & English content writing", "Talent-first culture & Life-Work Priority"], "locations": ["Kowloon Bay"], "categories": ["Media & Advertising", "Creative / Design", "Marketing / Public Relations", "Marketing - Marketing Communication", "Public Relations - Copy-writing"], "post_time": "2022-01-14T03:22:04Z", "salary": {"currency": null, "max": null, "min": null, "period": "monthly", "term": null}, "salary_visible": false, "title_keywords": ["senior officer"], "responsibilities": ["enhance creative concept", "from concept to delivery", "online advertising", "web sites", "develop digital storyboards", "ui and navigation design", "architecture", "execution of marketing materials", "top-quality design", "animation"], "requirements": {"degrees": ["higher diploma holder"], "majors": ["related disciplines", "art", "design"], "languages": [], "language_level": [], "hard_skills": ["graphics", "final cut pro", "plus", "illustrator", "after effect", "photoshop"], "soft_skills": ["communication skill", "creative", "passion for"], "languages_combined": []}, "experience_required": {"duration": ["2+ years"], "field": ["video", "brand", "graphic design", "development", "design"]}}, {"job_id": "100003009043473", "location_code": "hk", "company": "New Page Communications Ltd", "job_title": "Junior Motion Graphic Designer", "description": "We are currently seeking a specialist to join our creative team in HK.\u00a0 This opening offer an opportunity to work with well-known international brands and their professional team.\u00a0\n\nJob Duties:\n\nStrengthen the current creative offering in the areas of high-end/fine retail experiential\u00a0related industries.\u00a0\nTake creative lead on projects being involved at pitch stage and generally offering original, creative and effective design solutions.\nWork on projects from concept right the way through to finished product.\nYou will be comfortable driving creative pitch work, individually or by working with.\u00a0\u00a0\n\nRequirements:\n\nMinimum 2 years\u00a0Retail Experiential Design experience, solid experience in Cosmetics industry with Pop Up Event / Store Design / VM Design is more appreciated.\u00a0\nDiploma or Degree in Interior Design or any other equivalent.\nGood understanding of consumer behaviour and latest market trend.\nAble to develop strategic and conceptual ideas for innovative retail solutions.\nHave a strong creative background and a good eye for detail.\u00a0\nStrong problem solving and analytical ability, with teamwork spirit.\nGood time management skill, able to catch-up deadline.\u00a0\nGood overall project process knowledge, as factory visit is required.\nSoftware Requirement: 3DMAX (V-Ray), AutoCAD and Photoshop is a must.\nGood hand sketch ability is appreciated.\u00a0 \u00a0\nKey elements to join our TEAM:\n\nBe responsible\nBe positive\nBe open-minded\nGood Language skills (English, Mandarin)\nGood Team Player\nWilling to work overtime\n\nWe OFFER:\n\nFive Day Work Week\nYear End Performance Bonus\nMedical Insurance\nEducational Allowance\nSeniority Allowance\nCoaching and Training\nBirthday Allowance\nQuarterly Team Building\nActivity Overtime Allowance\n\nAction NOW:\n\nThis is an exciting opportunity for you to join our creative team that are passionate and committed to everything in retail design and brand experience!\u00a0 DON\u2019T HESITATE!!\u00a0\u00a0If you are passion to develop your career, please send your PORTFOLIO and CV to us.\u00a0 A step further to your success. Make sure you mark the current / expected salary and date of available in your CV.\n\nPersonal data collected is for recruitment purpose only", "employment_types": ["Full Time", "Permanent"], "selling_points": [], "locations": ["Kwun Tong Area"], "categories": ["Media & Advertising", "Creative / Design", "Design", "Graphics", "Multi-media"], "post_time": "2022-01-12T13:09:26Z", "salary": {"currency": null, "max": null, "min": null, "period": "monthly", "term": null}, "salary_visible": false, "title_keywords": ["graphic designer", "junior"], "responsibilities": ["design solutions"], "requirements": {"degrees": ["diploma", "degree"], "majors": ["design"], "languages": ["english", "mandarin"], "language_level": ["good"], "hard_skills": ["problem solving", "3dmax", "photoshop", "autocad"], "soft_skills": ["good team player", "work overtime", "creative", "responsible", "open-minded", "problem solving", "teamwork spirit", "time management skill", "eye for detail", "innovative", "positive"], "languages_combined": [{"language": "english", "language_level": ["good"]}, {"language": "mandarin", "language_level": ["good"]}]}, "experience_required": {"duration": ["minimum 2 years"], "field": ["retail", "design"]}}, {"job_id": "100003009049074", "location_code": "hk", "company": "Morgan Philips Hong Kong Limited", "job_title": "Senior Graphic Designer (Supervisory Level)", "description": "We are currently seeking a specialist to join our creative team in HK.\u00a0 This opening offer an opportunity to work with well-known international brands and their professional team.\u00a0\n\nJob Duties:\n\nStrengthen the current creative offering in the areas of high-end/fine retail experiential\u00a0related industries.\u00a0\nTake creative lead on projects being involved at pitch stage and generally offering original, creative and effective design solutions.\nWork on projects from concept right the way through to finished product.\nYou will be comfortable driving creative pitch work, individually or by working with. \u00a0You will also have a chance to mentoring and reviewing other team members work.\u00a0\n\nRequirements:\n\nMinimum 4 years\u00a0Retail Experiential Design experience, solid experience in Cosmetics industry with Pop Up Event / Store Design / VM Design is more appreciated.\u00a0\nSoftware Requirement: 3DMAX (V-Ray), AutoCAD and Photoshop is a must.\nDegree in Interior Design or any other equivalent.\nGood understanding of consumer behaviour and latest market trend.\nAble to develop strategic and conceptual ideas for innovative retail solutions.\nHave a strong creative background and a good eye for detail.\u00a0\nStrong problem solving and analytical ability, with teamwork spirit.\nGood time management skill, able to catch-up deadline.\u00a0\nGood overall project process knowledge, as factory visit is required.\nGood hand sketch ability is appreciated.\u00a0 \u00a0\nKey elements to join our TEAM:\n\nBe responsible\nBe positive\nBe open-minded\nGood Language skills (English, Mandarin)\nGood Team Player\nWilling to work overtime\n\nWe OFFER:\n\nFive Day Work Week\nYear End Performance Bonus\nMedical Insurance\nEducational Allowance\nSeniority Allowance\nCoaching and Training\nBirthday Allowance\nQuarterly Team Building\nActivity Overtime Allowance\n\nAction NOW:\n\nThis is an exciting opportunity for you to join our creative team that are passionate and committed to everything in retail design and brand experience!\u00a0 DON\u2019T HESITATE!!\u00a0\u00a0If you are passion to develop your career, please send your PORTFOLIO and CV to us.\u00a0 A step further to your success. Make sure you mark the current / expected salary and date of available in your CV.\n\nPersonal data collected is for recruitment purpose only", "employment_types": ["Full Time", "Permanent"], "selling_points": ["An European Buying Office", "A Supervisory Role - Lead a team of 2", "Design Focus"], "locations": ["Not Specified"], "categories": ["Media & Advertising", "Creative / Design", "Design", "Graphics", "Industrial / Product"], "post_time": "2022-01-14T08:03:36Z", "salary": {"currency": null, "max": null, "min": null, "period": "monthly", "term": null}, "salary_visible": false, "title_keywords": ["senior graphic designer"], "responsibilities": ["design solutions"], "requirements": {"degrees": ["degree"], "majors": ["design"], "languages": ["english", "mandarin"], "language_level": ["good"], "hard_skills": ["problem solving", "3dmax", "photoshop", "autocad"], "soft_skills": ["good team player", "work overtime", "creative", "responsible", "open-minded", "problem solving", "teamwork spirit", "time management skill", "eye for detail", "innovative", "positive"], "languages_combined": [{"language": "english", "language_level": ["good"]}, {"language": "mandarin", "language_level": ["good"]}]}, "experience_required": {"duration": ["minimum 4 years"], "field": ["retail", "design"]}}, {"job_id": "100003009046455", "location_code": "hk", "company": "TLB Hong Kong Limited", "job_title": "PR & Social Media Executive / Manager", "description": "My client is an European Buying Office with a small operations in Hong Kong.\u00a0\n\nResponsibility:\u00a0\n\n\nBe the point of contact; s/he will be the main contact person for design team with stakeholders.\nClose partnership with Product Managers and Quality Manager for new product developments.\nEnsure that the delivered products or services adhere to the policies and standards of the company.\nSupervise and lead the graphic designing team.\nDelegate job responsibilities among team members and oversee that quality work is being completed within the deadline.\nComplete the project work within the timeline and estimated budget.\nMonthly KPI reporting with Chief Marketing and Development Officer.\nMaintain good records of artwork and approval.\nPrepares final layout for suppliers production.\nMaintain and update artwork with latest EN standards on regular basis.\nTake the lead on maintenance the photography studio, repair, hardware and software upgrades, and upkeep of all equipment.\u00a0\n\nRequirements:\u00a0\n\nAdvanced level with Adobe Creative applications such Photoshop, Illustrator, InDesign and Lightroom.\nIntermediate level with Microsoft Office applications such Excel, PowerPoint.\nStrong creative skills and the vision to turn briefs into creative projects.\nExcellent leaderships, organisation and analytical skill .\nGood collaborative and communication skill.\nTime management and multi-tasking skills\nThe ability to solve complex design and communication issues.\nThe ability to adhere to tight deadlines and manage budget constraints.\nNegotiation skills so they can comfortably work with other teams to implement changes to a product\u2019s design, design managers influence others, leading them to understand why certain design aspects matter more than others.\nA natural inclination towards leadership and the ability to deliver clear feedback to their team members.\nThe ability to work to tight deadlines.", "employment_types": ["Full Time", "Contract"], "selling_points": ["Social media, Digital PR, Marketing", "KOL influencer management", "Company start-up ownership opportunity"], "locations": ["Kwai Hing"], "categories": ["Media & Advertising", "Creative / Design", "Marketing / Public Relations", "Marketing - Brand / Product Management", "Digital Marketing"], "post_time": "2022-01-15T03:28:23Z", "salary": {"currency": null, "max": null, "min": null, "period": "monthly", "term": null}, "salary_visible": false, "title_keywords": ["manager", "social media executive"], "responsibilities": ["reporting", "software", "maintenance", "upgrades", "policies", "budget", "quality", "design", "hardware", "repair", "maintain", "contact", "designing"], "requirements": {"degrees": [], "majors": [], "languages": [], "language_level": [], "hard_skills": ["excel", "analytical skill", "microsoft office", "indesign", "illustrator", "powerpoint", "adobe", "photoshop"], "soft_skills": ["analytical skill", "advanced", "communication skill", "collaborative", "time management", "communication", "negotiation skills", "clear", "organisation", "multi-tasking skills", "creative", "leadership"], "languages_combined": []}, "experience_required": {"duration": [], "field": []}}, {"job_id": "100003009039296", "location_code": "hk", "company": "Hong Kong Science & Technology Parks Corporation", "job_title": "Creative Designer [JDB/CD/220111]", "description": "We are looking for a candidate who is experienced in the social media/ PR field. Someone who feels he/she is ready to take the next step in his/her career in running and managing a startup in-house social media company that provides PR, social media and marketing services to our company's in-house brands based in the FMCG industry (beauty/ household/ personal care/ food etc) as well as future brands and potential clients.\n\n\n\nMain responsibilities:\n\n\n\nIdeation and production for digitally engaging content (photo, video, infographic, etc)\nSocial media platform planning and management (Instagram & Facebook etc)\nDrive engagement on social media platforms\nAds and marketing management\nIdentify, outreach, and build a growing list of influencers and Brand Ambassadors\nKOL influencer management, pitching, coordination. From initial contact to follow up.\nMedia pitching\nMeasure, optimize and report on campaigns to achieve maximum awareness & engagement, and use these results to further improve the content strategy\nWork closely with sales team\nResponsible for planning and execution of PR and marketing plans\nWe are looking for:\n\nMinimum 1 year's experience in social media/ digital agency or PR company\nExperienced and passionate with various social media platforms\nSocial media savvy who can act quick with ad-hoc happenings\nStrong interest in the FMCG field\nGood commercial sense\nCANVA skills is an advantage\nStrong KOL network is an advantage\nExperience in KOL influencer management\nStrong sense of ownership and self-sufficiency \u2013 eager to own, drive, and grow our platforms\nExtremely detail oriented and comfortable in multi-tasking and priority assessment\nAn avid social media user yourself with a genuine interest in the FMCG industry\nProactive, innovative, and curious", "employment_types": ["Full Time"], "selling_points": [], "locations": ["Shatin Area"], "categories": ["Media & Advertising", "Creative / Design", "Design", "Graphics", "Multi-media"], "post_time": "2022-01-11T09:21:49Z", "salary": {"currency": null, "max": null, "min": null, "period": "monthly", "term": null}, "salary_visible": false, "title_keywords": ["creative", "designer"], "responsibilities": ["ad-hoc", "social media", "management", "marketing plans", "social media platforms", "sales team", "contact", "coordination", "facebook", "report", "planning"], "requirements": {"degrees": [], "majors": [], "languages": [], "language_level": [], "hard_skills": ["facebook", "fmcg industry"], "soft_skills": ["passionate", "proactive", "responsible", "detail oriented", "innovative", "multi-tasking", "coordination", "genuine"], "languages_combined": []}, "experience_required": {"duration": ["minimum 1 year"], "field": ["social media", "pr", "management", "agency", "digital"]}}, {"job_id": "100003009048339", "location_code": "hk", "company": "Noble Ventures Group Limited", "job_title": "Assistant Projects Manager / Senior Projects Executive", "description": "Job Duties & Responsibilities:\n- Strong ability to develop compelling visuals and ideas\n- Responsible for design from concept creative to supervise production\n- Experience on wide range of works, such as event production, printing materials, POSM, etc.\n\nRequirements:\n- Diploma in Graphic Design or Related Discipline\n- Experience in advertising agency/ graphic house is preferred.\u00a0 Fresh graduate will be also considered.\n- With art senses, well organised, mature, highly responsible and independent\n- Willing to complete project under tight deadlines\n-\u00a0Work at holiday and even in overnight is required\n- Proficiency in Photoshop, Illustrator with Mac Experience", "employment_types": ["Full Time"], "selling_points": ["Fast growing digital media platform", "Best-in-class creative, digital, tech solutions", "Suitable for professionals with high character"], "locations": ["North Point"], "categories": ["Media & Advertising", "Creative / Design"], "post_time": "2022-01-14T06:21:26Z", "salary": {"currency": null, "max": null, "min": null, "period": "monthly", "term": null}, "salary_visible": false, "title_keywords": ["manager", "assistant", "executive"], "responsibilities": ["ideas", "design", "develop"], "requirements": {"degrees": ["diploma", "fresh graduate"], "majors": ["graphic design"], "languages": [], "language_level": [], "hard_skills": ["illustrator", "photoshop"], "soft_skills": ["independent", "responsible", "mature", "organised"], "languages_combined": []}, "experience_required": {"duration": [], "field": ["graphic", "advertising agency"]}}, {"job_id": "100003009044731", "location_code": "hk", "company": "New Media Group Publishing Limited", "job_title": "Senior Editor/ Online Editor/Social Editor (\u65b0Monday \u6f6e\u6d41/\u71b1\u8a71/\u5a1b\u6a02)", "description": "Responsibilities:\n\n\u00a0-Work as a part of our social media team to develop\u00a0well social media practice;\n\n- Create\u00a0innovative & attention-grabbing copy for our clients\u2019 pages e.g. Facebook, Instagram, Online Buzz;\u00a0\n\n- Aspire to receive thousands of \u201cLikes\u201d and positive \u201cComments\u201d by netizens on every one of your creative feeds in our social media websites;\n\n- Support the team of the creative solutions, digital marketing strategy for client\u2019s projects especially in online advertising and social media campaigns;\n\n- Work together with creative team to develop the best digital solutions for clients, also closely work together with design and technical team for production;\n\n- Prepare daily documents and presentation accordingly to client\u2019s requirements and provide appropriate suggestions / solutions based on client\u2019s enquiries.\n\n\n\nRequirements:\n\nAssociate Degree/\u00a0Degree\u00a0holder with major in\u00a0Arts/ Communications,\u00a0Marketing, Journalism, PR\u00a0or related discipline;\nAble to write excellent and stylish Cantonese and English;\nKnowledge in Photoshop and/ or video editing;\u00a0\nGood\u00a0project management\u00a0skills;\nCreative\u00a0and open-minded with a marketing sense;\nA believer in social media and experiential marketing;\nAble to work under pressure and tight deadlines;\nStrong people skills and communication skills;\nCopywriting experience\u00a0in PR,\u00a0Facebook feeds, Forum, magazine is\u00a0a plus.\nFresh Graduate will be also considered.\n\nWe offer performance bonus, medical coverage, bank holidays, and wedding leaves to right candidates.\u00a0\n\n*All information will be treated as confidential and used solely for recruitment purposes.", "employment_types": ["Full Time", "Permanent"], "selling_points": ["Digital and online knowledge", "Generating ideas for articles and features", "Great development opportunity, competitive package"], "locations": ["Kwun Tong"], "categories": ["Media & Advertising", "Creative / Design", "Others", "Editorial / Journalism"], "post_time": "2022-01-13T05:55:38Z", "salary": {"currency": null, "max": null, "min": null, "period": null, "term": null}, "salary_visible": false, "title_keywords": ["editor", "senior editor"], "responsibilities": ["social media", "social media campaigns", "client\u2019s requirements", "comments", "design", "develop", "digital marketing", "facebook", "online advertising", "support the team"], "requirements": {"degrees": ["associate degree", "fresh graduate", "degree holder"], "majors": ["journalism", "marketing", "communications"], "languages": ["cantonese", "english"], "language_level": ["excellent"], "hard_skills": ["plus", "video editing", "project management", "facebook", "photoshop"], "soft_skills": ["communication skills", "marketing sense", "open-minded", "project management skills", "creative", "work under pressure"], "languages_combined": [{"language": "cantonese", "language_level": ["excellent"]}, {"language": "english", "language_level": ["excellent"]}]}, "experience_required": {"duration": [], "field": ["copywriting", "pr", "magazine"]}}, {"job_id": "100003009046219", "location_code": "hk", "company": "Sing Tao Management Services Limited", "job_title": "Designer (New Media Business)", "description": "The successful candidate will work closely with other designers to develop creative assets like imagery and graphics, diagrams, video, animated illustrations, etc. to support corporate branding and key marketing initiatives. He / she must have strong typography, composition and layout skills, a high ability to work under tight schedules while maintaining a high level of quality and accuracy.\n\n\nResponsibilities:\nCreate engaging designs for marketing assets ATL/TTL/BTL (posters, brochure, digital display, EDM, web and App banners etc)\nDevelop creative concepts, layouts and artworks for creative marketing campaign\nProvide art direction and liaise with vendors to deliver quality output\nAssist in development of brand and creative assets system\nUphold the branding guidelines to ensure all artworks and designs to the public are consistent to it\nTake, edit, retouch photos and videos\nPerform any other special projects as assigned\nRequirements:\nDiploma or Degree holder in Design, Creative Media, Multimedia Design or any related fields\n1-2 years of art direction & design experience, preferable in advertising & digital marketing industries. Agency experience is a plus. Fresh graduates are also welcome.\nProficient in Adobe Illustrator, InDesign, Photoshop, Premiere, and After Effect\nExcellent sense of art direction, graphic design, good skills on layout presentation and artwork production Strong creative and brainstorming capabilities\nPositive, true team player, open-minded and possess a strong sense of responsibility\nAbility to work in a team environment and collaborate with both designer and non-designers\nMust be proactive and able to reach out for required information in order to complete the job\nGood command of Chinese and English\nWe offer market competitive compensation, 5-day work week, and generous benefits including medical and life insurance; and voluntary contribution in addition to the legal minimum MPF.\u00a0 To apply, please send your full resume with current and expected salary to the Human Resources & Office Administration Department, Hong Kong Science and Technology Parks Corporation, 5/F, Building 5E, 5 Science Park East Avenue, Hong Kong Science Park, Hong Kong or, by email via \"Apply Now\"\u00a0on or before 24 January 2022.\u00a0 \u00a0Please quote the reference number on the email subject/envelope and the application letter.\u00a0\nPersonal data provided will be treated in strict confidence and used for recruitment purpose only.\u00a0 All personal data collected will be used strictly in accordance with employer\u2019s personal data policies, you can access to HKSTP\u2019s Personal Information Collection Statement at https://www.hkstp.org/hkstp_web/en/hkstp/personal-information-collection-statement-recruitment\nApplicants not invited for interview within four weeks after application deadline may consider their applications unsuccessful.\u00a0 Personal data of unsuccessful applicants will be retained for a maximum of two years.\u00a0", "employment_types": ["Full Time", "Permanent"], "selling_points": [], "locations": ["Tseung Kwan O"], "categories": ["Media & Advertising", "Creative / Design", "Design", "Multi-media", "Marketing / Public Relations", "Digital Marketing"], "post_time": "2022-01-13T09:59:53Z", "salary": {"currency": null, "max": null, "min": null, "period": "monthly", "term": null}, "salary_visible": false, "title_keywords": ["designer"], "responsibilities": ["edm", "guidelines", "quality", "banners", "liaise with", "develop creative concepts"], "requirements": {"degrees": ["diploma", "degree holder"], "majors": ["multimedia design", "creative media", "design"], "languages": ["english", "chinese"], "language_level": ["good command"], "hard_skills": ["plus", "indesign", "premiere", "adobe illustrator", "multimedia", "after effect", "photoshop"], "soft_skills": ["proactive", "sense of responsibility", "open-minded", "team player", "creative", "presentation", "positive"], "languages_combined": [{"language": "english", "language_level": ["good command"]}, {"language": "chinese", "language_level": ["good command"]}]}, "experience_required": {"duration": ["1-2 years"], "field": ["agency", "advertising", "design", "digital marketing"]}}, {"job_id": "100003009045475", "location_code": "hk", "company": "INNO Idea Limited", "job_title": "Web Designer - Digital", "description": "We are a fast-growing digital company, which invests in and develops innovative and digital-enablement technologies, and owns and operates multiple premium digital media brands (Asia Business Leaders, Champimom, & Everwellth).\n\nWe are currently seeking a high-caliber\u00a0Assistant Projects Manager / Senior Projects Executive\u00a0to cope with our rapid expansion.\u00a0\n\nResponsibilities:\n\n\nAssist to drive and implement projects and initiatives that contribute to long-term operational excellence\nAssist with the coordination of special projects\nProvide full spectrum of executive support to the Senior Management team\nFacilitate communication between the Senior Management team and other key stakeholders\nSupport and coordinate with internal and external parties to ensure smooth execution of the tasks assigned\nSimple administration and IT support\u00a0\nInvolve in other ad-hoc duties\u00a0\n\nRequirements:\n\n\nBachelor's degree or above in Business\u00a0or related discipline\nMinimum 5 years experience, have digital marketing experiences would be a benefit\nFluent in English, Cantonese, and Mandarin\nEnergetic, eager to develop a career in digital\u00a0\nSolid project planning and management skills\nHighly organized and able to prioritize and handle multiple tasks simultaneously\nExcellent team player with analytical, communication, organizational, interpersonal, numerate, negotiation, and problem-solving skills\nHigh integrity, self-motivated, able to work independently and take up personal responsibility\nMaintain positive working attitude, mature, stable, detailed-minded\u00a0\nOpen mindset and flexible to handle different challenges\u00a0\n\n\nBenefits\u00a0\n\n\nOpportunity to work in a fast-paced and creative environment\n5 days Work + Public Holidays\nProfessional Training\nExcellent career prospects in the exciting digital marketing industry\n\nWe offer a very competitive remuneration package to the successful candidate.\u00a0 Interested candidates please send us your full resume with your current and expected remuneration package & available date and click on the \"Apply Now\" Button.\n", "employment_types": ["Full Time", "Permanent"], "selling_points": [], "locations": ["Lai Chi Kok"], "categories": ["Media & Advertising", "Creative / Design", "Production", "Strategic Planning"], "post_time": "2022-01-13T07:55:47Z", "salary": {"currency": null, "max": null, "min": null, "period": "monthly", "term": null}, "salary_visible": false, "title_keywords": ["designer"], "responsibilities": ["internal and external parties", "coordinate with", "executive support", "communication", "coordination", "ad-hoc duties", "senior management", "administration"], "requirements": {"degrees": ["degree or above", "bachelor"], "majors": ["business"], "languages": ["cantonese", "english", "mandarin"], "language_level": ["fluent"], "hard_skills": ["problem-solving skills"], "soft_skills": ["stable", "organized", "self-motivated", "work independently", "flexible", "negotiation", "able to prioritize", "organizational", "integrity", "mature", "handle multiple tasks", "communication", "positive working attitude", "problem-solving skills", "team player", "energetic", "interpersonal", "detailed"], "languages_combined": [{"language": "cantonese", "language_level": ["fluent"]}, {"language": "english", "language_level": ["fluent"]}, {"language": "mandarin", "language_level": ["fluent"]}]}, "experience_required": {"duration": ["minimum 5 years"], "field": ["digital marketing"]}}, {"job_id": "100003009043627", "location_code": "hk", "company": "Hip Shing Hong (Holdings) Company Limited", "job_title": "CREATIVE & MULTIMEDIA DESIGNER", "description": "Responsibilities:\n\nDevelop and execute concepts across digital and print disciplines\nPerform full spectrum of promotion activities by creating 2D graphic, motion graphic or animation\u00a0\u00a0\nCreate engaging content and artwork in various social media platforms, online and digital platform to drive performance\nWork closely with Marketing Team for brand/product promotion and ad-hoc tasks on creative\nPerform tasks as assigned which will include 2D marketing materials like print ad or other marketing materials if need\nInvolve in simple photography, retouching and editing for marketing materials if necessary\nWorking at in-house environment\nRequirements:\n\nDiploma or above in Multimedia Design, Creative Media or other related disciplines\n3+ years relevant working experience in graphic design and works applied in social media, digital areas as well\nProficient in Adobe CS, including Adobe Illustrator, Photoshop, Premiere Pro, After Effects or other graphic design/video editing tools\nFamiliar with web-site maintenance knowledge in HTML & CSS will be advantage\nExperience in performing simple video / photo shooting & editing is definitely an advantage\nGood understanding of consumer behavior and experience of handling project independently\u00a0\u00a0\nTeam player, self-motivated, smart, creative, proactive and adaptable\nAbility to work multi-tasks & under pressure with tight deadlines\nWith digital marketing agencies background is also welcomed\u00a0\u00a0\nWorking Location : Tseung Kwan O Industrial Estate\n\nInterested parties please\u00a0click \u201cApply Now\"\u00a0to submit your complete resume with\u00a0employment history and expected salary or by\u00a0post to\u00a0Human Resources Department, 3/F, Sing Tao News Corporation Building, 7 Chun Cheong Street, Tseung Kwan O Industrial Estate, Tseung Kwan O, New Territories, Hong Kong.\n\nWe are an equal opportunity employer and welcome applications from all qualified candidates. Information provided will be treated in strict confidence and only be used for recruitment related purpose. Applicant who is not invited for an interview within 6 weeks may consider their application not successful. All personal data of unsuccessful applicants will be destroyed within 6 months.\n\nwww.singtaonewscorp.com", "employment_types": ["Full Time", "Permanent"], "selling_points": ["Conceive, craft and execute digital ideas", "Handle graphic design in various digital platforms", "2 years' relevant working experience in Multimedia"], "locations": ["Central"], "categories": ["Media & Advertising", "Creative / Design", "Design", "Multi-media", "Marketing / Public Relations", "Digital Marketing"], "post_time": "2022-01-13T01:06:38Z", "salary": {"currency": null, "max": null, "min": null, "period": "monthly", "term": null}, "salary_visible": false, "title_keywords": ["creative", "multimedia designer"], "responsibilities": ["retouching", "ad-hoc tasks", "social media platforms", "digital platform", "develop", "marketing materials", "editing", "motion graphic", "animation"], "requirements": {"degrees": ["diploma or above"], "majors": ["multimedia design", "creative media", "related disciplines"], "languages": [], "language_level": [], "hard_skills": ["simple", "web", "maintenance", "html", "adobe illustrator", "video editing", "after effects", "premiere pro", "multimedia", "adobe cs", "css", "photoshop"], "soft_skills": ["self-motivated", "proactive", "independently", "under pressure", "multi-tasks", "adaptable", "team player", "creative"], "languages_combined": []}, "experience_required": {"duration": ["3+ years"], "field": ["social media", "video", "graphic design", "photo shooting", "relevant working experience", "digital", "editing"]}}, {"job_id": "100003009041984", "location_code": "hk", "company": "AdBeyond (Group) Limited", "job_title": "PR and Marketing Executive", "description": "Roles & Responsibilities:\n\nSupport graphical works / layout artwork / UX/UI design in across various types ofdigital projects\nFollow up client's request and provide professional advice to client\nWorking with project supervisor and programming teamto provide campaignideas, such as minisite, mobile apps, flash games, eDM, web banneretc\nEnsure projects are delivered on time and within budget\n\n\u00a0Requirements:\n\nDesign Institute Diploma holder or above.\nStrong sense of responsibility and hardworking, able to work independently and under pressure to meet tight schedule.\nStrong graphic sense and creative minded.\nProficiency in Adobe Creative Suite (Photoshop,Illustrator, AfterEffects, XD, etc.), Figma & Sketch\u00a0preferred.\nGood knowledge of UX/UI design principles and techniques, HTML5/CSS is a plus.\nGood interpersonal skills, well-organized and detail-minded.\nBe enthusiastic in digital and marketing industries.\nFluency in Cantonese and English is essential.\nFresh graduate without portfolio will also be considered.\nImmediately available is a plus.\n\n\u00a0We offer competitive remuneration package including 5-days work, annual leave, performance bonus, Medical and MPF.\n\n\n\n\nInterested Candidates please send your CV with Current and Expected Salary. Personal data collected will be used for recruitment purpose only.\n\n%MCEPASTEBIN%", "employment_types": ["Full Time"], "selling_points": ["Deliver innovative business solutions to clients", "Lead cross-functional teams", "International Exposure"], "locations": ["Kwun Tong"], "categories": ["Media & Advertising", "Creative / Design", "Marketing / Public Relations", "Marketing - Brand / Product Management", "Digital Marketing"], "post_time": "2022-01-12T04:59:49Z", "salary": {"currency": null, "max": null, "min": null, "period": "monthly", "term": null}, "salary_visible": false, "title_keywords": ["marketing executive"], "responsibilities": ["budget", "ui", "design", "edm"], "requirements": {"degrees": ["diploma holder", "fresh graduate"], "majors": ["design"], "languages": ["cantonese", "english"], "language_level": ["fluency"], "hard_skills": ["plus", "illustrator", "css", "adobe creative suite", "photoshop"], "soft_skills": ["detail-minded", "work independently", "under pressure", "sense of responsibility", "well-organized", "interpersonal skills", "enthusiastic", "creative", "hardworking"], "languages_combined": [{"language": "cantonese", "language_level": ["fluency"]}, {"language": "english", "language_level": ["fluency"]}]}, "experience_required": {"duration": [], "field": []}}, {"job_id": "100003009048618", "location_code": "hk", "company": "Kum Shing Group", "job_title": "Communication Officer", "description": "frengers communications\u00a0is a HK Based creative agency. We help brands to tell their authentic stories, in an aesthetic way. To cope with our rapid growth, we sincerely invite high calibrate candidates to join our young & energetic team!\n\nCheck out our work: https://fb.com/frengershk // http://www.frengers.com.hk/\n\nWe are looking for great storyteller\u2026 to inspire & be inspired.\n\nResponsibilities and Expectations:\n\nSomeone who want to be a good art director instead of an average one\nIt means your work scope & of course skill required will go beyond ART\n\nBe part of the creative team to create HIGH-QUALITY creative work and generate INNOVATIVE ideas\nArticulate insights, DISTRUPTIVE angle & CRAFTSMANSHIP to generate the best communication solution\nWork closely with Account Servicing Team to develop IMPACTFUL VISUALS (Presentation Deck, Video, Key Visuals, Activations, Installation, Social Campaigns, etc)\nManage & maintain GOOD RELATIONSHIPS with external parties including production partners, photographers and other suppliers\n\nBenefits:\n\nAnnual Incentive Trip, Book Subsidy, Team Building Activities, Birthday Leave, Medical, AND MOST IMPORTANTLY, an open & dynamic atmosphere to CREATE!\n\nRequirements:\n\nFun & open-minded\nStronger desire to launch impactful campaigns (IMC, ATL, Social)\nEager to learn & experiment\nExperience in Creative Agency is a MUST\nProficiency in using MAC and graphic design software, including Photoshop & Illustrator (Nice-to-have: After Effect, Premiere, Final Cut Pro)\nAble to work & more importantly generate idea independently\nStrong communications & graphic sense, creative & detail-oriented\nSelf-motivated, multi-tasking and able to work independently\nImmediate available is HIGHLY PREFERED", "employment_types": ["Full Time"], "selling_points": ["Degree holder of Communications / Public Relations", "Excellent career path", "Performance bonus, education subsidy, medical plan"], "locations": ["To Kwa Wan"], "categories": ["Media & Advertising", "Creative / Design", "Marketing / Public Relations", "Marketing - Brand / Product Management", "Marketing - Marketing Communication"], "post_time": "2022-01-14T06:54:39Z", "salary": {"currency": null, "max": null, "min": null, "period": "monthly", "term": null}, "salary_visible": false, "title_keywords": ["communication officer"], "responsibilities": ["installation", "ideas", "key visuals", "external parties", "quality", "develop", "communication", "maintain"], "requirements": {"degrees": [], "majors": [], "languages": [], "language_level": [], "hard_skills": [], "soft_skills": [], "languages_combined": []}, "experience_required": {"duration": [], "field": []}}, {"job_id": "100003009049989", "location_code": "hk", "company": "Manpower Services (Hong Kong) Limited", "job_title": "DTP Specialist (27.5K)", "description": "Hip Shing Hong strives to fill work and life with positive energy, and crafts spaces that promote wellness.\n\nCome and join us to take on new challenges where your creativity is cherished.\n\nWe are looking for a talent to:\n\nConceive, craft and execute a variety of creative and digital ideas, artworks and copywriting for online and offline advertising & social campaigns\nHandle graphic design, creative solution, layout, script writing, artwork and video production in various digital platforms such as social media, eDM, online banner and webpage etc.\nHandle layout design for offline marketing materials such as leaflet, posters and banner etc.\n360 VR, video and photographic shooting, production and editing\nOrganize digital projects, create and support marketing assets for interactive mobile, web and desktop platform\n\nBasic requirements:\n\nHigher Diploma or above in Multimedia Design, Graphic Design, Digital Marketing, Marketing Communications, or related disciplines\n2 years' relevant working experience in Multimedia, Graphic design, UI/UX, Photography, Videography or related exposure\nCandidate with knowledge of animation or illustration is an advantage\n\n\nBenefits:\u00a0\u00a0\n\nMedical insurance\nDental insurance\nDiscretionary year-end bonus\nEducation and training allowance\nPaid marriage leave & gift\nPaid emergency leave\nPaid children's birthday leave\nPaid compassionate leave\nAcademic scholarship\n\nWe are constantly looking for talents who are proactive and dedicated to be part of our Hip Shing Hong\u2019s family. If you are ready for the next challenge, please apply now. For more information, please visit our Company's website\u00a0https://www.hshd.com.hk/en/career/.\n\nAll information provided by applicants will be treated in strict confidence and be used for recruitment purpose only.\u00a0", "employment_types": ["Contract"], "selling_points": ["Marketing materials", "Graphic design", "Banking industry"], "locations": ["Central"], "categories": ["Media & Advertising", "Creative / Design", "Design", "Graphics", "Multi-media"], "post_time": "2022-01-14T09:36:06Z", "salary": {"currency": null, "max": null, "min": null, "period": "monthly", "term": null}, "salary_visible": false, "title_keywords": ["specialist"], "responsibilities": [], "requirements": {"degrees": [], "majors": [], "languages": [], "language_level": [], "hard_skills": [], "soft_skills": ["positive"], "languages_combined": []}, "experience_required": {"duration": [], "field": []}}, {"job_id": "100003009044802", "location_code": "hk", "company": "Hong Kong Tourism Board", "job_title": "Assistant Manager, Content Development (1-year Renewable Contract)", "description": "Reporting to the Senior Manager, the appointee will be responsible for but not limited to the following:\n\nResponsibilities:\n\nAssist in the planning and implementation of projects in support of business strategies;\nSupport all the marketing and promotion materials for business to business projects from design to communications;\nHandle website management and analysis including backend support, HTML and SEO;\nDrive social media strategy for multi-platform storytelling;\nPrepare communications materials for internal and external use;\nManage agencies and vendors;\nOccasional site visit is required;\nOther tasks as assigned by supervisor.\n\nRequirements \u2013 Qualification:\n\nDegree holder of Communications, Public Relations or related discipline;\nMinimum 5 years in Communications, Branding or related fields; candidate with less experience will be considered as\u00a0Assistant Communications Officer;\nPrevious experience in agency and with knowledge in Engineering industry is a highly preferable;\nUnderstanding multi-media communications with the use of different narration is a must;\nExcellent command of both written and spoken English and Chinese.\n\nRequirements \u2013 Competences:\n\nPresentable with good manner and excellent presentation skill;\nStrong interpersonal and communication skills;\nEnthusiasm, collaborative, resilience and a good team player;\nDigital communications and social media platform savvy.\n\nWe look forward to receiving your application with detailed resume stating\u00a0working experience,\u00a0academic and language qualifications, existing and EXPECTED SALARY\u00a0as well as\u00a0availability.\u00a0All applications will be kept strictly confidential.\n\nWe offer promising professional career and exposure\u00a0to right candidate, together with attractive remuneration package including\u00a0discretionary bonus, continuing education allowance, medical and dental coverage.\n\nPersonal Data collected will be used for recruitment-related purposes only.", "employment_types": ["Full Time", "Contract"], "selling_points": ["Plan and execute content campaigns", "Supervise the content production", "Liaison between the internal and external parties"], "locations": ["Tin Hau"], "categories": ["Media & Advertising", "Creative / Design", "Photography / Video", "Marketing / Public Relations", "Digital Marketing"], "post_time": "2022-01-13T06:20:26Z", "salary": {"currency": null, "max": null, "min": null, "period": "monthly", "term": null}, "salary_visible": false, "title_keywords": ["assistant manager,"], "responsibilities": ["social media", "management", "seo", "business projects", "analysis", "website", "design", "implementation of projects", "other tasks", "planning"], "requirements": {"degrees": ["degree holder"], "majors": ["communications"], "languages": ["english", "chinese"], "language_level": ["excellent"], "hard_skills": ["presentation skill"], "soft_skills": ["presentation skill", "communication skills", "good team player", "collaborative", "presentable", "interpersonal", "detailed"], "languages_combined": [{"language": "english", "language_level": ["excellent"]}, {"language": "chinese", "language_level": ["excellent"]}]}, "experience_required": {"duration": [], "field": ["agency", "engineering"]}}, {"job_id": "100003009043682", "location_code": "hk", "company": "Legato Technologies Limited", "job_title": "UI / UX Designer", "description": "Our client, a leading global bank, is looking for a DTP specialist.\n\nKey Responsibilities:\n\u2022 Produces a variety of marketing materials (e.g. covers, templates, newsletters, deal toy designs, invites, posters, flyers, HTML newsletters, etc.) using relevant graphic applications to an advanced level\n\u2022 Traces and produces logos, maps and illustrations\n\u2022 Creates concept and artwork for 2D and 3D tombstones (lucites)\n\u2022 Assists with the production of pitchbook materials and offers conceptual and visual solutions to enhance client materials\n\u2022 Ensures all materials produced are correctly branded as per\u00a0company\u00a0standards and advises clients on the use of the\u00a0company brand\n\u2022 Liaises directly with workflow staff and clients to determine deadlines, job instructions and design requirements\n\u2022 Completes related admin for accurate work billing and job tracking purposes\n\u2022 Assists with Intake coordination when required\n\u2022 Responsible for quality control of own work, as well as assisting colleagues with QC tasks\n\u2022 Buddies new joiners post-training\n\u2022 Contributes to best production practices through internal initiatives and programs\n\nRequirements:\n\u2022 3 years or above of admin/operational support in a corporate, service-oriented environment, ideally in a financial institution\n\u2022 Advanced knowledge of industry standard graphic design applications\u00a0\n\u2022 Advanced knowledge of Adobe Creative Suite (i.e. Illustrator, Photoshop, InDesign, Acrobat Professional)\n\u2022 Advanced knowledge of Microsoft Office (PowerPoint, Excel and Word)\n\u2022\u00a0Knowledge in Dreamweaver and Blender and external print processes is desirable\n\nQualifications:\n\u2022 Bachelor\u2019s degree or Diploma in Graphic Design with 3 years or above of relevant work experience in a corporate, service-oriented environment OR demonstrated ability to meet the job requirements through a comparable work experience\n\u2022 Must be able to provide a portfolio / samples of recent work\n\nInterested parties please email your resume (MS Word format) to\u00a0yan.chan@manpowergrc.hk\u00a0or clicking \"Apply Now\".", "employment_types": ["Full Time", "Part Time", "Permanent", "Contract", "Freelance"], "selling_points": [], "locations": ["Kowloon Bay"], "categories": ["Media & Advertising", "Creative / Design", "Design", "Others"], "post_time": "2022-01-13T01:28:01Z", "salary": {"currency": null, "max": null, "min": null, "period": "monthly", "term": null}, "salary_visible": false, "title_keywords": ["ux designer"], "responsibilities": ["design", "coordination", "visual", "marketing materials", "quality control", "tracking"], "requirements": {"degrees": ["diploma", "degree", "bachelor"], "majors": ["graphic design"], "languages": [], "language_level": [], "hard_skills": ["excel", "acrobat", "microsoft office", "indesign", "illustrator", "powerpoint", "word", "dreamweaver", "adobe creative suite", "photoshop"], "soft_skills": ["service-oriented", "creative", "advanced"], "languages_combined": []}, "experience_required": {"duration": ["3 years"], "field": ["graphic design"]}}, {"job_id": "100003009042096", "location_code": "hk", "company": "Global Virtual Design And Construction Limited", "job_title": "Junior Media Producer/ Trainee", "description": "Responsibilities\n\nFormulate, manage and execute the content campaigns and strategies, including content ideation, schedules and delivery implementation across multi-channels\nDevelop clear and engaging content that is aligned with the content framework and address consumer needs\nBrief, plan and supervise the content production with external content creators to ensure the contents are of high quality\nManage the in-house production team \u2013 create schedules, production plan and assist the team on location during shooting, and ensure timely delivery and completion\nAct as the primary liaison between the project team, trade partners and vendors\nAcquire resources and coordinate efforts of cross-function team members in order to deliver projects according to timeline and budgets\nCheck accuracy of content and ensure content adherence to brand guidelines\n\nRequirements\n\nDegree holder with minimum 8 years of experience in social media, advertising, journalism, marketing, or related fields\nWith background in video production or digital content creation would be a strong advantage.\nPossess a creative mindset with strong interest in trends within leisure travel and social media\nProficient in spoken and written English and Chinese including Mandarin\nDetailed-minded, with strong multitasking and analytical skills to make effective judgements independently\nOutspoken and outgoing personality with a strong desire and ability to learn\n\nInterested parties please send resume with present and expected salary by clicking \u201cApply Now\u201d.\n\nPersonal data provided by job applicants will be used strictly in accordance with our personal data policies, a copy of which will be provided upon request.\u00a0 Applicants may send a request for a copy of the Personal Information Collection Statement pertaining to Job\u00a0Application.\u00a0 Only shortlisted applicants will be contacted. \u00a0All Information received will be kept in strict confidence and\u00a0used\u00a0only for employment-related purpose.\n\nWe are an equal opportunities employer.", "employment_types": ["Full Time", "Permanent"], "selling_points": ["Responsible for creating the motion", "Responsible for the technical execution", "0-2 years of experience in Animation/CG Graphics"], "locations": ["Not Specified"], "categories": ["Media & Advertising", "Creative / Design", "Design", "Graphics", "Interior"], "post_time": "2022-01-12T06:05:58Z", "salary": {"currency": null, "max": null, "min": null, "period": "monthly", "term": null}, "salary_visible": false, "title_keywords": ["producer", "trainee", "junior"], "responsibilities": ["budgets", "schedules", "quality", "implementation", "develop", "coordinate", "brand guidelines", "plan", "contents"], "requirements": {"degrees": ["degree holder"], "majors": ["journalism", "marketing"], "languages": ["english", "chinese", "mandarin"], "language_level": ["proficient"], "hard_skills": ["make", "analytical skills"], "soft_skills": ["outgoing personality", "independently", "outspoken", "creative mindset", "analytical skills", "detailed"], "languages_combined": [{"language": "english", "language_level": ["proficient"]}, {"language": "chinese", "language_level": ["proficient"]}, {"language": "mandarin", "language_level": ["proficient"]}]}, "experience_required": {"duration": ["minimum 8 years"], "field": ["related", "social media", "marketing", "advertising"]}}, {"job_id": "100003009044007", "location_code": "hk", "company": "Hong Kong Sheng Kung Hui Welfare Council Limited", "job_title": "\u50b3\u8a0a\u53ca\u5e02\u5834\u63a8\u5ee3\u4e3b\u4efb (UC/MCO/2021-3)", "description": "Responsibilities\nResponsible for creating the motion of CG characters or objects\nResponsible for the technical execution of animating CG characters or objects\nRequirements\n0-2 years of experience in Animation/CG Graphics\nKnowledge of 3D character setup is preferred\nProficient in XSI, Maya or 3ds Max\nKnowledge of Photoshop, After Effects or other relative software\nAbility to modeling, animation, texturing and lighting\nStrong art and design sense and creative\nDetail-minded and a good team player\nWilling to learn and work under pressure and tight schedule\nOutdoor work is required\nLess experience will be considered as Trainee\nWe offer competitive remuneration package with comprehensive fringe benefits to the right candidates.\u00a0 Interested parties, please send your full resume, with current and expected salary, date of availability to email by clicking \"Apply Now\"", "employment_types": ["Full Time", "Contract"], "selling_points": [], "locations": ["Yuen Long"], "categories": ["Media & Advertising", "Creative / Design", "Editorial / Journalism", "Print Media"], "post_time": "2022-01-13T18:54:54Z", "salary": {"currency": null, "max": null, "min": null, "period": "monthly", "term": null}, "salary_visible": false, "title_keywords": [], "responsibilities": [], "requirements": {"degrees": [], "majors": [], "languages": [], "language_level": [], "hard_skills": ["graphics", "maya", "cg", "3ds max", "after effects", "photoshop"], "soft_skills": ["detail-minded", "good team player", "willing to learn", "creative", "work under pressure"], "languages_combined": []}, "experience_required": {"duration": ["0-2 years"], "field": []}}, {"job_id": "100003009041948", "location_code": "hk", "company": "Eagle Sky Media Limited", "job_title": "Digital Marketing Copywriter / Content Editor (Online advertising agency )", "description": "\nYou\u00a0will create impact via\u2026\n\nGenerate assets for print and digital mediums with deliverables including client testimonials, social media content, email marketing, pitch decks, advertisement copywriting and other branding communication materials\nSupport interactive content creation - photos/video shooting, production and edition for contents needed for the posting on websites, SEO, Ads copies, and different social media like Facebook and LinkedIn\nEnsure brand consistency across all materials\nSupport the content strategy across different channels\nCoordinate and support other projects as required\nCommunicate with internal stakeholders, partners or agencies as occasion arise\nThe follow attributes will be valued\u2026\n\nMinimum 4 years related working experience. Candidate with\u00a0tech, agency or FMCG background is an added advantage\nHighly fluent in written and spoken English and excellent attention to details\nA passion for story-telling and delivering great copy\nFlexible and organised under pressure. Able to multi-task and meet tight deadlines\nAble to work independently as well as in a team\nLess experience will be considered as Officer - Marketing Communications\u00a0\n\n\nWhat you get in return\u2026\n\nApart from competitive salary package and benefits, in HKBN, you will work flexibly under our\u00a0Talent-first culture\u00a0and we uphold\u00a0Life-Work Priority. Examples of our flexible initiatives:\n\nFive-day work week\u00a0\nHalf Day Off Friday once a month\u00a0\nHalf Day Off on Festival Eve\u00a0\nUnique leaves arrangement: Family-care leave, Anniversary leave, Bonus leave, Volunteer leave, Sabbatical leave, etc.\nComprehensive medical and life insurance coverage\nUpgraded maternity leave and paternity leave\nDiscounted Talent plan offers including broadband and mobile plans and other promoted products\nEducation subsidies and Examination leave\nYear-end discretionary bonus\nInterested parties, please click \"Apply Now\" to submit your application.\n\n\n\nJoin Us Today!\n\nAll information provided by applicants will be treated in strict confidence and used for consideration in relation to the relevant post within the company.\n\nAll personal data of unsuccessful applicants will be destroyed within\u00a0one year. Applicants who are not invited for an interview within 3 weeks may consider their application unsuccessful.", "employment_types": ["Full Time"], "selling_points": ["Copywriter", "Content Editor", "content marketing"], "locations": ["Tsuen Wan Area"], "categories": ["Media & Advertising", "Creative / Design", "Marketing / Public Relations", "Public Relations - Copy-writing", "Digital Marketing"], "post_time": "2022-01-12T04:47:02Z", "salary": {"currency": null, "max": null, "min": null, "period": "monthly", "term": null}, "salary_visible": false, "title_keywords": ["copywriter", "content editor", "digital marketing"], "responsibilities": ["communicate with", "social media", "seo", "communication", "coordinate", "video shooting", "social media content", "contents", "facebook", "brand consistency"], "requirements": {"degrees": [], "majors": [], "languages": ["english"], "language_level": ["excellent", "fluent"], "hard_skills": ["facebook", "seo"], "soft_skills": ["flexible", "meet tight deadlines", "work independently", "under pressure", "multi-task", "passion for", "communication", "attention to details", "organised"], "languages_combined": [{"language": "english", "language_level": ["excellent", "fluent"]}]}, "experience_required": {"duration": ["minimum 4 years"], "field": ["related", "marketing communications"]}}, {"job_id": "100003009042694", "location_code": "hk", "company": "New Media Group Publishing Limited", "job_title": "Visual & Graphic Designer", "description": "\u689d\u4ef6:\n\n\n\u6301\u5e02\u5834\u5b78\u5b78\u58eb\u5b78\u4f4d\u6216\u540c\u7b49\u5b78\u6b77\uff0c\u4e3b\u4fee\u5e02\u5834\u5b78\u6216\u50b3\u8a0a\u5b78\u7cfb\u7562\u696d\n\u5177\u826f\u597d\u4e2d\u82f1\u6587\u66f8\u5beb\u53ca\u6e9d\u901a\u80fd\u529b\n\u8077\u8cac\uff1a\n\n\u8ca0\u8cac\u767c\u5c55\u53ca\u5354\u8abf\u5e02\u5834\u7b56\u7565\u63a8\u5ee3\u540c\u5fc3\u6751\u670d\u52d9\n\u7c4c\u8fa6\u91cc\u7a0b\u7891\u76f8\u95dc\u6d3b\u52d5\n\u7de8\u8f2f\u8207\u88fd\u4f5c\u5ba3\u50b3\u520a\u7269\n\u5354\u52a9\u55ae\u4f4d\u8655\u7406\u50b3\u5a92\u67e5\u8a62\uff0c\u64b0\u5beb\u65b0\u805e\u7a3f\uff0c\u7d44\u7e54\u65b0\u805e\u767c\u4f48\u6703\u53ca\u50b3\u5a92\u63a1\u8a2a\n\n\u6b64\u8077\u4f4d\u5c6c\u300c\u9805\u76ee\u70ba\u672c\u300d(project based)\u6027\u8cea\u3002\n\n\n\n\u6709\u610f\u7533\u8acb\u4e0a\u8ff0\u8077\u4f4d\u8005\u8acb\u5177\u51fd\u4e26\u9644\u8a73\u7d30\u5c65\u6b77\uff0c\u73fe\u6642\u85aa\u916c\u53ca\u671f\u671b\u85aa\u916c\u7b49\u8cc7\u6599\uff0c\u5bc4\u9999\u6e2f\u7b72\u7b95\u7063\u8208\u6c11\u885768\u865f\u6d77\u5929\u5ee3\u58345\u6a13 \u2013 \u4eba\u529b\u8cc7\u6e90\u90e8\u6536\u6216\u6216\u6309\"Apply Now\"\uff0c\u4fe1\u5c01\u53ca\u96fb\u90f5\u8acb\u8a3b\u660e\u7533\u8acb\u7de8\u865f\u3002\u7533\u8acb\u4eba\u4e4b\u7be9\u9078\u5c07\u6703\u5373\u6642\u9032\u884c\u76f4\u81f3\u4e8c\u96f6\u4e8c\u4e8c\u5e74\u4e00\u6708\u4e8c\u5341\u516b\u65e5\u6216\u6709\u95dc\u8077\u4f4d\u7a7a\u7f3a\u5df2\u88ab\u586b\u88dc\u70ba\u6b62\u3002(\u5165\u8077\u85aa\u916c\u4e43\u6309\u5b78\u6b77\u53ca\u5de5\u4f5c\u7d93\u9a57\u800c\u8a02\u3002)\u00a0\u00a0\n\n\u4e00\u5207\u7533\u8acb\u8cc7\u6599\u7d55\u5c0d\u4fdd\u5bc6\u53ca\u53ea\u7528\u4f5c\u62db\u8058\u6709\u95dc\u8077\u4f4d\u3002\u5982\u7533\u8acb\u8005\u5728\u622a\u6b62\u65e5\u671f\u5f8c\u516b\u661f\u671f\u5167\u4ecd\u672a\u7372\u96fb\u8a71\u7d04\u898b\u8005\uff0c\u5176\u7533\u8acb\u53ef\u4f5c\u843d\u9078\u8ad6\uff0c\u6055\u4e0d\u53e6\u51fd\u901a\u77e5\uff0c\u672c\u798f\u5229\u5354\u6703\u5c07\u4fdd\u5b58\u7533\u8acb\u6587\u4ef6\u4e0d\u8d85\u904e\u516d\u500b\u6708\u3002", "employment_types": ["Full Time", "Permanent"], "selling_points": ["Design original graphics", "1-3 years of experience as a graphic designer", "Great development opportunity, competitive package"], "locations": ["Kwun Tong"], "categories": ["Media & Advertising", "Creative / Design", "Design", "Graphics", "Others"], "post_time": "2022-01-12T08:25:06Z", "salary": {"currency": null, "max": null, "min": null, "period": null, "term": null}, "salary_visible": false, "title_keywords": ["graphic designer"], "responsibilities": [], "requirements": {"degrees": [], "majors": [], "languages": [], "language_level": [], "hard_skills": [], "soft_skills": [], "languages_combined": []}, "experience_required": {"duration": [], "field": []}}, {"job_id": "100003009046983", "location_code": "hk", "company": "Centaline Property Agency Ltd", "job_title": "Production Officer (BUS)", "description": "We are looking for a talented visual & graphic designer to enhance our online presence with eye-catching and professional graphic designs. You will consult with the different function teams to determine design requirements, submit draft concepts for approval, and develop similar design prototypes for our products.\u00a0\n\nJob Description:\n\nDesign original graphics with unique colours, shapes, and typography fonts.\nSubmit graphic & visual design concepts for brainstorming and approval in a timely manner.\nCollaborate with the Project team and IT developers in aligning visual designs with website functionalities.\nDevelop prototypes to uniformly integrate logos and brand images to other products and platforms, including social media.\n\nRequirements:\n\nBachelor\u2019s or associate degree in graphic design, visual arts, or similar.\n1-3 years of experience as a graphic visual designer is preferred\nAdvanced proficiency in design software, such as Adobe Creative Suite's InDesign, Photoshop, and Illustrator.\nKnowledge of programming languages such as HTML and JavaScript would be advantageous.\nExtensive experience in determining visual design preferences and meeting deadlines.\nProficiency in keeping up with visual design technologies and industry trends.\nGood communication skills.\n\nWe offer competitive salary and benefits package( 5 days work, 14 days AL up, birthday leave, medical & dental insurance) with great opportunity for career development to the successful candidate.\n\nFor applications, please send the resume to us, specify in email title \u201cJob Application for\u00a0Visual & Graphic Designer\"", "employment_types": ["Full Time", "Permanent"], "selling_points": ["Video Production", "Both Video Shooting and Editing", "Multi tasking"], "locations": ["Tsim Sha Tsui"], "categories": ["Media & Advertising", "Creative / Design", "Production", "Photography / Video"], "post_time": "2022-01-14T01:56:24Z", "salary": {"currency": null, "max": null, "min": null, "period": "monthly", "term": null}, "salary_visible": false, "title_keywords": ["production officer"], "responsibilities": ["graphics", "design concepts", "collaborate with", "social media", "a timely manner", "website", "design", "develop", "visual"], "requirements": {"degrees": ["associate degree", "bachelor"], "majors": ["graphic design"], "languages": [], "language_level": [], "hard_skills": ["indesign", "illustrator", "html", "visual design", "javascript", "programming", "adobe creative suite", "photoshop"], "soft_skills": ["communication skills", "creative", "extensive", "advanced"], "languages_combined": []}, "experience_required": {"duration": ["1-3 years"], "field": ["graphic", "designer", "design"]}}, {"job_id": "100003009038065", "location_code": "hk", "company": "Ample Advertising Agency Limited", "job_title": "Junior Multimedia Designer", "description": "frengers communications\u00a0is a HK Based creative agency. We help brands to tell their authentic stories, in an aesthetic way. To cope with our rapid growth, we sincerely invite high calibrate candidates to join our young & energetic team!\n\nCheck out our work: https://fb.com/frengershk // http://www.frengers.com.hk/\n\nWe are looking for great storyteller\u2026 to inspire & be inspired\n(For ACD/CD role, we welcome both Art-Base or Copy-Base creative)\n\nResponsibilities and Expectations:\n\nLeading the creative team to create HIGH-QUALITY creative work and generate INNOVATIVE ideas\nArticulate insights, DISTRUPTIVE angle & CRAFTSMANSHIP to generate the best communication solution\nWork closely with Account Servicing Team to develop IMPACTFUL CAMPAIGNS (Presentation Deck, Big Ideas, KVs & Videos, Activations, Social Campaigns, etc)\nManage & maintain GOOD RELATIONSHIPS with external parties including production partners, photographers and other suppliers\n\nBenefits:\n\nAnnual Incentive Trip, Book Subsidy, Team Building Activities, Birthday Leave, Medical, AND MOST IMPORTANTLY, an open & dynamic atmosphere to CREATE!\n\nRequirements:\n\nFun & open-minded\nStronger desire to launch impactful campaigns (IMC, Digital, Social)\nExperience in leading small team\nExperience in Creative/Digital/Social agency is preferred (6+ Years)\nGood at execution & also with strategic mindset\nFamiliar with latest digital marketing trend & technology innovations\nStrong communications & graphic sense, creative & detail-oriented\nSelf-motivated, multi-tasking and able to work independently\nImmediate available is preferred\n\nCandidates with more experience may be considered as Creative Director", "employment_types": ["Full Time"], "selling_points": [], "locations": ["Wan Chai"], "categories": ["Media & Advertising", "Creative / Design"], "post_time": "2022-01-12T03:41:34Z", "salary": {"currency": null, "max": null, "min": null, "period": "monthly", "term": null}, "salary_visible": false, "title_keywords": ["multimedia designer", "junior"], "responsibilities": ["ideas", "external parties", "quality", "develop", "communication", "maintain"], "requirements": {"degrees": [], "majors": [], "languages": [], "language_level": [], "hard_skills": [], "soft_skills": [], "languages_combined": []}, "experience_required": {"duration": [], "field": []}}, {"job_id": "100003009036693", "location_code": "hk", "company": "Phoenix Satellite Television Co Ltd", "job_title": "\u8996\u89ba\u50b3\u9054\u8a2d\u8a08\u5e2b\uff08\u521d\u3001\u4e2d\u3001\u9ad8\u7d1a\uff09", "description": "Responsibilities:\n\nResponsible for graphic design and video editing\nMotion graphic composing\nOther ad hoc duties as assigned\n\nRequirements:\n\nStrong sense of branding, social media & digital marketing trends.\nProficient in software including After Effect, Photoshop and Illustrator, InDesign\nMajor in Multimedia Design, Video Production, or relative disciplines\nKnowledge in Motion Graphics\nOver 1-2 years as a Multimedia Designer (video editing and artwork design)\nCreative, independent, with good co-ordination and communication skill\nKnowledge in video shooting is preferable\nAble to\u00a0work under pressure & meet tight deadline\nInterested parties please send the design portfolio (less than 10MB) and your full CV stating your availability, current and expected salary", "employment_types": ["Full Time"], "selling_points": [], "locations": ["Tai Po Area"], "categories": ["Media & Advertising", "Creative / Design"], "post_time": "2022-01-10T12:41:14Z", "salary": {"currency": null, "max": null, "min": null, "period": null, "term": null}, "salary_visible": false, "title_keywords": [], "responsibilities": ["video editing", "graphic design", "motion graphic", "ad hoc duties"], "requirements": {"degrees": [], "majors": [], "languages": [], "language_level": [], "hard_skills": ["graphics", "indesign", "illustrator", "video editing", "multimedia", "after effect", "photoshop"], "soft_skills": ["independent", "communication skill", "meet tight deadline", "creative", "work under pressure"], "languages_combined": []}, "experience_required": {"duration": [], "field": []}}, {"job_id": "100003009039233", "location_code": "hk", "company": "The University of Hong Kong", "job_title": "Project Associate", "description": "\u5d17\u4f4d\u8077\u8cac\uff1a\n\n\u8ca0\u8cac\u9cf3\u51f0\u79c0\u65b0\u5a92\u9ad4\u7522\u54c1\u8996\u89ba\u8a2d\u8a08\u3001\u98a8\u683c\u898f\u7bc4\u8f38\u51fa\u8207\u5236\u5b9a\uff0c\u4ee5\u53ca\u73fe\u6709\u8996\u89ba\u7684\u512a\u5316\u8207\u7dad\u8b77\uff1b\n\n\u8ca0\u8cac\u8a2d\u8a08\u5c08\u6848\u524d\u671f\u898f\u5283\uff0c\u7522\u51fa\u5275\u610f\uff0c\u5236\u5b9a\u7db2\u8def\u548c\u8a2d\u8a08\u63d0\u6848\uff0c\u4e26\u628a\u63a7\u843d\u5730\u5be6\u6548\uff1b\n\n\u5c0d\u6574\u9ad4\u8a2d\u8a08\u6d41\u884c\u8da8\u52e2\u6709\u654f\u92b3\u7684\u6d1e\u5bdf\u8207\u898b\u89e3\uff0c\u80fd\u5c07\u5176\u904b\u7528\u5728\u9cf3\u51f0\u79c0\u5275\u65b0\u7684\u6574\u9ad4\u8996\u89ba\u98a8\u683c\u548c\u54c1\u724c\u8a2d\u8a08\u4e2d\uff1b\n\n\u5f15\u9818\u5718\u968a\u8996\u89ba\u8a2d\u8a08\u601d\u7dad\u7684\u5275\u65b0\uff0c\u5be6\u73fe\u8996\u89ba\u8a2d\u8a08\u5448\u73fe\u5728\u4f7f\u7528\u8005\u9ad4\u9a57\u4e0a\u7684\u5f15\u9818\u548c\u7a81\u7834\uff1b\n\n\u53c3\u8207\u524d\u77bb\u6027\u3001\u6982\u5ff5\u6027\u7684\u5275\u610f\u8a2d\u8a08\u3002\n\n\u4efb\u8077\u8981\u6c42\uff1a\n\n\u5168\u65e5\u5236\u672c\u79d1\u4ee5\u4e0a\u5b78\u6b77\uff0c\u8a2d\u8a08\u985e\u76f8\u95dc\u5c08\u696d\uff0c\u5a92\u9ad4\u3001\u65b0\u5a92\u9ad4\u884c\u696d\u4e00\u5e74\u4ee5\u4e0a\u5de5\u4f5c\u7d93\u9a57\uff1b\n\n\u7cbe\u901aAdobe\u7cfb\u5217\u3001Sketch\u7b49\u8996\u89ba\u8a2d\u8a08\u8edf\u9ad4\uff0c\u5177\u5099\u57fa\u790e\u7684\u4ea4\u4e92\u9ad4\u9a57\u3001\u524d\u7aef\u958b\u767c\u3001\u5370\u5237\u6750\u6599\u7b49\u77e5\u8b58\uff0c\u80fd\u5920\u628a\u63a7\u4e0a\u4e0b\u6e38\u548c\u6700\u7d42\u8a2d\u8a08\u54c1\u8cea\uff1b\n\n\u5177\u5099\u958b\u95ca\u7684\u8a2d\u8a08\u8996\u91ce\u548c\u5be9\u7f8e\u80fd\u529b\uff0c\u5275\u9020\u6027\u601d\u7dad\uff0c\u80fd\u63d0\u51fa\u539f\u5275\u6027\u60f3\u6cd5\u4e26\u8f49\u5316\u70ba\u8a2d\u8a08\u65b9\u6848\uff1b\n\n\u5177\u5099\u512a\u79c0\u7684\u6e9d\u901a\u80fd\u529b\uff0c\u5206\u6790\u554f\u984c\u548c\u89e3\u6c7a\u554f\u984c\u7684\u80fd\u529b\u3001\u8f03\u5f37\u7684\u5718\u968a\u5408\u4f5c\u7cbe\u795e\u3002", "employment_types": ["Full Time"], "selling_points": ["Hong Kong residents and fresh graduates", "have web-based digital skills", "provide support for events & workshops & projects"], "locations": ["Pok Fu Lam"], "categories": ["Media & Advertising", "Creative / Design"], "post_time": "2022-01-11T09:06:29Z", "salary": {"currency": null, "max": null, "min": null, "period": "monthly", "term": null}, "salary_visible": false, "title_keywords": ["associate"], "responsibilities": [], "requirements": {"degrees": [], "majors": [], "languages": [], "language_level": [], "hard_skills": [], "soft_skills": [], "languages_combined": []}, "experience_required": {"duration": [], "field": []}}, {"job_id": "100003009046894", "location_code": "hk", "company": "Theorigo Limited", "job_title": "Front-End Developer / Senior Front-End Developer / Analyst Developer", "description": "Project Associate in the Common Core Office (Ref.: 511517) (to commence as soon as possible for one year)\u00a0\n\nThe Common Core (https://commoncore.hku.hk/), HKU\u2019s distinctive form of holistic and integrative undergraduate education, is seeking a talented recent graduate to join our team to create the best possible learning experience for students, colleagues, and local and international partners.\n\nApplicants should be Hong Kong residents and fresh graduates (existing staff of the University need not apply). They should be self-motivated; have an excellent command of written and spoken English and Chinese; possess\u00a0very good communication, interpersonal and organizational skills, as well as web-based digital skills and facility with MS Word. Video and textual editing skills and some experience in using technology related to an educational context would be preferred.\n\nThe appointee will, in particular, provide appropriate support for events and workshops as well as for projects focused on gamification, the UN\u2019s Sustainable Development Goals (SDGs), and on transdisciplinary research. Shortlisted candidates will be invited to attend an interview and/or complete a written test.\n\nThe University only accepts online applications for the above post.\u00a0 Applicants should apply online at the University's career site (https://jobs.hku.hk) and upload an up-to-date C.V. Review of applications will commence as soon as possible and continue until February 18, 2022, or until the post is filled, whichever is earlier.\n\nThe University is an equal opportunities employer and\nis committed to equality, ethics, inclusivity, diversity and transparency", "employment_types": ["Full Time", "Permanent"], "selling_points": ["HTML5, CSS3, React, React Native, Vue.js", "Building responsive websites & hybrid app", "1-3 years of experiences"], "locations": ["Wan Chai"], "categories": ["Media & Advertising", "Creative / Design", "Information Technology (IT)", "Application Specialist - Software", "Software Development"], "post_time": "2022-01-15T03:49:32Z", "salary": {"currency": null, "max": null, "min": null, "period": "monthly", "term": null}, "salary_visible": false, "title_keywords": ["analyst", "developer"], "responsibilities": ["communication", "editing", "review"], "requirements": {"degrees": [], "majors": [], "languages": ["english", "chinese"], "language_level": ["excellent"], "hard_skills": ["workshops", "c", "web", "ms word"], "soft_skills": ["organizational skills", "self-motivated", "focused", "communication", "committed", "learning", "interpersonal"], "languages_combined": [{"language": "english", "language_level": ["excellent"]}, {"language": "chinese", "language_level": ["excellent"]}]}, "experience_required": {"duration": [], "field": ["video", "related", "education", "editing", "team"]}}, {"job_id": "100003009037471", "location_code": "hk", "company": "Havas Worldwide Hong Kong Limited", "job_title": "Copywriter", "description": "We are looking for designers who are:\n\n\nCreative storyteller with excellent\u00a0art sense & execution skills\nExtensive experience in social media videos production\nProfessional in photo retouch, brochures design & typesetting\nExpert in printing's output requirements & procedures\n10 years+ experience\u00a0in Advertising industry\n\nWhat do our designers do:\n\nConcept, key visual development & typesetting for printed materials\nIdea & concept development for videos\nArt direction for photo shooting\nHandle ATL & BTL jobs with minimal supervision\nInterested candidates please attach your\u00a0Job reference,\u00a0CV\u00a0&\u00a0Expected\u00a0Salary\u00a0with your application", "employment_types": ["Full Time", "Permanent"], "selling_points": ["5-day work week, birthday and other special leaves", "Creative and passionate thinker", "Experience with SEO concepts is an added advantage"], "locations": ["Kwun Tong"], "categories": ["Media & Advertising", "Creative / Design", "Strategic Planning", "Editorial / Journalism"], "post_time": "2022-01-11T02:55:08Z", "salary": {"currency": null, "max": null, "min": null, "period": "monthly", "term": null}, "salary_visible": false, "title_keywords": ["copywriter"], "responsibilities": ["social media", "advertising", "procedures", "design", "photo retouch", "visual"], "requirements": {"degrees": [], "majors": [], "languages": [], "language_level": [], "hard_skills": [], "soft_skills": ["creative", "extensive"], "languages_combined": []}, "experience_required": {"duration": [], "field": ["social media", "advertising industry"]}}, {"job_id": "100003009035752", "location_code": "hk", "company": "Rhapsody Factory", "job_title": "Art Director / Senior Graphic Designer", "description": "RESPONSIBILITIES:\n\nLife Changing Idea-Centric Creative\n\n\nGood art direction sense and production skill\nWork with creative team to achieve high efficiency, high quality visual art, graphic design, art direction and motion graphics\nWork with the copywriter to develop and execute the production.\nHelp the project to be completed on time budget\nResponsible for the internal multi-client project needs and Solutions\nContribute to big ideas and IMC ideas\n\nREQUIREMENTS:\n\n\n\u00a0 \u00a0 \u00a0 \u00a0 \u00a00-5 years\u2019 experience in advertising design. Experience in IMC and digital projects\n\u00a0\u00a0\u00a0\u00a0\u00a0\u00a0\u00a0\u00a0 Good at style of art, skilled use of adobe suite software\n\u00a0\u00a0\u00a0\u00a0\u00a0\u00a0\u00a0\u00a0 Able to work under pressure, strong sense of responsibility, team spirit\n\u00a0\u00a0\u00a0\u00a0\u00a0\u00a0\u00a0\u00a0 Able to work with high quality and efficiency", "employment_types": ["Full Time"], "selling_points": ["Designer with 10 years+ experience", "Friendly teammates + Comfy office + Stable job", "5 days work + 9 days AL + Bday leave + medical"], "locations": ["Kowloon Bay"], "categories": ["Media & Advertising", "Creative / Design", "Design", "Graphics", "Print Media"], "post_time": "2022-01-10T08:28:57Z", "salary": {"currency": null, "max": null, "min": null, "period": "monthly", "term": null}, "salary_visible": false, "title_keywords": ["art director", "senior graphic designer"], "responsibilities": ["ideas", "graphic design", "budget", "quality", "develop", "motion graphics", "visual"], "requirements": {"degrees": [], "majors": [], "languages": [], "language_level": [], "hard_skills": ["adobe"], "soft_skills": ["sense of responsibility", "team spirit", "work under pressure"], "languages_combined": []}, "experience_required": {"duration": ["0-5 years"], "field": ["digital", "advertising", "design"]}}, {"job_id": "100003009039822", "location_code": "hk", "company": "ViuTV", "job_title": "Production Assistant", "description": "Your New Role:\n\nAssist Producer in all aspects of production\nCoordinate with internal and external parties to ensure a smooth production operations\n\nWhat makes you succeed:\u00a0\n\n\nDegree or diploma holder, preferably in Mass Media Communications, Graphic Design or related disciplines\n1 year of relevant experience\nProficient in Premiere, After Effect and Final Cut Pro\nCreative mind with strong conceptual and execution skills\nDetail-minded, a good team player\nGood communication skills and able to work under pressure and meet tight deadlines\n\nWant to be one of us?\n\nIf you have the desire to create an exciting and rewarding career, please send us your resume immediately, quoting the reference number, your present and expected salary to\u00a0Human Resources Department by clicking \"Apply Now\".\n\n\nFor more information on other job opportunities of PCCW, please visit our website at\u00a0http://www.pccw.com/Careers/Job+Opportunities+%26+Application/Current+Opportunities?language=en_US\nPCCW is an equal opportunity employer and welcomes applications from all qualified candidates. Information provided will be treated in strict confidence and will only be used for recruitment-related purposes. Personal data provided by job applicants will be used strictly in accordance with the employer\u2019s\u00a0privacy statement\u00a0(www.pccw.com/privacy-statement/index.page), a copy of which will be provided immediately upon request.", "employment_types": ["Full Time"], "selling_points": ["Assist Producer in all aspects of production", "Ensure a smooth production operations", "1 year of relevant experience"], "locations": ["Kowloon Bay"], "categories": ["Media & Advertising", "Creative / Design", "Production", "Broadcasting - TV / Radio"], "post_time": "2022-01-11T11:40:46Z", "salary": {"currency": null, "max": null, "min": null, "period": "monthly", "term": null}, "salary_visible": false, "title_keywords": ["production assistant"], "responsibilities": ["operations", "graphic design", "internal and external parties", "coordinate with", "website", "communication", "recruitment", "personal data", "work under pressure"], "requirements": {"degrees": ["diploma holder", "degree"], "majors": ["related disciplines", "graphic design", "mass media", "communications"], "languages": [], "language_level": [], "hard_skills": ["final cut pro", "after effect", "premiere"], "soft_skills": ["detail-minded", "communication skills", "good team player", "meet tight deadlines", "confidence", "smooth", "creative", "work under pressure"], "languages_combined": []}, "experience_required": {"duration": ["1 year"], "field": ["relevant experience"]}}, {"job_id": "100003009038562", "location_code": "hk", "company": "Lemontree Tech Limited", "job_title": "Social Media Content Editor ( Digital Marketing )", "description": "Lemontree Tech Limited\nwww.lemontree-tech.com\n\nSOCIAL MEDIA EDITOR & DESIGNER\n\nJOB HIGHLIGHTS:\n\nGood conceptual thinking, creative and positive\nPassion in writing about marketing related articles\nExcellent command of writing in Chinese & English\n\nYOUR ROLE:\n\nResearch and brainstorm creative and exciting content ideas with sales\u00a0 manager to create high caliber contents in both English and Chinese on online and offline platforms, including Company websites , Facebook, Instagram and all other marketing materials.\u00a0\nManage all visual and product listing on online store ( including photo shoots, product description writing\u00a0\nWork closely and collaborate with senior designer and external marketing team on promotion, campaign and new product launch\nPerform ad-hoc projects and assist in operation jobs as assigned\n\nREQUIREMENTS:\n\nBachelor\u2019s Degree or above\u00a0in related disciplines\nFamiliar with social media culture and media tools such as Facebook and Instagram\nGood command & writing in English and Chinese\nExcellent communication and interpersonal skills\nRelevant experience as editor/graphic designer or related field is preferred\nKnowledge of Adobe Illustrator and photoshop is preferred\nWelcome fresh graduate\n\nBENEFITS:\n\nOpen-minded leader\nPassionate team member\nYearly Bonus\nAn opportunity to join a growing business\nWorking in a friendly working environment\u00a0\nFree snacks is provided\nAttractive salary and comprehensive benefits\nInterested parties should send their full resumes, stating their current and expected salaries via\n1) email\u00a0\n2) OR by clicking \"Apply Now\".\u00a0\n\nPersonal Information collected will be used for recruitment purpose only", "employment_types": ["Full Time", "Part Time", "Internship"], "selling_points": ["Excellent command of writing in Chinese & English", "Passionate about marketing and technology", "Welcome fresh graduate"], "locations": ["Kwai Hing"], "categories": ["Media & Advertising", "Creative / Design", "Editorial / Journalism", "Marketing / Public Relations", "Digital Marketing"], "post_time": "2022-01-11T07:23:32Z", "salary": {"currency": null, "max": null, "min": null, "period": "monthly", "term": null}, "salary_visible": false, "title_keywords": ["digital marketing", "social media content editor"], "responsibilities": ["company websites", "social media", "collaborate with", "ideas", "product listing", "communication", "visual", "contents", "marketing materials", "facebook", "ad-hoc projects"], "requirements": {"degrees": ["degree or above", "bachelor", "fresh graduate"], "majors": ["related disciplines"], "languages": ["english", "chinese"], "language_level": ["excellent", "good command"], "hard_skills": ["facebook", "photoshop", "adobe illustrator"], "soft_skills": ["creative", "communication and interpersonal skills", "positive", "passion in"], "languages_combined": [{"language": "english", "language_level": ["excellent", "good command"]}, {"language": "chinese", "language_level": ["excellent", "good command"]}]}, "experience_required": {"duration": [], "field": ["designer", "editor", "related", "graphic", "relevant experience"]}}, {"job_id": "100003009037624", "location_code": "hk", "company": "PixelMaxx Production Limited", "job_title": "Motion Graphics Designer", "description": "What You Will Be Doing:\n\n\nUnderstand clients\u2019 needs and deliver creative and innovative business solutions;\nSharp creative mind, collaborate with Account Management team to pitching/developing new ideas to clients\nIdentify market opportunities and potential strategic partnerships to capture new business and to expand market share\nLead cross-functional creative teams to elevate the creative concept, design, and execution of various formats of contents\nAssist in developing overall corporate branding and marketing strategy\n\nWhat You Need for this Position:\n\n\nBachelor\u2019s degree on Marketing, Multimedia,, Communications, or related disciplines;\n1 years\u2019 experience in digital marketing agency\nFluent in Cantonese, English and Mandarin ;\nProficient in MS PowerPoint and Excel;\nMultimedia experience is preferred;\nExcellent communication and analytical skills;\nCorporately presentable and business savvy\nAble to work under pressure and tight deadlines;\nExcellent attention to detail, work independently, flexible and willing to learn;", "employment_types": ["Full Time"], "selling_points": [], "locations": ["Kowloon Bay"], "categories": ["Media & Advertising", "Creative / Design", "Design", "Multi-media", "Marketing / Public Relations", "Digital Marketing"], "post_time": "2022-01-11T03:19:14Z", "salary": {"currency": null, "max": null, "min": null, "period": "monthly", "term": null}, "salary_visible": false, "title_keywords": ["designer"], "responsibilities": ["collaborate with", "management team", "teams", "developing", "design", "developing new ideas", "communication", "digital marketing", "contents", "work under pressure"], "requirements": {"degrees": ["degree", "bachelor"], "majors": ["related disciplines", "marketing", "communications"], "languages": ["cantonese", "english", "mandarin"], "language_level": ["fluent"], "hard_skills": ["excel", "ms powerpoint", "multimedia", "analytical skills"], "soft_skills": ["flexible", "work independently", "willing to learn", "presentable", "communication", "analytical skills", "innovative", "attention to detail", "creative", "work under pressure"], "languages_combined": [{"language": "cantonese", "language_level": ["fluent"]}, {"language": "english", "language_level": ["fluent"]}, {"language": "mandarin", "language_level": ["fluent"]}]}, "experience_required": {"duration": ["1 years"], "field": ["agency", "digital marketing"]}}, {"job_id": "100003009043471", "location_code": "hk", "company": "New Page Communications Ltd", "job_title": "Junior Video Editor", "description": "Responsibilities and Prerequisites\n\nWe are looking for a talented and enthusiastic\u00a0Junior Video Editor to work with our\u00a0post-production team in primarily video editing, composition, and studio recording.\n\nThe ideal candidate needs to have a creative flair, up-to-date knowledge of software used in the industry, and effective management of time, deadlines, and costs.\u00a0\n\nThe ability to manage multiple projects simultaneously, and work well under pressure is a pre-requisite.\n\nRequirements:\n\nUniversity or College graduate, major in multi-media design or equivalent\n1-2 years of above related working experience\nProficiency in multi-media applications including AVID, After-effect & Photoshop\nStrong communication and interpersonal skills, MUST be a team player\nShift duty is required\nImmediate availability is preferred\n\nSalary:\n\nNegotiable and commensurate with experience.\u00a0\n\nInterested parties please send full resume with present and expected salary and work samples (video link is preferable) by clicking \u201cApply Now\u201d.\n\nAll personal data collected will be used for recruitment purpose only.", "employment_types": ["Full Time", "Permanent"], "selling_points": [], "locations": ["Kwun Tong Area"], "categories": ["Media & Advertising", "Creative / Design", "Production", "Design", "Multi-media"], "post_time": "2022-01-12T13:07:45Z", "salary": {"currency": null, "max": null, "min": null, "period": "monthly", "term": null}, "salary_visible": false, "title_keywords": ["video editor", "junior"], "responsibilities": ["management", "software", "manage multiple projects", "video editing", "costs"], "requirements": {"degrees": [], "majors": [], "languages": [], "language_level": [], "hard_skills": ["photoshop"], "soft_skills": ["team player", "communication and interpersonal skills"], "languages_combined": []}, "experience_required": {"duration": ["1-2 years"], "field": ["related"]}}, {"job_id": "100003009042084", "location_code": "hk", "company": "Sekgamdong Limited", "job_title": "Web designer", "description": "Responsibilities :\n\nResponsible for web application and mobile apps UI & UX design\n\nWork closely with Users to provide UX wireframe, flowcharts and UI layouts\nWork closely with developers to ensure the UI & UX are well implemented and met with quality\nExperience in designing responsive UI, wireframe and prototypes is required\nExperience in HTML, CSS and JavaScript is a big advantage\n\nRequirements :\n\nDiploma or above in Web / Graphic / Multimedia Design or related disciplines\nAt least 1 year experience in Web and Graphic Design\nExperience in Figma, Photoshop and Illustrator, knowledge of HTML, CSS and JavaScript will be an advantage\nExperience in UI design\nGood communication skills and a good team player\nAble to work independently, under pressure and meet tight schedule\nPortfolio links should be provided in the resume\n\n\nSalary and benefit will commensurate with qualifications and experience.\u00a0\nWe offer 5-day work, competitive remuneration package & good career opportunities to the qualified candidate.\n\nInterested parties, please\u00a0send your full resume with current and expected\u00a0salary to us via Email.", "employment_types": ["Full Time", "Permanent"], "selling_points": ["Creative", "Passionate", "Interactive"], "locations": ["Hung Hom"], "categories": ["Media & Advertising", "Creative / Design", "Production", "Design", "Web Designer"], "post_time": "2022-01-12T05:59:43Z", "salary": {"currency": null, "max": null, "min": null, "period": "monthly", "term": null}, "salary_visible": false, "title_keywords": ["designer"], "responsibilities": ["quality", "ui", "design", "designing"], "requirements": {"degrees": ["diploma or above"], "majors": ["multimedia design", "related disciplines"], "languages": [], "language_level": [], "hard_skills": ["web", "illustrator", "html", "javascript", "multimedia", "css", "photoshop"], "soft_skills": ["communication skills", "good team player", "under pressure", "work independently"], "languages_combined": []}, "experience_required": {"duration": ["at least 1 year"], "field": ["graphic design", "design"]}}, {"job_id": "100003009042072", "location_code": "hk", "company": "Osmium Consulting Group Limited", "job_title": "UI / UX Designer | 38k-48k", "description": "Responsibilities:\u00a0\n\nSolid experience in Graphic Design and Advertising;\nResponsible for graphic design from design concept to final artwork\u00a0independently;\nLead and execute designs such as communication materials (EDM, souvenirs, online banners and materials for various social media platforms etc.);\nWork closely with internal teammates and other departments to ensure requirements and deadlines are met;\nAble to come up with creative ways for video production and editing;\nWork with different creators and empower their video contents;\n\nRequirements:\u00a0\u00a0\n\nDiploma or above in Art, Graphic Design, Multimedia or related disciplines in Graphic Design;\nAt least 3-5 years relevant experience in graphic design, with digital marketing agency exposure preferred;\nProficient in Photoshop, Adobe Illustrator of Mac environment;\nExperience in web design and front-end web development; \u00a0\nStrong creative senses, well organized, mature, highly responsible and independent;\nExcellent communication, interpersonal and teamwork skills with good spoken and written Mandarin and English;\n\nPlease attach your portfolio in email or URL in resume\n\nInterested candidates should apply with full resume stating expected salary\u00a0by clicking \"Apply Now\".\n\nAll personal data collected will be kept confidential and used for recruitment purpose only.", "employment_types": ["Full Time"], "selling_points": ["UX UI Designer | In House | Rare Opportunity", "5 Days Work | Bouns | Med", "Work From Home"], "locations": ["Not Specified"], "categories": ["Media & Advertising", "Creative / Design", "Design", "Web Designer", "Information Technology (IT)", "UI/UX Designer"], "post_time": "2022-01-12T05:54:06Z", "salary": {"currency": null, "max": null, "min": null, "period": "monthly", "term": null}, "salary_visible": false, "title_keywords": ["ux designer"], "responsibilities": ["advertising", "edm", "video production", "graphic design", "design concept", "social media platforms", "communication", "banners", "contents", "editing"], "requirements": {"degrees": ["diploma or above"], "majors": ["related disciplines", "graphic design", "art"], "languages": ["english", "mandarin"], "language_level": ["excellent", "good"], "hard_skills": ["web design", "web development", "mac environment", "adobe illustrator", "multimedia", "photoshop"], "soft_skills": ["independent", "responsible", "teamwork", "well organized", "mature", "communication", "creative", "interpersonal"], "languages_combined": [{"language": "english", "language_level": ["excellent", "good"]}, {"language": "mandarin", "language_level": ["excellent", "good"]}]}, "experience_required": {"duration": ["at least 3-5 years"], "field": ["agency", "graphic design", "development", "design", "relevant experience", "digital marketing"]}}, {"job_id": "100003009038126", "location_code": "hk", "company": "Eagle Sky Media Limited", "job_title": "Social media / Digital Marketing Officer (Advertising Agency , Digital Marketing)", "description": "\u00a0Responsibilities :\nDesign product flows and journeys that optimize user experience based on the acquired insights as well as business and technical requirements.\u00a0\nFollow through product from concept development, artwork design\u00a0and production\nExecute creative solutions to meet the client needs\nDevelop pixel-perfect UI components that are ready for production and ensure design consistency across different app and web platforms.\nDevelop pixel-perfect UI components that are ready for production and ensure design consistency across different app and web platforms.\nCreate compelling user interface designs for Mobile apps and\nwebsites\n\n\u00a0Requirements :\n\nDiploma or above in Graphic / Multimedia Design or related\u00a0disciplines\n3+ years of UX and UI design experience and have experience designing for large customer-facing platforms.\nUnderstanding of UI/UX design methodologies on mobile and desktop platform\nStrong skilled in Figma, Adobe, Sketch, etc.\n\nStrong self-motivation to start and run the work individually and with the teams.\n\nGood understanding of interaction, journeys and prototyping is an advantage\nSelf-motivated, willing to learn, and a strong sense of responsibility and commitment\nExperienced in the Website interface will be an advantag\nMore experience shall be considered as a Senior\u00a0UI / UX Designer", "employment_types": ["Full Time"], "selling_points": ["Socail media management", "Advertising Agency", "designer"], "locations": ["Tsuen Wan Area"], "categories": ["Media & Advertising", "Creative / Design", "Design", "Graphics", "Marketing / Public Relations", "Digital Marketing"], "post_time": "2022-01-11T05:21:02Z", "salary": {"currency": null, "max": null, "min": null, "period": "monthly", "term": null}, "salary_visible": false, "title_keywords": ["digital marketing officer", "digital marketing"], "responsibilities": ["user experience", "design", "develop", "user interface", "ui"], "requirements": {"degrees": ["diploma or above"], "majors": ["multimedia design", "related disciplines"], "languages": [], "language_level": [], "hard_skills": ["mobile", "adobe", "multimedia"], "soft_skills": ["self-motivated", "self-motivation", "willing to learn", "sense of responsibility"], "languages_combined": []}, "experience_required": {"duration": ["3+ years"], "field": ["designer", "design"]}}, {"job_id": "100003009038690", "location_code": "hk", "company": "AAStocks.com Limited", "job_title": "Reporter (Ref.: Fintv)", "description": "Responsibilities:\nSocial media management including content development & consumer engagement\nCommunicate and extent good relationships with on-line media, KOL, vendors & platform partners\nAnalyze market trends and explore new marketing techniques & business opportunities\nParticipate and support internal teams for different marketing campaign and operation needs\nPrepare marketing proposal for client\nPrepare regular reports for management review\nParticipate & support in all new business initiatives and all ad hoc projects\nGood content writer\nStrong Creative Designer is much preferred\n\nRequirements:\n\nDegree holder in Marketing / Communication / Multi-media Design preferred\nMin. 2 years\u2019 experienced in marketing\nExcellent interpersonal, presentation and communication skills\nProficient in MS Word, Excel, PowerPoint and Chinese Word Processing\nFluency in written and spoken Chinese and English\nExperience in CMS (Wordpress) ,graphic design tools (Adobe Photoshop and Adobe Illustrator)\nDetail-minded, tech-savvy, outgoing, and flexible to work\nHard-working, willing to learn and able to handle multi-task, work under pressure and meet deadlines\nCandidate with more experienced will be considered as Senior Marketing Executive", "employment_types": ["Full Time", "Permanent"], "selling_points": ["Conducting voice-over work", "Cheerful, Initiative, Outgoing, Self-motivated", "At least 1 year relevant media working experience"], "locations": ["Not Specified"], "categories": ["Media & Advertising", "Creative / Design", "Others", "Editorial / Journalism"], "post_time": "2022-01-11T07:38:38Z", "salary": {"currency": null, "max": null, "min": null, "period": "monthly", "term": null}, "salary_visible": false, "title_keywords": ["reporter"], "responsibilities": ["social media", "management", "business initiatives", "business opportunities", "review", "teams", "regular reports for management", "ad hoc projects"], "requirements": {"degrees": ["degree holder"], "majors": ["marketing", "design"], "languages": ["english", "chinese"], "language_level": ["fluency", "proficient"], "hard_skills": ["excel", "chinese word processing", "adobe photoshop", "powerpoint", "adobe illustrator", "wordpress", "ms word"], "soft_skills": ["detail-minded", "communication skills", "outgoing", "flexible", "multi-task", "willing to learn", "communication", "hard-working", "meet deadlines", "interpersonal", "presentation", "work under pressure"], "languages_combined": [{"language": "english", "language_level": ["fluency"]}, {"language": "chinese", "language_level": ["fluency", "proficient"]}]}, "experience_required": {"duration": [], "field": ["graphic design"]}}, {"job_id": "100003009039821", "location_code": "hk", "company": "ViuTV", "job_title": "Research Writer", "description": "RESPONSIBILITIES:\n\nLife Changing Idea-Centric Creative\n\nComplete project independently with quality and quantity in efficient manner\nLead a small task team to provide creative strategies and guide and supervise the team's creative execution\nIndependent creative thinking ability and logical thinking ability, excellent creative ability and art direction ability, push for more idea-driven with exceeding intention\nAbility to draft proposals, rich experience in project management and team building, strong communication skills, and be able to provide necessary training and guidance to the Department to complete tasks and improve work efficiency\nGood communication, coordination, able to create a good atmosphere for the team\n\nREQUIREMENTS:\n\nAt least 5 years working experience in traditional and digital advertising\nGood consumer insight, want to send idea, superior art ability\nGood at style of art, skilled use of adobe suite software\nEnglish and Chinese in communication level\nActive thinking, good communication skills, enthusiasm and sense of responsibility, and team spirit\nRegional FMCG and Healthcare experience both online and offline", "employment_types": ["Full Time"], "selling_points": ["Producing top quality TV Programmes", "1 to 3 years experience in TV production", "Good script writing skills"], "locations": ["Kowloon Bay"], "categories": ["Media & Advertising", "Creative / Design", "Production", "Broadcasting - TV / Radio"], "post_time": "2022-01-11T11:39:56Z", "salary": {"currency": null, "max": null, "min": null, "period": "monthly", "term": null}, "salary_visible": false, "title_keywords": [], "responsibilities": ["guidance", "quality", "communication", "project management", "coordination"], "requirements": {"degrees": [], "majors": [], "languages": ["english", "chinese"], "language_level": [], "hard_skills": ["adobe"], "soft_skills": ["communication skills", "team spirit", "sense of responsibility", "communication", "active", "superior"], "languages_combined": [{"language": "english", "language_level": []}, {"language": "chinese", "language_level": []}]}, "experience_required": {"duration": ["at least 5 years"], "field": ["digital", "fmcg", "advertising", "healthcare"]}}, {"job_id": "100003009042079", "location_code": "hk", "company": "Sekgamdong Limited", "job_title": "Frontend developer", "description": "Job Responsibilities:\nManage and create content for various social media platforms (Facebook, Instagram, YouTube...), including copy writing, image and basic video editing\nHosting live programmes including news reporting, script writing, and analyst interviewing\nParticipating in news programme design and planning\nWriting feature articles\nConducting voice-over work\nDoing research and assisting the production of live team\nJob Requirements:\nCheerful, Initiative, Outgoing, Self-motivated\nDegree holder, preferably in Journalism, Finance, Economics or Chinese Language\nAt least 1 year relevant media working experience (Fresh graduates are welcomed)\nFamiliar with stock market, listed company and financial analysis is an advantage\nFamiliar with digital media solutions (Social media, Facebook advertising, Google Analytics, SEO and SEM) is a plus\nProficiency in Chinese word processing", "employment_types": ["Full Time", "Permanent"], "selling_points": ["Creative", "Passionate", "Interactive"], "locations": ["Hung Hom"], "categories": ["Media & Advertising", "Creative / Design", "Production"], "post_time": "2022-01-12T05:58:56Z", "salary": {"currency": null, "max": null, "min": null, "period": "monthly", "term": null}, "salary_visible": false, "title_keywords": ["developer"], "responsibilities": ["reporting", "social media platforms", "design", "video editing", "facebook", "planning"], "requirements": {"degrees": ["degree holder"], "majors": ["journalism", "finance", "economics"], "languages": ["chinese"], "language_level": ["proficiency"], "hard_skills": ["google analytics", "plus", "seo", "chinese word processing", "financial analysis", "sem", "facebook"], "soft_skills": ["outgoing", "self-motivated", "cheerful", "initiative"], "languages_combined": [{"language": "chinese", "language_level": ["proficiency"]}]}, "experience_required": {"duration": ["at least 1 year"], "field": ["media"]}}, {"job_id": "100003009040069", "location_code": "hk", "company": "StarPro Agency Limited", "job_title": "Producer / Videographer", "description": "Your New Role:\n\n\nThe successful candidate will take on the challenge of formulating and producing top quality TV Programmes.\n\nWhat makes you succeed:\u00a0\n\n\nDegree / Diploma holder in any disciplines, preferably in TV Production / Mass Communications\n1 to 3 years experience in TV production\u00a0\nGood script writing skills\nOutgoing, creative and energetic\nA good team player\nPossess good communication skills and able to work under tight schedules and irregular hours\nExcellent in written and spoken English, Cantonese and Putonghua is a MUST\n\nWant to be one of us?\n\nIf you have the desire to create an exciting and rewarding career, please send us your resume immediately, quoting the reference number, your present and expected salary to\u00a0Human Resources Department by clicking \"Apply Now\".\n\n\nFor more information on other job opportunities of PCCW, please visit our website at\u00a0http://www.pccw.com/Careers/Job+Opportunities+%26+Application/Current+Opportunities?language=en_US\nPCCW is an equal opportunity employer and welcomes applications from all qualified candidates. Information provided will be treated in strict confidence and will only be used for recruitment-related purposes. Personal data provided by job applicants will be used strictly in accordance with the employer\u2019s\u00a0privacy statement\u00a0(www.pccw.com/privacy-statement/index.page), a copy of which will be provided immediately upon request.", "employment_types": ["Full Time"], "selling_points": ["5 days work", "year end bonus", "Degree or diploma holder"], "locations": ["Tsim Sha Tsui"], "categories": ["Media & Advertising", "Creative / Design", "Photography / Video", "Marketing / Public Relations", "Digital Marketing"], "post_time": "2022-01-12T01:13:30Z", "salary": {"currency": null, "max": null, "min": null, "period": "monthly", "term": null}, "salary_visible": false, "title_keywords": ["producer", "videographer"], "responsibilities": ["schedules", "quality", "website", "communication", "recruitment", "personal data"], "requirements": {"degrees": ["diploma holder", "degree"], "majors": ["any disciplines", "communications"], "languages": ["cantonese", "putonghua", "english"], "language_level": ["excellent"], "hard_skills": ["writing skills"], "soft_skills": ["outgoing", "communication skills", "good team player", "confidence", "creative", "writing skills", "energetic"], "languages_combined": [{"language": "cantonese", "language_level": ["excellent"]}, {"language": "putonghua", "language_level": ["excellent"]}, {"language": "english", "language_level": ["excellent"]}]}, "experience_required": {"duration": ["1 to 3 years"], "field": ["tv production"]}}, {"job_id": "100003009038394", "location_code": "hk", "company": "\u7d93\u6fdf\u4e00\u9031 EDigest", "job_title": "Social Media Executive/Digital Content Executive/Growth Editor (Business & Finance)", "description": "Responsibilities :\n\n\nWork closely with designers, project managers and developer\nDeliver and maintain high quality interface implementation to enable a great user experience.\u202f\u00a0\nOwn the products\u2019 interface implementation (HTML, CSS, presentational JS) and work with other teams to maintain a style guide for others to\u00a0reference.\u00a0\n\nRequirements :\n\nHigher Diploma or above in Computer Science, Software Engineering, Multimedia design or other relevant disciplines;\nA minimum of 1 years\u2019 experiences in web development;\nProficiency in HTML5, CSS3, JavaScript framework like Vue.js, React, jQuery, next.js/ nuxt.js;\nWell understanding in Nodejs/ JavaScript, Typescript is plus;\nBasic understanding of server-side CSS pre-processing platforms, such as LESS and SASS;\nSolid Experience with modern browser compatible responsive layout;\nExperience with RESTful API integration and version control through GIT;\nIndependent, self-disciplined, well communication, responsible, good problem solving skill and a good team player;\nImmediately available is preferable;\u00a0\n\nSalary and benefit will commensurate with qualifications and experience.\u00a0\nWe offer 5-day work, competitive remuneration package & good career opportunities to the qualified candidate.\n\nInterested parties, please\u00a0send your full resume with current and expected\u00a0salary to us via Email.", "employment_types": ["Full Time", "Permanent"], "selling_points": ["Content development & data analysis", "Experience in social media marketing field", "Great development opportunity, competitive package"], "locations": ["Kwun Tong"], "categories": ["Media & Advertising", "Creative / Design", "Others", "Editorial / Journalism"], "post_time": "2022-01-11T06:45:09Z", "salary": {"currency": null, "max": null, "min": null, "period": null, "term": null}, "salary_visible": false, "title_keywords": ["editor", "digital content executive", "social media executive"], "responsibilities": ["teams", "quality", "implementation", "user experience", "maintain"], "requirements": {"degrees": ["higher diploma or above"], "majors": ["multimedia design", "software engineering", "computer science"], "languages": [], "language_level": [], "hard_skills": ["web development", "plus", "basic", "restful api", "integration", "react", "git", "jquery", "problem solving", "javascript", "typescript", "multimedia", "server", "css", "processing"], "soft_skills": ["good team player", "independent", "responsible", "communication", "problem solving skill", "responsive"], "languages_combined": []}, "experience_required": {"duration": ["minimum of 1 years"], "field": ["development"]}}, {"job_id": "100003009034174", "location_code": "hk", "company": "Asia One HK Limited", "job_title": "Wedding Photographer / Photographer's Assistant", "description": "Job Highlights\n\nDegree holder with 2 years\u2019 experience\nAdvertising / Digital Media Writing\n5 days work with Medical insurance cover\n\nJob Description\n\nGenerate content in Social Media for our Clients (English and Chinese);\nPlan and execute marketing content, social media creatives and any marketing materials;\nWriting, reviewing, editing and updating content for website, Mainly social media platforms like FB and IG: content marketing\u00a0 Development.\nCreate and produce content for promotional campaigns.\nConduct research to learn about current trends and implement them in the content created;\nWork closely with teammates to establish campaign objectives, identify and solve problems;\nPerform ad-hoc tasks as required\nJob Requirements\n\nDegree / higher Diploma in Marketing, Journalism, Multimedia or related discipline;\nAt least 2 years\u2019 experience;\nGood command of both written and spoken English and Chinese is a MUST;\nDigital Marketing Agency Background is a huge Plus;\nFamiliar with different marketing tools;\nGoal oriented personality and be able to work independently as well as part of a team\nInterested candidates, please click the apply now button to submit your", "employment_types": ["Full Time", "Part Time", "Permanent", "Internship"], "selling_points": ["Performance Bonus", "High Remuneration", "5-day work"], "locations": ["Kowloon Bay"], "categories": ["Media & Advertising", "Creative / Design", "Production", "Photography / Video"], "post_time": "2022-01-10T02:53:49Z", "salary": {"currency": "HKD", "max": 24999, "min": 17000, "period": "monthly", "term": null}, "salary_visible": true, "title_keywords": ["assistant", "photographer"], "responsibilities": ["social media", "ad-hoc tasks", "social media platforms", "website", "plan", "marketing materials", "editing", "conduct research"], "requirements": {"degrees": ["diploma", "degree"], "majors": ["journalism", "marketing"], "languages": ["english", "chinese"], "language_level": ["good command"], "hard_skills": ["goal", "plus", "multimedia"], "soft_skills": ["work independently", "goal oriented"], "languages_combined": [{"language": "english", "language_level": ["good command"]}, {"language": "chinese", "language_level": ["good command"]}]}, "experience_required": {"duration": ["at least 2 years"], "field": []}}, {"job_id": "100003009036158", "location_code": "hk", "company": "Landcrowd Limited", "job_title": "UI designer - Recent Grads Welcome", "description": "Hello you.\nWe're a busy, growing design studio in Ngau Tau Kok area with a vacancy for an Art Director / Senior Graphic Designer.\u00a0We're looking for someone with 5+ years experience who has great attention to detail especially on product visuals and digital layout design, as well as a self-motivated positive pro-active attitude.\nExperience in product visualization and consumer electronics market preferred.\nWhat will you be doing?\n1)\u00a0Direct our 3D rendering team to create product visuals\u00a0that include beauty shots and technical feature illustrations. You will work with other designers to determine how to show communicate/visualize product functions in the best way possible and direct 3D illustrations. Knowing how to sketch is very important to generate and communicate ideas to the rendering team.\u00a0You will\u00a0be the person who will QC render quality and accuracy.\u00a0\n\n2) Create engaging digital layout concept design, based on our client's brand guidelines, to communicate/ highlight product benefits and features for sites such as Amazon, JD.com and Tmall.\n3)\u00a0Work with our PM to define/clarify project scope and expectation, present design and manage feedback and revision. You will need to be able to\u00a0communicate with confidence in\u00a0Putonghua\u00a0and\u00a0Cantonese\u00a0with clients.\u00a0\n4) Be\u00a0nice and pleasant\u00a0to everyone you work with.\nOur work environment is democratic and relaxed, but we expect everyone to carry their own responsibilities and most importantly, be happy and friendly.\u00a0Check out our work at www.coandco.hk to see our work and standards.\u00a0\nCompensation is based on your skill set and experience, please\u00a0specify your salary expectation\u00a0and include your portfolio when you apply.\u00a0\n\nThank you.\n\n", "employment_types": ["Full Time"], "selling_points": ["Fast-growing, profitable, exciting tech startup", "Friendly design-focused startup team/mentorship", "Strong career development, continuous learning"], "locations": ["Sheung Wan"], "categories": ["Media & Advertising", "Creative / Design", "Design", "Web Designer", "Information Technology (IT)", "UI/UX Designer"], "post_time": "2022-01-10T09:31:12Z", "salary": {"currency": "HKD", "max": 24999, "min": 17000, "period": "monthly", "term": null}, "salary_visible": true, "title_keywords": ["ui designer"], "responsibilities": ["communicate with", "ideas", "visualization", "3d rendering", "layout design", "quality", "design", "brand guidelines"], "requirements": {"degrees": [], "majors": [], "languages": ["cantonese", "putonghua"], "language_level": [], "hard_skills": ["nice", "amazon"], "soft_skills": ["self-motivated", "confidence", "pleasant", "friendly", "attention to detail", "pro-active", "positive"], "languages_combined": [{"language": "cantonese", "language_level": []}, {"language": "putonghua", "language_level": []}]}, "experience_required": {"duration": ["5+ years"], "field": ["digital", "design"]}}, {"job_id": "100003009050746", "location_code": "hk", "company": "AXA China Region Insurance Company Limited", "job_title": "Financial Manager \u7406\u8ca1\u7d93\u7406 / AXA Prime Program Trainee \u7ba1\u7406\u57f9\u8a13\u751f", "description": "WHO WE ARE AND WHAT WE DO:\n\nSpacious, Hong Kong's #1 internet property platform, is looking for a UI Designer, with a good sense of UX, to join our best-in-class Hong Kong based product team. You will work with a high-quality technology team of veterans and seasoned developers\u00a0to create amazing user experiences.\u00a0\n\nSpacious helps\u00a0to\u00a0make finding a property online\u00a0to\u00a0buy or rent easier and more efficient. Spacious has been providing the best-in-class search experience for property hunters in Greater China with its premium user interface, offering the highest quality listings and data comparisons for more than half a decade. This focus enables Spacious\u00a0to\u00a0generate the highest quality enquiries for property agents, developers, etc., who\u00a0pay\u00a0to\u00a0list.\n\nSpacious is a profitable, self-sustaining and proven business that is growing very quickly. We have over 1,000,000+ monthly high-value property searchers visiting our website/mobile app.\u00a0\n\nWe are a design-focused startup with a highly technical team with a technical founder who has coded various technologies for more than a decade.\u00a0UI/UX and technology are at the core of what we do and how we differentiate ourselves from our competition.\n\nFinding a home is one of life's most important (and stressful) events; by making the process easier, we positively impact people's lives every day with our work. Friends, family and strangers who have used Spacious to find a home often tell us how grateful they are for Spacious.\n\nWe are an international team with team members from the UK, USA, India and of course, Hong Kong.\nRoughly half our team are women.\nWe operate a friendly, collaborative company with diverse opinions in an environment that respects diversity and inclusion, from a top-quality office in the heart of Hong Kong.\nWe operate a flat organization with no strict reporting lines, open communication, and we trust our employees to manage their own time, offering a high degree of autonomy.\n\nThis is our website:\u00a0www.spacious.hk\nSpacious mobile apps are award winning on both Android and iOS apps.\n\nWHO WE ARE LOOKING FOR:\n\nDuties:\n(a)\u00a0Execute all visual design stages from concept to final hand-off to software engineering (50%)\n(b)\u00a0Collaborate with product management and engineering to define and implement innovative solutions for the product direction, visuals and experience (10%)\n(c)\u00a0Conceptualize original ideas that bring simplicity and user-friendliness to complex design roadblocks\u00a0(10%)\n(d)\u00a0Create wireframes, storyboards, user flows, process flows, and site maps to communicate interaction and design ideas effectively\u00a0(10%)\n(e)\u00a0Conduct user research and evaluate user feedback\u00a0(10%)\n(f)\u00a0Establish and promote design guidelines, best practices and standards (5%)\n(g) Help to create creative materials for paid ads, blog posts, social media,\u00a0clients content, offline banners when required (5%)\n\nRecent Grads welcome. This role is a fantastic opportunity to learn from one of Hong Kong's most experienced and highly skilled startup teams.\n\nThe ideal candidate should have an eye for clean and artful design, possess superior UI skills, translate high-level requirements into interaction flows and artefacts and transform them into beautiful, intuitive, and functional user interfaces.\n\nIf the challenge of working in an exciting, fast-paced startup that is growing quickly appeals to you, then get in touch.\n\nQualifications:\n\nDegree in design related subject.\nPrevious experience of UI Design for web and mobile App design or wireframing\nA portfolio of relevant design work (please attach samples as a cover letter or provide a link to your portfolio)\nPassionate about details and have a pixel-perfect obsession\nCareer Path\nSenior UI/UX Designer\nAs you gain experience and knowledge from the rest of the team - you will naturally move to more senior UX/UI roles with greater ownership levels. We have annual salary reviews and have quarterly catchups to offer feedback on how you are doing.\nUltimately this leads to a career path with people management leadership responsibilities.\n\nExperience\nRecent Grads Welcome\n\nWHY YOU SHOULD JOIN US:\n\nWe work in a fun, collaborative open space where we encourage creativity and ideas to flow freely.\u00a0\nYou'll be able to steer the future roadmap to improve our products, big or small, and see the results of your products reach our customers.\nGet to work with flexible working hours. Our priority is on getting the job done.\nFlat structure environment, you will be able to work independently and make your own choices.\nWe provide guidance and mentorship to polish your technical skills, business skills and entrepreneurship mindset.\nWe are one of the standout tech startups in Hong Kong, targeting a huge opportunity in Asia.\nBenefits\nExcellent monthly salary\nMPF\nMedical Insurance\n18 days annual leave\nA budget for continual learning", "employment_types": ["Full Time", "Internship"], "selling_points": ["\u6bcf\u6708\u6d25\u8cbc$15,000-$40,000+\u7121\u4e0a\u9650\u4f63\u91d1+ 9\u500b\u82b1\u7d05", "\u6bcf\u54684\u5e74\u5de5\u4f5c\uff0c\u5de5\u4f5c\u9748\u6d3b\u81ea\u4e3b\u5de5\u4f5c\u6642\u9593", "MDRT\u5e2b\u5f92\u5236\uff0c\u52a9\u4f60\u4ee5\u96f6\u6210\u672c\u5275\u696d"], "locations": ["Kwun Tong"], "categories": ["Media & Advertising", "Creative / Design", "Insurance", "Insurance Agent / Broker", "Marketing / Public Relations", "Digital Marketing"], "post_time": "2022-01-14T11:15:36Z", "salary": {"currency": "HKD", "max": 29999, "min": 14000, "period": "monthly", "term": null}, "salary_visible": true, "title_keywords": ["trainee", "financial manager"], "responsibilities": ["collaborate with", "ideas", "software", "data", "quality", "website", "design", "communication", "user interface", "banners", "storyboards", "mobile app", "teams", "visual", "ui", "reporting", "management", "social media", "design work", "guidelines", "evaluate"], "requirements": {"degrees": ["degree", "recent grads"], "majors": ["design"], "languages": [], "language_level": [], "hard_skills": ["clean", "small", "no", "web", "fun", "make", "mobile", "visual design", "c", "focus", "android"], "soft_skills": ["efficient", "flexible", "work independently", "creative", "focused", "collaborative", "communication", "diverse", "friendly", "leadership", "focus", "innovative", "superior", "passionate about", "ideal"], "languages_combined": []}, "experience_required": {"duration": [], "field": ["product management", "engineering", "design", "team"]}}, {"job_id": "100003009036242", "location_code": "hk", "company": "Omnipres Company Limited", "job_title": "Graphic Designer/ Senior Graphic Designer", "description": "Producer Video Production /Video Editing Multimedia /social media\n\nResponsibilities:\n- Work closely with design & marketing team to complete high quality of varies genre of videography\n- Responsible for video shoot including camera operation, lighting set up and audio recording\n-\u00a0Responsible for video editing and all the post-production process\n\nRequirements:\n- Degree or diploma holder, preferably in Communications, Graphic Design or related disciplines\n- Minimum 3-5 years experience in multimedia and video production or relevant working experience\n-\u00a0Proficient of video camera, also familiar with wide range of filming equipment (lights, audio & gimbal)\n-\u00a0Proficient in Premiere, After Effect and good knowledge in photoshop and illustrator.\n- Knowledge of Aerial photography is an advantage\n- Able to work independently and under pressure\n- Self-motivated, well-organized and a good team player\n-\u00a0Ability to multi-task and produce good content in tight schedule\n- Online portfolio is a must\nBenefit:\n- medical\n- early release on some festival dates\n- birthday leave\n- marriage leave\n\n", "employment_types": ["Full Time"], "selling_points": ["Highly creative in design with concrete skills", "Highly meticulous with driving excellence mindset", "Positive working attitudes & communications skills"], "locations": ["Lai Chi Kok"], "categories": ["Media & Advertising", "Creative / Design", "Design", "Graphics", "Print Media"], "post_time": "2022-01-10T09:51:25Z", "salary": {"currency": null, "max": null, "min": null, "period": "monthly", "term": null}, "salary_visible": false, "title_keywords": ["senior graphic designer", "graphic designer"], "responsibilities": ["production process", "quality", "design", "video editing", "audio"], "requirements": {"degrees": ["diploma holder", "degree"], "majors": ["related disciplines", "graphic design", "communications"], "languages": [], "language_level": [], "hard_skills": ["illustrator", "premiere", "multimedia", "after effect", "photoshop"], "soft_skills": ["good team player", "work independently", "under pressure", "self-motivated", "multi-task", "well-organized"], "languages_combined": []}, "experience_required": {"duration": ["minimum 3-5 years"], "field": ["video production", "relevant working experience"]}}, {"job_id": "100003009042790", "location_code": "hk", "company": "Sing Tao Management Services Limited", "job_title": "Account Executive / Senior Account Executive (Advertising Solution)", "description": "This position is suitable for those who have experience in social media platforms management, including FB, IG, Youtube and Linkedin. Fresh graduates who are familiar with social trends will be considered.\n\nJob Nature:\u00a0\u00a0\n\nFully responsible for social media activities (e.g. FB, IG, Youtube, Linkedin), on content development and execution, data analysis, strategy for growth etc.\nCreate core content that fit the channel nature\nHandle multiple projects simultaneously and manage various accounts/ campaigns in a timely and professional manner\nAnalyze data and insights to guide strategy and implementation of solutions\nTo manage campaigns deliverables and coordinate with the internal parties to implement digital campaigns\n\nCharacters / Qualifications:\u00a0\n\nDegree holder, 1+ years experience in social media marketing field. Candidates with more than 3 years experience will be considered for manager title.\nExperience in business/ and finance platform management will be an advantage\nDigitally savvy with strong interest in social trends\nDerive strong satisfaction in creating high engagement and viral content that fit our brands\nCheerful and creative, with marketing sense and data driven mind\nStrong communication skills and ability to influence counterparts/stakeholders at various levels\nSelf-motivated showing strong sense of ownership and able to work under pressure\n\nWe offer competitive salary and benefits package (5 days work, 14 days AL up, birthday leave, medical & dental insurance) with great opportunity for career development to the successful candidate.\n\nPlease send your detailed resume and expected salary to us by clicking \"Apply Now\" (please put position applied on subject line)", "employment_types": ["Full Time", "Permanent"], "selling_points": [], "locations": ["Tseung Kwan O"], "categories": ["Media & Advertising", "Account Servicing", "Creative / Design", "Sales, CS & Business Devpt", "Others"], "post_time": "2022-01-12T08:50:43Z", "salary": {"currency": null, "max": null, "min": null, "period": "monthly", "term": null}, "salary_visible": false, "title_keywords": ["account executive", "senior account executive"], "responsibilities": ["social media", "management", "data", "social media platforms", "professional manner", "implementation", "coordinate with", "data analysis", "communication", "digital campaigns", "career development", "analyze data", "multiple projects", "insurance", "internal parties", "work under pressure"], "requirements": {"degrees": ["degree holder"], "majors": ["marketing"], "languages": [], "language_level": [], "hard_skills": ["analysis"], "soft_skills": ["communication skills", "self-motivated", "cheerful", "marketing sense", "responsible", "timely", "detailed", "creative", "driven", "work under pressure"], "languages_combined": []}, "experience_required": {"duration": ["3 years", "1+ years"], "field": ["social media", "management", "finance", "business", "marketing"]}}]