[{"job_id": "100003009050497", "location_code": "hk", "company": "LABS Group Limited", "job_title": "Game Editor/\u904a\u6232\u6e2c\u8a66\u54e1 (English and Chinese)", "description": "\u00a0Motto: Are you a hardcore Gamer? Into Blockchain? Come and talk to us!\n\n\u00a0Responsibilities include:\n\nReview Gamefi / NFT / Blockchain Projects for content quality based on company requirements..\nAble to provide data & reports through analysis on market trends for Gamefi / NFTs.\nThoroughly check ad content with quality and accuracy.\nAnalyze data and evaluate trends/ patterns.\nRecommend generic marketing patterns / buying insight\nEscalating questions/issues from the team regarding the process and cascading updates to the team.\nPreparing weekly process reports & sending out to the concerned people.\nBecome a key personality within the team to potentially become a crypto influencer.\n\n\u00a0Requirements:\n\nMinimum 1 years of experience in\u00a0game QA testing,\u00a0developing test plans and test cases\nAim to choose crypto as long-term career pathStrong sense of art or degen in NFT discord channels is a plus\nHeavy game player is a strong bonusFull-time analyst\u00a0\nStrong communication\u00a0and\u00a0analytical skills\nFamiliar with the popular games released in past 5 years\n\nApplication Requirement:\n\nA writing sample that introduce you as a hardcore mobile gamer and why you're a good fit for us\n\n\n\nWhat We Offer:\n\nAttractive remuneration package that includes 5-day work\nPrivilege insurance plan for group medical (covers clinical, hospitalization with supplementary major medical) & dental\nConvenient office location in TsimShaTsui\nWork with the young and energetic team\nFree snacks, coffee, and tea\nFestival cash and gifts\nRegular staff activities\n\nPlease send your full resume in English, stating present and expected salary by clicking APPLY NOW.\n\nWe are an equal opportunity employer and welcome applications from all qualified candidates.\u00a0 Personal data collected will be treated in strictest confidence and handled confidentially by authorized personnel for recruitment-related purposes within the Group.", "employment_types": ["Full Time", "Permanent"], "selling_points": ["Joyful working environment with free snacks/drinks", "Young & friendly working environment", "5 days work medical and Dental Insurance"], "locations": ["Tsim Sha Tsui"], "categories": ["Media & Advertising", "Editorial / Journalism", "Information Technology (IT)", "Software Development", "Testing / QA"], "post_time": "2022-01-17T10:52:26Z", "salary": {"currency": null, "max": null, "min": null, "period": "monthly", "term": null}, "salary_visible": false, "title_keywords": ["editor"], "responsibilities": ["data", "analysis", "review", "quality", "evaluate", "reports", "analyze data"], "requirements": {"degrees": [], "majors": [], "languages": [], "language_level": [], "hard_skills": ["mobile", "plus", "crypto", "analytical skills"], "soft_skills": ["communication", "analytical skills"], "languages_combined": []}, "experience_required": {"duration": ["minimum 1 years"], "field": ["developing", "qa", "testing"]}}, {"job_id": "100003009054825", "location_code": "hk", "company": "Manner Production Limited", "job_title": "Scriptwriter \u7de8\u5287", "description": "Job Highlights\n\n\nFun, unique, young and joyful\nCreative and passionate believer in social media\nCreative lifestyle writing in native Cantonese\nProvide creative ideas for Original or ads video shooting\n\nJob Description\n\nResponsibilities:\n\n\nWrite story or script for videos, mainly for social platform and research ideas for screenplays\nDevelop relevant content to reach the company\u2019s target customers or original video shooting\nCreate an initial framework or shooting ways for screenplays\nCollaborate with creative team to interpret creative direction into persuasive copy concepts and scripts\nMaintain the idiographic creative philosophy but create a sense of unity throughout\nLink up the visual element of scenes to the specified plots and dialogue\nWork with producers and directors to brainstorm the script is needed\nLiaise with marketing, sales, artists team for production development\n\nRequirements:\n\n\nHigher Diploma or Degree or other related disciplines\nExperienced in social online media is preferred\nPassion in writing and good with research skills\nStrong sense of creativity, willing to accept new things or challenge\nGood communication skills, committed to work in a tight timeline\nWith high degree of responsibility and initiative, good team spirit\nCreative and passionate believer in social online media will be an advantage\nTravel to Macau maybe required\nImmediate available is highly preferred\nFresh Graduate also welcome\nA creative short script (\u4e2d\u6587\u5c0f\u5287\u672c) as\u00a0representative work with resume is needed\n\u6839\u64da\u64da\u8981\u6c42\u5b8c\u6210\u5287\u672c\u958b\u767c\n\u6709\u6545\u4e8b\u69cb\u601d\u80fd\u529b\uff0c\u7db2\u7d61\u5e73\u81fa\u53ca\u5e02\u5834\u89f8\u89ba\n\u7d44\u7e54\u908f\u8f2f\u80fd\u529b\u5f37 \u64c5\u9577\u6e9d\u901a\u5354\u8abf\n\nFor more information, please visit our website at\u00a0https://weilamanner.com/\n\nInterested parties please send detailed resume and\u00a0A\u00a0SHORT SCRIPT IN CHINESE\u00a0to us by clicking 'Apply Now'.Personal data collected will be used for recruitment purpose only.\n\n", "employment_types": ["Full Time"], "selling_points": ["sense of creativity", "committed to work in a tight timeline", "Outstanding in writing skills"], "locations": ["Causeway Bay"], "categories": ["Media & Advertising", "Production", "Editorial / Journalism"], "post_time": "2022-01-17T11:24:09Z", "salary": {"currency": null, "max": null, "min": null, "period": "monthly", "term": null}, "salary_visible": false, "title_keywords": [], "responsibilities": ["collaborate with", "ideas", "develop", "video shooting", "maintain", "visual", "liaise with"], "requirements": {"degrees": ["diploma", "degree", "fresh graduate"], "majors": ["related disciplines"], "languages": [], "language_level": [], "hard_skills": [], "soft_skills": ["passionate", "communication skills", "team spirit", "research skills", "passion in", "committed", "creative", "initiative"], "languages_combined": []}, "experience_required": {"duration": [], "field": []}}, {"job_id": "100003009055650", "location_code": "hk", "company": "Sing Tao News Corporation Limited (The Standard)", "job_title": "Trainee (Sub-Editor) \u2013 The Standard Subbing", "description": "Responsibilities:\n\nWrite compelling headlines, picture captions and story summaries\nCheck all names and facts; work with reporters to verify information and story details\nLearn the basics of newspaper page layout and production\nEdit copy written by reporters whose first language is not English\n\nRequirements:\n\nNative English speaker\nDegree holder majoring in Journalism, Mass Communications, English; Language or related discipline\n1-2 years\u2019 work experience; fresh graduates with positive attitude will be also considered\nSound local knowledge\nGood organizational skills and initiative; independent\nAble to work under extreme pressure and meet deadlines\nWilling to work antisocial hours\nWorking Location : Tseung Kwan O Industrial Estate\n\nInterested parties please\u00a0click \u201cApply Now\"\u00a0to submit your complete resume with\u00a0compensation history and expected salary or by\u00a0post to\u00a0Human Resources Department, 3/F, Sing Tao News Corporation Building, 7 Chun Cheong Street, Tseung Kwan O Industrial Estate, Tseung Kwan O, New Territories, Hong Kong.\n\nWe are an equal opportunity employer and welcome applications from all qualified candidates. Information provided will be treated in strict confidence and only be used for recruitment related purpose. Applicant who is not invited for an interview within 6 weeks may consider their application not successful. All personal data of unsuccessful applicants will be destroyed within 6 months.\n\nwww.singtaonewscorp.com\u00a0\n\n\n", "employment_types": ["Full Time", "Permanent"], "selling_points": [], "locations": ["Tseung Kwan O"], "categories": ["Media & Advertising", "Editorial / Journalism", "Print Media", "Others", "Student / Fresh Graduate / No Experience"], "post_time": "2022-01-18T02:50:04Z", "salary": {"currency": null, "max": null, "min": null, "period": "monthly", "term": null}, "salary_visible": false, "title_keywords": ["editor", "trainee"], "responsibilities": [], "requirements": {"degrees": ["degree holder"], "majors": ["journalism", "communications"], "languages": ["english"], "language_level": ["native"], "hard_skills": [], "soft_skills": ["organizational skills", "independent", "positive attitude", "meet deadlines", "initiative"], "languages_combined": [{"language": "english", "language_level": ["native"]}]}, "experience_required": {"duration": ["1-2 years"], "field": []}}, {"job_id": "100003009010878", "location_code": "hk", "company": "Television Broadcasts Limited (TVB)", "job_title": "Principal Subeditor (Pearl)", "description": "TVB News is inviting applications for a Principal Sub-Editor position for the English (Pearl) news desk.\n\n\nResponsibilities\n\n\nEdit and re-write local news stories and features\nWrite international news stories with voice over (based on wired stories)\nSupport the managing editor in editorial operations\nRequirements\n\nUniversity degree holder with at least 10 years\u2019 solid experience\nExcellent command of written and spoken English\nKnowledge of Cantonese not essential but would be an advantage\nShift duty is required \u00a0\nPlease send the application, quoting the appropriate reference number, with details of your qualifications and experience, expected salary and a contact telephone number to The Senior\u00a0Manager, Personnel Department,\u00a0Television Broadcasts Limited, TVB City, 77 Chun Choi Street, Tseung Kwan O Industrial Estate, Tseung Kwan O, Kowloon or email to us via Recruitment Centre.\n\n\nApplications received are solely for selection purpose. Those not invited for an interview within 4 weeks may consider their applications unsuccessful and their applications will be filed for another 3 months for future selection. Afterwards, all applications would be destroyed.", "employment_types": ["Full Time", "Permanent"], "selling_points": [], "locations": ["Others"], "categories": ["Media & Advertising", "Editorial / Journalism", "Broadcasting - TV / Radio"], "post_time": "2022-01-17T06:29:22Z", "salary": {"currency": null, "max": null, "min": null, "period": "monthly", "term": null}, "salary_visible": false, "title_keywords": [], "responsibilities": ["operations"], "requirements": {"degrees": ["university degree"], "majors": [], "languages": ["cantonese", "english"], "language_level": ["advantage", "excellent"], "hard_skills": [], "soft_skills": [], "languages_combined": [{"language": "cantonese", "language_level": ["advantage"]}, {"language": "english", "language_level": ["excellent"]}]}, "experience_required": {"duration": ["at least 10 years"], "field": ["recruitment"]}}, {"job_id": "100003009054723", "location_code": "hk", "company": "HK01 Company Limited", "job_title": "\u9805\u76ee\u7de8\u8f2f (Project Editor)", "description": "\u8077\u8cac\n\n\n\n\u7b56\u5283\u53ca\u64b0\u5beb\u80fd\u5438\u5f15\u5927\u773e\u7684\u7db2\u7d61\u5167\u5bb9\n\u5167\u5bb9\u884c\u92b7\uff0c\u70ba\u6f5b\u5728\u9867\u5ba2\u53ca\u7522\u54c1\u5275\u9020\u6709\u50f9\u503c\u7684\u5167\u5bb9\n\u88fd\u4f5c\u5546\u696d\u5408\u4f5c\u5167\u5bb9\uff0c\u4e26\u5354\u8abf\u5ee3\u544a\u5546\u696d\u5ba2\u6236\u8981\u6c42\uff08\u5305\u62ec\u4f46\u4e0d\u9650\u65bc\u751f\u6d3b\u8cc7\u8a0a\u3001\u5065\u5eb7\u3001\u6559\u80b2\u3001\u7f8e\u5bb9\u3001\u98f2\u98df\u53ca\u71b1\u8a71\u6587\u7ae0\u7b49\uff09\n\u57f7\u884c\u5167\u5bb9\u95dc\u9375\u5b57\u7b56\u7565\uff0c\u63d0\u5347\u53ca\u50b3\u64ad\u512a\u8cea\u5167\u5bb9\n\u6309\u9700\u8981\u51fa\u5e2d\u6216\u63a1\u8a2a\u5ba2\u6236\u6307\u5b9a\u6d3b\u52d5\uff0c\u6216\u53c3\u8207\u8a2a\u554f\u53ca\u76f8\u95dc\u62cd\u651d\u5de5\u4f5c\n\n\n\u5165\u8077\u8981\u6c42:\n\n\n\n\u5927\u5b78\u6216\u4ee5\u4e0a\u5b78\u6b77\u7a0b\u5ea6\uff0c\u5b78\u79d1\u80cc\u666f\u4e0d\u62d8\n2\u5e74\u6216\u4ee5\u4e0a\u5a92\u9ad4\u76f8\u95dc\u7d93\u9a57\uff0c\u5f9e\u4e8b\u65b0\u5a92\u9ad4\u7de8\u63a1\u5de5\u4f5c\u5c07\u512a\u5148\u8003\u616e\n\u719f\u6089\u751f\u6d3b\u985e\u578b\u984c\u6750\uff0c\u4ea6\u9858\u610f\u63a5\u89f8\u4e0d\u540c\u985e\u578b\u7684\u5167\u5bb9\u984c\u6750\n\u5177\u64b0\u5beb\u5546\u696d\u5408\u4f5c\u5167\u5bb9\u7d93\u9a57\u70ba\u4f73\uff0c\u80fd\u638c\u63e1\u8207\u5546\u696d\u5ba2\u6236\u7684\u6e9d\u901a\u548c\u8981\u6c42\n\u826f\u597d\u4e2d\u6587\u8b80\u5beb\u80fd\u529b\uff0c\u61c2\u5f97\u4e2d\u6587\u8f38\u5165\u6cd5\n\u5c0d\u4e92\u806f\u7db2\u53ca\u793e\u4ea4\u5e73\u53f0\u904b\u4f5c\u6709\u57fa\u672c\u6982\u5ff5\uff0c\u80fd\u5584\u7528Google Analytics\u53ca\u76f8\u95dc\u5206\u6790\u5de5\u5177\n\u5177\u6709\u5275\u610f\u3001\u7a4d\u6975\u4e3b\u52d5\u3001\u8655\u4e8b\u7d30\u5fc3\u3001\u5bcc\u8cac\u4efb\u611f\n\u5bcc\u5718\u968a\u5408\u4f5c\u7cbe\u795e\uff0c\u4e26\u80fd\u7368\u7acb\u5b8c\u6210\u5de5\u4f5c\u8077\u8cac\n\n\n\u7b56\u5283\u53ca\u64b0\u5beb\u80fd\u5438\u5f15\u5927\u773e\u7684\u7db2\u7d61\u5167\u5bb9\n\u5167\u5bb9\u884c\u92b7\uff0c\u70ba\u6f5b\u5728\u9867\u5ba2\u53ca\u7522\u54c1\u5275\u9020\u6709\u50f9\u503c\u7684\u5167\u5bb9\n\u88fd\u4f5c\u5546\u696d\u5408\u4f5c\u5167\u5bb9\uff0c\u4e26\u5354\u8abf\u5ee3\u544a\u5546\u696d\u5ba2\u6236\u8981\u6c42\uff08\u5305\u62ec\u4f46\u4e0d\u9650\u65bc\u751f\u6d3b\u8cc7\u8a0a\u3001\u5065\u5eb7\u3001\u6559\u80b2\u3001\u7f8e\u5bb9\u3001\u98f2\u98df\u53ca\u71b1\u8a71\u6587\u7ae0\u7b49\uff09\n\u57f7\u884c\u5167\u5bb9\u95dc\u9375\u5b57\u7b56\u7565\uff0c\u63d0\u5347\u53ca\u50b3\u64ad\u512a\u8cea\u5167\u5bb9\n\u6309\u9700\u8981\u51fa\u5e2d\u6216\u63a1\u8a2a\u5ba2\u6236\u6307\u5b9a\u6d3b\u52d5\uff0c\u6216\u53c3\u8207\u8a2a\u554f\u53ca\u76f8\u95dc\u62cd\u651d\u5de5\u4f5c\n\n\u5165\u8077\u8981\u6c42:\n\n\u5927\u5b78\u6216\u4ee5\u4e0a\u5b78\u6b77\u7a0b\u5ea6\uff0c\u5b78\u79d1\u80cc\u666f\u4e0d\u62d8\n3\u5e74\u6216\u4ee5\u4e0a\u5a92\u9ad4\u76f8\u95dc\u7d93\u9a57\uff0c\u5f9e\u4e8b\u65b0\u5a92\u9ad4\u7de8\u63a1\u5de5\u4f5c\u5c07\u512a\u5148\u8003\u616e\n\u719f\u6089\u751f\u6d3b\u985e\u578b\u984c\u6750\uff0c\u4ea6\u9858\u610f\u63a5\u89f8\u4e0d\u540c\u985e\u578b\u7684\u5167\u5bb9\u984c\u6750\n\u5177\u64b0\u5beb\u5546\u696d\u5408\u4f5c\u5167\u5bb9\u7d93\u9a57\u70ba\u4f73\uff0c\u80fd\u638c\u63e1\u8207\u5546\u696d\u5ba2\u6236\u7684\u6e9d\u901a\u548c\u8981\u6c42\n\u826f\u597d\u4e2d\u6587\u8b80\u5beb\u80fd\u529b\uff0c\u61c2\u5f97\u4e2d\u6587\u8f38\u5165\u6cd5\n\u5c0d\u4e92\u806f\u7db2\u53ca\u793e\u4ea4\u5e73\u53f0\u904b\u4f5c\u6709\u57fa\u672c\u6982\u5ff5\uff0c\u80fd\u5584\u7528Google Analytics\u53ca\u76f8\u95dc\u5206\u6790\u5de5\u5177\n\u5177\u6709\u5275\u610f\u3001\u7a4d\u6975\u4e3b\u52d5\u3001\u8655\u4e8b\u7d30\u5fc3\u3001\u5bcc\u8cac\u4efb\u611f\n\u5bcc\u5718\u968a\u5408\u4f5c\u7cbe\u795e\uff0c\u4e26\u80fd\u7368\u7acb\u5b8c\u6210\u5de5\u4f5c\n\n\n\n\n\u5982\u6709\u4efb\u4f55\u76f8\u95dc\u500b\u4eba\u4f5c\u54c1\uff0c\u8acb\u5c07\u8a72\u4f5c\u54c1\u52a0\u5165\u5c65\u6b77\u5167\u4e26\u4e00\u4f75\u63d0\u4ea4\u3002\u8acb\u65bc\u6c42\u8077\u4fe1\u8a3b\u660e\u6b32\u61c9\u5fb5\u4e4b\u8077\u4f4d\u3002\u6211\u5011\u6703\u70ba\u5408\u9069\u7684\u4eba\u9078\u63d0\u4f9b\u512a\u539a\u7684\u85aa\u916c\u5f85\u9047\u53ca\u798f\u5229(\u5305\u62ec\u4e94\u5929\u5de5\u4f5c\u5468)\u3002\u61c9\u5fb5\u8005\u8acb\u6309\u300cApply Now\u300d\u6309\u9215\u4e26\u63d0\u4f9b\u5c65\u6b77\u3001\u73fe\u6642\u53ca\u8981\u6c42\u7684\u85aa\u916c\u5f85\u9047\u7b49\u8cc7\u6599\u4f5c\u8077\u4f4d\u7533\u8acb\u3002\n\n\u6240\u6709\u6536\u96c6\u7684\u500b\u4eba\u8cc7\u6599\u90fd\u6703\u56b4\u683c\u4fdd\u5bc6\u4e26\u53ea\u4f5c\u62db\u8058\u7528\u9014\u30023\u500b\u6708\u5167\u672a\u7372\u9762\u8a66\u901a\u77e5\u7684\u7533\u8acb\u8005\uff0c\u53ef\u8996\u5176\u7533\u8acb\u70ba\u4e0d\u6210\u529f\u8ad6\u3002\u53e6\u4e00\u65b9\u9762\uff0c\u5c65\u6b77\u4ea6\u53ef\u80fd\u8ddf\u64da\u516c\u53f8\u96c6\u5718\u7684\u5167\u90e8\u9700\u8981\uff0c\u9032\u884c\u5167\u90e8\u8f49\u79fb\u3002\u672a\u7372\u63a5\u7d0d\u7684\u7533\u8acb\u8cc7\u6599\u5c07\u6703\u572812\u500b\u6708\u5167\u92b7\u6bc0\u3002\u00a0", "employment_types": ["Full Time", "Permanent"], "selling_points": ["\u5927\u5b78\u6216\u4ee5\u4e0a\u7a0b\u5ea6\uff0c2\u5e74\u6216\u4ee5\u4e0a\u5a92\u9ad4\u7d93\u9a57", "\u5177\u64b0\u5beb\u7db2\u7d61\u5167\u5bb9\u53ca\u5546\u696d\u5408\u4f5c\u5167\u5bb9\u7684\u7d93\u9a57", "\u5275\u610f\u3001\u7a4d\u6975\uff0c\u5c0d\u4e92\u806f\u7db2\u5a92\u9ad4\u6709\u8208\u8da3"], "locations": ["Tsuen Wan Area"], "categories": ["Media & Advertising", "Media Buying", "Editorial / Journalism", "Print Media"], "post_time": "2022-01-17T10:46:29Z", "salary": {"currency": null, "max": null, "min": null, "period": "monthly", "term": null}, "salary_visible": false, "title_keywords": ["editor"], "responsibilities": [], "requirements": {"degrees": [], "majors": [], "languages": [], "language_level": [], "hard_skills": [], "soft_skills": [], "languages_combined": []}, "experience_required": {"duration": [], "field": []}}, {"job_id": "100003009054336", "location_code": "hk", "company": "BCI Asia Construction Information Limited", "job_title": "Publication Content Editor (Freelance)", "description": "The Candidate\n\nWe are seeking a motivated and savvy Freelance Content Editor to support our publishing needs for a quarterly architectural publication. We prefer a candidate with experience in architectural/design writing/editing and/or work experience in architecture/building design.\n\nYou will work with a team to curate and develop compelling and engaging content for our audience. Your primary duties will include developing content, editing, proofreading, writing for our print and digital magazines/media.\n\nResponsibilities:\n\nDevelop content; write, edit and proofread (fact-check, spelling, grammar/syntax) following BCI\u2019s house style for a quarterly architectural publication.\nInterview 5-6 clients for publication quarterly.\nTo understand basic rules of content presentation/layout/format for readers\u2019 experience according to BCI\u2019s house style.\nEnsure that content is accurate and factual while adding value to readers and increase their knowledge, and meet the company\u2019s and/or clients\u2019 needs.\nWork with marketing and graphic design teams to ensure appealing and user-friendly readers\u2019 experience.\nCollaborate with co-workers and come up with fresh, creative content ideas, keeping our audience in mind.\nManage workload according to deadlines.\n\nRequirements:\n\nWork experience in architectural/design writing/editing AND/OR work experience in architecture/building design related fields.\nBachelor's Degree in Journalism, English OR Bachelor\u2019s Degree in Architecture/Design with work experience in writing/editing.\nExcellent command of the English language in writing and speaking.\nWriting, copy editing, editing and proofreading experiences.\nPositive attitude; adaptable to change; diligent and resourceful.\nGood communication and interpersonal skills.\nHighly organized and detail-oriented.\nProficient in desktop publishing software.\nProficient in Microsoft Office.\n\nIf you are interested, please apply with you cover letter explaining about yourself and your expected salary, together with your CV. Thank you.\n\nONLY SHORTLISTED CANDIDATE WILL BE NOTIFIED.", "employment_types": ["Freelance"], "selling_points": ["Remote Working", "Freelance job", "With experience in architecture design writing"], "locations": ["Hung Hom"], "categories": ["Media & Advertising", "Others", "Editorial / Journalism", "Print Media"], "post_time": "2022-01-17T09:11:39Z", "salary": {"currency": null, "max": null, "min": null, "period": "monthly", "term": null}, "salary_visible": false, "title_keywords": ["content editor"], "responsibilities": ["collaborate with", "ideas", "creative content", "graphic design", "teams", "develop", "publication"], "requirements": {"degrees": ["degree", "bachelor"], "majors": ["journalism", "architecture", "design"], "languages": ["english"], "language_level": ["excellent"], "hard_skills": ["microsoft office"], "soft_skills": ["organized", "resourceful", "adaptable", "diligent", "detail-oriented", "positive attitude", "communication and interpersonal skills"], "languages_combined": [{"language": "english", "language_level": ["excellent"]}]}, "experience_required": {"duration": [], "field": ["related", "editing", "writing", "design"]}}, {"job_id": "100003009055626", "location_code": "hk", "company": "Sing Tao News Corporation Limited (The Standard)", "job_title": "Reporter (The Standard Metro News)", "description": "Responsibilities:\n\n\nResponsible for reporting and writing local news\n\nRequirements:\n\n\nDegree in journalism, mass communication, law or related discipline\nAt least 1 year journalism experience is preferred, fresh graduates will also be considered\nSound knowledge of local current affairs\nGood command of English and excellent writing skill\nAble to work independently on tight deadlines\nOutgoing, good organization skills and attentive to details\nWorking Location : Tseung Kwan O Industrial Estate\n\nInterested parties please\u00a0click \u201cApply Now\"\u00a0to submit your complete resume with\u00a0employment history and expected salary or by\u00a0post to\u00a0Human Resources Department, 3/F, Sing Tao News Corporation Building, 7 Chun Cheong Street, Tseung Kwan O Industrial Estate, Tseung Kwan O, New Territories, Hong Kong.\n\nWe are an equal opportunity employer and welcome applications from all qualified candidates. Information provided will be treated in strict confidence and only be used for recruitment related purpose. Applicant who is not invited for an interview within 6 weeks may consider their application not successful. All personal data of unsuccessful applicants will be destroyed within 6 months.\n\nwww.singtaonewscorp.com\u00a0", "employment_types": ["Full Time", "Permanent"], "selling_points": [], "locations": ["Tseung Kwan O"], "categories": ["Media & Advertising", "Editorial / Journalism", "Print Media", "Others", "Student / Fresh Graduate / No Experience"], "post_time": "2022-01-18T02:48:40Z", "salary": {"currency": null, "max": null, "min": null, "period": "monthly", "term": null}, "salary_visible": false, "title_keywords": ["reporter"], "responsibilities": ["reporting"], "requirements": {"degrees": ["degree"], "majors": ["journalism", "law"], "languages": ["english"], "language_level": ["excellent", "good command"], "hard_skills": ["writing skill"], "soft_skills": ["outgoing", "work independently", "attentive to details", "writing skill", "communication", "organization skills"], "languages_combined": [{"language": "english", "language_level": ["excellent", "good command"]}]}, "experience_required": {"duration": ["at least 1 year"], "field": []}}, {"job_id": "100003009055810", "location_code": "hk", "company": "Ming Pao Publications Ltd", "job_title": "Assistant Editor", "description": "Responsibilities:\n\n\nAssist Publishing Manager in formulates and develop publishing plans/projects for Chinese books\nEdit and proofread Chinese manuscripts from writers and generate ideas on book layout and design\nExecute overall publication procedures including quality control and coordinate with suppliers, freelancers, production house and printing companies\n\nRequirements:\n\nUniversity graduate in Language, Journalism or related disciplines\nAt least 1 year working experience in editorial field, preferably in publishing industry\nExcellent command of both written & spoken English and Chinese, fluent in Mandarin is definitely an advantage\nProficiency in MS Office and Mac applications\nGood interpersonal and communication skills\nIndependent and able to work under pressure\n\nWe offer attractive remuneration package to the right candidate. Interested parties please send full resume with salary expected to the Human Resources Department, 15/F., Block A, Ming Pao Industrial Centre, 18 Ka Yip Street, Chaiwan, Hong Kong\u00a0 or apply by clicking the Apply Now button.\n\nPersonal data collected will be used for recruitment purpose only", "employment_types": ["Full Time", "Permanent"], "selling_points": [], "locations": ["Chai Wan"], "categories": ["Media & Advertising", "Editorial / Journalism", "Print Media"], "post_time": "2022-01-18T02:58:24Z", "salary": {"currency": null, "max": null, "min": null, "period": "monthly", "term": null}, "salary_visible": false, "title_keywords": ["assistant editor"], "responsibilities": ["ideas", "procedures", "coordinate with", "design", "develop", "quality control", "plans", "publication"], "requirements": {"degrees": ["university graduate"], "majors": ["journalism", "related disciplines"], "languages": ["english", "chinese", "mandarin"], "language_level": ["advantage", "excellent", "fluent"], "hard_skills": ["ms office"], "soft_skills": ["communication skills", "independent", "interpersonal", "work under pressure"], "languages_combined": [{"language": "english", "language_level": ["fluent", "advantage", "excellent"]}, {"language": "chinese", "language_level": ["fluent", "advantage", "excellent"]}, {"language": "mandarin", "language_level": ["fluent", "advantage", "excellent"]}]}, "experience_required": {"duration": ["at least 1 year"], "field": ["editorial", "publishing"]}}, {"job_id": "100003009052861", "location_code": "hk", "company": "Sing Tao Management Services Limited", "job_title": "\u8a18\u8005 (\u982d\u689d\u65e5\u5831-\u4e2d\u570b\u53ca\u570b\u969b\u65b0\u805e)", "description": "\u8077\u8cac\uff1a\n\n\u8ca0\u8cac\u8655\u7406\u4e2d\u570b\u548c\u570b\u969b\u65b0\u805e\u76f8\u95dc\u5831\u9053\n\n\u8981\u6c42\uff1a\n\n\u5927\u5b78\u7562\u696d\uff0c\u4e3b\u4fee\u8a9e\u8a00\u6216\u65b0\u805e\u512a\u5148\u8003\u616e\n\u51771\u5e74\u76f8\u95dc\u7d93\u9a57 (\u4e5f\u6b61\u8fce\u61c9\u5c46\u7562\u696d\u751f)\n\u826f\u597d\u4e2d\u82f1\u6587\u6e9d\u901a\u53ca\u66f8\u5beb\u80fd\u529b\n\u7a4d\u6975\u4e3b\u52d5\u3001\u8655\u4e8b\u7d30\u5fc3\u3001\u5bcc\u8cac\u4efb\u611f\u53ca\u80fd\u65bc\u58d3\u529b\u4e0b\u5de5\u4f5c\n\u80fd\u5373\u6642\u5230\u4efb\u70ba\u4f73\n\u5de5\u4f5c\u5730\u9ede\uff1a\u5c07\u8ecd\u6fb3\u5de5\u696d\u90a8\n\n\u6c42\u8077\u8005\u8acb\u8a73\u9644\u500b\u4eba\u5c65\u6b77\u53ca\u8981\u6c42\u5f85\u9047\uff0c\u5bc4\u9999\u6e2f\u65b0\u754c\u5c07\u8ecd\u6fb3\u5de5\u696d\u90a8\u99ff\u660c\u8857\u4e03\u865f\u661f\u5cf6\u65b0\u805e\u96c6\u5718\u5927\u5ec83\u6a13\u4eba\u529b\u8cc7\u6e90\u90e8\u6536\uff0c\u4fe1\u5c01\u9762\u8acb\u8a3b\u660e\u7533\u8acb\u8077\u4f4d\u6216\u6309\u201cApply Now\u201d\u63d0\u4ea4\u7533\u8acb\u3002\n\n\u672c\u516c\u53f8\u70ba\u516c\u5e73\u6a5f\u6703\u50f1\u4e3b\uff0c\u6b61\u8fce\u6240\u6709\u5408\u8cc7\u683c\u7684\u5019\u9078\u4eba\u7533\u8acb\u3002\u6240\u63d0\u4f9b\u7684\u4fe1\u606f\u5c07\u56b4\u683c\u4fdd\u5bc6\uff0c\u50c5\u7528\u65bc\u62db\u8058\u76f8\u95dc\u7528\u9014\u3002\u82e5\u672a\u80fd\u65bc 6 \u9031\u5167\u7372\u9080\u51fa\u5e2d\u9762\u8a66\u7684\u7533\u8acb\u8005\u6703\u81ea\u52d5\u843d\u9078\uff0c\u53e6\u6240\u6709\u843d\u9078\u7684\u7533\u8acb\u8005\u7684\u6240\u6709\u500b\u4eba\u8cc7\u6599\u5c07\u57286\u500b\u6708\u5167\u92b7\u6bc0\u3002\n\nwww.singtaonewscorp.com", "employment_types": ["Full Time", "Permanent"], "selling_points": [], "locations": ["Sai Kung"], "categories": ["Media & Advertising", "Others", "Editorial / Journalism", "Print Media"], "post_time": "2022-01-17T05:36:05Z", "salary": {"currency": null, "max": null, "min": null, "period": "monthly", "term": null}, "salary_visible": false, "title_keywords": ["\u8a18\u8005"], "responsibilities": [], "requirements": {"degrees": [], "majors": [], "languages": [], "language_level": [], "hard_skills": [], "soft_skills": [], "languages_combined": []}, "experience_required": {"duration": [], "field": []}}, {"job_id": "100003009052293", "location_code": "hk", "company": "Tianda Institute", "job_title": "\u52a9\u7406\u7de8\u8f2f Assistant Editor (Full Time/ Part Time)", "description": "\u4e3b\u8981\u8077\u8cac\uff1a\n\n\u00a0\u5354\u52a9\u7d71\u7c4c\u7814\u7a76\u9662\u66f8\u520a\u51fa\u7248\u7269\u7684\u7de8\u8f2f\u51fa\u7248;\n\u8ca0\u8cac\u7d44\u7a3f\u3001\u7de8\u8b6f\u3001\u6821\u5be9\u7b49\u4e8b\u52d9\uff1b\n\n\u8207\u66f8\u520a\u51fa\u7248\u76f8\u95dc\u7684\u5176\u5b83\u4e8b\u9805\u3002\n\n\u00a0\u5165\u8077\u689d\u4ef6\uff1a\n\n\u5b78\u58eb\u5b78\u4f4d\u6216\u4ee5\u4e0a\u5b78\u6b77\uff0c\u4e3b\u4fee\u4e2d\u6587\u3001\u82f1\u6587\u6216\u7ffb\u8b6f\u512a\u5148\u8003\u616e\uff1b\n\u51773\u5e74\u4ee5\u4e0a\u7ffb\u8b6f\u3001\u7de8\u8f2f\u53ca\u51fa\u7248\u76f8\u95dc\u5de5\u4f5c\u7d93\u9a57, \u4e2d\u82f1\u6587\u5beb\u4f5c\u80fd\u529b\u512a\u826f\uff0c\u719f\u6089\u4e2d\u570b\u653f\u6cbb\u8207\u7d93\u6fdf (\u5982\u7d93\u9a57\u8f03\u6dfa\u6216\u61c9\u5c46\u7562\u696d\u53ef\u8003\u616e\u70ba\u7de8\u8f2f\u52a9\u7406)\uff1b\n\u719f\u6089\u7c21\u9ad4\u4e2d\u6587\u7de8\u8f2f\u5beb\u4f5c\u6703\u512a\u5148\u8003\u616e\uff1b\n\u6b61\u8fceIANG\u7562\u696d\u751f\u61c9\u8058\uff1b\n\u71b1\u8aa0\u56b4\u8b39\uff0c\u5177\u6709\u826f\u597d\u7684\u6e9d\u901a\u80fd\u529b\u3001\u5354\u8abf\u80fd\u529b\u3002\n\n\u5929\u5927\u7814\u7a76\u9662\u63d0\u4f9b\u512a\u539a\u85aa\u916c\u798f\u5229\u3002\u6709\u610f\u7533\u8acb\u8005\u53ef\u5c07\u500b\u4eba\u5c65\u6b77\u3001\u76ee\u524d\u53ca\u671f\u671b\u85aa\u91d1\u767c\u9001\u5230\u672c\u9662\u96fb\u90f5\u3002\u5982\u6b32\u4e86\u89e3\u66f4\u591a\u8a73\u60c5\uff0c\u6b61\u8fce\u53c3\u95b1\u5929\u5927\u7814\u7a76\u9662\u5b98\u65b9\u7db2\u9801http://www.tiandainstitute.org/cn/index.html\u3002\u901a\u904e\u521d\u6b65\u7be9\u9078\u4e4b\u7533\u8acb\u4eba\u5c07\u57286\u5468\u5167\u6536\u5230\u901a\u77e5\u3002\n\n\u6240\u6709\u6536\u96c6\u7684\u8cc7\u6599\u5c07\u88ab\u56b4\u683c\u4fdd\u5bc6\uff0c\u4e26\u50c5\u4f5c\u62db\u8058\u7528\u9014\u3002", "employment_types": ["Full Time", "Part Time"], "selling_points": [], "locations": ["Admiralty"], "categories": ["Media & Advertising", "Editorial / Journalism", "Sciences, Lab, R&D", "Research & Development (R&D)", "Professional Services", "Translation"], "post_time": "2022-01-17T02:39:43Z", "salary": {"currency": null, "max": null, "min": null, "period": "monthly", "term": null}, "salary_visible": false, "title_keywords": ["assistant editor"], "responsibilities": [], "requirements": {"degrees": [], "majors": [], "languages": [], "language_level": [], "hard_skills": [], "soft_skills": [], "languages_combined": []}, "experience_required": {"duration": [], "field": []}}, {"job_id": "100003009054167", "location_code": "hk", "company": "i-CABLE Communications Limited", "job_title": "Assistant Librarian", "description": "News Department\nTo be responsible for providing video and information research to journalists; digitizing video tapes; tagging daily news stories and raw footages\nUniversity graduate with minimum 1 year relevant working experience\nGood command of both spoken and written English & Chinese\nFamiliar with Chinese word processing is a must\nAble to work independently in a fast-paced and news deadline-oriented environment\nKnowledge of Microsoft Word and Excel\nImmediate available is highly preferable\nWe offer 5-day work week, competitive remuneration packages and advancement opportunities. Interested parties, please write with full resume to Director, Human Resources, Human Resources Department, i-CABLE Communications Limited, 4/F Cable TV Tower, 9 Hoi Shing Road Tsuen Wan, N.T. or fax to 2112 7841 or via Apply Now (Please quote reference number and position applied for). For other information, please visit our website http://www.i-cable.com.\n\nYour application may be forwarded to any affiliate companies\u00a0and successful applicant may be seconded to work at any office as assigned.\u00a0 The information received will be used for consideration of employment only and all personal data supplied will be destroyed within 3 months.\n\nWe are an equal opportunity employer.", "employment_types": ["Full Time", "Permanent"], "selling_points": [], "locations": ["Tsuen Wan Area"], "categories": ["Media & Advertising", "Production", "Editorial / Journalism", "Broadcasting - TV / Radio"], "post_time": "2022-01-17T08:38:32Z", "salary": {"currency": null, "max": null, "min": null, "period": null, "term": null}, "salary_visible": false, "title_keywords": ["assistant"], "responsibilities": [], "requirements": {"degrees": ["university graduate"], "majors": [], "languages": ["english", "chinese"], "language_level": ["good command"], "hard_skills": ["excel", "microsoft word", "chinese word processing"], "soft_skills": ["work independently", "responsible"], "languages_combined": [{"language": "english", "language_level": ["good command"]}, {"language": "chinese", "language_level": ["good command"]}]}, "experience_required": {"duration": ["minimum 1 year"], "field": ["relevant working experience"]}}, {"job_id": "100003009054634", "location_code": "hk", "company": "HK01 Company Limited", "job_title": "\u8a18\u8005 (\u5973\u751f\u983b\u9053)", "description": "\n\u4e3b\u8981\u8077\u8cac\n\n\n\u64b0\u5beb\u6642\u4e0b\u5973\u6027\u76f8\u95dc\u53ca\u71b1\u9580\u4e4b\u5167\u5bb9\n\u8ca0\u8cac\u63a1\u8a2a\u3001\u62cd\u651d\u5de5\u4f5c\n\u914d\u5408\u5e02\u5834\u90e8\u88fd\u4f5c\u5546\u696d\u5408\u4f5c\u5167\u5bb9\n\u5165\u8077\u8981\u6c42\n\n\u5927\u5b78\u6216\u4ee5\u4e0a\u5b78\u6b77\u7a0b\u5ea6\uff0c\u5f9e\u4e8b\u7db2\u7d61\u5a92\u9ad4\u5c07\u512a\u5148\u8003\u616e\n\u5c0d\u8655\u7406\u7f8e\u5bb9\u6253\u626e\u3001\u60c5\u611f\u95dc\u4fc2\u7b49\u5167\u5bb9\u5177\u6709\u7d93\u9a57\n\u719f\u6089\u7db2\u7d61\u6587\u5316\n\u6027\u683c\u7a4d\u6975\u4e3b\u52d5\uff0c\u64c5\u9577\u8207\u4eba\u6e9d\u901a\uff0c\u5177\u5718\u9ad4\u7cbe\u795e\n\u6b64\u8077\u4f4d\u5c6c\u65bc \"\u5973\u751f\" \u983b\u9053\uff0c\u61c9\u5fb5\u8005\u53ef\u5230hk01.com\u67e5\u770b\n\n\n\n\n\u6211\u5011\u6703\u70ba\u5408\u9069\u7684\u4eba\u9078\u63d0\u4f9b\u512a\u539a\u7684\u85aa\u916c\u5f85\u9047\u53ca\u798f\u5229(\u5305\u62ec\u4e94\u5929\u5de5\u4f5c\u5468)\u3002\u61c9\u5fb5\u8005\u8acb\u6309 \"Apply Now\" \u6309\u9215\u4e26\u63d0\u4f9b\u5c65\u6b77\u3001\u73fe\u6642\u53ca\u8981\u6c42\u7684\u85aa\u916c\u5f85\u9047\u7b49\u8cc7\u6599\u4f5c\u8077\u4f4d\u7533\u8acb\u3002\n\n\u6240\u6709\u6536\u96c6\u7684\u500b\u4eba\u8cc7\u6599\u90fd\u6703\u56b4\u683c\u4fdd\u5bc6\u4e26\u53ea\u4f5c\u62db\u8058\u7528\u9014\u30023\u500b\u6708\u5167\u672a\u7372\u9762\u8a66\u901a\u77e5\u7684\u7533\u8acb\u8005\uff0c\u53ef\u8996\u5176\u7533\u8acb\u70ba\u4e0d\u6210\u529f\u8ad6\u3002\u53e6\u4e00\u65b9\u9762\uff0c\u5c65\u6b77\u4ea6\u53ef\u80fd\u8ddf\u64da\u516c\u53f8\u96c6\u5718\u7684\u5167\u90e8\u9700\u8981\uff0c\u9032\u884c\u5167\u90e8\u8f49\u79fb\u3002\u672a\u7372\u63a5\u7d0d\u7684\u7533\u8acb\u8cc7\u6599\u5c07\u6703\u572812\u500b\u6708\u5167\u92b7\u6bc0\u3002", "employment_types": ["Full Time", "Permanent"], "selling_points": ["\u64b0\u5beb\u5973\u6027\u76f8\u95dc\u53ca\u71b1\u9580\u4e4b\u5167\u5bb9", "\u6709\u65b0\u60f3\u6cd5\u53ca\u5bcc\u6709\u5beb\u4f5c\u6280\u5de7", "\u63d0\u4f9b\u8077\u696d\u767c\u5c55\u6a5f\u6703\uff0c\u53ca\u6709\u7af6\u722d\u529b\u7684\u85aa\u916c"], "locations": ["Tsuen Wan Area"], "categories": ["Media & Advertising", "Media Buying", "Strategic Planning", "Editorial / Journalism"], "post_time": "2022-01-17T10:20:08Z", "salary": {"currency": null, "max": null, "min": null, "period": "monthly", "term": null}, "salary_visible": false, "title_keywords": ["\u8a18\u8005"], "responsibilities": [], "requirements": {"degrees": [], "majors": [], "languages": [], "language_level": [], "hard_skills": [], "soft_skills": [], "languages_combined": []}, "experience_required": {"duration": [], "field": []}}, {"job_id": "100003009053140", "location_code": "hk", "company": "ORIENTAL HUMAN RESOURCES LIMITED", "job_title": "Reporter Trainee - Entertainment News", "description": "Responsible for reporting entertainment news articles\nUniversity or College graduate\nGood command of Chinese and English\nFamiliar with entertainment news\nKnowledge of Chinese word processing\nInitiative and possess good communication skills\nShift duty and rotated rest day are required\n\nApplication Method\n\nWe offer free shuttle bus, free parking and fringe benefits including medical scheme, discretionary bonus and public holidays\u00a0to the right candidate. Interested parties, please send full resume with expected salary to ORIENTAL HUMAN RESOURCES LIMITED\u00a0by\u00a0clicking \"Apply now\" ;\u00a0or fax to 3600 1900 ( Please quote reference on the application letter )\n\n\nPersonal Information Collection Statement\n\nPersonal data collected will be treated in accordance with our Personal Data Policy and handled in strict confidence by authorized personnel for recruitment related purpose only.\u00a0 \u00a0 \u00a0\n\u00a0 \u00a0 \u00a0 \u00a0 \u00a0 \u00a0\n\n\u00a0 \u00a0 \u00a0 \u00a0 \u00a0 \u00a0 \u00a0 \u00a0 \u00a0 \u00a0 \u00a0 \u00a0 \u00a0 \u00a0 \u00a0 \u00a0 \u00a0 \u00a0 \u00a0 \u00a0 \u00a0 \u00a0 \u00a0 \u00a0 \u00a0 \u00a0 \u00a0\u00a0on.cc\n\n", "employment_types": ["Full Time"], "selling_points": [], "locations": ["Tai Po Area"], "categories": ["Media & Advertising", "Creative / Design", "Others", "Editorial / Journalism"], "post_time": "2022-01-17T08:34:57Z", "salary": {"currency": null, "max": null, "min": null, "period": "monthly", "term": null}, "salary_visible": false, "title_keywords": ["reporter", "trainee"], "responsibilities": ["communication", "reporting"], "requirements": {"degrees": [], "majors": [], "languages": ["english", "chinese"], "language_level": ["good command"], "hard_skills": ["chinese word processing"], "soft_skills": ["communication skills", "initiative", "responsible"], "languages_combined": [{"language": "english", "language_level": ["good command"]}, {"language": "chinese", "language_level": ["good command"]}]}, "experience_required": {"duration": [], "field": []}}, {"job_id": "100003009055718", "location_code": "hk", "company": "Sing Tao News Corporation Limited (The Standard)", "job_title": "Web Reporter (The Standard Education)", "description": "Responsibilities:\n\nTo write feature articles for the student papers including Goodies, Junior Standard and The Student Standard\nUpdate and maintain the student website, app and other social media platforms\nDevelop new ideas to enhance the new student website\nCreate, manage and integrate multimedia content\n\nRequirements:\n\nUniversity graduate in Journalism or Communication\nAt least 1 year experience preferred; fresh graduate with intern experience will also be considered\nFluent in written and spoken English is a must; fluency in Cantonese would be an advantage\nOutstanding English writing skills and able to write interesting stories for students of all ages\nAble to work under tight deadlines\nConduct research and work independently\nGood organisation skills, enthusiastic and be a team player\nStrong interviewing skills and ability to shoot and edit videos for social media will be a plus\nBe tech savvy and familiar with social media. Fresh graduates are welcome\nWorking Location : Tseung Kwan O Industrial Estate\n\nInterested parties please\u00a0click \u201cApply Now\"\u00a0to submit your complete resume with\u00a0employment history and expected salary or by\u00a0post to\u00a0Human Resources Department, 3/F, Sing Tao News Corporation Building, 7 Chun Cheong Street, Tseung Kwan O Industrial Estate, Tseung Kwan O, New Territories, Hong Kong.\n\nWe are an equal opportunity employer and welcome applications from all qualified candidates. Information provided will be treated in strict confidence and only be used for recruitment related purpose. Applicant who is not invited for an interview within 6 weeks may consider their application not successful. All personal data of unsuccessful applicants will be destroyed within 6 months.\n\nwww.singtaonewscorp.com", "employment_types": ["Full Time", "Permanent"], "selling_points": [], "locations": ["Tseung Kwan O"], "categories": ["Media & Advertising", "Editorial / Journalism", "Photography / Video", "Others", "Student / Fresh Graduate / No Experience"], "post_time": "2022-01-18T02:53:03Z", "salary": {"currency": null, "max": null, "min": null, "period": "monthly", "term": null}, "salary_visible": false, "title_keywords": ["reporter"], "responsibilities": ["ideas", "social media platforms", "website", "develop", "maintain"], "requirements": {"degrees": ["university graduate", "fresh graduate"], "majors": ["journalism"], "languages": ["cantonese", "english"], "language_level": ["fluency", "advantage", "fluent"], "hard_skills": ["plus", "writing skills"], "soft_skills": ["work independently", "writing skills", "communication", "organisation", "enthusiastic", "team player"], "languages_combined": [{"language": "cantonese", "language_level": ["fluency", "advantage"]}, {"language": "english", "language_level": ["fluent"]}]}, "experience_required": {"duration": ["at least 1 year"], "field": []}}, {"job_id": "100003009051577", "location_code": "hk", "company": "Tsangs Group", "job_title": "Intern - Video Editing", "description": "Responsibilities:\n\nHandle various design projects, mainly focusing on video editing and animation, visual and graphic artwork design\nEdit video, effect composition, motion graphic and animations\nGenerate ideas and creative concepts for digital campaigns and social media posts\nTo draft both English and Chinese press and publication copies;\nManaging social media platforms;\nOther ad-hoc copywriting tasks required to facilitate various marketing activities;\nManage other ad hoc projects as assigned\nRequirements:\n\n\nDegree holder in Creative Media, Marketing, translation or relevant disciplines: communications, journalism or advertising;\nExcellent knowledge of photography/videography within the digital domain;\nExcel in Adobe Premiere and Adobe Photoshop;\nExcellent command of written, spoken English, Mandarin, and Cantonese;\nFamiliar with various social media platforms;\nMust possess outstanding proofreading skills;\nProficient in Microsoft Word, Excel, PowerPoint, and Chinese Word Processing;\nSelf-motivated and proactive team player with good communication skills.", "employment_types": ["Full Time"], "selling_points": ["Familiar with various social media platforms", "5-day working", "Handle design projects, such as video editing"], "locations": ["Central"], "categories": ["Design", "Multi-media", "Media & Advertising", "Editorial / Journalism", "Photography / Video"], "post_time": "2022-01-16T11:38:35Z", "salary": {"currency": null, "max": null, "min": null, "period": "monthly", "term": null}, "salary_visible": false, "title_keywords": ["intern"], "responsibilities": ["ad-hoc", "social media", "ideas", "social media platforms", "design", "publication", "video editing", "ad hoc projects", "animations", "digital campaigns", "visual", "motion graphic", "animation"], "requirements": {"degrees": ["degree holder"], "majors": ["journalism", "creative media", "marketing", "communications"], "languages": ["cantonese", "english", "chinese", "mandarin"], "language_level": ["excellent", "proficient"], "hard_skills": ["excel", "microsoft word", "chinese word processing", "adobe photoshop", "powerpoint", "adobe premiere", "translation"], "soft_skills": ["communication skills", "self-motivated", "proactive", "team player", "creative"], "languages_combined": [{"language": "cantonese", "language_level": ["excellent"]}, {"language": "english", "language_level": ["excellent"]}, {"language": "chinese", "language_level": ["proficient"]}, {"language": "mandarin", "language_level": ["excellent"]}]}, "experience_required": {"duration": [], "field": []}}, {"job_id": "100003009054849", "location_code": "hk", "company": "Manner Production Limited", "job_title": "Director \u5c0e\u6f14", "description": "Job Highlights\n\nFun, young, and joyful working environment\nCreate ideas & improve designs for Manner Group\nCoordinate with art and creative team\n\nResponsibilities:\n\nCopywriting or creating content and script for social media platforms\nHandle production and sales project and creative, pre-production, on location shooting and post-production;\nWork with Director and Production team to make sure project on time and within budget;\nTime management, able to meet tight deadlines and work independently under pressure in fast paced environment;\nKeep the team in a good production atmosphere\nRequirements:\n\nThree to five years of the production company or producer experience is preferred;\nAble to plan independently, to coordinate, organize, and screen projects, and be familiar with the program production process;\nWork experience in online marketing, social media group will be preferred;\nKnowledge of production software; after Effects, Photoshop and Illustrator etc.;\nHave a passion for the Internet or film industry, with enthusiasm, initiative, team awareness and coordination and strong resistance;\nWork with Production Team\n\n\u8077\u4f4d\u8981\u6c42:\n\n\u81f3\u5c11\u4e09\u81f3\u4e94\u5e74\u4ee5\u4e0a\u88fd\u4f5c\u516c\u53f8\u5275\u4f5c\u7d93\u9a57; \u7368\u7acb\u7d71\u7c4c\uff0c\u5275\u4f5c\u5f71\u7247\u5305\u62ec\u524d\u4e2d\u5f8c\u671f\u88fd\u4f5c\uff1b\u7be9\u9078\u9805\u76ee; \u719f\u6089\u88fd\u4f5c\u6d41\u7a0b\uff0c\u6709\u8c50\u5bcc\u5f71\u8996\u88fd\u4f5c\uff0c\u51dd\u805a\u5718\u968a\uff0c\u6709\u61c9\u8b8a\u80fd\u529b\u8655\u7406\u7a81\u767c\u5371\u6a5f\uff0c\u5354\u4f5c\u5287\u672c\u548c\u62cd\u651d\u8981\u6c42\u7b56\u5283\u62cd\u651d.\n\nTo apply, please send us your resume / CV to us.\u00a0Personal data collected will be used for recruitment purposes only.", "employment_types": ["Full Time"], "selling_points": ["Work with Manner creative team", "Opportunity to work with production team and KOLs", "Harmonious and funny working environment"], "locations": ["Causeway Bay"], "categories": ["Media & Advertising", "Production", "Editorial / Journalism", "Broadcasting - TV / Radio"], "post_time": "2022-01-17T12:15:57Z", "salary": {"currency": null, "max": null, "min": null, "period": "monthly", "term": null}, "salary_visible": false, "title_keywords": ["director"], "responsibilities": ["pre-production", "management", "social media platforms", "budget"], "requirements": {"degrees": [], "majors": [], "languages": [], "language_level": [], "hard_skills": ["after effects", "illustrator", "photoshop"], "soft_skills": ["independently", "initiative", "coordination", "passion for"], "languages_combined": []}, "experience_required": {"duration": ["three to five years"], "field": ["social media", "marketing"]}}, {"job_id": "100003009053523", "location_code": "hk", "company": "Chinese Bible International Limited", "job_title": "\u7de8\u8f2f/\u52a9\u7406\u7de8\u8f2f/\u7ffb\u8b6f", "description": "\n\u2022 \u5927\u5c08\u6216\u4ee5\u4e0a\uff0c\u4e2d\u82f1\u6587\u826f\u597d\uff0c\u5177\u6709\u7ffb\u8b6f\u53ca\u795e\u5b78\u8a13\u7df4\n\u2022 \u8ca0\u8cac\u7de8\u8f2f\u8056\u7d93\u7814\u7a76\u66f8\u7c4d\uff0c\u7de8\u5beb\u8056\u7d93\u6559\u6750\u53ca\u76f8\u95dc\u6750\u6599\n\u2022 \u6709\u7de8\u8f2f\u6216\u64b0\u5beb\u66f8\u7a3f\u7d93\u9a57\u8005\u512a\u5148\u8003\u616e\n** \u672c\u516c\u53f8\u6709\u5b8c\u5584\u7684\u85aa\u91d1\u5236\u5ea6\uff0c\u4e26\u63d0\u4f9b\u5168\u8077\u54e1\u5de5\u4ee5\u4e0b\u798f\u5229\uff1a\n\u2022 \u54e1\u5de5\u8cfc\u7269\u512a\u60e0\n\u2022 \u6709\u85aa\u5e74\u5047\n\u2022 \u9580\u8a3a\u53ca\u4f4f\u9662\u4fdd\u96aa\n\u2022 \u5c08\u696d\u5728\u8077\u57f9\u8a13\n\u2022 \u826f\u597d\u6649\u5347\u6a5f\u6703\n\u6709\u610f\u8005\u8acb\u5c07\u5c65\u6b77\uff0c\u8981\u6c42\u85aa\u91d1\uff0c\u9023\u540c\u6559\u6703\u8aee\u8a62\u4eba\u59d3\u540d\uff0c\u5bc4\u4e5d\u9f8d\u8354\u679d\u89d2\u901a\u5dde\u897f\u88571064-1066\u865f\u5b89\u6cf0\u5de5\u696d\u5927\u5ec8A\u5ea7\u4e5d\u6a13\u884c\u653f\u90e8\u6216\u96fb\u90f5 Apply Now\n\uff08\u7533\u8acb\u4eba\u6240\u63d0\u4f9b\u7684\u8cc7\u6599\u5c07\u4e88\u4fdd\u5bc6\u53ca\u53ea\u4f5c\u62db\u8058\u6709\u95dc\u8077\u4f4d\u7528\u9014\uff09\n\n", "employment_types": ["Full Time"], "selling_points": [], "locations": ["Not Specified"], "categories": ["Media & Advertising", "Others", "Editorial / Journalism"], "post_time": "2022-01-17T07:05:54Z", "salary": {"currency": null, "max": null, "min": null, "period": "monthly", "term": null}, "salary_visible": false, "title_keywords": ["\u7de8\u8f2f"], "responsibilities": [], "requirements": {"degrees": [], "majors": [], "languages": [], "language_level": [], "hard_skills": [], "soft_skills": [], "languages_combined": []}, "experience_required": {"duration": [], "field": []}}, {"job_id": "100003009053165", "location_code": "hk", "company": "\u5708\u50b3\u5a92\u6709\u9650\u516c\u53f8", "job_title": "Multimedia Reporter \u591a\u5a92\u9ad4\u8a18\u8005 / Video Editor \u526a\u7247 \u300a\u6e2f\u4eba\u8b1b\u5730\u300b - \uff08\u591a\u540d\uff09(5 days)", "description": "1. Multimedia Reporter \u591a\u5a92\u9ad4\u8a18\u8005\n\n\u8077\u8cac\uff1a\n\n\n\u64b0\u5beb\u65b0\u805e\u3001\u6642\u8a55\u3001\u5c08\u984c\u53ca\u591a\u5a92\u9ad4\u88fd\u4f5c\u7684\u5167\u5bb9\n\u4e3b\u52d5\u767c\u6398\u672c\u5730\u6642\u653f\u3001\u5169\u5cb8\u3001\u570b\u969b\u95dc\u4fc2\u4ee5\u53ca\u6b63\u80fd\u91cf\u5c08\u984c\n\u9700\u8981\u9032\u884c\u6236\u5167\u6216\u6236\u5916\u63a1\u8a2a\u5de5\u4f5c\uff0c\u6216\u6709\u9700\u8981\u6642\u5230\u5916\u5730\u5de5\u4f5c\n\u5165\u8077\u8981\u6c42\uff1a\n\n\n\u5927\u5c08\u6216\u4ee5\u4e0a\u5b78\u6b77\u7a0b\u5ea6\u512a\u5148\uff0c\u5b78\u79d1\u80cc\u666f\u4e0d\u62d8\n\u5177\u63a1\u8a2a\u6216\u7de8\u8f2f\u5de5\u4f5c\u7d93\u9a57\uff0c\u6216\u65b0\u5a92\u9ad4\u76f8\u95dc\u5de5\u4f5c\u7d93\u9a57\u512a\u5148\uff0c\u525b\u7562\u696d\u8005\u4ea6\u6703\u8003\u616e\n\u5c0d\u6642\u653f\u3001\u5169\u5cb8\u3001\u793e\u6703\u3001\u7d93\u6fdf\u3001\u5916\u4ea4\u3001\u570b\u969b\u95dc\u4fc2\u7b49\u8b70\u984c\u6709\u8a8d\u8b58\uff0c\u4e26\u5177\u6709\u76f8\u95dc\u5206\u6790\u80fd\u529b\n\u61c2\u5169\u6587\u4e09\u8a9e\uff0c\u4e2d\u82f1\u6587\u66f8\u5beb\u80fd\u529b\u8f03\u4f73\u8005\u7372\u512a\u5148\u8003\u616e\n\u5177\u8996\u983b\u88fd\u4f5c\u77e5\u8b58\u6216\u7d93\u9a57\u8005\u512a\u5148\n\u5c0d\u65b0\u5a92\u9ad4\u5de5\u4f5c\u6709\u71b1\u8aa0\uff0c\u6709\u5275\u610f\uff0c\u6027\u683c\u7a4d\u6975\u4e3b\u52d5\uff0c\u6709\u62da\u640f\u7cbe\u795e\uff0c\u64c5\u9577\u8207\u4eba\u6e9d\u901a\n\u4e94\u5929\u5de5\u4f5c\uff0c\u9700\u8f2a\u73ed\n\n2. Video Editor \u526a\u7247\n\n\u00a0\u00a0\u00a0\u00a0\u00a0\u00a0\u00a0\u00a0\u00a0\u00a0\u00a0 \u8077\u8cac\uff1a\n\n\n\u8ca0\u8cac\u65b0\u805e\u5f71\u7247\u526a\u63a5\u53ca\u5f8c\u671f\u88fd\u4f5c\n\n\u5165\u8077\u8981\u6c42\uff1a\n\n\n\u5c0d\u65b0\u805e\u5f71\u7247\u526a\u63a5\u6709\u8208\u8da3\uff0c\u64c1\u76f8\u95dc\u5de5\u4f5c\u7d93\u9a57\u8005\u512a\u5148\u8003\u616e\n\u9700\u719f\u6089\u500b\u4eba\u96fb\u8166\u53caMac\u6a5f\u61c9\u7528\u7a0b\u5f0f\u64cd\u4f5c\n\u651d\u5f71\u53ca\u526a\u7247\u5169\u7a2e\u6280\u80fd\u4ff1\u5099\u8005\uff0c\u7372\u512a\u5148\u8003\u616e\n\u826f\u597d\u6e9d\u901a\u6280\u5de7\uff0c\u559c\u6b61\u5718\u968a\u5de5\u4f5c\uff0c\u52e4\u596e\u597d\u5b78\uff0c\u559c\u6b61\u5275\u65b0\uff0c\u5c0d\u5de5\u4f5c\u6709\u8cac\u4efb\u611f\n\u4e94\u5929\u5de5\u4f5c\uff0c\u9700\u8f2a\u73ed\n\n\u6709\u610f\u8005\u8acb\u628a\u81ea\u5df1\u904e\u53bb\u62cd\u651d\u6216\u526a\u63a5\u7684\u4f5c\u54c1\u9023\u7d50\uff0c\u4e26\u9644\u4e0a\u5c65\u6b77\u53ca\u85aa\u91d1\u8981\u6c42\uff0c\u6309 \"Apply Now\" \u6309\u9215\u7533\u8acb\uff1b \u6216\u90f5\u5bc4\u81f3\u672c\u516c\u53f8\u4eba\u529b\u8cc7\u6e90\u90e8\uff0c\u5730\u5740:\u4e5d\u9f8d\u8354\u679d\u89d2\u9577\u9806\u88577\u865f\u897f\u9813\u4e2d\u5fc33305-7\u5ba4\uff0c\u4fe1\u5c01\u9762\u8acb\u8a3b\u660e\u300c\u61c9\u5fb5\u591a\u5a92\u9ad4\u8a18\u8005\u300d / \u300c\u61c9\u5fb5\u526a\u7247\u300d\u3002", "employment_types": ["Full Time"], "selling_points": [], "locations": ["Lai Chi Kok"], "categories": ["Media & Advertising", "Creative / Design", "Editorial / Journalism", "Photography / Video"], "post_time": "2022-01-17T06:11:10Z", "salary": {"currency": null, "max": null, "min": null, "period": "monthly", "term": null}, "salary_visible": false, "title_keywords": ["reporter", "video editor"], "responsibilities": [], "requirements": {"degrees": [], "majors": [], "languages": [], "language_level": [], "hard_skills": ["multimedia"], "soft_skills": [], "languages_combined": []}, "experience_required": {"duration": [], "field": []}}, {"job_id": "100003009055135", "location_code": "hk", "company": "Ocean Park Corporation", "job_title": "Contract Social Media Content Creator (Marketing Department)", "description": "Responsibilities:\n\nThe contract period will be until 30 June 2022\n\n1.Creating, editing, enhancing, promoting and supporting the implementations of digital contents/communication inclusive of a wide variety/broad spectrum of different media and creative promotional contents for different events and promotions taking place within the Park's existing and future social media platforms (e.g. Facebook, Instagram, YouTube, TikTok and many other popular social media platforms in Hong Kong);\n\n2.Creating and/or co-creating popular social media contents by following the latest local vibes while arousing interests of the general public of Hong Kong. Those working for this \"Creative Team of Story-telling\" should demonstrate good understandings of the Park's core values, being, Conservation & Education, and demonstrate the ability to create the relevant/heart-warming social media contents to better connect Ocean Park with the general public of Hong Kong general public, our precious guests;\n\n3.Supporting the promotion of OPC Corporate App and other creative content development initiatives all aims at better public penetrations, and more importantly public engagement\n\nRequirements\n\nFresh Graduates in any disciplines will be considered; yet candidates with Higher Diploma or above in Marketing and Digital Marketing or related disciplines will be a Plus (non-marketing major and/or candidates with lower academic qualifications will also be considered provided they can showcase their well-received past creations published on social media)\nCandidates with 1-year work experience in related field (candidates with no working experiences will be considered provided they can showcase their well-received past creations published on social media)\nSuper Creative is a MUST\nKnowledge in Photoshop and video editing software skills\nIndependent and detail minded with strong sense of responsibility\nComputer literacy in Excel, Word and Chinese Word processing\nGood command of both written and spoken English and Chinese\nFresh Graduates with strong interest in digital marketing and creative social media content development are also welcomed\n\nApplications including details of qualifications, working experience, expected salary, contact telephone number and address should be applied via:\u00a0http://careers.oceanpark.com.hk\u00a0--> Job opening --> Part time/ Short-term.\n\nApplicants not contacted within six weeks may consider their application unsuccessful. Personal data collected will be used for recruitment-related purpose only.", "employment_types": ["Temporary", "Contract"], "selling_points": ["Social Media Content Creator", "Marketing", "Digital Marketing"], "locations": ["Aberdeen"], "categories": ["Media & Advertising", "Editorial / Journalism", "Marketing / Public Relations", "Marketing - General / Support", "Digital Marketing"], "post_time": "2022-01-18T01:22:33Z", "salary": {"currency": null, "max": null, "min": null, "period": "monthly", "term": null}, "salary_visible": false, "title_keywords": [], "responsibilities": ["social media", "creative content", "social media platforms", "communication", "contents", "facebook", "editing"], "requirements": {"degrees": ["higher diploma or above"], "majors": ["related disciplines", "marketing", "digital marketing"], "languages": ["english", "chinese"], "language_level": ["good command"], "hard_skills": ["excel", "no", "plus", "chinese word processing", "word", "video editing", "photoshop"], "soft_skills": ["computer literacy", "creative", "independent", "sense of responsibility"], "languages_combined": [{"language": "english", "language_level": ["good command"]}, {"language": "chinese", "language_level": ["good command"]}]}, "experience_required": {"duration": ["1-year"], "field": ["related", "social media"]}}, {"job_id": "100003009054398", "location_code": "hk", "company": "i-CABLE Communications Limited", "job_title": "Media Librarian", "description": "Tape Library Department\nTo be responsible for\u00a0handling library material; assisting in data processing, archive management and managing all type of media; assisting to solve music copyright enquiries and the digitization project; performing ad-hoc tasks assigned by supervisor\nForm 5 or above with minimum 1 year relevant working experience\nGood command of both spoken and written English & Chinese\nFamiliar with Chinese word processing is a must\nAble to work independently on roster duty and work under pressure in a fast-paced\nKnowledge of Microsoft Office and copyright\nKnowledge in music and library relevant matters are preferred\nImmediate available is highly preferable\nWe offer 5-day work week, competitive remuneration packages and advancement opportunities. Interested parties, please write with full resume to Director, Human Resources, Human Resources Department, i-CABLE Communications Limited, 4/F Cable TV Tower, 9 Hoi Shing Road Tsuen Wan, N.T. or fax to 2112 7841 or via Apply Now (Please quote reference number and position applied for). For other information, please visit our website http://www.i-cable.com.\n\nYour application may be forwarded to any affiliate companies\u00a0and successful applicant may be seconded to work at any office as assigned.\u00a0 The information received will be used for consideration of employment only and all personal data supplied will be destroyed within 3 months.\n\nWe are an equal opportunity employer.", "employment_types": ["Full Time", "Permanent"], "selling_points": [], "locations": ["Tsuen Wan Area"], "categories": ["Media & Advertising", "Production", "Editorial / Journalism", "Broadcasting - TV / Radio"], "post_time": "2022-01-17T09:22:04Z", "salary": {"currency": null, "max": null, "min": null, "period": null, "term": null}, "salary_visible": false, "title_keywords": [], "responsibilities": ["work under pressure", "management", "ad-hoc tasks", "data processing"], "requirements": {"degrees": ["form 5 or above"], "majors": [], "languages": ["english", "chinese"], "language_level": ["good command"], "hard_skills": ["processing", "chinese word processing", "microsoft office"], "soft_skills": ["work independently", "responsible", "work under pressure"], "languages_combined": [{"language": "english", "language_level": ["good command"]}, {"language": "chinese", "language_level": ["good command"]}]}, "experience_required": {"duration": ["minimum 1 year"], "field": ["relevant working experience"]}}, {"job_id": "100003009055697", "location_code": "hk", "company": "Sing Tao News Corporation Limited (The Standard)", "job_title": "Online Reporter (The Standard Display Advertising - Supplement)", "description": "Responsibilities:\n\nResponsible for online website, app and social media platform\nInterview, editorial write up, translation for various supplements and projects\nAttend press conference, conduct interview, video shooting & editing\nMeeting & coordinate with clients and work closely with sales, design and editorial team\nGenerate stories, material sourcing and other Ad hoc projects\n\n\nRequirements:\n\nUniversity graduate major in Journalism / Communications / Language\nAt least 1 year working experience in relevant field, knowledge in video shooting and editing is preferred\nOutgoing and good\u00a0communication skill\nSelf-motivated, work independently\nAble to meet deadline and work under pressure\nExcellent written and spoken in English and Chinese\nWorking Location : Tseung Kwan O Industrial Estate\n\nInterested parties please\u00a0click \u201cApply Now\"\u00a0to submit your complete resume with\u00a0employment history and expected salary or by\u00a0post to\u00a0Human Resources Department, 3/F, Sing Tao News Corporation Building, 7 Chun Cheong Street, Tseung Kwan O Industrial Estate, Tseung Kwan O, New Territories, Hong Kong.\n\nWe are an equal opportunity employer and welcome applications from all qualified candidates. Information provided will be treated in strict confidence and only be used for recruitment related purpose. Applicant who is not invited for an interview within 6 weeks may consider their application not successful. All personal data of unsuccessful applicants will be destroyed within 6 months.\n\nwww.singtaonewscorp.com\u00a0", "employment_types": ["Full Time", "Permanent"], "selling_points": [], "locations": ["Tseung Kwan O"], "categories": ["Media & Advertising", "Editorial / Journalism", "Print Media", "Others", "Student / Fresh Graduate / No Experience"], "post_time": "2022-01-18T02:51:47Z", "salary": {"currency": null, "max": null, "min": null, "period": "monthly", "term": null}, "salary_visible": false, "title_keywords": ["online reporter"], "responsibilities": ["social media", "website", "design", "coordinate with clients", "video shooting", "ad hoc projects", "editing"], "requirements": {"degrees": ["university graduate"], "majors": ["journalism", "communications"], "languages": ["english", "chinese"], "language_level": ["excellent"], "hard_skills": [], "soft_skills": ["outgoing", "self-motivated", "work independently", "communication skill", "work under pressure"], "languages_combined": [{"language": "english", "language_level": ["excellent"]}, {"language": "chinese", "language_level": ["excellent"]}]}, "experience_required": {"duration": ["at least 1 year"], "field": ["editing", "video shooting"]}}, {"job_id": "100003009054463", "location_code": "hk", "company": "The Wing On Department Stores (Hong Kong) Limited", "job_title": "Assistant Marketing Manager (Promotions)", "description": "Responsibilities:\n\nDevelop and implement strategic advertising and promotional plans for our department stores across all platforms\nExecute translation, copywriting and editing on marketing materials, press release and advertorials, etc.\nWorking closely with internal and external parties for retail promotion program to ensure smooth planning and timelines\nManage the A&P budget and ensure effective ROI\n\nRequirements:\n\nDegree holder in Marketing, Communications, Journalism or related disciplines\nAt least \u00a04 years or above relevant experience in retail industry, preferably in marketing promotional\u00a0events\nExperience and good knowledge of print production and graphic interpretation\u00a0\nStrong in corporate level writing skills\nSensibility to figures & designs, initiative and detail-minded\nExcellent interpersonal and communication skills in English & Chinese\nProactive and able to work efficiently under pressure with ability to meet deadlines\nProficient in using MS Office and Chinese word processing\nCandidate with more experience or qualification will be considered as Promotions Manager\nImmediately available is highly preferred\n\nCommensurate remuneration and other fringe benefits will be offered to the right candidate.\u00a0 Interested parties please send your\u00a0full\u00a0resume\u00a0including\u00a0expected salary\u00a0to Human Resources Division, 3/F, Wing On Godown Building, 1 Wang Kee Street, Kowloon Bay, Kowloon, or by click \"APPLY NOW\" button below.\n\n(Candidates not invited for interview within one month may consider their applications filed for future reference.\u00a0 All information collected will be used for recruitment purpose only and will be destroyed after 6 months.)", "employment_types": ["Full Time", "Permanent"], "selling_points": [], "locations": ["Kowloon Bay"], "categories": ["Media & Advertising", "Editorial / Journalism", "Marketing / Public Relations", "Management", "Print Media"], "post_time": "2022-01-17T09:39:33Z", "salary": {"currency": null, "max": null, "min": null, "period": "monthly", "term": null}, "salary_visible": false, "title_keywords": ["assistant marketing manager"], "responsibilities": ["advertising", "internal and external parties", "budget", "develop", "marketing materials", "editing", "promotional plans", "planning"], "requirements": {"degrees": ["degree holder"], "majors": ["journalism", "related disciplines", "marketing", "communications"], "languages": ["english", "chinese"], "language_level": ["excellent", "proficient"], "hard_skills": ["chinese word processing", "writing skills", "ms office"], "soft_skills": ["detail-minded", "communication skills", "proactive", "under pressure", "writing skills", "meet deadlines", "initiative", "interpersonal"], "languages_combined": [{"language": "english", "language_level": ["excellent"]}, {"language": "chinese", "language_level": ["excellent", "proficient"]}]}, "experience_required": {"duration": ["4 years"], "field": ["retail industry", "print", "marketing", "relevant experience", "graphic"]}}, {"job_id": "100003009055707", "location_code": "hk", "company": "Sing Tao News Corporation Limited (The Standard)", "job_title": "Business News Reporter (The Standard Business)", "description": "Responsibilities:\n\nAttending press conferences, conduct one-on-one interview, write business news stories including online news\nMainly cover news on Hong Kong and China financial and property markets\n\nRequirements:\n\n\nDegree holder in Journalism, Communications or business-related studies\nHigh proficiency in both English and Chinese; speak fluent English, Cantonese, and Mandarin; as well as to read and write Chinese in addition to English\nGood to have accounting, business, finance, and economics background\nSound local knowledge\nFresh graduates are welcome\nWorking Location : Tseung Kwan O Industrial Estate\n\nInterested parties please\u00a0click \u201cApply Now\"\u00a0to submit your complete resume with\u00a0employment history and expected salary or by\u00a0post to\u00a0Human Resources Department, 3/F, Sing Tao News Corporation Building, 7 Chun Cheong Street, Tseung Kwan O Industrial Estate, Tseung Kwan O, New Territories, Hong Kong.\n\nWe are an equal opportunity employer and welcome applications from all qualified candidates. Information provided will be treated in strict confidence and only be used for recruitment related purpose. Applicant who is not invited for an interview within 6 weeks may consider their application not successful. All personal data of unsuccessful applicants will be destroyed within 6 months.\n\nwww.singtaonewscorp.com\u00a0", "employment_types": ["Full Time", "Permanent"], "selling_points": [], "locations": ["Tseung Kwan O"], "categories": ["Media & Advertising", "Editorial / Journalism", "Print Media", "Others", "Student / Fresh Graduate / No Experience"], "post_time": "2022-01-18T02:52:22Z", "salary": {"currency": null, "max": null, "min": null, "period": "monthly", "term": null}, "salary_visible": false, "title_keywords": ["reporter"], "responsibilities": ["conferences"], "requirements": {"degrees": ["degree holder"], "majors": ["journalism", "business", "communications"], "languages": ["cantonese", "english", "chinese", "mandarin"], "language_level": ["proficiency", "fluent"], "hard_skills": [], "soft_skills": [], "languages_combined": [{"language": "cantonese", "language_level": ["fluent"]}, {"language": "english", "language_level": ["proficiency", "fluent"]}, {"language": "chinese", "language_level": ["proficiency"]}, {"language": "mandarin", "language_level": ["fluent"]}]}, "experience_required": {"duration": [], "field": []}}, {"job_id": "100003009055834", "location_code": "hk", "company": "Ming Pao Publications Ltd", "job_title": "Marketing Executive/Assistant Marketing Executive", "description": "Responsibilities:\n\n\nAssist Marketing Manager in daily sales & marketing operations\n\nWork with designer to create advertising materials and marketing collateral\n\nBuild and maintain social media presence like Facebook, Instagram and YouTube\n\nResponsible for ad hoc assignments as required\n\nRequirements:\n\nUniversity graduate in Marketing, Business or related disciplines\nAt least 1-2 years' working experience in sales & marketing field, publishing industry will be definitely an advantage\n\nPaid social media advertising experience\nGood command of both written & spoken English and Chinese, include Putonghua\n\nProficiency in MS Office applications\nHighly organized, self-motivated, proactive team player\nGood interpersonal and communication skills\nIndependent and able to work under pressure\nImmediate availability is preferred\n\nWe offer attractive remuneration package to the right candidate. Interested parties please send full resume with salary expected to the Human Resources Department, 15/F., Block A, Ming Pao Industrial Centre, 18 Ka Yip Street, Chaiwan, Hong Kong\u00a0 or apply by clicking the Apply Now button.\n\nPersonal data collected will be used for recruitment purpose only", "employment_types": ["Full Time", "Permanent"], "selling_points": [], "locations": ["Chai Wan"], "categories": ["Media & Advertising", "Editorial / Journalism", "Print Media"], "post_time": "2022-01-18T02:59:48Z", "salary": {"currency": null, "max": null, "min": null, "period": "monthly", "term": null}, "salary_visible": false, "title_keywords": ["assistant marketing executive", "marketing executive"], "responsibilities": ["social media", "advertising", "operations", "maintain", "ad hoc assignments", "facebook"], "requirements": {"degrees": ["university graduate"], "majors": ["business", "related disciplines", "marketing"], "languages": ["putonghua", "english", "chinese"], "language_level": ["good command"], "hard_skills": ["ms office"], "soft_skills": ["organized", "self-motivated", "communication skills", "independent", "team player", "proactive", "interpersonal", "work under pressure"], "languages_combined": [{"language": "putonghua", "language_level": ["good command"]}, {"language": "english", "language_level": ["good command"]}, {"language": "chinese", "language_level": ["good command"]}]}, "experience_required": {"duration": ["at least 1-2 years"], "field": ["social media", "marketing", "advertising", "publishing"]}}, {"job_id": "100003009052933", "location_code": "hk", "company": "Passionation (Hong Kong) Limited", "job_title": "Editor (Lifestyle and Trending)", "description": "Primary Responsibilities\n\nIn charge of content development for a brand-new content platform, including articles, social media feeds, and video development, reaching agreed KPIs\nDrive, involve and participate in developing new content and programs that can build up the new platform\u2019s brand in the market\nLiaise with bloggers, influencers, guest editors, designers, and photographers for content development\nResearch topics, conduct interviews and content write up, especially on lifestyle and trendy topic\nRe-edit trendy topics and 3rd party contents for social usage\nAssist in daily channel content posting\nWork closely with local and regional team across departments\n\nSpecification and Requirement (Eligibility)\n\nBachelor's Degree and minimum 1 year of working experience in editorial. Fresh graduate will also be considered.\nGood knowledge in social media and story-telling skills\nExperience in fashion, beauty and lifestyle content is an advantage\nCreative and excellent digital and online knowledge\nAttentive to details and open minded\nGood communications skills in Cantonese, Mandarin, English and strong writing skills\u00a0", "employment_types": ["Full Time"], "selling_points": ["Min. 1 year of working experience in Editorial", "Creative and excellent online knowledge", "Good communications skills in Cantonese & English"], "locations": ["Quarry Bay"], "categories": ["Media & Advertising", "Creative / Design", "Editorial / Journalism", "Photography / Video"], "post_time": "2022-01-17T04:38:55Z", "salary": {"currency": null, "max": null, "min": null, "period": "monthly", "term": null}, "salary_visible": false, "title_keywords": ["editor"], "responsibilities": ["social media", "developing", "team across", "contents", "liaise with", "kpis"], "requirements": {"degrees": ["degree", "bachelor", "fresh graduate"], "majors": [], "languages": ["cantonese", "english", "mandarin"], "language_level": ["good"], "hard_skills": ["writing skills"], "soft_skills": ["creative", "open minded", "attentive to details", "writing skills"], "languages_combined": [{"language": "cantonese", "language_level": ["good"]}, {"language": "english", "language_level": ["good"]}, {"language": "mandarin", "language_level": ["good"]}]}, "experience_required": {"duration": ["minimum 1 year"], "field": ["editorial", "beauty"]}}, {"job_id": "100003009051488", "location_code": "hk", "company": "Imbee Limited", "job_title": "Creative Writer (English, Saas)", "description": "Please apply via:\u00a0https://jobs.lever.co/imbeelimited/93a6e4b9-05c5-417b-99fb-a7bb944bebd9\nHyper-growth tech startup. VC-backed. Competitive package. Remote work. Friendly team. : )\nAbout imBee\nimBee.io\u00a0is the #1 Customer Chat Management Platform - it provides one inbox for all communication channels with best-in-class business tools and workflow automation for brands to scale their business and communicate better externally with customers and internally with teams.\nAs one of the venture-backed, fastest-growing startups in Asia, we serve clients across industries and sizes. Some of our happy clients are insurance giants, telecom enterprises, and SMEs in the e-commerce, retail, education, and medical industry.\nOur Mission\nThe world is becoming more conversational - we\u2019re on a mission to empower businesses to scale on all communications channels effectively.\nWe\u2019re reinventing the way businesses communicate with their customers and teams, from the ground up, so businesses can sell more, accomplish more collaboratively, save more, and build better relationships with customers.\nOur Culture\nWe\u2019re ambitious, collaborative, and fun. We work smart and play hard, and pursue excellence in everything we do. It\u2019s a learning culture that we embrace.\u00a0\nAnd we care about each and everyone in our team - we want to help you achieve your personal goals and be part of this exciting and unforgettable journey.\nYou can enjoy a flexible work environment (remote work), free snacks and beers, game room, and more!\nRole\nWe are seeking an experienced writer to help improve the communication of our website, product messaging, and marketing materials. The ideal candidate will have a passion for writing and possess strong written communication skills.\n\nResponsibilities:\n\nTranslate customer needs and market demand into sharp and compelling messaging, content, sales tools, and campaigns to help us meet our business goals\nResearch and understand the client's needs and target audiences, through research, and interviews with subject matter experts\nWriting clear and engaging content for our website including blogs, and sales and marketing materials that reflects our brand\nDefine key messages and brand voice for external communications\nCollaborate with growth team and designers on marketing projects (e.g. email campaigns and landing pages)\nRequirements\n\nStrong editorial, proofreading, and writing skills (English)\nAbility to translate what customers want into compelling messages\nExperience with content marketing and cross-functional responsibilities\nExcellent interpersonal, verbal, and written communication skills\nAbility to manage multiple projects and meet deadlines under pressure\nPassion for writing with an excellent portfolio of work", "employment_types": ["Full Time", "Part Time", "Permanent", "Contract", "Freelance"], "selling_points": [], "locations": ["Kowloon City Area"], "categories": ["Media & Advertising", "Editorial / Journalism", "Marketing / Public Relations", "Public Relations - Copy-writing"], "post_time": "2022-01-16T04:16:56Z", "salary": {"currency": "HKD", "max": 24999, "min": 17000, "period": "monthly", "term": null}, "salary_visible": true, "title_keywords": ["creative"], "responsibilities": ["collaborate with", "business goals", "marketing projects", "website", "marketing materials"], "requirements": {"degrees": [], "majors": [], "languages": ["english"], "language_level": [], "hard_skills": ["writing skills"], "soft_skills": ["communication skills", "under pressure", "passion for", "writing skills", "meet deadlines", "interpersonal"], "languages_combined": [{"language": "english", "language_level": []}]}, "experience_required": {"duration": [], "field": ["marketing"]}}, {"job_id": "100003009052275", "location_code": "hk", "company": "New Media Group Publishing Limited", "job_title": "Project Editor (Sports Trend \u904b\u52d5\u6f6e\u6d41\uff09", "description": "Job Nature:\u00a0\u00a0\n\nResponsible for daily management of CS Content for social media platform\nProduce content video included writing script, web-articles and social-media contents\nWork close with content partnership and keep daily publish schedule run smooth\nHandling clients project, various ad hoc projects under tight schedule independently\nWork closely with internal parties and sales team\nGenerate regular content reports /\u00a0 CS reports for performance analysis\n\nCharacters / Qualifications:\n\n\nBachelor degree holder, preferably in journalism\nOver 1 years experience on lifestyle / sports reporting or editing\nStrong digital and online knowledge\nGood understanding of social Media environment and multi media industries\nGood communication skill\nHave good connections with KOLs and Sports pages\n\nWe offer competitive salary and benefits package( 5 days work, 14 days AL up, birthday leave, medical & dental insurance) with great opportunity for career development to the successful candidate.\n\nPlease send your detailed resume and expected salary to our Human Resources Department by clicking \"Apply Now\" (please put position applied on subject line).", "employment_types": ["Full Time", "Permanent"], "selling_points": ["Handling clients project, Strong digital knowledge", "Have good connections with KOLs and Sports pages", "Great development opportunity, competitive package"], "locations": ["Kwun Tong"], "categories": ["Media & Advertising", "Others", "Editorial / Journalism", "Marketing / Public Relations", "Digital Marketing"], "post_time": "2022-01-17T02:37:40Z", "salary": {"currency": null, "max": null, "min": null, "period": null, "term": null}, "salary_visible": false, "title_keywords": ["editor"], "responsibilities": ["social media", "management", "reporting", "analysis", "communication", "ad hoc projects", "schedule", "sales team", "contents", "reports", "career development", "editing", "insurance", "internal parties"], "requirements": {"degrees": ["bachelor degree holder"], "majors": ["journalism"], "languages": [], "language_level": [], "hard_skills": ["analysis", "web"], "soft_skills": ["independently", "responsible", "communication skill", "smooth", "detailed"], "languages_combined": []}, "experience_required": {"duration": ["1 years"], "field": ["editing"]}}, {"job_id": "100003009052171", "location_code": "hk", "company": "A-World Consulting Limited", "job_title": "Account Executive", "description": "Who we are:\n\nA-World Consulting (www.a-world.com.hk) is a Hong Kong-based, full-service communication and management consultancy covering Greater China.\u00a0 With affiliates/offices in various cities in Mainland China, we seek to provide creative solutions to clients through the combined networks and resources of a tight team of professionals with creative minds.\n\n\n\nJob Description:\n\n\nBusiness development and/or client servicing\n\nResearch, development and implementation of effective communication strategies and work plans for clients\n\nMonitor the larger environment and industry developments etc. to pre-empt clients of potential issues and opportunities, and provide corresponding solutions and recommendations\n\nAccount management in terms of finances, schedules and deliverables\n\nSupervision of junior staff as appropriate\u00a0\n\nRequirements:\n\nTertiary degree or equivalent in communication/public affairs/journalism\n\nAt least 2 years of experience in PR or related industries for Senior Account Executive and 1 years for Account Executive, preferably with agency background\n\nProven English and Chinese proficiency; fluency in Putonghua preferred\n\nPublic affairs/media/corporate communication experience and good network/relations\n\nExcellent business acumen, leadership and interpersonal skills, if applicable\n\nDetail-minded, proactive and able to work under tight schedule and pressure\n\nA good team player with a can-do spirit\n\nExperience in account management and mentoring junior executives, if applicable\n\n5-day work per week, but work outside normal working hours and days should be expected.\u00a0 Excellent compensation and attractive fringe benefits will be offered to the successful candidate.\u00a0 Interested parties please send full resume with availability and present and expected salary by clicking \"Apply Now\".\n\n\nAll personal data collected will be used for recruitment purpose only.\u00a0 Applicants not hearing from us within 6 months may consider their applications unsuccessful.\u00a0 All personal data supplied will be destroyed after 6 months.", "employment_types": ["Full Time", "Permanent"], "selling_points": ["5 days work per week", "performance bonus", "Fresh Graduate also welcome"], "locations": ["Sheung Wan"], "categories": ["Media & Advertising", "Editorial / Journalism", "Marketing / Public Relations", "Public Relations - Copy-writing", "Public Relations - Event Management"], "post_time": "2022-01-17T02:20:07Z", "salary": {"currency": null, "max": null, "min": null, "period": "monthly", "term": null}, "salary_visible": false, "title_keywords": ["account executive"], "responsibilities": [], "requirements": {"degrees": [], "majors": [], "languages": [], "language_level": [], "hard_skills": [], "soft_skills": [], "languages_combined": []}, "experience_required": {"duration": [], "field": []}}, {"job_id": "100003009052857", "location_code": "hk", "company": "Passionation (Hong Kong) Limited", "job_title": "Senior Editor (Lifestyle and Trending)", "description": "Primary Responsibilities\n\nIn charge of content and business development for a brand-new content platform, including articles, social media feeds, and video development, reaching agreed KPIs\nDrive, involve and participate in developing new content and programs that can build up the new platform\u2019s brand in the market\nLiaise with bloggers, influencers, guest editors, designers, and photographers for content development\nResearch topics, conduct interview and content write up, especially on lifestyle and trending topic\nRe-edit trending topics and 3rd party content for social use\nAssist in daily channel content posting\nCoach juniors to deliver good quality content timely\nWork closely with local and regional team from different departments\n\nSpecification and Requirement (Eligibility)\n\nBachelor's Degree and minimum 3 years of working experience in editorial\nGood knowledge in social media and story-telling skills\nExperience in fashion, beauty and lifestyle content is an advantage\nCreative and excellent digital and online knowledge\nAttentive to details and open minded\nGood communications skills in Cantonese, Mandarin, English, and strong writing skills\u00a0", "employment_types": ["Full Time"], "selling_points": ["Min. 3 years of working experience in Editorial", "Experience in Fashion & Lifestyle content", "Good knowledge in social media and story-telling"], "locations": ["Quarry Bay"], "categories": ["Media & Advertising", "Creative / Design", "Editorial / Journalism", "Photography / Video"], "post_time": "2022-01-17T04:25:55Z", "salary": {"currency": null, "max": null, "min": null, "period": "monthly", "term": null}, "salary_visible": false, "title_keywords": ["senior editor"], "responsibilities": ["social media", "quality", "developing", "liaise with", "kpis"], "requirements": {"degrees": ["degree", "bachelor"], "majors": [], "languages": ["cantonese", "english", "mandarin"], "language_level": ["good"], "hard_skills": ["writing skills"], "soft_skills": ["creative", "open minded", "attentive to details", "writing skills"], "languages_combined": [{"language": "cantonese", "language_level": ["good"]}, {"language": "english", "language_level": ["good"]}, {"language": "mandarin", "language_level": ["good"]}]}, "experience_required": {"duration": ["minimum 3 years"], "field": ["editorial", "beauty"]}}, {"job_id": "100003009055229", "location_code": "hk", "company": "ORIENTAL HUMAN RESOURCES LIMITED", "job_title": "Reporter / Editor Trainee - Local News / Financial News", "description": "University or College graduate, no experience is required, our company will provide comprehensive on-job training\nFamiliar and sensitive to local news / financial news\nGood command of Chinese and English\nShift duty and rotated rest day are required\n(Those with more experience will be considered as Senior position)\n\n\n\nApplication Method\n\nWe offer free shuttle bus, free parking and fringe benefits including medical scheme, discretionary bonus and public holidays\u00a0to the right candidate. Interested parties, please send full resume with expected salary to ORIENTAL HUMAN RESOURCES LIMITED\u00a0by\u00a0clicking \"Apply now\" ;\u00a0or fax to 3600 1900 ( Please quote reference on the application letter )\n\n\nPersonal Information Collection Statement\n\nPersonal data collected will be treated in accordance with our Personal Data Policy and handled in strict confidence by authorized personnel for recruitment related purpose only.\u00a0 \u00a0 \u00a0\n\u00a0 \u00a0 \u00a0 \u00a0 \u00a0 \u00a0\n\n\u00a0 \u00a0 \u00a0 \u00a0 \u00a0 \u00a0 \u00a0 \u00a0 \u00a0 \u00a0 \u00a0 \u00a0 \u00a0 \u00a0 \u00a0 \u00a0 \u00a0 \u00a0 \u00a0 \u00a0 \u00a0 \u00a0 \u00a0 \u00a0 \u00a0 \u00a0 \u00a0\u00a0on.cc\n\n", "employment_types": ["Full Time"], "selling_points": [], "locations": ["Tai Po Area"], "categories": ["Banking / Finance", "Others", "Media & Advertising", "Editorial / Journalism", "Print Media"], "post_time": "2022-01-18T01:53:01Z", "salary": {"currency": null, "max": null, "min": null, "period": "monthly", "term": null}, "salary_visible": false, "title_keywords": ["reporter", "editor", "trainee"], "responsibilities": [], "requirements": {"degrees": [], "majors": [], "languages": ["english", "chinese"], "language_level": ["good command"], "hard_skills": ["no"], "soft_skills": ["sensitive to", "comprehensive"], "languages_combined": [{"language": "english", "language_level": ["good command"]}, {"language": "chinese", "language_level": ["good command"]}]}, "experience_required": {"duration": [], "field": ["training"]}}, {"job_id": "100003009041988", "location_code": "hk", "company": "Pearson Education Asia Limited", "job_title": "Senior Content Developer / Content Developer (Senior Editor / Editor) - ELT", "description": "Responsibilities:\n\nStrong sense on health care topics, investigate and share with readers\nSolid grasp of information, with an unbiased standpoint\nAttentive, search and create engaging content to drive performances\nProficiency in video editorial, work independently for data collection and interviewing\n\nRequirements:\n\nInitiative, strong written communication skills\nGood team player; prepare quality articles, feature stories, etc.\nBachelor Degree holder with relevant experience will be considered in advanced\nFamiliar with major social platforms\nMedia work experiences with video editing and frame-out are preferred\nPlease bring along your portfolio or any references for interview\nWorking Location: Tseung Kwan O Industrial Estate\n\nInterested parties please click \u201cApply Now\" to submit your complete resume with\u00a0employment history, expected salary and REFERENCE NUMBER or by\u00a0post to\u00a0Human\u00a0Resources Department,\u00a0Sing Tao News Corporation Building, 7 Chun Cheong Street, Tseung Kwan O Industrial Estate, Tseung Kwan O, New Territories, Hong Kong\n\nWe are an equal opportunity employer and welcome applications from all qualified candidates. Information provided will be treated in strict confidence and only be used for recruitment related purpose. Applicant who is not invited for an interview within 6 weeks may consider their application not successful. All personal data of unsuccessful applicants will be destroyed within 6 months.\n\nwww.singtaonewscorp.com", "employment_types": ["Full Time", "Permanent"], "selling_points": ["5 days work, Flexible working hours", "13 months salary", "Performance bonus"], "locations": ["Quarry Bay"], "categories": ["Media & Advertising", "Editorial / Journalism", "Education", "Others", "Manufacturing", "Product Development / Management"], "post_time": "2022-01-12T05:00:56Z", "salary": {"currency": null, "max": null, "min": null, "period": "monthly", "term": null}, "salary_visible": false, "title_keywords": ["editor", "developer", "senior editor"], "responsibilities": ["data collection"], "requirements": {"degrees": ["bachelor degree holder"], "majors": [], "languages": [], "language_level": [], "hard_skills": ["video editing"], "soft_skills": ["advanced", "communication skills", "good team player", "initiative"], "languages_combined": []}, "experience_required": {"duration": [], "field": ["video", "relevant experience", "media", "editing"]}}, {"job_id": "100003009046101", "location_code": "hk", "company": "Sing Tao Management Services Limited", "job_title": "Content Creator (Technology - New Media Business)", "description": "Responsibilities:\n\nGreat interest on high end consumes and F&B\nSolid grasp of information, investigate and share with readers\nProficiency in video editorial, work independently for data collection and interviewing\n\nRequirements:\n\nInitiative, strong written communication skills\nGood team player; prepare quality articles, feature stories, etc.\nBachelor Degree holder with relevant experience will be considered in advanced\nFamiliar with major social platforms\nMedia work experiences with video editing and frame-out are preferred\nPlease bring along your portfolio or any references for interview\nWorking Location: Tseung Kwan O Industrial Estate\n\nInterested parties please click \u201cApply Now\" to submit your complete resume with\u00a0employment history, expected salary and REFERENCE NUMBER or by\u00a0post to\u00a0Human\u00a0Resources Department,\u00a0Sing Tao News Corporation Building, 7 Chun Cheong Street, Tseung Kwan O Industrial Estate, Tseung Kwan O, New Territories, Hong Kong\n\nWe are an equal opportunity employer and welcome applications from all qualified candidates. Information provided will be treated in strict confidence and only be used for recruitment related purpose. Applicant who is not invited for an interview within 6 weeks may consider their application not successful. All personal data of unsuccessful applicants will be destroyed within 6 months.\n\nwww.singtaonewscorp.com", "employment_types": ["Full Time", "Permanent"], "selling_points": [], "locations": ["Tseung Kwan O"], "categories": ["Media & Advertising", "Production", "Editorial / Journalism", "Photography / Video"], "post_time": "2022-01-13T09:36:45Z", "salary": {"currency": null, "max": null, "min": null, "period": "monthly", "term": null}, "salary_visible": false, "title_keywords": [], "responsibilities": ["data collection"], "requirements": {"degrees": ["bachelor degree holder"], "majors": [], "languages": [], "language_level": [], "hard_skills": ["video editing"], "soft_skills": ["advanced", "communication skills", "good team player", "initiative"], "languages_combined": []}, "experience_required": {"duration": [], "field": ["video", "relevant experience", "media", "editing"]}}, {"job_id": "100003009036691", "location_code": "hk", "company": "Phoenix Satellite Television Co Ltd", "job_title": "\u6e2f\u805e\u7de8\u8f2f", "description": "\u8077\u8cac\uff1a\n\n\n\u8ca0\u8cac\u5831\u9053\u6cd5\u5ead\u6848\u4ef6\u53ca\u76f8\u95dc\u8cc7\u8a0a\n\u5916\u52e4\u5de5\u4f5c\n\n\u8077\u4f4d\u8981\u6c42\uff1a\n\n\n\u5927\u5b78\u7a0b\u5ea6\uff0c\u4e3b\u4fee\u65b0\u805e\u7cfb\u512a\u5148\u8003\u616e\n\u4e2d\u82f1\u6587\u512a\u826f\uff0c\u5177\u76f8\u95dc\u7d93\u9a57\u512a\u5148\n\u4e3b\u52d5\u3001\u6295\u5165\u3001\u5bcc\u8cac\u4efb\u611f\n\u80fd\u5373\u6642\u5230\u4efb\u70ba\u4f73\n\u5de5\u4f5c\u5730\u9ede\uff1a\u5c07\u8ecd\u6fb3\u5de5\u696d\u90a8\u53ca\u5404\u5340\u6cd5\u9662\n\n\u6c42\u8077\u8005\u8acb\u8a73\u9644\u500b\u4eba\u5c65\u6b77\u53ca\u8981\u6c42\u5f85\u9047\uff0c\u5bc4\u9999\u6e2f\u65b0\u754c\u5c07\u8ecd\u6fb3\u5de5\u696d\u90a8\u99ff\u660c\u8857\u4e03\u865f\u661f\u5cf6\u65b0\u805e\u96c6\u5718\u5927\u5ec83\u6a13\u4eba\u529b\u8cc7\u6e90\u90e8\u6536\uff0c\u4fe1\u5c01\u9762\u8acb\u8a3b\u660e\u7533\u8acb\u8077\u4f4d\u6216\u6309\u201cApply Now\u201d\u63d0\u4ea4\u7533\u8acb\u3002\n\n\u672c\u516c\u53f8\u70ba\u516c\u5e73\u6a5f\u6703\u50f1\u4e3b\uff0c\u6b61\u8fce\u6240\u6709\u5408\u8cc7\u683c\u7684\u5019\u9078\u4eba\u7533\u8acb\u3002\u6240\u63d0\u4f9b\u7684\u4fe1\u606f\u5c07\u56b4\u683c\u4fdd\u5bc6\uff0c\u50c5\u7528\u65bc\u62db\u8058\u76f8\u95dc\u7528\u9014\u3002\u82e5\u672a\u80fd\u65bc 6 \u9031\u5167\u7372\u9080\u51fa\u5e2d\u9762\u8a66\u7684\u7533\u8acb\u8005\u6703\u81ea\u52d5\u843d\u9078\uff0c\u53e6\u6240\u6709\u843d\u9078\u7684\u7533\u8acb\u8005\u7684\u6240\u6709\u500b\u4eba\u8cc7\u6599\u5c07\u57286\u500b\u6708\u5167\u92b7\u6bc0\u3002\n\nwww.singtaonewscorp.com", "employment_types": ["Full Time"], "selling_points": [], "locations": ["Tai Po Area"], "categories": ["Media & Advertising", "Editorial / Journalism"], "post_time": "2022-01-10T12:39:50Z", "salary": {"currency": null, "max": null, "min": null, "period": null, "term": null}, "salary_visible": false, "title_keywords": [], "responsibilities": [], "requirements": {"degrees": [], "majors": [], "languages": [], "language_level": [], "hard_skills": [], "soft_skills": [], "languages_combined": []}, "experience_required": {"duration": [], "field": []}}, {"job_id": "100003009038394", "location_code": "hk", "company": "\u7d93\u6fdf\u4e00\u9031 EDigest", "job_title": "Social Media Executive/Digital Content Executive/Growth Editor (Business & Finance)", "description": "Job Duties:\n\n1. Conduct business risk and internal control review for major operating processes of the Headquarters and Business Units; complete audit working papers and draft audit reports;\n\n2. Follow up rectification status of the identified audit matters;\n\n3. Assist in compiling internal control-related policies and procedures;\n\n4. Assist in compiling ESG report;\n\n5. Handle the other tasks as assigned by the department head.\n\n\u5de5\u4f5c\u8077\u8cac:\n\n1. \u5c31\u7e3d\u90e8\u5c64\u9762\u4e3b\u8981\u904b\u4f5c\u6d41\u7a0b\u53ca\u96c6\u5718\u4e0b\u5c6c\u7d93\u71df\u55ae\u4f4d\uff0c\u9032\u884c\u7d93\u71df\u98a8\u96aa\u53ca\u5167\u90e8\u63a7\u5236\u6aa2\u8996\u5de5\u4f5c\uff0c\u5b8c\u6210\u5be9\u8a08\u5e95\u7a3f\u4e26\u7de8\u5beb\u5be9\u8a08\u5831\u544a\uff08\u4e2d\u6587\u6216\u82f1\u6587\uff09\uff1b\n\n2. \u5b9a\u671f\u8ddf\u9032\u5be9\u8a08\u554f\u984c\u7684\u6574\u6539\u60c5\u6cc1\uff1b\n\n3. \u5354\u52a9\u7de8\u5beb\u76f8\u95dc\u5167\u63a7\u7ba1\u7406\u5236\u5ea6\u53ca\u6d41\u7a0b\uff1b\n\n4. \u5354\u52a9\u7de8\u5beb\u96c6\u5718\u4e4b\u74b0\u5883\u3001\u793e\u6703\u53ca\u7ba1\u6cbb\u5831\u544a\uff1b\n\n5. \u5b8c\u6210\u4ea4\u8fa6\u7684\u5176\u4ed6\u5de5\u4f5c\u3002\n\n\n\nJob Duties:\n\n1. Possesses 3 years or above external or internal audit experiences;\n\n2. Possesses the Certified Internal Auditors (CIA) qualification;\n\n3. Knowledge in HK listing rules and working experience in Chinese companies is preferred;\n\n4. Strong analytical and communication skills; complete tasks independently;\n\n5. Team work, responsible, proactive and attentive;\n\n6. Good reporting writing skills and fluent Mandarin;\n\n7. Occasional travel on a job-by-job basis.\n\n8. Candidate with less experience will be considered as Internal Audit Assistant\n\n\u5de5\u4f5c\u8981\u6c42:\n\n1. \u5177\u67093\u5e74\u6216\u4ee5\u4e0a\u5728\u6703\u8a08\u5e2b\u4e8b\u52d9\u6240\u5f9e\u4e8b\u5916\u90e8\u5be9\u8a08\u6216\u5728\u4f01\u696d\u5f9e\u4e8b\u5167\u90e8\u5be9\u8a08\u5de5\u4f5c\u4e4b\u7d93\u9a57\uff1b\n\n2. \u5177\u6709\u570b\u969b\u5167\u90e8\u5be9\u8a08\u5e2b\u8cc7\u683c(CIA)\uff1b\n\n3. \u5c0d\u4e0a\u5e02\u689d\u4f8b\u6709\u4e00\u5b9a\u77ad\u89e3, \u53ca\u6709\u4e2d\u8cc7\u4f01\u696d\u5de5\u4f5c\u7d93\u9a57\u8005\u512a\u5148\uff1b\n\n4. \u5177\u6709\u8f03\u5f37\u7684\u5206\u6790\u80fd\u529b\u548c\u6e9d\u901a\u5354\u8abf\u80fd\u529b\uff0c\u80fd\u7368\u7acb\u5b8c\u6210\u5de5\u4f5c\u4efb\u52d9\uff1b\n\n5. \u5177\u6709\u826f\u597d\u7684\u5718\u968a\u5408\u4f5c\u7cbe\u795e\u3001\u6709\u8cac\u4efb\u611f\u3001\u7a4d\u6975\u4e3b\u52d5\u53ca\u7d30\u5fc3;\n\n6. \u5177\u6709\u826f\u597d\u7684\u5831\u544a\u5beb\u4f5c\u80fd\u529b\u53ca\u6d41\u5229\u666e\u901a\u8a71\uff1b\n\n7. \u6309\u5de5\u4f5c\u9700\u8981\u51fa\u5dee\u5167\u5730\u3002\n\nFor more details of our company, please visit our website at http://www.ifeng.com/\n\nWe offer attractive remuneration package to the right candidate. Interested parties please click \u201cApply Now\u201d to submit applications or send applications with detailed resume stating career history, present & expected salary and date available to Human Resources Department, Phoenix Satellite Television Co. Ltd. via fax: 2200 8620.\n\nPersonal data collected will be used for recruitment purpose only. Applicants not hearing from us within 6 weeks may consider their applications unsuccessful and all related information will be destroyed after 6 months.", "employment_types": ["Full Time", "Permanent"], "selling_points": ["Content development & data analysis", "Experience in social media marketing field", "Great development opportunity, competitive package"], "locations": ["Kwun Tong"], "categories": ["Media & Advertising", "Creative / Design", "Others", "Editorial / Journalism"], "post_time": "2022-01-11T06:45:09Z", "salary": {"currency": null, "max": null, "min": null, "period": null, "term": null}, "salary_visible": false, "title_keywords": ["editor", "digital content executive", "social media executive"], "responsibilities": ["reporting", "internal audit", "policies", "review", "rectification", "audit", "procedures", "website", "communication", "other tasks", "reports", "report", "listing", "internal control"], "requirements": {"degrees": [], "majors": [], "languages": ["chinese", "mandarin"], "language_level": ["fluent", "good"], "hard_skills": ["reporting writing skills", "internal control"], "soft_skills": ["attentive", "communication skills", "independently", "responsible", "writing skills", "proactive"], "languages_combined": [{"language": "chinese", "language_level": []}, {"language": "mandarin", "language_level": ["fluent", "good"]}]}, "experience_required": {"duration": ["3 years"], "field": ["audit"]}}, {"job_id": "100003009037529", "location_code": "hk", "company": "ORIENTAL HUMAN RESOURCES LIMITED", "job_title": "Reporter / Editor Trainee - Local News / Financial News", "description": "As the leader of the Chinese content writers team, you will need to work closely with other marketing teams to discuss about the content strategy and direction planning. You will need to ensure the quality of the content produced and matches with the brand's identity as well as the corporate image.\n\nWhat are your responsibilities?\n\nMaintaining and enhancing the quality of Mandarin content. Namely editing content produced by the CN team, including conceptualizing the projects upfront, assigning tasks and overseeing development and copy-editing prior to publishing.\u00a0\nContribute to producing high-quality articles, white papers, blogs, press releases, email marketing messages, SEO writing, and web copy\nPush the business to adopt better content creation practices through frequent testing of new content formats and distribution channels, including championing the increased use of data visualization\nManage and assign tasks to CN Content team members\nWork closely with English Content team and Brand Operation team for optimum team results\n\nWho are we looking for?\n\nEducation: Bachelor Degree and above\nAt least 3 to 5 years of content writing experience\nAble to communicate, read and write in Mandarin and English\nPrior team management experience\nExperienced in Finance or Tech industry will be an added advantage\nAble to adapt into fast-paced working environment, able to work under stress\n\nThe Doo Expectations\n\nYou don't need to know everything about our industry, because even we don't! This is an ever-changing industry that is expeditious and technology-filled - and we are learning new things every day. In this fast-paced environment, expect a lot of new challenges and changes along the way.\n\nIn a nutshell, we are looking for talent who is ready to grow and succeed together with Doo!\n\n#DooBeyondLimit #TogetherWeDooMore #SucceedYourCareerWithDoo", "employment_types": ["Full Time"], "selling_points": [], "locations": ["Tai Po Area"], "categories": ["Banking / Finance", "Others", "Media & Advertising", "Editorial / Journalism", "Print Media"], "post_time": "2022-01-11T03:02:45Z", "salary": {"currency": null, "max": null, "min": null, "period": "monthly", "term": null}, "salary_visible": false, "title_keywords": ["reporter", "editor", "trainee"], "responsibilities": ["management", "seo", "visualization", "maintaining", "data", "assign tasks", "quality", "teams", "testing", "editing", "conceptualizing", "planning"], "requirements": {"degrees": ["degree", "bachelor"], "majors": [], "languages": ["english", "chinese", "mandarin"], "language_level": [], "hard_skills": ["seo", "web", "data visualization"], "soft_skills": ["fast-paced environment", "learning"], "languages_combined": [{"language": "english", "language_level": []}, {"language": "chinese", "language_level": []}, {"language": "mandarin", "language_level": []}]}, "experience_required": {"duration": ["at least 3 to 5 years"], "field": ["content writing", "management", "team"]}}, {"job_id": "100003009035502", "location_code": "hk", "company": "Project Orbis Int'l Inc", "job_title": "Communications Executive", "description": "Responsibilities:\u00a0\n\nResearch and write news stories and/or features on education and parenting assigned by News Editor for web, magazine and social media platforms\uff08FB, IG, etc\uff09\nVideo shooting and editing events and news reports\nRegular website and social media work\nManage website, FB, IG, etc.\nLive streaming of special news events\nNeed to work on shift and weekends\n\nRequirements:\n\nJournalism/ Communication background preferred though equivalent experience will be considered\nKnowledge of graphic/video/image editing skills is required\nExcellent verbal and written communication skills are essential\nMust be creative, hard-working, and a self-starter\nWorking Location : Tseung Kwan O Industrial Estate\n\nInterested parties please\u00a0click \u201cApply Now\"\u00a0to submit your complete resume with\u00a0employment history and expected salary or by\u00a0post to\u00a0Human Resources Department, 3/F, Sing Tao News Corporation Building, 7 Chun Cheong Street, Tseung Kwan O Industrial Estate, Tseung Kwan O, New Territories, Hong Kong.\n\nWe are an equal opportunity employer and welcome applications from all qualified candidates. Information provided will be treated in strict confidence and only be used for recruitment related purpose. Applicant who is not invited for an interview within 6 weeks may consider their application not successful. All personal data of unsuccessful applicants will be destroyed within 6 months.\n\nwww.singtaonewscorp.com", "employment_types": ["Full Time", "Permanent"], "selling_points": ["Flexible work schedule", "Stable and friendly working environment", "Competitive package and attractive benefits"], "locations": ["Kwun Tong"], "categories": ["Media & Advertising", "Editorial / Journalism", "Marketing / Public Relations", "Marketing - Marketing Communication", "Public / Civil", "Social Services - Community / Non-profit Organization"], "post_time": "2022-01-10T07:27:57Z", "salary": {"currency": null, "max": null, "min": null, "period": "monthly", "term": null}, "salary_visible": false, "title_keywords": ["executive"], "responsibilities": ["social media", "manage website", "website", "video shooting", "reports", "editing"], "requirements": {"degrees": [], "majors": [], "languages": [], "language_level": [], "hard_skills": [], "soft_skills": ["communication", "communication skills", "creative", "hard-working"], "languages_combined": []}, "experience_required": {"duration": [], "field": []}}, {"job_id": "100003009035637", "location_code": "hk", "company": "Creative Art (HK) Culture Communication Co., Limited", "job_title": "\u6587\u6848\u7b56\u5283", "description": "Job Responsibilities:\nAssist in all editorial responsibilities relating to school publications, annual calendars, circulars, marketing and media material, digital content and any other material as required to support various departments and stakeholders of the school;\nManage all school portals and platforms;\nMultimedia content creation or editing; \u00a0\nAssist with school, media and public events;\nInternal and external coordination and relations with stakeholders and vendors; \u00a0\nNews monitoring and alert;\nHandling of general enquiries;\nAny other duties as assigned by the Senior Manager and Head of Communications; and\nAlign with and contribute to the overall strategy goals of the Communications and Communities office.\nRequirements:\nBachelor Degree in Communications, Journalism, Translation or related disciplines;\nMinimum 4 years of experience in marketing communications is preferable;\nDigital content and marketing skills a plus;\nExcellent written and verbal communication skills in English and Chinese (Cantonese and Putonghua);\nWilling to work overtime or weekends if required; and\nWell organized, self-motivated and a good team player.\nThe ISF Foundation, Academy & Pre-School are committed to ensuring safety and well-being of our students. We hold high standards of recruitment practices with specific attention to child protection. All applicants must be willing to undergo relevant background checks and screenings.\u00a0\u00a0\nFree Shuttle Bus travelling to and from The ISF Academy will be provided:\nRoute: North Point > Admiralty Centre > Causeway Bay > Aberdeen > The ISF Academy\nApplication Deadline: 28 January 2022\nRemuneration will commensurate with qualifications and experience. We will offer an attractive benefits package including medical, life insurance, and opportunities for professional development and continuing education to the right candidate. Please submit your application by completing the Application Form, Reference Check Statement which could be downloaded from our website: www.isf.edu.hk together with full Curriculum Vitae and Covering Letter. Please quote with our \u201cRef: no.\u201d by email via \"Apply Now\". \u00a0\u00a0\nPersonal data is collected for employment purposes only.", "employment_types": ["Full Time"], "selling_points": [], "locations": ["Mong Kok"], "categories": ["Media & Advertising", "Editorial / Journalism", "Marketing / Public Relations", "Marketing - Market Research", "Public Relations - Copy-writing"], "post_time": "2022-01-10T07:58:42Z", "salary": {"currency": null, "max": null, "min": null, "period": "monthly", "term": null}, "salary_visible": false, "title_keywords": [], "responsibilities": ["any other duties", "editing", "monitoring", "coordination"], "requirements": {"degrees": ["degree", "bachelor"], "majors": ["journalism", "related disciplines", "communications"], "languages": ["cantonese", "putonghua", "english", "chinese"], "language_level": ["excellent"], "hard_skills": ["no", "translation", "marketing skills", "plus"], "soft_skills": ["communication skills", "work overtime", "self-motivated", "good team player", "well organized", "committed"], "languages_combined": [{"language": "cantonese", "language_level": ["excellent"]}, {"language": "putonghua", "language_level": ["excellent"]}, {"language": "english", "language_level": ["excellent"]}, {"language": "chinese", "language_level": ["excellent"]}]}, "experience_required": {"duration": ["minimum 4 years"], "field": ["marketing communications"]}}, {"job_id": "100003009036689", "location_code": "hk", "company": "Phoenix Satellite Television Co Ltd", "job_title": "\u6e2f\u805e\u8a18\u8005", "description": "\u98df\u8166\u4f9d\u5bb6\u597dL\u591aJOB\uff0c\u6435\u5497\u597dL\u591a\u9322\n\u6240\u4ee5\u60f3\u7528\u4f4e\u65bc\u5e02\u50f9\u5605\u50f9\u9322\uff0c\u8acb\u591a\u4e00\u500b\u7de8\u5c0e\n\n\u82e5\u7136\u4f60\u81ea\u8a8d\u6709\u5e7d\u9ed8\u611f\n\u53c8\u6709\u559c\u5287\u7d30\u80de\n\u540c\u57cb\u5c11\u5c11\u6232\u5287\u89f8\u89ba\n\u800c\u4e14\u7dca\u8cbc\u6f6e\u6d41\u8a71\u984c\n\u7576\u7136\u4e0d\u5c11\u5f97\u8cac\u4efb\u5fc3\n\u80fd\u5920\u6371\u66f4\u62b5\u591c\n\u505a\u4eba\u505a\u4e8b\u90fd\u6709\u5718\u706b\u00a0\n\u540c\u6642\u4ea6\u5c0b\u8993\u7dca\u4e00\u73ed\u597d\u5144\u5f1f\n\u4e00\u500b\u5e73\u53f0\u52a9\u4f60\u4e00\u5c55\u6240\u9577\u7684\u8a71\n\n\u6b61\u8fce\u4f60\u52a0\u5165\u6211\u5730on9\u5927\u5bb6\u5ead\n\n- \u5287\u672c\u5275\u4f5c\u70ba\u4e3b\n- \u524d\u671f\u6e96\u5099\n- \u4e2d\u671f\u73fe\u5834\u62cd\u651d\n- \u5f8c\u671f\u64cd\u4f5c premiere, after effect, photoshop \u53ca illustrator\n- \u6709\u80fd\u529b\u5275\u9020\u7368\u7acb\u77ed\u7247\n- \u5927\u7d04\u6bcf\u67084\u689d\u7d045\u5206\u9418\u7db2\u7247\n\nBTW\u5176\u5be6\u9664\u5497\u7de8\u5c0e\u6211\u54cb\u90fd\u9700\u8981\u5e55\u524d\u5e55\u5f8c\u4eba\u624d\n\n", "employment_types": ["Full Time"], "selling_points": [], "locations": ["Tai Po Area"], "categories": ["Media & Advertising", "Editorial / Journalism"], "post_time": "2022-01-10T12:38:29Z", "salary": {"currency": null, "max": null, "min": null, "period": null, "term": null}, "salary_visible": false, "title_keywords": [], "responsibilities": [], "requirements": {"degrees": [], "majors": [], "languages": [], "language_level": [], "hard_skills": ["illustrator", "after effect", "premiere", "photoshop"], "soft_skills": [], "languages_combined": []}, "experience_required": {"duration": [], "field": []}}, {"job_id": "100003009037371", "location_code": "hk", "company": "MORE", "job_title": "Senior Marketing Executive", "description": "What are your key responsibilities?\u00a0\n\n\nConducting research to understand the market needs and targeted audience.\u00a0\nInterpreting briefs to develop and produce creative concepts through execution on assigned brands.\u00a0\nGenerating original copy,\u00a0editing content, and proofreading\u00a0a range of corporate marketing and communications materials across different platforms including social media platforms.\u00a0\nCollaborating with regional teams from concept development to delivery of final product.\u00a0\u00a0\nTranslating\u00a0contents from\u00a0English to Mandarin.\u00a0\nHandling ad-hoc tasks as and when needed.\u00a0\n\n\nWho are we looking for?\u00a0\n\n\nYou must possess a\u00a0Bachelor\u00a0degree,\u00a0i.e.\u00a0in the area of Linguistics/Languages, Mass Communications, Finance, Economy,\u00a0or equivalent.\u00a0\nMin. 3\u00a0years of experience is required.\u00a0\nKnowledge in finance and trading is a nice-to-have.\u00a0\nKnowledge in SEO, HTML, CSS, and WordPress\u00a0is a nice-to-have.\u00a0\nBe a\u00a0clear communicator and writer by translating financial terms into everyday language.\u00a0\nYou must have excellent command of written\u00a0and spoken Mandarin.\u00a0\n\nFresh graduates are welcome to apply.\n\nWe are hiring for 4 headcounts. The position level will be determined by your skills and experience.", "employment_types": ["Full Time", "Permanent"], "selling_points": ["Over 2-3 years experience in digital projects", "Assist in promotion plan development", "Great development opportunity, competitive package"], "locations": ["Kwun Tong"], "categories": ["Media & Advertising", "Strategic Planning", "Others", "Editorial / Journalism"], "post_time": "2022-01-11T02:37:41Z", "salary": {"currency": null, "max": null, "min": null, "period": null, "term": null}, "salary_visible": false, "title_keywords": ["senior marketing executive"], "responsibilities": ["seo", "ad-hoc tasks", "social media platforms", "teams", "develop", "proofreading", "contents", "editing"], "requirements": {"degrees": ["degree", "bachelor"], "majors": [], "languages": ["english", "mandarin"], "language_level": ["excellent"], "hard_skills": ["seo", "nice", "html", "wordpress", "css"], "soft_skills": ["clear", "communicator", "creative", "determined"], "languages_combined": [{"language": "english", "language_level": []}, {"language": "mandarin", "language_level": ["excellent"]}]}, "experience_required": {"duration": ["3 years"], "field": []}}, {"job_id": "100003009028534", "location_code": "hk", "company": "Art Map Limited", "job_title": "Social Media Executive/ Account Servicing Executive (Digital Marketing)", "description": "Apoidea Group is an AI-empowered Fintech company. As the founding business of Apoidea, Apoidea Media provides content marketing services to financial institutions. We own 4 media pages - Market Digest, Business Digest, Health Concept, and Beauty Digest and run other financial institution client pages. Apoidea Media has been serving a large proportion of active Equity Derivative Product Issuers in Hong Kong.\n\n\n\n\nWe are looking for a passionate Social Media Executive to manage and create content for our Business Digest and Market\u00a0Digest Instagram pages.\u00a0\n\n\n\n\nJob Description:\n\n\nManage and create content for the social media accounts (especially on Instagram), including copywriting and image creating/editing;\nClosely monitor social media channels for timely response to comments and inquiries from audiences;\nDevelop and lead all video content, including but not limited to script development, storyboarding, concept, editing, etc.\nEnsures contents are original, accurate and fact-based Editorial in driving concept development and content direction for editorial projects;\nSupport the marketing team with English/Chinese language proofreading, editing, copywriting, original content creation and content vetting, etc.\n\nRequirements:\n\nGood knowledge or experience in copywriting;\nDegree Holder in Design, Marketing, Business, E-commerce or related disciplines;\nExperience in using Photoshop, Illustrator, Powerpoint, other design softwares will be a good plus;\u00a0\n1 year of relevant experience in marketing, social media production, preferable in e-commerce industries will be a good plus while fresh graduates will also be considered;\u00a0\nFamiliar with various social media platforms (Facebook, Instagram, Youtube, and etc.);\nPassionate, responsible, and flexible to be a part of the cross-functional team;\nExcellent communication skills and strong problem-solving skills, able to work both independently and as a team;\nGood command of spoken and written Chinese and English.\u00a0", "employment_types": ["Full Time", "Permanent"], "selling_points": ["Assist Social Media platforms", "Provide daily support to the gallery operation", "At least 1 year of marketing and practical exp."], "locations": ["Not Specified"], "categories": ["Media & Advertising", "Account Servicing", "Editorial / Journalism", "Marketing / Public Relations", "Digital Marketing"], "post_time": "2022-01-10T06:34:03Z", "salary": {"currency": null, "max": null, "min": null, "period": "monthly", "term": null}, "salary_visible": false, "title_keywords": ["executive", "digital marketing", "social media executive"], "responsibilities": ["social media", "comments", "monitor", "develop", "proofreading", "contents", "editing"], "requirements": {"degrees": ["degree holder"], "majors": ["e-commerce", "design", "related disciplines", "business", "marketing"], "languages": ["english", "chinese"], "language_level": ["good command"], "hard_skills": ["plus", "design softwares", "e-commerce", "problem-solving skills", "illustrator", "powerpoint", "facebook", "photoshop"], "soft_skills": ["passionate", "communication skills", "flexible", "independently", "responsible", "problem-solving skills"], "languages_combined": [{"language": "english", "language_level": ["good command"]}, {"language": "chinese", "language_level": ["good command"]}]}, "experience_required": {"duration": ["1 year"], "field": ["social media", "e-commerce", "design", "marketing", "relevant experience", "copywriting"]}}, {"job_id": "100003009033882", "location_code": "hk", "company": "Gucci Group (Hong Kong) Limited", "job_title": "Contract Marketing and Communications Assistant (6 months)", "description": "Job Highlights\n\nDegree in Language, Linguistics or Translation\nEnsure the highest quality of work\nMinimum 5 years editorial experience\n\nJob Descriptions\n\nImplement publishing directions, goals and plans for both print and digital products\nCarry out editorial works for print and digital products\nEnsure highest quality of work and timely production of assigned titles\nCollaborate with freelancers, design, production and technical teams on publishing print and digital materials\nResponsible for market research and project related works\n\nJob requirements\n\nUniversity degree in Language, Linguistics, Translation or relevant disciplines\nMinimum 5 years editorial experiences in educational books\nExperience in digital publishing is an advantage\nGood analytical, organization and communication skills\nAbility to work under pressure\nInterested parties, please send email to\n[via APPLY NOW]\u00a0\n\n\u5b78\u6821 / \u6a5f\u69cb\u57fa\u672c\u8cc7\u6599\n\n\u62db\u8058\u5b78\u6821/\u6a5f\u69cb\u540d\u7a31 EVI Services Limited\n\u7533\u8acb\u65b9\u5f0f \u96fb\u90f5\n\u7533\u8acb\u806f\u7d61\u4eba Mr Choi\n\u96fb\u8a71\u00a035890840\n\u96fb\u90f5 APPLY NOW\n\u6a5f\u69cb\u985e\u5225 \u5176\u4ed6\n\n\nSummary\nIndustry:\nEducation / Training\nJob Category / Function:\nMedia (Editorial / Journalism)\nMedia (Translation)\nMedia (Others)\nJob Position Level:\nMiddle\nEmployment Term:\nFull Time\nMin. Edu. Level Req:\nBachelor\nMinimum QF Level attained:\n-\nTotal Working Exp:\n5\nSalary(HKD):\n-\nLocation:\nYau Tsim Mong District / Mong Kok", "employment_types": ["Full Time", "Contract"], "selling_points": ["Strong interpersonal and organization skills", "Proactive, detail minded, responsible", "High interest in retail / luxury fashion industry"], "locations": ["Quarry Bay"], "categories": ["Media & Advertising", "Editorial / Journalism", "Marketing / Public Relations", "Marketing - General / Support"], "post_time": "2022-01-10T02:02:31Z", "salary": {"currency": null, "max": null, "min": null, "period": "monthly", "term": null}, "salary_visible": false, "title_keywords": ["assistant"], "responsibilities": ["collaborate with", "teams", "quality", "design", "market research", "plans"], "requirements": {"degrees": ["university degree"], "majors": [], "languages": [], "language_level": [], "hard_skills": ["translation"], "soft_skills": ["communication skills", "work under pressure"], "languages_combined": []}, "experience_required": {"duration": ["minimum 5 years"], "field": ["digital", "editorial", "publishing"]}}, {"job_id": "100003009033971", "location_code": "hk", "company": "Babington Education Centre Limited", "job_title": "Editor", "description": "\u5d17\u4f4d\u8077\u8cac\uff1a\n\n\u8ffd\u8e64\u5404\u985e\u4fe1\u6e90\uff0c\u6316\u6398\u65b0\u805e\u7dda\u7d22\n\n\u9022\u91cd\u5927\u65b0\u805e\u4e8b\u4ef6\u7bc0\u9ede\uff0c\u80fd\u7368\u7acb\u7b56\u5283\u76f8\u95dc\u65b0\u805e\u5c08\u984c\n\n\u6839\u64da\u6e2f\u805e\u4fe1\u606f\uff0c\u7b56\u5283\u64b0\u5beb\u71b1\u9ede\u6587\u7ae0\u3001\u512a\u5316\u6a19\u984c\n\n\u6839\u64da\u6bcf\u65e5\u5167\u5bb9\u767c\u4f48\u9700\u6c42\u505a\u914d\u9069\u65b0\u805e\u5167\u5bb9\u7684\u5c01\u9762\u5716\u505a\u53ef\u8996\u5316\u5448\u73fe\n\n\u8077\u4f4d\u8981\u6c42\uff1a\n\n\u9999\u6e2f\u672c\u5730\u4e09\u5e74\u4ee5\u4e0a\u5a92\u9ad4\u884c\u696d\u4ece\u4e1a\u7d93\u9a57\u5177\u5907\u7368\u7acb\u5b8c\u6210\u6df1\u5ea6\u5831\u9053\u7684\u80fd\u529b\n\n\u71b1\u611b\u65b0\u805e\u5de5\u4f5c\uff0c\u5177\u5099\u826f\u597d\u7684\u65b0\u805e\u7d20\u990a\uff0c\u8fc5\u901f\u8ddf\u9032\u65b0\u805e\u71b1\u9ede\u4e8b\u4ef6\uff0c\u5feb\u901f\u53cd\u61c9\n\n\u5177\u512a\u79c0\u6587\u5b57\u529f\u5e95\uff0c\u6709\u767c\u73fe\u9078\u984c\u80fd\u529b\u548c\u8abf\u67e5\u7a81\u7834\u80fd\u529b\n\n\u6703\u719f\u7df4\u4f7f\u7528\u4f5c\u5716\u5de5\u5177\u3001\u4ee5\u53ca\u8996\u983b\u526a\u8f2f\u5de5\u5177\n\n\u5168\u65e5\u5236\u672c\u79d1\u4ee5\u4e0a\u5b78\u6b77\uff0c\u65b0\u805e\u3001\u793e\u79d1\u3001\u6587\u53f2\u985e\u76f8\u95dc\u5c08\u696d\n\n\u7cb5\u8a9e\u3001\u82f1\u8a9e\u3001\u666e\u901a\u8a71\u53e3\u8a9e\u6d41\u5229\n\n\u601d\u7dad\u908f\u8f2f\u7e1d\u5bc6\u3001\u5584\u65bc\u6e9d\u901a\u3001\u6027\u683c\u96a8\u548c\u3001\u80fd\u5920\u627f\u64d4\u9ad8\u5f37\u5ea6\u7684\u5de5\u4f5c\u58d3\u529b", "employment_types": ["Full Time", "Permanent"], "selling_points": [], "locations": ["Cheung Sha Wan"], "categories": ["Media & Advertising", "Editorial / Journalism", "Education", "Teacher", "Others"], "post_time": "2022-01-10T02:18:28Z", "salary": {"currency": null, "max": null, "min": null, "period": "hourly", "term": null}, "salary_visible": false, "title_keywords": ["editor"], "responsibilities": [], "requirements": {"degrees": [], "majors": [], "languages": [], "language_level": [], "hard_skills": [], "soft_skills": [], "languages_combined": []}, "experience_required": {"duration": [], "field": []}}, {"job_id": "100003009036233", "location_code": "hk", "company": "You Find Limited", "job_title": "Creative Copywriter", "description": "This position is suitable for those who have experience in social media platforms management, including FB, IG, Youtube and Linkedin. Fresh graduates who are familiar with social trends will be considered.\n\nJob Nature:\u00a0\u00a0\n\nFully responsible for social media activities (e.g. FB, IG, Youtube, Linkedin), on content development and execution, data analysis, strategy for growth etc.\nCreate core content that fit the channel nature\nHandle multiple projects simultaneously and manage various accounts/ campaigns in a timely and professional manner\nAnalyze data and insights to guide strategy and implementation of solutions\nTo manage campaigns deliverables and coordinate with the internal parties to implement digital campaigns\n\nCharacters / Qualifications:\u00a0\n\nDegree holder, 1+ years experience in social media marketing field. Candidates with more than 3 years experience will be considered for manager title.\nExperience in business/ and finance platform management will be an advantage\nDigitally savvy with strong interest in social trends\nDerive strong satisfaction in creating high engagement and viral content that fit our brands\nCheerful and creative, with marketing sense and data driven mind\nStrong communication skills and ability to influence counterparts/stakeholders at various levels\nSelf-motivated showing strong sense of ownership and able to work under pressure\n\nWe offer competitive salary and benefits package (5 days work, 14 days AL up, birthday leave, medical & dental insurance) with great opportunity for career development to the successful candidate.\n\nPlease send your detailed resume and expected salary to us by clicking \"Apply Now\" (please put position applied on subject line)", "employment_types": ["Full Time", "Permanent"], "selling_points": ["Fast growing digital marketing industry", "Good career prospect; strong team spirit", "5 days work; fun & energetic working environment"], "locations": ["Ngau Tau Kok"], "categories": ["Media & Advertising", "Editorial / Journalism", "Marketing / Public Relations", "Marketing - Marketing Communication", "Public Relations - Copy-writing"], "post_time": "2022-01-10T09:45:27Z", "salary": {"currency": null, "max": null, "min": null, "period": "monthly", "term": null}, "salary_visible": false, "title_keywords": ["creative copywriter"], "responsibilities": ["social media", "management", "data", "social media platforms", "professional manner", "implementation", "coordinate with", "data analysis", "communication", "digital campaigns", "career development", "analyze data", "multiple projects", "insurance", "internal parties", "work under pressure"], "requirements": {"degrees": ["degree holder"], "majors": ["marketing"], "languages": [], "language_level": [], "hard_skills": ["analysis"], "soft_skills": ["communication skills", "self-motivated", "cheerful", "marketing sense", "responsible", "timely", "detailed", "creative", "driven", "work under pressure"], "languages_combined": []}, "experience_required": {"duration": ["3 years", "1+ years"], "field": ["social media", "management", "finance", "business", "marketing"]}}, {"job_id": "100003009039433", "location_code": "hk", "company": "Hong Kong Science & Technology Parks Corporation", "job_title": "Senior Officer, Talent Engagement, HKSTP InnoAcademy [JDB/SOTEHKSTPI/220111]", "description": "JOB SUMMARY:\n\nBased on Orbis\u2019s development and communications objectives, the incumbent develops and implements PR projects with the aim to promote Orbis. He or she should maintain Orbis an active and quality presence in the online world.\n\nJOB RESPONSIBILITIES:\n\nDevise and administer HK website, social media sites, intranet, e-newsletter and display GIK online campaigns.\nCollaborate with internal teams to generate creative posts, landing pages and promotional emails that optimize user experience.\nMeasure campaigns performance & provide regular analytical report.\nAcquire new online insights and keep strategies upbeat.\nMaintain Orbis e-information center.\nProvide up-to-date visual stories to facilitate internal teams.\nAct as the project lead to manage the assigned Orbis campaigns and events.\nAssist Director, Communications and Communications Team to devise and execute online promotion strategies.\n\nQUALIFICATIONS & EXPERIENCE:\n\nUniversity degree majoring in media communications, digital communications, PR journalism or other related disciplines\n1-3 years of working experience in online journalism, digital creative house, PR marketing, communications highly preferred\n\n\u00a0KNOWLEDGE & SKILLS\n\nExcellent in writing skills with strong visual and aesthetic senses\nWell organized and could manage multiple priorities\nUnderstand the best practice of digital creative & marketing concepts\nKnowledge in Video maker, Photoshop, Illustrator, Animations\nKnowledge in DIY ad serving tools, google ad words and SEO/SEM\nA good team player with excellent communication and interpersonal skills\n\nAPPLICATION METHOD:\n\nIf you are interested in applying for\u00a0this position and joining the Orbis family, please\u00a0click\u00a0APPLY NOW.\n\nAll data collected will be kept confidential and used for recruitment purpose only.", "employment_types": ["Full Time"], "selling_points": [], "locations": ["Shatin Area"], "categories": ["Media & Advertising", "Editorial / Journalism", "Marketing / Public Relations", "Marketing - Marketing Communication", "Others"], "post_time": "2022-01-11T09:45:20Z", "salary": {"currency": null, "max": null, "min": null, "period": "monthly", "term": null}, "salary_visible": false, "title_keywords": ["senior officer"], "responsibilities": ["collaborate with", "social media", "online promotion", "seo", "data", "quality", "website", "teams", "user experience", "communication", "maintain", "recruitment", "animations", "sem", "visual", "report"], "requirements": {"degrees": ["university degree"], "majors": ["journalism", "related disciplines", "communications"], "languages": [], "language_level": [], "hard_skills": ["seo", "words", "illustrator", "writing skills", "sem", "photoshop"], "soft_skills": ["good team player", "creative", "interested in", "well organized", "writing skills", "communication and interpersonal skills", "active"], "languages_combined": []}, "experience_required": {"duration": ["1-3 years"], "field": ["digital", "pr", "marketing"]}}, {"job_id": "100003009035855", "location_code": "hk", "company": "Cathay Pacific Airways Ltd", "job_title": "Internal Communications and Engagement Lead", "description": "\u5de5\u4f5c\u8077\u8cac\uff1a\n\n-\u00a0 \u00a0\u64b0\u5beb\u5404\u985e\u6587\u7ae0\uff0c\u80fd\u5920\u7368\u7acb\u64b0\u5beb\u6d3b\u52d5\u65b9\u6848\u3001\u9805\u76ee\u7b56\u5283\u66f8\u7b49\uff1b\n\n-\u00a0\u50b3\u9054\u6e05\u6670\u53ca\u6e96\u78ba\u7684\u76f8\u95dc\u8cc7\u6599\u641c\u96c6\uff0c\u80fd\u5920\u7368\u7acb\u64b0\u5beb\u65b0\u805e\u7a3f\u3001\u8a55\u8ad6\u7a3f\u3001\u6703\u8b70\u8a18\u9304\u7b49\u5404\u985e\u5be6\u7528\u6587\u7a3f\uff1b\n\n-\u00a0\u00a0\u5354\u52a9\u8ddf\u9032\u4e0d\u540c\u7684\u9805\u76ee\u57f7\u884c\uff0c\u6536\u96c6\u4e26\u6574\u7406\u76f8\u95dc\u8cc7\u6599\uff1b\n\n-\u00a0\u00a0\u00a0\u914d\u5408\u4e0a\u7d1a\u5b8c\u6210\u76f8\u95dc\u9805\u76ee\u7b56\u5283\u7684\u6587\u5b57\u8868\u73fe\u5de5\u4f5c\u3002\n\n\n\n\u4efb\u8077\u8981\u6c42\uff1a\n-\u00a0 \u5c08\u4e0a\u6559\u80b2\u6216\u5177\u5099\u5b78\u58eb\u5b78\u4f4d\uff1b\n\n-\u00a0\u00a0\u8f03\u5f37\u7684\u6587\u6848\u5beb\u4f5c\u80fd\u529b\uff0c\u51fa\u8272\u7684\u6587\u5b57\u7d44\u7e54\u80fd\u529b\uff0c\u7b56\u5283\u5beb\u4f5c\u7d93\u9a57\u8c50\u5bcc\uff1b\n\n-\u00a0\u00a0\u7b56\u5283\u3001\u5ee3\u544a\u3001\u65b0\u805e\u3001\u4e2d\u6587\u3001\u5e02\u5834\u71df\u92b7\u76f8\u95dc\u5c08\u696d\u512a\u5148\u8003\u616e\uff1b\n\n-\u00a0\u00a0\u00a0\u7a4d\u6975\u4e3b\u52d5\uff0c\u8cac\u4efb\u5fc3\u5f37\uff0c\u5177\u5099\u826f\u597d\u7684\u81ea\u5b78\u80fd\u529b\u548c\u5718\u968a\u5408\u4f5c\u7cbe\u795e\u3002", "employment_types": ["Full Time", "Permanent"], "selling_points": ["8+ years\u2019 experience in a communications role", "Degree in communications / marketing", "Travel Benefits, 5-day work, Medical Benefits"], "locations": ["Lantau Island"], "categories": ["Media & Advertising", "Editorial / Journalism", "Marketing / Public Relations", "Public Relations - Event Management", "Public Relations - General / Support"], "post_time": "2022-01-10T08:33:06Z", "salary": {"currency": null, "max": null, "min": null, "period": "monthly", "term": null}, "salary_visible": false, "title_keywords": ["lead"], "responsibilities": [], "requirements": {"degrees": [], "majors": [], "languages": [], "language_level": [], "hard_skills": [], "soft_skills": [], "languages_combined": []}, "experience_required": {"duration": [], "field": []}}, {"job_id": "100003009036949", "location_code": "hk", "company": "ACT Company", "job_title": "Social Media Specialist \u793e\u4ea4\u5a92\u9ad4 x Wealth Management \u8ca1\u5bcc\u7ba1\u740615K-30K", "description": "\u5d17\u4f4d\u8077\u8cac\uff1a\n\n\u8ffd\u8e64\u5404\u985e\u4fe1\u6e90\uff0c\u6316\u6398\u65b0\u805e\u7dda\u7d22\n\u5c0d\u65b0\u805e\u7dda\u7d22\u9032\u884c\u63a1\u8a2a\u3001\u5831\u9053\u771f\u5be6\u6027\u6838\u5be6\n\u6839\u64da\u65b0\u805e\u63a1\u8a2a\u8cc7\u6599\uff0c\u5f9e\u4e0d\u540c\u89d2\u5ea6\u64b0\u5beb\u6587\u7ae0\u3001\u62cd\u651d\u8996\u983b\n\n\u4efb\u8077\u8981\u6c42\uff1a\n\n\u9999\u6e2f\u672c\u5730\u4e09\u5e74\u4ee5\u4e0a\u5a92\u9ad4\u884c\u696d\u4ece\u4e1a\u7d93\u9a57\u5177\u5907\u7368\u7acb\u5b8c\u6210\u6df1\u5ea6\u5831\u9053\u7684\u80fd\u529b\n\u71b1\u611b\u65b0\u805e\u5de5\u4f5c\uff0c\u5177\u5099\u826f\u597d\u7684\u65b0\u805e\u7d20\u990a\uff0c\u8fc5\u901f\u8ddf\u9032\u65b0\u805e\u71b1\u9ede\u4e8b\u4ef6\uff0c\u5feb\u901f\u53cd\u61c9\n\u5177\u512a\u79c0\u6587\u5b57\u529f\u5e95\uff0c\u6709\u767c\u73fe\u9078\u984c\u80fd\u529b\u548c\u8abf\u67e5\u7a81\u7834\u80fd\u529b\n\u5168\u65e5\u5236\u672c\u79d1\u4ee5\u4e0a\u5b78\u6b77\uff0c\u65b0\u805e\u3001\u793e\u79d1\u3001\u6587\u53f2\u985e\u76f8\u95dc\u5c08\u696d\n\u7cb5\u8a9e\u3001\u82f1\u8a9e\u3001\u666e\u901a\u8a71\u53e3\u8a9e\u6d41\u5229\n\u601d\u7dad\u908f\u8f2f\u7e1d\u5bc6\u3001\u5584\u65bc\u6e9d\u901a\u3001\u6027\u683c\u96a8\u548c\u3001\u6709\u5718\u968a\u610f\u8b58\uff0c\u80fd\u5920\u627f\u64d4\u9ad8\u5f37\u5ea6\u7684\u5de5\u4f5c\u58d3\u529b", "employment_types": ["Full Time", "Part Time", "Permanent", "Temporary", "Contract", "Internship", "Freelance"], "selling_points": ["\u7db2\u7d61\u71df\u92b7", "Instagram Facebook \u5c0f\u7de8", "Financial Planning"], "locations": ["Kwun Tong"], "categories": ["Media & Advertising", "Creative / Design", "Editorial / Journalism", "Marketing / Public Relations", "Marketing - Direct Marketing"], "post_time": "2022-01-11T00:56:18Z", "salary": {"currency": "HKD", "max": 29999, "min": 14000, "period": "monthly", "term": null}, "salary_visible": true, "title_keywords": ["wealth management", "social media specialist"], "responsibilities": [], "requirements": {"degrees": [], "majors": [], "languages": [], "language_level": [], "hard_skills": [], "soft_skills": [], "languages_combined": []}, "experience_required": {"duration": [], "field": []}}, {"job_id": "100003009030246", "location_code": "hk", "company": "Wondersky Online Limited", "job_title": "Beauty Editor-\u7f8e\u5bb9\u7de8\u8f2f (Full Time/Part Time)", "description": "Social Media Executive/ Account Servicing Executive (Digital Marketing)\n\u2022\u00a0\u00a0 \u00a0Social Media\n\u2022\u00a0\u00a0 \u00a0Marketing Executive\n\u2022\u00a0\u00a0 \u00a0Project Management\n\nThis candidate will have various exposure and connection to different\u00a0brands connection, especially Art & Gallery industry. The candidate will support many meaningful projects.\u00a0\n\nJob duty:\nAssist Social Media platforms, including but not limit to Facebook, Instagram content creation\u00a0n\n\u00a0Assist online video production and related online marketing campaigny\nAccount servicing - communication between clients & vendors\n\n\u00a0Generating reports on campaign effectiveness in social media sites and collect marketing intelligence\n\nProvide daily support to the gallery operation and administration works\nAsist with exhibition openings and different art events(e.g., Art fair)\nManage social media platform and event promotion\nProvide technical support and coordinate with the preparation of exhibition, e.g. artworks display, installation, storage, and dismantlement\nManage and organize the inventory\n\n\nRequirements:\nDegree holder of a recognized qualification in Journalism, Advertising, Marketing digital, Fine Art, Cultural Studies and/or a related discipline\nPassionate in marketing &/ digital,\u00a0publishing and art/cultural industry\nKnowledge of Photoshop, Adobe,\u00a0Excel, and Google documents strongly preferred\nGood at both written and spoken English and Chinese\nAbility of problem solving and multi-tasking is requested\nStrong administration ability, well-organized and able to work independently\nFamiliar with website development and maintenance as well as online platform\u00a0\u00a0\nStrong interest in Contemporary Art\nAt least 1 year of marketing and practical experience in social media platforms/ online marketing \u00a0\u00a0\u00a0\u00a0\u00a0\u00a0\u00a0\u00a0\u00a0\u00a0\u00a0\u00a0\u00a0\u00a0\u00a0\u00a0\u00a0\u00a0\u00a0\u00a0\u00a0\u00a0\u00a0\u00a0\u00a0\u00a0\u00a0\u00a0\u00a0\u00a0\u00a0\u00a0\u00a0\u00a0\u00a0\u00a0\u00a0\u00a0\u00a0\u00a0\u00a0\u00a0\u00a0\u00a0\u00a0\u00a0\u00a0\u00a0\u00a0\u00a0\u00a0\u00a0\u00a0\n\u00a0Preference will be given to a team player with passion for arts and the ability to work effectively and individually. The appointee will report to the Business Development Executive.\u00a0\nInterested parties please apply in strict confidence with complete resume,\u00a0compensation history (printed copy),\u00a0expected salary\u00a0to our email by clicking \"Apply Now\"\u00a0 or by post to Human Resources Department, Art Map Limited, Room 602, 6/F, Winfull Commercial Building, 172-176 Wing Lok Street, Sheung Wan, Hong Kong.\u00a0\nWe are an equal opportunity employer and welcome applications from all qualified candidates. Information provided will be treated in strict confidence and only be used for recruitment related purpose. Applicant who is not invited for an interview within 6 weeks may consider their application not successful. All personal data of unsuccessful applicants will be destroyed within 6 months.", "employment_types": ["Full Time"], "selling_points": [], "locations": ["Central & Western Area"], "categories": ["Media & Advertising", "Editorial / Journalism"], "post_time": "2022-01-07T07:04:26Z", "salary": {"currency": null, "max": null, "min": null, "period": "monthly", "term": null}, "salary_visible": false, "title_keywords": ["editor"], "responsibilities": ["social media", "installation", "advertising", "maintenance", "video production", "technical support", "inventory", "social media platforms", "coordinate with", "website", "communication", "project management", "digital marketing", "reports", "facebook", "report", "administration"], "requirements": {"degrees": ["degree holder"], "majors": ["journalism", "marketing", "fine art"], "languages": ["english", "chinese"], "language_level": ["good"], "hard_skills": ["excel", "maintenance", "problem solving", "project management", "adobe", "facebook", "photoshop"], "soft_skills": ["passionate", "work effectively", "work independently", "passion for", "well-organized", "communication", "project management", "multi-tasking", "problem solving", "team player"], "languages_combined": [{"language": "english", "language_level": ["good"]}, {"language": "chinese", "language_level": ["good"]}]}, "experience_required": {"duration": ["at least 1 year"], "field": ["social media", "marketing"]}}, {"job_id": "100003009036273", "location_code": "hk", "company": "Omnipres Company Limited", "job_title": "Relations Specialist", "description": "RESPONSIBILITIES:\n\nCreative advertising headlines and smart copy for efficient marketing works.\nWork with the team of creatives to come up with great creative ideas.\nUnderstand the interactive and integrated marketing mechanism, can participate in the planning stage creative thinking and copy writing.\nBe responsible for the proposal and planning of brand projects, participate in the creation of the discussion, with the implementation of the relevant documents;\nResponsible for the customer's campaign, hot topics creative discussions, and creative thinking and creative projects;\n\nREQUIREMNETS:\n\n1 to 4 years working experience in copy;\nGood understanding of ATL, digital and BTL;\nGood at all kinds of content, style of copywriting, skilled use of office software.\nActive thinking, good communication skills, enthusiasm and sense of responsibility, and team spirit;", "employment_types": ["Full Time"], "selling_points": ["Ever growing healthcare sector", "Brand new media channel", "Solid marketing and communications skills"], "locations": ["Lai Chi Kok"], "categories": ["Media & Advertising", "Editorial / Journalism", "Marketing / Public Relations", "Marketing - Marketing Communication", "Digital Marketing"], "post_time": "2022-01-10T09:53:46Z", "salary": {"currency": null, "max": null, "min": null, "period": "monthly", "term": null}, "salary_visible": false, "title_keywords": ["specialist"], "responsibilities": ["creative ideas", "advertising", "implementation", "planning"], "requirements": {"degrees": [], "majors": [], "languages": [], "language_level": [], "hard_skills": ["office software"], "soft_skills": ["communication skills", "active", "team spirit", "sense of responsibility"], "languages_combined": []}, "experience_required": {"duration": ["1 to 4 years"], "field": []}}, {"job_id": "100003009039803", "location_code": "hk", "company": "now TV", "job_title": "Finance Reporter \u2013 Features", "description": "Benefits:\n\n5 days Work + Bank Holidays\nFull Medical Coverage\nPerformance Bonus\nBirthday Leave, Wedding Leave\nTraining Subsidy\nProfessional Training + Good Career Prospect in the Growing Digital Marketing Industry\n\nResponsibilities include:\n\nCraft creative copy writing across social media platform;\nSupport creative project pitching;\nAssist online marketing execution team to plan and implement of digital marketing communication/programs to build brand awareness;\nWork with internal teams to ensure content for internal and external communication are published in the right channels;\nDevelop and edit content / copy for online customer communications;\nPerform quality control on all advertisements and content distribution; track monthly performance data.\n\nRequirements :\n\nPassionate in digital is a MUST;\nDiploma holder majoring in Journalism, Marketing, communications or PR related discipline or above;\n1 year of relevant work experience in publishing, editing or copywriting; experience in digital marketing agencies is a plus.\nExperience in creative project pitching is an advantage;\nExcellent in Chinese and English written skill;\nTo be responsible, organized, proactive and self-motivated.\nCandidates with more experience will be considered as Senior Copywriter.\n\nTo Apply:\n\nFor more information about You Find Ltd., please visit\u00a0www.youfind.hk\nWe offer attractive package to the right candidate. Interested parties please send your application by clicking \"Apply Now\".\nAll information received will be used for recruitment purpose only and will be kept in strict confidential.\n\nYouFind is an Equal Opportunity Employer and prohibits discrimination and harassment of any kind. All employment decisions at YouFind are based on business needs, job requirements and individual qualifications, without regard to race; family status; gender; disability status or any other status protected by the laws or regulations in Hong Kong.", "employment_types": ["Full Time", "Permanent"], "selling_points": ["Program production", "Property, technology and other features", "Financial news reporting"], "locations": ["Wan Chai"], "categories": ["Media & Advertising", "Editorial / Journalism", "Broadcasting - TV / Radio"], "post_time": "2022-01-11T11:28:53Z", "salary": {"currency": null, "max": null, "min": null, "period": null, "term": null}, "salary_visible": false, "title_keywords": ["reporter"], "responsibilities": [], "requirements": {"degrees": [], "majors": [], "languages": [], "language_level": [], "hard_skills": [], "soft_skills": [], "languages_combined": []}, "experience_required": {"duration": [], "field": []}}, {"job_id": "100003009036572", "location_code": "hk", "company": "HK01 Company Limited", "job_title": "\u8a18\u8005 - \u5a1b\u6a02 (\u901a\u5bb5\u66f4)", "description": "Job Description:\n\n\nAssist in handling legislative work\n\u00a0Write speeches and articles in both English and Chinese\nLiaise and work closely with different parties\nOrganize schedule arrangement\nFollow up on concerns from the business community\nSupport ad hoc duties when given\nJob Requirements:\n\u00a0 \u00a0 \u00a0 \u00a0 \u00a0\u00a0\nDegree holder in Communication, \u00a0Journalism, Translation or other\u00a0related disciplines\u00a0\nGood command of spoken and written\u00a0 English and\u00a0Chinese\nKnowledge of media relations and digital media\nSolid writing, editing and researching skills\n\u00a0Be a team player with good communication and presentation skills, and be able to work independently and flexibly;\u00a0\nAbility to work multi-task & under pressure with tight deadlines\n\nWork locations: Admiralty and Chai Wan\u00a0\n\nShortlisted applicants will be invited for an interview and a written test. Interested parties please email full CV by clicking \u201cAPPLY NOW\u201d.\u00a0 Please clearly state the Expected Salary in your resume.\nAll information provided by applicants will be handled with strictest confidence and will be solely used for the purpose of recruitment.", "employment_types": ["Full Time", "Permanent"], "selling_points": ["\u8ca0\u8cac\u672c\u5730\u53ca\u570b\u969b\u5a1b\u6a02\u65b0\u805e\u63a1\u8a2a\u5de5\u4f5c", "\u8ca0\u8cac\u5a1b\u6a02\u65b0\u805e\u8996\u983b\u88fd\u4f5c", "\u9700\u8f2a\u66f4\u7576\u503c\u53ca\u901a\u5bb5\u5de5\u4f5c"], "locations": ["Tsuen Wan Area"], "categories": ["Media & Advertising", "Others", "Editorial / Journalism", "Broadcasting - TV / Radio"], "post_time": "2022-01-10T11:07:05Z", "salary": {"currency": null, "max": null, "min": null, "period": "monthly", "term": null}, "salary_visible": false, "title_keywords": ["\u8a18\u8005"], "responsibilities": ["liaise", "schedule", "ad hoc duties"], "requirements": {"degrees": ["degree holder"], "majors": ["journalism", "related disciplines"], "languages": ["english", "chinese"], "language_level": ["good command"], "hard_skills": ["translation"], "soft_skills": ["work independently", "multi-task", "under pressure", "communication", "presentation skills", "team player"], "languages_combined": [{"language": "english", "language_level": ["good command"]}, {"language": "chinese", "language_level": ["good command"]}]}, "experience_required": {"duration": [], "field": []}}, {"job_id": "100003009040124", "location_code": "hk", "company": "Hong Kong Educational Publishing Company Ltd.", "job_title": "Mathematics Editor / Assistant Editor  (Secondary / Primary)", "description": "HKSTP InnoAcademy (innoacademy.hkstp.org) is HKSTP\u2019s initiative to nurture, inspire and engage talent for Hong Kong\u2019s innovation and technology (I&T) sector. Our vision is to develop Hong Kong into a global I&T talent hub that draws Hong Kong, Mainland and overseas I&T talent.\nWe are looking for a Senior Officer who is passionate about talent development for Hong Kong\u2019s I&T sector to join our growing and committed team. As a key member of the HKSTP InnoAcademy team, the Senior Officer will shape and contribute to the marketing of HKSTP InnoAcademy to engage our various stakeholders (talents, employers, educational institutions, industry partners, etc.), promote our programmes, and boost the talent pipeline for Hong Kong\u2019s I&T ecosystem.\nYou\u2019re a naturally creative and curious individual, always on top of the latest digital marketing and social media trends, figuring out why they work and how you can adapt the findings to your purposes. You\u2019re also an enthusiastic storyteller who is able to leverage tools and collaborate with teams and agencies to create compelling marketing assets.\nResponsibilities:\nAssist with the development and execution of digital marketing plans for HKSTP InnoAcademy\u2019s various initiatives to generate awareness and interest, and increase the number of talents and employers participating in HKSTP InnoAcademy\u2019s programmes\nWork with the InnoAcademy Team to create engaging marketing content and collateral either by yourself or via collaboration with agencies, including text, videos, infographics and posters for social media, website, emails, etc.\nManage the digital content calendar including the post frequency and content for HKSTP InnoAcademy\u2019s social media account(s)\nDevelop success stories and casebooks for HKSTP InnoAcademy\nAnalyze and report the performance of digital and content campaigns, integrate best practices, and optimize to improve the results\nSupport other marketing initiatives for these programmes and perform any other duties as assigned by supervisors\nRequirements:\nBachelor Degree in Marketing, Business, Journalism, Communications, Languages or other related disciplines\nMinimum 3 years of experience in digital marketing and content creation\nFamiliar with social media channels such as Facebook, LinkedIn and Instagram\nAble to use tools for digital marketing, such as eDM systems, website CMS, and content creation tools such as Photoshop or Canva\nExperience in digital performance analytics will be a plus\nA storyteller with high efficiency in written and spoken Chinese and English to create engaging and persuasive content\nAn effective communicator who works well with stakeholders at various levels and with strong project management skills\nStrong team player with a growth mindset, self-motivated, dynamic, independent, multi-tasking and willing to work under a fast-paced environment\nWe offer market competitive compensation, 5-day work week, and generous benefits including medical and life insurance; and voluntary contribution in addition to the legal minimum MPF.\u00a0 To apply, please send your full resume with current and expected salary to the Human Resources & Office Administration Department, Hong Kong Science and Technology Parks Corporation, 5/F, Building 5E, 5 Science Park East Avenue, Hong Kong Science Park, Hong Kong or, by email via \"Apply Now\" on or before 24 January 2022. Please quote the reference number on the email subject/envelope and the application letter.\u00a0\nPersonal data provided will be treated in strict confidence and used for recruitment purpose only. All personal data collected will be used strictly in accordance with employer\u2019s personal data policies, you can access to HKSTP\u2019s Personal Information Collection Statement at\u00a0https://www.hkstp.org/hkstp_web/en/hkstp/personal-information-collection-statement-recruitment\u00a0\nApplicants not invited for interview within four weeks after application deadline may consider their applications unsuccessful. Personal data of unsuccessful applicants will be retained for a maximum of two years.\u00a0\nwww.hkstp.org", "employment_types": ["Full Time", "Permanent"], "selling_points": [], "locations": ["Eastern Area"], "categories": ["Media & Advertising", "Editorial / Journalism", "Education", "Lecturer / Professor", "Teacher"], "post_time": "2022-01-12T01:32:24Z", "salary": {"currency": null, "max": null, "min": null, "period": "monthly", "term": null}, "salary_visible": false, "title_keywords": ["editor", "assistant editor"], "responsibilities": ["social media", "any other duties", "website", "develop", "digital marketing", "plans", "report"], "requirements": {"degrees": ["degree", "bachelor"], "majors": ["related disciplines", "journalism", "business", "marketing", "communications"], "languages": ["english", "chinese"], "language_level": [], "hard_skills": ["plus", "project management", "dynamic", "facebook", "photoshop"], "soft_skills": ["self-motivated", "persuasive", "independent", "fast-paced environment", "project management skills", "multi-tasking", "team player", "dynamic", "communicator"], "languages_combined": [{"language": "english", "language_level": []}, {"language": "chinese", "language_level": []}]}, "experience_required": {"duration": ["minimum 3 years"], "field": ["digital", "digital marketing", "content creation"]}}, {"job_id": "100003009028185", "location_code": "hk", "company": "\u5ee3\u6771\u5357\u65b9\u8ca1\u7d93\u5168\u5a92\u9ad4\u96c6\u5718\u80a1\u4efd\u6709\u9650\u516c\u53f8", "job_title": "\u8a18\u8005/reporter", "description": "Reports to:\u00a0Head of Internal Communications and Engagement\u00a0\nDepartment: People (PPL)\n\nRole Introduction\nAs an instinctive communicator, you will be responsible for creating and implementing internal communications and engagement strategies for key departments at Cathay to support their department\u2019s vision and strategic direction, with Cathay\u2019s IT and Digital department being one of your main stakeholders. You will be able to think outside the box to create campaigns and engagement initiatives that bring our brand to life and support our broader strategy and vision of the airline \u2013 with the ultimate goal of improving employee engagement. You will work closely with senior leadership to deliver important and compelling messages both within departments and for the broader Cathay community. You will also play an active role in supporting Cathay\u2019s external communications to build our digital leadership position.\u00a0\n\nKey Responsibilities\n\n\nInternal Communications\n\nDevise an internal communications and engagement strategy for key departments across Cathay, based on their unique needs and challenges, with the IT and Digital department being your main stakeholder \u00a0\nImplement, enhance and measure departmental communications and engagement strategies\nContinuously review and improve how to effectively engage, reach and target various employee groups within the department including managers and non-managers, as well as subsidiaries and those across the broader Cathay employee base\nWork with senior leaders across the business to deliver important messages and raise the profile of the leadership team\nDevelop and implement an annual content strategy for departmental communications under your remit\nWrite and edit content for online and offline channels \u2013 including day-to-day news and information both for the department and the broader Cathay employee base\nDevelop both reactive and proactive content and materials, including but not limited to newsletters, intranet updates, townhall briefings, emails, teams updates, presentations, videos, campaigns and social media\nPublish timely communications to targeted groups via internal communications platforms\nMeasure the effectiveness of internal communications messages and channels on an ongoing basis and make recommendations to review and amend as appropriate\nTranslate technical messages into easy to understand language to ensure effective communications\n\nEngagement\n\nPlan and implement departmental engagement programmes, initiatives, events and activities, including but not limited to departmental induction programmes, focus groups and recognition programmes\n\nExternal Communication\n\nPartner with the Corporate Affairs department and external industry partners (including vendors, external PR and industry bloggers) on external communications to showcase the company\u2019s IT and digital achievements and to establish Cathay\u2019s image as a digital leader; which will help us compete in the demanding talent market and be the preferred partner of leading technology companies and evolving start up ecosystem\nSupport communications needed for external events\n\nRequirements\n\nDegree in communications, marketing or related discipline\n8+ years\u2019 relevant experience in a communications role\nSolid experience in managing internal communications programmes and channels\nAbility to manage the end-to-end delivery of communications campaign independently\nExcellent interpersonal skills and good judgment; able to build rapport with people at all levels of seniority\nStrong attention to detail and an ability to manage multiple deadlines and competing demands in a fast-paced environment\nA confident and persuasive communicator who can adapt their style for different channels and audiences\u00a0\nAction-orientated and self-motivated\u00a0\nThrives in a fast-paced environment\nWorking knowledge of IT, digital technology is a plus\n\nApplication deadline: 24 January 2022\n\n\n\nPersonal & Application Information\nCathay Pacific is an Equal Opportunities Employer. Personal data provided by job applicants will be used strictly in accordance with our personal data policy and for recruitment purposes only. Candidates not notified within eight weeks may consider their application unsuccessful. All related information will be kept in our file for up to 24 months. A copy of our Personal Information Collection Statement will be provided upon request by contacting our Data Protection Officer.\n\nPlease note that with effect from 1 December 2021, all employees must be vaccinated in order to access Cathay City and all other Cathay Group Company premises in Hong Kong. Consideration will be given to those who are unable to get vaccinated for valid medical reasons.\n\n\n\n", "employment_types": ["Full Time"], "selling_points": ["\u516c\u53f8\u767c\u5c55\u6210\u9577\u5feb", "\u54e1\u5de5\u6649\u5347\u6a5f\u5236\u5b8c\u5584", "\u85aa\u916c\u798f\u5229\u5f85\u9047\u597d"], "locations": ["Aberdeen"], "categories": ["Media & Advertising", "Editorial / Journalism"], "post_time": "2022-01-07T03:07:42Z", "salary": {"currency": null, "max": null, "min": null, "period": "monthly", "term": null}, "salary_visible": false, "title_keywords": ["reporter", "\u8a18\u8005"], "responsibilities": ["make recommendations", "social media", "review", "teams", "presentations", "develop", "communication", "plan"], "requirements": {"degrees": ["degree"], "majors": ["marketing", "communications"], "languages": [], "language_level": [], "hard_skills": ["plus"], "soft_skills": ["confident", "self-motivated", "independently", "persuasive", "fast-paced environment", "interpersonal skills", "attention to detail", "communicator"], "languages_combined": []}, "experience_required": {"duration": ["8+ years"], "field": ["relevant experience"]}}, {"job_id": "100003009028791", "location_code": "hk", "company": "Aquis Search Limited", "job_title": "Chinese Editor / Writer (Native Mandarin) - International Law Firm (Up to 40K)", "description": "A leading public relations agency is seeking a Vice President to expand its businesses in Asia. With a strong client portfolio in North Asia and Greater China, the company is seeking to develop the South-east Asia market through strategic hires in Hong Kong.\n\nClient Details\n\nThis company is a renowned US-based agency with strong performances in public relations, investor relations and corporate communications. It provides a unique solution to multinational corporations (MNCs) - uplifting Asia-based companies' profiles in western markets (North America and Europe) in order to engage potential customers and investors.\n\nDescription\n\nThe VP for the Public Relations practice will be a strategic leader in the company's public relations businesses. Working with teammates across APAC (the company has presence in Mainland China, Hong Kong, Singapore, and India currently), you will deepen existing client relationships while developing new ones. The company is particularly strong in some geographical markets and industries. Hence, you can leverage on these strengths and increase penetration through cross-selling. There is also a large untapped market potential in new geographical markets and industries. The role of the VP is to identify potential growth areas and develop plans to expand the reach of the business. The VP will make use of the company's global consulting network to deliver client solutions. Gradually, the VP will also hire new staff based in Hong Kong to serve South-east Asia clients more effectively.\n\nProfile\n\nThe successful candidate should come with at least 10 years of experience in corporate communications, public relations (financial PR is preferred). Experiences working in an agency environment would make it easier for the candidate to adapt to the fast-paced and entrepreneurial environment. As a competent leader, the candidate should be able to deliver excellent products to clients, develop new businesses, manage stakeholders who are often in very senior positions in listed companies, and collaborate with teammates from across cultures and locations.\n\nStrong written and verbal communications skills in English are non-negotiable. Spoken Chinese competency is an advantage.\n\nJob Offer\n\nThis position offers an entrepreneurial candidate with an opportunity to take ownership of a business venture, while enjoying the backing of a well-established company. It also offers flexibility of remote work. Operating with established offices, staff are enabled to work in locations of their own preferences. Some travels may be required once Covid-related travel restrictions are lifted. Until then, the role is mainly based in Hong Kong.\n\nTo apply online please click the 'Apply' button below. For a confidential discussion about this role please contact Anthony Lau on +852 3412 4851.", "employment_types": ["Full Time"], "selling_points": ["Editor / Writer", "International Law Firm", "Convenient Work Location"], "locations": ["Central"], "categories": ["Media & Advertising", "Editorial / Journalism", "Professional Services", "Legal & Compliance", "Marketing / Public Relations", "Public Relations - Copy-writing"], "post_time": "2022-01-07T03:11:48Z", "salary": {"currency": null, "max": null, "min": null, "period": "monthly", "term": null}, "salary_visible": false, "title_keywords": ["editor"], "responsibilities": ["collaborate with", "consulting", "market potential", "developing", "develop", "contact", "develop plans"], "requirements": {"degrees": [], "majors": [], "languages": ["english", "chinese"], "language_level": ["advantage"], "hard_skills": ["make"], "soft_skills": ["unique", "competent"], "languages_combined": [{"language": "english", "language_level": []}, {"language": "chinese", "language_level": ["advantage"]}]}, "experience_required": {"duration": ["at least 10 years"], "field": ["pr", "public relations", "agency", "it", "financial"]}}, {"job_id": "100003009039385", "location_code": "hk", "company": "Hong Kong Science & Technology Parks Corporation", "job_title": "Senior Manager / Manager, Social Media & Content Marketing [JDB/SM_MSMCM/220111]", "description": "#\u975e\u4e00\u822c\u6253\u5de5\u65b9\u5f0f\n#\u597d\u73a9+\u6536\u5165\n\n\n\u00a0\u8aa0\u9080\u597d\u52d5\u5e74\u8f15\u4eba\u52a0\u5165\u00a0\n\n\u00a0Digital Marketing Specialist x Financial Planning 15K-30K\n\n\u73fe\u8aa0\u9080\u5f8c\u751f\u6709\u76f8\u95dc\u7d93\u9a57\u4eba\u58eb\u53c3\u8207\uff01\u597d\u73a9\u53ef\u767c\u5c55\uff01\n\n\u8b58\u5e73\u9762\u8a2d\u8a08\uff0c\u6709\u7ba1\u7406IG\u6216FB\u7d93\u9a57\u512a\u5148\n\n\u5de5\u4f5c\u7bc4\u7587\uff1a\n\n\u8ca0\u8cac Instagram Facebook\u00a0\u7db2\u7d61\u71df\u92b7\n\n\u5b9a\u671fUpdate\u53ca\u5206\u4eab\u5de5\u4f5c\u65e5\u5e38/\u7406\u8ca1\u6559\u5b78/\u8cc7\u8a0a\n\n\u984c\u6750\u4e3b\u8981\u4ee5\uff1a\u65e5\u5e38\u751f\u6d3b / \u6295\u8cc7 / \u7406\u8ca1\n\n\u4e00\u822c\u6587\u66f8\u8655\u7406\u5de5\u4f5c\n\n\u5b78\u7fd2\u7406\u8ca1\u7b56\u5283\u77e5\u8b58\uff0c\u5132\u84c4\u3001\u5f37\u7a4d\u91d1\u3001\u6295\u8cc7\u7b49\u91d1\u878d\u77e5\u8b58\n\n\u8207\u516c\u53f8\u4e0d\u540c\u5ba2\u6236\u806f\u7e6b\uff0c \u5354\u52a9\u88fd\u4f5c\u7db2\u7d61\u71df\u92b7\u76f8\u95dc\u7684\u7814\u7a76\uff0c\u63d0\u4f9b\u8ddf\u9032\u670d\u52d9\n\n\u798f\u5229\uff1a\n\n\u53e6\u4eab\u8c50\u539a\u4f63\u91d1\uff0c\u6bcf\u6708\u734e\u91d1\u53ca\u5e74\u5c3e\u82b1\u7d05\n\u5c08\u5c6c\u5168\u65b9\u4f4d\u6709\u6548\u57f9\u8a13\n\u5728\u8077\u92b7\u552e\u53ca\u7522\u54c1\u57f9\u8a13\n\u516c\u5e73\u6649\u5347\u5236\u5ea6\n\u89c0\u5858\u7532\u7d1a\u5546\u5834\u5beb\u5b57\u6a13\u5de5\u4f5c\n\u5730\u65b9\u5bec\u8eba\uff0c\u64c1\u6709\u8212\u9069\u4f11\u606f\u7a7a\u9593\n\u6642\u9593\u81ea\u4e3b\uff0c\u81ea\u6211\u5b89\u6392\u653e\u5047\u6642\u9593\uff0c\u4e0d\u8a2d\u5927\u5047\u65e5\u6578\n\u65c5\u884c\u734e\u8cde\uff0c\u5982\u9054\u6a19\u8005\u53ef\u4ee5\u4e00\u5e74\u53bb\u4e00\u6b21\u4e9e\u6d32\u8207\u6b50\u6d32\uff08\u6a5f\u7968\uff0b\u9152\u5e97)\u00a0\n\n\u8981\u6c42\uff1a\n\n\u4e2d\u5b78\u7562\u696d\u53ca\u4e94\u79d1\u5408\u683c\n\u6709\u826f\u597d\u7684\u4eba\u969b\u95dc\u4fc2\uff0c\u597d\u52d5\uff0c\u6709\u5275\u610f\n\u611b\u6e9d\u901a\uff0c\u4e3b\u52d5\uff0c\u6562\u65bc\u63a5\u53d7\u6311\u6230\n\u7d93\u9a57\u4e0d\u62d8\uff0c\u6b61\u8fce\u7562\u696d\u5927\u5b78\u751f\n\n*******\u6709\u610f\u8005\u8acb\u7acb\u523b\u9ede\u64caApply Now\u4ee5\u5b89\u6392\u9762\u8a66\u00a0**********", "employment_types": ["Full Time"], "selling_points": [], "locations": ["Shatin Area"], "categories": ["Media & Advertising", "Editorial / Journalism", "Marketing / Public Relations", "Marketing - Marketing Communication", "Digital Marketing"], "post_time": "2022-01-11T09:36:37Z", "salary": {"currency": null, "max": null, "min": null, "period": "monthly", "term": null}, "salary_visible": false, "title_keywords": ["senior manager", "manager"], "responsibilities": ["facebook", "digital marketing", "planning"], "requirements": {"degrees": [], "majors": [], "languages": [], "language_level": [], "hard_skills": ["facebook"], "soft_skills": [], "languages_combined": []}, "experience_required": {"duration": [], "field": []}}, {"job_id": "100003009029127", "location_code": "hk", "company": "Aristo Educational Press Ltd", "job_title": "Editor / Project Editor / Senior Editor (Biology)", "description": "\u5de5\u4f5c\u8077\u8cac\n\n\u8ca0\u8cac\u96dc\u8a8c\u53ca\u7db2\u7ad9(\u7f8e\u5bb9)\u4e4b\u63a1\u8a2a\u53ca\u64b0\u5beb\u6587\u7ae0\n\u7d71\u7c4c\u62cd\u651d\u5de5\u4f5c\n\u63d0\u4f9b\u5c08\u984c\u5831\u5c0e\u53ca\u8cc7\u6599\u532f\u5831\n\n\u4efb\u8077\u8981\u6c42\n\n\n\u50b3\u7406\u7cfb/ \u4e2d\u6587\u7cfb\u6216\u6709\u95dc\u5b78\u7cfb\u5927\u5b78\u5b78\u4f4d\u7a0b\u5ea6\n\u4e2d\u3001\u82f1\u6587\u826f\u597d,\u4e2d\u6587\u5beb\u4f5c\u6587\u7b46\u6d41\u66a2\n\u80fd\u5920\u5728\u58d3\u529b\u4e4b\u4e0b\u5b8c\u6210\u5de5\u4f5c\n\u80fd\u5920\u7368\u7acb\u8655\u7406\u63a1\u8a2a,\u5177\u5099\u7de8\u8f2f\u77e5\u8b58\u66f4\u4f73\n\u5de5\u4f5c\u7a4d\u6975\u4e3b\u52d5,\u5177\u8cac\u4efb\u5fc3\u3001\u5718\u968a\u5408\u4f5c\u7cbe\u795e\n\u5c0d\u5a5a\u79ae\u884c\u696d\u6709\u8208\u8da3\n\u80fd\u5373\u6642\u4e0a\u73ed\u8005\u512a\u5148\u8003\u616e\n\u4e09\u5e74\u4ee5\u4e0a\u5de5\u4f5c\u7d93\u9a57\n\u7d93\u9a57\u8f03\u6dfa\u8005\u53ef\u7533\u8acb\u7de8\u8f2f\u4e00\u8077\n\u6b61\u8fce\u61c9\u5c46\u7562\u696d\u751f\u7533\u8acb\n\n\n\u6709\u610f\u7533\u8acb\u8077\u4f4d\u8005\uff0c\u8acb\u6309\"Apply\" \u9375\n\n* \u6240\u6709\u6536\u96c6\u8cc7\u6599\u53ea\u7528\u4f5c\u62db\u8058\u7528\u9014\u3002", "employment_types": ["Full Time", "Permanent"], "selling_points": ["Production of printed and electronic publications", "5-day work week and other fringe benefits", "University degree in Biological Science"], "locations": ["Quarry Bay"], "categories": ["Media & Advertising", "Editorial / Journalism", "Education", "Teacher", "Print Media"], "post_time": "2022-01-07T04:01:31Z", "salary": {"currency": null, "max": null, "min": null, "period": "monthly", "term": null}, "salary_visible": false, "title_keywords": ["editor", "senior editor"], "responsibilities": [], "requirements": {"degrees": [], "majors": [], "languages": [], "language_level": [], "hard_skills": [], "soft_skills": [], "languages_combined": []}, "experience_required": {"duration": [], "field": []}}, {"job_id": "100003009025961", "location_code": "hk", "company": "The Executive Centre Limited", "job_title": "SEO Content Editor", "description": "Responsibilities:\n\nContribute to the development of marketing communications planning based on the group\u2019s business objectives and directions\nEstablish relationship with potential business partners, stakeholders. Manage relationship, work with a range of clients and partners in the current portfolios\nAnticipate and manage issues and create issues management strategies and tactics\nAssist and coordinate with digital marketing team in engagement strategy planning and execution to drive influence in support of the brands\nParticipate in business partners and stakeholders\u2019 engagement activities\n\nRequirements:\n\nDegree in Advertising, Marketing, E-commerce, PR, digital marketing or related discipline\nMinimum of 3+ years of relevant work experience in a capacity of client-facing exposure, preferably within the business-to-business environment. Experience in other sectors will also be considered\nExcellent communication, presentation and interpersonal skills\nStrong marketing and analytical sense\nFamiliar with the traditional and new relations building tactics\nExcellent command of copyrighting skills in Chinese and English\nA good team player and keen learner with creativity and strong sense of responsibility; being proactive, independent and organized\nHaving agency background is a definite plus\n\nBenefits:\n\nCompetitive remuneration\n5 days work\nBank holiday\nPerformance bonus\nMedical insurance and dental benefits\nLively working environment\nOn the job training", "employment_types": ["Full Time"], "selling_points": ["2-3 years of relevant work experience", "Degree in English, Journalism, Communications", "International team"], "locations": ["Southern Area"], "categories": ["Media & Advertising", "Editorial / Journalism"], "post_time": "2022-01-06T06:55:28Z", "salary": {"currency": null, "max": null, "min": null, "period": "monthly", "term": null}, "salary_visible": false, "title_keywords": ["content editor"], "responsibilities": ["management", "digital marketing", "coordinate with", "planning"], "requirements": {"degrees": ["degree"], "majors": ["marketing", "digital marketing", "e-commerce"], "languages": ["english", "chinese"], "language_level": ["excellent"], "hard_skills": ["plus", "e-commerce"], "soft_skills": ["organized", "good team player", "independent", "sense of responsibility", "keen", "communication", "interpersonal skills", "business environment", "proactive", "presentation", "client-facing"], "languages_combined": [{"language": "english", "language_level": ["excellent"]}, {"language": "chinese", "language_level": ["excellent"]}]}, "experience_required": {"duration": ["minimum of 3+ years"], "field": ["business", "client-facing"]}}, {"job_id": "100003009029689", "location_code": "hk", "company": "The Egg Company Limited", "job_title": "Junior SEO Specialist / Digital Editor / Digital Marketing Executive", "description": "Job Nature:\n\nAssist in promotion plan development to achieve business goals in marketing campaigns, e.g. acquiring new users and driving campaign participation\nResponsible for reward program/welcome gifts\nManage merchant relationship including negotiation of partnership terms, promotion offers and operation supports\nCommunicate and liaise with project stakeholders and decision-makers\nWorking with GM, BD & Sales Team to explore new business opportunities and collaboration\nWorking with team head in streamlining workflows and procedures strategically and evaluating projects in an effective and efficient manner\nCharacters / Qualifications:\n\nBachelor Degree\nOver 2-3 years experience in digital projects and social media management\nBe highly responsive and have a strong sense of digital and beauty trends\nExperience in the Beauty Industry and knowledge in Photoshop is strongly preferred\nGood communication skills, self-motivated\nAble to work independently with good execution ability\nAttention to detail, Positive, Energetic and Team-oriented\n\nWe offer competitive salary and benefits package( 5 days work, 14 days AL up, birthday leave, medical & dental insurance) with great opportunity for career development to the successful candidate.\n\nPlease send your detailed resume and expected salary to our Human Resources Department by clicking \"Apply Now\" (please put position applied on subject line).", "employment_types": ["Full Time", "Permanent"], "selling_points": ["Work with an international digital marketing team", "Work with the newest tools and tactics in digital", "Great exposure across a wide range of industries"], "locations": ["Causeway Bay"], "categories": ["Media & Advertising", "Editorial / Journalism", "Information Technology (IT)", "IT - Webmaster / SEO", "Marketing / Public Relations", "Marketing - Marketing Communication"], "post_time": "2022-01-07T07:24:19Z", "salary": {"currency": null, "max": null, "min": null, "period": "monthly", "term": null}, "salary_visible": false, "title_keywords": ["specialist", "digital marketing executive", "digital editor", "junior"], "responsibilities": ["social media", "business goals", "management", "explore new business opportunities", "procedures", "communication", "sales team", "marketing campaigns", "plan", "liaise with", "career development", "insurance"], "requirements": {"degrees": ["degree", "bachelor"], "majors": [], "languages": [], "language_level": [], "hard_skills": ["gm", "photoshop"], "soft_skills": ["efficient", "communication skills", "self-motivated", "work independently", "negotiation", "responsible", "attention to detail", "energetic", "responsive", "positive", "detailed"], "languages_combined": []}, "experience_required": {"duration": ["2-3 years"], "field": ["digital", "management", "social media", "beauty industry"]}}, {"job_id": "100003009029289", "location_code": "hk", "company": "The Warehouse Teenage Club Limited", "job_title": "Communications & Partnership Officer", "description": "KEY RESPONSIBILITIES\u00a0\n\nResponsible for providing administrative and operational support to Marketing and Communications Department\nAssist in preparing departmental powerpoint and editorial reports\nAssist in preparing all forms of press kit and marketing materials\nAssist in sample stock take, price check, sample delivery arrangement and maintain press room\u2019s cleanliness\nLiaise with both internal and external parties for event logistics details\nMaintain efficient and systematic magazine filing system\nSupport any other ad hoc assignments as required\n\nQUALIFICATIONS\u00a0\n\nBachelor degree or above in Communications, or Marketing or related disciplines\nMinimum\u00a01 year relevant experience, experience in digital and social media and fashion retail would be preferable\u00a0\nExcellent interpersonal and problem-solving skills\nSelf-motivated, energetic and organized.\u00a0 Flexible and be able to work under pressure.\nProficient PC skills in Microsoft Excel, Word, PowerPoint and Chinese Word processing\nGood command of written and spoken English and Chinese\nOccasionally work on events over weekends\nImmediate availability\u00a0is highly preferred\n\nInterested parties please send your\u00a0cover letter and full resume\u00a0(with stating your availability, latest and expected salaries)\u00a0to guccijob@ gucci.com or\u00a0by clicking the APPLY NOW button.\n\nData collected will be for recruitment purpose only.\n\n\n\n", "employment_types": ["Full Time"], "selling_points": [], "locations": ["Aberdeen"], "categories": ["Media & Advertising", "Editorial / Journalism", "Marketing / Public Relations", "Marketing - Marketing Communication", "Public Relations - General / Support"], "post_time": "2022-01-07T04:31:48Z", "salary": {"currency": null, "max": null, "min": null, "period": "monthly", "term": null}, "salary_visible": false, "title_keywords": ["officer"], "responsibilities": ["social media", "operational support", "internal and external parties", "stock take", "liaise with", "maintain", "reports", "logistics", "ad hoc assignments", "marketing materials", "work under pressure"], "requirements": {"degrees": ["degree or above", "bachelor"], "majors": ["related disciplines", "marketing", "communications"], "languages": ["english", "chinese"], "language_level": ["good command", "proficient"], "hard_skills": ["chinese word processing", "word", "powerpoint", "microsoft excel", "problem-solving skills", "pc skills"], "soft_skills": ["efficient", "organized", "self-motivated", "flexible", "responsible", "systematic", "problem-solving skills", "energetic", "interpersonal", "work under pressure"], "languages_combined": [{"language": "english", "language_level": ["good command"]}, {"language": "chinese", "language_level": ["good command", "proficient"]}]}, "experience_required": {"duration": ["minimum 1 year"], "field": ["digital", "retail", "relevant experience", "social media"]}}, {"job_id": "100003009030805", "location_code": "hk", "company": "PressLogic Limited", "job_title": "Digital Editor / Senior Editor (Health) - UrbanLife Health \u5065\u5eb7\u65b0\u614b\u5ea6", "description": "Responsibilities:\n\nAssist\u00a0in all stages of the production of mainly\u00a0kindergarten to primary courses\u00a0of English teaching and learning materials\nDevelop ideas, produce and edit mainly English learning and teaching materials that are in line with\u00a0syllabus\u00a0and educational frameworks for print and electronic materials\nManage and liaise with writers and illustrators to ensure timely production of projects\nConduct market research to monitor existing and/or initiate new projects\nPerform ad hoc duties assigned by management\u00a0\nWork from home flexibility\n\nRequirements:\n\nUniversity graduate or above (major in English, Translation, Education or related disciplines)\n2 years or above editorial working experience in educational publishing\u00a0\nGood command of Cantonese, Mandarin and English (spoken and written)\nGood computer knowledge\nGood communication and organization skills\nMeticulous to details\nImmediately available preferred\u00a0\n\nHow to apply:\n\nInterested parties please send us your CV.", "employment_types": ["Full Time", "Permanent"], "selling_points": ["\u6574\u5408\u3001\u5831\u9053\u91ab\u7642\u65b0\u805e\u3001\u5c08\u79d1\u75be\u75c5\u3001\u5065\u5eb7\u98f2\u98df\u3001\u4fdd\u5065\u7b49\u8cc7\u8a0a", "\u559c\u611b\u6587\u5b57\u5275\u4f5c\u548c\u8207\u8b80\u8005\u4ea4\u6d41", "\u6709\u8da3\uff0c\u6109\u5feb\u53ca\u6709\u6d3b\u529b\u7684\u5de5\u4f5c\u74b0\u5883"], "locations": ["Lai Chi Kok"], "categories": ["Media & Advertising", "Creative / Design", "Editorial / Journalism", "Photography / Video"], "post_time": "2022-01-07T08:21:38Z", "salary": {"currency": null, "max": null, "min": null, "period": "monthly", "term": null}, "salary_visible": false, "title_keywords": ["digital editor", "senior editor"], "responsibilities": ["ad hoc duties", "management", "ideas", "conduct market research", "monitor", "develop", "liaise with", "teaching materials"], "requirements": {"degrees": ["university graduate or above"], "majors": ["related disciplines"], "languages": ["cantonese", "english", "mandarin"], "language_level": ["good command"], "hard_skills": ["translation"], "soft_skills": ["communication", "meticulous", "organization skills"], "languages_combined": [{"language": "cantonese", "language_level": ["good command"]}, {"language": "english", "language_level": ["good command"]}, {"language": "mandarin", "language_level": ["good command"]}]}, "experience_required": {"duration": ["2 years"], "field": ["educational publishing", "editorial"]}}, {"job_id": "100003009030958", "location_code": "hk", "company": "\u5927\u7d00\u5143\u570b\u969b\u6709\u9650\u516c\u53f8", "job_title": "\u65b0\u805e\u64b0\u7a3f\u54e1 News Writers", "description": "Your New Role:\n\n\nProgram production including property, technology and other features\nFinancial news reporting / On air presentation for Now Business News Channel\nSocial media content production\nWhat makes you succeed:\u00a0\u00a0\n\n\nDegree holder in Journalism/ Finance/ Economics or related discipline\nFamiliar with and sensitive to financial news and current affairs\nProficiency in Chinese word processing is a must\nTeam player\nGood communication skills\nSelf-motivated and able to work under pressure and tight timeline\nShift duty is required\n\n\nWe offer attractive & competitive salary and benefits, an exciting work environment and excellent career development opportunities.\u00a0If you have the desire for an exciting and rewarding career, please send us your resume,\u00a0stating your present and expected salary to Human Resources Department by clicking \"Apply Now\"\u00a0\n\nFor more information on other job opportunities of PCCW, please visit our website at\u00a0http://www.pccw.com/Careers/Job+Opportunities+%26+Application/Current+Opportunities?language=en_US\nPCCW is an equal opportunity employer and welcomes applications from all qualified candidates. Information provided will be treated in strict confidence and will only be used for recruitment-related purposes. Personal data provided by job applicants will be used strictly in accordance with the employer\u2019s\u00a0privacy statement\u00a0(www.pccw.com/privacy-statement/index.page), a copy of which will be provided immediately upon request.\u00a0", "employment_types": ["Full Time"], "selling_points": [], "locations": ["Tsuen Wan Area"], "categories": ["Media & Advertising", "Editorial / Journalism"], "post_time": "2022-01-07T10:41:56Z", "salary": {"currency": null, "max": null, "min": null, "period": "monthly", "term": null}, "salary_visible": false, "title_keywords": [], "responsibilities": ["communication", "reporting", "social media content", "work under pressure"], "requirements": {"degrees": ["degree holder"], "majors": ["journalism", "finance", "economics"], "languages": ["chinese"], "language_level": ["proficiency"], "hard_skills": ["chinese word processing"], "soft_skills": ["communication skills", "self-motivated", "sensitive to", "team player", "presentation", "work under pressure"], "languages_combined": [{"language": "chinese", "language_level": ["proficiency"]}]}, "experience_required": {"duration": [], "field": []}}, {"job_id": "100003009030798", "location_code": "hk", "company": "PressLogic Limited", "job_title": "Digital Editor / Senior Editor  (Parenting & Education) - MamiDaily \u89aa\u5b50\u65e5\u5e38", "description": "\u4e3b\u8981\u8077\u8cac\n\n\u5f9e\u591a\u89d2\u5ea6\u767c\u6398\u8da3\u805e\u3001\u641c\u96c6\u8cc7\u6599\u53ca\u64b0\u5beb\u6587\u7ae0\n\u8ca0\u8cac\u672c\u5730\u53ca\u570b\u969b\u5a1b\u6a02\u65b0\u805e\u63a1\u8a2a\u5de5\u4f5c\n\u8ca0\u8cac\u5a1b\u6a02\u65b0\u805e\u8996\u983b\u88fd\u4f5c\n\n\u5165\u8077\u8981\u6c42\n\n\u6301\u5927\u5b78\u5b78\u4f4d\u6216\u4ee5\u4e0a\u5b78\u6b77\uff0c\u4e3b\u4fee\u5b78\u79d1\u4e0d\u62d8\n\u719f\u6089\u5404\u5730\u5a1b\u6a02\u8cc7\u8a0a\u6700\u65b0\u52d5\u614b\n\u64c1\u6709\u88fd\u4f5c\u53ca\u62cd\u651d\u5f71\u7247\u548c\u7d93\u71df\u793e\u4ea4\u5e73\u53f0\u7d93\u9a57\u66f4\u4f73\n\u5177\u65b0\u805e\u89f8\u89ba\u8207\u5224\u65b7\u529b\u3001\u61c9\u8b8a\u529b\u9ad8\u3001\u7a4d\u6975\u4e3b\u52d5\uff0c\u53ca\u64c5\u9577\u8207\u4eba\u6e9d\u901a\n\u5c0d\u5468\u908a\u4e8b\u7269\u6709\u597d\u5947\u5fc3\uff0c\u80fd\u5f9e\u4e0d\u540c\u6e20\u9053\u767c\u6398\u65b0\u9bae\u4e8b\u7269\n\u9700\u8f2a\u66f4\u7576\u503c\u53ca\u901a\u5bb5\u5de5\u4f5c\n\u61c9\u5fb5\u8005\u8acb\u5728\u5c65\u6b77\u8868\u4e2d\u9644\u4e0a\u76f8\u95dc\u4e4b\u500b\u4eba\u4f5c\u54c1\n\n\u8acb\u65bc\u6c42\u8077\u4fe1\u8a3b\u660e\u6b32\u61c9\u5fb5\u4e4b\u8077\u4f4d\u3002\u6211\u5011\u6703\u70ba\u5408\u9069\u7684\u4eba\u9078\u63d0\u4f9b\u512a\u539a\u7684\u85aa\u916c\u5f85\u9047\u53ca\u798f\u5229(\u5305\u62ec\u4e94\u5929\u5de5\u4f5c\u5468)\u3002\u61c9\u5fb5\u8005\u8acb\u6309\u300cApply Now\u300d\u6309\u9215\u4e26\u63d0\u4f9b\u5c65\u6b77\u3001\u73fe\u6642\u53ca\u8981\u6c42\u7684\u85aa\u916c\u5f85\u9047\u7b49\u8cc7\u6599\u4f5c\u8077\u4f4d\u7533\u8acb\u3002\n\n\u6240\u6709\u6536\u96c6\u7684\u500b\u4eba\u8cc7\u6599\u90fd\u6703\u56b4\u683c\u4fdd\u5bc6\u4e26\u53ea\u4f5c\u62db\u8058\u7528\u9014\u30023\u500b\u6708\u5167\u672a\u7372\u9762\u8a66\u901a\u77e5\u7684\u7533\u8acb\u8005\uff0c\u53ef\u8996\u5176\u7533\u8acb\u70ba\u4e0d\u6210\u529f\u8ad6\u3002\u53e6\u4e00\u65b9\u9762\uff0c\u5c65\u6b77\u4ea6\u53ef\u80fd\u6839\u64da\u516c\u53f8\u96c6\u5718\u7684\u5167\u90e8\u9700\u8981\uff0c\u9032\u884c\u5167\u90e8\u8f49\u79fb\u3002\u672a\u7372\u63a5\u7d0d\u7684\u7533\u8acb\u8cc7\u6599\u5c07\u6703\u572812\u500b\u6708\u5167\u92b7\u6bc0\u3002", "employment_types": ["Full Time", "Permanent"], "selling_points": ["\u751f\u65e5\u5047\u671f\uff06\u5165\u8077\u7d00\u5ff5\u5047\u671f", "\u6574\u5408,\u7de8\u5beb\u5831\u9053\u6709\u95dc\u89aa\u5b50,\u6559\u80b2\u7b49\u6587\u7ae0\u6216\u71b1\u9580\u65b0\u805e", "\u6709\u8da3\uff0c\u6109\u5feb\u53ca\u6709\u6d3b\u529b\u7684\u5de5\u4f5c\u74b0\u5883"], "locations": ["Lai Chi Kok"], "categories": ["Media & Advertising", "Creative / Design", "Strategic Planning", "Editorial / Journalism"], "post_time": "2022-01-07T08:21:23Z", "salary": {"currency": null, "max": null, "min": null, "period": "monthly", "term": null}, "salary_visible": false, "title_keywords": ["digital editor", "senior editor"], "responsibilities": [], "requirements": {"degrees": [], "majors": [], "languages": [], "language_level": [], "hard_skills": [], "soft_skills": [], "languages_combined": []}, "experience_required": {"duration": [], "field": []}}, {"job_id": "100003009032871", "location_code": "hk", "company": "Hong Kong Design Centre Limited", "job_title": "Project Executive", "description": "\u00a0A bachelor degree in related subject\n2 years or above experiences in educational book publishing and/or teaching would be an advantage (Candidates with Master degree but less working experience may be considered)\nProficient in MS Office applications\n\nWe offer a 5-day week and a competitive remuneration package including medical benefits and 13th month salary. Please forward your application letter and resume, with expected salary indicated, to Human Resources Department, Hong Kong Educational Publishing Company Ltd., 9/F Eastern Central Plaza, 3 Yiu Hing Road, Shau Kei Wan, Hong Kong or click \"Apply Now\" for application. (Please quote our reference: MS112JOBS.)\n\nAll information collected will be kept confidential and used for recruitment purposes only.", "employment_types": ["Full Time"], "selling_points": [], "locations": ["Kowloon Bay"], "categories": ["Media & Advertising", "Editorial / Journalism", "Marketing / Public Relations", "Marketing - General / Support", "Public Relations - Copy-writing"], "post_time": "2022-01-08T01:49:28Z", "salary": {"currency": null, "max": null, "min": null, "period": "monthly", "term": null}, "salary_visible": false, "title_keywords": ["project executive"], "responsibilities": [], "requirements": {"degrees": ["degree", "bachelor", "master degree"], "majors": [], "languages": [], "language_level": [], "hard_skills": ["ms office"], "soft_skills": [], "languages_combined": []}, "experience_required": {"duration": ["2 years"], "field": ["publishing", "teaching"]}}, {"job_id": "100003009028061", "location_code": "hk", "company": "HETERMEDIA SERVICES LIMITED", "job_title": "Content Validation Officer \u5167\u5bb9\u6838\u5be6\u4e3b\u4efb", "description": "Our team is looking for an experienced digital marketing professional, skilled at developing and managing omni-channel campaigns\u00a0from content creation, design to execution across a range of content types \u2013 web, app, social, video and more.\nYou will be working with us \u2014HKSTP\u2019s Digital & Content Marketing team\u2014in showing the world Hong Kong\u2019s innovation and technology (I&T) achievements, as well as telling the stories of Hong Kong\u2019s innovators, researchers and tech talents. These content will engage both local and international audiences through campaigns of various levels.\nThis role requires a high level of creativity, storytelling, language proficiency and project management skills. It also requires an individual who is very proud of this city and region, and demonstrates a strong desire and aptitude to amplify HKSTP\u2019s brand and stories throughout the digital space.\nIf this sounds like a role for you, read on for key responsibilities and requirements.\nResponsibilities:\nLead and formulate multiple levels of campaigns including brand, flagship events and always-on social content, by collaborating with cross functional teams, HKSTP park companies, media partners and external agencies\nDevelop and execute multi-platform digital content and media plan to engage global and local online audiences through social activation ideas and innovation stories\nWork with the Digital Experience and Data Analysis team to analyze digital and content performance,\u00a0integrate best practices and A/B testing to improve engagement and conversions\nServe as a copy editor for digital asset like\u00a0web, social\u00a0media\u00a0and eDM\nPerform any special project assignment as required\nRequirements:\nBachelor Degree in Marketing, Journalism, Communications, Languages or other related disciplines\nMinimum 8 \u2013 10 years of experience in marketing with proven track record in digital marketing and content creation\nA creative storyteller that creates engaging and persuasive content\nAn effective communicator with strong project management skills and high proficiency in written English and Chinese\nExperience in performance-driven marketing, with the ability to optimize campaigns based on analytics\nSelf-motivated, dynamic, independent, multi-tasking and willing to work under a fast-paced environment\nEager to learn and stay up-to-date with the latest digital marketing best practices\nCandidates with less experience will also be considered for lower positions.\nWe offer market competitive compensation, 5-day work week, and generous benefits including medical and life insurance; and voluntary contribution in addition to the legal minimum MPF.\u00a0 To apply, please send your full resume with current and expected salary to the Human Resources & Office Administration Department, Hong Kong Science and Technology Parks Corporation, 5/F, Building 5E, 5 Science Park East Avenue, Hong Kong Science Park, Hong Kong or, by email via \"Apply Now\"\u00a0on or before 24 January 2022. Please quote the reference number on the email subject/envelope and the application letter.\u00a0\nPersonal data provided will be treated in strict confidence and used for recruitment purpose only.\u00a0 All personal data collected will be used strictly in accordance with employer\u2019s personal data policies, you can access to HKSTP\u2019s Personal Information Collection Statement at https://www.hkstp.org/hkstp_web/en/hkstp/personal-information-collection-statement-recruitment\nApplicants not invited for interview within four weeks after application deadline may consider their applications unsuccessful.\u00a0 Personal data of unsuccessful applicants will be retained for a maximum of two years.\u00a0\nwww.hkstp.org", "employment_types": ["Full Time", "Permanent"], "selling_points": ["Proofread the content & layout of documents", "Offer shift allowance to mid & overnight shift", "Birthday leave, Paid overtime, Group Medical"], "locations": ["Sheung Wan"], "categories": ["Media & Advertising", "Production", "Editorial / Journalism", "Print Media"], "post_time": "2022-01-08T21:06:42Z", "salary": {"currency": null, "max": null, "min": null, "period": "monthly", "term": null}, "salary_visible": false, "title_keywords": ["officer"], "responsibilities": ["social media", "ideas", "edm", "teams", "develop", "data analysis", "testing", "plan"], "requirements": {"degrees": ["degree", "bachelor"], "majors": ["journalism", "related disciplines", "marketing", "communications"], "languages": ["english", "chinese"], "language_level": ["proficiency"], "hard_skills": ["project management", "dynamic"], "soft_skills": ["self-motivated", "persuasive", "independent", "fast-paced environment", "project management skills", "eager to learn", "multi-tasking", "dynamic", "communicator", "creative", "driven"], "languages_combined": [{"language": "english", "language_level": ["proficiency"]}, {"language": "chinese", "language_level": ["proficiency"]}]}, "experience_required": {"duration": ["10 years"], "field": ["marketing", "digital marketing", "content creation"]}}, {"job_id": "100003009026106", "location_code": "hk", "company": "ConnectedGroup Limited", "job_title": "Senior Content Editor, Racing", "description": "Responsibility:\n\nDevelop and execute SEO content strategies to generate growth for the business\nWork with all stakeholders to prioritise, coordinate and ensure the content creation process is aligned with the SEO best practice\nWork with copywriters to ensure our content is well SEO and bring impact to the business\nConduct keyword/topics research to spot trending topics in flexible workspace, future of work and any emerging new trends\nKeep abreast with the latest SEO and industry trends to bring fresh ideas for our content creation\nWork with the product team to implement SEO features\nOther projects with a focus on SEO\n\nRequirement:\n\n2-3 years of relevant work experience in publishing, editing or copywriting; experience in SEO content writing is a definite advantage\nExcellent verbal and written communication skills in English and Chinese is highly preferred\nData-driven mindset and ability to take action from data\nSelf-motivated, independent and a strong team player\nA degree in English, Journalism, Communications or a related discipline is preferred\nA strong eye for detail, language, and flow\nExperience in data analytics is an advantage\nCandidates with less experience will be considered as SEO Content Associate\n\nWhat can you expect from us?\n\nWe offer an attractive compensation package working in the flexible workspace industry\nHuge responsibilities from Day 1. Be the owner of your own learning curve. The possibilities are limitless and depend on you\nYou get to work in a very dynamic environment and be part of an international team", "employment_types": ["Full Time", "Permanent"], "selling_points": ["Racing domain specialist", "Stable work environment", "Attractive total package"], "locations": ["Not Specified"], "categories": ["Media & Advertising", "Others", "Editorial / Journalism", "Broadcasting - TV / Radio"], "post_time": "2022-01-06T07:20:36Z", "salary": {"currency": null, "max": null, "min": null, "period": "monthly", "term": null}, "salary_visible": false, "title_keywords": ["content editor"], "responsibilities": ["coordinate", "seo", "ideas", "develop"], "requirements": {"degrees": ["degree"], "majors": ["journalism", "communications"], "languages": ["english", "chinese"], "language_level": ["excellent"], "hard_skills": ["data analytics", "seo"], "soft_skills": ["communication skills", "self-motivated", "independent", "eye for detail", "team player", "driven"], "languages_combined": [{"language": "english", "language_level": ["excellent"]}, {"language": "chinese", "language_level": ["excellent"]}]}, "experience_required": {"duration": ["2-3 years"], "field": ["copywriting", "editing", "publishing", "content writing"]}}, {"job_id": "100003009031206", "location_code": "hk", "company": "i-CABLE Communications Limited", "job_title": "Anchor / Reporter", "description": "Key Responsibilities:\nSupport all aspects of Search Engine Optimization (SEO) campaigns from strategy development, planning, execution, optimization to analysis and reporting.\nUnderstand the key concepts of keyword research, on-site optimization and link building techniques.\nMonitor key metrics and analyze results to provide recommendations and strategies for continued campaign improvement.\nManage client campaigns to ensure deliverables and performance goals are met.\nDemonstrate passion for the search engine and online marketing space by staying abreast of industry news.\nNo programming is required in the job role.\nRequirements:\nNative Cantonese speaker with high level of English.\nUniversity degree holder.\nAny relevant experience in blogging/web development is a strong plus.\nProficiency in Microsoft Office applications, especially Excel functions such as vlookup, pivot table, etc.\nSoft Skills:\nAttentive to details and well organized.\nPatience and flexibility to handle multiple ongoing tasks.\nProblem solving skills.\nExcellent communicator.\nAbility to work with little supervision.\nCooperative team player.\nPossesses strong business ethics, is reliable and dependable.\n\nPlease send your cover letter, resume and expected salary to us.", "employment_types": ["Full Time", "Permanent"], "selling_points": [], "locations": ["Tsuen Wan Area"], "categories": ["Media & Advertising", "Production", "Editorial / Journalism", "Broadcasting - TV / Radio"], "post_time": "2022-01-07T09:03:47Z", "salary": {"currency": null, "max": null, "min": null, "period": null, "term": null}, "salary_visible": false, "title_keywords": ["reporter", "anchor"], "responsibilities": ["reporting", "seo", "analysis", "monitor", "provide recommendations", "planning"], "requirements": {"degrees": ["university degree"], "majors": [], "languages": ["cantonese", "english"], "language_level": ["native"], "hard_skills": ["excel", "web development", "plus", "microsoft office", "pivot table", "problem solving skills", "vlookup"], "soft_skills": ["attentive to details", "cooperative", "well organized", "team player", "patience", "problem solving skills", "reliable", "communicator"], "languages_combined": [{"language": "cantonese", "language_level": ["native"]}, {"language": "english", "language_level": ["native"]}]}, "experience_required": {"duration": [], "field": ["development", "relevant experience"]}}, {"job_id": "100003009025528", "location_code": "hk", "company": "Social Galaxy Limited", "job_title": "Creative Editor / Editorial Assistant \u5275\u610f\u7de8\u8f2f/\u7de8\u8f2f\u52a9\u7406\uff0814k-25k\uff09", "description": "\u8077\u8cac:\n\n\n\u8ca0\u8cac\u6574\u5408\u3001\u5831\u9053\u91ab\u7642\u65b0\u805e\u3001\u5c08\u79d1\u75be\u75c5\u3001\u5065\u5eb7\u98f2\u98df\u3001\u4fdd\u5065\u7b49\u8cc7\u8a0a\n\u8cc7\u6599\u641c\u96c6\uff0c\u806f\u7d61\u5c08\u8a2a\uff0c\u5b89\u6392\u62cd\u651d\n\u719f\u6089\u7db2\u7d61\u751f\u614b\uff0c\u88fd\u4f5c\u50b3\u95b1\u91cf\u9ad8\u7684\u5167\u5bb9\n\u7ba1\u7406FB\u3001IG\u7b49\u793e\u4ea4\u5e73\u53f0\uff0c\u8207\u4e00\u773e\u7db2\u6c11\u4e92\u52d5\n\n\u8077\u4f4d\u8981\u6c42:\n\n\u5927\u5b78\u7a0b\u5ea6\uff0c2-3\u5e74\u76f8\u95dc\u7d93\u9a57\n\u559c\u611b\u6587\u5b57\u5275\u4f5c\u548c\u8207\u8b80\u8005\u4ea4\u6d41\n\u5beb\u4f5c\u89c0\u9ede\u7cbe\u78ba\uff0c\u80fd\u5f15\u8d77\u8b80\u8005\u5171\u9cf4\n\u64c1\u6709\u6642\u4e8b\u89f8\u89d2\uff0c\u4e26\u4e14\u719f\u6089\u7db2\u8def\n\u61c2\u5f97\u4f7f\u7528Photoshop\u7b49\u8edf\u4ef6\uff0c\u5177\u5099\u57fa\u672c\u8a2d\u8a08\u6280\u5de7\n\u61c2\u5f97\u62cd\u651d\u3001\u7de8\u88fd\u548c\u526a\u63a5\u77ed\u7247\uff08\u53ef\u589e\u52a0\u53d7\u50f1\u6a5f\u6703\uff09\n\n*\u5177\u6709\u66f4\u591a\u7d93\u9a57\u7684\u6c42\u8077\u8005\u6703\u88ab\u8003\u616e\u70ba\u9ad8\u7d1a\u7de8\u8f2f\u8077\u4f4d\n\n\n\u6211\u5011\u63d0\u4f9b:\n\n5\u5929\u5de5\u4f5c\n\u5f48\u6027\u4e0a\u73ed\u6642\u9593\n\u751f\u65e5\u5047\u671f\uff06\u5165\u8077\u7d00\u5ff5\u5047\u671f\n\u91ab\u7642\u4fdd\u96aa\n\u6709\u8da3\uff0c\u6109\u5feb\u53ca\u6709\u6d3b\u529b\u7684\u5de5\u4f5c\u74b0\u5883\n\n\u61c9\u5fb5\u8005\u8acb\u9023\u540c\u8981\u6c42\u85aa\u91d1\u53ca\u6700\u65e9\u53ef\u4e0a\u4efb\u65e5\u671f\uff0c\u6309\u300cApply Now\u300d\u7533\u8acb\u53ca\u63d0\u4ea4\u3002\n\n\u66f4\u591a\u516c\u53f8\u8cc7\u8a0a\uff0c\u8acb\u53c3\u95b1\u7db2\u7ad9\u00a0http://www.presslogic.com/.\n\n\u7533\u8acb\u8005\u63d0\u4f9b\u4e4b\u8cc7\u6599\u5c07\u7d55\u5c0d\u4fdd\u5bc6\u4e26\u53ea\u4f9b\u672c\u516c\u53f8\u4f5c\u62db\u8058\u53ca\u7504\u9078\u7528\u9014\u3002", "employment_types": ["Full Time", "Part Time"], "selling_points": [], "locations": ["Kwun Tong"], "categories": ["Media & Advertising", "Creative / Design", "Editorial / Journalism", "Marketing / Public Relations", "Public Relations - Copy-writing"], "post_time": "2022-01-06T04:55:34Z", "salary": {"currency": null, "max": null, "min": null, "period": "monthly", "term": null}, "salary_visible": false, "title_keywords": ["creative editor", "assistant", "\u5275\u610f\u7de8\u8f2f"], "responsibilities": [], "requirements": {"degrees": [], "majors": [], "languages": [], "language_level": [], "hard_skills": [], "soft_skills": [], "languages_combined": []}, "experience_required": {"duration": [], "field": []}}, {"job_id": "100003009026260", "location_code": "hk", "company": "Fimmick Limited", "job_title": "Creative Copywriter (English and Chinese)", "description": "\u8077\u8cac\uff1a\n\n\u64b0\u5beb\u53ca\u7de8\u8f2f\u672c\u5730\u53ca\u6d77\u5916\u65b0\u805e\n\u7559\u610f\u6642\u4e8b\uff0c\u4e3b\u52d5\u767c\u6398\u5831\u5c0e\u984c\u6750\n\u8981\u6c42\uff1a\n\n\u5927\u5b78\u6216\u4ee5\u4e0a\u5b78\u6b77\n\u5177\u826f\u597d\u4e2d\u82f1\u6587\u95b1\u8b80\u3001\u5beb\u4f5c\u80fd\u529b\n\u80fd\u8655\u7406\u7a81\u767c\u65b0\u805e\uff0c\u4e26\u5feb\u901f\u6e96\u78ba\u5b8c\u6210\u7a3f\u4ef6\n\u7d30\u5fc3\uff0c\u80fd\u7368\u7acb\u5b8c\u6210\u5de5\u4f5c\n\u6709\u610f\u8005\u8acb\u9ede\u64ca\"Apply Now\"\uff0c\u4e26\u9644\u4e0a\u5c65\u6b77\u53ca\u8981\u6c42\u5f85\u9047\u3002\n\u7533\u8acb\u4eba\u6240\u63d0\u4f9b\u7684\u8cc7\u6599\u5c07\u4e88\u4fdd\u5bc6\u53ca\u53ea\u4f5c\u62db\u8058\u6709\u95dc\u8077\u4f4d\u7528\u9014\uff0c\u672a\u7372\u8058\u7528\u8005\u4e4b\u8cc7\u6599\u5c07\u6703\u92b7\u6bc0\u3002", "employment_types": ["Full Time", "Permanent"], "selling_points": ["Natural written English", "Write appropriate and engaging content", "Passionate and creative"], "locations": ["Kwun Tong"], "categories": ["Media & Advertising", "Editorial / Journalism", "Marketing / Public Relations", "Marketing - General / Support", "Public Relations - Copy-writing"], "post_time": "2022-01-06T07:47:26Z", "salary": {"currency": null, "max": null, "min": null, "period": "monthly", "term": null}, "salary_visible": false, "title_keywords": ["creative copywriter"], "responsibilities": [], "requirements": {"degrees": [], "majors": [], "languages": [], "language_level": [], "hard_skills": [], "soft_skills": [], "languages_combined": []}, "experience_required": {"duration": [], "field": []}}, {"job_id": "100003009031270", "location_code": "hk", "company": "\u5927\u7d00\u5143\u570b\u969b\u6709\u9650\u516c\u53f8", "job_title": "\u8a18\u8005/\u9ad8\u7d1a\u8a18\u8005 (Reporter/ Senior Reporter)", "description": "\u5de5\u4f5c\u5167\u5bb9:\n\n\u8ca0\u8cac\u6574\u5408\u3001\u7de8\u5beb\u5831\u9053\u6709\u95dc\u89aa\u5b50\uff0f\u5e7c\u5152\uff0f\u80b2\u5152\uff0f\u6559\u80b2\uff0f\u5bb6\u5ead\u8cc7\u8a0a\u7684\u6587\u7ae0\u6216\u71b1\u9580\u65b0\u805e\n\u8cc7\u6599\u641c\u96c6\uff0c\u806f\u7d61\u5c08\u8a2a\uff0c\u5b89\u6392\u62cd\u651d\n\u914d\u5408\u92b7\u552e\u90e8\u70ba\u5ba2\u6236\u9805\u76ee\u88fd\u4f5c\u53ca\u57f7\u884c\u63d0\u6848\n\u7ba1\u7406\u793e\u4ea4\u5e73\u53f0\uff0c\u8207\u4e00\u773e\u7db2\u6c11\u4e92\u52d5\n\u719f\u6089\u7db2\u7d61\u751f\u614b\uff0c\u88fd\u4f5c\u50b3\u95b1\u91cf\u9ad8\u7684\u5c08\u984c\u53ca\u77ed\u7247\n\n\u8077\u4f4d\u8981\u6c42:\n\n\u5c08\u4e0a\u7a0b\u5ea6\uff0c2\u5e74\u6216\u4ee5\u4e0a\u7de8\u63a1\u5de5\u4f5c\u7d93\u9a57\n\u559c\u611b\u6587\u5b57\u5275\u4f5c\u548c\u8207\u8b80\u8005\u4ea4\u6d41\n\u5beb\u4f5c\u89c0\u9ede\u7cbe\u78ba\uff0c\u80fd\u5f15\u8d77\u8b80\u8005\u5171\u9cf4\n\u6700\u91cd\u8981\u7684\u662f\u559c\u6b61\u5617\u65b0\uff0c\u4e26\u4e14\u719f\u6089\u7db2\u8def\n\u61c2\u5f97\u4f7f\u7528Photoshop\u7b49\u8edf\u4ef6\uff0c\u5177\u5099\u57fa\u672c\u8a2d\u8a08\u6280\u5de7\n\u61c2\u5f97\u62cd\u651d\u3001\u7de8\u88fd\u548c\u526a\u63a5\u77ed\u7247\uff08\u53ef\u589e\u52a0\u53d7\u50f1\u6a5f\u6703\uff09\n\u53cb\u5584\u3001\u5916\u5411\u3001\u614b\u5ea6\u7a4d\u6975\uff0c\u6e9d\u901a\u80fd\u529b\u597d\uff0c\u559c\u6b61\u5718\u968a\u5de5\u4f5c\n\u5177\u6709\u66f4\u591a\u7d93\u9a57\u7684\u6c42\u8077\u8005\u6703\u88ab\u8003\u616e\u70ba\u9ad8\u7d1a\u7de8\u8f2f\u8077\u4f4d\n\n\u6211\u5011\u63d0\u4f9b:\n\n5\u5929\u5de5\u4f5c\n\u5f48\u6027\u4e0a\u73ed\u6642\u9593\n\u751f\u65e5\u5047\u671f\uff06\u5165\u8077\u7d00\u5ff5\u5047\u671f\n\u91ab\u7642\u4fdd\u96aa\n\u6709\u8da3\uff0c\u6109\u5feb\u53ca\u6709\u6d3b\u529b\u7684\u5de5\u4f5c\u74b0\u5883\n\n\u61c9\u5fb5\u8005\u8acb\u9023\u540c\u8981\u6c42\u85aa\u91d1\u53ca\u6700\u65e9\u53ef\u4e0a\u4efb\u65e5\u671f\uff0c\u6309\u300cApply Now\u300d\u7533\u8acb\u53ca\u63d0\u4ea4\u3002\n\n\u66f4\u591a\u516c\u53f8\u8cc7\u8a0a\uff0c\u8acb\u53c3\u95b1\u7db2\u7ad9\u00a0http://www.presslogic.com/\n\n\u7533\u8acb\u8005\u63d0\u4f9b\u4e4b\u8cc7\u6599\u5c07\u7d55\u5c0d\u4fdd\u5bc6\u4e26\u53ea\u4f9b\u672c\u516c\u53f8\u4f5c\u62db\u8058\u53ca\u7504\u9078\u7528\u9014\u3002", "employment_types": ["Full Time"], "selling_points": [], "locations": ["Not Specified"], "categories": ["Media & Advertising", "Editorial / Journalism"], "post_time": "2022-01-07T10:35:57Z", "salary": {"currency": null, "max": null, "min": null, "period": "monthly", "term": null}, "salary_visible": false, "title_keywords": ["reporter", "\u9ad8\u7d1a\u8a18\u8005", "\u8a18\u8005"], "responsibilities": [], "requirements": {"degrees": [], "majors": [], "languages": [], "language_level": [], "hard_skills": [], "soft_skills": [], "languages_combined": []}, "experience_required": {"duration": [], "field": []}}, {"job_id": "100003009032242", "location_code": "hk", "company": "Plan International Hong Kong \u570b\u969b\u57f9\u5e7c\u6703", "job_title": "Programme Officer", "description": "The Roles:\n\nAs a member of Fashion Programme and work with the Fashion Team in executing various fashion promotional initiatives, including Fashion Asia Hong Kong\nCopywriting for programme content and contribute to the dissemination of fashion related knowledge across traditional and digital platforms\nPlan and implement PR, advertising, and social media strategy for FA to maximize exposure in the region campaigns\nDevelop and implement marketing, promotion, communication, and partnership strategies of fashion related programmes\nEffectively handle logistics, work progresses, result evaluation and reporting, make sure the process and documentations are in compliance with governance and administrative requirements\nWork closely with professional service providers and liaise with internal and external parties within and outside Hong Kong\nPerform ad hoc assignments as required\n\nRequirements:\n\n\nBachelor degree holder who is highly motivated and versatile individual\n2 years\u2019 work experience in content/journalism/PR/marketing\nPossesses excellent communication skills in written and spoken English & Chinese, comfortably works in a cultural diverse environment\nBe proactive, detailed-mined, responsive and adaptable team player with tactful interpersonal skills to deal with working partners from all levels\nIndependent, collaborative and good problem-solving abilities are essential\nStrictly adhere to project timeline and deadlines\nWilling to take up certain degree of secretarial and administrative duties\nBe proficient MS Office and Chinese Word Processing\n\nMore information about Fashion Asia:\nhttps://www.fashionasiahk.com/\n\nWork Location: Kowloon Bay / Tsuen Wan\n\nInterested parties are invited to apply by sending your resume with full details of education, work experience, current & expected salary, contact telephone number and earliest available date to the Human Resources Office, Hong Kong Design Centre, Unit 602, 6/F, Mill 5, The Mills, 45 Pak Tin Par Street, Tsuen Wan or by clicking \u201cApply Now\u201d or email to:\u00a0hr[@]hkdesigncentre.org\u00a0on or before 21 January 2022. HKDC reserves the right not to make appointment for the post(s) advertised. Only short-listed candidates will be notified. All information received will be kept in strict confidence for six months and data will only be used for recruitment purpose.", "employment_types": ["Full Time", "Permanent"], "selling_points": ["Programme Administration", "Programme Officer", "Event Coordiation"], "locations": ["Ngau Tau Kok"], "categories": ["Media & Advertising", "Editorial / Journalism", "Others", "Junior Executive", "Public / Civil", "Social Services - Community / Non-profit Organization"], "post_time": "2022-01-07T10:32:27Z", "salary": {"currency": null, "max": null, "min": null, "period": "monthly", "term": null}, "salary_visible": false, "title_keywords": ["officer"], "responsibilities": ["social media", "reporting", "advertising", "compliance", "internal and external parties", "develop", "communication", "executing", "logistics", "plan", "evaluation", "liaise with", "ad hoc assignments", "administrative duties"], "requirements": {"degrees": ["degree", "bachelor degree holder"], "majors": [], "languages": ["english", "chinese"], "language_level": ["excellent", "proficient"], "hard_skills": ["chinese word processing", "problem-solving", "make", "documentations", "ms office"], "soft_skills": ["communication skills", "independent", "adaptable", "versatile", "problem-solving", "collaborative", "communication", "diverse", "motivated", "interpersonal skills", "tactful", "team player", "proactive", "responsive", "detailed"], "languages_combined": [{"language": "english", "language_level": ["excellent"]}, {"language": "chinese", "language_level": ["excellent", "proficient"]}]}, "experience_required": {"duration": ["2 years"], "field": ["pr", "marketing"]}}, {"job_id": "100003009022924", "location_code": "hk", "company": "Hong Kong Economic Journal Company Limited", "job_title": "\u6708\u520a\u8a18\u8005", "description": "Responsibilies:\nThe individual in this role will perform following functions:\n\n\nProofread the content and layout of documents to ensure accuracy, completeness and consistency\nEnsure timely delivery of final product to customers and related working parties\nHandle e-submission to HKEx\n\n\nRequirements:\n\nCertificate of Secondary Education or above\nRelated experience is preferred, but not essential\nGood command of English, Cantonese and Mandarin\nGood computing skill in Word and PDF\nSelf-motivated and detail-minded\nOrganized, responsible and willing to learn\nAble to work under pressure and result-oriented\nWilling to work on shift (morning: 0900-1800 / mid: 1400-2300 / overnight:2100-0600), usually Mid Shift will be assigned\nShift Allowances are offered to Mid Shift and Overnight Shift\n\n\u5de5\u4f5c\u8077\u8cac\n\n\u6821\u5c0d\u6587\u4ef6\u7684\u5167\u5bb9\u548c\u7248\u9762\u8a2d\u8a08\uff0c\u4ee5\u78ba\u4fdd\u6e96\u78ba\u6027\uff0c\u5b8c\u6574\u6027\u548c\u4e00\u81f4\u6027\n\u78ba\u4fdd\u53ca\u6642\u5411\u5ba2\u6236\u548c\u76f8\u95dc\u5de5\u4f5c\u55ae\u4f4d\u4ea4\u4ed8\u5b8c\u6210\u54c1\n\u8655\u7406\u96fb\u5b50\u5448\u4ea4\u4e88\u9999\u6e2f\u4ea4\u6613\u6240\n\n\u4efb\u8077\u8981\u6c42\n\n\u4e2d\u5b78\u7562\u696d\u6216\u4ee5\u4e0a\u7a0b\u5ea6\n\u6709\u7d93\u9a57\u8005\u512a\u5148\uff0c\u4f46\u4e26\u975e\u5fc5\u8981\n\u5177\u6709\u826f\u597d\u7684\u82f1\u8a9e\uff0c\u7cb5\u8a9e\u548c\u666e\u901a\u8a71\u80fd\u529b\n\u826f\u597d\u7684\u96fb\u8166\u61c9\u7528\u80fd\u529b\uff08Word & PDF\uff09\n\u7a4d\u6975\u4e3b\u52d5\uff0c\u6ce8\u91cd\u7d30\u7bc0\n\u7d44\u7e54\u80fd\u529b\u5f37\uff0c\u8ca0\u8cac\u4efb\uff0c\u6a02\u65bc\u5b78\u7fd2\n\u91cd\u8996\u6210\u679c\uff0c\u4e26\u80fd\u5920\u5728\u58d3\u529b\u4e0b\u5de5\u4f5c\n\u9858\u610f\u8f2a\u73ed\u5de5\u4f5c\uff08\u65e9\u73ed: 0900-1800 / \u4e2d\u73ed: 1400-2300 / \u591c\u73ed: 2100-06:00\uff09\uff0c\u901a\u5e38\u6703\u5b89\u6392\u4e2d\u73ed\uff0c\u4e26\u6709\u8f2a\u73ed\u6d25\u8cbc\u767c\u653e\u4e8e\u4e2d\u73ed\uff0c\u591c\u73ed\n\nWe are a client-focused company and we strongly believe in quality service delivery. Come and join us and we offer a very competitive package and a long term career development. Please send your CV and expected salary to:\n\nHuman Resources Department\n\nHM Group\n\n9/F, Infinitus Plaza, 199 Des Voeux Road Central, Hong Kong\n\nWebsite: http://www.hetermedia.com/", "employment_types": ["Permanent"], "selling_points": [], "locations": ["Ngau Tau Kok"], "categories": ["Media & Advertising", "Editorial / Journalism", "Print Media"], "post_time": "2022-01-05T06:53:35Z", "salary": {"currency": null, "max": null, "min": null, "period": "monthly", "term": null}, "salary_visible": false, "title_keywords": [], "responsibilities": [], "requirements": {"degrees": ["certificate", "secondary education"], "majors": [], "languages": ["cantonese", "english", "mandarin"], "language_level": ["good command"], "hard_skills": ["word"], "soft_skills": ["detail-minded", "organized", "self-motivated", "responsible", "focused", "willing to learn", "result-oriented", "work under pressure"], "languages_combined": [{"language": "cantonese", "language_level": ["good command"]}, {"language": "english", "language_level": ["good command"]}, {"language": "mandarin", "language_level": ["good command"]}]}, "experience_required": {"duration": [], "field": ["related"]}}, {"job_id": "100003009028767", "location_code": "hk", "company": "Lauris Walton International Limited", "job_title": "E-Commerce Assistant \u2013 MNC", "description": "Job Description\n\nOur client is a prestigious law firm with strong presence in the field. To support the continuous expansion, they are now looking for a Chinese Editor / Writer\u00a0 to join their Marketing team based in Hong Kong.\n\nJob Responsibilities\n\nAssist partners in preparing presentations and meeting materials (English and Chinese pitch books, panel RFPs, brochures, deal sheets and lawyers biographies\nPrepare credentials information for legal directories, league tables, surveys and awards\nAssist in tasks related to client relationships (e.g. data entry, presentation preparation).\nAssist in translation for marketing initiatives\nHandle ad-hoc projects as and when required\n\nJob Requirements\n\nBachelor degree holder in business or related discipline; preferably in\u00a0marketing/ communication/ journalism/ translation\nExcellent communications and presentation\nExcellent command in both English and Chinese\nNative Mandarin\u00a0is a MUST\u00a0\nAble to work independently and a great team player\nExperience gained from\u00a0professional firm, law firm or financial institution\u00a0is highly appreciated\n\nContact Details\n\nInterested parties, please email Kelsey at\u00a0kelseyso @ aquissearch.com\u00a0for more details.\u00a0", "employment_types": ["Full Time", "Permanent"], "selling_points": [], "locations": ["Not Specified"], "categories": ["Media & Advertising", "Editorial / Journalism", "Marketing / Public Relations", "Marketing - Brand / Product Management", "E-commerce", "Marketing - Brand / Product Management"], "post_time": "2022-01-07T03:07:18Z", "salary": {"currency": null, "max": null, "min": null, "period": "monthly", "term": null}, "salary_visible": false, "title_keywords": ["assistant"], "responsibilities": ["ad-hoc projects", "presentations", "data entry"], "requirements": {"degrees": ["bachelor degree holder"], "majors": ["business"], "languages": ["english", "chinese", "mandarin"], "language_level": ["native", "excellent"], "hard_skills": ["translation"], "soft_skills": ["communication", "work independently", "team player", "presentation"], "languages_combined": [{"language": "english", "language_level": ["excellent"]}, {"language": "chinese", "language_level": ["excellent"]}, {"language": "mandarin", "language_level": ["native"]}]}, "experience_required": {"duration": [], "field": ["financial"]}}, {"job_id": "100003009018581", "location_code": "hk", "company": "QooApp Limited", "job_title": "Game Editor (English)", "description": "News Department\n\nTo be responsible for delivering of daily newscasts at video-wall set and covering live events; identifying and reflecting issues related to on-air presentation; maintaining professional\u00a0on-air presentation quality; anchoring breaking news and talk shows; participating in dubbing for acquisition programmes; researching on current news topics, gathering news, writing and translating packages\nUniversity graduate\u00a0with minimum 1 year relevant working experience in newspaper or broadcasting industry\nGood command of both spoken and written English & Chinese; fluent in Putonghua is an advantage\nGood communication skills, presentable, energetic and able to work under pressure\n\nWe offer competitive remuneration packages and advancement opportunities. Interested parties, please write with full resume to Director, Human Resources, Human Resources Department, i-CABLE Communications Limited, 4th Floor, Cable TV Tower, 9 Hoi Shing Road, Tsuen Wan, Hong Kong or fax to 2112 7841 or via Apply Now (Please quote reference number and position applied for). For other information, please visit our website http://www.i-cable.com.\n\nYour application may be forwarded to any affiliate companies and successful applicant may be seconded to work at any office as assigned. The information received will be used for consideration of employment only and all personal data supplied will be destroyed within 3 months.\n\nWe are an equal opportunity employer.", "employment_types": ["Full Time"], "selling_points": [], "locations": ["Kwun Tong"], "categories": ["Media & Advertising", "Editorial / Journalism"], "post_time": "2022-01-05T04:44:50Z", "salary": {"currency": null, "max": null, "min": null, "period": "monthly", "term": null}, "salary_visible": false, "title_keywords": ["editor"], "responsibilities": ["communication", "quality", "maintaining", "work under pressure"], "requirements": {"degrees": ["university graduate"], "majors": [], "languages": ["putonghua", "english", "chinese"], "language_level": ["advantage", "good command", "fluent"], "hard_skills": [], "soft_skills": ["communication skills", "responsible", "presentable", "energetic", "presentation", "work under pressure"], "languages_combined": [{"language": "putonghua", "language_level": ["fluent", "advantage"]}, {"language": "english", "language_level": ["good command"]}, {"language": "chinese", "language_level": ["good command"]}]}, "experience_required": {"duration": ["minimum 1 year"], "field": ["relevant working experience", "newspaper"]}}, {"job_id": "100003009031075", "location_code": "hk", "company": "Alchemist HK Limited", "job_title": "Senior Project Marketing Executive/ Communication Executive", "description": "Responsibilities:\n\n\nImplement publishing directions, plans and goals set by the management\nCarry out editorial work for printed and electronic publications\nEnsure the publications are accurate and meet market needs\nCollaborate with freelancers, design and production teams on publishing and multimedia productions\nAssist in market research and develop teacher network\n\nRequirements:\n\nUniversity degree in Biological Science, Education or relevant disciplines\nExcellent command of both English and Chinese\nGood organizational and communication skills\nStrong interest in biology and education\nExperience in digital publishing is an advantage\nCandidates with better experience and capability will be considered for senior post\n\nInterested parties please send application letter and detailed resume with public exam results and expected salary to\u00a0hr @ aristo.com.hk.\n\n(All information provided will be used for recruitment related purpose only.)\u00a0", "employment_types": ["Full Time", "Permanent"], "selling_points": ["Creative and dynamic work environment", "Good opportunity to excel", "Advertising agency experiencce is an advantage"], "locations": ["Tin Hau"], "categories": ["Media & Advertising", "Editorial / Journalism", "Marketing / Public Relations", "Marketing - Marketing Communication", "Public Relations - Copy-writing"], "post_time": "2022-01-07T08:55:09Z", "salary": {"currency": null, "max": null, "min": null, "period": "monthly", "term": null}, "salary_visible": false, "title_keywords": ["executive", "marketing executive"], "responsibilities": ["collaborate with", "management", "teams", "market research", "design", "develop", "plans"], "requirements": {"degrees": ["university degree"], "majors": ["biological science"], "languages": ["english", "chinese"], "language_level": ["excellent"], "hard_skills": [], "soft_skills": ["communication skills", "organizational"], "languages_combined": [{"language": "english", "language_level": ["excellent"]}, {"language": "chinese", "language_level": ["excellent"]}]}, "experience_required": {"duration": [], "field": ["digital", "publishing"]}}, {"job_id": "100003009027676", "location_code": "hk", "company": "Spread-it Limited", "job_title": "Copywriter (Chinese)", "description": "Job Responsibilities:\n\nParticipate in brainstorming sessions and work closely with the team to generate visual and copy ideas\nRecognise consumer needs and create innovative campaigns aligned with the overall strategy\nWrite appropriate and engaging contents, including ATL and BTL copies, video scripts and social media posts\nKeep updated with the latest developments in local social media, popular culture and hot topics\n\nRequirements:\n\nNative written English\nBachelor's degree or higher in related disciplines\nA minimum of 1 year's work experience\nPassionate and imaginative\nWork well within tight time limits\n\nBenefits:\n\nStaff Training\nFive-day work per week\nTeam Building Activities\nBirthday Leave, General Holiday and Medical Allowance\n\nWe offer attractive remuneration package, commensurate with candidates\u2019 qualification and experience. Interested parties, please send your application letter, detailed CV including date of availability and current and expected salary by clicking \"APPLY NOW\". Only short-listed candidates will be notified for an interview\n\nAll information received will be kept in STRICT CONFIDENCE and only for employment related purpose.\n\nFor more information about Fimmick, please visit our website www.fimmick.com.", "employment_types": ["Full Time"], "selling_points": ["Copywriter (Chinese)", "Preferably 1+ years experience in writing Chinese", "Fast paced, fun, and energetic startup"], "locations": ["Cheung Sha Wan"], "categories": ["Media & Advertising", "Creative / Design", "Editorial / Journalism", "Marketing / Public Relations", "Digital Marketing"], "post_time": "2022-01-06T11:02:53Z", "salary": {"currency": null, "max": null, "min": null, "period": "monthly", "term": null}, "salary_visible": false, "title_keywords": ["copywriter"], "responsibilities": ["social media", "contents", "ideas", "visual"], "requirements": {"degrees": ["degree", "bachelor"], "majors": ["related disciplines"], "languages": ["english"], "language_level": ["native"], "hard_skills": [], "soft_skills": ["passionate", "imaginative"], "languages_combined": [{"language": "english", "language_level": ["native"]}]}, "experience_required": {"duration": ["minimum of 1 year"], "field": []}}, {"job_id": "100003009024429", "location_code": "hk", "company": "Maxzer Limited", "job_title": "Social Media Editor / Creative Writer", "description": "\u4e3b\u8981\u8077\u8cac\uff1a\n\n\u63a1\u8a2a\u53ca\u64b0\u5beb/\u7de8\u8f2f\u5831\u9053\uff0c\u6e2f\u805e\u6216\u9700\u300c\u5373\u63a1\u5373\u7de8\u300d\n\u5c08\u984c\u63a1\u8a2a\uff0c\u80fd\u9032\u884c\u6df1\u5ea6\u8abf\u67e5\u8005\u66f4\u4f73\n\u4e3b\u52d5\u806f\u7d61\u3001\u767c\u6398\u53d7\u8a2a\u8005\u53ca\u7368\u7acb\u63a1\u8a2a\n\u5165\u8077\u8981\u6c42\uff1a\n\n\u5177\u76f8\u95dc\u63a1\u8a2a\u5de5\u4f5c\u7d93\u9a57\uff0c\u6e2f\u805e\u8a18\u8005\u9700\u5177\u524d\u7dda\u65b0\u805e\u63a1\u8a2a\u76f8\u95dc\u5de5\u4f5c\u7d93\u9a57\n\u6297\u58d3\u80fd\u529b\u9ad8\uff0c\u80fd\u61c9\u4ed8\u7a81\u767c\u65b0\u805e\u63a1\u8a2a\n\u4e2d\u82f1\u6587\u826f\u597d\n\u61c2\u62cd\u651d\u6280\u5de7\u66f4\u4f73\n\u9700\u5916\u52e4\u5de5\u4f5c\u53ca\u9069\u61c9\u5f48\u6027\u5de5\u4f5c\u6642\u9593\n\u6709\u610f\u8005\u8acb\u9ede\u64ca\"Apply Now\"\uff0c\u4e26\u9644\u4e0a\u5c65\u6b77\u53ca\u8981\u6c42\u5f85\u9047\u3002\n\u7533\u8acb\u4eba\u6240\u63d0\u4f9b\u7684\u8cc7\u6599\u5c07\u4e88\u4fdd\u5bc6\u53ca\u53ea\u4f5c\u62db\u8058\u6709\u95dc\u8077\u4f4d\u7528\u9014\uff0c\u672a\u7372\u8058\u7528\u8005\u4e4b\u8cc7\u6599\u5c07\u6703\u92b7\u6bc0\u3002", "employment_types": ["Full Time", "Permanent"], "selling_points": ["Create advertising campaigns and post", "Min. 1-2 yrs related experience", "5 work days, extra leave and friendly environment"], "locations": ["Kwun Tong"], "categories": ["Media & Advertising", "Creative / Design", "Editorial / Journalism"], "post_time": "2022-01-06T00:03:51Z", "salary": {"currency": null, "max": null, "min": null, "period": "monthly", "term": null}, "salary_visible": false, "title_keywords": ["social media editor", "creative"], "responsibilities": [], "requirements": {"degrees": [], "majors": [], "languages": [], "language_level": [], "hard_skills": [], "soft_skills": [], "languages_combined": []}, "experience_required": {"duration": [], "field": []}}, {"job_id": "100003009027917", "location_code": "hk", "company": "Rubison Marketing Solutions Limited", "job_title": "Digital Marketing Specialist/ Content Marketing Specialist", "description": "Responsibilities:\n\n- Assist in the organizational communications functions, including but not limited to creating and developing content and managing digital and social media channels and platforms, including but not limited to e-newsletter, website, Facebook and Instagram\n\n- Assist in developing and implementing effective communications strategies\n\n- Reach out and engage with a broad spectrum of partners ranging from NGOs, government departments, community, schools to corporates\n\n- Support the implementation and execution of partnership programme, including but not limited to logistics arrangement, administration and reporting\n\n- Perform other duties as assigned by supervisor\n\nRequirements:\n\n- Degree holder in Languages, Communications, Journalism, Marketing, Public Relations or related disciplines\n\n- 1-3 years of relevant professional experience\n\n- Proficient in MS Office; knowledge of Photoshop / Adobe Illustrator / Video editing would be an advantage\n\n- Excellent interpersonal and communication skills\n\n- Good command of both spoken and written Chinese & English\n\n- Willing to work on shift and public holidays\n\n- Working location at Aberdeen\n\n- Required to conduct the Sexual Conviction Record Check due to work nature\n\nInterested parties may apply with resume, stating source of recruitment information, expected salary (application without expected salary will not be considered) and availability to\n\nHuman Resources Department\nThe Warehouse Teenage Club Limited\n25/F Wofoo Commercial Building\n574-576 Nathan Road\nMongkok, Kowloon, Hong Kong\n\nor by clicking \"Apply Now\"\n\nOur website: www.warehouse.org.hk\n\nPersonal data collected will be kept in strict confidence and used for employment-related purpose only.", "employment_types": ["Full Time", "Permanent"], "selling_points": ["Working with a dynamic and creative team", "Projects from a versatile, reputable clients", "Good exposure and promising career path"], "locations": ["Central"], "categories": ["Media & Advertising", "Editorial / Journalism", "Marketing / Public Relations", "Public Relations - Copy-writing", "Digital Marketing"], "post_time": "2022-01-06T20:03:52Z", "salary": {"currency": null, "max": null, "min": null, "period": "monthly", "term": null}, "salary_visible": false, "title_keywords": ["digital marketing specialist", "marketing specialist"], "responsibilities": ["social media", "reporting", "perform other duties", "logistics arrangement", "implementation", "developing", "website", "facebook", "administration"], "requirements": {"degrees": ["degree holder"], "majors": ["journalism", "related disciplines", "marketing", "communications"], "languages": ["english", "chinese"], "language_level": ["good command"], "hard_skills": ["video editing", "adobe illustrator", "photoshop", "ms office"], "soft_skills": ["communication skills", "interpersonal"], "languages_combined": [{"language": "english", "language_level": ["good command"]}, {"language": "chinese", "language_level": ["good command"]}]}, "experience_required": {"duration": ["1-3 years"], "field": []}}, {"job_id": "100003009022783", "location_code": "hk", "company": "Iyuno Hong Kong Limited", "job_title": "Subtitle Editor | Translation | Media Subtitling | 1+ yr exp", "description": "PRINCIPAL ROLES AND RESPONSIBILITIES:\n\n\nOrganise and coordinate influencing events initiated by the department such as conferences, symposiums, workshops, etc.\nCoordinate the development of the Child Safeguarding portal website and be responsible for the upload of contents supplied by different content providers onto the organisation website on a timely basis.\nDevelop promotional videos, flyers, and other relevant educational materials\u2026etc. for promoting the initiatives of the department.\nAssist the supervisor to maintain a smooth operation of the department.\nAs an effective administrator to keep all information related to the works of the Department.\nPerform the project administrative work to support the implementation.\nWork with other Department for fund application, including Programme design, resource mobilisation, and grants management\nWork with other units in implementing other organisation\u2019s activities.\n\nQUALIFICATIONS:\n\n\nUniversity degree in child development, journalism, social science or related fields.\nAt least 2 years\u2019 experience in the non-profit sector or demonstrated knowledge of relevant areas\nHas a track record in event and conference management with strong administrative capacity in an organisation.\nCommitment to Plan\u2019s mission and vision and observe strictly to data privacy and child protection policies\n\nPersonal Qualities\n\nPassionate in serving society and children in adversity.\nHighly motivated to child right programmes, quick learner, able to work independently and with good team spirits\nOrganised, detailed-minded and demonstrate a can-do attitude\nSelf-initiated and responsible\nMulti-tasking, flexible, problem-solving skills and attention to details\nProficient in MS Office applications\nProficient in the application of graphic software and digital production for service promotion\nEnglish requirement \u2013 Preferable with Grade C or above in HKCEE (Syl. B) / 7 or above in IELTS", "employment_types": ["Full Time", "Permanent"], "selling_points": [], "locations": ["Kowloon Bay"], "categories": ["Media & Advertising", "Production", "Editorial / Journalism", "Professional Services", "Translation"], "post_time": "2022-01-05T06:31:53Z", "salary": {"currency": null, "max": null, "min": null, "period": "monthly", "term": null}, "salary_visible": false, "title_keywords": ["subtitle editor"], "responsibilities": ["management", "administrative work", "software", "data", "policies", "website", "implementation", "develop", "coordinate", "design", "conferences", "maintain", "plan", "contents"], "requirements": {"degrees": ["university degree"], "majors": ["journalism", "science"], "languages": ["english"], "language_level": [], "hard_skills": ["workshops", "problem-solving skills", "c", "ms office"], "soft_skills": ["passionate", "flexible", "work independently", "responsible", "can-do attitude", "timely", "quick learner", "detailed", "multi-tasking", "motivated", "organisation", "smooth", "attention to details", "problem-solving skills", "organised"], "languages_combined": [{"language": "english", "language_level": []}]}, "experience_required": {"duration": ["at least 2 years"], "field": []}}, {"job_id": "100003009031412", "location_code": "hk", "company": "i-CABLE Communications Limited", "job_title": "Senior Visual Effect Producer", "description": "\u8077\u4f4d\u8981\u6c42:\n\n\u5927\u5b78\u7a0b\u5ea6\u6216\u4ee5\u4e0a;\n\u4e2d\u3001\u82f1\u6587\u826f\u597d\uff0c\u6587\u7b46\u6d41\u66a2;\n\u5169\u5e74\u6216\u4ee5\u4e0a\u7d93\u9a57\uff0c\u5177\u8ca1\u7d93\u65b0\u805e\u63a1\u8a2a\u7d93\u9a57\u8005\u512a\u5148;\n\u559c\u6b61\u5beb\u6df1\u5ea6\u7684\u5831\u9053\u6587\u7ae0\n\u7a4d\u6975\u4e3b\u52d5\u3001\u8655\u4e8b\u7d30\u5fc3\u3001\u7368\u7acb\u8655\u4e8b\u80fd\u529b\u3001\u80fd\u5728\u58d3\u529b\u4e0b\u5de5\u4f5c\u00a0\n\n\u61c9\u5fb5\u8005\u8acb\u96fb\u90f5\u6216\u89aa\u7e55\u5c65\u6b77\u3001\u8981\u6c42\u5f85\u9047\uff0c\u5bc4\u89c0\u5858\u52f5\u696d\u885711\u865f\u806f\u50d1\u5ee3\u5834\u5730\u4e0b\uff0c\u4eba\u529b\u8cc7\u6e90\u90e8\u6536\u6216\u6309'Apply Now'\u63d0\u4ea4\u7533\u8acb\u3002\n\n\u300a\u7533\u8acb\u4eba\u6240\u63d0\u4f9b\u4e4b\u8cc7\u6599\u5c07\u4fdd\u5bc6\u53ca\u53ea\u7528\u4f5c\u62db\u8058\u7528\u9014\u300b", "employment_types": ["Full Time", "Permanent"], "selling_points": [], "locations": ["Tsuen Wan Area"], "categories": ["Design", "Graphics", "Media & Advertising", "Editorial / Journalism", "Broadcasting - TV / Radio"], "post_time": "2022-01-07T09:18:25Z", "salary": {"currency": null, "max": null, "min": null, "period": null, "term": null}, "salary_visible": false, "title_keywords": ["producer"], "responsibilities": [], "requirements": {"degrees": [], "majors": [], "languages": [], "language_level": [], "hard_skills": [], "soft_skills": [], "languages_combined": []}, "experience_required": {"duration": [], "field": []}}, {"job_id": "100003009028650", "location_code": "hk", "company": "The Hang Seng University of Hong Kong", "job_title": "Executive Assistant - Communications and Public Affairs Office", "description": "The Laboratory for AI-Powered Financial Technologies Limited (AIFT) aims to be a leading research center on the financial technologies and services.\u00a0We are seeking for PR Executive/ PR Assistant\u00a0to promote the company communication and activities.\n\nKey Accountabilities\n\nResponsible for various kinds of corporate materials and communications copy, including electronic and print communications, company publications, press release, newsletters, social networking platform, social media, promotional materials, proposal and post-event report write-up etc.\nAssist in planning and implementing of external and internal communication initiatives as well as corporate activities.\nSupport and organize events in accordance with the company\u2019s areas of focus.\nSupport the other copywriting & translation as and when required.\nHandle administrative duties for the team.\nAssist in any ad hoc projects as assigned.\nQualification / Knowledge & Experience\n\nBachelor\u2019s degree in Journalism, Communications or \u00a0Marketing related disciplines is preferred.\nMinimum 2-3 years experience in PR and Communicates.\nGood time management and meet a tight deadline.\nProactive, responsible, can-do attitude and good team player.\nComputer literacy in MS Office, PowerPoint and social networking tools.\nGood verbal and written communication skills in English and Chinese.\nAll information will be treated in strict CONFIDENTIAL and will be only used for this recruitment.", "employment_types": ["Full Time"], "selling_points": [], "locations": ["Shatin Area"], "categories": ["Media & Advertising", "Editorial / Journalism", "Marketing / Public Relations", "Marketing - Marketing Communication", "Digital Marketing"], "post_time": "2022-01-07T09:24:37Z", "salary": {"currency": null, "max": null, "min": null, "period": "monthly", "term": null}, "salary_visible": false, "title_keywords": ["executive assistant"], "responsibilities": ["social media", "management", "communication", "promotional materials", "administrative duties", "ad hoc projects", "recruitment", "report", "planning"], "requirements": {"degrees": ["degree", "bachelor"], "majors": ["journalism", "related disciplines", "marketing", "communications"], "languages": ["english", "chinese"], "language_level": ["good"], "hard_skills": ["ai", "powerpoint", "translation", "focus", "ms office"], "soft_skills": ["communication skills", "good team player", "proactive", "responsible", "can-do attitude", "communication", "computer literacy", "focus", "time management"], "languages_combined": [{"language": "english", "language_level": ["good"]}, {"language": "chinese", "language_level": ["good"]}]}, "experience_required": {"duration": ["minimum 2-3 years"], "field": ["pr"]}}, {"job_id": "100003009023485", "location_code": "hk", "company": "Ming Pao Magazines Limited", "job_title": "\u8a18\u8005 Reporter / \u7de8\u8f2f Editor - Top Gear \u6975\u901f\u8a8c", "description": "Job Responsibilities\n\nWork closely with clients, internal/external parties to collect the information; create, write up and/or translate marketing collaterals, such as press release, press materials, flyers, newsletters, brochures, video scripts etc. in sound English & Chinese\nWork independently from content research to copy development, editing and proofreading\nLiaise with internal and external parties on execution of advertising campaigns, pr activities and events\nPerform ad hoc assignments as required\n\nJob Requirements\n\nDegree holder with major in Arts/ Communications, Journalism, Marketing, PR, or related discipline\nMinimum 2 years\u2019 related working experience. Copywriting experience in advertising agency is an advantage\nProficient in English & Chinese copywriting & editing skills\nCreative, willing to learn, self-initiative & motivated, responsible, supportive and able to work under pressure, independently and over time\nGood team player with excellent interpersonal and communication skills\nCreative thinking and strong interpersonal skills\nWilling to work under tight schedules and high pressure\nFresh graduate with less experience will also be considered\nImmediate availability is preferred", "employment_types": ["Full Time", "Permanent"], "selling_points": [], "locations": ["Chai Wan"], "categories": ["Media & Advertising", "Creative / Design", "Editorial / Journalism"], "post_time": "2022-01-05T08:54:46Z", "salary": {"currency": null, "max": null, "min": null, "period": "monthly", "term": null}, "salary_visible": false, "title_keywords": ["reporter", "\u7de8\u8f2f", "editor", "\u8a18\u8005"], "responsibilities": ["external parties", "marketing collaterals", "internal and external parties", "proofreading", "ad hoc assignments", "liaise with", "editing", "advertising campaigns"], "requirements": {"degrees": ["fresh graduate", "degree holder"], "majors": ["journalism", "marketing", "communications"], "languages": ["english", "chinese"], "language_level": ["proficient"], "hard_skills": [], "soft_skills": ["communication skills", "supportive", "independently", "good team player", "responsible", "willing to learn", "motivated", "self-initiative", "interpersonal skills", "creative", "interpersonal", "work under pressure"], "languages_combined": [{"language": "english", "language_level": ["proficient"]}, {"language": "chinese", "language_level": ["proficient"]}]}, "experience_required": {"duration": ["minimum 2 years"], "field": ["related", "copywriting", "advertising agency"]}}, {"job_id": "100003009021445", "location_code": "hk", "company": "\u6a02\u601d\u6559\u80b2\u51fa\u7248\u6709\u9650\u516c\u53f8", "job_title": "Senior Editor / Editor (\u5c0f\u5b78\u4e2d\u6587\u88dc\u5145 \u9ad8\u7d1a\u7de8\u8f2f / \u7de8\u8f2f)", "description": "We are looking for a talented Content Creator and a digitally-savvy Social Media Specialist to take lead on a wide variety of projects.\u00a0\n\nROLE & RESPONSIBILITIES\n\n1. Content Marketing Specialist/ Content Creator\n\nTo provide and lead copywriting and visual direction for:\n\nPress Materials\u00a0\nBrand story and identity curation\nWork with Marcom Team to identify unique media angles for clients\u2019 projects and prepare press materials including press release, event invitation, company profile or individual biography\u00a0\nOnline and Offline Advertising\n\nCompelling headlines and body copy development\nWork with creative team to develop impactful and engaging visual materials\u00a0\nSocial media captions and visuals\u00a0\n\nBusiness\u00a0Pitch\nWork with respective teams to develop a variety of marketing concepts and generate innovative ideas for clients'\u00a0campaigns\u00a0\nResearch and brainstorm creative and exciting content ideas for new business pitches\nDevelop professional powerpoint/ keynotes presentation decks \u00a0\n2. Social Media Specialist/ Digital Marketing Specialist\n\nCreate and manage social media channels (IG, FB, LinkedIn, YouTube, WeChat, etc.) and other digital marketing activities for clients and the assigned brands\nDevelop compelling content for brands following an aligned direction\nLead social media advertising based on consumer insights, target audience and market trend, etc.\nProvide post implementation reports as needed\nJOB REQUIREMENTS:\nBachelor\u2019s degree in marketing, Journalism, Communications or equivalent discipline\n2-3 years' relevant experience in writing, publication, content editing or social media management\nExperiences in customer-facing or media copywriting and content development in both English and Traditional Chinese\nExcellent sense of storytelling; creative mind with strong copywriting skills\u00a0\nExperience in social media and digital content management\nSkill in video editing, video production and image editing will be an advantage\nSelf-motivated, creative, able to work under pressure and meet tight schedule\nApplicants with fewer experience will be considered for the executive role. Interest parties please\u00a0state your current and expected package in your application\u00a0alongside your CV and a short introduction about yourself.", "employment_types": ["Full Time", "Permanent"], "selling_points": ["\u7d93\u9a57\u4e2d\u6587\u6559\u6750\u7de8\u8f2f\u51fa\u7248, \u719f\u6089\u6d41\u7a0b\u53ca\u51fa\u7248\u5de5\u4f5c", "\u7368\u7acb\u8655\u7406\u7de8\u52d9\u53ca\u5be9\u95b1\u7a3f\u4ef6", "\u559c\u6b61\u6311\u6230\uff0c\u80fd\u627f\u53d7\u58d3\u529b, \u6df1\u539a\u6587\u5b57\u529f\u5e95"], "locations": ["Tsuen Wan Area"], "categories": ["Media & Advertising", "Editorial / Journalism", "Education", "Tutor / Instructor", "Print Media"], "post_time": "2022-01-07T19:19:13Z", "salary": {"currency": null, "max": null, "min": null, "period": "monthly", "term": null}, "salary_visible": false, "title_keywords": ["editor", "\u7de8\u8f2f", "\u9ad8\u7d1a\u7de8\u8f2f", "senior editor"], "responsibilities": ["social media", "advertising", "ideas", "consumer insights", "teams", "implementation", "develop", "digital marketing", "reports", "visual"], "requirements": {"degrees": ["degree", "bachelor"], "majors": ["journalism", "marketing", "communications"], "languages": ["english", "chinese"], "language_level": [], "hard_skills": ["video editing"], "soft_skills": ["self-motivated", "creative", "work under pressure"], "languages_combined": [{"language": "english", "language_level": []}, {"language": "chinese", "language_level": []}]}, "experience_required": {"duration": ["2-3 years"], "field": ["social media", "management", "content development", "digital content", "relevant experience", "writing", "copywriting", "editing", "media"]}}, {"job_id": "100003009025962", "location_code": "hk", "company": "Hong Kong Educational Publishing Co", "job_title": "\u7de8\u8f2f\uff0f\u52a9\u7406\u7de8\u8f2f\u3000\u2500\u2500\u3000\u4eba\u6587\u793e\u79d1 Editor / Assistant Editor", "description": "Job Description\n\nResponsible to create bold, strategic and persuasive advertising campaigns\nWork in creative team to develop ideas and design imaginative copy\nAdapt your writing style to suit various target audiences and marketing campaigns\nResponsible for creative ideas, writing and editing content\nStrong ability to liaise and communicate with creative team, account servicing team and production team\n\nThe Successful Applicant\n\nDegree holder in Communications, Journalism, Languages or related disciplines\nAt least 1-2 years of copywriting experience in advertising agency or media\nExperience in digital marketing or advertising is a plus\nExcellent command of both English and Chinese and be able to demonstrate your copywriting and proof-reading capabilities\nFully conversant with Chinese typing and reading simplified characters\nBe able to work independently & under pressure on multiple accounts with tight schedule\nFresh graduates are also welcome\n\nWhat's On Offer\n\n5-day Work\nBank Holidays and\u00a0other leave (e.g. Birthday Leave, Wedding Leave and Family leave, etc.)\nMedical Insurance\nFriendly Work Environment\n\nInterest parties please send your CV \u00a0& portfolio\u00a0with availability, current and expected salary to us.\u00a0\n**Personal data collected will be used for recruitment purpose only**", "employment_types": ["Full Time", "Permanent"], "selling_points": [], "locations": ["Eastern Area"], "categories": ["Media & Advertising", "Editorial / Journalism", "Education", "Teacher"], "post_time": "2022-01-06T06:55:46Z", "salary": {"currency": null, "max": null, "min": null, "period": "monthly", "term": null}, "salary_visible": false, "title_keywords": ["editor", "assistant editor"], "responsibilities": ["liaise", "communicate with", "creative ideas", "ideas", "advertising", "design", "develop", "digital marketing", "schedule", "marketing campaigns", "personal data", "recruitment", "editing", "insurance", "advertising campaigns"], "requirements": {"degrees": ["degree holder"], "majors": ["journalism", "related disciplines", "communications"], "languages": ["english", "chinese"], "language_level": ["excellent"], "hard_skills": ["plus", "typing"], "soft_skills": ["work independently", "persuasive", "under pressure", "responsible", "bold", "friendly", "imaginative", "creative"], "languages_combined": [{"language": "english", "language_level": ["excellent"]}, {"language": "chinese", "language_level": ["excellent"]}]}, "experience_required": {"duration": ["at least 1-2 years"], "field": ["advertising", "digital marketing", "advertising agency", "copywriting", "media"]}}, {"job_id": "100003009032589", "location_code": "hk", "company": "Hong Kong Green Building Council Limited", "job_title": "Marketing & PR Executive", "description": "This is an excellent career opportunity for young and energetic language talents!\n\nRole Description\nThe Subtitle Editor is responsible for translating and subtitling videos and related materials from English/ Korean into traditional Chinese, conducting proofreading for the translation files, and providing coaching for freelancers.\nThis role will work with a variety of different types of scripts for a range of local and international clients.\n\nCapabilities & Skills\n\nDemonstrate a proficient level of language skill in English, Cantonese, Mandarin and Korean (preferrable)\nStrong and consistent communication skills to build and nurture relationships with freelancers, rewriters, project managers and operational leadership as required to assist in meeting our delivery fulfilment deadlines\nLanguage curiosity, to take responsibility and ownership of staying up to date with culture, media and language of the target area\nAble to provide a strong delivery and operational leadership with an eye for detail. Edit text to established reading speeds, retaining the content and flavour of the source material, whilst ensuring that subtitles stay synchronised with the soundtrack and allow adequate access to picture and graphics\nRequirements\n\nDegree holder in Translation, Journalism, Language or related disciplines\nPractical work experience in media translation or proofreading is a MUST\nExcellent command of both written and oral Chinese, English and Mandarin\nStrong sense of responsibility, able to work independently under minimum supervision\nImmediate available is highly preferred\n\nApplication Interested parties please send your application with full CV including current and expected salary and availability by clicking below icon\u00a0\"Apply Now\".\n\nTest will be sent to the shortlisted candidates.\n\nAll personal information will be treated strictly confidential and solely for recruitment purpose.", "employment_types": ["Full Time", "Permanent"], "selling_points": [], "locations": ["Kowloon City Area"], "categories": ["Media & Advertising", "Editorial / Journalism", "Marketing / Public Relations", "Marketing - Marketing Communication", "Public Relations - Event Management"], "post_time": "2022-01-07T11:43:01Z", "salary": {"currency": null, "max": null, "min": null, "period": "monthly", "term": null}, "salary_visible": false, "title_keywords": ["executive"], "responsibilities": ["communication", "proofreading", "graphics"], "requirements": {"degrees": ["degree holder"], "majors": ["journalism", "related disciplines"], "languages": ["english", "chinese", "mandarin"], "language_level": ["excellent"], "hard_skills": ["translation"], "soft_skills": ["oral", "work independently", "sense of responsibility"], "languages_combined": [{"language": "english", "language_level": ["excellent"]}, {"language": "chinese", "language_level": ["excellent"]}, {"language": "mandarin", "language_level": ["excellent"]}]}, "experience_required": {"duration": [], "field": ["media"]}}, {"job_id": "100003009031751", "location_code": "hk", "company": "Investor and Financial Education Council", "job_title": "Part-time Temporary Administrator (1-Year Contract) - IFEC (Ref.:JDB/PT/TADM/IFEC/220107)", "description": "On-Air Promotion\u00a0Department\nTo be responsible for producing on-air promos; following up with non-linear editing and post production work; providing creative ideas on all promotional campaigns and projects; initiating motion graphic design for promotion video\u00a0\nProficient in After Effects, Illustrator, Final Cut Pro, Maya, 3Ds Max and Photoshop\u00a0\nUniversity graduate with minimum 2 years experience in TV or creative industry\nGood command of both spoken and written English and Chinese\nAlert to deadlines with Can-do attitude\nGood interpersonal and communication skills\n\nWe offer 5-day work week, competitive remuneration packages and advancement opportunities. Interested parties, please write with full resume to Director, Human Resources, Human Resources Department, i-CABLE Communications Limited, 4/F Cable TV Tower, 9 Hoi Shing Road Tsuen Wan, N.T. or fax to 2112 7841 or via Apply Now (Please quote reference number and position applied for). For other information, please visit our website http://www.i-cable.com.\n\nYour application may be forwarded to any affiliate companies and successful applicant may be seconded to work at any office as assigned.\u00a0 The information received will be used for consideration of employment only and all personal data supplied will be destroyed within 3 months.\n\n\nWe are an equal opportunity employer.", "employment_types": ["Contract"], "selling_points": ["Publish digital content on websites", "Conduct quality check and testing of online tools", "Provide administrative support"], "locations": ["Quarry Bay"], "categories": ["Admin & HR", "Clerical / Admin Staff", "Media & Advertising", "Editorial / Journalism", "Marketing / Public Relations", "Public Relations - General / Support"], "post_time": "2022-01-07T09:43:13Z", "salary": {"currency": null, "max": null, "min": null, "period": "hourly", "term": null}, "salary_visible": false, "title_keywords": ["administrator"], "responsibilities": ["communication", "editing", "creative ideas", "motion graphic design"], "requirements": {"degrees": ["university graduate"], "majors": [], "languages": ["english", "chinese"], "language_level": ["good command"], "hard_skills": ["final cut pro", "maya", "3ds max", "illustrator", "after effects", "photoshop"], "soft_skills": ["communication skills", "responsible", "can-do attitude", "creative", "interpersonal"], "languages_combined": [{"language": "english", "language_level": ["good command"]}, {"language": "chinese", "language_level": ["good command"]}]}, "experience_required": {"duration": ["minimum 2 years"], "field": []}}, {"job_id": "100003009025911", "location_code": "hk", "company": "Imperial Gallery Limited", "job_title": "Digital Content Specialist (Social Media)", "description": "\u5d17\u4f4d\u8077\u8cac\uff1a\n1.\u57f7\u884c\u8ca1\u7d93\u91d1\u878d\u65b0\u805e\u9078\u984c\u7b56\u5283\uff1b\n2.\u8ca0\u8cac\u71b1\u9ede\u65b0\u805e\u7684\u8ddf\u8e64\u5831\u5c0e\uff1b\n3.\u5354\u52a9\u9999\u6e2f\u7ad9\u5718\u968a\u9032\u884c\u5c08\u6848\u7b56\u5283\u57f7\u884c\u3001\u53c3\u8207\u8abf\u7814\u5831\u544a\u7b49\u3002\n\n\u4efb\u8077\u8981\u6c42\uff1a\n1.\u5168\u65e5\u5236\u672c\u79d1\u53ca\u4ee5\u4e0a\u5b78\u6b77\uff0c\u65b0\u805e\u3001\u91d1\u878d\u3001\u8ca1\u52d9\u5c08\u696d\u512a\u5148\uff1b\n2.\u53ef\u63a5\u53d7\u65b0\u805e\u5de5\u4f5c\u6642\u6548\u6027\u8981\u6c42\uff0c\u71b1\u611b\u5a92\u9ad4\u884c\u696d\uff0c\u52e4\u596e\u523b\u82e6\uff1b\n3.\u80fd\u5920\u5feb\u901f\u9032\u5165\u5de5\u4f5c\u72c0\u614b\uff0c\u670d\u5f9e\u7d44\u7e54\u5b89\u6392\uff1b\n4.\u57f7\u884c\u529b\u5f37\u3001\u64c5\u65bc\u8207\u4eba\u6e9d\u901a\u3001\u4ea4\u6d41\uff0c\u5177\u6709\u5718\u968a\u5408\u4f5c\u610f\u8b58\uff1b\n5.\u6709\u5176\u4ed6\u8ca1\u7d93\u5a92\u9ad4\u76f8\u95dc\u5be6\u7fd2/\u5de5\u4f5c\u7d93\u9a57\u6216\u76f8\u95dc\u4ee3\u8868\u4f5c\u54c1\u7684\u512a\u5148\uff1b\n6.\u82f1\u6587\u807d\u8aaa\u8b80\u5beb\u80fd\u529b\u512a\u7570\uff0c\u7cb5\u8a9e\u6d41\u5229\u3002", "employment_types": ["Full Time", "Part Time", "Permanent", "Contract", "Freelance"], "selling_points": ["Vlogger/Youtuber/KOL", "Creating fun digital contents", "New digital marketing role"], "locations": ["Tsim Sha Tsui"], "categories": ["Media & Advertising", "Editorial / Journalism", "Marketing / Public Relations", "Public Relations - Copy-writing", "Digital Marketing"], "post_time": "2022-01-06T06:45:33Z", "salary": {"currency": null, "max": null, "min": null, "period": "monthly", "term": null}, "salary_visible": false, "title_keywords": ["specialist"], "responsibilities": [], "requirements": {"degrees": [], "majors": [], "languages": [], "language_level": [], "hard_skills": [], "soft_skills": [], "languages_combined": []}, "experience_required": {"duration": [], "field": []}}, {"job_id": "100003009021472", "location_code": "hk", "company": "Pan Lloyds Publishers Limited", "job_title": "Project Manager(e-Learning)", "description": "(Ref: EA (CPAO) 2022-01-07)\n\nResponsibilities:\nassist in developing creative contents for social media, including but not limited to website, social media (Facebook, Instagram, WeChat, Weibo, etc.);\nassist in initiating marketing and PR activities to drive traffic for the online platforms;\nassist in brand building activities in the mainland China market;\nbe responsible to the content development and management of the University website for mainland China target audience;\nparticipate in University promotion and student recruitment activities in mainland China if necessary;\nprovide support in organising CPAO events / activities / exhibitions / ceremonies / conferences; and\nliaise and coordinate with internal staff and outside parties such as media reporter / advertising agency / school representatives for CPAO / advertising campaigns or school talks.\n\nApplicants should:\npossess a recognised university degree, preferably in communication, public relations, journalism, business, marketing, advertising or other related disciplines;\nhave at least 1 year of work experience in public relations, corporate communications, social media, publications relating activities, event management, marketing or brand building;\nhave experience in digital marketing and video production;\nhave good knowledge and practical experience in graphic design software;\nhave effective administrative, communication and social media skills;\npreferably have experience in website content development and management;\npreferably have brand promotion experience in mainland China;\nhave excellent command of written and spoken English and Chinese (including Mandarin); and\nbe well-organised, a good team player and able to handle multi-tasks efficiently.\n\nWorking outside normal office hours may be required.\nSalary will be commensurate with qualifications and experience.\u00a0 Applicants should send a full resume with expected salary by email via \"Apply Now\" or by post to Human Resources Office, The Hang Seng University of Hong Kong, Hang Shin Link, Siu Lek Yuen, Shatin, N.T., Hong Kong on or before 23 January 2022.\u00a0 Please indicate the post applied for and mark 'Application - Confidential' and the reference number on the cover.\u00a0 The University reserves the right not to fill the position in this exercise.\nApplicants who are not invited to an interview within three months may consider their applications unsuccessful.\u00a0 All information received will be treated in strict confidence, and the data collected will be used for recruitment purposes only.\u00a0 The Personal Information Collection Statement will be provided upon request.\nThe Hang Seng University of Hong Kong, incorporated in Hong Kong with limited liability by guarantee, is an equal opportunity employer.", "employment_types": ["Full Time", "Permanent"], "selling_points": ["manage e-project requirement, direction & schedule", "experience in editorial & familar elearning trends", "5-day work, tsuen wan, educational"], "locations": ["Tsuen Wan Area"], "categories": ["Media & Advertising", "Strategic Planning", "Editorial / Journalism", "Education", "Lecturer / Professor"], "post_time": "2022-01-07T19:19:14Z", "salary": {"currency": null, "max": null, "min": null, "period": "monthly", "term": null}, "salary_visible": false, "title_keywords": [], "responsibilities": ["liaise", "software", "data", "website", "communication", "facebook", "advertising", "video production", "developing", "conferences", "social media", "management", "provide support", "coordinate with", "digital marketing", "contents", "advertising campaigns", "graphic design", "student recruitment activities", "recruitment"], "requirements": {"degrees": ["university degree"], "majors": ["journalism", "related disciplines", "business", "marketing"], "languages": ["english", "chinese", "mandarin"], "language_level": ["excellent"], "hard_skills": ["facebook", "wechat"], "soft_skills": ["good team player", "confidence", "responsible", "multi-tasks", "communication", "well-organised", "creative"], "languages_combined": [{"language": "english", "language_level": ["excellent"]}, {"language": "chinese", "language_level": ["excellent"]}, {"language": "mandarin", "language_level": ["excellent"]}]}, "experience_required": {"duration": ["at least 1 year"], "field": ["social media", "management", "public relations", "content development", "brand", "video production", "graphic design", "marketing", "digital marketing"]}}, {"job_id": "100003009027717", "location_code": "hk", "company": "Ogilvy & Mather (Hong Kong) Private Ltd", "job_title": "Associate Social Strategist (Social Media / Digital / Fresh Graduate will be considered)", "description": "\u5165\u8077\u8981\u6c42\uff1a\u00a0\n\n\u8ca0\u8cac\u6c7d\u8eca\u53ca\u5176\u76f8\u95dc\u5167\u5bb9\u7684\u7de8\u63a1\u5de5\u4f5c\u53ca\u6df1\u5ea6\u5c08\u8a2a\n\u5fc5\u9808\u5c0d\u793e\u6587\u5a92\u9ad4\u3001\u8996\u983b\u53ca\u7db2\u7d61\u71df\u904b\u6709\u5be6\u8cea\u5de5\u4f5c\u7d93\u9a57\n\u4e2d\u3001\u82f1\u6587\u826f\u597d\uff0c\u4e2d\u6587\u5beb\u4f5c\u6587\u7b46\u6d41\u66a2\n\u7a4d\u6975\u4e3b\u52d5\uff0c\u5177\u8cac\u4efb\u5fc3\u53ca\u5718\u968a\u5408\u4f5c\u7cbe\u795e\n\n\u672c\u516c\u53f8\u63d0\u4f9b\u5b8c\u5584\u798f\u5229\u5236\u5ea6\uff0c\u6709\u610f\u7533\u8acb\u4e0a\u8ff0\u8077\u4f4d\u8005\uff0c\u8acb\u89aa\u7e55\u5c65\u6b77\u3001\u8981\u6c42\u5f85\u9047\u53ca\u806f\u7d61\u96fb\u8a71\u5bc4\u67f4\u7063\u5609\u696d\u885718\u865f\u660e\u5831\u5de5\u696d\u4e2d\u5fc3A\u5ea715\u6a13\u4eba\u529b\u8cc7\u6e90\u90e8\u6536\u6216\u6309\u00a0Apply Now\u00a0\u9375\u7533\u8acb\u3002\n\n\n\u7533\u8acb\u4eba\u6240\u63d0\u4f9b\u7684\u8cc7\u6599, \u53ea\u7528\u4f5c\u62db\u8058\u6709\u95dc\u7528\u9014", "employment_types": ["Full Time", "Permanent"], "selling_points": ["Intern experience in an advertising agency", "Online research and social media monitoring", "Campaign execution in content, community mgmt"], "locations": ["Quarry Bay"], "categories": ["Media & Advertising", "Editorial / Journalism", "Marketing / Public Relations", "Marketing - Brand / Product Management", "Digital Marketing"], "post_time": "2022-01-06T11:25:34Z", "salary": {"currency": null, "max": null, "min": null, "period": "monthly", "term": null}, "salary_visible": false, "title_keywords": ["associate"], "responsibilities": [], "requirements": {"degrees": [], "majors": [], "languages": [], "language_level": [], "hard_skills": [], "soft_skills": [], "languages_combined": []}, "experience_required": {"duration": [], "field": []}}, {"job_id": "100003009026556", "location_code": "hk", "company": "Next81 Limited", "job_title": "Copywriter", "description": "\u8077\u8cac\uff1a\n\n\u00a0\u00a0\u00a0\u00a0\u00a0\u00a0\u00a0 \u8ca0\u8cac\u65b0\u805e\u8cc7\u8a0a\u985e\u96fb\u8996\u7bc0\u76ee\u4e4b\u7de8\u6392\u3001\u88fd\u4f5c\u53ca\u64ad\u51fa\n\u00a0\u00a0\u00a0\u00a0\u00a0\u00a0\u00a0 \u4e3b\u5c0e\u7bc0\u76ee\u5275\u610f\u3001\u9078\u984c\u8ddf\u9032\uff0c\u7b56\u5283\u5927\u578b\u65b0\u805e\u76f4\u64ad\n\u00a0\u00a0\u00a0\u00a0\u00a0\u00a0\u00a0 \u8ca0\u8cac\u6709\u95dc\u7bc0\u76ee\u4e8b\u52d9\u7684\u8de8\u90e8\u9580\u6e9d\u901a\u4ee5\u53ca\u5c0d\u5916\u806f\u7d61\n\u00a0\u00a0\u00a0\u00a0\u00a0\u00a0\u00a0 \u53c3\u8207\u516c\u53f8\u65b0\u5a92\u9ad4\u5e73\u53f0\u7684\u5167\u5bb9\u5275\u4f5c\u4e26\u63d0\u4f9b\u65b0\u7406\u5ff5\n\n\u00a0\u5165\u8077\u8981\u6c42\uff1a\n\n\u00a0\u00a0\u00a0\u00a0\u00a0\u00a0\u00a0 \u5927\u5b78\u672c\u79d1\u6216\u4ee5\u4e0a\u5b78\u6b77\uff0c\u8ca1\u7d93\u3001\u65b0\u805e\u7b49\u76f8\u95dc\u5c08\u696d\u512a\u5148\n\u00a0\u00a0\u00a0\u00a0\u00a0\u00a0\u00a0 \u5177\u50995\u5e74\u6216\u4ee5\u4e0a\u8ca1\u7d93\u3001\u65b0\u805e\u7de8\u8f2f\u6216\u63a1\u8a2a\u7d93\u9a57\uff0c\u6709\u96fb\u8996\u7bc0\u76ee\u88fd\u4f5c\u6216\u65b0\u5a92\u9ad4\u7d93\u9a57\u00a0 \u8005\u512a\u5148\n\u00a0\u00a0\u00a0\u00a0\u00a0\u00a0\u00a0 \u826f\u597d\u7684\u65b0\u805e\u7d20\u990a\uff0c\u65b0\u805e\u654f\u611f\u6027\u5f37\uff0c\u77ad\u89e3\u5169\u5cb8\u56db\u5730\u7684\u91cd\u5927\u65b0\u805e\u4e8b\u4ef6\u548c\u65b0\u805e\u80cc\u666f\n\u00a0\u00a0\u00a0\u00a0\u00a0\u00a0\u00a0 \u826f\u597d\u7684\u4e2d\u82f1\u6587\u8b80\u5beb\u80fd\u529b\uff0c\u5305\u62ec\u666e\u901a\u8a71\u53ca\u7cb5\u8a9e\uff0c\u4e2d\u6587\u6587\u5b57\u529f\u5e95\u624e\u5be6\n\u00a0\u00a0\u00a0\u00a0\u00a0\u00a0\u00a0 \u5177\u6709\u57fa\u672c\u7684\u8996\u983b\u526a\u8f2f\u6280\u5de7\n\u00a0\u00a0\u00a0\u00a0\u00a0\u00a0\u00a0 \u80fd\u9069\u61c9\u7dca\u5f35\u7e41\u5fd9\u7684\u5de5\u4f5c\u74b0\u5883\u3001\u6297\u58d3\u6027\u5f37\uff0c\u6709\u5f37\u70c8\u7684\u5718\u968a\u5408\u4f5c\u7cbe\u795e\n\u00a0\u00a0\u00a0\u00a0\u00a0\u00a0\u00a0 \u9700\u8f2a\u73ed\u5de5\u4f5c\n\u00a0\u00a0\u00a0\u00a0\u00a0\u00a0\u00a0 \u8cc7\u6b77\u8f03\u6dfa\u8005\u4ea6\u53ef\u7372\u8003\u616e\u70ba\u526f\u65b0\u805e\u4e3b\u7de8\n\u5de5\u4f5c\u5730\u9ede\uff1a\u9999\u6e2f", "employment_types": ["Full Time", "Permanent"], "selling_points": [], "locations": ["Kwun Tong"], "categories": ["Media & Advertising", "Editorial / Journalism"], "post_time": "2022-01-06T08:18:40Z", "salary": {"currency": null, "max": null, "min": null, "period": "monthly", "term": null}, "salary_visible": false, "title_keywords": ["copywriter"], "responsibilities": [], "requirements": {"degrees": [], "majors": [], "languages": [], "language_level": [], "hard_skills": [], "soft_skills": [], "languages_combined": []}, "experience_required": {"duration": [], "field": []}}, {"job_id": "100003009021478", "location_code": "hk", "company": "Ambitious People Group", "job_title": "Associate Editor (Asset management, digital platform)", "description": "\u8077\u8cac\n\n\u7d71\u7c4c\u3001\u7de8\u8f2f\u3001\u6821\u5c0d\u4e2d\u6587\u79d1\u51fa\u7248\u7269\n\u78ba\u4fdd\u51fa\u7248\u7269\u7d20\u8cea\u53ca\u6309\u6642\u5b8c\u6210\n\u4efb\u4f55\u5176\u4ed6\u6307\u6d3e\u7684\u5de5\u4f5c\n\n\u8077\u4f4d\u8981\u6c42\n\n\u5927\u5b78\u672c\u79d1\u6216\u4ee5\u4e0a, \u4e3b\u4fee\u4e2d\u570b\u8a9e\u6587\u6216\u4e2d\u570b\u6587\u5b78\n6 \u5e74\u6216\u4ee5\u4e0a\u6559\u80b2\u7de8\u8f2f\u7d93\u9a57\n\u719f\u6089\u7de8\u8f2f\u6d41\u7a0b\u548c\u51fa\u7248\u696d\u52d9, \u80fd\u7368\u7acb\u8655\u7406\u7de8\u52d9\u53ca\u5be9\u95b1\u7a3f\u4ef6\n\u719f\u6089\u5c0f\u5b78\u4e2d\u570b\u8a9e\u6587\u79d1\u8ab2\u7a0b\n\u5177\u6709\u6df1\u539a\u7684\u6587\u5b57\u529f\u5e95\n\u5bcc\u5275\u610f\u3001\u7d30\u5fc3\u3001\u8cac\u4efb\u611f\u53ca\u627f\u64d4\u529b\n\u559c\u6b61\u6311\u6230\uff0c\u71b1\u611b\u5de5\u4f5c\uff0c\u80fd\u627f\u53d7\u58d3\u529b\n\u5177\u826f\u597d\u7d44\u7e54\u53ca\u6e9d\u901a\u80fd\u529b\n\u719f\u6089\u96fb\u8166\u64cd\u4f5c\u3001\u4e00\u822c\u8edf\u4ef6\u53ca\u4e2d\u6587\u6253\u5b57\n\u5bcc\u591a\u5a92\u9ad4\u6559\u6750\u88fd\u4f5c\u7d93\u9a57\u66f4\u4f73\n\u7d93\u9a57\u8f03\u5c11\u8005\u53ef\u7533\u8acb\u9805\u76ee\u7de8\u8f2f / \u7de8\u8f2f\u00a0\u4e00\u8077\n\n\u672c\u516c\u53f8\u63d0\u4f9b\u826f\u597d\u4e8b\u696d\u767c\u5c55\u6a5f\u6703\u53ca\u5177\u7af6\u722d\u6027\u85aa\u916c\u53ca\u798f\u5229\u5f85\u9047\u5305\u62ec\uff1a\u4e94\u5929\u5de5\u4f5c\u3001\u914c\u60c5\u916c\u91d1\u3001\u91ab\u7642\u8a08\u5283\u3001\u54e1\u5de5\u57f9\u8a13\u53ca\u54e1\u5de5\u8cfc\u7269\u512a\u60e0\u7b49\u3002\u6709\u8208\u8da3\u8005\u8acb\u6309 \"Apply Now\" \u63d0\u4ea4\u500b\u4eba\u5c65\u6b77\u3002\n\n\u6240\u6709\u8077\u4f4d\u7533\u8acb\u5c07\u4f5c\u6a5f\u5bc6\u8cc7\u6599\u8655\u7406\u53ca\u53ea\u4f5c\u62db\u8058\u7528\u9014\u3002\n\n\u6b61\u8fce\u700f\u89bd\u672c\u516c\u53f8\u7db2\u9801:\u00a0\nhttp://www.popular.com.hk\u00a0/\nhttp://pl.popularworldhk.com/\nhttp://jp.popularworldhk.com", "employment_types": ["Full Time", "Permanent"], "selling_points": ["High base salary", "Dynamic working environment", "Comprehensive benefit scheme"], "locations": ["Not Specified"], "categories": ["Media & Advertising", "Editorial / Journalism", "Marketing / Public Relations", "Marketing - Marketing Communication", "Public Relations - Copy-writing"], "post_time": "2022-01-05T04:05:24Z", "salary": {"currency": null, "max": null, "min": null, "period": "monthly", "term": null}, "salary_visible": false, "title_keywords": ["editor", "associate", "asset management"], "responsibilities": [], "requirements": {"degrees": [], "majors": [], "languages": [], "language_level": [], "hard_skills": ["pl"], "soft_skills": [], "languages_combined": []}, "experience_required": {"duration": [], "field": []}}, {"job_id": "100003009030005", "location_code": "hk", "company": "Sing Tao Management Services Limited", "job_title": "Operations Executive (New Media Business)", "description": "\u5165\u8077\u8981\u6c42\uff1a\n\n\n\u00a0\u5927\u5b78\u7562\u696d\u6216\u4ee5\u4e0a\u7a0b\u5ea6\uff0c\u4e3b\u4fee\u4e2d\u570b\u6b77\u53f2\u3001\u6b77\u53f2\u3001\u7d93\u6fdf\u3001\u7ffb\u8b6f\u79d1\u76ee\n\n\u00a0\u4e00\u5e74\u6216\u4ee5\u4e0a\u7de8\u8f2f\u5de5\u4f5c\u7d93\u9a57( \u5177\u78a9\u58eb\u5b78\u6b77\u4f46\u5de5\u4f5c\u7d93\u9a57\u8f03\u6dfa\u8005\u4ea6\u53ef\u61c9\u5fb5 )\n\u00a0\u719f\u6089\u96fb\u8166\u8edf\u4ef6\u64cd\u4f5c ( MS Office)\n\u00a0\u66fe\u6709\u6559\u79d1\u66f8\u51fa\u7248\u6216\u6559\u5b78\u7d93\u9a57\u8005\u512a\u5148\nRequirements\ufe30\n\nA bachelor degree in Chinese History, History, Economics, Translation\nAt least 1 years' editorial and publishing experience (Candidates with Master degree but less working experience may be considered)\nProficient in MS Office applications\nExperience in educational book publishing and/or teaching would be an advantage\n\u672c\u516c\u53f8\u70ba\u54e1\u5de5\u63d0\u4f9b\u5404\u9805\u798f\u5229\uff0c\u4f8b\u5982\uff1a\u91ab\u7642\u3001\u96d9\u85aa\u7b49\uff0c\u6bcf\u9031\u5de5\u4f5c\u4e94\u5929\u3002\u6709\u610f\u61c9\u5fb5\u8005\uff0c\u8acb\u89aa\u7e55\u5c65\u6b77\uff0c\u4e26\u9644\u85aa\u916c\u8981\u6c42\uff0c\u5bc4\u9999\u6e2f\u6559\u80b2\u5716\u66f8\u6709\u9650\u516c\u53f8\u9999\u6e2f\u7b72\u7b95\u7063\u8000\u8208\u90533\u865f\u6771\u532f\u5ee3\u58349\u6a13\u884c\u653f\u4eba\u4e8b\u90e8\u6536\u6216\u7d93 \" Apply Now\" \u905e\u4ea4\u7533\u8acb \u3002(\u7533\u8acb\u4eba\u8acb\u8a3b\u660e\u8077\u4f4d\u7de8\u865f\uff1aED106JOBS)\n\n\n\u6b61\u8fce\u6240\u6709\u5408\u8cc7\u683c\u4eba\u58eb\u7533\u8acb\u8077\u4f4d\u3002\u7533\u8acb\u4eba\u6240\u63d0\u4f9b\u7684\u8cc7\u6599\u7d55\u5c0d\u4fdd\u5bc6\uff0c\u53ea\u7528\u65bc\u8207\u62db\u8058\u76f8\u95dc\u7684\u7528\u9014\u3002\nAll applications will be treated in strict confidence and all personal data collected will be used for recruitment purposes only.", "employment_types": ["Full Time", "Permanent"], "selling_points": [], "locations": ["Tseung Kwan O"], "categories": ["Media & Advertising", "Editorial / Journalism", "Marketing / Public Relations", "Marketing - Marketing Communication"], "post_time": "2022-01-07T06:35:11Z", "salary": {"currency": null, "max": null, "min": null, "period": "monthly", "term": null}, "salary_visible": false, "title_keywords": ["operations executive"], "responsibilities": ["personal data", "recruitment"], "requirements": {"degrees": ["degree", "bachelor", "master degree"], "majors": ["economics", "history"], "languages": ["chinese"], "language_level": [], "hard_skills": ["translation", "ms office"], "soft_skills": ["confidence"], "languages_combined": [{"language": "chinese", "language_level": []}]}, "experience_required": {"duration": ["at least 1 years"], "field": ["editorial", "publishing", "teaching"]}}, {"job_id": "100003009022862", "location_code": "hk", "company": "Randstad Hong Kong Limited", "job_title": "Senior English Editor / Writer / Translator (listed com) $55K", "description": "Established in 2009, Hong Kong Green Building Council (\u201cthe Council\u201d) is the leading body, co-founded by four major construction industry and environmental organisations, driving the market transformation towards green and sustainable buildings in Hong Kong through engagement with the industry, the government and broader community.\n\nHKGBC is expanding its secretariat team in line with its positioning as Hong Kong's leading member-based body dedicated to green building development, with opening for the post of\u00a0Marketing & PR Executive:\n\nJob Description\n\n\u00a0Assisting the Head of Marketing, to plan, organise and execute all marketing & PR related duties including:\n\n\u00a0Key Roles\n\nTo organise and follow through the planning, budget control, execution and logistic arrangements of various types of events, including large scale public campaign, exhibitions, press conferences and site visits, etc.\nTo develop various online and offline marketing collaterals from conception, content development, layout design to production\nTo assist in corporate marketing and project marketing initiatives\nTo develop and monitor social media and related applications\nTo write and develop content for HKGBC publications, official website, press and marketing materials\nTo coordinate with event and PR agencies or other vendors and monitor the service delivery\nTo build good rapport among media and relevant stakeholders\nTo support the team in other activities as required and necessary\n\n\u00a0Requirements:\n\nDegree holder in Marketing, Communications, Business, Language or related disciplines\n2 to 4 years of working experience, preferably in marketing, PR or event management; candidate with less experience may be considered as Marketing Assistant\nGood command of written and spoken English and Chinese\nNaturally outgoing, proactive and sociable\nGood project management skills, multi-tasking, detail-minded and able to meet tight deadlines\nA team player with good interpersonal, organisational and communication skills\nPassion towards building a sustainable city and endorsing a green lifestyle\nProficiency in Adobe Photoshop, Illustrator and InDesign would be an advantage\n\nHow to Apply\n\nThe Council is an equal opportunity employer and offers attractive career prospects and remuneration to our staff. Recruitment will be initially under contract terms of two years with the possibility of converting to a permanent post.\u00a0Interested applicants please apply by sending\u00a0full resume with date of availability, present and expected salary, contact telephone number, as well as results of public examinations\u00a0to the\u00a0Executive Director, Hong Kong Green Building Council\u00a0via e-mail\u00a0careers @ hkgbc.org.hk, or by post to\u00a01/F, Jockey Club Environmental Building, 77 Tat Chee Avenue, Kowloon Tong, Hong Kong. Please state the position you want to apply for on the envelope.\n\n(N.B. Application with incomplete information as requested above may not be considered.)\n\nApplicants who do not receive a response within six weeks from the date of this advertisement may consider their applications filed for future reference. Personal data will be used strictly for recruitment related purposes only and retained for no more than six months.", "employment_types": ["Full Time", "Permanent"], "selling_points": [], "locations": ["Causeway Bay"], "categories": ["Media & Advertising", "Editorial / Journalism", "Marketing / Public Relations", "Public Relations - Copy-writing", "Professional Services", "Translation"], "post_time": "2022-01-05T06:44:22Z", "salary": {"currency": "HKD", "max": 54999, "min": 45000, "period": "monthly", "term": null}, "salary_visible": true, "title_keywords": ["editor", "translator"], "responsibilities": ["service delivery", "social media", "marketing collaterals", "layout design", "monitor", "website", "develop", "coordinate with", "conferences", "plan", "marketing materials", "budget control", "support the team", "planning"], "requirements": {"degrees": ["degree holder"], "majors": ["business", "related disciplines", "marketing", "communications"], "languages": ["english", "chinese"], "language_level": ["good command"], "hard_skills": ["no", "indesign", "adobe photoshop", "illustrator", "project management"], "soft_skills": ["outgoing", "detail-minded", "meet tight deadlines", "communication skills", "project management skills", "sociable", "multi-tasking", "team player", "proactive", "interpersonal"], "languages_combined": [{"language": "english", "language_level": ["good command"]}, {"language": "chinese", "language_level": ["good command"]}]}, "experience_required": {"duration": ["2 to 4 years"], "field": ["pr", "marketing", "management"]}}, {"job_id": "100003009032218", "location_code": "hk", "company": "Epoch Group Limited", "job_title": "Business Reporter, The Epoch Times (NewYork)", "description": "Ref.:\u00a0JDB/PT/TADM/IFEC/220107\n\nDuties & Responsibilities:\n\n\nPublish digital content on our websites via content management system and/or html editing\nConduct quality check and testing of online tools and mobile apps\nProvide administrative support for the Communications & Resources team\n\nRequirements:\n\nTertiary education, preferably a major in Computer Science, Communication, Marketing, Business, Finance or equivalent field with at least 2 years of work experience\nMinimum 1 year of experience using a content management system, e.g. Wordpress\nBasic knowledge of HTML and web publishing \u2022 Ability to organise and prioritise daily work tasks\nProactive, accountable and meticulous\nPhotoshop or Illustrator skills would be a plus\nExperience in proof reading layout and design on webpages and tools\nGood command of Chinese (Cantonese, Putonghua) and English\n\nPlease quote the reference and apply by\u00a021 January 2022\u00a0with details of qualifications, previous experience, current and expected salary to:\n\nRecruitment Manager\nSecurities & Futures Commission\n54/F, One Island East,\n18 Westlands Road, Quarry Bay,\u00a0Hong Kong\n\nFor online applications, please refer to\u00a0https://www.sfc.hk/en/Career/Why-the-SFC/Join-us-as-an-experienced-professional/Current-Openings/210423-Part-time-Temporary-Administrator-1-year-contract---Investor-and-Financial-Education-Councilhttps://www.sfc.hk/en/Career/Why-the-SFC/Join-us-as-an-experienced-professional/Current-Openings/220107-Part-time-Temporary-Administrator-1-year-contract---IEFC\u00a0or click \"Apply Now\" button.\n\nAll applications will be handled in strict confidence by authorised personnel and will only be used for recruitment related purposes. Applicants who do not hear from us within six months from the application deadline may consider their applications as unsuccessful. All information on unsuccessful candidates will be destroyed after six months.", "employment_types": ["Full Time"], "selling_points": [], "locations": ["Not Specified"], "categories": ["Media & Advertising", "Editorial / Journalism", "Print Media"], "post_time": "2022-01-07T10:30:25Z", "salary": {"currency": null, "max": null, "min": null, "period": "monthly", "term": null}, "salary_visible": false, "title_keywords": ["reporter"], "responsibilities": ["quality check", "management", "testing", "provide administrative support", "editing"], "requirements": {"degrees": [], "majors": [], "languages": ["cantonese", "putonghua", "english", "chinese"], "language_level": ["good command"], "hard_skills": ["plus", "basic", "web", "illustrator", "html", "wordpress", "photoshop"], "soft_skills": ["meticulous", "confidence", "accountable", "prioritise", "communication", "proactive"], "languages_combined": [{"language": "cantonese", "language_level": ["good command"]}, {"language": "putonghua", "language_level": ["good command"]}, {"language": "english", "language_level": ["good command"]}, {"language": "chinese", "language_level": ["good command"]}]}, "experience_required": {"duration": ["at least 2 years", "minimum 1 year"], "field": ["management", "finance", "design", "education", "business", "marketing"]}}, {"job_id": "100003009018735", "location_code": "hk", "company": "Sing Tao News Corporation Limited (The Standard)", "job_title": "Trainee (Sub-Editor) \u2013 The Standard Subbing", "description": "Are you passionate about Tea?\n\nAt Tea Chateau, we're aspired by the tea craftsmanship and culture that are rooted in thousand years of wisdom. We are seeking passionate and dynamic\u00a0Digital Content Specialist to join our team who can share our believe, and deliver the emotional satisfactions to our customers.\n\nWe will empower you to share your tea know-how and bring a new tea experience that all the greatness of tea can now be unleashed effortlessly, just a click away.\n\nYou will be.....\n\nCreating and producing the social media contents enhance our digital performance.\u00a0\nRecruiting and sourcing influencers to generate fruitful contents.\u00a0\nOur KOL / vlogger to promote our brand and products, if you are interested to be.\u00a0\nBringing in the latest digital trends and work together with marketing team for digital campaigns.\nAbout our Digital Content Specialist:\n\nAn individual with passion in digital or social media from any industry. Hands-on experience in photography, videography or any format of content generating skills on social media channels is a must. If you are an all-rounded digital content specialist are welcome.\u00a0A professional with strong communication, team playing and collaboration skills is a must.\n\nInterested?\u00a0Send us your profile via hrd @ teachateau.com or Apply Now!", "employment_types": ["Full Time", "Permanent"], "selling_points": [], "locations": ["Tseung Kwan O"], "categories": ["Media & Advertising", "Editorial / Journalism", "Print Media", "Others", "Student / Fresh Graduate / No Experience"], "post_time": "2022-01-04T04:33:30Z", "salary": {"currency": null, "max": null, "min": null, "period": "monthly", "term": null}, "salary_visible": false, "title_keywords": ["editor", "trainee"], "responsibilities": ["communication", "social media", "digital campaigns", "contents"], "requirements": {"degrees": [], "majors": [], "languages": [], "language_level": [], "hard_skills": ["dynamic", "tea"], "soft_skills": ["passionate", "passion in", "communication", "hands-on", "dynamic", "passionate about"], "languages_combined": []}, "experience_required": {"duration": [], "field": ["social media"]}}, {"job_id": "100003009031626", "location_code": "hk", "company": "Loving Game Limited", "job_title": "Digital Marketing Assistant - Game Platform", "description": "Responsibilities:\n\nDevelop project direction, plans, project standards, schedules, budgets and resources\nManage business requirements gathering, analysis and documentation\nEnsure the project milestones and deliverable to be completed on time, within agreed cost and meet the required quality standard\nTo lead, guide and train editorial team in performing job-related works\nLiaise with authors and other freelance personnel to facilitate content development; Reviewing scripts and monitor editorial works\nRequirements:\nDegree holder in any discipline\nAt least 8 years or above working experience on multimedia or editorial\nFamiliar with latest e-Learning trends in education industry\nGood project management and leadership skills\nExcellent command of written and spoken Chinese & English\nGood communication, analytical and interpersonal skills\nMeticulous to details and sensitive to the market demand\nOrganized, self-motivated and flexible\nAble to handle multiple tasks and meet tight deadlines\nWe offer excellent career development opportunities to unleash your potential, competitive remuneration package including a 5-day work week, discretionary bonus, Medical Scheme, staff training and staff purchasing discount etc.\nInterested parties please click\u00a0\"Apply Now\"\u00a0to submit your full resume stating present and expected salary.\nPersonal data provided by job applicants will be kept strictly confidential and will be used solely for employment related purposes. Only short-listed candidates will be contacted.\nYou are welcome to visit our website to know more about us:\u00a0\nhttp://www.popular.com.hk\u00a0/\nhttp://pl.popularworldhk.com/\nhttp://jp.popularworldhk.com", "employment_types": ["Full Time"], "selling_points": [], "locations": ["Ngau Tau Kok"], "categories": ["Media & Advertising", "Editorial / Journalism", "Marketing / Public Relations", "Digital Marketing", "E-commerce", "Marketing - Brand / Product Management"], "post_time": "2022-01-07T09:34:52Z", "salary": {"currency": null, "max": null, "min": null, "period": "monthly", "term": null}, "salary_visible": false, "title_keywords": ["digital marketing", "assistant"], "responsibilities": ["budgets", "cost", "schedules", "analysis", "quality", "monitor", "develop", "liaise with", "documentation", "plans"], "requirements": {"degrees": ["degree holder"], "majors": [], "languages": ["english", "chinese"], "language_level": ["excellent"], "hard_skills": ["project management", "multimedia", "scheme"], "soft_skills": ["flexible", "meticulous", "organized", "self-motivated", "meet tight deadlines", "leadership skills", "communication", "project management", "sensitive to", "learning", "interpersonal skills", "handle multiple tasks"], "languages_combined": [{"language": "english", "language_level": ["excellent"]}, {"language": "chinese", "language_level": ["excellent"]}]}, "experience_required": {"duration": ["at least 8 years"], "field": ["editorial"]}}, {"job_id": "100003009026809", "location_code": "hk", "company": "Hypebeast Hong Kong Limited", "job_title": "Social Media Coordinator", "description": "\u5de5\u4f5c\u8077\u8cac\uff1a\n\n-\u8ca0\u8cac\u7d93\u71df\u793e\u4ea4\u5a92\u9ad4\uff0c\u5beb\u8da3\u5473\u7db2\u6587\uff0b\u5716\uff0c\u540c\u8b80\u8005\u50be\u8a08\u4e92\u52d5\n-\u64b0\u5beb\u6f6e\u6d41\u8a71\u984c\uff0c\u4ee5\u6295\u8cc7\u3001\u91ab\u7642\u70ba\u4e3b\n-\u540c\u6642\u4ea6\u8acb\u7dca\u4eba\u5c08\u5beb\u52a0\u5bc6\u8ca8\u5e63\u3001NFT\u7b49\u5167\u5bb9\n-\u9032\u884c\u5c08\u8a2a\uff0c\u70ba\u8b80\u8005\u63d0\u4f9b\u5c08\u984c\u5206\u6790\n-\u719f\u6089Facebook\u3001Instagram\u3001Youtube\u904b\u4f5c\n-\u64c5\u9577\u767c\u6398\u6f6e\u6d41\u8a71\u984c\uff0c\u540c\u62cd\u651d\u540c\u4e8b\u914d\u5408\uff0c\u7b56\u5283\u5f71\u7247\u5927\u7db1\u540c\u4e2d\u671f\u88fd\u4f5c\n\n\u8077\u4f4d\u8981\u6c42\uff1a\n\n-\u6587\u6191\u6216\u4ee5\u4e0a\u5b78\u6b77\u7a0b\u5ea6\uff0c\u5b78\u79d1\u80cc\u666f\u4e0d\u62d8 \uff1b\n-\u6709\u7de8\u63a1\u5de5\u4f5c\u7d93\u9a57\u6216\u51fa\u93e1\u7d93\u9a57\u512a\u5148\uff0c\u719f\u6089 (Facebook / IG / Youtube) \u5e73\u53f0\u64cd\u4f5c\uff1b\n-\u719f\u6089Adobe\u7b49\u8a2d\u8a08\u8edf\u4ef6\u64cd\u4f5c\uff1b\n-\u5177\u5099\u512a\u79c0\u7684\u4e2d\u6587\u5beb\u4f5c\u548c\u7de8\u8f2f\u80fd\u529b\uff0c\u53ca\u826f\u597d\u7684\u82f1\u6587\u8b80\u5beb\u80fd\u529b\uff1b\n-\u5177\u5099\u512a\u79c0\u7684\u8cc7\u6599\u8490\u96c6\u80fd\u529b\u548c\u6545\u4e8b\u50b3\u905e\u6280\u5de7\uff1b\n-\u5c0d\u5de5\u4f5c\u6709\u71b1\u8aa0\u3001\u7a4d\u6975\u4e3b\u52d5\uff0c\u8655\u4e8b\u7d30\u5fc3\u3001\u6709\u8cac\u4efb\u611f\uff0c\u6709\u5275\u610f, \u6709\u826f\u597d\u6642\u9593\u7ba1\u7406\n-\u6b61\u8fce\u61c9\u5c46\u7562\u696d\u751f\n-\u5982\u6709\u76f8\u95dc\u5de5\u4f5c\u7d93\u9a57\u8005\uff0c\u6703\u7372\u8058\u70ba\u300c\u9ad8\u7d1a\u7de8\u8f2f\u300d\u4e00\u8077\n\n\u5982\u679c\u4f60\u7747\u5230\u5462\u5ea6\uff0c\u5176\u5be6\u6211\u54cb Full Time/Part Time \u90fd\u8acb\u7dca\uff0c\u60f3\u767c\u63ee\u6240\u9577\u505a\u597d\u5167\u5bb9/\u5a92\u9ad4\u5605\u4f60\uff0c\u6709\u8208\u8da3\u5373\u7ba1\u5831\u540d\u8a66\u4e0b\u5566\uff01\n\n\u61c9\u5fb5\u8005\u8acb\u96c6\u9f4a\u96fb\u90f5\u5c65\u6b77\u3001\u8981\u6c42\u5f85\u9047\u3001\u53ca\u500b\u4eba\u7167\u7247\u6216\u77ed\u7247\uff0c\u6309\"Apply Now\"\u63d0\u4ea4\u7533\u8acb\u3002\n\n*\u7533\u8acb\u4eba\u6240\u63d0\u4f9b\u4e4b\u8cc7\u6599\u5c07\u4fdd\u5bc6\u53ca\u53ea\u7528\u4f5c\u62db\u8058\u7528\u9014", "employment_types": ["Full Time"], "selling_points": ["Comprehensive social media channel exposure", "Young, energetic and international team members", "Rapidly expanding team"], "locations": ["Kwai Hing"], "categories": ["Media & Advertising", "Editorial / Journalism", "Marketing / Public Relations", "Marketing - Marketing Communication", "Digital Marketing"], "post_time": "2022-01-06T08:40:58Z", "salary": {"currency": null, "max": null, "min": null, "period": "monthly", "term": null}, "salary_visible": false, "title_keywords": ["coordinator"], "responsibilities": ["facebook"], "requirements": {"degrees": [], "majors": [], "languages": [], "language_level": [], "hard_skills": ["facebook"], "soft_skills": [], "languages_combined": []}, "experience_required": {"duration": [], "field": []}}, {"job_id": "100003009024815", "location_code": "hk", "company": "Sun Hung Kai Properties Ltd", "job_title": "CORPORATE COMMUNICATIONS OFFICER / ASSISTANT CORPORATE COMMUNICATIONS OFFICER (EDITORIAL)", "description": "Ogilvy Social is a global, cross-discipline team of social experts from across all of Ogilvy\u2019s businesses. We know there\u2019s a new customer and stakeholder journey defined by the increasing impact our networks have on purchase decision and our behaviors. We design integrated social solutions that combine deep disciplines like CRM, public relations and shopper marketing and rooted in what drives behavior.\n\nResponsibilities include:\n\nContribute to cross-discipline social media team, spanning public relations, direct marketing, advertising and shopper marketing\nOnline research and social media monitoring using a variety of social media listening tools\nSocial media strategy development\nCampaign execution in the areas of content, community management, influencer identification, influencer outreach and offline activation\nMeasure campaign effectiveness using a variety of social media analytics tools\nDay-to-day client relationship management\nProject management\n\nIn order to be successful in this role you must:\n\nHave a Bachelors degree or equivalent with a strong academic record\nWith internship experience in an advertising or PR agency, or related field is preferred\nBe fluent in English language, reading and writing (test will be given)\nHave excellent communication skills \u2013 verbal and written\nThink critically and creatively, meaning the ability to think clearly and rationally, solve problems and develop new and useful possibilities\nPlan and execute on multiple projects simultaneously in an organized fashion\nWork calmly and maintain good judgment in a fast-paced work environment\nCollaborate with colleagues in different countries and appreciate cultural differences\nUnderstand current and emerging media platforms and their usage from a consumer and business perspective\nUnderstand how to drive conversations and online word of mouth\nBe passionate about social media and word of mouth marketing\n\nInterested parties please submit your resume with portfolio for our review.\n\nWe offer 5-day work with attractive salary, fringe benefits and good career prospects to the right candidates.\n\nAll information will be treated in the strictest confidence and used for recruitment purposes.\u00a0Only short-listed candidates will be contacted for interview.", "employment_types": ["Full Time", "Permanent"], "selling_points": ["Bachelor degree with 5 yrs' relevant experience", "Bilingual copywriting, translating and editing", "Production of various publications of the Group"], "locations": ["Wan Chai"], "categories": ["Media & Advertising", "Editorial / Journalism", "Marketing / Public Relations", "Public Relations - Copy-writing", "Print Media"], "post_time": "2022-01-06T02:34:41Z", "salary": {"currency": null, "max": null, "min": null, "period": null, "term": null}, "salary_visible": false, "title_keywords": ["corporate communications officer", "assistant corporate communications officer"], "responsibilities": ["collaborate with", "social media", "management", "analytics tools", "advertising", "monitoring", "design", "develop", "communication", "project management", "purchase", "maintain", "plan", "multiple projects"], "requirements": {"degrees": ["degree"], "majors": [], "languages": ["english"], "language_level": ["fluent"], "hard_skills": ["analytics tools", "project management", "word"], "soft_skills": ["communication skills", "organized", "deep", "project management", "solve problems", "passionate about"], "languages_combined": [{"language": "english", "language_level": ["fluent"]}]}, "experience_required": {"duration": [], "field": ["agency", "pr", "advertising", "related"]}}, {"job_id": "100003009025336", "location_code": "hk", "company": "Cathay Pacific Airways Ltd", "job_title": "Assistant Manager Internal Communications", "description": "Responsibilities:\n\n\u00a0\u00a0\u00a0\u00a0\u00a0\u00a0\u00a0\u00a0 Responsible for Chinese Copywriting, editing, proofreading and translating various printed and digital marketing collaterals including user manual, brochure, press release, print advertisement, corporate, etc.\n\u00a0\u00a0\u00a0\u00a0\u00a0\u00a0\u00a0\u00a0 Create compelling, well-structured and innovative campaigns that's align with the overall strategy\n\u00a0\u00a0\u00a0\u00a0\u00a0\u00a0\u00a0\u00a0 Coordinate, implement and manage various marketing campaigns including Advertising, PR, Event, Print and Joint Promotion\n\u00a0\u00a0\u00a0\u00a0\u00a0\u00a0\u00a0\u00a0 Liaise closely with various business units and teams including Design, Sales, Marketing and Purchasing, to ensure effective communication and to progress all marketing campaigns at each stage, from information gathering to concepts, from copy writing to production\n\u00a0 \u00a0 \u00a0 \u00a0 \u00a0Develop creative ideas and marketing programs\n\nRequirements:\n\n\u00a0\u00a0\u00a0\u00a0\u00a0\u00a0\u00a0\u00a0 Degree\u00a0in Languages / Communications / Journalism / Marketing\n\u00a0\u00a0\u00a0\u00a0\u00a0\u00a0\u00a0\u00a0 At least 3 years\u2019 solid experience in writing position\n\u00a0\u00a0\u00a0\u00a0\u00a0\u00a0\u00a0\u00a0 Agency / in-house marketing communications experience is a plus\n\u00a0\u00a0\u00a0\u00a0\u00a0\u00a0\u00a0\u00a0 Work experience in the field of marketing, advertising, public relations, prints production or event managementis highly preferred\n\u00a0\u00a0\u00a0\u00a0\u00a0\u00a0\u00a0\u00a0 Able to work under pressure and meet deadline\n\u00a0\u00a0\u00a0\u00a0\u00a0\u00a0\u00a0\u00a0 Enjoy working in a fast-paced and dynamic environment\n\u00a0\u00a0\u00a0\u00a0\u00a0\u00a0\u00a0\u00a0 Strong copywriting skill is a must\n\u00a0\u00a0\u00a0\u00a0\u00a0\u00a0\u00a0\u00a0 Excellent command of Chinese\n\u00a0\u00a0\u00a0\u00a0\u00a0\u00a0\u00a0\u00a0 Immediate availability is preferred", "employment_types": ["Full Time", "Permanent"], "selling_points": ["3-5 years\u2019 experience in a communications role", "Bachelor\u2019s degree in Communications / Journalism", "Travel Benefits, 5-days work, Medical Benefits"], "locations": ["Lantau Island"], "categories": ["Media & Advertising", "Creative / Design", "Editorial / Journalism", "Marketing / Public Relations", "Public Relations - Event Management"], "post_time": "2022-01-06T04:12:14Z", "salary": {"currency": null, "max": null, "min": null, "period": "monthly", "term": null}, "salary_visible": false, "title_keywords": ["assistant manager"], "responsibilities": ["liaise", "advertising", "teams", "design", "coordinate", "communication", "proofreading", "digital marketing", "marketing campaigns", "editing", "develop creative ideas"], "requirements": {"degrees": ["degree"], "majors": ["journalism", "marketing", "communications"], "languages": ["chinese"], "language_level": ["excellent"], "hard_skills": ["plus", "dynamic"], "soft_skills": ["enjoy working", "dynamic environment", "work under pressure"], "languages_combined": [{"language": "chinese", "language_level": ["excellent"]}]}, "experience_required": {"duration": ["at least 3 years"], "field": ["public relations", "advertising", "agency", "marketing communications", "marketing", "writing"]}}, {"job_id": "100003009024995", "location_code": "hk", "company": "Hong Kong Christian Service", "job_title": "\u4f01\u696d\u62d3\u5c55\u53ca\u7814\u7a76\u90e8-\u591a\u5a92\u9ad4\u8a2d\u8a08\u54e1(\u5e73\u9762)", "description": "Responsibilities:\n\n\nSingTao UGC platform management\nExamine and approval of user generated contents\nContent quality control\nUsers management and communication\n\nRequirements:\n\n\nDegree holder preferably in Communications, Journalism or related discipline. Non-degree holder with related experience is also welcomed\n2-3 years relevant editing working experience\nFull professional proficiency in written English and Chinese\nStrong organisation and communication skills\nWorking Location : Tseung Kwan O Industrial Estate\n\nInterested parties please\u00a0click \u201cApply Now\"\u00a0to submit your complete resume with\u00a0employment history and expected salary or by\u00a0post to\u00a0Human Resources Department, 3/F, Sing Tao News Corporation Building, 7 Chun Cheong Street, Tseung Kwan O Industrial Estate, Tseung Kwan O, New Territories, Hong Kong.\u00a0 \u00a0 \u00a0 \u00a0\u00a0\n\nWe are an equal opportunity employer and welcome applications from all qualified candidates. Information provided will be treated in strict confidence and only be used for recruitment related purpose. Applicant who is not invited for an interview within 6 weeks may consider their application not successful. All personal data of unsuccessful applicants will be destroyed within 6 months.\n\nwww.singtaonewscorp.com\u00a0", "employment_types": ["Full Time"], "selling_points": [], "locations": ["Tsim Sha Tsui"], "categories": ["Media & Advertising", "Creative / Design", "Editorial / Journalism", "Print Media"], "post_time": "2022-01-06T03:04:57Z", "salary": {"currency": null, "max": null, "min": null, "period": "monthly", "term": null}, "salary_visible": false, "title_keywords": [], "responsibilities": ["communication", "management", "quality control", "contents"], "requirements": {"degrees": ["degree holder"], "majors": ["journalism", "communications"], "languages": ["english", "chinese"], "language_level": ["proficiency"], "hard_skills": [], "soft_skills": ["communication skills", "organisation"], "languages_combined": [{"language": "english", "language_level": ["proficiency"]}, {"language": "chinese", "language_level": ["proficiency"]}]}, "experience_required": {"duration": ["2-3 years"], "field": ["related", "editing"]}}, {"job_id": "100003009024695", "location_code": "hk", "company": "Phoenix Satellite Television Co Ltd", "job_title": "SUB-EDITOR", "description": "Senior English Editor / Writer\n\nOur client is a sizable industry-leading listed company in Hong Kong. The company is looking for a seasoned Senior Editor / Writer to lead the English content production, translation and proofreading at the Corporate Communications department.\n\nabout the job.\n\nWriting, editing and proofreading English content across different formats and platforms (e.g. newsletters, speeches, website updates, presentations, etc.)\nLiaise with internal and external parties for the production of corporate communications materials (e.g. interim reports, annual reports, announcements, etc.)\nTranslating and localising relevant materials from Chinese to English\n\nskills & experiences required.\n\nDegree holder of English, Media, Journalism, Communications, Public Relations, Translation or any relevant discipline\n8+ years of experience in writing, communications, translation, etc.\nExcellent interpersonal skills\nExcellent command of written English; Chinese is a MUST\n\nInterested candidates, please send your updated resume + WRITING SAMPLES / PORTFOLIO to Scarlett Chan at scarlett.chan@randstad.com.hk", "employment_types": ["Full Time", "Permanent"], "selling_points": [], "locations": ["Tai Po Area"], "categories": ["Media & Advertising", "Others", "Editorial / Journalism", "Broadcasting - TV / Radio"], "post_time": "2022-01-06T02:14:22Z", "salary": {"currency": null, "max": null, "min": null, "period": null, "term": null}, "salary_visible": false, "title_keywords": ["editor"], "responsibilities": ["internal and external parties", "website", "presentations", "proofreading", "reports", "liaise with", "editing"], "requirements": {"degrees": ["degree holder"], "majors": ["journalism", "communications"], "languages": ["english", "chinese"], "language_level": ["excellent"], "hard_skills": ["translation", "presentations"], "soft_skills": ["interpersonal skills"], "languages_combined": [{"language": "english", "language_level": ["excellent"]}, {"language": "chinese", "language_level": []}]}, "experience_required": {"duration": ["8+ years"], "field": ["writing"]}}, {"job_id": "100003009025933", "location_code": "hk", "company": "Phoenix Satellite Television Co Ltd", "job_title": "Reporter (Hong Kong Channel)                              (REF:R-HKC-DB)", "description": "Job Responsibilities:\n\nDeliver business news reports and enterprise stories for print and digital platforms\nConduct interviews and gather information that leads to accurate and balanced stories for all platforms, including websites, newsletters, mobile app, podcasts, videos, and print magazines.\nSpot and analyze trends to find out stories behind the scenes\nWork remotely with editors in the New York Epoch Times to assure that stories are complete, fair and in context.\n\nRequirements:\n\nDegree holder, major in journalism, communications or business-related studies with at least 3 years\u2019 reporting experience\nHigh proficiency in both English and Chinese; must be able to conduct interviews in fluent English, Cantonese, and Mandarin; strong English and Chinese writing skills\nBusiness, finance, and economics background will be a bonus\nThe candidate will report directly to the Epoch Times headquarter (New York), and work in Hong Kong\nInterested candidates please click \u201cApply Now\u201d to submit your complete resume with compensation history, expected salary.\n\nInformation provided will be treated in strict confidence and only be used for recruitment-related purposes. Applicant who is not invited for an interview within 6 weeks may consider their application not successful. All personal data of unsuccessful applicants will be destroyed within 6 months.", "employment_types": ["Full Time", "Permanent"], "selling_points": [], "locations": ["Tai Po Area"], "categories": ["Media & Advertising", "Others", "Editorial / Journalism", "Broadcasting - TV / Radio"], "post_time": "2022-01-06T06:49:18Z", "salary": {"currency": null, "max": null, "min": null, "period": null, "term": null}, "salary_visible": false, "title_keywords": ["reporter"], "responsibilities": ["mobile app", "reports"], "requirements": {"degrees": ["degree holder"], "majors": ["journalism", "business", "communications"], "languages": ["cantonese", "english", "chinese", "mandarin"], "language_level": ["proficiency", "fluent"], "hard_skills": ["writing skills"], "soft_skills": ["writing skills"], "languages_combined": [{"language": "cantonese", "language_level": ["fluent"]}, {"language": "english", "language_level": ["proficiency", "fluent"]}, {"language": "chinese", "language_level": ["proficiency"]}, {"language": "mandarin", "language_level": ["fluent"]}]}, "experience_required": {"duration": ["at least 3 years"], "field": ["related", "business"]}}]