[{"job_id": "100003009055755", "location_code": "hk", "company": "Hakuhodo Hong Kong Ltd", "job_title": "Media Executive", "description": "Job Description\n\n\nMaintain daily operations for the social media advertising campaigns including content creation, posting, ad placing and monitoring;\nClosely monitor and analyze the social media advertising performance and its return of investment;\nFormulate insightful strategies and creative ideas to meet clients\u2019 objectives, ensure successful execution, flow and end-result;\nWork closely with internal teams and clients to deliver outstanding account servicing;\nRegularly generate report and drive analytics and recommendations;\nAssist in preparing document to pitch clients e.g. marketing plan, schedule, budget.\n\nThe Successful Applicant\n\n\nTertiary-educated;\nMinimum 1 year of account servicing and practical experience in social media platforms;\nUnderstanding on social media trends and best practices across the digital and new media sectors;\nFast-learner, passionate in online advertising industry;\nEager to learn, cheerful, detail-oriented and polite;\nGood team player with excellent communications and interpersonal skills;\nProficiency in MS Office applications e.g. Word, Excel etc.;\nGood written and spoken English & Chinese;\nCandidate with more experience will be considered as Senior Digital Performance Specialist.\nWhat's On Offer\n\n\n5-day work\nBank Holidays and other special leave (e.g. Birthday Leave, Family Leave, etc...)\nMedical Insurance\nTeam Building Activities\nDigital Marketing Training will be provided\nFriendly Work Environment\nInterest parties please send your CV with availability, current and expected salary to us.\n**Personal data collected will be used for recruitment purpose only**\n\n\n", "employment_types": ["Full Time", "Permanent"], "selling_points": ["Degree in communications/ advertising/ media", "1 yr work exp in media agency / media sales", "Fresh graduate"], "locations": ["North Point"], "categories": ["Media & Advertising", "Media Buying", "Strategic Planning", "Others"], "post_time": "2022-01-18T02:55:39Z", "salary": {"currency": null, "max": null, "min": null, "period": "monthly", "term": null}, "salary_visible": false, "title_keywords": ["executive"], "responsibilities": ["social media", "creative ideas", "advertising", "monitoring", "monitor", "maintain daily operations", "teams", "budget", "social media platforms", "marketing plan", "digital marketing", "schedule", "recruitment", "online advertising", "personal data", "insurance", "advertising campaigns", "report"], "requirements": {"degrees": [], "majors": [], "languages": ["english", "chinese"], "language_level": ["good"], "hard_skills": ["excel", "word", "ms office"], "soft_skills": ["passionate", "good team player", "cheerful", "polite", "detail-oriented", "eager to learn", "interpersonal skills", "friendly", "creative"], "languages_combined": [{"language": "english", "language_level": ["good"]}, {"language": "chinese", "language_level": ["good"]}]}, "experience_required": {"duration": ["minimum 1 year"], "field": ["social media", "account servicing", "digital"]}}, {"job_id": "100003009050222", "location_code": "hk", "company": "Passionation (Hong Kong) Limited", "job_title": "Associate Sales Manager / Sales Manager \u2013 SME Business", "description": "Requirements\n\nDegree holder in marketing communications/ advertising/ journalism/\u00a0media related disciplines\n1 year relevant work experience in media agency or media sales\nFresh graduate is also considered\nFluent in both written and spoken English and Chinese\nExcellent PC skills of MS Word, Excel and PowerPoint\nAttentive to details, sensitive to figures, responsible, willing to work overtime and under pressure\n\n\n\nJob Duties\n\nMedia booking and materials follow up\nDaily coordination and liaison with external media partners and media vendors\nPreparation of competitive reports and post buy reports to clients\nProvide support on clerical works, handle monthly billing and material flow when needed\nGather market information for the regular media and research updates\n\n\n\nInterested applicants please send full resume with expected salary by clicking \u201cAPPLY NOW\u201d or by post to Administration Director, 25/F., Prosperity Millennia Plaza, 663 King\u2019s Road, North Point, Hong Kong.\n\nPersonal data collected will be used for recruitment purpose only.", "employment_types": ["Full Time"], "selling_points": ["Min. 2 years Advertising Sales Experience", "with SME client base is an advantage", "Basic Salary + Commission"], "locations": ["Quarry Bay"], "categories": ["Media & Advertising", "Media Buying", "Sales, CS & Business Devpt", "Direct Sales", "Marketing / Public Relations", "Digital Marketing"], "post_time": "2022-01-17T04:00:11Z", "salary": {"currency": null, "max": null, "min": null, "period": "monthly", "term": null}, "salary_visible": false, "title_keywords": ["associate", "sales manager"], "responsibilities": ["provide support", "market information", "reports", "booking", "coordination", "recruitment", "personal data", "administration"], "requirements": {"degrees": ["fresh graduate", "degree holder"], "majors": ["marketing communications", "related disciplines", "journalism"], "languages": ["english", "chinese"], "language_level": ["fluent"], "hard_skills": ["excel", "pc skills", "powerpoint", "ms word"], "soft_skills": ["work overtime", "under pressure", "attentive to details", "responsible", "sensitive to figures"], "languages_combined": [{"language": "english", "language_level": ["fluent"]}, {"language": "chinese", "language_level": ["fluent"]}]}, "experience_required": {"duration": ["1 year"], "field": ["agency", "media", "media sales"]}}, {"job_id": "100003009053872", "location_code": "hk", "company": "Deep Sea Network Technology Limited", "job_title": "Digital Marketing Officer", "description": "What we offer\u00a0:\n\n\u2022 Competitive package & Performance Bonus\n\u2022 Medical insurance including dental insurance\n\u2022 13+ days Annual Leave\n\u2022 Good working environment &\u00a0Free drinks and snack\n\u2022 Company events\u00a0\uff08Group party, Christmas Party etc.\uff09\n\n\nJob Responsibilities :\n\nDevelop strategic digital marketing initiatives to achieve business targets including but not limited to YouTube, Facebook, Twitter, Instagram, etc online platforms\nResponsible for content marketing including but not limited to brand communication, product features and marketing strategies on various social media platforms\nImplement and optimize online marketing campaign by analyzing customers\u2019 behavior and latest market trends to maximize the usersactivity\nAnalyze and review the performance of social media platforms regularly, ie content, fans count and interactive\nProvide insights and suggestions for improvements and optimizations\n\nJob Requirements :\n\nBachelor degree or above, preferably in advertising, marketing, business or related disciplines\nMinimum 3 years of work experience, experience in Financial industry is an advantage\nPractical experience & familiar with the operation of new media platforms\nExperience in operation team management is an advantage\nFamiliar with KOL marketing and operation. With KOL platforms connections is an advantage", "employment_types": ["Full Time", "Permanent"], "selling_points": ["3 years of work experience in Digital Marketing", "Customer & Brand Experience", "Proficient in Data analysis"], "locations": ["Tsim Sha Tsui"], "categories": ["Media & Advertising", "Media Buying", "Marketing / Public Relations", "Marketing - Marketing Communication", "Digital Marketing"], "post_time": "2022-01-17T07:39:56Z", "salary": {"currency": null, "max": null, "min": null, "period": "monthly", "term": null}, "salary_visible": false, "title_keywords": ["digital marketing officer"], "responsibilities": [], "requirements": {"degrees": [], "majors": [], "languages": [], "language_level": [], "hard_skills": [], "soft_skills": [], "languages_combined": []}, "experience_required": {"duration": [], "field": []}}, {"job_id": "100003009053100", "location_code": "hk", "company": "Innity China Co., Limited", "job_title": "Business Development Executive", "description": "Primary Responsibilities\n\nDrive and manage the development of our ad network and enhancement of ad performances to strengthen product offerings and increase market share in the local market.\nCreate and establish strong business relationships with new and existing publisher partners.\nOversee, manage, and resolve campaign performance issues.\nAlign goals and objectives with internal and external stakeholders.\nWork closely with in-house Ad Ops team, design, product teams and local sales team in closing business deals.\u00a0\n\nSpecification and Requirement (Eligibility)\n\nBachelor\u2019s Degree in Marketing and Advertising related field\nMinimum 1 year working experience in digital marketing, advertising, or related field. However, fresh graduates will also be considered.\nIndependent and good communication skill.\nCoordination, prioritization, and relationship building skills are essential\nComfortable with managing multiple projects with deadlines and influencing partners and co-workers at all levels of an organization.\u00a0\nPossess great attitude, passionate, proactive, and innovative\nInitiative and eye for details and can work independently or collaboratively in a team environment\nCandidate who with more working experience will be considered for senior post.", "employment_types": ["Full Time"], "selling_points": ["1+ year working experience in advertising industry", "Independent and good communication skill", "Strong business mindset"], "locations": ["Quarry Bay"], "categories": ["Media & Advertising", "Media Buying", "Sales, CS & Business Devpt", "Business Development", "Marketing / Public Relations", "Digital Marketing"], "post_time": "2022-01-17T07:18:15Z", "salary": {"currency": null, "max": null, "min": null, "period": "monthly", "term": null}, "salary_visible": false, "title_keywords": ["business development executive"], "responsibilities": ["sales team", "teams", "design"], "requirements": {"degrees": ["degree", "bachelor"], "majors": ["marketing"], "languages": [], "language_level": [], "hard_skills": [], "soft_skills": ["passionate", "work independently", "independent", "communication skill", "innovative", "coordination", "proactive", "initiative"], "languages_combined": []}, "experience_required": {"duration": ["minimum 1 year"], "field": ["related", "advertising", "digital marketing"]}}, {"job_id": "100003009047989", "location_code": "hk", "company": "IPG Mediabrands (HK) Limited", "job_title": "Media Buyer / Senior Buyer (Buying & Operation Team)", "description": "Primary Responsibilities\n\nProactively prospect, develop and cultivate leads for the sales pipeline.\nGrow and maintain advertisers\u2019 relationships to effectively build and grow ad revenue.\nResponsible for achieving monthly and annual sales targets according to sales plan.\nDisplay a thorough understanding of assigned account's business needs and revenue potential.\nPrepare innovative and turn-key sales proposals (across multiple solutions) to meet clients needs and expectations.\nPresent, negotiate and sell Influencer Marketing Solution to prospective direct clients (SME) via cold call selling and SME workshop, typically pitching to company owners and marketing manager.\nWork and co-ordinate with local and regional team to anticipate and respond to a variety of business needs.\n\n\u00a0Specification and Requirement (Eligibility)\n\nBachelor's Degree and Minimum 2 years of experience specializing in advertising, sales, client servicing or equivalent.\nProven track record of sales success with direct advertisers (SME) relationships is an added bonus.\nGood communication skills, possess an analytical mind and have good problem solving skills.\nSolid understanding of the advertising landscape and SME sales operations. Some knowledge of online advertising with regards to advertising options and technology.\nCandidate who with more working experience will be considered for senior post.", "employment_types": ["Full Time"], "selling_points": [], "locations": ["Quarry Bay"], "categories": ["Media & Advertising", "Account Servicing", "Media Buying", "Marketing / Public Relations", "Marketing - Marketing Communication"], "post_time": "2022-01-14T04:40:43Z", "salary": {"currency": null, "max": null, "min": null, "period": "monthly", "term": null}, "salary_visible": false, "title_keywords": [], "responsibilities": ["advertising", "co-ordinate with", "operations", "workshop", "develop", "communication", "maintain", "plan", "sme", "online advertising"], "requirements": {"degrees": ["degree", "bachelor"], "majors": [], "languages": [], "language_level": [], "hard_skills": ["problem solving skills"], "soft_skills": ["communication skills", "responsible", "analytical mind", "thorough", "problem solving skills", "innovative"], "languages_combined": []}, "experience_required": {"duration": ["minimum 2 years"], "field": ["advertising"]}}, {"job_id": "100003009054634", "location_code": "hk", "company": "HK01 Company Limited", "job_title": "\u8a18\u8005 (\u5973\u751f\u983b\u9053)", "description": "Job Description\n\n\nDelivering social media campaigns through social media platforms: Facebook, LinkedIn, Twitter, LINE, Wechat etc.;\nPlanning and executing online advertising strategies of various platforms;\nMaintain daily operations for the social media advertising campaigns including content creation, posting, ad placing and monitoring;\nClosely monitor and analyze the social media advertising performance and its return of investment;\nFormulate insightful strategies and creative ideas to meet clients\u2019 objectives, ensure successful execution, flow and end-result;\nMaintain relationship with new and existing customers;\nPerform any ad-hoc duties as assigned.\nThe Successful Applicant\n\n\nBachelor\u2019s degree in Marketing Communication or related;\nMinimum 3 year practical experience in social media platforms, agency experience preferred;\nUnderstanding on social media trends and best practices across the digital and new media sectors;\nAbility to lead and motivate a team to deliver results;\nEager to learn, cheerful, detail-oriented and polite;\nProficiency in MS Office applications e.g. Word, Excel etc.\nmedia sectors;\nGood written and spoken English & Chinese;\nCandidate with more experience will be considered as Digital Performance Manager.\nWhat's On Offer\n\n\n5-day work\nBank Holidays and other special leave (e.g. Birthday Leave, Family Leave, etc...)\nMedical Insurance\nTeam Building Activities\nDigital Marketing Training will be provided\nFriendly Work Environment\nInterest parties please send your CV with availability, current and expected salary to us.\n**Personal data collected will be used for recruitment purpose only**\n\n\n", "employment_types": ["Full Time", "Permanent"], "selling_points": ["\u64b0\u5beb\u5973\u6027\u76f8\u95dc\u53ca\u71b1\u9580\u4e4b\u5167\u5bb9", "\u6709\u65b0\u60f3\u6cd5\u53ca\u5bcc\u6709\u5beb\u4f5c\u6280\u5de7", "\u63d0\u4f9b\u8077\u696d\u767c\u5c55\u6a5f\u6703\uff0c\u53ca\u6709\u7af6\u722d\u529b\u7684\u85aa\u916c"], "locations": ["Tsuen Wan Area"], "categories": ["Media & Advertising", "Media Buying", "Strategic Planning", "Editorial / Journalism"], "post_time": "2022-01-17T10:20:08Z", "salary": {"currency": null, "max": null, "min": null, "period": "monthly", "term": null}, "salary_visible": false, "title_keywords": ["\u8a18\u8005"], "responsibilities": ["social media platforms", "communication", "maintain", "facebook", "personal data", "online advertising", "advertising", "social media campaigns", "maintain daily operations", "monitor", "social media", "monitoring", "executing", "digital marketing", "ad-hoc duties", "advertising campaigns", "creative ideas", "recruitment", "insurance", "planning"], "requirements": {"degrees": ["degree", "bachelor"], "majors": ["marketing"], "languages": ["english", "chinese"], "language_level": ["good"], "hard_skills": ["excel", "word", "wechat", "facebook", "ms office"], "soft_skills": ["cheerful", "polite", "detail-oriented", "communication", "eager to learn", "friendly", "ad-hoc duties", "creative"], "languages_combined": [{"language": "english", "language_level": ["good"]}, {"language": "chinese", "language_level": ["good"]}]}, "experience_required": {"duration": ["minimum 3 year"], "field": ["agency", "social media", "digital"]}}, {"job_id": "100003009043478", "location_code": "hk", "company": "Bowtie Life Insurance Company Limited", "job_title": "Digital Media Officer", "description": "Key responsibilities\n\nContent Acquisition \u2013 Now TV Team:\n\nResponsible for the important role of \u00a0Asian content acquisition, primarily drama series, across Now TV and its affiliates\u2019 media services in Hong Kong.\nHeads up a team to manage all aspects of content acquisition and management including research, negotiation, contract drafting, viewership tracking, financial analysis and contract database maintenance.\nManage the programming and scheduling of exclusive Asian drama linear channels and on-demand services to ensure that they are popular with customers.\u00a0\nCollaborate with internal stakeholders such as Marketing, Product, Legal, Finance and Overseas business teams to align budgets and forecasts, programming plans, marketing and promotional activities as well as to drive content \u00a0engagement across all customer touchpoints.\nMonitor industry trends to drive strategic content decisions, formulate business plans and develop content strategies for both internal and external stakeholders.\n\nQualifications\n\nUniversity degree required with 8+ years of relevant work experience in the media industry or content acquisition / distribution fields and with 3+ years of supervisory experience.\nExperience in negotiations and ability to manage legal agreements and contracts.\u00a0\nRelevant knowledge of Asian drama market and industry trends.\nAbility to learn in fast-paced environment, prioritizing and balancing multiple projects and deadlines simultaneously.\nGreat interpersonal skills, business judgment, proven strategic thinking and problem solving skills.\nExcellent verbal and written communication skills\u00a0in Cantonese/ Mandarin/ English.\nPreferred proficiency in a foreign language such as \u00a0Japanese/Korean but not required.", "employment_types": ["Full Time", "Permanent"], "selling_points": ["Good platform for early-career digital marketer", "Learning form experienced teammates", "Flexible, startup culture"], "locations": ["Wan Chai"], "categories": ["Media & Advertising", "Media Buying", "Marketing / Public Relations", "Digital Marketing"], "post_time": "2022-01-15T03:49:16Z", "salary": {"currency": null, "max": null, "min": null, "period": "monthly", "term": null}, "salary_visible": false, "title_keywords": ["officer"], "responsibilities": ["collaborate with", "budgets", "management", "maintenance", "contracts", "teams", "monitor", "business plans", "develop", "financial analysis", "scheduling", "communication", "promotional activities", "database", "plans", "multiple projects", "tracking"], "requirements": {"degrees": ["university degree"], "majors": [], "languages": ["cantonese", "english", "mandarin", "japanese", "korean"], "language_level": ["excellent", "proficiency"], "hard_skills": ["financial analysis", "programming", "problem solving skills", "maintenance"], "soft_skills": ["communication skills", "negotiation", "responsible", "strategic thinking", "fast-paced environment", "interpersonal skills", "problem solving skills", "prioritizing"], "languages_combined": [{"language": "cantonese", "language_level": ["excellent"]}, {"language": "english", "language_level": ["excellent"]}, {"language": "mandarin", "language_level": ["excellent"]}, {"language": "japanese", "language_level": ["proficiency"]}, {"language": "korean", "language_level": ["proficiency"]}]}, "experience_required": {"duration": ["8+ years", "3+ years"], "field": ["media", "legal", "supervisory experience"]}}, {"job_id": "100003009052333", "location_code": "hk", "company": "New iMedia Solutions Limited", "job_title": "Digital Performance Executive / Specialist | Digital Advertising | SEM | (Department Expansion)", "description": "\n\u4e3b\u8981\u8077\u8cac\n\n\n\u64b0\u5beb\u6642\u4e0b\u5973\u6027\u76f8\u95dc\u53ca\u71b1\u9580\u4e4b\u5167\u5bb9\n\u8ca0\u8cac\u63a1\u8a2a\u3001\u62cd\u651d\u5de5\u4f5c\n\u914d\u5408\u5e02\u5834\u90e8\u88fd\u4f5c\u5546\u696d\u5408\u4f5c\u5167\u5bb9\n\u5165\u8077\u8981\u6c42\n\n\u5927\u5b78\u6216\u4ee5\u4e0a\u5b78\u6b77\u7a0b\u5ea6\uff0c\u5f9e\u4e8b\u7db2\u7d61\u5a92\u9ad4\u5c07\u512a\u5148\u8003\u616e\n\u5c0d\u8655\u7406\u7f8e\u5bb9\u6253\u626e\u3001\u60c5\u611f\u95dc\u4fc2\u7b49\u5167\u5bb9\u5177\u6709\u7d93\u9a57\n\u719f\u6089\u7db2\u7d61\u6587\u5316\n\u6027\u683c\u7a4d\u6975\u4e3b\u52d5\uff0c\u64c5\u9577\u8207\u4eba\u6e9d\u901a\uff0c\u5177\u5718\u9ad4\u7cbe\u795e\n\u6b64\u8077\u4f4d\u5c6c\u65bc \"\u5973\u751f\" \u983b\u9053\uff0c\u61c9\u5fb5\u8005\u53ef\u5230hk01.com\u67e5\u770b\n\n\n\n\n\u6211\u5011\u6703\u70ba\u5408\u9069\u7684\u4eba\u9078\u63d0\u4f9b\u512a\u539a\u7684\u85aa\u916c\u5f85\u9047\u53ca\u798f\u5229(\u5305\u62ec\u4e94\u5929\u5de5\u4f5c\u5468)\u3002\u61c9\u5fb5\u8005\u8acb\u6309 \"Apply Now\" \u6309\u9215\u4e26\u63d0\u4f9b\u5c65\u6b77\u3001\u73fe\u6642\u53ca\u8981\u6c42\u7684\u85aa\u916c\u5f85\u9047\u7b49\u8cc7\u6599\u4f5c\u8077\u4f4d\u7533\u8acb\u3002\n\n\u6240\u6709\u6536\u96c6\u7684\u500b\u4eba\u8cc7\u6599\u90fd\u6703\u56b4\u683c\u4fdd\u5bc6\u4e26\u53ea\u4f5c\u62db\u8058\u7528\u9014\u30023\u500b\u6708\u5167\u672a\u7372\u9762\u8a66\u901a\u77e5\u7684\u7533\u8acb\u8005\uff0c\u53ef\u8996\u5176\u7533\u8acb\u70ba\u4e0d\u6210\u529f\u8ad6\u3002\u53e6\u4e00\u65b9\u9762\uff0c\u5c65\u6b77\u4ea6\u53ef\u80fd\u8ddf\u64da\u516c\u53f8\u96c6\u5718\u7684\u5167\u90e8\u9700\u8981\uff0c\u9032\u884c\u5167\u90e8\u8f49\u79fb\u3002\u672a\u7372\u63a5\u7d0d\u7684\u7533\u8acb\u8cc7\u6599\u5c07\u6703\u572812\u500b\u6708\u5167\u92b7\u6bc0\u3002", "employment_types": ["Full Time"], "selling_points": ["Flexi-Hour, Monthly Early Friday-off & Incentive", "Young & Energetic Talent with Passion in Digital", "Digital Performance & Strategies"], "locations": ["Kwun Tong"], "categories": ["Media & Advertising", "Account Servicing", "Media Buying", "Marketing / Public Relations", "Digital Marketing"], "post_time": "2022-01-17T02:47:43Z", "salary": {"currency": null, "max": null, "min": null, "period": "monthly", "term": null}, "salary_visible": false, "title_keywords": ["specialist", "performance executive"], "responsibilities": [], "requirements": {"degrees": [], "majors": [], "languages": [], "language_level": [], "hard_skills": [], "soft_skills": [], "languages_combined": []}, "experience_required": {"duration": [], "field": []}}, {"job_id": "100003009054723", "location_code": "hk", "company": "HK01 Company Limited", "job_title": "\u9805\u76ee\u7de8\u8f2f (Project Editor)", "description": "To become a digital expertise in our Company, you will enjoy our attractive benefits:\n\nCompetitive remuneration package\nPerformance Bonus\nMedical Insurance\n5-day work per week\nFlexi-working hour\nGeneral Holiday, Annual Leave, Family Care Leave and Anniversary Leave\nCasual wear in office\nFriendly working environment\n\n\u00a0\u00a0The Job\n\nStrong analytical skills to consolidate data from numerous digital advertising platforms, analyze various metrics, and to convert them into strategies and action plans\nCommunicate with client on campaign performance, insight and recommendation\nDemonstrate to clients how digital advertising and web analytics can reach their marketing objectives towards business goal\nAttentive to details, execute and optimize various digital media channels (i.e. Facebook, Google, Yahoo, LinkedIn Programmatics DSP), including but not limited to search engine marketing, display ad, social media marketing, conversion tracking and web analysis.\nCollaborate with internal teams to manage and monitor for search engine marketing and social media campaign, to deliver results and KPIs\nKeep up-to-date with platform knowledge and industry news\nAble to work independently, under pressure and to work on multiple projects with tight schedule\n\n\u00a0The Person\n\nDegree in Business, Marketing, IT or related discipline\u00a0\n2 years' experience in online business incl. Search Engine Marketing, Social Media Marketing, Web Analytic\u00a0and account management; Candidate with less experience may be considered as Executive;\nKnowledge of the Search Engine Marketing in Search engines like Google and Yahoo is preferable\nSolid understanding of the current technologies available for online advertising e,g, Search Engine Marketing, Display Advertising, Social Media Marketing, Programmatics, Website development, etc.\nAttentive to details, good with figures and strong analytical skills\nStrong passion for the Internet/Digital environment, result-oriented, proactive and independent\nAble to work collaboratively across teams as a good team player, with client-centric mindset\nGood command of written, spoken English and Chinese, knowledge of Mandarin is preferable\nAble to work independently, under pressure and to work on multiple projects with tight schedule\n\nCandidate with less experience will be considered as Digital Advertising Executive. Fresh graduates are also welcome if you possess knowledge in digital analytics, ad platforms like Google, Facebook, Bing, etc.\n\nPlease send your application with full resume stating\u00a0your present and expected salary\u00a0to the Company by clicking\u00a0on the\u00a0\"Apply now\".\u00a0Please also quote the\u00a0reference number\u00a0of the applied position in the subject field.", "employment_types": ["Full Time", "Permanent"], "selling_points": ["\u5927\u5b78\u6216\u4ee5\u4e0a\u7a0b\u5ea6\uff0c2\u5e74\u6216\u4ee5\u4e0a\u5a92\u9ad4\u7d93\u9a57", "\u5177\u64b0\u5beb\u7db2\u7d61\u5167\u5bb9\u53ca\u5546\u696d\u5408\u4f5c\u5167\u5bb9\u7684\u7d93\u9a57", "\u5275\u610f\u3001\u7a4d\u6975\uff0c\u5c0d\u4e92\u806f\u7db2\u5a92\u9ad4\u6709\u8208\u8da3"], "locations": ["Tsuen Wan Area"], "categories": ["Media & Advertising", "Media Buying", "Editorial / Journalism", "Print Media"], "post_time": "2022-01-17T10:46:29Z", "salary": {"currency": null, "max": null, "min": null, "period": "monthly", "term": null}, "salary_visible": false, "title_keywords": ["editor"], "responsibilities": [], "requirements": {"degrees": [], "majors": [], "languages": [], "language_level": [], "hard_skills": [], "soft_skills": [], "languages_combined": []}, "experience_required": {"duration": [], "field": []}}, {"job_id": "100003009051586", "location_code": "hk", "company": "Medialink Entertainment Limited", "job_title": "Distribution Manager - Content", "description": "\u8077\u8cac\n\n\n\n\u7b56\u5283\u53ca\u64b0\u5beb\u80fd\u5438\u5f15\u5927\u773e\u7684\u7db2\u7d61\u5167\u5bb9\n\u5167\u5bb9\u884c\u92b7\uff0c\u70ba\u6f5b\u5728\u9867\u5ba2\u53ca\u7522\u54c1\u5275\u9020\u6709\u50f9\u503c\u7684\u5167\u5bb9\n\u88fd\u4f5c\u5546\u696d\u5408\u4f5c\u5167\u5bb9\uff0c\u4e26\u5354\u8abf\u5ee3\u544a\u5546\u696d\u5ba2\u6236\u8981\u6c42\uff08\u5305\u62ec\u4f46\u4e0d\u9650\u65bc\u751f\u6d3b\u8cc7\u8a0a\u3001\u5065\u5eb7\u3001\u6559\u80b2\u3001\u7f8e\u5bb9\u3001\u98f2\u98df\u53ca\u71b1\u8a71\u6587\u7ae0\u7b49\uff09\n\u57f7\u884c\u5167\u5bb9\u95dc\u9375\u5b57\u7b56\u7565\uff0c\u63d0\u5347\u53ca\u50b3\u64ad\u512a\u8cea\u5167\u5bb9\n\u6309\u9700\u8981\u51fa\u5e2d\u6216\u63a1\u8a2a\u5ba2\u6236\u6307\u5b9a\u6d3b\u52d5\uff0c\u6216\u53c3\u8207\u8a2a\u554f\u53ca\u76f8\u95dc\u62cd\u651d\u5de5\u4f5c\n\n\n\u5165\u8077\u8981\u6c42:\n\n\n\n\u5927\u5b78\u6216\u4ee5\u4e0a\u5b78\u6b77\u7a0b\u5ea6\uff0c\u5b78\u79d1\u80cc\u666f\u4e0d\u62d8\n2\u5e74\u6216\u4ee5\u4e0a\u5a92\u9ad4\u76f8\u95dc\u7d93\u9a57\uff0c\u5f9e\u4e8b\u65b0\u5a92\u9ad4\u7de8\u63a1\u5de5\u4f5c\u5c07\u512a\u5148\u8003\u616e\n\u719f\u6089\u751f\u6d3b\u985e\u578b\u984c\u6750\uff0c\u4ea6\u9858\u610f\u63a5\u89f8\u4e0d\u540c\u985e\u578b\u7684\u5167\u5bb9\u984c\u6750\n\u5177\u64b0\u5beb\u5546\u696d\u5408\u4f5c\u5167\u5bb9\u7d93\u9a57\u70ba\u4f73\uff0c\u80fd\u638c\u63e1\u8207\u5546\u696d\u5ba2\u6236\u7684\u6e9d\u901a\u548c\u8981\u6c42\n\u826f\u597d\u4e2d\u6587\u8b80\u5beb\u80fd\u529b\uff0c\u61c2\u5f97\u4e2d\u6587\u8f38\u5165\u6cd5\n\u5c0d\u4e92\u806f\u7db2\u53ca\u793e\u4ea4\u5e73\u53f0\u904b\u4f5c\u6709\u57fa\u672c\u6982\u5ff5\uff0c\u80fd\u5584\u7528Google Analytics\u53ca\u76f8\u95dc\u5206\u6790\u5de5\u5177\n\u5177\u6709\u5275\u610f\u3001\u7a4d\u6975\u4e3b\u52d5\u3001\u8655\u4e8b\u7d30\u5fc3\u3001\u5bcc\u8cac\u4efb\u611f\n\u5bcc\u5718\u968a\u5408\u4f5c\u7cbe\u795e\uff0c\u4e26\u80fd\u7368\u7acb\u5b8c\u6210\u5de5\u4f5c\u8077\u8cac\n\n\n\u7b56\u5283\u53ca\u64b0\u5beb\u80fd\u5438\u5f15\u5927\u773e\u7684\u7db2\u7d61\u5167\u5bb9\n\u5167\u5bb9\u884c\u92b7\uff0c\u70ba\u6f5b\u5728\u9867\u5ba2\u53ca\u7522\u54c1\u5275\u9020\u6709\u50f9\u503c\u7684\u5167\u5bb9\n\u88fd\u4f5c\u5546\u696d\u5408\u4f5c\u5167\u5bb9\uff0c\u4e26\u5354\u8abf\u5ee3\u544a\u5546\u696d\u5ba2\u6236\u8981\u6c42\uff08\u5305\u62ec\u4f46\u4e0d\u9650\u65bc\u751f\u6d3b\u8cc7\u8a0a\u3001\u5065\u5eb7\u3001\u6559\u80b2\u3001\u7f8e\u5bb9\u3001\u98f2\u98df\u53ca\u71b1\u8a71\u6587\u7ae0\u7b49\uff09\n\u57f7\u884c\u5167\u5bb9\u95dc\u9375\u5b57\u7b56\u7565\uff0c\u63d0\u5347\u53ca\u50b3\u64ad\u512a\u8cea\u5167\u5bb9\n\u6309\u9700\u8981\u51fa\u5e2d\u6216\u63a1\u8a2a\u5ba2\u6236\u6307\u5b9a\u6d3b\u52d5\uff0c\u6216\u53c3\u8207\u8a2a\u554f\u53ca\u76f8\u95dc\u62cd\u651d\u5de5\u4f5c\n\n\u5165\u8077\u8981\u6c42:\n\n\u5927\u5b78\u6216\u4ee5\u4e0a\u5b78\u6b77\u7a0b\u5ea6\uff0c\u5b78\u79d1\u80cc\u666f\u4e0d\u62d8\n3\u5e74\u6216\u4ee5\u4e0a\u5a92\u9ad4\u76f8\u95dc\u7d93\u9a57\uff0c\u5f9e\u4e8b\u65b0\u5a92\u9ad4\u7de8\u63a1\u5de5\u4f5c\u5c07\u512a\u5148\u8003\u616e\n\u719f\u6089\u751f\u6d3b\u985e\u578b\u984c\u6750\uff0c\u4ea6\u9858\u610f\u63a5\u89f8\u4e0d\u540c\u985e\u578b\u7684\u5167\u5bb9\u984c\u6750\n\u5177\u64b0\u5beb\u5546\u696d\u5408\u4f5c\u5167\u5bb9\u7d93\u9a57\u70ba\u4f73\uff0c\u80fd\u638c\u63e1\u8207\u5546\u696d\u5ba2\u6236\u7684\u6e9d\u901a\u548c\u8981\u6c42\n\u826f\u597d\u4e2d\u6587\u8b80\u5beb\u80fd\u529b\uff0c\u61c2\u5f97\u4e2d\u6587\u8f38\u5165\u6cd5\n\u5c0d\u4e92\u806f\u7db2\u53ca\u793e\u4ea4\u5e73\u53f0\u904b\u4f5c\u6709\u57fa\u672c\u6982\u5ff5\uff0c\u80fd\u5584\u7528Google Analytics\u53ca\u76f8\u95dc\u5206\u6790\u5de5\u5177\n\u5177\u6709\u5275\u610f\u3001\u7a4d\u6975\u4e3b\u52d5\u3001\u8655\u4e8b\u7d30\u5fc3\u3001\u5bcc\u8cac\u4efb\u611f\n\u5bcc\u5718\u968a\u5408\u4f5c\u7cbe\u795e\uff0c\u4e26\u80fd\u7368\u7acb\u5b8c\u6210\u5de5\u4f5c\n\n\n\n\n\u5982\u6709\u4efb\u4f55\u76f8\u95dc\u500b\u4eba\u4f5c\u54c1\uff0c\u8acb\u5c07\u8a72\u4f5c\u54c1\u52a0\u5165\u5c65\u6b77\u5167\u4e26\u4e00\u4f75\u63d0\u4ea4\u3002\u8acb\u65bc\u6c42\u8077\u4fe1\u8a3b\u660e\u6b32\u61c9\u5fb5\u4e4b\u8077\u4f4d\u3002\u6211\u5011\u6703\u70ba\u5408\u9069\u7684\u4eba\u9078\u63d0\u4f9b\u512a\u539a\u7684\u85aa\u916c\u5f85\u9047\u53ca\u798f\u5229(\u5305\u62ec\u4e94\u5929\u5de5\u4f5c\u5468)\u3002\u61c9\u5fb5\u8005\u8acb\u6309\u300cApply Now\u300d\u6309\u9215\u4e26\u63d0\u4f9b\u5c65\u6b77\u3001\u73fe\u6642\u53ca\u8981\u6c42\u7684\u85aa\u916c\u5f85\u9047\u7b49\u8cc7\u6599\u4f5c\u8077\u4f4d\u7533\u8acb\u3002\n\n\u6240\u6709\u6536\u96c6\u7684\u500b\u4eba\u8cc7\u6599\u90fd\u6703\u56b4\u683c\u4fdd\u5bc6\u4e26\u53ea\u4f5c\u62db\u8058\u7528\u9014\u30023\u500b\u6708\u5167\u672a\u7372\u9762\u8a66\u901a\u77e5\u7684\u7533\u8acb\u8005\uff0c\u53ef\u8996\u5176\u7533\u8acb\u70ba\u4e0d\u6210\u529f\u8ad6\u3002\u53e6\u4e00\u65b9\u9762\uff0c\u5c65\u6b77\u4ea6\u53ef\u80fd\u8ddf\u64da\u516c\u53f8\u96c6\u5718\u7684\u5167\u90e8\u9700\u8981\uff0c\u9032\u884c\u5167\u90e8\u8f49\u79fb\u3002\u672a\u7372\u63a5\u7d0d\u7684\u7533\u8acb\u8cc7\u6599\u5c07\u6703\u572812\u500b\u6708\u5167\u92b7\u6bc0\u3002\u00a0", "employment_types": ["Full Time"], "selling_points": ["Min 3 years exp in media / content distribution", "Enthusiasm in Japanese Animation & Drama Series", "Familiar w/ international & Asian content markets"], "locations": ["Tsim Sha Tsui"], "categories": ["Media & Advertising", "Media Buying", "Production", "Broadcasting - TV / Radio"], "post_time": "2022-01-16T13:01:09Z", "salary": {"currency": null, "max": null, "min": null, "period": "monthly", "term": null}, "salary_visible": false, "title_keywords": ["manager"], "responsibilities": [], "requirements": {"degrees": [], "majors": [], "languages": [], "language_level": [], "hard_skills": [], "soft_skills": [], "languages_combined": []}, "experience_required": {"duration": [], "field": []}}, {"job_id": "100003009047546", "location_code": "hk", "company": "Motiva Consulting Limited", "job_title": "Digital Marketing Executive", "description": "Responsibilities :\n\nPrepare proposals and perform industry research to evaluate various negotiating positions and strategies for Content Licensing deals with new and existing clients\nAnalyze and assess results from clients and compare with market and industry data to formulate new business initiatives and business models\nParticipate in deal negotiations with clients\nUnderstand the trends in technology, digital media, content protection and consumer viewing habits\nManage and monitor the deal approval process\nPerform leadership and strategic planning on complicated deal structures, new windowing initiatives impacting Content Distribution\nBe a key and initial point of contact for members of the sales team, directing deal proposals from initiation to finalization\nResponsible for regional distribution on Animation, Drama series and Live movies\nHandle ad-hoc projects involving budget, forecast and deal track\nRequirement :\n\nMinimum 3 years solid experience in media / content distribution\nExposure in content production is a plus\nFamiliar with international and Asian content markets, major and independent program producers / distributors and Asian broadcasters\nGood command of written and spoken English and Chinese (including Mandarin)\nEnthusiasm in Japanese Animation and Drama Series is an advantage\nStrong analytical skills, sales-oriented, attention to details with strong work ethics\nProactive, independent, good team player with good working attitude\nWe offer 5-day work week, medical scheme, dental plan, discretionary bonus, and good career prospect to the right candidate. Interested parties, please send full resume with present & expected salaries and date availability to HR & Admin Department by \u201cApply Now\u201d below.\n", "employment_types": ["Full Time"], "selling_points": ["E-commerce", "Digital Marketing", "Product management"], "locations": ["Tsuen Wan Area"], "categories": ["Media & Advertising", "Media Buying", "Marketing / Public Relations", "Digital Marketing", "E-commerce", "Marketing - Brand / Product Management"], "post_time": "2022-01-14T03:25:44Z", "salary": {"currency": null, "max": null, "min": null, "period": "monthly", "term": null}, "salary_visible": false, "title_keywords": ["digital marketing executive"], "responsibilities": ["business initiatives", "strategic planning", "data", "budget", "monitor", "evaluate", "sales team", "contact", "forecast", "ad-hoc projects", "animation"], "requirements": {"degrees": [], "majors": [], "languages": ["japanese", "english", "chinese", "mandarin"], "language_level": ["advantage", "good command"], "hard_skills": ["plus", "analytical skills"], "soft_skills": ["good working attitude", "good team player", "independent", "analytical skills", "attention to details", "proactive"], "languages_combined": [{"language": "japanese", "language_level": ["advantage"]}, {"language": "english", "language_level": ["good command"]}, {"language": "chinese", "language_level": ["good command"]}, {"language": "mandarin", "language_level": ["good command"]}]}, "experience_required": {"duration": ["minimum 3 years"], "field": ["media"]}}, {"job_id": "100003009041577", "location_code": "hk", "company": "Digitas Hong Kong Limited", "job_title": "Digital Media Executive", "description": "Qualifications and Requirements:\n\n1-3 year of working experience in media buying / planning\u00a0\u00a0\nUniversity graduated in Business, Marketing, Advertising, Communications, Mathematics or related field will be an advantage\nFluent in English and Chinese, both written and spoken language skills; \u00a0\u00a0\nPassion for advertising / media\nA good team player with good communication skills and self-motivated;\nWell organized multi-tasker and able to work under pressure\nGood PC Skills, especially in Excel, PowerPoint & internet operations\nImmediately availability is preferred\n\nJob Scope:\n\nLiaise with both offline and digital media vendors on buying cost\nOptimization of media budget and provide the best value / solution for client;\nParticipate in implementing an integrated offline and digital advertising campaign from material co-ordination, booking, post campaign reporting / evaluation to monthly billing\nKeep monitoring the advertising market change, client\u2019s competitors move and the transformation of media consumption behavior\nCoodination with local and regional markets and reporting\nBuilding relationships with different working partners internally and externally\nInitiate \u201cout-of-box\u201d ideas to your client\n\nWe offer 5 days\u2019 work week, good salary package with MPF and Medical Plan with Dental Care and staff training for development.\u00a0 Interested applicants should submit resumes with expected salary and date of availability to us.\n\nFor further information about IPG Mediabrands, please visit:\u00a0http://www.ipgmediabrands.com/\n\n", "employment_types": ["Full Time", "Permanent"], "selling_points": ["World's 3rd largest integrated Communication Group", "Attractive salary and benefits; energetic culture", "Spacious, Stylish office with an outdoor balcony"], "locations": ["Kwun Tong"], "categories": ["Media & Advertising", "Account Servicing", "Media Buying", "Marketing / Public Relations", "Digital Marketing"], "post_time": "2022-01-12T04:03:41Z", "salary": {"currency": null, "max": null, "min": null, "period": "monthly", "term": null}, "salary_visible": false, "title_keywords": ["executive"], "responsibilities": ["reporting", "cost", "advertising", "ideas", "operations", "budget", "monitoring", "communication", "planning", "booking", "evaluation", "liaise with", "work under pressure"], "requirements": {"degrees": [], "majors": [], "languages": ["english", "chinese"], "language_level": ["fluent"], "hard_skills": ["excel", "pc skills", "powerpoint"], "soft_skills": ["communication skills", "good team player", "self-motivated", "passion for", "well organized", "work under pressure"], "languages_combined": [{"language": "english", "language_level": ["fluent"]}, {"language": "chinese", "language_level": ["fluent"]}]}, "experience_required": {"duration": ["1-3 year"], "field": ["media buying", "planning"]}}, {"job_id": "100003009040808", "location_code": "hk", "company": "VS Media Limited", "job_title": "Account Executive (Campaign)", "description": "Bowtie\u2019s mission is to make insurance good again and our vision is to build a category-defining health insurance company.\u00a0\n\nAs the very first virtual insurer in Hong Kong, digital is the key marketing channel for us to create engagements with our customers and drive business results. We focus on performance marketing through a mix of marketing channels and tactics to convert prospects to customers.\n\nThe Role\n\nThis is an entry-level position with great opportunities to gain in-house agency experience. You will be working closely with the team to:\n\nUnderstand our core target audience to come up with tactics for customers acquisition\nManage the acquisition campaign set up and monitoring through the platforms such as Google Analytics, Google Campaign Manager, Search Ad 360, DV360, Facebook Business Manager, and Google Tag Manager\nSupport the day-to-day operation and monitoring of the acquisition campaigns\nCompile daily reports to monitor paid channel performance to ensure campaigns are executed according to the media plan and to analyze the results\nPropose and apply optimizations on a timely basis\nWork on marketing materials (e.g. Display Banner, SEM Ad copy, Social Ad) and optimize marketing message to improve the response rate\n\nExperience and Skills\n\nDegree in Marketing, Communication or equivalent\n1-2 years of hands-on technical digital media experience\nData-driven and performance-driven with strong skills in data analysis using Excel and BI tools\nStrong project management skills, accuracy and detail-minded\nSolid technical knowledge and hands-on experience on DV360, Google Analytics, Google Campaign Manager, Search Ad 360, Facebook Business Manager and Google Tag Manager\nRelevant experience in marketing, marketing research, or insurance product-related experience will be an advantage\nStrong PC skills including MS Word, Excel, PowerPoint, and Chinese word-processing\nExcellent communication skills, and fluent in written and spoken English\n\nRequirements for Success\n\nUp-to-date knowledge of digital communication best practices, strategies, and industry standards\nExcellent time management skills and the ability to manage conflicting priorities and cope with stress\nDemonstrated ability to learn new systems quickly\nSelf-motivated, highly organized, and flexible with strong attention to detail\nAbility to work in a collaborative team, and autonomously as required\nA kind person - you know how to have fun.\nA committed team player - we work as a team, and we leave no one behind!\n\nWhat do we offer?\n\nA competitive package that is commensurate with your experience\nFlexible working arrangement (a hybrid of work from home and in-person)\nFun, cooperative, flexible, and autonomous start-up culture\nWeekly sharing sessions and regular social gatherings (including happy hours), regularly stocked pantry with healthy snacks\nEmployee discounts for both our cafe - Bow Coffee - and clinic - Bowtie & JP Health\n\nAbout Bowtie\u00a0\n\nWe are the first licensed virtual insurer (\u865b\u64ec\u4fdd\u96aa\u516c\u53f8) in Hong Kong and we are building one of the most iconic, category-defining health insurance companies in Asia.\n\nWe believe that insurance is fundamentally good, and we are here to bring the good back through our passionate, innovative, and customer-centric team.\u00a0We take pride in bringing our deep domain expertise and our own proprietary modern technology into Hong Kong.\u00a0\n\nAs we grow, we're always looking for highly dynamic, hands-on, and passionate talent to join our team. If you are looking for a rewarding career where you will grow together with strong talents from different backgrounds and build products and services that bring a positive impact on the lives of millions of people in Hong Kong / Asia, apply to our opening today!\n\nInformation collected will be treated in strict confidence and used solely for recruitment purposes.\n\nThe company will retain all applications no longer than 24 months of which will be destroyed thereafter.\n\nWe are an equal opportunity employer. We do not discriminate on the basis of race, sex, disability, or family status in the employment process.", "employment_types": ["Full Time", "Permanent"], "selling_points": ["Digital Media, Campaign, Advertisement", "Account Servicing", "Social media, Influencer landscape,"], "locations": ["Kwun Tong"], "categories": ["Media & Advertising", "Account Servicing", "Media Buying", "Strategic Planning"], "post_time": "2022-01-12T03:23:52Z", "salary": {"currency": null, "max": null, "min": null, "period": "monthly", "term": null}, "salary_visible": false, "title_keywords": ["account executive"], "responsibilities": ["management", "daily reports", "data", "monitoring", "monitor", "systems", "communication", "data analysis", "project management", "marketing research", "plan", "sem", "marketing materials", "facebook", "insurance", "day-to-day operation"], "requirements": {"degrees": ["degree"], "majors": ["marketing"], "languages": ["english", "chinese"], "language_level": ["excellent", "fluent"], "hard_skills": ["google analytics", "excel", "bi", "no", "chinese word-processing", "fun", "analysis", "powerpoint", "make", "project management", "sem", "facebook", "focus", "pc skills", "ms word"], "soft_skills": ["detail-minded", "communication skills", "self-motivated", "organized", "flexible", "work as a team", "time management skills", "project management skills", "timely", "collaborative", "communication", "committed", "hands-on", "team player", "attention to detail", "focus", "driven"], "languages_combined": [{"language": "english", "language_level": ["fluent", "excellent"]}, {"language": "chinese", "language_level": []}]}, "experience_required": {"duration": ["1-2 years"], "field": ["research", "agency", "related", "marketing", "digital media", "relevant experience", "business", "insurance"]}}, {"job_id": "100003009038333", "location_code": "hk", "company": "Optimum Media Direction", "job_title": "Media Executive (Advertising & Media Field)", "description": "\u00a0Job Responsibilities:\u00a0\n\nAssist the team in developing and implementing an integrated on/off advertising campaign\nHelp on competitive data generation, analysis and presentation\nPrepare evaluation of media opportunities, keep tracks of market trends by using industry tools and other research methods\nPrepare media plan, budget summary and campaign follow up\nActively participate in brain-storming for big ideas and consumer insights\nMaintain and strengthen relationships with industry partners.\n\n\u00a0Job Requirements:\u00a0\n\nUniversity degree in business, marketing, advertising, communications, or a related field\n0-1 year of media planning/buying experience preferably (fresh graduates are also welcomed)\nMust be well organized and have strong quantitative/analytical skills\nAble to build relationship internally and externally\nAbility to manage multi-task well in a fast-paced environment and a team player.\nMust be numerate and have strong attention to detail\nPassionate about building a career in advertising field\nFluent written and spoken English and Chinese is a must\nProficiency in Word, Excel and PowerPoint\n\nWorking Location: Cyberport (\u6578\u78bc\u6e2f), Hong Kong\n\nWe offer a 5-day week of work, group medical & life insurance coverage and free shuttle bus to the right candidate. Interested parties please send your application letter and resume to click the \"Apply Now\" at the bottom.\n\nAll information collected will be used for recruitment only and treated in strict confidence. We will retain the personal data of unsuccessful applicants for future recruitment purpose for a maximum period of 2 years.", "employment_types": ["Full Time", "Permanent"], "selling_points": ["Free Shuttle Bus & Free Breakfast", "Birthday, Family Day & Self-Love Day Leave", "5-Day Work Week"], "locations": ["Pok Fu Lam"], "categories": ["Media & Advertising", "Account Servicing", "Media Buying", "Others"], "post_time": "2022-01-11T06:34:00Z", "salary": {"currency": null, "max": null, "min": null, "period": "monthly", "term": null}, "salary_visible": false, "title_keywords": ["executive"], "responsibilities": ["advertising", "ideas", "consumer insights", "data", "analysis", "budget", "developing", "maintain", "plan", "evaluation"], "requirements": {"degrees": ["university degree"], "majors": ["business", "communications", "marketing"], "languages": ["english", "chinese"], "language_level": ["fluent"], "hard_skills": ["excel", "word", "powerpoint", "analytical skills"], "soft_skills": ["multi-task", "fast-paced environment", "well organized", "analytical skills", "attention to detail", "team player", "passionate about"], "languages_combined": [{"language": "english", "language_level": ["fluent"]}, {"language": "chinese", "language_level": ["fluent"]}]}, "experience_required": {"duration": ["0-1 year"], "field": ["media", "planning"]}}, {"job_id": "100003009046294", "location_code": "hk", "company": "XGD Media Limited", "job_title": "Advertising Account Executive / Account Manager / Sales Manager", "description": "We are currently searching for an ambitious\u00a0Account Executive / Account Manager / Sales Manager with a strong interest in the outdoor advertising industry. You will find yourself in a fun working environment with opportunities to interact with multiple major brands while helping the company to achieve company sales targets. We value your opinions and you will be constantly challenged to think outside of the box to generate new ideas across multiple channels.\u00a0\n\nResponsibilities:\n\nSolicit new businesses for the Company\u2019s outdoor media sales\nEnsure our service commitments are fulfilled and meet customers' requirements\nAchieve company assigned sales target\nFollow up on campaign logistics and provide post campaign services to clients\nFrequently report newest market intelligence to Company\u00a0\u00a0\n\n\u00a0Desired Skills/Qualifications:\n\nUniversity graduate is preferred\nFresh Graduates welcome\nProactive & Entrepreneurial - eager to help the company grow!\nIndependent, organized and able to deliver under pressure\u00a0\nExcellent communication/interpersonal skills\n\nGood account servicing and management skill\u00a0\nProficient in Chinese (Cantonese & Mandarin) and English\u00a0\nFresh graduates or candidates with less experience will be considered for junior positions\u00a0\n\nIf you are an awesome person and most importantly, you want to build something you can call your own, it is time you join our extremely passionate founding team and apply now!\u00a0\n\nWe offer a competitive package with attractive commission schemes with many additional benefits. All personal data provided by job applications will be used strictly for recruitment purposes only.\u00a0\n\nTo apply: Please email us\u00a0with your CV and salary expectations.\u00a0", "employment_types": ["Full Time", "Permanent"], "selling_points": ["Fresh Graduates welcome.", "Proactive & Entrepreneurial", "Competitive Salary & Great Commission Scheme"], "locations": ["Central"], "categories": ["Media & Advertising", "Account Servicing", "Media Buying", "Sales, CS & Business Devpt", "Account Servicing"], "post_time": "2022-01-13T10:21:02Z", "salary": {"currency": null, "max": null, "min": null, "period": "monthly", "term": null}, "salary_visible": false, "title_keywords": ["account executive", "account manager", "sales manager"], "responsibilities": ["management", "advertising", "ideas", "sales target", "communication", "logistics", "report"], "requirements": {"degrees": ["university graduate"], "majors": [], "languages": ["cantonese", "english", "chinese", "mandarin"], "language_level": ["proficient"], "hard_skills": ["fun"], "soft_skills": ["passionate", "organized", "independent", "under pressure", "communication", "interpersonal skills", "proactive"], "languages_combined": [{"language": "cantonese", "language_level": ["proficient"]}, {"language": "english", "language_level": ["proficient"]}, {"language": "chinese", "language_level": ["proficient"]}, {"language": "mandarin", "language_level": ["proficient"]}]}, "experience_required": {"duration": [], "field": []}}, {"job_id": "100003009037981", "location_code": "hk", "company": "IPG Mediabrands (HK) Limited", "job_title": "Media Executive (Buying & Operation Team)", "description": "Responsibilities:\n\nResponsible for supporting all business activities of assigned brand with focus on ecommerce business.\nManage the daily operations of the website and e-commerce platform functions including but not limited to product listing & upload, promotion launch, campaign management, daily report, inventory planning & logistics, content preparation and after-sales service support.\nAnalyze the online sales performance and roll out effective digital marketing activities and promotion to reach sales target.\nDrive content creation including banners, copyrighting, layout design to promote brand on website and different social media platforms.\nResearch and identify new potential partnerships and e-commerce opportunities.\nCoordinate marketplace partnership and build relationship.\nPrepare sales, traffic, promotion reports and competitor analysis regularly.\nPerform ad-hoc duties as assigned.\n\nRequirements:\n\nDegree or above in E-commerce, marketing or related discipline.\n3-4 years' relevant experience preferably in retail/ fashion industry.\nProficient PC skills in MS Excel, Word, PowerPoint and Chinese work processing.\nKnowledge in design software such as AI, PS is preferred.\nFluent in spoken and written English and Mandarin.", "employment_types": ["Full Time"], "selling_points": [], "locations": ["Quarry Bay"], "categories": ["Media & Advertising", "Account Servicing", "Media Buying", "Marketing / Public Relations", "Marketing - Marketing Communication"], "post_time": "2022-01-11T04:28:56Z", "salary": {"currency": null, "max": null, "min": null, "period": "monthly", "term": null}, "salary_visible": false, "title_keywords": ["executive"], "responsibilities": ["layout design", "social media platforms", "website", "banners", "content preparation", "sales performance", "sales target", "prepare sales", "reports", "business activities", "inventory planning & logistics", "promotion launch", "daily operations", "digital marketing", "ad-hoc duties", "campaign management", "product listing & upload", "analysis", "coordinate", "after-sales service", "daily report", "e-commerce platform"], "requirements": {"degrees": ["degree or above"], "majors": ["marketing", "e-commerce"], "languages": ["english", "chinese", "mandarin"], "language_level": ["fluent", "proficient"], "hard_skills": ["e-commerce", "processing", "ai", "word", "powerpoint", "ms excel", "pc skills"], "soft_skills": [], "languages_combined": [{"language": "english", "language_level": ["fluent"]}, {"language": "chinese", "language_level": ["proficient"]}, {"language": "mandarin", "language_level": ["fluent"]}]}, "experience_required": {"duration": ["3-4 years"], "field": ["retail", "relevant experience"]}}, {"job_id": "100003009041986", "location_code": "hk", "company": "Guru Online", "job_title": "Senior Digital Performance Executive", "description": "What you get:\u00a0\n\nJob security:\u00a0 Part of Publicis Groupe - world's 3rd largest, fully\u00a0integrated communications group\u00a0with offices across 100 countries, employing over 80,000 staffs globally\nExcellent office environment - conveniently located, spacious, stylish office with an outdoor terrace for some fresh air\nLearning opportunity:\u00a0 Chance to work with, and learn the management philosophies from a well-structured organisation\nBirthday leave\n5-day work-week\nGroup medical & life insurance coverage\nFun & energetic company culture\n\nThe Digital Executive will work closely supporting the PPC business with the day-to-day management of paid search campaigns. This person will report directly to the Digital Manager and is responsible for tracking, analyzing and executing paid search strategies, ensuring that all deliverables are executed on time and produce a high standard of quality for all client deliverables. The Digital Executive will acquire in-depth paid search knowledge, while utilizing the creativity, attention to detail and analytical skills needed to grow a career within the agency.\n\nResponsibilities\n\nHolistic SEM program management including keywords development, ad creative and strategy, trafficking recommendations, optimizing program towards key business goals and reporting\nActively participating in meetings and proactively documenting takeaways and next steps\nAssimilating data from multiple sources, compiling the information and drawing actionable conclusions that can be measured and reported\nBid strategy optimization and testing. Daily checks on program KPIs, thresholds and campaign budget caps. Ongoing management of budget and pacing.\nTranslating campaign/client goals into SEM tactics and effectively executing those tactics against the client\u2019s strategy\nImplementing Paid Search best practices, providing refinement and optimization recommendations and proactively identifying campaign execution issues\nMonitoring emerging industry trends and summarizing them for internal and external stakeholders\nLeveraging and developing proficiencies with SEM platforms, tools and resources\nDeveloping campaign ad copy (text-based titles and descriptions or feed-based images) and tagging traffic or creative elements to sites per creative rotation instructions\nHelp develop performance forecasts, budget allocations and providing data-based rationale for these recommendations\nCollaborating with both clients and internal cross-channel colleagues by providing reporting as requested in a concise and timely fashion\nFostering relationship with internal teams, external partners and clients\n\nCompetencies\n\nFresh graduates with a relevant degree such with a concentration such as Business Systems Management and Information Management, with the passion and interest in the digital media business\n1 or more years of paid search experience, with knowledge of bid management platforms a plus\nStrong ability to work closely with your team to problem solve, prioritize tasks, and manage time effectively\nA detail-oriented approach and a desire to achieve objectives accurately\nSolid quantitative and research skills, and proven data interpretation capability\nFamiliarity with the digital advertising space and a passion for growing that interest into a career\nStrong communication skills \u2013 you\u2019re clear and thorough, yet concise\nA passion for building relationships and a desire to contribute to team building and event planning\nExudes confidence and won\u2019t hesitate to connect with\u00a0colleagues\u00a0throughout the organization to get the job done right\nCandidates with more experience may be considered as Digital Specialist\u00a0\n\n\nAll information collected will be solely used for recruitment purposes only.", "employment_types": ["Full Time", "Permanent"], "selling_points": ["monitoring campaign delivery results and KPI", "Fun, young and joyful environment", "attractive incentive plan"], "locations": ["Kwun Tong"], "categories": ["Media & Advertising", "Media Buying", "Strategic Planning", "Marketing / Public Relations", "Digital Marketing"], "post_time": "2022-01-12T04:59:50Z", "salary": {"currency": null, "max": null, "min": null, "period": "monthly", "term": null}, "salary_visible": false, "title_keywords": ["performance executive"], "responsibilities": ["business goals", "data", "budget", "quality", "communication", "advertising", "teams", "developing", "testing", "day-to-day management", "develop", "kpis", "report", "reporting", "management", "monitoring", "executing", "tracking", "systems", "recruitment", "sem", "insurance", "planning"], "requirements": {"degrees": ["degree"], "majors": ["business"], "languages": [], "language_level": [], "hard_skills": ["sem", "plus", "fun", "analytical skills"], "soft_skills": ["communication skills", "confidence", "creative", "responsible", "research skills", "problem solve", "passion for", "timely", "prioritize", "analytical skills", "detail-oriented", "clear", "learning", "thorough", "organisation", "structured", "attention to detail", "energetic"], "languages_combined": []}, "experience_required": {"duration": [], "field": ["digital", "management"]}}, {"job_id": "100003009037903", "location_code": "hk", "company": "PHD Limited", "job_title": "Digital Operation Executive (Advertising & Media Field)", "description": "Responsibility:\n\nHandle multiple client projects such as video production, influencer activation, social media management, and other digital marketing campaigns;\nProvide creative inputs in social media content and campaign planning;\nManage timeline to ensure smooth project execution;\nPrepare proposals and support new clients pitching;\nLiaise with and provide creative briefings to vendors, designers, internal and external parties;\nMonitor project implementation and performance against KPIs;\nCompile regular and post-campaign reports for project performance evaluations;\nStay alert to industry happenings and able to share insights;\u00a0\n\nRequirement:\u00a0\n\nDegree in Media, Marketing, Communications or related discipline;\nMinimum 1 year experience on digital/social media management or other relevant work experience;\nDemonstrate strong communication and presentation skills;\nFamiliar with the social media & influencer landscape and practices in Hong Kong;\u00a0\nProficiency in written and spoken English and Chinese;\u00a0\nProactive, passionate, and a detail-minded team player;\nGood multi-tasking skills, willing to work under pressure and tight schedules;\nExperience working with social listening and social media management tools is a plus; \u00a0\nImmediate availability is highly preferred;\nCandidate with more experience will be considered as Senior Account Executive;\n\nAll personal data collected will be kept confidential and used for recruitment purpose only.", "employment_types": ["Full Time", "Permanent"], "selling_points": ["Free Shuttle Bus & Free Breakfast", "Birthday, Family Day & Self-Love Day Leave", "5-Day Work Week"], "locations": ["Pok Fu Lam"], "categories": ["Media & Advertising", "Account Servicing", "Media Buying", "Others"], "post_time": "2022-01-11T04:11:59Z", "salary": {"currency": null, "max": null, "min": null, "period": "monthly", "term": null}, "salary_visible": false, "title_keywords": ["operation executive"], "responsibilities": ["social media", "management", "video production", "digital marketing campaigns", "internal and external parties", "monitor", "implementation", "social media content", "reports", "liaise with", "kpis", "planning"], "requirements": {"degrees": ["degree"], "majors": ["marketing", "communications"], "languages": ["english", "chinese"], "language_level": ["proficiency"], "hard_skills": ["plus"], "soft_skills": ["detail-minded", "passionate", "communication", "presentation skills", "multi-tasking skills", "team player", "proactive", "work under pressure"], "languages_combined": [{"language": "english", "language_level": ["proficiency"]}, {"language": "chinese", "language_level": ["proficiency"]}]}, "experience_required": {"duration": ["minimum 1 year"], "field": ["digital", "management", "social media"]}}, {"job_id": "100003009034624", "location_code": "hk", "company": "GroupM Limited", "job_title": "GroupM | Media Planner/ Senior Planner", "description": "Being a crucial member of the team, the successful candidate will be responsible for implementing media placements, liaising with client, creative agency, and media vendor to make campaign GO LIVES. We also aim to provide best services and value to our client.\nTraining on negotiation process and usage on proprietary tools will be provided. This entry-level opportunity will kick-start your career in media and provide a platform to partner with the world\u2019s leading consumer brands.\n\nQualifications and Requirements:\n\nPassion for advertising / media\nForm 7 / Diploma / University graduated in any discipline;\nFluent in English and Chinese, both written and spoken language skills; \u00a0\u00a0\nDetail oriented, organised and sensitive to numbers;\nA good team player with good communication skills and self-motivated;\n\nJob Scope:\n\nLiaise with both traditional and digital media vendors on buying cost\nOptimisation of media budget and provide the best value / solution for client;\nParticipate in implementing an integrated traditional and digital advertising campaign from material co-ordination, booking, post campaign reporting / evaluation to monthly billing\nKeep monitoring the advertising market change, client\u2019s competitors move and the transformation of media consumption behavior\nInitiate \u201cout-of-box\u201d ideas to your client\n\nWe offer 5 days\u2019 work week, good salary package with MPF and Medical Plan with Dental Care and staff training for development.\u00a0 Interested applicants should submit resumes with expected salary and date of availability to our email address\u00a0(please indicate the relevant job position: Media Executive Buying & Operation Team)\n\nFor further information about IPG Mediabrands, please visit:\u00a0http://www.ipgmediabrands.com/\n\n", "employment_types": ["Full Time", "Permanent"], "selling_points": [], "locations": ["Quarry Bay"], "categories": ["Media & Advertising", "Account Servicing", "Media Buying"], "post_time": "2022-01-10T03:49:28Z", "salary": {"currency": null, "max": null, "min": null, "period": "monthly", "term": null}, "salary_visible": false, "title_keywords": [], "responsibilities": ["reporting", "cost", "advertising", "ideas", "budget", "monitoring", "liaising with", "communication", "booking", "evaluation", "liaise with", "negotiation process"], "requirements": {"degrees": ["diploma"], "majors": [], "languages": ["english", "chinese"], "language_level": ["fluent"], "hard_skills": ["make", "go", "vendor"], "soft_skills": ["communication skills", "good team player", "self-motivated", "negotiation", "responsible", "passion for", "detail oriented", "organised", "sensitive to numbers", "creative"], "languages_combined": [{"language": "english", "language_level": ["fluent"]}, {"language": "chinese", "language_level": ["fluent"]}]}, "experience_required": {"duration": [], "field": []}}, {"job_id": "100003009043352", "location_code": "hk", "company": "Morgan McKinley", "job_title": "Digital Media Planner, APAC - Luxury Brand (MNC) - 25k", "description": "Planning\n\n\n\nAssist the Manager to develop media strategy, channel/ platform recommendations and prepare the detailed media flow-plan;\nLeverage available planning tools and liaise with media owners for proposals;\nEngage clients on day to day operations, media trend updates and various campaign reports on local/regional/global levels.\n\nBuying\n\n\n\nNegotiate with media owners for better rates and value adds;\nBook ads - both managed service and self-service across various platforms;\nLiaise with media vendors & creative agencies for material submission;\nDigital ad ops (campaign set up on self-serve platforms, tagging of ads and client's site, ensure ads are properly served and tags are firing);\nGlobal ops (adhering and following globally set parameters and campaign execution processes while also guiding others);\nOversee all performance across channels (Search, Social, Programmatic etc.);\nMonitor and optimize performance during campaign period across platforms such as Google Adwords, Facebook, LinkedIn etc.\nWeekly digital reporting, end of campaign reporting and reconciliation of final costs for finance billings.\n\nQualifications\n\n\n1 - 3 years' of digital media experience\nMeticulous, good with numbers and able to organise and prioritise tasks and work under tight timelines\nResilient to change and willing to keen to learn new skills\nStrong communication skills, both written and verbal, with internal and external parties\nReady to take up initiatives and ownership of projects\nPlay well with others and are a team player\nGood command of English and Chinese", "employment_types": ["Full Time", "Permanent"], "selling_points": ["2 years media planning/ digital advertising exp", "Immediately available is preferred", "Top tier Luxury brand"], "locations": ["Not Specified"], "categories": ["Media & Advertising", "Account Servicing", "Media Buying", "Marketing / Public Relations", "Digital Marketing"], "post_time": "2022-01-12T10:57:38Z", "salary": {"currency": "HKD", "max": 24999, "min": 20000, "period": "monthly", "term": null}, "salary_visible": true, "title_keywords": [], "responsibilities": ["reporting", "day to day operations", "billings", "internal and external parties", "monitor", "develop", "communication", "reports", "plan", "liaise with", "facebook", "costs", "planning"], "requirements": {"degrees": [], "majors": [], "languages": ["english", "chinese"], "language_level": ["good command"], "hard_skills": ["adwords", "facebook"], "soft_skills": ["meticulous", "communication skills", "keen", "prioritise", "team player", "creative", "detailed"], "languages_combined": [{"language": "english", "language_level": ["good command"]}, {"language": "chinese", "language_level": ["good command"]}]}, "experience_required": {"duration": ["1 - 3 years"], "field": ["digital media"]}}, {"job_id": "100003009041249", "location_code": "hk", "company": "FiveStones Limited", "job_title": "Analytics Specialist", "description": "What You Will Be Doing:\n\n\u00a0Keeping up to date with industry news and developments\n\u00a0In charge individual account servicing to clients / brands & fulfil clients / brands different requirements about their campaigns;\nHave an understanding of the various digital media channels (Social Media, SEM, Display, Programmatic) and the potential for them in your clients marketing activities\nOperating paid-media platforms including social ad platforms, Facebook, Instagram, Google ad platform as well as some self-serve programmatic platform.\nAccount management and monitoring campaign delivery results and KPI\nStart building an understanding of the client\u2019s business and digital marketing objectives\nHelp in preparation for and attend client reviews as required\nProvide regular results analysis, reporting and recommendations\nKeep clients and account team updated on the status of account activities\nExcellence in Client Service and\u00a0effectively manage client expectations\n\nWhat You Need for this Position\u00a0 \u00a0\n\n2 years experience in\u00a0digital performance, preferably in\u00a0managing online advertising and social media projects;\nExperience in developing advance Excel, Word and Power Point presentation.\nExcellent knowledge and passion for digital\nStrong client-facing skills: understanding client needs, maintaining relationships, building partnerships\nStrong numerical skills and attention to detail\nAble to work in high pressure environment and resolve client issues\nAble to work collaboratively across teams\nDemonstrates honesty and integrity\nFluent in English and Cantonese\n\nBenefits We Offer:\n\n5 days\u2019\u00a0work\nQuarterly Performance Bonus\nMedical Coverage including Dental\nFlexible Working Hours\nOvertime\u00a0Meal\u00a0and Transportation allowance\nBirthday, Wedding, Graduation and other special leaves\nFun, young and joyful environment\u00a0\n\nBe a GURU, be our next great hire.\u00a0APPLY NOW!\u00a0\n\nInterested parties\u00a0please send a cover letter stating your expected salary, resume and\u00a0a full set of your portfolio\u00a0to us.\u00a0\n\n*All information will be treated as confidential and used solely for recruitment purposes.", "employment_types": ["Full Time"], "selling_points": ["Higher Diploma & Fresh Grad are welcome", "Experience in CSS, HTML", "Proactive and self-motivated to work"], "locations": ["Kowloon Bay"], "categories": ["Media & Advertising", "Media Buying", "Marketing / Public Relations", "Digital Marketing"], "post_time": "2022-01-12T03:38:52Z", "salary": {"currency": null, "max": null, "min": null, "period": "monthly", "term": null}, "salary_visible": false, "title_keywords": ["specialist"], "responsibilities": ["social media", "management", "reporting", "maintaining", "analysis", "monitoring", "teams", "developing", "media channels", "digital marketing", "sem", "facebook", "online advertising"], "requirements": {"degrees": [], "majors": [], "languages": ["cantonese", "english"], "language_level": ["fluent"], "hard_skills": ["excel", "analysis", "word", "numerical skills", "sem", "power point", "facebook"], "soft_skills": ["passion for", "integrity", "attention to detail", "client-facing skills", "presentation"], "languages_combined": [{"language": "cantonese", "language_level": ["fluent"]}, {"language": "english", "language_level": ["fluent"]}]}, "experience_required": {"duration": ["2 years"], "field": ["digital", "advertising", "developing", "social media"]}}, {"job_id": "100003009027059", "location_code": "hk", "company": "PHD Limited", "job_title": "Media Executive (Advertising & Media Field)", "description": "The Role\n\nReporting to the Digital Marketing Director, this position requires a candidate who has a passion for digital media and Ad-Tech industry. You will be growing quickly, learning how the ecosystem of digital media and data operates in the Hong Kong market from the one of the biggest agencies in the region.\n\n\n\nResponsibilities\n\nAd Trafficking, including 3rd party ad serving (Google Campaign Manager), website tracking, brand safety and associated technologies.\nConversion Tag tracking for different digital platform.\nGathering data through various third party platforms and analytics tools.\nData management including dashboards.\nData QA and analysis on media/performance trends, identify insights for campaign strategy/ planning.\n\nKey Requirements\n\nPreferably 1-2 years experience with digital marketing agency.\u00a0 Fresh graduate will also be considered.\nUnderstanding of Digital Media buying, including IO, DSP, Social Media, Search.\nStrong analytical skills, highly numerate and comfortable with data processing and interpretation.\nGood team player with excellent time-management and strong organizational skills to handle multiple projects.\nWork under pressure and meet tight deadline.\nGood in communications skills.\nExcellent command of English and Cantonese; written and spoken\nStrong attention to detail and problem-solving skills\nEagerness to learn and collaborate with others\nOpenness to change and willingness to work through challenges\nProficiency in Microsoft Office (Words, Excel and PowerPoint) is a must.\nA bachelor's degree, preferably with combined studies in Information Systems and Media, or related business field.\n\nWorking Location: Cyberport (\u6578\u78bc\u6e2f), Hong Kong\u00a0\n\nWe offer a 5-day work of week, group medical & life insurance coverage to the right candidate. Interested parties please send your application letter and resume with current and expected salary\u00a0by clicking the \"Apply Now\" button.\n\nAll information collected will be used for recruitment only and treated in strict confidence. We will retain the personal data of unsuccessful applicants for future recruitment purpose for a maximum period of 2 years.", "employment_types": ["Full Time", "Permanent"], "selling_points": ["Free Shuttle Bus & Free Breakfast", "Birthday, Family Day & Self-Love Day Leave", "5-Day Work Week"], "locations": ["Pok Fu Lam"], "categories": ["Media & Advertising", "Account Servicing", "Media Buying", "Others"], "post_time": "2022-01-06T09:04:02Z", "salary": {"currency": null, "max": null, "min": null, "period": "monthly", "term": null}, "salary_visible": false, "title_keywords": ["executive"], "responsibilities": ["analytics tools", "management", "data", "analysis", "website", "digital platform", "planning", "third party", "tracking"], "requirements": {"degrees": ["degree", "bachelor", "fresh graduate"], "majors": ["business"], "languages": ["cantonese", "english"], "language_level": ["excellent"], "hard_skills": ["excel", "io", "words", "microsoft office", "powerpoint", "analytical skills", "problem-solving skills", "processing"], "soft_skills": ["organizational skills", "good team player", "analytical skills", "willingness to work", "meet tight deadline", "attention to detail", "problem-solving skills", "work under pressure"], "languages_combined": [{"language": "cantonese", "language_level": ["excellent"]}, {"language": "english", "language_level": ["excellent"]}]}, "experience_required": {"duration": ["1-2 years"], "field": ["agency", "digital marketing"]}}, {"job_id": "100003009039601", "location_code": "hk", "company": "Ginger Advertising Limited", "job_title": "Advertising Coordinator (Media)", "description": "Job Responsibilities:\n\nPerform from campaign planning to buying implementation, performance optimization and post-campaign analysis to meet client\u2019s communication needs\nPrepare and maintain budget plans and flowcharts, deliver media evaluation and presentation decks, generate and conclude market analysis\nWork in a team to develop integrated strategic communication plan to strive for best clients\u2019 interest\nExplore new opportunity and applicability of media vehicles actively with media vendors and technology partners\nBuild accountable and trustworthy relationship with different stakeholders\n\n\u00a0Job Requirements:\u00a0\n\nUniversity degree in business, marketing, advertising, communications, or a related field\n0-1 year of media planning/buying experience preferably (fresh graduates are also welcomed)\nImportantly, must be passionate and with full commitment to work\nAbility to manage multi-task well in a fast-paced environment\nAbility to develop strong relationship, both internally and externally, and feel comfortable interacting with people from different disciplines and cultures\nMust be well organized and have strong quantitative/analytical skills\nMust be numerate and have strong attention to details\nQuick learner and self-motivated to learn new skillset\nFluent written and spoken English and Chinese is a must\nProficiency in Word, Excel, PowerPoint and data processing\n\nWorking Location: Cyberport (\u6578\u78bc\u6e2f), Hong Kong\u00a0\n\nWe offer a 5-day work of week, group medical & life insurance coverage to the right candidate. Interested parties please send your application letter and resume with current and expected salary\u00a0by clicking the \"Apply Now\" button.\n\nAll information collected will be used for recruitment only and treated in strict confidence. We will retain the personal data of unsuccessful applicants for future recruitment purpose for a maximum period of 2 years.", "employment_types": ["Full Time"], "selling_points": [], "locations": ["Tsim Sha Tsui"], "categories": ["Media & Advertising", "Media Buying", "Strategic Planning", "Marketing / Public Relations", "Digital Marketing"], "post_time": "2022-01-11T10:12:06Z", "salary": {"currency": null, "max": null, "min": null, "period": "monthly", "term": null}, "salary_visible": false, "title_keywords": ["coordinator"], "responsibilities": ["analysis", "budget", "implementation", "develop", "communication", "maintain", "market analysis", "plan", "evaluation", "plans", "planning"], "requirements": {"degrees": ["university degree"], "majors": ["business", "communications", "marketing"], "languages": ["english", "chinese"], "language_level": ["fluent"], "hard_skills": ["excel", "word", "powerpoint", "analytical skills", "processing"], "soft_skills": ["passionate", "self-motivated", "multi-task", "fast-paced environment", "well organized", "quick learner", "analytical skills", "attention to details"], "languages_combined": [{"language": "english", "language_level": ["fluent"]}, {"language": "chinese", "language_level": ["fluent"]}]}, "experience_required": {"duration": ["0-1 year"], "field": ["media", "planning"]}}, {"job_id": "100003009034066", "location_code": "hk", "company": "Webs s'up Production Company Limited", "job_title": "Media Buyer/Planner", "description": "5-Day Work Week\n\nJob Requirements:\nMatriculated or above\nAt least 2-year working experience in related field\nFamiliar with Multimedia & Digital Marketing (ad buy and ad placement, include FB Ad Manager, GDN, Google Keyword, YouTube ad, etc.)\nGood command of written & spoken English & Mandarin\nProficient in computer skill\nCommunicative, Self-motivated and aggressive", "employment_types": ["Full Time", "Permanent"], "selling_points": ["Competitive salary with attractive Talent Benefits", "Five-day work week in Kowloon Bay Office", "Media buying/planning experience"], "locations": ["Kowloon Bay"], "categories": ["Media & Advertising", "Media Buying", "Marketing / Public Relations", "Digital Marketing"], "post_time": "2022-01-10T02:34:35Z", "salary": {"currency": null, "max": null, "min": null, "period": "monthly", "term": null}, "salary_visible": false, "title_keywords": [], "responsibilities": ["digital marketing"], "requirements": {"degrees": [], "majors": [], "languages": ["english", "mandarin"], "language_level": ["good command"], "hard_skills": ["computer skill", "multimedia"], "soft_skills": ["self-motivated"], "languages_combined": [{"language": "english", "language_level": ["good command"]}, {"language": "mandarin", "language_level": ["good command"]}]}, "experience_required": {"duration": ["at least 2-year"], "field": ["related"]}}, {"job_id": "100003009036193", "location_code": "hk", "company": "BuzzFever", "job_title": "Project/Account Executive (Digital Marketing)", "description": "We\u2019re Webs S\u2019 up, a digital consultancy with a singular mission \u2013 We Enhance Engagement.\n\n\n\nJoin us to become a Webs S\u2019 up family member!\n\nYou will be entitled to a competitive salary and attractive staff benefits including:\n\nAnnual leave, paid sick leave, compensation leave, marriage leave, maternity leave, paternity leave and compassionate leave\nFive-day work week in Kowloon Bay Office\nComprehensive medical and dental coverage\nProfessional training and career advancement opportunities\nFriendly working environment\u00a0and work-life balance culture\n\n\nWhat do you need to do?\n\nOperate Digital and Social Media placements with planning teams, media vendors and clients in buying executions on a day-to-day basis\nNegotiate the best price, quality placement of advertisements and explore new opportunities for your clients\nExplore new channels/groups in Facebook/Telegram/Forums, etc.\nAd setup and budget pacing monitoring for biddable media platforms e.g. social and programmatic\nManage 3rd party social page cost negotiation and follow through the write-up process with vendor and client\nApply progress of measures on the whole journey of media plan implementation, from material coordination, media bookings, ad monitoring, post-campaign reporting, placement reports to monthly billings\n\n\u00a0\nWhat do you need to have?\n\nDiploma or University degree in business, marketing, advertising, communications, or a related field\nAt least 1 year of working experience in media buying/planning experience\nStrong ability in handling multi-tasking roles, responsible and attentive to numberings and details\nProven skill in managing direct relationships with vendors and clients, and cross-functional team's collaboration\nProactive team player with excellent interpersonal skills & problem-solving mindset\nExcellent written and oral communication skills in Cantonese and English, Mandarin is a plus\n\nReady to join us? Apply now to submit your resume & expected salary to us!\n\n(Personal data will be used for Webs s\u2019 up Production Limited recruitment purposes only. We will retain the applications of candidates for no more than 12 months.)", "employment_types": ["Full Time"], "selling_points": ["Project management", "digital marketing", "Project/Account Executive"], "locations": ["Kwai Hing"], "categories": ["Media & Advertising", "Media Buying", "Strategic Planning", "Marketing / Public Relations", "Digital Marketing"], "post_time": "2022-01-10T09:36:42Z", "salary": {"currency": null, "max": null, "min": null, "period": "monthly", "term": null}, "salary_visible": false, "title_keywords": ["account executive", "digital marketing"], "responsibilities": [], "requirements": {"degrees": [], "majors": [], "languages": [], "language_level": [], "hard_skills": [], "soft_skills": [], "languages_combined": []}, "experience_required": {"duration": [], "field": []}}, {"job_id": "100003009043010", "location_code": "hk", "company": "Mediacom Limited", "job_title": "MediaCom | Senior Manager", "description": "Job Description:\n\nAssist manager to prepare and execute digital advertising campaigns;\nWork closely with vendors and internal teams to plan, develop and execute digital marketing projects;\nMeet and liaise with clients to ensure client satisfaction;\nCoordinate with art directors and social media editors to develop\u00a0social media contents;\u00a0\nResponsible for committed timelines and deliverable throughout projects;\nPrepare advertising plans for search, display, video and social media ads;\nOther ad-hoc assignments.\n\n\nRequirements:\n\nStrong Responsibility in handling projects;\u00a0\nHave experience in managing one or more of below digital marketing channels is preferred: Facebook, Instagram, KOL,\u00a0micro influencer, video production, Google Adwords or Forum;\n1 - 3 years working experience in an agency or in a marketing position;\nGood project management and communication skill;\nAttention to details and ability to work under tight timeline and multi-task independently;\nKnowledge in video or photo editing is a plus.\n\nBenefits:\n\nFive-day work week\nBirthday Leave\nBank holidays\nShuttle Bus to/from work\n\nLocation: Kwai Chung\n\nPersonal data collected will be used for recruitment purpose only.", "employment_types": ["Full Time", "Permanent"], "selling_points": [], "locations": ["Quarry Bay"], "categories": ["Media & Advertising", "Account Servicing", "Media Buying", "Strategic Planning"], "post_time": "2022-01-12T09:31:31Z", "salary": {"currency": null, "max": null, "min": null, "period": "monthly", "term": null}, "salary_visible": false, "title_keywords": ["senior manager"], "responsibilities": ["liaise with clients", "social media", "advertising", "ad-hoc assignments", "teams", "coordinate with", "develop", "digital marketing", "plan", "contents", "plans", "advertising campaigns"], "requirements": {"degrees": [], "majors": [], "languages": [], "language_level": [], "hard_skills": ["facebook", "project management", "adwords", "plus"], "soft_skills": ["independently", "multi-task", "communication skill", "project management", "attention to details"], "languages_combined": []}, "experience_required": {"duration": ["1 - 3 years"], "field": ["video production", "agency", "marketing", "digital marketing"]}}, {"job_id": "100003009040300", "location_code": "hk", "company": "The Wing On Department Stores (Hong Kong) Limited", "job_title": "Marketing Officer (Advertising)", "description": "Overview of job\n\nMediaCom is an agency of GroupM, the world\u2019s largest media investment company and are a part of WPP. In fact, we are responsible for one in every three ads you see globally. We are currently looking for a\u00a0Senior Manager\u00a0to join us. In this role, you will be responsible for servicing clients of international brands at regional level, providing integrated media strategy plans as well as managing campaign executions and reporting. You will be working closely with few local markets in APAC, and to provide them guidance and to shape local media recommendations. You will also assist team leader in mentoring junior staff and collaborating with cross functional teams within the Company offices and the WPP network.\n\nAt GroupM APAC, our people are our strength, which is why fostering a culture of diversity and inclusion is important to us.\n\nReporting of the role\n\nThis role reports to: Regional Business Director\n\n3 best things about the job:\n\nYou will work on various accounts which will challenge your critical thinking & creative ideations\nWork side-by-side with few key markets in APAC and guide and educate to ensure consistent and high-quality media recommendation. Bridge communications with some of the HQ offices in US, UK & Paris offices\nJoin the winning team that is proud of the work they deliver while enjoying what we do\n\nIn this role, your goals will be:\n\nIn 3 months:\n\nCompleted inductions with internal teams and develop a rock-solid chemistry with key stakeholders, including the clients and local markets;\nBecome fully up-to-speed with the APAC media landscape in general, and competitor media landscape specifically to the travel industry;\nUnderstand the clients\u2019 business and brand situation, and the way of working and communication flow with local teams and agency partners;\nCompleted all the tools training (if not familiar with the systems already) and understand how MediaCom develops communication planning;\nProvided constructive feedback about the day-to-day job duty of junior members of the team\n\nIn 6 months:\n\nHave a full understanding of all key accounts and their performance and ad operations requirements;\nAlready established trusted relationship with client management and custodianship;\nDemonstrated ability to evaluate and provide constructive feedback to local teams in shaping their strategies and media recommendations;\nDemonstrated creativity and innovative mindset in client\u2019s briefs and problem solving.\n\n\u00a0In 12 months:\n\nGot into a strong habit of delivering excellent work with accuracy;\nManaged the full annual planning proposal for your key accounts;\nSuccessfully work on, or lead, cross-functional teams with clients, internal teams, and media owners;\nWorked in close collaboration with the team on future communication directives for your assigned client to address the dynamic media development, with a focus on innovation;\nBecome an invaluable partner to your clients.\n\nWhat your day job looks like:\n\nOversee campaign strategy, planning, implementation, and reporting;\nWork closely with local markets in guiding on planning and execution;\nDevelop and maintain strong relationships with clients, agency partners and vendors;\nSet expectations and manage delivery on multiple projects at the same time;\nSupervise implementation team on deliverables, provide suggestions to problem solve issues;\nSupervise a team comprised of 2-3 junior team members.\n\nMinimum qualifications:\n\n6+ years account planning, media communications planning, brand strategy, or marketing experience\nExperience in working on regional capacity is preferred but not a must\nYou\u2019ll be comfortable taking action on follow-ups by doing the nuts and bolts work yourself and leading by example\nDemonstrate strategic & critical thinking and effective problem-solving skills\nStrong quantitative & qualitative analytical skills especially in the area of assessing consumer insights, media landscape & media metrics\nExperience in TV planning is a plus\nYou enjoy working in, and managing multi-cultural teams where English is not the first language\nExcellent communication skills\nFluent written and spoken English and Chinese is a must\nAbility to work effectively and collaboratively with other teams/business units\nNatural curiosity and dynamism\nEnjoy challenging the status quo and push through new ideas\n\nAbout MediaCom\n\nWe believe in People First, Better Results.\n\nMediaCom unleashes brands\u2019 growth by helping them See the Bigger Picture. This means that we apply our unique \u2018Systems Thinking\u2019 philosophy and technology to all marketing levers: media, message and data. As a result, we design communication strategies that deliver short term results and help brands build for the future.\n\nAs part of WPP, the world's largest marketing communications services group, and GroupM, WPP\u2019s consolidated media investment management arm, we have access to the richest data, most robust benchmarks and most advanced capabilities in the market. This helps us provide comprehensive solutions to all marketing challenges.\n\nOur success is underpinned by our long-standing \u2018People First, Better Results\u2019 belief. We know that by investing in our people\u2019s whole-person wellbeing, careers and capabilities, we will help grow our clients\u2019 businesses.\n\nIn 2020 this approach led MediaCom to be crowned Global Media Network of the Year by Eurobest and Festival of Media Global, in addition to being the most awarded agency at the WARC Media Awards.\n\nMediaCom is one of the world\u2019s leading media communications specialists, with billings of US$17.6 billion (Source: COMvergence, 2020), employing 8,000 people in 125 offices across 100 countries. Its global client roster includes adidas, Coca-Cola (TCCC), Dell, Groupe PSA, Hasbro, Mars, NBC Universal, P&G, Richemont, Shell, Sony, Uber and Walgreens Boots Alliance.\n\nTo find out more about MediaCom visit us here:\u00a0 www.mediacom.com", "employment_types": ["Full Time", "Permanent"], "selling_points": [], "locations": ["Kowloon Bay"], "categories": ["Media & Advertising", "Media Buying", "Marketing / Public Relations", "Public Relations - Copy-writing"], "post_time": "2022-01-12T02:12:27Z", "salary": {"currency": null, "max": null, "min": null, "period": "monthly", "term": null}, "salary_visible": false, "title_keywords": ["marketing officer"], "responsibilities": ["ideas", "data", "operations", "quality", "design", "communication", "maintain", "plans", "communications with", "billings", "teams", "implementation", "develop", "reports", "guidance", "reporting", "management", "consumer insights", "cross-functional teams", "systems", "evaluate", "multiple projects", "planning"], "requirements": {"degrees": [], "majors": [], "languages": ["english", "chinese"], "language_level": ["fluent"], "hard_skills": ["plus", "analytical skills", "problem solving", "dynamic", "problem-solving skills", "focus"], "soft_skills": ["work effectively", "communication skills", "advanced", "responsible", "problem solve", "enjoy working", "unique", "innovative", "communication", "problem solving", "analytical skills", "dynamic", "robust", "comprehensive", "problem-solving skills", "focus", "creative", "constructive"], "languages_combined": [{"language": "english", "language_level": ["fluent"]}, {"language": "chinese", "language_level": ["fluent"]}]}, "experience_required": {"duration": ["6+ years"], "field": ["marketing", "brand", "media", "planning"]}}, {"job_id": "100003009036795", "location_code": "hk", "company": "QEELIN LTD", "job_title": "QEELIN Communications Executive (1 year renewable contract)", "description": "Your Role\n\n\nAnalytics Specialist is a technical role in FiveStones for anyone who aims at developing a data & analytics consulting career in the digital ad technology industry.\u00a0\n\nYour typical day could be a combination of the followings:\n\nDevelop tracking plans for analytics implementations\nImplement tags in tag management systems\nWork with team members to provide dashboards and reports\nTroubleshoot issues with tracking tags and data reports\nHandle ad-hoc projects as assigned\nYou will learn these on the go:\n\nJavaScript and Google Apps Script snippets\n\u200b\u200bUse of web analytics and tag management tools, e.g. Google Analytics, Google Tag Manager\nTo Qualify, Individuals Must Possess\n\nHigher Diploma or above in Computer Science, Information Engineering or equivalent fields. Fresh graduates are welcome.\n0-2 years relevant experience for entry level. Candidates with more experience will also be considered for senior roles.\u00a0\nExperience in CSS, HTML\nFamiliar with scripting language, such as JavaScript, Python, PHP, Ruby, Bash\nResilient, curious and with a growth mindset\nProactive and self-motivated to work independently & make things happen\nWillingness of learning new programming languages and technologies\nComfortable working in a fast paced & multinational environment and with distributed team\nGood presentation skills, verbal and written communication skills in Chinese and English\nA good team player & fast learner with a good \u201cpeople person\u201d personality & sense of humour\nWhat We Offer\nBe part of a growing organization with discretionary bonus, medical benefits, birthday leave, flexible working location, learning sponsorship, and more.\n\n", "employment_types": ["Full Time"], "selling_points": ["1 year renewable contract", "12 Days AL, with medical coverage", "Relevant experience in retail industry is a plus"], "locations": ["Wan Chai"], "categories": ["Media & Advertising", "Media Buying", "Marketing / Public Relations", "Marketing - Marketing Communication", "Public Relations - Event Management"], "post_time": "2022-01-10T14:26:42Z", "salary": {"currency": null, "max": null, "min": null, "period": "monthly", "term": null}, "salary_visible": false, "title_keywords": ["executive"], "responsibilities": ["management", "consulting", "data", "systems", "developing", "develop", "communication", "reports", "troubleshoot", "plans", "ad-hoc projects", "tracking"], "requirements": {"degrees": ["higher diploma or above"], "majors": ["engineering", "computer science"], "languages": ["english", "chinese"], "language_level": ["good"], "hard_skills": ["google analytics", "php", "ruby", "html", "python", "bash", "make", "javascript", "google apps script", "programming", "web analytics", "css", "go"], "soft_skills": ["communication skills", "self-motivated", "work independently", "good team player", "presentation skills", "learning", "troubleshoot", "web analytics", "proactive", "fast learner"], "languages_combined": [{"language": "english", "language_level": ["good"]}, {"language": "chinese", "language_level": ["good"]}]}, "experience_required": {"duration": ["0-2 years"], "field": ["relevant experience"]}}, {"job_id": "100003009053449", "location_code": "hk", "company": "Madcradle Online Limited", "job_title": "(Senior) Digital Marketing Executive", "description": "Job Description\n\n\nPlan and execute integrated digital marketing strategies for clients on different platforms, including but not limited to Search Engine, Display and Social Media;\nSetup and manage Google Ads, Yahoo & Bing campaigns;\nAnalyze media performances with different tracking tools such as Google Analytics;\nHandle reports with insights on an ad-hoc / weekly / monthly basis;\nPrepare pitching materials and review with clients on media performance + formulate strategies on optimization;\nPrepare presentation deck and materials for client pitching.\nThe Successful Applicant\n\nBachelor's degree;\nGood command of both spoken and written Chinese and English, native English is an advantage;\n\nMinimum 1 year of experience in digital advertising field or advertising agency;\n\nExperience in Google Ads / Yahoo / Bing advertising campaign management and Google Analytics is an advantage;\n\nExcellent communication and interpersonal skills;\nProficient in Microsoft Excel and PowerPoint;\n\nImmediate availability is preferred.\n\nWhat's On Offer\n\n\nAttractive Remuneration Package and Benefits\n5-day work\nBank Holidays and other special leave (e.g. Birthday Leave, Family Leave, etc...)\nMedical Insurance\nSales and Product Training will be provided\nTeam Building Activites\nOpportunity for Job Promotion\nFriendly Work Environment\nInterest parties please send your CV with availability, current and expected salary to us.\u00a0\n\n\n**Personal data collected will be used for recruitment purpose only**", "employment_types": ["Full Time", "Permanent"], "selling_points": ["Plan & execute digital marketing strategies", "Analyze & report media performances", "Prepare pitching materials and review with clients"], "locations": ["Kwun Tong"], "categories": ["Media & Advertising", "Account Servicing", "Media Buying", "Marketing / Public Relations", "Digital Marketing"], "post_time": "2022-01-17T06:59:53Z", "salary": {"currency": null, "max": null, "min": null, "period": "monthly", "term": null}, "salary_visible": false, "title_keywords": ["digital marketing executive"], "responsibilities": ["ad-hoc", "social media", "digital marketing strategies", "advertising", "review", "communication", "reports", "plan", "campaign management", "setup", "tracking"], "requirements": {"degrees": ["degree", "bachelor"], "majors": [], "languages": ["english", "chinese"], "language_level": ["native", "good command", "advantage"], "hard_skills": ["google analytics", "powerpoint", "microsoft excel"], "soft_skills": ["communication and interpersonal skills", "presentation"], "languages_combined": [{"language": "english", "language_level": ["native", "good command", "advantage"]}, {"language": "chinese", "language_level": ["native", "good command", "advantage"]}]}, "experience_required": {"duration": ["minimum 1 year"], "field": ["digital", "management", "advertising", "advertising agency"]}}, {"job_id": "100003009053450", "location_code": "hk", "company": "Madcradle Online Limited", "job_title": "(Senior) Digital Performance Specialist", "description": "Job Description\n\n\nMaintain daily operations for the social media advertising campaigns including content creation, posting, ad placing and monitoring;\nClosely monitor and analyze the social media advertising performance and its return of investment;\nFormulate insightful strategies and creative ideas to meet clients\u2019 objectives, ensure successful execution, flow and end-result;\nWork closely with internal teams and clients to deliver outstanding account servicing;\nRegularly generate report and drive analytics and recommendations;\nAssist in preparing document to pitch clients e.g. marketing plan, schedule, budget.\n\nThe Successful Applicant\n\n\nTertiary-educated;\nMinimum 1 year of account servicing and practical experience in social media platforms;\nUnderstanding on social media trends and best practices across the digital and new media sectors;\nFast-learner, passionate in online advertising industry;\nEager to learn, cheerful, detail-oriented and polite;\nGood team player with excellent communications and interpersonal skills;\nProficiency in MS Office applications e.g. Word, Excel etc.;\nGood written and spoken English & Chinese;\nCandidate with more experience will be considered as Senior Digital Performance Specialist.\nWhat's On Offer\n\n\n5-day work\nBank Holidays and other special leave (e.g. Birthday Leave, Family Leave, etc...)\nMedical Insurance\nTeam Building Activities\nDigital Marketing Training will be provided\nFriendly Work Environment\nInterest parties please send your CV with availability, current and expected salary to us.\n**Personal data collected will be used for recruitment purpose only**\n\n\n", "employment_types": ["Full Time", "Permanent"], "selling_points": ["Maintain operations for social media campaigns", "Monitor social media advertising performance", "Report and drive analytics and recommendations"], "locations": ["Kwun Tong"], "categories": ["Media & Advertising", "Account Servicing", "Media Buying", "Marketing / Public Relations", "Digital Marketing"], "post_time": "2022-01-17T06:59:54Z", "salary": {"currency": null, "max": null, "min": null, "period": "monthly", "term": null}, "salary_visible": false, "title_keywords": ["digital performance specialist"], "responsibilities": ["social media", "creative ideas", "advertising", "monitoring", "monitor", "maintain daily operations", "teams", "budget", "social media platforms", "marketing plan", "digital marketing", "schedule", "recruitment", "online advertising", "personal data", "insurance", "advertising campaigns", "report"], "requirements": {"degrees": [], "majors": [], "languages": ["english", "chinese"], "language_level": ["good"], "hard_skills": ["excel", "word", "ms office"], "soft_skills": ["passionate", "good team player", "cheerful", "polite", "detail-oriented", "eager to learn", "interpersonal skills", "friendly", "creative"], "languages_combined": [{"language": "english", "language_level": ["good"]}, {"language": "chinese", "language_level": ["good"]}]}, "experience_required": {"duration": ["minimum 1 year"], "field": ["social media", "account servicing", "digital"]}}, {"job_id": "100003009056102", "location_code": "hk", "company": "Madcradle Online Limited", "job_title": "Assistant Digital Performance Manager", "description": "Job Description\n\n\nDelivering social media campaigns through social media platforms: Facebook, LinkedIn, Twitter, LINE, Wechat etc.;\nPlanning and executing online advertising strategies of various platforms;\nMaintain daily operations for the social media advertising campaigns including content creation, posting, ad placing and monitoring;\nClosely monitor and analyze the social media advertising performance and its return of investment;\nFormulate insightful strategies and creative ideas to meet clients\u2019 objectives, ensure successful execution, flow and end-result;\nMaintain relationship with new and existing customers;\nPerform any ad-hoc duties as assigned.\nThe Successful Applicant\n\n\nBachelor\u2019s degree in Marketing Communication or related;\nMinimum 3 year practical experience in social media platforms, agency experience preferred;\nUnderstanding on social media trends and best practices across the digital and new media sectors;\nAbility to lead and motivate a team to deliver results;\nEager to learn, cheerful, detail-oriented and polite;\nProficiency in MS Office applications e.g. Word, Excel etc.\nmedia sectors;\nGood written and spoken English & Chinese;\nCandidate with more experience will be considered as Digital Performance Manager.\nWhat's On Offer\n\n\n5-day work\nBank Holidays and other special leave (e.g. Birthday Leave, Family Leave, etc...)\nMedical Insurance\nTeam Building Activities\nDigital Marketing Training will be provided\nFriendly Work Environment\nInterest parties please send your CV with availability, current and expected salary to us.\n**Personal data collected will be used for recruitment purpose only**\n\n\n", "employment_types": ["Full Time", "Permanent"], "selling_points": ["Plan & execute Digital Marketing strategies", "Monitor Social Media advertising performance", "5-day week, Competitive Remuneration Package"], "locations": ["Kwun Tong"], "categories": ["Media & Advertising", "Media Buying", "Strategic Planning", "Marketing / Public Relations", "Digital Marketing"], "post_time": "2022-01-18T03:19:04Z", "salary": {"currency": null, "max": null, "min": null, "period": "monthly", "term": null}, "salary_visible": false, "title_keywords": ["manager", "assistant"], "responsibilities": ["social media platforms", "communication", "maintain", "facebook", "personal data", "online advertising", "advertising", "social media campaigns", "maintain daily operations", "monitor", "social media", "monitoring", "executing", "digital marketing", "ad-hoc duties", "advertising campaigns", "creative ideas", "recruitment", "insurance", "planning"], "requirements": {"degrees": ["degree", "bachelor"], "majors": ["marketing"], "languages": ["english", "chinese"], "language_level": ["good"], "hard_skills": ["excel", "word", "wechat", "facebook", "ms office"], "soft_skills": ["cheerful", "polite", "detail-oriented", "communication", "eager to learn", "friendly", "ad-hoc duties", "creative"], "languages_combined": [{"language": "english", "language_level": ["good"]}, {"language": "chinese", "language_level": ["good"]}]}, "experience_required": {"duration": ["minimum 3 year"], "field": ["agency", "social media", "digital"]}}, {"job_id": "100003009056174", "location_code": "hk", "company": "PCCW Media (NowTV)", "job_title": "Senior Content Development Manager / Content Development Manager (Content Acquisition)", "description": "Key responsibilities\n\nContent Acquisition \u2013 Now TV Team:\n\nResponsible for the important role of \u00a0Asian content acquisition, primarily drama series, across Now TV and its affiliates\u2019 media services in Hong Kong.\nHeads up a team to manage all aspects of content acquisition and management including research, negotiation, contract drafting, viewership tracking, financial analysis and contract database maintenance.\nManage the programming and scheduling of exclusive Asian drama linear channels and on-demand services to ensure that they are popular with customers.\u00a0\nCollaborate with internal stakeholders such as Marketing, Product, Legal, Finance and Overseas business teams to align budgets and forecasts, programming plans, marketing and promotional activities as well as to drive content \u00a0engagement across all customer touchpoints.\nMonitor industry trends to drive strategic content decisions, formulate business plans and develop content strategies for both internal and external stakeholders.\n\nQualifications\n\nUniversity degree required with 8+ years of relevant work experience in the media industry or content acquisition / distribution fields and with 3+ years of supervisory experience.\nExperience in negotiations and ability to manage legal agreements and contracts.\u00a0\nRelevant knowledge of Asian drama market and industry trends.\nAbility to learn in fast-paced environment, prioritizing and balancing multiple projects and deadlines simultaneously.\nGreat interpersonal skills, business judgment, proven strategic thinking and problem solving skills.\nExcellent verbal and written communication skills\u00a0in Cantonese/ Mandarin/ English.\nPreferred proficiency in a foreign language such as \u00a0Japanese/Korean but not required.", "employment_types": ["Full Time"], "selling_points": ["Asian content acquisition, Primarily drama series", "Content acquisition and management", "Performance bonus, Medical benefit, 5day work week"], "locations": ["Kowloon Bay"], "categories": ["Media & Advertising", "Media Buying", "Strategic Planning", "Broadcasting - TV / Radio"], "post_time": "2022-01-18T03:28:48Z", "salary": {"currency": null, "max": null, "min": null, "period": "monthly", "term": null}, "salary_visible": false, "title_keywords": ["manager"], "responsibilities": ["collaborate with", "budgets", "management", "maintenance", "contracts", "teams", "monitor", "business plans", "develop", "financial analysis", "scheduling", "communication", "promotional activities", "database", "plans", "multiple projects", "tracking"], "requirements": {"degrees": ["university degree"], "majors": [], "languages": ["cantonese", "english", "mandarin", "japanese", "korean"], "language_level": ["excellent", "proficiency"], "hard_skills": ["financial analysis", "programming", "problem solving skills", "maintenance"], "soft_skills": ["communication skills", "negotiation", "responsible", "strategic thinking", "fast-paced environment", "interpersonal skills", "problem solving skills", "prioritizing"], "languages_combined": [{"language": "cantonese", "language_level": ["excellent"]}, {"language": "english", "language_level": ["excellent"]}, {"language": "mandarin", "language_level": ["excellent"]}, {"language": "japanese", "language_level": ["proficiency"]}, {"language": "korean", "language_level": ["proficiency"]}]}, "experience_required": {"duration": ["8+ years", "3+ years"], "field": ["media", "legal", "supervisory experience"]}}, {"job_id": "100003009033949", "location_code": "hk", "company": "GroupM Limited", "job_title": "Xaxis | Programmatic Trading Specialist", "description": "HOW YOU WILL CONTRIBUTE\n\nMedia/Advertising\n\nFollow up with internal design on the availability of media assets\nAssist on advertising execution including external vendors liaison, e.g advertising material submission\n\n\u00a0Public Relations\n\nAssist on handling celebrities dressing, gifting arrangement\nAssist on product shooting and assets creation\nPrepare various PR and Communications reports\nManage PR resources library\nSupport in organizing & implementing for all aspects of PR activities, e.g. press events\nAssist on KOL collaboration\n\n\u00a0\nDigital/Social Media\n\nFollow up with internal design on the availability of social media assets\nAssist on social media calendar compilation\nAssist on maintaining social media platforms and staying active by creating and posting content\n\nGeneral\n\nCoordinate with retail team and internal departments to ensure smooth execution of media loans and shootings\nManage samples loan and logistics\n\nWHO YOU ARE\n\nDiploma holder or above in Business related faculties\nStrong interest to explore career in luxury retail industry\nRelevant working experience in retail industry will be an advantage\nA good team player with good interpersonal skills and positive attitude, responsible, willing to learn and result-oriented.\nDetailed minded, well organized and number-driven, able to work independently\nGood command of both spoken and written English and Chinese (Cantonese and Mandarin)\nProficiency in MS Office\nImmediately available is highly preferred\n\nHOW TO APPLY\n\n\nInterested parties please send your\u00a0full resume, stating your availability, latest and expected salary\u00a0by clicking the APPLY NOW button.\n\nData collected will be for recruitment purpose only.\n\n\nWHY WORK WITH US?\nUnique opportunity to be working in Hong Kong under the headquarter office, and to strategically be a fashion-forwarder with new ideas and initiatives to be implemented globally.\n\nTalent development is a managerial principle, promoting entrepreneurial spirit for highly empowered teams. We want to cultivate a \u201cstartup\u201d mindset where business agility is key to our fast paced development, and where every employee can reach their full potential in a stimulating and fulfilling workplace environment.\n\nJob Type\n\nFixed Term (Fixed Term)\n\nSchedule\n\nFull time\n\nOrganization\n\nQEELIN LTD", "employment_types": ["Full Time", "Permanent"], "selling_points": [], "locations": ["Quarry Bay"], "categories": ["Media & Advertising", "Account Servicing", "Media Buying", "Others"], "post_time": "2022-01-10T02:14:42Z", "salary": {"currency": null, "max": null, "min": null, "period": "monthly", "term": null}, "salary_visible": false, "title_keywords": ["specialist"], "responsibilities": ["social media", "advertising", "maintaining", "social media platforms", "product shooting", "coordinate with", "design", "reports", "logistics"], "requirements": {"degrees": ["diploma holder"], "majors": ["business"], "languages": ["cantonese", "english", "chinese", "mandarin"], "language_level": ["good command"], "hard_skills": ["ms office"], "soft_skills": ["good team player", "work independently", "responsible", "willing to learn", "well organized", "driven", "positive attitude", "interpersonal skills", "smooth", "active", "result-oriented", "detailed"], "languages_combined": [{"language": "cantonese", "language_level": ["good command"]}, {"language": "english", "language_level": ["good command"]}, {"language": "chinese", "language_level": ["good command"]}, {"language": "mandarin", "language_level": ["good command"]}]}, "experience_required": {"duration": [], "field": ["retail industry", "relevant working experience"]}}, {"job_id": "100003009039741", "location_code": "hk", "company": "Infinitech Solutions Limited", "job_title": "Assistant Digital Communications Manager \u2013 Beauty Brand", "description": "Our client is a global FMCG brand with strong retail presence in Hong Kong. They are currently looking for a digital communication candidate to further develop their digital content strategy & social media paid strategies for brand awareness in Hong Kong.\u00a0 \u00a0\u00a0\n\nJob Description\n\n\u00a0\u00a0\u00a0\u00a0\u00a0\u00a0\u00a0\u00a0 Assist to plan overall annual digital marketing strategy\n\u00a0\u00a0\u00a0\u00a0\u00a0\u00a0\u00a0\u00a0 Lead, drive & optimize online paid media planning, content creation and O2O communication journey\n\u00a0\u00a0\u00a0\u00a0\u00a0\u00a0\u00a0\u00a0 Own and manage official SNS platforms including FB, IG, and Wechat\n\u00a0\u00a0\u00a0\u00a0\u00a0\u00a0\u00a0\u00a0 Develop and implement social media campaigns including calendar planning, content creation, and leads cultivation\n\u00a0\u00a0\u00a0\u00a0\u00a0\u00a0\u00a0\u00a0 Lead and drive digital marketing activations (EX: UGC, AR, gaming, etc.) at omni-channels with clear KPI\n\u00a0\u00a0\u00a0\u00a0\u00a0\u00a0\u00a0\u00a0 Grow brand presence and foster advocacy within social communities via livestreams, affiliate programs and assist in influencers management\n\u00a0\u00a0\u00a0\u00a0\u00a0\u00a0\u00a0\u00a0 Analyze online data, social media performance, audience behavior and conversion funnel to provide effective recommendations and insights\n\u00a0\u00a0\u00a0\u00a0\u00a0\u00a0\u00a0\u00a0 Collaborate with other marketing teams to formulate integrated campaign digital strategies and execution\n\u00a0\u00a0\u00a0\u00a0\u00a0\u00a0\u00a0\u00a0 Stay up-to-date with the latest digital and social media trends. Adopt new innovations as appropriate\n\nThe Successful Applicant\n\nThe successful candidate will be degree educated in marketing, business, digital or a related discipline. You will have a minimum of 6 years relevant experience in digital communications or digital marketing (digital media planning & creative experience preferred). Good Digital analytical skills including but not limited to Google Analytics, tagging, and web analytics. Excellent interpersonal skills with good communication skills in Both English and Chinese.", "employment_types": ["Full Time", "Permanent"], "selling_points": ["MNC Work Culture", "Hong Kong Market", "Digital Content & Social Media Focus"], "locations": ["Not Specified"], "categories": ["Media & Advertising", "Media Buying", "Marketing / Public Relations", "Marketing - Marketing Communication", "Digital Marketing"], "post_time": "2022-01-11T10:49:58Z", "salary": {"currency": null, "max": null, "min": null, "period": "monthly", "term": null}, "salary_visible": false, "title_keywords": ["manager", "assistant"], "responsibilities": ["collaborate with", "social media", "management", "ar", "social media campaigns", "data", "teams", "develop", "communication", "digital marketing", "plan", "digital strategies", "planning"], "requirements": {"degrees": ["degree"], "majors": ["business", "marketing"], "languages": ["english", "chinese"], "language_level": ["excellent", "good"], "hard_skills": ["google analytics", "ar", "analytical skills", "wechat", "web analytics"], "soft_skills": ["communication skills", "analytical skills", "communication", "clear", "interpersonal skills", "web analytics", "creative"], "languages_combined": [{"language": "english", "language_level": ["excellent", "good"]}, {"language": "chinese", "language_level": ["excellent", "good"]}]}, "experience_required": {"duration": ["minimum of 6 years"], "field": ["digital media", "relevant experience", "digital marketing", "digital", "planning"]}}, {"job_id": "100003009033953", "location_code": "hk", "company": "Admango.com Ltd", "job_title": "Data Analyst", "description": "To become a digital expertise in our Company, you will enjoy our attractive benefits:\n\nCompetitive remuneration package\nPerformance Bonus\nMedical Insurance\n5-day work per week\nFlexi-working hour\nGeneral Holiday, Annual Leave, Family Care Leave and Anniversary Leave\nCasual wear in office\nFriendly working environment\n\n\u00a0\u00a0The Job\n\nStrong analytical skills to consolidate data from numerous digital advertising platforms, analyze various metrics, and to convert them into strategies and action plans\nCommunicate with client on campaign performance, insight and recommendation\nDemonstrate to clients how digital advertising and web analytics can reach their marketing objectives towards business goal\nAttentive to details, execute and optimize various digital media channels (i.e. Facebook, Google, Yahoo, LinkedIn Programmatics DSP), including but not limited to search engine marketing, display ad, social media marketing, conversion tracking and web analysis.\nCollaborate with internal teams to manage and monitor for search engine marketing and social media campaign, to deliver results and KPIs\nKeep up-to-date with platform knowledge and industry news\nAble to work independently, under pressure and to work on multiple projects with tight schedule\n\n\u00a0The Person\n\nDegree in Business, Marketing, IT or related discipline\u00a0\n2 years' experience in online business incl. Search Engine Marketing, Social Media Marketing, Web Analytic\u00a0and account management; Candidate with less experience may be considered as Executive;\nKnowledge of the Search Engine Marketing in Search engines like Google and Yahoo is preferable\nSolid understanding of the current technologies available for online advertising e,g, Search Engine Marketing, Display Advertising, Social Media Marketing, Programmatics, Website development, etc.\nAttentive to details, good with figures and strong analytical skills\nStrong passion for the Internet/Digital environment, result-oriented, proactive and independent\nAble to work collaboratively across teams as a good team player, with client-centric mindset\nGood command of written, spoken English and Chinese, knowledge of Mandarin is preferable\nAble to work independently, under pressure and to work on multiple projects with tight schedule\n\nCandidate with less experience will be considered as Digital Advertising Executive. Fresh graduates are also welcome if you possess knowledge in digital analytics, ad platforms like Google, Facebook, Bing, etc.\n\nPlease send your application with full resume stating\u00a0your present and expected salary\u00a0to the Company by clicking\u00a0on the\u00a0\"Apply now\".\u00a0Please also quote the\u00a0reference number\u00a0of the applied position in the subject field.", "employment_types": ["Full Time", "Permanent"], "selling_points": [], "locations": ["Wan Chai"], "categories": ["Media & Advertising", "Media Buying", "Marketing / Public Relations", "Marketing - Market Research", "Information Technology (IT)", "Data Scientist"], "post_time": "2022-01-10T02:15:25Z", "salary": {"currency": null, "max": null, "min": null, "period": "monthly", "term": null}, "salary_visible": false, "title_keywords": ["data analyst"], "responsibilities": [], "requirements": {"degrees": [], "majors": [], "languages": [], "language_level": [], "hard_skills": [], "soft_skills": [], "languages_combined": []}, "experience_required": {"duration": [], "field": []}}, {"job_id": "100003009029247", "location_code": "hk", "company": "Shun Hing Advertising Co Ltd", "job_title": "Media Planner", "description": "Overview of job\u00a0\n\nGroupM is the world\u2019s largest media investment company and are a part of WPP. In fact, we are responsible for one in every three ads you see globally. We are currently looking for a\u00a0Performance Specialist\u00a0to join us. In this role, you will be responsible for delivering planning recommendations and ensuring smooth account coordination internally and externally with our clients.\u00a0\n\nAt GroupM APAC, our people are our strength, which is why fostering a culture of diversity and inclusion is important to us.\n\nReporting of the role\u00a0\n\nThis role reports to\u00a0Business Director.\n\n3 best things about the job:\n\nYou will be working on a leading brand in a Global Leading Media Agency.\nDynamic working environment.\nAbundant learning opportunities on digital & media aspects, locally and regionally.\n\nIn this role, your goals will be:\nIn three months:\n\nAbility to manage day-to-day digital media implementation\nBecome a trusted team member to ensure seamless execution of media plans across these media platforms\n\nIn six months:\n\nHave the ability to independently manage campaigns with little supervision\nBe able to proactively propose media solutions to drive effective results for the business\n\nIn 12 months:\n\nDevelop a media recommendation proposal independently\nHandle the implementation process independently\nPresent media review and evaluation deck to client\n\nWhat your day job looks like at GroupM:\n\nPlan, develop, present and execute online media campaigns in multiple channels including display, \u00a0mobile and social media\nWork close with other agency teams to establish and achieve specific media goals and objectives\nMonitor the results of all campaigns \u00a0and provide campaign reports with insights and suggested optimizations\nWork closely with dynamic and international team members to meet tight deadlines\n\nMinimum qualifications:\n\n1-2 years of relevant experience in a progressive media or interactive advertising agency or portal focused on digital marketing\u00a0\nExcellent project and client management skills\nFluent in Cantonese and English\nUnderstand\u00a0agency\u00a0process, team culture, and work flow.\nUnderstand the basic concepts of digital media and process of digital media campaigns.\n\nMore about GroupM\n\nGroupM leads and shapes media markets by delivering performance enhancing media products and services, powered by data and technology. Our global network agencies and businesses enable our people to work collaboratively across borders with the best in class, providing them the opportunity to accelerate their progress and development. We are not limited by teams or geographies; our scale and diverse range of clients lets us be more adventurous with our business and talent. We give our talent the space, support and tools to innovate and grow.\n\nDiscover more about GroupM at\u00a0www.groupm.com\nFollow @GroupMAPAC on Twitter\nFollow GroupM on LinkedIn -\u00a0https://www.linkedin.com/company/groupm\n\nAbout Hong Kong\n\nHong Kong\u2019s small yet highly dynamic and efficient media market means it gets to operate with agility. Its internet and digital penetration continues to grow year-on-year, and has the highest smartphone penetration in Asia Pacific at 87%, while tablet ownership clocks in at 57%. Hong Kong\u2019s digital market boasts a healthy mix of local, regional and global players, providing new opportunities in the media space.\n\nIf you want a future in media and communications, and believe in Hong Kong\u2019s belief of \u201cwork hard, play hard\u201d, there is clearly no place more vibrant, challenging and exciting than Hong Kong, where opportunities for you to innovate and grow are unparalleled.\u00a0", "employment_types": ["Full Time", "Permanent"], "selling_points": [], "locations": ["Tsim Sha Tsui"], "categories": ["Media & Advertising", "Media Buying"], "post_time": "2022-01-07T04:23:41Z", "salary": {"currency": null, "max": null, "min": null, "period": "monthly", "term": null}, "salary_visible": false, "title_keywords": [], "responsibilities": ["reporting", "social media", "management", "advertising", "data", "review", "teams", "implementation", "monitor", "develop", "reports", "digital marketing", "coordination", "evaluation", "plan", "plans", "planning"], "requirements": {"degrees": [], "majors": [], "languages": ["cantonese", "english"], "language_level": ["fluent"], "hard_skills": ["small", "no", "basic", "mobile", "dynamic"], "soft_skills": ["efficient", "meet tight deadlines", "independently", "responsible", "focused", "diverse", "learning", "dynamic", "coordination", "smooth", "progressive", "team member"], "languages_combined": [{"language": "cantonese", "language_level": ["fluent"]}, {"language": "english", "language_level": ["fluent"]}]}, "experience_required": {"duration": ["1-2 years"], "field": ["relevant experience", "media", "advertising agency", "digital marketing"]}}, {"job_id": "100003009027035", "location_code": "hk", "company": "PHD Limited", "job_title": "Senior Media Buyer (Advertising & Media Field)", "description": "Xaxis is seeking for a Programmatic Trading Specialist to join the Programmatic Trading team in Hong Kong.\n\nThe Programmatic Trading team is at the heart of all Xaxis activity and is pivotal to the success of each programmatic advertising campaign that is executed. You will be someone who has a positive attitude and is a dedicated individual who thrives on challenges.\n\nDescription\n\nXaxis is seeking for a Programmatic Trading Specialist to join the Programmatic Trading team in Hong Kong. The Programmatic Trading team is at the heart of all Xaxis activity and is pivotal to the success of each programmatic advertising campaign that is executed. You will be someone who has a positive attitude and is a dedicated individual who thrives on challenges.\n\nThe team works closely with all other teams within the Xaxis family from Client Development and Ad Operations to Data and Product. We are looking for someone with a positive attitude, enthusiastic and is flexible with embracing changes and new challenges.\n\nReporting of the role\n\nThis role reports to the Associate Director, Programmatic Trading.\n\n3 best things about the job:\n\nIt\u2019s a great work environment - You will collaborate with a group of quick witted, humorous, diverse and extremely dedicated colleagues who are all passionate about programmatic and making advertising welcome.\nOpinions and ideas are highly encouraged, and everyone has a voice at Xaxis. Ambition is expected and passion is admired. We are always open to new ways of thinking from everyone, especially those that will contribute to the overall success of Xaxis.\nIt is never static. You are empowered to create your own balance and be proactive. There is always something new to learn, new challenges to overcome, and new technology to embrace everyday.\n\n\nMeasures of success \u2013\u00a0\n\nIn three months, you would:\n\nGain an in depth understanding of the programmatic landscape\nBe trained on the various Xaxis platforms and tools\nContribute to the day-to-day operations of the Xaxis Programmatic Trading team and take ownership of simple campaign set ups, campaign monitoring and basic optimization\n\nIn six months, you would:\n\nDevelop relationships and earn trust with Client Development and Operations teams\nManage and be responsible for branding campaigns from start to completion\nIncorporate and recommend other aspects of the Xaxis business including audience planning and insights, Xaxis products and Xaxis Marketplace as part of the overall campaign execution.\n\nIn 12 months, you would:\n\nBe responsible and confidently manage campaigns of all KPIs from start to completion\nBe a trusted advisor to Xaxis HK team and support their activity\nTest and learn, share and seek different optimization tactics and knowledge share with the wider trading team\n\nResponsibilities of the role:\u00a0\n\nSupport the Programmatic Trading Team in executing campaigns with Client Development Team and Ad Operations\u00a0Team closely\nOversee day-to-day optimization and monitoring of campaigns, and ensure optimal delivery and performance, report any anomalies to Programmatic Trading Manager.\nDevelop basic yield optimization strategies by monitoring campaign performance and identifying opportunities to optimize, improve ROI and pitch for incremental revenue\nDeploy testing methodologies on campaigns under the direction of Associate Director, Programmatic Trading\nAnalyze data from ad serving providers like Campaign Manager, Sizmek as well as conversion tracking to map the complete consumer journey\nInvolve to advise/consult with Xaxis HK team regarding inventory performance and forecasting, campaign performance, insights and suggestions.\nAssist in preparing post campaign analysis report along with the Analytics team\n\n\nWhat you will need:\n\n3 years of Professional experience with digital marketing agency, ad network or other digital media company\nKnowledge along with a passion for digital\nResult-oriented with strong communication and analytical skills\nAbility to work both independently and under supervision once objectives have been set\nAbility to work within a fast-paced deadline driven environment\nExperience managing digital ad campaigns, - display, video, mobile or paid search\nApplied knowledge of 3rd party ad serving, website tracking and associated technologies\nUnderstanding of programmatic buying, including DSPs/SSPs, RTB, ad exchanges, DMPs, audience targeting will be a bonus\nGood command in written and spoken English and Cantonese\nProficiency in Microsoft Excel and PowerPoint\nCantonese speaking is a must\nCandidate with les experience may considered as Programmatic Trader\n\nAbout Xaxis\n\nXaxis is a global digital media platform that programmatically connects advertisers to audiences across all addressable channels. Through the expert use of proprietary data and advertising technology along with unparalleled media relationships, Xaxis delivers results for over 2,800 clients in 40 markets across North America, Europe, Asia Pacific, Latin America and the Middle East. Advertisers working with Xaxis achieve exceptionally high return on advertising spend through the company\u2019s proprietary media products, as well as through its wholly-owned specialist companies, Light Reaction, Bannerconnect, and ActionX.\u00a0 For more information, visit\u00a0www.xaxis.com.\n\n\n\nAbout Hong Kong\n\nHong Kong SAR\u2019s small yet highly dynamic and efficient media market allows us to operate with agility. Its internet and digital penetration continues to grow year-on-year, and has the highest smartphone penetration in Asia Pacific at 87%, while tablet ownership clocks in at 57%. Hong Kong SAR\u2019s digital market boasts a healthy mix of local, regional and global players, providing new opportunities in the media space.\n\nIf you want a future in media and communications, and believe in Hong Kong SAR\u2019s belief of \u201cwork hard, play hard\u201d, there is clearly no place more vibrant, challenging and exciting than Hong Kong SAR, where opportunities for you to innovate and grow are unparalleled.\n\nGroupM is an equal opportunity employer. We view everyone as an individual and we understand that inclusion is more than just diversity \u2013 it\u2019s about belonging. We celebrate the fact that everyone is unique and that\u2019s what makes us so good at what we do. We pride ourselves on being a company that embraces difference and truly represents the global clients we work with.", "employment_types": ["Full Time", "Permanent"], "selling_points": ["Free Shuttle Bus & Free Breakfast", "Birthday, Family Day & Self-Love Day Leave", "5-Day Work Week"], "locations": ["Pok Fu Lam"], "categories": ["Media & Advertising", "Account Servicing", "Media Buying", "Others"], "post_time": "2022-01-06T09:02:08Z", "salary": {"currency": null, "max": null, "min": null, "period": "monthly", "term": null}, "salary_visible": false, "title_keywords": [], "responsibilities": ["collaborate with", "ideas", "data", "analysis report", "operations", "inventory", "day-to-day operations", "website", "communication", "deploy", "advertising", "teams", "develop", "testing", "reports", "analyze data", "kpis", "forecasting", "report", "reporting", "monitoring", "executing", "digital marketing", "tracking", "planning"], "requirements": {"degrees": [], "majors": [], "languages": ["cantonese", "english"], "language_level": ["good command"], "hard_skills": ["simple", "small", "no", "basic", "analysis", "powerpoint", "analytical skills", "microsoft excel", "mobile", "dynamic"], "soft_skills": ["flexible", "efficient", "independently", "responsible", "passion for", "driven", "unique", "analytical skills", "positive attitude", "diverse", "communication", "dynamic", "enthusiastic", "proactive", "result-oriented", "passionate about"], "languages_combined": [{"language": "cantonese", "language_level": ["good command"]}, {"language": "english", "language_level": ["good command"]}]}, "experience_required": {"duration": ["3 years"], "field": ["video", "agency", "digital media", "digital marketing", "digital"]}}, {"job_id": "100003009018330", "location_code": "hk", "company": "Zenith", "job_title": "Media Executive - World's 3rd largest one-stop Comms & Media network", "description": "GroupM, the world\u2019s largest media investment company and are a part of WPP. In fact, we are responsible for one in every three ads you see globally. We are currently looking for a\u00a0Planning\u00a0Supervisor\u00a0to join us.\n\nAt GroupM, our people are our strength, which is why fostering a culture of diversity and inclusion is important to us.\n\n\u00a0\nDescription\n\n3 best things about the job:\n\nOpportunity to learn advanced integrated media planning skills from the experienced team lead\nOpportunity to learn advanced planning approach with heavily digital focus operation and advanced digital solution\nWork with young and energetic team\n\nMeasures of success\n\nIn three months:\n\nBecome familiar with all relevant media and finance systems, and the team processes\nProvided support to the team as well as build knowledge of the media landscape & skillsets\n\n\u00a0In six months:\n\nMaster client reporting and tracking of booked media\nStarted to build relationships with the key decision makers within the client and agency organizations\n\nIn 12 months:\n\nConfidence and precision in updating integrated media schedules and participate to construct a holistic campaign\nBe the person whom the client goes to for day- to-day activities. Able to propose ideas and activities to answer identified challenges\n\nWhat your day job looks like at GroupM:\n\nContribute to overall media strategy development. This will include the ability to understand and interpret briefs and the application of insights to develop marketing and communications solutions\nUnderstand the client\u2019s market position to achieve optimal negotiation for clients\nEnsure regular reporting is delivered on time and accurately\nEnsure that campaigns are tracked and measured based on agreed KPIs and media efficiencies\nDevelop and build relationships with clients, acting as first point of contact on account requirements\nDevelop strong working relationship with key agency and media partners. This will include acting as the first point of contact for operational issues\nKeep current on media trends, identify and implement local media initiatives\n\nMinimum qualifications:\n\nDegree relating to marketing or business will be preferable and you have been working with media and communication planning for several years\n4 years of experience in media agency, including client-side or media owner capacity\nYou are a team player with good interpersonal skills and you thrive in an energetic and fast paced environment.\nAn affinity for numbers and experience in Excel is highly desired.\nExperience working with multiple stakeholders, e.g. suppliers, advertising/marketing agencies, media owners and internal specialist resources\nCompetent in communications planning, media planning and buying across all platforms with a good understanding and working knowledge of both traditional and new media\nStrong analytical mind, good flair of creativity and with an eye for details\nStrong communication and presentation skills\nCandidate with more experience will be considered as Assistant Manager/ Manager\n\n\u00a0More about GroupM\n\nGroupM leads and shapes media markets by delivering performance enhancing media products and services, powered by data and technology. Our global network agencies and businesses enable our people to work collaboratively across borders with the best in class, providing them the opportunity to accelerate their progress and development. We are not limited by teams or geographies; our scale and diverse range of clients lets us be more adventurous with our business and talent. We give our talent the space, support and tools to innovate and grow.\n\nDiscover more about GroupM at\u00a0www.groupm.com\nFollow @GroupMAPAC on Twitter\nFollow GroupM on LinkedIn -\u00a0https://www.linkedin.com/company/groupm\n\nAbout Hong Kong\n\nHong Kong SAR\u2019s small yet highly dynamic and efficient media market allows us to operate with agility. Its internet and digital penetration continues to grow year-on-year, and has the highest smartphone penetration in Asia Pacific at 87%, while tablet ownership clocks in at 57%. Hong Kong SAR\u2019s digital market boasts a healthy mix of local, regional and global players, providing new opportunities in the media space.\n\nIf you want a future in media and communications, and believe in Hong Kong SAR\u2019s belief of \u201cwork hard, play hard\u201d, there is clearly no place more vibrant, challenging and exciting than Hong Kong SAR, where opportunities for you to innovate and grow are unparalleled.\n\nGroupM is an equal opportunity employer. We view everyone as an individual and we understand that inclusion is more than just diversity \u2013 it\u2019s about belonging. We celebrate the fact that everyone is unique and that\u2019s what makes us so good at what we do. We pride ourselves on being a company that embraces difference and truly represents the global clients we work with.", "employment_types": ["Full Time", "Freelance"], "selling_points": ["World's 3rd largest one-stop Comms & Media network", "Competitive salary and benefits; energetic culture", "Serves some of world\u2019s biggest & boldest marketers"], "locations": ["Kwun Tong"], "categories": ["Media & Advertising", "Account Servicing", "Media Buying", "Strategic Planning"], "post_time": "2022-01-04T03:20:02Z", "salary": {"currency": null, "max": null, "min": null, "period": "monthly", "term": null}, "salary_visible": false, "title_keywords": ["executive"], "responsibilities": ["reporting", "ideas", "advertising", "data", "schedules", "systems", "teams", "develop", "communication", "planning", "contact", "kpis", "tracking"], "requirements": {"degrees": ["degree", "master"], "majors": ["business", "marketing"], "languages": [], "language_level": [], "hard_skills": ["small", "excel", "no", "dynamic", "finance systems", "focus"], "soft_skills": ["efficient", "planning skills", "confidence", "advanced", "responsible", "negotiation", "competent", "unique", "communication", "diverse", "presentation skills", "team player", "interpersonal skills", "analytical mind", "dynamic", "focus", "energetic"], "languages_combined": []}, "experience_required": {"duration": ["4 years"], "field": ["agency", "media"]}}, {"job_id": "100003009031370", "location_code": "hk", "company": "Hakuhodo Hong Kong Ltd", "job_title": "Media Executive", "description": "Responsibilities:\n\n\nConduct research in digital and\u00a0social\u00a0media include data preprocessing and analyzing\nAggregate multiple data sources to create and present weekly and monthly reports, and conduct ad hoc deep dives as required\nUphold the highest level of data quality control and precision and build strategies to ensure ongoing data accuracy\n\nRequirements:\n\n\nDegree\u00a0Holder in Statistics, Mathematics or in related field with 2 years of working experience\nProven experience with data\u00a0analytics project\u00a0setup, reporting and visualization\nAdvanced experience with Microsoft Excel to create advanced\u00a0reportingfrom concept to completion (e.g., pivot tables, charts, vlookup, sumifs, etc.)\nGood analytical / logical thinking and\u00a0attentive to details\nSelf-motivated, well-organized and a good team player\nProficiency in AdWords is an advantage", "employment_types": ["Full Time", "Permanent"], "selling_points": ["Degree in communications/ advertising/ media", "1 yr work exp in media agency / media sales", "Fresh graduate"], "locations": ["North Point"], "categories": ["Media & Advertising", "Media Buying", "Strategic Planning", "Others"], "post_time": "2022-01-07T09:16:07Z", "salary": {"currency": null, "max": null, "min": null, "period": "monthly", "term": null}, "salary_visible": false, "title_keywords": ["executive"], "responsibilities": ["social media", "ad hoc", "data", "quality control", "weekly and monthly reports", "conduct research", "build strategies"], "requirements": {"degrees": ["degree holder"], "majors": ["mathematics", "statistics"], "languages": [], "language_level": [], "hard_skills": ["data analytics", "vlookup", "adwords", "microsoft excel"], "soft_skills": ["good team player", "self-motivated", "advanced", "attentive to details", "well-organized"], "languages_combined": []}, "experience_required": {"duration": ["2 years"], "field": ["related", "statistics"]}}, {"job_id": "100003009022032", "location_code": "hk", "company": "Everwell Digital Creative Ltd", "job_title": "Digital Marketing Executive", "description": "Job Responsibilities:\u00a0\u00a0\n\nWork with planning teams, media vendors and clients on buying executions for Digital, Social, TV and Outdoor placements, on a day-to-day basis\nNegotiate buying costs with media vendors and explore new opportunities to your clients\nFollow through the whole journey of media plan implementation, from material coordination, media bookings, ad monitoring, post campaign reporting, placement reports to monthly billings\nAd setup and budget pacing monitoring for biddable media platform e.g. social and programmatic\nManage 3rd party social page cost negotiation and follow through the write-up process with vendor and client\n\nJob Requirements:\u00a0\u00a0\n\nDiploma or\u00a0University degree in business, marketing, advertising, communications, or a related field\nAt least 3 years of working experience in media buying / planning experience\nStrong ability in handling multi-tasking roles, responsible and attentive to numberings and details\nSolid hands-on experience of tools such as admanGO, Instar, Nielsen Clear Decisions.\nProven skill in managing direct relationship with vendors and clients, and cross-functional team's collaboration\nProactive team player with excellent interpersonal skills & problem-solving mindset\nExcellent written and oral communication skills in Cantonese and English, Mandarin is a plus\n\nWorking Location: Cyberport (\u6578\u78bc\u6e2f), Hong Kong\n\nWe offer a 5-day work of week, group medical & life insurance coverage, free shuttle bus to the right candidate. Interested parties please send your application letter and resume with current and expected salary by clicking the \"Apply Now\" button.\u00a0\u00a0\n\nAll information collected will be used for recruitment only and treated in strict confidence. We will retain the personal data of unsuccessful applicants for future recruitment purpose for a maximum period of 2 years.", "employment_types": ["Full Time", "Part Time", "Permanent", "Temporary", "Freelance"], "selling_points": [], "locations": ["Kwai Fong"], "categories": ["Media & Advertising", "Creative / Design", "Media Buying", "Marketing / Public Relations", "Marketing - Direct Marketing"], "post_time": "2022-01-06T11:27:52Z", "salary": {"currency": null, "max": null, "min": null, "period": "monthly", "term": null}, "salary_visible": false, "title_keywords": ["digital marketing executive"], "responsibilities": ["reporting", "cost", "billings", "monitoring", "teams", "implementation", "budget", "reports", "plan", "coordination", "setup", "costs", "planning"], "requirements": {"degrees": ["diploma", "university degree"], "majors": ["business", "communications", "marketing"], "languages": ["cantonese", "english", "mandarin"], "language_level": ["excellent"], "hard_skills": ["problem-solving", "plus"], "soft_skills": ["attentive", "communication skills", "oral", "responsible", "problem-solving", "clear", "hands-on", "multi-tasking", "interpersonal skills", "team player", "proactive"], "languages_combined": [{"language": "cantonese", "language_level": ["excellent"]}, {"language": "english", "language_level": ["excellent"]}, {"language": "mandarin", "language_level": ["excellent"]}]}, "experience_required": {"duration": ["at least 3 years"], "field": ["media buying", "planning"]}}, {"job_id": "100003009023962", "location_code": "hk", "company": "PHD Limited", "job_title": "Performance Lead, ASP HUB (Advertising and Media Field)", "description": "Responsibilities\n- Support\u00a0Manager for media planning, media buying, campaign execution and monitoring, placement report to monthly billing, etc.\n-\u00a0Work with Client Services Department and develop media planning and recommendations\n-\u00a0Negotiate the competitive offer with external media partners and media vendors\n- Perform from campaign planning to buying implementation and monitor the whole process from briefing to post buy\n\n\u00a0Requirements\n-\u00a0Degree holder in business / marketing / advertising / communication or a related field\n- 2-3 years media planning and buying experience\n-\u00a0Must be numerate and have strong attention to details\n- Good communication skills, self-motivated, responsible and detail minded\n-\u00a0Good command in written and spoken English and Chinese\n-\u00a0Proficiency in MS Word, Excel & Power-point", "employment_types": ["Full Time", "Permanent"], "selling_points": ["Free Shuttle Bus & Free Breakfast", "Birthday, Family Day & Self-Love Day Leave", "5-Day Work Week"], "locations": ["Pok Fu Lam"], "categories": ["Media & Advertising", "Account Servicing", "Media Buying", "Others"], "post_time": "2022-01-05T10:09:16Z", "salary": {"currency": null, "max": null, "min": null, "period": "monthly", "term": null}, "salary_visible": false, "title_keywords": ["lead"], "responsibilities": ["monitoring", "monitor", "implementation", "develop", "planning", "report"], "requirements": {"degrees": ["degree holder"], "majors": ["business", "marketing"], "languages": ["english", "chinese"], "language_level": ["good command"], "hard_skills": ["excel", "ms word"], "soft_skills": ["communication skills", "self-motivated", "responsible", "communication", "attention to details"], "languages_combined": [{"language": "english", "language_level": ["good command"]}, {"language": "chinese", "language_level": ["good command"]}]}, "experience_required": {"duration": ["2-3 years"], "field": ["media", "planning"]}}, {"job_id": "100003009022796", "location_code": "hk", "company": "Optimum Media Direction", "job_title": "Planner (Advertising & Media Field)", "description": "Zenith is one of the world's leading global media services agencies with 250 offices in 74 countries. We are part of Publicis Groupe, one of the world\u2019s largest communications groups. The Publicis Groupe is present in 108 countries and employs 60,000 professionals.\n\nWe offer a wide range of services, from the development of communications strategy, to media planning, negotiation and implementation. We also co-ordinate campaigns across countries and regions, working with clients in the way that best meets their individual needs. Our service is underpinned with the latest in research, tools and systems.\n\nWe are looking for a smart, energetic individual with a positive attitude to join our media team, servicing clients and developing communications solutions for Hong Kong and our Regional clients.\n\nWhat you also get:\u00a0\n\nJob security:\u00a0 Part of Publicis Groupe - world's 3rd largest, fully\u00a0integrated communications group\u00a0with offices across 100 countries, employing over 80,000 staffs globally\nExcellent office environment - conveniently located, spacious, stylish office with an outdoor terrace for some fresh air\nLearning opportunity:\u00a0 Chance to work with, and learn the management philosophies from a well-structured organisation\nBirthday leave\n5-day work-week\nGroup medical & life insurance coverage\nFun & energetic company culture\n\nJob Description\n\nResponsibilities\n\n\nSupport for the media team and\u00a0liaising with clients\nDay to day management of media plans, reports and follow up on materials\nProduce competitive analysis and reports for the relevant consumer and business sectors\nSupport for the media team and working with planning team on buying executions on a day to day basis\nImplementation of media plans including material follow up\nCoordination for reports\n\nDesired Skills and Experience\n\n\nSome experience/knowledge in media planning/buying & client servicing is highly preferred\nInterested in a career in media/communications\nGood at numbers and have strong attention to details\nExcellent communication skills\nPositive attitude and proactive\nA team player and able to work independently\nProficiency in MS Word, Excel, Power-point\nFluent in speaking /writing English and Chinese\u00a0\u00a0We are an international media agency with multinational blue chip clients. We offer competitive remuneration packages and training for the career development of our staff.\n\nIf you are interested, please reply with your CV, expected salary and availability.", "employment_types": ["Full Time", "Permanent"], "selling_points": ["Free Shuttle Bus & Free Breakfast", "Birthday, Family Day & Self-Love Day Leave", "5-Day Work Week"], "locations": ["Pok Fu Lam"], "categories": ["Media & Advertising", "Account Servicing", "Media Buying", "Others"], "post_time": "2022-01-05T06:34:54Z", "salary": {"currency": null, "max": null, "min": null, "period": "monthly", "term": null}, "salary_visible": false, "title_keywords": [], "responsibilities": [], "requirements": {"degrees": [], "majors": [], "languages": [], "language_level": [], "hard_skills": [], "soft_skills": [], "languages_combined": []}, "experience_required": {"duration": [], "field": []}}, {"job_id": "100003009014259", "location_code": "hk", "company": "Optimum Media Direction", "job_title": "Media Executive, Buying (Advertising & Media Field)", "description": "Digital Marketing Executive (Full Time / Part time)\n\nKwai Fong (Near MTR)\u00a0 Salary negotiable\n\nJob Highlights\n\nExecute digital and social media campaign\nSupport on proposal and quotation\n1 + years of working experience in digital marketing\n\nJob Description\n\nResponsibilities:\n\nExecute digital and social media campaign for our client\nMaintain daily operations for online advertising campaigns and social media on content creation, scheduling, monitoring and reporting\nClosely monitor and analyze the advertising and campaign performance and its return of investment\nProvide suggestions to clients on digital marketing and social media solutions\nAssist business development with support on proposal and quotation\nWork closely with other project team member on assisting other projects e.g. design, production, graphic design etc.\n\nRequirements:\n\n1+year of working experience in digital marketing or as a digital media specialist is preferred\nKnowledge of Online Marketing; Google network & PPC, Facebook & IG, with good understanding or major marketing channels in preferred\nStrong PC skills in Word, Excel, PowerPoint and Chinese word processing\nKnowledge in HTML, Adobe Photoshop/Illustrator or other related software knowledge will be an advantage\nSelf-motivated team player able to work independently\nGood interpersonal and communication skill\n\nWe offer :\u00a0\n\n5 days work\n14 days annual leave + benefit\nFriendly working environment", "employment_types": ["Full Time", "Permanent"], "selling_points": ["Free Shuttle Bus & Free Breakfast", "Birthday, Family Day & Self-Love Day Leave", "5-Day Work Week"], "locations": ["Pok Fu Lam"], "categories": ["Media & Advertising", "Account Servicing", "Media Buying", "Others"], "post_time": "2022-01-03T03:12:45Z", "salary": {"currency": null, "max": null, "min": null, "period": "monthly", "term": null}, "salary_visible": false, "title_keywords": ["executive"], "responsibilities": ["social media", "reporting", "advertising", "graphic design", "monitoring", "maintain daily operations", "monitor", "quotation", "design", "scheduling", "digital marketing", "online advertising"], "requirements": {"degrees": [], "majors": [], "languages": ["chinese"], "language_level": [], "hard_skills": ["excel", "chinese word processing", "adobe photoshop", "word", "powerpoint", "html", "illustrator", "facebook", "pc skills"], "soft_skills": ["self-motivated", "work independently", "communication skill", "team player", "interpersonal"], "languages_combined": [{"language": "chinese", "language_level": []}]}, "experience_required": {"duration": [], "field": ["digital media", "digital marketing"]}}, {"job_id": "100003009025363", "location_code": "hk", "company": "VS Media Limited", "job_title": "Account Executive (Digital Media)", "description": "The ASP HUB is the Centre of Excellence regional team, executing client's digital acquisition campaigns for 11 markets in Asia.\n\nWe work closely with local PHD and our clients to deliver campaign performance. We continuously share learning's to fast-track initiatives across markets, and we take pride in sharing our knowledge to improve client performance and agency capabilities.\n\nThe advantage of working in the regional team is that you have exposure to multiple markets, working closely with different departments internally and externally (e.g. marketing, product, data & analytics).\n\nWe have a very collaborate approach within the team; everyone\u2019s role and personal approach is critical to our success, especially as the team continues to grow. We invest in everyone\u2019s development, with a clear progression path tailored to support everyone to become industry leaders.\n\nBusiness Responsibilities:\n\nLead Digital Performance across Hong Kong, Singapore, Taiwan, Malaysia, and India\nLead and develop true first to market and beta opportunities to drive value to the client.\nSupport and guide the team on the development of marketing strategies for Digital Acquisition.\nManaging a team of 12 individuals who are responsible for executing the campaigns and hitting KPIs.\nGather market intelligence on post-campaign results, consumer insights, media landscape and competitive activity to drive best in class strategy and performance optimisations.\nInspire and motivate the team to identify innovation opportunities and support them in developing these into actionable outcomes, with clear metrics of success across the year.\nDrive a culture and environment for innovation and innovative thinking first\nMaintain good relationships and manage expectations with local markets teams and the regional client\nManage the accounts team to deliver case studies, monthly and quarterly reviews, and regional reports\nBuild test and learn frameworks to increase efficiency when rolling out opportunities across the ASP Region\n\nSkills and Behaviours:\n\nExcellent understanding of the digital landscape\nPeople Management\nEffective time management skills with an ability to multitask and prioritize\nDetail-oriented\nAble to produce high quality work within a fast paced, dynamic environment\nExcellent verbal and written communication skills\nProficient in Excel and PowerPoint\n\nQualifications and Other Relevant Information:\n\n8+ years relevant lead generation bidding experience\nExperience within Hong Kong and Banking Industry\nPrior people management experience\u00a0\n\nWorking Locations:\n\nclient office in Olympic, with occasional requirements to work from PHD office in Cyberport\n\nWe offer a 5-day work of week, group medical & life insurance coverage to the right candidate. Interested parties please send your application letter and resume with current and expected salary\u00a0by clicking the \"Apply Now\" button.\n\nAll information collected will be used for recruitment only and treated in strict confidence. We will retain the personal data of unsuccessful applicants for future recruitment purpose for a maximum period of 2 years.", "employment_types": ["Full Time", "Permanent"], "selling_points": ["Digital Media, Media Buy", "Account Servicing, Project Management", "Advertising"], "locations": ["Kwun Tong"], "categories": ["Media & Advertising", "Account Servicing", "Media Buying", "Others"], "post_time": "2022-01-06T04:14:08Z", "salary": {"currency": null, "max": null, "min": null, "period": "monthly", "term": null}, "salary_visible": false, "title_keywords": ["account executive"], "responsibilities": ["collaborate", "management", "marketing strategies", "consumer insights", "data", "teams", "developing", "quality", "develop", "communication", "maintain", "executing", "reports", "banking", "kpis", "managing a team"], "requirements": {"degrees": [], "majors": [], "languages": [], "language_level": [], "hard_skills": ["excel", "dynamic", "beta", "powerpoint"], "soft_skills": ["communication skills", "dynamic environment", "responsible", "time management skills", "prioritize", "detail-oriented", "clear", "learning", "ability to multitask", "innovative"], "languages_combined": []}, "experience_required": {"duration": ["8+ years"], "field": ["banking industry", "people management"]}}, {"job_id": "100003009013596", "location_code": "hk", "company": "Dentsu Trading Hong Kong Limited", "job_title": "Media Buyer (Fresh Graduate Welcome)", "description": "Job Responsibilities:\n\nAssist Manager in developing, implementing, and maintaining media communication objectives, strategies, media planning, and campaign executions across all types of media\nPrepare and maintain media plan budgets, flowcharts, POVs, and PowerPoint decks, generate and maintain competitive analyses.\u00a0 Work with calculations and other quantitative data\nMeet with media sales representatives to explore new opportunities and applicability of media vehicles\nWork in Excel and PowerPoint, as well as various media planning tools\n\n\u00a0Job Requirements:\n\nUniversity degree in business, marketing, advertising, communications, or a related field\n1 year or above media planning/buying experience preferably\nAbility to multi-task well in a fast-paced environment\nAbility to develop strong relationships, both internally and externally, and feel comfortable interacting with people from different disciplines and cultures\nMust be well organized and have strong quantitative/analytical skills\nMust be numerate and have strong attention to details\nInterest in learning new trends and development in advertising and marketing\nImportantly, must be passionate about building a career in advertising field\nFluent written and spoken English and Chinese is a must, and fluent spoken Cantonese is highly preferred\nProficiency in Word, Excel and PowerPoint\n\nWorking Location: Cyberport (\u6578\u78bc\u6e2f), Hong Kong\n\nWe offer a 5-day week of work, group medical & life insurance coverage and free shuttle bus to the right candidate. Interested parties please send your application letter and resume to click the \"Apply Now\" at the bottom.\n\nAll information collected will be used for recruitment only and treated in strict confidence. We will retain the personal data of unsuccessful applicants for future recruitment purpose for a maximum period of 2 years.", "employment_types": ["Full Time", "Permanent"], "selling_points": ["Implementation of media plans", "Building relationships with working partners", "Follow up on media buying execution"], "locations": ["Quarry Bay"], "categories": ["Media & Advertising", "Account Servicing", "Media Buying", "Strategic Planning"], "post_time": "2022-01-03T02:31:14Z", "salary": {"currency": null, "max": null, "min": null, "period": "monthly", "term": null}, "salary_visible": false, "title_keywords": [], "responsibilities": ["budgets", "maintaining", "data", "developing", "communication", "maintain", "plan", "planning"], "requirements": {"degrees": ["university degree"], "majors": ["business", "communications", "marketing"], "languages": ["cantonese", "english", "chinese"], "language_level": ["fluent"], "hard_skills": ["excel", "word", "powerpoint", "analytical skills"], "soft_skills": ["multi-task", "fast-paced environment", "well organized", "analytical skills", "learning", "attention to details", "passionate about"], "languages_combined": [{"language": "cantonese", "language_level": ["fluent"]}, {"language": "english", "language_level": ["fluent"]}, {"language": "chinese", "language_level": ["fluent"]}]}, "experience_required": {"duration": ["1 year"], "field": ["media", "planning"]}}, {"job_id": "100003009016405", "location_code": "hk", "company": "IPG Mediabrands (HK) Limited", "job_title": "Media Executive (Planning)", "description": "Job Responsibilities:\u00a0\n\nTo\u00a0negotiate buying costs with media suppliers\nTo prepare the plan for client approval\nTo execute and follow-up on approved plans\nTo prepare post-campaign monitoring reports\nTo issue the monthly billings\nTo prepare regular\u00a0reports as per client request\n\nJob Requirements:\u00a0\n\nUniversity degree in business, marketing, advertising, communications, or a related field\n0 - 1 year of working experience, media planning / buying experience preferably\u00a0(fresh graduates are also welcomed)\nAbility to manage multi-task well in a fast-paced environment\nAbility to develop strong relationship, both internally and externally, and feel comfortable interacting with people from different disciplines and cultures\nMust be well organized and have strong quantitative / analytical skills\nMust be numerate and have strong attention to detail\nInterest in learning new trend and development\nImportantly, must be passionate about building a career in advertising field\nFluent written and spoken English and Chinese (Cantonese) is a must\nProficiency in Word, Excel and PowerPoint\nHave basic computer knowledge, especially Excel and Powerpoint\n\nWorking Location: Cyberport (\u6578\u78bc\u6e2f),\u00a0Hong Kong\n\nWe offer a 5-day work of week, group medical & life insurance coverage and free shuttle bus to the right candidate. Interested parties please send your application letter and resume with currect and expected salary\u00a0to click\u00a0\"Apply Now\" button.\u00a0\u00a0\n\nFor more information of OMD, please visit our website at http://www.omd.com/hong-kong\n\nAll information collected will be used for recruitment only and treated in strict confidence. We will retain the personal data of unsuccessful applicants for future recruitment purpose for a maximum period of 2 years.", "employment_types": ["Full Time"], "selling_points": [], "locations": ["Quarry Bay"], "categories": ["Media & Advertising", "Account Servicing", "Media Buying", "Marketing / Public Relations", "Marketing - Marketing Communication"], "post_time": "2022-01-03T09:01:18Z", "salary": {"currency": null, "max": null, "min": null, "period": "monthly", "term": null}, "salary_visible": false, "title_keywords": ["executive"], "responsibilities": ["billings", "monitoring", "reports", "plan", "plans", "costs"], "requirements": {"degrees": ["university degree"], "majors": ["business", "communications", "marketing"], "languages": ["cantonese", "english", "chinese"], "language_level": ["fluent"], "hard_skills": ["excel", "basic", "word", "powerpoint", "analytical skills"], "soft_skills": ["multi-task", "fast-paced environment", "well organized", "analytical skills", "learning", "attention to detail", "passionate about"], "languages_combined": [{"language": "cantonese", "language_level": ["fluent"]}, {"language": "english", "language_level": ["fluent"]}, {"language": "chinese", "language_level": ["fluent"]}]}, "experience_required": {"duration": ["0 - 1 year"], "field": ["media", "planning"]}}, {"job_id": "100003009019614", "location_code": "hk", "company": "PRADA Asia Pacific Ltd", "job_title": "Senior Regional Media Executive / Regional Media Executive", "description": "Qualifications and Requirements:\n\nPassion for advertising/media\nA desire to understand all things digital, from advertising to the role of the internet in the path to purchase\nExceptional attention to detail \u2013 scratching beneath the surface of a challenge to reveal the optimum solution\nExcellent communication skills, both written and verbal in English and Chinese\nStrong quantitative skills, including analytical abilities\nAbility to be flexible and be a team player\nSelf-motivated, keen organizer, and multi-tasking capabilities\nProficiency at MS Suite: Excel, Powerpoint, Word\nBachelor\u2019s degree (in marketing, communication, new media or a related field would be ideal, but not essential)\n\nRole Description:\n\nDevelop and demonstrate a thorough understanding of all traditional and Digital media.\nAssist in all areas of day-to-day campaign management to meet clients\u2019 business objectives and KPI\u2019s - from initial brief, constructing a plan, negotiating, and buying space, to post campaign performance reviews\nManage day to day delivery of traditional & digital media and the associated administration - compiling client reports, regular campaign optimisation, live checks, analysing data and report on trends, media owner requests and issues, resolving straightforward campaign delivery issues or problems\nLearn and demonstrate a thorough understanding of our unique planning process and proprietary planning tools as well as all industry research tools\nActively seek creative and innovative media solutions to achieve our ambition of inventing the future of media\nEvaluate media options and demonstrate knowledge of the traditional & digital marketplace\nContribute to and present implementational plans and campaign results both internally and externally, working closely with other disciplines within the agency\nEnsure that all media buys are reconciled, assist management of all billing/invoicing requirements for clients\n\nWe offer 5-day work week, birthday and other special leaves, staff training, good salary package with MPF and Medical Coverage including Dental Care. \u00a0Interested parties please\u00a0submit resumes with expected salary and date of available\u00a0to us.\n\nFor further information about Mediabrands, please visit: https://www.ipgmediabrands.com/\n\n", "employment_types": ["Full Time", "Permanent"], "selling_points": ["3 - 5 years relevant experience", "Support both online & offline media plans", "Immediate available is an advantage"], "locations": ["Quarry Bay"], "categories": ["Media & Advertising", "Media Buying", "Marketing / Public Relations", "Marketing - Market Research", "Marketing - Marketing Communication"], "post_time": "2022-01-04T08:07:54Z", "salary": {"currency": null, "max": null, "min": null, "period": "monthly", "term": null}, "salary_visible": false, "title_keywords": ["executive"], "responsibilities": ["client reports", "management", "delivery issues", "data", "planning process", "develop", "evaluate", "invoicing", "planning", "plan", "plans", "report", "campaign management", "administration"], "requirements": {"degrees": ["degree", "bachelor"], "majors": ["marketing"], "languages": ["english", "chinese"], "language_level": ["excellent"], "hard_skills": ["excel", "word", "powerpoint"], "soft_skills": ["flexible", "communication skills", "self-motivated", "passion for", "keen", "communication", "multi-tasking", "attention to detail", "team player", "ideal"], "languages_combined": [{"language": "english", "language_level": ["excellent"]}, {"language": "chinese", "language_level": ["excellent"]}]}, "experience_required": {"duration": [], "field": []}}, {"job_id": "100003009022777", "location_code": "hk", "company": "Hilti (HK) Ltd", "job_title": "Part-time Marketing Assistant", "description": "Job Summary/Purposes:\n\nThe incumbent is responsible to support the implementation of Online and Offline media plans to maximize brand exposure of Prada, Miu Miu, Church\u2019s across Asia Pacific.\n\u00a0\n\nResponsibilities:\n\n\nSupport the Regional Media team to implement Online and Offline media plans across Asia Pacific Region.\nCo-ordinate multimedia advertising materials, such as Outdoor Banners, Print, Online, Mobile and Social Media across Asia Pacific Region.\nAssist the Regional Media Manager to conduct marketing research on latest media trends and provide reports when required.\nConsolidate media post buy reports upon media execution.\nManage media database, magazines library and finance duties for AP team.\nAny other duties as may assigned.\n\nRequirements:\n\nDegree holder in Marketing/Communication/Media or related discipline.\nMinimum 3 -5 years working experiences, preferably in luxury brand marketing or media agency.\nSelf-motivated, multi-tasked and able to work under pressure in a fast-paced working environment.\nExcellent communication and organization skills.\nGood command in spoken and written English, Chinese and Mandarin.\nImmediate available is preferable.\nCandidate with less experience will be considered as Regional Media Executive\nWe offer attractive remuneration in commensurate with qualifications and experience.\u00a0Interested parties please send your\u00a0detailed curriculum vitae together with current and expected salary\u00a0to us.\u00a0\n\n\n\u00a0All information provided will be treated in strict confidence and used for recruitment purposes only", "employment_types": ["Part Time"], "selling_points": ["Global leader in construction solutions", "Tertiary graduate or undergraduate", "Daily marketing and event operation"], "locations": ["Kwun Tong"], "categories": ["Media & Advertising", "Media Buying", "Marketing / Public Relations", "Digital Marketing", "E-commerce", "Marketing - Brand / Product Management"], "post_time": "2022-01-05T06:30:48Z", "salary": {"currency": null, "max": null, "min": null, "period": null, "term": null}, "salary_visible": false, "title_keywords": ["marketing assistant"], "responsibilities": ["ap", "social media", "any other duties", "advertising", "finance duties", "provide reports", "banners", "marketing research", "reports", "database", "plans"], "requirements": {"degrees": ["degree holder"], "majors": ["marketing"], "languages": ["english", "chinese", "mandarin"], "language_level": ["good command"], "hard_skills": [], "soft_skills": ["self-motivated", "communication", "multi-tasked", "organization skills", "work under pressure"], "languages_combined": [{"language": "english", "language_level": ["good command"]}, {"language": "chinese", "language_level": ["good command"]}, {"language": "mandarin", "language_level": ["good command"]}]}, "experience_required": {"duration": ["minimum 3 -5 years"], "field": ["agency", "media", "marketing", "brand"]}}, {"job_id": "100003009015904", "location_code": "hk", "company": "RFI Asia Limited", "job_title": "Senior Digital Marketing Executive", "description": "Account Executive\n\nThe qualified candidate should have strong interest in\u00a0digital advertising, high\u00a0written and verbal communications proficiency in English and Chinese (Mandarin is a plus), as well as being intuitive and creative within the Internet marketing field.\u00a0\u00a0You should be confident with the ability to communicate effectively with clients to meet their needs, and leverage internal resources to achieve the assigned objectives.\u00a0\n\n\n\nResponsibilities include:\n\n\nExecute all aspects of digital media campaigns across different channels, such as Facebook, Google, YouTube, etc.;\nPrepare text ad copies for search engine marketing, social media and others web content writing;\nProvide in-depth analysis to get insights using all obtainable analytics tools;\nAssist Account Manager to achieve campaign objectives through close monitoring and frequent optimizations;\nDeep dive into campaign analysis to proactively troubleshoot, identify problems, and present solutions to clients;\nLeverage internal resources to deliver integrated advertising services to clients;\n\n\u00a0\nRequirements:\u00a0 \u00a0 \u00a0 \u00a0\n\n\nUniversity Degree in Communication, Marketing or other relevant fields is preferred;\nExperience in Advertising & Marketing industry is a plus;\nPassionate about digital marketing;\nProficient in Chinese language (Traditional & Simplified) and English is a must (Mandarin is a plus);\nProven skills in analyzing large quantities of data, making recommendations, and offering strategic consultation;\nExcellent communication, problem solving, organizational, and time management skills;\nPassionate about Internet and latest online advertising technologies;\nAbility to work under pressure by handling multiple assignments and meeting tight deadlines;\nSelf-motivated and problem solver, with strong CAN DO spirit;\nCandidate with more experience will be considered as Senior Account Executive;\n\n\n\nAll personal data collected will be kept confidential and used for recruitment purpose only.", "employment_types": ["Full Time", "Permanent", "Contract"], "selling_points": ["Seeking experienced digital marketing specialist", "Advise clients and lead new projects", "Grow to become a powerful digital strategist"], "locations": ["Southern Area"], "categories": ["Media & Advertising", "Account Servicing", "Media Buying", "Marketing / Public Relations", "Digital Marketing"], "post_time": "2022-01-03T07:53:19Z", "salary": {"currency": null, "max": null, "min": null, "period": "monthly", "term": null}, "salary_visible": false, "title_keywords": ["senior digital marketing executive"], "responsibilities": ["analytics tools", "social media", "advertising", "analysis", "monitoring", "troubleshoot", "facebook"], "requirements": {"degrees": ["university degree"], "majors": ["marketing"], "languages": ["english", "chinese", "mandarin"], "language_level": ["proficient"], "hard_skills": ["problem solving", "plus"], "soft_skills": ["self-motivated", "meeting tight deadlines", "problem solver", "time management skills", "organizational", "communication", "problem solving", "passionate about", "work under pressure"], "languages_combined": [{"language": "english", "language_level": ["proficient"]}, {"language": "chinese", "language_level": ["proficient"]}, {"language": "mandarin", "language_level": ["proficient"]}]}, "experience_required": {"duration": [], "field": ["marketing", "advertising"]}}, {"job_id": "100003009018763", "location_code": "hk", "company": "Doo Technology Limited", "job_title": "Senior Digital Marketing Specialist (Performance Marketing)", "description": "Who are Hilti?\nIf you\u2019re new to our industry, you might not have heard of us. We provide leading-edge tools, technologies, software and services for the global construction sector. We have a proud heritage, built over 80 years, and a worldwide reputation for pioneering products and first-rate service. With some 30,000 people in more than 120 countries. Our unique culture and career development opportunities have gained worldwide recognition. Great Place to Work\u00ae Institute ranked Hilti the 11th World Best Multinational Workplace. In Hong Kong, Hilti was accredited the Kincentric Best Employer in 2021. Therefore, we are a great place for you to learn, grow and carve-out your career\n\nYour Responsibilities\n\n\nTo provide secretarial and logistics support to senior staff.\nTo support daily marketing and event operation.\nAssist in preparing marketing communication materials.\nTo prepare presentation material for various management promotion.\nHandle website content editing and updating.\nHandle administrative task and ad hoc projects as assigned by senior staff.\n\nYour Profile\n\n\nTertiary graduate or undergraduate from Business/ e-Commerce/ Marketing or related discipline\nHonest and self-discipline.\nDetail oriented, well-organized, responsible and self-motivated.\nStrong PC skills in Word, Excel, Powerpoint.\nProficiency in English and Chinese with strong communications skill.\nGood at using Photoshop and video production software will be an advantage.\n\nLaunch your application\nInterested applicants please apply by clicking \"Apply Now\"\n\nBy submitting your candidate data, you confirm and agree that Hilti may process the candidate data according to the recruitment purposes set out.\n\nWe look forward to receiving your application and regret that only shortlisted candidates will be notified.", "employment_types": ["Full Time", "Permanent"], "selling_points": [], "locations": ["Kowloon Bay"], "categories": ["Media & Advertising", "Media Buying", "Strategic Planning", "Marketing / Public Relations", "Digital Marketing"], "post_time": "2022-01-04T04:38:36Z", "salary": {"currency": "HKD", "max": 34999, "min": 20000, "period": "monthly", "term": null}, "salary_visible": true, "title_keywords": ["digital marketing specialist"], "responsibilities": [], "requirements": {"degrees": [], "majors": [], "languages": [], "language_level": [], "hard_skills": [], "soft_skills": [], "languages_combined": []}, "experience_required": {"duration": [], "field": []}}, {"job_id": "100003009026744", "location_code": "hk", "company": "China Mobile International Limited", "job_title": "Assistant Content Operations Manager (CMIJD-0106-ACOMPMHK)", "description": "Roles and responsibilities\n\nOptimal each unit dollar to enlarge the overall buying efficiency in the most effective way\nImplementation of media plans including material follow up\nCoordination with local & regional markets & reporting\nInvoicing in monthly basis\nWorking with planning team on buying executions in daily basis\nBuilding relationships with various working partners, including clients and vendors\nFollow up on media buying execution with planning team and different creative teams\nCreating / generating creative buying ideas\n\n\u00a0Requirements\n\nUniversity graduate\u00a0(With degree in Business / Advertising / Mathematics related steams will be an advantage)\nEnthusiastic and keen to learn about media in general\nGood English, Putonghua and interpersonal communication\nGood team player / Positive \u2018can-do\u201d attitude\nDetail-minded and able to work under pressure with limited turnaround time\nWell organized multi-tasker\nVery bright with confident\nHas a passion and curiosity for all things new and creative\nInterested in different technology\nGood PC skill, especially in excel, PowerPoint & internet operations, proficiency in full suite of Microsoft Office\nFresh graduates/ Immediately availability is preferred\n\nWe offer 5 days work and attractive compensation package to suitable candidates. Interested parties, please send your full resume including your present & expected salary to us.\n\nPlease note that only short-listed applicants will be notified. All information provided will be treated in strictly confidential and used solely for recruitment purpose.", "employment_types": ["Full Time", "Permanent"], "selling_points": ["Degree holder, 3 years exp", "Content Operations", "OTT, new media, TV, film industry"], "locations": ["Kwai Hing"], "categories": ["Media & Advertising", "Account Servicing", "Media Buying", "Strategic Planning"], "post_time": "2022-01-06T08:33:47Z", "salary": {"currency": null, "max": null, "min": null, "period": "monthly", "term": null}, "salary_visible": false, "title_keywords": ["operations manager", "assistant"], "responsibilities": ["reporting", "ideas", "coordination with", "teams", "implementation", "invoicing", "plans", "planning"], "requirements": {"degrees": ["university graduate", "degree"], "majors": ["mathematics", "business"], "languages": ["putonghua", "english"], "language_level": ["good"], "hard_skills": ["powerpoint", "excel", "pc skill", "microsoft office"], "soft_skills": ["detail-minded", "confident", "good team player", "keen", "interested in", "well organized", "communication", "can-do", "enthusiastic", "creative", "interpersonal", "positive", "work under pressure"], "languages_combined": [{"language": "putonghua", "language_level": ["good"]}, {"language": "english", "language_level": ["good"]}]}, "experience_required": {"duration": [], "field": []}}, {"job_id": "100003009016491", "location_code": "hk", "company": "Wavemaker Hong Kong Limited", "job_title": "Wavemaker | Performance Planner", "description": "We seek to hire an impressive digital marketing specialist to join our award-winning team.\u00a0\n\nThe ideal candidate is a promising digital and social media marketing professional, well-trained and -practiced in an agency environment and highly-motivated to become a powerful digital strategist.\n\nSupporting the Digital Marketing Manager, we set high expectations for this role to drive service excellence for our coveted portfolio of renown multi-national brand partners. Solving brand and marketing challenges with impact-driven ideas and performance-based solutions.\u00a0This is not a support role, so we require quality client service and project management skills.\n\nYou can expect to:\n\nMaintain and help build client relationships as the key point of contact with the support of the Manager\nPartner with a creative planner and performance specialist to develop smart strategies and breakthrough ideas that create measurable value for the client\nPrepare convincing campaign proposals, carefully detailed execution plans, and clear project schedules\nLead projects from start to finish, capturing opportunities to drive campaign success and build our digital marketing portfolio\nEstablish client confidence, ensuring transparency around priority and progress through project plans, timelines, RACIs, delivery cadences, and feedback loops\nStrengthen your digital marketing knowledge, skills and portfolio\n\n\u00a0\nQualifications:\n\nImpress us with your ambition, your digital know-how, and your aptitude to successfully carry out marketing strategies and deliver solutions\nMinimum 1-2 years of digital marketing experience from an agency, directly servicing clients and managing execution\nA keen willingness to up-skill and drive progress, proving you can excel with multiple priorities in a fast-paced environment\nConfidence is key as a\u00a0convincing communicator (speaking and writing)\u00a0\nHighly self-motivated, ambitious and humble is everything\u00a0\nMust be fluent in English, ideally bilingual in Cantonese, and Mandarin is a plus\n\n\n\n\nWe look forward to hearing from you!\n\n\nYou\u2019re right for the job if you feel like you haven\u2019t yet realised your potential and you want to be challenged. What we offer is room to grow with the opportunity to sharpen your marketing expertise and a portfolio that you can be proud of.\n\nDo consider this as a career opportunity, because we invest in our professionals to be at their best and go as far as their ambition will take them.", "employment_types": ["Full Time", "Permanent"], "selling_points": [], "locations": ["Quarry Bay"], "categories": ["Media & Advertising", "Account Servicing", "Media Buying", "Others"], "post_time": "2022-01-03T09:12:12Z", "salary": {"currency": null, "max": null, "min": null, "period": "monthly", "term": null}, "salary_visible": false, "title_keywords": [], "responsibilities": ["social media", "ideas", "marketing strategies", "schedules", "quality", "develop", "project management", "maintain", "digital marketing", "contact", "plans"], "requirements": {"degrees": [], "majors": [], "languages": ["cantonese", "english", "mandarin"], "language_level": ["fluent"], "hard_skills": ["planner", "project management", "plus", "excel"], "soft_skills": ["self-motivated", "confidence", "fast-paced environment", "project management skills", "keen", "detailed", "clear", "motivated", "communicator", "creative", "driven", "ideal"], "languages_combined": [{"language": "cantonese", "language_level": []}, {"language": "english", "language_level": ["fluent"]}, {"language": "mandarin", "language_level": []}]}, "experience_required": {"duration": ["minimum 1-2 years"], "field": ["agency", "digital marketing"]}}, {"job_id": "100003009016025", "location_code": "hk", "company": "Richemont Asia Pacific Limited - Van Cleef & Arpels", "job_title": "Senior Media & Digital Executive", "description": "Responsibilities:\n\nUndertake content marketing business, take initiative to achieve business target, including UI design, promotion, and formulation of strategic plans\nResponsible to product positioning, explore audience needs and maintain product content\nMeasure and evaluate business performance, identify and trouble shooting in response to global content operations\nConsolidate and analyze content business operations report in a regular basis. Participate in devising business plans, content roadmap and so on to improve engagement through innovative online activities\nForecast/ identify market trends and insights to optimize/ maximize content performance\n\nRequirements:\n\nBachelor Degree of above\nMinimum 3 years\u2019 working experience in content operations\nExperience in OTT, new media, TV and film industry, knowledge in Telecom industry in preferred\nPassion on content business, keen to develop new business, proactive problem solving attitude, team work\nGood interpersonal skills, well-organized, self-motivated, innovative and able to work under pressure\nProficiency in graphics/ video software, MS Office applications and Chinese Word Processing\nFluent in both spoken and written English and Chinese; Fluent in Putonghua is definitely an advantage\nCandidate with more experience will also be considered.\u00a0\n\nInterested parties please send your full resume with current & expected salary by e-mail to\u00a0hr @cmi.chinamobile.com . Please indicate the reference in the subject line.\n\u00a0\n\nAll personal data provided will be used for consideration of your job application only.", "employment_types": ["Full Time", "Permanent"], "selling_points": ["Year end double pay", "Great career progression", "Friendly working environment"], "locations": ["Central"], "categories": ["Media & Advertising", "Media Buying", "Marketing / Public Relations", "Marketing - Marketing Communication", "Sales, CS & Business Devpt", "Wholesale"], "post_time": "2022-01-03T08:08:36Z", "salary": {"currency": null, "max": null, "min": null, "period": "monthly", "term": null}, "salary_visible": false, "title_keywords": ["digital executive"], "responsibilities": ["strategic plans", "operations", "design", "business plans", "evaluate", "maintain", "forecast", "product content", "ui", "report"], "requirements": {"degrees": ["degree", "bachelor"], "majors": [], "languages": ["putonghua", "english", "chinese"], "language_level": ["advantage", "proficiency", "fluent"], "hard_skills": ["problem solving", "chinese word processing", "graphics", "ms office"], "soft_skills": ["self-motivated", "keen", "well-organized", "innovative", "problem solving", "interpersonal skills", "proactive", "work under pressure"], "languages_combined": [{"language": "putonghua", "language_level": ["fluent", "advantage"]}, {"language": "english", "language_level": ["fluent"]}, {"language": "chinese", "language_level": ["fluent", "proficiency"]}]}, "experience_required": {"duration": ["minimum 3 years"], "field": ["media"]}}, {"job_id": "100003009016401", "location_code": "hk", "company": "Walters People (HK)", "job_title": "SEM Officer (Inhouse/ Financial Services)", "description": "Overview of job\nWavemaker is an agency of GroupM, the world\u2019s largest media investment company and are a part of WPP. In fact, we are responsible for one in every three ads you see globally. We are currently looking for a\u00a0Performance Planner to join us.\n\nAt GroupM APAC, our people are our strength, which is why fostering a culture of diversity and inclusion is important to us.\n\n\nReporting of the role\nThis role reports to: Performance Manager\n\n3 best things about the job:\n1. Exposure to top tier finance client\n2. Opportunity to learn performance media including full funnel media planning and optimization skill set\n\n3. Sufficient on job training to receive up-to-date digital knowledge and updates\u00a0\u00a0\n\n\nIn this role, your goals will be:\n\nIn 3 months:\n\n\u2022 With strong understanding on client\u2019s need and gals and proactively translate into media tactics and effectively executing those tactics against the client\u2019s strategy.\n\n\u2022 Be able to proactively propose media solutions and execute the optimization plan to drive effective result for the business\n\n\u2022 Become a trusted team member to ensure seamless execution of media plans across media platforms and optimize towards client\u2019s KPI\n\n\nIn 6 months:\n\n\u2022 Deliver basic tactical campaigns independently from briefing to post campaign analysis\n\n\u2022 Handle the implementation process, including platform management and optimization independently\n\nIn 12 months:\n\u2022 Gain trust of client and feel confident making recommendations\n\n\u2022 Prepare media recommendation, media review and evaluation deck independently and participate in presentation to client\n\n\u2022 Proactively connect with media vendors to share media updates and knowledges internally and deliver a thought piece to our clients\n\n\nWhat your day job looks like at Wavemaker:\n\u2022 Working with the team as supporting role from briefing to post campaign analysis.\n\n\u2022 Set up campaigns and keep monitoring campaign performance and pacing on a day-to-day basis, using a data informed approach to optimize campaigns\n\n\u2022 Coordinate with client/creative partners on creative assets\n\u2022 Support in reporting: competitive insights, post campaign analysis, proof of activity, acceptance as required\n\u2022 Support on financial procedures and ensuring bookings on system are accurate and up to date\n\u2022 Attend all the training that is available to you within Wavemaker and GroupM\n\nMinimum qualifications:\n\u2022 Preferably around 2+ years digital performance marketing experience, ideally with hand-on execution experience across major media platforms and tools such as Editors of Google and Bing, Facebook Ads Manager and Google Marketing Platform (CM and SA360), etc.\n\n\u2022 Business Proficiency in English and Chinese\n\n\u2022 Proficiency with Microsoft Excel and PowerPoint\n\n\u2022 Consistently demonstrate hunger for learning and sharing\n\n\u2022 Effective communication skills and ability to effectively adjust to a fast-changing environment\n\n\u2022 Team player - able to receive and provide feedback professionally, thrive in a team environment and able to work collaboratively\n\n\u2022 Team player demonstrated by the ability to receive and provide feedback professionally, thrive and collaborate in a cross-functional environment\n\nAbout Wavemaker\n\nWe always believe there is a better way to grow our clients and our people.\n\nWe do this by positively provoking growth for our clients and people. We work with clients to help them grow and shape their consumers\u2019 brand decisions and experiences through media, content, and technology. We have one single attitude \u2013 Positive Provocation.\n\nOur name is our mission and our method. To make waves, you need to be provocative, even fearless. We always make sure we have each other\u2019s backs through our inclusive culture. We do our best work for brave brands and people who want to be challenged to go further and faster. We know it\u2019s not easy, but if it\u2019s in you, we will get it out of you.\n\nOur attitude of Positive Provocation is enabled by:\n\nThe deep\u00a0Knowledge\u00a0we have of our clients\u2019 business\nThe confidence to\u00a0Challenge\u00a0what\u2019s gone before\nThe\u00a0Support\u00a0to go further than we thought possible\n\nWe are a part of GroupM, WPP\u2019s global media investment management company. Discover more on\u00a0wavemakerglobal.com,\u00a0Twitter\u00a0and\u00a0LinkedIn\u00a0\n\nAbout Hong Kong\n\nHong Kong\u2019s small yet highly dynamic and efficient media market means it gets to operate with agility. Its internet and digital penetration continues to grow year-on-year, and has the highest smartphone penetration in Asia Pacific at 87%, while tablet ownership clocks in at 57%. Hong Kong\u2019s digital market boasts a healthy mix of local, regional and global players, providing new opportunities in the media space.\n\nIf you want a future in media and communications, and believe in Hong Kong\u2019s belief of \u201cwork hard, play hard\u201d, there is clearly no place more vibrant, challenging and exciting than Hong Kong, where opportunities for you to innovate and grow are unparalleled.", "employment_types": ["Full Time", "Permanent"], "selling_points": ["Inhouse SEM, Performance Marketing", "FinTech company", "Up to 25k + bonus"], "locations": ["Not Specified"], "categories": ["Media & Advertising", "Media Buying"], "post_time": "2022-01-03T09:01:04Z", "salary": {"currency": "HKD", "max": 24999, "min": 20000, "period": "monthly", "term": null}, "salary_visible": true, "title_keywords": ["officer"], "responsibilities": ["collaborate", "reporting", "management", "data", "analysis", "review", "monitoring", "implementation", "coordinate with", "procedures", "communication", "reports", "executing", "plan", "evaluation", "plans", "facebook", "planning"], "requirements": {"degrees": [], "majors": [], "languages": ["english", "chinese"], "language_level": ["proficiency"], "hard_skills": ["planner", "small", "no", "basic", "analysis", "powerpoint", "microsoft excel", "make", "dynamic", "facebook", "bookings", "go"], "soft_skills": ["confident", "communication skills", "efficient", "independently", "confidence", "creative", "responsible", "accurate", "deep", "learning", "dynamic", "team player", "team member", "presentation", "positive"], "languages_combined": [{"language": "english", "language_level": ["proficiency"]}, {"language": "chinese", "language_level": ["proficiency"]}]}, "experience_required": {"duration": ["2+ years"], "field": ["digital", "marketing", "brand", "media"]}}, {"job_id": "100003009014146", "location_code": "hk", "company": "Links International", "job_title": "Channel Marketing Officer (Fintech)", "description": "WHO ARE WE?\nA high jewelry Maison creating exceptional pieces since 1906 and transmitting exceptional know-hows in an enchanting, creative, and poetic environment.\nOur Maison is looking for talents to contribute to its development with care and no compromise.\nBy joining us, you will be surrounded by experts with a passion and will contribute to various exciting projects.\n\nDo you match this profile?\nDo you have at least 3 years previous experience within a similar role?\nDo you have a passion for jewelry, arts and culture?\nDo you enjoy working in a fast moving and collaborative environment?\nAre workplace culture and values important to you in your everyday working life?\n\nWhat do we expect from you?\nThe\u00a0Senior Media & Digital Executive\u00a0will beworking closely with local, regional team members, media and digital agency on Paid Media, Digital & Owned / Partner Media, E-comm of HK and Macau market.\n\nMore than a job\u2026 it\u2019s an experience!\nBy joining the Maison, you are joining a team in which professional development is one of our main focuses.\nThe recruitment process:\n\nApply online\nIf your profile matches our search, you will be contacted by our HR team for an interview. Otherwise, you will receive an email to inform you that your application has not been successful.\nYou will meet with the HR Business Partner, Hong Kong Macao Communication Director\u00a0\n\n#BloomWithVca", "employment_types": ["Full Time", "Permanent"], "selling_points": ["Leading financial trading platform", "Advertising channels", "3 yrs+ exp"], "locations": ["Not Specified"], "categories": ["Media & Advertising", "Media Buying"], "post_time": "2022-01-03T03:04:59Z", "salary": {"currency": null, "max": null, "min": null, "period": "monthly", "term": null}, "salary_visible": false, "title_keywords": ["marketing officer"], "responsibilities": [], "requirements": {"degrees": [], "majors": [], "languages": [], "language_level": [], "hard_skills": [], "soft_skills": [], "languages_combined": []}, "experience_required": {"duration": [], "field": []}}, {"job_id": "100003009015958", "location_code": "hk", "company": "PRIZM", "job_title": "Media Planning Manager", "description": "My client is a Hong Kong based Fintech group, focusing on APAC market.\n\nThey have several office in Hong Kong, handing different products and platforms.\n\nCurrently, they are aggressively hiring for several SEM talents to join their marketing team and manage their social media performance and paid ads.\n\nMain responsibilities:\n\nResponsible for the formulation and execution of SEM and CPC advertising channels' strategies and optimization planning;\nProvide SEM budget plan and monitor the advertisements, perform real-time optimization and implement solutions correspondingly;\nAnalyze the advertising data, summarize the feedback of advertisements, and formulate solutions;\nResearch and monitor the strategies and methods of competitor SEM, and adjust the SEM plan in time\n\nMain requirements:\n\nUniversity degree in Marketing, Business, Media or related disciplines\nMinimum 2 year working experience in SEM\nProficient in Facebook, Instagram, Google Ads, Twitter, Youtube and other platforms\nFinancial Services, Fintech or Media Agency background is highly preferred\nGood command of Chinese (mandarin) and English\nFresh graduate or INAG with relevant internship experience is also welcome", "employment_types": ["Full Time", "Permanent"], "selling_points": ["4 years' exp. in Digital Marketing / Media buying", "Develop strategic and integrated media planning", "Leading a team and provide guidance"], "locations": ["Kwun Tong"], "categories": ["Media & Advertising", "Media Buying", "Strategic Planning", "Marketing / Public Relations", "Digital Marketing"], "post_time": "2022-01-03T20:52:16Z", "salary": {"currency": null, "max": null, "min": null, "period": "monthly", "term": null}, "salary_visible": false, "title_keywords": ["manager"], "responsibilities": ["advertising", "advertisements", "data", "budget", "monitor", "plan", "sem", "planning"], "requirements": {"degrees": ["university degree", "fresh graduate"], "majors": ["business", "related disciplines", "marketing"], "languages": ["english", "chinese", "mandarin"], "language_level": ["good command"], "hard_skills": ["facebook", "sem"], "soft_skills": [], "languages_combined": [{"language": "english", "language_level": ["good command"]}, {"language": "chinese", "language_level": ["good command"]}, {"language": "mandarin", "language_level": ["good command"]}]}, "experience_required": {"duration": ["minimum 2 year"], "field": []}}, {"job_id": "100003009016982", "location_code": "hk", "company": "Ecole Internationale de Gen\u00e8ve", "job_title": "Teacher of English and Humanities - Sabbatical leave replacement for 2 years", "description": "We're hiring an all-rounded Senior Digital Marketing Specialist with solid hands-on experience in SEO/SEM is playing an important role in the company.\u00a0\u00a0You will be spearheading the SEO functions as well as online advertising and performance analysis tasks. In addition, providing insights and strategies to achieve the business goals by optimizing the ads and campaigns.\n\n\nWhat are your key responsibilities?\nPerform SEO tasks including execute, optimize, manage, and track SEM campaigns by setting relevant keywords and optimizing ads regularly to make an adjustment, improve quality score, improve CTR, and increase conversion rate.\nPlan & execute online advertising and retargeting channels such as SEM, Display Channels, Social Media Channels, Programmatic Channels, EDM, GDN, Facebook etc.\nAssist in the strategic planning of the overall performance marketing channels.\nPrepare reports, analyze data and track the performance of ads campaigns and adjust/give insight to achieve the agreed objectives.\n\n\nWho are we looking for?\u00a0\n\nBachelor's Degree in Marketing/E-Commerce/Journalism or relevant disciplines.\nAt least 4 years of working experience in the related field is required for this position.\nAble to read and write in English and Mandarin (liaise with HK/CN counterparts).\nStrong knowledge of SEO.\nStrong knowledge in online marketing tools, including Google Adwords, Google Search Console, Google Analytics, Baidu, etc.\nMature and pleasant personality with good communication skills.\nThe candidate must be a team player, have flexibility, and positive 'can do' attitude.\nAttentive to details, multi-tasking with good organizational skills, able to work independently.\nCandidates with both Global and China exposure will be an added advantage.", "employment_types": ["Temporary"], "selling_points": [], "locations": ["Central & Western Area"], "categories": ["Media & Advertising", "Media Buying", "Education", "Teacher"], "post_time": "2022-01-03T10:14:56Z", "salary": {"currency": "HKD", "max": 7999, "min": 0, "period": "monthly", "term": null}, "salary_visible": true, "title_keywords": ["teacher of english"], "responsibilities": ["social media", "business goals", "seo", "strategic planning", "edm", "analysis", "quality", "communication", "liaise with", "digital marketing", "sem", "plan", "prepare reports", "facebook", "online advertising", "analyze data"], "requirements": {"degrees": ["degree", "bachelor"], "majors": ["journalism", "marketing", "e-commerce"], "languages": ["english", "mandarin"], "language_level": [], "hard_skills": ["google analytics", "seo", "e-commerce", "adwords", "analysis", "make", "sem", "facebook"], "soft_skills": ["communication skills", "organizational skills", "work independently", "attentive to details", "mature", "pleasant", "hands-on", "multi-tasking", "team player", "positive"], "languages_combined": [{"language": "english", "language_level": []}, {"language": "mandarin", "language_level": []}]}, "experience_required": {"duration": ["at least 4 years"], "field": ["related", "digital marketing"]}}, {"job_id": "100003009015187", "location_code": "hk", "company": "ConnectedGroup Limited", "job_title": "(Senior) Manager, Ecom & Performance Marketing - Insurance", "description": "PRIZM \u2013 More than a Marketing Agency\n\nAs a prominent full-service digital marketing agency in Hong Kong,\u00a0PRIZM\u00a0stands at the frontier of the social digital transformation wave. Over the years, our creative vigour and innovative solutions have been recognized not just by our clients but also among our peers. Some of the awards that we have the honour of receiving include: Best of Mob-Ex \u2013 Agency of the Year, Digital Agency of the Year, E-Commerce Agency of the Year, and many more to come!\u00a0\n\nJob Responsibilities:\n\nDevelop\u00a0strategic and integrated media planning & recommendations for clients\nResearch\u00a0and study various media inventory and products including analysis of digital space, tracking and reporting tools\nImplement\u00a0media plans and monitor and entire proper execution of the entire media buying process\nMeasure\u00a0and formulate media performance report with analytics skills and deliver and review presentations to clients\nStay\u00a0abreast of updates and trends of digital channels including social media\nLead\u00a0a team of junior colleagues and provide guidance on work quality\nManage\u00a0task allocation among the team members and streamline the collaboration process with other internal teams\n\nJob Requirements:\n\nBachelor\u2019s degree in Business, Marketing, Advertising, Communication, or a related discipline\nAt least 4 years' experience in Digital Marketing / Digital Media Buying\nKnowledge in\u00a0various digital media buy, including Social ads, SEO/SEM, Youtube, Display Network, influencer network etc.\nExperience\u00a0in programmatic buy or China media buy will be a big plus\nAbility\u00a0to digest and compile online advertising reporting data from multiple sources\nBe a good team player with excellent interpersonal and communication skills\nHighly proficient in spoken and written English and Chinese\nMore experience will be considered as\u00a0Senior Media Planning Manager\n\n\u00a0Benefits:\n\n5-day work week\nPerformance bonus\nMedical insurance\nDental\u00a0insurance\nBirthday leave\n\nWe offer attractive compensation package to suitable candidates. Interested parties, please click \"Apply Now\" to submit your application including your present & expected salary.\n\n(Personal data collected will be used for recruitment purposes only.)", "employment_types": ["Full Time", "Permanent"], "selling_points": ["A growing local Insurance Company", "Plan and implement Digital campaign strategy", "Ecommerce experience is a must"], "locations": ["Not Specified"], "categories": ["Media & Advertising", "Media Buying", "Marketing / Public Relations", "Marketing - Market Research", "Marketing - Marketing Communication"], "post_time": "2022-01-03T06:06:54Z", "salary": {"currency": null, "max": null, "min": null, "period": "monthly", "term": null}, "salary_visible": false, "title_keywords": ["manager"], "responsibilities": ["reporting", "tracking", "social media", "analysis", "inventory", "monitor", "review", "presentations", "develop", "teams", "lead a team", "work quality", "plans", "provide guidance", "report", "planning"], "requirements": {"degrees": ["degree", "bachelor"], "majors": ["business", "marketing"], "languages": ["english", "chinese"], "language_level": ["proficient"], "hard_skills": ["plus", "seo", "sem"], "soft_skills": ["communication", "communication skills", "good team player", "interpersonal"], "languages_combined": [{"language": "english", "language_level": ["proficient"]}, {"language": "chinese", "language_level": ["proficient"]}]}, "experience_required": {"duration": ["at least 4 years"], "field": ["digital media", "digital marketing", "media", "planning"]}}, {"job_id": "100003009013137", "location_code": "hk", "company": "PCCW Media (NowTV)", "job_title": "Senior Content Development Manager / Content Development Manager (Content Acquisition)", "description": "Our client is a Fintech company and they are currently looking for a Channel Marketing Officer to join their team.\n\nResponsibilities\n\n\nOptimize global advertising channels, such as Facebook, Google, Twitter and so on\nInitiate and manage budget plan and advertising plan\nCoordinate among various stakeholders to manage the marketing cost-effectiveness\nAnalyze competitors' marketing activities, thereby proposing corresponding actions\nProvide an in-depth report and analysis every week\n\nRequirements\n\n\nBachelor degree holder in Advertising, Marketing, Business or other related disciplines\nAt least 3 years experience in Marketing\nExperiences in Financial industry would be an advantage\nExperience in media buying and marketing analytics tools, such as Google Analytics, Similarweb etc\nResults-oriented person with outstanding data analysis and communication skills", "employment_types": ["Full Time"], "selling_points": ["Asian content acquisition, Primarily drama series", "Content acquisition and management", "Performance bonus, Medical benefit, 5day work week"], "locations": ["Kowloon Bay"], "categories": ["Media & Advertising", "Media Buying", "Strategic Planning", "Broadcasting - TV / Radio"], "post_time": "2022-01-03T01:30:35Z", "salary": {"currency": null, "max": null, "min": null, "period": "monthly", "term": null}, "salary_visible": false, "title_keywords": ["manager"], "responsibilities": ["cost", "advertising", "analysis", "budget", "coordinate", "plan", "facebook", "report"], "requirements": {"degrees": ["bachelor degree holder"], "majors": ["business", "related disciplines", "marketing"], "languages": [], "language_level": [], "hard_skills": ["analytics tools", "analysis", "google analytics"], "soft_skills": ["communication skills"], "languages_combined": []}, "experience_required": {"duration": ["at least 3 years"], "field": ["marketing", "financial industry", "media buying"]}}, {"job_id": "100003009010859", "location_code": "hk", "company": "RedLotus (Hong Kong) Limited", "job_title": "Senior Sales Manager/ Sales Manager/ Sales Executive (Digital Advertising)", "description": "Job description:\n\nTo complete our team, we are looking for a:\n\nTeacher of English and Humanities - Sabbatical leave replacement for 2 years\nFull-time \u2013 24 Period(s)\n\nResponsibilities\n\u25cf To teach English and Humanities (History/Geography) to students in Years 7-8, as a member of a core interdisciplinary team.\n\n\n\n\nRequired profile:\n\nCandidate requirements\n\u25cf Teaching qualification as well as degree in English or Humanities.\n\u25cf The successful candidate will be experienced in working with this age group and able to differentiate teaching to adapt to the learning needs of the students.\n\u25cf S/he will be flexible, enthusiastic and collaborative, working with a year level core teaching team.\n\u25cf English mother tongue, good working knowledge of French.\n\nCandidates are requested to apply online attaching their CV and a covering letter. The application must be addressed to Conrad Hughes, International School of Geneva, La Grande Boissi\u00e8re Campus by 21st January 2022 mentioning the reference number 330 223.\n\n\u00a0\u00a0\u00a0\u00a0\u00a0\u00a0\u00a0\u00a0\u00a0\u00a0\u00a0\u00a0\u00a0\u00a0\u00a0\u00a0\u00a0\u00a0\u00a0\u00a0\u00a0\u00a0\u00a0\u00a0\u00a0\u00a0\u00a0\u00a0\u00a0\u00a0\u00a0\u00a0\u00a0\u00a0\u00a0\u00a0\u00a0\u00a0\u00a0\u00a0\u00a0\u00a0\u00a0\u00a0\u00a0\u00a0\u00a0\u00a0\u00a0\u00a0\u00a0\u00a0\u00a0\u00a0\u00a0\u00a0\u00a0Please note that only applications via our website will be considered\n\nThe International School of Geneva values and encourages diversity among its staff. As such, we welcome applications from candidates with a wide range of backgrounds and experience. The School is seriously committed to safeguarding and promoting the welfare of children. All successful candidates will be subject to rigorous conduct and child protection checks appropriate to their position, including prior checks with their previous employers and the authorities.\n\n\n\n\nWhat we offer:\n\nRelocation package for expatriates", "employment_types": ["Full Time", "Permanent"], "selling_points": [], "locations": ["Kwun Tong"], "categories": ["Media & Advertising", "Account Servicing", "Media Buying", "Strategic Planning"], "post_time": "2021-12-31T05:14:33Z", "salary": {"currency": null, "max": null, "min": null, "period": "monthly", "term": null}, "salary_visible": false, "title_keywords": ["senior sales manager", "sales executive", "sales manager"], "responsibilities": [], "requirements": {"degrees": [], "majors": [], "languages": [], "language_level": [], "hard_skills": [], "soft_skills": [], "languages_combined": []}, "experience_required": {"duration": [], "field": []}}, {"job_id": "100003009006506", "location_code": "hk", "company": "Hylink (HK) Digital Solution Co., Limited", "job_title": "Senior Digital Marketing Specialist/Digital Marketing Specialist", "description": "Our client is one of the biggest local insurance company and they are expanding their Digital team across web marketing, performance marketing and content marketing. They are now looking for a high caliber to join their digital acquisition team to drive innovation in ecommerce and performance marketing.\n\nResponsibilities:\n\nTo plan and implement digital marketing campaign strategy for business development and set clear measurable KPIs;\nTo keep up with digital trends, competitive activities, and best practices to drive innovation in performance marketing;\nTo leverage CRM platforms to deliver personalised and relevant content to audience;\nTo set up measurements and drive performance of all digital marketing campaigns and our e-commerce site to achieve traffic and digital lead KPIs;\nTo expand new customers and retain existing customers through driving digital marketing campaigns and the integration of social and mobile channels;\nTo liaise with various levels of management and be responsible for implementing strategic change aligned with the firm wise digital strategic goals;\nTo track and monitor the effectiveness of all digital marketing efforts against business goals;\nTo present category/campaign business results and insights to senior leaders and executives on a regular basis including scorecards, testing results, new initiatives, business reviews, etc.\n\nRequirements:\n\nBachelor's degree in Marketing, ecommerce or Business management;\nAt least 7 years of experience of E-commerce and Performance Marketing, within financial services is a plus;\nCore business strategy skills for strategy definition, roadmap development, budget planning, success measurement, etc.\nStrong analytical and quantitative skills; ability to use customer and acquisition data and business metrics to support business decisions, optimization and generate insights;\nSuccessful track record of helping develop, present and execute strategic digital campaigns, deep understanding of the E-Commerce sales & digital marketing channels;\nFamiliar with media agency performance checking for digital marketing campaign activities;\nDigital savvy and with an analytical mindset;\nStructured thinker with strong problem-solving skills;\nExcellent presentation and communication skills;\n\nInterested individuals can click apply now or send through updated resume in WORD format to Jason.tsui@connectedgroup.com. For a more comprehensive list of current opportunities, please visit www.connectedgroup.com", "employment_types": ["Full Time"], "selling_points": ["Regional Exposure with Global brand", "Digital Marketing Campaign Planning", "Hands-On Campaign Experience"], "locations": ["Ngau Tau Kok"], "categories": ["Media & Advertising", "Media Buying", "Strategic Planning", "Marketing / Public Relations", "Digital Marketing"], "post_time": "2021-12-31T05:01:40Z", "salary": {"currency": null, "max": null, "min": null, "period": "monthly", "term": null}, "salary_visible": false, "title_keywords": ["digital marketing specialist"], "responsibilities": ["management", "business goals", "digital marketing campaigns", "monitor", "testing", "digital marketing", "plan", "liaise with", "kpis"], "requirements": {"degrees": ["degree", "bachelor"], "majors": ["ecommerce", "marketing", "business"], "languages": [], "language_level": [], "hard_skills": ["business management", "plus", "e-commerce", "word", "problem-solving skills"], "soft_skills": ["communication skills", "deep", "comprehensive", "problem-solving skills", "structured", "presentation"], "languages_combined": []}, "experience_required": {"duration": ["at least 7 years"], "field": ["marketing", "financial services", "e-commerce"]}}, {"job_id": "100003009011069", "location_code": "hk", "company": "AsiaPac Net Media Ltd", "job_title": "Sr. Digital/ Digital Performance Manager (Online Ad/ Digital Marketing/ SEM/ SEO/ Programmatic)", "description": "Due to business growth, we would like to invite high calibre and ambitious, entrepreneurial-minded candidates with a passion in the digital advertising sector to join our dynamic team.\n\nResponsibilities\n\nActively seeking potential new clients in the assigned categories\nEnsure clients in the assigned categories receive the best possible service\nWork with advertisers and agencies to develop total digital solutions and identify new opportunities\nEducate the benefits of multi-screen advertising solutions and why RedLotus is the partner of choice\nDevelop proposals and holistic advertising solutions\nMaintain customer loyalty and develop continuous revenue streams\nWork closely with the Head of Business Development in forecasting revenues and prospecting clients and Operations Team in ensuring timely delivery of pre and post sales activities\n\nRequirements\n\n2+ years\u2019 experience in advertising sales\nHighly motivated, driven, and ambitious\nProficient in written and spoken Cantonese and English\nCandidates with less experience will be considered as Sales Executive\nCandidates with a well-built and comprehensive client base will be considered as Senior Sales Manager\n\nIf you feel you have the ambition, driven, and enjoy high autonomy, please email your updated resume with current and expected salary to christine.tong @ redlotus.com or press Apply Now.\n\nDue to the volume of applications, only shortlisted candidates will be contacted.", "employment_types": ["Full Time"], "selling_points": ["Manage digital marketing accounts", "Equip basic knowledge of Google Adwords, SEM, SEO", "Serve and liaise with good portfolio of clients"], "locations": ["Lai Chi Kok"], "categories": ["Media & Advertising", "Account Servicing", "Media Buying", "Marketing / Public Relations", "Digital Marketing"], "post_time": "2021-12-31T06:21:04Z", "salary": {"currency": null, "max": null, "min": null, "period": "monthly", "term": null}, "salary_visible": false, "title_keywords": ["manager", "digital marketing"], "responsibilities": ["develop"], "requirements": {"degrees": [], "majors": [], "languages": [], "language_level": [], "hard_skills": [], "soft_skills": [], "languages_combined": []}, "experience_required": {"duration": [], "field": []}}, {"job_id": "100003009010857", "location_code": "hk", "company": "RedLotus (Hong Kong) Limited", "job_title": "Senior Business Development / BD Manager / Executive (Digital Advertising)", "description": "Performance Marketing / Biddable Media\n\nJob Highlights\n\n5-day work\nGroup medical insurance\nTransportation allowance\nRegional exposure\nFriendly working environment\n\nRole Description\n\nThe Senior Digital Marketing Executive role we are looking for involves skillsets within digital media including research, planning, negotiation, implementation, and analysis across different media channels including SEM, Display, and heavily focus on Paid Social\n\nKey Accountabilities\n\nMedia strategy Planning & Implementation.\nLeverage marketing landscapes, competitor insights, and audience insights to create compelling multi-channel media strategies and media plans for the portfolio of clients based on client business and marketing objectives.\nImplement campaigns using tools and advertising platforms including Facebook Ad Manager, Adwords Editor, Twitter, DCM, and DV360.\nUnderstanding metrics and KPIs and continually suggest optimizations to improve campaign performance.\nProvide regular performance report, result analysis, and recommendations and also helping in performance review presentations.\nKeep clients and account team updated on the status of account activities and keeping track of budget pacing.\nParticipate in weekly team meetings to share new ideas and strategies.\n\n\u00a0Account Management & Team Coordination\n\nTogether with the account servicing team, the Senior Digital Marketing Executive is responsible for the day to day planning, execution, operations across the accounts assigned and is required to front face clients regularly.\nEstablish, maintain strong and effective relationships with different stakeholders, as well as work with Finance to resolve billing discrepancies.\nMeet with vendors to stay on top of all advances and offerings in digital media.\nRegional account management with at least 2 markets exposure.\n\n\u00a0Key Requirements\n\nDegree holder in advertising /PR /marketing communications /business studies related disciplines.\n2 - 4 years of digital advertising experience.\nGood interpersonal and client servicing skills, presentable, hardworking, and able to work under pressure.\nWorks well in a team environment but also able to work as an independent operator.\nFluent in both written and spoken Cantonese, English, and Mandarin.\nProficiency in MS Office including MS Word, Excel, and PowerPoint.\nAbility to manage, collect, and integrate online advertising reporting data from multiple sources including web analytics, ad servers, and other sources with strong numerical skills and attention to detail.\nCandidate with more experience will be considered as Account Manager\nConsumer Electronics industry experiences will be a plus.\nRegional exposure will be a plus.\n\nAbout Us\n\nHylink (HK) Digital Solution Co., Limited\n\nWe are the Hong Kong branch of China's largest independent digital advertising agency listed in Shanghai Stock Exchange (603825.SS)\n\nFounded with the mission, \u201cChina, Connected\u201d \u2013 connection, really is, at the heart of everything we do.\u00a0\nWith an expansive global reach, we\u2019re a team of creators, communicators, problem-solvers, and lateral thinkers, whose effectiveness lies in our targeted approach toward helping clients navigate the Chinese market and achieve their goals.\n\nAnd in another way round, we also connect Chinese advertisers towards overseas with our global present and vision.", "employment_types": ["Full Time", "Permanent"], "selling_points": [], "locations": ["Kwun Tong"], "categories": ["Media & Advertising", "Account Servicing", "Media Buying", "Strategic Planning"], "post_time": "2021-12-31T05:12:58Z", "salary": {"currency": null, "max": null, "min": null, "period": "monthly", "term": null}, "salary_visible": false, "title_keywords": ["manager", "executive"], "responsibilities": ["ideas", "operations", "budget", "media channels", "maintain", "plans", "facebook", "advertising", "implementation", "presentations", "kpis", "report", "management", "review", "digital marketing", "analysis", "sem", "coordination", "planning"], "requirements": {"degrees": ["degree holder"], "majors": ["marketing communications", "related disciplines", "business"], "languages": ["cantonese", "english", "chinese", "mandarin"], "language_level": ["fluent"], "hard_skills": ["excel", "plus", "servers", "powerpoint", "numerical skills", "web analytics", "ms office", "exchange", "ms word"], "soft_skills": ["independent", "presentable", "attention to detail", "web analytics", "interpersonal", "hardworking", "work under pressure"], "languages_combined": [{"language": "cantonese", "language_level": ["fluent"]}, {"language": "english", "language_level": ["fluent"]}, {"language": "chinese", "language_level": []}, {"language": "mandarin", "language_level": ["fluent"]}]}, "experience_required": {"duration": ["2 - 4 years"], "field": ["digital", "advertising"]}}, {"job_id": "100003009000957", "location_code": "hk", "company": "Fabcom Limited", "job_title": "Senior Performance Specialist", "description": "This is an excellent opportunity for a talented digital marketing professional with strong passion in digital advertising to join our friendly, dynamic team.\n\nResponsibilities\n\nSeek new opportunities for potential publishers in line with our commercial growth strategy\nParticipate on the partnership acquisition process\nMaintain good relationships with our partnered publishers\nRecommend improvements to partnership collaboration and offering to increase value to publishers\nDevelop and manage the strategic and tactical partnership pipeline\nShare the market insight and educate selling tactics to the staffs\nHandle media kit, sales material and marketing research for the products in charge\nCost and Profit Control\nAct as the tutor in a regular meeting to share the market insight and educate selling tactics to the staffs\n\nRequirements\n\n\u00a0 3+ years\u2019 experience in digital marketing/ advertising\n\u00a0 Excellent presentation, interpersonal and communications skills\n\u00a0 Highly motivated, driven and passionate about digital advertising\n\u00a0 Advanced level of MS PowerPoint & MS Excel preferred\n\u00a0 Candidates with less experience will be considered as Senior/ Business Executive\nWhether you're an experienced advertising professional or a talent with a passion for the digital advertising sector, we'd like to hear from you.\u00a0 Please email your updated resume with current and expected salary to\u00a0christine.tong @ redlotus.com or press Apply Now.\u00a0\n\nDue to the volume of applications, only shortlisted candidates will be contacted.\u00a0", "employment_types": ["Full Time"], "selling_points": ["Working in the award-winning agency", "5-day work and flexible working environment", "Competitive remuneration & year-end bonus"], "locations": ["Kowloon Bay"], "categories": ["Media & Advertising", "Account Servicing", "Media Buying", "Marketing / Public Relations", "Digital Marketing"], "post_time": "2021-12-27T16:13:42Z", "salary": {"currency": null, "max": null, "min": null, "period": "monthly", "term": null}, "salary_visible": false, "title_keywords": ["performance specialist"], "responsibilities": ["cost", "control", "develop", "marketing research", "maintain"], "requirements": {"degrees": [], "majors": [], "languages": [], "language_level": [], "hard_skills": ["ms powerpoint", "ms excel"], "soft_skills": ["advanced", "passion for", "presentation", "driven", "motivated", "interpersonal", "passionate about"], "languages_combined": []}, "experience_required": {"duration": ["3+ years"], "field": ["advertising", "business", "digital marketing"]}}, {"job_id": "100003009006893", "location_code": "hk", "company": "Phoenix Satellite Television Co Ltd", "job_title": "PROGRAMME ACQUISITION EXECUTIVE", "description": "With on-the-job training, you will be able to develop in-depth knowledge and hands-on experience on programmatic display, social advertising and other related fields.\u00a0\n\nYou will also be learning how to master data-analytic and tracking tools like Analytics 360, Campaign Manager, Sizmek, etc., to better understand audiences\u2019 on-site behavior, full path-to-conversion funnel, and the effectiveness of different marketing strategies.\u00a0\u00a0\n\nResponsibilities:\n\nWork with internal team in monitoring project delivery and conduct continuous optimization to improve campaign performance\nHandle the backend operation on platforms like Google Ads, Bing Ads, Facebook/Instagram Ads, Display and Video 360, etc.\nDevelop a strong understanding of clients\u2019 business objectives, work closely with clients to achieve the KPIs\nHandle regular performance reports and digest data to turn into quality learnings and insights to clients\nParticipate in media planning\n\nRequirements:\n\n2-3 years of solid experience in digital or media agency industry with account management\nPassionate about digital marketing or online media advertising\nGood project management and problem-solving skills, with strong sense of responsibility\nGood communication and interpersonal skills\nProficiency in MS Excel, PowerPoint\nImmediate availability is preferred\n\nWe offer competitive package to right candidates, a 5-day work week with excellent benefits including year-end bonus, medical scheme, birthday leave and trainings.\u00a0", "employment_types": ["Full Time", "Permanent"], "selling_points": [], "locations": ["Tai Po Area"], "categories": ["Media & Advertising", "Media Buying", "Others", "Broadcasting - TV / Radio"], "post_time": "2021-12-29T11:41:17Z", "salary": {"currency": null, "max": null, "min": null, "period": null, "term": null}, "salary_visible": false, "title_keywords": ["executive"], "responsibilities": ["performance reports", "data", "monitoring", "quality", "develop", "kpis", "facebook", "planning"], "requirements": {"degrees": [], "majors": [], "languages": [], "language_level": [], "hard_skills": ["scheme", "powerpoint", "project management", "ms excel", "problem-solving skills"], "soft_skills": ["sense of responsibility", "project management", "communication and interpersonal skills", "problem-solving skills", "passionate about"], "languages_combined": []}, "experience_required": {"duration": ["2-3 years"], "field": ["agency", "digital", "account management", "media"]}}, {"job_id": "100003009004288", "location_code": "hk", "company": "FiveStones Limited", "job_title": "Business Strategy Manager", "description": "Responsibilities:\u00a0\n\nAssist in sourcing and buying programmes from global distributors\nHandling screeners, screening and evaluating programmes, proofreading contracts, following up with distributors on material delivery.\nResponsible for administrative work for the department, especially those related to programme acquisition process.\nUndertake programmes research through multiple sources, both inside and outside TV industry.\n\nRequirements:\n\nDiploma/Degree holder, 2 years relevant working experience in TV industry preferable.\nDetail oriented, organized, good social skills and strong problem solving ability.\nSelf-motivated, hard-working and able to work independently.\nFamiliar with MS Word, Excel, PowerPoint and proficiency in Chinese Word Processing is a must.\nExcellent command of written and spoken English and Chinese,\u00a0proficiency in Putonghua is a MUST.\nCandidates with less experience will be considered for the position of Assistant Programme Acquisition Executive.\n\nFor more details of our company, please visit our website at\u00a0http://www.ifeng.com\n\nWe offer attractive remuneration package to the right candidate.\u00a0Interested parties please click \u201cApply Now\u201d to submit applications or send applications with detailed resume stating career history, present & expected salary and date available to Human Resources Department, Phoenix Satellite Television Co. Ltd. via fax:\u00a02200 8620.\u00a0\n\nPersonal data collected will be used for recruitment purpose only.\u00a0 Applicants not hearing from us within 6 weeks may consider their applications unsuccessful and all related information will be destroyed after 6 months.", "employment_types": ["Full Time"], "selling_points": ["Solid knowledge of Google Marketing Platform", "1+ yr exp. in technical/solutions sales", "Seek and develop new business opportunities"], "locations": ["Kowloon Bay"], "categories": ["Media & Advertising", "Media Buying", "Marketing / Public Relations", "Digital Marketing"], "post_time": "2021-12-29T01:55:12Z", "salary": {"currency": null, "max": null, "min": null, "period": "monthly", "term": null}, "salary_visible": false, "title_keywords": ["manager"], "responsibilities": ["contracts", "proofreading", "administrative work"], "requirements": {"degrees": ["diploma", "degree holder"], "majors": [], "languages": ["putonghua", "english", "chinese"], "language_level": ["proficiency", "excellent"], "hard_skills": ["excel", "chinese word processing", "powerpoint", "problem solving", "ms word"], "soft_skills": ["organized", "self-motivated", "work independently", "detail oriented", "problem solving", "hard-working"], "languages_combined": [{"language": "putonghua", "language_level": ["proficiency", "excellent"]}, {"language": "english", "language_level": ["proficiency", "excellent"]}, {"language": "chinese", "language_level": ["proficiency", "excellent"]}]}, "experience_required": {"duration": ["2 years"], "field": ["relevant working experience"]}}, {"job_id": "100003009007073", "location_code": "hk", "company": "AT Global Services Limited", "job_title": "SEM Manager", "description": "Your role\nDigital Advertising Executive is an entry-level role in FiveStones for anyone who aims at developing a career in the digital ad technology industry. You will gain solid knowledge and skills in the most up-to-date digital marketing and analytics solutions. The major duties of this role are as follows:\n\n\nAssist in customer\u2019s on-boarding & training for the Google Marketing Platform (GMP)\nCreate and maintain documentations for product updates, roadmaps, best practices and more\nBe the first responder and solution provider for customer GMP technical enquiries whilst ensuring quality of response, information and communication is of high standards\nAssist the Customer Success Manager in managing the relationships with existing clients\nCollaborate with internal teams to deliver Digital Maturity solutions\nHandle ad-hoc projects as assigned\nTo Qualify, Individuals Must Possess\n\n\u00a00-2 years experience in digital marketing\nBachelor\u2019s Degree in Marketing, Communications or related discipline\nResilient, curious and with growth mindset\nProactive & self-motivated to work independently & make things happen\nWillingness of continuous learning\nComfortable working in a fast paced & multinational environment and with distributed team\nExcellent presentation skills, verbal and written communication skills in Chinese (Cantonese and Mandarin) and English\nEffective at multitasking and prioritisation\nA good team player & fast learner with good \u201cpeople person\u201d personality & sense of humour\nKnowledge of Programmatic advertising, SEM, Google Tag Manager & Google Analytics preferred\nExperience in customer service/support or technical support environment preferred\nExperience in technical writing preferred\nKnowledge of HTML, CSS & JavaScript preferred\nWhat We Offer\nBe part of a growing organization with discretionary bonus, medical benefits, birthday leave, flexible working location, learning sponsorship, and more.\n\n\nWe embrace an employee-first culture. We emphasize personal development for every single team member, provide them with a supportive environment to work in. We offer a 5-day work week, dental insurance, medical insurance, MPF, bank holidays, and competitive remuneration package to the right candidate. We offer regular team activities, training, free weekly breakfast, and snacks. Interested parties please send your full resume with expected salary and availability to us. Cover letter is preferred.\u00a0\n\nAll information collected will be used for recruitment-related purposes only and will be treated in strict confidence.", "employment_types": ["Full Time", "Permanent"], "selling_points": ["Develop and execute paid search marketing campaign", "Optimize the paid campaign keyword and ad level", "AB testing, bidding strategies, keyword management"], "locations": ["Wan Chai"], "categories": ["Media & Advertising", "Media Buying", "Banking / Finance", "Financial Services", "Marketing / Public Relations", "Digital Marketing"], "post_time": "2021-12-30T01:21:06Z", "salary": {"currency": null, "max": null, "min": null, "period": "monthly", "term": null}, "salary_visible": false, "title_keywords": ["manager"], "responsibilities": ["collaborate with", "advertising", "technical support", "quality", "developing", "teams", "communication", "maintain", "digital marketing", "customer service", "sem", "ad-hoc projects"], "requirements": {"degrees": ["degree", "bachelor"], "majors": ["marketing", "communications"], "languages": ["cantonese", "english", "chinese", "mandarin"], "language_level": ["excellent"], "hard_skills": ["google analytics", "html", "make", "javascript", "sem", "css", "documentations"], "soft_skills": ["communication skills", "self-motivated", "work independently", "good team player", "communication", "presentation skills", "learning", "customer service", "proactive", "fast learner"], "languages_combined": [{"language": "cantonese", "language_level": ["excellent"]}, {"language": "english", "language_level": ["excellent"]}, {"language": "chinese", "language_level": ["excellent"]}, {"language": "mandarin", "language_level": ["excellent"]}]}, "experience_required": {"duration": ["0-2 years"], "field": ["customer service", "digital marketing", "writing"]}}, {"job_id": "100003008938036", "location_code": "hk", "company": "AXA China Region Insurance Company Limited", "job_title": "Business Development Manager (HK or China Division)", "description": "We are seeking to recruit a SEM manager to manage the global SEM campaign for international investment firm. This is an exciting opportunity to be a part of a fast moving and dynamic team and to work with industry leaders.\u00a0\n\nResponsibilities:\n\n\nDevelop, implement and execute paid search marketing campaigns across multiple search engines.\u00a0\nOptimize the paid campaign from campaign, ad group, keyword and ad level to achieve target CPL and CPA.\u00a0\u00a0\nWork with translation agency and regional manager to ensure local campaigns are executed and optimized\u00a0\nDrive strategy to grow existing SEM channels, as well as strategy for testing and growing new paid marketing channels\u00a0\nUtilize various banner for AB testing, bidding strategies, and keyword management on PPC search engines.\u00a0\nQualifications:\n\n3+\u00a0years experience\u00a0in SEM handling monthly of budget US$250,000+\u00a0\nHands-on experience with Google AdWords, Bing Ad,\u00a0Adroll.\u00a0\nHands-on experience with Baidu, Qihoo 360 and PPC tool like Kenshoo, Marin Software are a plus\u00a0\nExcellent verbal and written communication in English & Chinese\u00a0\nWorking experience in Financial Service is a plus\u00a0\n\n\n\nWe offer an exciting career opportunity and competitive remuneration to the successful candidate. Please send us your detailed resume with current and expected salary by clicking \u201cApply Now\u201d\n\nAll information provided will be treated in strict confidence and used solely for the recruitment purposes.", "employment_types": ["Full Time", "Permanent"], "selling_points": ["Manage Corporate Business Account", "Professional Financial Services Provision", "5 years working experience is required"], "locations": ["Kwun Tong"], "categories": ["Media & Advertising", "Media Buying", "Print Media", "Photography / Video"], "post_time": "2021-12-26T16:20:31Z", "salary": {"currency": null, "max": null, "min": null, "period": "monthly", "term": null}, "salary_visible": false, "title_keywords": ["business development manager"], "responsibilities": ["management", "software", "budget", "testing", "develop", "communication", "marketing campaigns", "sem"], "requirements": {"degrees": [], "majors": [], "languages": ["english", "chinese"], "language_level": ["excellent"], "hard_skills": ["plus", "adwords", "cpl", "cpa", "dynamic", "sem", "translation"], "soft_skills": ["communication", "hands-on", "dynamic"], "languages_combined": [{"language": "english", "language_level": ["excellent"]}, {"language": "chinese", "language_level": ["excellent"]}]}, "experience_required": {"duration": ["3+ years"], "field": ["financial"]}}, {"job_id": "100003008989967", "location_code": "hk", "company": "Grey Anderson Limited", "job_title": "HEAD OF GLOBAL MEDIA PLANNING & BUYING (SHENZHEN)", "description": "DESCRIPTION\n\n\u00a0\u00a0\u00a0\u00a0\u00a0\u00a0\u00a0Pre-sale & post-sale planning, organizing and executing social & digital campaigns\n\u00a0\u00a0\u00a0\u00a0\u00a0\u00a0\u00a0Liaise with 3rd Party (KOLs, publishers, vendors, etc.) for collaboration\n\u00a0\u00a0\u00a0\u00a0\u00a0\u00a0\u00a0Developing, managing and executing strategic digital marketing plans and market research\n\u00a0\u00a0\u00a0\u00a0\u00a0\u00a0\u00a0Working closely with the company\u2019s professional team on implementing the\u00a0client strategy and marketing plan\n\u00a0\u00a0\u00a0\u00a0\u00a0\u00a0\u00a0Preparing marketing data-mining and presentation materials, manage and update the contents on company\u2019s social media platforms and company\u2019s website\n\u00a0\u00a0\u00a0\u00a0\u00a0\u00a0\u00a0Building or enhancing good relationships with business partners and explore new business opportunities\n\u00a0\u00a0\u00a0\u00a0\u00a0\u00a0\u00a0Strengthening the Company's reputation and branding in the industry\n\nREQUIREMENTS\n\n\u00a0\u00a0\u00a0\u00a0\u00a0\u00a0\u00a0Degree holder, preferably in business or corporate administration, marketing or public relation\n\u00a0\u00a0\u00a0\u00a0\u00a0\u00a0\u00a01-2 years\u2019 solid digital marketing, business development experience\u00a0\n\u00a0\u00a0\u00a0\u00a0\u00a0\u00a0\u00a0Able to work independently on daily correspondence, proactive and with excellent communication skills\n\u00a0\u00a0\u00a0\u00a0\u00a0\u00a0\u00a0Strong interest in influencer & digital marketing trend\n\u00a0\u00a0\u00a0\u00a0\u00a0\u00a0\u00a0Mature, high ethical standard, a good team player\n\u00a0\u00a0\u00a0\u00a0\u00a0\u00a0\u00a0Pleasant, detail oriented, well organized and strong sense of responsibility\n\u00a0\u00a0\u00a0\u00a0\u00a0\u00a0\u00a0Proficiency in MS office and various social media\n\u00a0\u00a0\u00a0\u00a0\u00a0\u00a0\u00a0Good command of English and Chinese and Putonghua\n\u00a0\u00a0\u00a0\u00a0\u00a0\u00a0\u00a0Fresh Graduates are welcomed", "employment_types": ["Permanent"], "selling_points": ["Fast-growing listed Company", "A global position", "Manage a large team"], "locations": ["Others"], "categories": ["Media & Advertising", "Media Buying", "Strategic Planning", "Marketing / Public Relations", "Digital Marketing"], "post_time": "2021-12-21T07:02:12Z", "salary": {"currency": null, "max": null, "min": null, "period": "monthly", "term": null}, "salary_visible": false, "title_keywords": [], "responsibilities": ["explore new business opportunities", "data", "social media platforms", "developing", "market research", "website", "marketing plan", "executing", "digital marketing", "digital campaigns", "contents", "liaise with", "plans", "planning"], "requirements": {"degrees": ["degree holder"], "majors": ["business", "marketing"], "languages": ["putonghua", "english", "chinese"], "language_level": ["good command"], "hard_skills": ["ms office"], "soft_skills": ["communication skills", "work independently", "good team player", "sense of responsibility", "detail oriented", "well organized", "mature", "pleasant", "ethical", "proactive"], "languages_combined": [{"language": "putonghua", "language_level": ["good command"]}, {"language": "english", "language_level": ["good command"]}, {"language": "chinese", "language_level": ["good command"]}]}, "experience_required": {"duration": ["1-2 years"], "field": ["business development", "digital marketing"]}}, {"job_id": "100003008989125", "location_code": "hk", "company": "EternityX Marketing Technology Limited", "job_title": "Senior Account Executive - Digital Marketing", "description": "Our client is a leading global financial trading platform. They are currently looking for Digital Marketing Manager to join their team. Candidates with more experience will be considered as Senior Manager.\n\n\nJob Description\n\nDevelop and execute overall digital marketing strategies for Greater China & Korea Market\nWork closely with the global digital team and manage both internal and external resources to develop marketing efforts spanning across PPC, Programmatic and Display media\nPerform day-to-day execution, management, expansion and in-depth analysis of all paid digital media activities coping closely with agency and media partners, including creative copywriting, media evaluation, A/B testing, campaign trafficking, media cue, optimization, and reporting\nDrive in-depth analysis, prepare reports and dashboards of paid advertisement campaigns\nIdentify new opportunities and review marketing strategies with up-to-date industry trends\n\nJob Requirements\n\nBachelor Degree holder\n5+ years of related experience with solid digital marketing experience for China Market\nProven experience in developing display and paid media plans, performance marketing and acquisition marketing\nExperience in managing marketing budget is a MUST\nExperience gained from financial industries, or fintech platforms will be a definite advantage\nHands-on experience in DoubleClick Campaign Manager and Google Analytics 360\nHighly proficient in both written and spoken English & Chinese (Mandarin & Cantonese)\nCandidate with more experience will be considered as Senior Manager", "employment_types": ["Full Time"], "selling_points": ["Competitive salary & Performance Bonus", "Fast Promotion Path", "Peaceful and Happy Work Environment"], "locations": ["Sheung Wan"], "categories": ["Media & Advertising", "Account Servicing", "Media Buying", "Marketing / Public Relations", "Digital Marketing"], "post_time": "2021-12-21T02:48:24Z", "salary": {"currency": null, "max": null, "min": null, "period": "monthly", "term": null}, "salary_visible": false, "title_keywords": ["senior account executive", "digital marketing"], "responsibilities": ["reporting", "management", "digital marketing strategies", "marketing strategies", "analysis", "review", "develop", "testing", "evaluation", "prepare reports"], "requirements": {"degrees": ["bachelor degree holder"], "majors": [], "languages": ["cantonese", "english", "chinese", "mandarin"], "language_level": ["proficient"], "hard_skills": ["google analytics"], "soft_skills": ["hands-on"], "languages_combined": [{"language": "cantonese", "language_level": ["proficient"]}, {"language": "english", "language_level": ["proficient"]}, {"language": "chinese", "language_level": ["proficient"]}, {"language": "mandarin", "language_level": ["proficient"]}]}, "experience_required": {"duration": ["5+ years"], "field": ["related", "developing", "marketing", "digital marketing", "media", "financial"]}}, {"job_id": "100003008986432", "location_code": "hk", "company": "AsiaPac Net Media Ltd", "job_title": "Sr. Digital/ Digital Performance Executive (Online Ad/ Digital Marketing/ SEM/ SEO/ Programmatic)", "description": "Responsibilities:\n\nDeliver a consistent standard media planning and buying service for the business\nEnsure the working media budget is efficiently and effectively optimized\nEnsure the highest possible return on investment for the company media to contribute to increasing market penetration and competitive presence\nEnsure that the global brand directives can be effectively and efficiently brought to life in the market, through the right media agency resource\nLead a team of media planners and ads placement to support the brand team in media investment decisions\nActively advise Brand and Marketing managers on Media opportunities\nLead the team to execute the media plans with both in-house resources and external media agencies\n\nRequirements:\n\nAt least 10 years of relevant experience including people management and leadership skills\u00a0\u00a0\nExperience in Media or Digital agencies / Advertisers Media Management or Media Company / Media Research Agencies\nExperience with international (Euro, US etc.) media planning and buying is a must\nStrong negotiating skills as well as the ability to analyse disparate streams of data is needed\nStrategic thinking for alignment with the company's long term objectives\nPassionate for media planning and buying with high levels of integrity, autonomy, and self-motivation\nExcellent analytical, organizational, project management and time management skills\nSharp communication skills are requisite with fluency in English and Chinese", "employment_types": ["Full Time"], "selling_points": ["Manage digital marketing accounts", "Equip basic knowledge of Google Adwords, SEM, SEO", "Serve and liaise with good portfolio of clients"], "locations": ["Lai Chi Kok"], "categories": ["Media & Advertising", "Account Servicing", "Media Buying", "Marketing / Public Relations", "Digital Marketing"], "post_time": "2021-12-20T03:01:43Z", "salary": {"currency": null, "max": null, "min": null, "period": "monthly", "term": null}, "salary_visible": false, "title_keywords": ["performance executive", "digital marketing"], "responsibilities": ["lead a team", "budget", "plans", "planning"], "requirements": {"degrees": [], "majors": [], "languages": ["english", "chinese"], "language_level": ["fluency"], "hard_skills": ["project management"], "soft_skills": ["passionate", "communication skills", "ability to analyse", "strategic thinking", "time management skills", "organizational", "leadership skills", "integrity", "project management", "self-motivation"], "languages_combined": [{"language": "english", "language_level": ["fluency"]}, {"language": "chinese", "language_level": ["fluency"]}]}, "experience_required": {"duration": ["at least 10 years"], "field": ["management", "research", "people management", "relevant experience", "digital", "media"]}}, {"job_id": "100003008988021", "location_code": "hk", "company": "Perfect Shape (Holdings) Limited", "job_title": "Digital Marketing Assistant - China market (IANG / Fresh Graduates are welcome)", "description": "Job Responsibilities :\n\nExecute all aspects of digital media campaign executions across different channels\nPerform digital media planning, buying across all products and platforms in the market\nPerform fundamental support for pitch, proposal and projects on a local, national and international basis\nProvide in-\u00addepth analysis to get insights using all obtainable analytics tools.\nAssist Senior Account Manager to achieve all campaign objectives through close monitoring and frequent optimisations.\nProvide clients servicing and answer enquires for corporate clients, advertising agencies and resellers at both local and regional level.\nDeliver accurate updates on campaigns to clients on both overall business and daily campaign performance\nBuild strong, long-term client relationships and maintain frequent contact\n\n\n\nRequirements:\n\n2 years or above experience in a media agency and/or digital marketing related fields.\n\nExperience for working in 4As agency is preferable\nExperience in operating digital advertising platform, (such as\u00a0Facebook, Google, DBM, The Trade Desk...etc) is preferable\nExperience in handling China Related Media platforms (such as\u00a0Baidu, Wechat, Weibo, 360...etc) is preferable\nAble to communicate in Cantonese, English & Mandarin.\nProficient in Chinese language (Simplified & Traditional) and fluent in English.\nStrong interpersonal skills with great attention to details.\nMulti-tasking and able to work under pressure to meet deadlines & business targets.\nPassionate about the Internet and latest online advertising technologies.\n\nBenefits:\n\n5 days Work + Bank Holidays\nCompetitive Remuneration Package & Performance Bonus\nMedical and Dental Insurance after passing probation\nOvertime Meal and Transportation allowance\nProfessional Training in digital marketing & related Technology\nFast track career progression in this growing industry\nEnergetic, Fun, Young, Fast-paced environment", "employment_types": ["Full Time"], "selling_points": ["Solid knowledge in Wechat, Xiaohongshu, Weibo", "Expert in Social media", "Ability to work independently"], "locations": ["Mong Kok"], "categories": ["Media & Advertising", "Media Buying", "Marketing / Public Relations", "Marketing - Market Research", "Digital Marketing"], "post_time": "2021-12-20T08:56:54Z", "salary": {"currency": null, "max": null, "min": null, "period": "monthly", "term": null}, "salary_visible": false, "title_keywords": ["digital marketing", "assistant"], "responsibilities": ["analytics tools", "advertising", "analysis", "monitoring", "maintain", "contact", "planning"], "requirements": {"degrees": [], "majors": [], "languages": ["cantonese", "english", "chinese", "mandarin"], "language_level": ["fluent", "proficient"], "hard_skills": ["facebook", "wechat"], "soft_skills": ["multi-tasking", "interpersonal skills", "attention to details", "meet deadlines", "passionate about", "work under pressure"], "languages_combined": [{"language": "cantonese", "language_level": []}, {"language": "english", "language_level": ["fluent", "proficient"]}, {"language": "chinese", "language_level": ["fluent", "proficient"]}, {"language": "mandarin", "language_level": []}]}, "experience_required": {"duration": ["2 years"], "field": ["advertising", "agency", "related", "digital marketing", "digital", "media"]}}, {"job_id": "100003008987640", "location_code": "hk", "company": "BTCC Limited", "job_title": "Performance Marketing Officer (in house)", "description": "Responsibilities:\n\nDevelop creative ideas and\u00a0contents for brand promotions on social media platforms;\nPlan and execute\u00a0creative digital marketing campaigns\u00a0and effective content distribution strategy;\nPlan and implement outbound and inbound digital marketing activities by demonstrating expertise\n\nRequirements:\n\nDiploma or above in any disciplines;\nRelevant experience / knowledge in marketing and social media is an advantage;\nFamiliar with China social media (Wechat / Weibo / Douyin / Xiaohongshu / Dianping) is compulsory;\nGood communication skills, presentable, result-oriented and able to work under pressure;\nWelcome Fresh graduate & Mainland China graduates (IANG);\nMore experience will be considered as Marketing Executive\n\nWe offer attractive remuneration package to the right candidate. Interested parties please send your full resume with present and expected salary by clicking\u00a0'Apply Now'\n\nPersonal information collected will be used for recruitment purpose only.", "employment_types": ["Full Time", "Permanent"], "selling_points": ["Advertising agency background preferred", "Monitor budget & performance of paid-ad campaigns", "Expand paid channels and acquire new sources"], "locations": ["Admiralty"], "categories": ["Media & Advertising", "Media Buying", "Strategic Planning", "Marketing / Public Relations", "Digital Marketing"], "post_time": "2021-12-20T07:21:30Z", "salary": {"currency": null, "max": null, "min": null, "period": "monthly", "term": null}, "salary_visible": false, "title_keywords": ["marketing officer"], "responsibilities": ["digital marketing campaigns", "social media platforms", "digital marketing", "plan", "contents", "develop creative ideas"], "requirements": {"degrees": ["fresh graduate", "diploma or above"], "majors": ["any disciplines"], "languages": [], "language_level": [], "hard_skills": ["wechat"], "soft_skills": ["work under pressure", "communication skills", "result-oriented", "presentable"], "languages_combined": []}, "experience_required": {"duration": [], "field": ["social media", "marketing", "relevant experience"]}}, {"job_id": "100003008988508", "location_code": "hk", "company": "HK01 Company Limited", "job_title": "\u8a18\u8005 (\u89aa\u5b50\u8a71\u984c)", "description": "Responsibilities:\n\nManage the performance of a portfolio of programmatic and ad network partners for global new user acquisition campaigns;\nMonitor budget distribution and performance of paid-ad campaigns;\nRecommend app install and in-app engagement campaigns optimizations and run A/B tests accordingly;\nMaintain relationship with existing advertising agency / partners and leverage their performance by providing insight from internal reports;\nExpand paid channels, able to acquire new paid media sources;\nAble to pull and analyze the data and gain insights from the data;\nIdentify market opportunities for acquisition growth;\nAssist in performing day-to-day optimization efforts to meet campaign objectives;\nExperiment and identify channels to test, running tests, performing customer / audience segmentation analysis, developing social media presence, and finding ways to optimize paid channels.\nRequirements:\n\nDegree in marketing, mass communications or related discipline;\n2+ years' paid media advertising in overseas markets, mobile-app preferred but not a must;\nStrong analytical skills, with a data-driven and strategic mindset particularly for consumer insights and business growth;\nUser-focused and product-driven: strong understanding of product, technology, platform and audience;\nIndependent, attentive to details and self-motivated;\nEnergetic with can-do attitude and team spirit;\nStrong communication skills in English and Mandarin;\nCandidates from marketing agencies are welcome.\nWe offer:\n\n5 days work\n13-21 days annual leave\nDiscretionary bonus\nFestival cash incentives\nFull-paid sick leave\nMarriage leave\nCompassionate leave\nMedical insurance\nDental scheme\nWFH policy", "employment_types": ["Full Time", "Permanent"], "selling_points": ["\u64b0\u5beb\u89aa\u5b50\u76f8\u95dc\u53ca\u71b1\u9580\u4e4b\u5167\u5bb9", "\u5c0d\u89aa\u5b50\u5177\u6fc3\u539a\u8208\u8da3", "\u63d0\u4f9b\u8077\u696d\u767c\u5c55\u6a5f\u6703\uff0c\u53ca\u6709\u7af6\u722d\u529b\u7684\u85aa\u916c"], "locations": ["Tsuen Wan Area"], "categories": ["Media & Advertising", "Media Buying", "Strategic Planning", "Editorial / Journalism"], "post_time": "2021-12-20T11:13:49Z", "salary": {"currency": null, "max": null, "min": null, "period": "monthly", "term": null}, "salary_visible": false, "title_keywords": ["\u8a18\u8005"], "responsibilities": ["social media", "advertising", "data", "analysis", "budget", "monitor", "developing", "maintain", "reports"], "requirements": {"degrees": ["degree"], "majors": ["marketing", "communications"], "languages": ["english", "mandarin"], "language_level": [], "hard_skills": ["mobile", "analytical skills"], "soft_skills": ["communication skills", "self-motivated", "team spirit", "independent", "attentive to details", "focused", "can-do attitude", "analytical skills", "energetic", "driven"], "languages_combined": [{"language": "english", "language_level": []}, {"language": "mandarin", "language_level": []}]}, "experience_required": {"duration": [], "field": []}}]