[{"job_id": "100003009054336", "location_code": "hk", "company": "BCI Asia Construction Information Limited", "job_title": "Publication Content Editor (Freelance)", "description": "The Candidate\n\nWe are seeking a motivated and savvy Freelance Content Editor to support our publishing needs for a quarterly architectural publication. We prefer a candidate with experience in architectural/design writing/editing and/or work experience in architecture/building design.\n\nYou will work with a team to curate and develop compelling and engaging content for our audience. Your primary duties will include developing content, editing, proofreading, writing for our print and digital magazines/media.\n\nResponsibilities:\n\nDevelop content; write, edit and proofread (fact-check, spelling, grammar/syntax) following BCI\u2019s house style for a quarterly architectural publication.\nInterview 5-6 clients for publication quarterly.\nTo understand basic rules of content presentation/layout/format for readers\u2019 experience according to BCI\u2019s house style.\nEnsure that content is accurate and factual while adding value to readers and increase their knowledge, and meet the company\u2019s and/or clients\u2019 needs.\nWork with marketing and graphic design teams to ensure appealing and user-friendly readers\u2019 experience.\nCollaborate with co-workers and come up with fresh, creative content ideas, keeping our audience in mind.\nManage workload according to deadlines.\n\nRequirements:\n\nWork experience in architectural/design writing/editing AND/OR work experience in architecture/building design related fields.\nBachelor's Degree in Journalism, English OR Bachelor\u2019s Degree in Architecture/Design with work experience in writing/editing.\nExcellent command of the English language in writing and speaking.\nWriting, copy editing, editing and proofreading experiences.\nPositive attitude; adaptable to change; diligent and resourceful.\nGood communication and interpersonal skills.\nHighly organized and detail-oriented.\nProficient in desktop publishing software.\nProficient in Microsoft Office.\n\nIf you are interested, please apply with you cover letter explaining about yourself and your expected salary, together with your CV. Thank you.\n\nONLY SHORTLISTED CANDIDATE WILL BE NOTIFIED.", "employment_types": ["Freelance"], "selling_points": ["Remote Working", "Freelance job", "With experience in architecture design writing"], "locations": ["Hung Hom"], "categories": ["Media & Advertising", "Others", "Editorial / Journalism", "Print Media"], "post_time": "2022-01-17T09:11:39Z", "salary": {"currency": null, "max": null, "min": null, "period": "monthly", "term": null}, "salary_visible": false, "title_keywords": ["content editor"], "responsibilities": ["collaborate with", "ideas", "creative content", "graphic design", "teams", "develop", "publication"], "requirements": {"degrees": ["degree", "bachelor"], "majors": ["journalism", "architecture", "design"], "languages": ["english"], "language_level": ["excellent"], "hard_skills": ["microsoft office"], "soft_skills": ["organized", "resourceful", "adaptable", "diligent", "detail-oriented", "positive attitude", "communication and interpersonal skills"], "languages_combined": [{"language": "english", "language_level": ["excellent"]}]}, "experience_required": {"duration": [], "field": ["related", "editing", "writing", "design"]}}, {"job_id": "100003009053523", "location_code": "hk", "company": "Chinese Bible International Limited", "job_title": "\u7de8\u8f2f/\u52a9\u7406\u7de8\u8f2f/\u7ffb\u8b6f", "description": "About the job\n\nThe right candidate is responsible for overseeing the development of a media platform business goals and objectives. The typically work is to increase business revenue, identify and develop business opportunities. Other duties and responsibilities may include establishing effective company policies, goals, and sales targets. Business directors are also expected to negotiate contracts with clients and suppliers and propose and develop new partnerships.", "employment_types": ["Full Time"], "selling_points": [], "locations": ["Not Specified"], "categories": ["Media & Advertising", "Others", "Editorial / Journalism"], "post_time": "2022-01-17T07:05:54Z", "salary": {"currency": null, "max": null, "min": null, "period": "monthly", "term": null}, "salary_visible": false, "title_keywords": ["\u7de8\u8f2f"], "responsibilities": ["business goals", "other duties", "policies", "business opportunities", "contracts", "develop"], "requirements": {"degrees": [], "majors": [], "languages": [], "language_level": [], "hard_skills": [], "soft_skills": ["responsible"], "languages_combined": []}, "experience_required": {"duration": [], "field": []}}, {"job_id": "100003009053140", "location_code": "hk", "company": "ORIENTAL HUMAN RESOURCES LIMITED", "job_title": "Reporter Trainee - Entertainment News", "description": "Responsible for reporting entertainment news articles\nUniversity or College graduate\nGood command of Chinese and English\nFamiliar with entertainment news\nKnowledge of Chinese word processing\nInitiative and possess good communication skills\nShift duty and rotated rest day are required\n\nApplication Method\n\nWe offer free shuttle bus, free parking and fringe benefits including medical scheme, discretionary bonus and public holidays\u00a0to the right candidate. Interested parties, please send full resume with expected salary to ORIENTAL HUMAN RESOURCES LIMITED\u00a0by\u00a0clicking \"Apply now\" ;\u00a0or fax to 3600 1900 ( Please quote reference on the application letter )\n\n\nPersonal Information Collection Statement\n\nPersonal data collected will be treated in accordance with our Personal Data Policy and handled in strict confidence by authorized personnel for recruitment related purpose only.\u00a0 \u00a0 \u00a0\n\u00a0 \u00a0 \u00a0 \u00a0 \u00a0 \u00a0\n\n\u00a0 \u00a0 \u00a0 \u00a0 \u00a0 \u00a0 \u00a0 \u00a0 \u00a0 \u00a0 \u00a0 \u00a0 \u00a0 \u00a0 \u00a0 \u00a0 \u00a0 \u00a0 \u00a0 \u00a0 \u00a0 \u00a0 \u00a0 \u00a0 \u00a0 \u00a0 \u00a0\u00a0on.cc\n\n", "employment_types": ["Full Time"], "selling_points": [], "locations": ["Tai Po Area"], "categories": ["Media & Advertising", "Creative / Design", "Others", "Editorial / Journalism"], "post_time": "2022-01-17T08:34:57Z", "salary": {"currency": null, "max": null, "min": null, "period": "monthly", "term": null}, "salary_visible": false, "title_keywords": ["reporter", "trainee"], "responsibilities": ["communication", "reporting"], "requirements": {"degrees": [], "majors": [], "languages": ["english", "chinese"], "language_level": ["good command"], "hard_skills": ["chinese word processing"], "soft_skills": ["communication skills", "initiative", "responsible"], "languages_combined": [{"language": "english", "language_level": ["good command"]}, {"language": "chinese", "language_level": ["good command"]}]}, "experience_required": {"duration": [], "field": []}}, {"job_id": "100003009052861", "location_code": "hk", "company": "Sing Tao Management Services Limited", "job_title": "\u8a18\u8005 (\u982d\u689d\u65e5\u5831-\u4e2d\u570b\u53ca\u570b\u969b\u65b0\u805e)", "description": "\u8077\u8cac\uff1a\n\n\u8ca0\u8cac\u8655\u7406\u4e2d\u570b\u548c\u570b\u969b\u65b0\u805e\u76f8\u95dc\u5831\u9053\n\n\u8981\u6c42\uff1a\n\n\u5927\u5b78\u7562\u696d\uff0c\u4e3b\u4fee\u8a9e\u8a00\u6216\u65b0\u805e\u512a\u5148\u8003\u616e\n\u51771\u5e74\u76f8\u95dc\u7d93\u9a57 (\u4e5f\u6b61\u8fce\u61c9\u5c46\u7562\u696d\u751f)\n\u826f\u597d\u4e2d\u82f1\u6587\u6e9d\u901a\u53ca\u66f8\u5beb\u80fd\u529b\n\u7a4d\u6975\u4e3b\u52d5\u3001\u8655\u4e8b\u7d30\u5fc3\u3001\u5bcc\u8cac\u4efb\u611f\u53ca\u80fd\u65bc\u58d3\u529b\u4e0b\u5de5\u4f5c\n\u80fd\u5373\u6642\u5230\u4efb\u70ba\u4f73\n\u5de5\u4f5c\u5730\u9ede\uff1a\u5c07\u8ecd\u6fb3\u5de5\u696d\u90a8\n\n\u6c42\u8077\u8005\u8acb\u8a73\u9644\u500b\u4eba\u5c65\u6b77\u53ca\u8981\u6c42\u5f85\u9047\uff0c\u5bc4\u9999\u6e2f\u65b0\u754c\u5c07\u8ecd\u6fb3\u5de5\u696d\u90a8\u99ff\u660c\u8857\u4e03\u865f\u661f\u5cf6\u65b0\u805e\u96c6\u5718\u5927\u5ec83\u6a13\u4eba\u529b\u8cc7\u6e90\u90e8\u6536\uff0c\u4fe1\u5c01\u9762\u8acb\u8a3b\u660e\u7533\u8acb\u8077\u4f4d\u6216\u6309\u201cApply Now\u201d\u63d0\u4ea4\u7533\u8acb\u3002\n\n\u672c\u516c\u53f8\u70ba\u516c\u5e73\u6a5f\u6703\u50f1\u4e3b\uff0c\u6b61\u8fce\u6240\u6709\u5408\u8cc7\u683c\u7684\u5019\u9078\u4eba\u7533\u8acb\u3002\u6240\u63d0\u4f9b\u7684\u4fe1\u606f\u5c07\u56b4\u683c\u4fdd\u5bc6\uff0c\u50c5\u7528\u65bc\u62db\u8058\u76f8\u95dc\u7528\u9014\u3002\u82e5\u672a\u80fd\u65bc 6 \u9031\u5167\u7372\u9080\u51fa\u5e2d\u9762\u8a66\u7684\u7533\u8acb\u8005\u6703\u81ea\u52d5\u843d\u9078\uff0c\u53e6\u6240\u6709\u843d\u9078\u7684\u7533\u8acb\u8005\u7684\u6240\u6709\u500b\u4eba\u8cc7\u6599\u5c07\u57286\u500b\u6708\u5167\u92b7\u6bc0\u3002\n\nwww.singtaonewscorp.com", "employment_types": ["Full Time", "Permanent"], "selling_points": [], "locations": ["Sai Kung"], "categories": ["Media & Advertising", "Others", "Editorial / Journalism", "Print Media"], "post_time": "2022-01-17T05:36:05Z", "salary": {"currency": null, "max": null, "min": null, "period": "monthly", "term": null}, "salary_visible": false, "title_keywords": ["\u8a18\u8005"], "responsibilities": [], "requirements": {"degrees": [], "majors": [], "languages": [], "language_level": [], "hard_skills": [], "soft_skills": [], "languages_combined": []}, "experience_required": {"duration": [], "field": []}}, {"job_id": "100003009055205", "location_code": "hk", "company": "New Media Group Publishing Limited", "job_title": "Senior Project Executive/Project Executive (Ad operations/ Social Ad boosting/Digital Marketing)", "description": "Responsibilities:\n\n\nDeveloping creative concepts, visual and artwork for event, coordination of production, social media, campaign, leaflet, poster, packaging, website, etc.\nHandling 2D and 3D design work\nAbility to demonstrate excellence in creativity across multiple media\nImplementation of marketing plans & promotion and supporting Event & Marketing team on product launching\nWorking closely with the project team to ensure smooth daily operations\n\nRequirements:\n\n\nDegree/higher diploma holder in a relevant design discipline\n1-2 years or above working experience in graphic design for print ads, booklets, event backdrops, exhibition, mall decoration, etc.\nHands-on experience in using Adobe CS, particularly in Photoshop and Illustrator\nGood hand drawing skill is preferable\nWith knowledge in multi-media & web design\nGood layout and presentation skill\nProficient in 3D Max/C4D/3D software\nSelf-motivated, creative, independent, be able to work under pressure and meet deadlines\nHaving positive and passionate approach with a can-do attitude\nWilling to work overtime and outside normal office hours\nImmediately is preferable\n\nOffice location: Yau Tong\n\nInterested parties please send your detailed resume, portfolio and expected salary to\u00a0us.\u00a0(All personal data collected will be used for recruitment purpose only)\u00a0", "employment_types": ["Full Time", "Permanent"], "selling_points": ["Social media marketing ad strategies", "Fact-check P&L system & Boosting details", "Great development opportunity, competitive package"], "locations": ["Kwun Tong"], "categories": ["Media & Advertising", "Others"], "post_time": "2022-01-18T01:45:16Z", "salary": {"currency": null, "max": null, "min": null, "period": null, "term": null}, "salary_visible": false, "title_keywords": ["senior project executive", "project executive", "digital marketing", "ad operations"], "responsibilities": ["design work", "social media", "marketing plans", "leaflet", "developing", "website", "implementation", "daily operations", "coordination", "visual"], "requirements": {"degrees": ["degree", "higher diploma holder"], "majors": ["design"], "languages": [], "language_level": [], "hard_skills": ["presentation skill", "web design", "c4d", "3d software", "illustrator", "adobe cs", "max", "photoshop"], "soft_skills": ["presentation skill", "passionate", "self-motivated", "work overtime", "independent", "can-do attitude", "hands-on", "meet deadlines", "creative", "positive", "work under pressure"], "languages_combined": []}, "experience_required": {"duration": ["1-2 years"], "field": ["graphic design", "print", "cs"]}}, {"job_id": "100003009053143", "location_code": "hk", "company": "Omnicom Media Group", "job_title": "Account Manager (Content and Social)", "description": "Job Nature :\u00a0\u00a0\n\nExecute social media marketing ad strategies for clients on Facebook & Instagram\nOperate Social Media Business Manager, Adverts Manager & Power Edit to set campaign and creative\nFact-check P&L system & Boosting details\u00a0\nControl Facebook marketing spend and monitor performance; conduct report and analysis\nKeep up-to-date social media trend and provide business opportunity insight from Facebook & Instagram updates\n\nCharacters / Qualifications:\u00a0\n\nDegree holder\nEfficiency in MS applications including PowerPoint & Excel\nDigital and online knowledge\u00a0\nFamiliar with Facebook advertising formats and functions would be an advantage\u00a0\nWilling to work overtime and capable to work under tight schedule\nExcellent communication and interpersonal skills to be able to coordinate and work toward to achieve goals\nProficient in written and spoken English and Chinese\nCandidate with less experienced will be considered as project executive.\u00a0\n\n", "employment_types": ["Full Time", "Permanent"], "selling_points": ["Free Shuttle Bus & Free Breakfast", "Birthday, Family Day & Self-Love Day Leave", "5-Day Work Week"], "locations": ["Pok Fu Lam"], "categories": ["Media & Advertising", "Account Servicing", "Creative / Design", "Others"], "post_time": "2022-01-17T06:11:49Z", "salary": {"currency": null, "max": null, "min": null, "period": "monthly", "term": null}, "salary_visible": false, "title_keywords": ["account manager"], "responsibilities": ["social media", "control", "advertising", "monitor performance", "analysis", "p&l", "communication", "coordinate", "schedule", "facebook", "report"], "requirements": {"degrees": ["degree holder"], "majors": [], "languages": ["english", "chinese"], "language_level": ["proficient"], "hard_skills": ["excel", "ms applications", "analysis", "powerpoint", "facebook"], "soft_skills": ["work overtime", "creative", "capable", "communication and interpersonal skills"], "languages_combined": [{"language": "english", "language_level": ["proficient"]}, {"language": "chinese", "language_level": ["proficient"]}]}, "experience_required": {"duration": [], "field": []}}, {"job_id": "100003009052275", "location_code": "hk", "company": "New Media Group Publishing Limited", "job_title": "Project Editor (Sports Trend \u904b\u52d5\u6f6e\u6d41\uff09", "description": "Requirements\n\nDegree holder in marketing communications/ advertising/ journalism/\u00a0media related disciplines\n1 year relevant work experience in media agency or media sales\nFresh graduate is also considered\nFluent in both written and spoken English and Chinese\nExcellent PC skills of MS Word, Excel and PowerPoint\nAttentive to details, sensitive to figures, responsible, willing to work overtime and under pressure\n\n\n\nJob Duties\n\nMedia booking and materials follow up\nDaily coordination and liaison with external media partners and media vendors\nPreparation of competitive reports and post buy reports to clients\nProvide support on clerical works, handle monthly billing and material flow when needed\nGather market information for the regular media and research updates\n\n\n\nInterested applicants please send full resume with expected salary by clicking \u201cAPPLY NOW\u201d or by post to Administration Director, 25/F., Prosperity Millennia Plaza, 663 King\u2019s Road, North Point, Hong Kong.\n\nPersonal data collected will be used for recruitment purpose only.", "employment_types": ["Full Time", "Permanent"], "selling_points": ["Handling clients project, Strong digital knowledge", "Have good connections with KOLs and Sports pages", "Great development opportunity, competitive package"], "locations": ["Kwun Tong"], "categories": ["Media & Advertising", "Others", "Editorial / Journalism", "Marketing / Public Relations", "Digital Marketing"], "post_time": "2022-01-17T02:37:40Z", "salary": {"currency": null, "max": null, "min": null, "period": null, "term": null}, "salary_visible": false, "title_keywords": ["editor"], "responsibilities": ["provide support", "market information", "reports", "booking", "coordination", "recruitment", "personal data", "administration"], "requirements": {"degrees": ["fresh graduate", "degree holder"], "majors": ["marketing communications", "related disciplines", "journalism"], "languages": ["english", "chinese"], "language_level": ["fluent"], "hard_skills": ["excel", "pc skills", "powerpoint", "ms word"], "soft_skills": ["work overtime", "under pressure", "attentive to details", "responsible", "sensitive to figures"], "languages_combined": [{"language": "english", "language_level": ["fluent"]}, {"language": "chinese", "language_level": ["fluent"]}]}, "experience_required": {"duration": ["1 year"], "field": ["agency", "media", "media sales"]}}, {"job_id": "100003009052295", "location_code": "hk", "company": "Tianda Institute", "job_title": "\u7814\u7a76\u90e8\u4e3b\u4efb Director of Research Department", "description": "Job Nature:\u00a0\u00a0\n\nResponsible for daily management of CS Content for social media platform\nProduce content video included writing script, web-articles and social-media contents\nWork close with content partnership and keep daily publish schedule run smooth\nHandling clients project, various ad hoc projects under tight schedule independently\nWork closely with internal parties and sales team\nGenerate regular content reports /\u00a0 CS reports for performance analysis\n\nCharacters / Qualifications:\n\n\nBachelor degree holder, preferably in journalism\nOver 1 years experience on lifestyle / sports reporting or editing\nStrong digital and online knowledge\nGood understanding of social Media environment and multi media industries\nGood communication skill\nHave good connections with KOLs and Sports pages\n\nWe offer competitive salary and benefits package( 5 days work, 14 days AL up, birthday leave, medical & dental insurance) with great opportunity for career development to the successful candidate.\n\nPlease send your detailed resume and expected salary to our Human Resources Department by clicking \"Apply Now\" (please put position applied on subject line).", "employment_types": ["Full Time"], "selling_points": [], "locations": ["Central"], "categories": ["Media & Advertising", "Others", "Professional Services", "Business Analysis / Data Analysis", "Editorial / Journalism"], "post_time": "2022-01-17T02:39:44Z", "salary": {"currency": null, "max": null, "min": null, "period": "monthly", "term": null}, "salary_visible": false, "title_keywords": ["director"], "responsibilities": ["social media", "management", "reporting", "analysis", "communication", "ad hoc projects", "schedule", "sales team", "contents", "reports", "career development", "editing", "insurance", "internal parties"], "requirements": {"degrees": ["bachelor degree holder"], "majors": ["journalism"], "languages": [], "language_level": [], "hard_skills": ["analysis", "web"], "soft_skills": ["independently", "responsible", "communication skill", "smooth", "detailed"], "languages_combined": []}, "experience_required": {"duration": ["1 years"], "field": ["editing"]}}, {"job_id": "100003009053813", "location_code": "hk", "company": "Quko Int'l Development Limited", "job_title": "\u92b7\u552e\u5de5\u7a0b\u5e2b**", "description": "\u5929\u5927\u7814\u7a76\u9662\u662f\u4e00\u5bb6\u8a2d\u7acb\u65bc\u9999\u6e2f\u7684\u516c\u76ca\u6027\u6230\u7565\u7814\u7a76\u667a\u5eab\uff0c\u8457\u91cd\u65bc\u5b8f\u89c0\u6230\u7565\u554f\u984c\u53ca\u61c9\u7528\u6027\u653f\u7b56\u8ab2\u984c\u7684\u524d\u77bb\u6027\u7814\u7a76\u3002\u7814\u7a76\u9818\u57df\u5305\u62ec\u570b\u969b\u548c\u5b89\u5168\u6230\u7565\u3001\u7d93\u6fdf\u548c\u91d1\u878d\u6230\u7565\u3001\u793e\u6703\u554f\u984c\u548c\u516c\u5171\u653f\u7b56\u3001\u8cc7\u6e90\u548c\u74b0\u5883\u3001\u6e2f\u6fb3\u81fa\u554f\u984c\u7b49\uff0c\u4e26\u51fa\u7248\u300a\u5929\u5927\u5831\u544a\u300b\u3002\u7814\u7a76\u9662\u5e0c\u671b\u901a\u904e\u5c0d\u4e2d\u570b\u548c\u5168\u7403\u554f\u984c\u7684\u6df1\u5ea6\u601d\u8003\u3001\u63a2\u8a0e\u548c\u7814\u7a76\uff0c\u63d0\u51fa\u65b0\u89c0\u9ede\u3001\u65b0\u601d\u60f3\u548c\u65b0\u8209\u63aa\uff0c\u70ba\u6c11\u65cf\u5fa9\u8208\u3001\u570b\u5bb6\u767c\u5c55\u8207\u4e16\u754c\u548c\u5e73\u670d\u52d9\u3002\n\u00a0\n\u73fe\u8aa0\u8058\u7814\u7a76\u90e8\u4e3b\u4efb\uff0c\u7d71\u7c4c\u7814\u7a76\u5de5\u4f5c, \u8ca0\u8cac\u7d44\u7e54\u5be6\u65bd\u7814\u7a76\u8a08\u5283\uff0c\u6309\u9032\u5ea6\u5b8c\u6210\u7814\u7a76\u5831\u544a, \u5f62\u6210\u6709\u5f71\u97ff\u529b\u7684\u7814\u7a76\u6210\u679c\uff1b\u5bc6\u5207\u95dc\u6ce8\u570b\u5167\u5916\u653f\u7b56\u767c\u5c55\u52d5\u614b\u8207\u8da8\u52e2, \u5236\u5b9a\u8ab2\u984c\u548c\u9805\u76ee\u7814\u7a76\u8a08\u5283\uff1b\u7d44\u7e54\u6216\u53c3\u52a0\u5404\u7a2e\u7814\u8a0e\u6d3b\u52d5\u3002\u00a0\n\u00a0 \u00a0\n\u7533\u8acb\u4eba\u61c9\u64c1\u6709\u5168\u7403\u77e5\u540d\u5927\u5b78\u535a\u58eb\u5b78\u6b77\uff0c\u5177\u570b\u5167\u80cc\u666f\u8005\u512a\u5148\uff1b\u9808\u5177\u509910\u5e74\u4ee5\u4e0a\u653f\u7b56\u7814\u7a76\u6216\u76f8\u95dc\u5de5\u4f5c\u7d93\u9a57\uff0c\u6709\u51fa\u8272\u7684\u4e2d\u82f1\u6587\u8868\u9054\u80fd\u529b\uff0c\u7368\u7acb\u7814\u7a76\u80fd\u529b\u7a81\u51fa, \u66fe\u767c\u8868\u9ad8\u8cea\u91cf\u4e2d\u82f1\u6587\u51fa\u7248\u7269\uff0c\u5177\u5099\u51fa\u8272\u7684\u7814\u7a76\u9805\u76ee\u5354\u8abf\u53ca\u7ba1\u7406\u80fd\u529b\u3002\u00a0\n\u00a0 \u00a0\n\u5929\u5927\u7814\u7a76\u9662\u63d0\u4f9b5\u5929\u5de5\u4f5c\u9031\u53ca\u512a\u539a\u85aa\u916c\u798f\u5229\u3002\u6709\u610f\u7533\u8acb\u8005\u6309\"Apply Now\" \u63d0\u4ea4\u500b\u4eba\u5c65\u6b77\u3001\u76ee\u524d\u53ca\u671f\u671b\u85aa\u91d1\u3002\u5982\u6b32\u4e86\u89e3\u66f4\u591a\u8a73\u60c5\uff0c\u6b61\u8fce\u53c3\u95b1\u5929\u5927\u7814\u7a76\u9662\u5b98\u65b9\u7db2\u9801https://www.tiandainstitute.org\u3002\u901a\u904e\u521d\u6b65\u7be9\u9078\u4e4b\u7533\u8acb\u4eba\u5c07\u57284\u9031\u5167\u6536\u5230\u901a\u77e5\u3002", "employment_types": ["Full Time"], "selling_points": [], "locations": ["Kwun Tong"], "categories": ["Media & Advertising", "Others", "Engineering", "Others", "Sales, CS & Business Devpt", "Others"], "post_time": "2022-01-17T07:34:10Z", "salary": {"currency": null, "max": null, "min": null, "period": "monthly", "term": null}, "salary_visible": false, "title_keywords": [], "responsibilities": [], "requirements": {"degrees": [], "majors": [], "languages": [], "language_level": [], "hard_skills": [], "soft_skills": [], "languages_combined": []}, "experience_required": {"duration": [], "field": []}}, {"job_id": "100003009052953", "location_code": "hk", "company": "Roundtable \u5be6\u653f\u5713\u684c", "job_title": "\u7530\u5317\u8fb0\u8b70\u54e1\u8fa6\u4e8b\u8655 - Office of Hon. Michael Tien - Public Affairs Assistant", "description": "\n\u8077\u8cac :\u4e00\u822c\u92b7\u552e\u5de5\u7a0b\u5e2b\u5de5\u4f5c, \u92b7\u552e\u53ca\u63a8\u5ee3\u5404\u985e\u578b\u5ba4\u5167\u7a7a\u6c23\u8cea\u7d20IAQ\u7522\u54c1\uff0c\u4f8b\u5982\u7a7a\u6c23\u6de8\u5316\u6a5f,\u9ad8\u6548\u7a7a\u6c23\u6de8\u5316\u6bba\u83cc\u6a5f,\u6bba\u83cc\u5668\u548c\u5100\u8868\u7b49\n\n\u8cc7\u6b77 :\u5c08\u4e0a\u6559\u80b2\uff1a\u6587\u6191/\u8b49\u66f8; 2\u5e74\u7d93\u9a57; \u826f\u597d\u7cb5\u8a9e; \u4e00\u822c\u666e\u901a\u8a71; \u826f\u597d\u82f1\u8a9e; \u61c2\u8b80\u5beb\u4e2d\u6587; \u61c2\u8b80\u5beb\u82f1\u6587; Sales experience is preferred, \u5177\u92b7\u552e\u91ab\u7642,\u8b77\u8001,\u6559\u80b2\u7b49\u7522\u54c1\u7d93\u9a57\u512a\u5148\n\n\u5f85\u9047 :\u6bcf\u6708$13,500 - $15,500, \u6709\u9280\u884c\u5047\u671f, \u7259\u79d1\u798f\u5229, \u5728\u8077\u57f9\u8a13, \u91ab\u7642\u4fdd\u96aa \u53ca\u4f63\u91d1, \u661f\u671f\u4e00\u81f3\u4e94: \u4e0a\u53489\u6642\u81f3\u4e0b\u53486\u6642, \u6bcf\u9031\u5de5\u4f5c5\u5929\n\n\u7533\u8acb\u9808\u77e5 :\u6c42\u8077\u8005\u53ef\u96fb\u90f5(Apply Now)\u5c65\u6b77\u8868\u7d66\u7ff9\u9ad8\u570b\u969b\u767c\u5c55\u6709\u9650\u516c\u53f8\u3002\u5982\u8981\u7d22\u53d6\u6536\u96c6\u500b\u4eba\u8cc7\u6599\u8072\u660e, \u8acb\u8207\u7f85\u5c0f\u59d0(Email)\u806f\u7d61\u3002\n\n", "employment_types": ["Full Time"], "selling_points": ["Sense of current affairs preferred", "Fun and exciting work environment", "Fresh graduates are welcome"], "locations": ["Admiralty"], "categories": ["Media & Advertising", "Others", "Public / Civil", "Civil Services", "Marketing / Public Relations", "Public Relations - General / Support"], "post_time": "2022-01-17T04:41:24Z", "salary": {"currency": null, "max": null, "min": null, "period": "monthly", "term": null}, "salary_visible": false, "title_keywords": ["assistant"], "responsibilities": [], "requirements": {"degrees": [], "majors": [], "languages": [], "language_level": [], "hard_skills": [], "soft_skills": [], "languages_combined": []}, "experience_required": {"duration": [], "field": []}}, {"job_id": "100003009055937", "location_code": "hk", "company": "Page Group Hong Kong", "job_title": "Digital Bilingual Copywriter - Top Tier Financial Institution", "description": "Our client is looking for a passionate and determined digital bilingual copywriter to join their winning team. Candidates with adaptability in writing style, able to effectively target a wide range of audiences are highly preferred. The successful candidate will assist in launching a series of new digital features to deliver best in class digital experience.\n\nClient Details\n\nOur client is a world-renowned bank with strong business presence across all financial services sectors in Hong Kong. Its business areas include but not limited to retail banking, commercial banking, wealth management and global private banking.\n\nIt is an excellent opportunity for candidates who have strong communication and written skills in English and Chinese (both traditional and simplified). The successful candidate will be assisting in creating concise and high-quality copies of new digital journeys.\n\nDescription\n\nResponsible for:\n\nCreate customer-centric content to highlight the newly launched digital features and products.\nWorking with different stakeholders within the organisation to develop content for projects\nOwn, edit and provide feedback on work written by other team members\nActing as guardian for the brand tone of voice\n\nProfile\n\nQualifications:\n\nDegree in Marketing / Communication/ Journalism / Language / Related discipline\n3+ years working experience in copy-writing\nStrong communication and written skills in English or Chinese (both Traditional and Simplified)\nExperience in financial services industry is a plus\nReliable, ambitious, and an excellent team player.\n\nJob Offer\n\nConvenient working location\nGreat career prospect\nResourceful organisation\n\nTo apply online please click the 'Apply' button below. For a confidential discussion about this role please contact Crystal Cheuk on +852 2258 3536", "employment_types": ["Full Time", "Temporary"], "selling_points": ["Tier 1 bank", "Strong user experience mindset", "Convenient working location"], "locations": ["Not Specified"], "categories": ["Media & Advertising", "Others", "Banking / Finance", "Others", "Editorial / Journalism"], "post_time": "2022-01-18T03:06:28Z", "salary": {"currency": "HKD", "max": 44999, "min": 20000, "period": "monthly", "term": null}, "salary_visible": true, "title_keywords": ["copywriter"], "responsibilities": ["management", "quality", "develop", "communication", "contact", "banking"], "requirements": {"degrees": ["degree"], "majors": ["journalism", "marketing"], "languages": ["english", "chinese"], "language_level": ["excellent"], "hard_skills": ["plus"], "soft_skills": ["passionate", "determined", "responsible", "resourceful", "communication", "adaptability", "organisation", "team player", "reliable"], "languages_combined": [{"language": "english", "language_level": ["excellent"]}, {"language": "chinese", "language_level": ["excellent"]}]}, "experience_required": {"duration": ["3+ years"], "field": ["digital", "financial services industry", "writing"]}}, {"job_id": "100003009052772", "location_code": "hk", "company": "Imagine Lab Limited", "job_title": "Senior 3D Designer", "description": "Job Descriptions :\n\nType, prepare and input information\u00a0into the system\nConvert documents with both languages in Chinese and English into finished artworks\n\nJob Requirements :\n\nFast and accurate typing,\u00a0Chinese word processing (Changjie input) with minimum of 40 w.p.m. in English typing\nShift duty is required\u00a0(shift allowance will be provided for afternoon and overnight shift)\nProficiency in PC operating systems; experience in InDesign, Illustrator, Photoshop will be an advantage\n\nWe offer an attractive remuneration package and fringe benefits to the right candidate.\nTo apply, please send your full resume and expected salary via email to:\n\nEmail: Click \"Apply Now\"\n\n(Personal data provided will be used for recruitment purpose only)", "employment_types": ["Full Time", "Permanent"], "selling_points": [], "locations": ["Others"], "categories": ["Media & Advertising", "Others", "Design", "Graphics", "Multi-media"], "post_time": "2022-01-17T06:45:53Z", "salary": {"currency": null, "max": null, "min": null, "period": "monthly", "term": null}, "salary_visible": false, "title_keywords": ["senior 3d designer"], "responsibilities": [], "requirements": {"degrees": [], "majors": [], "languages": ["english", "chinese"], "language_level": [], "hard_skills": ["chinese word processing", "indesign", "illustrator", "typing", "pc", "photoshop"], "soft_skills": ["accurate"], "languages_combined": [{"language": "english", "language_level": []}, {"language": "chinese", "language_level": []}]}, "experience_required": {"duration": [], "field": []}}, {"job_id": "100003009055870", "location_code": "hk", "company": "Ming Pao Holdings Ltd", "job_title": "Accounts Clerk", "description": "Responsibilities:\n\nGenerate design concept, structural design, environment design & space planning for events & exhibitions\nHandle 3D rendering projects, technical drawing and floor plan for production\nComplete 3D design drawing in full set for events and exhibitions, photo retouch technique is required.\nRequirements:\n\nDegree / Diploma or above in related courses (space design/ exhibition design/ multimedia design. etc)\nGood at handling 2D and 3D software (e.g. 3Ds Max, Cine 4D, Illustrator, Photoshop)\nHands-on experience in working on 3D, graphic, artwork, and output production independently is essential\n2 years\u2019 experience or above in exhibition/event design/production house/interior decoration will be an advantage\nImmediately is preferable\n\n\u00a0Office location: Yau Tong\n\nInterested parties please send your detailed resume and expected salary to\u00a0us.\n(All personal data collected will be used for recruitment purpose only)\u00a0", "employment_types": ["Full Time", "Permanent"], "selling_points": [], "locations": ["Chai Wan"], "categories": ["Accounting", "Accounting Clerk / Supervisor", "Others", "Media & Advertising", "Others"], "post_time": "2022-01-18T03:02:03Z", "salary": {"currency": null, "max": null, "min": null, "period": "monthly", "term": null}, "salary_visible": false, "title_keywords": ["accounts clerk"], "responsibilities": ["3d rendering", "design concept", "design", "photo retouch", "planning", "plan", "technical drawing"], "requirements": {"degrees": ["degree", "diploma or above"], "majors": ["multimedia design", "design"], "languages": [], "language_level": [], "hard_skills": ["3d software", "3ds max", "illustrator", "multimedia", "photoshop"], "soft_skills": ["hands-on", "independently"], "languages_combined": []}, "experience_required": {"duration": ["2 years"], "field": ["graphic", "design"]}}, {"job_id": "100003009053912", "location_code": "hk", "company": "Nissin Foods (H.K.) Company Limited", "job_title": "Senior Officer/Officer-Advertising", "description": "Responsibilities:\n\nTo assist daily accounting functions, processing invoices, AP/AR, month end closing, etc.\n\nRequirements:\n\nF.5/DSE or above with LCCI Intermediate level\nGood command of both spoken and written English & Chinese\nProficiency in MS Word and Excel operation\nGood communication and presentation skills, independent and able to work under pressure\nImmediate availability is highly preferred\n\nWe offer attractive remuneration package to the right candidate. Interested parties please send full resume with salary expected to the\u00a0 Human Resources Department, 15/F., Block A, Ming Pao Industrial Centre, 18 Ka Yip Street, Chaiwan, Hong Kong\u00a0or apply by clicking the\u00a0Apply Now\u00a0button.\n\n\u00a0Personal data collected will be used for recruitment purpose only", "employment_types": ["Full Time", "Permanent"], "selling_points": [], "locations": ["Tai Po Area"], "categories": ["Media & Advertising", "Account Servicing", "Production", "Others"], "post_time": "2022-01-17T07:45:08Z", "salary": {"currency": null, "max": null, "min": null, "period": "monthly", "term": null}, "salary_visible": false, "title_keywords": ["senior officer", "officer"], "responsibilities": ["ap", "month end closing", "ar", "invoices", "daily accounting"], "requirements": {"degrees": ["dse"], "majors": [], "languages": ["english", "chinese"], "language_level": ["good command"], "hard_skills": ["excel", "ms word"], "soft_skills": ["communication", "presentation skills", "independent", "work under pressure"], "languages_combined": [{"language": "english", "language_level": ["good command"]}, {"language": "chinese", "language_level": ["good command"]}]}, "experience_required": {"duration": [], "field": []}}, {"job_id": "100003009055053", "location_code": "hk", "company": "The Hong Kong Jockey Club", "job_title": "Public Affairs Support Manager (Social Media)", "description": "Job Description\n\nSupport Marketing teams to plan and execute both online and offline advertising campaigns for achieving business objectives and goals, including coordinate and manage with internal teams and agencies on strategies, proposals, creative, media plan, artwork, action plan and campaign execution.\nManage social media platforms daily and liaise with agencies, including social listening, content creation, schedule posts, monitor and response comments.\nCoordinate and liaise with different departments & vendors for managing corporate website content, function, enhancement and maintenance.\nCompile reports on the performance and effectiveness of advertising campaigns and various digital platforms.\nConduct market research and explore new trends (e.g. the industry, target audience, etc.), advertising channels & technologies and identify opportunities to enhance advertising campaigns.\nHandle multiple projects simultaneously and liaise with various departments & agencies in a timely and professional manner.\n\nJob Specification\n\nDegree holder preferably in Business, Marketing or related disciplines\nMinimum 5 years of relevant working experience in Marketing or Media & Advertising fields, preferably in FMCG.\nGood command of both written and spoken English and Chinese.\nProficient in PC skills and MS Office.\nKnowledge of digital marketing and website or hands-on execution experience of digital platforms (e.g. Facebook ad manager, Google analytics, etc.)\nInterest in Japanese culture and ACG is an advantage.\nCandidate with less experience will be considered as Officer.\nApplicant please email detailed resume with present and expected salary to Human Resources Department\n\n(All personal data collected will be kept confidentially and used for recruitment purpose only)", "employment_types": ["Full Time", "Permanent"], "selling_points": ["Proven experience in social media management", "Experience in corporate social media accounts", "Organise regular social media campaigns"], "locations": ["Causeway Bay"], "categories": ["Media & Advertising", "Others", "Marketing / Public Relations", "Others"], "post_time": "2022-01-18T00:58:07Z", "salary": {"currency": null, "max": null, "min": null, "period": null, "term": null}, "salary_visible": false, "title_keywords": ["public affairs support manager"], "responsibilities": ["conduct market research", "social media platforms", "professional manner", "website", "plan", "liaise with", "facebook", "personal data", "advertising", "teams", "monitor", "liaise with various departments", "schedule", "digital marketing", "advertising campaigns", "maintenance", "compile reports", "comments", "coordinate", "recruitment", "multiple projects"], "requirements": {"degrees": ["degree holder"], "majors": ["related disciplines", "business", "marketing"], "languages": ["japanese", "english", "chinese"], "language_level": ["advantage", "good command"], "hard_skills": ["google analytics", "maintenance", "facebook", "pc skills", "ms office"], "soft_skills": ["timely", "creative", "hands-on", "detailed"], "languages_combined": [{"language": "japanese", "language_level": ["advantage"]}, {"language": "english", "language_level": ["good command"]}, {"language": "chinese", "language_level": ["good command"]}]}, "experience_required": {"duration": ["minimum 5 years"], "field": ["fmcg", "advertising", "relevant working experience", "marketing", "digital marketing", "digital", "media"]}}, {"job_id": "100003009049322", "location_code": "hk", "company": "Phoenix Satellite Television Co Ltd", "job_title": "Audio Operator", "description": "The Job\nYou will:\n\nAssist in the development of the Club\u2019s Corporate and Charities social media strategy to raise the Club\u2019s online presence on social media platforms\nassist to manage and monitor designated Club social media accounts, including the development of social media content (e.g. copy-writing, graphic and video production), and coordination with various Club divisions on shared content posting; maintenance of a content calendar\norganise regular social media campaigns to support corporate and charities communications' publicity effort, and drive engagement, reach and viewership\nassist to manage issues, handle enquiries, develop line-to-take\ngenerate regular performance analysis reports\nprovide support in developing corporate and charities communications material for internal & external stakeholders\n\nAbout You\nYou should have:\n\nuniversity degree in a related discipline or relevant qualification, with a minimum of 8 years' experience\nGood knowledge about HK's social-political and media scenes, especially social media\nproven experience in social media management\nexperience and knowledge in managing and developing content for corporate social media accounts\nself-motivated, strong critical and analytical mind\nhigh level of proficiency in written and spoken English and Chinese\nhands-on experience of using MS office, Word, Excel and Power Point.\n\nTerms of employment\nThe level of appointment will be commensurate with qualifications and experience.\n\nHow to Apply\nPlease send your resume, complete with expected salary and job reference by clicking the Apply Now button.", "employment_types": ["Full Time", "Permanent"], "selling_points": [], "locations": ["Tai Po Area"], "categories": ["Media & Advertising", "Production", "Others", "Broadcasting - TV / Radio"], "post_time": "2022-01-14T08:28:18Z", "salary": {"currency": null, "max": null, "min": null, "period": null, "term": null}, "salary_visible": false, "title_keywords": ["operator"], "responsibilities": ["social media", "provide support", "management", "maintenance", "social media campaigns", "video production", "analysis reports", "social media platforms", "monitor", "coordination with", "developing", "develop", "handle enquiries", "social media content"], "requirements": {"degrees": ["university degree"], "majors": [], "languages": ["english", "chinese"], "language_level": ["proficiency"], "hard_skills": ["excel", "maintenance", "analysis", "word", "power point", "ms office"], "soft_skills": ["hands-on", "self-motivated", "analytical mind", "coordination"], "languages_combined": [{"language": "english", "language_level": ["proficiency"]}, {"language": "chinese", "language_level": ["proficiency"]}]}, "experience_required": {"duration": ["minimum of 8 years"], "field": ["related", "social media", "management", "developing"]}}, {"job_id": "100003009056118", "location_code": "hk", "company": "\u5b89\u7d22\u5e15\u9999\u6e2f\u6709\u9650\u516c\u53f8", "job_title": "Community Manager - Isobar", "description": "Responsibilities:\u00a0\n\nResponsible for operating audio equipments in 24 hours news live studio and post production audio suite.\u00a0\n\n\u00a0Requirements:\u00a0\n\nF.5 or above.\nPrefer 2 years\u2019 experience of news live studio is an advantage.\nSelf-motivated and able to work independently.\nAble to work 24-hour shift duties.\nExcellent command of written and spoken English and Chinese.\n\nFor more details of our company, please visit our website at http://www.ifeng.com/\n\nWe offer attractive remuneration package to the right candidate. Interested parties please click \u201cApply Now\u201d to submit applications or send applications with detailed resume stating career history, present & expected salary and date available to Human Resources Department, Phoenix Satellite Television Co. Ltd. via fax: 2200 8620.\n\n\u00a0Personal data collected will be used for recruitment purpose only. Applicants not hearing from us within 6 weeks may consider their applications unsuccessful and all related information will be destroyed after 6 months.", "employment_types": ["Full Time", "Permanent"], "selling_points": ["global platform / social media strategy", "marketing, communications, strategic planning", "4As, digital agency"], "locations": ["North Point"], "categories": ["Media & Advertising", "Account Servicing", "Strategic Planning", "Others"], "post_time": "2022-01-18T03:21:26Z", "salary": {"currency": null, "max": null, "min": null, "period": "monthly", "term": null}, "salary_visible": false, "title_keywords": ["manager"], "responsibilities": ["audio"], "requirements": {"degrees": [], "majors": [], "languages": ["english", "chinese"], "language_level": ["excellent"], "hard_skills": [], "soft_skills": ["self-motivated", "work independently"], "languages_combined": [{"language": "english", "language_level": ["excellent"]}, {"language": "chinese", "language_level": ["excellent"]}]}, "experience_required": {"duration": ["2 years"], "field": []}}, {"job_id": "100003009052294", "location_code": "hk", "company": "Tianda Institute", "job_title": "\u7814\u7a76\u54e1 Researcher (Full time or Part time)", "description": "The Opportunity:\n\nOur community manager will be responsible to lead our clients\u2019 social presence with a whip-smart team of creative and content strategists. This is a unique opportunity for Social Media communications professionals to work on integrated businesses and to develop cutting-edge always on communications and marketing campaign.\n\nWe're looking for someone to:\n\n\u00a0\u00a0\u00a0\u00a0\u00a0\u00a0\u00a0 Understanding client\u2019s goal and challenges and translate them into social strategies and communication.\n\u00a0\u00a0\u00a0\u00a0\u00a0\u00a0\u00a0 Concept, develop, execute and manage creative social content, engagement and interaction in partnership with strategy, media and creative teams.\n\u00a0\u00a0\u00a0\u00a0\u00a0\u00a0\u00a0 Perform competitive landscape analyses, audience research, social listening, and other market research\n\u00a0\u00a0\u00a0\u00a0\u00a0\u00a0\u00a0 Tell client stories in a fresh and interesting way that\u2019s native to the online communities\n\u00a0\u00a0\u00a0\u00a0\u00a0\u00a0\u00a0 Present data-driven plans, recommendations, and performance updates (internally and externally), and respond to requests for information or strategic course\n\u00a0\u00a0\u00a0\u00a0\u00a0\u00a0\u00a0 Manage relationship with clients and social followers.\n\u00a0\u00a0\u00a0\u00a0\u00a0\u00a0\u00a0 Advise on owned, earned, and paid media strategies across platforms\u00a0\n\u00a0\u00a0\u00a0\u00a0\u00a0\u00a0\u00a0 Participate in strategy development initiatives for clients and new business\n\u00a0\u00a0\u00a0\u00a0\u00a0\u00a0\u00a0 Identify the technology or tools needed for running campaigns, moderating online communities, posting content, and social listening\n\nWe are looking for:\n\nA digital and social native who is obsessed with social media and emerging trends and has an understanding of new and existing social delivery methods.\n\n\u00a0\u00a0\u00a0\u00a0\u00a0\u00a0\u00a0 3 - 4+ years' experience in running social platforms, preferably with global platform experience\n\u00a0\u00a0\u00a0\u00a0\u00a0\u00a0\u00a0 Tertiary qualifications in marketing, communication and/or a related discipline\n\u00a0\u00a0\u00a0\u00a0\u00a0\u00a0\u00a0 Experience building workflows to manage and collaborate on content\n\u00a0\u00a0\u00a0\u00a0\u00a0\u00a0\u00a0 Familiarity with Facebook, Instagram, Linkedin and WeChat\n\u00a0\u00a0\u00a0\u00a0\u00a0\u00a0\u00a0 Up-to-date with the latest social media trends, technologies and best practices ensuring maximum effectiveness.\n\u00a0\u00a0\u00a0\u00a0\u00a0\u00a0\u00a0 Experience with social media operation tools, promotions and implementing plans\n\u00a0\u00a0\u00a0\u00a0\u00a0\u00a0\u00a0 Familiarity with analytics tools and methods for measuring success through data\n\u00a0\u00a0\u00a0\u00a0\u00a0\u00a0\u00a0 Strong oral and written communications skills and the ability to produce clear, compelling, client-ready written deliverables in both Chinese and English\n\u00a0\u00a0\u00a0\u00a0\u00a0\u00a0\u00a0 Strong work ethic complemented by a positive, can-do attitude\n\u00a0\u00a0\u00a0\u00a0\u00a0\u00a0\u00a0 Creative and innovative thinking with strong attention to detail\n\u00a0\u00a0\u00a0\u00a0\u00a0\u00a0\u00a0 A great sense of humour!", "employment_types": ["Full Time", "Permanent"], "selling_points": [], "locations": ["Central"], "categories": ["Media & Advertising", "Others", "Professional Services", "Business Analysis / Data Analysis", "Education", "Others"], "post_time": "2022-01-17T02:39:43Z", "salary": {"currency": null, "max": null, "min": null, "period": "monthly", "term": null}, "salary_visible": false, "title_keywords": ["researcher"], "responsibilities": ["collaborate", "social media", "analytics tools", "data", "teams", "market research", "develop", "communication", "plans", "facebook"], "requirements": {"degrees": [], "majors": [], "languages": ["english", "chinese"], "language_level": [], "hard_skills": ["goal", "facebook", "analytics tools", "wechat"], "soft_skills": ["oral", "responsible", "cutting-edge", "can-do attitude", "unique", "innovative", "communication", "clear", "work ethic", "attention to detail", "creative", "driven", "positive"], "languages_combined": [{"language": "english", "language_level": []}, {"language": "chinese", "language_level": []}]}, "experience_required": {"duration": ["4+ years"], "field": ["social media operation"]}}, {"job_id": "100003009052230", "location_code": "hk", "company": "ORIENTAL HUMAN RESOURCES LIMITED", "job_title": "Senior Editor / Reporter - Local News /  Financial News", "description": "\u5929\u5927\u7814\u7a76\u9662\u662f\u4e00\u5bb6\u8a2d\u7acb\u65bc\u9999\u6e2f\u7684\u516c\u76ca\u6027\u6230\u7565\u7814\u7a76\u667a\u5eab\uff0c\u8457\u91cd\u65bc\u5b8f\u89c0\u6230\u7565\u554f\u984c\u53ca\u61c9\u7528\u6027\u653f\u7b56\u8ab2\u984c\u7684\u524d\u77bb\u6027\u7814\u7a76\u3002\u7814\u7a76\u9818\u57df\u5305\u62ec\u570b\u969b\u548c\u5b89\u5168\u6230\u7565\u3001\u7d93\u6fdf\u548c\u91d1\u878d\u6230\u7565\u3001\u793e\u6703\u554f\u984c\u548c\u516c\u5171\u653f\u7b56\u3001\u8cc7\u6e90\u548c\u74b0\u5883\u3001\u6e2f\u6fb3\u81fa\u554f\u984c\u7b49\uff0c\u4e26\u51fa\u7248\u300a\u5929\u5927\u5831\u544a\u300b\u3002\u7814\u7a76\u9662\u5e0c\u671b\u901a\u904e\u5c0d\u4e2d\u570b\u548c\u5168\u7403\u554f\u984c\u7684\u6df1\u5ea6\u601d\u8003\u3001\u63a2\u8a0e\u548c\u7814\u7a76\uff0c\u63d0\u51fa\u65b0\u89c0\u9ede\u3001\u65b0\u601d\u60f3\u548c\u65b0\u8209\u63aa\uff0c\u70ba\u6c11\u65cf\u5fa9\u8208\u3001\u570b\u5bb6\u767c\u5c55\u8207\u4e16\u754c\u548c\u5e73\u670d\u52d9\u3002\n\n\u73fe\u8aa0\u8058\u7814\u7a76\u54e1\uff0c\u8ca0\u8cac\u7814\u7a76\u9662\u5404\u76f8\u95dc\u9818\u57df\u7814\u7a76\u5de5\u4f5c\u3002\u7533\u8acb\u4eba\u9808\u6301\u6709\u76f8\u95dc\u9818\u57df\u4e4b\u535a\u58eb\u5b78\u4f4d\uff0c\u4e26\u5728\u5b78\u8853\u7814\u7a76\u6216\u516c\u5171\u6a5f\u69cb\u64c1\u6709\u81f3\u5c113\u5e74\u4ee5\u4e0a\u5b8f\u89c0\u6230\u7565\u6216\u516c\u5171\u7814\u7a76\u7d93\u9a57\u3002\u7533\u8acb\u4eba\u9808\u5177\u5099\u512a\u79c0\u4e2d\u82f1\u6587\u53e3\u8a9e\u53ca\u66f8\u9762\u8868\u9054\u80fd\u529b\uff0c\u80fd\u7368\u7acb\u5236\u5b9a\u7814\u7a76\u8a08\u756b\u3001\u64b0\u5beb\u8ad6\u6587\u53ca\u5831\u544a\uff0c\u80fd\u4ee5\u6d41\u5229\u7684\u666e\u901a\u8a71\u53ca\u82f1\u6587\u9032\u884c\u6703\u8b70\u548c\u8a0e\u8ad6\uff08\u517c\u5177\u6d41\u5229\u7cb5\u8a9e\u8005\u512a\u5148\uff09\u3002\u901a\u904e\u7be9\u9078\u4e4b\u7533\u8acb\u4eba\u9700\u8981\u9032\u884c\u7b46\u8a66\u3002\n\n\u5929\u5927\u7814\u7a76\u9662\u63d0\u4f9b5\u5929\u5de5\u4f5c\u9031\u53ca\u512a\u539a\u85aa\u916c\u798f\u5229\u3002\u6709\u610f\u7533\u8acb\u8005\u6309\"Apply Now\" \u63d0\u4ea4\u500b\u4eba\u5c65\u6b77\u3001\u76ee\u524d\u53ca\u671f\u671b\u85aa\u91d1\u3002\u5982\u6b32\u4e86\u89e3\u66f4\u591a\u8a73\u60c5\uff0c\u6b61\u8fce\u53c3\u95b1\u5929\u5927\u7814\u7a76\u9662\u5b98\u65b9\u7db2\u9801https://www.tiandainstitute.org\u3002\u901a\u904e\u521d\u6b65\u7be9\u9078\u4e4b\u7533\u8acb\u4eba\u5c07\u57284\u9031\u5167\u6536\u5230\u901a\u77e5\u3002", "employment_types": ["Full Time"], "selling_points": [], "locations": ["Tai Po Area"], "categories": ["Media & Advertising", "Others", "Banking / Finance", "Others", "Editorial / Journalism"], "post_time": "2022-01-17T02:31:17Z", "salary": {"currency": null, "max": null, "min": null, "period": "monthly", "term": null}, "salary_visible": false, "title_keywords": ["reporter", "senior editor"], "responsibilities": [], "requirements": {"degrees": [], "majors": [], "languages": [], "language_level": [], "hard_skills": [], "soft_skills": [], "languages_combined": []}, "experience_required": {"duration": [], "field": []}}, {"job_id": "100003009053521", "location_code": "hk", "company": "Manulife (International) Limited", "job_title": "\u8ca1\u5bcc\u7ba1\u7406\u7d93\u7406/\u696d\u52d9\u62d3\u5c55\u7d93\u7406 Wealth Management Manager/Business Development Manager", "description": "University or College graduate\n5 years or above experience in Press or Media industry\nStrong sense on local news / financial news\nGood command of Chinese and English\nKnowledge of Chinese word processing\n(Less experience or fresh graduates\u00a0will be considered as Junior Position)\n\n\n\nApplication Method\n\nWe offer free shuttle bus, free parking and fringe benefits including medical scheme, discretionary bonus and public holidays\u00a0to the right candidate. Interested parties, please send full resume with expected salary to ORIENTAL HUMAN RESOURCES LIMITED\u00a0by\u00a0clicking \"Apply now\" ;\u00a0or fax to 3600 1900 ( Please quote reference on the application letter )\n\n\nPersonal Information Collection Statement\n\nPersonal data collected will be treated in accordance with our Personal Data Policy and handled in strict confidence by authorized personnel for recruitment related purpose only.\u00a0 \u00a0 \u00a0\n\u00a0 \u00a0 \u00a0 \u00a0 \u00a0 \u00a0\n\n\u00a0 \u00a0 \u00a0 \u00a0 \u00a0 \u00a0 \u00a0 \u00a0 \u00a0 \u00a0 \u00a0 \u00a0 \u00a0 \u00a0 \u00a0 \u00a0 \u00a0 \u00a0 \u00a0 \u00a0 \u00a0 \u00a0 \u00a0 \u00a0 \u00a0 \u00a0 \u00a0\u00a0on.cc\n\n", "employment_types": ["Full Time", "Permanent", "Contract", "Internship"], "selling_points": ["\u6642\u9593\u81ea\u4e3b Work Life Balance", "\u5efa\u7acb\u5718\u968a, \u6e05\u6670\u53ca\u900f\u660e\u7684\u6649\u5347\u968e\u68af", "\u5b8c\u5584\u7684\u8077\u524d\u53ca\u5728\u8077\u5c08\u696d\u57f9\u8a13"], "locations": ["Kwun Tong Area"], "categories": ["Media & Advertising", "Others", "Medical Services", "Others", "Building & Construction", "Others"], "post_time": "2022-01-17T09:31:45Z", "salary": {"currency": "HKD", "max": 54999, "min": 20000, "period": "monthly", "term": null}, "salary_visible": true, "title_keywords": ["business development manager", "wealth management manager", "\u8ca1\u5bcc\u7ba1\u7406\u7d93\u7406"], "responsibilities": [], "requirements": {"degrees": [], "majors": [], "languages": ["english", "chinese"], "language_level": ["good command"], "hard_skills": ["chinese word processing"], "soft_skills": [], "languages_combined": [{"language": "english", "language_level": ["good command"]}, {"language": "chinese", "language_level": ["good command"]}]}, "experience_required": {"duration": ["5 years"], "field": ["media"]}}, {"job_id": "100003009048853", "location_code": "hk", "company": "A Mall", "job_title": "Digital Content Editor (Japanese Sake / Wine / Gourmet)", "description": "\u6211\u5011\u662f\u4e00\u7fa4\u8cc7\u6b77\u8c50\u5bcc\u517c\u5bcc\u6709\u6d3b\u529b\u7684\u5718\u968a\uff0c\n\u6210\u54e1\u5927\u591a\u4f86\u81ea\u9280\u884c\u53ca\u4fdd\u96aa\u696d\u4e26\u5df2\u670d\u52d9\u905420\u5e74\n\n\u6211\u5011\u81f4\u529b\u70ba\u5ba2\u4eba\u63d0\u4f9b\u5c08\u696d\u7406\u8ca1\u65b9\u6848\uff0c\u5982\u500b\u4eba\u65b9\u6848\uff1a\u91ab\u7642\u5eb7\u5065\u3001\u76ee\u6a19\u5132\u84c4\u3001 \u9000\u4f11\u7b56\u5283\u3001\u4fdd\u8cbb\u878d\u8cc7\uff1b\u4f01\u696d\u65b9\u6848\uff1a\u50f1\u4e3b\u5f37\u7a4d\u91d1\u8a08\u5283\u3001 \u5718\u9ad4\u91ab\u7642\n\n\u5718\u968a\u7406\u5ff5\uff1a\u6211\u5011\u6df1\u4fe1\u85c9\u8457\u300c\u5718\u968a\u7cbe\u795e\u300d, \u300c\u4e92\u76f8\u5e6b\u52a9\u300d\u9054\u81f4\u5171\u5b34\n\n\u5982\u679c\u4f60\u5bcc\u6709\u5922\u60f3\uff0c\u6562\u65bc\u6311\u6230\uff0c\u52c7\u65bc\u8df3\u51fa\u4f60\u7684\u8212\u9069\u5708\uff0c\u8acb\u52a0\u5165\u6211\u5011 \uff01!\n\n\u4f60\u7684\u5f85\u9047\uff1a\n\u62db\u52df\u6d25\u8cbc($14,000 - $50,000)\uff0c\u65b0\u5165\u8077\u6bcf\u6708\u984d\u5916\u734e\u91d1+\u5e74\u7d42\u82b1\u7d05\n\u81ea\u4e3b\u5de5\u4f5c\u6642\u9593\uff0c\u64f4\u95ca\u793e\u4ea4\u5708\u5b50\uff0c\u6b61\u8fce\u822a\u7a7a\u696d/\u65c5\u904a\u696d/\u9152\u5e97\u696d/\u5168\u8077\u5abd\u5abd\n\u8457\u91cd\u5de5\u4f5c\u8207\u751f\u6d3b\u5e73\u8861\uff0c\u771f\u6b63\u5f48\u6027\u81ea\u4e3b\u81ea\u7531\n\u5b8c\u5584\u53ca\u5c08\u696d\u8077\u524d\u53ca\u5728\u8077\u57f9\u8a13\uff0c\u63d0\u5347\u92b7\u552e\u6280\u5de7\u53ca\u7522\u54c1\u8cc7\u8a0a\n\u6bcf\u5e74\u6d77\u5916\u696d\u52d9\u6703\u8b70\u53ca\u5718\u9ad4\u65c5\u884c\n\u8cc7\u52a9\u6301\u7e8c\u5c08\u696d\u57f9\u8a13\uff0c\u914d\u5408\u5718\u968a\u7d93\u7406\u63d0\u4f9b\u500b\u2f08\u6307\u5c0e\uff0c\u52a9\u60a8\u6649\u8eab\u6210\u2f8f\u696d\u5167\u6700\u9802\u5c16\u7684\u767e\u842c\u5713\u684c\u6703\uff08MDRT\uff09\n\u5de5\u4f5c\u7bc4\u570d\n\n\n\u4e86\u89e3\u53ca\u767c\u6398\u5ba2\u6236\u7684\u9700\u6c42\uff0c\u63d0\u4f9b\u9069\u5207\u53ca\u5ea6\u8eab\u8a02\u9020\u7684\u7406\u8ca1\u65b9\u6848\n\u70ba\u5ba2\u6236\u63d0\u4f9b\u8cc7\u7522\u4fdd\u8b77/\u50b3\u627f\u53ca\u914d\u7f6e\n\u63d0\u4f9b\u57f9\u8a13\uff0c\u52a0\u5f37\u5718\u968a\u92b7\u552e\u80fd\u529b\u53ca\u7522\u54c1\u77e5\u8b58\n\u53c3\u8207\u4e0d\u540c\u985e\u578b\u7684\u5e02\u5834\u63a8\u5ee3\u6d3b\u52d5\n\u5354\u52a9\u500b\u4eba\u5ba2\u6236\u8fa6\u7406\u4fdd\u969c\u8a08\u5283/\u5f37\u7a4d\u91d1\u6236\u53e3\u6574\u5408/\u7406\u8ca1\u7522\u54c1\n\u7b56\u5283\u9000\u4f11\u65b9\u6848 (\u53ef\u6263\u7a05\u5e74\u91d1\uff0c\u53ef\u6263\u7a05\u81ea\u9858\u6027\u5f37\u7a4d\u91d1\uff0c\u81ea\u9858\u91ab\u4fdd)\uff0c\u5718\u9ad4\u91ab\u7642\u65b9\u6848\n\u57fa\u91d1\u6295\u8cc7\u898f\u5283\u53ca\u7ba1\u7406\uff0c\u63d0\u4f9b\u5c08\u696d\u552e\u5f8c\u53ca\u8ca1\u653f\u8aee\u8a62\u670d\u52d9\n\u5efa\u7acb\u500b\u4eba\u5f62\u8c61\uff0c\u5de5\u4f5c\u7406\u5ff5\u53ca\u5718\u968a\u7406\u5ff5\uff0c\u70ba\u5c07\u4f86\u6210\u70ba\u9818\u5c0e\u8005\u800c\u8216\u8def\n\u5c0d\u8c61\u8981\u6c42 :\n\u4e2d\u4e94\u7562\u696d\u3001\u9999\u6e2f\u4e2d\u5b78\u2f42\u6191\uff08\u4e2d\u6578\u6216\u82f1\u6578\u4e94\u79d1\u53ca\u683c\uff09\u6216\u6301\u540c\u7b49\u5b78\u6b77\u4ee5\u4e0a\n\u4e3b\u52d5\uff0c\u6709\u5e79\u52c1\uff0c\u5177\u670d\u52d9\u7cbe\u795e\u53ca\u6709\u8cac\u4efb\u611f\n\u826f\u597d\u6e9d\u901a\u80fd\u529b\u53ca\u4eba\u969b\u95dc\u4fc2\uff0c\u6210\u719f\u7a69\u91cd\u3001\u6027\u683c\u958b\u6717\u3001\u7a4d\u6975\u9032\u53d6\n\u5c0d\u751f\u6d3b\u6709\u8981\u6c42\u548c\u6e34\u671b\uff0c\u559c\u6b61\u5b78\u7fd2\u65b0\u4e8b\u7269\n\u5177\u92b7\u552e\uff0c\u5e02\u5834\u63a8\u5ee3\uff0c\u9280\u884c\u53ca\u4fdd\u96aa\u696d\u7d93\u9a57\u8005\u66f4\u4f73\n\u6211\u5011\u7684\u512a\u52e2\uff1a\n\n\u00a0\u70ba\u5ba2\u6236\u63d0\u4f9b\u6700\u5c08\u696d \u6700\u5408\u9069\u7684\u5206\u6790\u670d\u52d9, \u8207\u5ba2\u6236\u4fdd\u6301\u9577\u9060\u800c\u53c8\u6301\u4e45\u7684\u95dc\u4fc2, \u5c07\u4e00\u5207\u6a5f\u6703\u5316\u6210\u300c\u5546\u6a5f\u300d\uff0c\u6642\u4ee3\u4e0d\u65b7\u8f49\u8b8a\uff0c\u8981\u8fce\u5408\u5e02\u5834\u9700\u6c42\uff0c\u5c31\u8981\u53ca\u65e9\u638c\u63e1\u2f8f\u696d\u5546\u6a5f !\n\u5b8f\u5229\u662f\u5168\u6e2f\u6700\u4ee4\u5ba2\u6236\u6eff\u610f\u7684\u4fdd\u96aa\u54c1\u724c\u4e4b\u4e00\uff0c\u5f37\u7a4d\u91d1\u5e02\u5834\u4f54\u6709\u7387\u6392\u884cNO.1\n\u75ab\u60c5\u6f38\u8da8\u7a69\u5b9a\uff0c\u65b0\u6210\u2f74\u7684\u516c\u53f8\u5c07\u6703\u9678\u7e8c\u51fa\u73fe\uff0c\u50f1\u4e3b\u5fc5\u9808\u70ba\u54e1\u2f2f\u8a2d\u2f74\u5f37\u7a4d\u2fa6\u8a08\u5283\u53ca\u8cfc\u8cb7\u52de\u2f2f\u4fdd\u96aa (\u6cd5\u4f8b\u898f\u5b9a)\n\u91ab\u7642\u901a\u8139\u9a5a\u2f08\uff0c\u7a4d\u84c4\u6613\u88ab\u84b8\u767c\u3002\u75ab\u60c5\u4e0b\u5371\u75be\u53ca\u4f4f\u9662\u4fdd\u96aa\u66f4\u4ee4\u2f08\u95dc\u6ce8\n\u53ef\u9000\u7a05\u5e74\u2fa6\u3001TVC\u53ca\u2f83\u9858\u91ab\u4fdd\u8cfc\u8cb7\u71b1\u6f6e\u5347\u6eab\uff0c\u5207\u8eab\u7684\u7406\u8ca1\u6aa2\u8996\u670d\u52d9\u9700\u6c42\u2f24\u589e\u3002\n\u2fb9\u6e2f\u87ec\u806f\u5168\u7403\u6700\u2ed1\u58fd\u5730\u5340\uff0c\u2faf\u5c0d\u6f2b\u2ed1\u7684\u9000\u4f11\u2f63\u6d3b\uff0c\u5e74\u2fa6\u8a08\u5283\u80fd\u66f4\u6709\u6548\u7684\u61c9\u5c0d\u2ed1\u58fd\u2fb5\u96aa\u3002\n\n\u672a\u4f86\u5728\u4f60\u624b\uff0c\u7d66\u81ea\u5df1\u4e00\u500b\u6a5f\u6703, \u8aa0\u9080\u4f60\u52a0\u2f0a\u6211\u5011\u5718\u968a!\n\n\u2f74\u5373\u7533\u8acb \u201cApply now\u201d\u00a0\u00a0\u5c07\u5c65\u6b77\u96fb\u90f5\u7d66\u6211\u5011\uff0c\u8e0f\u51fa\u6210\u529f\u7684\u7b2c\u2f00\u6b65!", "employment_types": ["Full Time"], "selling_points": [], "locations": ["Kwun Tong"], "categories": ["Media & Advertising", "Others"], "post_time": "2022-01-14T07:27:41Z", "salary": {"currency": null, "max": null, "min": null, "period": "monthly", "term": null}, "salary_visible": false, "title_keywords": ["content editor"], "responsibilities": [], "requirements": {"degrees": [], "majors": [], "languages": [], "language_level": [], "hard_skills": [], "soft_skills": [], "languages_combined": []}, "experience_required": {"duration": [], "field": []}}, {"job_id": "100003009049324", "location_code": "hk", "company": "Phoenix Satellite Television Co Ltd", "job_title": "Technical Director", "description": "We are looking for a talented\u00a0Content Creator\u00a0to take lead on enhancing the quality and quantity of our content in our websites (www.amall.com.hk and www.sakeromance.com) and digital media (Facebook, IG)\n\n\nResponsibilities:\n\nPrepare relevant content that fits different digital media e.g. Company eCommerce Website (www.amall.com.hk), Sake Content Website (www.sakeromance.com), Company social media page (IG, FB and others)\nWrite,\u00a0localize or translate\u00a0a range of content around Japanese Sake and Delicacies including latest sake trend, sake introduction, newly launch products, brewery stories, food matching and other related topics\u2026etc\u00a0\nCreate and edit social media content in various formats including (but not limited to) feeds, videos, photos, etc.\nAssist and cooperate with Marketing team to manage and publish content in different digital media including Facebook, Instagram, Company Websites etc\nResearch industry-related topics\nIdentify\u00a0gaps and draw observations on the needs of new content.\u00a0 Able to\u00a0recommend new topics or new approaches\u00a0on\u00a0how to write content for different Sake related topics\nPerform other job duties as requested.\u00a0\n\n\n\nRequirements:\n\nAt least 1-2 years of copywriting experience in media or advertising agency\nExcellent command of Chinese and be able to demonstrate your copywriting and proof-reading capabilities\nFully conversant with Chinese typing and reading\nKnowledge and experience in Social Media Platform like IG and Facebook is preferred\nKnowledge in sake or wine is an advantage. Holder of WSET, SSI or alike is an advantage\nExperience in digital marketing or advertising is a plus\nBe able to work independently & under pressure with tight schedule\nCapability to read and speak Japanese is an absolute advantage (which could facilitate regular communication with our Japanese Breweries)\n\n\u00a0Interested candidates, kindly send your detailed resume including:\n\n1) Expected salary\n2) Current and last drawn salaries\n3) Reason for leaving current and past employments\n\n\n\nWhat's On Offer\n\n5-day Work\nBank Holidays\nFriendly Working Environment\n\nCompany Overview\n\nEstablished in 2013, Amall is one of the most renowned and popular Japanese Sake Distributors. \u00a0Our brand purpose is to have more people understand and appreciate Japanese Sake thru helping them to select, match and enjoy properly.\u00a0 Our brand values is to offer trendiest, latest and best sake to our customers.\u00a0\n\nWith all these in mind, we carried more than 300 different items and be the sole distributor of more than 10 Japanese Sake Breweries. We launch our own eCommerce website as well as Content website to promote Japanese Sake culture and our products.", "employment_types": ["Full Time", "Permanent"], "selling_points": [], "locations": ["Tai Po Area"], "categories": ["Media & Advertising", "Production", "Others", "Broadcasting - TV / Radio"], "post_time": "2022-01-14T08:28:18Z", "salary": {"currency": null, "max": null, "min": null, "period": null, "term": null}, "salary_visible": false, "title_keywords": ["director"], "responsibilities": ["company websites", "social media", "website", "social media content", "facebook", "cooperate with"], "requirements": {"degrees": [], "majors": [], "languages": ["japanese", "chinese"], "language_level": ["advantage", "excellent"], "hard_skills": ["facebook", "plus", "typing"], "soft_skills": ["communication", "work independently", "under pressure"], "languages_combined": [{"language": "japanese", "language_level": ["advantage"]}, {"language": "chinese", "language_level": ["excellent"]}]}, "experience_required": {"duration": ["at least 1-2 years"], "field": ["social media", "advertising", "digital marketing", "advertising agency", "copywriting", "media"]}}, {"job_id": "100003009037383", "location_code": "hk", "company": "\u7d93\u6fdf\u4e00\u9031 EDigest", "job_title": "Social Media Executive/Digital Content Executive (Business & Finance)", "description": "Job Description\n\nBe responsible for day-to-day schedule of the director;\nProvide all-rounded secretarial and administrative support to the director;\nCoordinate and accompany the director to attend meetings, conferences, PR functions and social events; and follow up relevant issues after attending the above events;\nLiaise with different government departments, interest groups and media for the organization;\nAssist in writing and preparing public policy related speeches, papers and submissions for the organization;\nAssist in management of promotional materials and online marketing scheme for the organization;\nAssist in event planning and coordination for the organization.\n\n\nJob Requirements\n\nHigher diploma or above in journalism, public administration, politics or other related disciplines;\n2 years\u2019 experience in handling public policy issues, fresh graduates will also be considered;\nStrong awareness of Hong Kong\u2019s current affairs;\nExperience in media, public relation, and event management is preferable;\nThoughtful, attentive, detail-minded and self-motivated;\nA good team player and able to finish multi tasks within tight deadline;\nGood oral and written skills in both Chinese and English (Cantonese is a must), proficiency in Putonghua is\u00a0advantageous;\nProficiency in using Microsoft Word, Excel, PowerPoint and Chinese word processing; and\nWilling to work overtime and in non-office settings.\nBenefits:\n\n\n14-day annual leave;\n5-day work week, bank holiday;\nContract-end gratuity;\nMedical Benefit (both hospitalization & out-patient);\nCompensation leave arrangement.\n\nInterested parties please send your full resume, current salary and expected salary.\n\nWe are an equal opportunity employer and welcome applications from all qualified candidates. The information provided will be treated in strict confidence and be used only for consideration of your application for relevant / similar posts within the Office of Hon. Michael Tien and Roundtable. Applicants not hearing from us within four weeks from the date of advertisement may consider their applications unsuccessful. We retain the unsuccessful applications for a maximum period of six months.", "employment_types": ["Full Time", "Permanent"], "selling_points": ["Content development & data analysis", "Experience in social media marketing field", "Great development opportunity, competitive package"], "locations": ["Kwun Tong"], "categories": ["Media & Advertising", "Creative / Design", "Others", "Editorial / Journalism"], "post_time": "2022-01-16T21:50:10Z", "salary": {"currency": null, "max": null, "min": null, "period": null, "term": null}, "salary_visible": false, "title_keywords": ["digital content executive", "social media executive"], "responsibilities": ["management", "administrative support", "coordinate", "liaise with", "conferences", "promotional materials", "schedule", "coordination", "attend meetings", "planning"], "requirements": {"degrees": ["higher diploma or above"], "majors": ["journalism", "related disciplines", "public administration"], "languages": ["cantonese", "putonghua", "english", "chinese"], "language_level": ["proficiency", "good"], "hard_skills": ["excel", "microsoft word", "chinese word processing", "powerpoint"], "soft_skills": ["attentive", "detail-minded", "good team player", "oral", "self-motivated", "work overtime"], "languages_combined": [{"language": "cantonese", "language_level": ["good"]}, {"language": "putonghua", "language_level": ["proficiency", "good"]}, {"language": "english", "language_level": ["good"]}, {"language": "chinese", "language_level": ["good"]}]}, "experience_required": {"duration": ["2 years"], "field": ["public relation", "management", "media"]}}, {"job_id": "100003009055213", "location_code": "hk", "company": "Asiaray Advertising Media Limited", "job_title": "Sales Executive - Advertising", "description": "\u8077\u52d9\u7bc4\u570d\uff1a\n\n\u8ca0\u8cac\u9818\u5c0e\u9304\u5f71\u5ee0\u65e5\u5e38\u6280\u8853\u64cd\u4f5c\n\n\u5165\u8077\u8981\u6c42\uff1a\n\n\u4e2d\u4e94\u4ee5\u4e0a\u7a0b\u5ea6\u4e26\u67095\u5e74\u6216\u4ee5\u4e0a\u76f8\u95dc\u5de5\u4f5c\u7d93\u9a57\n\u5177\u6709\u9304\u5f71\u5ee0\u5404\u7a2e\u57fa\u672c\u5668\u6750\u64cd\u4f5c\u77e5\u8b58\u8005\u00a0\n\u6ce8\u91cd\u5718\u968a\u5408\u4f5c\u4e26\u80fd\u65bc\u58d3\u529b\u4e0b\u7368\u7acb\u5de5\u4f5c\n\u80fd\u592024\u5c0f\u6642\u8f2a\u73ed\u5de5\u4f5c\n\u80fd\u8b1b\u7cb5\u8a9e\u3001\u666e\u901a\u8a71\u3001\u82f1\u8a9e\uff0c\u5177\u5099\u826f\u597d\u53e3\u8a9e\u53ca\u66f8\u5beb\u80fd\u529b\n\nResponsibilities:\n\nIn charge of daily studio technical operations.\n\nRequirements:\n\nForm 5 or above with over 5 years relevant working experience.\nKnowledge of general studio equipment.\nA good team player, independent and able to work under pressure.\nAble to work 24-hour shift duties.\nGood command of written and spoken English and Chinese, proficiency in Putonghua is an advantage.\n\nFor more details of our company, please visit our website at http://www.ifeng.com/\n\nWe offer attractive remuneration package to the right candidate. Interested parties please click \u201cApply Now\u201d to submit applications or send applications with detailed resume stating career history, present & expected salary and date available to Human Resources Department, Phoenix Satellite Television Co. Ltd. via fax: 2200 8620.\n\n\u00a0Personal data collected will be used for recruitment purpose only. Applicants not hearing from us within 6 weeks may consider their applications unsuccessful and all related information will be destroyed after 6 months.", "employment_types": ["Full Time", "Permanent"], "selling_points": ["Sales & Marketing", "Outdoor media sales", "Account Servicing"], "locations": ["Tai Koo"], "categories": ["Media & Advertising", "Account Servicing", "Others", "Sales, CS & Business Devpt", "Account Servicing"], "post_time": "2022-01-18T01:48:17Z", "salary": {"currency": null, "max": null, "min": null, "period": "monthly", "term": null}, "salary_visible": false, "title_keywords": ["sales executive"], "responsibilities": ["operations"], "requirements": {"degrees": ["form 5 or above"], "majors": [], "languages": ["putonghua", "english", "chinese"], "language_level": ["advantage", "proficiency", "good command"], "hard_skills": [], "soft_skills": ["good team player", "independent", "work under pressure"], "languages_combined": [{"language": "putonghua", "language_level": ["proficiency", "advantage", "good command"]}, {"language": "english", "language_level": ["proficiency", "advantage", "good command"]}, {"language": "chinese", "language_level": ["proficiency", "advantage", "good command"]}]}, "experience_required": {"duration": ["5 years"], "field": ["relevant working experience"]}}, {"job_id": "100003009055665", "location_code": "hk", "company": "BDO Financial Services Limited", "job_title": "Senior Manager, Marketing", "description": "This position is suitable for those who have experience in social media platforms management, including FB, IG, Youtube and Linkedin. Fresh graduates who are familiar with social trends will be considered.\n\nJob Nature:\u00a0\u00a0\n\nFully responsible for social media activities (e.g. FB, IG, Youtube, Linkedin), on content development and execution, data analysis, strategy for growth etc.\nCreate core content that fit the channel nature\nHandle multiple projects simultaneously and manage various accounts/ campaigns in a timely and professional manner\nAnalyze data and insights to guide strategy and implementation of solutions\nTo manage campaigns deliverables and coordinate with the internal parties to implement digital campaigns\n\nCharacters / Qualifications:\u00a0\n\nDegree holder, 1+ years experience in social media marketing field. Candidates with more than 3 years experience will be considered for manager title.\nExperience in business/ and finance platform management will be an advantage\nDigitally savvy with strong interest in social trends\nDerive strong satisfaction in creating high engagement and viral content that fit our brands\nCheerful and creative, with marketing sense and data driven mind\nStrong communication skills and ability to influence counterparts/stakeholders at various levels\nSelf-motivated showing strong sense of ownership and able to work under pressure\n\nWe offer competitive salary and benefits package (5 days work, 14 days AL up, birthday leave, medical & dental insurance) with great opportunity for career development to the successful candidate.\n\nPlease send your detailed resume and expected salary to us by clicking \"Apply Now\" (please put position applied on subject line)", "employment_types": ["Full Time", "Permanent"], "selling_points": ["Team Leadership", "A Highly Visible Role", "Stable Work Hours"], "locations": ["Not Specified"], "categories": ["Media & Advertising", "Others", "Marketing / Public Relations", "Marketing - Brand / Product Management", "E-commerce", "Marketing - Brand / Product Management"], "post_time": "2022-01-18T02:50:28Z", "salary": {"currency": null, "max": null, "min": null, "period": "monthly", "term": null}, "salary_visible": false, "title_keywords": ["senior manager"], "responsibilities": ["social media", "management", "data", "social media platforms", "professional manner", "implementation", "coordinate with", "data analysis", "communication", "digital campaigns", "career development", "analyze data", "multiple projects", "insurance", "internal parties", "work under pressure"], "requirements": {"degrees": ["degree holder"], "majors": ["marketing"], "languages": [], "language_level": [], "hard_skills": ["analysis"], "soft_skills": ["communication skills", "self-motivated", "cheerful", "marketing sense", "responsible", "timely", "detailed", "creative", "driven", "work under pressure"], "languages_combined": []}, "experience_required": {"duration": ["3 years", "1+ years"], "field": ["social media", "management", "finance", "business", "marketing"]}}, {"job_id": "100003009049327", "location_code": "hk", "company": "Phoenix Satellite Television Co Ltd", "job_title": "Programme Editor", "description": "Our client is engaged in the selling of wellness products and is looking for a seasoned Marketing professional to lead a team to drive the business forward\n\nKey Responsibilities\u00a0\n\nManage a team and to formulate marketing strategies to support the firm\u2019s future business growth\nDevelop marketing strategies to promote the firm\u2019s product and brand\nPrepare budgets and forecasts and assist in the development of new initiatives\nDrive monthly, quarterly, and annual promotion and campaign strategy\nSet project priorities, define and rollout market\u2019s marketing plans and provide strategic leadership\nCreation of compelling propositions that are segment and industry-relevant and highlight the company's points of differentiation\nIdentify market-specific growth opportunities and evaluate progress towards goals and timelines\nEnhance, monitor, and evaluate existing marketing initiatives and results\nPerform data analysis on market, competitors, and customer to establish marketing direction\nConduct review and evaluate marketing programs from time to time and make recommendations on program modifications, where necessary\n\n\u00a0Key Requirements:\u00a0\u00a0\n\nBachelor degree in business management, marketing or related disciplines\n\nSolid 8-12 years experience in marketing & communication with a multinational company\nFamiliar with MLM Marketing / Beauty/Health Care/Pharmaceutical Marketing\nProven track record of successfully developing and executing integrated marketing initiatives, particularly promotions/campaigns\nDemonstrates business plan development skills and experience including competitive analysis, SWAT analysis, value proposition, break-even analysis, forecasting, etc.\nStrong data analysis, reporting, research, and problem-solving skills\n\nInterested parties please send your application\u00a0with full career history, current and expected salary by\u00a0clicking\u00a0Apply Now\u00a0button below. Applications will be treated in strict confidence. Personal data collected will be used for recruitment purposes only.", "employment_types": ["Full Time", "Permanent"], "selling_points": [], "locations": ["Tai Po Area"], "categories": ["Media & Advertising", "Production", "Others", "Broadcasting - TV / Radio"], "post_time": "2022-01-14T08:28:19Z", "salary": {"currency": null, "max": null, "min": null, "period": null, "term": null}, "salary_visible": false, "title_keywords": ["editor"], "responsibilities": ["make recommendations", "budgets", "marketing strategies", "marketing plans", "review", "monitor", "develop", "evaluate", "data analysis"], "requirements": {"degrees": ["degree", "bachelor"], "majors": ["related disciplines", "business", "marketing"], "languages": [], "language_level": [], "hard_skills": ["business management", "problem-solving skills", "analysis"], "soft_skills": ["communication", "problem-solving skills"], "languages_combined": []}, "experience_required": {"duration": ["8-12 years"], "field": ["business", "development", "marketing", "multinational company"]}}, {"job_id": "100003009052767", "location_code": "hk", "company": "GDC Technology Limited", "job_title": "Digital Media Technician", "description": "Support Post-Production Department, including but not limited to:\n\nOperation of Video/Audio encoding (tape-based) and transcoding (file-based) hardware and software\nOperation of digital contents distribution\nSome Insert/Assembly Editing using various software packages; viewing and quality control of encoded video clips\nUtilize and monitor production database(s), inputting data as necessary to track progress on work orders\nAssist in video editing by using Canva, Adobe or other tools\nNight shift is occasional\nOther ad hoc duties as required\n\n\u00a0Requirements:\n\nHigher diploma in IT, Multimedia or other related disciplines\nFamiliarity with video processing software, excellent in Final Cut Pro and Adobe Premiere are preferred\nKnowledge in video editing is preferred\nFamiliarity with Windows and Mac environments\nAble to work with limited supervision\nGood communications skills in English\nAbility to interact in a clear and logical manner\nAbility to work in a fast-paced team environment\nImmediate availability is preferred\n\nAttractive remuneration package will be offered.\n\nAll information provided by applicants will be treated in strict confidence and used only for processing application.\n", "employment_types": ["Full Time", "Permanent"], "selling_points": [], "locations": ["North Point"], "categories": ["Media & Advertising", "Production", "Others", "Others", "Others"], "post_time": "2022-01-17T03:58:54Z", "salary": {"currency": null, "max": null, "min": null, "period": "monthly", "term": null}, "salary_visible": false, "title_keywords": ["technician"], "responsibilities": ["ad hoc duties", "software", "editing", "data", "monitor", "video editing", "hardware", "quality control", "contents", "audio"], "requirements": {"degrees": ["diploma"], "majors": ["related disciplines", "it"], "languages": ["english"], "language_level": ["good"], "hard_skills": ["clips", "final cut pro", "video editing", "hardware", "adobe", "adobe premiere", "multimedia", "processing"], "soft_skills": ["clear", "confidence"], "languages_combined": [{"language": "english", "language_level": ["good"]}]}, "experience_required": {"duration": [], "field": []}}, {"job_id": "100003009056398", "location_code": "hk", "company": "One Media Group Limited", "job_title": "Business Director, Business Solutions", "description": "About the job\n\nThe right candidate is responsible for overseeing the development of a media platform business goals and objectives. The typically work is to increase business revenue, identify and develop business opportunities. Other duties and responsibilities may include establishing effective company policies, goals, and sales targets. Business directors are also expected to negotiate contracts with clients and suppliers and propose and develop new partnerships.", "employment_types": ["Full Time"], "selling_points": [], "locations": ["Not Specified"], "categories": ["Media & Advertising", "Others", "Management", "Top Executives (CEO, CFO, CTO, GM, MD etc.)"], "post_time": "2022-01-18T04:09:26Z", "salary": {"currency": null, "max": null, "min": null, "period": "monthly", "term": null}, "salary_visible": false, "title_keywords": ["director"], "responsibilities": ["business goals", "other duties", "policies", "business opportunities", "contracts", "develop"], "requirements": {"degrees": [], "majors": [], "languages": [], "language_level": [], "hard_skills": [], "soft_skills": ["responsible"], "languages_combined": []}, "experience_required": {"duration": [], "field": []}}, {"job_id": "100003009052723", "location_code": "hk", "company": "Imagine Lab Limited", "job_title": "Designer", "description": "Responsibilities:\n\n\nDeveloping creative concepts, visual and artwork for event, coordination of production, social media, campaign, leaflet, poster, packaging, website, etc.\nHandling 2D and 3D design work\nAbility to demonstrate excellence in creativity across multiple media\nImplementation of marketing plans & promotion and supporting Event & Marketing team on product launching\nWorking closely with the project team to ensure smooth daily operations\n\nRequirements:\n\n\nDegree/higher diploma holder in a relevant design discipline\n1-2 years or above working experience in graphic design for print ads, booklets, event backdrops, exhibition, mall decoration, etc.\nHands-on experience in using Adobe CS, particularly in Photoshop and Illustrator\nGood hand drawing skill is preferable\nWith knowledge in multi-media & web design\nGood layout and presentation skill\nProficient in 3D Max/C4D/3D software\nSelf-motivated, creative, independent, be able to work under pressure and meet deadlines\nHaving positive and passionate approach with a can-do attitude\nWilling to work overtime and outside normal office hours\nImmediately is preferable\n\nOffice location: Yau Tong\n\nInterested parties please send your detailed resume, portfolio and expected salary to\u00a0us.\u00a0(All personal data collected will be used for recruitment purpose only)\u00a0", "employment_types": ["Full Time", "Permanent"], "selling_points": [], "locations": ["Others"], "categories": ["Media & Advertising", "Others", "Design", "Graphics", "Multi-media"], "post_time": "2022-01-17T03:48:35Z", "salary": {"currency": null, "max": null, "min": null, "period": "monthly", "term": null}, "salary_visible": false, "title_keywords": ["designer"], "responsibilities": ["design work", "social media", "marketing plans", "leaflet", "developing", "website", "implementation", "daily operations", "coordination", "visual"], "requirements": {"degrees": ["degree", "higher diploma holder"], "majors": ["design"], "languages": [], "language_level": [], "hard_skills": ["presentation skill", "web design", "c4d", "3d software", "illustrator", "adobe cs", "max", "photoshop"], "soft_skills": ["presentation skill", "passionate", "self-motivated", "work overtime", "independent", "can-do attitude", "hands-on", "meet deadlines", "creative", "positive", "work under pressure"], "languages_combined": []}, "experience_required": {"duration": ["1-2 years"], "field": ["graphic design", "print", "cs"]}}, {"job_id": "100003009055755", "location_code": "hk", "company": "Hakuhodo Hong Kong Ltd", "job_title": "Media Executive", "description": "Requirements\n\nDegree holder in marketing communications/ advertising/ journalism/\u00a0media related disciplines\n1 year relevant work experience in media agency or media sales\nFresh graduate is also considered\nFluent in both written and spoken English and Chinese\nExcellent PC skills of MS Word, Excel and PowerPoint\nAttentive to details, sensitive to figures, responsible, willing to work overtime and under pressure\n\n\n\nJob Duties\n\nMedia booking and materials follow up\nDaily coordination and liaison with external media partners and media vendors\nPreparation of competitive reports and post buy reports to clients\nProvide support on clerical works, handle monthly billing and material flow when needed\nGather market information for the regular media and research updates\n\n\n\nInterested applicants please send full resume with expected salary by clicking \u201cAPPLY NOW\u201d or by post to Administration Director, 25/F., Prosperity Millennia Plaza, 663 King\u2019s Road, North Point, Hong Kong.\n\nPersonal data collected will be used for recruitment purpose only.", "employment_types": ["Full Time", "Permanent"], "selling_points": ["Degree in communications/ advertising/ media", "1 yr work exp in media agency / media sales", "Fresh graduate"], "locations": ["North Point"], "categories": ["Media & Advertising", "Media Buying", "Strategic Planning", "Others"], "post_time": "2022-01-18T02:55:39Z", "salary": {"currency": null, "max": null, "min": null, "period": "monthly", "term": null}, "salary_visible": false, "title_keywords": ["executive"], "responsibilities": ["provide support", "market information", "reports", "booking", "coordination", "recruitment", "personal data", "administration"], "requirements": {"degrees": ["fresh graduate", "degree holder"], "majors": ["marketing communications", "related disciplines", "journalism"], "languages": ["english", "chinese"], "language_level": ["fluent"], "hard_skills": ["excel", "pc skills", "powerpoint", "ms word"], "soft_skills": ["work overtime", "under pressure", "attentive to details", "responsible", "sensitive to figures"], "languages_combined": [{"language": "english", "language_level": ["fluent"]}, {"language": "chinese", "language_level": ["fluent"]}]}, "experience_required": {"duration": ["1 year"], "field": ["agency", "media", "media sales"]}}, {"job_id": "100003009056540", "location_code": "hk", "company": "Cre8 (Greater China) Limited", "job_title": "Compositor / Typesetter / Operator (\u96fb\u8166\u6392\u7248\u54e1 / \u6392\u7248\u690d\u5b57\u54e1)", "description": "Job Descriptions :\n\nType, prepare and input information\u00a0into the system\nConvert documents with both languages in Chinese and English into finished artworks\n\nJob Requirements :\n\nFast and accurate typing,\u00a0Chinese word processing (Changjie input) with minimum of 40 w.p.m. in English typing\nShift duty is required\u00a0(shift allowance will be provided for afternoon and overnight shift)\nProficiency in PC operating systems; experience in InDesign, Illustrator, Photoshop will be an advantage\n\nWe offer an attractive remuneration package and fringe benefits to the right candidate.\nTo apply, please send your full resume and expected salary via email to:\n\nEmail: Click \"Apply Now\"\n\n(Personal data provided will be used for recruitment purpose only)", "employment_types": ["Full Time", "Permanent"], "selling_points": ["Changjie input & word processing with 40 w.p.m.", "Shift duty is required", "Shift allowance (for pm & overnight shift)"], "locations": ["Central"], "categories": ["Media & Advertising", "Others", "Print Media", "Others", "Student / Fresh Graduate / No Experience"], "post_time": "2022-01-18T04:44:30Z", "salary": {"currency": null, "max": null, "min": null, "period": "monthly", "term": null}, "salary_visible": false, "title_keywords": ["compositor", "operator", "typesetter"], "responsibilities": [], "requirements": {"degrees": [], "majors": [], "languages": ["english", "chinese"], "language_level": [], "hard_skills": ["chinese word processing", "indesign", "illustrator", "typing", "pc", "photoshop"], "soft_skills": ["accurate"], "languages_combined": [{"language": "english", "language_level": []}, {"language": "chinese", "language_level": []}]}, "experience_required": {"duration": [], "field": []}}, {"job_id": "100003009049705", "location_code": "hk", "company": "Global Fitness Training Association Company Limited", "job_title": "\u4f38\u5c55/\u904b\u52d5\u8b1b\u5e2b", "description": "Responsibilities:\u00a0\n\nResponsible for the production of TV programmes, especially live newscast.\n\nRequirements:\n\n\nCertificate/Diploma/Degree holder in Journalism/Communication, with 5 years relevant working experience in programme production.\nExperienced in handling live newscast and programme\nWorking at digital media platform is an advantage.\nKnowledge in editing\nSelf-motivated, creative and independent.\nAble to work 24-hour shift duties.\nGood command of written and spoken English and Chinese, proficiency in Putonghua is an advantage.\n\nFor more details of our company, please visit our website at http://www.ifeng.com\n\nWe offer attractive remuneration package to the right candidate. Interested parties please click \u201cApply Now\u201d to submit applications or send applications with detailed resume stating career history, present & expected salary and date available to Human Resources Department, Phoenix Satellite Television Co. Ltd. via fax: 2200 8620.\n\n\u00a0Personal data collected will be used for recruitment purpose only. Applicants not hearing from us within 6 weeks may consider their applications unsuccessful and all related information will be destroyed after 6 months.", "employment_types": ["Part Time"], "selling_points": [], "locations": ["Not Specified"], "categories": ["Media & Advertising", "Others", "Medical Services", "Medical Services Technician", "Specialist"], "post_time": "2022-01-14T09:07:51Z", "salary": {"currency": null, "max": null, "min": null, "period": "hourly", "term": null}, "salary_visible": false, "title_keywords": [], "responsibilities": [], "requirements": {"degrees": ["certificate", "diploma", "degree holder"], "majors": ["journalism"], "languages": ["putonghua", "english", "chinese"], "language_level": ["advantage", "proficiency", "good command"], "hard_skills": [], "soft_skills": ["communication", "self-motivated", "creative", "independent"], "languages_combined": [{"language": "putonghua", "language_level": ["proficiency", "advantage", "good command"]}, {"language": "english", "language_level": ["proficiency", "advantage", "good command"]}, {"language": "chinese", "language_level": ["proficiency", "advantage", "good command"]}]}, "experience_required": {"duration": ["5 years"], "field": ["relevant working experience"]}}, {"job_id": "100003009049326", "location_code": "hk", "company": "Phoenix Satellite Television Co Ltd", "job_title": "EFP Technician \u5916\u666f\u63a1\u8a2a\u6280\u8853\u54e1", "description": "\u8077\u52d9\u7bc4\u570d\uff1a\n\n\u64cd\u4f5c\u9304\u5f71\u5ee0\u5167\u76f8\u95dc\u5668\u6750\uff0c\u5982\u8996\u8a0a\u5207\u63db\u53f0\u53ca\u64ad\u51fa\u4f3a\u670d\u5668\u7b49\n\u652f\u63f4\u65e5\u5e38\u9304\u5f71\u5ee0\u7684\u4e00\u822c\u904b\u4f5c\u00a0 \u00a0\n\n\u5165\u8077\u8981\u6c42\uff1a\n\n\u4e2d\u4e94\u7562\u696d\u6216\u4ee5\u4e0a\u5b78\u6b77\n\u6709\u95dc\u5de5\u4f5c\u7d93\u9a57\u6703\u512a\u5148\u8003\u616e\n\u5177\u76f8\u95dc\u5ee3\u64ad\u5668\u6750\u64cd\u4f5c\u77e5\u8b58\u8005\u6703\u512a\u5148\u8003\u616e\u00a0\n\u9700\u65bc\u58d3\u529b\u4e0b\u5de5\u4f5c\u53ca\u5177\u5718\u9ad4\u7cbe\u795e\n\u9700\u8f2a\u73ed\u53ca\u901a\u5bb5\u5de5\u4f5c\n\u826f\u597d\u7684\u4e2d\u82f1\u6587\u8b80\u5beb\u80fd\u529b\u53ca\u666e\u901a\u8a71\u807d\u529b\n\nResponsibilities:\n\nOperate related studio equipment as assigned, such as Video Switcher and Video Server.\nProvide comprehensive support to daily studio operations.\n\nRequirements:\n\nForm 5 or above with relevant working experience is preferable.\nKnowledge of operating electronic equipment is an advantage.\nAble to work under pressure and must be a team player.\nAble to work 24-hour shift duties.\nExcellent command of written and spoken English and Chinese, good understanding in Putonghua.\n\nFor more details of our company, please visit our website at http://www.ifeng.com/\n\nWe offer attractive remuneration package to the right candidate. Interested parties please click \u201cApply Now\u201d to submit applications or send applications with detailed resume stating career history, present & expected salary and date available to Human Resources Department, Phoenix Satellite Television Co. Ltd. via fax: 2200 8620.\n\n\u00a0Personal data collected will be used for recruitment purpose only. Applicants not hearing from us within 6 weeks may consider their applications unsuccessful and all related information will be destroyed after 6 months.", "employment_types": ["Full Time", "Permanent"], "selling_points": [], "locations": ["Tai Po Area"], "categories": ["Media & Advertising", "Production", "Others", "Broadcasting - TV / Radio"], "post_time": "2022-01-14T08:28:19Z", "salary": {"currency": null, "max": null, "min": null, "period": null, "term": null}, "salary_visible": false, "title_keywords": ["technician"], "responsibilities": ["operations"], "requirements": {"degrees": ["form 5 or above"], "majors": [], "languages": ["putonghua", "english", "chinese"], "language_level": ["excellent", "good"], "hard_skills": [], "soft_skills": ["team player", "work under pressure"], "languages_combined": [{"language": "putonghua", "language_level": ["excellent", "good"]}, {"language": "english", "language_level": ["excellent", "good"]}, {"language": "chinese", "language_level": ["excellent", "good"]}]}, "experience_required": {"duration": [], "field": ["relevant working experience"]}}, {"job_id": "100003009044731", "location_code": "hk", "company": "New Media Group Publishing Limited", "job_title": "Senior Editor/ Online Editor/Social Editor (\u65b0Monday \u6f6e\u6d41/\u71b1\u8a71/\u5a1b\u6a02)", "description": "Responsibilities :\n\nPropose and implement marketing / promotional programs with clients\nCo-ordinate sales & marketing projects and conduct event management\nResponsible to prepare, design and review all marketing materials including website content, layout, brochures, posters and sales materials\nWork closely with clients, vendors, designers, sales team and internal parties\nPerform ad-hoc projects as assigned\n\nRequirements :\n\nDegree holder in Marketing or related disciplines\n2-3 years marketing experience, experience in media / publication will be an advantage\nGood command of spoken and written English and Chinese\nstrong sense of responsibility, well-organized, self-motivated with excellent communication skills\nImmediately available is preferred\n\n\n\nApplication Method\n\nWe offer competitive salary, discretionary bonus, 5-day work week, public holidays and fringe benefits. Interested parties, please send full resume with expected salary to\u00a0ORIENTAL HUMAN RESOURCES LIMITED\u00a0by clicking \"Apply now\" ;\u00a0or\u00a0fax to 3600 1900\u00a0( Please quote reference on the application letter )\n\n\u00a0\nPersonal Information Collection Statement\n\nPersonal data collected will be treated in accordance with our Personal Data Policy and handled in strict confidence by authorized personnel for recruitment related purpose only.\n\non.cc", "employment_types": ["Full Time", "Permanent"], "selling_points": ["Digital and online knowledge", "Generating ideas for articles and features", "Great development opportunity, competitive package"], "locations": ["Kwun Tong"], "categories": ["Media & Advertising", "Creative / Design", "Others", "Editorial / Journalism"], "post_time": "2022-01-13T05:55:38Z", "salary": {"currency": null, "max": null, "min": null, "period": null, "term": null}, "salary_visible": false, "title_keywords": ["editor", "senior editor"], "responsibilities": ["management", "review", "marketing projects", "design", "website", "sales team", "marketing materials", "ad-hoc projects", "internal parties"], "requirements": {"degrees": ["degree holder"], "majors": ["related disciplines", "marketing"], "languages": ["english", "chinese"], "language_level": ["good command"], "hard_skills": [], "soft_skills": ["communication skills", "self-motivated", "well-organized", "sense of responsibility"], "languages_combined": [{"language": "english", "language_level": ["good command"]}, {"language": "chinese", "language_level": ["good command"]}]}, "experience_required": {"duration": ["2-3 years"], "field": ["marketing", "media"]}}, {"job_id": "100003009048642", "location_code": "hk", "company": "EVI Services Limited", "job_title": "Digital Sales & Marketing Executive", "description": "Responsibilities:\n\nTechnical support for location shooting and news covering including audio, lighting and signal transmission etc.\n\nRequirements:\n\nSecondary education or above with 3 years\u2019 relevant work experience\nGood command of written and spoken English, Chinese and Putonghua\nKnowledge in PC and Internet\nShift duty and overseas travel required\nProactive and a team player\nRelevant experience in TV industry is preferred\n\nFor more details of our company, please visit our website at http://www.ifeng.com/\n\nWe offer attractive remuneration package to the right candidate. Interested parties please click \u201cApply Now\u201d to submit applications or send applications with detailed resume stating career history, present & expected salary and date available to Human Resources Department, Phoenix Satellite Television Co. Ltd. via fax: 2200 8620.\n\nPersonal data collected will be used for recruitment purpose only. Applicants not hearing from us within 6 weeks may consider their applications unsuccessful and all related information will be destroyed after 6 months.", "employment_types": ["Full Time"], "selling_points": [], "locations": ["Mong Kok"], "categories": ["Media & Advertising", "Others"], "post_time": "2022-01-14T07:04:29Z", "salary": {"currency": null, "max": null, "min": null, "period": "monthly", "term": null}, "salary_visible": false, "title_keywords": ["sales & marketing executive"], "responsibilities": ["technical support", "audio"], "requirements": {"degrees": ["secondary education"], "majors": [], "languages": ["putonghua", "english", "chinese"], "language_level": ["good command"], "hard_skills": ["pc"], "soft_skills": ["team player", "proactive"], "languages_combined": [{"language": "putonghua", "language_level": ["good command"]}, {"language": "english", "language_level": ["good command"]}, {"language": "chinese", "language_level": ["good command"]}]}, "experience_required": {"duration": ["3 years"], "field": ["relevant experience", "education"]}}, {"job_id": "100003009046099", "location_code": "hk", "company": "Sing Tao Management Services Limited", "job_title": "Content Creator (Local Feature - New Media Business)", "description": "Job Nature:\n\nGenerating ideas for articles and features\nEdit article\nRe-edit magazine content for online\nAnalyze data\nCharacters / Qualifications:\n\nBachelor degree holder\nOver 1-5 years experience on lifestyle reporting and editing\nDigital and online knowledge\nUnderstanding of the magazine and multimedia industries\nGood communication skills and self motivated\nGood judgement & Good\u00a0execution ability\nTeam oriented, Well organized\nPositive and hard working\n\nWe offer competitive salary and benefits package( 5 days work, 14 days AL up, birthday leave, medical & dental insurance) with great opportunity for career development to the successful candidate.\n\nPlease send your detailed resume and expected salary to us by clicking \"Apply Now\" (please put position applied on subject line).", "employment_types": ["Full Time", "Permanent"], "selling_points": [], "locations": ["Tseung Kwan O"], "categories": ["Media & Advertising", "Production", "Others", "Editorial / Journalism"], "post_time": "2022-01-13T09:36:45Z", "salary": {"currency": null, "max": null, "min": null, "period": "monthly", "term": null}, "salary_visible": false, "title_keywords": [], "responsibilities": ["reporting", "ideas", "communication", "career development", "analyze data", "editing", "insurance"], "requirements": {"degrees": ["bachelor degree holder"], "majors": [], "languages": [], "language_level": [], "hard_skills": ["multimedia"], "soft_skills": ["communication skills", "hard working", "well organized", "self motivated", "positive", "detailed"], "languages_combined": []}, "experience_required": {"duration": ["1-5 years"], "field": ["editing"]}}, {"job_id": "100003009047708", "location_code": "hk", "company": "F T GROUP LIMITED", "job_title": "\u651d\u5f71\u5e2b\u52a9\u7406 Photographer Assistant", "description": "\u00a0 \u00a0 \u00a0 -\u00a0Proactively monitor and optimize campaigns spending and performance\u00a0on\n\u00a0 \u00a0 \u00a0 \u00a0 Website, Facebook, Google Ads, and other digital platforms on a daily basis.\n\u00a0 \u00a0 \u00a0 -\u00a0\u00a0Closely communicate with advertising partners and manage agency accounts\n\u00a0 \u00a0 \u00a0 \u00a0 \u00a0to ensure performance is delivered.\n\u00a0 \u00a0 \u00a0 -\u00a0Produce regular data analysis, market trending research and reporting\n\u00a0 \u00a0 \u00a0 \u00a0 \u00a0with associated insights.\n\u00a0 \u00a0 \u00a0 -\u00a0Develop, present, and sell customized packages based on client briefs.\n\u00a0 \u00a0 \u00a0 -\u00a0Strong presentation, communication, interpersonal, time management and\n\u00a0 \u00a0 \u00a0 \u00a0 \u00a0problem-solving skills.\n\u00a0 \u00a0 \u00a0 - Coordinate and support sales and marketing tasks.\n\u00a0 \u00a0 \u00a0 -\u00a0Work with design/production teams to promote sales events.\n\u00a0 \u00a0 \u00a0 -\u00a0Perform ad-hoc duties as assigned by Department Head.\n\u00a0 \u00a0 \u00a0 - Assist in developing business opportunities to achieve advertising sales targets.\n\nQualifications & Skills\n\n\u00a0\u00a0\u00a0 \u00a0 -\u00a0Familiar with digital marketing tools including Facebook ads manager,\u00a0social\n\u00a0 \u00a0 \u00a0 \u00a0 \u00a0 media, 3rd party tracking, LTV modeling, SEO and Google Analytics.\n\u00a0 \u00a0 \u00a0 -\u00a0Proficiency in MS Word, Excel and PowerPoint and Chinese Word Processing.\n\u00a0 \u00a0 \u00a0 -\u00a0Bachelor Degree in Business, Marketing, Advertising, eCommerce or related\n\u00a0 \u00a0 \u00a0 \u00a0 \u00a0disciplines\n\u00a0 \u00a0 \u00a0 -\u00a02 years of digital marketing experience\n\u00a0 \u00a0 \u00a0 -\u00a0Strong in written and spoken English and Chinese\n\u00a0 \u00a0 \u00a0 - Potential fresh graduates are also welcome", "employment_types": ["Full Time"], "selling_points": ["\u559c\u6b61\u5c0f\u670b\u53cb,\u5f85\u4eba\u6709\u79ae,\u505a\u4e8b\u6709\u8010\u6027", "\u7d93\u9a57\u4e0d\u9650, \u6b61\u8fce\u525b\u7562\u696d\u6709\u5fd7\u6210\u70ba\u651d\u5f71\u5e2b\u7684\u6c42\u8077\u8005", "\u5354\u52a9\u651d\u5f71\u5e2b\u5b8c\u6210\u6bcf\u5929\u62cd\u651d\u5de5\u4f5c"], "locations": ["Not Specified"], "categories": ["Media & Advertising", "Others", "Design", "Others", "Photography / Video"], "post_time": "2022-01-14T03:47:35Z", "salary": {"currency": null, "max": null, "min": null, "period": "monthly", "term": null}, "salary_visible": false, "title_keywords": ["assistant", "photographer"], "responsibilities": ["website", "design", "communication", "facebook", "advertising", "monitor", "teams", "developing", "develop", "reporting", "management", "seo", "business opportunities", "data analysis", "digital marketing", "ad-hoc duties", "tracking", "communicate with", "coordinate"], "requirements": {"degrees": ["degree", "bachelor"], "majors": ["ecommerce", "business", "marketing"], "languages": ["english", "chinese"], "language_level": ["proficiency"], "hard_skills": ["google analytics", "excel", "seo", "chinese word processing", "analysis", "powerpoint", "problem-solving skills", "facebook", "ms word"], "soft_skills": ["presentation", "communication", "ad-hoc duties", "problem-solving skills", "time management", "interpersonal"], "languages_combined": [{"language": "english", "language_level": []}, {"language": "chinese", "language_level": ["proficiency"]}]}, "experience_required": {"duration": ["2 years"], "field": ["digital marketing"]}}, {"job_id": "100003009042291", "location_code": "hk", "company": "Big Honor Entertainment Limited", "job_title": "Digital Marketing Executive", "description": "Responsibilities:\n\nStrong sense on local news & current affairs\nSearch and explore local special topics\nProficiency in video editorial, work independently for data collection and interviewing\nWillingness to appear upon the camera\n\nRequirements:\n\nInitiative, strong written communication skills\nGood team player; prepare quality articles, feature stories, etc.\nBachelor Degree holder with relevant experience will be considered in advanced\nFamiliar with major social platforms\nMedia work experiences with video editing and frame-out are preferred\nPlease bring along your portfolio or any references for interview\nWorking Location: Tseung Kwan O Industrial Estate\n\nInterested parties please click \u201cApply Now\" to submit your complete resume with\u00a0employment history, expected salary and REFERENCE NUMBER or by\u00a0post to\u00a0Human\u00a0Resources Department,\u00a0Sing Tao News Corporation Building, 7 Chun Cheong Street, Tseung Kwan O Industrial Estate, Tseung Kwan O, New Territories, Hong Kong\n\nWe are an equal opportunity employer and welcome applications from all qualified candidates. Information provided will be treated in strict confidence and only be used for recruitment related purpose. Applicant who is not invited for an interview within 6 weeks may consider their application not successful. All personal data of unsuccessful applicants will be destroyed within 6 months.\n\nwww.singtaonewscorp.com", "employment_types": ["Full Time"], "selling_points": ["Digital Marketing Executive", "Degree or Diploma holder", "Fresh graduates"], "locations": ["Kwun Tong"], "categories": ["Media & Advertising", "Others"], "post_time": "2022-01-12T06:53:27Z", "salary": {"currency": null, "max": null, "min": null, "period": "monthly", "term": null}, "salary_visible": false, "title_keywords": ["digital marketing executive"], "responsibilities": ["data collection"], "requirements": {"degrees": ["bachelor degree holder"], "majors": [], "languages": [], "language_level": [], "hard_skills": ["video editing"], "soft_skills": ["advanced", "communication skills", "good team player", "initiative"], "languages_combined": []}, "experience_required": {"duration": [], "field": ["video", "relevant experience", "media", "editing"]}}, {"job_id": "100003009047451", "location_code": "hk", "company": "The University of Hong Kong", "job_title": "Project Associate", "description": "\u5354\u52a9\u651d\u5f71\u5e2b\u5b8c\u6210\u6bcf\u5929\u62cd\u651d\u5de5\u4f5c\n\nAssist photographer to complete the daily work.\n\n\u559c\u6b61\u5c0f\u670b\u53cb,\u5f85\u4eba\u6709\u79ae,\u505a\u4e8b\u6709\u8010\u6027\n\nBe kind and patience, Love Kids.\n\n\u6027\u683c\u5916\u5411\uff0c\u958b\u6717\u6d3b\u6f51\n\nOutgoing, cheerful and lively.\n\n\u9700\u65bc\u5f71\u6a13\u53ca\u6236\u5916\u5de5\u4f5c\n\nNeed to work in Studio and Outdoor.\n\n\u7d93\u9a57\u4e0d\u9650, \u6b61\u8fce\u525b\u7562\u696d\u6709\u5fd7\u6210\u70ba\u651d\u5f71\u5e2b\u7684\u6c42\u8077\u8005\n\nExperience not limited, welcome fresh graduate.\n\n\u61c2Photoshop, Premiere \u64cd\u4f5c\u512a\u5148\u8003\u616e\n\nPhotoshop, Premiere knowledge will have priority.", "employment_types": ["Full Time"], "selling_points": ["Events and knowledge exchange activities", "Photos and video shooting and editing", "Content creation and management"], "locations": ["Pok Fu Lam"], "categories": ["Media & Advertising", "Others"], "post_time": "2022-01-14T03:07:12Z", "salary": {"currency": null, "max": null, "min": null, "period": "monthly", "term": null}, "salary_visible": false, "title_keywords": ["associate"], "responsibilities": [], "requirements": {"degrees": ["fresh graduate"], "majors": [], "languages": [], "language_level": [], "hard_skills": ["premiere", "photoshop"], "soft_skills": ["outgoing", "cheerful", "patience"], "languages_combined": []}, "experience_required": {"duration": [], "field": []}}, {"job_id": "100003009048061", "location_code": "hk", "company": "Speechless Financial Technology Company Limited", "job_title": "Social Media Executive (Finance)", "description": "Responsibilities:\n\nDevelop and design Company website\nUpdate contents for online communications channels, including but not limited to website, apps and social media platforms\nAssist for creative copywriting, including research, writing, editing and content management\nMonitor the performance of social media platforms and make support to the frontend and backend of website and apps for further development\nPerform ad-hoc marketing duties as assigned\n\nRequirements: \u00a0\u00a0\u00a0\u00a0\u00a0\n\nDegree or Diploma holder in Marketing / Communications / Multi-media or other disciplines\n1-2 years relevant experience in marketing, with experience in media field is an advantage\nProactive, independent and willing to learn\nGood knowledge of designing and editing softwares, such as Photoshop, Adobe After Effects, Adobe Illustrators etc.\u00a0\nFamiliar with programming languages, including HTML, CSS and JavaScript etc.\u00a0\u00a0\nFresh graduates will also be considered", "employment_types": ["Full Time", "Permanent"], "selling_points": ["Young, fun and energized company", "Flexible and creative working environment", "#marketdigest #businessdigest"], "locations": ["Lai Chi Kok"], "categories": ["Media & Advertising", "Others", "Editorial / Journalism", "Marketing / Public Relations", "Digital Marketing"], "post_time": "2022-01-14T04:38:01Z", "salary": {"currency": null, "max": null, "min": null, "period": "monthly", "term": null}, "salary_visible": false, "title_keywords": ["social media executive"], "responsibilities": ["ad-hoc", "management", "social media platforms", "website", "design", "develop", "monitor the performance", "contents", "editing", "company website"], "requirements": {"degrees": ["diploma holder", "degree"], "majors": ["marketing", "communications"], "languages": [], "language_level": [], "hard_skills": ["html", "adobe after effects", "adobe", "javascript", "programming", "css", "photoshop"], "soft_skills": ["proactive", "independent", "willing to learn"], "languages_combined": []}, "experience_required": {"duration": ["1-2 years"], "field": ["marketing", "relevant experience", "media"]}}, {"job_id": "100003009049816", "location_code": "hk", "company": "Hakuhodo Hong Kong Ltd", "job_title": "Account Executive / Senior Account Executive (4As Advertising Agency)", "description": "Project Associate\u00a0in the Hong Kong Institute for the Humanities and Social Sciences (Ref.: 511494) (to commence as soon as possible for one year, with the possibility of renewal subject to satisfactory performance and funding availability)\n\nApplicants should possess a Bachelor\u2019s degree or above in Journalism, Communication, Multimedia, Visual Communication or a related discipline. \u00a0They should have an excellent command of written and spoken English and Chinese; the ability to work independently with high standards of professionalism and organizational skills; and good interpersonal, analytical and communication skills.\u00a0 They should have strong proficiency in Final Cut Pro X and/or Adobe Premiere CC, knowledge of designing storyboard, colour correction, audio engineering and sound design, Adobe After Effect and Photoshop, latest multimedia technology, knowledge management system and photography.\n\nThe appointee will assist in events and knowledge exchange activities. \u00a0He/She will be responsible for photos and video shooting and editing, and content creation and management. \u00a0He/she will also provide research-related administrative support to the Institute.\n\nApplicants should be Hong Kong residents and fresh graduates. \u00a0Existing staff of the University need not apply.\u00a0\n\nThe University only accepts online application for the above post. \u00a0Applicants should apply online and upload an up-to-date CV. \u00a0Review of applications will start as soon as possible and continue until\u00a0February 28, 2022, or until the post is filled, whichever is earlier.", "employment_types": ["Full Time", "Permanent"], "selling_points": ["Degree in advertising/marketing", "1 yr BTL/production exp", "Self motivated, good communication skill"], "locations": ["North Point"], "categories": ["Media & Advertising", "Account Servicing", "Production", "Others"], "post_time": "2022-01-14T09:16:47Z", "salary": {"currency": null, "max": null, "min": null, "period": "monthly", "term": null}, "salary_visible": false, "title_keywords": ["account executive", "senior account executive"], "responsibilities": ["management", "editing", "administrative support", "review", "design", "communication", "video shooting", "visual", "designing", "audio"], "requirements": {"degrees": ["degree or above", "bachelor"], "majors": ["journalism"], "languages": ["english", "chinese"], "language_level": ["excellent"], "hard_skills": ["final cut pro", "adobe after effect", "visual communication", "adobe premiere", "multimedia", "exchange", "photoshop"], "soft_skills": ["organizational skills", "work independently", "communication skills", "responsible", "communication", "interpersonal"], "languages_combined": [{"language": "english", "language_level": ["excellent"]}, {"language": "chinese", "language_level": ["excellent"]}]}, "experience_required": {"duration": [], "field": []}}, {"job_id": "100003009046098", "location_code": "hk", "company": "Sing Tao Management Services Limited", "job_title": "Content Creator (Consume, F&B - New Media Business)", "description": "Degree holder in advertising /marketing communications /business studies related disciplines\n1yr+ exp of integrated advertising / digital agency / production house\nPrevious exp in handling BTL / production is highly preferred\nGood interpersonal and communication skills, self motivated and able to work under pressure\nFluent in both written and spoken English and Mandarin\nExcellent PC skills of MS Word, Excel and PowerPoint", "employment_types": ["Full Time", "Permanent"], "selling_points": [], "locations": ["Tseung Kwan O"], "categories": ["Media & Advertising", "Production", "Others", "Editorial / Journalism"], "post_time": "2022-01-13T09:36:44Z", "salary": {"currency": null, "max": null, "min": null, "period": "monthly", "term": null}, "salary_visible": false, "title_keywords": [], "responsibilities": ["communication", "advertising", "work under pressure"], "requirements": {"degrees": ["degree holder"], "majors": ["marketing communications", "related disciplines", "business"], "languages": ["english", "mandarin"], "language_level": ["fluent"], "hard_skills": ["excel", "pc skills", "powerpoint", "ms word"], "soft_skills": ["self motivated", "communication skills", "interpersonal", "work under pressure"], "languages_combined": [{"language": "english", "language_level": ["fluent"]}, {"language": "mandarin", "language_level": ["fluent"]}]}, "experience_required": {"duration": [], "field": []}}, {"job_id": "100003009044197", "location_code": "hk", "company": "City University of Hong Kong", "job_title": "Public Relations Assistant I/II (Graphic Design) in Communications and Public Relations Office", "description": "Responsibilities:\n\nGreat interest on high end consumes and F&B\nSolid grasp of information, investigate and share with readers\nProficiency in video editorial, work independently for data collection and interviewing\n\nRequirements:\n\nInitiative, strong written communication skills\nGood team player; prepare quality articles, feature stories, etc.\nBachelor Degree holder with relevant experience will be considered in advanced\nFamiliar with major social platforms\nMedia work experiences with video editing and frame-out are preferred\nPlease bring along your portfolio or any references for interview\nWorking Location: Tseung Kwan O Industrial Estate\n\nInterested parties please click \u201cApply Now\" to submit your complete resume with\u00a0employment history, expected salary and REFERENCE NUMBER or by\u00a0post to\u00a0Human\u00a0Resources Department,\u00a0Sing Tao News Corporation Building, 7 Chun Cheong Street, Tseung Kwan O Industrial Estate, Tseung Kwan O, New Territories, Hong Kong\n\nWe are an equal opportunity employer and welcome applications from all qualified candidates. Information provided will be treated in strict confidence and only be used for recruitment related purpose. Applicant who is not invited for an interview within 6 weeks may consider their application not successful. All personal data of unsuccessful applicants will be destroyed within 6 months.\n\nwww.singtaonewscorp.com", "employment_types": ["Full Time", "Contract"], "selling_points": ["Gratuity, leave, medical and dental schemes", "5 passes in HKCEE/HKDSEE", "2 years\u2019 relevant working experience"], "locations": ["Not Specified"], "categories": ["Media & Advertising", "Production", "Others", "Marketing / Public Relations", "Public Relations - General / Support"], "post_time": "2022-01-13T18:54:37Z", "salary": {"currency": null, "max": null, "min": null, "period": "monthly", "term": null}, "salary_visible": false, "title_keywords": ["assistant"], "responsibilities": ["data collection"], "requirements": {"degrees": ["bachelor degree holder"], "majors": [], "languages": [], "language_level": [], "hard_skills": ["video editing"], "soft_skills": ["advanced", "communication skills", "good team player", "initiative"], "languages_combined": []}, "experience_required": {"duration": [], "field": ["video", "relevant experience", "media", "editing"]}}, {"job_id": "100003009044158", "location_code": "hk", "company": "City University of Hong Kong", "job_title": "Research Assistant in the School of Creative Media (Appointment for 5 months) [Ref. C/R/399/03]", "description": "Public Relations Assistant I/II (Graphic Design) in Communications and Public Relations Office\u00a0[Ref. D/317/03]\n\nDuties :\u00a0\n\nThe appointee is responsible for providing professional design services for the publicity and publication projects of the Office.\u00a0 Main duties include designing and updating layouts of brochures, magazines, advertorials, social media posts and other corporate communications materials; retouching photos for printing and online publishing through Content Management System (CMS); maintaining the smooth operation of online communication platforms; providing clerical and logistics support for university events; and performing any other duties as assigned.\n\nRequirements :\u00a0\u00a0\n5 passes in HKCEE/HKDSEE including English Language, Chinese Language and Mathematics, with 2 years\u2019 relevant post-qualification working experience in sizeable companies.\u00a0 Good command of written and spoken English and Chinese; computer literacy in Photoshop, Illustrator, InDesign, PowerPoint, English and Chinese word-processing; basic knowledge of video format conversion; good interpersonal and teamwork skills; and ability to work independently and under pressure against tight schedules are required.\u00a0 Preference will be given to candidates with professional training in design or related disciplines.\n\nCandidates with more than 6 years\u2019 relevant post-qualification working experience may be considered for appointment as Public Relations Assistant I (Graphic Design).\n\nShortlisted candidates will be invited for a written test.\nSalary and Conditions of Service\nRemuneration package will be highly competitive, commensurate with qualifications and experience.\u00a0 Appointment will be made on a fixed-term contract; fringe benefits include gratuity, leave, medical and dental schemes.\nInformation and Application\nFurther information on the post and the University is available at http://www.cityu.edu.hk, or from the Human Resources Office, City University of Hong Kong, Tat Chee Avenue, Kowloon Tong, Hong Kong [Fax : 2788 1154 or 3442 0311].\u00a0\nTo apply, please submit an online application at http://jobs.cityu.edu.hk.\u00a0 The closing date is\u00a028 January 2022.\u00a0 Applications will receive full consideration and only shortlisted applicants will be contacted.\u00a0 The University\u2019s privacy policy is available on the homepage.\nCity University of Hong Kong is an equal opportunity employer. \u00a0We are committed to the principle of diversity. Personal data provided by applicants will be used for recruitment and other employment-related purposes.\nWorldwide recognition ranking #53 (QS survey 2022), and #4 among top 50 universities under age 50 (QS survey 2021); #1 in the World\u2019s Most International Universities (THE survey 2020); #1 in Engineering/Technology/Computer Sciences in Hong Kong (ARWU survey 2016); and #1 Business School in Asia-Pacific region (UT Dallas survey 2019).", "employment_types": ["Full Time", "Contract"], "selling_points": ["A Master\u2019s degree in Law", "No more than a total of 6 years of service", "Leave, medical and dental consultations"], "locations": ["Wong Tai Sin Area"], "categories": ["Media & Advertising", "Others", "Editorial / Journalism"], "post_time": "2022-01-13T18:54:40Z", "salary": {"currency": null, "max": null, "min": null, "period": "monthly", "term": null}, "salary_visible": false, "title_keywords": ["creative", "research assistant"], "responsibilities": ["retouching", "social media", "management", "any other duties", "maintaining", "design", "communication", "logistics", "designing", "publication"], "requirements": {"degrees": [], "majors": [], "languages": ["english", "chinese"], "language_level": ["good command"], "hard_skills": ["basic", "chinese word-processing", "indesign", "illustrator", "powerpoint", "photoshop"], "soft_skills": ["work independently", "under pressure", "teamwork", "computer literacy", "interpersonal"], "languages_combined": [{"language": "english", "language_level": ["good command"]}, {"language": "chinese", "language_level": ["good command"]}]}, "experience_required": {"duration": ["6 years", "2 years"], "field": ["chinese language", "graphic design", "public relations", "post-qualification"]}}, {"job_id": "100003009039537", "location_code": "hk", "company": "Price.com.hk Limited", "job_title": "Anchor / Editor", "description": "Project :\n\nAccountability and Transparency of International Social Media Platforms in HKSAR in the Algorithmic Era\n\n\nDuties :\u00a0\n\nThe appointee will work on multi-disciplinary research in digital communication and media law, and study the regulations of digital content, including creative works and entertainment. Main duties include, but not limited to the following:\u00a0\n\n\n\nConduct literature review on the issues;\nCollect and systematise relevant laws and regulations;\nAssist the supervisor in conducting law and policies analysis; and\nPerform other administrative and research tasks.\n\nRequirements :\u00a0\u00a0\n\n\nA Master\u2019s degree in Law with no more than a total of 6 years of service at the University;\nFluency in both written and spoken English and Chinese (including Putonghua);\nFamiliarity with HKSAR law and the field of Communication, and preferably with UK/EU Law;\nFamiliarity with doctrinal legal analysis, empirical research methods and comparative studies;\nDemonstrated ability to conduct qualitative research of high-quality;\nPreference will be given to candidates having research publications, particularly papers published in peer-reviewed journals; and\nSkills in quantitative methodology, programming, coding, understanding of AI and machine learning principles would be an advantage.\nImmediate availability is preferred.\n\nSalary and Conditions of Service\n\nSalary offered will be highly competitive, commensurate with qualifications and experience. Fringe benefits include leave, medical and dental consultations at the campus clinic.\n\nInformation and Application\n\nFurther information on the post and the University is available at\u00a0http://www.cityu.edu.hk, or from the Human Resources Office, City University of Hong Kong, Tat Chee Avenue, Kowloon Tong, Hong Kong.\u00a0 [Fax : 2788 1154 or 3442 0311].\u00a0\n\nTo apply, please submit an online application at http://jobs.cityu.edu.hk, and include the following documents:\n\na statement of interests (2 pages maximum);\nan up-to-date CV; and\nno more than two examples of research publications or any other examples of previous legal analytical or research work.\n\nThe closing date is\u00a012 February 2022. Applications will receive full consideration and only shortlisted applicants will be contacted. The University's privacy policy is available on the homepage.\n\nCity University of Hong Kong is an equal opportunity employer. \u00a0We are committed to the principle of diversity. Personal data provided by applicants will be used for recruitment and other employment-related purposes.\n\nWorldwide recognition ranking #53 (QS survey 2022), and #4 among top 50 universities under age 50 (QS survey 2021); #1 in the World\u2019s Most International Universities (THE survey 2020); #1 in Engineering/Technology/Computer Sciences in Hong Kong (ARWU survey 2016); and #1 Business School in Asia-Pacific region (UT Dallas survey 2019).", "employment_types": ["Full Time", "Permanent"], "selling_points": ["Fast Growing Industry", "An Expanding E-Commerce Company", "Offer Training & Development"], "locations": ["Kwun Tong"], "categories": ["Media & Advertising", "Others", "Editorial / Journalism", "Marketing / Public Relations", "Public Relations - Copy-writing"], "post_time": "2022-01-11T10:01:21Z", "salary": {"currency": null, "max": null, "min": null, "period": "monthly", "term": null}, "salary_visible": false, "title_keywords": ["editor", "anchor"], "responsibilities": ["regulations", "policies", "analysis", "communication", "literature review"], "requirements": {"degrees": ["degree", "master"], "majors": ["law"], "languages": ["putonghua", "english", "chinese"], "language_level": ["fluency"], "hard_skills": ["no", "analysis", "programming", "ai"], "soft_skills": ["communication", "learning"], "languages_combined": [{"language": "putonghua", "language_level": []}, {"language": "english", "language_level": ["fluency"]}, {"language": "chinese", "language_level": ["fluency"]}]}, "experience_required": {"duration": [], "field": []}}, {"job_id": "100003009044805", "location_code": "hk", "company": "Big Big Channel Limited", "job_title": "BUSINESS DEVELOPMENT MANAGER", "description": "Join us to create new values to the online offline commerce communities\n\nPrice.com.hk, being one of the most popular online platforms* in Hong Kong, strives to bring extra values to merchants and consumers by not only connecting them seamlessly with our state-of-the-art technology but co-creating a community that encourages a more user centric shopping experience combined with the application of big data analytics.\n\nWe start with a goal to minimize market information costs incurred upon consumers allowing them to find their favorite products easier and faster and at the same time enable merchants to successfully run their brick and click strategies to reach their targeted consumers at the lowest cost possible. Today, we are serving 2M+ monthly unique visitors. We cannot accomplish that without working together with individuals who are passionate about what they do.\u00a0\n\n*According to Alexa, Price.com.hk is one of the top 25 most frequently visited sites in Hong Kong. https://www.alexa.com/siteinfo/price.com.hk\n\n\nWebsite:\u00a0http://www.price.com.hk/\nFacebook Page:\u00a0http://bit.ly/1VkYTJx\nYoutube channel:\u00a0https://bit.ly/3z7jB7d\n\nYour role with us involves:\nHost for Youtube channel:\nhttps://www.youtube.com/channel/UCUEJok-GiWaGlv5nIPwk-GQ\nAble to face the camera professionally and confidently\nProduce comprehensive and reliable content on product comparisons and reviews in both article and/or script formats\nDiscover the hottest and newest topics and products, write about them in fresh and engaging ways\nObserve and analyze the interests of our readers and cater to their tastes\nCreate advertorial content\nCollaborate with other departments and business partners\n\nAs an employer, our role is to empower you by bringing your true talents and best self to this dynamic digital world and the people we serve. We welcome individuals from all backgrounds, ideally with skills and traits as below:\n\nDiploma or above\nMinimum 1 year experience in copywriting, social media or related fields\nFamiliar with consumer electronics and gadgets\nSelf-motivated and able to work independently\nAttention to details\nProficient in MS Office and Chinese Word Processing\n\n\u00a0\u00a0Be part of us, you will enjoy:\n\nDiscretionary Bonus\n5-day Work Week\nFlexible Working Hour\nBirthday, Marriage, Maternity and Paternity Leave\nBirthday Gift\nMedical Insurance\nMonthly Birthday Party\nTeam Event and Team Building Activities\nHappy and Dynamic Environment\nCasual Dress Code\nWorking Location: Kwun Tong (5 minutes from Kwun Tong MTR station)\n\n\nInterested parties, please click \"Apply now\" to submit your resume with the availability and expected salary to us.\n\nPersonal data collected will be kept strictly confidential and only be used for recruitment related purpose.\n", "employment_types": ["Full Time", "Permanent"], "selling_points": [], "locations": ["Not Specified"], "categories": ["Media & Advertising", "Others", "Sales, CS & Business Devpt", "Business Development", "Account Servicing"], "post_time": "2022-01-13T06:21:42Z", "salary": {"currency": null, "max": null, "min": null, "period": "monthly", "term": null}, "salary_visible": false, "title_keywords": ["business development manager"], "responsibilities": ["collaborate with", "social media", "cost", "market information", "big data", "website", "facebook", "insurance", "costs"], "requirements": {"degrees": ["diploma or above"], "majors": [], "languages": ["chinese"], "language_level": ["proficient"], "hard_skills": ["chinese word processing", "data analytics", "code", "goal", "dynamic", "facebook", "ms office"], "soft_skills": ["flexible", "self-motivated", "work independently", "dynamic environment", "unique", "comprehensive", "dynamic", "attention to details", "reliable", "passionate about"], "languages_combined": [{"language": "chinese", "language_level": ["proficient"]}]}, "experience_required": {"duration": ["minimum 1 year"], "field": ["copywriting", "social media", "related"]}}, {"job_id": "100003009050111", "location_code": "hk", "company": "Mani Limited", "job_title": "SENIOR MARKETING EXECUTIVE / MARKETING EXECUTIVE", "description": "Responsibilities\nTo assist team to develop new advertising products between TV Content and Digital Assets.\nResponsible for preparation of all-rounded media proposals with ability to understand clients\u2019 marketing needs and objective\nTo prospect and develop new clients through personal connection, cold calls to direct clients and achieving revenue targets\nAble to develop new business with creative approach\nTo ensure clients\u2019 campaign is fulfilled along the entire sales cycle, from pitching, production and deliverables\nRequirements\nUniversity graduate with Minimum 2-year working experience related to business development /media sales / account servicing \u00a0\nFresh graduates with can-do attitude will also be considered\nMature, creative, aggressive, self-motivated and energetic\nExcellent interpersonal skills with both internal and external stakeholders\nFluency in both English and Chinese\nFamiliar with digital, content marketing and social media solution selling is an advantage\nCandidate with more experience will be offered a senior position\nImmediate available is an advantage\nAttractive remuneration package and excellent prospect will be offered to the right candidate.\u00a0 Please send application with our reference no., detailed resume, present and expected salary to Human Resources Manager, BIG BIG CHANNEL Limited, 8/F, Main Block, TVB City, 77 Chun Choi Street, Tseung Kwan O Industrial Estate, Tseung Kwan O, Kowloon or fax to 2335-9751 or by clicking \u201cApply Now\u201d.\nAll information provided will be used for recruitment purpose only.\u00a0 All personal data of unsuccessful candidates will be destroyed.", "employment_types": ["Full Time", "Permanent"], "selling_points": [], "locations": ["Lai Chi Kok"], "categories": ["Media & Advertising", "Others", "Marketing / Public Relations", "Marketing - General / Support", "Public Relations - Event Management"], "post_time": "2022-01-14T09:47:46Z", "salary": {"currency": null, "max": null, "min": null, "period": "monthly", "term": null}, "salary_visible": false, "title_keywords": ["senior marketing executive", "marketing executive"], "responsibilities": ["develop new business", "advertising", "develop"], "requirements": {"degrees": ["university graduate"], "majors": ["business"], "languages": ["english", "chinese"], "language_level": ["fluency"], "hard_skills": ["no"], "soft_skills": ["self-motivated", "creative", "can-do attitude", "mature", "interpersonal skills", "energetic", "detailed"], "languages_combined": [{"language": "english", "language_level": ["fluency"]}, {"language": "chinese", "language_level": ["fluency"]}]}, "experience_required": {"duration": ["minimum 2-year"], "field": ["related", "account servicing", "business development", "media sales"]}}, {"job_id": "100003009036683", "location_code": "hk", "company": "Phoenix Satellite Television Co Ltd", "job_title": "\u5167\u5bb9\u904b\u71df\u7de8\u8f2f\uff08\u521d\u7d1a\u3001\u4e2d\u7d1a\u3001\u9ad8\u7d1a\uff09", "description": "Responsibilities:\n\nDirect strategic and operating plan development to market company services and products, inclusive of performing R & D, formulating marketing strategy, launching new projects / marketing plan, building brand name and image, and handling of advertising and promotional activities.\nPlan, organize, and manage advertising and promotion, PR & publicity activities so as to achieve business goals.\nDevelop effective marketing and communication plans, budgets and new project implementation schedules.\nOversee the implementation of event / exhibition projects from planning, recruiting exhibitors /\u00a0visitors, liaison with business partners and media, on-site management to post-event evaluation.\nCooperate and interface with high profile business partners for impactful launch of new event projects/ products and bolstering company market positioning, and increasing market reach.\n\n\n\nRequirements:\n\nUniversity graduate in Marketing / Business Administration or related disciplines.\nOver 2 years experience in Marketing related areas and/ or FMCG industry.\nProven ability and successful track record to acquire, build and grow worldwide renowned brands / properties through marketing tactics.\nHands-on experience in broad range of marketing functions including event / exhibition management, advertising and PR, brand building, publicity, retail marketing, and coordination with principals / agencies.\nGood command of spoken and written English and Chinese. \u00a0Proficiency in Chinese copywriting.\nTeam player who is self-motivated, creative, energetic, and result-oriented. Able to work independently and under pressure and meet tight deadlines.\nSound leadership skill and excellent communication & presentation skills for effective teamwork, staff management and the development of positive working relationships with team members, customers, suppliers, licensors, principals, and strategic alliances.\nStrong media networking and media relations skills required.\n\nWe offer 5-day work, attractive remuneration package and a challenging environment for professionals with immediate availability preferred. Interested parties please send resume with current and expected salary via e-mail by clicking \"Apply Now\" for application.\n\nPersonal data collected will be used for recruitment purpose only.\n", "employment_types": ["Full Time"], "selling_points": [], "locations": ["Tai Po Area"], "categories": ["Media & Advertising", "Others"], "post_time": "2022-01-10T12:29:13Z", "salary": {"currency": null, "max": null, "min": null, "period": null, "term": null}, "salary_visible": false, "title_keywords": [], "responsibilities": ["budgets", "business goals", "advertising", "schedules", "implementation", "site management", "develop", "communication", "marketing plan", "promotional activities", "plan", "evaluation", "plans", "planning"], "requirements": {"degrees": ["university graduate"], "majors": ["related disciplines", "marketing", "business administration"], "languages": ["english", "chinese"], "language_level": ["proficiency", "good command"], "hard_skills": ["fmcg industry"], "soft_skills": ["self-motivated", "work independently", "under pressure", "meet tight deadlines", "leadership skill", "teamwork", "communication", "hands-on", "energetic", "presentation skills", "coordination", "team player", "creative", "result-oriented", "positive"], "languages_combined": [{"language": "english", "language_level": ["good command"]}, {"language": "chinese", "language_level": ["proficiency", "good command"]}]}, "experience_required": {"duration": ["2 years"], "field": ["management", "fmcg", "advertising", "pr", "brand", "related", "marketing", "retail"]}}, {"job_id": "100003009046402", "location_code": "hk", "company": "Wheelock Properties (Hong Kong) Ltd", "job_title": "Assistant Corporate Communications Officer", "description": "\u5d17\u4f4d\u8077\u8cac\uff1a\n\n\u8ca0\u8cac\u6bcf\u5929\u6536\u96c6\u5404\u65b9\u71b1\u9ede\u3001\u8981\u805e\uff0c\u63d0\u4f9b\u9078\u984c\u7dda\u7d22\uff0c\u6839\u64da\u9078\u984c\uff0c\u57f7\u884c\u904b\u71df\u65b9\u6848\uff1b\n\n\u2022\u8ca0\u8cac\u6240\u5c6c\u7248\u9762\u5404\u985e\u5167\u5bb9\u8cc7\u6e90\u7684\u7de8\u8f2f\u3001\u5be9\u6838\u3001\u4e0a\u4e0b\u7dda\u53ca\u767c\u4f48\uff1b\n\n\u8ca0\u8cac\u90e8\u5206\u6587\u5b57\u7de8\u8f2f\u5de5\u4f5c\uff0c\u53ca\u57fa\u672c\u5e73\u9762\u88fd\u4f5c\u6216\u8996\u983b\u526a\u8f2f\u5de5\u4f5c\uff1b\n\n\u2022\u8ca0\u8cac\u8a71\u984c\u9810\u71b1\u3001\u7c89\u7d72\u4e92\u52d5\u3001\u88fd\u4f5c\u5c08\u984c\u3001\u9032\u884c\u6d3b\u52d5\u76f4\u64ad\u7b49\uff1b\n\n\u5176\u4ed6\u5b89\u6392\u7684\u5de5\u4f5c\n\n\u5d17\u4f4d\u8981\u6c42\uff1a\n\n\u672c\u79d1\u4ee5\u4e0a\u5b78\u6b77\uff0c\u4e00\u5e74\u4ee5\u4e0a\u5a92\u9ad4\u3001\u4e92\u806f\u7db2\u7b49\u76f8\u95dc\u5de5\u4f5c\u7d93\u9a57\n\u71b1\u611b\u5404\u985e\u8cc7\u8a0a\uff0c\u6709\u71b1\u60c5\uff0c\u6709\u654f\u92b3\u7684\u6d1e\u5bdf\u529b\u548c\u6355\u6349\u80fd\u529b\uff0c\u6709\u826f\u597d\u7684\u7684\u908f\u8f2f\u601d\u8003\u548c\u8cc7\u6599\u5206\u6790\u80fd\u529b\n\u6709\u826f\u597d\u7684\u4e2d\u6587\u3001\u82f1\u6587\u3001\u7cb5\u8a9e\u7684\u8b80\u5beb\u548c\u8868\u9054\u80fd\u529b\n\u80fd\u64cd\u4f5c\u8996\u983b\u53ca\u5e73\u9762\u7de8\u8f2f\u8edf\u4ef6\n\u6709\u8f03\u597d\u7684\u6587\u5b57\u529f\u5e95\n\u71b1\u611b\u5a92\u9ad4\u884c\u696d\uff0c\u71b1\u611b\u4e92\u806f\u7db2\u884c\u696d\uff0c\u5c0d\u65b0\u9bae\u4e8b\u7269\u6709\u597d\u5947\u5fc3\n\u71b1\u611b\u9999\u6e2f\uff0c\u77ad\u89e3\u9999\u6e2f\uff0c\u64c1\u6709\u9999\u6e2f\u6216\u5927\u7063\u5340\u5a92\u9ad4\u8cc7\u6e90\u8005\u512a\u5148\n\u80fd\u63a5\u53d7\u8f2a\u73ed\u53ca\u5468\u672b\u4e0a\u73ed\uff08\u6709\u88dc\u4f11\uff09", "employment_types": ["Full Time", "Permanent"], "selling_points": [], "locations": ["Central"], "categories": ["Media & Advertising", "Others", "Marketing / Public Relations", "Others"], "post_time": "2022-01-13T18:55:20Z", "salary": {"currency": null, "max": null, "min": null, "period": null, "term": null}, "salary_visible": false, "title_keywords": ["assistant corporate communications officer"], "responsibilities": [], "requirements": {"degrees": [], "majors": [], "languages": [], "language_level": [], "hard_skills": [], "soft_skills": [], "languages_combined": []}, "experience_required": {"duration": [], "field": []}}, {"job_id": "100003009038338", "location_code": "hk", "company": "PHD Limited", "job_title": "Planning Manager (Advertising & Media Field)", "description": "Apoidea Group is an AI-empowered Fintech company. As the founding business of Apoidea, Apoidea Media provides content marketing services to financial institutions. We own 4 media pages - Market Digest, Business Digest, Health Concept, and Beauty Digest and run other financial institution client pages. Apoidea Media has been serving a large proportion of active Equity Derivative Product Issuers in Hong Kong.\n\n\n\n\nWe are looking for a passionate Social Media Executive to manage and create content for our Business Digest and Market\u00a0Digest Instagram pages.\u00a0\n\n\n\n\nJob Description:\n\n\nManage and create content for the social media accounts (especially on Instagram), including copywriting and image creating/editing;\nClosely monitor social media channels for timely response to comments and inquiries from audiences;\nDevelop and lead all video content, including but not limited to script development, storyboarding, concept, editing, etc.\nEnsures contents are original, accurate and fact-based Editorial in driving concept development and content direction for editorial projects;\nSupport the marketing team with English/Chinese language proofreading, editing, copywriting, original content creation and content vetting, etc.\n\nRequirements:\n\nGood knowledge or experience in copywriting;\nDegree Holder in Design, Marketing, Business, E-commerce or related disciplines;\nExperience in using Photoshop, Illustrator, Powerpoint, other design softwares will be a good plus;\u00a0\n1 year of relevant experience in marketing, social media production, preferable in e-commerce industries will be a good plus while fresh graduates will also be considered;\u00a0\nFamiliar with various social media platforms (Facebook, Instagram, Youtube, and etc.);\nPassionate, responsible, and flexible to be a part of the cross-functional team;\nExcellent communication skills and strong problem-solving skills, able to work both independently and as a team;\nGood command of spoken and written Chinese and English.\u00a0", "employment_types": ["Full Time", "Permanent"], "selling_points": ["Free Shuttle Bus & Free Breakfast", "Birthday, Family Day & Self-Love Day Leave", "5-Day Work Week"], "locations": ["Pok Fu Lam"], "categories": ["Media & Advertising", "Account Servicing", "Strategic Planning", "Others"], "post_time": "2022-01-11T06:35:04Z", "salary": {"currency": null, "max": null, "min": null, "period": "monthly", "term": null}, "salary_visible": false, "title_keywords": ["manager"], "responsibilities": ["social media", "comments", "monitor", "develop", "proofreading", "contents", "editing"], "requirements": {"degrees": ["degree holder"], "majors": ["e-commerce", "design", "related disciplines", "business", "marketing"], "languages": ["english", "chinese"], "language_level": ["good command"], "hard_skills": ["plus", "design softwares", "e-commerce", "problem-solving skills", "illustrator", "powerpoint", "facebook", "photoshop"], "soft_skills": ["passionate", "communication skills", "flexible", "independently", "responsible", "problem-solving skills"], "languages_combined": [{"language": "english", "language_level": ["good command"]}, {"language": "chinese", "language_level": ["good command"]}]}, "experience_required": {"duration": ["1 year"], "field": ["social media", "e-commerce", "design", "marketing", "relevant experience", "copywriting"]}}, {"job_id": "100003009042823", "location_code": "hk", "company": "MRRM Publishing Ltd", "job_title": "Assistant Editor / Editor (Digital & Feature)", "description": "Responsibilities:\n\n\nRender logistical and administrative support for the Corporate Communications Department\nDraft correspondences and prepare reports and meeting papers\nConduct research as required\nNews monitoring and reporting\nUpdate and maintain media contact database\nUpdate and coordinate all corporate information\nMaintain departmental budget and corporate subscriptions\nPerform ad hoc duties as required\n\nRequirements:\n\n\nUniversity graduate in communications or related disciplines can be an advantage\nMinimum 3 years of relevant experience, preferably acquired from large corporations\nStrong communication and interpersonal skills\nWell organized and details oriented\nWorks well independently and as a team player\nCan work under pressure and meet tight deadlines\nAble to suggest and implement ideas to increase efficiency\nResourceful and can think outside the box\nProficient in English and Chinese writing\n\nWe offer ample opportunities for career development and attractive salary package commensurate with experience and qualifications. \u00a0Interested parties please apply with full resume via\u00a0\u201cAPPLY NOW\u201d.\u00a0\u00a0 \u00a0\u00a0\n\nFor further information on Wheelock Properties (Hong Kong) Limited, please visit our website: www.wheelockpropertieshk.com\n\n\nWe are an equal opportunities employer and invite applications from all qualified candidates. Personal data collected will be treated in strict confidence and handled by authorized persons for recruitment-related purposes only within the Wheelock & Wharf Group.\u00a0 Applicants not hearing from us within two months may consider their applications unsuccessful.", "employment_types": ["Full Time"], "selling_points": [], "locations": ["Wan Chai"], "categories": ["Media & Advertising", "Others", "Editorial / Journalism", "Print Media"], "post_time": "2022-01-12T08:56:09Z", "salary": {"currency": null, "max": null, "min": null, "period": "monthly", "term": null}, "salary_visible": false, "title_keywords": ["editor", "assistant editor"], "responsibilities": ["ad hoc duties", "reporting", "administrative support", "monitoring", "budget", "coordinate", "maintain", "contact", "database", "prepare reports", "conduct research"], "requirements": {"degrees": ["university graduate"], "majors": ["related disciplines", "communications"], "languages": ["english", "chinese"], "language_level": ["proficient"], "hard_skills": [], "soft_skills": ["meet tight deadlines", "independently", "resourceful", "well organized", "communication and interpersonal skills", "team player", "work under pressure"], "languages_combined": [{"language": "english", "language_level": ["proficient"]}, {"language": "chinese", "language_level": ["proficient"]}]}, "experience_required": {"duration": ["minimum 3 years"], "field": ["relevant experience"]}}, {"job_id": "100003009047457", "location_code": "hk", "company": "Fortune Media Hong Kong Limited", "job_title": "Video Reporter", "description": "The Role Encompasses:\n\nLead the communication planning process for campaigns which includes:\n\nMaintaining good relationship and manage expectation with clients.\nDiscussion and understanding of the brief with client and agency partners.\nDevelop the communication strategy; guiding through to execution to ensure the integrity of the strategy lands in implementation.\nCampaign presentation.\nTo develop competitive/category analysis and provide actionable learnings that are relevant to the brand(s).\nTo lead planning team, to gather market intelligence on post-campaign results, consumer insights, media landscape and competitive activity.\nCascade new skill sets required to implement and drive innovation amongst planners/ executives.\n\n\u00a0We are looking for:\n\nMinimum 4 years + experienced in Media Agency\nFamiliar with Targeting Strategies in AD Network\nStrong knowledge in Programmatic / SEM / Social buying and optimisation\nExperience leading a team and natural ability to develop relationship with your team members\nCantonese and English are a must for this role\nHolding a Bachelor\u2019s Degree or above\n\nWorking Location: Cyberport (\u6578\u78bc\u6e2f), Hong Kong:\n\n\nWe offer a 5-day work of week, group medical & life insurance coverage, free shuttle bus to the right candidate. Interested parties please send your application letter and resume with current and expected salary by clicking the \"Apply Now\" button.\u00a0\u00a0\n\nAll information collected will be used for recruitment only and treated in strict confidence. We will retain the personal data of unsuccessful applicants for future recruitment purpose for a maximum period of 2 years.", "employment_types": ["Full Time", "Permanent"], "selling_points": ["5 days work", "Medical Insurance covered family members", "Near by MTR Kowloon Bay MTR Station"], "locations": ["Kowloon Bay"], "categories": ["Media & Advertising", "Others", "Editorial / Journalism", "Photography / Video"], "post_time": "2022-01-14T03:09:40Z", "salary": {"currency": null, "max": null, "min": null, "period": "monthly", "term": null}, "salary_visible": false, "title_keywords": ["reporter"], "responsibilities": ["consumer insights", "maintaining", "analysis", "planning process", "implementation", "develop", "communication", "good relationship", "sem", "planning"], "requirements": {"degrees": ["degree or above", "bachelor"], "majors": [], "languages": ["cantonese", "english"], "language_level": [], "hard_skills": ["analysis", "sem"], "soft_skills": ["communication", "integrity", "presentation"], "languages_combined": [{"language": "cantonese", "language_level": []}, {"language": "english", "language_level": []}]}, "experience_required": {"duration": [], "field": ["team"]}}, {"job_id": "100003009036572", "location_code": "hk", "company": "HK01 Company Limited", "job_title": "\u8a18\u8005 - \u5a1b\u6a02 (\u901a\u5bb5\u66f4)", "description": "Responsibilities:\n\nManage online content to ensure the accuracy and timeliness of the content\nProvide ideas and continuous input to improve the website\nTo ensure the website\u2019s smoothness and efficiency\u00a0\nWork closely with various departments on providing best content for our users\nVideo recording & editing\nProvide editorial for print version\n\nRequirements:\n\nDiploma or degree holder, prefer in Multimedia-related course\nSolid experience in web content editing work\nGood command of written Chinese\nUnderstanding of web technologies, including Social Media, Content Management Systems, HTML\nProficient in MAC applications (Photoshop, Premiere, iMovie, etc.)\nPassion for fashion and quality lifestyle\n\n\u00a0Interested candidate please provide full resume with latest and expected salary.\n\nPersonal data collected will be used for recruitment purpose only.", "employment_types": ["Full Time", "Permanent"], "selling_points": ["\u8ca0\u8cac\u672c\u5730\u53ca\u570b\u969b\u5a1b\u6a02\u65b0\u805e\u63a1\u8a2a\u5de5\u4f5c", "\u8ca0\u8cac\u5a1b\u6a02\u65b0\u805e\u8996\u983b\u88fd\u4f5c", "\u9700\u8f2a\u66f4\u7576\u503c\u53ca\u901a\u5bb5\u5de5\u4f5c"], "locations": ["Tsuen Wan Area"], "categories": ["Media & Advertising", "Others", "Editorial / Journalism", "Broadcasting - TV / Radio"], "post_time": "2022-01-10T11:07:05Z", "salary": {"currency": null, "max": null, "min": null, "period": "monthly", "term": null}, "salary_visible": false, "title_keywords": ["\u8a18\u8005"], "responsibilities": ["editing", "ideas", "website"], "requirements": {"degrees": ["diploma", "degree holder"], "majors": [], "languages": ["chinese"], "language_level": ["good command"], "hard_skills": ["web", "premiere", "html", "multimedia", "web technologies", "photoshop"], "soft_skills": ["passion for"], "languages_combined": [{"language": "chinese", "language_level": ["good command"]}]}, "experience_required": {"duration": [], "field": ["editing work"]}}, {"job_id": "100003009041952", "location_code": "hk", "company": "Sing Tao Management Services Limited", "job_title": "\u6559\u80b2\u526f\u520a/ \u591a\u5a92\u9ad4\u8a18\u8005 (\u661f\u5cf6\u65e5\u5831\u6559\u80b2\u7248)", "description": "Fortune Media Group\u2014the proprietor of FORTUNE magazine, Fortune.com, the Fortune 500 ranking, and business conferences including the Fortune Global Forum\u2014seeks a video producer to support all aspects of the company\u2019s video operations in Asia. The position, to be based in Hong Kong, will report to the Executive Editor, Asia, and work closely with Asia editorial team as well as Fortune\u2019s global video production and live event team.\n\nRole and Responsibilities\n\n\nProduce Fortune\u2019s weekly Eastworld Spotlight interview series\nContribute regular short \u201cRadar\u201d videos on news and current events\nProduce, edit, and provide technical support for Fortune\u2019s virtual and in-person events in Asia.\nManage and maintain all Fortune video and audio equipment in Hong Kong, including tripods, monitors, lighting, and audio recorders\nManage video assets on subscription-based video and audio platforms such as Getty Images and Associated Press\n\nRequirements:\n\n\nSuccessful candidates for the Video Producer role will demonstrate experience:\n\nShooting video on cameras such as the CanonC100, Canon c300, or Sony FS7\nEditing with software such as Adobe Premiere, Avid or Final Cut\nShooting b-roll\nShooting and running sound simultaneously\nWorking in both office and field environments\nBasic lighting techniques\nConducting interviews\nAbility to write stories in English in various lengths and formats\nAbility to generate story ideas and to identify\u00a0trends before they become consensus\nMandarin and/or Cantonese language skills preferred but not required\nWe offer a dynamic working environment; good career development opportunities and attractive compensation and benefit packages. Interested parties please send your application with full resume stating your present and expected salary by clicking \" Apply Now\".", "employment_types": ["Full Time", "Permanent"], "selling_points": [], "locations": ["Tseung Kwan O"], "categories": ["Media & Advertising", "Others", "Editorial / Journalism", "Others", "Others"], "post_time": "2022-01-12T04:47:56Z", "salary": {"currency": null, "max": null, "min": null, "period": "monthly", "term": null}, "salary_visible": false, "title_keywords": [], "responsibilities": ["technical support", "audio", "maintain"], "requirements": {"degrees": [], "majors": [], "languages": ["cantonese", "english", "mandarin"], "language_level": [], "hard_skills": ["adobe premiere", "basic"], "soft_skills": [], "languages_combined": [{"language": "cantonese", "language_level": []}, {"language": "english", "language_level": []}, {"language": "mandarin", "language_level": []}]}, "experience_required": {"duration": [], "field": ["video"]}}, {"job_id": "100003009041936", "location_code": "hk", "company": "Sing Tao Management Services Limited", "job_title": "Reporter (Daily News - Local News)", "description": "\u4e3b\u8981\u8077\u8cac\n\n\u5f9e\u591a\u89d2\u5ea6\u767c\u6398\u8da3\u805e\u3001\u641c\u96c6\u8cc7\u6599\u53ca\u64b0\u5beb\u6587\u7ae0\n\u8ca0\u8cac\u672c\u5730\u53ca\u570b\u969b\u5a1b\u6a02\u65b0\u805e\u63a1\u8a2a\u5de5\u4f5c\n\u8ca0\u8cac\u5a1b\u6a02\u65b0\u805e\u8996\u983b\u88fd\u4f5c\n\n\u5165\u8077\u8981\u6c42\n\n\u6301\u5927\u5b78\u5b78\u4f4d\u6216\u4ee5\u4e0a\u5b78\u6b77\uff0c\u4e3b\u4fee\u5b78\u79d1\u4e0d\u62d8\n\u719f\u6089\u5404\u5730\u5a1b\u6a02\u8cc7\u8a0a\u6700\u65b0\u52d5\u614b\n\u64c1\u6709\u88fd\u4f5c\u53ca\u62cd\u651d\u5f71\u7247\u548c\u7d93\u71df\u793e\u4ea4\u5e73\u53f0\u7d93\u9a57\u66f4\u4f73\n\u5177\u65b0\u805e\u89f8\u89ba\u8207\u5224\u65b7\u529b\u3001\u61c9\u8b8a\u529b\u9ad8\u3001\u7a4d\u6975\u4e3b\u52d5\uff0c\u53ca\u64c5\u9577\u8207\u4eba\u6e9d\u901a\n\u5c0d\u5468\u908a\u4e8b\u7269\u6709\u597d\u5947\u5fc3\uff0c\u80fd\u5f9e\u4e0d\u540c\u6e20\u9053\u767c\u6398\u65b0\u9bae\u4e8b\u7269\n\u9700\u8f2a\u66f4\u7576\u503c\u53ca\u901a\u5bb5\u5de5\u4f5c\n\u61c9\u5fb5\u8005\u8acb\u5728\u5c65\u6b77\u8868\u4e2d\u9644\u4e0a\u76f8\u95dc\u4e4b\u500b\u4eba\u4f5c\u54c1\n\n\u8acb\u65bc\u6c42\u8077\u4fe1\u8a3b\u660e\u6b32\u61c9\u5fb5\u4e4b\u8077\u4f4d\u3002\u6211\u5011\u6703\u70ba\u5408\u9069\u7684\u4eba\u9078\u63d0\u4f9b\u512a\u539a\u7684\u85aa\u916c\u5f85\u9047\u53ca\u798f\u5229(\u5305\u62ec\u4e94\u5929\u5de5\u4f5c\u5468)\u3002\u61c9\u5fb5\u8005\u8acb\u6309\u300cApply Now\u300d\u6309\u9215\u4e26\u63d0\u4f9b\u5c65\u6b77\u3001\u73fe\u6642\u53ca\u8981\u6c42\u7684\u85aa\u916c\u5f85\u9047\u7b49\u8cc7\u6599\u4f5c\u8077\u4f4d\u7533\u8acb\u3002\n\n\u6240\u6709\u6536\u96c6\u7684\u500b\u4eba\u8cc7\u6599\u90fd\u6703\u56b4\u683c\u4fdd\u5bc6\u4e26\u53ea\u4f5c\u62db\u8058\u7528\u9014\u30023\u500b\u6708\u5167\u672a\u7372\u9762\u8a66\u901a\u77e5\u7684\u7533\u8acb\u8005\uff0c\u53ef\u8996\u5176\u7533\u8acb\u70ba\u4e0d\u6210\u529f\u8ad6\u3002\u53e6\u4e00\u65b9\u9762\uff0c\u5c65\u6b77\u4ea6\u53ef\u80fd\u6839\u64da\u516c\u53f8\u96c6\u5718\u7684\u5167\u90e8\u9700\u8981\uff0c\u9032\u884c\u5167\u90e8\u8f49\u79fb\u3002\u672a\u7372\u63a5\u7d0d\u7684\u7533\u8acb\u8cc7\u6599\u5c07\u6703\u572812\u500b\u6708\u5167\u92b7\u6bc0\u3002", "employment_types": ["Full Time", "Permanent"], "selling_points": [], "locations": ["Tseung Kwan O"], "categories": ["Media & Advertising", "Others", "Editorial / Journalism", "Others", "Others"], "post_time": "2022-01-12T04:42:58Z", "salary": {"currency": null, "max": null, "min": null, "period": "monthly", "term": null}, "salary_visible": false, "title_keywords": ["reporter"], "responsibilities": [], "requirements": {"degrees": [], "majors": [], "languages": [], "language_level": [], "hard_skills": [], "soft_skills": [], "languages_combined": []}, "experience_required": {"duration": [], "field": []}}, {"job_id": "100003009042996", "location_code": "hk", "company": "Phoenix Satellite Television Co Ltd", "job_title": "Broadcast Operator \u5ee3\u64ad\u904b\u4f5c\u6280\u8853\u54e1", "description": "Responsibilities:\n\nWork with professional Broadcast system and Master Control for Digital TV.\nPrepare and inspect on-air schedules and materials according to procedures.\nHandle program transmission operations, pre-recorded playout and live broadcast to ensure broadcast safely.\nMonitor and manipulate incoming and outgoing TV signals traffic and support satellite, live streaming and base-band feed receptions according to bookings.\nPrepare operational report for logistic and follow-up purposes.\n\nRequirements:\n\n\nForm 5/DSE graduates or above, preferably in computing/engineering related disciplines. Fresh graduates will also be considered.\nUnderstanding of broadcast operations, with experience on using different kinds of automation system is an advantage.\nTeam player and detail-oriented at work.\nAble to work in shift hours, including overnight shift.\nExcellent command of written and spoken English and Chinese, proficiency in Putonghua, MS Word and Excel.\n\n\u8077\u8cac\uff1a\n\n\u00a0\u00a0\u00a0\u00a0\u00a0\u00a0 \u8655\u7406\u5c08\u696d\u6578\u78bc\u96fb\u8996\u5ee3\u64ad\u7cfb\u7d71\u548c\u4e2d\u592e\u4fe1\u865f\u7e3d\u63a7\u5de5\u4f5c\u3002\n\u00a0\u00a0\u00a0\u00a0\u00a0\u00a0 \u6309\u7a0b\u5e8f\u6aa2\u6536\u7bc0\u76ee\u64ad\u51fa\u6392\u7a0b\u53ca\u5ee3\u64ad\u6750\u6599\u3002\n\u00a0\u00a0\u00a0\u00a0\u00a0\u00a0 \u8655\u7406\u7bc0\u76ee\u64ad\u653e\uff0c\u5305\u62ec\u9810\u9304\u548c\u73fe\u5834\u76f4\u64ad\uff0c\u4fdd\u969c\u64ad\u51fa\u5b89\u5168\u3002\n\u00a0\u00a0\u00a0\u00a0\u00a0\u00a0 \u76e3\u5bdf\u548c\u64cd\u63a7\u4fe1\u865f\u9032\u51fa\uff0c\u6839\u64da\u9810\u8a02\u652f\u6301\u885b\u661f\u3001\u5be6\u6642/\u78bc\u6d41\u5a92\u9ad4\u994b\u9001\u63a5\u6536\u3002\n\u00a0\u00a0\u00a0\u00a0\u00a0\u00a0 \u70ba\u5f8c\u52e4\u548c\u7ba1\u7406\u6e96\u5099\u904b\u71df\u5831\u544a\u3002\n\u8981\u6c42\uff1a\n\u00a0\u00a0\u00a0\u00a0\u00a0\u00a0 \u9999\u6e2f\u4e2d\u5b78\u6703\u8003/\u6587\u6191\u8a66\u7562\u696d\u6216\u4ee5\u4e0a\u5b78\u6b77\uff0c\u4ee5\u96fb\u8166/\u5de5\u7a0b\u6216\u76f8\u95dc\u5b78\u79d1\u70ba\u4f73\u3002\u61c9\u5c46\u7562\u696d\u751f\u4e5f\u6703\u8003\u616e\u3002\n\u00a0\u00a0\u00a0\u00a0\u00a0\u00a0 \u4e86\u89e3\u5ee3\u64ad\u904b\u4f5c\uff0c\u6709\u4f7f\u7528\u4e0d\u540c\u985e\u578b\u81ea\u52d5\u5316\u7cfb\u7d71\u7d93\u9a57\u8005\u512a\u5148\u3002\n\u00a0\u00a0\u00a0\u00a0\u00a0\u00a0 \u6ce8\u91cd\u5718\u968a\u5408\u4f5c\u53ca\u5de5\u4f5c\u7d30\u7bc0\u3002\n\u00a0\u00a0\u00a0\u00a0\u00a0\u00a0 \u80fd\u5920\u8f2a\u73ed\u5de5\u4f5c\uff0c\u5305\u62ec\u591c\u73ed\u3002\n\u00a0\u00a0\u00a0\u00a0\u00a0\u00a0 \u512a\u79c0\u4e2d\u82f1\u6587\u66f8\u9762\u548c\u53e3\u8a9e\u80fd\u529b\uff0c\u719f\u7df4\u666e\u901a\u8a71\uff0c\u901a\u66c9MS Word\u3001Excel\u904b\u4f5c\nFor more details of our company, please visit our website at http://www.ifeng.com/\n\n\n\nWe offer attractive remuneration package to the right candidate. Interested parties please click \u201cApply Now\u201d to submit applications or send applications with detailed resume stating career history, present & expected salary and date available to Human Resources Department, Phoenix Satellite Television Co. Ltd. via fax: 2200 8620.\n\n\u00a0Personal data collected will be used for recruitment purpose only. Applicants not hearing from us within 6 weeks may consider their applications unsuccessful and all related information will be destroyed after 6 months.", "employment_types": ["Full Time", "Permanent"], "selling_points": [], "locations": ["Tai Po Area"], "categories": ["Media & Advertising", "Others", "Broadcasting - TV / Radio"], "post_time": "2022-01-12T09:27:38Z", "salary": {"currency": null, "max": null, "min": null, "period": null, "term": null}, "salary_visible": false, "title_keywords": ["operator"], "responsibilities": ["control", "schedules", "operations", "procedures", "monitor", "report"], "requirements": {"degrees": ["form 5", "dse"], "majors": ["related disciplines", "engineering"], "languages": ["putonghua", "english", "chinese"], "language_level": ["excellent", "proficiency"], "hard_skills": ["excel", "ms word"], "soft_skills": ["team player", "detail-oriented"], "languages_combined": [{"language": "putonghua", "language_level": ["proficiency", "excellent"]}, {"language": "english", "language_level": ["proficiency", "excellent"]}, {"language": "chinese", "language_level": ["proficiency", "excellent"]}]}, "experience_required": {"duration": [], "field": []}}, {"job_id": "100003009045737", "location_code": "hk", "company": "L.M.D.C. Hong Kong Limited", "job_title": "Assistant Marketing Manager", "description": "Responsibilities\n\nFormulate brand marketing and communications strategies and overseeing marketing campaigns rollout to contribute to the overall brand objectives\nDevelop and manage marketing tools for new product launches and promotions (POSM, Press Release, Yearly Catalogue, Leaflet, etc.) and maintain merchandising standard in the region\nAssist in local campaign collection design development and seasonal collection forecast\nManage CRM programme including data acquisition and maintenance\nPlan and produce social media content; manage social media platforms\nBuild and maintain professional relationship with agencies and vendors to support overall marketing & communications initiatives\nConduct sales analysis reports and competitors benchmark\nResponsible for executing all digital marketing activities and campaigns; to co-ordinate and create content for e-boutique; create and manage e-DM campaigns, SEM, SEO, google adwords etc.\nHandle general e-boutique customers inquires and orders issues\n\n\u00a0Requirements\n\nUniversity graduate in Marketing or related discipline\nAt least 5 years' marketing experience with focus in digital marketing or brand marketing\nNative Cantonese, excellent English and very good Mandarin,\nKnowledge of French language is a strong advantage\nGood knowledge of French Culture\nGood writing skills\nExcellent interpersonal and communication skills\nVery well-organized and independent\nBe meticulous\nHigh adaptability and strong multitasking skills\nImmediate available preferred\n\n\nWe offer 5-day work week and our remuneration packages will be commensurate with your qualifications, experience and capability.\u00a0", "employment_types": ["Full Time", "Permanent"], "selling_points": ["digital marketing or brand marketing", "5 years' marketing experience", "social media"], "locations": ["Ngau Tau Kok"], "categories": ["Media & Advertising", "Others", "Marketing / Public Relations", "Marketing - Brand / Product Management"], "post_time": "2022-01-13T08:29:18Z", "salary": {"currency": null, "max": null, "min": null, "period": "monthly", "term": null}, "salary_visible": false, "title_keywords": ["assistant marketing manager"], "responsibilities": ["seo", "maintenance", "data", "analysis reports", "leaflet", "merchandising", "social media platforms", "design", "develop", "maintain", "social media content", "executing", "marketing campaigns", "forecast", "plan", "digital marketing", "sem", "catalogue"], "requirements": {"degrees": ["university graduate"], "majors": ["marketing"], "languages": ["cantonese", "english", "french", "mandarin"], "language_level": ["native", "excellent", "good", "advantage"], "hard_skills": ["focus", "writing skills"], "soft_skills": ["communication skills", "meticulous", "independent", "well-organized", "writing skills", "adaptability", "focus", "interpersonal"], "languages_combined": [{"language": "cantonese", "language_level": ["native", "excellent", "good"]}, {"language": "english", "language_level": ["native", "excellent", "good"]}, {"language": "french", "language_level": ["good", "advantage"]}, {"language": "mandarin", "language_level": ["native", "excellent", "good"]}]}, "experience_required": {"duration": ["at least 5 years"], "field": ["marketing", "digital marketing", "brand"]}}, {"job_id": "100003009048566", "location_code": "hk", "company": "Executive Search", "job_title": "Marketing and Sales Executive (with attractive bonus)", "description": "Job Description\n\nPURPOSE OF ROLE:\nAs a Marketing and Sales Executive,\u00a0you\u2019ll work to support the development of our multiplatform ecosystem and activation campaigns in driving growth and enhancing customer experiences.\u00a0\u00a0 Also, you\u2019ll will be working tightly with the product and marketing teams of our company.\n\nYour success:\u00a0Increase reach and traffic to financial touchpoints - while simultaneously developing your skills in\u00a0 marketing and sales field.\u00a0\n\nWHAT YOU\u2019LL GET:\nAt GBA, we ask a lot of our team members, which is why we give so much in return. In addition to your competitive salary, medical/insurance and leave entitlement, we\u2019ll shower you with perks, including:\n\nEnvironment: Open, sunny office.\nFlexibility:\u00a0Staggered working hours - pick your own work schedule to fit your own plan.\nBonus:\u00a0Extremely well pay bonus\nLocation:\u00a0\u00a0Above MTR Station, get here quickly thanks to our highly accessible location.\nWellness:\u00a0Chill yourself by joining our wellness programme and bright pantry. Have FUN!\nLove Travel?\u00a0Enjoy FREE incentive trips.\n\nWHAT YOU\u2019LL NEED:\n\nExperience:\u00a01-2 year work experience in customer service, marketing, sales or promotion.\nEducation:\u00a0University or Diploma equivalent qualification.\nSkills:\u00a0Excellent command of written and spoken English and Chinese. Good communication skills.\nPersonality:\u00a0If you are agile, flexible and enjoy working in a dynamic and fast-pace environment, then this is a job for you. Being detail-oriented, independent and diligent is also important.\nExtra Awesome:\u00a0Having an international mindset with a certain understanding of mainland China behaviour is highly preferred\n\nWHAT YOU\u2019LL DO:\n\nCo-ordinate\u00a0with marketing team to manage campaign planning and execution.\nManage\u00a0and implement go-to-market materials and development to drive campaign success\nUnderstand clients need and facilitate to provide suitable solution to them\nGBA provide multiplatform solutions to Hong Kong and the Great Bay Area. We provide solutions on Overseas property, immigration and various financial services area.", "employment_types": ["Full Time", "Permanent"], "selling_points": ["Fun & Dynamic working environment", "Well pay bonus", "Fast growing platform"], "locations": ["Wan Chai"], "categories": ["Media & Advertising", "Others", "Management", "General Management", "Insurance", "Others"], "post_time": "2022-01-14T06:49:00Z", "salary": {"currency": null, "max": null, "min": null, "period": "monthly", "term": null}, "salary_visible": false, "title_keywords": ["sales executive"], "responsibilities": ["co-ordinate with", "teams", "developing", "communication", "customer service", "schedule", "plan", "insurance", "planning"], "requirements": {"degrees": ["diploma"], "majors": [], "languages": ["english", "chinese"], "language_level": ["excellent"], "hard_skills": ["agile", "fun", "chill", "dynamic", "go"], "soft_skills": ["flexible", "communication skills", "independent", "agile", "enjoy working", "diligent", "detail-oriented", "customer service", "dynamic"], "languages_combined": [{"language": "english", "language_level": ["excellent"]}, {"language": "chinese", "language_level": ["excellent"]}]}, "experience_required": {"duration": ["1-2 year"], "field": ["development", "marketing", "customer service"]}}, {"job_id": "100003009039645", "location_code": "hk", "company": "Carat Media Services Hong Kong Limited", "job_title": "Associate Media Manager/ Media Manager", "description": "\u5d17\u4f4d\u8077\u8cac\uff1a\n\n\u5354\u52a9\u5167\u5bb9\u4e3b\u7de8\u5b89\u6392\u63a1\u7de8\u90e8\u5404\u7d44\u6bcf\u65e5\u5de5\u4f5c\u5167\u5bb9\u3001\u91cd\u9ede\u5927\u4e8b\u7b56\u5283\u3001\u6bcf\u65e5\u5404\u7d44\u5167\u5bb9\u9078\u984c\u65b9\u5411\u628a\u63e1\n\u5177\u9ad4\u8ca0\u8cac\u5c0d\u5167\u5bb9\u767c\u4f48\u9032\u884c\u5be9\u6838\n\u91dd\u5c0d\u63a1\u7de8\u90e8\u5167\u5bb9\u751f\u7522\u6d41\u7a0b\u9032\u884c\u6709\u6548\u7684\u512a\u5316\u7ba1\u7406\uff0c\u7d44\u7e54\u843d\u5be6\u696d\u52d9\u7d50\u69cb\u6d41\u7a0b\u8abf\u6574\n\n\u4efb\u8077\u8981\u6c42\uff1a\n\n\u719f\u6089\u76ee\u6a19\u53d7\u773e\u6240\u5728\u5730\u5a92\u9ad4\u751f\u614b\uff0c\u81f3\u5c11\u5728\u9999\u6e2f\u4e09\u5e74\u4ee5\u4e0a\u5a92\u9ad4\u884c\u696d\u5f9e\u696d\u7d93\u9a57\uff0c\u5169\u5e74\u4ee5\u4e0a\u7684\u5718\u968a\u7ba1\u7406\u7d93\u9a57\uff0c\u57f7\u884c\u80fd\u529b\u5f37\uff0c\u6709\u512a\u79c0\u7684\u5718\u968a\u7ba1\u7406\u6c34\u5e73\n\u6709\u8c50\u5bcc\u7684\u539f\u5275\u5167\u5bb9\u751f\u7522\u7d93\u9a57\uff0c\u5c0d\u65b0\u805e\u9078\u984c\u5167\u5bb9\u6709\u5c08\u696d\u7684\u5224\u65b7\u80fd\u529b\u4ee5\u53ca\u5c08\u696d\u7d20\u990a\n\u5168\u65e5\u5236\u672c\u79d1\u4ee5\u4e0a\u5b78\u6b77\uff0c\u65b0\u805e\u3001\u793e\u79d1\u3001\u6587\u53f2\u985e\u76f8\u95dc\u5c08\u696d\n\u7cb5\u8a9e\u3001\u82f1\u8a9e\u3001\u666e\u901a\u8a71\u53e3\u8a9e\u6d41\u5229\n\u6709\u8cac\u4efb\u5fc3\u3001\u601d\u7dad\u908f\u8f2f\u7e1d\u5bc6\u3001\u5584\u65bc\u6e9d\u901a\u3001\u6027\u683c\u96a8\u548c\u3001\u80fd\u5920\u627f\u64d4\u9ad8\u5f37\u5ea6\u7684\u5de5\u4f5c\u58d3\u529b", "employment_types": ["Full Time", "Permanent"], "selling_points": ["media planning", "integrated marketing", "marketing strategy"], "locations": ["Quarry Bay"], "categories": ["Media & Advertising", "Account Servicing", "Strategic Planning", "Others"], "post_time": "2022-01-11T10:19:43Z", "salary": {"currency": null, "max": null, "min": null, "period": "monthly", "term": null}, "salary_visible": false, "title_keywords": ["associate", "manager"], "responsibilities": [], "requirements": {"degrees": [], "majors": [], "languages": [], "language_level": [], "hard_skills": [], "soft_skills": [], "languages_combined": []}, "experience_required": {"duration": [], "field": []}}, {"job_id": "100003009038690", "location_code": "hk", "company": "AAStocks.com Limited", "job_title": "Reporter (Ref.: Fintv)", "description": "\u5d17\u4f4d\u8077\u8cac\uff1a\n\n\u8ca0\u8cac\u5b89\u6392\u63a1\u7de8\u90e8\u5404\u7d44\u6bcf\u65e5\u5de5\u4f5c\u5167\u5bb9\u3001\u91cd\u9ede\u5927\u4e8b\u7b56\u5283\u3001\u6bcf\u65e5\u5167\u5bb9\u5404\u7d44\u9078\u984c\u65b9\u5411\u628a\u63e1\u3001\u6574\u9ad4\u5167\u5bb9\u65b9\u6848\u7684\u5236\u5b9a\u8207\u8abf\u6574\n\u7b56\u5283\u5b89\u6392\u539f\u5275\u5167\u5bb9\u7684\u751f\u7522\uff0c\u914d\u5408\u904b\u71df\u90e8\u9580\u505a\u597d\u5167\u5bb9\u7522\u51fa\u8bbe\u8ba1\u4e0e\u843d\u5b9e\n\u8ca0\u8cac\u5236\u5b9a\u6709\u6548\u7684\u8cac\u7de8\u3001\u4e3b\u7de8\u5be9\u7a3f\u6a5f\u5236\uff0c\u5c0d\u5167\u5bb9\u767c\u4f48\u9032\u884c\u5be9\u6838\n\n\u4efb\u8077\u8981\u6c42\uff1a\n\n\u719f\u6089\u76ee\u6a19\u53d7\u773e\u6240\u5728\u5730\u5a92\u9ad4\u751f\u614b\uff0c\u81f3\u5c11\u6709\u76f8\u95dc\u884c\u696d\u4e94\u5e74\u4ee5\u4e0a\u5f9e\u696d\u7d93\u9a57\uff0c\u4e09\u5e74\u4ee5\u4e0a\u7684\u5718\u968a\u7ba1\u7406\u7d93\u9a57\uff0c\u57f7\u884c\u80fd\u529b\u5f37\uff0c\u6709\u512a\u79c0\u7684\u5718\u968a\u7ba1\u7406\u6c34\u5e73\n\u6709\u8c50\u5bcc\u7684\u539f\u5275\u5167\u5bb9\u751f\u7522\u7d93\u9a57\uff0c\u5c0d\u65b0\u805e\u5167\u5bb9\u5275\u4f5c\u6709\u6df1\u5165\u7684\u601d\u8003\uff0c\u5177\u5099\u512a\u79c0\u7684\u6587\u5b57\u529f\u5e95\n\u5c0d\u65b0\u805e\u9078\u984c\u5167\u5bb9\u6709\u5c08\u696d\u7684\u5224\u65b7\u80fd\u529b\u4ee5\u53ca\u5c08\u696d\u7d20\u990a\n\u5c0d\u4e92\u806f\u7db2\u3001\u65b0\u5a92\u9ad4\u5167\u5bb9\u50b3\u64ad\u6709\u6e05\u6670\u7684\u8a8d\u8b58\u548c\u7406\u89e3\uff0c\u719f\u6089\u65b0\u5a92\u9ad4\u904b\u4f5c\u898f\u5f8b\n\u5168\u65e5\u5236\u672c\u79d1\u4ee5\u4e0a\u5b78\u6b77\uff0c\u65b0\u805e\u3001\u793e\u79d1\u3001\u6587\u53f2\u985e\u76f8\u95dc\u5c08\u696d\n\u7cb5\u8a9e\u3001\u82f1\u8a9e\u3001\u666e\u901a\u8a71\u53e3\u8a9e\u6d41\u5229\n\u6709\u8cac\u4efb\u5fc3\u3001\u601d\u7dad\u908f\u8f2f\u7e1d\u5bc6\u3001\u5584\u65bc\u6e9d\u901a\u3001\u6027\u683c\u96a8\u548c\u3001\u80fd\u5920\u627f\u64d4\u9ad8\u5f37\u5ea6\u7684\u5de5\u4f5c\u58d3\u529b", "employment_types": ["Full Time", "Permanent"], "selling_points": ["Conducting voice-over work", "Cheerful, Initiative, Outgoing, Self-motivated", "At least 1 year relevant media working experience"], "locations": ["Not Specified"], "categories": ["Media & Advertising", "Creative / Design", "Others", "Editorial / Journalism"], "post_time": "2022-01-11T07:38:38Z", "salary": {"currency": null, "max": null, "min": null, "period": "monthly", "term": null}, "salary_visible": false, "title_keywords": ["reporter"], "responsibilities": [], "requirements": {"degrees": [], "majors": [], "languages": [], "language_level": [], "hard_skills": [], "soft_skills": [], "languages_combined": []}, "experience_required": {"duration": [], "field": []}}, {"job_id": "100003009038394", "location_code": "hk", "company": "\u7d93\u6fdf\u4e00\u9031 EDigest", "job_title": "Social Media Executive/Digital Content Executive/Growth Editor (Business & Finance)", "description": "The ASP HUB is the Centre of Excellence regional team, executing client's digital acquisition campaigns for 11 markets in Asia.\n\nWe work closely with local PHD and our clients to deliver campaign performance. We continuously share learning's to fast-track initiatives across markets, and we take pride in sharing our knowledge to improve client performance and agency capabilities.\n\nThe advantage of working in the regional team is that you have exposure to multiple markets, working closely with different departments internally and externally (e.g. marketing, product, data & analytics).\n\nWe have a very collaborate approach within the team; everyone\u2019s role and personal approach is critical to our success, especially as the team continues to grow. We invest in everyone\u2019s development, with a clear progression path tailored to support everyone to become industry leaders.\n\nResponsibilities:\n\nExecution strategy for multiple products, looking at previous campaign performance and market insights.\nSetup and execution of performance campaigns across SEM, Social and Display/Programmatic\nOn-going optimization to achieve client\u2019s KPI target\nEffectively manage campaign budget spend by implementing relevant bidding strategies and keeping track of budget pacing, updating the strategy, and troubleshoot accordingly\nProactively identity initiatives and opportunities for your market, aligned against local market KPIs\nLead the coordination, preparation, and execute multi-channel strategies\nProactively supply solutions to troubleshoot any account issues when budget and bid pacing, including major volume or cost shifts.\nProduce and develop reports on monthly campaign performance, audiences, creative analysis, and cross channel attribution - update client performance reports, analyse and format data, supply insights and commentary.\nLead the preparation and rationale of paid media recommendations, new tactics, and annual plan presentations for your given market/s\nProduce case studies and best practices on campaigns that best utilized data/research products, including insights from 3rd Party Sources.\nLead the communication and maintain effective relationships within team, business units and client\n\nExperience required:\n\n2+ years hands on experience in digital paid media operations and customer acquisition campaigns\nExpert with Google Marketing Platform (e.g. SA360, DV360, Campaign Manager), Facebook Ads Manager and Programmatic platforms\nOutstanding analytical, decision-making, and problem-solving skills; sharp attention to detail.\nA strong desire to learn and passion for both performance marketing and analytics\nAble to produce high quality work within a fast paced, dynamic environment\nUnderstanding of web analytic metrics\nDevelops knowledge of client\u2019s business, competition and latest industry news and trends\nDigital savvy, with specific proficiency at MS Suite: Excel, Word, PowerPoint\nExcellent verbal and written communication skills in Cantonese and English\n\nWorking Location: client office in Olympic, with occasional requirements to work from PHD office in Cyberport\n\nWe offer a 5-day work of week, group medical & life insurance coverage to the right candidate. Interested parties please send your application letter and resume with current and expected salary\u00a0by clicking the \"Apply Now\" button.\n\nAll information collected will be used for recruitment only and treated in strict confidence. We will retain the personal data of unsuccessful applicants for future recruitment purpose for a maximum period of 2 years.", "employment_types": ["Full Time", "Permanent"], "selling_points": ["Content development & data analysis", "Experience in social media marketing field", "Great development opportunity, competitive package"], "locations": ["Kwun Tong"], "categories": ["Media & Advertising", "Creative / Design", "Others", "Editorial / Journalism"], "post_time": "2022-01-11T06:45:09Z", "salary": {"currency": null, "max": null, "min": null, "period": null, "term": null}, "salary_visible": false, "title_keywords": ["editor", "digital content executive", "social media executive"], "responsibilities": ["performance reports", "data", "operations", "budget", "quality", "communication", "maintain", "troubleshoot", "plan", "facebook", "collaborate", "presentations", "develop", "reports", "kpis", "setup", "cost", "executing", "analysis", "sem", "coordination", "execution strategy", "analyse"], "requirements": {"degrees": [], "majors": [], "languages": ["cantonese", "english"], "language_level": ["excellent"], "hard_skills": ["excel", "web", "problem-solving skills", "analysis", "word", "presentations", "powerpoint", "dynamic", "sem", "execution strategy", "facebook"], "soft_skills": ["communication skills", "dynamic environment", "passion for", "clear", "communication", "learning", "hands on", "troubleshoot", "coordination", "attention to detail", "problem-solving skills", "creative"], "languages_combined": [{"language": "cantonese", "language_level": ["excellent"]}, {"language": "english", "language_level": ["excellent"]}]}, "experience_required": {"duration": ["2+ years"], "field": ["digital", "media"]}}, {"job_id": "100003009043406", "location_code": "hk", "company": "Center Point Personnel", "job_title": "General Clerk [13k /HK Island/ 5 months contract]", "description": "Job Responsibilities :\n\nAssist the team leader in planning international marketing, both online and offline and help to service multi-national clients across a range of markets in APAC.\nPrepare evaluation of media opportunities, keep tracks of market trends by using industry tools and other research methods\nWork closely with media and digital planners, understand campaign objectives and implementation needs\nPrepare media plans, budget summaries, campaign follow ups and reports regularly\n\nJob Requirements\u00a0\u00a0:\n\nUniversity degree in business, marketing, advertising, communications, or a related field\n0-2 years of media planning/buying experience (Fresh graduate welcome)\u00a0\nMust be well organized and have strong quantitative/analytical skills\nAttentive to detail\nFluent written and spoken English and Chinese is a must\nProficiency in Word, Excel and PowerPoint\nWe offer 5-day work week, birthday and other special leaves, staff training, good salary package with MPF and Medical Coverage.\u00a0Interested parties please apply with full resume stating availability, current and expected salaries by clicking \"APPLY NOW\"\u00a0.\n\nFurther information about Havas Group is available on the company\u2019s website: havasgroup.com\n\nDue to high volume of applications, only eligible or matching candidates will be contacted by us. All personal data received will only be used for recruitment purpose and will be destroyed after the position is filled.", "employment_types": ["Full Time", "Contract"], "selling_points": [], "locations": ["Wan Chai Area"], "categories": ["Admin & HR", "Clerical / Admin Staff", "Media & Advertising", "Others", "Marketing / Public Relations", "Marketing - General / Support"], "post_time": "2022-01-12T11:31:58Z", "salary": {"currency": null, "max": null, "min": null, "period": "monthly", "term": null}, "salary_visible": false, "title_keywords": ["general clerk"], "responsibilities": ["budget", "implementation", "reports", "evaluation", "plans", "planning"], "requirements": {"degrees": ["university degree", "fresh graduate"], "majors": ["business", "communications", "marketing"], "languages": ["english", "chinese"], "language_level": ["fluent"], "hard_skills": ["excel", "word", "powerpoint", "analytical skills"], "soft_skills": ["attentive to detail", "well organized", "analytical skills"], "languages_combined": [{"language": "english", "language_level": ["fluent"]}, {"language": "chinese", "language_level": ["fluent"]}]}, "experience_required": {"duration": ["0-2 years"], "field": ["media", "planning"]}}, {"job_id": "100003009043800", "location_code": "hk", "company": "JCDecaux Pearl & Dean Limited", "job_title": "Operations Manager / Senior Operations Manager", "description": "\n\u8077\u8cac :\u8ca0\u8cac\u516c\u53f8\u7522\u54c1\u7684\u92b7\u552e\u53ca\u63a8\u5ee3\uff0c\u6709\u7368\u7acb\u958b\u767c\u65b0\u5ba2\u6236\u80fd\u529b(\u61c2\u5ba2\u6236\u95dc\u7cfb\u7dad\u6301\u5c0d\u5de5\u63a7\u884c\u696d\u7522\u54c1\u6709\u4e00\u5b9a\u4e86\u89e3,\u6709\u5de5\u63a7\u57fa\u790e\u7406\u8ad6\u77e5\u8b58\u6216\u540c\u884c\u512a\u5148,\u61c2\u5ba2\u6236\u95dc\u7cfb\u7dad\u6301) (\u9700\u9577\u99d0\u6df1\u5733\u5de5\u4f5c)\n\n\u8cc7\u6b77 :\u5c08\u4e0a\u6559\u80b2\uff1a\u6587\u6191/\u8b49\u66f8; \u4e00\u822c\u666e\u901a\u8a71; \u4e00\u822c\u82f1\u8a9e; \u61c2\u8b80\u5beb\u4e2d\u6587; \u7565\u61c2\u8b80\u5beb\u82f1\u6587; \u61c2Microsoft Office; \u6709\u6a5f\u96fb\u4e00\u9ad4\u5316\u6216\u6a5f\u68b0\u96fb\u5b50\u5c08\u696d\u512a\u5148,\u719f\u7df4\u99d5\u99db\u512a\u5148\n\n\u5f85\u9047 :\u6bcf\u6708$18,000, \u661f\u671f\u4e00\u81f3\u4e94: \u4e0a\u53488\u6642\u534a\u81f3\u4e0b\u53485\u664245\u5206\u53ca\u661f\u671f\u516d: \u4e0a\u53488\u6642\u534a\u81f3\u4e2d\u534812\u6642, \u6bcf\u9031\u5de5\u4f5c5\u5929\u534a\n\n\u7533\u8acb\u9808\u77e5 :\u6c42\u8077\u8005\u53ef\u96fb\u90f5(Apply Now)\u5c65\u6b77\u8868\u7d66\u73fe\u4ee3\u79d1\u7814\u6709\u9650\u516c\u53f8\u3002\u5982\u8981\u7d22\u53d6\u6536\u96c6\u500b\u4eba\u8cc7\u6599\u8072\u660e, \u8acb\u8207\u99ac\u5c0f\u59d0(Email)\u806f\u7d61\u3002\n\n", "employment_types": ["Full Time"], "selling_points": [], "locations": ["Quarry Bay"], "categories": ["Admin & HR", "Administration / Operation Manager", "Media & Advertising", "Others", "Print Media"], "post_time": "2022-01-13T02:01:22Z", "salary": {"currency": null, "max": null, "min": null, "period": "monthly", "term": null}, "salary_visible": false, "title_keywords": ["senior operations", "operations manager", "manager"], "responsibilities": [], "requirements": {"degrees": [], "majors": [], "languages": [], "language_level": [], "hard_skills": [], "soft_skills": [], "languages_combined": []}, "experience_required": {"duration": [], "field": []}}, {"job_id": "100003009042641", "location_code": "hk", "company": "Openrice Limited", "job_title": "Marketing Executive", "description": "My client is an international well-known beauty skincare brand. They are now looking for an Assistant Digital Marketing Manager to join their HK team.\n\nResponsibility\n\nAssist on the overall digital marketing strategy and plan the digital marketing initiative\nManage, develop digital and social media campaign and content to drive the online performance and achieve business targets\nManage marketing plan with omnichannel platform including own ecommerce site and marketplace platform\nExecute digital marketing activities including but not limited online paid media planning, content creation, social media campaign etc.\nAnalyze digital & social media data to provide strategic & actionable insights and optimize ROAS / ROI\n\nRequirement\n\nDegree holder in Marketing or related disciplines\nAt least 6 years of relevant experience in digital marketing, preferable in beauty / retail\nHands-on experience and digital marketing campaign management\nTeam player with excellent communication skill and\u00a0strong business acumen\nSpeaks fluent in English, Cantonese and Mandarin", "employment_types": ["Full Time", "Permanent"], "selling_points": ["Stable and fast growing business", "Flexible working hours", "Immediate availability is preferred"], "locations": ["Quarry Bay"], "categories": ["Media & Advertising", "Others", "Marketing / Public Relations", "Digital Marketing", "E-commerce", "Marketing - Brand / Product Management"], "post_time": "2022-01-12T08:15:01Z", "salary": {"currency": null, "max": null, "min": null, "period": "monthly", "term": null}, "salary_visible": false, "title_keywords": ["marketing executive"], "responsibilities": ["social media", "data", "develop", "marketing plan", "digital marketing", "plan", "planning"], "requirements": {"degrees": ["degree holder"], "majors": ["related disciplines", "marketing"], "languages": ["cantonese", "english", "mandarin"], "language_level": ["fluent"], "hard_skills": ["acumen"], "soft_skills": ["communication skill", "hands-on", "team player", "business acumen"], "languages_combined": [{"language": "cantonese", "language_level": ["fluent"]}, {"language": "english", "language_level": ["fluent"]}, {"language": "mandarin", "language_level": ["fluent"]}]}, "experience_required": {"duration": ["at least 6 years"], "field": ["management", "relevant experience", "beauty", "digital marketing", "retail"]}}, {"job_id": "100003009040238", "location_code": "hk", "company": "New Media Group Publishing Limited", "job_title": "Senior Mobile App Developer/ Mobile App Developer/Software Engineer (IOS/Android)", "description": "\u00a0Job Responsibilities:\u00a0\n\nAssist the team in developing and implementing an integrated on/off advertising campaign\nHelp on competitive data generation, analysis and presentation\nPrepare evaluation of media opportunities, keep tracks of market trends by using industry tools and other research methods\nPrepare media plan, budget summary and campaign follow up\nActively participate in brain-storming for big ideas and consumer insights\nMaintain and strengthen relationships with industry partners.\n\n\u00a0Job Requirements:\u00a0\n\nUniversity degree in business, marketing, advertising, communications, or a related field\n0-1 year of media planning/buying experience preferably (fresh graduates are also welcomed)\nMust be well organized and have strong quantitative/analytical skills\nAble to build relationship internally and externally\nAbility to manage multi-task well in a fast-paced environment and a team player.\nMust be numerate and have strong attention to detail\nPassionate about building a career in advertising field\nFluent written and spoken English and Chinese is a must\nProficiency in Word, Excel and PowerPoint\n\nWorking Location: Cyberport (\u6578\u78bc\u6e2f), Hong Kong\n\nWe offer a 5-day week of work, group medical & life insurance coverage and free shuttle bus to the right candidate. Interested parties please send your application letter and resume to click the \"Apply Now\" at the bottom.\n\nAll information collected will be used for recruitment only and treated in strict confidence. We will retain the personal data of unsuccessful applicants for future recruitment purpose for a maximum period of 2 years.", "employment_types": ["Full Time", "Permanent"], "selling_points": ["Responsible for app design, testing & development", "AWS cloud, Git Flow, Mobile App Unit Test process", "Great development opportunity, competitive package"], "locations": ["Kwun Tong"], "categories": ["Media & Advertising", "Others", "Information Technology (IT)", "Others", "Mobile / Wireless Communications"], "post_time": "2022-01-12T01:58:31Z", "salary": {"currency": null, "max": null, "min": null, "period": null, "term": null}, "salary_visible": false, "title_keywords": ["software engineer", "developer"], "responsibilities": ["advertising", "ideas", "consumer insights", "data", "analysis", "budget", "developing", "maintain", "plan", "evaluation"], "requirements": {"degrees": ["university degree"], "majors": ["business", "communications", "marketing"], "languages": ["english", "chinese"], "language_level": ["fluent"], "hard_skills": ["excel", "word", "powerpoint", "analytical skills"], "soft_skills": ["multi-task", "fast-paced environment", "well organized", "analytical skills", "attention to detail", "team player", "passionate about"], "languages_combined": [{"language": "english", "language_level": ["fluent"]}, {"language": "chinese", "language_level": ["fluent"]}]}, "experience_required": {"duration": ["0-1 year"], "field": ["media", "planning"]}}, {"job_id": "100003009042571", "location_code": "hk", "company": "Blue Chip Group Limited", "job_title": "Sales Manager for Fast Growing Media Agency", "description": "Accountabilities \u2013 Key Result Areas\n\nResponsible for storyboard, video shooting, and conducting interview for that and normal short series of video\nResponsible in video editing and mostly visual brainstorming from beginning to end, pitch concepts, write scripts, shoot, edit & post-production\nHas cinematography experience: lighting & operating a range of cameras\nVisual insight is required\n\nExperience / Qualification Requirements\n\nDiploma in photography or related discipline\nWith a minimum of 3-4 years solid experience in fashion shooting experience\nHave a firm understanding of aesthetics, styling and branding\nProficient in MAC software applications, in particular AI and Photoshop\nResponsible, organized, self-motivated and a good team player\nCan work independently under minimal supervision\nAbility to handle multiple projects and meeting tight deadlines\n\nCompetitive remuneration and benefit package will be offered to the right candidate. Please submit your application by clicking \"Apply Now\" below.\n\nAll data collected is for recruitment purpose only.\n\nSure you want to know more about our company and brands, simply follow our\n\nWEBSITE at\u00a0http://www.ithk.com\u00a0\u00a0 \u00a0 \u00a0 \u00a0 \u00a0 \u00a0 \u00a0 \u00a0 \u00a0 \u00a0 \u00a0 \u00a0 \u00a0 \u00a0 \u00a0 \u00a0 \u00a0 \u00a0 \u00a0 \u00a0 \u00a0 \u00a0 \u00a0 \u00a0 \u00a0 \u00a0 \u00a0 \u00a0 \u00a0 \u00a0 \u00a0 \u00a0 \u00a0 \u00a0\n\nFACEBOOK at\u00a0http://www.facebook.com/I.Ttheofficialpage\u00a0\u00a0 \u00a0 \u00a0 \u00a0 \u00a0 \u00a0 \u00a0 \u00a0 \u00a0 \u00a0 \u00a0 \u00a0 \u00a0 \u00a0\n\nINSTAGRAM at\u00a0http://instagram.com/ithk\u00a0 \u00a0 \u00a0 \u00a0 \u00a0 \u00a0 \u00a0 \u00a0 \u00a0 \u00a0 \u00a0 \u00a0 \u00a0 \u00a0 \u00a0 \u00a0 \u00a0 \u00a0 \u00a0 \u00a0 \u00a0 \u00a0 \u00a0 \u00a0 \u00a0 \u00a0 \u00a0 \u00a0\n\nWEIBO at\u00a0http://e.weibo.com/ithongkong", "employment_types": ["Full Time", "Part Time", "Permanent", "Temporary", "Internship"], "selling_points": [], "locations": ["Tsim Sha Tsui"], "categories": ["Media & Advertising", "Account Servicing", "Others", "Sales, CS & Business Devpt", "Business Development"], "post_time": "2022-01-12T08:02:43Z", "salary": {"currency": null, "max": null, "min": null, "period": "monthly", "term": null}, "salary_visible": false, "title_keywords": ["sales manager"], "responsibilities": ["software", "data", "website", "video editing", "video shooting", "recruitment", "visual", "multiple projects", "facebook"], "requirements": {"degrees": ["diploma"], "majors": [], "languages": [], "language_level": [], "hard_skills": ["video editing", "facebook", "photoshop", "ai"], "soft_skills": ["organized", "self-motivated", "work independently", "good team player", "meeting tight deadlines", "responsible"], "languages_combined": []}, "experience_required": {"duration": ["minimum of 3-4 years"], "field": ["fashion shooting"]}}, {"job_id": "100003009042903", "location_code": "hk", "company": "MRRM Publishing Ltd", "job_title": "Assistant Sales Manager / Senior Sales Executive", "description": "Responsibilities\n\nServe as a media strategist across all applicable company accounts and projects\nDevelop strategic, innovative and integrated communication recommendation with full understanding on consumer consumption behaviour across different touch points to fulfil clients\u2019 business objectives\nManage and develop the media team in delivering high quality of services from providing recommendation to post campaign analysis\nSupport departmental business development with occasional new business pitches and client presentations\nPerform ad-hoc consumer, market, and/or industry research to inform strategic rationale and build an information repository for Carat\nProvide forward-thinking recommendations for the vision, practice, and growth of the Media department\nManage individual projects on an as-need basis with professionalism, organization, and high quality of service\nAbility to be self-motivated, entrepreneurial, and organized across multiple projects with various internal teams, clients and deadlines\nAbility to apply tactical knowledge into strategic recommendations for a variety of industries and business situations\nDesire to push innovation with a sound business mind and passion for ongoing education of strategic practice in the convergent media industry\n\nRequirements\n\nAt least 5 years of experience in media planning in an agency environment\nExperience in working on integrated marketing programs, with an understanding of how digital can build off of other media channels a plus\nExperience in full-cycle planning from consumer insights, to marketing strategy, to data analytics is a plus\nGood relationship built with media vendors\nProficiency in the full suite of Microsoft Office tools\nFluent, persuasive, and concise English presentation and writing skills\nPositive \u201ccan-do\u201d attitude\nCantonese and good command of English\n\nWe offer 5 days work and attractive compensation package to suitable candidates. Interested parties, please send your full resume including your date of available,\u00a0present & expected salary to us.\n\nPlease note that only short-listed applicants will be notified. All information provided will be treated in strictly confidential and used solely for recruitment purpose.", "employment_types": ["Full Time"], "selling_points": [], "locations": ["Wan Chai"], "categories": ["Media & Advertising", "Account Servicing", "Others", "Sales, CS & Business Devpt", "Others"], "post_time": "2022-01-12T09:11:25Z", "salary": {"currency": null, "max": null, "min": null, "period": "monthly", "term": null}, "salary_visible": false, "title_keywords": ["assistant sales manager", "senior sales executive"], "responsibilities": ["ad-hoc", "analysis", "company accounts", "quality", "teams", "presentations", "develop", "multiple projects", "integrated communication"], "requirements": {"degrees": [], "majors": [], "languages": ["cantonese", "english"], "language_level": ["good command", "fluent"], "hard_skills": ["data analytics", "plus", "writing skills", "microsoft office"], "soft_skills": ["persuasive", "writing skills", "can-do", "presentation", "positive"], "languages_combined": [{"language": "cantonese", "language_level": ["good command"]}, {"language": "english", "language_level": ["good command", "fluent"]}]}, "experience_required": {"duration": ["at least 5 years"], "field": ["agency", "marketing", "digital", "media", "planning"]}}, {"job_id": "100003009042639", "location_code": "hk", "company": "Openrice Limited", "job_title": "Senior Marketing Executive / Assistant Marketing Manager", "description": "Job Responsibilities:\nManage and create content for various social media platforms (Facebook, Instagram, YouTube...), including copy writing, image and basic video editing\nHosting live programmes including news reporting, script writing, and analyst interviewing\nParticipating in news programme design and planning\nWriting feature articles\nConducting voice-over work\nDoing research and assisting the production of live team\nJob Requirements:\nCheerful, Initiative, Outgoing, Self-motivated\nDegree holder, preferably in Journalism, Finance, Economics or Chinese Language\nAt least 1 year relevant media working experience (Fresh graduates are welcomed)\nFamiliar with stock market, listed company and financial analysis is an advantage\nFamiliar with digital media solutions (Social media, Facebook advertising, Google Analytics, SEO and SEM) is a plus\nProficiency in Chinese word processing", "employment_types": ["Full Time", "Permanent"], "selling_points": ["Stable and fast growing business", "Flexible working hours", "Immediate availability is preferred"], "locations": ["Quarry Bay"], "categories": ["Media & Advertising", "Others", "Marketing / Public Relations", "Digital Marketing", "E-commerce", "Marketing - Brand / Product Management"], "post_time": "2022-01-12T08:15:00Z", "salary": {"currency": null, "max": null, "min": null, "period": "monthly", "term": null}, "salary_visible": false, "title_keywords": ["assistant marketing manager", "senior marketing executive"], "responsibilities": ["reporting", "social media platforms", "design", "video editing", "facebook", "planning"], "requirements": {"degrees": ["degree holder"], "majors": ["journalism", "finance", "economics"], "languages": ["chinese"], "language_level": ["proficiency"], "hard_skills": ["google analytics", "plus", "seo", "chinese word processing", "financial analysis", "sem", "facebook"], "soft_skills": ["outgoing", "self-motivated", "cheerful", "initiative"], "languages_combined": [{"language": "chinese", "language_level": ["proficiency"]}]}, "experience_required": {"duration": ["at least 1 year"], "field": ["media"]}}, {"job_id": "100003009038689", "location_code": "hk", "company": "AAStocks.com Limited", "job_title": "Reporter", "description": "This position is suitable for those who have experience in social media platforms management, including FB, IG, Youtube and Linkedin. Fresh graduates who are familiar with social trends will be considered.\n\nJob Nature:\u00a0\u00a0\n\nFully responsible for social media activities (e.g. FB, IG, Youtube, Linkedin), on content development and execution, data analysis, strategy for growth etc.\nCreate core content that fit the channel nature\nHandle multiple projects simultaneously and manage various accounts/ campaigns in a timely and professional manner\nAnalyze data and insights to guide strategy and implementation of solutions\nTo manage campaigns deliverables and coordinate with the internal parties to implement digital campaigns\n\nCharacters / Qualifications:\u00a0\n\nDegree holder, 1+ years experience in social media marketing field. Candidates with more than 3 years experience will be considered for manager title.\nExperience in business/ and finance platform management will be an advantage\nDigitally savvy with strong interest in social trends\nDerive strong satisfaction in creating high engagement and viral content that fit our brands\nCheerful and creative, with marketing sense and data driven mind\nStrong communication skills and ability to influence counterparts/stakeholders at various levels\nSelf-motivated showing strong sense of ownership and able to work under pressure\n\nWe offer competitive salary and benefits package (5 days work, 14 days AL up, birthday leave, medical & dental insurance) with great opportunity for career development to the successful candidate.\n\nPlease send your detailed resume and expected salary to us by clicking \"Apply Now\" (please put position applied on subject line)", "employment_types": ["Full Time", "Permanent"], "selling_points": ["Attend press conference and report financial news", "Bachelor degree in Communication/Journalism", "1 year solid experience in relevant media industry"], "locations": ["Not Specified"], "categories": ["Media & Advertising", "Others", "Editorial / Journalism"], "post_time": "2022-01-11T07:38:38Z", "salary": {"currency": null, "max": null, "min": null, "period": "monthly", "term": null}, "salary_visible": false, "title_keywords": ["reporter"], "responsibilities": ["social media", "management", "data", "social media platforms", "professional manner", "implementation", "coordinate with", "data analysis", "communication", "digital campaigns", "career development", "analyze data", "multiple projects", "insurance", "internal parties", "work under pressure"], "requirements": {"degrees": ["degree holder"], "majors": ["marketing"], "languages": [], "language_level": [], "hard_skills": ["analysis"], "soft_skills": ["communication skills", "self-motivated", "cheerful", "marketing sense", "responsible", "timely", "detailed", "creative", "driven", "work under pressure"], "languages_combined": []}, "experience_required": {"duration": ["3 years", "1+ years"], "field": ["social media", "management", "finance", "business", "marketing"]}}, {"job_id": "100003009030258", "location_code": "hk", "company": "Miracle Workshop", "job_title": "\u517c\u8077\u4ee3\u5531\u6b4c\u624b", "description": "Job Duties:\u00a0\n\nTo provide general office support to a scholarship scheme and the Office, including receiving and dispatching documents and materials, mailing letters, handling fax messages, photocopying, sorting and binding documents, etc. Outdoor work and frequent travelling within Hong Kong territory are required;\nTo assist in maintaining updated database and filing system to support the operation of the scholarship scheme; and\nTo undertake any other duties as assigned by senior officers.\n\nRequirements:\n\nCompletion of Form 5, or equivalent; preferably with Level 2 or above in Chinese Language and English Language in HKDSE/ HKCEE\nProficiency in Word Processing (English: 45 wpm; Chinese: 30 wpm) and preferable has related clerical working experience\u00a0", "employment_types": ["Part Time", "Freelance"], "selling_points": ["\u5ee3\u544a\u96fb\u5f71\u6b4c\u66f2/\u5361\u62c9OK\u5e55\u5f8c\u4ee3\u5531", "\u80fd\u64cd\u6d41\u5229\u5ee3\u6771\u8a71\uff0c\u7537\u5973\u5747\u53ef\uff0c\u5e74\u9f61\u4e0d\u9650", "\u7d93\u9a57\u4e0d\u62d8\u3001\u5de5\u4f5c\u6642\u9593\u4efb\u64c7\u3001\u85aa\u916c\u9762\u8b70"], "locations": ["Not Specified"], "categories": ["Media & Advertising", "Production", "Others", "Others", "Entertainment - Artists / Singers / Musicians"], "post_time": "2022-01-07T07:05:59Z", "salary": {"currency": null, "max": null, "min": null, "period": "hourly", "term": null}, "salary_visible": false, "title_keywords": [], "responsibilities": ["any other duties", "outdoor work", "maintaining", "letters", "office support", "database"], "requirements": {"degrees": ["form 5", "hkdse"], "majors": [], "languages": ["english", "chinese"], "language_level": ["proficiency"], "hard_skills": ["word processing"], "soft_skills": [], "languages_combined": [{"language": "english", "language_level": ["proficiency"]}, {"language": "chinese", "language_level": []}]}, "experience_required": {"duration": [], "field": ["related", "clerical"]}}, {"job_id": "100003009037646", "location_code": "hk", "company": "Cody Outdoor International (HK) Limited", "job_title": "Digital Sales Manager/Assistant Digital Sales Manager", "description": "JOIN OpenRice\u2026\u2026if you want to service our\n\n\u00a05 million App users with\n\n\u00a09 million pageviews per day in Hong Kong!\u00a0\n\n\nOpenRice\u00a0is seeking an energetic and passionate individual to join a dynamic and collaborative environment as part of marketing\u00a0team.\n\nYou will be responsible for:\n\nImplement strategic marketing plan into action plan\nPropose creative and social media friendly ideas in order to maximize campaign buzz\u00a0\nResponsible for copywriting and translation of press releases, newsletter and other marketing materials\nDevelop and maintain a strong network of media contacts, celebrities, influencers and bloggers\nIdentify new media / social media partners and market trends proactively\nSupport events organization and logistics arrangement\n\nYou should possess:\n\nDegree holder in marketing / business or related discipline\n1-2 years relevant marketing experiences. Experience in food tech / e-commerce / consumer app / digital agency is definitely a plus.\nExcellent command of written and spoken English and Cantonese\nCreative, detail-minded, outgoing and self-motivated\n\nWe offer a competitive remuneration package including excellent career prospects to the right candidate. Interested parties please submit your detailed resume with expected salary and available date by clicking the Quick Apply button.\n\nAll personal information submitted by job applicants will be used for recruitment purposes and we reserve the rights to consider the applications for other positions in our Group.", "employment_types": ["Full Time", "Permanent"], "selling_points": [], "locations": ["Causeway Bay"], "categories": ["Media & Advertising", "Others"], "post_time": "2022-01-11T03:22:49Z", "salary": {"currency": null, "max": null, "min": null, "period": "monthly", "term": null}, "salary_visible": false, "title_keywords": ["assistant", "sales manager"], "responsibilities": ["social media", "ideas", "logistics arrangement", "develop", "marketing plan", "maintain", "plan", "marketing materials"], "requirements": {"degrees": ["degree holder"], "majors": ["business", "marketing"], "languages": ["cantonese", "english"], "language_level": ["excellent"], "hard_skills": ["translation", "plus", "dynamic", "e-commerce"], "soft_skills": ["passionate", "detail-minded", "outgoing", "self-motivated", "creative", "responsible", "collaborative", "dynamic", "friendly", "energetic"], "languages_combined": [{"language": "cantonese", "language_level": ["excellent"]}, {"language": "english", "language_level": ["excellent"]}]}, "experience_required": {"duration": ["1-2 years"], "field": ["e-commerce", "agency", "digital", "tech", "marketing", "food"]}}, {"job_id": "100003009038075", "location_code": "hk", "company": "Ample Advertising Agency Limited", "job_title": "Assistant Sales Manager/Senior Sales Executive", "description": "\u8077\u8cac\uff1a\n\n\u8ca0\u8cac\u661f\u5cf6\u6559\u80b2\u526f\u520a\u53ca\u661f\u5cf6\u6559\u80b2\u7db2\u7684\u63a1\u8a2a\u5de5\u4f5c\uff0c\u5305\u62ec\u5c08\u984c\u5831\u9053\u3001\u7279\u7a3f\u53ca\u5c08\u6b04\u7b49\n\u5354\u52a9\u661f\u5cf6\u6559\u80b2\u7db2\u5e73\u53f0\u65e5\u5e38\u904b\u4f5c\n\n\u8077\u4f4d\u8981\u6c42\uff1a\n\n\u5927\u5b78\u7562\u696d\uff0c\u826f\u597d\u4e2d\u6587\u5beb\u4f5c\u80fd\u529b\n\u9808\u559c\u611b\u6587\u5b57\u53ca\u5a92\u9ad4\u5de5\u4f5c\uff0c\u826f\u597d\u6e9d\u901a\u80fd\u529b\n\u6709\u63a1\u8a2a\u7d93\u9a57\u8005\u512a\u5148\n\u6b61\u8fce\u61c9\u5c4a\u7562\u696d\u751f\u7533\u8acb\n\u5de5\u4f5c\u5730\u9ede\uff1a\u5c07\u8ecd\u6fb3\u5de5\u696d\u90a8\n\n\n\n\u6c42\u8077\u8005\u8acb\u8a73\u9644\u500b\u4eba\u5c65\u6b77\u53ca\u8981\u6c42\u5f85\u9047\uff0c\u5bc4\u9999\u6e2f\u65b0\u754c\u5c07\u8ecd\u6fb3\u5de5\u696d\u90a8\u99ff\u660c\u8857\u4e03\u865f\u661f\u5cf6\u65b0\u805e\u96c6\u5718\u5927\u5ec83\u6a13\u4eba\u529b\u8cc7\u6e90\u90e8\u6536\uff0c\u4fe1\u5c01\u9762\u8acb\u8a3b\u660e\u7533\u8acb\u8077\u4f4d\u6216\u6309\u201cApply Now\u201d\u63d0\u4ea4\u7533\u8acb\u3002\n\n\u672c\u516c\u53f8\u70ba\u516c\u5e73\u6a5f\u6703\u50f1\u4e3b\uff0c\u6b61\u8fce\u6240\u6709\u5408\u8cc7\u683c\u7684\u5019\u9078\u4eba\u7533\u8acb\u3002\u6240\u63d0\u4f9b\u7684\u4fe1\u606f\u5c07\u56b4\u683c\u4fdd\u5bc6\uff0c\u50c5\u7528\u65bc\u62db\u8058\u76f8\u95dc\u7528\u9014\u3002\u82e5\u672a\u80fd\u65bc 6 \u9031\u5167\u7372\u9080\u51fa\u5e2d\u9762\u8a66\u7684\u7533\u8acb\u8005\u6703\u81ea\u52d5\u843d\u9078\uff0c\u53e6\u6240\u6709\u843d\u9078\u7684\u7533\u8acb\u8005\u7684\u6240\u6709\u500b\u4eba\u8cc7\u6599\u5c07\u57286\u500b\u6708\u5167\u92b7\u6bc0\u3002\n\nwww.singtaonewscorp.com", "employment_types": ["Full Time"], "selling_points": [], "locations": ["Wan Chai"], "categories": ["Media & Advertising", "Others"], "post_time": "2022-01-12T03:42:25Z", "salary": {"currency": null, "max": null, "min": null, "period": "monthly", "term": null}, "salary_visible": false, "title_keywords": ["assistant sales manager", "senior sales executive"], "responsibilities": [], "requirements": {"degrees": [], "majors": [], "languages": [], "language_level": [], "hard_skills": [], "soft_skills": [], "languages_combined": []}, "experience_required": {"duration": [], "field": []}}, {"job_id": "100003009036676", "location_code": "hk", "company": "Phoenix Satellite Television Co Ltd", "job_title": "\u5167\u5bb9\u904b\u71df\u7d93\u7406", "description": "Responsibilities:\n\nResponsible for visiting and local news, researching and interviewing\n\nRequirements:\n\nDegree holder in any disciplines, Journalism/ Communication background is preferred\n2 years\u2019 related experience,\u00a0fresh graduates with positive attitude are also welcome\nStrong oral and written communication skills\nCreative, outgoing, good organization skills, independent and initiative\nWorking Location : Tseung Kwan O Industrial Estate\n\nInterested parties please\u00a0click \u201cApply Now\"\u00a0to submit your complete resume with\u00a0employment history and expected salary or by\u00a0post to\u00a0Human Resources Department, 3/F, Sing Tao News Corporation Building, 7 Chun Cheong Street, Tseung Kwan O Industrial Estate, Tseung Kwan O, New Territories, Hong Kong.\n\nWe are an equal opportunity employer and welcome applications from all qualified candidates. Information provided will be treated in strict confidence and only be used for recruitment related purpose. Applicant who is not invited for an interview within 6 weeks may consider their application not successful. All personal data of unsuccessful applicants will be destroyed within 6 months.\n\nwww.singtaonewscorp.com", "employment_types": ["Full Time"], "selling_points": [], "locations": ["Tai Po Area"], "categories": ["Media & Advertising", "Others"], "post_time": "2022-01-10T12:20:07Z", "salary": {"currency": null, "max": null, "min": null, "period": null, "term": null}, "salary_visible": false, "title_keywords": [], "responsibilities": [], "requirements": {"degrees": ["degree holder"], "majors": ["journalism", "any disciplines"], "languages": [], "language_level": [], "hard_skills": [], "soft_skills": ["outgoing", "communication skills", "oral", "independent", "communication", "positive attitude", "organization skills", "creative", "initiative"], "languages_combined": []}, "experience_required": {"duration": ["2 years"], "field": ["related"]}}, {"job_id": "100003009037371", "location_code": "hk", "company": "MORE", "job_title": "Senior Marketing Executive", "description": "Job Description and Responsibilities\n- Research and assess local and global market for potential partnership opportunities\n- Plan, pitch and present\u00a0media revenue opportunities\n-\u00a0Explore new media channel opportunities\u00a0\n- Develop new business\n- Identify client business needs and proactively develop advertising solutions to meet objectives\n- Meet challenging objectives in a high profile, competitive marketplace\n- Other projects as assigned by the MD\n- Travelling often to meet with vendors across the regions\n\nRequirements\n- 1-5 years of experience in a media agency/media owner\u00a0role will be highly preferred\n- Undergraduate degree in related field or a combination of related education and work experience\n- Highly self-motivated, resourceful, enthusiastic, start-up personality\n- Creative thinker and problem solver\n- Ability to handle multiple priorities and simultaneous projects\n- Excellent presentation and communication skills\n- Fluent in English and Chinese\n- Speaking Korean would be a great asset", "employment_types": ["Full Time", "Permanent"], "selling_points": ["Over 2-3 years experience in digital projects", "Assist in promotion plan development", "Great development opportunity, competitive package"], "locations": ["Kwun Tong"], "categories": ["Media & Advertising", "Strategic Planning", "Others", "Editorial / Journalism"], "post_time": "2022-01-11T02:37:41Z", "salary": {"currency": null, "max": null, "min": null, "period": null, "term": null}, "salary_visible": false, "title_keywords": ["senior marketing executive"], "responsibilities": ["develop new business", "advertising", "plan", "develop"], "requirements": {"degrees": ["degree"], "majors": [], "languages": ["english", "chinese", "korean"], "language_level": ["fluent"], "hard_skills": [], "soft_skills": ["communication skills", "self-motivated", "problem solver", "resourceful", "enthusiastic", "creative", "presentation"], "languages_combined": [{"language": "english", "language_level": ["fluent"]}, {"language": "chinese", "language_level": ["fluent"]}, {"language": "korean", "language_level": []}]}, "experience_required": {"duration": ["1-5 years"], "field": ["agency", "media", "related", "education"]}}, {"job_id": "100003009035985", "location_code": "hk", "company": "EVI Services Limited", "job_title": "Senior Editor / Chief Editor", "description": "Job Description:\n\n\u3002Explore and develop new business opportunities to meet sales target\n\u3002Prepare proposals, sales and presentation materials to client\n\u3002Follow up new or potential clients\u2019 inquires\n\u3002Coordinate with other teams to ensure smooth operations\n\n\nRequirements:\n\n\u3002Degree holder in Communication, Marketing, Business Administration, Journalism or related discipline are preferred\n\u3002At least 3 years media\u00a0sales experience on print, digital,or product\n\u3002Extensive network with local corporate clients or retail merchants\n\u3002Knowledge of social media trend is preferable\n\u3002Cheerful, initiative and well organized\n\u3002Excellent spoken and written English and Chinese\n\u3002Strong network in certain industry is highly preferred\n\u3002Candidates with\u00a0less experience would be considered as Senior Sales Executive\n\n\n\n\u00a0Interested candidate please provide full resume with latest and expected salary.\n\n\u00a0Personal data collected will be used for recruitment purpose only.", "employment_types": ["Full Time"], "selling_points": [], "locations": ["Yau Tsim Mong Area"], "categories": ["Media & Advertising", "Others", "Design", "Multi-media", "Editorial / Journalism"], "post_time": "2022-01-10T09:00:35Z", "salary": {"currency": null, "max": null, "min": null, "period": "monthly", "term": null}, "salary_visible": false, "title_keywords": ["editor", "senior editor"], "responsibilities": ["develop new business", "sales target", "coordinate with", "teams", "ensure smooth operations"], "requirements": {"degrees": ["degree holder"], "majors": ["journalism", "marketing", "business administration"], "languages": ["english", "chinese"], "language_level": ["excellent"], "hard_skills": [], "soft_skills": ["cheerful", "well organized", "communication", "extensive", "initiative"], "languages_combined": [{"language": "english", "language_level": ["excellent"]}, {"language": "chinese", "language_level": ["excellent"]}]}, "experience_required": {"duration": ["at least 3 years"], "field": ["digital", "print", "media sales"]}}, {"job_id": "100003009035965", "location_code": "hk", "company": "EVI Services Limited", "job_title": "Chief Editor", "description": "JOIN OpenRice\u2026\u2026if you want to service our\n\n\u00a05 million App users with\n\n\u00a09 million pageviews per day in Hong Kong!\u00a0\n\n\nOpenRice\u00a0is seeking an energetic and passionate individual to join a dynamic and collaborative environment as part of marketing\u00a0team.\n\nYou will be responsible for:\n\n\nSupport and execute the marketing strategies and planning set by the company in order to drive business growth.\nInitiate new marketing ideas and implement creative marketing & communications programs, CRM activities and other tactical campaigns.\nCoordinate digital marketing activities; monitor and enhance the brand\u2019s social media and digital presence.\nDevelop media plan and press materials as well as manage media liaison.\nDrive the loyalty program to engage and reward our loyal customers.\nConduct market research and analytical reports to identify opportunities and trends in the market.\n\nYou should possess:\n\n\n\nDegree holder in marketing / communication / business or related discipline\nMinimum 5 years relevant marketing experiences. Experience in food tech / e-commerce / consumer app / digital agency is definitely a plus.\nExcellent command of written and spoken English and Cantonese\nCreative, detail-minded, outgoing and self-motivated\nCandidates with more experience will be considered as Assistant Marketing Manager\n\nWe offer a competitive remuneration package including excellent career prospects to the right candidate. Interested parties please submit your detailed resume with expected salary and available date by clicking the Quick Apply button.\n\nAll personal information submitted by job applicants will be used for recruitment purposes and we reserve the rights to consider the applications for other positions in our Group.", "employment_types": ["Full Time"], "selling_points": [], "locations": ["Not Specified"], "categories": ["Media & Advertising", "Others", "Design", "Multi-media", "Editorial / Journalism"], "post_time": "2022-01-10T08:56:48Z", "salary": {"currency": null, "max": null, "min": null, "period": "monthly", "term": null}, "salary_visible": false, "title_keywords": ["editor"], "responsibilities": ["social media", "marketing strategies", "ideas", "conduct market research", "monitor", "develop", "coordinate", "communication", "digital marketing", "reports", "plan", "planning"], "requirements": {"degrees": ["degree holder"], "majors": ["business", "marketing"], "languages": ["cantonese", "english"], "language_level": ["excellent"], "hard_skills": ["plus", "dynamic", "e-commerce"], "soft_skills": ["passionate", "detail-minded", "outgoing", "self-motivated", "creative", "responsible", "collaborative", "communication", "dynamic", "loyal", "energetic"], "languages_combined": [{"language": "cantonese", "language_level": ["excellent"]}, {"language": "english", "language_level": ["excellent"]}]}, "experience_required": {"duration": ["minimum 5 years"], "field": ["e-commerce", "agency", "digital", "tech", "marketing", "food"]}}, {"job_id": "100003009037903", "location_code": "hk", "company": "PHD Limited", "job_title": "Digital Operation Executive (Advertising & Media Field)", "description": "Job Responsibilities:\nAttend press conference and report financial news\nJob Requirements:\nBachelor degree in Communication/Journalism or related disciplines\nAbove 1 year solid experience in relevant media industry (instant financial news experience is an advantage)\nFamiliar and sensitive with Hong Kong stock market\nExcellent command of written Chinese and English\nAble to work under pressure with tight schedule and independently", "employment_types": ["Full Time", "Permanent"], "selling_points": ["Free Shuttle Bus & Free Breakfast", "Birthday, Family Day & Self-Love Day Leave", "5-Day Work Week"], "locations": ["Pok Fu Lam"], "categories": ["Media & Advertising", "Account Servicing", "Media Buying", "Others"], "post_time": "2022-01-11T04:11:59Z", "salary": {"currency": null, "max": null, "min": null, "period": "monthly", "term": null}, "salary_visible": false, "title_keywords": ["operation executive"], "responsibilities": ["report"], "requirements": {"degrees": ["degree", "bachelor"], "majors": ["journalism", "related disciplines"], "languages": ["english", "chinese"], "language_level": ["excellent"], "hard_skills": [], "soft_skills": ["communication", "work under pressure", "independently", "sensitive"], "languages_combined": [{"language": "english", "language_level": ["excellent"]}, {"language": "chinese", "language_level": ["excellent"]}]}, "experience_required": {"duration": ["1 year"], "field": ["media", "financial"]}}, {"job_id": "100003009033949", "location_code": "hk", "company": "GroupM Limited", "job_title": "Xaxis | Programmatic Trading Specialist", "description": "Responsibilities:\n\nOversee, plan and manage the daily posting, maintenance and cleaning works for all advertising formats covering light box, digital panels and temporary executions.\nEnsure that all works by company staff and contractors are carried out with high standard of safety and quality while monitoring overall performance.\nManage and supervise all related resources: staff, vehicles, equipment & tools, posting material, contractors, warehouses and stock as well as spare parts.\nMaintain exhaustive and detailed record of all media inventory and specifications, as well as operational activities and events logs.\nEnsure that all operations comply with Health and safety requirements and local regulations.\nEnsure all interior and exterior advertising formats and media are maintained in optimal safety and working conditions, clean and tidy with quality posting.\nBe the main contact window at all times with landlords and authorities for all operation related matters. Maintain immediate responsiveness with night shift operatives to liaise with relevant parties (authority, vendors, other company departments) to investigate, solve and report all issues.\nEnsure timely submissions and approval for all required operational submissions (work and access permits, certifications, forms and trainings, etc).\nClose cooperation and site support with Projects Department to ensure all new installations and projects are carried out in safe conditions.\nProactively support other company departments in answering raised queries and issues by providing timely response and close follow up until issues are solved.\nHave a proactive role in understanding company requirements and scope to review the working procedure, and propose improvement methods to management.\n\nRequirements:\n\nMaster\u2019s Degree holder in operations, mechanical engineering, electrical engineering or other related disciplines.\nEnvironmental, Quality and Health & Safety related certifications and experience\nAt least 8 years working experience in operations industry with at least 3 years at managerial / supervisory level.\nRelevant experience in media or advertising industry, safety and/or electrical qualifications, will be an definite advantage.\nIndependent, responsible, analytical and well-organized with interpersonal skills.\nGood leadership and communications skills, detail-minded and capable of solving problems with a clear recording and reporting methodology.\nProficiency in both spoken and written English and Chinese.\nGreen card holder\nIrregular and holiday working hours may be necessary.\n\nWe offer a 5-day week with excellent benefits including medical, dental plan to the right candidate. Interested parties please send your full resume stating your current and expected salary to Human Resources Department by clicking\u00a0APPLY NOW\u00a0button below.\n\n\u00a0***** All data collected will only be used for recruitment purpose only *****", "employment_types": ["Full Time", "Permanent"], "selling_points": [], "locations": ["Quarry Bay"], "categories": ["Media & Advertising", "Account Servicing", "Media Buying", "Others"], "post_time": "2022-01-10T02:14:42Z", "salary": {"currency": null, "max": null, "min": null, "period": "monthly", "term": null}, "salary_visible": false, "title_keywords": ["specialist"], "responsibilities": ["regulations", "management", "advertising", "maintenance", "operations", "inventory", "monitoring", "quality", "review", "maintain", "specifications", "contact", "plan", "cleaning", "liaise with", "report"], "requirements": {"degrees": ["degree holder", "master"], "majors": ["related disciplines", "electrical engineering", "mechanical engineering"], "languages": ["english", "chinese"], "language_level": ["proficiency"], "hard_skills": ["green card"], "soft_skills": ["detail-minded", "independent", "capable", "responsible", "well-organized", "clear", "interpersonal skills", "leadership"], "languages_combined": [{"language": "english", "language_level": ["proficiency"]}, {"language": "chinese", "language_level": ["proficiency"]}]}, "experience_required": {"duration": ["at least 8 years", "at least 3 years"], "field": ["managerial", "related", "advertising industry", "environmental", "relevant experience", "supervisory level", "media"]}}, {"job_id": "100003009036688", "location_code": "hk", "company": "Phoenix Satellite Television Co Ltd", "job_title": "\u63a1\u8a2a\u4e3b\u4efb", "description": "\n\u517c\u8077\u4ee3\u5531\u6b4c\u624b\n\u5c0d\u5531\u6b4c\u6709\u8208\u8da3\u4e4b\u4eba\u4ed5\u3002\u53c3\u8207\u5ee3\u544a\u96fb\u5f71\u6b4c\u66f2/\u5361\u62c9OK\u5e55\u5f8c\u4ee3\u5531\uff08\u5305\u62ec\u6d41\u884c\u66f2\u53ca\u61f7\u820a\u91d1\u66f2\uff09/\u5bb4\u6703\u6d3b\u52d5\u7b49\u5de5\u4f5c\u3002 \u80fd\u64cd\u6d41\u5229\u5ee3\u6771\u8a71\uff0c\u7537\u5973\u5747\u53ef\u3001\u9700\u5e74\u6eff20\u6b72\u4ee5\u4e0a\u3002\n\n\u7d93\u9a57\u4e0d\u62d8\u3001\u5de5\u4f5c\u6642\u9593\u4efb\u64c7 \u3002 \u85aa\u916c\u9762\u8b70 (\u5305\u62ec\ufe55\u6642\u85aa\ufe51\u6708\u85aa\u6216\u6309\u6bcf\u9805\u5de5\u4f5c\u8a08\u7b97)\u00a0 \u6b61\u8fce20\u6b72\u4ee5\u4e0a\u4eba\u58eb\u9810\u7d04\u9762\u8a66\u3002\n\n\u5982\u8981\u7d04\u898b\u9762\u8a66\uff0c\u8acb\u81f4\u96fb2781 4355\u8607\u751f\uff0812:00-18:00\uff09\u6d3d\u3002\u00a0\u6216\u6309APPLY NOW\u63d0\u4ea4\u7533\u8acb\n\u5947\u8e5f\u5de5\u4f5c\u574a\n\n\n", "employment_types": ["Full Time"], "selling_points": [], "locations": ["Tai Po Area"], "categories": ["Media & Advertising", "Others"], "post_time": "2022-01-10T12:36:55Z", "salary": {"currency": null, "max": null, "min": null, "period": null, "term": null}, "salary_visible": false, "title_keywords": [], "responsibilities": [], "requirements": {"degrees": [], "majors": [], "languages": [], "language_level": [], "hard_skills": [], "soft_skills": [], "languages_combined": []}, "experience_required": {"duration": [], "field": []}}, {"job_id": "100003009037380", "location_code": "hk", "company": "\u5fc5\u9ad8\u4eba\u4e8b\u9867\u554f\u6709\u9650\u516c\u53f8", "job_title": "Digital Marketing Specialist (Fresh Graduates will be considered)", "description": "\u5c97\u4f4d\u804c\u8d23\uff1a\n\n\u7ba1\u7406\u7d71\u7c4c\u5167\u5bb9\u904b\u71df\u5718\u968a\uff1b\n\u7d71\u7c4c\u8cc7\u8a0a\u3001\u7bc0\u76ee\u3001\u7d9c\u85dd\u3001\u5287\u96c6\u3001\u5546\u696d\u6d3b\u52d5\u3001\u76f4\u64ad\u7b49\u5404\u985e\u5167\u5bb9\u7684\u904b\u71df\u53ca\u6548\u679c\uff1b\n\u7b56\u5283\u548c\u88fd\u4f5c\u65b0\u5a92\u9ad4\u539f\u5275\u5167\u5bb9\uff1b\n\u5916\u90e8\u8cc7\u6e90\u5c0d\u63a5\u548c\u62d3\u5c55\uff1b\n\u914d\u5408\u516c\u53f8\u6230\u7565\u65b9\u5411\u767c\u5c55\u65b0\u696d\u52d9\uff1b\n\n\u4efb\u804c\u8d44\u683c\uff1a\n\n\u2022\u672c\u79d1\u4ee5\u4e0a\u5b78\u6b77\uff0c5\u5e74\u4ee5\u4e0a\u5167\u5bb9\u3001\u5a92\u9ad4\u3001\u4e92\u806f\u7db2\u904b\u71df\u7b49\u76f8\u95dc\u7d93\u9a57\n\n\u71b1\u611b\u5a92\u9ad4\u884c\u696d\uff0c\u71b1\u611b\u4e92\u806f\u7db2\u884c\u696d\uff0c\u5c0d\u65b0\u9bae\u4e8b\u7269\u6709\u597d\u5947\u5fc3,\u6709\u8f03\u9ad8\u7684\u6587\u5316\u7d20\u990a\uff1b\n\u512a\u79c0\u7684\u4e2d\u82f1\u6587\u8b80\u5beb\u80fd\u529b\uff0c\u61c2\u5ee3\u6771\u8a71\u512a\u5148\uff1b\n\u6709\u5718\u968a\u7ba1\u7406\u7d93\u9a57\u53ca\u672c\u5730\uff08\u9999\u6e2f/\u6df1\u5733\uff09\u5a92\u9ad4\u8cc7\u6e90\u8005\u512a\u5148\u3002", "employment_types": ["Full Time", "Contract"], "selling_points": ["Fresh graduates will be considered", "Boutique firm - SEM / SEO", "Great exposure across a wide range of industries"], "locations": ["Central & Western Area"], "categories": ["Media & Advertising", "Others", "Marketing / Public Relations", "Others", "Digital Marketing"], "post_time": "2022-01-11T02:39:44Z", "salary": {"currency": null, "max": null, "min": null, "period": "monthly", "term": null}, "salary_visible": false, "title_keywords": ["digital marketing specialist"], "responsibilities": [], "requirements": {"degrees": [], "majors": [], "languages": [], "language_level": [], "hard_skills": [], "soft_skills": [], "languages_combined": []}, "experience_required": {"duration": [], "field": []}}, {"job_id": "100003009034521", "location_code": "hk", "company": "\u4e00\u5a92\u9ad4\u5ee3\u544a\u7b56\u5283\u6709\u9650\u516c\u53f8", "job_title": "CG Artist / 3D Artist \u2013 Hong Kong", "description": "Job Highlights\n\nDegree in Language, Linguistics or Translation\nEnsure the highest quality of work\nMinimum 5 years editorial experience\n\nJob Descriptions\n\nImplement publishing directions, goals and plans for both print and digital products\nCarry out editorial works for print and digital products\nEnsure highest quality of work and timely production of assigned titles\nCollaborate with freelancers, design, production and technical teams on publishing print and digital materials\nResponsible for market research and project related works\n\nJob requirements\n\nUniversity degree in Language, Linguistics, Translation or relevant disciplines\nMinimum 5 years editorial experiences in educational books\nExperience in digital publishing is an advantage\nGood analytical, organization and communication skills\nAbility to work under pressure\nInterested parties, please send email to\n[via APPLY NOW]\u00a0\n\n\u5b78\u6821 / \u6a5f\u69cb\u57fa\u672c\u8cc7\u6599\n\n\u62db\u8058\u5b78\u6821/\u6a5f\u69cb\u540d\u7a31 EVI Services Limited\n\u7533\u8acb\u65b9\u5f0f \u96fb\u90f5\n\u7533\u8acb\u806f\u7d61\u4eba Mr Choi\n\u96fb\u8a71\u00a035890840\n\u96fb\u90f5 APPLY NOW\n\u6a5f\u69cb\u985e\u5225 \u5176\u4ed6\n\n\nSummary\nIndustry:\nEducation / Training\nJob Category / Function:\nMedia (Editorial / Journalism)\nMedia (Translation)\nMedia (Others)\nJob Position Level:\nMiddle\nEmployment Term:\nFull Time\nMin. Edu. Level Req:\nBachelor\nMinimum QF Level attained:\n-\nTotal Working Exp:\n5\nSalary(HKD):\n-\nLocation:\nYau Tsim Mong District / Mong Kok", "employment_types": ["Full Time", "Permanent"], "selling_points": [], "locations": ["Ngau Tau Kok"], "categories": ["Media & Advertising", "Creative / Design", "Others"], "post_time": "2022-01-10T03:33:49Z", "salary": {"currency": null, "max": null, "min": null, "period": "monthly", "term": null}, "salary_visible": false, "title_keywords": [], "responsibilities": ["collaborate with", "teams", "quality", "design", "market research", "plans"], "requirements": {"degrees": ["university degree"], "majors": [], "languages": [], "language_level": [], "hard_skills": ["translation"], "soft_skills": ["communication skills", "work under pressure"], "languages_combined": []}, "experience_required": {"duration": ["minimum 5 years"], "field": ["digital", "editorial", "publishing"]}}, {"job_id": "100003009030181", "location_code": "hk", "company": "JCDecaux Pearl & Dean Limited", "job_title": "Operations Manager / Senior Operations Manager", "description": "Job Descriptions\n\n\n\nImplement publishing directions, goals and plans for both print and digital products\nCarry out editorial works for print and digital products\nEnsure highest quality of work and timely production of assigned titles\nCollaborate with freelancers, design, production and technical teams on publishing print and digital materials\nResponsible for market research and project related works\n\n\n\nJob Requirements\n\nUniversity degree in Language, Linguistics, Translation or relevant disciplines\nMinimum 6 years editorial experiences in educational books\nExperience in digital publishing is an advantage\nGood analytical, organization and communication skills\nAbility to work under pressure\nInterested parties, please send email to\n[via APPLY NOW]\u00a0\n\n\nSummary\nIndustry:\nEducation / Training\nJob Category / Function:\nMedia (Editorial / Journalism)\nMedia (Translation)\nMedia (Others)\nJob Position Level:\nMiddle\nEmployment Term:\nFull Time\nMin. Edu. Level Req:\nBachelor\nMinimum QF Level attained:\n-\nTotal Working Exp:\n6", "employment_types": ["Full Time"], "selling_points": ["Oversee, plan and manage the daily posting", "Manage and supervise all related resources", "8 years working experience in operations industry"], "locations": ["Quarry Bay"], "categories": ["Admin & HR", "Administration / Operation Manager", "Media & Advertising", "Others", "Print Media"], "post_time": "2022-01-07T06:55:29Z", "salary": {"currency": null, "max": null, "min": null, "period": "monthly", "term": null}, "salary_visible": false, "title_keywords": ["senior operations", "operations manager", "manager"], "responsibilities": ["collaborate with", "teams", "quality", "design", "market research", "plans"], "requirements": {"degrees": ["university degree"], "majors": [], "languages": [], "language_level": [], "hard_skills": ["translation"], "soft_skills": ["communication skills", "work under pressure"], "languages_combined": []}, "experience_required": {"duration": ["minimum 6 years"], "field": ["digital", "editorial", "publishing"]}}, {"job_id": "100003009034606", "location_code": "hk", "company": "Frengers Communications Limited", "job_title": "Associate Creative Director / CD / Senior Copywriter", "description": "\u5d17\u4f4d\u8077\u8cac\n\n\u7ba1\u7406\u5916\u63a1\u8a18\u8005\u5718\u968a\uff1b\n\u7d71\u7c4c\u65e5\u5e38\u63a1\u8a2a\u5b89\u6392\u53ca\u5167\u5bb9\u4e8b\u9805\uff1b\n\u6839\u64da\u5167\u5bb9\u904b\u71df\u5b89\u6392\u7b56\u5283\u53ca\u5b89\u6392\u5c08\u984c\u63a1\u8a2a\uff1b\n\u62d3\u5c55\u548c\u7dad\u8b77\u516c\u53f8\u63a1\u8a2a\u8cc7\u6e90\n\n\u4efb\u804c\u8d44\u683c\uff1a\n\n3\u5e74\u4ee5\u4e0a\u65b0\u805e\u63a1\u8a2a\u5f9e\u696d\u7d93\u9a57\uff0c\u6709\u9ad8\u5ea6\u654f\u92b3\u7684\u65b0\u805e\u55c5\u89ba\uff0c\u6709\u8c50\u5bcc\u63a1\u8a2a\u8cc7\u6e90\u8005\u512a\u5148\uff1b\n\u719f\u6089\u50b3\u7d71\u5a92\u9ad4\u6216\u65b0\u5a92\u9ad4\u7684\u88fd\u4f5c\u6d41\u7a0b\uff1b\n\u512a\u79c0\u7684\u4e2d\u82f1\u6587\u8b80\u5beb\u80fd\u529b\uff0c\u61c2\u5ee3\u6771\u8a71\u512a\u5148\uff1b4\u3001", "employment_types": ["Full Time"], "selling_points": [], "locations": ["Kwun Tong"], "categories": ["Media & Advertising", "Creative / Design", "Others", "Design", "Graphics"], "post_time": "2022-01-10T03:47:40Z", "salary": {"currency": null, "max": null, "min": null, "period": "monthly", "term": null}, "salary_visible": false, "title_keywords": ["creative director", "associate", "copywriter"], "responsibilities": [], "requirements": {"degrees": [], "majors": [], "languages": [], "language_level": [], "hard_skills": [], "soft_skills": [], "languages_combined": []}, "experience_required": {"duration": [], "field": []}}, {"job_id": "100003009034625", "location_code": "hk", "company": "GroupM Limited", "job_title": "GroupM | Performance Specialist/ Senior Performance Specialist", "description": "Job Nature:\n\nLead a team of mobile app developers\nAnalyze requirements from product owner, ux designer etc and translate the requirements to tech design for developers.\nWork with Product Owner, UX designer, Backend Team and Project manager closely to deliver quality mobile app\nResponsible for iOS and Android applications design, testing and development\nMaintenance and enhancements of existing mobile app\nKeep up with current trends in mobile app development industry\nCharacters / Qualifications:\n\nDiploma, associate degree or bachelor\u2019s degree in Computer Science or related discipline or equivalent industry experience\nMinimum 5 years relevant experience\nGood communication skills and able to translate technical concept to layman is a must\nGood Knowledge in Swift or Kotlin and App Deployment is a must\nGood Knowledge of firebase is an advantage\nKnowledge in Google Flutter would be an advantage\nFamiliar with below is a plus\n- AWS cloud\n- Git Flow\n- Mobile App Unit Test process\nExperience in handling JSON and RESTful APIs integration\nGood understanding of OOP and Design Patterns\n\nWe offer competitive salary and benefits package( 5 days work, 14 days AL up, birthday leave, medical & dental insurance) with great opportunity for career development to the successful candidate.\n\nPlease send your detailed resume and expected salary to our Human Resources Department by clicking \"Apply Now\" (please put position applied on subject line).", "employment_types": ["Full Time", "Permanent"], "selling_points": [], "locations": ["Quarry Bay"], "categories": ["Media & Advertising", "Media Buying", "Others"], "post_time": "2022-01-10T03:49:29Z", "salary": {"currency": null, "max": null, "min": null, "period": "monthly", "term": null}, "salary_visible": false, "title_keywords": ["performance specialist"], "responsibilities": ["mobile app", "maintenance", "quality", "design", "testing", "communication", "lead a team", "career development", "insurance"], "requirements": {"degrees": ["associate degree", "diploma", "degree", "bachelor"], "majors": ["computer science"], "languages": [], "language_level": [], "hard_skills": ["plus", "git", "maintenance", "integration", "aws", "mobile", "deployment", "swift", "kotlin", "android"], "soft_skills": ["communication skills", "responsible", "detailed"], "languages_combined": []}, "experience_required": {"duration": ["minimum 5 years"], "field": ["related", "relevant experience"]}}, {"job_id": "100003009038331", "location_code": "hk", "company": "Optimum Media Direction", "job_title": "Digital Manager (Advertising & Media Field)", "description": "\n\n\nJob Description:\n\nExplore and develop new business opportunities to meet sales target\nPrepare proposals, sales materials and presentation to client\nFollow up new / potential customers inquires\nCoordinate with other teams to ensure smooth operations\u00a0\n\nJob Requirements:\n\n\nAt least 3 years media\u00a0sales experience (print/ digital/ outdoor/ product)\nHave the extensive network with local corporate clients / retail merchants\nKnowledge of social media trend is preferable\nInitiative and well organized\nExcellent spoken and written English and Chinese\nStrong network in certain industry is highly preferred\nCandidates with less experience would be considered as Senior Sales Executive\n\nInterested parties please send your full resume with expected salary and date available by clicking \u201cAPPLY NOW\u201d.\u00a0\n\nPersonal data will be used for recruitment purpose only.", "employment_types": ["Full Time", "Permanent"], "selling_points": ["Free Shuttle Bus & Free Breakfast", "Birthday, Family Day & Self-Love Day Leave", "5-Day Work Week"], "locations": ["Pok Fu Lam"], "categories": ["Media & Advertising", "Account Servicing", "Strategic Planning", "Others"], "post_time": "2022-01-11T06:33:19Z", "salary": {"currency": null, "max": null, "min": null, "period": "monthly", "term": null}, "salary_visible": false, "title_keywords": ["manager"], "responsibilities": ["develop new business", "sales target", "coordinate with", "teams", "ensure smooth operations"], "requirements": {"degrees": [], "majors": [], "languages": ["english", "chinese"], "language_level": ["excellent"], "hard_skills": [], "soft_skills": ["extensive", "initiative", "well organized"], "languages_combined": [{"language": "english", "language_level": ["excellent"]}, {"language": "chinese", "language_level": ["excellent"]}]}, "experience_required": {"duration": ["at least 3 years"], "field": ["digital", "print", "media sales"]}}, {"job_id": "100003009039932", "location_code": "hk", "company": "csl.", "job_title": "Senior Marketing Executive (retail visual merchandising)", "description": "Job Nature:\n\nAssist in promotion plan development to achieve business goals in marketing campaigns, e.g. acquiring new users and driving campaign participation\nResponsible for reward program/welcome gifts\nManage merchant relationship including negotiation of partnership terms, promotion offers and operation supports\nCommunicate and liaise with project stakeholders and decision-makers\nWorking with GM, BD & Sales Team to explore new business opportunities and collaboration\nWorking with team head in streamlining workflows and procedures strategically and evaluating projects in an effective and efficient manner\nCharacters / Qualifications:\n\nBachelor Degree\nOver 2-3 years experience in digital projects and social media management\nBe highly responsive and have a strong sense of digital and beauty trends\nExperience in the Beauty Industry and knowledge in Photoshop is strongly preferred\nGood communication skills, self-motivated\nAble to work independently with good execution ability\nAttention to detail, Positive, Energetic and Team-oriented\n\nWe offer competitive salary and benefits package( 5 days work, 14 days AL up, birthday leave, medical & dental insurance) with great opportunity for career development to the successful candidate.\n\nPlease send your detailed resume and expected salary to our Human Resources Department by clicking \"Apply Now\" (please put position applied on subject line).", "employment_types": ["Full Time"], "selling_points": ["Support retail branding", "Prepare and manage retail stores planograms", "Safeguard the brand essence in retail environment"], "locations": ["Quarry Bay"], "categories": ["Media & Advertising", "Others", "Marketing / Public Relations", "Marketing - Marketing Communication", "Others"], "post_time": "2022-01-11T15:36:29Z", "salary": {"currency": null, "max": null, "min": null, "period": "monthly", "term": null}, "salary_visible": false, "title_keywords": ["merchandising", "senior marketing executive"], "responsibilities": ["social media", "business goals", "management", "explore new business opportunities", "procedures", "communication", "sales team", "marketing campaigns", "plan", "liaise with", "career development", "insurance"], "requirements": {"degrees": ["degree", "bachelor"], "majors": [], "languages": [], "language_level": [], "hard_skills": ["gm", "photoshop"], "soft_skills": ["efficient", "communication skills", "self-motivated", "work independently", "negotiation", "responsible", "attention to detail", "energetic", "responsive", "positive", "detailed"], "languages_combined": []}, "experience_required": {"duration": ["2-3 years"], "field": ["digital", "management", "social media", "beauty industry"]}}, {"job_id": "100003009027059", "location_code": "hk", "company": "PHD Limited", "job_title": "Media Executive (Advertising & Media Field)", "description": "Job Role:\n\nThe Digital Manager supervises all day to day planning/\u200bclient service activity.\u200b\u00a0 Reporting to the Business Director, the Digital Manager work in providing digital planning recommendations to the client.\u200b The Manager oversees preparation of digital strategy and media plans and supervises media plan implementation.\u200b The Manager is also in charge of supervising the Planners/\u200bSenior Planners in executing media plans.\u200b\n\n\nKey Responsibilities:\n\nMaintain day-to-day contact for all clients to execute requests flawlessly while adhering to clients\u2019 strategic direction.\nCoordinate and execute workflow between planning, operations and buying.\nIntelligence gathering of research, analysis and other strategic support materials. Translate/interpret data into clear and succinct information and relevant insights.\nSeek out new opportunities to grow clients business and provide necessary Point of View and rationale.\nLead internal and external status meetings/calls.\nThe role may involve performing additional media agency duties as required.\n\nKey Requirements:\n\nAt least 5-6 years of digital industry work experience. \u00a0\nCollege degree preferably in Marketing.\nProficiency in Microsoft Office\nExcellent written and verbal communication skills\nExperience in digital buying/planning\nAbility to manage tight deadlines while multitasking\nExperience/background in digital buying/planning.\nKnowledge of Display, Mobile, SEM/SEO, Social Media, Programmatic, Social Listening and content marketing.\nWorking Location: Cyberport (\u6578\u78bc\u6e2f), Hong Kong\nWe offer a 5-day week of work, group medical & life insurance coverage and free shuttle bus to the right candidate. Interested parties please send your application letter and resume with your current and expected salary by clicking \u201cApply Now\u201d button.\nAll information collected will be used for recruitment only and treated in strict confidence. We will retain the personal data of unsuccessful applicants for future recruitment purpose for a maximum period of 2 years.", "employment_types": ["Full Time", "Permanent"], "selling_points": ["Free Shuttle Bus & Free Breakfast", "Birthday, Family Day & Self-Love Day Leave", "5-Day Work Week"], "locations": ["Pok Fu Lam"], "categories": ["Media & Advertising", "Account Servicing", "Media Buying", "Others"], "post_time": "2022-01-06T09:04:02Z", "salary": {"currency": null, "max": null, "min": null, "period": "monthly", "term": null}, "salary_visible": false, "title_keywords": ["executive"], "responsibilities": ["data", "operations", "analysis", "coordinate", "maintain", "contact", "planning"], "requirements": {"degrees": ["degree"], "majors": ["marketing"], "languages": [], "language_level": [], "hard_skills": ["mobile", "seo", "sem", "microsoft office"], "soft_skills": ["communication skills"], "languages_combined": []}, "experience_required": {"duration": ["at least 5-6 years"], "field": ["digital", "digital industry", "planning"]}}, {"job_id": "100003009035493", "location_code": "hk", "company": "Carat Media Services Hong Kong Limited", "job_title": "Media Executive (Fresh graduate welcome)", "description": "Your role\n\nSupport retail branding and merchandizing strategy implementation\nCoordinate and liaise with internal teams, including sales and marketing teams, to deliver effective marketing communications materials for different marketing programs at our retail shops\nBrief, manage and evaluate external agencies in delivering quality and effective communications materials in a timely and cost efficient manner\nPrepare and manage retail stores planograms to maximize products and services exposure\nBe the brand champion to safeguard the brand essence in retail environment\nPerform quality checks and shop visits to ensure smooth and complete implementation of visual merchandising materials according to the guideline and standard\nHandle and follow up retail\u2019s enquiries on visual merchandizing and replenishment request\nUndertake any other activities as assigned by supervisors\n\nTo succeed in this role\n\nDegree holder preferably in marketing, communications or business disciplines\n2-3 years of working experience in marketing communications, advertising agency background is an advantage\nSelf-motivated, able to work independently and handle multi-tasks\nDetailed oriented, creative, strong organizational skills\nAble to work under high pressure and long hours and meet tight deadline\nExcellent English and Chinese in both written and verbal communications\nProficiency in MS window application including Excel, Word and Chinese word processing\n\u00a0\n\nHKT is an equal opportunity employer and welcomes applications from all qualified candidates. Information provided will be treated in strict confidence and will only be used for recruitment-related purposes.\nPersonal data provided by job applicants will be used strictly in accordance with the employer's privacy statement (www.hkt.com/privacy-statement), a copy of which will be provided immediately upon request.", "employment_types": ["Full Time", "Permanent"], "selling_points": ["Prepare implementational buying briefs", "Prepare competitive analysis", "Quality check spot plans"], "locations": ["Quarry Bay"], "categories": ["Media & Advertising", "Account Servicing", "Strategic Planning", "Others"], "post_time": "2022-01-10T07:25:18Z", "salary": {"currency": null, "max": null, "min": null, "period": "monthly", "term": null}, "salary_visible": false, "title_keywords": ["executive"], "responsibilities": ["cost", "advertising", "teams", "implementation", "quality", "merchandising", "coordinate", "evaluate", "replenishment", "recruitment", "visual", "liaise with", "personal data"], "requirements": {"degrees": ["degree holder"], "majors": ["business", "marketing", "communications"], "languages": ["english", "chinese"], "language_level": ["excellent", "proficiency"], "hard_skills": ["merchandizing", "excel", "chinese word processing", "visual merchandising", "word"], "soft_skills": ["efficient", "organizational skills", "work independently", "self-motivated", "detailed oriented", "confidence", "multi-tasks", "timely", "work under high pressure", "meet tight deadline", "smooth", "creative"], "languages_combined": [{"language": "english", "language_level": ["excellent"]}, {"language": "chinese", "language_level": ["excellent", "proficiency"]}]}, "experience_required": {"duration": ["2-3 years"], "field": ["marketing communications", "advertising agency"]}}, {"job_id": "100003009028400", "location_code": "hk", "company": "Liang Yi Museum", "job_title": "Museum Assistant", "description": "Responsibilities:\n\nOversee, plan and manage the daily posting, maintenance and cleaning works for all advertising formats covering light box, digital panels and temporary executions.\nEnsure that all works by company staff and contractors are carried out with high standard of safety and quality while monitoring overall performance.\nManage and supervise all related resources: staff, vehicles, equipment & tools, posting material, contractors, warehouses and stock as well as spare parts.\nMaintain exhaustive and detailed record of all media inventory and specifications, as well as operational activities and events logs.\nEnsure that all operations comply with Health and safety requirements and local regulations.\nEnsure all interior and exterior advertising formats and media are maintained in optimal safety and working conditions, clean and tidy with quality posting.\nBe the main contact window at all times with landlords and authorities for all operation related matters. Maintain immediate responsiveness with night shift operatives to liaise with relevant parties (authority, vendors, other company departments) to investigate, solve and report all issues.\nEnsure timely submissions and approval for all required operational submissions (work and access permits, certifications, forms and trainings, etc).\nClose cooperation and site support with Projects Department to ensure all new installations and projects are carried out in safe conditions.\nProactively support other company departments in answering raised queries and issues by providing timely response and close follow up until issues are solved.\nHave a proactive role in understanding company requirements and scope to review the working procedure, and propose improvement methods to management.\n\nRequirements:\n\nMaster\u2019s Degree holder in operations, mechanical engineering, electrical engineering or other related disciplines.\nEnvironmental, Quality and Health & Safety related certifications and experience\nAt least 8 years working experience in operations industry with at least 3 years at managerial / supervisory level.\nRelevant experience in media or advertising industry, safety and/or electrical qualifications, will be an definite advantage.\nIndependent, responsible, analytical and well-organized with interpersonal skills.\nGood leadership and communications skills, detail-minded and capable of solving problems with a clear recording and reporting methodology.\nProficiency in both spoken and written English and Chinese.\nGreen card holder\nIrregular and holiday working hours may be necessary.\n\nWe offer a 5-day week with excellent benefits including medical, dental plan to the right candidate. Interested parties please send your full resume stating your current and expected salary to Human Resources Department by clicking\u00a0APPLY NOW\u00a0button below.\n\n\u00a0***** All data collected will only be used for recruitment purpose only *****", "employment_types": ["Full Time"], "selling_points": ["Front-desk duties", "Working with curatorial and collections team", "Participating in public relations, marketing"], "locations": ["Central & Western Area"], "categories": ["Media & Advertising", "Others", "Sales, CS & Business Devpt", "Customer Service - Supervisor / Officer", "Marketing / Public Relations", "Public Relations - Event Management"], "post_time": "2022-01-11T08:48:33Z", "salary": {"currency": null, "max": null, "min": null, "period": "monthly", "term": null}, "salary_visible": false, "title_keywords": ["assistant"], "responsibilities": ["regulations", "management", "advertising", "maintenance", "operations", "inventory", "monitoring", "quality", "review", "maintain", "specifications", "contact", "plan", "cleaning", "liaise with", "report"], "requirements": {"degrees": ["degree holder", "master"], "majors": ["related disciplines", "electrical engineering", "mechanical engineering"], "languages": ["english", "chinese"], "language_level": ["proficiency"], "hard_skills": ["green card"], "soft_skills": ["detail-minded", "independent", "capable", "responsible", "well-organized", "clear", "interpersonal skills", "leadership"], "languages_combined": [{"language": "english", "language_level": ["proficiency"]}, {"language": "chinese", "language_level": ["proficiency"]}]}, "experience_required": {"duration": ["at least 8 years", "at least 3 years"], "field": ["managerial", "related", "advertising industry", "environmental", "relevant experience", "supervisory level", "media"]}}, {"job_id": "100003009033947", "location_code": "hk", "company": "GroupM Limited", "job_title": "GroupM | Data Analytics Executive (Fresh Grad are welcome)", "description": "The Role\n\nReporting to the Digital Marketing Director, this position requires a candidate who has a passion for digital media and Ad-Tech industry. You will be growing quickly, learning how the ecosystem of digital media and data operates in the Hong Kong market from the one of the biggest agencies in the region.\n\n\n\nResponsibilities\n\nAd Trafficking, including 3rd party ad serving (Google Campaign Manager), website tracking, brand safety and associated technologies.\nConversion Tag tracking for different digital platform.\nGathering data through various third party platforms and analytics tools.\nData management including dashboards.\nData QA and analysis on media/performance trends, identify insights for campaign strategy/ planning.\n\nKey Requirements\n\nPreferably 1-2 years experience with digital marketing agency.\u00a0 Fresh graduate will also be considered.\nUnderstanding of Digital Media buying, including IO, DSP, Social Media, Search.\nStrong analytical skills, highly numerate and comfortable with data processing and interpretation.\nGood team player with excellent time-management and strong organizational skills to handle multiple projects.\nWork under pressure and meet tight deadline.\nGood in communications skills.\nExcellent command of English and Cantonese; written and spoken\nStrong attention to detail and problem-solving skills\nEagerness to learn and collaborate with others\nOpenness to change and willingness to work through challenges\nProficiency in Microsoft Office (Words, Excel and PowerPoint) is a must.\nA bachelor's degree, preferably with combined studies in Information Systems and Media, or related business field.\n\nWorking Location: Cyberport (\u6578\u78bc\u6e2f), Hong Kong\u00a0\n\nWe offer a 5-day work of week, group medical & life insurance coverage to the right candidate. Interested parties please send your application letter and resume with current and expected salary\u00a0by clicking the \"Apply Now\" button.\n\nAll information collected will be used for recruitment only and treated in strict confidence. We will retain the personal data of unsuccessful applicants for future recruitment purpose for a maximum period of 2 years.", "employment_types": ["Full Time", "Permanent"], "selling_points": [], "locations": ["Quarry Bay"], "categories": ["Media & Advertising", "Others", "Others", "Student / Fresh Graduate / No Experience", "Information Technology (IT)", "Data Scientist"], "post_time": "2022-01-10T02:14:42Z", "salary": {"currency": null, "max": null, "min": null, "period": "monthly", "term": null}, "salary_visible": false, "title_keywords": ["executive"], "responsibilities": ["analytics tools", "management", "data", "analysis", "website", "digital platform", "planning", "third party", "tracking"], "requirements": {"degrees": ["degree", "bachelor", "fresh graduate"], "majors": ["business"], "languages": ["cantonese", "english"], "language_level": ["excellent"], "hard_skills": ["excel", "io", "words", "microsoft office", "powerpoint", "analytical skills", "problem-solving skills", "processing"], "soft_skills": ["organizational skills", "good team player", "analytical skills", "willingness to work", "meet tight deadline", "attention to detail", "problem-solving skills", "work under pressure"], "languages_combined": [{"language": "cantonese", "language_level": ["excellent"]}, {"language": "english", "language_level": ["excellent"]}]}, "experience_required": {"duration": ["1-2 years"], "field": ["agency", "digital marketing"]}}, {"job_id": "100003009042846", "location_code": "hk", "company": "Most Kwai Chung Limited", "job_title": "Senior Sales Executive", "description": "Job Responsibilities:\n\nPerform from campaign planning to buying implementation, performance optimization and post-campaign analysis to meet client\u2019s communication needs\nPrepare and maintain budget plans and flowcharts, deliver media evaluation and presentation decks, generate and conclude market analysis\nWork in a team to develop integrated strategic communication plan to strive for best clients\u2019 interest\nExplore new opportunity and applicability of media vehicles actively with media vendors and technology partners\nBuild accountable and trustworthy relationship with different stakeholders\n\n\u00a0Job Requirements:\u00a0\n\nUniversity degree in business, marketing, advertising, communications, or a related field\n0-1 year of media planning/buying experience preferably (fresh graduates are also welcomed)\nImportantly, must be passionate and with full commitment to work\nAbility to manage multi-task well in a fast-paced environment\nAbility to develop strong relationship, both internally and externally, and feel comfortable interacting with people from different disciplines and cultures\nMust be well organized and have strong quantitative/analytical skills\nMust be numerate and have strong attention to details\nQuick learner and self-motivated to learn new skillset\nFluent written and spoken English and Chinese is a must\nProficiency in Word, Excel, PowerPoint and data processing\n\nWorking Location: Cyberport (\u6578\u78bc\u6e2f), Hong Kong\u00a0\n\nWe offer a 5-day work of week, group medical & life insurance coverage to the right candidate. Interested parties please send your application letter and resume with current and expected salary\u00a0by clicking the \"Apply Now\" button.\n\nAll information collected will be used for recruitment only and treated in strict confidence. We will retain the personal data of unsuccessful applicants for future recruitment purpose for a maximum period of 2 years.", "employment_types": ["Full Time", "Permanent"], "selling_points": ["KOL management, Advertising", "Basic Salary + Attractive Commission and Allowance", "Fresh graduates are also welcome"], "locations": ["Kwai Hing"], "categories": ["Media & Advertising", "Others", "Marketing / Public Relations", "Marketing - General / Support", "Sales, CS & Business Devpt", "Sales - Sales Management"], "post_time": "2022-01-12T08:59:18Z", "salary": {"currency": null, "max": null, "min": null, "period": "monthly", "term": null}, "salary_visible": false, "title_keywords": ["senior sales executive"], "responsibilities": ["analysis", "budget", "implementation", "develop", "communication", "maintain", "market analysis", "plan", "evaluation", "plans", "planning"], "requirements": {"degrees": ["university degree"], "majors": ["business", "communications", "marketing"], "languages": ["english", "chinese"], "language_level": ["fluent"], "hard_skills": ["excel", "word", "powerpoint", "analytical skills", "processing"], "soft_skills": ["passionate", "self-motivated", "multi-task", "fast-paced environment", "well organized", "quick learner", "analytical skills", "attention to details"], "languages_combined": [{"language": "english", "language_level": ["fluent"]}, {"language": "chinese", "language_level": ["fluent"]}]}, "experience_required": {"duration": ["0-1 year"], "field": ["media", "planning"]}}, {"job_id": "100003009031706", "location_code": "hk", "company": "PHD Limited", "job_title": "Planner (Advertising & Media Field)", "description": "Responsibilities\u00a0\n\n\nWorking with the Media Planners to support the Business Director on account management on a day to day basis.\nBeing part of team in creating / generating communication ideas.\nCompiling reviews on competitive activities and market research on media consumptions.\nCommunicate with different parties, including clients and vendors, during the planning process.\u00a0\u00a0\nCollate monthly plan updates with buying team or different creative teams on executions.\u00a0\n\n\u00a0Requirements\n\n\nTertiary education or above\nWell organized multi-tasker\nPositive \u201ccan-do\u201d attitude\nGood team player\nInterested in different technologies\nDetail-minded and able to work under pressure.\nEnthusiastic and keen to learn about media in Hong Kong\nGood English and interpersonal communication\nGood PC skill , especially excel, PowerPoint and internet operation, proficiency in the full suite of Microsoft Office tools\n\nWe offer 5 days work and attractive compensation package to suitable candidates. Interested parties, please send your full resume including your present & expected salary to us by email.\n\nPlease note that only short-listed applicants will be notified. All information provided will be treated in strictly confidential and used solely for recruitment purpose.", "employment_types": ["Full Time", "Permanent"], "selling_points": ["Free Shuttle Bus & Free Breakfast", "Birthday, Family Day & Self-Love Day Leave", "5-Day Work Week"], "locations": ["Pok Fu Lam"], "categories": ["Media & Advertising", "Account Servicing", "Strategic Planning", "Others"], "post_time": "2022-01-07T09:41:14Z", "salary": {"currency": null, "max": null, "min": null, "period": "monthly", "term": null}, "salary_visible": false, "title_keywords": [], "responsibilities": ["communicate with", "management", "ideas", "planning process", "teams", "market research", "communication", "plan"], "requirements": {"degrees": [], "majors": [], "languages": ["english"], "language_level": ["good"], "hard_skills": ["powerpoint", "excel", "pc skill", "microsoft office"], "soft_skills": ["detail-minded", "good team player", "keen", "interested in", "well organized", "communication", "can-do", "enthusiastic", "interpersonal", "positive", "work under pressure"], "languages_combined": [{"language": "english", "language_level": ["good"]}]}, "experience_required": {"duration": [], "field": []}}, {"job_id": "100003009029630", "location_code": "hk", "company": "Greenpeace East Asia", "job_title": "Multimedia Designer", "description": "Xaxis is seeking for a Programmatic Trading Specialist to join the Programmatic Trading team in Hong Kong.\n\nThe Programmatic Trading team is at the heart of all Xaxis activity and is pivotal to the success of each programmatic advertising campaign that is executed. You will be someone who has a positive attitude and is a dedicated individual who thrives on challenges.\n\nDescription\n\nXaxis is seeking for a Programmatic Trading Specialist to join the Programmatic Trading team in Hong Kong. The Programmatic Trading team is at the heart of all Xaxis activity and is pivotal to the success of each programmatic advertising campaign that is executed. You will be someone who has a positive attitude and is a dedicated individual who thrives on challenges.\n\nThe team works closely with all other teams within the Xaxis family from Client Development and Ad Operations to Data and Product. We are looking for someone with a positive attitude, enthusiastic and is flexible with embracing changes and new challenges.\n\nReporting of the role\n\nThis role reports to the Associate Director, Programmatic Trading.\n\n3 best things about the job:\n\nIt\u2019s a great work environment - You will collaborate with a group of quick witted, humorous, diverse and extremely dedicated colleagues who are all passionate about programmatic and making advertising welcome.\nOpinions and ideas are highly encouraged, and everyone has a voice at Xaxis. Ambition is expected and passion is admired. We are always open to new ways of thinking from everyone, especially those that will contribute to the overall success of Xaxis.\nIt is never static. You are empowered to create your own balance and be proactive. There is always something new to learn, new challenges to overcome, and new technology to embrace everyday.\n\n\nMeasures of success \u2013\u00a0\n\nIn three months, you would:\n\nGain an in depth understanding of the programmatic landscape\nBe trained on the various Xaxis platforms and tools\nContribute to the day-to-day operations of the Xaxis Programmatic Trading team and take ownership of simple campaign set ups, campaign monitoring and basic optimization\n\nIn six months, you would:\n\nDevelop relationships and earn trust with Client Development and Operations teams\nManage and be responsible for branding campaigns from start to completion\nIncorporate and recommend other aspects of the Xaxis business including audience planning and insights, Xaxis products and Xaxis Marketplace as part of the overall campaign execution.\n\nIn 12 months, you would:\n\nBe responsible and confidently manage campaigns of all KPIs from start to completion\nBe a trusted advisor to Xaxis HK team and support their activity\nTest and learn, share and seek different optimization tactics and knowledge share with the wider trading team\n\nResponsibilities of the role:\u00a0\n\nSupport the Programmatic Trading Team in executing campaigns with Client Development Team and Ad Operations\u00a0Team closely\nOversee day-to-day optimization and monitoring of campaigns, and ensure optimal delivery and performance, report any anomalies to Programmatic Trading Manager.\nDevelop basic yield optimization strategies by monitoring campaign performance and identifying opportunities to optimize, improve ROI and pitch for incremental revenue\nDeploy testing methodologies on campaigns under the direction of Associate Director, Programmatic Trading\nAnalyze data from ad serving providers like Campaign Manager, Sizmek as well as conversion tracking to map the complete consumer journey\nInvolve to advise/consult with Xaxis HK team regarding inventory performance and forecasting, campaign performance, insights and suggestions.\nAssist in preparing post campaign analysis report along with the Analytics team\n\n\nWhat you will need:\n\n3 years of Professional experience with digital marketing agency, ad network or other digital media company\nKnowledge along with a passion for digital\nResult-oriented with strong communication and analytical skills\nAbility to work both independently and under supervision once objectives have been set\nAbility to work within a fast-paced deadline driven environment\nExperience managing digital ad campaigns, - display, video, mobile or paid search\nApplied knowledge of 3rd party ad serving, website tracking and associated technologies\nUnderstanding of programmatic buying, including DSPs/SSPs, RTB, ad exchanges, DMPs, audience targeting will be a bonus\nGood command in written and spoken English and Cantonese\nProficiency in Microsoft Excel and PowerPoint\nCantonese speaking is a must\nCandidate with les experience may considered as Programmatic Trader\n\nAbout Xaxis\n\nXaxis is a global digital media platform that programmatically connects advertisers to audiences across all addressable channels. Through the expert use of proprietary data and advertising technology along with unparalleled media relationships, Xaxis delivers results for over 2,800 clients in 40 markets across North America, Europe, Asia Pacific, Latin America and the Middle East. Advertisers working with Xaxis achieve exceptionally high return on advertising spend through the company\u2019s proprietary media products, as well as through its wholly-owned specialist companies, Light Reaction, Bannerconnect, and ActionX.\u00a0 For more information, visit\u00a0www.xaxis.com.\n\n\n\nAbout Hong Kong\n\nHong Kong SAR\u2019s small yet highly dynamic and efficient media market allows us to operate with agility. Its internet and digital penetration continues to grow year-on-year, and has the highest smartphone penetration in Asia Pacific at 87%, while tablet ownership clocks in at 57%. Hong Kong SAR\u2019s digital market boasts a healthy mix of local, regional and global players, providing new opportunities in the media space.\n\nIf you want a future in media and communications, and believe in Hong Kong SAR\u2019s belief of \u201cwork hard, play hard\u201d, there is clearly no place more vibrant, challenging and exciting than Hong Kong SAR, where opportunities for you to innovate and grow are unparalleled.\n\nGroupM is an equal opportunity employer. We view everyone as an individual and we understand that inclusion is more than just diversity \u2013 it\u2019s about belonging. We celebrate the fact that everyone is unique and that\u2019s what makes us so good at what we do. We pride ourselves on being a company that embraces difference and truly represents the global clients we work with.", "employment_types": ["Full Time"], "selling_points": ["Medical and Dental insirance", "Flexible workplace", "Graphic design experience"], "locations": ["Wong Tai Sin Area"], "categories": ["Media & Advertising", "Production", "Others", "Design", "Graphics"], "post_time": "2022-01-07T05:40:32Z", "salary": {"currency": null, "max": null, "min": null, "period": "monthly", "term": null}, "salary_visible": false, "title_keywords": ["multimedia designer"], "responsibilities": ["collaborate with", "ideas", "data", "analysis report", "operations", "inventory", "day-to-day operations", "website", "communication", "deploy", "advertising", "teams", "develop", "testing", "reports", "analyze data", "kpis", "forecasting", "report", "reporting", "monitoring", "executing", "digital marketing", "tracking", "planning"], "requirements": {"degrees": [], "majors": [], "languages": ["cantonese", "english"], "language_level": ["good command"], "hard_skills": ["simple", "small", "no", "basic", "analysis", "powerpoint", "analytical skills", "microsoft excel", "mobile", "dynamic"], "soft_skills": ["flexible", "efficient", "independently", "responsible", "passion for", "driven", "unique", "analytical skills", "positive attitude", "diverse", "communication", "dynamic", "enthusiastic", "proactive", "result-oriented", "passionate about"], "languages_combined": [{"language": "cantonese", "language_level": ["good command"]}, {"language": "english", "language_level": ["good command"]}]}, "experience_required": {"duration": ["3 years"], "field": ["video", "agency", "digital media", "digital marketing", "digital"]}}, {"job_id": "100003009033004", "location_code": "hk", "company": "Pernod Ricard Hong Kong Ltd - Regional", "job_title": "Contract Media Planner", "description": "Hong Kong's largest private museum is looking for an energetic team-player to join our expanding team, in an entry-level position that offers training in all 4 main departments: operations, curation, collections management and events management.\n\nResponsibilities include:\n\nFront-desk duties such as responding to inquiries and interacting with visitors\nAssisting the operations team to ensure smooth day-to-day running of museum\nWorking with curatorial and collections team to provide administrative support for the museum's exhibitions and docent duties\nParticipating in public relations, marketing and social media under direction of digital and print manager\nAssisting events manager at both internal and external events held at museum\n\nJob requirements:\n\nBachelor's degree, preferably in art history, museology, or related disciplines\nProficiency in English and Chinese (Cantonese or Mandarin), third language is a plus\nHave excellent organisation and administrative skills, including a high level of proficiency with basic computing such as Adobe, Excel, PowerPoint and social media platforms (Instagram, WeChat)\nProven ability to multi-task and meet challenging deadlines\nMust be detail-oriented, flexible, proactive, and reliable\n1-year relevant experience required, preferably in auction houses, art galleries, art publishing, or academia\n\nInterested parties please submit application letter and full resume, including your current, expected salary and availability, by clicking \"Apply Now\".", "employment_types": ["Full Time", "Contract"], "selling_points": ["6 months Renewable contract", "Media Planning; Digital media; Digital advertising", "Good work environment; MNC; Wine & Spirit Industry"], "locations": ["Tsim Sha Tsui"], "categories": ["Media & Advertising", "Strategic Planning", "Others", "Marketing / Public Relations", "Digital Marketing"], "post_time": "2022-01-08T05:43:31Z", "salary": {"currency": null, "max": null, "min": null, "period": "monthly", "term": null}, "salary_visible": false, "title_keywords": [], "responsibilities": ["provide administrative support", "operations", "social media"], "requirements": {"degrees": ["degree", "bachelor"], "majors": ["related disciplines", "history", "art"], "languages": ["cantonese", "english", "chinese", "mandarin"], "language_level": ["proficiency"], "hard_skills": ["excel", "plus", "basic", "powerpoint", "wechat", "adobe"], "soft_skills": ["flexible", "multi-task", "detail-oriented", "reliable", "organisation", "proactive"], "languages_combined": [{"language": "cantonese", "language_level": ["proficiency"]}, {"language": "english", "language_level": ["proficiency"]}, {"language": "chinese", "language_level": ["proficiency"]}, {"language": "mandarin", "language_level": ["proficiency"]}]}, "experience_required": {"duration": ["1-year"], "field": ["publishing", "relevant experience"]}}, {"job_id": "100003009030932", "location_code": "hk", "company": "Imagine Lab Limited", "job_title": "Art Director/Senior Designer", "description": "Our client is a boutique digital marketing firm in Hong Kong specialising in digital\ntransformation, search and programmatic marketing. If you have relevant experience and\nwould like to advance your career in a promising company, or a fresh graduate wanting to\nkickstart their career in digital marketing apply to the following role.\n\nJob description:\n\nManaging marketing budgets and activities across all multiple marketing channels from strategy to execution\nUnderstand principle of SEM / SEO\nRunning analysis, operational campaign management and able to asses marketing performance\nPrepare reports and updates for clients\nUnderstand principle of onsite optimisations\nIdentify business opportunities for our clients, including expanding marketing\u00a0operation, capital allocation and overall planning\nRequirements:\n\nPrevious digital marketing experience preferred but not required, fresh graduates will be considered\nFluency in English for internal communications\nExtremely good analytical and communication skills including Google analytics,\nGoogle Sheets, Excel and other analytical tools\nWe are open to fresh graduate wanting to make their first foray in digital marketing", "employment_types": ["Full Time", "Permanent"], "selling_points": [], "locations": ["Others"], "categories": ["Media & Advertising", "Others", "Design", "Graphics", "Multi-media"], "post_time": "2022-01-07T08:39:30Z", "salary": {"currency": null, "max": null, "min": null, "period": "monthly", "term": null}, "salary_visible": false, "title_keywords": ["art director", "senior designer"], "responsibilities": ["budgets", "seo", "identify business opportunities", "analysis", "sem", "prepare reports", "campaign management", "planning"], "requirements": {"degrees": ["fresh graduate"], "majors": ["digital marketing"], "languages": ["english"], "language_level": ["fluency"], "hard_skills": ["google analytics", "make", "excel"], "soft_skills": ["communication skills"], "languages_combined": [{"language": "english", "language_level": ["fluency"]}]}, "experience_required": {"duration": [], "field": ["digital marketing"]}}, {"job_id": "100003009027281", "location_code": "hk", "company": "The Hong Kong Ballet Ltd", "job_title": "Video Production Manager (12 months contract)", "description": "Responsibilities\nDevelop and explore new business opportunities to meet sales targets;\nAchieve individual sales targets by selling creative solutions and production services;\nServe as the client\u2019s primary point of contact for the program, create, design and plan online marketing campaigns to clients;\nMaintain a close relationship and develop lasting business relationships with clients;\nCoordinate projects with clients and the internal team to deliver clients' requirements.\n\nRequirements\n\nUniversity graduates or high school graduates will also be considered.\n1-2 years of experience in Marketing / Advertising / Media Sales / Digital Sales is highly preferred.\nFresh graduated and no related experiences in Digital and Advertising industry will consider as Sales Executive\nCreative, organized, hardworking, independent, and able to work under pressure.\nStrong communication presentation & negotiation skills.\nSound PC knowledge with excellent MS Office skills.\nImmediately available is an advantage.\n\nWe offer a 5-day week of work, group medical insurance coverage & birthday leave.\n\nInterested parties, please send your detailed resume with the expected salary via Apply Now.\n\nThis role is located and based in Hong Kong. Candidates must be eligible to work in Hong Kong.", "employment_types": ["Contract"], "selling_points": ["Minimum 3 years experience in film production", "Open to flexible working hours", "Experience in dance/ballet project is an advantage"], "locations": ["Causeway Bay"], "categories": ["Media & Advertising", "Others", "Photography / Video"], "post_time": "2022-01-06T09:44:22Z", "salary": {"currency": null, "max": null, "min": null, "period": "monthly", "term": null}, "salary_visible": false, "title_keywords": ["production manager"], "responsibilities": ["explore new business opportunities", "design", "develop", "coordinate", "maintain", "contact", "plan", "marketing campaigns"], "requirements": {"degrees": ["high school"], "majors": [], "languages": [], "language_level": [], "hard_skills": ["no", "pc knowledge", "ms office"], "soft_skills": ["organized", "independent", "communication", "negotiation skills", "creative", "presentation", "hardworking", "work under pressure"], "languages_combined": []}, "experience_required": {"duration": ["1-2 years"], "field": ["advertising", "digital sales", "media sales", "related", "advertising industry", "marketing", "digital"]}}, {"job_id": "100003009025771", "location_code": "hk", "company": "Phoenix Satellite Television Co Ltd", "job_title": "\u65b0\u805e\u4e3b\u7de8", "description": "As one of the leading marketing agencies in Hong Kong, we are looking for 3D Artist who can bring to the table creativity when designing stylized and realistic graphics for our virtual production. You will have experience in creating at least some of the following: Environments, Lighting or Cameras.\u00a0\n\nYou will need to \u2013\u00a0\nUse 3D modelling, texture, mapping, and other techniques to create graphics, visual effects, and animations.\nUnderstand the project requirements and conceptualize creative ideas.\nCreate photorealistic set/stage design for virtual production and project, not limited to online events/concerts, TV commercials and music videos.\nCreate and maintain CG assets library for different studio needs and requests of clients.\nReceive feedback from directors and clients, and edit your creations based on the comments received.\nReview 3D arts and recommending improvements.\nRequirements:\nAt least 3 years experiences in games, apps or equivalent. Ideally worked on at least 1 shipped app or game;\nArt/Design-related degree and/or comparable professional experience;\nA good sense of creating virtual environment in photorealistic quality.\nA strong portfolio of previous CGI work.\nImaginative and Creative.\nStrong working knowledge of industry-standard software, including 3ds Max, V-Ray, SketchUp, Maya, Substance, Blender. Unreal knowledge is a good plus.\nAn eye for composition, realism, texture, color, and lighting.\nGood communication and teamwork skills.\nVirtual production experience is highly appreciated.\nWillingness to remain up-to-date on the latest creative software and hardware.\nInterested parties please send full resume with expected salary to us.\u00a0\n\nPlease visit our group website for more information:\u00a0www.onemediagroup.asia\n\nPersonal data will be used for recruitment purpose only.\n\njobsDB will send your application for review directly to\nOne Media Group\n\njobsDB will send your application for review directly to\n\u4e00\u5a92\u9ad4\u5ee3\u544a\u7b56\u5283\u6709\u9650\u516c\u53f8", "employment_types": ["Full Time"], "selling_points": [], "locations": ["Tai Po Area"], "categories": ["Media & Advertising", "Others", "Editorial / Journalism", "Broadcasting - TV / Radio"], "post_time": "2022-01-06T06:27:24Z", "salary": {"currency": null, "max": null, "min": null, "period": null, "term": null}, "salary_visible": false, "title_keywords": [], "responsibilities": ["graphics", "project requirements", "creative ideas", "software", "comments", "designing", "review", "design", "quality", "communication", "hardware", "maintain", "animations", "visual"], "requirements": {"degrees": ["degree"], "majors": ["art", "design"], "languages": [], "language_level": [], "hard_skills": ["graphics", "3ds max", "cg", "maya", "plus", "3d modelling", "hardware", "visual effects", "sketchup"], "soft_skills": ["communication", "creative", "imaginative", "teamwork"], "languages_combined": []}, "experience_required": {"duration": ["at least 3 years"], "field": ["related", "design"]}}, {"job_id": "100003009027319", "location_code": "hk", "company": "The Hong Kong Ballet Ltd", "job_title": "Videographer / Editor (12 months contract)", "description": "frengers communications\u00a0is a HK Based creative agency. We help brands to tell their authentic stories, in an aesthetic way. To cope with our rapid growth, we sincerely invite high calibrate candidates to join our young & energetic team!\n\nCheck out our work: https://fb.com/frengershk // http://www.frengers.com.hk/\n\nWe are looking for great storyteller\u2026 to inspire & be inspired\n(For ACD/CD role, we welcome both Art-Base or Copy-Base creative)\n\nResponsibilities and Expectations:\n\nLeading the creative team to create HIGH-QUALITY creative work and generate INNOVATIVE ideas\nArticulate insights, DISTRUPTIVE angle & CRAFTSMANSHIP to generate the best communication solution\nWork closely with Account Servicing Team to develop IMPACTFUL CAMPAIGNS (Presentation Deck, Big Ideas, KVs & Videos, Activations, Social Campaigns, etc)\nManage & maintain GOOD RELATIONSHIPS with external parties including production partners, photographers and other suppliers\n\nBenefits:\n\nAnnual Incentive Trip, Book Subsidy, Team Building Activities, Birthday Leave, Medical, AND MOST IMPORTANTLY, an open & dynamic atmosphere to CREATE!\n\nRequirements:\n\nFun & open-minded\nStronger desire to launch impactful campaigns (IMC, Digital, Social)\nExperience in leading small team\nExperience in Creative/Digital/Social agency is preferred (6+ Years)\nGood at execution & also with strategic mindset\nFamiliar with latest digital marketing trend & technology innovations\nStrong communications & graphic sense, creative & detail-oriented\nSelf-motivated, multi-tasking and able to work independently\nImmediate available is preferred\n\nCandidates with more experience may be considered as Creative Director", "employment_types": ["Contract"], "selling_points": ["3 years+ experience in cinematography & editing", "Open to flexible working hours", "Experience in dance/ballet project is an advantage"], "locations": ["Causeway Bay"], "categories": ["Media & Advertising", "Others", "Photography / Video"], "post_time": "2022-01-06T09:43:31Z", "salary": {"currency": null, "max": null, "min": null, "period": "monthly", "term": null}, "salary_visible": false, "title_keywords": ["editor", "videographer"], "responsibilities": ["ideas", "external parties", "quality", "develop", "communication", "maintain"], "requirements": {"degrees": [], "majors": [], "languages": [], "language_level": [], "hard_skills": [], "soft_skills": [], "languages_combined": []}, "experience_required": {"duration": [], "field": []}}, {"job_id": "100003009033177", "location_code": "hk", "company": "Center Point Personnel", "job_title": "General Clerk [14.3k /HK Island/ 5 months contract]", "description": "Overview of job\u00a0\n\nGroupM is the world\u2019s largest media investment company and are a part of WPP. In fact, we are responsible for one in every three ads you see globally. We are currently looking for a\u00a0Performance Specialist\u00a0to join us. In this role, you will be responsible for delivering planning recommendations and ensuring smooth account coordination internally and externally with our clients.\u00a0\n\nAt GroupM APAC, our people are our strength, which is why fostering a culture of diversity and inclusion is important to us.\n\nReporting of the role\u00a0\n\nThis role reports to\u00a0Business Director.\n\n3 best things about the job:\n\nYou will be working on a leading brand in a Global Leading Media Agency.\nDynamic working environment.\nAbundant learning opportunities on digital & media aspects, locally and regionally.\n\nIn this role, your goals will be:\nIn three months:\n\nAbility to manage day-to-day digital media implementation\nBecome a trusted team member to ensure seamless execution of media plans across these media platforms\n\nIn six months:\n\nHave the ability to independently manage campaigns with little supervision\nBe able to proactively propose media solutions to drive effective results for the business\n\nIn 12 months:\n\nDevelop a media recommendation proposal independently\nHandle the implementation process independently\nPresent media review and evaluation deck to client\n\nWhat your day job looks like at GroupM:\n\nPlan, develop, present and execute online media campaigns in multiple channels including display, \u00a0mobile and social media\nWork close with other agency teams to establish and achieve specific media goals and objectives\nMonitor the results of all campaigns \u00a0and provide campaign reports with insights and suggested optimizations\nWork closely with dynamic and international team members to meet tight deadlines\n\nMinimum qualifications:\n\n1-2 years of relevant experience in a progressive media or interactive advertising agency or portal focused on digital marketing\u00a0\nExcellent project and client management skills\nFluent in Cantonese and English\nUnderstand\u00a0agency\u00a0process, team culture, and work flow.\nUnderstand the basic concepts of digital media and process of digital media campaigns.\n\nMore about GroupM\n\nGroupM leads and shapes media markets by delivering performance enhancing media products and services, powered by data and technology. Our global network agencies and businesses enable our people to work collaboratively across borders with the best in class, providing them the opportunity to accelerate their progress and development. We are not limited by teams or geographies; our scale and diverse range of clients lets us be more adventurous with our business and talent. We give our talent the space, support and tools to innovate and grow.\n\nDiscover more about GroupM at\u00a0www.groupm.com\nFollow @GroupMAPAC on Twitter\nFollow GroupM on LinkedIn -\u00a0https://www.linkedin.com/company/groupm\n\nAbout Hong Kong\n\nHong Kong\u2019s small yet highly dynamic and efficient media market means it gets to operate with agility. Its internet and digital penetration continues to grow year-on-year, and has the highest smartphone penetration in Asia Pacific at 87%, while tablet ownership clocks in at 57%. Hong Kong\u2019s digital market boasts a healthy mix of local, regional and global players, providing new opportunities in the media space.\n\nIf you want a future in media and communications, and believe in Hong Kong\u2019s belief of \u201cwork hard, play hard\u201d, there is clearly no place more vibrant, challenging and exciting than Hong Kong, where opportunities for you to innovate and grow are unparalleled.\u00a0", "employment_types": ["Full Time", "Contract"], "selling_points": [], "locations": ["Wan Chai Area"], "categories": ["Admin & HR", "Clerical / Admin Staff", "Media & Advertising", "Others", "Marketing / Public Relations", "Marketing - General / Support"], "post_time": "2022-01-08T13:15:36Z", "salary": {"currency": null, "max": null, "min": null, "period": "monthly", "term": null}, "salary_visible": false, "title_keywords": ["general clerk"], "responsibilities": ["reporting", "social media", "management", "advertising", "data", "review", "teams", "implementation", "monitor", "develop", "reports", "digital marketing", "coordination", "evaluation", "plan", "plans", "planning"], "requirements": {"degrees": [], "majors": [], "languages": ["cantonese", "english"], "language_level": ["fluent"], "hard_skills": ["small", "no", "basic", "mobile", "dynamic"], "soft_skills": ["efficient", "meet tight deadlines", "independently", "responsible", "focused", "diverse", "learning", "dynamic", "coordination", "smooth", "progressive", "team member"], "languages_combined": [{"language": "cantonese", "language_level": ["fluent"]}, {"language": "english", "language_level": ["fluent"]}]}, "experience_required": {"duration": ["1-2 years"], "field": ["relevant experience", "media", "advertising agency", "digital marketing"]}}, {"job_id": "100003009026106", "location_code": "hk", "company": "ConnectedGroup Limited", "job_title": "Senior Content Editor, Racing", "description": "frengers communications\u00a0is a HK Based creative agency. We help brands to tell their authentic stories, in an aesthetic way. To cope with our rapid growth, we sincerely invite high calibrate candidates to join our young & energetic team!\n\nCheck out our work: https://fb.com/frengershk // http://www.frengers.com.hk/\n\nWe are looking for great storyteller\u2026 to inspire & be inspired.\n\nResponsibilities and Expectations:\n\nSomeone who want to be a good art director instead of an average one\nIt means your work scope & of course skill required will go beyond ART\n\nBe part of the creative team to create HIGH-QUALITY creative work and generate INNOVATIVE ideas\nArticulate insights, DISTRUPTIVE angle & CRAFTSMANSHIP to generate the best communication solution\nWork closely with Account Servicing Team to develop IMPACTFUL VISUALS (Presentation Deck, Video, Key Visuals, Activations, Installation, Social Campaigns, etc)\nManage & maintain GOOD RELATIONSHIPS with external parties including production partners, photographers and other suppliers\n\nBenefits:\n\nAnnual Incentive Trip, Book Subsidy, Team Building Activities, Birthday Leave, Medical, AND MOST IMPORTANTLY, an open & dynamic atmosphere to CREATE!\n\nRequirements:\n\nFun & open-minded\nStronger desire to launch impactful campaigns (IMC, ATL, Social)\nEager to learn & experiment\nExperience in Creative Agency is a MUST\nProficiency in using MAC and graphic design software, including Photoshop & Illustrator (Nice-to-have: After Effect, Premiere, Final Cut Pro)\nAble to work & more importantly generate idea independently\nStrong communications & graphic sense, creative & detail-oriented\nSelf-motivated, multi-tasking and able to work independently\nImmediate available is HIGHLY PREFERED", "employment_types": ["Full Time", "Permanent"], "selling_points": ["Racing domain specialist", "Stable work environment", "Attractive total package"], "locations": ["Not Specified"], "categories": ["Media & Advertising", "Others", "Editorial / Journalism", "Broadcasting - TV / Radio"], "post_time": "2022-01-06T07:20:36Z", "salary": {"currency": null, "max": null, "min": null, "period": "monthly", "term": null}, "salary_visible": false, "title_keywords": ["content editor"], "responsibilities": ["installation", "ideas", "key visuals", "external parties", "quality", "develop", "communication", "maintain"], "requirements": {"degrees": [], "majors": [], "languages": [], "language_level": [], "hard_skills": [], "soft_skills": [], "languages_combined": []}, "experience_required": {"duration": [], "field": []}}]