[{"job_id": "100003009055849", "location_code": "hk", "company": "FWD Life Insurance Company (Bermuda) Limited", "job_title": "Claims, Employee Benefits (Several openings from Assistant Officer to Senior Manager)", "description": "Established in Asia in 2013 with a trailblazer mentality, FWD is the primary insurance business of investment group, Pacific Century Group (PCG), with minority shareholders Swiss Re Group, GIC Ventures, RRJ Capital and Hopu Investments.\n\nFWD spans 10 markets in Asia including Hong Kong SAR & Macau SAR, Thailand, Indonesia, the Philippines, Singapore, Vietnam, Japan, Malaysia and Cambodia. In Hong Kong, FWD offers life and medical insurance, general insurance, employee benefits, and financial planning. We focus on creating fresh customer experiences and making the insurance journey simpler, faster and smoother, with innovative propositions and easy-to-understand products, supported by digital technology. Through this customer-led approach, FWD aims to be a leading pan-Asian insurer by changing the way people feel about insurance.\n\nIf you are looking for a company where can fuel your inspiration and cultivate your expertise, join us on our exciting journey.\n\nThe Purpose:\n\nTo manage the operations of the medical pre-authorization approval claims and ensure that the operation of panel doctor networks are running smoothly plus administer day-to-day claim functions efficiently and accurately. \u00a0\n\nThe Job:\n\nProvide services on pre-authorization approval and manage panel doctor networks on inpatient and outpatient\nHandle all medical claims assessment and investigation\nProvide quality services to designated major accounts including maintaining and ensuring the SLA\nSupervise team and perform duties allocation among the subordinates\nProvide training on medical claims knowledge to internal staff\nAssist in system development and enhancement project\nPerform claims reporting and carry out other duties assigned by management\n\nThe Person:\n\nDegree holder\nExperience in panel doctor network management and medical claims\nQualification of FLMI is an advantage\nMedical knowledge qualification is an advantage\nProficiency in MS Office (Word, Excel and PowerPoint)\nGood spoken and written in English and Chinese\nGood management, communication and coaching skills\n\nCandidates' experience will be matched to relevant job level accordingly.\n\nWe offer 5-day work, 20-22 days annual leaves, excellent learning & development opportunities and an attractive package to the right candidate.\n\nInformation collected will be treated in strict confidence and used solely for recruitment purpose. The company will retain all applications no longer than 24 months of which will be destroyed thereafter. When there are vacancies in any of our subsidiaries, holding companies, associated or affiliated companies of, or companies controlled by, or under common control with the Company during that period, we may transfer your application to them for consideration of employment. We are an equal opportunity employer. We do not discriminate on the basis of race, sex, disability or family status in employment process.", "employment_types": ["Full Time"], "selling_points": ["Handle all medical claims assessment", "Assist in system development project", "Perform claims reporting"], "locations": ["Sheung Wan"], "categories": ["Insurance", "Claims Officer"], "post_time": "2022-01-18T03:00:43Z", "salary": {"currency": null, "max": null, "min": null, "period": "monthly", "term": null}, "salary_visible": false, "title_keywords": ["assistant officer", "senior manager"], "responsibilities": [], "requirements": {"degrees": [], "majors": [], "languages": [], "language_level": [], "hard_skills": [], "soft_skills": [], "languages_combined": []}, "experience_required": {"duration": [], "field": []}}, {"job_id": "100003009055347", "location_code": "hk", "company": "ZIM Integrated Shipping Services Ltd", "job_title": "Claims Deputy Manager", "description": "Key Responsibilities\n\nManage enquiries from agencies and customers in a professional manner\nHandle accident involved and follow up with all related ports and concerned parties for immediate remedial actions\nExamine title of claimant and correspond with overseas agents and claimants to obtain documentary evidence\nAnalyze information gathered from investigation and surveyors\u2019 findings and recommendations\nCollect relevant evidences for substantiating involvement of 3rd party liability\nMonitor unclaimed cargo and compile monthly report to headquarter, and analyze the data for further follow up with local agencies\nOther matter related to claims handling and marine casualties/events, including data management in the system, contracts reviewing, etc.\n\nWho we are looking for\n\n5+ years of experience in claims & insurance with good knowledge in liner shipping industry\nUniversity degree or above in Logistics industry / Shipping / Insurance or Management\nGood command of spoken and written English and Mandarin\nProficient in computer skills (MS Word, Excel & PowerPoint and Chinese word processing)\nA good team player with excellent communication and interpersonal skills\nCandidates with less experience but having high potential would be also considered\n\nWe offer\n\nExcellent opportunities for advancement with regional exposure\nCompetitive salary package\n5-Days Work\n18 - 20 days Annual Leave\nDouble Pay\nPerformance Bonus\nMedical & Dental Insurance\nLife Insurance\nBirthday Gifts\nMarriage Leave\nPaternity Leave\nWork from home arrangement\n\nInterested parties please share with us your latest resume showing current and expected remuneration package.", "employment_types": ["Full Time", "Permanent"], "selling_points": ["Claims handling, marine casualties / events", "Excellent opportunities for advancement", "Work from home arrangement"], "locations": ["Kwun Tong"], "categories": ["Transportation & Logistics", "Others", "Insurance", "Claims Officer"], "post_time": "2022-01-18T02:24:34Z", "salary": {"currency": null, "max": null, "min": null, "period": "monthly", "term": null}, "salary_visible": false, "title_keywords": ["deputy manager"], "responsibilities": ["management", "shipping", "data", "contracts", "monitor", "professional manner", "investigation", "communication", "logistics", "monthly report", "insurance"], "requirements": {"degrees": ["degree or above"], "majors": ["insurance"], "languages": ["english", "chinese", "mandarin"], "language_level": ["good command", "proficient"], "hard_skills": ["excel", "data management", "chinese word processing", "powerpoint", "computer skills", "ms word"], "soft_skills": ["good team player", "communication and interpersonal skills"], "languages_combined": [{"language": "english", "language_level": ["good command"]}, {"language": "chinese", "language_level": ["proficient"]}, {"language": "mandarin", "language_level": ["good command"]}]}, "experience_required": {"duration": ["5+ years"], "field": ["insurance", "shipping industry"]}}, {"job_id": "100003009049631", "location_code": "hk", "company": "CLP Power Hong Kong Limited", "job_title": "Insurance & Claims Specialist [Ref. CLPP-I&C-I&CS]", "description": "We are now looking for a high calibre professional to join our Insurance & Claims team of CLP Power Hong Kong Limited.\u00a0\n\nReporting to Insurance & Claims Manager, the appointee will be responsible for the following duties:\n\nProfessionally implement the agreed insurance strategies / policies and design the appropriate insurance solutions to achieve cost effective annual insurance programmes of generation assets in Hong Kong and Southern China & those other than Scheme of Control business in Hong Kong and meet their respective project insurance requirements\nAct independently to address the various insurance needs of internal clients based on the agreed retained risk profile of the business units.\nWorking with insurance consultants in areas of risk and liability assessments, contractual risk analysis and associated insurance requirements\nCarry out policy vetting of insurance documents within delegated authority independently applying in-depth insurance knowledge for proper asset and liability protection of the internal clients, by ensuring that the products purchased addresses the insurance needs of the business units\nProactively analyze and review the various insurance contract provisions independently for the internal clients in Hong Kong in a professional manner and in accordance with the broad insurance policy\nSupport in insurance strategy formation of group synergy\n\nRequirements:\n\nBachelor Degree or above; insurance, engineering or related discipline will be an advantage\nAssociate of Chartered Insurance Institute or Senior Associate in Australian and New Zealand Institute of Insurance and Finance, or equivalent\nA minimum of 6 years\u2019 relevant work experience in corporate / industrial insurance, with at least 3 years in insurance broking / underwriting\nStrong interpersonal and communication skills\nConversant with the latest insurance market practices and local insurance requirements in Hong Kong & Mainland China\nProficient in PC applications e.g. Microsoft Word, Excel, PowerPoint\nGood command of spoken and written English and Chinese (including Putonghua)\nPlease apply by\u00a0clicking the button \"Apply Now\"\u00a0\u00a0giving a detailed C.V., including career history, major achievements and personal attributes on or before 8\u00a0February 2022.\n\n\nApplicants not invited for interview within 6 weeks from the closing date may assume their applications unsuccessful.\n\nInformation provided will be for recruitment purpose within the CLP Group and only short-listed candidates will be contacted. We comply with all applicable laws and regulations of HKSAR in handling applications. For details of the Personal Information Collection Statement, please visit our website: https://clp.to/engPICS\n\nFor further information on our company, please visit our website:\n\nhttps://www.clpgroup.com/", "employment_types": ["Full Time", "Permanent"], "selling_points": [], "locations": ["Hung Hom"], "categories": ["Insurance", "Claims Officer", "Others"], "post_time": "2022-01-17T16:20:50Z", "salary": {"currency": null, "max": null, "min": null, "period": "monthly", "term": null}, "salary_visible": false, "title_keywords": ["specialist"], "responsibilities": ["regulations", "reporting", "cost", "control", "policies", "review", "professional manner", "website", "design", "communication", "recruitment", "risk analysis", "insurance"], "requirements": {"degrees": ["degree or above", "bachelor"], "majors": [], "languages": ["putonghua", "english", "chinese"], "language_level": ["good command"], "hard_skills": ["excel", "microsoft word", "analysis", "scheme", "powerpoint", "pc applications", "c"], "soft_skills": ["communication skills", "independently", "responsible", "interpersonal", "detailed"], "languages_combined": [{"language": "putonghua", "language_level": ["good command"]}, {"language": "english", "language_level": ["good command"]}, {"language": "chinese", "language_level": ["good command"]}]}, "experience_required": {"duration": ["at least 3 years", "minimum of 6 years"], "field": ["underwriting", "insurance"]}}, {"job_id": "100003009046871", "location_code": "hk", "company": "Dr. Vio & Partners Limited", "job_title": "Medical Claims/Expenses Officer", "description": "Job Duties:\n\n\nHandle out-patient and in-patient precertification or case approvals;\nLiaise with doctors, other service providers, and internal business units to gather information pertinent to a particular case;\nConduct case reviews/follow up if necessary;\nHandle medical claims related issues and enquiries;\nDeliver professional customer service to the network, clients, and other service providers;\nTake on other assignments as required\u00a0\n\nRequirements & Attributes:\n\n\nHolder of Bachelor\u2019s Degree;\n3 years of experience in health care management, medical or insurance claims;\nGood communication skills in both English and Chinese including Putonghua;\nExcellent customer service skills;\nProficiency in\u00a0Microsoft\u00a0Office;\nCandidates with higher qualifications or more experience will be considered for the position of Senior Officer;\nImmediately available is an advantage\n\nWe offer regular working hours, friendly work environment, and a competitive remuneration package to the right candidate commensurate with his/her qualifications and working experience.\u00a0 Fringe benefits include medical schemes (including eligible dependants), discretionary performance-based bonus, birthday leave, etc.\n\n\nApplicants should send their C. V. with expected salary & availability to HR at DoctorVio.com\u00a0or by clicking \"Apply Now\".\n", "employment_types": ["Full Time", "Permanent"], "selling_points": [], "locations": ["Sheung Wan"], "categories": ["Insurance", "Claims Officer", "Medical Services", "Others"], "post_time": "2022-01-16T21:50:17Z", "salary": {"currency": null, "max": null, "min": null, "period": "monthly", "term": null}, "salary_visible": false, "title_keywords": ["officer"], "responsibilities": ["liaise with", "customer service"], "requirements": {"degrees": ["degree", "bachelor"], "majors": [], "languages": ["putonghua", "english", "chinese"], "language_level": ["good"], "hard_skills": ["microsoft office"], "soft_skills": ["communication skills", "friendly", "customer service skills"], "languages_combined": [{"language": "putonghua", "language_level": ["good"]}, {"language": "english", "language_level": ["good"]}, {"language": "chinese", "language_level": ["good"]}]}, "experience_required": {"duration": ["3 years"], "field": ["health care", "insurance", "management", "medical"]}}, {"job_id": "100003009055741", "location_code": "hk", "company": "Robert Walters (HK)", "job_title": "Claims Specialist", "description": "We have an in-house opportunity for an experienced claims professional who is outcomes driven and passionate about risk and claims management. This role will work with a small but focused insurance team and perform a critical role in managing, investigating, and processing insurance claims and appeals. The successful candidate will also be responsible for providing customer service to internal clients in the area of risk management.\n\nResponsibilities\n\nAdministration and renewals of insurance policies, drafting/ distribution of insurance certificates\nLiaise with insurance brokers, lawyers and others involved in the management of claims\nProcurement of project specific insurances and development of bespoke insurance solutions\nPrepare claim reports and analysis of claim data\nAnswer enquiries and provide insurance advices to internal stakeholders\nAssist in ad-hoc duties as assigned\n\nRequirements\n\nDegree qualified\nAt least 4 years of experience in claims servicing\nA keen interest in providing customer service and understanding customer needs\nStrong interpersonal and communication skills\nExcellent command in spoken and written English, Cantonese and Mandarin\nAttention to detail, accuracy and be able to work under pressure and meet deadlines\nPro-active, mature, well-organised and an excellent team player", "employment_types": ["Full Time", "Permanent"], "selling_points": ["in-house insurance role", "blue chip company", "risk and liability"], "locations": ["Not Specified"], "categories": ["Insurance", "Claims Officer", "Others", "Others", "Others"], "post_time": "2022-01-18T02:54:37Z", "salary": {"currency": "HKD", "max": 44999, "min": 30000, "period": "monthly", "term": null}, "salary_visible": true, "title_keywords": ["specialist"], "responsibilities": ["management", "data", "policies", "analysis", "reports", "ad-hoc duties", "liaise with", "insurances", "insurance", "administration"], "requirements": {"degrees": ["degree"], "majors": [], "languages": ["cantonese", "english", "mandarin"], "language_level": ["excellent"], "hard_skills": [], "soft_skills": ["communication skills", "keen", "mature", "customer service", "team player", "attention to detail", "pro-active", "well-organised", "meet deadlines", "interpersonal", "work under pressure"], "languages_combined": [{"language": "cantonese", "language_level": ["excellent"]}, {"language": "english", "language_level": ["excellent"]}, {"language": "mandarin", "language_level": ["excellent"]}]}, "experience_required": {"duration": ["at least 4 years"], "field": []}}, {"job_id": "100003009051828", "location_code": "hk", "company": "Chubb Life Insurance Company Ltd.", "job_title": "Assistant Manager, Claims", "description": "Job Duties:\n\nParticipate in various projects on the development, maintenance and enhancement of operations systems\nPrepare regular claims management reports and analysis\nAssist to handle the processing of claim assessment and policy transactions for claim purpose\nHandle enquiries from agency and other parties\nMaintain the service standard and ensure the quality of work of the team\nSupport ad hoc projects as requested\nRequirements:\n\nUniversity graduate in any disciplines\nProfessional qualification of FLMI or partial fulfillment of professional qualifications is preferred\nMinimum 5 years working experience in insurance claims and/or underwriting\nIndependent and with high degree of responsibility\nProficient in MS Word, Excel, Powerpointand Chinese Word Processing\nGood command of both spoken and written English and Chinese\nCandidates with less experience will be considered as Senior Claims Executive \u00a0\u00a0 \u00a0\nCareers at Chubb2A Career with Chubb offers varied and interesting work, multinational exposure and freedom and opportunity to develop in a challenging professional environment.\u00a0 A competitive compensation package will be offered to the successful candidate. \u00a0\nTo register your interest, you may send us your application with academic qualifications, career experience, existing and expected salary and contact information, in complete confidence to our Human Resources Department, 33/F, Windsor House, 311 Gloucester Road, Causeway Bay, Hong Kong or by clicking \"Apply Now\".\u00a0 Before doing so, please read and understand our Company\u2019s Privacy Policy and below Personal Information Collection Statement.\nChubb Life Insurance Company Ltd. (Incorporated in Bermuda with Limited Liability)\n\n\n******************************************************************************************\n\nPERSONAL INFORMATION COLLECTION STATEMENT\n\nYou acknowledge and understand that, before sending your application to us, you are required to read, understand and consent to the Company\u2019s data practices described in this Personal Information Collection Statement (\u201cPICS\u201d).\n\nAll data provided will be treated in STRICT CONFIDENCE and subject to this PICS.\n\nThe personal data collected during recruitment process may be used, processed, or stored by the Company for:-\nassessing your suitability to the position for which you have applied; and/or\nnegotiating with and making offers of employment.\nYour application may not be considered or the outcome of your application may be influenced if you fail to provide certain information and/or data as requested.\n\nApplicants who are not contacted within four weeks may consider their applications unsuccessful. For the personal data of the unsuccessful applicant, the Company may also retain, disclose or transfer his/her personal data to the companies within the group of which the Company is a subsidiary (the \u201cGroup Companies\u201d) for:-\nfuture recruitment purposes; and/or\nassessing your suitability for a vacancy within the Group Companies.\nIt is the Company\u2019s policy that the personal data of the unsuccessful applicant shall be kept and stored by our Company for a period of not more than two years.\u00a0 The Company will also disclose or transfer his/her personal data to the Group Companies within the prescribed time.\u00a0 When doing so, the Company will use practical endeavours to ensure proper security and erasure of the data.\n\nYou are entitled to request access to or make amendments to your own personal data kept by the Company by writing to the Data Protection Officer of the Human Resources Department of the Company at 33/F., Windsor House, 311 Gloucester Road, Causeway Bay, Hong Kong Special Administrative Region. A reasonable fee may be charged by the Company for processing of the access request.", "employment_types": ["Full Time", "Permanent"], "selling_points": ["Prepare regular claims management reports", "Handle enquiries from agency and other parties", "Minimum 5 years working experience"], "locations": ["Not Specified"], "categories": ["Insurance", "Claims Officer", "Underwriter", "Others"], "post_time": "2022-01-17T01:18:27Z", "salary": {"currency": null, "max": null, "min": null, "period": "monthly", "term": null}, "salary_visible": false, "title_keywords": ["assistant manager,"], "responsibilities": ["service standard", "maintenance", "operations", "analysis", "systems", "quality", "transactions", "handle enquiries", "management reports", "maintain", "ad hoc projects"], "requirements": {"degrees": ["university graduate", "degree"], "majors": ["any disciplines"], "languages": ["english", "chinese"], "language_level": ["good command", "proficient"], "hard_skills": ["excel", "chinese word processing", "professional qualifications", "make", "processing", "ms word"], "soft_skills": ["confidence", "independent"], "languages_combined": [{"language": "english", "language_level": ["good command"]}, {"language": "chinese", "language_level": ["good command", "proficient"]}]}, "experience_required": {"duration": ["minimum 5 years"], "field": ["underwriting", "insurance", "human resources"]}}, {"job_id": "100003009051829", "location_code": "hk", "company": "Chubb Life Insurance Company Ltd.", "job_title": "Senior Claims Executive - Life Insurance", "description": "Job Duties:\nAssist the Assistant Manager in day-to-day claim operations including maintenance of service standard and ensuring quality of work defined by the Company.\nProcessing of minor claims including assessment, follow up on insufficient / outstanding information, claim payment requisition and correspondence issuing\nAssess, recommend actions and approve claims subject to authority assigned\nHandle the system transactions in relation to claim processing.\nDraft and check out-going correspondence.\nCommunicate with reinsurers, lawyers, other companies, doctors and /or investigator in connection with claim processing\nHandle enquiries (walk-in/telephone) from agents and customers in claims matters\nHandle enquiries from other companies or organization regarding client\u2019s claim record\nAssist in development, maintenance & enhancement of workflow system and Claim administration system\nincluding the user requirement write-up and user testing, arranging implementation, training and write up of procedural manual, etc..\nAssist for day-to-day administration of the claim administration system\nResponsible for maintenance of administrative manuals and other information materials available on LA Portal opened to agency forces.\nAssist in preparation and verification of reinsurance recovery records with Financial Services Department according to the risk share arrangement as specified in the reinsurance treaty with different reinsurers\nGive feedback on claims process, procedure, and manual in order to improve efficiency and quality of claims operation.\nParticipate in ad hoc assigned projects.\nExperience & Qualifications:\nDegree holder in any disciplines\nFLMI is an advantage but not a must\nLife insurance claims experience\u00a0\nMinimum 2 years solid experience in life insurance company, preferably in Operations/Business Analysis/Project Management function\nExperience in handling printing solution/correspondence design is a plus\nExcellent problem solving skills\nGood PC skills and MS Office application\nGood communication, interpersonal and analytical skills\nA Career with Chubb offers varied and interesting work, multinational exposure and freedom and opportunity to develop in a challenging professional environment.\u00a0 A competitive compensation package will be offered to the successful candidate.\u00a0 \u00a0\nTo register your interest, you may send us your application with academic qualifications, career experience, existing and expected salary and contact information, in complete confidence to our Human Resources Department, 33/F, Windsor House, 311 Gloucester Road, Causeway Bay, Hong Kong or via email by clicking \"Apply Now\".\u00a0 Before doing so, please read and understand our Company\u2019s Privacy Policy and below Personal Information Collection Statement. \u00a0\nChubb Life Insurance Company Ltd. (Incorporated in Bermuda with Limited Liability)\n\n******************************************************************************************\nPERSONAL INFORMATION COLLECTION STATEMENT\nYou acknowledge and understand that, before sending your application to us, you are required to read, understand and consent to the Company\u2019s data practices described in this Personal Information Collection Statement (\u201cPICS\u201d). \u00a0\nAll data provided will be treated in STRICT CONFIDENCE and subject to this PICS.\nThe personal data collected during recruitment process may be used, processed, or stored by the Company for:-\na.\u00a0\u00a0 \u00a0assessing your suitability to the position for which you have applied; and/or\nb.\u00a0\u00a0 \u00a0negotiating with and making offers of employment.\nYour application may not be considered or the outcome of your application may be influenced if you fail to provide certain information and/or data as requested.\nApplicants who are not contacted within four weeks may consider their applications unsuccessful. For the personal data of the unsuccessful applicant, the Company may also retain, disclose or transfer his/her personal data to the companies within the group of which the Company is a subsidiary (the \u201cGroup Companies\u201d) for:-\na.\u00a0\u00a0 \u00a0future recruitment purposes; and/or\nb.\u00a0\u00a0 \u00a0assessing your suitability for a vacancy within the Group Companies.\nIt is the Company\u2019s policy that the personal data of the unsuccessful applicant shall be kept and stored by our Company for a period of not more than two years.\u00a0 The Company will also disclose or transfer his/her personal data to the Group Companies within the prescribed time.\u00a0 When doing so, the Company will use practical endeavours to ensure proper security and erasure of the data.\nYou are entitled to request access to or make amendments to your own personal data kept by the Company by writing to the Data Protection Officer of the Human Resources Department of the Company at 33/F., Windsor House, 311 Gloucester Road, Causeway Bay, Hong Kong Special Administrative Region. A reasonable fee may be charged by the Company for processing of the access request.\n\n*******************************************************************************************\n", "employment_types": ["Full Time", "Permanent"], "selling_points": ["Life claims experience", "Degree holder in any disciplines", "Minimum 2 years solid experience"], "locations": ["Causeway Bay"], "categories": ["Insurance", "Claims Officer", "Underwriter", "Others"], "post_time": "2022-01-17T01:18:28Z", "salary": {"currency": null, "max": null, "min": null, "period": null, "term": null}, "salary_visible": false, "title_keywords": ["executive"], "responsibilities": ["service standard", "data", "operations", "quality", "transactions", "design", "communication", "payment", "personal data", "administration", "user requirement", "ad hoc", "implementation", "testing", "develop", "handle enquiries", "give feedback", "contact", "recruitment process", "communicate with", "maintenance", "project management", "recruitment", "business analysis", "insurance"], "requirements": {"degrees": ["degree holder"], "majors": ["any disciplines"], "languages": [], "language_level": [], "hard_skills": ["pc skills", "plus", "maintenance", "analysis", "analytical skills", "project management", "make", "problem solving skills", "processing", "ms office"], "soft_skills": ["confidence", "responsible", "analytical skills", "communication", "project management", "problem solving skills", "interpersonal"], "languages_combined": []}, "experience_required": {"duration": ["minimum 2 years"], "field": ["design", "project management", "life insurance company", "business analysis", "insurance", "human resources"]}}, {"job_id": "100003009055138", "location_code": "hk", "company": "AMG Wealth Management Limited", "job_title": "Officer / Senior Officer \u2013 Operations", "description": "Job Responsibilities:\n\n\nLiaise with different internal departments and external parties for business support process\u00a0\nSupervise and support for record keeping purpose, such as data entry, scanning and filing etc.\nLiaise with financial advisers on pending cases and service requests\nHandle financial advisers' enquiries and provide professional and accurate response with service standard\nAssist in preparation of monthly operations reports for management purposes\n\nJob Requirements:\n\n\nDiploma in Business Administration or other related disciplines\nMinimum 2 years working experience in the business support and administration area\nRelevant IFA working experience is a definite plus\nGood command of both spoken and written English and Chinese. Fluent in Putonghua is an advantage\nCandidate with more experience will be considered as Senior Officer\nSelf-motivated, independent and able to work under pressure\nExcellent presentation, communication and interpersonal skills\n\nInterested parties, please send full resume by clicking \"Apply Now\" or mail to Human Resource Department at 40/F, 118 Connaught Road West, HONG KONG.\n\n\nPersonal data collected will be used for recruitment purpose only.", "employment_types": ["Full Time", "Permanent"], "selling_points": ["Medical & Dental Insurance & Birthday Leave", "Comprehensive Training", "Promotion Opportunity"], "locations": ["Sai Ying Pun"], "categories": ["Insurance", "Claims Officer", "Insurance Agent / Broker", "Banking / Finance", "Order Processing & Operation / Settlement"], "post_time": "2022-01-18T01:25:03Z", "salary": {"currency": null, "max": null, "min": null, "period": "monthly", "term": null}, "salary_visible": false, "title_keywords": ["officer", "senior officer", "operations"], "responsibilities": ["scanning", "management", "service standard", "data entry", "operations", "external parties", "reports", "liaise with"], "requirements": {"degrees": ["diploma"], "majors": ["related disciplines", "business administration"], "languages": ["putonghua", "english", "chinese"], "language_level": ["advantage", "good command", "fluent"], "hard_skills": ["plus"], "soft_skills": ["self-motivated", "independent", "communication and interpersonal skills", "presentation", "work under pressure"], "languages_combined": [{"language": "putonghua", "language_level": ["fluent", "advantage"]}, {"language": "english", "language_level": ["good command"]}, {"language": "chinese", "language_level": ["good command"]}]}, "experience_required": {"duration": ["minimum 2 years"], "field": ["business support", "administration"]}}, {"job_id": "100003009052214", "location_code": "hk", "company": "Aon Services Hong Kong Limited \u6021\u5b89\u670d\u52d9\u9999\u6e2f\u6709\u9650\u516c\u53f8", "job_title": "Account Manager - Claims Services", "description": "We\u2019re hiring!\n\nAon is currently recruiting an Account Manager - Claims Services\u00a0to join our team in Hong Kong.\n\nAbout Aon\n\nHeadquartered in London, Aon Plc is a leading global professional services firm providing a broad range of risk, retirement and health solutions. Our 50,000 colleagues in 120 countries empower results for clients by using proprietary data and analytics to deliver insights that reduce volatility and improve performance.\n\nAt Aon, you\u2019ll be part of a team which will support and inspire you and provide the opportunities and resources to develop your skills. It\u2019s an environment which encourages you to achieve your best - together we\u2019ll empower results.\u00a0\n\nResponsibilities:\n\nManage claims for clients, including some with operations on a global scale\nHandle all classes of commercial lines insurance (EC, PDBI, PAR, Motor, PPL, Marine Cargo, CAR, etc.)\nServe internal business units and clients at operational and senior management level requiring liaising and\ncoordinating with insurers and third party services providers such as loss adjusters, rehabilitation managers and\nlawyers and our network offices in different countries\nManage and analyse claims data and advising clients on risk management improvement measures\nDevelop junior claims staff\n\nRequirements:\u00a0\n\nMinimum five years claims handling experience, in insurance broking firm preferred\nIIQE qualified or holder of ACII or ANZIIF (Associate) preferred\nSome supervisory experience is preferable\nTeam work is required whilst being proactive and working independently\nAbility to understand and apply data analysis to risk management issues\nMust be able to work with data and present information in clear manner\nGood command of written and spoken English and Chinese (Cantonese and Putonghua)\nGood computer skills including MS Word, Excel, Powerpoint\n\nHow to Apply\n\nYour opportunity to empower results could start right here. Make your mark and apply online today with a brief covering letter and your resume, sharing relevant achievements for this position.\n\nWe Offer You\n\nA competitive total rewards package, continuing education & training, and tremendous potential with a growing worldwide organization.\n\nOur Colleague Experience\n\nEvery day, our colleagues make a difference, work with the best, own their potential, and value one another. Together, we share this one purpose: to empower economic and human possibility around the world. This unifying goal is at the heart of our identity, and it lives in everything we do. To learn more about our colleague experience, visit Aon Colleague Experience.\n\nAon is an equal opportunities employer. We are committed to creating a winning and inclusive culture where everyone feels valued and has opportunities for growth and development.", "employment_types": ["Full Time", "Permanent"], "selling_points": [], "locations": ["Quarry Bay"], "categories": ["Insurance", "Claims Officer", "Underwriter", "Others"], "post_time": "2022-01-17T02:30:32Z", "salary": {"currency": null, "max": null, "min": null, "period": "monthly", "term": null}, "salary_visible": false, "title_keywords": ["account manager"], "responsibilities": ["rehabilitation", "management", "data", "operations", "develop", "senior management", "insurance", "third party", "analyse"], "requirements": {"degrees": [], "majors": [], "languages": ["cantonese", "putonghua", "english", "chinese"], "language_level": ["good command"], "hard_skills": ["excel", "iiqe", "analysis", "powerpoint", "make", "computer skills", "ms word"], "soft_skills": ["clear", "proactive", "independently"], "languages_combined": [{"language": "cantonese", "language_level": ["good command"]}, {"language": "putonghua", "language_level": ["good command"]}, {"language": "english", "language_level": ["good command"]}, {"language": "chinese", "language_level": ["good command"]}]}, "experience_required": {"duration": ["minimum five years"], "field": ["insurance", "supervisory experience"]}}, {"job_id": "100003009046521", "location_code": "hk", "company": "Sun Hung Kai Properties Ltd", "job_title": "ASSISTANT OFFICER \u2013 INSURANCE CLAIMS", "description": "Requirements:\n\nBachelor\u2019s degree\n2-3 years\u2019 relevant experience in insurance field\nProven English proficiency and good command of Putonghua\nFamiliar with PC software e.g. MS Word, Excel, PowerPoint & Chinese Word Processing\n\nResponsibilities:\n\nResponsible for handling insurance claims, including verify claims documents, prepare payments, follow up with claimants and business partners, prepare reports & statistics, etc.\u00a0\n\nGood remuneration and attractive fringe benefits will be offered to the successful applicant. Interested parties please apply with full resume, present and expected salary, available date by clicking \u201cApply Now\u201d.\n\nFor further information, please visit our company website: http://www.shkp.com/.\n\n\nWe are an equal opportunity employer and welcome applications from all qualified candidates. All personal data collected will be used for recruitment purpose only.\u00a0 Applicants not hearing from us within 3 months may consider their applications unsuccessful.\u00a0 All personal data collected will be destroyed within 24 months.", "employment_types": ["Full Time", "Permanent"], "selling_points": ["Bachelor\u2019s degree with 2-3 yrs\u2019 exp in insurance", "Handling insurance claims eg verify claims doc", "Prepare reports & statistics"], "locations": ["Wan Chai"], "categories": ["Insurance", "Claims Officer", "Others"], "post_time": "2022-01-13T13:02:34Z", "salary": {"currency": null, "max": null, "min": null, "period": null, "term": null}, "salary_visible": false, "title_keywords": ["assistant officer"], "responsibilities": ["prepare reports", "insurance", "payments"], "requirements": {"degrees": ["degree", "bachelor"], "majors": [], "languages": ["putonghua", "english", "chinese"], "language_level": ["proficiency", "good command"], "hard_skills": ["excel", "chinese word processing", "powerpoint", "pc", "ms word"], "soft_skills": [], "languages_combined": [{"language": "putonghua", "language_level": ["proficiency", "good command"]}, {"language": "english", "language_level": ["proficiency", "good command"]}, {"language": "chinese", "language_level": []}]}, "experience_required": {"duration": ["2-3 years"], "field": ["insurance", "relevant experience"]}}, {"job_id": "100003009055148", "location_code": "hk", "company": "BUPA Asia Limited", "job_title": "Administrative officer, Medical Underwriting", "description": "Accountabilities and Activities\n\n\nProvide administrative duties of Medical Underwriting team in accordance with the standard operating procedure of the department, including:\n\nPreparing underwriting letters\nHandling incoming mails and documents\nFiling of documents and maintaining relevant records\nUpdating system record\nAssisting in preparation of reports\nPrioritizing workloads effectively; working to team SLA\u2019s whilst maintaining quality of work\nBeing compliant with guidelines and SOPs, escalate when (and only when) necessary\nPerforms other related administrative duties as required\n\nTo be considered for this role, you should ideally have\n\n\n\nHolders of Bachelor degree or Diploma\nProficient in MS Excel, Word, Outlook and Chinese word processing\n1 year of working experience in clerical role and in insurance industry is preferred\nAttentive to details and willing to learn\n\n\nBupa offers 5 days\u2019 work per week and comprehensive remuneration packages including base salary, study assistance plan, company pension plan, life and medical benefit, dental benefit, annual leave, examination leave, etc.\n\nBupa is an equal opportunity employer and welcomes applications from qualified candidates. Information provided will be treated in strict confidence and only be used for consideration of application with Bupa.\n\nPersonal data collected will be used for recruitment purposes only. Only candidates selected for interviews will be contacted. Bupa will be in touch for any opportunities that matches your profile. All personal data of unsuccessful application will be destroyed 24 months from the date of receiving the application.", "employment_types": ["Full Time", "Contract"], "selling_points": ["Holders of Bachelor degree or Diploma", "Excellent career development & working environment", "Competitive benefits package"], "locations": ["Not Specified"], "categories": ["Beauty Care / Health", "Others", "Insurance", "Claims Officer", "Underwriter"], "post_time": "2022-01-18T01:27:59Z", "salary": {"currency": null, "max": null, "min": null, "period": "monthly", "term": null}, "salary_visible": false, "title_keywords": ["administrative officer"], "responsibilities": ["maintaining", "guidelines", "quality", "letters", "administrative duties", "reports", "sops", "plan", "recruitment", "personal data", "insurance"], "requirements": {"degrees": ["diploma", "degree", "bachelor"], "majors": [], "languages": ["chinese"], "language_level": ["proficient"], "hard_skills": ["chinese word processing", "word", "sla", "ms excel", "outlook"], "soft_skills": ["confidence", "attentive to details", "willing to learn", "comprehensive", "prioritizing"], "languages_combined": [{"language": "chinese", "language_level": ["proficient"]}]}, "experience_required": {"duration": ["1 year"], "field": ["insurance industry", "clerical"]}}, {"job_id": "100003009052741", "location_code": "hk", "company": "Quality HealthCare Medical Services Ltd", "job_title": "Assistant Officer, Approval Service", "description": "Responsibilities:\n\nAs a part of Well Link Insurance, he/she will promote our brand vision/company values and comply with company\u2019s working practices and business ethics\nProvide high-quality claims services for all line of business that in line with the company objective and department goals\nTo analyze and identify specific trends in controlling claim costs effectively and closely work with inter-departments across functions\nResponsible for managing Personal and Commercial lines claims in line with the policies and comply with relevant protocols in the Claims Manual\u00a0\u00a0\nEnsure fast and fair settlement of claims from customers and the third party claimants with the pre-defined authority limit\nDeliver the highest level of consistent, quality claims services to our customers and come across as knowledgeable, friendly and customer oriented\nHandle the claims hotline\nEnsure to make accurate claims reserving and regular review of the outstanding cases\u00a0\nClaim document management including verification, indexing, reserving, payment and fillings etc\nPerform ad hoc duties as assigned by Senior\nRequirements:\n\nProfessional qualification such as IIQE/ANZIIF/ACII and related discipline\nMinimum 2-3 years relevant experience in handling general insurance claims\nGood technical and negotiation skills\u00a0\nExcellent command of written and spoken in Chinese, English and proficient in Mandarin\nMust be proficient with Word, Excel, PowerPoint\nEffective interpersonal & communication skills with internal\nAble to work independently and work under pressure\nWe are an equal opportunity employer and welcome applications from all qualified candidates.\n\nPlease send your full resume stating present and expected salary to\u00a0Human Resources Manager by clicking APPLY NOW.\nAll\u00a0 personal data provided will be treated in the strictest confidence and used\u00a0only for recruitment related purposes.\u00a0 All personal data will be\u00a0destroyed after 6 months of submission.\nOnly short listed candidates will be contacted.", "employment_types": ["Full Time", "Permanent"], "selling_points": ["Assist in approval processing", "Answer provider enquiry hotline", "Case follow up"], "locations": ["Kowloon Bay"], "categories": ["Insurance", "Claims Officer", "Medical Services", "Nursing", "Others"], "post_time": "2022-01-17T03:52:57Z", "salary": {"currency": null, "max": null, "min": null, "period": "monthly", "term": null}, "salary_visible": false, "title_keywords": ["assistant officer"], "responsibilities": ["ad hoc duties", "management", "policies", "quality", "regular review", "payment", "insurance", "third party", "costs"], "requirements": {"degrees": [], "majors": [], "languages": ["english", "chinese", "mandarin"], "language_level": ["excellent", "proficient"], "hard_skills": ["excel", "iiqe", "word", "powerpoint"], "soft_skills": ["communication skills", "work independently", "confidence", "negotiation skills", "interpersonal", "work under pressure"], "languages_combined": [{"language": "english", "language_level": ["excellent"]}, {"language": "chinese", "language_level": ["proficient", "excellent"]}, {"language": "mandarin", "language_level": ["excellent"]}]}, "experience_required": {"duration": ["minimum 2-3 years"], "field": ["general insurance", "relevant experience"]}}, {"job_id": "100003009047516", "location_code": "hk", "company": "Well Link General Insurance Company Limited", "job_title": "Claims Specialist / Senior Claims Specialist", "description": "This role works collaboratively with business partners to ensure compliance with COG Best Practices, claims guidelines, processes and country specific guidelines. Continuously improves the technical quality and operational performance of the claims product, measuring compliance through the use of file reviews. Supports the delivery and roll out of Best Practices and the QA process, leading training sessions throughout APAC. Facilitates calibration of QA process within the claims teams through re-reviews, training and feedback. Partners with various levels of internal and external claims management to analyze and communicate findings, recommend solutions, and assist in the development of meaningful action plans.\n\nThis position works closely with country Claims teams and Regional Lines of Business Claims Leaders. Partners with various levels of internal and external claims management to analyze and communicate findings, recommend solutions, and assist in the development of meaningful action plans.\n\nThis position reports to the Asia Pacific Regional Claims Quality Assurance Manager and working closely with a team of Senior QA officers with a highly results driven focus.\n\n\n\nResponsibilities:\n\n\n\nPolicy, Process and Procedures\u00a0- Assists in the development and enhancement of COG Best Practice Guidelines\nTechnical Performance - Conducts Claim Technical Quality Reviews across multiple lines of business and languages of:\n\u00a0 COG Line of Business / Countries / Offices\n\u00a0 Third Party Administrators\n\u00a0 Claim Vendors & Suppliers\n\u00a0 Claims Operational Controls\nLeads the review and analysis of claims risks to ensure compliance with claims quality review policies and procedures, Chubb standards, and industry best practice\nPrepare detailed working papers that evidence work performed, issues discovered and recommendations for improvement\nCommunicates claims expectations and ensure best practices are understood and implemented to ensure appropriate performance\nDelivers training to managers throughout APAC on the audit process including the QA system and the calibration process to support QA quality\nContinuously collaborates with claim management in the development of meaningful action plans that detail the tasks, resources, and timeframes necessary to improve claim handling\nFacilitates, supports, and measures the execution of action plans. Provides consultation and advice to the claims teams to ensure the prompt and effective delivery of action plans\nLeads or actively participates in training claim handlers on technical claims content\nInteract with multiple business partners (Underwriting, Claims, Internal Audit, TPAs, Vendors, Accounts, Legal & Compliance etc.)\nRequirements:\n\n\nMinimum 5 years of working experience in technical claims handling in insurance companies\nDegree / Diploma in Business, Insurance or Law preferred\nFlexibility to work within multiple time zones\n\nAbility to participate in on-site reviews involving international travel of consecutive 2 weeks each quarter\nAbility to learn and navigate claim systems effectively\nAbility to learn and apply claims best practice adherence to claim file\nAbility to demonstrate high degree of credibility and influence among stakeholders supported\nAbility to analyze training needs and situations to determine if performance can be improved through training\nExcellent communication skills\n\nKnowledge and Experience:\n\n\nIndepth knowledge of insurance and minimum 3 years of technical claim adjusting experience with specialization in two major lines of business (Property, Liability, A&H, Personal Lines etc.)\nAbility to learn and adapt to new product lines\nFluent in English Language and ideally fluent in second Asian language\nExperience in claims technical quality audit desirable\nEffective communications and interpersonal skills to be capable of dealing a diverse group of multinational internal stakeholders, external partners and customers\nExperience of delivering training to a variety of groups is desirable\nIT savvy and demonstrated knowledge of and experience with software applications, including multiple claim systems, web based systems, and MS Office, with particular focus on Excel spreadsheets/ charts/pivot tables, and PowerPoint\nAbility to dissect QA data sets, identifies root causes/trends, and quantifies the \u201ccost of non-compliance\u201d\nExcellent time management and organizational skills. Must be able to excel independently and in team environment\nAbility to provide consultation and expert advice to management\n\n\nPlease click \"Apply now\" to submit your application.\n\nPersonal data collected will be used for recruitment purpose only.", "employment_types": ["Full Time", "Permanent"], "selling_points": ["Insurance, Claims, Claims Specialist", "Professional qualification: IIQE/ANZIIF/ACII", "Medical and Dental Insurance, Birthday Leave"], "locations": ["Sheung Wan"], "categories": ["Insurance", "Claims Officer"], "post_time": "2022-01-14T03:21:52Z", "salary": {"currency": null, "max": null, "min": null, "period": "monthly", "term": null}, "salary_visible": false, "title_keywords": ["specialist"], "responsibilities": ["practice guidelines", "management", "internal audit", "policies", "analysis", "review", "procedures", "quality", "audit", "ensure compliance", "teams", "compliance", "plans", "third party"], "requirements": {"degrees": ["diploma", "degree"], "majors": ["business", "insurance", "law"], "languages": ["english"], "language_level": ["fluent"], "hard_skills": ["excel", "web", "powerpoint", "focus", "ms office"], "soft_skills": ["communication skills", "organizational skills", "independently", "capable", "ability to analyze", "diverse", "interpersonal skills", "focus", "time management"], "languages_combined": [{"language": "english", "language_level": ["fluent"]}]}, "experience_required": {"duration": ["minimum 5 years", "minimum 3 years"], "field": ["training", "audit", "business", "it", "insurance"]}}, {"job_id": "100003009050131", "location_code": "hk", "company": "Chubb Insurance Hong Kong Limited", "job_title": "Regional Claims Quality Assurance Officer", "description": "Chevalier\u00a0Insurance Company\u00a0Limited, a subsidiary of Chevalier Group, is now inviting high calibre persons to apply for this position:\n\nResponsibilities\n\nHandle all classes of insurance claim and supervise subordinates to facilitate the process\nHandle cases involving litigation and direct settlement\nAnswer claims inquiries from clients\nAssist Claims Manager in preparing management reports and statistics\nAssist in ad-hoc projects assigned\n\nRequirements\n\nHKDSE or above\nPossess ANZIIF (Senior Associate) or ACII qualification or equivalent is preferable\n3 years\u00a0relevant experience in EC and Casualty\nGood command\u00a0of both written and spoken\u00a0English and Chinese, knowledge in Putonghua will be an advantage\nGood supervisory skills, strong career mind and enthusiastic about job\nProficient in MS Word, Excel and Powerpoint\n\nAttractive remuneration package will be offered to the right candidate. Interested parties, please send us your resume with current and expected salary by clicking \"Apply Now\" or mail to:\n\nThe\u00a0Human Resources\u00a0Manager, Chevalier Group, 22/F, Chevalier\u00a0Commercial Centre,\u00a08\u00a0Wang Hoi\u00a0Road, Kowloon Bay, Hong Kong.\n\n\nWe are an equal opportunity employer and welcome applications from all qualified candidates. Personal data collected would be used for recruitment purpose only.", "employment_types": ["Full Time"], "selling_points": ["Regional role (APAC focus)", "Claims Quality Assurance", "General Insurance"], "locations": ["Quarry Bay"], "categories": ["Insurance", "Claims Officer", "Underwriter", "Others"], "post_time": "2022-01-14T09:49:55Z", "salary": {"currency": null, "max": null, "min": null, "period": "monthly", "term": null}, "salary_visible": false, "title_keywords": ["quality assurance officer"], "responsibilities": ["ad-hoc projects", "management reports", "insurance"], "requirements": {"degrees": ["hkdse"], "majors": [], "languages": ["putonghua", "english", "chinese"], "language_level": ["advantage", "good command"], "hard_skills": ["excel", "powerpoint", "ms word"], "soft_skills": ["enthusiastic"], "languages_combined": [{"language": "putonghua", "language_level": ["advantage", "good command"]}, {"language": "english", "language_level": ["advantage", "good command"]}, {"language": "chinese", "language_level": ["advantage", "good command"]}]}, "experience_required": {"duration": ["3 years"], "field": ["relevant experience"]}}, {"job_id": "100003009050488", "location_code": "hk", "company": "Chevalier Group \u2013 Insurance Services", "job_title": "Claims Officer", "description": "We\u2019re hiring!\n\nAon is currently recruiting an Assistant Account Manager - Partnerships to join our team in Hong Kong.\u00a0\n\nAbout Aon\n\nHeadquartered in London, Aon Plc is a leading global professional services firm providing a broad range of risk, retirement and health solutions. Our 50,000 colleagues in 120 countries empower results for clients by using proprietary data and analytics to deliver insights that reduce volatility and improve performance.\n\nAt Aon, you\u2019ll be part of a team which will support and inspire you and provide the opportunities and resources to develop your skills. It\u2019s an environment which encourages you to achieve your best - together we\u2019ll empower results.\u00a0\n\nResponsibilities:\n\nProvide quality broker service to clients for new, penetration and renewal business\nDiscuss with potential clients for their insurance needs, present insurance solutions to them, provide insurance advice\nNegotiate with underwriters to get the best terms\nComply with Aon\u2019s operational KPIs including overdue renewal processing, premium collection, invoice performance, e-filing, client data maintenance\nAdvise clients on claims reporting, co-ordinate with Claims Team in the claims process\nAnd any additional duties that may be allocated to you by the Company from time to time.\u00a0\n\n\n\nRequirements:\n\nOver 5 years of insurance working experience\nProfessional insurance qualification in General/Life Insurance preferred (e.g. IIQE/ACII/LOMA designate)\nHave good communication skills\nDetail oriented, self- motivated and have a can-do attitude\nProficient in written and spoken English & Chinese\n\nHow to Apply\n\nYour opportunity to empower results could start right here. Make your mark and apply online today with a brief covering letter and your resume, sharing relevant achievements for this position.\n\nWe Offer You\n\nA competitive total rewards package, continuing education & training, and tremendous potential with a growing worldwide organization.\n\nOur Colleague Experience\n\nEvery day, our colleagues make a difference, work with the best, own their potential, and value one another. Together, we share this one purpose: to empower economic and human possibility around the world. This unifying goal is at the heart of our identity, and it lives in everything we do. To learn more about our colleague experience, visit Aon Colleague Experience.\n\nAon is an equal opportunities employer. We are committed to creating a winning and inclusive culture where everyone feels valued and has opportunities fo", "employment_types": ["Full Time", "Permanent"], "selling_points": ["Handle insurance claims & claim enquiries", "ANZIIF, ACII qualification", "3 year experience in claim"], "locations": ["Kowloon Bay"], "categories": ["Insurance", "Claims Officer", "Others"], "post_time": "2022-01-14T10:30:26Z", "salary": {"currency": null, "max": null, "min": null, "period": null, "term": null}, "salary_visible": false, "title_keywords": ["claims officer"], "responsibilities": ["reporting", "maintenance", "data", "invoice", "co-ordinate with", "additional duties", "quality", "kpis", "insurance"], "requirements": {"degrees": [], "majors": [], "languages": ["english", "chinese"], "language_level": ["proficient"], "hard_skills": ["make", "iiqe"], "soft_skills": ["communication skills", "detail oriented", "motivated", "can-do attitude"], "languages_combined": [{"language": "english", "language_level": ["proficient"]}, {"language": "chinese", "language_level": ["proficient"]}]}, "experience_required": {"duration": ["5 years"], "field": ["insurance"]}}, {"job_id": "100003009052217", "location_code": "hk", "company": "Aon Services Hong Kong Limited \u6021\u5b89\u670d\u52d9\u9999\u6e2f\u6709\u9650\u516c\u53f8", "job_title": "Assistant Account Manager - Partnerships", "description": "\u00a0\nJob Responsibilities\nHandle enquiries from both telephone hotline and email from different stakeholders on various claims issues\nCommunicate with various stakeholders to handle pending outpatient and inpatient claims\nEnhance and improve overall communication with other inter-department and corporate partners in providing support on direct billing services\nMaintain the service standard and turnaround time for claims process\nParticipate in various projects on the development, maintenance and enhancement of operations systems\nIndexing / data input for outpatient claims information\nAssist to manage daily claims operation and provide supervision to junior team members\nPrepare regular claims management reports and analysis\nFollow up on relevant account receivables\nSupport ad-hoc projects as requested\nRequirements\nDiploma or above in related discipline\nRelevant working experience in medical claim / insurance field\nProficient in MS Office, especially Excel\nBe self-motivated and proactive with the ability to prioritize with limited guidance\nAble to work effectively under pressure with competing and rapidly changing priorities\nExcellent interpersonal, customer service and communication skills\nExcellent English written and verbal communication skills\u00a0", "employment_types": ["Full Time", "Permanent"], "selling_points": [], "locations": ["Quarry Bay"], "categories": ["Insurance", "Claims Officer", "Insurance Agent / Broker", "Underwriter"], "post_time": "2022-01-17T02:30:35Z", "salary": {"currency": null, "max": null, "min": null, "period": "monthly", "term": null}, "salary_visible": false, "title_keywords": ["assistant account manager"], "responsibilities": ["communicate with", "service standard", "maintenance", "operations", "analysis", "systems", "data input", "provide supervision", "communication", "handle enquiries", "management reports", "maintain", "providing support", "ad-hoc projects"], "requirements": {"degrees": ["diploma or above"], "majors": [], "languages": ["english"], "language_level": ["excellent"], "hard_skills": ["excel", "ms office"], "soft_skills": ["work effectively", "communication skills", "self-motivated", "under pressure", "prioritize", "customer service", "proactive", "interpersonal"], "languages_combined": [{"language": "english", "language_level": ["excellent"]}]}, "experience_required": {"duration": [], "field": ["insurance", "relevant working experience", "medical"]}}, {"job_id": "100003009046123", "location_code": "hk", "company": "Gleneagles Hospital Hong Kong", "job_title": "Claims Officer", "description": "In the heart of the role:\n\nAssist in approval processing (including medication, diagnostic and imaging, minor operation, surgical operation, admission, etc)\nAnswer provider enquiry hotline\nCase follow up or investigation\nArrange medication or lab referral from Affiliate Doctor\nLiaise with corporate or insurer on approval and procedure fee\u00a0\nDesired Qualification and Education:\n\nHKDSEE/HKALE or higher diploma preferable\n2 years or above relevant experience in Insurance / HealthCare Industry\u00a0\nGood PC skills\nSelf-starter, independent with good communication and analytical thinking\nFamiliar with corporate / insurance medical contract arrangement and clinic operation\nWe offer attractive remuneration and fringe benefits. Interested parties please send your full resume with current salary and expected salary to Human Resources Department, Quality HealthCare Medical Services Limited, 3/F, Skyline Tower, 39 Wang Kwong Road, Kowloon Bay, Kowloon or by clicking \"Apply Now\".\n\n\n(All applications will be treated in strict confidence and data collected will be used for recruitment purposes only)\n\n\n\n", "employment_types": ["Full Time", "Permanent"], "selling_points": ["A top tier healthcare provider in Hong Kong", "Clear career path for personal development", "Competitive compensation & benefit"], "locations": ["Southern Area"], "categories": ["Sales, CS & Business Devpt", "Customer Service - Manager", "Insurance", "Claims Officer", "Medical Services", "Others"], "post_time": "2022-01-13T09:39:59Z", "salary": {"currency": null, "max": null, "min": null, "period": "monthly", "term": null}, "salary_visible": false, "title_keywords": ["claims officer"], "responsibilities": ["liaise with", "insurance", "communication", "investigation"], "requirements": {"degrees": ["diploma"], "majors": [], "languages": [], "language_level": [], "hard_skills": ["pc skills", "processing"], "soft_skills": ["communication", "independent"], "languages_combined": []}, "experience_required": {"duration": ["2 years"], "field": ["healthcare industry", "insurance", "relevant experience"]}}, {"job_id": "100003009052219", "location_code": "hk", "company": "Aon Services Hong Kong Limited \u6021\u5b89\u670d\u52d9\u9999\u6e2f\u6709\u9650\u516c\u53f8", "job_title": "Assistant Account Executive \u2013 Health Solutions", "description": "We\u2019re hiring!\u00a0\n\nAon is currently recruiting an Assistant Account Executive\u00a0to join our team in\u00a0Hong Kong.\n\n\nAbout Aon\n\nHeadquartered in London, Aon Plc is a leading global professional services firm providing a broad range of risk, retirement and health solutions. Our 50,000 colleagues in 120 countries empower results for clients by using proprietary data and analytics to deliver insights that reduce volatility and improve performance.\n\n\u00a0At Aon, you\u2019ll be part of a team which will support and inspire you and provide the opportunities and resources to develop your skills. It\u2019s an environment which encourages you to achieve your best - together we\u2019ll empower results.\u00a0\n\nThe Roles:\u00a0\n\nSupport Account Managers on consultative services to clients\nHandle client enquiries and liaise with insurers and service providers\nWork closely with underwriters on policy matters\nCheck policy documents and prepare debit notes\nProvide support in data analytics and result interpretation\nMaintain the quality and timeliness of client deliverables, provide assistance in report development in clear and concise manner\nProcess post-renewal documents and follow up\n\n\nOur Requirements:\n\nUniversity graduate, with minimum 1 year of working experience in Employee Benefits in broker firm(s) or insurance company(ies) preferred\nPassed in IIQE papers I, II, III & IV is preferred\nDetail-oriented, customer focused with effective client communication skills\nProactive, multi-tasker and able to work independently and as a team\u00a0\u00a0\nGood command of spoken and written English and Chinese.\nGood computer skills including MS Word, Excel & PowerPoint\n\nHow to Apply\n\nYour opportunity to empower results could start right here. Make your mark and apply online today with a brief covering letter and your resume, sharing relevant achievements for this position.\u00a0\n\nWe Offer You\n\nA competitive total rewards package, continuing education & training, and tremendous potential with a growing worldwide organization.\u00a0\n\nOur Colleague Experience\n\nEvery day, our colleagues make a difference, work with the best, own their potential, and value one another. Together, we share this one purpose: to empower economic and human possibility around the world. This unifying goal is at the heart of our identity, and it lives in everything we do. To learn more about our colleague experience, visit Aon Colleague Experience.\n\nAon is an equal opportunities employer. We are committed to creating a winning and inclusive culture where everyone feels valued and has opportunities for growth and development.\n\nAll applications will be treated in strict confidence and data collected will be used for recruitment purposes only.\u00a0 Only selected candidates will be contacted for interview.", "employment_types": ["Full Time", "Permanent"], "selling_points": [], "locations": ["Quarry Bay"], "categories": ["Insurance", "Claims Officer", "Underwriter", "Others"], "post_time": "2022-01-17T02:30:36Z", "salary": {"currency": null, "max": null, "min": null, "period": "monthly", "term": null}, "salary_visible": false, "title_keywords": ["assistant account executive"], "responsibilities": ["provide support", "data", "quality", "develop", "policy documents", "maintain", "liaise with", "provide assistance", "report"], "requirements": {"degrees": [], "majors": [], "languages": [], "language_level": [], "hard_skills": ["data analytics", "plc"], "soft_skills": ["clear"], "languages_combined": []}, "experience_required": {"duration": [], "field": []}}, {"job_id": "100003009049780", "location_code": "hk", "company": "Sun Mobility Insurance and Claims Services Limited", "job_title": "Executive Trainee", "description": "Responsibility\n\nHandle transport liability claims (e.g. cargo loss, damage, delay, misdelivery, misdirection, uncollected cargoes, general average) for our clients (e.g. freight forwarders, shipping companies, warehouses, terminals) including: advise our clients on their legal / contractual liability pursuant to their B/Ls and AWBs, deal with claimants for our clients.\nFollow up with our clients\u2019 transport liability insurers to process the transport liability claim handling and settlement.\nMonitor the performance of surveyors, lawyers, adjusters, correspondents of our clients\u2019 transport liability insurers.\n\n\n\nTarget Candidates\n\nDegree holder (fresh graduate will also be considered).\nExcellent command of both spoken and written English (HKDSE Level 5 or above in English), Chinese and/or Mandarin.\u00a0\nEnthusiastic & interested in transport and insurance industries.\n\nEmployment Terms\n\nHK$16,000-HK$18,000 per month\nGroup medical insurance\nGroup life insurance\nGroup personal accident insurance\nAnnual leave\n5 work days per week\n\nWe offer a competitive salary and employee benefits. Please apply with a full resume and expected salary to Carol Lam.\n\nTel. no .\u00a0\u00a0 \u00a0:\u00a0\u00a0 \u00a02299 5528\nAddress\u00a0\u00a0 \u00a0:\u00a0\u00a0 \u00a023/F, Excel Centre, 483A Castle Peak Road, Lai Chi Kok, Kowloon, Hong Kong\n\n\n\nPersonal data collected will be used for recruitment purposes only.", "employment_types": ["Full Time", "Permanent", "Contract"], "selling_points": [], "locations": ["Lai Chi Kok"], "categories": ["Insurance", "Claims Officer", "Transportation & Logistics", "Freight Forwarding", "Shipping"], "post_time": "2022-01-14T09:13:39Z", "salary": {"currency": null, "max": null, "min": null, "period": "monthly", "term": null}, "salary_visible": false, "title_keywords": ["executive", "trainee"], "responsibilities": ["shipping", "monitor the performance", "insurance"], "requirements": {"degrees": ["hkdse", "fresh graduate", "degree holder"], "majors": [], "languages": ["english", "chinese", "mandarin"], "language_level": ["excellent"], "hard_skills": [], "soft_skills": ["interested in", "enthusiastic"], "languages_combined": [{"language": "english", "language_level": ["excellent"]}, {"language": "chinese", "language_level": ["excellent"]}, {"language": "mandarin", "language_level": ["excellent"]}]}, "experience_required": {"duration": [], "field": []}}, {"job_id": "100003009042248", "location_code": "hk", "company": "Gravitas Recruitment Group (Hong Kong) Limited", "job_title": "Claims Senior Officer / Officer", "description": "My client is a top tier insurer, and they are now looking for claims specialists to join their claims team. They are well-established and offering a higher position for candidates to further develop their career in insurance claims.\n\nJob Description\n\nAccess major and minor claims and conduct claims investigations\nApprove subordinates\u2019 cases with higher authority\nHandle complaint and complex claims cases\nAnswer and handle claims enquiries\nParticipate in projects and ad hoc tasks assigned by higher management\n\nApply if you are:\n\nWith 3+ years of claims experience\nExperienced in individual life / medical insurance\nDegree holder with professional qualification in life insurance\n\nCandidates with less experience will be considered as claims officer.\n\nFor interested parties, please apply now with your detailed CV. Shortlisted candidates would be called to discuss further.", "employment_types": ["Full Time"], "selling_points": ["Well established life insurer", "Life / medical claims", "2-3 years of working experience"], "locations": ["Not Specified"], "categories": ["Insurance", "Claims Officer"], "post_time": "2022-01-12T06:43:34Z", "salary": {"currency": "HKD", "max": 29999, "min": 20000, "period": "monthly", "term": null}, "salary_visible": true, "title_keywords": ["senior officer", "officer"], "responsibilities": ["management", "insurance", "ad hoc tasks", "develop"], "requirements": {"degrees": ["degree holder"], "majors": ["insurance"], "languages": [], "language_level": [], "hard_skills": [], "soft_skills": [], "languages_combined": []}, "experience_required": {"duration": ["3+ years"], "field": []}}, {"job_id": "100003009052221", "location_code": "hk", "company": "Aon Services Hong Kong Limited \u6021\u5b89\u670d\u52d9\u9999\u6e2f\u6709\u9650\u516c\u53f8", "job_title": "Account Manager - Health Solutions", "description": "My client is a well-established insurer, and they are looking for a claims specialist to join their claims team. This is an exciting opportunity for individuals who want to develop their career in a higher position and work in a top tier insurer.\n\nWhy should you apply:\n\nAssess and approve major claims cases, investigate complex claims\nBe in a supervisory position and be responsible for providing guidance and coaching junior teammates on case assessments\nParticipate in projects to increase the effectiveness of claims processes by enhancing the claims system and streamlining workflow\nPerform claims data analysis and monitor trends to generate reports\n\nThe ideal candidate:\n\n4 years+ claims experience\nSolid life / medical insurance claims understanding and skillset\nExperience in participating in projects with strong life insurance product knowledge\nBe able to bring insights to improve the claims process and efficiency\n\nFor interested parties, please Apply Now with your detailed CV. Shortlisted candidates would be called to discuss further.", "employment_types": ["Full Time", "Permanent"], "selling_points": [], "locations": ["Quarry Bay"], "categories": ["Insurance", "Claims Officer", "Insurance Agent / Broker", "Banking / Finance", "Risk Management"], "post_time": "2022-01-17T02:30:37Z", "salary": {"currency": null, "max": null, "min": null, "period": "monthly", "term": null}, "salary_visible": false, "title_keywords": ["account manager"], "responsibilities": ["guidance", "monitor", "develop", "data analysis", "reports", "insurance"], "requirements": {"degrees": [], "majors": [], "languages": [], "language_level": [], "hard_skills": ["analysis"], "soft_skills": ["responsible", "ideal"], "languages_combined": []}, "experience_required": {"duration": [], "field": ["insurance"]}}, {"job_id": "100003009052220", "location_code": "hk", "company": "Aon Services Hong Kong Limited \u6021\u5b89\u670d\u52d9\u9999\u6e2f\u6709\u9650\u516c\u53f8", "job_title": "Senior / Executive, Enrolment - Health Solutions", "description": "We\u2019re hiring!\n\nAon is currently recruiting an Account Manager - Health Solutions\u00a0to join our team in Hong Kong.\n\nAbout Aon\n\nHeadquartered in London, Aon Plc is a leading global professional services firm providing a broad range of risk, retirement and health solutions. Our 50,000 colleagues in 120 countries empower results for clients by using proprietary data and analytics to deliver insights that reduce volatility and improve performance.\n\nAt Aon, you\u2019ll be part of a team which will support and inspire you and provide the opportunities and resources to develop your skills. It\u2019s an environment which encourages you to achieve your best - together we\u2019ll empower results.\u00a0\n\nResponsibilities:\n\nThe incumbent will be responsible to assist the business line department in providing account management to the existing and potential clients. Duties include:\n\nManaging and providing high quality broking services to our existing clients\nAchieving business growth by penetration from current portfolio and by prospects\nLiaise with insurers and service providers to ensure smooth renewal and tackle related issues \u00a0\nPerform claims data analytics and result interpretation for renewal preparation\nMaintain the quality and timeliness of client deliverables, responsible for report development in clear and concise manner\nSupport various projects as assigned by Supervisor\n\nRequirements:\n\nUniversity graduate with minimum\u00a05 years of working experience in Employee Benefits in broker firm or insurance company(ies)\nHolder of FLMI or passed in IIQE Paper I, II, III & IV are preferred\nMature and be a self-starter\nGood organization skills and effective interpersonal skills\nGood analytics and negotiations skills\nGood command of written and spoken English and Chinese; knowledge of Mandarin will be an advantage\nGood command of computer skills including MS Office (Word, Excel, Powerpoint)\n\nHow to Apply\n\nYour opportunity to empower results could start right here. Make your mark and apply online today with a brief covering letter and your resume, sharing relevant achievements for this position.\n\nWe Offer You\n\nA competitive total rewards package, continuing education & training, and tremendous potential with a growing worldwide organization.\n\nOur Colleague Experience\n\nEvery day, our colleagues make a difference, work with the best, own their potential, and value one another. Together, we share this one purpose: to empower economic and human possibility around the world. This unifying goal is at the heart of our identity, and it lives in everything we do. To learn more about our colleague experience, visit Aon Colleague Experience.\n\nAon is an equal opportunities employer. We are committed to creating a winning and inclusive culture where everyone feels valued and has opportunities for growth and development.", "employment_types": ["Full Time", "Permanent"], "selling_points": [], "locations": ["Quarry Bay"], "categories": ["Admin & HR", "Clerical / Admin Staff", "Insurance", "Claims Officer", "Others"], "post_time": "2022-01-17T02:30:37Z", "salary": {"currency": null, "max": null, "min": null, "period": "monthly", "term": null}, "salary_visible": false, "title_keywords": ["executive"], "responsibilities": ["management", "data", "quality", "maintain", "liaise with", "report"], "requirements": {"degrees": [], "majors": [], "languages": [], "language_level": [], "hard_skills": [], "soft_skills": [], "languages_combined": []}, "experience_required": {"duration": [], "field": []}}, {"job_id": "100003009049781", "location_code": "hk", "company": "Sun Mobility Insurance and Claims Services Limited", "job_title": "Manager / Assistant Manager / Claims Executive", "description": "Responsibility\n\nHandle transport liability claims (e.g. cargo loss, damage, delay, misdelivery, misdirection, uncollected cargoes, general average) for our clients (e.g. freight forwarders, shipping companies, warehouses, terminals) including: advise our clients on their legal / contractual liability pursuant to their B/Ls and AWBs, deal with claimants for our clients.\nFollow up with our clients\u2019 transport liability insurers to process the transport liability claim handling and settlement.\nMonitor the performance of surveyors, lawyers, adjusters, correspondents of our clients\u2019 transport liability insurers.\n\n\n\nTarget Candidates\n\nUniversity graduates.\nWorking experience in the insurance, shipping, airfreight, forwarding, and/or logistics industries.\nExperienced in handling transport liability claims is an advantage.\nGood command of written English and Chinese.\n\n\n\nWe offer competitive salary and employee benefits. Please apply with full resume and expected salary to Carol Lam.\n\nTel. no .\u00a0\u00a0 \u00a0:\u00a0\u00a0 \u00a02299 5528\nAddress\u00a0\u00a0 \u00a0:\u00a0\u00a0 \u00a023/F, Excel Centre, 483A Castle Peak Road, Lai Chi Kok, Kowloon, Hong Kong\n\n\n\nPersonal data collected will be used for recruitment purposes only.", "employment_types": ["Full Time", "Permanent", "Contract"], "selling_points": [], "locations": ["Lai Chi Kok"], "categories": ["Insurance", "Claims Officer", "Transportation & Logistics", "Freight Forwarding", "Shipping"], "post_time": "2022-01-14T09:13:39Z", "salary": {"currency": null, "max": null, "min": null, "period": "monthly", "term": null}, "salary_visible": false, "title_keywords": ["assistant manager", "manager", "executive"], "responsibilities": ["shipping", "logistics", "monitor the performance", "insurance"], "requirements": {"degrees": [], "majors": [], "languages": ["english", "chinese"], "language_level": ["good command"], "hard_skills": [], "soft_skills": [], "languages_combined": [{"language": "english", "language_level": ["good command"]}, {"language": "chinese", "language_level": ["good command"]}]}, "experience_required": {"duration": [], "field": ["insurance", "logistics"]}}, {"job_id": "100003009042238", "location_code": "hk", "company": "Gravitas Recruitment Group (Hong Kong) Limited", "job_title": "Life  / Medical Claims - Assistant Manager / Manager", "description": "My client is a well-established insurer, and they are looking for a claims specialist to join their claims team. This is an exciting opportunity for individuals who want to develop their career in a higher position and work in a top tier insurer.\n\nWhy should you apply:\n\nAssess and approve major claims cases, investigate complex claims\nBe in a supervisory position and be responsible for providing guidance and coaching junior teammates on case assessments\nParticipate in projects to increase the effectiveness of claims processes by enhancing the claims system and streamlining workflow\nPerform claims data analysis and monitor trends to generate reports\n\nThe ideal candidate:\n\n4 years+ claims experience\nSolid life / medical insurance claims understanding and skillset\nExperience in participating in projects with strong life insurance product knowledge\nBe able to bring insights to improve the claims process and efficiency\n\nFor interested parties, please Apply Now with your detailed CV. Shortlisted candidates would be called to discuss further.", "employment_types": ["Full Time"], "selling_points": ["Conduct life / medical claims assessments", "4 years of experience in claims", "Top tier insurer"], "locations": ["Not Specified"], "categories": ["Insurance", "Claims Officer"], "post_time": "2022-01-12T06:42:32Z", "salary": {"currency": "HKD", "max": 54999, "min": 35000, "period": "monthly", "term": null}, "salary_visible": true, "title_keywords": ["assistant manager", "manager"], "responsibilities": ["guidance", "monitor", "develop", "data analysis", "reports", "insurance"], "requirements": {"degrees": [], "majors": [], "languages": [], "language_level": [], "hard_skills": ["analysis"], "soft_skills": ["responsible", "ideal"], "languages_combined": []}, "experience_required": {"duration": [], "field": ["insurance"]}}, {"job_id": "100003009037763", "location_code": "hk", "company": "Dah Sing Financial Group", "job_title": "Officer / Senior Officer, Claims (General Insurance)", "description": "Major responsibilities:\n\nManaging claims handling inquiry; coverage determination, quantum analysis, and legal liability assessment, where appropriate within authority limits;\nDemonstrating a basic standard of technical claims competence for handling all Property & Liability Insurance claims;\nMeet service turnaround time and achieve claims KPI targets;\nParticipate in-service meetings with client groups;\nProvide quality customer services and handle a complaint;\nAssist in reviewing workflow, implementing continuous claims process improvement;\nAssist in compiling regular management reports;\nHandle ad hoc projects such as systems enhancement and ad hoc reporting.\n\nQualification and Experience Requirement:\n\n\nDegree holder or tertiary graduate with professional qualifications in insurance or related disciplines;\n2 \u2013 5 years\u2019 Property & Liability insurance claims handling experience;\nCustomer-oriented with good communication and interpersonal skills;\nGood team player, able to work independently and under pressure;\nResult-oriented, self-motivated, analytical, and detailed-minded in problem-solving;\nStrong sense of responsibility with a high level of integrity and trust;\nGood command of English and Chinese in both written and spoken;\nSound PC skills in MS Word, Excel & Chinese word processing;\nFor strong candidates with less experience will be considered for an Officer position.", "employment_types": ["Permanent"], "selling_points": ["Assist in UAT", "Secondary education or above", "At least 2 years\u2019 relevant experience"], "locations": ["North Point"], "categories": ["Sales, CS & Business Devpt", "Customer Service - Supervisor / Officer", "Insurance", "Claims Officer", "Others"], "post_time": "2022-01-11T03:45:53Z", "salary": {"currency": null, "max": null, "min": null, "period": "monthly", "term": null}, "salary_visible": false, "title_keywords": ["officer", "senior officer"], "responsibilities": ["reporting", "ad hoc", "analysis", "systems", "quality", "customer services", "management reports", "ad hoc projects", "insurance"], "requirements": {"degrees": ["degree holder"], "majors": ["related disciplines", "insurance"], "languages": ["english", "chinese"], "language_level": ["good command"], "hard_skills": ["excel", "chinese word processing", "professional qualifications", "problem-solving", "pc skills", "ms word"], "soft_skills": ["good team player", "work independently", "under pressure", "self-motivated", "sense of responsibility", "problem-solving", "integrity", "customer-oriented", "communication and interpersonal skills", "result-oriented", "detailed"], "languages_combined": [{"language": "english", "language_level": ["good command"]}, {"language": "chinese", "language_level": ["good command"]}]}, "experience_required": {"duration": ["5 years"], "field": ["insurance"]}}, {"job_id": "100003009037519", "location_code": "hk", "company": "QBE General Insurance (Hong Kong) Limited", "job_title": "Senior / Claims Officer \u2013 Property & Engineering Claims", "description": "Accountabilities and Activities\n\nAssess medical claims in compliance with the terms and conditions of the policy\nProcess claims payment in accordance with the company's objectives\nLiaise with medical professionals and customers to conduct assessment and investigation\nFollow up customers' request with other departments\nContact customers to follow up outstanding issues\nAble to manage different types of jobs at the same time in orderly manner\nProvide training to Junior staff and meet the timeline and service standard on the assigned tasks\nAssists in enhancing the system and work flow to meet customers\u2019 need and services standards\n\n\nTo be considered for the role, you should ideally have\n\n\nBachelor\u2019s degree will be an advantage\nAt least 3 years of experience in medical claim processing\nExperience in processing medical claims and with customer services experience will be an advantage\nCustomer-oriented with excellent communication and interpersonal skills\nStrong team player, willing to learn, able to work independently and\u00a0under pressure\nSelf-motivated, analytical and detailed-minded in problem solving\nStrong sense of responsibility with high level of integrity and trust\nGood command of English and Chinese in both written and spoken\nSound PC skills in MS Word, Excel & Chinese word processing\nBupa offers 5 days work per week and comprehensive remuneration packages including base salary, study assistance plan, life and medical benefit, dental benefit, annual leave, examination leave, etc.\nBupa is an equal opportunity employer and welcomes applications from qualified candidates. Information provided will be treated in strict confidential and only be used for consideration of application with Bupa.\u00a0\u00a0\u00a0\u00a0\u00a0\u00a0\u00a0\u00a0\u00a0\u00a0\u00a0\u00a0\u00a0\u00a0\nPersonal data collected will be used for recruitment purposes only. Only candidates selected for interviews will be contacted. Bupa will be in touch for any opportunities that matches your profile. All personal data of unsuccessful application will be destroyed 24 months from the date of receiving the application.", "employment_types": ["Full Time", "Permanent"], "selling_points": ["Claims officer, Property & Engineering Claims", "Property & Casualty Insurance claims", "Case handler, litigation and direct settlement"], "locations": ["Quarry Bay"], "categories": ["Insurance", "Claims Officer", "Others", "Banking / Finance", "Order Processing & Operation / Settlement"], "post_time": "2022-01-11T03:00:56Z", "salary": {"currency": null, "max": null, "min": null, "period": "monthly", "term": null}, "salary_visible": false, "title_keywords": ["claims officer"], "responsibilities": ["provide training", "service standard", "compliance", "investigation", "customer services", "communication", "payment", "recruitment", "contact", "plan", "liaise with", "personal data"], "requirements": {"degrees": ["degree", "bachelor"], "majors": [], "languages": ["english", "chinese"], "language_level": ["good command"], "hard_skills": ["excel", "chinese word processing", "processing", "problem solving", "pc skills", "ms word"], "soft_skills": ["work independently", "self-motivated", "under pressure", "sense of responsibility", "orderly", "willing to learn", "integrity", "problem solving", "customer-oriented", "communication and interpersonal skills", "comprehensive", "team player", "detailed"], "languages_combined": [{"language": "english", "language_level": ["good command"]}, {"language": "chinese", "language_level": ["good command"]}]}, "experience_required": {"duration": ["at least 3 years"], "field": ["customer services", "medical"]}}, {"job_id": "100003009046027", "location_code": "hk", "company": "FWD Life Insurance Company (Bermuda) Limited", "job_title": "Senior Business Analyst/ Business Analyst, Life Claims (1-year Contract)", "description": "Major responsibilities:\n\n\nAssist Assistant Claims Manager to support the team in daily claims operation;\nAssess and approve Employees Compensation Insurance claims within authority limits;\nStriving for continuous improvement on claim file handling;\nMeet service turnaround time and achieve claims KPI targets;\nParticipate in-service meetings with client groups;\nProvide quality customer services and handle a complaint;\nAssist in reviewing workflow, implementing continuous claims process improvement;\nAssist in compiling regular management reports;\nHandle ad hoc projects such as systems enhancement and ad hoc reporting.\n\nQualification and Experience Requirement:\n\n\nDegree holder or tertiary graduate with professional qualifications in insurance or related disciplines;\n2 \u2013 5 years\u2019 Employees Compensation insurance claims handling experience;\nCustomer-oriented with good communication and interpersonal skills;\nGood team player, able to work independently and under pressure;\nResult-oriented, self-motivated, analytical, and detailed-minded in problem-solving;\nStrong sense of responsibility with a high level of integrity and trust;\nGood command of English and Chinese in both written and spoken;\nSound PC skills in MS Word, Excel & Chinese word processing.\nFor strong candidates with less experience will be considered for an Officer position.", "employment_types": ["Full Time"], "selling_points": ["3 years experience in insurance firm", "Strong communication and writing skills", "Contract role, 14 ALs, Medical, Dental & Gratuity"], "locations": ["Kwun Tong"], "categories": ["Professional Services", "Business Analysis / Data Analysis", "Insurance", "Claims Officer"], "post_time": "2022-01-13T09:27:14Z", "salary": {"currency": null, "max": null, "min": null, "period": "monthly", "term": null}, "salary_visible": false, "title_keywords": ["senior business analyst", "business analyst"], "responsibilities": ["reporting", "ad hoc", "systems", "quality", "customer services", "management reports", "ad hoc projects", "insurance", "support the team"], "requirements": {"degrees": ["degree holder"], "majors": ["related disciplines", "insurance"], "languages": ["english", "chinese"], "language_level": ["good command"], "hard_skills": ["excel", "chinese word processing", "professional qualifications", "problem-solving", "pc skills", "ms word"], "soft_skills": ["good team player", "work independently", "under pressure", "self-motivated", "sense of responsibility", "problem-solving", "integrity", "customer-oriented", "communication and interpersonal skills", "result-oriented", "detailed"], "languages_combined": [{"language": "english", "language_level": ["good command"]}, {"language": "chinese", "language_level": ["good command"]}]}, "experience_required": {"duration": ["5 years"], "field": ["insurance"]}}, {"job_id": "100003009037520", "location_code": "hk", "company": "QBE General Insurance (Hong Kong) Limited", "job_title": "Assistant Manager /Senior Officer \u2013 Property Claims", "description": "Established in Asia in 2013 with a trailblazer mentality, FWD is the primary insurance business of investment group, Pacific Century Group (PCG), with minority shareholders Swiss Re Group, GIC Ventures, RRJ Capital and Hopu Investments.\n\nFWD spans 10 markets in Asia including Hong Kong SAR & Macau SAR, Thailand, Indonesia, the Philippines, Singapore, Vietnam, Japan, Malaysia and Cambodia. In Hong Kong, FWD offers life and medical insurance, general insurance, employee benefits, and financial planning. We focus on creating fresh customer experiences and making the insurance journey simpler, faster and smoother, with innovative propositions and easy-to-understand products, supported by digital technology. Through this customer-led approach, FWD aims to be a leading pan-Asian insurer by changing the way people feel about insurance.\n\nIf you are looking for a company where can fuel your inspiration and cultivate your expertise, join us on our exciting journey.\n\nThe Job:\n\nResponsible for managing various parts of Life operation project, including claim system development and data migration \u00a0\nWork with team members and other departments to support various initiatives/ projects.\nHandle system issues and coordinate with different IT teams to solve system production issues and provide solution to handle the fix\nPrepare user requirement, UAT plan and manage UAT testing; and\nSupport UAT and troubleshoot software development problems.\nHandle ad-hoc tasks assigned by supervisor.\nAssist in operation guidelines write-ups and updates\nEnsure quality outputs are delivered according to project timeline\n\nThe Person:\n\nMinimum 3 years\u2019 experience of working as a business analyst in Life Insurance\nExperience with claims system, change process and project management\nExperience with policy systems AS400 / Life Asia\nGood knowledge of PC, particularly proficient in MS Office tools\nProficiency in Chinese and English\nStrong communication and writing skills\nStrong analytical anal independent problem solving capability\n\nWe offer 5-day work, excellent learning & development opportunities and an attractive package to the right candidate.\n\nInformation collected will be treated in strict confidence and used solely for recruitment purpose. The company will retain all applications no longer than 24 months of which will be destroyed thereafter. When there are vacancies in any of our subsidiaries, holding companies, associated or affiliated companies of, or companies controlled by, or under common control with the Company during that period, we may transfer your application to them for consideration of employment. We are an equal opportunity employer. We do not discriminate on the basis of race, sex, disability or family status in employment process.", "employment_types": ["Full Time", "Permanent"], "selling_points": ["Claims officer, Property Claims", "Property & Casualty Insurance claims", "case handler, litigation, examinar"], "locations": ["Quarry Bay"], "categories": ["Insurance", "Claims Officer", "Others", "Banking / Finance", "Order Processing & Operation / Settlement"], "post_time": "2022-01-11T03:00:56Z", "salary": {"currency": null, "max": null, "min": null, "period": "monthly", "term": null}, "salary_visible": false, "title_keywords": ["assistant manager", "senior officer"], "responsibilities": [], "requirements": {"degrees": [], "majors": [], "languages": [], "language_level": [], "hard_skills": [], "soft_skills": [], "languages_combined": []}, "experience_required": {"duration": [], "field": []}}, {"job_id": "100003009043477", "location_code": "hk", "company": "Page Personnel", "job_title": "Underwriting and Claims Officer- Top Reinsurer Firm!", "description": "Our client is one of the largest reinsurers in the world that provides insurance companies with a diversified and innovative range of solutions and services to control and manage risk. They are looking for a life underwriting and claims trainee to handle life underwriting and claims services and product development activities. The candidate should have 1-2 years of working experience in life underwriting, claims or policy admin within insurance industry.\n\nClient Details\n\nOur client is one of the leading tier 1 reinsurance companies, founded in 1970, providing life & health, property and casualty reinsurance solutions to its clients. They are now looking for a life underwriting and claims officer to join the underwriting and claims team to handle life and medical underwriting and claims services/ applications and product development initiatives. The specialist teams operate in over 120 countries and they provide a broad range of innovative reinsurance solutions and an underwriting policy founded on profitability to their clients mostly insurers and large corporations\n\nDescription\n\nResponsible for providing high quality underwriting and claims adjudication services and support on client servicing, underwriting and claims assessments and daily BAU business\nAssist in product development activities like product design, business development, medical research and defining terms for innovative insurance solution for various products including Critical Illness, Life, Group, and Medical Insurance\nHandle underwriting and claims applications and activities including screening, data entry on new business and providing decisions for both life and health products\nEnhance team activities including review of reinsurance treaty agreement terms and conditions and monthly case monitoring report\nMaintain accurate records of company information include treaties, provisions and guidelines\n\nProfile\n\nBachelor's degree with major in risk management, insurance management, biology science or relevant discipline\nAt least 1-2 years of working experience in life and medical underwriting, claims or policy admin for group and individual within insurance industry\nRelevant reinsurance internship experience to reinsurance products is preferred\nStrong product knowledge in life and health/ medical\nExcellent attitudes including being highly motivated, observant, confident and willing to learn\nStrong English, Cantonese verbal and written skills\n\nJob Offer\n\nInternational and dynamic working environment\nChallenging and stimulating job tasks\nCompetitive packages and benefits\nMedical benefits\n15 days AL\n\nTo apply online please click the 'Apply' button below. For a confidential discussion about this role please contact Esther Liu on +852 2258 3537", "employment_types": ["Full Time", "Permanent"], "selling_points": ["International and dynamic working environment", "Huge exposure to juniors", "Competitive packages and benefits"], "locations": ["Not Specified"], "categories": ["Insurance", "Claims Officer", "Underwriter", "Others"], "post_time": "2022-01-12T13:26:42Z", "salary": {"currency": null, "max": null, "min": null, "period": "monthly", "term": null}, "salary_visible": false, "title_keywords": ["claims officer"], "responsibilities": ["control", "management", "data entry", "guidelines", "review", "quality", "teams", "monitoring", "product design", "maintain", "insurance", "report"], "requirements": {"degrees": ["degree", "bachelor"], "majors": ["risk management", "biology", "insurance", "science"], "languages": ["cantonese", "english"], "language_level": [], "hard_skills": ["dynamic"], "soft_skills": ["confident", "accurate", "responsible", "willing to learn", "motivated", "dynamic", "innovative"], "languages_combined": [{"language": "cantonese", "language_level": []}, {"language": "english", "language_level": []}]}, "experience_required": {"duration": ["at least 1-2 years", "1-2 years"], "field": ["underwriting", "insurance industry", "life underwriting", "admin", "medical"]}}, {"job_id": "100003009035736", "location_code": "hk", "company": "Toplis & Harding (Hong Kong) Limited", "job_title": "Trainee Claims Adjusters / Trainee Loss Adjusters", "description": "A Golden Opportunity to develop a Professional Career in Loss Adjusting - Employees' Compensation Division\n\nJob Highlights\n\nField Investigations / Taking Statements / Report Writing\u00a0\nRehabilitation Monitoring / Settlement Negotiations\nQualifications\nUniversity graduates, all Faculties with good academic results or Insurance related Diploma, with a strong desire to develop a career in the profession.\nOR\u00a0Experience in Casualty/EC stream loss adjusting, capable of handling claims independently.\nPersonal Traits\n\nQuick learner, responsible character, attention to detail and people-oriented.\nFluent in English, Cantonese, Mandarin and computer usage.\nBenefit\n\nFull training & best remuneration package / bonus scheme offered\n5 days work week in Kwun Tong\nMedical Insurance\nPerformance Bonus\nTransportation Allowance\n\nInterested parties, please apply in own handwriting (application letter only) with CV and email to us, please press the APPLY NOW button.\u00a0\n\n", "employment_types": ["Full Time", "Permanent"], "selling_points": ["Claims Handler, Claims Adjusters", "Examine claims data, investigate the facts of loss", "Medical Insurance; Transportation Allowance"], "locations": ["Kwun Tong"], "categories": ["Sales, CS & Business Devpt", "Customer Service - Supervisor / Officer", "Insurance", "Claims Officer", "Others"], "post_time": "2022-01-10T08:18:59Z", "salary": {"currency": null, "max": null, "min": null, "period": "monthly", "term": null}, "salary_visible": false, "title_keywords": ["trainee"], "responsibilities": ["rehabilitation", "monitoring", "develop", "insurance", "report"], "requirements": {"degrees": ["diploma"], "majors": ["insurance"], "languages": ["cantonese", "english", "mandarin"], "language_level": ["fluent"], "hard_skills": [], "soft_skills": ["independently", "capable", "responsible", "quick learner", "attention to detail", "people-oriented"], "languages_combined": [{"language": "cantonese", "language_level": ["fluent"]}, {"language": "english", "language_level": ["fluent"]}, {"language": "mandarin", "language_level": ["fluent"]}]}, "experience_required": {"duration": [], "field": []}}, {"job_id": "100003009036992", "location_code": "hk", "company": "Generali Life (Hong Kong) Limited", "job_title": "Manager / Senior Manager, Employee Benefits Claims", "description": "Job Descriptions:\n\n\u00a0\u00a0\u00a0\u00a0\u00a0\u00a0\u00a0\u00a0 Assist in implementing marketing plan and activities\n\u00a0\u00a0\u00a0\u00a0\u00a0\u00a0\u00a0\u00a0 Handle client's inquiries and orders\n\u00a0\u00a0\u00a0\u00a0\u00a0\u00a0\u00a0\u00a0 Provide full support to the marketing team\u00a0\n\u00a0\u00a0\u00a0\u00a0\u00a0\u00a0\u00a0\u00a0 Perform ad-hoc projects as assigned\n\nRequirements:\n\n\u00a0\u00a0\u00a0\u00a0\u00a0\u00a0\u00a0\u00a0 Degree holder in marketing or related disciplines\n\u00a0\u00a0\u00a0\u00a0\u00a0\u00a0\u00a0\u00a0 Fresh Graduates are welcomed\n\u00a0\u00a0\u00a0\u00a0\u00a0\u00a0\u00a0\u00a0 Minimum 1 year relevant working experience, preferably in B&B service industry\n\u00a0\u00a0\u00a0\u00a0\u00a0\u00a0\u00a0\u00a0 Familiar in digital marketing software (e.g. Photoshop/Illustrator)\u00a0\n\u00a0\u00a0\u00a0\u00a0\u00a0\u00a0\u00a0\u00a0 Experience in e-marketing is an advantage\n\u00a0\u00a0\u00a0\u00a0\u00a0\u00a0\u00a0\u00a0 Self-motivated, good team player\u00a0and willing to work under pressure\n\u00a0\u00a0\u00a0\u00a0\u00a0\u00a0\u00a0\u00a0 Strong communication & presentation skills, creative and well-organized\n\u00a0\u00a0\u00a0\u00a0\u00a0\u00a0\u00a0\u00a0 Good command in spoken and written English & Chinese\n\u00a0\u00a0\u00a0\u00a0\u00a0\u00a0\u00a0\u00a0 Delivery meaningful messages to target customers\n\u00a0\u00a0\u00a0\u00a0\u00a0\u00a0\u00a0\u00a0 Manage clients\u2019 data base contact list.", "employment_types": ["Full Time", "Permanent"], "selling_points": [], "locations": ["Tai Koo"], "categories": ["Insurance", "Claims Officer", "Others"], "post_time": "2022-01-11T01:15:54Z", "salary": {"currency": null, "max": null, "min": null, "period": "monthly", "term": null}, "salary_visible": false, "title_keywords": ["senior manager", "manager"], "responsibilities": ["marketing plan", "ad-hoc projects"], "requirements": {"degrees": ["degree holder"], "majors": ["related disciplines", "marketing"], "languages": ["english", "chinese"], "language_level": ["good command"], "hard_skills": ["illustrator", "photoshop"], "soft_skills": ["good team player", "self-motivated", "well-organized", "communication", "presentation skills", "creative", "work under pressure"], "languages_combined": [{"language": "english", "language_level": ["good command"]}, {"language": "chinese", "language_level": ["good command"]}]}, "experience_required": {"duration": ["minimum 1 year"], "field": ["marketing", "relevant working experience", "service industry"]}}, {"job_id": "100003009038294", "location_code": "hk", "company": "FWD Life Insurance Company (Bermuda) Limited", "job_title": "Manager/ Assistant Manager, Life Claims (1-year Contract)", "description": "Key Responsibilities:\n\nFormulate and implement Employee Benefits claims strategy and development plan to achieve the company objectives for profitability and growth;\nMonitor & approve claims within the pre-set authority and provide appropriate commentary, recommendations and justifications to senior management to seek for approval when necessary;\u00a0\nManage and supervise the daily operations of the Employee Benefits claims team;\nComplaint handling and resolving disputes;\nDevelop high quality work teams with clear accountabilities and performance expectations to ensure ability to deliver high performance;\nActively improve processes and efficiency using service benchmarks and analytical data;\nImplement the Group compliance policy to adhere the relevant local and Group compliance procedures and obtain satisfactory audit and regulators\u2019 review reports;\nEngage in continuing education and training opportunities when possible.\nManage ad hoc projects as required.\n\nKey Requirements:\n\nDegree holder and preferably with insurance-related qualifications, e.g. FLMI, ICA, ACII/ANZIIF;\nMinimum 10 years\u2019 experience in medical & life claims and with 5+ years in managerial positions;\nUnderstand the impact of market forces and regulatory issues on the insurance industry;\nCan compare the company's insurance practices to other organizations;\nCan describe key industry benchmarks and relate them to own organization or functional specialty;\nHold digital mindset and able to initiate & implement technology and processes changes;\nStrong analytical and problem solving, self-motivated, excellent interpersonal and communication skills;\nGood team player and self-starter; able to interact with people at all levels;\nAbility to be multi-task and work under pressure;\nStrong sense of responsibility with high level of integrity and trust;\nGood command of English and Chinese in both written and spoken;\nSound PC skills in MS Word, Excel and power point;\nKnowledge of FDA health regulations.\n\nWe offer 5-day work, good career prospects and attractive remuneration package to the right candidates. Interested parties please send full resume with expected salary to: The Human Resources Department, 21/F, Cityplaza One,1111 King\u2019s Road, Taikoo Shing, Hong Kong or by email.\n\nPersonal data collected will be strictly used for recruitment purpose only. All unsuccessful applications will be destroyed after two years", "employment_types": ["Full Time"], "selling_points": ["Involve in approving claims cases", "Coordinate BAU system enhancement", "5 years working experience in Claims"], "locations": ["Kwun Tong"], "categories": ["Insurance", "Claims Officer"], "post_time": "2022-01-11T06:26:40Z", "salary": {"currency": null, "max": null, "min": null, "period": "monthly", "term": null}, "salary_visible": false, "title_keywords": ["manager", "assistant manager,"], "responsibilities": [], "requirements": {"degrees": [], "majors": [], "languages": [], "language_level": [], "hard_skills": [], "soft_skills": [], "languages_combined": []}, "experience_required": {"duration": [], "field": []}}, {"job_id": "100003009035629", "location_code": "hk", "company": "ONEDEGREE HONG KONG LIMITED", "job_title": "Claims Assessor - Insurtech Startup", "description": "Established in Asia in 2013 with a trailblazer mentality, FWD is the primary insurance business of investment group, Pacific Century Group (PCG), with minority shareholders Swiss Re Group, GIC Ventures, RRJ Capital and Hopu Investments.\n\nFWD spans 10 markets in Asia including Hong Kong SAR & Macau SAR, Thailand, Indonesia, the Philippines, Singapore, Vietnam, Japan, Malaysia and Cambodia. In Hong Kong, FWD offers life and medical insurance, general insurance, employee benefits, and financial planning. We focus on creating fresh customer experiences and making the insurance journey simpler, faster and smoother, with innovative propositions and easy-to-understand products, supported by digital technology. Through this customer-led approach, FWD aims to be a leading pan-Asian insurer by changing the way people feel about insurance.\n\nIf you are looking for a company where can fuel your inspiration and cultivate your expertise, join us on our exciting journey.\n\nThe Job:\n\nMaintain the service standard and ensure the quality of work of the team\nInvolve in approving claims cases within own claims authority; make recommendation to senior management for those claims exceeding own authority limits\nTo coordinate BAU system enhancement activities to meet business priorities\nResponsible for handling enquiries and complaints from customers, sales force, other insurance regulatory bodies and internal staff\nBack-up teammate\u2019s work if necessary\n\nThe Person:\n\nUniversity graduate or above\nMinimum 5 years working experience in insurance claims\nProfessional qualification in Life Insurance including FLMI (Fellow, Life Management Institute), ALHC (Associate, Life and Health Claims), ACS (Associate, Customer Service)\nGood PC skills in MS Words, EXCEL, Powerpoint\nIndependent, and with high degree of responsibility\nFluent English and Cantonese\nGood written English and Chinese\n\nWe offer excellent learning & development opportunities and an attractive package to the right candidate.\n\nInformation collected will be treated in strict confidence and used solely for recruitment purpose. The company will retain all applications no longer than 24 months of which will be destroyed thereafter. When there are vacancies in any of our subsidiaries, holding companies, associated or affiliated companies of, or companies controlled by, or under common control with the Company during that period, we may transfer your application to them for consideration of employment. We are an equal opportunity employer. We do not discriminate on the basis of race, sex, disability or family status in employment process.", "employment_types": ["Full Time"], "selling_points": ["Flat structure, job flexibility and empowerment", "Fast-growing insurtech startup", "Work-life balance, medical benefits"], "locations": ["Ngau Tau Kok"], "categories": ["Insurance", "Claims Officer"], "post_time": "2022-01-10T07:56:22Z", "salary": {"currency": null, "max": null, "min": null, "period": "monthly", "term": null}, "salary_visible": false, "title_keywords": [], "responsibilities": [], "requirements": {"degrees": [], "majors": [], "languages": [], "language_level": [], "hard_skills": [], "soft_skills": [], "languages_combined": []}, "experience_required": {"duration": [], "field": []}}, {"job_id": "100003009037005", "location_code": "hk", "company": "Generali Life (Hong Kong) Limited", "job_title": "Head of NL Claims (Manager / Senior Manager)", "description": "In this role, you will carry out the instruction rendered by the Supervisor to meet or exceed satisfactory operating standards.\nMain Responsibilities:\nVerification of claims particulars before claim registration\nProcessing and settlement of Motor, Employees\u2019 Compensation and Personal Lines claims\nHandle and settle insurance claims within well-defined guidelines\nAnswer Claims Hotlines and general telephone enquiries\nApprove and validate claims settlement and cheque requisitions within the limit of authority\nIdentify and input the blacklisted clients and poor risk cancellation / revision of policy terms to Business Development and Underwriting Department\nApproach injured workers in order to identify EC problematic cases\nApproach motor policyholders guiding them in own damage claims with an aim to have their vehicles repaired in our approved repairers for costs savings purpose\nAssist in UAT\nAssist in ad hoc projects as assigned by supervisors\nTo meet the challenge, you should have the following qualifications and attributes:\nSecondary education or above\nAt least 2 years\u2019 relevant experience with general knowledge in the general insurance industry\nGeneral knowledge in general insurance claims\nGood command of both written and spoken English and Chinese\nGood communication and analytical skills\nGood computer skills\nPlease note that only shortlisted candidates will be notified.", "employment_types": ["Full Time", "Permanent"], "selling_points": [], "locations": ["Tai Koo"], "categories": ["Insurance", "Claims Officer", "Others", "Banking / Finance", "Order Processing & Operation / Settlement"], "post_time": "2022-01-11T01:17:07Z", "salary": {"currency": null, "max": null, "min": null, "period": "monthly", "term": null}, "salary_visible": false, "title_keywords": ["senior manager", "manager"], "responsibilities": ["uat", "guidelines", "communication", "ad hoc projects", "insurance", "costs"], "requirements": {"degrees": ["secondary education"], "majors": [], "languages": ["english", "chinese"], "language_level": ["good command"], "hard_skills": ["processing", "computer skills", "analytical skills"], "soft_skills": ["communication", "analytical skills"], "languages_combined": [{"language": "english", "language_level": ["good command"]}, {"language": "chinese", "language_level": ["good command"]}]}, "experience_required": {"duration": ["at least 2 years"], "field": ["general insurance", "relevant experience"]}}, {"job_id": "100003009036999", "location_code": "hk", "company": "Generali Life (Hong Kong) Limited", "job_title": "Head of NL Claims (Manager / Senior Manager)", "description": "\u00a0Responsibilities:\n\nProvide administrative assistance in the delivery of claims service for the Property & Casualty Insurance claims team\nMaintain daily operations of the team to ensure consistent, accurate and fair claims processing in a high level of integrity\nDetermine proper policy coverage to conclude, investigate, evaluate and negotiate assigned cases\nHandle cases involving litigation and direct settlement\nUpkeep the claim status and undertake periodical reviews\nHandle claims related enquiries and provide support to Claims Managers in preparing management report and statistics\nProvide ad-hoc administrative support to the department as assigned\nCoordinate and participate in UAT activities such as preparation of test plan, test cases, pre-UAT quality check, \u00a0monitoring of bug fixing, retest progress, UAT reports and post implementation monitoring\n\nQualifications:\n\nHigher Diploma/Tertiary educated with at least 4 years of relevant working experience\nPrevious exposure in the General Insurance industry is a definite advantage.\nExperience in a claims administrative role or policy administration activities would be preferred.\nGood communication and interpersonal skills.\nGood supervisory skills, strong career mind and enthusiastic about job\u00a0\nProficiency in computer skills, including MS Word, Excel and PowerPoint.\nCustomer-oriented, attentive to details and able to meet tight deadlines.\nGood command of spoken and written English and Chinese\n\nInterested candidates, please email us your full resume with current and expected remuneration package & available date.\n\nOnly shortlisted candidates will be notified. All data collected will be treated in strict confidentiality and used for recruitment purpose only. Personal data of unsuccessful applicants will be destroyed within 24 months", "employment_types": ["Full Time", "Permanent"], "selling_points": [], "locations": ["Tai Koo"], "categories": ["Insurance", "Claims Officer", "Others", "Banking / Finance", "Order Processing & Operation / Settlement"], "post_time": "2022-01-11T01:15:56Z", "salary": {"currency": null, "max": null, "min": null, "period": "monthly", "term": null}, "salary_visible": false, "title_keywords": ["senior manager", "manager"], "responsibilities": ["ad-hoc", "provide support", "quality check", "uat", "administrative support", "monitoring", "maintain daily operations", "implementation", "evaluate", "coordinate", "communication", "administrative assistance", "reports", "plan", "insurance", "management report", "administration"], "requirements": {"degrees": ["diploma"], "majors": [], "languages": ["english", "chinese"], "language_level": ["good command"], "hard_skills": ["excel", "powerpoint", "computer skills", "processing", "ms word"], "soft_skills": ["meet tight deadlines", "attentive to details", "integrity", "customer-oriented", "communication and interpersonal skills", "enthusiastic", "accurate"], "languages_combined": [{"language": "english", "language_level": ["good command"]}, {"language": "chinese", "language_level": ["good command"]}]}, "experience_required": {"duration": ["at least 4 years"], "field": ["administrative", "relevant working experience", "policy administration"]}}, {"job_id": "100003009038579", "location_code": "hk", "company": "AIG Insurance Hong Kong Limited", "job_title": "Assistant Customer Service Officer", "description": "\u00a0Responsibilities:\n\nProvide administrative assistance in the delivery of claims service for the Property & Casualty Insurance claims team\nMaintain daily operations of the team to ensure consistent, accurate and fair claims processing in a high level of integrity\nDetermine proper policy coverage to conclude, investigate, evaluate and negotiate assigned cases\nHandle cases involving litigation and direct settlement\nUpkeep the claim status and undertake periodical reviews\nHandle claims related enquiries and provide support to Claims Managers in preparing management report and statistics\nProvide ad-hoc administrative support to the department as assigned\nCoordinate and participate in UAT activities such as preparation of test plan, test cases, pre-UAT quality check, \u00a0monitoring of bug fixing, retest progress, UAT reports and post implementation monitoring\nQualifications\n\nHigher Diploma/Tertiary educated with at least 5 years of relevant working experience\nPrevious exposure in the General Insurance industry is a definite advantage.\nExperience in a property claims administrative role or policy administration would be preferred.\nGood communication and interpersonal skills.\nGood supervisory skills, strong career mind and enthusiastic about job\u00a0\nProficiency in computer skills, including MS Word, Excel and PowerPoint.\nCustomer-oriented, attentive to details and able to meet tight deadlines.\nGood command of spoken and written English and Chinese\n\nInterested candidates, please email us your full resume with current and expected remuneration package & available date.\n\nOnly shortlisted candidates will be notified. All data collected will be treated in strict confidentiality and used for recruitment purpose only. Personal data of unsuccessful applicants will be destroyed within 24 months from the date of receipt.", "employment_types": ["Full Time", "Permanent"], "selling_points": ["Administrative role", "Higher diploma or above, 1 year work experience", "5-day work, 15 days AL, birthday leave"], "locations": ["Quarry Bay"], "categories": ["Admin & HR", "Clerical / Admin Staff", "Sales, CS & Business Devpt", "Customer Service - Supervisor / Officer", "Insurance", "Claims Officer"], "post_time": "2022-01-11T07:25:31Z", "salary": {"currency": null, "max": null, "min": null, "period": "monthly", "term": null}, "salary_visible": false, "title_keywords": ["customer service officer", "assistant"], "responsibilities": ["ad-hoc", "provide support", "quality check", "uat", "administrative support", "monitoring", "maintain daily operations", "implementation", "evaluate", "coordinate", "communication", "administrative assistance", "reports", "plan", "insurance", "management report", "administration"], "requirements": {"degrees": ["diploma"], "majors": [], "languages": ["english", "chinese"], "language_level": ["good command"], "hard_skills": ["excel", "powerpoint", "computer skills", "processing", "ms word"], "soft_skills": ["meet tight deadlines", "attentive to details", "integrity", "customer-oriented", "communication and interpersonal skills", "enthusiastic", "accurate"], "languages_combined": [{"language": "english", "language_level": ["good command"]}, {"language": "chinese", "language_level": ["good command"]}]}, "experience_required": {"duration": ["at least 5 years"], "field": ["administrative", "relevant working experience", "policy administration"]}}, {"job_id": "100003009033011", "location_code": "hk", "company": "AXA Hong Kong", "job_title": "Assistant Claims Manager", "description": "OneDegree is a new generation of InsurTech that reimagining the industry with design and digital innovation. Our mission is to set new standards for insurance that puts customers first.\n\nWe are among the first batch of virtual insurers authorized by the Hong Kong Insurance Authority to provide insurance products purely through online channels. We pride ourselves on providing breakthrough innovations in products and services via our digital platform. We are currently offering Pet and Fire Insurance and expected to provide wider coverage to the general public in the coming year.\n\nWant to join us and make a change? We are looking for a Claims Assessor who support in processing insurance claims.\n\nIf you are detail-minded and self-motivated, come and join our team!\n\n\n\nWhat you will be doing:\n\nHandling claims enquiry and complaints\nData input for a new submission claim\nLiaising with medical professionals and customers to conduct assessment and investigation\nContacting customers to follow up outstanding issues\nSupporting project and business initiatives as assigned by superior\n\nWhat we are looking for:\n\nAt least 1 year of relevant working experience in Claims / insurance\nKnowledge in medical insurance is a plus!\nStrong sense of responsibility with high level of integrity and trust\nGood communicate and time management skills\nProficiency in MS office (Word, Excel), Chinese word processing is necessary.\nExcellent command of spoken and written in English and Chinese\nAbility to work independently, take direction, and prioritize accordingly\nAbility to work cross-functionally in a fast-paced environment\nHighly self-motivated, organized, and a team player\nWillingness and ability to operate in a team environment\n\nMore about us:\n\nFast-growing insurtech startup in Hong Kong\nYoung and energetic team\nFlat organization structure\nOpportunities to grow and shine!\n\nWe value our employees:\u00a0\n\nTo us, people are our greatest asset and we are more than happy to invest in employees! We create a healthy\u00a0work atmosphere and provide you with the tools and support for doing your job successfully.\u00a0With a culture of flexibility and transparency,\u00a0we believe there should be no barriers, and everyone\u2019s contributions matter.\n\nWe would like to be an \u2018EMPLOYER OF CHOICE\u2019!\u00a0", "employment_types": ["Full Time", "Permanent"], "selling_points": ["Claims", "Life Insurance Claims", "Life Insurance"], "locations": ["Southern Area"], "categories": ["Insurance", "Claims Officer", "Others"], "post_time": "2022-01-08T06:03:52Z", "salary": {"currency": null, "max": null, "min": null, "period": "monthly", "term": null}, "salary_visible": false, "title_keywords": ["assistant claims manager"], "responsibilities": ["online channels", "business initiatives", "management", "data input", "digital platform", "design", "liaising with", "investigation", "insurance"], "requirements": {"degrees": [], "majors": [], "languages": ["english", "chinese"], "language_level": ["proficiency", "excellent"], "hard_skills": ["excel", "plus", "no", "chinese word processing", "word", "make", "batch", "processing", "ms office"], "soft_skills": ["detail-minded", "organized", "self-motivated", "work independently", "sense of responsibility", "time management skills", "fast-paced environment", "integrity", "prioritize", "team player", "energetic", "superior"], "languages_combined": [{"language": "english", "language_level": ["excellent"]}, {"language": "chinese", "language_level": ["proficiency", "excellent"]}]}, "experience_required": {"duration": ["at least 1 year"], "field": ["insurance", "relevant working experience"]}}, {"job_id": "100003009030764", "location_code": "hk", "company": "The Tokio Marine and Fire Insurance Co (HK) Ltd", "job_title": "Senior Officer, Claims", "description": "Major responsibilities:\n\nManage and supervise the daily operations of the NL Claims Department;\nMonitor & approve claims within the pre-set authority and provide appropriate commentary, recommendations and justifications to senior management to seek approval when necessary;\nDevelop high-quality work teams with clear accountabilities and performance expectations to ensure the ability to deliver high performance;\nFormulate and implement P&C claims strategy and development plan to achieve the company objectives for profitability and growth;\nReview current work processes; identify gaps and provide improvements or solutions to increase proficiency and supervise effective resolution of all claim inquiries;\nDevelop processes such as claims rules, to facilitate claims automation;\nImplement the Group compliance policy to adhere to the relevant local and Group compliance procedures and obtain satisfactory audit and regulators\u2019 review reports;\nEngage in continuing education and training opportunities when possible;\nAnalyze all claims to ensure optimal quality; provide regular and management reports & statistics to various business units; clients and management;\nComplaint handling and resolving disputes;\nManage ad hoc projects as required.\n\nQualification and Experience Requirement:\n\n\nDegree holder or tertiary graduate with professional qualifications in insurance or related disciplines;\nAt least 10 years\u2019 experience in general insurance, with strong knowledge of the industry\u2019s challenges and competitive landscape. Candidates with less experience will be considered as Manager.\nStrategic thinking, planning, and organizational skills;\nResult-oriented, self-motivated, analytical, and detailed-minded in problem-solving;\nStrong interpersonal, communication, and presentation skill\nStrong sense of responsibility with a high level of integrity and trust;\nExperienced in project management and working with stakeholders management at the senior level\nGood command of English and Chinese in both written and spoken;\nSound PC skills in MS Word, Excel & PowerPoint", "employment_types": ["Full Time"], "selling_points": [], "locations": ["Admiralty"], "categories": ["Insurance", "Claims Officer"], "post_time": "2022-01-07T19:20:19Z", "salary": {"currency": null, "max": null, "min": null, "period": "monthly", "term": null}, "salary_visible": false, "title_keywords": ["senior officer"], "responsibilities": ["management", "review", "monitor", "quality", "teams", "develop", "resolution", "compliance", "daily operations", "procedures", "audit", "reports", "plan", "management reports", "ad hoc projects", "senior management"], "requirements": {"degrees": ["degree holder"], "majors": ["related disciplines", "insurance"], "languages": ["english", "chinese"], "language_level": ["good command"], "hard_skills": ["presentation skill", "excel", "professional qualifications", "problem-solving", "powerpoint", "project management", "pc skills", "ms word"], "soft_skills": ["presentation skill", "organizational skills", "self-motivated", "strategic thinking", "sense of responsibility", "problem-solving", "integrity", "communication", "project management", "interpersonal", "result-oriented", "detailed"], "languages_combined": [{"language": "english", "language_level": ["good command"]}, {"language": "chinese", "language_level": ["good command"]}]}, "experience_required": {"duration": ["at least 10 years"], "field": ["general insurance"]}}, {"job_id": "100003009030370", "location_code": "hk", "company": "China Taiping Insurance (HK) Company Limited", "job_title": "Claims Officer / Claims Assistant - Junior/Intermediate level", "description": "Major responsibilities:\n\nManage and supervise the daily operations of the NL Claims Department;\nMonitor & approve claims within the pre-set authority and provide appropriate commentary, recommendations and justifications to senior management to seek approval when necessary;\nDevelop high-quality work teams with clear accountabilities and performance expectations to ensure the ability to deliver high performance;\nFormulate and implement P&C claims strategy and development plan to achieve the company objectives for profitability and growth;\nReview current work processes; identify gaps and provide improvements or solutions to increase proficiency and supervise effective resolution of all claim inquiries;\nDevelop processes such as claims rules, to facilitate claims automation;\nImplement the Group compliance policy to adhere to the relevant local and Group compliance procedures and obtain satisfactory audit and regulators\u2019 review reports;\nEngage in continuing education and training opportunities when possible;\nAnalyze all claims to ensure optimal quality; provide regular and management reports & statistics to various business units; clients and management;\nComplaint handling and resolving disputes;\nManage ad hoc projects as required.\n\nQualification and Experience Requirement:\n\n\nDegree holder or tertiary graduate with professional qualifications in insurance or related disciplines;\nAt least 10 years\u2019 experience in general insurance, with strong knowledge of the industry\u2019s challenges and competitive landscape. Candidates with less experience will be considered as Manager.\nStrategic thinking, planning, and organizational skills;\nResult-oriented, self-motivated, analytical, and detailed-minded in problem-solving;\nStrong interpersonal, communication, and presentation skill\nStrong sense of responsibility with a high level of integrity and trust;\nExperienced in project management and working with stakeholders management at the senior level\nGood command of English and Chinese in both written and spoken;\nSound PC skills in MS Word, Excel & PowerPoint", "employment_types": ["Full Time"], "selling_points": ["Open to all university graduates and experienced", "ensure fair settlement of valid claims", "insurance claims handler in Property and Casualty"], "locations": ["North Point"], "categories": ["Insurance", "Claims Officer"], "post_time": "2022-01-07T07:20:26Z", "salary": {"currency": null, "max": null, "min": null, "period": "monthly", "term": null}, "salary_visible": false, "title_keywords": ["claims officer", "assistant", "junior"], "responsibilities": ["management", "review", "monitor", "quality", "teams", "develop", "resolution", "compliance", "daily operations", "procedures", "audit", "reports", "plan", "management reports", "ad hoc projects", "senior management"], "requirements": {"degrees": ["degree holder"], "majors": ["related disciplines", "insurance"], "languages": ["english", "chinese"], "language_level": ["good command"], "hard_skills": ["presentation skill", "excel", "professional qualifications", "problem-solving", "powerpoint", "project management", "pc skills", "ms word"], "soft_skills": ["presentation skill", "organizational skills", "self-motivated", "strategic thinking", "sense of responsibility", "problem-solving", "integrity", "communication", "project management", "interpersonal", "result-oriented", "detailed"], "languages_combined": [{"language": "english", "language_level": ["good command"]}, {"language": "chinese", "language_level": ["good command"]}]}, "experience_required": {"duration": ["at least 10 years"], "field": ["general insurance"]}}, {"job_id": "100003009029129", "location_code": "hk", "company": "Jobson Mores Limited", "job_title": "Insurance - Claims Senior Officer/Assistant Manager (Life)", "description": "Assist Claims Manager to support the claims team in claims investigation, daily claims operation, enquiry, and continuous claims process improvement\nAssess and approve complicated claims\nMonitor and control daily operations to be carried out smoothly\nTo ensure delivery of agreed service standards\nTo handle enquiries from distribution enquiry team, customer enquiry teams and complaint team\nReview staff performance, develop and monitor plan for staff development\nDrive and oversee plans for system modifications and to continue meeting, improving and anticipating customer needs and developing relationship with agency force\nImplement continuous claims process improvement to strive for operational efficiency\nProvide training to claim colleagues and other internal staff so as to uplift their claims knowledge\nReview and revise internal claims manuals, guidelines and practices\nTo assist in all operational and project issues\n\nReqirements\n\nUniversity graduate or above with FLMI or equivalent\nAt least 5-years' experience in Claims with at least 1 years in management position\nStrong technical skills and knowledge of Claims\nCustomer Centric minded and good communication skill\nResult-oriented, self-motivated, patient, cheerful and positive\nHigh emotional maturity and able to work under pressure\nExcellent command of both written and spoken English and Chinese, Mandarin is an advantage", "employment_types": ["Full Time"], "selling_points": ["3-5 years of claims experience", "Strong analytical and problem solving skills", "Multiple Vacancies/Mon-Fri Work"], "locations": ["Wan Chai"], "categories": ["Insurance", "Claims Officer", "Others", "Professional Services", "Translation"], "post_time": "2022-01-07T04:02:11Z", "salary": {"currency": null, "max": null, "min": null, "period": "monthly", "term": null}, "salary_visible": false, "title_keywords": ["senior officer", "assistant manager"], "responsibilities": ["provide training", "control", "management", "guidelines", "review", "monitor", "teams", "investigation", "develop", "developing", "handle enquiries", "service standards", "daily operations", "communication", "plan", "plans", "work under pressure"], "requirements": {"degrees": ["university graduate or above"], "majors": [], "languages": ["english", "chinese", "mandarin"], "language_level": ["advantage", "excellent"], "hard_skills": [], "soft_skills": ["self-motivated", "cheerful", "communication skill", "technical skills", "patient", "result-oriented", "positive", "work under pressure"], "languages_combined": [{"language": "english", "language_level": ["excellent"]}, {"language": "chinese", "language_level": ["excellent"]}, {"language": "mandarin", "language_level": ["advantage", "excellent"]}]}, "experience_required": {"duration": ["at least 1 years"], "field": ["management position"]}}, {"job_id": "100003009036142", "location_code": "hk", "company": "Hong Kong Medical Consultants Limited", "job_title": "Insurance Clerk", "description": "Job Responsibilities :\n\nAccess and process the Marine Cargo Claims\u00a0\u00a0\nProvide claims service and handle claims enquires to customers (internal & external)\u00a0\nAssist in preparing claims statistics / report\nOther ad hoc projects as required\n\n\u00a0Job requirements:\n\nDiploma or above with recognized insurance professional qualification\nMember of ANZIIIF (Snr. Associate) or CII\nMinimum of\u00a0 3 years' experience in handling Marine Cargo claims or equivalent is preferable\u00a0\nFluent in spoken and written English & Cantonese\nProficiency in PC skills including MS Word, Excel and AS400\nAble to work independently and under pressure\nGood communication and interpersonal skills\nStrong sense of responsibility, Organized and Detail minded\n\n(Applicants with lesser experience will be considered as Officer)", "employment_types": ["Full Time"], "selling_points": ["Handle general enquiries & insurance", "Experience in insurance field preferred", "Good interpersonal skill"], "locations": ["Central"], "categories": ["Insurance", "Claims Officer", "Others", "Medical Services", "Others"], "post_time": "2022-01-10T09:27:09Z", "salary": {"currency": null, "max": null, "min": null, "period": "monthly", "term": null}, "salary_visible": false, "title_keywords": ["clerk"], "responsibilities": ["ad hoc projects", "report"], "requirements": {"degrees": ["diploma or above"], "majors": ["insurance"], "languages": ["cantonese", "english"], "language_level": ["fluent"], "hard_skills": ["excel", "pc skills", "ms word"], "soft_skills": ["organized", "work independently", "under pressure", "sense of responsibility", "communication and interpersonal skills"], "languages_combined": [{"language": "cantonese", "language_level": ["fluent"]}, {"language": "english", "language_level": ["fluent"]}]}, "experience_required": {"duration": ["3 years"], "field": []}}, {"job_id": "100003009034301", "location_code": "hk", "company": "BUPA Asia Limited", "job_title": "Senior Advisor, Case Management", "description": "Job Description\n\nAs an insurance claims handler\u00a0in Property and Casualty,\u00a0you'll be involved in managing a claim from the start through to settlement, making decisions on the extent and validity of a claim, and checking for any potential fraudulent activity.\n\nYou'll coordinate services that may be required by policyholders following an accident or incident.\n\nJob Responsibilities:\n\n1.\u00a0provide advice on making a claim and the processes involved\n\n2.\u00a0collect accurate information and documents to proceed with a claim\n\n3.\u00a0analyse a claim made by a policymaker to establish whether it satisfies the policy conditions\n\n4.\u00a0guide policyholders on how to proceed with the claim\n\n5.\u00a0contact service provider from a network of approved professionals\n\n6.\u00a0monitor the progress of a claim\n\n7.\u00a0ensure fair settlement of a valid claim\n\nQualifications:\n\nOpen to all university graduates and experienced claims handler.\n\nSkills:\n\n1.\u00a0excellent interpersonal and customer service skills\n\n2.\u00a0negotiation, questioning and decision-making skills\n\n3.\u00a0good planning and analytical skills\n\n4.\u00a0communication skills and confidence when dealing with people, often in difficult circumstances\n\n5.\u00a0organisational and time management skills\n\n6.\u00a0the ability to work well under pressure", "employment_types": ["Full Time", "Permanent"], "selling_points": ["4 years\u2019 relevant working experience in medical", "Assess Preauthorization Application", "Lead a team"], "locations": ["Not Specified"], "categories": ["Insurance", "Claims Officer", "Others", "Medical Services", "Others"], "post_time": "2022-01-10T03:06:47Z", "salary": {"currency": null, "max": null, "min": null, "period": "monthly", "term": null}, "salary_visible": false, "title_keywords": ["advisor"], "responsibilities": ["management", "monitor", "checking", "coordinate", "communication", "provide advice", "customer service", "contact", "planning", "insurance", "analyse"], "requirements": {"degrees": [], "majors": [], "languages": [], "language_level": [], "hard_skills": ["analytical skills"], "soft_skills": ["customer service skills", "communication skills", "confidence", "under pressure", "negotiation", "time management skills", "analytical skills", "accurate", "interpersonal"], "languages_combined": []}, "experience_required": {"duration": [], "field": []}}, {"job_id": "100003009036611", "location_code": "hk", "company": "Bluemont Consulting", "job_title": "Reinsurance / Treaty specialist (contract drafting)", "description": "Assess and approve Life Claims\u00a0within authority\nEnsure the claims handled are complied with guidelines\nProvide recommendations and justifications to seek approval when necessary\nConduct investigation of suspicious claims\nResponsible for complaint and inquiries\nAssist Manager to review and update procedures and guidelines\n\nQualification\u00a0Requirements\u00a0\n\nDegree Holder\nPossess FLMI / ACII / ANZIIF or in progress\n4-5 years\u2019 experience in supervisory position of Life / EB Department\nStrong Medical Knowledge background would be an advantage\nGood command of both written and spoken English\n\nOther Job Openings\n\n\nPlease visit \u201cJoin Us\u201d in our website\u00a0http://www.asiainsurance.hk\n\nAt\u00a0Asia\u00a0 Insurance\u00a0 Co.,\u00a0 Ltd.,\u00a0 we\u00a0 are\u00a0 committed\u00a0 to\u00a0 offer\u00a0 good\u00a0 career\u00a0 prospects, 5\u00a0 days\u00a0 week, 16 days\u00a0 Annual\u00a0 Leave, Birthday Leave,\u00a0competitive remuneration and benefits package. \u00a0\n\nInterested parties may apply with full resume including present & expected salary, contact phone number, job reference code above and send it to\u00a0Human\u00a0 Resources\u00a0 Department,\u00a0 Asia\u00a0 Insurance\u00a0 Co.,\u00a0 Ltd., 8/F\u00a0 118 Connaught\u00a0 Road\u00a0 West, Sheung Wan, Hong Kong\u00a0or click \"Apply Now\" to submit your application. Applicants who are not contacted within one month may consider their applications unsuccessful.\n\nAll information provided by applicants\u00a0 will be used in the strictest confidential in accordance\u00a0 with the employer's personal data policy, and\u00a0 will\u00a0 be\u00a0 handled\u00a0 by\u00a0 authorized\u00a0 personnel\u00a0 for\u00a0 recruitment-related\u00a0 purposes\u00a0 only.\u00a0 Applicants\u00a0 may\u00a0 be\u00a0 considered\u00a0 for\u00a0 other\u00a0 suitable positions within the Company and our subsidiary or associate companies over a four-month period, after which their personal data will be destroyed.", "employment_types": ["Permanent"], "selling_points": ["Global reinsurance player", "Stable working environment", "Can consider people from Underwriting or Claims"], "locations": ["Central & Western Area"], "categories": ["Insurance", "Actuarial", "Claims Officer", "Underwriter"], "post_time": "2022-01-10T11:22:56Z", "salary": {"currency": "HKD", "max": 44999, "min": 30000, "period": "monthly", "term": null}, "salary_visible": true, "title_keywords": ["specialist"], "responsibilities": ["guidelines", "review", "procedures", "website", "investigation", "provide recommendations", "insurance"], "requirements": {"degrees": ["degree holder"], "majors": [], "languages": ["english"], "language_level": ["good command"], "hard_skills": [], "soft_skills": ["committed", "responsible"], "languages_combined": [{"language": "english", "language_level": ["good command"]}]}, "experience_required": {"duration": ["4-5 years"], "field": ["supervisory"]}}, {"job_id": "100003009036461", "location_code": "hk", "company": "Sinoasia Alliance Group Limited", "job_title": "Operation Executive Trainee", "description": "Responsibilities:\n\nHandle inbound calls from internal and external customers for general enquiries & insurance\nHandle patient\u2019s insurance related administrative and clerical work including quotation, pre-approval form, medical voucher and claim form\nRegular contact with insurance company/hospital/clinic/doctor for following up of claims cases\nAssist in ad-hoc projects assigned\n\nRequirement:\n\nHKDSE or above\nMinimum 1 to 2 years working experience in insurance field preferred\nResponsible, proactive and well-organized\nGood interpersonal & communication skills\nGood command\u00a0of both written and spoken\u00a0English and Chinese, knowledge in Putonghua will be an advantage\nProficiency in PC applications including\u00a0MS\u00a0Word, Excel,\u00a0Powerpoint, Outlook and\u00a0Chinese Word Processing", "employment_types": ["Full Time", "Permanent"], "selling_points": ["Minimum Education - Degree Holder", "No Work Experience Required", "15k Basic Salary"], "locations": ["Tsim Sha Tsui"], "categories": ["Insurance", "Claims Officer", "Insurance Agent / Broker", "Underwriter"], "post_time": "2022-01-10T16:52:50Z", "salary": {"currency": null, "max": null, "min": null, "period": "monthly", "term": null}, "salary_visible": false, "title_keywords": ["trainee", "operation executive"], "responsibilities": ["internal and external customers", "quotation", "contact", "ad-hoc projects", "insurance"], "requirements": {"degrees": ["hkdse"], "majors": [], "languages": ["putonghua", "english", "chinese"], "language_level": ["advantage", "proficiency", "good command"], "hard_skills": ["excel", "chinese word processing", "powerpoint", "pc applications", "outlook", "ms word"], "soft_skills": ["communication skills", "responsible", "well-organized", "proactive", "interpersonal"], "languages_combined": [{"language": "putonghua", "language_level": ["advantage", "good command"]}, {"language": "english", "language_level": ["advantage", "good command"]}, {"language": "chinese", "language_level": ["advantage", "proficiency", "good command"]}]}, "experience_required": {"duration": ["minimum 1 to 2 years"], "field": ["insurance"]}}, {"job_id": "100003009025077", "location_code": "hk", "company": "BOC Group Life Assurance Company Ltd", "job_title": "Senior Claims Officer", "description": "Position Overview\n\nResponsible for drafting treaties/amendments and agreements in a timely manner to support the execution of won deals and support administrative and corporate tasks in order to meet functional objectives.\n\nResponsibilities\n\n\u00a0\u00a0\u00a0\u00a0\u00a0\u00a0\u00a0\u00a0 Prepares treaties/amendments and and any other related contract documents (e.g. letter of intent, confidentiality agreement, service agreement etc.), using best practices standard treaty template, that accurately reflects the underlying quote and are in line with appropriate treaty process and guidelines;\n\u00a0\u00a0\u00a0\u00a0\u00a0\u00a0\u00a0\u00a0 Evaluates client prepared documents and propose necessary recommendations for change, resolve and/or escalate differences and inconsistencies in comparison to the companies best practice wordings ensuring all issues are appropriately addressed;\n\u00a0\u00a0\u00a0\u00a0\u00a0\u00a0\u00a0\u00a0 Obtains comments, necessary approvals and responds to treaty related inquiries internally/externally;\n\u00a0\u00a0\u00a0\u00a0\u00a0\u00a0\u00a0\u00a0 Maintains contact and build relationships with outside legal and treaty resources;\n\u00a0\u00a0\u00a0\u00a0\u00a0\u00a0\u00a0\u00a0 Ensures treaty templates and clauses are completed and approved as required and meet the needs of the business unit and comply with Divisional standards, local regulations and business practices;\n\u00a0\u00a0\u00a0\u00a0\u00a0\u00a0\u00a0\u00a0 Completes Signature Request Form (SRF) for treaty documents and obtains authorized signatures for the treaty finalization;\n\u00a0\u00a0\u00a0\u00a0\u00a0\u00a0\u00a0\u00a0 Sends treaty documents to clients for signature and follow up;\n\u00a0\u00a0\u00a0\u00a0\u00a0\u00a0\u00a0\u00a0 Monitors status of outstanding documentation to ensure service standards are met and report/escalate to management as required;\n\u00a0\u00a0\u00a0\u00a0\u00a0\u00a0\u00a0\u00a0 Updates TIMS (Treaty Information Management System) throughout the process and ensures final TIMS entry is completed and accurate;\n\u00a0\u00a0\u00a0\u00a0\u00a0\u00a0\u00a0\u00a0 Acts as an on-the-job trainer for educating new staff as to reinsurance treaties;\n\u00a0\u00a0\u00a0\u00a0\u00a0\u00a0\u00a0\u00a0 Assists in preparation for, negotiation on and resolving disputes/lawsuits;\n\u00a0\u00a0\u00a0\u00a0\u00a0\u00a0\u00a0\u00a0 Performs other duties as assigned.\n\nRequirements\n\n\u00a0\u00a0\u00a0\u00a0\u00a0\u00a0\u00a0\u00a0 Bachelor degree;\n\u00a0\u00a0\u00a0\u00a0\u00a0\u00a0\u00a0\u00a0 Minimum 5 years\u2019 working experience; knowledge of the life insurance/reinsurance industry, types of reinsurance arrangements and reinsurance treaty provisions will be viewed favorably;\u00a0\n\u00a0\u00a0\u00a0\u00a0\u00a0\u00a0\u00a0\u00a0 Ability of technical writing and editing;\n\u00a0\u00a0\u00a0\u00a0\u00a0\u00a0\u00a0\u00a0 Advanced oral and written communication skills in English, in particular a persuasion skill to resolve issues/problems is an advantage;\n\u00a0\u00a0\u00a0\u00a0\u00a0\u00a0\u00a0\u00a0 Highly organized and ability to meet tight deadlines;\n\u00a0\u00a0\u00a0\u00a0\u00a0\u00a0\u00a0\u00a0 Detail-oriented, efficient, ability to multitask and work independently;\n\u00a0\u00a0\u00a0\u00a0\u00a0\u00a0\u00a0\u00a0 Self-motivated with strong interpersonal skills;\n\u00a0\u00a0\u00a0\u00a0\u00a0\u00a0\u00a0\u00a0 Very discrete in handling confidential information;\n\u00a0\u00a0\u00a0\u00a0\u00a0\u00a0\u00a0\u00a0 Flexibility to adapt to changes;\n\u00a0\u00a0\u00a0\u00a0\u00a0\u00a0\u00a0\u00a0 Good command of computer skills such as MS Word and Excel.", "employment_types": ["Full Time"], "selling_points": [], "locations": ["Tai Koo"], "categories": ["Insurance", "Claims Officer"], "post_time": "2022-01-06T03:23:30Z", "salary": {"currency": null, "max": null, "min": null, "period": "monthly", "term": null}, "salary_visible": false, "title_keywords": ["claims officer"], "responsibilities": ["regulations", "management", "other duties", "guidelines", "comments", "service standards", "contact", "documentation", "report"], "requirements": {"degrees": ["degree", "bachelor"], "majors": [], "languages": ["english"], "language_level": ["advantage"], "hard_skills": ["excel", "computer skills", "ms word"], "soft_skills": ["efficient", "organized", "communication skills", "oral", "meet tight deadlines", "advanced", "work independently", "self-motivated", "detail-oriented", "interpersonal skills", "ability to multitask"], "languages_combined": [{"language": "english", "language_level": ["advantage"]}]}, "experience_required": {"duration": ["minimum 5 years"], "field": []}}, {"job_id": "100003009033317", "location_code": "hk", "company": "Polaris Consultancy Limited", "job_title": "Operation/Customer Services (Pensions/Life.General Insurance)", "description": "Job Duties\n\nTo support and assist the Chief Broking Manager of Sinoasia Broking on activities of their operations around the world, including but not limited to China, HKSAR, Kazakhstan, South Korea, Malaysia, Mongolia and the United Kingdom.\u00a0\nTo travel on business to China Mainland and overseas required, as pandemic situations permit.\nTo receive professional and on-the-job training on risk and insurance management provided by Sinoasia Alliance Group\u00a0\u00a0\n\nSpecific Responsibilities\n\nTo assist the Deputy Head of Sinoasia Broking on all insurance broking activities with international insurance markets, including but not limited to:-\n\nPreparation of insurance/reinsurance broking information,\nNegotiation with insurance and reinsurance markets and companies around the world;\nManagement of insurance claims, etc.", "employment_types": ["Full Time"], "selling_points": ["Pensions operation role, contribution, enrollment", "Life insurance claims, General Insurance support", "Life and Pensions customer services call centre"], "locations": ["Not Specified"], "categories": ["Sales, CS & Business Devpt", "Customer Service - Supervisor / Officer", "Insurance", "Claims Officer", "Banking / Finance", "Order Processing & Operation / Settlement"], "post_time": "2022-01-09T07:35:01Z", "salary": {"currency": null, "max": null, "min": null, "period": "monthly", "term": null}, "salary_visible": false, "title_keywords": [], "responsibilities": ["operations", "management", "insurance"], "requirements": {"degrees": [], "majors": [], "languages": [], "language_level": [], "hard_skills": [], "soft_skills": ["negotiation"], "languages_combined": []}, "experience_required": {"duration": [], "field": []}}, {"job_id": "100003009027293", "location_code": "hk", "company": "Allianz Worldwide Partners (Hong Kong) Limited", "job_title": "Claims Officer/Senior Claims Officer", "description": "We are currently seeking a Claims Senior Officer/Assistant Manager (Life)\u00a0\n\nRESPONSIBILITIES:\n\nAssist the superior(s) for managing the claims team to provide quality claims services to both internal and external customers including day-to-day claims operations\nPreparation of various management reports, adjudicating claims cases with prescribed limit and conducting claims related training to internal and external customers.\u00a0\nIn addition, he /she would be expected to assist in departmental projects/initiatives to ensure continuous improvement of the claims services.\nREQUIREMENTS\n\nDegree holder, preferrably with professional insurance qualification (e.g. FLMI or CFP).\n3 - 5 years of relevant working experience in life claims\u00a0\nGood communication skill with customer-centric mindset\nStrong analytical and problem solving skills\nAble to work under high pressure with professional business acumen\nFamiliar with MS Word, Excel & PowerPoint\nProficient in spoken & written English & Chinese (Cantonese & Mandarin)\n\nAPPLY FOR THIS JOB\n\nInterested candidate please\u00a0CLICK\u00a0apply button to apply online or send your resume in MS word format to\u00a0Jobson Mores Recruitment\n\nPlease note that only shortlisted candidate will be notified. All information will be treated in strict confidence and solely used for recruitment purposes.", "employment_types": ["Full Time", "Permanent"], "selling_points": ["Being part of the Global 500 - Allianz", "Competitive remuneration and benefits package", "Manage all claim and reinsurance matters"], "locations": ["Tai Koo"], "categories": ["Sales, CS & Business Devpt", "Customer Service - Supervisor / Officer", "Insurance", "Claims Officer", "Others"], "post_time": "2022-01-06T09:37:18Z", "salary": {"currency": null, "max": null, "min": null, "period": "monthly", "term": null}, "salary_visible": false, "title_keywords": ["claims officer"], "responsibilities": ["internal and external customers", "management reports", "quality", "operations"], "requirements": {"degrees": ["degree holder"], "majors": ["insurance"], "languages": ["cantonese", "english", "chinese", "mandarin"], "language_level": ["proficient"], "hard_skills": ["excel", "powerpoint", "acumen", "problem solving skills", "ms word"], "soft_skills": ["confidence", "communication skill", "analytical and problem solving skills", "work under high pressure", "business acumen"], "languages_combined": [{"language": "cantonese", "language_level": []}, {"language": "english", "language_level": ["proficient"]}, {"language": "chinese", "language_level": ["proficient"]}, {"language": "mandarin", "language_level": []}]}, "experience_required": {"duration": ["3 - 5 years"], "field": ["relevant working experience"]}}, {"job_id": "100003009024320", "location_code": "hk", "company": "FWD Life Insurance Company (Bermuda) Limited", "job_title": "Officer / Senior Officer, Claims, Employee Benefits", "description": "Polaris Consultancy Limited reaches 23rd Anniversary.\n\n\u00a0\u00a0**Visit our Website:\u00a0http://www.polariscl.com.hk/\u00a0for\u00a0job details.\u00a0\u00a0\u00a0\n\nOn behalf of clients, we are seeking high calibre candidates for the following:\u00a0\u00a0\n\nPosition:\u00a0Operation/Customer Services (Pensions/Life.General Insurance)\u00a0-\u00a0Many\n\nPositions offered would be depending on the qualifications and experience of the candidates.\u00a0\u00a0\u00a0\n\n\nRESPONSIBILITIES:\u00a0\u00a0\u00a0\u00a0\n\nTo\u00a0execute\u00a0any\u00a0of the following\u00a0job functions:\u00a0 \u00a0\u00a0\n\na).\u00a0 Supervisor\u00a0(Pensions Operations)\u00a0\n\n\nAssist the Manager in managing team members with respect to standards of accuracy, timeliness and productivity.\nEnsure smooth running of the assigned accounts, resolve complicated issues and escalate the situations when necessary.\nHandling customers' enquiries and complaints, providing possible solutions.\nStaff coaching and support staff development plans\nImplement procedures, processes and projects for process streamlining of operations and service improvement initiatives.\nb).\u00a0 Assistant Officer (Pensions operation)\u00a0\n\nManage the assigned MPF/ ORSO scheme accounts & perform daily MPF administration functions of employer/member enrolment, contribution, termination and data change within the company under minimum supervision\nAble to perform the majority of processing transactions in an accurate and timely manner\nHandle client\u2019s enquiries or complaints, and escalate to the manager if appropriate\nAssist in process streamlining and service improvement initiatives\nPerform UAT of system enhancement projects\nSupport ad-hoc projects as required\n\nc).\u00a0 Fund & Scheme Accounting (Accounting Assistant)\n\n\nHandling daily scheme investment order and fund transfer\nReconciling daily fund prices and investment fund unit movement\nHandling bank reconciliation and unit holding reconciliation periodically\nPreparing monthly scheme general ledgers\nd).\u00a0 \u00a0Senior Claims Officer\u00a0\nHandle claims enquiries and deliver claims servicing support to customers and agents\nFollow up claims cases with agent/ customer/ physician/ hospital\nAssist in claims adjudication\nTake part in departmental projects/ ad hoc task provided by the management\n\ne).\u00a0\u00a0Administration Assistant/Officer (General Insurance Marketing) - x 2\n** positions offered depends on the individual's experience\n\nMonitor policies/endorsements/declarations to/from insurers/clients\nPrepare renewal and quotation slips\nTo assist in ad-hoc duties when required\n\nf).\u00a0 Senior Officer/Officer\u00a0(Life Insurance, Customer Service Call Centre)\u00a0\n\nMeet service standards and KPIs according to internal guidelines and rules\nConduct various outbound calls with documented protocols\nLiaise with internal departments, channels and customers on replies to enquiries and required documents\nMaintain and improve quality results by adhering to standards and guidelines; recommending improved procedures.\nProvide customers with product and service information\nIdentify and escalate priority issues\nDocument all call information according to standard operating procedures\nParticipate in customer service-related projects and provide recommendations to improve work processes and service levels of the team.\n\n\ng).\u00a0 Officer/Senior Representative/Representative\u00a0(Pensions, Customer Service Call Centre)\n\nFollow up customer enquiries and feedback with good quality standard\u00a0\nEnsure the delivery of service meet with our service standard & comply with regulatory requirements\n\nREQUIREMENTS:\u00a0\u00a0\u00a0\u00a0\n\nA. \u00a0General Requirements\u00a0\n\nSecondary, Associate, HD, Degree in Business Administration or other disciplines\nAble to work under high pressure with professional business acumen\nHighly adaptable to changes with a flexible and positive working attitude\nFamiliar with MS Word, Excel & PowerPoint\nExcellent written and verbal communication skills in both English and Chinese (Cantonese and Mandarin)\u00a0\u00a0\u00a0\u00a0\u00a0\n\nB. \u00a0Experience Requirements\u00a0\n\na).\u00a0\u00a0for\u00a0\u00a0Supervisor\u00a0requires at least \u00a07 years solid experience in handling MPF administration and in a supervisory role.\n\nb).\u00a0 for\u00a0\u00a0Assistant Officer (Pensions Operations) requires at least 2- 3 years working experience in pensions administration.\n\nc).\u00a0\u00a0for\u00a0\u00a0Fund & Scheme Accounting (Accounting Assistant)\u00a0requires\u00a0Diploma in Finance/ Accounting or any equivalent disciplines, with at\u00a0least 1 year of working experience in finance or accounting field.\n\nd).\u00a0\u00a0for\u00a0Senior Claims Officer\u00a0requires at\u00a0 least\u00a03 years of life claims experience, customer-service mindset with effective interpersonal and communication skill.\n\ne).\u00a0\u00a0for\u00a0\u00a0Administration Assistant/Officer (GI Marketing)\u00a0requires at least\u00a02 years of insurance experience preferably in a broking firm.\n\nf). \u00a0for\u00a0Senior Officer/Officer\u00a0(Life Insurance\u00a0Customer Service Call Centre)\u00a0\u00a0requires\u00a04 years in client service with good knowledge of insurance industry preferred\n\ng). \u00a0for\u00a0Officer/Senior Representative/Representative\u00a0(Pensions\u00a0Customer Service Call Centre)\u00a0requires\u00a0at least 1-year experience in\u00a0banking and financial industries, customer-focused with positive attitude & communication skills.\u00a0 Willing to take an examination for\u00a0MPF.\u00a0\u00a0\n**Candidate with more experience will be considered for\u00a0Senior Client Service Representative or Officer\u00a0position\n\n\n\nNote: Positions offered would be depending on the qualifications and experience of the candidates.\u00a0\u00a0\u00a0\n\n\nCOMPANY OVERVIEW\n\nWe are experienced human resources professionals. Our expertise is in our in-depth knowledge of all industries, be it IT, financial, insurance, trading, manufacturing, industrial, and engineering fields. We also offer professional advice on an individual's career path and on the latest job market.\n\n**We also provide the service of seeking work visa for expatriate candidates on behalf of the employer**\n\n**Tel:\u00a025811913**\u00a0\nVisit\u00a0our\u00a0website:\u00a0\u00a0http://www.polariscl.com.hk/\u00a0for more\u00a0job details.\u00a0\n\nApplication Method\nQuoting job title by sending\u00a0Word\u00a0resume to:\u00a0\nTeresa Choy\nPolaris Consultancy Ltd\nEnquiry: 852-25811913", "employment_types": ["Full Time"], "selling_points": ["Handle inpatient and outpatient claims assessment", "Check and authorize claims settlement", "Support project and business initiatives"], "locations": ["Sheung Wan"], "categories": ["Insurance", "Claims Officer"], "post_time": "2022-01-05T14:26:43Z", "salary": {"currency": null, "max": null, "min": null, "period": "monthly", "term": null}, "salary_visible": false, "title_keywords": ["officer", "senior officer"], "responsibilities": ["service standard", "data", "operations", "regulatory requirements", "quotation", "quality", "bank reconciliation", "transactions", "service standards", "customer service", "maintain", "liaise with", "plans", "ad-hoc projects", "administration", "ad hoc", "uat", "monitor", "kpis", "management", "mpf", "customer enquiries", "procedures", "provide recommendations", "ad-hoc duties", "enhancement projects", "guidelines", "policies", "insurance"], "requirements": {"degrees": ["diploma", "degree"], "majors": ["finance", "accounting", "business administration"], "languages": ["cantonese", "english", "chinese", "mandarin"], "language_level": ["excellent"], "hard_skills": ["excel", "scheme", "powerpoint", "acumen", "word", "c", "ms word"], "soft_skills": ["flexible", "communication skills", "customer-focused", "adaptable", "communication skill", "positive attitude", "positive working attitude", "customer service", "work under high pressure", "business acumen", "interpersonal"], "languages_combined": [{"language": "cantonese", "language_level": ["excellent"]}, {"language": "english", "language_level": ["excellent"]}, {"language": "chinese", "language_level": ["excellent"]}, {"language": "mandarin", "language_level": ["excellent"]}]}, "experience_required": {"duration": ["at least 2- 3 years", "least 3 years", "at least 1-year", "7 years", "at least 2 years", "at least 1 year"], "field": ["supervisory", "pensions administration", "financial", "finance", "mpf administration", "marketing", "customer service", "insurance", "banking", "accounting", "administration"]}}, {"job_id": "100003009021051", "location_code": "hk", "company": "AXA Hong Kong", "job_title": "Senior Claims Officer", "description": "Job Description\nThe jobholder will be responsible for the administrative/case support duties of Case Management/TPA team in accordance with the standard operating procedure of the department, including:\n\nProcess pre-authorization for customers according to the policy\u2019s administration guidelines\nCoordinate with various service providers to ensure that all hospitalization and/or surgical requirements are satisfied\nHandle provider enquiry hotline\nProvide administrative support to the team including handle incoming/outgoing mails and documents, filing and maintain relevant records\nPrioritizing workloads effectively; working to team SLA\u2019s whilst maintaining quality of work\nLead a team to facilitate team members to achieve above\nPerforms other related duties as required\n\nEducation & Experience:\n\n\n4 years\u2019 relevant working experience in medical insurance\nUniversity Graduate or professional qualification, preferably with LOMA qualification, medical discipline or equivalent\nStrong verbal and written communication skills, experience in communicating with healthcare providers is preferred\nSkills in analyzing & resolving problems.\nProficiency in MS office applications\nFluency in written and spoken English and Cantonese. Mandarin is an advantage.\u00a0\nBupa offers 5 days\u2019 work per week and comprehensive remuneration packages including base salary, study assistance plan, company pension plan, life and medical benefit, dental benefit, annual leave, examination leave, etc.\nBupa is an equal opportunity employer and welcomes applications from qualified candidates. Information provided will be treated in strict confidence and only be used for consideration of application with Bupa.\nPersonal data collected will be used for recruitment purposes only. Only candidates selected for interviews will be contacted. Bupa will be in touch for any opportunities that matches your profile. All personal data of unsuccessful application will be destroyed 24 months from the date of receiving the application.", "employment_types": ["Full Time", "Permanent"], "selling_points": ["Corporate role in Life Claims team", "Possesses around 3-years' experience in claims", "Good opportunity to develop managerial skills"], "locations": ["Not Specified"], "categories": ["Insurance", "Claims Officer"], "post_time": "2022-01-05T02:58:23Z", "salary": {"currency": null, "max": null, "min": null, "period": "monthly", "term": null}, "salary_visible": false, "title_keywords": ["claims officer"], "responsibilities": ["management", "maintaining", "guidelines", "coordinate with", "quality", "communication", "lead a team", "maintain", "communicating with", "recruitment", "plan", "provide administrative support", "personal data", "insurance", "administration"], "requirements": {"degrees": ["university graduate"], "majors": [], "languages": ["cantonese", "english", "mandarin"], "language_level": ["fluency", "advantage"], "hard_skills": ["sla", "ms office"], "soft_skills": ["outgoing", "communication skills", "confidence", "responsible", "comprehensive", "prioritizing"], "languages_combined": [{"language": "cantonese", "language_level": ["fluency"]}, {"language": "english", "language_level": ["fluency"]}, {"language": "mandarin", "language_level": ["advantage"]}]}, "experience_required": {"duration": ["4 years"], "field": ["healthcare", "relevant working experience", "education", "insurance", "medical"]}}, {"job_id": "100003009025724", "location_code": "hk", "company": "Fillture Group Limited", "job_title": "Claims Manager / Assistant Claims Manager", "description": "Allianz Partners is a leading Insurance provider globally. With relevant industry background, understanding of our customers\u2019 needs, the successful candidate will play a key role within our call centre team in providing high standards of customer service and answer any queries covering Travel Insurance, Road Side Assistance and Extended Warranty\n\n\n\nJob Purpose:\u00a0\n\nManage all claim related matters and reinsurance activities\nProvide service to customers and designated accounts management\nAssist in enhancing the systems and workflows\nAssist in production of all reporting activities\n\nAccountabilities:\n\n\nHandle claims in compliance with company guidelines and manuals\nExercise prudence in the process, investigation and settlement of claims\nProvide high standard and timely customer services in accordance with the agreed guidelines and manuals\nManage all classes of claims and recovery proactively, discuss and review contentious, large and complex claims with fellow adjusters and management to obtain opinions/feedback\nCoordinate and liaise with partners / customers / internals / externals on claim related matters\nManage timely production of management information reports (e.g. monthly major claims movements) and proactively identify loss trends\nSupport establishment of claims management procedures on new business accounts in association with clients, brokers and loss adjusters, workshops\nEnsure unpursued claims are settled in accordance with settlement guidelines\nDevelop and maintain strong relationships with key brokers and clients and other relevant stakeholders (e.g. workshops, third party adjusters\u00a0etc.)\nAny other duties as and when deemed necessary\n\nRequirements:\n\n\nBachelor degree or above\nAt least 5 years of experience in general insurance claims handling and management, especially in automotive, property, liability and health related personal insurance; candidate with less experience will be considered as Claims Officer\nKnowledge of claims handling process and reserving principles & practices\nCompletion of professional insurance qualification (e.g. ACII/ Fellowship of ANZIIF) is preferred.\nCustomer-oriented with excellent communication and interpersonal skills\nStrong team player, willing to learn, able to work independently and under pressure\nGood analytical, self-motivated and open-minded problem solving skills\nProactive and receptive to new ideas and cope well with changes\nGood command of English, Cantonese and Putonghua in both written and spoken\nPC skills in MS Word, Excel & PowerPoint & Chinese word processing\n\nApplication Process:\n\nCompetitive remuneration and benefits package will be offered. Please send your application, with details of current and expected salary to Human Resources Division, Allianz Worldwide Partners (Hong Kong) Limited by clicking \"Apply Now\" button.\u00a0Personal data collected will be used for recruitment purpose only.", "employment_types": ["Full Time", "Permanent"], "selling_points": ["Global Renowned Insurance Brand", "Manage the daily operation of Claims", "Attractive Salary Package and Benefits"], "locations": ["Central & Western Area"], "categories": ["Insurance", "Claims Officer", "Others"], "post_time": "2022-01-06T06:22:52Z", "salary": {"currency": null, "max": null, "min": null, "period": "monthly", "term": null}, "salary_visible": false, "title_keywords": ["assistant claims manager", "manager"], "responsibilities": ["any other duties", "ideas", "communication", "customer service", "maintain", "liaise with", "compliance", "customer services", "develop", "reports", "reporting", "management", "review", "procedures", "investigation", "third party", "guidelines", "systems", "company guidelines", "coordinate", "insurance"], "requirements": {"degrees": ["degree or above", "bachelor"], "majors": [], "languages": ["cantonese", "putonghua", "english", "chinese"], "language_level": ["good command"], "hard_skills": ["excel", "chinese word processing", "powerpoint", "workshops", "problem solving skills", "pc skills", "ms word"], "soft_skills": ["work independently", "self-motivated", "under pressure", "open-minded", "timely", "willing to learn", "receptive", "customer-oriented", "customer service", "communication and interpersonal skills", "problem solving skills", "team player", "proactive"], "languages_combined": [{"language": "cantonese", "language_level": ["good command"]}, {"language": "putonghua", "language_level": ["good command"]}, {"language": "english", "language_level": ["good command"]}, {"language": "chinese", "language_level": []}]}, "experience_required": {"duration": ["at least 5 years"], "field": ["general insurance", "management", "insurance", "related"]}}, {"job_id": "100003009024321", "location_code": "hk", "company": "FWD Life Insurance Company (Bermuda) Limited", "job_title": "Claims, Employee Benefits (Several openings from Assistant Officer to Senior Manager)", "description": "Established in Asia in 2013 with a trailblazer mentality, FWD is the primary insurance business of investment group, Pacific Century Group (PCG), with minority shareholders Swiss Re Group, GIC Ventures, RRJ Capital and Hopu Investments.\n\nFWD spans 10 markets in Asia including Hong Kong SAR & Macau SAR, Thailand, Indonesia, the Philippines, Singapore, Vietnam, Japan, Malaysia and Cambodia. In Hong Kong, FWD offers life and medical insurance, general insurance, employee benefits, and financial planning. We focus on creating fresh customer experiences and making the insurance journey simpler, faster and smoother, with innovative propositions and easy-to-understand products, supported by digital technology. Through this customer-led approach, FWD aims to be a leading pan-Asian insurer by changing the way people feel about insurance.\n\nIf you are looking for a company where can fuel your inspiration and cultivate your expertise, join us on our exciting journey.\n\nThe Job:\n\nHandle inpatient and outpatient claims assessment independently\nCheck and authorize claims settlement according to the authorization limit\nHandle enquiries and complaints\nSupport project and business initiatives as assigned by superiors\n\nThe Person:\n\nTertiary education or above\n4 years or above relevant working experience in medical claims\nQualification of FLMI is advantage\nKnowledge in medical insurance\nGood command of spoken and written English and Chinese\nResponsible, detail-minded and with good communication skill\nProficiency in MS office (Word, Excel and Chinese word processing)\nCandidate with less experience will be considered as Officer.\n\nWe offer 5-day work, 20-22 days annual leaves, excellent learning & development opportunities and an attractive package to the right candidate.\n\nInformation collected will be treated in strict confidence and used solely for recruitment purpose. The company will retain all applications no longer than 24 months of which will be destroyed thereafter. When there are vacancies in any of our subsidiaries, holding companies, associated or affiliated companies of, or companies controlled by, or under common control with the Company during that period, we may transfer your application to them for consideration of employment. We are an equal opportunity employer. We do not discriminate on the basis of race, sex, disability or family status in employment process.", "employment_types": ["Full Time"], "selling_points": ["Pre-authorization approval", "manage panel doctor networks on in/out-patient", "Handle all medical claims assessment"], "locations": ["Sheung Wan"], "categories": ["Insurance", "Claims Officer"], "post_time": "2022-01-05T14:26:47Z", "salary": {"currency": null, "max": null, "min": null, "period": "monthly", "term": null}, "salary_visible": false, "title_keywords": ["assistant officer", "senior manager"], "responsibilities": [], "requirements": {"degrees": [], "majors": [], "languages": [], "language_level": [], "hard_skills": [], "soft_skills": [], "languages_combined": []}, "experience_required": {"duration": [], "field": []}}, {"job_id": "100003009025755", "location_code": "hk", "company": "Allied World", "job_title": "AVP, Claims (Marine, Property and Engineering)", "description": "Job Responsibilities:\n\nThe incumbent will be responsible for coordinating and providing claims support and services to the customers and agents, including but not limited to:\n\nHandle claims enquiries and deliver claims servicing support to customers and agents\n\nFollow up claims cases with agent/ customer/ physician/ hospital\n\nAssist in claims adjudication\n\nTake part in departmental projects/ ad hoc task provided by the management\n\nJob Requirements:\n\nBachelor Degree or above or with equivalent insurance professional qualifications\nMinimum 3 years of claims experience\nCustomer-service mindset with effective interpersonal and communication skill\nTeam player with positive working attitude\nFamiliar with MS Word, Excel & PowerPoint\nProficient in spoken & written English & Chinese (Cantonese & Mandarin)\n\nWe offer 5-day work week, attractive remuneration package and excellent training & development opportunities. Interested parties please submit application through our company website: http://boclife.com.hk\n\n(Data collected will be used for recruitment purpose only.)", "employment_types": ["Full Time"], "selling_points": ["Excellent team to work with", "Great career development opportunities", "Claims team management experience"], "locations": ["Eastern Area"], "categories": ["Insurance", "Claims Officer"], "post_time": "2022-01-06T06:26:16Z", "salary": {"currency": null, "max": null, "min": null, "period": "monthly", "term": null}, "salary_visible": false, "title_keywords": [], "responsibilities": ["management", "ad hoc"], "requirements": {"degrees": ["degree or above", "bachelor"], "majors": ["insurance"], "languages": ["cantonese", "english", "chinese", "mandarin"], "language_level": ["proficient"], "hard_skills": ["ms word", "excel", "powerpoint", "professional qualifications"], "soft_skills": ["positive working attitude", "team player", "communication skill", "interpersonal"], "languages_combined": [{"language": "cantonese", "language_level": []}, {"language": "english", "language_level": ["proficient"]}, {"language": "chinese", "language_level": ["proficient"]}, {"language": "mandarin", "language_level": []}]}, "experience_required": {"duration": ["minimum 3 years"], "field": []}}, {"job_id": "100003009025657", "location_code": "hk", "company": "ONEDEGREE HONG KONG LIMITED", "job_title": "Assistant Claims Manager - Insurtech Startup", "description": "Our client is one of the world's leading insurance company and is now looking for claim expertise to support their business.\n\nResponsibilities:\n\nAssess minor and major claim cases as well as approve the claim cases escalated by the claim subordinates\nManage the daily operation of Claims and ensure service standard meets with Company\u2019s standard\nProvide management information on claims experience and suggestions/executions of claims monitoring controls\nParticipate in determining system requirements for claim administrations\nProvide market information on new service ideas and workflow to streamline the procedure and improve service\nParticipate in ad hoc assigned projects\n\nRequirements:\n\n8-10 years of solid work experience in life claims environment with minor and major claim authority\nFluent in both spoken and written English and Chinese\nGood communication and negotiation skills, with a thorough understanding of company products and an analytical mind\nUniversity graduate with professional qualification in life insurance such as FLMI, ALHC;\nCustomer focus is a must with excellent service skill\nLess experience will be considered as Assistant Manager\n\nApply for this job:\n\nInterested candidate please CLICK apply button to apply online or send your resume in MS word format to Fillture Group Limited\n\nFor more information please contact\u00a0Danvis Lau\u00a0+852 2814 9388.\n\nPlease note that only shortlisted candidate will be notified. All information will be treated in strict confidence and solely used for recruitment purposes.", "employment_types": ["Full Time"], "selling_points": ["Flat structure, job flexibility and empowerment", "Fast-growing insurtech startup", "Work-life balance, medical benefits"], "locations": ["Ngau Tau Kok"], "categories": ["Insurance", "Claims Officer", "Others"], "post_time": "2022-01-06T06:07:46Z", "salary": {"currency": null, "max": null, "min": null, "period": "monthly", "term": null}, "salary_visible": false, "title_keywords": ["assistant claims manager"], "responsibilities": ["management", "market information", "ideas", "service standard", "ad hoc", "monitoring", "daily operation"], "requirements": {"degrees": ["university graduate"], "majors": ["insurance"], "languages": ["english", "chinese"], "language_level": ["fluent"], "hard_skills": ["focus", "ms word"], "soft_skills": ["confidence", "communication", "negotiation skills", "analytical mind", "thorough", "customer focus"], "languages_combined": [{"language": "english", "language_level": ["fluent"]}, {"language": "chinese", "language_level": ["fluent"]}]}, "experience_required": {"duration": ["8-10 years"], "field": []}}, {"job_id": "100003009032779", "location_code": "hk", "company": "RecruitFirst Limited", "job_title": "EB Policy Administration Senior Officer (Urgent/Insurance/Taikoo/5-day-work)", "description": "Established in Asia in 2013 with a trailblazer mentality, FWD is the primary insurance business of investment group, Pacific Century Group (PCG), with minority shareholders Swiss Re Group, GIC Ventures, RRJ Capital and Hopu Investments.\n\nFWD spans 10 markets in Asia including Hong Kong SAR & Macau SAR, Thailand, Indonesia, the Philippines, Singapore, Vietnam, Japan, Malaysia and Cambodia. In Hong Kong, FWD offers life and medical insurance, general insurance, employee benefits, and financial planning. We focus on creating fresh customer experiences and making the insurance journey simpler, faster and smoother, with innovative propositions and easy-to-understand products, supported by digital technology. Through this customer-led approach, FWD aims to be a leading pan-Asian insurer by changing the way people feel about insurance.\n\nIf you are looking for a company where can fuel your inspiration and cultivate your expertise, join us on our exciting journey.\n\nThe Purpose:\n\nTo manage the operations of the medical pre-authorization approval claims and ensure that the operation of panel doctor networks are running smoothly plus administer day-to-day claim functions efficiently and accurately. \u00a0\n\nThe Job:\n\nProvide services on pre-authorization approval and manage panel doctor networks on inpatient and outpatient\nHandle all medical claims assessment and investigation\nProvide quality services to designated major accounts including maintaining and ensuring the SLA\nSupervise team and perform duties allocation among the subordinates\nProvide training on medical claims knowledge to internal staff\nAssist in system development and enhancement project\nPerform claims reporting and carry out other duties assigned by management\n\nThe Person:\n\nDegree holder\nExperience in panel doctor network management and medical claims\nQualification of FLMI is an advantage\nMedical knowledge qualification is an advantage\nProficiency in MS Office (Word, Excel and PowerPoint)\nGood spoken and written in English and Chinese\nGood management, communication and coaching skills\n\nCandidates' experience will be matched to relevant job level accordingly.\n\nWe offer 5-day work, 20-22 days annual leaves, excellent learning & development opportunities and an attractive package to the right candidate.\n\nInformation collected will be treated in strict confidence and used solely for recruitment purpose. The company will retain all applications no longer than 24 months of which will be destroyed thereafter. When there are vacancies in any of our subsidiaries, holding companies, associated or affiliated companies of, or companies controlled by, or under common control with the Company during that period, we may transfer your application to them for consideration of employment. We are an equal opportunity employer. We do not discriminate on the basis of race, sex, disability or family status in employment process.", "employment_types": ["Full Time", "Permanent"], "selling_points": [], "locations": ["Tai Koo"], "categories": ["Professional Services", "Business Analysis / Data Analysis", "Insurance", "Claims Officer", "Others"], "post_time": "2022-01-07T16:45:31Z", "salary": {"currency": null, "max": null, "min": null, "period": "monthly", "term": null}, "salary_visible": false, "title_keywords": ["senior officer"], "responsibilities": [], "requirements": {"degrees": [], "majors": [], "languages": [], "language_level": [], "hard_skills": [], "soft_skills": [], "languages_combined": []}, "experience_required": {"duration": [], "field": []}}, {"job_id": "100003009021433", "location_code": "hk", "company": "BUPA Asia Limited", "job_title": "Senior Advisor, Claims", "description": "Job Summary:\nThis position is responsible for overseeing the day to day management of claims and staff under Marine, Property and\u00a0Engineering lines to ensure delivery of excellent claims services and efficient claims operation.\n\nJob Duties:\n\nManages the team for the Involved Lines\u00a0of Business and provide/recommend necessary training mentoring and guidance to the team members.\nReview, evaluate, negotiate and resolve non-standard and complex cases, within designated personal authority level, in line with established standards, procedures and guidance provided.\nExhibit technical leadership, both internally and externally, on claims matter which the Company participates.\nIdentifying, investigate suspicious / fraudulent claims and take appropriate actions and keep relevant stakeholders closely informed.\nManaging customer/intermediary interactions in an efficient, courteous and timely manner in order to deliver high standards of customer satisfaction. This also includes handling and resolving any customer feedback or complaints.\nOrganizing and using approved internal and/or external suppliers to ensure appropriate and timely services are provided to customers.\u00a0\nProactively supervise and manage expenses of independent vendors and legal counsels for involved Line(s) of Business.\nInteract with relevant internal / external stakeholders to support and deliver business strategy.\nMeet with existing or prospective clients or intermediaries to promote Claims and support business development.\nEnsure performance of periodic internal review of claim files including monitoring/pursuing of outstanding recoveries.\nPreparation of reports or analysis where necessary.\nEnsure compliance with all legal, regulatory and policy requirements internally and externally.\nAdditional duties and responsibilities as warranted.\n\nEssential Requirements:\n\nRelevant academic qualifications with a minimum of 7 to 10 years' solid working experience including experience in managing a team of the Involved Lines\u00a0of Business.\nPreferably a holder or in progress of professional insurance qualification such as ANZIIF or ACII and meet minimum local mandatory qualification requirement where relevant.\nSolid experience in handling complex / legal cases independently with sound judgment, strong negotiating and analytical ability in the Involved Lines of Business.\u00a0\nLegal knowledge or legal training is as an advantage.\nStrong leadership and communication skills.\u00a0\nKnowledge and experience in claims process improvements including strong organizational skills.\nStrong team player with proven ability to work with senior management, internal and external parties.\u00a0\nDemonstrate ability to select, hire, evaluate and work with legal counsel and experts on cases.\nSelf-motivated individual with ability to work independently and handle a diverse range of claims and responsibilities.\nStrong customer service oriented attitude.\u00a0\nStrong in oral and written communication skills in English and Cantonese.\u00a0\nAbility to work on relevant PC applications.\u00a0\nAll information collected from applicants will be kept in accordance with Allied World Assurance Company, Ltd \u2018s (Hong Kong branch) privacy and security policy.\n\u00a0\nAbout Allied World\nAllied World Assurance Company Holdings, GmbH, through its subsidiaries, is a global provider of insurance and reinsurance solutions. We operate under the brand Allied World and have supported clients, cedents and trading partners with thoughtful service and meaningful coverages since 2001. We are a subsidiary of Fairfax Financial Holdings Limited, and we benefit from a worldwide network of affiliated entities that allow us to think and respond in non-traditional ways. Our capital base is strong, our solutions anticipate rather than react to changing trends, and our teams are focused on establishing long-term relationships that are mutually beneficial.\n\u00a0\nWe have over 1,400 employees in offices across North America, Europe and Asia-Pacific. Allied World is an equal opportunity employer. Subject to applicable law, all qualified applicants will be considered for employment without regard to race, color, religion or belief, sex, age, disability, military service, marital or civil partnership status, family status, sexual orientation, ethnic or national origin, genetic information or any other characteristic protected by applicable law or regulation in the relevant jurisdiction where we operate.\n\u00a0\nLearn more about Allied World by visiting: Web: www.awac.com | Facebook: www.facebook.com/alliedworld | LinkedIn: https://www.linkedin.com/company/allied-world\n\u00a0\n\u00a0", "employment_types": ["Full Time", "Permanent"], "selling_points": ["3 + years of related experience", "Process claims payment / Follow up request", "Provide training to Junior staff"], "locations": ["Not Specified"], "categories": ["Admin & HR", "Clerical / Admin Staff", "Insurance", "Claims Officer", "Others"], "post_time": "2022-01-05T03:57:13Z", "salary": {"currency": null, "max": null, "min": null, "period": "monthly", "term": null}, "salary_visible": false, "title_keywords": ["advisor"], "responsibilities": ["guidance", "additional duties", "analysis", "review", "procedures", "expenses", "monitoring", "ensure compliance", "evaluate", "reports"], "requirements": {"degrees": [], "majors": [], "languages": ["cantonese", "english"], "language_level": [], "hard_skills": ["facebook", "react", "web", "pc applications"], "soft_skills": ["communication skills", "organizational skills", "independently", "self-motivated", "work independently", "customer service oriented", "oral", "focused", "diverse", "team player", "leadership"], "languages_combined": [{"language": "cantonese", "language_level": []}, {"language": "english", "language_level": []}]}, "experience_required": {"duration": ["minimum of 7 to 10 years"], "field": ["managing a team", "business", "analytical", "legal"]}}, {"job_id": "100003009015343", "location_code": "hk", "company": "Captar Partners", "job_title": "Claims Officer, Life/ Medical", "description": "Our client, a global insurance firm is looking operations professionals to join their policy administration team.\n\nKey Responsibilities:\n\nAssist with policy issuance and renewal process\nResponsible for billing process\nAssist with policy premium adjustments\nAssist in system enhancements assigned by the Manager\nSupport teammates on routine operations\n\nKey Requirements:\n\nBachelor\u2019s Degree in Business or relevant major\nProfessional insurance qualification is preferred\n1-3 years\u2019 direct experiences in General Insurance / Employee Benefits\nExcellent communication and presentation skills\nKnowledge in MS Word, MS Excel, Chinese word-processing", "employment_types": ["Permanent"], "selling_points": ["Life/ Medical Claims", "Sizeable Insurance Business", "Career Progression"], "locations": ["Not Specified"], "categories": ["Insurance", "Claims Officer"], "post_time": "2022-01-03T06:33:57Z", "salary": {"currency": "HKD", "max": 29999, "min": 14000, "period": "monthly", "term": null}, "salary_visible": true, "title_keywords": ["claims officer"], "responsibilities": ["operations", "billing process"], "requirements": {"degrees": ["degree", "bachelor"], "majors": ["business"], "languages": [], "language_level": [], "hard_skills": [], "soft_skills": [], "languages_combined": []}, "experience_required": {"duration": [], "field": []}}, {"job_id": "100003009019951", "location_code": "hk", "company": "Hong Leong Insurance (Asia) Limited", "job_title": "Senior Claims Assessor \u2013 Personal Lines", "description": "Responsibilities:\n\nAssist Claims Manager to support the claims team in claims investigation, daily claims operation, enquiry, and continuous claims process improvement\nAssess and approve complicated claims\nMonitor and control daily operations to be carried out smoothly\nTo ensure delivery of agreed service standards\nTo handle enquiries from distribution enquiry team, customer enquiry teams and complaint team\nReview staff performance, develop and monitor plan for staff development\nDrive and oversee plans for system modifications and to continue meeting, improving and anticipating customer needs and developing relationship with agency force\nImplement continuous claims process improvement to strive for operational efficiency\nProvide training to claim colleagues and other internal staff so as to uplift their claims knowledge\nReview and revise internal claims manuals, guidelines and practices\nTo assist in all operational and project issues\n\nRequirements:\n\nUniversity graduate or above with FLMI or equivalent\nAt least 5 years' experience in Claims with at least 1 years in management position\nStrong technical skills and knowledge of Claims\nCustomer Centric minded and good communication skill\nResult-oriented, self-motivated, patient, cheerful and positive\nHigh emotional maturity and able to work under pressure\nExcellent command of both written and spoken English and Chinese, Mandarin is an advantage", "employment_types": ["Full Time", "Permanent"], "selling_points": [], "locations": ["North Point"], "categories": ["Insurance", "Claims Officer", "Others"], "post_time": "2022-01-04T09:34:36Z", "salary": {"currency": null, "max": null, "min": null, "period": "monthly", "term": null}, "salary_visible": false, "title_keywords": ["personal"], "responsibilities": ["provide training", "control", "guidelines", "review", "monitor", "teams", "investigation", "develop", "developing", "handle enquiries", "service standards", "daily operations", "plan", "plans"], "requirements": {"degrees": ["university graduate or above"], "majors": [], "languages": ["english", "chinese", "mandarin"], "language_level": ["advantage", "excellent"], "hard_skills": [], "soft_skills": ["self-motivated", "cheerful", "communication skill", "technical skills", "patient", "result-oriented", "positive", "work under pressure"], "languages_combined": [{"language": "english", "language_level": ["excellent"]}, {"language": "chinese", "language_level": ["excellent"]}, {"language": "mandarin", "language_level": ["advantage", "excellent"]}]}, "experience_required": {"duration": ["at least 5 years", "at least 1 years"], "field": ["management position"]}}, {"job_id": "100003009016760", "location_code": "hk", "company": "Bank of China Group Insurance Company Limited", "job_title": "Senior Officer /Officer/ Assistant Officer \u2013 Claims Department", "description": "Job Description\n\u00a0\n\nApprove claims and ensure the claims handled within the authority and complying with handling guideline\nAssist Claims Manager in providing guidance to junior staff and daily operation of team\nConduct investigation of suspicious claims and handle inquiries agency and other parties\nParticipate in projects on the development and enhancement of operations systems\n\n\u00a0\nDesired Skills and Experience\n\u00a0\n\nGood insurance knowledge with\u00a0at least 1 year of experience in Life/ Medical claims\nGood command of spoken and written English and Chinese\nKeen attention to detail and an aptitude for problem solving", "employment_types": ["Full Time", "Permanent"], "selling_points": [], "locations": ["Central"], "categories": ["Insurance", "Claims Officer"], "post_time": "2022-01-03T09:47:03Z", "salary": {"currency": null, "max": null, "min": null, "period": "monthly", "term": null}, "salary_visible": false, "title_keywords": ["assistant officer", "senior officer", "officer"], "responsibilities": ["guidance", "operations", "systems", "daily operation", "investigation", "insurance"], "requirements": {"degrees": [], "majors": [], "languages": ["english", "chinese"], "language_level": ["good command"], "hard_skills": ["problem solving"], "soft_skills": ["problem solving", "keen", "attention to detail"], "languages_combined": [{"language": "english", "language_level": ["good command"]}, {"language": "chinese", "language_level": ["good command"]}]}, "experience_required": {"duration": ["at least 1 year"], "field": ["insurance", "medical"]}}, {"job_id": "100003009016824", "location_code": "hk", "company": "Rod and Staff Recruitment Group (Hong Kong) Limited", "job_title": "Claims Officer", "description": "The appointee will be primarily responsible for handling Personal Lines claims including but not limited to Home, Hospital Cash, Personal Accident, Travel and Domestic Helper\u2019s claims\n\nRequirements:\n\nSecondary Education or above, with ANZIIF Associateship or ACII qualification or above is preferable\n2-3 years' claims experience in insurance company\nCustomer service oriented\nGood communication and interpersonal skills\nGood command of spoken English and Chinese\nProficiency in MS Word, Excel and Chinese word processing\nKnowledge in AS400, SAS is a plus\nPlease apply (preferably in Word or PDF format) with present and expected salaries,\u00a0quoting job reference (JDBI/0401/SCAPL)\u00a0to Head of Human Resources, 50/F The Center, 99 Queen\u2019s Road Central, Hong Kong or email to us\u00a0or fax to 2285 3209. You are invited to visit our website at:\u00a0http://www.hl-insurance.com.\n\n\n\nAll applications will be treated in strict confidence and used for recruitment purpose within Guoco Group Limited, or Hong Leong Group of which Guoco is a member (together, \u201cthe Group\u201d) only. A copy of our personal data policy is available on request.\n\nApplicants not hearing from us within\u00a08 weeks may consider their applications unsuccessful. We may also consider their application for other or future vacancies within the Group.\u00a0 Personal data of unsuccessful applicants will be retained by the Group for a maximum period of one year.", "employment_types": ["Full Time"], "selling_points": ["Attractive Remuneration", "Convenient Location", "Work-life Balance"], "locations": ["Central & Western Area"], "categories": ["Insurance", "Claims Officer"], "post_time": "2022-01-03T09:55:01Z", "salary": {"currency": null, "max": null, "min": null, "period": "monthly", "term": null}, "salary_visible": false, "title_keywords": ["claims officer"], "responsibilities": ["website", "communication", "customer service", "recruitment", "personal data", "insurance"], "requirements": {"degrees": ["secondary education"], "majors": [], "languages": ["english", "chinese"], "language_level": ["proficiency", "good command"], "hard_skills": ["excel", "plus", "chinese word processing", "sas", "word", "ms word"], "soft_skills": ["confidence", "communication and interpersonal skills", "customer service oriented", "responsible"], "languages_combined": [{"language": "english", "language_level": ["good command"]}, {"language": "chinese", "language_level": ["proficiency", "good command"]}]}, "experience_required": {"duration": ["2-3 years"], "field": ["insurance"]}}, {"job_id": "100003009020706", "location_code": "hk", "company": "China Ping An Insurance (Hong Kong) Co Ltd", "job_title": "Claims Executive/Sr. Claims Executive", "description": "Responsibilities:\n\nMainly responsible for handling liability insurance claims, experience in\u00a0 motor insurance claims is an advantage.\nTake responsibility to resolve all enquiries from both customer and external contacts to ensure delivery of a focused, quality and professional claims service.\nEnsure claims procedures, documentation is adhered to the group claims management requirement and best practice.\n\nRequirements:\n\nDegree holder, preferably with progress in professional insurance qualification such as ACII or ANZIIF\n2-3 years' working experience in\u00a0liability insurance claims\nExcellent customer services, negotiation and communication skills internally and externally.\nCustomer orientated, self initiative and able to work under pressure.\nStrong interpersonal skills with proven ability to communicate effectively at all levels of management.\nGood command of spoken and written English, Mandarin and Cantonese.\nProficiency in MS Word, Excel and Chinese word processing.\nFresh graduates or candidates with less experience will be considered as Assistant Officer.\n\nWe offer competitive remuneration package. Interested parties, please send your resume with CURRENT & EXPECTED salary and DATE AVAILABLE by clicking 'Apply Now'.\n\n(Data collected would be used for recruitment purpose only)", "employment_types": ["Full Time", "Permanent"], "selling_points": ["Check policy coverage online", "Experience in Insurance Claims", "Double pay + Performance Bonus"], "locations": ["Ngau Tau Kok"], "categories": ["Insurance", "Claims Officer", "Others"], "post_time": "2022-01-05T01:19:21Z", "salary": {"currency": null, "max": null, "min": null, "period": "monthly", "term": null}, "salary_visible": false, "title_keywords": ["executive"], "responsibilities": ["management", "quality", "procedures", "documentation", "insurance"], "requirements": {"degrees": ["degree holder"], "majors": ["insurance"], "languages": ["cantonese", "english", "chinese", "mandarin"], "language_level": ["proficiency", "good command"], "hard_skills": ["excel", "chinese word processing", "ms word"], "soft_skills": ["communication skills", "negotiation", "interpersonal skills", "initiative", "work under pressure"], "languages_combined": [{"language": "cantonese", "language_level": ["good command"]}, {"language": "english", "language_level": ["good command"]}, {"language": "chinese", "language_level": ["proficiency"]}, {"language": "mandarin", "language_level": ["good command"]}]}, "experience_required": {"duration": ["2-3 years"], "field": ["insurance"]}}, {"job_id": "100003009017043", "location_code": "hk", "company": "China Everbright Securities International Company Limited", "job_title": "Analyst / Senior Analyst, Claims Services (Corporate Insurance)", "description": "About the company\nOur client is an international leader in the insurance industry, providing both general and life insurance to customers. They are currently looking for Officer/Senior Claims Officer to join their Operation Department.\u00a0\n\n\nJob Description\n\u2022 Process day-to-day claims assessment and follow-up cases\n\u2022 Claims approval\n\u2022 Collaborate with different stakeholders\n\u2022 Handle and solve claims inquiries from customers and sales agents\n\u2022 Enhance claim sytem and workflow\n\nRequirements\n\u2022 Degree Holder\n\u2022 Minimum 2 years working in life and/or medical claims\u00a0\n\u2022 Fast learner under dynamic environment\n\u2022 Proficient in both written and spoken English and Cantonese", "employment_types": ["Full Time", "Permanent"], "selling_points": [], "locations": ["Causeway Bay"], "categories": ["Insurance", "Claims Officer", "Insurance Agent / Broker", "Others"], "post_time": "2022-01-03T10:24:25Z", "salary": {"currency": null, "max": null, "min": null, "period": "monthly", "term": null}, "salary_visible": false, "title_keywords": ["analyst", "senior analyst"], "responsibilities": ["collaborate with"], "requirements": {"degrees": ["degree holder"], "majors": [], "languages": ["cantonese", "english"], "language_level": ["proficient"], "hard_skills": ["dynamic"], "soft_skills": ["dynamic environment", "fast learner"], "languages_combined": [{"language": "cantonese", "language_level": ["proficient"]}, {"language": "english", "language_level": ["proficient"]}]}, "experience_required": {"duration": [], "field": []}}, {"job_id": "100003009029069", "location_code": "hk", "company": "Gain Miles Assurance Consultants Limited", "job_title": "Senior Officer / Officer - Customer Services & Policy Administration", "description": "Accountabilities and Activities\n\nAssess medical claims in compliance with the terms and conditions of the policy\nProcess claims payment in accordance with the company's objectives\nLiaise with medical professionals and customers to conduct assessment and investigation\nFollow up customers' request with other departments\nContact customers to follow up outstanding issues\nAble to manage different types of jobs at the same time in orderly manner\nProvide training to Junior staff and meet the timeline and service standard on the assigned tasks\nAssists in enhancing the system and work flow to meet customers\u2019 need and services standards\n\n\nTo be considered for the role, you should ideally have\n\n\nBachelor\u2019s degree will be an advantage\nAt least 3 years of experience in medical claim processing\nExperience in processing medical claims and with customer services experience will be an advantage\nCustomer-oriented with excellent communication and interpersonal skills\nStrong team player, willing to learn, able to work independently and\u00a0under pressure\nSelf-motivated, analytical and detailed-minded in problem solving\nStrong sense of responsibility with high level of integrity and trust\nGood command of English and Chinese in both written and spoken\nSound PC skills in MS Word, Excel & Chinese word processing\nBupa offers 5 days work per week and comprehensive remuneration packages including base salary, study assistance plan, life and medical benefit, dental benefit, annual leave, examination leave, etc.\nBupa is an equal opportunity employer and welcomes applications from qualified candidates. Information provided will be treated in strict confidential and only be used for consideration of application with Bupa.\u00a0\u00a0\u00a0\u00a0\u00a0\u00a0\u00a0\u00a0\u00a0\u00a0\u00a0\u00a0\u00a0\u00a0\nPersonal data collected will be used for recruitment purposes only. Only candidates selected for interviews will be contacted. Bupa will be in touch for any opportunities that matches your profile. All personal data of unsuccessful application will be destroyed 24 months from the date of receiving the application.", "employment_types": ["Full Time"], "selling_points": ["5-days work week", "Higher diploma holder of business-related", "Possessing 3 years related experience"], "locations": ["Not Specified"], "categories": ["Admin & HR", "Clerical / Admin Staff", "Sales, CS & Business Devpt", "Customer Service - Supervisor / Officer", "Insurance", "Claims Officer"], "post_time": "2022-01-07T03:54:52Z", "salary": {"currency": null, "max": null, "min": null, "period": "monthly", "term": null}, "salary_visible": false, "title_keywords": ["senior officer", "officer"], "responsibilities": ["provide training", "service standard", "compliance", "investigation", "customer services", "communication", "payment", "recruitment", "contact", "plan", "liaise with", "personal data"], "requirements": {"degrees": ["degree", "bachelor"], "majors": [], "languages": ["english", "chinese"], "language_level": ["good command"], "hard_skills": ["excel", "chinese word processing", "processing", "problem solving", "pc skills", "ms word"], "soft_skills": ["work independently", "self-motivated", "under pressure", "sense of responsibility", "orderly", "willing to learn", "integrity", "problem solving", "customer-oriented", "communication and interpersonal skills", "comprehensive", "team player", "detailed"], "languages_combined": [{"language": "english", "language_level": ["good command"]}, {"language": "chinese", "language_level": ["good command"]}]}, "experience_required": {"duration": ["at least 3 years"], "field": ["customer services", "medical"]}}, {"job_id": "100003009025527", "location_code": "hk", "company": "Page Personnel", "job_title": "Operation/Admin Officer - Leading Insurance Platform", "description": "Key Responsibilities\n\nSupport day to day operation of billing and revenue management;\nHandle patient billing issues and ensure accuracy and completeness of chargeable items;\nHandle budget estimate of hospital stays;\nShift duty is required; and\nPerform any other duties as assigned.\n\nJob Requirements\n\nHolder of a Diploma in any discipline\nAt least 2 years\u2019 relevant work experience\nExperience in hospital / healthcare field is preferred\nGood command of both spoken and written English and Chinese\nProficient in MS Office applications\n\nCompensation and Employment Terms\n\nWe provide a unique employment experience for people seeking careers in hospital and healthcare industry; and offer competitive remuneration packages to the successful candidates. Appointment will be made on a 3-year contract with contract-end gratuity, renewable subject to good performance and mutual agreement.\n\nApplication Closing Date\n\n20 January 2022\n\nPersonal Information Collection Statement\n\nData collected will only be used for job application processing. Applicants not contacted by CUHK Medical Centre Limited within eight weeks from the application closing date may assume their applications unsuccessful. All personal data collected will be kept for a period of 12 months from the application closing date, and will be destroyed thereafter.", "employment_types": ["Full Time", "Permanent"], "selling_points": ["Excellent Brand Name", "Welcome Candidate with Insurance Background", "Competitive Pay and Fringe Benefits"], "locations": ["Not Specified"], "categories": ["Insurance", "Claims Officer", "Underwriter", "Others"], "post_time": "2022-01-06T04:55:28Z", "salary": {"currency": "HKD", "max": 19999, "min": 17000, "period": "monthly", "term": null}, "salary_visible": true, "title_keywords": ["officer", "admin"], "responsibilities": ["any other duties", "management", "budget"], "requirements": {"degrees": ["diploma"], "majors": [], "languages": ["english", "chinese"], "language_level": ["good command"], "hard_skills": ["ms office"], "soft_skills": [], "languages_combined": [{"language": "english", "language_level": ["good command"]}, {"language": "chinese", "language_level": ["good command"]}]}, "experience_required": {"duration": ["at least 2 years"], "field": ["healthcare"]}}, {"job_id": "100003009016067", "location_code": "hk", "company": "Gemini Personnel Limited", "job_title": "Claims Officer (Medical Insurance), MOC-J077776", "description": "Check policy coverage online\nAssign loss adjusters & surveyors\nOpen new files & prepare worksheets and loss reserving\nAnswer telephone enquiries from client/broker/agent\nPhotocopying, scanning & filing\nPrepare payment memo & cheque\nDispatch claim form to client/broker/agent\nNotify Business Dept of outstanding premium before payment\nCheck with Accounts Dept to ensure premium has been paid\nPerform any job duties assigned by reporting manager/supervisor\nJob Requirements:\nTertiary education with significant experience in insurance claims\nSome progress in professional insurance Exam preferable but not essential\nFluent English and Mandarin\nComputer literate including Chinese characters typing\nImmediate available is preferable\nWorking Location: Ngau Tau Kok\n\nLess experience will be consider as Claims Executive\n\nInterested parties, please click \"Apply Now\" to submit your application.\n\nPersonal data collected will be used for recruitment purpose only.\n\n", "employment_types": ["Full Time", "Permanent"], "selling_points": ["5 years of solid experience in medical claims", "Fluency in spoken and written English and Chinese", "Strong problem-solving skills and analytical skill"], "locations": ["Wan Chai"], "categories": ["Insurance", "Claims Officer"], "post_time": "2022-01-03T08:13:13Z", "salary": {"currency": null, "max": null, "min": null, "period": "monthly", "term": null}, "salary_visible": false, "title_keywords": ["claims officer"], "responsibilities": ["scanning", "reporting", "memo", "payment", "insurance"], "requirements": {"degrees": [], "majors": [], "languages": ["english", "chinese", "mandarin"], "language_level": ["fluent"], "hard_skills": ["typing"], "soft_skills": [], "languages_combined": [{"language": "english", "language_level": ["fluent"]}, {"language": "chinese", "language_level": []}, {"language": "mandarin", "language_level": ["fluent"]}]}, "experience_required": {"duration": [], "field": ["insurance", "education"]}}, {"job_id": "100003009016854", "location_code": "hk", "company": "The Kowloon Motor Bus Co (1933) Ltd", "job_title": "Legal Officer", "description": "Ref: ASACS/CI/030122DB/07\n\nResponsibilities\n\nAssist the team to facilitate the operation of claim function for all lines of general insurance\nResponsible for handling claims cases for the Claims Division\nNegotiate with insurers\u00a0and third parties for claims settlement & recovery\nPrepare claims reports/analysis for pitching new/renewal business\nCommunicate closely with the respective parties and clients for claims settlement\nAttend claims/business meeting with clients\u00a0and insurers when necessary\nRequirements\n\nDegree holder or equivalent with good progression in insurance professional qualification\nProactive, with good communication and interpersonal skills\nProficiency in MS Office applications and Chinese Word Processing\nGood command of both written and spoken English and Chinese.\u00a0 Fluency in Putonghua will be an advantage\n\nWe offer a competitive remuneration package to the right candidate. If you are interested in the post, please send your resume together with your present and expected salaries by clicking \u201cApply Now\u201d.\u00a0\n\nFor more information about China Everbright Securities International Company Limited, please visit www.ebshk.com.\n\nWe are an equal opportunity employer and welcome applications from all qualified candidates. All applications will be treated in the strictest confidence. Personal data provided will be used for recruitment purposes only. The job applicant will assume all or any risks arising out of or in connection with the job application transmission process prior to our actual receipt of the same including but not limited to accidental or unauthorized loss or disclosure of personal information, to which we will not be responsible in any way.\n\nUnder the Personal Data (Privacy) Ordinance, you may request access to, and / or correction of your personal data in relation to your application. If you wish to do so, please email to us.", "employment_types": ["Full Time"], "selling_points": [], "locations": ["Kowloon Bay"], "categories": ["Insurance", "Claims Officer", "Professional Services", "Legal & Compliance", "Transportation & Logistics", "Public Transportation"], "post_time": "2022-01-03T09:59:57Z", "salary": {"currency": null, "max": null, "min": null, "period": "monthly", "term": null}, "salary_visible": false, "title_keywords": ["officer"], "responsibilities": ["analysis", "insurance", "reports"], "requirements": {"degrees": ["degree holder"], "majors": ["insurance"], "languages": ["putonghua", "english", "chinese"], "language_level": ["fluency", "advantage", "proficiency", "good command"], "hard_skills": ["chinese word processing", "ms office"], "soft_skills": ["proactive", "communication and interpersonal skills"], "languages_combined": [{"language": "putonghua", "language_level": ["fluency", "advantage"]}, {"language": "english", "language_level": ["good command"]}, {"language": "chinese", "language_level": ["proficiency", "good command"]}]}, "experience_required": {"duration": [], "field": []}}, {"job_id": "100003009025179", "location_code": "hk", "company": "Ethos BeathChapman Hong Kong Limited", "job_title": "Medical Project Manager", "description": "Our client is a leading insurance company operating in Hong Kong for over 100 years. They are now looking for candidates with insurance operation background to join them.\n\nClient Details\n\nOur client is a leading insurance company operating in Hong Kong for over 100 years. The company offers a diverse range of protection and wealth products and services to individual and corporate customers.\n\nThey are now looking for candidates with insurance operation background to join them. The candidate would be expected to support the MPF operation functions such as enrolment, termination and contribution. The company has excellent brand name among the market and are very supportive to their employee's career growth.\n\nDescription\n\nSupport fund admin duties such as documentation for enrolment, switching, termination and redemption\nContact clients for following up action on missing information or data correctness through emails and phone calls\nAssist in managing key accounts\nHandles enquiries and provide solution and information to clients\n\nProfile\n\nTertiary education or above\nOperation/Administration experience in insurance company\nSelf-motive, well organised and attentive to details\nGood interpersonal, communication skills\nProficient in both English and Chinese, both spoken and written\n\nJob Offer\n\nExcellent brand name\nMedical, life insurance covering dependent\nAnnual leave: 15 days\nBirthday leave\nYear-end bonus\nYearly salary review\n\nTo apply online please click the 'Apply' button below. For a confidential discussion about this role please contact Janet CHang on +852 3602 2459.", "employment_types": ["Temporary", "Contract"], "selling_points": ["One of Hong Kong\u2019s leading banks", "Dynamic international working environment", "Attractive salary"], "locations": ["Central & Western Area"], "categories": ["Banking / Finance", "Financial Services", "Insurance", "Claims Officer", "Others"], "post_time": "2022-01-06T03:49:37Z", "salary": {"currency": "HKD", "max": 69999, "min": 55000, "period": "monthly", "term": null}, "salary_visible": true, "title_keywords": ["project manager"], "responsibilities": ["year-end", "mpf", "data", "review", "communication", "contact", "documentation", "insurance", "phone calls", "administration"], "requirements": {"degrees": [], "majors": [], "languages": ["english", "chinese"], "language_level": ["proficient"], "hard_skills": ["documentation"], "soft_skills": ["communication skills", "supportive", "attentive to details", "diverse", "organised", "interpersonal"], "languages_combined": [{"language": "english", "language_level": ["proficient"]}, {"language": "chinese", "language_level": ["proficient"]}]}, "experience_required": {"duration": [], "field": ["operation", "insurance", "administration"]}}, {"job_id": "100003009027741", "location_code": "hk", "company": "Hays", "job_title": "Company Secretary, FI, IPO", "description": "Our client, a well-established Medical Insurance Company is looking for a high caliber candidate to fulfill the above mentioned job. Details are as followings:\n\nResponsibilities:\n\nAdjudicate travel and medical claims according to company\u2019s guidelines.\nPre-authorize claims according to authority.\nLiaise with medical providers/ administrators/ hospitals.\nHandle claims administrative tasks.\nAssist Claims Manager to provide quality claims services to clients.\nPerform any ad hoc task as required by Claims Manager.\nRequirements:\n\nUniversity graduate with 5 years of solid experience in medical claims.\nWork experience in provider network will be an asset.\nSound knowledge with medical terms.\nStrong problem-solving skills and analytical skills.\nMature, attentive to details, self-motivated, work independently, good team player.\nGood communication skills with fluency in spoken and written English.\nGood PC skills.\nPackage:\n\n13 months, bonus (discretionary)\nMedical insurance coverage\nPublic Holidays", "employment_types": ["Full Time", "Permanent"], "selling_points": ["Work Flexibility", "Hybrid workplace", "Career advancement"], "locations": ["Not Specified"], "categories": ["Insurance", "Claims Officer", "Insurance Agent / Broker", "Others"], "post_time": "2022-01-06T11:52:34Z", "salary": {"currency": "HKD", "max": 89999, "min": 55000, "period": "monthly", "term": null}, "salary_visible": true, "title_keywords": ["company secretary"], "responsibilities": ["ad hoc", "guidelines", "quality", "liaise with", "administrative tasks"], "requirements": {"degrees": ["university graduate"], "majors": [], "languages": ["english"], "language_level": ["fluency", "good"], "hard_skills": ["problem-solving skills", "pc skills", "analytical skills"], "soft_skills": ["communication skills", "self-motivated", "work independently", "good team player", "attentive to details", "mature", "analytical skills", "problem-solving skills"], "languages_combined": [{"language": "english", "language_level": ["fluency", "good"]}]}, "experience_required": {"duration": ["5 years"], "field": ["medical"]}}, {"job_id": "100003009032180", "location_code": "hk", "company": "Page Group Hong Kong", "job_title": "Quality Assurance Analyst- Global Top Financial Institution", "description": "Requirements:\nUniversity graduate in related disciplines\nAt least 4 years or above experience in insurance related or legal firm\u00a0\nBasic claims handling knowledge (motor or general claims, or insurance (underwriting or claims), or insurance claims data management\nGood telephone manner and interpersonal skills\nProficiency in MS Office, Knowledge in MS Access is preferred\nResponsibilities:\nHandle large volume of claims related telephone enquiries\nHandle claims and motor claims recovery\nConduct settlement negotiation and represent the company to conduct trials or attend hearings at Small Claim Tribunals or other related forum\nMaintain and manage claims data and statistics, insurance claims data, and insurance administration matters\nWorking Location:\nKowloon Bay\nApplicants who are not invited for interview within 6 weeks may consider their applications unsuccessful.\nPersonal data collected will be used for recruitment purpose only. The Company will keep personal data of unsuccessful job applicants for a maximum period of 12 months. After that time, the personal data will be destroyed.", "employment_types": ["Full Time", "Contract"], "selling_points": ["Career opportunity in a sizeable group", "Attractive remuneration package", "At least one year of testing experience"], "locations": ["Not Specified"], "categories": ["Information Technology (IT)", "Product Management / Business Analyst", "Testing / QA", "Insurance", "Claims Officer"], "post_time": "2022-01-07T10:23:46Z", "salary": {"currency": "HKD", "max": 44999, "min": 20000, "period": "monthly", "term": null}, "salary_visible": true, "title_keywords": ["quality assurance analyst"], "responsibilities": ["administration", "maintain", "insurance", "data"], "requirements": {"degrees": ["university graduate"], "majors": ["related disciplines"], "languages": [], "language_level": [], "hard_skills": ["basic", "data management", "ms office"], "soft_skills": ["telephone manner", "interpersonal skills"], "languages_combined": []}, "experience_required": {"duration": ["at least 4 years"], "field": ["related", "insurance", "legal"]}}, {"job_id": "100003008997907", "location_code": "hk", "company": "AXA Hong Kong", "job_title": "Assistant Claims Officer", "description": "Responsibilities:\n\nMainly responsible for handling liability insurance claims, experience in handling bodily injury Insurance claims is an advantage.\nTake responsibility to resolve all enquiries from both customer and external contacts to ensure delivery of a focused, quality and professional claims service.\nEnsure claims procedures, documentation is adhered to the group claims management requirement and best practice.\n\nRequirements:\n\nDegree holder, preferably with progress in professional insurance qualification such as ACII or ANZIIF\n2-3 years' working experience in\u00a0liability insurance claims\nExcellent customer services, negotiation and communication skills internally and externally.\nCustomer orientated, self initiative and able to work under pressure.\nStrong interpersonal skills with proven ability to communicate effectively at all levels of management.\nGood command of spoken and written English, Mandarin and Cantonese.\nProficiency in MS Word, Excel and Chinese word processing.\nFresh graduates or candidates with less experience will be considered as Assistant Officer.\n\nWe offer competitive remuneration package. Interested parties, please send your resume with CURRENT & EXPECTED salary and DATE AVAILABLE by clicking 'Apply Now'.\n\n(Data collected would be used for recruitment purpose only)", "employment_types": ["Full Time", "Temporary"], "selling_points": ["Corporate role in Life Claims team", "Exposure to Insurance Industry", "Fresh Grads welcome"], "locations": ["Not Specified"], "categories": ["Insurance", "Claims Officer", "Others", "Student / Fresh Graduate / No Experience"], "post_time": "2021-12-24T02:02:02Z", "salary": {"currency": null, "max": null, "min": null, "period": "monthly", "term": null}, "salary_visible": false, "title_keywords": ["claims officer", "assistant"], "responsibilities": ["management", "quality", "procedures", "documentation", "insurance"], "requirements": {"degrees": ["degree holder"], "majors": ["insurance"], "languages": ["cantonese", "english", "chinese", "mandarin"], "language_level": ["proficiency", "good command"], "hard_skills": ["excel", "chinese word processing", "ms word"], "soft_skills": ["communication skills", "negotiation", "interpersonal skills", "initiative", "work under pressure"], "languages_combined": [{"language": "cantonese", "language_level": ["good command"]}, {"language": "english", "language_level": ["good command"]}, {"language": "chinese", "language_level": ["proficiency"]}, {"language": "mandarin", "language_level": ["good command"]}]}, "experience_required": {"duration": ["2-3 years"], "field": ["insurance"]}}, {"job_id": "100003009000229", "location_code": "hk", "company": "Bernhard Schulte ShipMgt (HK) Ltd Partnership", "job_title": "Insurance & Claims Officer", "description": "What are your main responsibilities?\n\nObtain relevant licenses to perform duties accordingly.\nAssist to communicate with regulators.\nAssist internal-external controlled system set up.\nAssist AC matters and compliance related.\nProvide all-rounded support for our Responsible Officer in the business unit of insurance brokerage.\nPerform general clerical duties and handle ad hoc tasks as assigned.\nCoordinate and liaise with internal and external parties on daily business operations.\nRespond to clients and prospective clients in an efficient and professional manner.\n\n\n\nWho are we looking for?\n\nPossess at least a Diploma in any field.\nMin. 3 years of administrative support or any relevant working experience in the insurance industry.\nMust passed IIQE Paper 1 & 2 & 3.\nIIQE Paper 5 and MPF is ideal.\nFamiliar with IT software and applications will be an added advantage.\nProficient in English, Mandarin, and Cantonese is a must.\nHardworking, positive 'can-do' attitude.", "employment_types": ["Full Time", "Permanent"], "selling_points": ["Liaise with various parties for claims", "Maintain P&I & H&M claims documentations &database", "Accurate booking and charging to owner"], "locations": ["North Point"], "categories": ["Insurance", "Claims Officer", "Transportation & Logistics", "Maritime - General"], "post_time": "2021-12-24T15:37:39Z", "salary": {"currency": null, "max": null, "min": null, "period": null, "term": null}, "salary_visible": false, "title_keywords": ["claims officer"], "responsibilities": ["communicate with", "mpf", "software", "administrative support", "brokerage", "operations", "compliance", "ad hoc tasks", "internal and external parties", "professional manner", "coordinate", "liaise with", "insurance"], "requirements": {"degrees": ["diploma"], "majors": [], "languages": ["cantonese", "english", "mandarin"], "language_level": ["proficient"], "hard_skills": ["iiqe paper"], "soft_skills": ["efficient", "responsible", "perform duties", "positive", "can-do", "controlled", "hardworking", "ideal"], "languages_combined": [{"language": "cantonese", "language_level": ["proficient"]}, {"language": "english", "language_level": ["proficient"]}, {"language": "mandarin", "language_level": ["proficient"]}]}, "experience_required": {"duration": ["3 years"], "field": ["insurance industry", "administrative", "relevant working experience"]}}, {"job_id": "100003008998910", "location_code": "hk", "company": "Chubb Insurance Hong Kong Limited", "job_title": "Senior Claims Executive, Marine", "description": "In this role, you will carry out the instruction rendered by the Supervisor to meet or exceed satisfactory operating standards.\nMain Responsibilities:\nVerification of claims particulars before claim registration\nProcessing and settlement of Motor, Employees\u2019 Compensation and Personal Lines claims\nHandle and settle insurance claims within well-defined guidelines\nAnswer Claims Hotlines and general telephone enquiries\nApprove and validate claims settlement and cheque requisitions within the limit of authority\nIdentify and input the blacklisted clients and poor risk cancellation / revision of policy terms to Business Development and Underwriting Department\nApproach injured workers in order to identify EC problematic cases\nApproach motor policyholders guiding them in own damage claims with an aim to have their vehicles repaired in our approved repairers for costs savings purpose\nAssist in UAT\nAssist in ad hoc projects as assigned by supervisors\nTo meet the challenge, you should have the following qualifications and attributes:\nSecondary education or above\nAt least 2 years\u2019 relevant experience with general knowledge in the general insurance industry\nGeneral knowledge in general insurance claims\nGood command of both written and spoken English and Chinese\nGood communication and analytical skills\nGood computer skills\nPlease note that only shortlisted candidates will be notified.", "employment_types": ["Full Time"], "selling_points": ["Largest P&C Insurer", "Great exposure", "General Insurance"], "locations": ["Quarry Bay"], "categories": ["Insurance", "Claims Officer", "Insurance Agent / Broker"], "post_time": "2021-12-24T04:38:34Z", "salary": {"currency": null, "max": null, "min": null, "period": "monthly", "term": null}, "salary_visible": false, "title_keywords": ["executive"], "responsibilities": ["uat", "guidelines", "communication", "ad hoc projects", "insurance", "costs"], "requirements": {"degrees": ["secondary education"], "majors": [], "languages": ["english", "chinese"], "language_level": ["good command"], "hard_skills": ["processing", "computer skills", "analytical skills"], "soft_skills": ["communication", "analytical skills"], "languages_combined": [{"language": "english", "language_level": ["good command"]}, {"language": "chinese", "language_level": ["good command"]}]}, "experience_required": {"duration": ["at least 2 years"], "field": ["general insurance", "relevant experience"]}}, {"job_id": "100003009000338", "location_code": "hk", "company": "Hays", "job_title": "Business Analyst (Claims operation) (25K - 40K)", "description": "Key Responsibilities\n\nHandle insurance pre-approval/ direct billing related administrative and clerical work;\nCoordinate and answer questions from both patients and insurance companies;\nMaintain the service standard and turnaround time for claims process;\nFollow up and ensure insurance forms are completed;\nLiaise with healthcare professionals, patients, customers, cooperate and insurance companies for payment follow up;\nWork closely with clinical departments on operation and billing issues; and\nPerform any other duties as assigned by supervisor(s).\n\u00a0\n\u00a0\n\nJob Requirements\n\nHolder of a Diploma in any disciplines\nAt least 2 years\u2019 relevant experience with prior experience in hospital and insurance company preferred\nExperience in the area of insurance, medical billing, financial counselling or customer service would be an advantage\nCustomer-oriented with excellent communication and interpersonal skills\nTeam player, and able to work independently and under pressure\nAble to work on shift duties\nGood command of both spoken and written English and Chinese\nProficient in MS Office applications\n\nCompensation and Employment Terms\n\nWe provide a unique employment experience for people seeking careers in hospital and healthcare industry; and offer competitive remuneration packages to the successful candidates. Appointment will be made on a 3-year contract with contract-end gratuity, renewable subject to good performance and mutual agreement.\n\nApplication Closing Date\n\n11 January 2022\n\nPersonal Information Collection Statement\n\nData collected will only be used for job application processing. Applicants not contacted by CUHK Medical Centre Limited within eight weeks from the application closing date may assume their applications unsuccessful. All personal data collected will be kept for a period of 12 months from the application closing date, and will be destroyed thereafter.", "employment_types": ["Full Time", "Temporary"], "selling_points": ["Fast growing", "Excellent learning & development opportunities", "Attractive package"], "locations": ["Not Specified"], "categories": ["Information Technology (IT)", "Product Management / Business Analyst", "Insurance", "Claims Officer", "Others"], "post_time": "2021-12-25T04:00:32Z", "salary": {"currency": null, "max": null, "min": null, "period": "monthly", "term": null}, "salary_visible": false, "title_keywords": ["business analyst"], "responsibilities": ["any other duties", "service standard", "coordinate", "payment", "maintain", "liaise with", "insurance"], "requirements": {"degrees": ["diploma"], "majors": ["any disciplines"], "languages": ["english", "chinese"], "language_level": ["good command"], "hard_skills": ["ms office"], "soft_skills": ["work independently", "under pressure", "customer-oriented", "customer service", "communication and interpersonal skills", "team player"], "languages_combined": [{"language": "english", "language_level": ["good command"]}, {"language": "chinese", "language_level": ["good command"]}]}, "experience_required": {"duration": ["at least 2 years"], "field": ["billing", "customer service", "relevant experience", "medical", "insurance", "financial"]}}, {"job_id": "100003008994480", "location_code": "hk", "company": "Hong Leong Insurance (Asia) Limited", "job_title": "Senior Claims Assessor \u2013 Personal Lines", "description": "Responsibilities:\n\nAssist Assistant Claims Manager to support the claims team in daily claims operation, enquiry and continuous claims process improvement\nAssess and approve complicated claims\nMeet service turnaround time and achieve claims KPI targets\nTo handle enquiries from distribution enquiry team, customer enquiry team and customer complaint team\nAssist in reviewing workflow, implementing continuous claims process improvement\nAssist in compiling regular management report\nAssist in conducting training to colleagues and distributors\nParticipate in assigned projects\n\nRequirements:\n\nUniversity graduate with FLMI or equivalent\nRelevant experience in Claims and Insurance Industry is preferred\nCustomer Centric minded and good communication skill\nHigh emotional maturity and able to work under pressure\nExcellent command of both written and spoken English and Chinese\nResult-oriented, self-motivated, patient, cheerful and positive", "employment_types": ["Full Time", "Permanent"], "selling_points": [], "locations": ["North Point"], "categories": ["Insurance", "Claims Officer", "Others"], "post_time": "2021-12-23T01:44:54Z", "salary": {"currency": null, "max": null, "min": null, "period": "monthly", "term": null}, "salary_visible": false, "title_keywords": ["personal"], "responsibilities": ["handle enquiries", "management report"], "requirements": {"degrees": ["university graduate"], "majors": [], "languages": ["english", "chinese"], "language_level": ["excellent"], "hard_skills": [], "soft_skills": ["self-motivated", "cheerful", "communication skill", "patient", "result-oriented", "positive", "work under pressure"], "languages_combined": [{"language": "english", "language_level": ["excellent"]}, {"language": "chinese", "language_level": ["excellent"]}]}, "experience_required": {"duration": [], "field": ["relevant experience", "insurance industry"]}}, {"job_id": "100003008990874", "location_code": "hk", "company": "AXA Hong Kong", "job_title": "Assistant Claims Manager", "description": "Core Responsibilities\n\n\u00a0\u00a0\u00a0\u00a0\u00a0\u00a0\u00a0 Co-ordinate and liaise with the P&I Clubs, Ship owners, surveyors on all related matter to claims\n\u00a0\u00a0\u00a0\u00a0\u00a0\u00a0\u00a0 Ensure all claims are handled and finalized in a timely manner\n\u00a0\u00a0\u00a0\u00a0\u00a0\u00a0\u00a0 Maintain P&I and H&M claims documentations and database\n\u00a0\u00a0\u00a0\u00a0\u00a0\u00a0\u00a0 Co-ordinate with internally parties for accurate booking and charging to owner\n\u00a0\u00a0\u00a0\u00a0\u00a0\u00a0\u00a0 Provide full support in other ad hoc assignments as required\n\nRequirements\n\n\u00a0\u00a0\u00a0\u00a0\u00a0\u00a0\u00a0 Diploma or above\n\u00a0\u00a0\u00a0\u00a0\u00a0\u00a0\u00a0 Around 3 years relevant working experience and preferably with some multinational environment exposure\n\u00a0\u00a0\u00a0\u00a0\u00a0\u00a0\u00a0 Good knowledge of P&I rules, marine insurance industry and claim experience\n\u00a0\u00a0\u00a0\u00a0\u00a0\u00a0\u00a0 Have knowledge in local and international laws relevant to maritime industry\n\u00a0\u00a0\u00a0\u00a0\u00a0\u00a0\u00a0 Good team player, hard working and well-organized\n\u00a0\u00a0\u00a0\u00a0\u00a0\u00a0\u00a0 Self-motivated, independent and detail-minded\n\u00a0\u00a0\u00a0\u00a0\u00a0\u00a0\u00a0 Good command of both spoken and written English\n\u00a0\u00a0\u00a0\u00a0\u00a0\u00a0\u00a0 \u00a0Proficient in MS Office applications, especially in MS Excel\n\n\n\n\nWe offer competitive remuneration package to the right candidate.\u00a0 Interested candidates, please send your CV and application letter to HR Department, Bernhard Schulte Shipmanagement (Hong Kong) Limited Partnership, 26/F K Wah Center, 191 Java Road, North Point, Hong Kong or to our direct fax number 2960-1530 or apply through \u201cApply Now\u201d function.\u00a0 Personal data collected will be used for recruitment purpose only and treated in accordance with Personal Data (Privacy) Ordinance.", "employment_types": ["Full Time", "Permanent"], "selling_points": ["Admin Management", "Claims", "People Manager"], "locations": ["Not Specified"], "categories": ["Insurance", "Claims Officer"], "post_time": "2021-12-22T02:11:39Z", "salary": {"currency": null, "max": null, "min": null, "period": "monthly", "term": null}, "salary_visible": false, "title_keywords": ["assistant claims manager"], "responsibilities": ["co-ordinate with", "a timely manner", "maintain", "booking", "database", "ad hoc assignments", "liaise with"], "requirements": {"degrees": ["diploma or above"], "majors": [], "languages": ["english"], "language_level": ["good command"], "hard_skills": ["ms excel", "ms office"], "soft_skills": ["detail-minded", "good team player", "self-motivated", "independent", "hard working", "well-organized"], "languages_combined": [{"language": "english", "language_level": ["good command"]}]}, "experience_required": {"duration": ["3 years"], "field": ["insurance industry", "relevant working experience"]}}, {"job_id": "100003008991406", "location_code": "hk", "company": "Assicurazioni Generali S.p.A.- Hong Kong Branch", "job_title": "Officer, EB Claims", "description": "(Candidates with less experience will be considered for the position of Claims Executive)\n\n\nResponsibilities:\n\n\n\nHandle, examine and settle Marine claims according with Company philosophy and guidelines\nComply with claims instructions and provide quality work effectively and efficiently\nHandle related enquiries from the policyholders, brokers or relevant parties\nSupport manager to implement initiatives to improve performance\nMaintain positive relationship with all stakeholders\u00a0\nRequirements:\n\n\nBachelor\u2019s degree in any discipline, with ANZIIF (Senior Associate) qualification or equivalent level of Insurance qualification holder is preferred\nAt least 3-5 years working experience in handling\u00a0Marine claims, Freight Forwarder\u2019s Liability is preferred\nResults oriented, self-motivated, responsible individual with high levels of integrity\nGood command of written & spoken English and Cantonese, good speaking Mandarin is preferred\nPC literate in MS Word, Excel and PowerPoint\u00a0\n\nPlease click \"Apply now\" to submit your application.\n\n\nPersonal data collected will be used for recruitment purpose only.\n\n", "employment_types": ["Full Time"], "selling_points": [], "locations": ["Tai Koo"], "categories": ["Insurance", "Claims Officer", "Others"], "post_time": "2021-12-22T03:23:36Z", "salary": {"currency": null, "max": null, "min": null, "period": "monthly", "term": null}, "salary_visible": false, "title_keywords": ["officer"], "responsibilities": ["guidelines", "maintain", "quality"], "requirements": {"degrees": ["degree", "bachelor"], "majors": ["insurance"], "languages": ["cantonese", "english", "mandarin"], "language_level": ["good command", "good"], "hard_skills": ["excel", "pc literate", "powerpoint", "ms word"], "soft_skills": ["self-motivated", "integrity", "responsible"], "languages_combined": [{"language": "cantonese", "language_level": ["good command"]}, {"language": "english", "language_level": ["good command"]}, {"language": "mandarin", "language_level": ["good", "good command"]}]}, "experience_required": {"duration": ["at least 3-5 years"], "field": []}}, {"job_id": "100003008991442", "location_code": "hk", "company": "Talent Pro Recruitment Company Limited", "job_title": "Claims Officer (Secondment role)", "description": "The appointee will be primarily responsible for handling Personal Lines claims including but not limited to Home, Hospital Cash, Personal Accident, Travel and Domestic Helper\u2019s claims\n\nRequirements:\n\nSecondary Education or above, with ANZIIF Associateship or ACII qualification or above is preferable\n2-3 years' claims experience in insurance company\nCustomer service oriented\nGood communication and interpersonal skills\nGood command of spoken English and Chinese\nProficiency in MS Word, Excel and Chinese word processing\nKnowledge in AS400, SAS is a plus\nPlease apply (preferably in Word or PDF format) with present and expected salaries,\u00a0quoting job reference (JDBI/2312/SCAPL)\u00a0to Head of Human Resources, 50/F The Center, 99 Queen\u2019s Road Central, Hong Kong or email to us\u00a0or fax to 2285 3209. You are invited to visit our website at:\u00a0http://www.hl-insurance.com.\n\n\n\nAll applications will be treated in strict confidence and used for recruitment purpose within Guoco Group Limited, or Hong Leong Group of which Guoco is a member (together, \u201cthe Group\u201d) only. A copy of our personal data policy is available on request.\n\nApplicants not hearing from us within\u00a08 weeks may consider their applications unsuccessful. We may also consider their application for other or future vacancies within the Group.\u00a0 Personal data of unsuccessful applicants will be retained by the Group for a maximum period of one year.", "employment_types": ["Contract"], "selling_points": ["5-day work week", "Minimum of 1 year claims experience", "Secondment role"], "locations": ["Central & Western Area"], "categories": ["Insurance", "Claims Officer", "Others"], "post_time": "2021-12-22T03:26:41Z", "salary": {"currency": null, "max": null, "min": null, "period": "monthly", "term": null}, "salary_visible": false, "title_keywords": ["claims officer"], "responsibilities": ["website", "communication", "customer service", "recruitment", "personal data", "insurance"], "requirements": {"degrees": ["secondary education"], "majors": [], "languages": ["english", "chinese"], "language_level": ["proficiency", "good command"], "hard_skills": ["excel", "plus", "chinese word processing", "sas", "word", "ms word"], "soft_skills": ["confidence", "communication and interpersonal skills", "customer service oriented", "responsible"], "languages_combined": [{"language": "english", "language_level": ["good command"]}, {"language": "chinese", "language_level": ["proficiency", "good command"]}]}, "experience_required": {"duration": ["2-3 years"], "field": ["insurance"]}}, {"job_id": "100003008995187", "location_code": "hk", "company": "Golden Century International Holdings Group Limited", "job_title": "Insurance Operation Officer/Senior Officer", "description": "Assist Claims Manager to support the claims team in claims investigation, daily claims operation, enquiry, and continuous claims process improvement\nAssess and approve complicated claims\nMonitor and control daily operations to be carried out smoothly\nTo ensure delivery of agreed service standards\nTo handle enquiries from distribution enquiry team, customer enquiry teams and complaint team\nReview staff performance, develop and monitor plan for staff development\nDrive and oversee plans for system modifications and to continue meeting, improving and anticipating customer needs and developing relationship with agency force\nImplement continuous claims process improvement to strive for operational efficiency\nProvide training to claim colleagues and other internal staff so as to uplift their claims knowledge\nReview and revise internal claims manuals, guidelines and practices\nTo assist in all operational and project issues\nUniversity graduate or above with FLMI or equivalent\nAt least 5-years' experience in Claims with at least 1 years in management position\nStrong technical skills and knowledge of Claims\nCustomer Centric minded and good communication skill\nResult-oriented, self-motivated, patient, cheerful and positive\nHigh emotional maturity and able to work under pressure\nExcellent command of both written and spoken English and Chinese, Mandarin is an advantage", "employment_types": ["Full Time", "Temporary"], "selling_points": ["General Insurance", "Qualification in IIQE Paper I,II", "Minimum 2 years related work experience"], "locations": ["Causeway Bay"], "categories": ["Insurance", "Claims Officer", "Insurance Agent / Broker", "Others"], "post_time": "2021-12-24T03:00:17Z", "salary": {"currency": null, "max": null, "min": null, "period": "monthly", "term": null}, "salary_visible": false, "title_keywords": ["senior officer", "operation officer"], "responsibilities": ["provide training", "control", "management", "guidelines", "review", "monitor", "teams", "investigation", "develop", "developing", "handle enquiries", "service standards", "daily operations", "communication", "plan", "plans", "work under pressure"], "requirements": {"degrees": ["university graduate or above"], "majors": [], "languages": ["english", "chinese", "mandarin"], "language_level": ["advantage", "excellent"], "hard_skills": [], "soft_skills": ["self-motivated", "cheerful", "communication skill", "technical skills", "patient", "result-oriented", "positive", "work under pressure"], "languages_combined": [{"language": "english", "language_level": ["excellent"]}, {"language": "chinese", "language_level": ["excellent"]}, {"language": "mandarin", "language_level": ["advantage", "excellent"]}]}, "experience_required": {"duration": ["at least 1 years"], "field": ["management position"]}}, {"job_id": "100003008993655", "location_code": "hk", "company": "RecruitFirst Limited", "job_title": "EB Policy Administration Senior Officer", "description": "Job Descriptions\nHandle adjudication and pre-approval process for medical claims\nHandle enquiry calls from both members and panel providers\nProvide administrative support, such as data entry, filing, report compilation, doctor panel movements, etc.\nAny other duties as assigned by the supervisors\nRequirements\nDiploma holder or above in relevant disciplines\nMinimum 2 years\u2019 relevant experience; experience in medical claims processing is definitely an advantage\nGood interpersonal and communication skills\nGood problem solving skills, a team player and customer-oriented\nAble to work independently with tight schedule\nExcellent\u00a0command of\u00a0both written and spoken English and Cantonese\nProficiency in Microsoft Office\n5-day work week; shift work may be required\nImmediately available is an advantage\nCandidate with lesser experience will be considered as Assistant Claims Officer\nInterested parties please send full resume with last and expected salary in English to Raffles Medical Group (Hong Kong) Limited by clicking \"Apply Now\".\n\n\n(Only shortlisted candidates will be contacted for interview. All personal data collected will be treated in strict confidence and will only be used for recruitment related purpose.)", "employment_types": ["Full Time", "Permanent"], "selling_points": [], "locations": ["Tai Koo"], "categories": ["Professional Services", "Business Analysis / Data Analysis", "Insurance", "Claims Officer", "Others"], "post_time": "2021-12-22T08:50:27Z", "salary": {"currency": null, "max": null, "min": null, "period": "monthly", "term": null}, "salary_visible": false, "title_keywords": ["senior officer"], "responsibilities": ["any other duties", "data entry", "handle enquiry", "provide administrative support", "report"], "requirements": {"degrees": ["diploma holder"], "majors": [], "languages": ["cantonese", "english"], "language_level": ["excellent"], "hard_skills": ["problem solving skills", "processing", "microsoft office"], "soft_skills": ["communication skills", "work independently", "customer-oriented", "team player", "problem solving skills", "interpersonal"], "languages_combined": [{"language": "cantonese", "language_level": ["excellent"]}, {"language": "english", "language_level": ["excellent"]}]}, "experience_required": {"duration": ["minimum 2 years"], "field": ["relevant experience", "medical"]}}, {"job_id": "100003008993773", "location_code": "hk", "company": "Chandler Macleod Group (HK) Limited", "job_title": "Insurance Policy Assistant Manager (Up to 35K/mth)", "description": "Job Descriptions:\n\nFollow up on additional supporting documents to facilitate the decision on underwriting, compliance and premium financing after case submission\nPrepare and check decline / after investigation letters\nInput personal data and prepare reports\nConduct claims investigation\nHandle claims appeal case / complaint cases related to claims\nRespond to agents enquiries and other agent related enquiries\n\nJob Requirements:\n\nDegree from a recognized University professional qualification in Life Insurance including FLMI (Fellow, Life Management Institute), ALHC (Associate, Life and Health Claims), ACS (Associate, Customer Service) would be an advantage.\nMinimum of 1 year claims experience in insurance industry\nGood PC skills. Good English and Cantonese. Good written English and Chinese.\n\nData collected will be used for recruitment purposes only. Candidates who are not being contacted within 2 weeks would consider their application unsuccessful.\u00a0", "employment_types": ["Full Time", "Contract"], "selling_points": ["A well-established financial services firm", "Must have complaint handling experience", "Immediately available highly preferred"], "locations": ["Not Specified"], "categories": ["Banking / Finance", "Financial Services", "Insurance", "Claims Officer", "Others"], "post_time": "2021-12-22T09:17:45Z", "salary": {"currency": null, "max": null, "min": null, "period": "monthly", "term": null}, "salary_visible": false, "title_keywords": ["assistant manager"], "responsibilities": ["compliance", "letters", "investigation", "prepare reports", "personal data"], "requirements": {"degrees": ["degree"], "majors": ["insurance"], "languages": ["cantonese", "english", "chinese"], "language_level": ["good"], "hard_skills": ["pc skills"], "soft_skills": ["customer service"], "languages_combined": [{"language": "cantonese", "language_level": ["good"]}, {"language": "english", "language_level": ["good", "good"]}, {"language": "chinese", "language_level": ["good"]}]}, "experience_required": {"duration": ["minimum of 1 year"], "field": ["insurance industry"]}}]