[{"job_id": "100003009054890", "location_code": "hk", "company": "Jobson Mores Limited", "job_title": "Insurance - Senior Manager, Office Administration (Over 500 employees)", "description": "Job Description\n\nThe incumbent will\u00a0 handle\u00a0 all\u00a0 the\u00a0 operations in Underwriting\u00a0 team;\u00a0 and assist Supervisor /\u00a0Manager in all aspects relating to Underwriting and Policy Administration.\n\n\nQualification Requirements\n\nForm 7 or above, with pass in English, Mathematics and Chinese\n3 - 5 years relevant experience\nGood interpersonal and communication skills\nExcellent spoken and written skills in English and Chinese\nHands-on PC skills in MS Word and MS Excel\nOrganized, responsible and careful\nImmediate available is preferred\nCandidates with less experience will be considered as Clerk\n\n\nOther Job Openings\n\nPlease visit \u201cCareer Opportunities\u201d in our website http://www.asiainsurance.hk\n\nAt Asia\u00a0 Insurance\u00a0 Co.,\u00a0 Ltd.,\u00a0 we\u00a0 are\u00a0 committed\u00a0 to\u00a0 offer\u00a0 good\u00a0 career\u00a0 prospects, 5\u00a0 days\u00a0 week, 16 days\u00a0 Annual\u00a0 Leave, Birthday Leave, competitive remuneration and benefits package. \u00a0\n\nInterested parties may apply with full resume including present & expected salary, contact phone number, job reference code above and send it to Human\u00a0 Resources\u00a0 Department,\u00a0 Asia\u00a0 Insurance\u00a0 Co.,\u00a0 Ltd., 8/F\u00a0 118 Connaught\u00a0 Road\u00a0 West, Sheung Wan, Hong Kong or click \"Apply Now\" to submit your application. Applicants who are not contacted within one month may consider their applications unsuccessful.\n\nAll information provided by applicants\u00a0 will be used in the strictest confidential in accordance\u00a0 with the employer's personal data policy, and\u00a0 will\u00a0 be\u00a0 handled\u00a0 by\u00a0 authorized\u00a0 personnel\u00a0 for\u00a0 recruitment-related\u00a0 purposes\u00a0 only.\u00a0 Applicants\u00a0 may\u00a0 be\u00a0 considered\u00a0 for\u00a0 other\u00a0 suitable positions within the Company and our subsidiary or associate companies over a four-month period, after which their personal data will be destroyed.", "employment_types": ["Full Time"], "selling_points": ["Full Spectrum of Administrative Support", "Procurement, Contract and Documentations", "Mature, Self-motivated and Meticulous"], "locations": ["Tai Koo"], "categories": ["Admin & HR", "Administration / Operation Manager", "Clerical / Admin Staff", "Insurance", "Others"], "post_time": "2022-01-17T12:49:28Z", "salary": {"currency": null, "max": null, "min": null, "period": "monthly", "term": null}, "salary_visible": false, "title_keywords": ["senior manager"], "responsibilities": ["operations", "administration"], "requirements": {"degrees": [], "majors": [], "languages": ["english", "chinese"], "language_level": ["excellent"], "hard_skills": ["ms excel", "pc skills", "ms word"], "soft_skills": ["organized", "communication skills", "careful", "responsible", "committed", "hands-on", "interpersonal"], "languages_combined": [{"language": "english", "language_level": ["excellent"]}, {"language": "chinese", "language_level": ["excellent"]}]}, "experience_required": {"duration": ["3 - 5 years"], "field": ["relevant experience"]}}, {"job_id": "100003009051614", "location_code": "hk", "company": "Lo Lo's Workshop", "job_title": "Secretary", "description": "Responsibilities:\n\nAssist in preparing policy endorsements, contract provisions and confirmation letter for policy changes\n\nAssist in document sorting and filling, quality checking, policy binding, arrange files for settling bill payment\n\nMeet service turnaround time to achieve target includes productivity, error rate, complaint rate and customer satisfaction rate\n\nMaintain a good control on output logistic\n\nPerform other related duties and ad hoc task to support the operation of the department\n\n\nRequirements:\n\nForm 6 or above\n\nAt least 1 year relevant working experience\n\nGood interpersonal and communication skills\n\nSelf-motivated, detail-oriented and positive mind set\n\nGood command of both written and spoken in English & Chinese\n\nGood PC skills including Chinese Typing\n\nKnowledge in AS400 is preferable\n\nFresh Graduate will also be considered\n", "employment_types": ["Full Time", "Permanent"], "selling_points": [], "locations": ["Kwun Tong Area"], "categories": ["Admin & HR", "Secretary", "Insurance", "Others", "Sales, CS & Business Devpt", "Sales Administration"], "post_time": "2022-01-16T14:33:51Z", "salary": {"currency": null, "max": null, "min": null, "period": "monthly", "term": null}, "salary_visible": false, "title_keywords": ["secretary"], "responsibilities": ["quality checking", "control", "ad hoc", "payment", "maintain"], "requirements": {"degrees": ["fresh graduate"], "majors": [], "languages": ["english", "chinese"], "language_level": ["good command", "good"], "hard_skills": ["pc skills", "typing"], "soft_skills": ["communication skills", "self-motivated", "detail-oriented", "interpersonal", "positive"], "languages_combined": [{"language": "english", "language_level": ["good command", "good"]}, {"language": "chinese", "language_level": ["good command", "good", "good"]}]}, "experience_required": {"duration": ["at least 1 year"], "field": ["relevant working experience"]}}, {"job_id": "100003009053259", "location_code": "hk", "company": "BestServe Financial Ltd", "job_title": "Supervisor, TPA Operations (Pensions - Termination Team)", "description": "Responsibilities\n\nTo provide secretarial support to Senior Manager in insurance\u00a0company agency office\nPrepare agenda & minutes\nPrepare meeting clients' documents, scheduling meetings and appointments and so on\nAssist in monitoring admin progress and preparing status report\nMaintain up-to-date and systematic filing system; Administer and monitor clients calls\nAlso responsible for team administration\nNO SALES job and DON'T need to meet clients\n\nRequirements\n\nForm 7 or above with\u00a0secretarial or business training\u00a0\nOver\u00a05 years secretarial and administrative experience, advantageous to have relevant secretarial experience in insurance company / bank\nFamiliar with PC applications including MS Excel, Word and Chinese Word Processing ( Excel is important in this job post )\nGood command of both written and spoken English and Cantonese, Mandarin is a plus\nMature and independent, detail-minded, with initiatives and positive attitude\n\nPlease apply with full resume including expected salary and date availability\n\n\nAll applications will be treated in strict confidence.", "employment_types": ["Full Time", "Permanent"], "selling_points": ["Pensions Administration / Termination / MPF ORSO", "Process transaction / Supervisor / Mentor / Coach", "UAT / Projects / e-MPF / 5 days work"], "locations": ["Hung Hom"], "categories": ["Admin & HR", "Administration / Operation Manager", "Insurance", "Others", "Banking / Finance", "Order Processing & Operation / Settlement"], "post_time": "2022-01-17T06:35:54Z", "salary": {"currency": null, "max": null, "min": null, "period": "monthly", "term": null}, "salary_visible": false, "title_keywords": ["operations", "supervisor"], "responsibilities": ["administration", "monitoring", "monitor", "scheduling", "maintain", "secretarial support", "insurance", "report"], "requirements": {"degrees": [], "majors": [], "languages": ["cantonese", "english", "chinese", "mandarin"], "language_level": ["good command"], "hard_skills": ["excel", "plus", "chinese word processing", "word", "pc applications", "ms excel"], "soft_skills": ["detail-minded", "confidence", "independent", "mature", "positive attitude"], "languages_combined": [{"language": "cantonese", "language_level": ["good command"]}, {"language": "english", "language_level": ["good command"]}, {"language": "chinese", "language_level": []}, {"language": "mandarin", "language_level": ["good command"]}]}, "experience_required": {"duration": ["5 years"], "field": ["secretarial", "administrative", "insurance"]}}, {"job_id": "100003009053118", "location_code": "hk", "company": "Asia-Pacific Property & Casualty Insurance Co., Ltd.", "job_title": "Admin & HR Clerk/Officer (6 months contract)", "description": "Job Responsibilities\nConduct the pre/post sales call by face-to-face or phone with stipulate the tailor-made script to MCV with frequent Mandarin speaking.\nHandle customer enquiries via hotline and walk-in services\nMeet service standard and KPIs according to internal guidelines and rules\nConduct various outbound calls with documented protocols\nLiaise with internal departments, channels and customers on replies to enquiries and required documents\nMaintain and improves quality results by adhering to standards and guidelines; recommending improved procedures.\nProvide customers with product and service information\nIdentify and escalate priority issues\nDocument all call information according to standard operating procedures\nParticipate in customer service-related projects and provide recommendations to improve work processes and service level of the team\nJob Requirements\nDiploma or above in any discipline\nMinimum of 4 years in client service with good knowledge of insurance industry preferred\nHolder of IIQE paper 1, 3 and 5 is preferable\nStrong team player with positive attitude\nClient-centric with good communication and interpersonal skills\nDetail-minded, multi-tasked and able to work under pressure\nGood spoken and written English & Chinese (both Cantonese and Mandarin)\nGood PC skills in MS Office\n\u00a0\nWe offer attractive salary, MPF, group life and group medical insurance and excellent career development opportunities to the right candidate.\nWe are an equal opportunity employer and welcome applications from all qualified candidates. Application forms and resume will be kept for a period of\u00a024 months after completion of the recruitment process. (All information will be held in strict confidence and only used for recruitment purpose.)", "employment_types": ["Full Time", "Temporary", "Contract"], "selling_points": ["Admin HR Clerk Officer Contract", "5-day work", "Attractive benefits"], "locations": ["Sheung Wan"], "categories": ["Insurance", "Others"], "post_time": "2022-01-17T05:55:11Z", "salary": {"currency": null, "max": null, "min": null, "period": "monthly", "term": null}, "salary_visible": false, "title_keywords": ["hr clerk", "officer", "admin"], "responsibilities": ["handle customer enquiries", "service standard", "guidelines", "quality", "procedures", "maintain", "customer service", "provide recommendations", "liaise with", "kpis"], "requirements": {"degrees": ["diploma or above"], "majors": [], "languages": ["cantonese", "english", "chinese", "mandarin"], "language_level": ["good"], "hard_skills": ["iiqe paper", "pc skills", "ms office"], "soft_skills": ["detail-minded", "positive attitude", "communication and interpersonal skills", "multi-tasked", "team player", "work under pressure"], "languages_combined": [{"language": "cantonese", "language_level": ["good"]}, {"language": "english", "language_level": ["good"]}, {"language": "chinese", "language_level": ["good"]}, {"language": "mandarin", "language_level": ["good"]}]}, "experience_required": {"duration": [], "field": []}}, {"job_id": "100003009053216", "location_code": "hk", "company": "Sun Life Hong Kong Ltd", "job_title": "Assistant Administration Officer (Cashier - Insurance Service Centre)", "description": "You are as unique as your background, experience and point of view. Here, you\u2019ll be encouraged, empowered and challenged to be your best self. You'll work with dynamic colleagues - experts in their fields - who are eager to share their knowledge with you. Your leaders will inspire and help you reach your potential and soar to new heights. Every day, you'll have new and exciting opportunities to make life brighter for our Clients - who are at the heart of everything we do. Discover how you can make a difference in the lives of individuals, families and communities around the world.\nJob Description:\nJob Responsibilities:\nPerform or review most of MPF/ORSO business processes and approves various business transactions up to predefined authority limits.\nReview majority processing transactions for working partner(s).\nEnsure the completion of business transactions according to the service standards and statutory timeline.\nMake recommendations and execute process streamlining and service improvement initiatives.\nCoach and mentor junior staff so as to achieve the service standard and department objectives.\nHandle and resolve complicated issues or complaints and escalate to manager in a timely manner.\nPerform daily MPF administration functions of contribution, employer enrolment and data and member/preserved member enrolment and data change.\nUpdate relevant administration / imaging system and control log timely and accurately\nHandle UAT and ad-hoc project as required.\nReport any irregularities to manager promptly.\u200b\nJob Requirements:\nHKDSE (Hong Kong Diploma of Secondary Education) holder\u00a0 / Form 7 graduate or above\nAt least 5 years of relevant experience in MPF industry.\nKnowledge of MPF, customer service principle and retirement fund operations.\nGood in analytical, planning and organizing skills.\nCustomer focused, with good problem-solving and communication skills\nAttention to details\nAble to work independently and under pressure\nGood PC skills in MS Word & Excel. Candidate with skill in Access is preferable\nGood command of both written and spoken English and Chinese\u200b\nWe offer 5-day work, attractive salary, MPF, group life and group medical insurance and excellent career development opportunities to the right candidate.\nWe are an equal opportunity employer and welcome applications from all qualified candidates. Application forms and resume will be kept for a period of\u00a024 months after completion of the recruitment process. (All information will be held in strict confidence and only used for recruitment purpose.)", "employment_types": ["Full Time", "Permanent"], "selling_points": ["Cashier / Payment / Service Centre / Mandarin", "Customer Service / Centre operation / Counter", "3 years working experience"], "locations": ["Hung Hom"], "categories": ["Sales, CS & Business Devpt", "Customer Service - Supervisor / Officer", "Insurance", "Others", "Others"], "post_time": "2022-01-17T06:27:35Z", "salary": {"currency": null, "max": null, "min": null, "period": "monthly", "term": null}, "salary_visible": false, "title_keywords": ["assistant administration officer"], "responsibilities": ["make recommendations", "ad-hoc", "control", "mpf", "service standard", "data", "uat", "review", "a timely manner", "report any irregularities", "transactions", "service standards", "administration"], "requirements": {"degrees": ["diploma", "hkdse", "secondary education"], "majors": [], "languages": ["english"], "language_level": ["good command"], "hard_skills": ["excel", "problem-solving", "pc skills", "ms word"], "soft_skills": ["communication skills", "work independently", "confidence", "under pressure", "focused", "problem-solving", "customer service", "attention to details"], "languages_combined": [{"language": "english", "language_level": ["good command"]}]}, "experience_required": {"duration": ["at least 5 years"], "field": ["relevant experience", "mpf"]}}, {"job_id": "100003009052223", "location_code": "hk", "company": "Aon Services Hong Kong Limited \u6021\u5b89\u670d\u52d9\u9999\u6e2f\u6709\u9650\u516c\u53f8", "job_title": "Assistant Account Executive - General Insurance", "description": "Job Responsibilities\n\nProviding receptionist service, handling telephone calls, courier services;\nHandling office supplies, place order and stock keeping;\nResponsible for general duties of HR, maintain attendance records in the personnel files;\nOffice administrative support to Maintenance & Repair;\nCapable to handle correspondence and multitask independently;\nCo-ordinate and support scheduled activities;\nAssist in ad hoc duties as assigned.\n\nJob Requirements\n\nDiploma or above;\nAt least 2 years of experience in office administration, related to insurance office is preferred;\nProficiency in Microsoft Office applications;\nGood command of both spoken and written English and Mandarin;\nGood communication and interpersonal skills;\nIndependent and able to work under pressure;\nImmediately available is highly preferred.\n\nWe offer 5-day week, competitive remuneration package, and good career prospects to the right candidate. Interested parties please send your resume with\u00a0EXPECTED SALARY\u00a0by clicking \u201cAPPLY NOW\u201d. All personal data collected would be used for recruitment purpose only)", "employment_types": ["Full Time", "Permanent"], "selling_points": [], "locations": ["Quarry Bay"], "categories": ["Admin & HR", "Clerical / Admin Staff", "Insurance", "Insurance Agent / Broker", "Others"], "post_time": "2022-01-17T02:30:38Z", "salary": {"currency": null, "max": null, "min": null, "period": "monthly", "term": null}, "salary_visible": false, "title_keywords": ["assistant account executive"], "responsibilities": ["ad hoc duties", "attendance", "maintenance", "administrative support", "office supplies", "hr", "repair", "maintain"], "requirements": {"degrees": ["diploma or above"], "majors": [], "languages": ["english", "mandarin"], "language_level": ["good command"], "hard_skills": ["microsoft office"], "soft_skills": ["communication and interpersonal skills", "independent", "work under pressure"], "languages_combined": [{"language": "english", "language_level": ["good command"]}, {"language": "mandarin", "language_level": ["good command"]}]}, "experience_required": {"duration": ["at least 2 years"], "field": ["related", "office administration", "insurance"]}}, {"job_id": "100003009052220", "location_code": "hk", "company": "Aon Services Hong Kong Limited \u6021\u5b89\u670d\u52d9\u9999\u6e2f\u6709\u9650\u516c\u53f8", "job_title": "Senior / Executive, Enrolment - Health Solutions", "description": "Job Responsibilities\nPerform cashier duties in Cashier Offices to ensure its smooth operation to meet our service pledge.\nEnsure the transactions are being handled in accordance to company's procedure and guidelines including AML, payment settlement of the case is made accurately and timely.\nHandle administrative duties\nSupport in Mainland Customer Verification\nJob Requirements\nDSE graduate or above\n3 years solid working experience in Cashiering / Client Services, with good knowledge in insurance, financial services and regulatory guidelines\nProficient in both written and spoken Cantonese, Mandarin and English\nWe offer 5-day work, attractive salary, MPF, group life and group medical insurance; and excellent career development opportunities to the right candidate.\nWe are an equal opportunity employer and welcome applications from all qualified candidates. Application forms and resume will be kept for a period of 24 months after completion of the recruitment process. (All information will be held in strict confidence and only be used for recruitment purpose).", "employment_types": ["Full Time", "Permanent"], "selling_points": [], "locations": ["Quarry Bay"], "categories": ["Admin & HR", "Clerical / Admin Staff", "Insurance", "Claims Officer", "Others"], "post_time": "2022-01-17T02:30:37Z", "salary": {"currency": null, "max": null, "min": null, "period": "monthly", "term": null}, "salary_visible": false, "title_keywords": ["executive"], "responsibilities": ["aml", "guidelines", "transactions", "payment", "administrative duties"], "requirements": {"degrees": ["dse"], "majors": [], "languages": ["cantonese", "english", "mandarin"], "language_level": ["proficient"], "hard_skills": [], "soft_skills": [], "languages_combined": [{"language": "cantonese", "language_level": ["proficient"]}, {"language": "english", "language_level": ["proficient"]}, {"language": "mandarin", "language_level": ["proficient"]}]}, "experience_required": {"duration": ["3 years"], "field": ["insurance", "financial services"]}}, {"job_id": "100003009053119", "location_code": "hk", "company": "Asia-Pacific Property & Casualty Insurance Co., Ltd.", "job_title": "Manager, Business Development", "description": "Job Scope\nYou will be contributing in developing and implementing of individual health insurance\u2019s strategy to achieve strategic objectives and financial targets. In addition to this, you will be supporting after sale services in individual health insurance business.\n\nMain Responsibilities\n\nSupport sales in individual health insurance business for both life and non-life units \u2013 providing insurance products assistance (pre-sale and post-sale enquiries) to sales/broker, medical and healthcare service providers\nCo-ordinate with different departments to manage the selling process and monitor the after-sale servicing issues to provide high quality service\nMonitor and implement the underwriting and operations processes & identify areas of improvement to enhance operational efficiency and service standard.\nCollect feedbacks and review health insurance policies and guidelines & act as an advisor on medical/health services.\nAssist all aspects of policy servicing with respect to New Health Insurance Business and/or New Health Products\nSupport marketing initiatives to other business units for business development activities.\n\nRequirement\n\nAt least 5-8 years\u2019 working experience in medical insurance operation.\nExcellent customer service skill to handle sales and customer enquiries\nGood interpersonal, organization, problem-solving and communication skills.\nProficient in PC and system applications, e.g., AS400 and GIS\nProfessional qualification in insurance industry or any health care disciplines, and university graduated in nursing, pharmacy or other medical/pharmaceutical or other related discipline (not a must).\nGood command of written and spoken Chinese and English", "employment_types": ["Full Time", "Permanent"], "selling_points": ["Business Development", "5-day work", "Attractive benefits"], "locations": ["Sheung Wan"], "categories": ["Insurance", "Others"], "post_time": "2022-01-17T05:55:11Z", "salary": {"currency": null, "max": null, "min": null, "period": "monthly", "term": null}, "salary_visible": false, "title_keywords": ["manager"], "responsibilities": ["service standard", "co-ordinate with", "operations", "policies", "review", "quality", "monitor", "guidelines", "insurance"], "requirements": {"degrees": [], "majors": [], "languages": ["english", "chinese"], "language_level": ["good command"], "hard_skills": ["pc", "problem-solving"], "soft_skills": ["communication skills", "problem-solving", "customer service", "interpersonal"], "languages_combined": [{"language": "english", "language_level": ["good command"]}, {"language": "chinese", "language_level": ["good command"]}]}, "experience_required": {"duration": ["at least 5-8 years"], "field": ["operation", "insurance", "medical"]}}, {"job_id": "100003009053279", "location_code": "hk", "company": "BestServe Financial Ltd", "job_title": "Senior Manager, TPA Operations (Pensions Administration)", "description": "Hong Kong based Insurance Strategy Opportunity\n\nYour new company\nAn emerging Life Insurance firm is looking to grow within their strategy team. This multi-award winning organization is now looking for a Strategy Manager to oversee business initiatives within various areas of the company.\n\nYour new role\nAs the Strategy, working within the Strategy Team, you will conduct business planning, gather data on various segments of the business and assist in the executive of the company's strategic plan and vision. You will liaise with various levels of management and be responsible for implementing strategic change aligned with the company's strategic goals.\n\nWhat you'll need to succeed\nA successful applicant you will have at least 5 years' experience in a Consultancy or Business-Orientated function. Insurance or Financial Services industry experience will be a key asset. Strong communications in English & Cantonese are required for this role.\n\nCandidates with less experience will be considered for Assistant Manager\n\nWhat you'll get in return\nIn return, there will be plenty of career opportunity within this top-tier insurance organization and remuneration will be attractive.\n\nWhat you need to do now\nIf you fulfil all the qualifications mentioned above and have the drive to succeed or are interested in similar roles within insurance, please contact me with an attached CV at Jason.Kwong@hays.com.hk or please call +852-2230-7939", "employment_types": ["Full Time", "Permanent"], "selling_points": ["Pensions Administration / E-mpf / Projects", "10 years\u2019 experience / Operation revamp", "Managerial skills / MPF ORSO operations"], "locations": ["Hung Hom"], "categories": ["Insurance", "Others"], "post_time": "2022-01-17T06:39:38Z", "salary": {"currency": null, "max": null, "min": null, "period": "monthly", "term": null}, "salary_visible": false, "title_keywords": ["senior manager", "operations"], "responsibilities": ["management", "business initiatives", "data", "contact", "plan", "liaise with", "insurance", "planning"], "requirements": {"degrees": [], "majors": [], "languages": ["cantonese", "english"], "language_level": [], "hard_skills": [], "soft_skills": ["interested in", "responsible"], "languages_combined": [{"language": "cantonese", "language_level": []}, {"language": "english", "language_level": []}]}, "experience_required": {"duration": ["at least 5 years"], "field": ["financial services industry", "business", "insurance"]}}, {"job_id": "100003009052216", "location_code": "hk", "company": "Aon Services Hong Kong Limited \u6021\u5b89\u670d\u52d9\u9999\u6e2f\u6709\u9650\u516c\u53f8", "job_title": "Account Manager - Corporate", "description": "Key Responsibilities\n\nProvide high-quality customer services with appropriate telephone etiquette\nHandle appointment bookings and general enquiries\nUpdate and maintain Frequently Asked Questions\nAssist in compiling various operation procedures, guidelines, working manuals, reports and other documents required\nProvide administrative support to the hospital administration team\nPerform any other duties (in the capacity as Customer Service Officer) as assigned by supervisor(s) from time to time\nShift duty is required\n\nJob Requirements\n\nHolder of a diploma in Health Management, Hospitality Management or Customer Service related disciplines\nAt least 2 years\u2019 relevant working experience, preferably in hospital\nDemonstrates good communication, customer services, interpersonal and problem-solving skills\nAble to handle multi-task independently\nProficient in MS Office applications\nWilling to rotate to different business unites\nProficiency in both spoken and written English and Chinese, including Mandarin\n\nCompensation and Employment Terms\n\nWe provide a unique employment experience for people seeking careers in hospital and healthcare industry; and offer competitive remuneration packages to the successful candidates. Appointment will be made on a 3-year contract with contract-end gratuity, renewable subject to good performance and mutual agreement.\n\nApplication Deadline\n\n30 January 2022\n\nPersonal Information Collection Statement\n\nData collected will only be used for job application processing. Applicants not contacted by CUHK Medical Centre Limited within eight weeks from the application closing date may assume their applications unsuccessful. All personal data collected will be retained for less than 12 months from the application closing date, and will be destroyed thereafter.", "employment_types": ["Full Time", "Permanent"], "selling_points": [], "locations": ["Quarry Bay"], "categories": ["Insurance", "Claims Officer", "Underwriter", "Others"], "post_time": "2022-01-17T02:30:35Z", "salary": {"currency": null, "max": null, "min": null, "period": "monthly", "term": null}, "salary_visible": false, "title_keywords": ["account manager"], "responsibilities": ["any other duties", "guidelines", "quality", "procedures", "customer services", "maintain", "reports", "customer service", "provide administrative support", "administration"], "requirements": {"degrees": ["diploma"], "majors": ["hospitality management", "related disciplines"], "languages": ["english", "chinese", "mandarin"], "language_level": ["proficiency"], "hard_skills": ["problem-solving skills", "ms office"], "soft_skills": ["independently", "multi-task", "communication", "customer service", "problem-solving skills", "interpersonal"], "languages_combined": [{"language": "english", "language_level": ["proficiency"]}, {"language": "chinese", "language_level": ["proficiency"]}, {"language": "mandarin", "language_level": ["proficiency"]}]}, "experience_required": {"duration": ["at least 2 years"], "field": ["relevant working experience"]}}, {"job_id": "100003009054478", "location_code": "hk", "company": "CUHK Medical Centre Limited", "job_title": "Customer Service Officer (Call Centre)", "description": "Our Client :\u00a0\nTop Insurers in HK\n\n\u00a0Role\u00a0Overview:\n\nMarket Company products and services to Agency / Brokerage Channel partners in order to increase the sales volume and maximize the business opportunities.\nStrengthen and maintain a good relationship with assigned brokers to drive the new initiatives\nProvide all levels of Marketing / Sales support to Channel Partners to capture the business opportunities\n\nIdeal Profile:\n\n\u00a0\u00a0\u00a0\u00a0\u00a0\u00a0\u00a0\u00a0 University / College graduate plus at least 4 years relevant experience in insurance or retail banking", "employment_types": ["Full Time"], "selling_points": ["Handle appointment bookings and general enquiries", "Relevant working experience in hospital", "Stable work environment with competitive benefits"], "locations": ["Shatin Area"], "categories": ["Sales, CS & Business Devpt", "Customer Service - Supervisor / Officer", "Insurance", "Others", "Medical Services", "Others"], "post_time": "2022-01-17T09:43:01Z", "salary": {"currency": null, "max": null, "min": null, "period": "monthly", "term": null}, "salary_visible": false, "title_keywords": ["customer service officer"], "responsibilities": ["brokerage", "business opportunities", "good relationship", "maintain", "banking", "insurance"], "requirements": {"degrees": [], "majors": [], "languages": [], "language_level": [], "hard_skills": ["plus", "sales support"], "soft_skills": ["ideal"], "languages_combined": []}, "experience_required": {"duration": ["at least 4 years"], "field": ["retail banking", "insurance", "relevant experience"]}}, {"job_id": "100003009054328", "location_code": "hk", "company": "Moses Wills Limited", "job_title": "Underwriter", "description": "Handle policy administration for new, renewal cases such as arrange renewal proposal, data entry on member movement, issue billing and policy/ endorsements for group life and group medical insurance\nPerform routine administrative duties and provide operational support to corporate clients.\nAssist in handling customer service enquiries and perform data entry and document preparation to meet customers' expectation.\nPrepare the Management and Financial reports\nHandle project as assigned by Assistant Manager/Manager\nProvide sales support to distribution channels and quality inquiry to internal departments\nEnsure quality work output and accuracy\n\nJob Requirement\n\nUniversity degree of any discipline\nAt least 2 year's customer service or administrative experience, preferably in service industry or sizeable organization.\nExcellent communication and interpersonal skills\nGood customer service skills\nAttend to details with good organizing skills\nGood PC skills including Word and Excel\nGood command of both spoken and written English and Chinese", "employment_types": ["Full Time", "Permanent"], "selling_points": ["Immediate available is highly preferred", "13 months\u2019 Salary", "Underwriting (General Insurance)"], "locations": ["Admiralty"], "categories": ["Banking / Finance", "Others", "Insurance", "Underwriter", "Others"], "post_time": "2022-01-17T09:10:40Z", "salary": {"currency": null, "max": null, "min": null, "period": "monthly", "term": null}, "salary_visible": false, "title_keywords": [], "responsibilities": ["management", "operational support", "financial reports", "data entry", "quality", "communication", "customer service", "administrative duties", "insurance", "administration"], "requirements": {"degrees": ["university degree"], "majors": [], "languages": ["english", "chinese"], "language_level": ["good command"], "hard_skills": ["excel", "pc skills", "sales support", "word"], "soft_skills": ["customer service skills", "customer service", "communication and interpersonal skills"], "languages_combined": [{"language": "english", "language_level": ["good command"]}, {"language": "chinese", "language_level": ["good command"]}]}, "experience_required": {"duration": ["at least 2 year"], "field": ["customer service", "service industry", "administrative"]}}, {"job_id": "100003009054133", "location_code": "hk", "company": "China Life Insurance (Overseas) Company Limited", "job_title": "Senior Human Resources Manager /Human Resources Manager", "description": "Job Description\n\n\nAchieve his or her own sales target by developing renewal and new business\n\nAssist the team to achieve the whole sales team's targets.\n\nResponsible for business development of medical insurance through different distribution channels to achieve the business targets.\n\nCoordinate product launch related marketing activities\n\nProvide services to customers and intermediaries\n\nMaintain close relationship with key business contact\n\nDevelop new business sources\n\nSupport team head on develop and perform strategic plan\n\nRequirement\n\n\nDegree or above with insurance\nAt least 4 years experience in Medical underwriting and business development\nWith strong leadership, can deliver results under pressure\nGood command of spoken and written English and Cantonese", "employment_types": ["Full Time", "Permanent"], "selling_points": ["Business Partner role", "Talent Management", "Manpower planning"], "locations": ["Hung Hom"], "categories": ["Admin & HR", "HR Director / Manager", "Recruitment / Executive Search", "Insurance", "Others"], "post_time": "2022-01-17T08:30:57Z", "salary": {"currency": null, "max": null, "min": null, "period": "monthly", "term": null}, "salary_visible": false, "title_keywords": ["manager", "human resources"], "responsibilities": ["develop new business", "sales target", "developing", "develop", "coordinate", "maintain", "sales team", "contact", "plan", "insurance"], "requirements": {"degrees": ["degree or above"], "majors": ["insurance"], "languages": ["cantonese", "english"], "language_level": ["good command"], "hard_skills": [], "soft_skills": ["leadership", "under pressure"], "languages_combined": [{"language": "cantonese", "language_level": ["good command"]}, {"language": "english", "language_level": ["good command"]}]}, "experience_required": {"duration": ["at least 4 years"], "field": ["underwriting", "business development", "medical"]}}, {"job_id": "100003009053823", "location_code": "hk", "company": "Cornerstone Global Partners", "job_title": "Insurance Business Development Sr Manager / Manager (Agency / Brokerage Channel, up to 70k)", "description": "We\u2019re hiring!\n\nAon is currently recruiting an Assistant Account Executive - General Insurance\u00a0to join our team in Hong Kong.\n\nAbout Aon\n\nHeadquartered in London, Aon Plc is a leading global professional services firm providing a broad range of risk, retirement and health solutions. Our 50,000 colleagues in 120 countries empower results for clients by using proprietary data and analytics to deliver insights that reduce volatility and improve performance.\n\nAt Aon, you\u2019ll be part of a team which will support and inspire you and provide the opportunities and resources to develop your skills. It\u2019s an environment which encourages you to achieve your best - together we\u2019ll empower results.\u00a0\n\nResponsibilities:\n\nPrepare policy endorsements and debit notes\nProcess policy renewals and claims\nCarry out general clerical admin. work and file storage housekeeping\nAssist in any other ad-hoc tasks as assigned by Supervisors\n\nRequirements:\n\nAt least 1 year of clerical working experience; knowledge in Insurance preferred\nPassed in IIQE papers is an advantage\nWell-organized with good administration skills\nGood command of spoken and written English and Chinese\nGood command of computer skills including Microsoft Word, Excel and Chinese Typing\n\nHow to Apply\n\nYour opportunity to empower results could start right here. Make your mark and apply online today with a brief covering letter and your resume, sharing relevant achievements for this position.\n\nWe Offer You\n\nA competitive total rewards package, continuing education & training, and tremendous potential with a growing worldwide organization.\n\nOur Colleague Experience\n\nEvery day, our colleagues make a difference, work with the best, own their potential, and value one another. Together, we share this one purpose: to empower economic and human possibility around the world. This unifying goal is at the heart of our identity, and it lives in everything we do. To learn more about our colleague experience, visit Aon Colleague Experience.\n\nAon is an equal opportunities employer. We are committed to creating a winning and inclusive culture where everyone feels valued and has opportunities for growth and development.", "employment_types": ["Full Time", "Permanent"], "selling_points": ["Life Brokerage / Agency channel exposure", "B2B Channel Development (Growth Channel Business)", "Provide Marketing / Training support to channel"], "locations": ["Not Specified"], "categories": ["Banking / Finance", "Retail Banking", "Insurance", "Others", "Wealth Management"], "post_time": "2022-01-17T07:34:58Z", "salary": {"currency": "HKD", "max": 69999, "min": 35000, "period": "monthly", "term": null}, "salary_visible": true, "title_keywords": ["manager"], "responsibilities": ["housekeeping", "ad-hoc tasks", "file storage"], "requirements": {"degrees": [], "majors": [], "languages": ["english", "chinese"], "language_level": ["good command"], "hard_skills": ["excel", "iiqe", "microsoft word", "typing", "make", "computer skills"], "soft_skills": ["administration skills", "well-organized"], "languages_combined": [{"language": "english", "language_level": ["good command"]}, {"language": "chinese", "language_level": ["good command", "good command"]}]}, "experience_required": {"duration": ["at least 1 year"], "field": ["clerical"]}}, {"job_id": "100003009053081", "location_code": "hk", "company": "GF Holdings (Hong Kong) Corporation Ltd", "job_title": "Associate/VP, Relationship Management (Insurance Brokerage Business)", "description": "Principal Hong Kong is one of the major service providers of total retirement solutions in Hong Kong.\u00a0We are one of the winners received \"The 2021 MPF Award\" by MPF Ratings. Pension Operations plays a critical role to contribute the success of our business, join us if you are striving in an exciting operational environment or want to be a pension operation expert!\n\n\nThe Officer will participate in end-to-end pension operations process. You will handle daily administration of retirement schemes including but not limited to member enrollments, contributions, terminations, and group changes, in accordance with internal approved procedures, policies and local ordinance and regulations.\u00a0\n\nOther responsibilities include:\n\nProcess data and perform quality checking\nProvide customer service to clients and/or respond clients' verbal and written enquiries\nMaintain accurate records and thorough documentation\nAssist in any ad-hoc assignments or special projects\n\nEssential Skills, Experience and Competencies\n\nWe are looking for detail-minded candidates with strong time management skill. Competent in communicating across a wide variety of clients and deliver excellent customer service skills. Passionate about operational process with continuous improvement mindset will be a key to success.\n\nOther key skills required for the role:\n\nGraduates in business, finance or other related disciplines\n1 year of experience in Operations role\nExperience or sound knowledgeable in MPF and/or ORSO schemes administration is highly preferred\nA self-starter and good team player\nAble to meet tight timeline\nStrong PC applications especially Microsoft Excel and Word\nGood command of spoken and written English and Chinese\nFresh graduates who want to develop your career in Pension industry are welcome to apply/ candidate with less experience will be considered as Assistant Officer\n\nWhat We Offer\n\nPrincipal offers employees a competitive package and a comprehensive range of benefits to help meeting your needs now and in the future, including:\n\n5-Day Work Week\nYear-end Payment\nDiscretionary Bonus\nBirthday Leave\nMedical Plan\nLife Insurance\nPension Scheme\nEmployee Stock Purchase Plan\nAnd Growth Opportunities!", "employment_types": ["Full Time"], "selling_points": ["2-3 years\u2019 experience in insurance or WM", "Insurance license holder", "Attractive remuneration package and fringe benefit"], "locations": ["Sheung Wan"], "categories": ["Sales, CS & Business Devpt", "Business Development", "Insurance", "Others", "Banking / Finance", "Wealth Management"], "post_time": "2022-01-17T05:41:10Z", "salary": {"currency": null, "max": null, "min": null, "period": "monthly", "term": null}, "salary_visible": false, "title_keywords": ["associate"], "responsibilities": ["provide customer service", "quality checking", "management", "data", "ad-hoc assignments", "maintain", "customer service", "documentation"], "requirements": {"degrees": [], "majors": [], "languages": ["english", "chinese"], "language_level": ["good command"], "hard_skills": ["microsoft excel", "word", "pc applications"], "soft_skills": ["good team player"], "languages_combined": [{"language": "english", "language_level": ["good command"]}, {"language": "chinese", "language_level": ["good command"]}]}, "experience_required": {"duration": ["1 year"], "field": ["mpf", "administration"]}}, {"job_id": "100003009054718", "location_code": "hk", "company": "MSIG Insurance (Hong Kong) Limited", "job_title": "Customer Service Representative, Customer Centre", "description": "We\u2019re hiring!\n\nAon is currently recruiting a Senior Executive / Executive, Enrolment - Health Solutions to join our team in Hong Kong.\n\nAbout Aon\n\nHeadquartered in London, Aon Plc is a leading global professional services firm providing a broad range of risk, retirement and health solutions. Our 50,000 colleagues in 120 countries empower results for clients by using proprietary data and analytics to deliver insights that reduce volatility and improve performance.\n\u00a0\n\nAt Aon, you\u2019ll be part of a team which will support and inspire you and provide the opportunities and resources to develop your skills. It\u2019s an environment which encourages you to achieve your best - together we\u2019ll empower results.\u00a0\n\nResponsibilities:\n\nThe job incumbent will be responsible to assist the business line department in providing administrative support in relation to the employee benefits schemes of our clients. Duties include:\n\nReporting member changes of client\u2019s employee benefits schemes to the underwriters including but not limited to Group Medical, Group Life and Retirement Schemes\nHandling clients enquiries on member\u2019s record\nProviding professional customer service & relationship building\nMentoring the enrolment team member's day to day delivery of client services, ensuring quality of services meet client agreed SLAs\nMonitoring the administrative process to ensure the accuracy and efficiency\u00a0\n\n\nRequirements:\n\nForm 7 / DSE or above with minimum 3 years working experience in Employee Benefits in broker firm or insurance company(ies)\nHolder of FLMI or LOMA preferred or passed in IIQE Papers\nCustomer oriented\nWell-organized and detail-minded\nGood organization skills and effective interpersonal skills\nGood command of written and spoken English and Chinese\nGood command of computer skills including MS Office (Word, Excel)\nCandidate will less experience can be considered as Executive position.\u00a0\n\n\nHow to Apply\nYour opportunity to empower results could start right here. Make your mark and apply online today with a brief covering letter and your resume, sharing relevant achievements for this position.\n\nWe Offer You\nA competitive total rewards package, continuing education & training, and tremendous potential with a growing worldwide organization.\n\nOur Colleague Experience\nEvery day, our colleagues make a difference, work with the best, own their potential, and value one another. Together, we share this one purpose: to empower economic and human possibility around the world. This unifying goal is at the heart of our identity, and it lives in everything we do. To learn more about our colleague experience, visit Aon Colleague Experience.\u00a0\n\nAon is an equal opportunities employer. We are committed to creating a winning and inclusive culture where everyone feels valued and has opportunities for growth and development.", "employment_types": ["Full Time", "Permanent"], "selling_points": ["Manage customer enquiries and complaints", "Maintain good customer relationship", "Double pay, 5-days work, medical, training subsidy"], "locations": ["Tai Koo"], "categories": ["Sales, CS & Business Devpt", "Call Centre", "Insurance", "Others"], "post_time": "2022-01-17T10:42:28Z", "salary": {"currency": null, "max": null, "min": null, "period": "monthly", "term": null}, "salary_visible": false, "title_keywords": ["customer service representative"], "responsibilities": ["reporting", "administrative support", "monitoring", "quality", "customer service"], "requirements": {"degrees": [], "majors": [], "languages": [], "language_level": [], "hard_skills": [], "soft_skills": [], "languages_combined": []}, "experience_required": {"duration": [], "field": []}}, {"job_id": "100003009045933", "location_code": "hk", "company": "AXA Hong Kong", "job_title": "Policy Servicing Officer (Health and Medical)", "description": "Responsibilities :\nDrive service excellent to the team & facilitate the achievement of business objectives;\nProcess quotations and comparisons as required.\nCoordinate with both internally and externally parties.\nSales Administration, including applications & documents handling, client file maintenance, filing etc\nAssist Department Head / colleagues with ad-hoc tasks as assigned\nRequirements :\n\nMinimum 1 years of solid Sales Support experience within the general insurance industry\nEnergetic, outgoing & confident with a strong attention to detail\nGood numeric skills and capable of multi-tasking\nProficient in PC skills, including Microsoft Word, Excel and PowerPoint\nHolding valid IIQE papers 1,2\n\n\n\nWe offer competitive remuneration package. Interested parties, please send your resume with CURRENT & EXPECTED salary and DATE AVAILABLE by clicking 'Apply Now'\n\n(Data collected would be used for recruitment purpose only)", "employment_types": ["Full Time", "Permanent"], "selling_points": ["Corporate role in AXA", "Health and Employee Benefits Business", "Policy Administration"], "locations": ["Southern Area"], "categories": ["Admin & HR", "Clerical / Admin Staff", "Insurance", "Others"], "post_time": "2022-01-13T09:10:57Z", "salary": {"currency": "HKD", "max": 19999, "min": 17000, "period": "monthly", "term": null}, "salary_visible": true, "title_keywords": ["officer"], "responsibilities": ["sales administration", "client file maintenance", "ad-hoc tasks", "internally and externally parties", "documents handling", "coordinate with", "process quotations"], "requirements": {"degrees": [], "majors": [], "languages": [], "language_level": [], "hard_skills": ["excel", "iiqe", "microsoft word", "sales support", "powerpoint", "pc skills"], "soft_skills": ["outgoing", "confident", "capable", "multi-tasking", "attention to detail", "energetic"], "languages_combined": []}, "experience_required": {"duration": ["minimum 1 years"], "field": ["general insurance", "sales support"]}}, {"job_id": "100003009049652", "location_code": "hk", "company": "Hang Seng Bank Ltd", "job_title": "Assistant Case Manager", "description": "In the heart of the role:\n\n\n\nHandle feedbacks, complaints and compliments including investigations and liaise with team leaders, supervisors, third parties, to collect information and resolving issues\nResponsible to reply to customer by phone/ in writing\nEscalate case to Legal / Medical Director for advice when necessary\nPrepare meeting agenda and meeting notes\nPrepare report for periodically review by relevant parties, including basic data management and analysis\nMake recommendations based on the feedback themes and trends to improve customer experience, ensuring the improvement actions are tracked through to completion\nOther duties as required by line manager\n\nDesired Qualification & Experience:\n\n\n\nBachelor\u2019s Degree, with relevant customer service experience preferred\nA minimum of 5 years of customer service/ customer experience/complaint handling related experience\nExperience in medical/insurance industry and complaint handling is definitely advantage\nGood problem solving skill with customer centric mindset;\nDemonstrate ability to work independently\nExcellent written and verbal communications in English, Chinese and Mandarin\nProficient in Microsoft Office Suite - Word, Excel, PowerPoint\n\n(All applications will be treated in strict confidence and data collected will be used for recruitment purposes only)", "employment_types": ["Full Time", "Permanent"], "selling_points": [], "locations": ["Not Specified"], "categories": ["Banking / Finance", "Others", "Insurance", "Others"], "post_time": "2022-01-17T02:26:06Z", "salary": {"currency": null, "max": null, "min": null, "period": "monthly", "term": null}, "salary_visible": false, "title_keywords": ["assistant", "case manager"], "responsibilities": ["make recommendations", "prepare report", "management", "other duties", "data", "analysis", "review", "customer service experience", "customer service", "recruitment", "liaise with", "insurance"], "requirements": {"degrees": ["degree", "bachelor"], "majors": [], "languages": ["english", "chinese", "mandarin"], "language_level": ["excellent"], "hard_skills": ["excel", "basic", "data management", "analysis", "word", "powerpoint", "problem solving", "make", "microsoft office suite"], "soft_skills": ["make recommendations", "work independently", "confidence", "responsible", "customer service", "problem solving skill"], "languages_combined": [{"language": "english", "language_level": ["excellent"]}, {"language": "chinese", "language_level": ["excellent"]}, {"language": "mandarin", "language_level": ["excellent"]}]}, "experience_required": {"duration": ["minimum of 5 years"], "field": ["related", "customer service", "insurance industry", "medical"]}}, {"job_id": "100003009053591", "location_code": "hk", "company": "Principal Trust Company (Asia) Limited", "job_title": "Officer, Pension Operations", "description": "Responsibilities\n\nGenerate sales, meet sales targets and manage a portfolio of renewal and new business\nEngage end-to-end customer service including needs identification, solution recommendations, application fulfillment, and follows up\nProvide comprehensive service including professional advice for both enterprises and individual high-end clients\nEstablish stable partnership with key channels and explore new business opportunities\n\nEstablish effective working relationships with other teams in order to ensure a consistent approach and application of outstanding service standard\nPlan, organize and coordinate business development activities to achieve company target\nParticipate in any ad hoc projects\n\nRequirements\n\nUniversity graduate; holder of ANZIIF(Sr. Associate) qualifications or equivalent\nSolid track records in marketing and sales in insurance industry with at least 5 years\u2019 sales management experience\nExtensive product knowledge in general insurance, especially in group medical; strong ability to drive for business results\nProactive, good communication, interpersonal and presentation skills\nSelf-motivated with good business sense\nExcellent command of written and spoken English and Chinese\nWe offer 5-day week, competitive remuneration package, and good career prospects to the right candidate. Interested parties please send your resume with EXPECTED SALARY\u00a0by clicking \u201cAPPLY NOW\u201d. All personal data collected would be used for recruitment purpose only)", "employment_types": ["Full Time", "Permanent"], "selling_points": ["Participate in entire pension operations process", "Experience in MPF/ORSO is highly preferred", "Fresh graduates are welcome to apply"], "locations": ["Kwun Tong"], "categories": ["Banking / Finance", "Financial Services", "Insurance", "Others", "Order Processing & Operation / Settlement"], "post_time": "2022-01-17T07:12:35Z", "salary": {"currency": null, "max": null, "min": null, "period": "monthly", "term": null}, "salary_visible": false, "title_keywords": ["officer", "operations"], "responsibilities": ["service standard", "explore new business opportunities", "fulfillment", "teams", "coordinate", "customer service", "ad hoc projects", "plan", "working relationships"], "requirements": {"degrees": ["university graduate"], "majors": [], "languages": ["english", "chinese"], "language_level": ["excellent"], "hard_skills": [], "soft_skills": ["self-motivated", "business sense", "communication", "presentation skills", "proactive", "extensive", "interpersonal"], "languages_combined": [{"language": "english", "language_level": ["excellent"]}, {"language": "chinese", "language_level": ["excellent"]}]}, "experience_required": {"duration": ["at least 5 years"], "field": ["management", "marketing", "insurance industry"]}}, {"job_id": "100003009051829", "location_code": "hk", "company": "Chubb Life Insurance Company Ltd.", "job_title": "Senior Claims Executive - Life Insurance", "description": "Responsibilities and Requirements\uff1a\nUniversity degree or accredited insurance professional qualification;\nMainly responsible for policy administration and daily operation support;\n2 - 3 years of relevant work experience, applicant with property insurance experience will be advantage;\nProficient in Chinese and English spoken and written expressions;\nGood interpersonal and communication skills;\nSelf-motivated, independent, able to work under pressure.\n\nWe offer competitive remuneration package. Interested parties, please send your resume with CURRENT & EXPECTED salary and DATE AVAILABLE by clicking 'Apply Now'.\n\n(Data collected would be used for recruitment purpose only\uff09\u00a0", "employment_types": ["Full Time", "Permanent"], "selling_points": ["Life claims experience", "Degree holder in any disciplines", "Minimum 2 years solid experience"], "locations": ["Causeway Bay"], "categories": ["Insurance", "Claims Officer", "Underwriter", "Others"], "post_time": "2022-01-17T01:18:28Z", "salary": {"currency": null, "max": null, "min": null, "period": null, "term": null}, "salary_visible": false, "title_keywords": ["executive"], "responsibilities": [], "requirements": {"degrees": ["university degree"], "majors": ["insurance"], "languages": ["english", "chinese"], "language_level": ["proficient"], "hard_skills": ["operation support"], "soft_skills": ["communication skills", "self-motivated", "independent", "responsible", "interpersonal", "work under pressure"], "languages_combined": [{"language": "english", "language_level": ["proficient"]}, {"language": "chinese", "language_level": ["proficient"]}]}, "experience_required": {"duration": ["2 - 3 years"], "field": ["insurance"]}}, {"job_id": "100003009048297", "location_code": "hk", "company": "Bank of China Group Insurance Company Limited", "job_title": "Sales Support Officer (General Insurance)", "description": "Job Descriptions\n\nManage full spectrum of recruitment services, including but not limited to interviewing candidates, understanding their' needs, assessing and identifying the right candidates;\nTranslate business requirements into recruitment practices and deliver solutions aligned with business objectives;\nSource and evaluate the effectiveness of advertising and recruitment channel;\nResponsible for sales management of the team including hiring, training and performance evaluation.\n\n\u00a0Job Requirements\n\nBachelor\u2019s degree holder, with major in relevant sector preferable;\nPossess excellent presentation and influencing skills to advise candidate at all levels in a professional manner;\nExcellent command in English, Mandarin and Cantonese.\n\n\u00a0Benefits\n\nBasic salary up to 25,000 + competitive commission;\nComprehensive training programs;\nExcellent career path;\nRemuneration negotiable.\n\nCandidates without recruitment or sales experience but have the right motivation and attitude are welcomed. Training will be provided.", "employment_types": ["Full Time", "Permanent"], "selling_points": [], "locations": ["Kowloon Bay"], "categories": ["Insurance", "Insurance Agent / Broker", "Underwriter", "Others"], "post_time": "2022-01-14T06:09:59Z", "salary": {"currency": null, "max": null, "min": null, "period": null, "term": null}, "salary_visible": false, "title_keywords": ["sales support officer"], "responsibilities": ["advertising", "evaluate", "recruitment", "evaluation", "sales management"], "requirements": {"degrees": ["bachelor", "degree holder"], "majors": [], "languages": ["cantonese", "english", "mandarin"], "language_level": ["excellent"], "hard_skills": [], "soft_skills": ["presentation"], "languages_combined": [{"language": "cantonese", "language_level": ["excellent"]}, {"language": "english", "language_level": ["excellent"]}, {"language": "mandarin", "language_level": ["excellent"]}]}, "experience_required": {"duration": [], "field": []}}, {"job_id": "100003009053638", "location_code": "hk", "company": "Hang Seng Bank Ltd", "job_title": "Manager, General Insurance", "description": "Deliver first-class customer services and operational duties\n\nYour new company\nOur client is a multinational UK-based firm in the insurance industry, this fast-growing business has been one of the market-leaders in wealth and insurance-based wealth solutions. Due to their strong determination to expand, they are looking for a passionate candidate in the provision of excellent customer services and operational duties.\n\nYour new role\nAs one of the key members in the customer service team, you will be providing customer service support such as handling enquiries through telephone calls and emails. You will deliver quality service and ensure high quality service standard. For a smooth operation flow, you will also provide administration supports such as handling ad hoc projects and assignments in a timely manner.\n\nWhat you'll need to succeed\n\nAt least one year of customer services experience\nFresh graduate with good communication skills will also be considered\nHigh level of proficiency of English, Chinese and Putonghua\nOutgoing and great interpersonal skills\nPassionate in offer best-in-class customer services to customers\n\n\n\nWhat you'll get in return\n\nA rewarding career in a high-performing culture\nWork in a dynamic environment in a multinational setting\nExcellent career development prospects\nGreat opportunity to build insights in the industry\n\n\n\nWhat you need to do now\nIf you fulfil all the qualifications mentioned above and have the drive to succeed or are interested in similar roles within insurance, please contact me with an attached CV at yumi.yung@hays.com.hk or please call +852-2230-7933.", "employment_types": ["Full Time", "Permanent"], "selling_points": [], "locations": ["Not Specified"], "categories": ["Banking / Finance", "Others", "Insurance", "Others"], "post_time": "2022-01-17T09:23:16Z", "salary": {"currency": null, "max": null, "min": null, "period": "monthly", "term": null}, "salary_visible": false, "title_keywords": ["manager"], "responsibilities": ["service standard", "customer service support", "quality", "a timely manner", "customer services", "communication", "customer service", "ad hoc projects", "contact", "career development", "insurance", "operational duties", "administration"], "requirements": {"degrees": ["fresh graduate"], "majors": [], "languages": ["putonghua", "english", "chinese"], "language_level": ["proficiency"], "hard_skills": ["dynamic"], "soft_skills": ["passionate", "communication skills", "outgoing", "first-class", "dynamic environment", "timely", "interested in", "customer service", "interpersonal skills", "smooth"], "languages_combined": [{"language": "putonghua", "language_level": ["proficiency"]}, {"language": "english", "language_level": ["proficiency"]}, {"language": "chinese", "language_level": ["proficiency"]}]}, "experience_required": {"duration": ["at least one year"], "field": ["customer services"]}}, {"job_id": "100003009053345", "location_code": "hk", "company": "Cornerstone Global Partners", "job_title": "Insurance Business Development Director (Major Consultancy, Life Actuarial, 1.5m-2m p.a + Bonus)", "description": "Responsibilities:\n\nManage a team of employee ensring MPF operation team provides accrate and timely servcie aliging with business and regulatory requirements.\nManage and drive team productivity to achieve/exceed the respective service level agreement.\u00a0\nStreamline the workflow so as to improve efficiency and effectiveness, improving client service and compile with statutory requirement.\nDevelop, coach and provide development opportunities for team members.\nParticipate in any ad-hoc projects as assigned.\n\nRequirements:\n\nA recognized Bachelor Degree holder or equivalent.\nAt least 10 years\u2019 experience in pension industry.\nA deep and thorough understanding about the MPF business and operation, as well as the prevailing regulations that could have an impact to the operation.\nStrong in analytical, problem solving and communication skills.\nA good interpretation of the organization dynamics and be able to translate them into management policies, procedures and actions to meet the requirements\nAmiable personality and ability to communicate the direction effectively to peers and stakeholders\nStrong problem solving skills with client-centric mindset.\nSolid team management skills.\nProficiency in spoken and written English and Chinese.\nGood PC skills in MS Word & Excel. Candidate with skill in Access is preferable\n\nWe offer 5-day work, attractive salary, MPF, group life and group medical insurance and excellent career development opportunities to the right candidate.\n\nWe are an equal opportunity employer and welcome applications from all qualified candidates. Application forms and resume will be kept for a period of 24 months after completion of the recruitment process. (All information will be held in strict confidence and only used for recruitment purpose.)\u00a0", "employment_types": ["Full Time"], "selling_points": ["Business Development Director", "Actuarial/Technology Driven", "High Basic Salary"], "locations": ["Not Specified"], "categories": ["Sales, CS & Business Devpt", "Business Development", "Insurance", "Actuarial", "Others"], "post_time": "2022-01-17T06:48:52Z", "salary": {"currency": "HKD", "max": null, "min": 120000, "period": "monthly", "term": null}, "salary_visible": true, "title_keywords": ["business development director"], "responsibilities": ["regulatory requirements", "ad-hoc projects", "mpf", "develop"], "requirements": {"degrees": ["bachelor degree holder"], "majors": [], "languages": ["english", "chinese"], "language_level": ["proficiency"], "hard_skills": ["excel", "problem solving", "problem solving skills", "pc skills", "ms word"], "soft_skills": ["communication skills", "amiable", "confidence", "deep", "problem solving", "thorough", "problem solving skills"], "languages_combined": [{"language": "english", "language_level": ["proficiency"]}, {"language": "chinese", "language_level": ["proficiency"]}]}, "experience_required": {"duration": ["at least 10 years"], "field": []}}, {"job_id": "100003009048344", "location_code": "hk", "company": "Bank of China Group Insurance Company Limited", "job_title": "Senior Clerk/Deputy Officer - Policy Administration (General Insurance)", "description": "We are now seeking for Clerk in handle policy administration in general insurance. Candidates meeting the following requirement are encouraged to apply for this position.\n\nJobs Description: \u00a0\n\nProvide general clerical and office administration work.\nHandle telephone calls\u00a0\nPolicy Documents checking, posting, filing\nOther ad hoc assignments.\n\nRequirements:\n\nHKCEE / HKDSEE or above\n1 - 2 years of Clerical experience\u00a0 \u00a0\u00a0\nGood PC skills in Microsoft Word & Excel\nGood command of spoken and written English and Chinese\nGood interpersonal skill and client focus\nPositive attitude and self-motivated\nHave passion in development insurance as long term career\n\nWe offer 5-Day work, medical insurance, double pay and competitive remuneration package. \u00a0\n\nInterested candidates please send full resume with expected salary & available date by clicking \"Apply Now\" or fax\u00a02575 8398\n\u00a0\nAll personal data will be used for recruitment purposes.", "employment_types": ["Full Time", "Permanent"], "selling_points": [], "locations": ["Central"], "categories": ["Insurance", "Insurance Agent / Broker", "Underwriter", "Others"], "post_time": "2022-01-14T06:23:07Z", "salary": {"currency": "HKD", "max": 24999, "min": 14000, "period": "monthly", "term": null}, "salary_visible": true, "title_keywords": ["officer", "senior clerk"], "responsibilities": ["checking", "ad hoc assignments", "policy documents", "office administration work"], "requirements": {"degrees": [], "majors": [], "languages": ["english", "chinese"], "language_level": ["good command"], "hard_skills": ["excel", "focus", "pc skills", "microsoft word"], "soft_skills": ["self-motivated", "passion in", "interpersonal skill", "positive attitude", "focus"], "languages_combined": [{"language": "english", "language_level": ["good command"]}, {"language": "chinese", "language_level": ["good command"]}]}, "experience_required": {"duration": ["1 - 2 years"], "field": ["clerical"]}}, {"job_id": "100003009051602", "location_code": "hk", "company": "Success Meteor", "job_title": "Recruitment Manager", "description": "Roles & Responsibilities:\n\nHandle the full cycle of policy administration for new businesses, renewal policies including but not limited to policy issuance, endorsements, commission, after-sales services with high service standard & within assigned authority\nLiaison with both internal and external partners (e.g. product providers, business partners, sales channels) within turnaround time to ensure the smoothness of daily operations\nPrepare regular internal reporting to ensure visibility of department performance, service issues and action plans\nPrepare Product comparison table\nLicensed TR is highly preferred\nUpdate and maintain accuracy in internal system\nHandle Life/GI/MPF business\nAccept any additional responsibilities or activities relevant to the department as assigned by the superiors\nSkills and Experience :\u00a0\n\nDiploma or above with professional insurance qualifications is advantageous\nMin. 2 years relevant working experience, solid knowledge in policy administration in insurance industry\nBe proactive, result oriented with strong sense of responsibility and problem-solving skill\nIndependent, well organized, attentive to details with ability to multi-tasks\nGood interpersonal skill and be part of a team environment\nGood time management skills and ability to work under pressure\nGood command of written and spoken English and Chinese\nProficient in MS Office & Chinese Word Processing\nCandidates with less experience will be considered as Assistant.\n\n\nAll information collected for recruitment purpose only.\n\nInterested parties please send full resume with available date, current & expected salary to Human Resources Department by \"Apply Now\"\n\nAll information provided by applicants will be treated in strictly confidential and used only for recruitment purposes. Applicants may be considered for other suitable positions by our Company not more than three months, after which their personal data will be destroyed.", "employment_types": ["Full Time"], "selling_points": ["Excellent working environment", "Competitive basic salary and commission structure", "Candidates with relevant experience are preferable"], "locations": ["Tsim Sha Tsui"], "categories": ["Management", "General Management", "Admin & HR", "HR Director / Manager", "Insurance", "Others"], "post_time": "2022-01-16T13:59:47Z", "salary": {"currency": "HKD", "max": 54999, "min": 25000, "period": "monthly", "term": null}, "salary_visible": true, "title_keywords": ["manager"], "responsibilities": ["reporting", "management", "service standard", "mpf", "work under pressure", "policies", "maintain accuracy", "daily operations", "recruitment", "plans", "insurance", "administration"], "requirements": {"degrees": ["diploma or above"], "majors": ["insurance"], "languages": ["english", "chinese"], "language_level": ["good command", "proficient"], "hard_skills": ["problem-solving", "chinese word processing", "ms office"], "soft_skills": ["independent", "attentive to details", "sense of responsibility", "multi-tasks", "time management skills", "problem-solving", "well organized", "interpersonal skill", "result oriented", "proactive", "work under pressure"], "languages_combined": [{"language": "english", "language_level": ["good command"]}, {"language": "chinese", "language_level": ["good command", "proficient"]}]}, "experience_required": {"duration": ["2 years"], "field": ["insurance industry", "relevant working experience", "policy administration"]}}, {"job_id": "100003009051301", "location_code": "hk", "company": "GRS Insurance Consultants Limited", "job_title": "Clerk", "description": "Responsibilities:\u00a0\n\n\nPerform daily logistic, circulation and replenishment support for document and other office consumable.\nProvide support on the facilities repair and maintenance, room setting and relocation work.\nProvide support on organizing staff event/activities and sourcing office supplies/ad hoc items.\nProvide administrative support to the Administration Team and other department unit.\nHandle and maintain records and files, prepare reports, documents and presentations.\nLiaise and communicate with internal and external parties on daily operation issue.\nHandle enquiries and provide reception/counter service if needed.\nPerform ad hoc tasks assigned by supervisor.\n\nRequirements:\n\n\nDiploma or above in Administrative or Facilities Management or related discipline is preferred.\u00a0\nAt least 2 years working experience in large Corporation/MNC.\nStrong sense of responsibility, well organized, meticulous & self-motivated.\nGood command of written and spoken Cantonese and Chinese.\nComputer literate in MS Office including Chinese word processing is advantage\nImmediate available is preferable\n\n\u00a0We offer competitive remuneration including career prospects to the right candidate. Interested parties please send detailed resume with availability, current and expected salaries to\u00a0Human Resources Department, Convoy Global Holdings Limited, Trust Tower, 68 Johnston Road, Wan Chai, Hong Kong\u00a0or by clicking the\u00a0Apply Now\u00a0button and upload your CV and cover letter.\n\n(All applications will be treated in strict confidence and used for recruitment purpose within Convoy Global Holdings Limited only. All applicants are kept on file 6 months from the date of the application.)\n", "employment_types": ["Full Time", "Permanent"], "selling_points": [], "locations": ["North Point"], "categories": ["Insurance", "Others"], "post_time": "2022-01-15T07:46:21Z", "salary": {"currency": null, "max": null, "min": null, "period": "monthly", "term": null}, "salary_visible": false, "title_keywords": ["clerk"], "responsibilities": ["liaise", "communicate with", "provide support", "ad hoc", "prepare reports", "maintenance", "office supplies", "internal and external parties", "daily operation", "replenishment", "presentations", "ad hoc tasks", "handle enquiries", "repair", "maintain", "provide administrative support", "administration"], "requirements": {"degrees": ["diploma or above"], "majors": [], "languages": ["cantonese", "chinese"], "language_level": ["advantage", "good command"], "hard_skills": ["facilities management", "chinese word processing", "ms office"], "soft_skills": ["meticulous", "self-motivated", "well organized", "sense of responsibility"], "languages_combined": [{"language": "cantonese", "language_level": ["good command"]}, {"language": "chinese", "language_level": ["advantage", "good command"]}]}, "experience_required": {"duration": ["at least 2 years"], "field": []}}, {"job_id": "100003009048583", "location_code": "hk", "company": "ZUU Digital Financial Services Limited", "job_title": "Assistant Officer, Policy Administration & Operations", "description": "Job Responsibilities:\n\nProvide technical support to senior on treaty renewal and system updates\nEnsure the protection of existing business and alignment of company standard by conducting a smooth renewal of treaty reinsurance programs\nPrepare reinsurance treaty renewal data, slip wording review, terms comparing, and placement process support\nProvide assistance in updating catastrophe data , risk profiles, major loss status summary and other underwriting information package, etc. for treaty renewal\nPrepare\u00a0accurate statistical reports/data for management\u2019s review on treaty results within a time frame\nProvide accurate fire accumulation calculation to underwriters and ensure no overexposure risk/location for new, renewal and endorsement cases in the fire accumulation register.\nAssist in preparing the regular reinsurance treaty related bordereaux and ensure all reinsurance transactions report in systems are correct within a set time frame\nAssist in handling enquiries raised by parties\nSupport the manager to create underwriting plans and manage risk exposures through limits and reinsurances\nHandle any ad-hoc work as assigned\n\n\u00a0Job Requirements:\n\nDegree holder\nProfessional Insurance qualification such as ANZIIF/CII qualification\n5 years\u2019 or above experience in underwriting and reinsurance preferred;\nProficient in MS Word, Excel and PowerPoint\nGood command in English, Cantonese and Mandarin.\n\nThe company provides competitive salary package. Interested parties may submit update CV with current and expected salary, or contact Ms Lee at +852 3952 0594 for confidential discussion.", "employment_types": ["Full Time", "Permanent"], "selling_points": ["Perform daily policy administration on full cycle", "Perform quality control", "Stable company with continuous business expansion"], "locations": ["Causeway Bay"], "categories": ["Insurance", "Insurance Agent / Broker", "Others"], "post_time": "2022-01-14T06:50:48Z", "salary": {"currency": null, "max": null, "min": null, "period": "monthly", "term": null}, "salary_visible": false, "title_keywords": ["assistant officer", "operations"], "responsibilities": ["ad-hoc", "management", "data", "technical support", "system updates", "review", "systems", "transactions", "reports", "plans", "provide assistance", "report"], "requirements": {"degrees": ["degree holder"], "majors": [], "languages": ["cantonese", "english", "mandarin"], "language_level": ["good command"], "hard_skills": ["excel", "powerpoint", "ms word"], "soft_skills": [], "languages_combined": [{"language": "cantonese", "language_level": ["good command"]}, {"language": "english", "language_level": ["good command"]}, {"language": "mandarin", "language_level": ["good command"]}]}, "experience_required": {"duration": ["5 years"], "field": ["underwriting"]}}, {"job_id": "100003009054317", "location_code": "hk", "company": "China BOCOM Insurance Company Limited", "job_title": "Winter Intern", "description": "Responsibilities\n\nProvide value-added HR services and advisory support on manpower planning, recruitment and selection, talent management and staff relations\nMaintain the professional standard of recruitment services for both internal and external parties\nSupport end-to-end recruitment from sourcing, screening, interviewing to salary negotiation\nReview and streamline recruitment process and workflow to enhance productivity and efficiency\nPlan and coordinate campus recruitment events and activities, such as job fairs and recruitment talks\nDesign, implement and sustain talent management programs including career and leadership development, succession planning, performance management, and organization development plan\nUndertake HR projects and initiatives as required\n\nRequirement\n\nUniversity degree in HR Management, Business Administration or a related discipline\nMinimum of 8 years of relevant HR experience in sizeable company, preferably in Insurance industry\nStrong self-motivation and attention to details with high quality\nAbility to work under pressure with strong multi-tasking skills\nStrong communication, interpersonal and project management skills\nProficiency in both English and Chinese (Cantonese and Mandarin)", "employment_types": ["Full Time", "Temporary", "Contract", "Internship"], "selling_points": [], "locations": ["Central"], "categories": ["Insurance", "Others"], "post_time": "2022-01-17T09:08:03Z", "salary": {"currency": null, "max": null, "min": null, "period": "monthly", "term": null}, "salary_visible": false, "title_keywords": ["intern"], "responsibilities": ["management", "hr", "internal and external parties", "review", "plan and coordinate", "design", "maintain", "recruitment", "plan", "recruitment process", "planning"], "requirements": {"degrees": ["university degree"], "majors": ["business administration"], "languages": ["cantonese", "english", "chinese", "mandarin"], "language_level": ["proficiency"], "hard_skills": ["project management"], "soft_skills": ["project management skills", "communication", "self-motivation", "attention to details", "multi-tasking skills", "interpersonal", "work under pressure"], "languages_combined": [{"language": "cantonese", "language_level": []}, {"language": "english", "language_level": ["proficiency"]}, {"language": "chinese", "language_level": ["proficiency"]}, {"language": "mandarin", "language_level": []}]}, "experience_required": {"duration": ["minimum of 8 years"], "field": ["hr", "insurance industry"]}}, {"job_id": "100003009056090", "location_code": "hk", "company": "Asia Insurance Co Ltd", "job_title": "Underwriting Assistant (Job Ref: AI/UWA/JD)", "description": "Job Description\n\nThe incumbent will\u00a0 handle\u00a0 all\u00a0 the\u00a0 operations in Underwriting\u00a0 team;\u00a0 and assist Supervisor /\u00a0Manager in all aspects relating to Underwriting and Policy Administration.\n\n\nQualification Requirements\n\nForm 7 or above, with pass in English, Mathematics and Chinese\n3 - 5 years relevant experience\nGood interpersonal and communication skills\nExcellent spoken and written skills in English and Chinese\nHands-on PC skills in MS Word and MS Excel\nOrganized, responsible and careful\nImmediate available is preferred\nCandidates with less experience will be considered as Clerk\n\n\nOther Job Openings\n\nPlease visit \u201cCareer Opportunities\u201d in our website http://www.asiainsurance.hk\n\nAt Asia\u00a0 Insurance\u00a0 Co.,\u00a0 Ltd.,\u00a0 we\u00a0 are\u00a0 committed\u00a0 to\u00a0 offer\u00a0 good\u00a0 career\u00a0 prospects, 5\u00a0 days\u00a0 week, 16 days\u00a0 Annual\u00a0 Leave, Birthday Leave, competitive remuneration and benefits package. \u00a0\n\nInterested parties may apply with full resume including present & expected salary, contact phone number, job reference code above and send it to Human\u00a0 Resources\u00a0 Department,\u00a0 Asia\u00a0 Insurance\u00a0 Co.,\u00a0 Ltd., 8/F\u00a0 118 Connaught\u00a0 Road\u00a0 West, Sheung Wan, Hong Kong or click \"Apply Now\" to submit your application. Applicants who are not contacted within one month may consider their applications unsuccessful.\n\nAll information provided by applicants\u00a0 will be used in the strictest confidential in accordance\u00a0 with the employer's personal data policy, and\u00a0 will\u00a0 be\u00a0 handled\u00a0 by\u00a0 authorized\u00a0 personnel\u00a0 for\u00a0 recruitment-related\u00a0 purposes\u00a0 only.\u00a0 Applicants\u00a0 may\u00a0 be\u00a0 considered\u00a0 for\u00a0 other\u00a0 suitable positions within the Company and our subsidiary or associate companies over a four-month period, after which their personal data will be destroyed.", "employment_types": ["Full Time", "Permanent"], "selling_points": [], "locations": ["Sai Ying Pun"], "categories": ["Admin & HR", "Clerical / Admin Staff", "Insurance", "Underwriter", "Others"], "post_time": "2022-01-18T03:16:31Z", "salary": {"currency": null, "max": null, "min": null, "period": "monthly", "term": null}, "salary_visible": false, "title_keywords": ["assistant"], "responsibilities": ["operations", "administration"], "requirements": {"degrees": [], "majors": [], "languages": ["english", "chinese"], "language_level": ["excellent"], "hard_skills": ["ms excel", "pc skills", "ms word"], "soft_skills": ["organized", "communication skills", "careful", "responsible", "committed", "hands-on", "interpersonal"], "languages_combined": [{"language": "english", "language_level": ["excellent"]}, {"language": "chinese", "language_level": ["excellent"]}]}, "experience_required": {"duration": ["3 - 5 years"], "field": ["relevant experience"]}}, {"job_id": "100003009056014", "location_code": "hk", "company": "AXA Hong Kong", "job_title": "Assistant Officer, Policy Administration (1-year contract)", "description": "Responsibilities:\n\nAssist in preparing policy endorsements, contract provisions and confirmation letter for policy changes\n\nAssist in document sorting and filling, quality checking, policy binding, arrange files for settling bill payment\n\nMeet service turnaround time to achieve target includes productivity, error rate, complaint rate and customer satisfaction rate\n\nMaintain a good control on output logistic\n\nPerform other related duties and ad hoc task to support the operation of the department\n\n\nRequirements:\n\nForm 6 or above\n\nAt least 1 year relevant working experience\n\nGood interpersonal and communication skills\n\nSelf-motivated, detail-oriented and positive mind set\n\nGood command of both written and spoken in English & Chinese\n\nGood PC skills including Chinese Typing\n\nKnowledge in AS400 is preferable\n\nFresh Graduate will also be considered\n", "employment_types": ["Full Time", "Temporary"], "selling_points": ["Handle daily policy admin functions in P&C team", "Data entry, Documents sorting & filing", "Fresh Grads welcome"], "locations": ["Not Specified"], "categories": ["Insurance", "Others", "Others", "Student / Fresh Graduate / No Experience"], "post_time": "2022-01-18T03:11:28Z", "salary": {"currency": null, "max": null, "min": null, "period": "monthly", "term": null}, "salary_visible": false, "title_keywords": ["assistant officer"], "responsibilities": ["quality checking", "control", "ad hoc", "payment", "maintain"], "requirements": {"degrees": ["fresh graduate"], "majors": [], "languages": ["english", "chinese"], "language_level": ["good command", "good"], "hard_skills": ["pc skills", "typing"], "soft_skills": ["communication skills", "self-motivated", "detail-oriented", "interpersonal", "positive"], "languages_combined": [{"language": "english", "language_level": ["good command", "good"]}, {"language": "chinese", "language_level": ["good command", "good", "good"]}]}, "experience_required": {"duration": ["at least 1 year"], "field": ["relevant working experience"]}}, {"job_id": "100003009053201", "location_code": "hk", "company": "Sun Life Hong Kong Ltd", "job_title": "Senior Client Service Representative (Call Centre - Life & Health)", "description": "Job Responsibilities\nConduct the pre/post sales call by face-to-face or phone with stipulate the tailor-made script to MCV with frequent Mandarin speaking.\nHandle customer enquiries via hotline and walk-in services\nMeet service standard and KPIs according to internal guidelines and rules\nConduct various outbound calls with documented protocols\nLiaise with internal departments, channels and customers on replies to enquiries and required documents\nMaintain and improves quality results by adhering to standards and guidelines; recommending improved procedures.\nProvide customers with product and service information\nIdentify and escalate priority issues\nDocument all call information according to standard operating procedures\nParticipate in customer service-related projects and provide recommendations to improve work processes and service level of the team\nJob Requirements\nDiploma or above in any discipline\nMinimum of 4 years in client service with good knowledge of insurance industry preferred\nHolder of IIQE paper 1, 3 and 5 is preferable\nStrong team player with positive attitude\nClient-centric with good communication and interpersonal skills\nDetail-minded, multi-tasked and able to work under pressure\nGood spoken and written English & Chinese (both Cantonese and Mandarin)\nGood PC skills in MS Office\n\u00a0\nWe offer attractive salary, MPF, group life and group medical insurance and excellent career development opportunities to the right candidate.\nWe are an equal opportunity employer and welcome applications from all qualified candidates. Application forms and resume will be kept for a period of\u00a024 months after completion of the recruitment process. (All information will be held in strict confidence and only used for recruitment purpose.)", "employment_types": ["Full Time", "Permanent"], "selling_points": ["Hotline Service / Call Centre / Contact Centre", "Life / Health / Medical Insurance / CS", "IIQE paper 1, 3, 5 / Mandarin / Chinese Client"], "locations": ["Hung Hom"], "categories": ["Sales, CS & Business Devpt", "Call Centre", "Customer Service - Supervisor / Officer", "Insurance", "Others"], "post_time": "2022-01-17T06:25:42Z", "salary": {"currency": null, "max": null, "min": null, "period": "monthly", "term": null}, "salary_visible": false, "title_keywords": ["representative"], "responsibilities": ["handle customer enquiries", "service standard", "guidelines", "quality", "procedures", "maintain", "customer service", "provide recommendations", "liaise with", "kpis"], "requirements": {"degrees": ["diploma or above"], "majors": [], "languages": ["cantonese", "english", "chinese", "mandarin"], "language_level": ["good"], "hard_skills": ["iiqe paper", "pc skills", "ms office"], "soft_skills": ["detail-minded", "positive attitude", "communication and interpersonal skills", "multi-tasked", "team player", "work under pressure"], "languages_combined": [{"language": "cantonese", "language_level": ["good"]}, {"language": "english", "language_level": ["good"]}, {"language": "chinese", "language_level": ["good"]}, {"language": "mandarin", "language_level": ["good"]}]}, "experience_required": {"duration": [], "field": []}}, {"job_id": "100003009056357", "location_code": "hk", "company": "Generali Life (Hong Kong) Limited", "job_title": "Officer - Policy Services (Retail Life & Retail Health Operations)", "description": "Job Scope\nYou will be contributing in developing and implementing of individual health insurance\u2019s strategy to achieve strategic objectives and financial targets. In addition to this, you will be supporting after sale services in individual health insurance business.\n\nMain Responsibilities\n\nSupport sales in individual health insurance business for both life and non-life units \u2013 providing insurance products assistance (pre-sale and post-sale enquiries) to sales/broker, medical and healthcare service providers\nCo-ordinate with different departments to manage the selling process and monitor the after-sale servicing issues to provide high quality service\nMonitor and implement the underwriting and operations processes & identify areas of improvement to enhance operational efficiency and service standard.\nCollect feedbacks and review health insurance policies and guidelines & act as an advisor on medical/health services.\nAssist all aspects of policy servicing with respect to New Health Insurance Business and/or New Health Products\nSupport marketing initiatives to other business units for business development activities.\n\nRequirement\n\nAt least 5-8 years\u2019 working experience in medical insurance operation.\nExcellent customer service skill to handle sales and customer enquiries\nGood interpersonal, organization, problem-solving and communication skills.\nProficient in PC and system applications, e.g., AS400 and GIS\nProfessional qualification in insurance industry or any health care disciplines, and university graduated in nursing, pharmacy or other medical/pharmaceutical or other related discipline (not a must).\nGood command of written and spoken Chinese and English", "employment_types": ["Full Time", "Permanent"], "selling_points": ["Health Insurance Professional", "Great Team Culture", "Competitive Market Salary"], "locations": ["Tai Koo"], "categories": ["Insurance", "Insurance Agent / Broker", "Others", "Sales, CS & Business Devpt", "Sales - Sales Management"], "post_time": "2022-01-18T04:03:54Z", "salary": {"currency": null, "max": null, "min": null, "period": "monthly", "term": null}, "salary_visible": false, "title_keywords": ["officer", "operations"], "responsibilities": ["service standard", "co-ordinate with", "operations", "policies", "review", "quality", "monitor", "guidelines", "insurance"], "requirements": {"degrees": [], "majors": [], "languages": ["english", "chinese"], "language_level": ["good command"], "hard_skills": ["pc", "problem-solving"], "soft_skills": ["communication skills", "problem-solving", "customer service", "interpersonal"], "languages_combined": [{"language": "english", "language_level": ["good command"]}, {"language": "chinese", "language_level": ["good command"]}]}, "experience_required": {"duration": ["at least 5-8 years"], "field": ["operation", "insurance", "medical"]}}, {"job_id": "100003009051400", "location_code": "hk", "company": "Insurance Authority", "job_title": "Manager (Non-life Business)", "description": "Reporting to the Senior Manager (Non-life Business), the incumbent will undertake the following:\n\nKey Responsibilities\n\nPerform prudential supervision of authorized non-life insurers\nParticipate in conducting inspection and monitoring non-life insurers' compliance with regulatory requirements\nSupport initiatives to promote the non-life insurance market of Hong Kong\nOther duties as assigned by senior management to facilitate the administration of the statutory functions of IA\u00a0\n\nRequirements\n\nA Bachelor\u2019s degree in accounting, finance, economics, statistics, actuarial science or related disciplines. Qualified CPA or actuary is recommended\nMinimum 5 years' solid work experience\nKnowledge of the local regulatory requirements, insurance products, industry practices and market dynamics relating to the insurance business.\nWork experience in a local or overseas insurance regulatory agency or non-life actuarial practices is preferred\nStrong problem-solving, analytical, interpersonal and communication skills, and able to work in a team in a collaborative environment\nAble to work independently and under pressure\nStrong command of both written and spoken English and Chinese. Proficiency in Putonghua will be an advantage\u00a0\n\nRemuneration Package\nA competitive remuneration package commensurate with the successful candidate\u2019s experience and qualifications will be offered.\n\nApplication\nReview of the applications will start as soon as possible and continue until the posts are filled. Interested applicants may send a letter of application quoting the reference number in the heading, together with a full resume stating public examination and university academic results as well as current and expected salaries by clicking \"Apply Now\".\n\nThe Insurance Authority is an equal opportunities employer. Applicants not invited for an interview within 2 months from the submission date may assume their applications unsuccessful. Applications may be considered for other suitable positions within IA. All applications will be handled in strict confidence and the information collected will only be used for recruitment purposes. All information on non-shortlisted applicants will be destroyed after 6 months from the submission of their applications.", "employment_types": ["Full Time", "Permanent"], "selling_points": [], "locations": ["Southern Area"], "categories": ["Accounting", "Others", "Insurance", "Others", "Public / Civil", "Others"], "post_time": "2022-01-15T14:24:49Z", "salary": {"currency": null, "max": null, "min": null, "period": "monthly", "term": null}, "salary_visible": false, "title_keywords": ["manager"], "responsibilities": ["other duties", "regulatory requirements", "compliance", "monitoring", "inspection", "senior management", "insurance", "administration"], "requirements": {"degrees": ["degree", "bachelor"], "majors": ["actuarial science", "finance", "economics", "statistics", "related disciplines", "accounting"], "languages": ["putonghua", "english", "chinese"], "language_level": ["advantage", "proficiency"], "hard_skills": ["cpa", "problem-solving"], "soft_skills": ["communication skills", "work independently", "confidence", "under pressure", "problem-solving", "collaborative", "interpersonal"], "languages_combined": [{"language": "putonghua", "language_level": ["proficiency", "advantage"]}, {"language": "english", "language_level": []}, {"language": "chinese", "language_level": []}]}, "experience_required": {"duration": ["minimum 5 years"], "field": ["agency", "insurance"]}}, {"job_id": "100003009055803", "location_code": "hk", "company": "Hays", "job_title": "STRATEGY MANAGER - INSURANCE", "description": "Hong Kong based Insurance Strategy Opportunity\n\nYour new company\nAn emerging Life Insurance firm is looking to grow within their strategy team. This multi-award winning organization is now looking for a Strategy Manager to oversee business initiatives within various areas of the company.\n\nYour new role\nAs the Strategy, working within the Strategy Team, you will conduct business planning, gather data on various segments of the business and assist in the executive of the company's strategic plan and vision. You will liaise with various levels of management and be responsible for implementing strategic change aligned with the company's strategic goals.\n\nWhat you'll need to succeed\nA successful applicant you will have at least 5 years' experience in a Consultancy or Business-Orientated function. Insurance or Financial Services industry experience will be a key asset. Strong communications in English & Cantonese are required for this role.\n\nCandidates with less experience will be considered for Assistant Manager\n\nWhat you'll get in return\nIn return, there will be plenty of career opportunity within this top-tier insurance organization and remuneration will be attractive.\n\nWhat you need to do now\nIf you fulfil all the qualifications mentioned above and have the drive to succeed or are interested in similar roles within insurance, please contact me with an attached CV at Jason.Kwong@hays.com.hk or please call +852-2230-7939", "employment_types": ["Full Time", "Permanent"], "selling_points": ["Leading insurance organisation", "Work at an award-winning company", "Excellent opportunities for growth"], "locations": ["Not Specified"], "categories": ["Professional Services", "Business Analysis / Data Analysis", "Insurance", "Others", "Sales, CS & Business Devpt", "Channel / Distribution"], "post_time": "2022-01-18T02:57:57Z", "salary": {"currency": null, "max": null, "min": null, "period": "monthly", "term": null}, "salary_visible": false, "title_keywords": ["manager"], "responsibilities": ["management", "business initiatives", "data", "contact", "plan", "liaise with", "insurance", "planning"], "requirements": {"degrees": [], "majors": [], "languages": ["cantonese", "english"], "language_level": [], "hard_skills": [], "soft_skills": ["interested in", "responsible"], "languages_combined": [{"language": "cantonese", "language_level": []}, {"language": "english", "language_level": []}]}, "experience_required": {"duration": ["at least 5 years"], "field": ["financial services industry", "business", "insurance"]}}, {"job_id": "100003009055780", "location_code": "hk", "company": "AXA Hong Kong", "job_title": "Assistant Business Development Manager, Employee Benefits", "description": "Job Description\n\n\nAchieve his or her own sales target by developing renewal and new business\n\nAssist the team to achieve the whole sales team's targets.\n\nResponsible for business development of medical insurance through different distribution channels to achieve the business targets.\n\nCoordinate product launch related marketing activities\n\nProvide services to customers and intermediaries\n\nMaintain close relationship with key business contact\n\nDevelop new business sources\n\nSupport team head on develop and perform strategic plan\n\nRequirement\n\n\nDegree or above with insurance\nAt least 4 years experience in Medical underwriting and business development\nWith strong leadership, can deliver results under pressure\nGood command of spoken and written English and Cantonese", "employment_types": ["Full Time", "Permanent"], "selling_points": ["Corporate role in AXA", "Health and Employee Benefits Business", "Business Development (Direct Channel)"], "locations": ["Southern Area"], "categories": ["Sales, CS & Business Devpt", "Business Development", "Insurance", "Others", "Direct Sales"], "post_time": "2022-01-18T02:56:42Z", "salary": {"currency": null, "max": null, "min": null, "period": "monthly", "term": null}, "salary_visible": false, "title_keywords": ["assistant business development manager"], "responsibilities": ["develop new business", "sales target", "developing", "develop", "coordinate", "maintain", "sales team", "contact", "plan", "insurance"], "requirements": {"degrees": ["degree or above"], "majors": ["insurance"], "languages": ["cantonese", "english"], "language_level": ["good command"], "hard_skills": [], "soft_skills": ["leadership", "under pressure"], "languages_combined": [{"language": "cantonese", "language_level": ["good command"]}, {"language": "english", "language_level": ["good command"]}]}, "experience_required": {"duration": ["at least 4 years"], "field": ["underwriting", "business development", "medical"]}}, {"job_id": "100003009055889", "location_code": "hk", "company": "Quality HealthCare Medical Services Ltd", "job_title": "Assistant Manager, Customer Relations", "description": "In the heart of the role:\n\n\n\nHandle feedbacks, complaints and compliments including investigations and liaise with team leaders, supervisors, third parties, to collect information and resolving issues\nResponsible to reply to customer by phone/ in writing\nEscalate case to Legal / Medical Director for advice when necessary\nPrepare meeting agenda and meeting notes\nPrepare report for periodically review by relevant parties, including basic data management and analysis\nMake recommendations based on the feedback themes and trends to improve customer experience, ensuring the improvement actions are tracked through to completion\nOther duties as required by line manager\n\nDesired Qualification & Experience:\n\n\n\nBachelor\u2019s Degree, with relevant customer service experience preferred\nA minimum of 5 years of customer service/ customer experience/complaint handling related experience\nExperience in medical/insurance industry and complaint handling is definitely advantage\nGood problem solving skill with customer centric mindset;\nDemonstrate ability to work independently\nExcellent written and verbal communications in English, Chinese and Mandarin\nProficient in Microsoft Office Suite - Word, Excel, PowerPoint\n\n(All applications will be treated in strict confidence and data collected will be used for recruitment purposes only)", "employment_types": ["Full Time", "Permanent"], "selling_points": ["Customer Service", "Customer Centric", "Complaints Handling"], "locations": ["Kowloon Bay"], "categories": ["Sales, CS & Business Devpt", "Customer Service - Supervisor / Officer", "Insurance", "Others", "Medical Services", "Others"], "post_time": "2022-01-18T03:03:20Z", "salary": {"currency": null, "max": null, "min": null, "period": "monthly", "term": null}, "salary_visible": false, "title_keywords": ["assistant manager,"], "responsibilities": ["make recommendations", "prepare report", "management", "other duties", "data", "analysis", "review", "customer service experience", "customer service", "recruitment", "liaise with", "insurance"], "requirements": {"degrees": ["degree", "bachelor"], "majors": [], "languages": ["english", "chinese", "mandarin"], "language_level": ["excellent"], "hard_skills": ["excel", "basic", "data management", "analysis", "word", "powerpoint", "problem solving", "make", "microsoft office suite"], "soft_skills": ["make recommendations", "work independently", "confidence", "responsible", "customer service", "problem solving skill"], "languages_combined": [{"language": "english", "language_level": ["excellent"]}, {"language": "chinese", "language_level": ["excellent"]}, {"language": "mandarin", "language_level": ["excellent"]}]}, "experience_required": {"duration": ["minimum of 5 years"], "field": ["related", "customer service", "insurance industry", "medical"]}}, {"job_id": "100003009055789", "location_code": "hk", "company": "Hays", "job_title": "Customer Services Administrator, Fresh Grad Welcome", "description": "Deliver first-class customer services and operational duties\n\nYour new company\nOur client is a multinational UK-based firm in the insurance industry, this fast-growing business has been one of the market-leaders in wealth and insurance-based wealth solutions. Due to their strong determination to expand, they are looking for a passionate candidate in the provision of excellent customer services and operational duties.\n\nYour new role\nAs one of the key members in the customer service team, you will be providing customer service support such as handling enquiries through telephone calls and emails. You will deliver quality service and ensure high quality service standard. For a smooth operation flow, you will also provide administration supports such as handling ad hoc projects and assignments in a timely manner.\n\nWhat you'll need to succeed\n\nAt least one year of customer services experience\nFresh graduate with good communication skills will also be considered\nHigh level of proficiency of English, Chinese and Putonghua\nOutgoing and great interpersonal skills\nPassionate in offer best-in-class customer services to customers\n\n\n\nWhat you'll get in return\n\nA rewarding career in a high-performing culture\nWork in a dynamic environment in a multinational setting\nExcellent career development prospects\nGreat opportunity to build insights in the industry\n\n\n\nWhat you need to do now\nIf you fulfil all the qualifications mentioned above and have the drive to succeed or are interested in similar roles within insurance, please contact me with an attached CV at yumi.yung@hays.com.hk or please call +852-2230-7933.", "employment_types": ["Full Time", "Permanent"], "selling_points": ["Work-Life Balance", "Attractive Employee Benefits", "Dynamic Working Culture"], "locations": ["Not Specified"], "categories": ["Insurance", "Others"], "post_time": "2022-01-18T02:57:07Z", "salary": {"currency": null, "max": null, "min": null, "period": "monthly", "term": null}, "salary_visible": false, "title_keywords": ["administrator"], "responsibilities": ["service standard", "customer service support", "quality", "a timely manner", "customer services", "communication", "customer service", "ad hoc projects", "contact", "career development", "insurance", "operational duties", "administration"], "requirements": {"degrees": ["fresh graduate"], "majors": [], "languages": ["putonghua", "english", "chinese"], "language_level": ["proficiency"], "hard_skills": ["dynamic"], "soft_skills": ["passionate", "communication skills", "outgoing", "first-class", "dynamic environment", "timely", "interested in", "customer service", "interpersonal skills", "smooth"], "languages_combined": [{"language": "putonghua", "language_level": ["proficiency"]}, {"language": "english", "language_level": ["proficiency"]}, {"language": "chinese", "language_level": ["proficiency"]}]}, "experience_required": {"duration": ["at least one year"], "field": ["customer services"]}}, {"job_id": "100003009047977", "location_code": "hk", "company": "Convoy Global Holdings Limited", "job_title": "Assistant, Administration", "description": "Responsibilities:\u00a0\n\n\nPerform daily logistic, circulation and replenishment support for document and other office consumable.\nProvide support on the facilities repair and maintenance, room setting and relocation work.\nProvide support on organizing staff event/activities and sourcing office supplies/ad hoc items.\nProvide administrative support to the Administration Team and other department unit.\nHandle and maintain records and files, prepare reports, documents and presentations.\nLiaise and communicate with internal and external parties on daily operation issue.\nHandle enquiries and provide reception/counter service if needed.\nPerform ad hoc tasks assigned by supervisor.\n\nRequirements:\n\n\nDiploma or above in Administrative or Facilities Management or related discipline is preferred.\u00a0\nAt least 2 years working experience in large Corporation/MNC.\nStrong sense of responsibility, well organized, meticulous & self-motivated.\nGood command of written and spoken Cantonese and Chinese.\nComputer literate in MS Office including Chinese word processing is advantage\nImmediate available is preferable\n\n\u00a0We offer competitive remuneration including career prospects to the right candidate. Interested parties please send detailed resume with availability, current and expected salaries to\u00a0Human Resources Department, Convoy Global Holdings Limited, Trust Tower, 68 Johnston Road, Wan Chai, Hong Kong\u00a0or by clicking the\u00a0Apply Now\u00a0button and upload your CV and cover letter.\n\n(All applications will be treated in strict confidence and used for recruitment purpose within Convoy Global Holdings Limited only. All applicants are kept on file 6 months from the date of the application.)\n", "employment_types": ["Full Time", "Permanent"], "selling_points": ["administration support", "facility management", "office administration"], "locations": ["Wan Chai"], "categories": ["Admin & HR", "Clerical / Admin Staff", "Others", "Insurance", "Others"], "post_time": "2022-01-14T04:24:25Z", "salary": {"currency": null, "max": null, "min": null, "period": "monthly", "term": null}, "salary_visible": false, "title_keywords": ["assistant"], "responsibilities": ["liaise", "communicate with", "provide support", "ad hoc", "prepare reports", "maintenance", "office supplies", "internal and external parties", "daily operation", "replenishment", "presentations", "ad hoc tasks", "handle enquiries", "repair", "maintain", "provide administrative support", "administration"], "requirements": {"degrees": ["diploma or above"], "majors": [], "languages": ["cantonese", "chinese"], "language_level": ["advantage", "good command"], "hard_skills": ["facilities management", "chinese word processing", "ms office"], "soft_skills": ["meticulous", "self-motivated", "well organized", "sense of responsibility"], "languages_combined": [{"language": "cantonese", "language_level": ["good command"]}, {"language": "chinese", "language_level": ["advantage", "good command"]}]}, "experience_required": {"duration": ["at least 2 years"], "field": []}}, {"job_id": "100003009042217", "location_code": "hk", "company": "Gravitas Recruitment Group (Hong Kong) Limited", "job_title": "Policy Administration Officer - Life / Group Life", "description": "Our client is a top tier insurance company with strong presence and good reputation internationally. They are now looking for addition talents to the policy administration team!\n\nKey Responsibilities:\n\nDeliver administrative support and customer service regarding individual / group life clients\nCoordinate and review escalated cases from offshore team and perform follow-up actions\nManage client requests professionally\nParticipate in AML / Customer Due Diligence checking\n\nJob Requirements:\n\n2-3 year of working experience in policy administration (Individual life / Group life)\nA good team player and desire to work in a team-oriented environment\nGood command of spoken English, Mandarin and Cantonese\n\nFor interested parties, please Apply Now with your detailed CV. Shortlisted candidates would be called to discuss further.", "employment_types": ["Full Time"], "selling_points": ["Top tier insurer", "5-days working days", "Individual life / Group life Policy Administration"], "locations": ["Not Specified"], "categories": ["Insurance", "Others"], "post_time": "2022-01-12T06:39:20Z", "salary": {"currency": null, "max": null, "min": null, "period": "monthly", "term": null}, "salary_visible": false, "title_keywords": ["administration officer"], "responsibilities": ["aml", "administrative support", "review", "checking", "coordinate", "customer due diligence", "customer service"], "requirements": {"degrees": [], "majors": [], "languages": ["cantonese", "english", "mandarin"], "language_level": ["good command"], "hard_skills": [], "soft_skills": ["good team player"], "languages_combined": [{"language": "cantonese", "language_level": ["good command"]}, {"language": "english", "language_level": ["good command"]}, {"language": "mandarin", "language_level": ["good command"]}]}, "experience_required": {"duration": ["2-3 year"], "field": ["policy administration"]}}, {"job_id": "100003009044602", "location_code": "hk", "company": "Hong Kong Life Insurance Limited", "job_title": "Insurance Specialist Manager", "description": "Responsibilities\n\nAnalyze and valuate a wide range of financial products, including but not limited to bonds, structure notes, other structured products, etc;\nPrepare daily P&L reporting, Calculate P&Ls of different investment pools;\nCoordinate with internal stakeholders including front desk, Risk Department on the development of valuation model;\nParticipate in related valuation system enhancement projects;\nProduce daily and quarterly product control reports to management;\nAd-hoc analysis and PNL reporting as needed;\nHandle other ad-hoc tasks as assigned by Financial Controller.\nRequirement\n\nDegree holder, major in accounting or other finance related subjects\nMinimum 5 years\u2019 work experience in the field of Product Control in sizable financial institutions;\nFamiliar with the valuation of different financial products, especially in Fixed Income Products (bonds, structure notes, etc);\nStrong & Solid knowledge on financial instruments & market operations\nProficient in setting up valuation model;\nIndependent, strong analytical abilities and communication skill, good time management and high attention to details\nExcellent written and oral English and Chinese, Mandarin preferred\nWe offer attractive remuneration package and fringe benefits to the right candidate. Interested applicants please send detailed resume stating present & expected salaries and date of availability to Human Resources Department by clicking \"APPLY NOW\".\n\nFurther information about our group companies can be found at www.gfgroup.com.hk and www.gf.com.cn.\n\nAll applications will be treated in the strictest confidence and personal data collected will be used for recruitment purpose only.", "employment_types": ["Full Time", "Permanent"], "selling_points": ["Provide Professional insurance solution", "Execute sales strategies and business plans", "Conduct sales coaching, monitor sales performance"], "locations": ["Not Specified"], "categories": ["Sales, CS & Business Devpt", "Business Development", "Insurance", "Others", "Channel / Distribution"], "post_time": "2022-01-13T04:48:16Z", "salary": {"currency": null, "max": null, "min": null, "period": "monthly", "term": null}, "salary_visible": false, "title_keywords": ["insurance specialist", "manager"], "responsibilities": ["ad-hoc", "valuation", "reporting", "control", "management", "analysis", "ad-hoc tasks", "coordinate with", "p&l", "reports", "enhancement projects"], "requirements": {"degrees": ["degree holder"], "majors": ["finance", "accounting"], "languages": ["english", "chinese", "mandarin"], "language_level": ["excellent"], "hard_skills": [], "soft_skills": ["oral", "independent", "communication skill", "attention to details", "time management"], "languages_combined": [{"language": "english", "language_level": ["excellent"]}, {"language": "chinese", "language_level": ["excellent"]}, {"language": "mandarin", "language_level": []}]}, "experience_required": {"duration": ["minimum 5 years"], "field": ["financial institutions"]}}, {"job_id": "100003009050824", "location_code": "hk", "company": "Chubb Insurance Hong Kong Limited", "job_title": "Client Service Executive", "description": "Responsibilities\n\nSupport Senior Management in all aspects of business and administration, coordination and communication with headquarters in executing Group business strategies to Hong Kong office as a subsidiary of the Group;\nIn charge of independent management meeting arrangement and prepare agenda, meeting materials and post-meeting minutes;\nResponsible for coordinating business requests via the internal OA system, and maintain OA system\u2019s daily operation;\nResponsible for drafting and consolidating management reports for management perusal;\nProvide internal departmental support, such as announcement of company rules and regulations, company important notice to staff;\nAssist in projects for GF corporate branding;\nAssist in ad-hoc projects assigned by Company Senior Management.\nRequirement\n\nDegree holder in Business Administration, Finance, Economics or relevant discipline;\n3 - 4 years\u2019 relevant experience in financial institutions, preferably in PRC-based investment banking;\nExcellent command of both written and spoken English and Chinese; fluency in Putonghua is preferred;\nProficient in MS Word, Excel, PowerPoint & Outlook;\nStrong self-motivation and able to work independently within tight timeline;\nGood communication, interpersonal and presentation skills;\nAbility to work in fast-paced environment with strong team spirit.\nWe offer attractive remuneration package and fringe benefits to the right candidate. Interested applicants please send detailed resume stating present & expected salaries and date of availability to Human Resources Department by clicking \"APPLY NOW\".\u00a0\n\nFurther information about our group companies can be found at www.gfgroup.com.hk and www.gf.com.cn.\u00a0\n\nAll applications will be treated in the strictest confidence and personal data collected will be used for recruitment purpose only.", "employment_types": ["Full Time"], "selling_points": ["General Insurance", "Property & Casualty", "Welcome Fresh Graduate"], "locations": ["Quarry Bay"], "categories": ["Insurance", "Others", "Banking / Finance", "Order Processing & Operation / Settlement", "Sales, CS & Business Devpt", "Sales Administration"], "post_time": "2022-01-14T11:29:33Z", "salary": {"currency": null, "max": null, "min": null, "period": "monthly", "term": null}, "salary_visible": false, "title_keywords": ["service executive"], "responsibilities": ["regulations", "management", "ad-hoc projects", "daily operation", "communication", "management reports", "maintain", "executing", "coordination", "senior management", "administration"], "requirements": {"degrees": ["degree holder"], "majors": ["finance", "economics", "business administration"], "languages": ["putonghua", "english", "chinese"], "language_level": ["fluency", "excellent"], "hard_skills": ["excel", "outlook", "powerpoint", "ms word"], "soft_skills": ["work independently", "team spirit", "communication", "presentation skills", "self-motivation", "work in fast-paced environment", "within tight timeline", "interpersonal"], "languages_combined": [{"language": "putonghua", "language_level": ["fluency"]}, {"language": "english", "language_level": ["excellent"]}, {"language": "chinese", "language_level": ["excellent"]}]}, "experience_required": {"duration": ["3 - 4 years"], "field": ["financial institutions", "relevant experience", "investment", "banking"]}}, {"job_id": "100003009049077", "location_code": "hk", "company": "Gain Miles Assurance Consultants Limited", "job_title": "Account Executive / Sr. Account Executive - Renewal Services", "description": "Responsibilities\n\nLead the team in execution of corporate finance transactions, including but not limited to IPO, Financial advisory and corporate finance related transactions;\nLead the team in liaising with professional parties and relevant authorities, such as SFC and Hong Kong Stock Exchange in connection with execution of projects;\nBe actively involved in due diligence, market research, financial analysis and regulatory check;\u00a0\nSupervise preparation of pitching materials\nRequirements\n\nAt least 6 years\u2019 working experience in corporate finance, preferably with focus in HK IPO execution;\nGood analytical and interpersonal skills with a proven track record in executing IPOs;\nWell versed with Listing Rules and Takeovers Code;\nProficiency in both written and spoken English and Chinese, fluency in Putonghua;\nAble to work under pressure, self-motivated and a good team player.\nWe offer attractive remuneration package and fringe benefits to the right candidate. Interested applicants please send detailed resume stating present & expected salaries and date of availability to Human Resources Department by clicking \"APPLY NOW\".\n\nFurther information about our group companies can be found at www.gfgroup.com.hk and www.gf.com.cn.\n\nAll applications will be treated in the strictest confidence and personal data collected will be used for recruitment purpose only.", "employment_types": ["Full Time"], "selling_points": ["Providing consultative services to clients", "Working closely with service providers", "5-day work"], "locations": ["Not Specified"], "categories": ["Insurance", "Insurance Agent / Broker", "Others"], "post_time": "2022-01-14T08:04:47Z", "salary": {"currency": null, "max": null, "min": null, "period": "monthly", "term": null}, "salary_visible": false, "title_keywords": ["account executive"], "responsibilities": ["due diligence", "liaising with", "transactions", "market research", "financial analysis"], "requirements": {"degrees": [], "majors": [], "languages": ["putonghua", "english", "chinese"], "language_level": ["fluency", "proficiency"], "hard_skills": ["code", "focus"], "soft_skills": ["good team player", "self-motivated", "interpersonal skills", "focus", "work under pressure"], "languages_combined": [{"language": "putonghua", "language_level": ["fluency", "proficiency"]}, {"language": "english", "language_level": ["proficiency"]}, {"language": "chinese", "language_level": ["proficiency"]}]}, "experience_required": {"duration": ["at least 6 years"], "field": ["corporate finance"]}}, {"job_id": "100003009050493", "location_code": "hk", "company": "AXA Hong Kong", "job_title": "Assistant Support Officer (1 year contract)", "description": "Responsibilities\n\nAssist dealing team in Broker Supplied System (BSS) User Acceptance Test (UAT) planning, UAT co-ordination, UAT test cases preparation and execution\nDesign test cases based on exchange rules and business requirement to ensure comprehensive coverage of test cases\nManage execution of test cases\nCompile test result and monitor the defect fixing progress\nMonitor UAT schedule and progress and support the rollout of system\nRequirement\n\nDegree Holder\nFamiliar with Hong Kong, China Stock Connect, US and Foreign stock trading, Knowledge on Wealth Management Products is an advantage\nKnowledge in Broker Supplied System (BSS)\n1-2 working experience\nSelf-initiative, able to work independently and under pressure, and meet tight deadline\nExcellent communication and interpersonal skills\nGood command of both written and spoken English and Chinese, able to speak Putonghua\nWe offer attractive remuneration package and fringe benefits to the right candidate. Interested applicants please send detailed resume stating present & expected salaries and date of availability to Human Resources Department by clicking \"APPLY NOW\".\n\nFurther information about our group companies can be found at www.gfgroup.com.hk and www.gf.com.cn.\n\nAll applications will be treated in the strictest confidence and personal data collected will be used for recruitment purpose only.", "employment_types": ["Full Time", "Permanent"], "selling_points": ["Support role on distribution channels", "Good communications with positive attitude", "Good working environment & culture"], "locations": ["Southern Area"], "categories": ["Insurance", "Others", "Sales, CS & Business Devpt", "Others", "Sales Administration"], "post_time": "2022-01-14T10:31:36Z", "salary": {"currency": null, "max": null, "min": null, "period": "monthly", "term": null}, "salary_visible": false, "title_keywords": ["assistant support officer"], "responsibilities": ["uat", "monitor", "design", "schedule", "planning"], "requirements": {"degrees": ["degree holder"], "majors": [], "languages": ["putonghua", "english", "chinese"], "language_level": ["good command"], "hard_skills": [], "soft_skills": ["work independently", "under pressure", "communication and interpersonal skills", "self-initiative", "meet tight deadline"], "languages_combined": [{"language": "putonghua", "language_level": ["good command"]}, {"language": "english", "language_level": ["good command"]}, {"language": "chinese", "language_level": ["good command"]}]}, "experience_required": {"duration": [], "field": []}}, {"job_id": "100003009050751", "location_code": "hk", "company": "China Life Insurance (Overseas) Company Limited", "job_title": "Sales and Operation Manager", "description": "Responsibilities:\n\nReview and evaluate business proposals of bond investment and structured products including TRS, Leveraged Note and cross-border transactions, negotiate with business on the risk management requirements;\nConduct credit analysis of counterparties and issuers of underlying securities;\nReview and confirm the internal credit rating of counterparties/bond issuers;\nKeep close attention on risk incidents and adverse market news, evaluate the potential risks and provide warnings/risk mitigation suggestions to business;\nWork closely with relevant parties to enhance the functionality and stability of the risk reporting system;\nCompose/update internal risk management report on regular basis or upon request.\nRequirements:\n\nBachelor Degree or above major in Business, Science or Engineering;\nAt least 5 years\u2019 experience in financial institutions with exposures to offshore Fixed Income/Equity market and structured products.\u00a0\nProfessional qualifications, such as CFA / FRM / CPA will be an advantage;\nProficiency in MS Office is a must;\nDetail-oriented and sensitive to numbers;\nGood communication skills, fluent in Putonghua, proficient in Chinese writing.\nCandidates with less experience will be considered for Associate position.\nWe offer attractive remuneration package and fringe benefits to the right candidate. Interested applicants please send detailed resume stating present & expected salaries and date of availability to Human Resources Department by clicking \"APPLY NOW\".\n\nFurther information about our group companies can be found at www.gfgroup.com.hk and www.gf.com.cn.\n\nAll applications will be treated in the strictest confidence and personal data collected will be used for recruitment purpose only.", "employment_types": ["Permanent"], "selling_points": ["Pls refer to the Job Adv", "Pls refer to the Job Adv", "Pls refer to the Job Adv"], "locations": ["Wan Chai"], "categories": ["Banking / Finance", "Others", "Insurance", "Insurance Agent / Broker", "Others"], "post_time": "2022-01-14T11:16:13Z", "salary": {"currency": null, "max": null, "min": null, "period": "monthly", "term": null}, "salary_visible": false, "title_keywords": ["sales", "operation manager"], "responsibilities": ["reporting", "management", "analysis", "review", "transactions", "evaluate", "management report"], "requirements": {"degrees": ["degree or above", "bachelor"], "majors": ["science", "business", "engineering"], "languages": ["putonghua", "chinese"], "language_level": ["fluent", "proficient", "good"], "hard_skills": ["professional qualifications", "cfa", "cpa", "frm", "ms office"], "soft_skills": ["communication skills", "sensitive to numbers", "structured", "detail-oriented"], "languages_combined": [{"language": "putonghua", "language_level": ["fluent", "proficient", "good"]}, {"language": "chinese", "language_level": ["proficient", "good"]}]}, "experience_required": {"duration": ["at least 5 years"], "field": ["financial institutions"]}}, {"job_id": "100003009033836", "location_code": "hk", "company": "Regional Insurance Management (International) Ltd", "job_title": "Operations Assistant \u2013 Policy Administration", "description": "Requirements:\n\n\nBachelor\u2019s degree in any disciplines\nRecognized insurance qualification ANZIIF / ACII or equivalent preferred\nMinimum 6 years\u2019 working experience in insurance field\nSound knowledge of General Insurance Products\nProven English proficiency and Putonghua\nFamiliar with PC software e.g. MS Word, Excel, PowerPoint & Chinese Word Processing\nExcellent interpersonal skills and customer-oriented\n\n\nResponsibilities:\n\n\nPerform underwriting duties for risk assessment, quotation preparation and negotiation, etc.\nHandle customer\u2019s enquires relating to insurance policy matters\nArrange facultative reinsurance\n\n\n(Candidates with more experience will be considered for Senior Officer.)\n\nGood remuneration and attractive fringe benefits will be offered to the successful applicant. Interested parties please apply with full resume, present and expected salary, available date by clicking \"Apply Now\".\n\nFor further information, please visit our company website:\u00a0www.shkp.com.\n\nWe are an equal opportunity employer and welcome applications from all qualified candidates. All personal data collected will be used for recruitment purpose only.\u00a0 Applicants not hearing from us within 3 months may consider their applications unsuccessful.\u00a0 All personal data collected will be destroyed within 24 months.", "employment_types": ["Full Time", "Permanent"], "selling_points": ["Year-end bonus and performance bonus", "5-days work week, bank holidays", "Policy administration and daily operations"], "locations": ["Ngau Tau Kok"], "categories": ["Admin & HR", "Clerical / Admin Staff", "Insurance", "Insurance Agent / Broker", "Others"], "post_time": "2022-01-10T01:54:31Z", "salary": {"currency": null, "max": null, "min": null, "period": "monthly", "term": null}, "salary_visible": false, "title_keywords": ["operations assistant"], "responsibilities": ["quotation", "insurance"], "requirements": {"degrees": ["degree", "bachelor"], "majors": ["any disciplines"], "languages": ["putonghua", "english", "chinese"], "language_level": ["proficiency"], "hard_skills": ["excel", "chinese word processing", "powerpoint", "pc", "ms word"], "soft_skills": ["customer-oriented", "interpersonal skills"], "languages_combined": [{"language": "putonghua", "language_level": ["proficiency"]}, {"language": "english", "language_level": ["proficiency"]}, {"language": "chinese", "language_level": []}]}, "experience_required": {"duration": ["minimum 6 years"], "field": ["insurance"]}}, {"job_id": "100003009050491", "location_code": "hk", "company": "Chevalier Insurance Company Limited", "job_title": "Underwriting Clerk", "description": "Responsibilities\n\nDesign, develop, implement, and maintain programs by specifying training objectives, content, activities and methods in program design/plan to meet with the identified training needs supporting business partners and sales channels\n\nIdentify the extent of a program's impact on participants and maintain follow-up on their applications after the program\n\nReview course evaluation for further enhancement or improvement\n\nConduct analysis on information/data/resources relating to section\u2019s training activities, and report findings in regular reports\n\nPrepare regular reports on training activities to management according to the guidelines given\n\nExecute and deliver quality and effective training to different target participants \u2022 Manage the training library / record / file management\n\nRequirements\n\nDegree holder or equivalent in Business Administration, Marketing or Finance\n\nMinimum 8 years of working experience in life insurance company with at least 5 years in training\n\nTraining program design experience is preferred\n\nSales experience in insurance, personal products or financial planning a definite advantage\n\nPasses in IIQE Paper 1, 3 & 5\n\nExcellent presentation and communication skills Proficiency in computer applications, e.g. MS Word, Excel and Chinese Word Processing\n\nGood command of verbal and written English and Chinese (Cantonese & Mandarin)\n\nCandidate with less experience will be considered as Assistant Training Manager\n\nInterested parties please send a detailed resume, stating current and expected salary to Human Resources Department.\u00a0[via APPLY NOW]\n\nInformation supplied will be treated in strict confidence and used in accordance with the Personal Data (Privacy) Ordinance. Applicants not invited for interview within 6 weeks may consider their applications unsuccessful.", "employment_types": ["Full Time", "Permanent"], "selling_points": ["Prepare insurance policies & related documents", "HKDSE or above", "At least 1 year of relevant work experience"], "locations": ["Kowloon Bay"], "categories": ["Admin & HR", "Clerical / Admin Staff", "Insurance", "Underwriter", "Others"], "post_time": "2022-01-14T10:31:27Z", "salary": {"currency": null, "max": null, "min": null, "period": null, "term": null}, "salary_visible": false, "title_keywords": ["clerk"], "responsibilities": ["management", "data", "training activities", "guidelines", "analysis", "review", "quality", "design", "develop", "maintain", "reports", "plan", "evaluation", "file management", "report"], "requirements": {"degrees": ["degree holder"], "majors": ["finance", "marketing", "business administration"], "languages": ["cantonese", "english", "chinese", "mandarin"], "language_level": ["good command"], "hard_skills": ["iiqe paper", "excel", "chinese word processing", "ms word"], "soft_skills": ["communication skills", "presentation"], "languages_combined": [{"language": "cantonese", "language_level": ["good command"]}, {"language": "english", "language_level": ["good command"]}, {"language": "chinese", "language_level": ["good command"]}, {"language": "mandarin", "language_level": ["good command"]}]}, "experience_required": {"duration": ["minimum 8 years", "at least 5 years"], "field": ["training", "design", "life insurance company", "planning", "insurance", "financial"]}}, {"job_id": "100003009050263", "location_code": "hk", "company": "AXA Hong Kong", "job_title": "Business Development Manager, Employee Benefits", "description": "Responsibilities:\n\nProvide professional general insurance service to customers\nAnswer customer enquiries and provide one stop service\nNegotiate terms with clients and prepare quotations\nProvide quality post-sales services to product features\nFollow up with customers to collect outstanding premium\nLiaise with internal departments to resolve customer problems\nPerform any other ad hoc projects as assigned by team leader\n\nRequirements:\n\nDegree holder in Marketing or Banking and financial services\nPasses in IIQE Examinations Paper 1 and 2\n3 year sales & marketing experience in general insurance industry\nGood service attitude & outgoing personality\nGood interpersonal & communication skills\nProficient in written & spoken English & Chinese, including Putonghua\nSelf-motivated, independent, able to work under pressure\nFamiliar with MS Office applications\nImmediate available is much preferred\n\nWe offer competitive remuneration package. Interested parties, please send your resume with CURRENT & EXPECTED salary and DATE AVAILABLE by clicking APPLY NOW.\n\n(Data collected would be used for recruitment purpose only)", "employment_types": ["Full Time", "Permanent"], "selling_points": ["Business Development for Group Life & Medical", "Sales Management", "Good working environment & culture"], "locations": ["Southern Area"], "categories": ["Sales, CS & Business Devpt", "Business Development", "Insurance", "Insurance Agent / Broker", "Others"], "post_time": "2022-01-14T10:03:14Z", "salary": {"currency": null, "max": null, "min": null, "period": "monthly", "term": null}, "salary_visible": false, "title_keywords": ["business development manager"], "responsibilities": ["customer enquiries", "quality", "ad hoc projects", "liaise with", "insurance"], "requirements": {"degrees": ["degree holder"], "majors": ["marketing"], "languages": ["putonghua", "english", "chinese"], "language_level": ["proficient"], "hard_skills": ["iiqe", "ms office"], "soft_skills": ["outgoing personality", "communication skills", "self-motivated", "independent", "interpersonal", "work under pressure"], "languages_combined": [{"language": "putonghua", "language_level": ["proficient"]}, {"language": "english", "language_level": ["proficient"]}, {"language": "chinese", "language_level": ["proficient"]}]}, "experience_required": {"duration": ["3 year"], "field": ["general insurance", "marketing"]}}, {"job_id": "100003009052105", "location_code": "hk", "company": "BUPA Asia Limited", "job_title": "Information Security Manager", "description": "Job Duties:\n\nParticipate in various projects on the development, maintenance and enhancement of operations systems\nPrepare regular claims management reports and analysis\nAssist to handle the processing of claim assessment and policy transactions for claim purpose\nHandle enquiries from agency and other parties\nMaintain the service standard and ensure the quality of work of the team\nSupport ad hoc projects as requested\nRequirements:\n\nUniversity graduate in any disciplines\nProfessional qualification of FLMI or partial fulfillment of professional qualifications is preferred\nMinimum 5 years working experience in insurance claims and/or underwriting\nIndependent and with high degree of responsibility\nProficient in MS Word, Excel, Powerpointand Chinese Word Processing\nGood command of both spoken and written English and Chinese\nCandidates with less experience will be considered as Senior Claims Executive \u00a0\u00a0 \u00a0\nCareers at Chubb2A Career with Chubb offers varied and interesting work, multinational exposure and freedom and opportunity to develop in a challenging professional environment.\u00a0 A competitive compensation package will be offered to the successful candidate. \u00a0\nTo register your interest, you may send us your application with academic qualifications, career experience, existing and expected salary and contact information, in complete confidence to our Human Resources Department, 33/F, Windsor House, 311 Gloucester Road, Causeway Bay, Hong Kong or by clicking \"Apply Now\".\u00a0 Before doing so, please read and understand our Company\u2019s Privacy Policy and below Personal Information Collection Statement.\nChubb Life Insurance Company Ltd. (Incorporated in Bermuda with Limited Liability)\n\n\n******************************************************************************************\n\nPERSONAL INFORMATION COLLECTION STATEMENT\n\nYou acknowledge and understand that, before sending your application to us, you are required to read, understand and consent to the Company\u2019s data practices described in this Personal Information Collection Statement (\u201cPICS\u201d).\n\nAll data provided will be treated in STRICT CONFIDENCE and subject to this PICS.\n\nThe personal data collected during recruitment process may be used, processed, or stored by the Company for:-\nassessing your suitability to the position for which you have applied; and/or\nnegotiating with and making offers of employment.\nYour application may not be considered or the outcome of your application may be influenced if you fail to provide certain information and/or data as requested.\n\nApplicants who are not contacted within four weeks may consider their applications unsuccessful. For the personal data of the unsuccessful applicant, the Company may also retain, disclose or transfer his/her personal data to the companies within the group of which the Company is a subsidiary (the \u201cGroup Companies\u201d) for:-\nfuture recruitment purposes; and/or\nassessing your suitability for a vacancy within the Group Companies.\nIt is the Company\u2019s policy that the personal data of the unsuccessful applicant shall be kept and stored by our Company for a period of not more than two years.\u00a0 The Company will also disclose or transfer his/her personal data to the Group Companies within the prescribed time.\u00a0 When doing so, the Company will use practical endeavours to ensure proper security and erasure of the data.\n\nYou are entitled to request access to or make amendments to your own personal data kept by the Company by writing to the Data Protection Officer of the Human Resources Department of the Company at 33/F., Windsor House, 311 Gloucester Road, Causeway Bay, Hong Kong Special Administrative Region. A reasonable fee may be charged by the Company for processing of the access request.", "employment_types": ["Full Time", "Permanent"], "selling_points": ["Min. 7  years experience", "Excellent career development & working environment", "Competitive benefits package"], "locations": ["Not Specified"], "categories": ["Information Technology (IT)", "IT Management", "Security", "Insurance", "Others"], "post_time": "2022-01-17T02:05:55Z", "salary": {"currency": null, "max": null, "min": null, "period": "monthly", "term": null}, "salary_visible": false, "title_keywords": ["information security manager"], "responsibilities": ["service standard", "maintenance", "operations", "analysis", "systems", "quality", "transactions", "handle enquiries", "management reports", "maintain", "ad hoc projects"], "requirements": {"degrees": ["university graduate", "degree"], "majors": ["any disciplines"], "languages": ["english", "chinese"], "language_level": ["good command", "proficient"], "hard_skills": ["excel", "chinese word processing", "professional qualifications", "make", "processing", "ms word"], "soft_skills": ["confidence", "independent"], "languages_combined": [{"language": "english", "language_level": ["good command"]}, {"language": "chinese", "language_level": ["good command", "proficient"]}]}, "experience_required": {"duration": ["minimum 5 years"], "field": ["underwriting", "insurance", "human resources"]}}, {"job_id": "100003009051399", "location_code": "hk", "company": "Insurance Authority", "job_title": "Part-time Consultant in Health Insurance", "description": "We\u2019re hiring!\u00a0\n\nAon is currently recruiting an Assistant Account Executive\u00a0to join our team in\u00a0Hong Kong.\n\n\nAbout Aon\n\nHeadquartered in London, Aon Plc is a leading global professional services firm providing a broad range of risk, retirement and health solutions. Our 50,000 colleagues in 120 countries empower results for clients by using proprietary data and analytics to deliver insights that reduce volatility and improve performance.\n\n\u00a0At Aon, you\u2019ll be part of a team which will support and inspire you and provide the opportunities and resources to develop your skills. It\u2019s an environment which encourages you to achieve your best - together we\u2019ll empower results.\u00a0\n\nThe Roles:\u00a0\n\nSupport Account Managers on consultative services to clients\nHandle client enquiries and liaise with insurers and service providers\nWork closely with underwriters on policy matters\nCheck policy documents and prepare debit notes\nProvide support in data analytics and result interpretation\nMaintain the quality and timeliness of client deliverables, provide assistance in report development in clear and concise manner\nProcess post-renewal documents and follow up\n\n\nOur Requirements:\n\nUniversity graduate, with minimum 1 year of working experience in Employee Benefits in broker firm(s) or insurance company(ies) preferred\nPassed in IIQE papers I, II, III & IV is preferred\nDetail-oriented, customer focused with effective client communication skills\nProactive, multi-tasker and able to work independently and as a team\u00a0\u00a0\nGood command of spoken and written English and Chinese.\nGood computer skills including MS Word, Excel & PowerPoint\n\nHow to Apply\n\nYour opportunity to empower results could start right here. Make your mark and apply online today with a brief covering letter and your resume, sharing relevant achievements for this position.\u00a0\n\nWe Offer You\n\nA competitive total rewards package, continuing education & training, and tremendous potential with a growing worldwide organization.\u00a0\n\nOur Colleague Experience\n\nEvery day, our colleagues make a difference, work with the best, own their potential, and value one another. Together, we share this one purpose: to empower economic and human possibility around the world. This unifying goal is at the heart of our identity, and it lives in everything we do. To learn more about our colleague experience, visit Aon Colleague Experience.\n\nAon is an equal opportunities employer. We are committed to creating a winning and inclusive culture where everyone feels valued and has opportunities for growth and development.\n\nAll applications will be treated in strict confidence and data collected will be used for recruitment purposes only.\u00a0 Only selected candidates will be contacted for interview.", "employment_types": ["Part Time"], "selling_points": [], "locations": ["Southern Area"], "categories": ["Insurance", "Others", "Public / Civil", "Others"], "post_time": "2022-01-15T14:24:26Z", "salary": {"currency": null, "max": null, "min": null, "period": "monthly", "term": null}, "salary_visible": false, "title_keywords": ["consultant"], "responsibilities": ["provide support", "data", "quality", "develop", "policy documents", "maintain", "liaise with", "provide assistance", "report"], "requirements": {"degrees": [], "majors": [], "languages": [], "language_level": [], "hard_skills": ["data analytics", "plc"], "soft_skills": ["clear"], "languages_combined": []}, "experience_required": {"duration": [], "field": []}}, {"job_id": "100003009046581", "location_code": "hk", "company": "BUPA Asia Limited", "job_title": "Senior Officer  Business Development (1 year Contract with gratuity)", "description": "Chevalier\u00a0Insurance Company\u00a0Limited, a subsidiary of Chevalier Group, is now inviting high calibre persons to apply for this position:\n\n\n\nResponsibilities\n\nPrepare insurance policies and related documents\nPerform ad hoc tasks as assigned\n\nRequirements\n\nHKDSE or above\nAt least 1 year of relevant work experience\nProficient in MS Word and Excel\nGood command\u00a0of both written and spoken\u00a0English and Chinese\nEnthusiastic about job and willing to learn\nCandidate with more experience will be considered for the position of Senior Clerk\n\n\nAttractive remuneration package will be offered to the right candidate. Interested parties, please send us your resume with current and expected salary by clicking \"Apply Now\" or mail to:\n\nThe Human Resources Manager, Chevalier Group, 22F, Chevalier\u00a0Commercial Centre,\u00a08\u00a0Wang Hoi\u00a0Road, Kowloon Bay, Hong Kong\n\nWe are an equal opportunity employer and welcome applications from all qualified candidates. Personal data collected would be used for recruitment purpose only.", "employment_types": ["Full Time", "Permanent"], "selling_points": ["Insurance License holder (Paper 1 & 2)", "Business development role", "Flexible Culture & Competitive Remunerations"], "locations": ["Not Specified"], "categories": ["Insurance", "Others", "Sales, CS & Business Devpt", "Sales - Sales Management", "Others"], "post_time": "2022-01-13T14:57:23Z", "salary": {"currency": null, "max": null, "min": null, "period": "monthly", "term": null}, "salary_visible": false, "title_keywords": ["senior officer"], "responsibilities": ["related documents", "policies", "insurance", "ad hoc tasks"], "requirements": {"degrees": ["hkdse"], "majors": [], "languages": ["english", "chinese"], "language_level": ["good command"], "hard_skills": ["excel", "ms word"], "soft_skills": ["willing to learn", "enthusiastic"], "languages_combined": [{"language": "english", "language_level": ["good command"]}, {"language": "chinese", "language_level": ["good command"]}]}, "experience_required": {"duration": ["at least 1 year"], "field": []}}, {"job_id": "100003009047979", "location_code": "hk", "company": "Convoy Global Holdings Limited", "job_title": "Assistant Manager, General Insurance Brokerage", "description": "Responsibilities\n\nSupport daily operation tasks\nCompiles data and performs routine clerical tasks to relieve underwriter of minor administrative detail.\nReviews correspondence records and reports to select routine matters for processing.\nRoutes risk-involved matters to underwriter for evaluation.\n\nQualification :\u00a0\u00a0\u00a0\u00a0\u00a0\u00a0\u00a0\u00a0\u00a0\u00a0\u00a0\u00a0\u00a0\u00a0\u00a0\n\nF.6 or above with 1\u00a0year\u00a0or above working experience, prefer in clerical or admin area\nProficiency in MS Office, Chinese typing, Powerpoint/ Excel skills and English typing\n", "employment_types": ["Full Time", "Permanent"], "selling_points": ["Provide service to sales force", "Provide professional advice", "Handle and follow up on quotation"], "locations": ["Wan Chai"], "categories": ["Banking / Finance", "Financial Services", "Insurance", "Insurance Agent / Broker", "Others"], "post_time": "2022-01-14T04:24:25Z", "salary": {"currency": null, "max": null, "min": null, "period": "monthly", "term": null}, "salary_visible": false, "title_keywords": ["assistant manager,"], "responsibilities": ["evaluation", "daily operation", "reports", "data"], "requirements": {"degrees": [], "majors": [], "languages": ["english", "chinese"], "language_level": ["proficiency"], "hard_skills": ["excel", "typing", "powerpoint", "processing", "ms office"], "soft_skills": [], "languages_combined": [{"language": "english", "language_level": ["proficiency"]}, {"language": "chinese", "language_level": ["proficiency"]}]}, "experience_required": {"duration": ["1 year"], "field": ["admin", "clerical"]}}, {"job_id": "100003009050489", "location_code": "hk", "company": "Chevalier Group \u2013 Insurance Services", "job_title": "Clerk", "description": "Job Responsibilities:\n\nAchieve his or her own sales target by developing renewal and new business\nAssist the team to achieve the whole sales team's targets\n\nResponsible for business development of Employee Benefits through agency channel to achieve the business targets\n\nCoordinate product launch and promotion related market activities\n\nProvide services and sales support to agents and customers\n\nMaintain close relationship with key business contact\n\nDevelop new business souorces and agent growth\n\nSupport team head on develop and perform strategic plan\n\nJob Requirements:\n\nDegree or above with insurance\n\nAt least 5 years experience in Employee Benefits business development in agency channel\n\nWith strong leadership, can deliver results under pressure\n\nGood command of spoken and written English and Cantonese\n", "employment_types": ["Full Time", "Permanent"], "selling_points": ["Perform clerical works & data entries", "HKDSE or above, 1+ exp. preferably", "Good telephone manner & communication skills"], "locations": ["Kowloon Bay"], "categories": ["Admin & HR", "Clerical / Admin Staff", "Others", "Insurance", "Others"], "post_time": "2022-01-14T10:30:50Z", "salary": {"currency": null, "max": null, "min": null, "period": null, "term": null}, "salary_visible": false, "title_keywords": ["clerk"], "responsibilities": ["sales target", "sales team", "developing"], "requirements": {"degrees": [], "majors": [], "languages": [], "language_level": [], "hard_skills": [], "soft_skills": [], "languages_combined": []}, "experience_required": {"duration": [], "field": []}}, {"job_id": "100003009050262", "location_code": "hk", "company": "AXA Hong Kong", "job_title": "Head of Direct Sales, Employee Benefits", "description": "OneDegree is a new generation of InsurTech that reimagining the industry with design and digital innovation. Our mission is to set new standards for insurance that puts customers first.\n\nWe are among the first batch of virtual insurers authorized by the Hong Kong Insurance Authority to provide insurance products purely through online channels. We pride ourselves on providing breakthrough innovations in products and services via our digital platform. We are currently offering Pet, Fire and Critical Illness Insurance and expected to provide wider coverage to the general public in the coming year.\n\nWant to join us and make a change? We are looking for a Policy Administration Officer who acts as the gatekeeper of our day-to-day policy administrative activities.\n\nIf you are detail-minded and self-motivated, come and join our team!\n\u00a0\n\nWhat you will be doing:\n\nManaging the day to day policy administrative activities\nHandling and follow up inquiries from internal and external customer and outsourcing teams regarding policy issuance, subscription payment status, and change of particulars\nVerifying data from various daily and monthly reports to ensure data accuracy\nEnsuring all tasks are done within the turnaround time and following the policy administration procedures\nTaking minutes for the monthly department meeting\nAssisting in ad hoc UATs and assignments\nBuilding and scale a new team that owns the customer experience and works to exceed their expectations\nProviding support to other teams, including claims, policy admin, account management, and product development\n\nWhat we are looking for:\n\nHigh school certification or above, university degree preferred. Fresh graduates are also welcome!\nExperience in the General Insurance industry is a plus!\nExcellent communication in verbal and written form (Both English and Chinese)\nExcellent typing skills in both English and Traditional Chinese\nHighly self-motivated, organized, and a team player\nWillingness and ability to operate in a team environment\nAbility to streamline processes and prioritize issues, support multiple tasks and be responsive\nRemain calm in high-pressure situations. Positive attitude, patient with people and willing to learn - Self-starter and a good team player\nCurious and interested in technology and new products\u00a0\n*Canadidate with less experience will be considered as Policy Administrative Assistant.\n\n\n\n\nMore about us:\n\nFast-growing insurtech startup in Hong Kong\nYoung and energetic team\nFlat organization structure\nOpportunities to grow and shine!\n\nWe value our employee - let\u2019s check out what we offer\n\n15 days annual leave\nMedical benefits\nWork-life balance environment\n\nTo us, people are our greatest asset and we are more than happy to invest in employees! We create a healthy work atmosphere and provide you with the tools and support for doing your job successfully. With a culture of flexibility and transparency, we believe there should be no barriers, and everyone\u2019s contributions matter.\n\nWe would like to be an \u2018EMPLOYER OF CHOICE\u2019!", "employment_types": ["Full Time", "Permanent"], "selling_points": ["Team Lead of EB direct Sales team", "Business development for Employee Benefits", "Good working environment & culture"], "locations": ["Southern Area"], "categories": ["Sales, CS & Business Devpt", "Business Development", "Insurance", "Insurance Agent / Broker", "Others"], "post_time": "2022-01-14T10:03:13Z", "salary": {"currency": null, "max": null, "min": null, "period": "monthly", "term": null}, "salary_visible": false, "title_keywords": ["sales"], "responsibilities": ["online channels", "management", "ad hoc", "data", "monthly reports", "teams", "ensure data accuracy", "digital platform", "design", "administration procedures", "communication", "payment", "providing support", "insurance", "administrative activities", "administration"], "requirements": {"degrees": ["university degree", "high school"], "majors": [], "languages": ["english", "chinese"], "language_level": ["excellent"], "hard_skills": ["make", "batch", "typing", "plus"], "soft_skills": ["detail-minded", "organized", "self-motivated", "good team player", "multiple tasks", "interested in", "willing to learn", "prioritize", "calm", "communication", "positive attitude", "patient", "team player", "energetic", "responsive"], "languages_combined": [{"language": "english", "language_level": ["excellent", "excellent"]}, {"language": "chinese", "language_level": ["excellent", "excellent"]}]}, "experience_required": {"duration": [], "field": ["general insurance", "administrative", "team"]}}, {"job_id": "100003009048348", "location_code": "hk", "company": "Lloyd Karson International Limited", "job_title": "Senior Officer / Officer - CS Management & Complaint Investigation (Life Insurance) (HKD20k \u2013 30k)", "description": "Reporting to the Executive Director - Non-life Business, the incumbent will assume the following:\n\nKey Responsibilities\n\nOffer subject matter expertise support as well as training on health insurance to case officers in the prudential supervision of health insurers\nProvide insights on key market topics, emerging issues and future trends in the changing health insurance environment\nUndertake analysis of health insurance related topics and provide such other relevant support and services to the IA as may be required by the Authority from time to time\n\nRequirements\n\nGood knowledge of the health insurance market in Hong Kong, the competitive environment as well as the value chain in the healthcare segment in Hong Kong market\nSolid understanding of the key value drivers and performance metrics in health insurance\nRelevant professional knowledge in health insurance products, pricing, underwriting governance, claims and management of network of medical service providers\nExperience in health insurance product review, underwriting and claims audit and internal peer review\n\nRemark: This is a purposeful role and is ideal for newly retired health insurance professional seeking to contribute to the wellbeing and professional development of the Hong Kong health insurance market.\n\nRemuneration Package\nA competitive remuneration package commensurate with the successful candidate\u2019s experience and qualifications on a 1-year contract will be offered.\n\nApplication\nReview of the applications will start as soon as possible and continue until the post is filled. Interested applicants may send a letter of application quoting the reference number in the heading, together with a full resume stating current and expected salaries by clicking \"Apply Now\".\n\nThe Insurance Authority is an equal opportunities employer. Applicants not invited for an interview within 2 months from the submission date may assume their applications unsuccessful. Applications may be considered for other suitable positions within IA. All applications will be handled in strict confidence and the information collected will only be used for recruitment purposes. All information on non-shortlisted applicants will be destroyed after 6 months from the submission of their applications.\n", "employment_types": ["Full Time", "Permanent"], "selling_points": ["Experience in Insurance", "Strong client servicing / CS skills", "Draft complaint reply"], "locations": ["Quarry Bay"], "categories": ["Sales, CS & Business Devpt", "Call Centre", "Customer Service - Supervisor / Officer", "Insurance", "Others"], "post_time": "2022-01-14T06:38:14Z", "salary": {"currency": "HKD", "max": 29999, "min": 20000, "period": "monthly", "term": null}, "salary_visible": true, "title_keywords": ["senior officer", "officer"], "responsibilities": ["provide insights", "analysis", "insurance"], "requirements": {"degrees": [], "majors": [], "languages": [], "language_level": [], "hard_skills": [], "soft_skills": ["confidence", "ideal", "purposeful"], "languages_combined": []}, "experience_required": {"duration": ["1-year"], "field": ["underwriting", "insurance", "audit"]}}, {"job_id": "100003009037627", "location_code": "hk", "company": "BUPA Asia Limited", "job_title": "Customer Service Advisor / Senior Customer Service Advisor (5-day work, Monday - Friday)", "description": "As the leading financial advisory firm in Hong Kong, Convoy upholds its core values of Passion, Integrity and Professionalism in providing the best advices and service to help customers investing in their future.\n\nDue to our business expansion, we are looking for high calibre candidates to share our vision and venture our success.\n\n\nResponsibilities:\u00a0\n\nProvide service to sales force to achieve company targets\nBuild good working relationships with business partners\nProvide professional advice and broking service to sales force and clients to ensure the service excellence and customer retentions;\nHandle and follow up on quotation, product selection, insurance policy issuing, underwriting, renewals, policy changes, claims service and premium matters;\nLiaise between service providers on policy premium and product coverage; Assist on premium collection with sales force/clients\nReview and verify application documents are in compliance with the requirements;\nPerform ad hoc assignments and projects if necessary.\n\nRequirements:\n\nUniversity graduate with hands on experience in managing general insurance business portfolio;\nQualifications in IIQE preferred;\nMinimum 5 years\u2019 working experience in insurance administration support and client servicing;\nEnergetic, self-disciplined with strong sense of responsibility, well-organized, detail-minded and can work independently;\nGood communication skills with good command of both written and spoken in Cantonese, Mandarin and English;\nProficient in computer software for day-to-day operations.\n\nWe offer competitive remuneration including career prospects to the right candidate. Interested parties please send detailed resume with availability, current and expected salaries to\u00a0Human Resources Department, Convoy Global Holdings Limited, Trust Tower, 68 Johnston Road, Wan Chai, Hong Kong\u00a0or by clicking the\u00a0Apply Now\u00a0button and upload your CV and cover letter.\n\n(All applications will be treated in strict confidence and used for recruitment purpose within Convoy Global Holdings Limited only. All applicants are kept on file 6 months from the date of the application.)", "employment_types": ["Full Time", "Permanent"], "selling_points": ["Monday - Friday, Shift time between 9am - 7pm", "IIQE Paper 1 & 2 preferred", "Flexible Culture & Competitive Package"], "locations": ["Not Specified"], "categories": ["Sales, CS & Business Devpt", "Call Centre", "Customer Service - Supervisor / Officer", "Insurance", "Others"], "post_time": "2022-01-11T03:19:16Z", "salary": {"currency": null, "max": null, "min": null, "period": "monthly", "term": null}, "salary_visible": false, "title_keywords": ["customer service advisor"], "responsibilities": ["liaise", "review", "quotation", "compliance", "application documents", "ad hoc assignments", "working relationships", "insurance"], "requirements": {"degrees": ["university graduate"], "majors": ["business", "insurance"], "languages": ["cantonese", "english", "mandarin"], "language_level": ["good command", "good"], "hard_skills": ["iiqe"], "soft_skills": ["detail-minded", "communication skills", "work independently", "sense of responsibility", "well-organized", "hands on", "energetic"], "languages_combined": [{"language": "cantonese", "language_level": ["good command", "good"]}, {"language": "english", "language_level": ["good command", "good"]}, {"language": "mandarin", "language_level": ["good command", "good"]}]}, "experience_required": {"duration": ["minimum 5 years"], "field": ["general insurance", "business", "insurance", "administration"]}}, {"job_id": "100003009042227", "location_code": "hk", "company": "Gravitas Recruitment Group (Hong Kong) Limited", "job_title": "Pension Operations - Policy Administration and Customer Service", "description": "We\u2019re hiring!\n\nAon is currently recruiting an\u00a0Accounting Officer\u00a0to join our team in Hong Kong.\n\nAbout Aon\n\nHeadquartered in London, Aon Plc is a leading global professional services firm providing a broad range of risk, retirement and health solutions. Our 50,000 colleagues in 120 countries empower results for clients by using proprietary data and analytics to deliver insights that reduce volatility and improve performance.\n\nAt Aon, you\u2019ll be part of a team which will support and inspire you and provide the opportunities and resources to develop your skills. It\u2019s an environment which encourages you to achieve your best - together we\u2019ll empower results.\u00a0\n\nResponsibilities:\n\nWork in Reinsurance department\nPerform daily accounting operation in account payable and receivable function\nHandle invoice payments, receipts, and reconciliation of accounts with client & reinsurers\nInvestigate if any discrepancies within the reconciliation and follow up with respective units\nParticipate in Short-term project, such as clearance of legacy balance\nLiaise with client manager to understand client\u2019s needs and resolve accounting issues\nParticipate in UAT for system projects in relating to system enhancement if required\nAssist managers on reporting and other ad-hoc tasks.\n\nRequirements:\n\nGraduate with Accounting/ Finance/ Business degree.\nAt least 2-3 years relevant Accounting experience is preferred.\nStrong technical skills in MS Excel.\nProficiency in English and Mandarin.\nGood analytical skill and problem-solving skill.\nGood interpersonal skill\nDetailed minded, proactive, accurate and meticulous.\nMature, independent, self-starter.\nImmediate available preferred.\n\nHow to Apply\n\nYour opportunity to empower results could start right here. Make your mark and apply online today with a brief covering letter and your resume, sharing relevant achievements for this position.\n\nWe Offer You\n\nA competitive total rewards package, continuing education & training, and tremendous potential with a growing worldwide organization.\n\nOur Colleague Experience\n\nEvery day, our colleagues make a difference, work with the best, own their potential, and value one another. Together, we share this one purpose: to empower economic and human possibility around the world. This unifying goal is at the heart of our identity, and it lives in everything we do. To learn more about our colleague experience, visit Aon Colleague Experience.\n\nAon is an equal opportunities employer. We are committed to creating a winning and inclusive culture where everyone feels valued and has opportunities for growth and development.", "employment_types": ["Full Time", "Permanent"], "selling_points": ["Top tier insurer", "MPF operations", "Officer and senior officer positions"], "locations": ["Not Specified"], "categories": ["Insurance", "Others"], "post_time": "2022-01-12T06:40:11Z", "salary": {"currency": null, "max": null, "min": null, "period": "monthly", "term": null}, "salary_visible": false, "title_keywords": ["operations", "customer service"], "responsibilities": ["reporting", "receipts", "uat", "invoice", "ad-hoc tasks", "assist managers", "liaise with client", "payments", "daily accounting"], "requirements": {"degrees": ["degree"], "majors": ["business", "finance", "accounting"], "languages": ["english", "mandarin"], "language_level": ["proficiency"], "hard_skills": ["problem-solving", "make", "ms excel", "analytical skill"], "soft_skills": ["meticulous", "analytical skill", "independent", "accurate", "problem-solving", "mature", "interpersonal skill", "technical skills", "proactive", "detailed"], "languages_combined": [{"language": "english", "language_level": ["proficiency"]}, {"language": "mandarin", "language_level": ["proficiency"]}]}, "experience_required": {"duration": ["at least 2-3 years"], "field": ["accounting experience"]}}, {"job_id": "100003009046310", "location_code": "hk", "company": "China Taiping Life Insurance (Hong Kong) Company Limited", "job_title": "Administrative Assistant (Healthcare)", "description": "Chevalier\u00a0Insurance Company\u00a0Limited, a subsidiary of Chevalier Group, is now inviting high calibre persons to apply for this position:\n\nResponsibilities\n\nResponsible for\u00a0general clerical works and data entries\nSupport superiors on after-sales service related duties\nPerform other ad hoc tasks as assigned\n\nRequirements\n\nHKDSE or above\n1 year relevant working experience is preferred\nProficient in MS Word and Excel\nGood command\u00a0of both written and spoken\u00a0English and Chinese, knowledge in Putonghua will be an advantage\nGood telephone manner and communication skills\n\n\nAttractive remuneration package will be offered to the right candidate. Interested parties, please send us your resume with current and expected salary by clicking \"Apply Now\" or mail to:\n\nThe\u00a0Human Resources\u00a0Manager, Chevalier Group, 22/F, Chevalier\u00a0Commercial Centre,\u00a08\u00a0Wang Hoi\u00a0Road, Kowloon Bay, Hong Kong.\n\nWe are an equal opportunity employer and welcome applications from all qualified candidates. Personal data collected would be used for recruitment purpose only.", "employment_types": ["Full Time", "Permanent"], "selling_points": ["Bachelor degree, healthcare/insurance working exp.", "Maintain relationship with Doctor, Clinic, etc", "Provide support for internal and external customer"], "locations": ["Causeway Bay"], "categories": ["Beauty Care / Health", "Others", "Insurance", "Others", "Medical Services", "Nursing"], "post_time": "2022-01-13T10:25:04Z", "salary": {"currency": null, "max": null, "min": null, "period": "monthly", "term": null}, "salary_visible": false, "title_keywords": ["administrative assistant"], "responsibilities": ["after-sales service", "ad hoc tasks", "data"], "requirements": {"degrees": ["hkdse"], "majors": [], "languages": ["putonghua", "english", "chinese"], "language_level": ["advantage", "good command"], "hard_skills": ["excel", "ms word"], "soft_skills": ["communication skills", "telephone manner"], "languages_combined": [{"language": "putonghua", "language_level": ["advantage", "good command"]}, {"language": "english", "language_level": ["advantage", "good command"]}, {"language": "chinese", "language_level": ["advantage", "good command"]}]}, "experience_required": {"duration": ["1 year"], "field": ["relevant working experience"]}}, {"job_id": "100003009048314", "location_code": "hk", "company": "Bank of China Group Insurance Company Limited", "job_title": "Assistant Underwriter", "description": "To manage and grow profitably of Employee Benefits portfolio through best-in-class client servicing, active cross-selling initiatives and penetration to group members via Direct Channel\n\n\nManage a team of BDM to achieve their persnoal sales target by developing renewal and new business\nResponsible for business development of medical insurance through direct channels to achieve the business targets.\nCoordinate product launch related marketing activities\nProvide services to customers\nMaintain close relationship with keyclients and business contacts\nDevelop new business sources\nDevelop and perform strategic plan\n\nJob Requirements:\n\nUniversity degree with at least 10 - 15 years working experience\nExcellent presentation, planning, negotiation and organizational skills\nStrong problem solving, communication and time management skills\nAchievement oriented, drive for results.", "employment_types": ["Full Time", "Permanent"], "selling_points": [], "locations": ["Central"], "categories": ["Insurance", "Insurance Agent / Broker", "Underwriter", "Others"], "post_time": "2022-01-14T06:13:04Z", "salary": {"currency": null, "max": null, "min": null, "period": null, "term": null}, "salary_visible": false, "title_keywords": ["assistant"], "responsibilities": ["management", "develop new business", "sales target", "developing", "develop", "coordinate", "communication", "maintain", "plan", "insurance", "planning"], "requirements": {"degrees": ["university degree"], "majors": [], "languages": [], "language_level": [], "hard_skills": ["problem solving"], "soft_skills": ["organizational skills", "negotiation", "responsible", "time management skills", "problem solving", "communication", "active", "presentation"], "languages_combined": []}, "experience_required": {"duration": ["at least 10 - 15 years"], "field": []}}, {"job_id": "100003009051215", "location_code": "hk", "company": "Jobson Mores Limited", "job_title": "Insurance - Compliance/ AML, Manager/ Assistant Manager", "description": "The client is a global prestigious MNC Insurance Group, is now seeking a new headcount for Senior Officer / Officer - CS Management & Complaint Investigation (Life Insurance) (HKD20k \u2013 30k) to join their team\n\nResponsibilities:\n\nSupport complaint case handling and TNPS preliminary investigation (e.g. retrieve call record, jot down conversation in manual script\u2026etc.) for manager review\nFollow Complaint Protocol and handling procedure / workflow (e.g., issue acknowledge, prepare case summary, discuss with relevant parties to seek advice and propose resolution to resolve case, draft reply, etc.) to meet SLA for complaint case\nContact internal department and external customers if needed and assist in drafting complaint reply\nMake suggestions and streamline process for improving customer satisfaction\nGenerate regular reports including call management report, attendance report, retention report, TNPS report, costing report, etc\nAssist system UAT and project user requirements, and ad-hoc projects\n\nRequirements:\n\nDiploma or above with minimum 3 years of working experience, preferably in call center service\nIIQE Paper 1 and 3 required\nKnowledge of Life insurance product and operations\nKnowledge of call center operation workflow & procedures\nKnowledge of telephony system (NICE, Avaya & IVR)\nGood interpersonal and problem-solving skills, attentive to details\nGood command of English, Mandarin and Cantonese\nProficiency in Microsoft Office applications including Word, Excel and Chinese Word Processing\nCandidate with less experience will be considered as Officer\n\nIf you would like to apply for Senior Officer / Officer - CS Management & Complaint Investigation (Life Insurance) (HKD20k \u2013 30k) role or find out more, please click \"Apply Now\" or send your resume to arthurwong(at)lloydkarson.com quoting the reference: 134322", "employment_types": ["Full Time", "Permanent"], "selling_points": ["6+ years Compliance & AML experience in Insurance", "One of the fast growing Insurer in HK", "WorkLife balance, attractive Bonus & Good Benefits"], "locations": ["Wan Chai Area"], "categories": ["Banking / Finance", "Others", "Insurance", "Others", "Professional Services", "Legal & Compliance"], "post_time": "2022-01-15T05:03:10Z", "salary": {"currency": "HKD", "max": 69999, "min": 45000, "period": "monthly", "term": null}, "salary_visible": true, "title_keywords": ["assistant manager", "manager"], "responsibilities": ["attendance", "uat", "review", "investigation", "resolution", "reports", "contact", "ad-hoc projects", "management report", "report"], "requirements": {"degrees": ["diploma or above"], "majors": [], "languages": ["cantonese", "english", "chinese", "mandarin"], "language_level": ["proficiency", "good command"], "hard_skills": ["excel", "chinese word processing", "microsoft office", "nice", "word", "iiqe paper", "problem-solving skills"], "soft_skills": ["problem-solving skills", "interpersonal", "attentive to details"], "languages_combined": [{"language": "cantonese", "language_level": ["good command"]}, {"language": "english", "language_level": ["good command"]}, {"language": "chinese", "language_level": ["proficiency"]}, {"language": "mandarin", "language_level": ["good command"]}]}, "experience_required": {"duration": ["minimum 3 years"], "field": ["call center"]}}, {"job_id": "100003009040263", "location_code": "hk", "company": "AXA Hong Kong", "job_title": "Senior Customer Service Officer", "description": "Our client is a top tier insurer with strong presence in Hong Kong. With their rapid expansion, they are looking to hire insurance operations professionals who, ideally, have MPF or pension experiences to join their company.\n\nGiven the large-scale project, they have multiple roles and are offering both contract and permanent positions as options within administration or customer service. This is an exciting opportunity for individuals to join a global insurer.\n\nResponsibilities:\n\nManage MPF scheme accounts, perform account enrolment, termination, contribution, and data update\nPerform and review transaction processes\nProvide customer service and administration support\nAssist in streamlining and ensuring client service quality\n\nRequirements\n\nExperience in customer service or policy administration in life insurance industry\nKnowledge and understanding of MPF / ORSO / pension is beneficial\nStrong communications skills for Customer Service delivery\n\nGiven we are hiring for multiple roles across either Customer Service or Administration, if you are interested and have any of the above requirements then please Apply Now with your detailed CV.", "employment_types": ["Full Time", "Permanent"], "selling_points": ["Handle daily incoming premium collection", "Reconciliation and back office support", "Detail-minded, with good numeric sense"], "locations": ["Not Specified"], "categories": ["Accounting", "Accountant", "Banking / Finance", "Credit Collection", "Insurance", "Others"], "post_time": "2022-01-12T02:02:37Z", "salary": {"currency": null, "max": null, "min": null, "period": "monthly", "term": null}, "salary_visible": false, "title_keywords": ["senior customer service officer"], "responsibilities": ["provide customer service", "mpf", "data", "review", "quality", "administration"], "requirements": {"degrees": [], "majors": [], "languages": [], "language_level": [], "hard_skills": [], "soft_skills": ["customer service", "detailed"], "languages_combined": []}, "experience_required": {"duration": [], "field": ["customer service", "insurance industry", "policy administration"]}}, {"job_id": "100003009043312", "location_code": "hk", "company": "Gravitas Recruitment Group (Hong Kong) Limited", "job_title": "Senior Officer, Operational Support", "description": "Responsibilities\n\nProvide efficient and effective support for customers regarding medical and health services\u00a0\nCoordinate with internal department and outsourcing partners to prepare for necessary resources to support the customer\u2019s need\nMaintain customer satisfaction and good relationship with service provider (e.g. Doctor, Clinic, Hospital etc)\nAssist the Manager to expand local and global medical and healthcare network\nAssist the Manager to monitor the service provider\u2019s activity including compliance of agreed process, network pricing and network service quality standards\nProvide assistance in health market research for new project incentives and newest medical services\nProvide assistance in general administrative activities and any other ad hoc projects as assigned\n\nRequirement\n\nBachelor degree\nOver 1 year of working experience in the healthcare or insurance sector\nTeam player who is detail-minded, service-oriented and has good communications and interpersonal skills\nGood command of spoken and written in English and Chinese. Fluency in Putonghua is preferred\nProficient in MS Office\nExperience in sales and marketing support is preferred\nCandidates with more experience will be considered as Officer/Senior Officer\n\n\nApplications\nInterested parties please send a detailed resume, stating current and expected salary to Human Resources Department.\n\nInformation supplied will be treated in strict confidence and used in accordance with the Personal Data (Privacy) Ordinance.\u00a0 Applicants not invited for interview within 6 weeks may consider their applications unsuccessful.", "employment_types": ["Full Time"], "selling_points": ["Life insurance operations", "Policy servicing support", "Work-life balance enviornment"], "locations": ["Not Specified"], "categories": ["Insurance", "Others"], "post_time": "2022-01-12T10:40:21Z", "salary": {"currency": null, "max": null, "min": null, "period": "monthly", "term": null}, "salary_visible": false, "title_keywords": ["senior officer"], "responsibilities": ["compliance", "monitor", "coordinate with", "quality", "market research", "good relationship", "maintain", "ad hoc projects", "provide assistance", "administrative activities"], "requirements": {"degrees": ["degree", "bachelor"], "majors": [], "languages": ["putonghua", "english", "chinese"], "language_level": ["fluency", "good command"], "hard_skills": ["ms office"], "soft_skills": ["detail-minded", "team player", "interpersonal skills", "service-oriented"], "languages_combined": [{"language": "putonghua", "language_level": ["fluency"]}, {"language": "english", "language_level": ["good command"]}, {"language": "chinese", "language_level": ["good command"]}]}, "experience_required": {"duration": ["1 year"], "field": ["healthcare", "insurance", "marketing"]}}, {"job_id": "100003009042476", "location_code": "hk", "company": "AEON CREDIT SERVICE (ASIA) CO., LTD.", "job_title": "Assistant Manager/ Senior Officer \u2013 Branch Sales (Several openings & locations to select: HK/KLN/NT)", "description": "Responsibilities:\n\nPerform underwriting, provide quotation and handle referrals within delegated authority;\nAssist\u00a0for project management activities;\nParticipate in system development and/ or enhancement related to new product developments;\nClose collaboration with distribution teams to achieve business target;\nMaintain underwriting guideline, rating table, policy/clause wording and respective governance framework.\n\nRequirement:\n\nDegree holder in any discipline with 1-3 years working experience in underwriting or project related experience;\nExperience in SME or Group PA or employee compensation underwriting is preferred;\u00a0\nPositive and can do attitude, solution oriented;\nAnalytical mind, data and fact orientation;\nGood interpersonal and communication skills;\nProficient in spoken and written English and Chinese;\nSelf-motivated, independent, able to work under pressure;\nFamiliar with MS Office applications and good numerical skills.\u00a0\n\nWe offer competitive remuneration package. Interested parties, please send your resume with CURRENT & EXPECTED salary and DATE AVAILABLE by clicking APPLY NOW.\n\n(Data collected would be used for recruitment purpose only)", "employment_types": ["Full Time"], "selling_points": ["Diploma or above in any discipline", "4 years experience in retail/ banking industry", "Willing to work in weekend and public holidays"], "locations": ["Not Specified"], "categories": ["Banking / Finance", "Retail Banking", "Sales, CS & Business Devpt", "Business Development", "Insurance", "Others"], "post_time": "2022-01-12T07:39:25Z", "salary": {"currency": null, "max": null, "min": null, "period": "monthly", "term": null}, "salary_visible": false, "title_keywords": ["assistant manager", "senior officer", "sales"], "responsibilities": ["maintain", "quotation", "teams", "project management activities"], "requirements": {"degrees": ["degree holder"], "majors": [], "languages": ["english", "chinese"], "language_level": ["proficient"], "hard_skills": ["numerical skills", "ms office"], "soft_skills": ["communication skills", "self-motivated", "independent", "analytical mind", "interpersonal", "positive", "work under pressure"], "languages_combined": [{"language": "english", "language_level": ["proficient"]}, {"language": "chinese", "language_level": ["proficient"]}]}, "experience_required": {"duration": ["1-3 years"], "field": ["underwriting", "related"]}}, {"job_id": "100003009048566", "location_code": "hk", "company": "Executive Search", "job_title": "Marketing and Sales Executive (with attractive bonus)", "description": "We\u2019re hiring!\n\nAon is currently recruiting an Account Manager - Claims Services\u00a0to join our team in Hong Kong.\n\nAbout Aon\n\nHeadquartered in London, Aon Plc is a leading global professional services firm providing a broad range of risk, retirement and health solutions. Our 50,000 colleagues in 120 countries empower results for clients by using proprietary data and analytics to deliver insights that reduce volatility and improve performance.\n\nAt Aon, you\u2019ll be part of a team which will support and inspire you and provide the opportunities and resources to develop your skills. It\u2019s an environment which encourages you to achieve your best - together we\u2019ll empower results.\u00a0\n\nResponsibilities:\n\nManage claims for clients, including some with operations on a global scale\nHandle all classes of commercial lines insurance (EC, PDBI, PAR, Motor, PPL, Marine Cargo, CAR, etc.)\nServe internal business units and clients at operational and senior management level requiring liaising and\ncoordinating with insurers and third party services providers such as loss adjusters, rehabilitation managers and\nlawyers and our network offices in different countries\nManage and analyse claims data and advising clients on risk management improvement measures\nDevelop junior claims staff\n\nRequirements:\u00a0\n\nMinimum five years claims handling experience, in insurance broking firm preferred\nIIQE qualified or holder of ACII or ANZIIF (Associate) preferred\nSome supervisory experience is preferable\nTeam work is required whilst being proactive and working independently\nAbility to understand and apply data analysis to risk management issues\nMust be able to work with data and present information in clear manner\nGood command of written and spoken English and Chinese (Cantonese and Putonghua)\nGood computer skills including MS Word, Excel, Powerpoint\n\nHow to Apply\n\nYour opportunity to empower results could start right here. Make your mark and apply online today with a brief covering letter and your resume, sharing relevant achievements for this position.\n\nWe Offer You\n\nA competitive total rewards package, continuing education & training, and tremendous potential with a growing worldwide organization.\n\nOur Colleague Experience\n\nEvery day, our colleagues make a difference, work with the best, own their potential, and value one another. Together, we share this one purpose: to empower economic and human possibility around the world. This unifying goal is at the heart of our identity, and it lives in everything we do. To learn more about our colleague experience, visit Aon Colleague Experience.\n\nAon is an equal opportunities employer. We are committed to creating a winning and inclusive culture where everyone feels valued and has opportunities for growth and development.", "employment_types": ["Full Time", "Permanent"], "selling_points": ["Fun & Dynamic working environment", "Well pay bonus", "Fast growing platform"], "locations": ["Wan Chai"], "categories": ["Media & Advertising", "Others", "Management", "General Management", "Insurance", "Others"], "post_time": "2022-01-14T06:49:00Z", "salary": {"currency": null, "max": null, "min": null, "period": "monthly", "term": null}, "salary_visible": false, "title_keywords": ["sales executive"], "responsibilities": ["rehabilitation", "management", "data", "operations", "develop", "senior management", "insurance", "third party", "analyse"], "requirements": {"degrees": [], "majors": [], "languages": ["cantonese", "putonghua", "english", "chinese"], "language_level": ["good command"], "hard_skills": ["excel", "iiqe", "analysis", "powerpoint", "make", "computer skills", "ms word"], "soft_skills": ["clear", "proactive", "independently"], "languages_combined": [{"language": "cantonese", "language_level": ["good command"]}, {"language": "putonghua", "language_level": ["good command"]}, {"language": "english", "language_level": ["good command"]}, {"language": "chinese", "language_level": ["good command"]}]}, "experience_required": {"duration": ["minimum five years"], "field": ["insurance", "supervisory experience"]}}, {"job_id": "100003009045834", "location_code": "hk", "company": "FTLife Insurance Company Limited", "job_title": "Business Analyst, Strategic Projects, Product Development", "description": "Our client, a well-known MPF company in Hong Kong, is looking for a high caliber to join the group.\n\nSenior Client Service, Pension team\n\nProvide MPF scheme administration support, such as enrollment, contribution, switching and termination (align with all regulatory requirements)\nHandle customers' enquiries and provide possible solutions\u00a0\nPerform clerical duties including data input, scanning and filing\u00a0\u00a0\n\nRequirement:\n\nDiploma or above and at least 1 year working experience is preferred\nMPF knowledge\u00a0\n\nAssociate/Senior Associate \u2013 Fund Services (Fund Accounting & Valuation)\n\nPrepare reports, such as customer reports, internal and financial status.\nReconcile accounts with banks, plans, and people, and ensure that relevant records and entries are updated to the accounting system.\nPrepare accounting entries and expense schedules for plans and funds.\nPrepare an evaluation report to ensure that all transactions and pricing are correctly updated in the accounting system, and calculate the net value of each unit of funds. Handle customers' enquiries and provide possible solutions\n\nRequirement:\n\nForm 6 or above, LCC Higher and preferably university graduate\n1-2 years working experience is also preferable. Candidate with 3 years direct experience will be considered as Senior Associate.\nStrong in MS Excel and MS Word\u00a0\n\nBusiness Development Manager\n\nDevelop business with designated channel partners and prospects referred in establishing and operating their employee retirement scheme\nService selected clients for their pension schemes in compliance with the service standards\nHandle enquiries and complaints from channel partners and clients and acquire a good understanding of client\u2019s needs\nAssist in developing business strategy and implementing business plan and relevant business development activities\nSupport business development functions including project management and product promotion\nProvide support to customer service activities\u00a0\n\nRequirement:\n\nDegree holder\n4 years\u2019 relevant work experience in client services areas within financial institutions\nGood knowledge of MPF and ORSO is an advantage\u00a0\n\nOfficer, Call Center - Inbound\u00a0/ Outbound\n\nHandle MPF & ORSO enquiries through hotlines & emails\nProvide outbound service to promote company product & service\n\nRequirement:\n\nTertiary educated or above\n1-2 years working experience in call center / customer service environment / financial industry.\u00a0\u00a0\u00a0\n\nOthers Position\u00a0\n\nTo apply, please send your detailed resume or contact Ms Tsui at 3955 1358 for a confidential discussion.\nOnly shortlisted candidates will be notified.\u00a0\nApplicants who are not contacted within two weeks may consider their applications unsuccessful.\u00a0\nAll data collected will be used for recruitment purpose only & will be used strictly confidential.\u00a0\n\nConners Consulting Limited\u00a0\n2005 Kai Tak Commercial Building 317 Des Voeux Road Central Hong Kong\nTel: (852) 3996 8090\u00a0\u00a0\u00a0\u00a0\u00a0\u00a0 Website: www.connersconsulting.com", "employment_types": ["Full Time", "Permanent"], "selling_points": ["Analyze business needs and impacts", "Elicit user requirements & work out solutions", "Act as a key liaison between users, IT and vendors"], "locations": ["Ngau Tau Kok"], "categories": ["Insurance", "Others"], "post_time": "2022-01-13T08:52:16Z", "salary": {"currency": null, "max": null, "min": null, "period": null, "term": null}, "salary_visible": false, "title_keywords": ["product development", "business analyst"], "responsibilities": ["consulting", "data", "schedules", "regulatory requirements", "website", "transactions", "service standards", "customer service", "evaluation", "plans", "administration", "scanning", "compliance", "handle enquiries and complaints", "developing", "develop", "reports", "business plan", "report", "valuation", "enrollment", "provide support", "mpf", "reconcile accounts", "contact", "data input", "project management", "recruitment", "prepare reports"], "requirements": {"degrees": ["university graduate", "diploma or above", "degree holder"], "majors": [], "languages": [], "language_level": [], "hard_skills": ["scheme", "project management", "ms excel", "lcc", "accounting system", "ms word"], "soft_skills": ["project management", "customer service", "detailed"], "languages_combined": []}, "experience_required": {"duration": ["3 years", "4 years", "at least 1 year", "1-2 years"], "field": ["financial institutions", "call center", "customer service", "financial industry"]}}, {"job_id": "100003009047684", "location_code": "hk", "company": "PERSOLKELLY Hong Kong Limited", "job_title": "Junior/Senior Financial Operation/Analyst (2-year contract, Insurance industry, 15K-40K)", "description": "Responsibilities:\n\nWork closely with branches/business units to solicit General Insurance business from potential clients\nHandle General Insurance business enquires including product features, terms and conditions from clients referred\nNegotiate terms and conditions with clients and prepare insurance quotations, and follow-up on renewal business\nProvide quality post-sales services to clients\nAssist in ad hoc marketing projects as assigned\n\nRequirements:\n\nPost-secondary education or above, with at least 5 subjects passed in HKCEE/HKDSE, including Chinese, English and Mathematics\nAt least 1 year of sales and marketing experience in General Insurance or Intermediary Company\nFresh graduate who are determined to develop his/her career in General Insurance will also be considered\nPassed in Paper I and II under Insurance Intermediaries Qualifying Examination (IIQE) preferred\nHolder of ANZIIF preferred\nBasic knowledge of General Insurance products\nSelf-motivated, sales driven and client focused\nGood people and problem-solving skills\n\nAttractive remuneration package will be offered to the right candidates. Interested parties please click \"Apply Now\" to submit your full resume with current and expected salary to the Human Resources Division.\n\nPlease visit us at www.shacombank.com.hk for more information about our Bank.\n\nAll personal data collected will be used for recruitment related purposes strictly in accordance with the Bank's personal data policies, a copy of which will be provided immediately upon request by contacting our Personal Data Compliance Officer. Applicants who are not contacted within two months may consider their applications unsuccessful and the personal data collected from the applicants will be retained for no longer than two years from the date of rejection during which the applicants may be considered for other suitable positions within the Bank.", "employment_types": ["Full Time", "Contract"], "selling_points": ["Great career path", "Less experience will consider as Officer/Analyst", "Welcome insurance and banking background"], "locations": ["Kowloon Bay"], "categories": ["Banking / Finance", "Financial Services", "Insurance", "Others"], "post_time": "2022-01-14T03:44:51Z", "salary": {"currency": null, "max": null, "min": null, "period": "monthly", "term": null}, "salary_visible": false, "title_keywords": ["analyst", "junior"], "responsibilities": ["ad hoc", "insurance", "quality", "marketing projects"], "requirements": {"degrees": ["hkdse", "secondary education", "fresh graduate"], "majors": ["mathematics", "insurance"], "languages": ["english", "chinese"], "language_level": [], "hard_skills": ["problem-solving skills", "iiqe", "basic"], "soft_skills": ["self-motivated", "determined", "focused", "problem-solving skills", "driven"], "languages_combined": [{"language": "english", "language_level": []}, {"language": "chinese", "language_level": []}]}, "experience_required": {"duration": ["at least 1 year"], "field": ["general insurance", "marketing"]}}, {"job_id": "100003009054110", "location_code": "hk", "company": "Manulife (International) Limited", "job_title": "\u5f37\u7a4d\u91d1\u5c08\u54e1 MPF Services Assistant (5 DAYS 20K-35K)", "description": "About the Client\n\nMy client is a major life insurance company providing Insurance, investment, and retirement to MPF solutions for customers in Hong Kong and Macau.\u00a0\n\nThey hire now seeking a high-performing Legal and Compliance Manager/ Assistant Manager specializing in Anti-Money Laundering (AML) to cope with their business expansion in 2022.\n\nAbout the Position\n\n\u00a0 \u00a0 \u00a0 \u00a0 \u00a0 Reporting to the Head of Legal and Compliance, you would be responsible for AML regulatory compliance issues of the company\n\u00a0\u00a0\u00a0\u00a0\u00a0\u00a0\u00a0\u00a0\u00a0 Review and develop AML policies and procedures\n\u00a0\u00a0\u00a0\u00a0\u00a0\u00a0\u00a0\u00a0\u00a0 Handle daily AML regulatory compliance matters\n\u00a0\u00a0\u00a0\u00a0\u00a0\u00a0\u00a0\u00a0\u00a0 Conduct compliance reviews and trainings as well as providing appropriate and relevant compliance advice to different departments\n\nAbout YOU\n\n\u00a0\u00a0\u00a0\u00a0\u00a0\u00a0\u00a0\u00a0\u00a0 6+ years of experience in AML and Insurance industry\n\u00a0\u00a0\u00a0\u00a0\u00a0\u00a0\u00a0\u00a0\u00a0 Bachelor Degree holder\n\u00a0\u00a0\u00a0\u00a0\u00a0\u00a0\u00a0\u00a0\u00a0 Good command of written and oral English, Cantonese and Mandarin\n\u00a0\u00a0\u00a0\u00a0\u00a0\u00a0\u00a0\u00a0\u00a0 Detail oriented with good self-initiative and interpersonal skills\u00a0 \u00a0\n\u00a0 \u00a0 \u00a0 \u00a0 \u00a0 Open to considering Manager or Assistant Manager grade", "employment_types": ["Full Time", "Permanent"], "selling_points": ["Banking", "5 Days", "Fresh graduate"], "locations": ["Kwun Tong"], "categories": ["Banking / Finance", "Financial Services", "Insurance", "Others", "Others", "Others"], "post_time": "2022-01-17T08:25:14Z", "salary": {"currency": "HKD", "max": 29999, "min": 14000, "period": "monthly", "term": null}, "salary_visible": true, "title_keywords": ["\u5f37\u7a4d\u91d1\u5c08\u54e1", "assistant"], "responsibilities": ["reporting", "aml", "mpf", "policies", "compliance", "review", "procedures", "develop", "insurance"], "requirements": {"degrees": ["bachelor degree holder"], "majors": [], "languages": ["cantonese", "english", "mandarin"], "language_level": ["good command"], "hard_skills": ["aml", "anti-money laundering"], "soft_skills": ["oral", "responsible", "detail oriented", "self-initiative", "interpersonal skills"], "languages_combined": [{"language": "cantonese", "language_level": ["good command"]}, {"language": "english", "language_level": ["good command"]}, {"language": "mandarin", "language_level": ["good command"]}]}, "experience_required": {"duration": ["6+ years"], "field": ["insurance industry"]}}, {"job_id": "100003009048313", "location_code": "hk", "company": "Bank of China Group Insurance Company Limited", "job_title": "Assistant Underwriting Manager - Property Lines", "description": "My client is looking for an insurance operations talent to join their operations team. This role will be handling job duties across policy administration, customer service and backend support.\n\nJob description:\n\nDesign and conduct content management of all customer correspondence and service form in fulfilling business and regulatory requirements\nCoordinate with business stakeholders for designing, reviewing and approving process of the materials to ensure timely completion in various business processes\nExplore improvement and transformations opportunities for the overall printing and designing operations\nsupport system testing and successful implementation on realted processess\nFacilitates timely and accurate management information reports\nRequirements:\n\n3 years of experience in life insurance operations, i.e. new business, policy servicing or customer service etc.\nKnowledge of Chinese word processing and editorial\u00a0\nExperience in Software applications, e.g. Adobe Acrobat Professional, Photoshop, Illustrator is a plus\nExcellent communication and be able to work across multiple stakeholders\nGood command of written and spoken English\u00a0\nA team player, energy and drive with a positive attitude\n\n\nFor interesting parties, please click Apply Now.", "employment_types": ["Full Time", "Permanent"], "selling_points": [], "locations": ["Central"], "categories": ["Insurance", "Insurance Agent / Broker", "Underwriter", "Others"], "post_time": "2022-01-14T06:13:03Z", "salary": {"currency": null, "max": null, "min": null, "period": null, "term": null}, "salary_visible": false, "title_keywords": ["manager", "assistant"], "responsibilities": ["management", "regulatory requirements", "operations", "coordinate with", "implementation", "design", "testing", "reports", "designing"], "requirements": {"degrees": [], "majors": [], "languages": ["english", "chinese"], "language_level": ["good command"], "hard_skills": ["plus", "chinese word processing", "illustrator", "adobe acrobat", "photoshop"], "soft_skills": ["communication", "positive attitude", "team player", "customer service"], "languages_combined": [{"language": "english", "language_level": ["good command"]}, {"language": "chinese", "language_level": []}]}, "experience_required": {"duration": ["3 years"], "field": ["insurance"]}}, {"job_id": "100003009049018", "location_code": "hk", "company": "Cornerstone Global Partners", "job_title": "Agency Management - Business Development Analyst (Major Life Insurer, EB/Pension,  Up to 30K)", "description": "Job Description\n\nHandle insurance policy administration works and documentation\nMaintain accurate records and storage\nPerform clerical support such as data inputting, filing and scanning\nAssist in any ad-hoc tasks or duties as requested\n\nRequirements:\u00a0\n\nHKCEE /DSE or above\nAt least 2 years of relevant work experience, applicant with general insurance experience will be advantage\nIIQE Paper 1 & 2 qualification preferred\nSelf-starter, team player and attentive to details\nStrong analytical skills and good at PC applications (i.e. MS Office)\nStrong communication and customer service skills;\nGood command of spoken and written English and Chinese\nImmediate available is preferred\n\nPlease apply in confidence with full resume, current and expected salary, date of availability in the subject line and clicking \u201cApply Now\u201d.\n\n\n\n", "employment_types": ["Full Time"], "selling_points": ["Agency Management/Business Development", "EB/Pension", "Major Life Insurer"], "locations": ["Not Specified"], "categories": ["Insurance", "Insurance Agent / Broker", "Underwriter", "Others"], "post_time": "2022-01-14T07:55:40Z", "salary": {"currency": null, "max": null, "min": null, "period": "monthly", "term": null}, "salary_visible": false, "title_keywords": ["business development analyst"], "responsibilities": ["scanning", "data", "ad-hoc tasks", "clerical support", "maintain", "documentation", "insurance", "administration"], "requirements": {"degrees": ["dse"], "majors": [], "languages": ["english", "chinese"], "language_level": ["good command"], "hard_skills": ["iiqe paper", "pc applications", "ms office", "analytical skills"], "soft_skills": ["customer service skills", "confidence", "attentive to details", "analytical skills", "communication", "team player"], "languages_combined": [{"language": "english", "language_level": ["good command"]}, {"language": "chinese", "language_level": ["good command"]}]}, "experience_required": {"duration": ["at least 2 years"], "field": ["general insurance"]}}, {"job_id": "100003009034186", "location_code": "hk", "company": "Inter Partner Assistance Hong Kong Limited", "job_title": "Administration Officer, TPA", "description": "Responsibilities:\n\nWork closely with branches/business units to solicit General Insurance business from potential clients\nHandle General Insurance business enquiries including product features, terms and conditions from clients\nNegotiate terms and conditions with clients and prepare insurance quotations, and follow-up on renewal business\nProvide quality post-sales services to clients\nAssist in ad hoc marketing projects as assigned\n\nRequirements:\n\nPost-secondary education or above, with at least 5 subjects passed in HKCEE/HKDSE, including Chinese, English and Mathematics\nAt least 3 years of sales and marketing experience in General Insurance or Intermediary Company\nPassed in Paper I and II under Insurance Intermediaries Qualifying Examination (IIQE) preferred\nHolder of ACII or ANZIIF preferred\nSound knowledge of General Insurance products\nGood understanding of market trend in General Insurance industry\nSelf-motivated, sales driven and client focused\nGood people and problem-solving skills\nCandidate with less experience would be considered for the position of Officer, Business Development\n\nAttractive remuneration package will be offered to the right candidates. Interested parties please click\u00a0\"Apply Now\"\u00a0to submit your full resume with current and expected salary to the\u00a0Human Resources Division.\n\nPlease visit us at\u00a0www.shacombank.com.hk\u00a0for more information about our Bank.\n\nAll personal data collected will be used for recruitment related purposes strictly in accordance with the Bank's personal data policies, a copy of which will be provided immediately upon request by contacting our Personal Data Compliance Officer. Applicants who are not contacted within two months may consider their applications unsuccessful and the personal data collected from the applicants will be retained for no longer than two years from the date of rejection during which the applicants may be considered for other suitable positions within the Bank.", "employment_types": ["Full Time", "Permanent"], "selling_points": ["Friendly working environment", "Good starts in MNC, 5 days work a week", "New graduates welcome, well pay"], "locations": ["Kwun Tong"], "categories": ["Admin & HR", "Clerical / Admin Staff", "Insurance", "Others", "Others", "Student / Fresh Graduate / No Experience"], "post_time": "2022-01-10T02:55:03Z", "salary": {"currency": null, "max": null, "min": null, "period": "monthly", "term": null}, "salary_visible": false, "title_keywords": ["administration officer"], "responsibilities": ["ad hoc", "insurance", "quality", "marketing projects"], "requirements": {"degrees": ["hkdse", "secondary education"], "majors": ["mathematics"], "languages": ["english", "chinese"], "language_level": [], "hard_skills": ["problem-solving skills", "iiqe"], "soft_skills": ["problem-solving skills", "self-motivated", "driven", "focused"], "languages_combined": [{"language": "english", "language_level": []}, {"language": "chinese", "language_level": []}]}, "experience_required": {"duration": ["at least 3 years"], "field": ["general insurance", "marketing", "business development"]}}, {"job_id": "100003009043774", "location_code": "hk", "company": "Zurich Insurance (Hong Kong)", "job_title": "Customer Care Consultant (General Insurance)", "description": "Responsibilities:\n\nPerform underwriting, provide quotation and handle referrals within delegated authority;\nAssist\u00a0for project management activities;\nParticipate in system development and/ or enhancement related to new product developments;\nClose collaboration with distribution teams to achieve business target;\nMaintain underwriting guideline, rating table, policy/clause wording and respective governance framework.\n\nRequirement:\n\nDegree holder in any discipline with 3+ years working experience in underwriting or project related experience;\nExperience in underwriting property lines is preferred\nPositive and can do attitude, solution oriented;\nAnalytical mind, data and fact orientation;\nGood interpersonal and communication skills;\nProficient in spoken and written English and Chinese;\nSelf-motivated, independent, able to work under pressure;\nFamiliar with MS Office applications and good numerical skills.\n\nCandidate with less experience will be considered\n\nWe offer competitive remuneration package. Interested parties, please send your resume with CURRENT & EXPECTED salary and DATE AVAILABLE by clicking APPLY NOW.\n\n(Data collected would be used for recruitment purpose only)", "employment_types": ["Full Time", "Permanent"], "selling_points": ["Handle customer enquiries and complaints", "Provide quality service to customers", "IIQE Paper 1 and 2"], "locations": ["Quarry Bay"], "categories": ["Banking / Finance", "Others", "Sales, CS & Business Devpt", "Customer Service - Supervisor / Officer", "Insurance", "Others"], "post_time": "2022-01-13T01:55:06Z", "salary": {"currency": null, "max": null, "min": null, "period": "monthly", "term": null}, "salary_visible": false, "title_keywords": ["consultant"], "responsibilities": ["maintain", "quotation", "teams", "project management activities"], "requirements": {"degrees": ["degree holder"], "majors": [], "languages": ["english", "chinese"], "language_level": ["proficient"], "hard_skills": ["numerical skills", "ms office"], "soft_skills": ["communication skills", "self-motivated", "independent", "analytical mind", "interpersonal", "positive", "work under pressure"], "languages_combined": [{"language": "english", "language_level": ["proficient"]}, {"language": "chinese", "language_level": ["proficient"]}]}, "experience_required": {"duration": ["3+ years"], "field": ["underwriting", "related"]}}, {"job_id": "100003009033980", "location_code": "hk", "company": "The People's Insurance Co of China (HK), Ltd", "job_title": "Staff of Policy Administration", "description": "Reporting to Senior Manager, Internal Audit, assist to perform risk-based internal audits to safeguard the Group from significant risks.\n\nResponsibilities:\n\nAssist to perform risk-based internal audits of the Group through the collaborating with the other business units\nHelp to evaluate the control efficiency and effectiveness\nPrepare clear and concise audit documentation, including drafting audit findings and recommendations for Senior Manager\u2019s further review\nFollow up on the implementation progress of audit recommendations\nPerform ad-hoc projects/duties whenever assigned\n\nRequirements:\n\nBachelor\u2019s degree holder of accounting or equivalent\nHolder or finalist of professional qualification, e.g. CPA, CIA, CISA\nAt least 5 years of relevant internal audit experience\nGood interpersonal skill, be self-initiative and well-organized\nProficiency in MS Applications such as Word, Excel, PowerPoint\nWe offer competitive remuneration including career prospects to the right candidate. Interested parties please send detailed resume with availability, current and expected salaries to\u00a0Human Resources Department, Convoy Global Holdings Limited, Trust Tower, 68 Johnston Road, Wan Chai, Hong Kong\u00a0or by clicking the\u00a0Apply Now\u00a0button and upload your CV and cover letter.\n(All applications will be treated in strict confidence and used for recruitment purpose within Convoy Global Holdings Limited only. All applicants are kept on file 6 months from the date of the application.)", "employment_types": ["Full Time"], "selling_points": [], "locations": ["Sheung Wan"], "categories": ["Insurance", "Others"], "post_time": "2022-01-10T02:20:01Z", "salary": {"currency": null, "max": null, "min": null, "period": "monthly", "term": null}, "salary_visible": false, "title_keywords": ["staff"], "responsibilities": ["control", "documentation", "review", "audit", "implementation", "evaluate", "audits", "ad-hoc projects"], "requirements": {"degrees": ["bachelor", "degree holder"], "majors": ["accounting"], "languages": [], "language_level": [], "hard_skills": ["excel", "ms applications", "word", "powerpoint", "cpa"], "soft_skills": ["self-initiative", "well-organized", "interpersonal skill"], "languages_combined": []}, "experience_required": {"duration": ["at least 5 years"], "field": ["audit experience"]}}, {"job_id": "100003009045730", "location_code": "hk", "company": "AXA Hong Kong", "job_title": "Senior Product Officer", "description": "Job Duties:\n- Handling all HR activities while mainly focusing on recruitment & selection\n- Handling compensation & benefits and any other HR initiatives as required\n- Provide HR support on staff-related issues\n- Assist in reviewing or formulating HR strategies, policies, and procedures\n- Prepare reports and analysis for management review\n- Handle ad-hoc projects as assigned\n\nRequirements:\n- Diploma or above in Human Resources Management or related disciplines\n- Minimum 1 year\u2019 relevant experience\n- Good command of computer knowledge, proficient in MS Office and Chinese Word Processing\n- Good interpersonal skills, detail-oriented, willing to learn, and able to work under pressure\n- Better to have IIQE licenses 1 & 3 after on board", "employment_types": ["Full Time", "Permanent"], "selling_points": ["Corporate role in AXA", "Health and Employee Benefits Business", "Product Development"], "locations": ["Southern Area"], "categories": ["Insurance", "Others"], "post_time": "2022-01-13T08:27:54Z", "salary": {"currency": null, "max": null, "min": null, "period": "monthly", "term": null}, "salary_visible": false, "title_keywords": ["officer"], "responsibilities": ["hr", "recruitment"], "requirements": {"degrees": [], "majors": [], "languages": [], "language_level": [], "hard_skills": [], "soft_skills": [], "languages_combined": []}, "experience_required": {"duration": [], "field": []}}, {"job_id": "100003009043484", "location_code": "hk", "company": "Insurance Authority", "job_title": "Assistant Manager (Long Term Business \u2013 Group-wide Supervision)", "description": "Job Purpose:\n\n\nAssist and support Customer Service Hotline team to deliver excellent service to our Internal and external customers\nAnswering various types of enquiries via hotline on policy information, policy change and claims submission etc.\nProvide support to Customer Service Centre for walk-in clients when necessary\n\n\u00a0Job Responsibilities:\n\nHandle customer/salesperson enquiries from different Hotlines in professional manner to achieve service excellence\nFollow guidelines to protect customers\u2019 privacy by verifying callers\u2019 personal information\nArrange follow-up calls to customer/salesperson when necessary or assigned by supervisor\nMaintain and improves quality results by adhering to standards and guidelines\nUpdate job knowledge by studying new product description and other materials\nManage and resolve customer complaints\nDocument all call information in the Customer Service Logging System\nPerform ad-hoc task as required\n\nJob\u00a0Requirements:\n\nF.7 or above and passed in IIQE 1,3,5 with at least 2 years relevant working experience\nGood spoken and writing in both English and Chinese (Mandarin and Cantonese)\nCareful mindset, patient, pleasant, good telephone manner and interpersonal skills\nCustomer-oriented with passion and caring attitude\nHands on PC skills including Chinese word processing\nExperience in working in Customer Services of life insurance company is an advantage\nAble to work on weekend", "employment_types": ["Full Time", "Permanent"], "selling_points": [], "locations": ["Southern Area"], "categories": ["Accounting", "Audit", "Insurance", "Others", "Public / Civil", "Others"], "post_time": "2022-01-12T13:52:44Z", "salary": {"currency": null, "max": null, "min": null, "period": "monthly", "term": null}, "salary_visible": false, "title_keywords": ["assistant manager"], "responsibilities": ["ad-hoc", "customer service logging system", "resolve customer complaints", "guidelines", "protect customers\u2019 privacy", "professional manner", "quality", "maintain", "follow-up calls"], "requirements": {"degrees": [], "majors": [], "languages": ["cantonese", "english", "chinese", "mandarin"], "language_level": ["good"], "hard_skills": ["iiqe", "pc skills", "chinese word processing"], "soft_skills": ["careful", "pleasant", "customer-oriented", "hands on", "interpersonal skills", "patient", "telephone manner"], "languages_combined": [{"language": "cantonese", "language_level": ["good"]}, {"language": "english", "language_level": ["good"]}, {"language": "chinese", "language_level": ["good"]}, {"language": "mandarin", "language_level": ["good"]}]}, "experience_required": {"duration": ["at least 2 years"], "field": ["life insurance company", "relevant working experience", "customer services"]}}, {"job_id": "100003009037614", "location_code": "hk", "company": "BUPA Asia Limited", "job_title": "Telemarketing Consultant, Medical Insurance", "description": "Responsibilities\n\nMonitor outstanding balance, chasing overdue balance and handle debt settlement\nLiaise with multiple parties \u2013 such as insurance company, staffs from other departments and patient\nPerform daily accounting duties for both AP and AR\nPrepare monthly statements to insurance companies and corporate clients\nHandle all insurance enquiries and coordinate with clients\u00a0\nPerform any data entry and ad hoc tasks as assigned\n\nRequirement\n\nUniversity Graduate, Degree in Accounting be a plus\n1 to 2 years\u2019 experience will be preferable;\nDetailed minded and a Team player\nFluency in English and proficiency in Chinese\nGood communication and interpersonal skills to different parties such as insurance company, staffs from other department and patients\nWilling to learn, while solving different problems\nAdaptive to environment while able to propose improvements to existing operation\nMore experienced will be considered as Account Officer\n\nPlease apply in confidence with full resume, expected salary and availability to the Human Resources Department, OT&P by emailing us via\u00a0 projob@ otandp.com\u00a0or\u00a0 by clicking \u201cApply Now\u201d button.\n\nThe information provided will be used for selection purpose only. All information of unsuccessful applicants will be destroyed within six months.", "employment_types": ["Full Time", "Permanent"], "selling_points": ["Monday to Friday, shift time between 9am - 7pm", "IIQE license holder (Paper 1 & 2)", "No cold calls, referral leads only"], "locations": ["Not Specified"], "categories": ["Insurance", "Others", "Sales, CS & Business Devpt", "Tele-sales (Telemarketing)", "Direct Sales"], "post_time": "2022-01-11T03:18:02Z", "salary": {"currency": null, "max": null, "min": null, "period": "monthly", "term": null}, "salary_visible": false, "title_keywords": ["consultant", "telemarketing"], "responsibilities": ["ap", "ar", "data entry", "monitor", "ad hoc tasks", "coordinate with clients", "liaise with", "daily accounting", "insurance"], "requirements": {"degrees": ["university graduate", "degree"], "majors": ["accounting"], "languages": ["english", "chinese"], "language_level": ["fluency", "proficiency"], "hard_skills": ["plus"], "soft_skills": ["confidence", "willing to learn", "communication and interpersonal skills", "team player", "detailed"], "languages_combined": [{"language": "english", "language_level": ["fluency", "proficiency"]}, {"language": "chinese", "language_level": []}]}, "experience_required": {"duration": ["1 to 2 years"], "field": []}}, {"job_id": "100003009048359", "location_code": "hk", "company": "Bank of China Group Insurance Company Limited", "job_title": "Actuarial Analyst", "description": "Responsibilities\n\nTo provide back-up service to the Marketing Manager of the company\n\nTo handle general enquiries from client\n\nTo provide insurance service to individual &/or corporate clients\n\nTo present quotations to clients and provides assistance to clients in the event of claim\nTake up any ad hoc projects and tasks and when assigned by the supervisor\n\nRequirements\n\nPost-secondary education level with at least 2 years' solid experience in general insurance field\n\nPass in IIQE Licensing Examination\nProficiency in MS Office applications\nSelf-motivated, positive and flexible\n\nNice and helpful personality\n\nTeam player with good customer service and good interpersonal skills\n\nGood communication skills, well organized, proactive and able to work under pressure\n\nPlease apply with full resume and expected salary to Fax: 2231-0399 / E-mail by clicking \"Apply Now\".\u00a0 For enquiry, please contact Ms. Lee on 2231-0333.\n\nAll information provided by applicants will be treated in strictest confidence, will be used solely for recruitment purposes and strictly in accordance with our personal data policy.\u00a0\u00a0 Storfield will retain all applications no longer than 6 months of which will be destroyed thereafter.", "employment_types": ["Full Time", "Permanent"], "selling_points": [], "locations": ["Central"], "categories": ["Insurance", "Actuarial", "Underwriter", "Others"], "post_time": "2022-01-14T06:25:15Z", "salary": {"currency": null, "max": null, "min": null, "period": null, "term": null}, "salary_visible": false, "title_keywords": ["actuarial analyst"], "responsibilities": ["insurance", "ad hoc projects"], "requirements": {"degrees": ["secondary education"], "majors": ["insurance"], "languages": [], "language_level": [], "hard_skills": ["no", "iiqe", "nice", "ms office"], "soft_skills": ["flexible", "communication skills", "self-motivated", "confidence", "well organized", "customer service", "interpersonal skills", "team player", "proactive", "positive", "work under pressure"], "languages_combined": []}, "experience_required": {"duration": ["at least 2 years"], "field": ["general insurance", "education"]}}, {"job_id": "100003009041425", "location_code": "hk", "company": "Ahan Thai", "job_title": "\u897f\u6cf0\u83dc\u9910\u5ef3\u98f2\u54c1\u6c96\u8abf\u54e1", "description": "Responsibilities:\n\nAssists in preparing policy and endorsements;\nAssist in document sorting and filling, quality checking, policy binding;\nHandling internal enquiry in daily inward business\nTo able to work independently and under pressure, detail-oriented and self-motivated;\nTo perform ad-hoc assignment as required;\nAssist in ad hoc UATs and assignments.\n\nRequirements:\n\nBachelor\u2019s degree holder in any discipline;\nMin. 1-2 years in policy administration in insurance company and reinsurance working experience is preferred;\nMature, self-motivated, positive and strong personal drive;\nGood command of spoken and written English and Chinese;\nProficient in MS Office Applications such as Excel, Word and PowerPoint.\n\nWe offer competitive salary, 5-day work week, provident fund and medical benefits.\nIf you are interested in building a career with PICC, please send your resume in both English and Chinese with expected salary.\nAll information provided by applicants will be treated in strict confidence for recruitment-related purposes of PICC (HK).", "employment_types": ["Full Time"], "selling_points": [], "locations": ["Kwun Tong"], "categories": ["Professional Services", "Business Consultancy", "Insurance", "Others", "Others", "Student / Fresh Graduate / No Experience"], "post_time": "2022-01-12T03:52:58Z", "salary": {"currency": null, "max": null, "min": null, "period": "monthly", "term": null}, "salary_visible": false, "title_keywords": [], "responsibilities": ["ad-hoc", "quality checking", "ad hoc"], "requirements": {"degrees": ["bachelor", "degree holder"], "majors": [], "languages": ["english", "chinese"], "language_level": ["good command"], "hard_skills": ["excel", "word", "powerpoint", "ms office"], "soft_skills": ["self-motivated", "positive", "mature"], "languages_combined": [{"language": "english", "language_level": ["good command"]}, {"language": "chinese", "language_level": ["good command"]}]}, "experience_required": {"duration": ["1-2 years"], "field": ["insurance", "policy administration"]}}, {"job_id": "100003009042357", "location_code": "hk", "company": "BUPA Asia Limited", "job_title": "Manager, Business Development", "description": "Job Responsibilities:\n\nAssist in risk management and perform advisory assignments;\nAssist in prepare regular reporting on capital, local solvency, ORSA and HKRBC etc.;\nConduct comprehensive data analysis, provide accurate results during reporting and forecasts;\nHandle ad-hoc projects and other duties as required.\n\nJob Requirements:\n\nBachelor Degree in Actuarial Science, Finance, Risk Management, Mathematics or Statistics, or related disciplines;\nProficient in MS Office and computer programming;\n1-2 years actuarial experience;\nGood analytical skills;\nGood communication and interpersonal competencies;\nAttention to details;\nWilling to work under pressure and deadlines.\n\n\n\n\u00a0We offer competitive remuneration package. Interested parties, please send your resume with CURRENT & EXPECTED salary and DATE AVAILABLE by clicking 'Apply Now'.\n\n(Data collected would be used for recruitment purpose only)", "employment_types": ["Full Time", "Permanent"], "selling_points": ["Experience in leading a sales team", "Sales strategy for intermediaries / direct clients", "Achieve persistency targets"], "locations": ["Not Specified"], "categories": ["Sales, CS & Business Devpt", "Business Development", "Insurance", "Others", "Sales - Sales Management"], "post_time": "2022-01-12T07:10:26Z", "salary": {"currency": null, "max": null, "min": null, "period": "monthly", "term": null}, "salary_visible": false, "title_keywords": ["manager"], "responsibilities": ["reporting", "management", "other duties", "data analysis", "ad-hoc projects"], "requirements": {"degrees": ["degree", "bachelor"], "majors": ["mathematics", "risk management", "actuarial science", "finance", "statistics", "related disciplines"], "languages": [], "language_level": [], "hard_skills": ["analytical skills", "programming", "ms office"], "soft_skills": ["analytical skills", "communication", "attention to details", "interpersonal", "work under pressure"], "languages_combined": []}, "experience_required": {"duration": ["1-2 years"], "field": []}}, {"job_id": "100003009037910", "location_code": "hk", "company": "Manulife (International) Limited", "job_title": "Senior Customer Service Officer", "description": "RESPONSIBILITIES:\n\n\nHandle all classes of Insurance (individual and commercial insurance, EC, motor, medical, travel etc)\nObtain and negotiate insurance terms with insurers and prepare quotations\nAnswer customer inquiries\nPrepare insurance renewal\nHandle any ad hoc assignments\n\nREQUIREMENTS:\n\nDSE & above\n2 years working experience, in insurance industry would be an advantage\nPassing IIQE Paper 1 & 2 would be highly preferred\nGood organizational skill and able to work independent\nGood written and spoken skills in English and Chinese\nKnowledge in Microsoft Word / Excel is preferable\u00a0\n\nOUR OFFER:\n\n15 Days annual leave\nBirthday Leave\nDiscretionary Bonus\nEmployer MPF Contribution 6%\nLife & Medical Insurance\nMarriage Leave and Paternity Leave\nTraining and Development Programs\nWork Life Balance\nEmployee Wellness Programs and Staff Discount\nFor more information about our company, please visit\nwww.jebsen-insurance.com\nwww.mfjebsen.com\n\nInterested parties please send full resume with\u00a0available date,\u00a0current & expected salary\u00a0to Group Human Resources Department by clicking \u201cApply Now\u201d\n\nAll information provided by applicants will be treated in strictly confidential and used only for recruitment purposes. Applicants may be considered for other suitable positions by our Company not more than three months, after which their personal data will be destroyed.", "employment_types": ["Full Time"], "selling_points": ["Mature and pleasant personality", "You obsess about customers, listen, engage", "You do what is right, work with integrity"], "locations": ["Kwun Tong Area"], "categories": ["Sales, CS & Business Devpt", "Customer Service - Supervisor / Officer", "Insurance", "Others", "Others"], "post_time": "2022-01-11T04:13:17Z", "salary": {"currency": null, "max": null, "min": null, "period": "monthly", "term": null}, "salary_visible": false, "title_keywords": ["senior customer service officer"], "responsibilities": ["insurance", "ad hoc assignments", "customer inquiries"], "requirements": {"degrees": ["dse"], "majors": [], "languages": ["english", "chinese"], "language_level": ["good"], "hard_skills": ["iiqe paper", "excel", "microsoft word"], "soft_skills": ["independent", "organizational skill"], "languages_combined": [{"language": "english", "language_level": ["good"]}, {"language": "chinese", "language_level": ["good"]}]}, "experience_required": {"duration": ["2 years"], "field": ["insurance industry"]}}, {"job_id": "100003009038250", "location_code": "hk", "company": "Hong Kong Life Insurance Limited", "job_title": "Project Officer / Senior Project Officer, Life Operations", "description": "\u00a0Responsibilities\n\u00a0\nTo manage jumbo size contracts - to achieve persistency targets in pursuit of the most favorable terms and profitability to the company\nAssist to develop and maintain a sales strategy and business plan for intermediaries and direct clients. Use the business plan as a roadmap for setting/developing sales goals.\nCommunicate the agreed sales strategy to the sales team clearly and effectively\nTo serve agents/brokers/direct customers and maintain good relationship with them aiming to build up a strong customer base\nTo identify business opportunities and generate potential sales enquiries for new business team.\nTo prepare proposals and presentation materials.\nTo handle enquiries and complaints.\nTo update management the business status through sales report.\nTo collect market intelligence on competitors\u2019 activities including competitors\u2019 products, pricing, catalogues, selling tactics, etc.\nTo develop and review marketing materials, e.g., training materials, staff briefing materials, etc.\nTo perform underwriting according to the Company\u2019s guidelines and within authorized limits\n\n\u00a0Qualifications, Training and Experience\n\nBachelor degree in business or equivalent with 10 \u2013 12 years\u2019 solid on the job experience including experience in expanding relationships and driving sales in new channels (experience in medical insurance business is preferred)\nPossess valid general insurance license\nSignificant management experience in leading a sales team\nStrong relationship with intermediaries\nCustomer-centric\nStrong interpersonal and influencing skills\nGood communication and presentation skills\nProven leadership skills and possess qualities of sound judgement\nSelf-motivated and result-oriented\nProficiency in both written and spoken English and Chinese\nComputer literacy in the use of MS Office\n\nBupa offers 5 days\u2019 work per week and comprehensive remuneration packages including base salary, study assistance plan, company pension plan, life and medical benefit, dental benefit, annual leave, examination leave, etc.\n\n\nBupa is an equal opportunity employer and welcomes applications from qualified candidates. Information provided will be treated in strict confidence and only be used for consideration of application with Bupa.\n\nPersonal data collected will be used for recruitment purposes only. Only candidates selected for interviews will be contacted. Bupa will be in touch for any opportunities that matches your profile. All personal data of unsuccessful application will be destroyed 24 months from the date of receiving the application.", "employment_types": ["Full Time", "Permanent"], "selling_points": ["Minimum 1 year exp. in insurance / banking field", "Assist in driving projects", "More exp. will be considered as Senior Officer"], "locations": ["Sheung Wan"], "categories": ["Insurance", "Others"], "post_time": "2022-01-11T06:20:38Z", "salary": {"currency": null, "max": null, "min": null, "period": "monthly", "term": null}, "salary_visible": false, "title_keywords": ["operations", "project officer", "senior project officer"], "responsibilities": ["communication", "maintain", "plan", "personal data", "sales report", "contracts", "developing", "handle enquiries and complaints", "develop", "maintain good relationship", "business plan", "management", "review", "identify business opportunities", "guidelines", "sales team", "recruitment", "marketing materials", "insurance"], "requirements": {"degrees": ["degree", "bachelor"], "majors": ["business", "insurance"], "languages": ["english", "chinese"], "language_level": ["proficiency"], "hard_skills": ["ms office"], "soft_skills": ["result-oriented", "self-motivated", "confidence", "leadership skills", "presentation", "communication", "computer literacy", "presentation skills", "comprehensive", "interpersonal"], "languages_combined": [{"language": "english", "language_level": ["proficiency"]}, {"language": "chinese", "language_level": ["proficiency"]}]}, "experience_required": {"duration": ["12 years"], "field": ["management", "training", "business", "team", "insurance", "medical"]}}, {"job_id": "100003009046449", "location_code": "hk", "company": "Page Group Hong Kong", "job_title": "Data Administration Analyst - MNC Insurance Co.", "description": "\u00a0Responsibilities:\n\nProvide administrative assistance in the delivery of claims service for the Property & Casualty Insurance claims team\nMaintain daily operations of the team to ensure consistent, accurate and fair claims processing in a high level of integrity\nDetermine proper policy coverage to conclude, investigate, evaluate and negotiate assigned cases\nHandle cases involving litigation and direct settlement\nUpkeep the claim status and undertake periodical reviews\nHandle claims related enquiries and provide support to Claims Managers in preparing management report and statistics\nProvide ad-hoc administrative support to the department as assigned\nCoordinate and participate in UAT activities such as preparation of test plan, test cases, pre-UAT quality check, \u00a0monitoring of bug fixing, retest progress, UAT reports and post implementation monitoring\n\nQualifications:\n\nHigher Diploma/Tertiary educated with at least 4 years of relevant working experience\nPrevious exposure in the General Insurance industry is a definite advantage.\nExperience in a claims administrative role or policy administration activities would be preferred.\nGood communication and interpersonal skills.\nGood supervisory skills, strong career mind and enthusiastic about job\u00a0\nProficiency in computer skills, including MS Word, Excel and PowerPoint.\nCustomer-oriented, attentive to details and able to meet tight deadlines.\nGood command of spoken and written English and Chinese\n\nInterested candidates, please email us your full resume with current and expected remuneration package & available date.\n\nOnly shortlisted candidates will be notified. All data collected will be treated in strict confidentiality and used for recruitment purpose only. Personal data of unsuccessful applicants will be destroyed within 24 months", "employment_types": ["Full Time", "Permanent"], "selling_points": ["Basic in Python/VBA/SQL is sufficient", "Insurance experience a definite plus", "Open to insurance candidates interested in data"], "locations": ["Not Specified"], "categories": ["Information Technology (IT)", "DBA", "Software Development", "Insurance", "Others"], "post_time": "2022-01-13T11:15:53Z", "salary": {"currency": "HKD", "max": 24999, "min": 17000, "period": "monthly", "term": null}, "salary_visible": true, "title_keywords": ["analyst"], "responsibilities": ["ad-hoc", "provide support", "quality check", "uat", "administrative support", "monitoring", "maintain daily operations", "implementation", "evaluate", "coordinate", "communication", "administrative assistance", "reports", "plan", "insurance", "management report", "administration"], "requirements": {"degrees": ["diploma"], "majors": [], "languages": ["english", "chinese"], "language_level": ["good command"], "hard_skills": ["excel", "powerpoint", "computer skills", "processing", "ms word"], "soft_skills": ["meet tight deadlines", "attentive to details", "integrity", "customer-oriented", "communication and interpersonal skills", "enthusiastic", "accurate"], "languages_combined": [{"language": "english", "language_level": ["good command"]}, {"language": "chinese", "language_level": ["good command"]}]}, "experience_required": {"duration": ["at least 4 years"], "field": ["administrative", "relevant working experience", "policy administration"]}}, {"job_id": "100003009033142", "location_code": "hk", "company": "Marsh (Hong Kong) Limited", "job_title": "Client Manager \u2013 MMC ShunTak (Hong Kong)", "description": "Our Client is one of the leading financial services institutions in the market. We are currently hiring a Specialist to join its Communications team.\n\nYou will be reporting directly to the Head of Communications focusing on English writing at corporate level.\n\nResponsibilities:\n\nDesign, prepare and publish contents for a range of marketing and campaign materials, i.e. senior executive speeches, brochures, newsletters, annual report sections, digital channels, etc.\nWrite, edit and proof-read of a variety of internal communications for strategic targets\nWork closely with other internal parties and provide support to internal messages, such as press releases, Q&A documents, etc.\nCreate and maintain specific writing guidelines to ensure brand consistency and accuracy\nPerform other ad-hoc projects\n\nRequirements:\n\nBachelor's Degree in English, Communications or Journalism is preferred\nAt least 8 years of experience as a professional writer (English) and/or editor (English) within large organizations, journalists are also welcomed\nStrong communication and interpersonal skills, with good storytelling skills\nExcellent writing/editorial skills with proven portfolio\nExperience working in finance related content a plus\n\nFor those who are interested, please submit your latest profile (in WORD Format) to raman.hong@connectedgroup.com. Only qualified candidates will be contacted.\n\nFor more job opportunities, please visit our web-site: www.connectedgroup.com.", "employment_types": ["Full Time", "Permanent"], "selling_points": ["Provide brokering, consulting and admin service", "3 years\u2019 experience in broking firm", "IIQE (Paper 1 & 2 ) qualified or equivalent"], "locations": ["Quarry Bay"], "categories": ["Professional Services", "Business Consultancy", "Insurance", "Insurance Agent / Broker", "Others"], "post_time": "2022-01-08T10:44:41Z", "salary": {"currency": null, "max": null, "min": null, "period": "monthly", "term": null}, "salary_visible": false, "title_keywords": ["client manager"], "responsibilities": ["provide support", "guidelines", "design", "maintain", "contents", "brand consistency", "ad-hoc projects", "internal parties", "report"], "requirements": {"degrees": ["degree", "bachelor"], "majors": ["journalism", "communications"], "languages": ["english"], "language_level": [], "hard_skills": ["plus", "word", "web"], "soft_skills": ["communication and interpersonal skills"], "languages_combined": [{"language": "english", "language_level": []}]}, "experience_required": {"duration": ["at least 8 years"], "field": ["editor", "finance", "related"]}}, {"job_id": "100003009043467", "location_code": "hk", "company": "Jobson Mores Limited", "job_title": "Insurance - Graphic, UX/UI Designer (Manager)", "description": "Our client, a leading global insurance group, is now looking for a high caliber to fill up above position for their company.\n\nActuarial / Reinsurance Assistant or Analyst\u00a0\n\n\nResponsibilities\n- To provide support and assist in updating risk profiles, catastrophe data, major loss status summary and other underwriting information package, etc. for treaty renewal.\n- To provide accurate fire accumulation calculation to underwriters and ensure no overexposure risk/location for new, renewal and endorsement cases in the fire accumulation register.\n- To assist in monitoring the underwriting limit of all lines of business and ensure the sufficient coverage of the portfolio.\n- To assist in preparing the regular reinsurance treaty related bordereaux.\n- To assist in handling enquiries raised by internal and external stakeholders\n- To assist in identifying system needs, prepare user requirement, perform any UAT, health check, follow up with IT and ensure all R/I transactions report generated in system are correct and meet time line.\n- To resolve deficiencies in the system with IT project team.\n\n\nRequirements\n- 0-5 years experience\n- Preferable to have reinsurance knowledge\n- Diploma holder in insurance and any related discipline\n- Recognized insurance qualification ANZII / ACII or equivalent preferred\n- Good in spoken and written English and Chinese\n- Knowledge of PC (i.e. Excel, Word, PowerPoint, Access)\n- Experience in reinsurance field with solid background\n- Data Programming (SAS, VBA, R) is a plus\n- Fresh graduate will be considered as Assistant, more experience will be considered as Analyst\n\n\nAttractive remuneration package and excellent career prospects will be provided to the right candidate.\n\nInterested parties please send full resume with followings to cv2@ peoplus.com.hk\n1. Current & Expected Salary\n2. Availability\n3. Date of Achievement : Academic Result\n4. Quoting the Emp. Ref. No. : EK220115-01\n\nAll personal data provided by job applicants will be used for recruitment purpose only", "employment_types": ["Full Time"], "selling_points": ["Lead Creative Strategies, Concepts, and Content", "Well versd in UI/UX, Research, Animation, Motion", "Strong marketing sense & Business Acumen,"], "locations": ["Wan Chai"], "categories": ["Insurance", "Others", "Marketing / Public Relations", "Digital Marketing", "Information Technology (IT)", "UI/UX Designer"], "post_time": "2022-01-12T12:55:55Z", "salary": {"currency": null, "max": null, "min": null, "period": "monthly", "term": null}, "salary_visible": false, "title_keywords": ["ui designer", "manager"], "responsibilities": ["user requirement", "provide support", "uat", "data", "monitoring", "transactions", "report"], "requirements": {"degrees": ["diploma holder", "fresh graduate"], "majors": ["insurance"], "languages": ["english", "chinese"], "language_level": ["good"], "hard_skills": ["excel", "vba", "plus", "r", "sas", "word", "powerpoint", "programming", "pc"], "soft_skills": [], "languages_combined": [{"language": "english", "language_level": ["good"]}, {"language": "chinese", "language_level": ["good"]}]}, "experience_required": {"duration": ["0-5 years"], "field": []}}, {"job_id": "100003009042018", "location_code": "hk", "company": "Chubb Insurance Hong Kong Limited", "job_title": "Assistant Manager, Commercial Operations (A&H Corporate and SME, focus)", "description": "Responsibilities:\n\nAssist in driving digital projects\nAssist in monitoring and executing Life Operations projects including new products/ initiatives and system enhancement\nCollect and analyze business requirements and prepare user requirements specification (URS)\nDevelop test plan and participate/ assist end users in user acceptance testing (UAT) as and when required\nLiaise between Life Operations and IT teams\nAssist in project planning, resources allocation and progress monitoring\nSupport on any ad hoc projects provided by management\n\nRequirements:\n\nUniversity degree in business, finance, information technology, computer science or other related disciplines\nExperience in working on or developing mobile/ electronic application, electronic claim and/or other operations projects is highly preferred\nExperience in gathering business requirements, developing test scenarios and performing user acceptance testing\nExcellent interpersonal, communication and problem-solving skills\nGood command of both written and spoken English and Chinese\nMinimum of 1 year related experience in insurance and/ or banking and finance sectors\nCandidates with more experience will be considered for Senior Officer", "employment_types": ["Full Time"], "selling_points": ["General Insurance Operations", "Accident & Health, SME", "Team Lead"], "locations": ["Quarry Bay"], "categories": ["Insurance", "Underwriter", "Others", "Banking / Finance", "Order Processing & Operation / Settlement"], "post_time": "2022-01-12T05:18:10Z", "salary": {"currency": null, "max": null, "min": null, "period": "monthly", "term": null}, "salary_visible": false, "title_keywords": ["operations", "assistant manager,"], "responsibilities": ["liaise", "project planning", "management", "uat", "operations", "monitoring", "teams", "develop", "testing", "executing", "ad hoc projects", "plan"], "requirements": {"degrees": ["university degree"], "majors": ["finance", "information technology", "related disciplines", "business", "computer science"], "languages": ["english", "chinese"], "language_level": ["good command"], "hard_skills": ["problem-solving skills", "mobile"], "soft_skills": ["communication", "problem-solving skills", "interpersonal"], "languages_combined": [{"language": "english", "language_level": ["good command"]}, {"language": "chinese", "language_level": ["good command"]}]}, "experience_required": {"duration": ["minimum of 1 year"], "field": ["related", "finance", "developing", "testing", "business", "banking", "insurance"]}}, {"job_id": "100003009037590", "location_code": "hk", "company": "QBE General Insurance (Hong Kong) Limited", "job_title": "Customer Services Officer", "description": "Responsibilities:\nEstablish and develop new prospects on insurance broker business\nFollow up the potential policyholder referred by the group or approved business channels in a timely and professional manner\nConduct Financial Need Analysis (FNA) to identify the insurance and financial need of potential policyholder\nHandle the potential policyholder on providing insurance advisory, sales and marketing of insurance products, insurance application, follow up all underwriting process and other after sales services, if any.\nComply with regulatory requirement and group policy of insurance brokerage activities\nRequirements:\nHigher Diploma or above. Degree holder is preferred.\nPassed in IIQE Paper 1, 2 & 3\nMinimum 3 years of solid experience in selling insurance product for banks and/or insurance brokers in HK\nGood knowledge of General Insurance, Life Insurance products & market trend\nUnderstand AML, CFT and KYC procedures for insurance brokerage activities\nSelf-motivated, sales driven, customer focused and can work under pressure\nProficient in both spoken and written English and Chinese, fluent in Putonghua is preferred\nProficient in MS Word, Excel and PowerPoint", "employment_types": ["Full Time", "Permanent"], "selling_points": ["Non sales hotline", "General Insurance Company", "Customer Service"], "locations": ["Quarry Bay"], "categories": ["Sales, CS & Business Devpt", "Call Centre", "Insurance", "Others"], "post_time": "2022-01-11T03:14:12Z", "salary": {"currency": null, "max": null, "min": null, "period": "monthly", "term": null}, "salary_visible": false, "title_keywords": ["customer services officer"], "responsibilities": ["brokerage", "analysis", "professional manner", "develop", "insurance"], "requirements": {"degrees": ["higher diploma or above", "degree holder"], "majors": [], "languages": ["putonghua", "english", "chinese"], "language_level": ["fluent", "proficient"], "hard_skills": ["excel", "aml", "powerpoint", "iiqe paper", "cft", "kyc", "ms word"], "soft_skills": ["self-motivated", "driven", "focused", "work under pressure"], "languages_combined": [{"language": "putonghua", "language_level": ["fluent", "proficient"]}, {"language": "english", "language_level": ["fluent", "proficient"]}, {"language": "chinese", "language_level": ["fluent", "proficient"]}]}, "experience_required": {"duration": ["minimum 3 years"], "field": ["insurance"]}}, {"job_id": "100003009040141", "location_code": "hk", "company": "Crossings Executive Search", "job_title": "Assistant Manager, Business Analyst (Life Insurance, Multiple Openings) (Ref: AMBA/HL)", "description": "This is an great opportunity to join a well known US insurance company. With many ongoing internal projects across APAC, they are currently looking for a candidate that ideally has data experience in an insurance / reinsurance company. Candidates who have experience in insurance settlements / claims / operations and some basic skills in SQL / VBA / Python will definitely be considered as well.\n\nClient Details\n\nThis is an great opportunity to join a well known insurance company, headquartered in the United States. Founded over 50 years ago and listed on the stock exchange, their revenue in 2020 exceeded USD 16 billion.\n\nThis is an great opportunity to join a well known US insurance company. The candidate will join the the company's team that handles all of APAC's data. With many ongoing internal projects, they are currently looking for a candidate that ideally has data experience in an insurance / reinsurance company. Candidates who have experience in insurance settlements / claims / operations and some basic skills in SQL / VBA / Python will definitely be considered as well.\n\nCandidates must have strong communication skills in both English and Cantonese.\n\nDescription\n\nResponsibilities:\n\nExtract and cleanse data sets\nManage structured and unstructured data\nAnalyse and validate data to ensure data integrity\nDiscuss and identify process efficiency opportunities with different departments\nPrepare regular regulatory and client reports\nAny ad-hoc duties and projects as assigned\n\nProfile\n\nRequirements:\n\nBachelor's degree in Statistics, Computer Science, Actuarial Science or any related degree\n1 to 3 years of experience in insurance or re-insurance industry (settlements, operations, claims, analysis or data driven roles in insurance)\nFoundational knowledge in Python / VBA and SQL\nFresh graduates with relevant internship experience are welcome to apply\nCandidate should be logical, have strong analytic skills and be willing to learn\nExcellent communication skills in both Cantonese and English\n\nJob Offer\n\n16 days annual leave\nGuaranteed bonus\nMedical insurance\nDental insurance\nVery stable and friendly team\nTraining and internal growth opportunities\nMNC and western working environment\n\nTo apply online please click the 'Apply' button below. For a confidential discussion about this role please contact Jacqueline Lung on +852 3602 2471", "employment_types": ["Full Time", "Permanent"], "selling_points": ["A leading life insurance company", "At least 5 years of experience in life insurance", "Attractive remuneration package"], "locations": ["Ngau Tau Kok"], "categories": ["Information Technology (IT)", "Product Management / Business Analyst", "Insurance", "Others"], "post_time": "2022-01-12T01:38:21Z", "salary": {"currency": "HKD", "max": 54999, "min": 45000, "period": "monthly", "term": null}, "salary_visible": true, "title_keywords": ["assistant manager,", "business analyst"], "responsibilities": ["client reports", "analyse", "ad-hoc duties", "data"], "requirements": {"degrees": ["degree", "bachelor"], "majors": ["statistics", "actuarial science", "computer science"], "languages": ["cantonese", "english"], "language_level": ["excellent"], "hard_skills": ["vba", "analysis", "sql", "analytic skills", "python"], "soft_skills": ["communication skills", "willing to learn", "friendly", "stable", "driven"], "languages_combined": [{"language": "cantonese", "language_level": ["excellent"]}, {"language": "english", "language_level": ["excellent"]}]}, "experience_required": {"duration": ["1 to 3 years"], "field": ["insurance", "insurance industry"]}}, {"job_id": "100003009049986", "location_code": "hk", "company": "China Life Insurance (Overseas) Company Limited", "job_title": "Assistant General Manager of Actuarial Department \u2013 Capital and Modelling", "description": "Responsibilities:\nProvide brokering, consulting and administration services to existing portfolios of Hong Kong based corporate clients.\nProvide customer service and handle customer enquiries in policy administration and insurance program.\nProvide support on new business and achieve penetration budget through prospecting referral and review of client\u2019s new insurance needs.\nPrepare proposal, benchmark and analysis report to clients and conduct presentation with clients and underwriters.\n\nJob Requirements:\n\nHigher diploma in Insurance or Finance related disciplines\nMinimum 3 years\u2019 experience in broking firm and servicing corporate clients\nIIQE (Paper I and Paper II) qualified or equivalent relevant qualification\nCustomer focused with good communication and presentation skills\nProficiency in spoken and written English is essential\nStrong computer skills including MS Word, Excel and PowerPoint\nSelf-motivated and able to work independently\n\nAttractive remuneration and incentives will be offered to the right candidate.\u00a0\n\nJob applications should be sent in confidence with details in education, working history and salary expectation to us by applying below.\u00a0\n\n\nWe are an Equal Opportunity Employer. Visit us at www.marsh-asia.com\u00a0\n\n\nAll information received will be kept in strict confidence and be used only for employment-related purposes.", "employment_types": ["Full Time"], "selling_points": ["Lead and conduct risk assessments", "Complete any capital management project", "10 years of relevant experience"], "locations": ["Not Specified"], "categories": ["Banking / Finance", "Financial Services", "Management", "General Management", "Insurance", "Others"], "post_time": "2022-01-14T09:35:50Z", "salary": {"currency": null, "max": null, "min": null, "period": "monthly", "term": null}, "salary_visible": false, "title_keywords": ["assistant general manager"], "responsibilities": ["provide customer service", "provide support", "handle customer enquiries", "consulting", "analysis report", "budget", "review", "insurance", "administration"], "requirements": {"degrees": ["diploma"], "majors": ["related disciplines", "finance", "insurance"], "languages": ["english"], "language_level": ["proficiency"], "hard_skills": ["excel", "iiqe", "powerpoint", "computer skills", "ms word"], "soft_skills": ["self-motivated", "work independently", "confidence", "focused", "communication", "presentation skills"], "languages_combined": [{"language": "english", "language_level": ["proficiency"]}]}, "experience_required": {"duration": ["minimum 3 years"], "field": []}}, {"job_id": "100003009038691", "location_code": "hk", "company": "BestServe Financial Ltd", "job_title": "Client Service Representative (12-month contract)", "description": "The successful candidate will be responsible to handle policy administration and related activities.\u00a0\n\nResponsibilities:\n\nHandle enquiries regarding policy administration from clients, intermediaries, reinsurers, and inter-departments.\nIssue policies, endorsements, reinsurance closing (both direct and facultative inwards) and renewals.\nUndertake risk accumulation control (Fire/ Vessel Risk Blocking) in accordance with the prescribed retention limits.\nOffice administration support including ad hoc task to be assigned from time to time.\n\nRequirements:\u00a0\u00a0\n\nForm 6 or above.\nExperience in handling policy administration in general insurance industry is an advantage.\nStrong sense of responsibility.\nWork independently and able to work ahead of deadline.\nGood command of spoken and written English and Chinese.\nProficiency in MS office (Word, Excel, Power point and Chinese Word Processing).\n\nPosition and salary would be offered depends on experiences.\n\nWe offer attractive remuneration package with excellent benefits including double pay, performance bonus, Top-up MPF,\u00a0medical benefits with extended coverage to dependent,\u00a0birthday\u00a0leave, family leave, training subsidy, etc. to the right candidate.\n\nIf interested, please provide your resume\u00a0with current and\u00a0expected salary\u00a0by clicking \"Apply Now\".\n\n(All information collected is for recruitment purpose only.)", "employment_types": ["Full Time", "Temporary"], "selling_points": ["Knowledge of MPF and ORSO legislation", "Knowledge in Customer Service Functions", "Call Centre/ Customer Service"], "locations": ["Hung Hom"], "categories": ["Sales, CS & Business Devpt", "Call Centre", "Insurance", "Others"], "post_time": "2022-01-11T07:38:50Z", "salary": {"currency": null, "max": null, "min": null, "period": "monthly", "term": null}, "salary_visible": false, "title_keywords": ["representative"], "responsibilities": ["control", "office administration support", "ad hoc", "policies", "handle enquiries", "administration"], "requirements": {"degrees": [], "majors": [], "languages": ["english", "chinese"], "language_level": ["proficiency", "good command"], "hard_skills": ["excel", "chinese word processing", "word", "power point", "ms office"], "soft_skills": ["work independently", "sense of responsibility"], "languages_combined": [{"language": "english", "language_level": ["good command"]}, {"language": "chinese", "language_level": ["proficiency", "good command"]}]}, "experience_required": {"duration": [], "field": ["general insurance", "policy administration"]}}, {"job_id": "100003009032682", "location_code": "hk", "company": "Jobson Mores Limited", "job_title": "Insurance - Policy Administration Officer/Senior Officer", "description": "We are currently looking for an INSURANCE - GRAPHIC, UX/UI DESIGNER (MANAGER)\u00a0\n\n\n\nRESPONSIBILITIES\n\n\nLead creative strategies, concepts, and content that meet business objectives\nDrive design innovation across all the design disciplines,\u00a0 including design innovation, leading the creation of new design patterns and thought leadership of design evolution in the external context\nDevelop clear and impactful digital content and messages\nIdeate and execute on compelling digital communications and campaigns to drive customer engagement and customer stickiness\nLead content standards across different digital channels & platforms and be a champion for best practices\n\nREQUIREMENTS\u00a0\n\nUniversity degree, with at least 8 years\u2019 relevant experience\nHands on experiences of developing and implementing digital customer communication and campaign\nWell versed in all disciplines of design (UI/UX, Research, Animation, Motion)\nProven experience in managing and measuring digital content marketing is a plus\nCulturally sensitive and understanding of global and local customer needs.\nStrong marketing sense, business acumen, excellent leadership and communication skills\nExcellent English , Mandarin and Cantonese\nAPPLY FOR THE JOB\n\nInterested candidate please\u00a0CLICK\u00a0apply button to apply online or send your resume in MS word format to\u00a0Jobson Mores Recruitment\n\nPlease note that only shortlisted candidate will be notified. All information will be treated in strict confidence and solely used for recruitment purposes.", "employment_types": ["Full Time"], "selling_points": ["2-3 years relevant experience", "Input policy data and verify on application", "Handle enquires from internal"], "locations": ["Wan Chai"], "categories": ["Banking / Finance", "Others", "Insurance", "Others"], "post_time": "2022-01-07T14:30:53Z", "salary": {"currency": null, "max": null, "min": null, "period": "monthly", "term": null}, "salary_visible": false, "title_keywords": ["administration officer", "senior officer"], "responsibilities": ["design", "develop"], "requirements": {"degrees": ["university degree"], "majors": [], "languages": ["cantonese", "english", "mandarin"], "language_level": ["excellent"], "hard_skills": ["ms word", "plus", "acumen"], "soft_skills": ["communication skills", "confidence", "marketing sense", "communication", "hands on", "sensitive", "business acumen", "leadership"], "languages_combined": [{"language": "cantonese", "language_level": ["excellent"]}, {"language": "english", "language_level": ["excellent"]}, {"language": "mandarin", "language_level": ["excellent"]}]}, "experience_required": {"duration": ["at least 8 years"], "field": ["digital content", "developing", "marketing", "relevant experience", "digital"]}}, {"job_id": "100003009046501", "location_code": "hk", "company": "AXA Hong Kong", "job_title": "Investment Analyst / Assistant Analyst", "description": "The position is responsible for ensuring that the local operations of Accident & Health (A&H) Corporate and Small and Medium-sized Enterprise (SME) under Commercial Operations team, is adequately equipped and properly aligned to support business, service, sales, and product delivery requirements, and reporting to Commercial Operations Manager directly.\n\nResponsibilities:\n\n\n\nOperational Lead\n\nLead an A&H Underwriting Assistants Unit and SME Policy Administration team to support pre-bind and post-bind policy services for Underwriting teams\nManage daily operations, ensure smooth and effective operational service supports to underwriters and external customers\nProperly arrange and assign daily works, provide timely coaching and guidance to the Ops team members to solve daily operational issues\nWork proactively and constantly improve productivity by identifying weaknesses, recommending solutions and implementing changes/quick wins\nQuality Control\n\nConduct quality control on data inputs, deliverables and procedures through monthly review and sample checking\u00a0\nMaintain up-to-date system manuals and operational workflow documents on new rules and procedures. Identified onshore and offshore team members\u2019 knowledge and skill gaps, and provide necessary training sessions for corrections and improvements\nMonitor accuracy and turnaround time on defined service level agreement for regular reporting\n\nOther Support\n\nGenerate monthly KPI metrics reporting to Regional counterparts and local business stakeholders\nPromote team work and collaboration with business units\nParticipate in user acceptance test (UAT) on new or enhanced technology solutions\n\nRequirements:\n\n\n\nBachelor\u2019s degree or above in Accounting, Economics, Finance, or other Business-related discipline\nAt least 5 years of relevant working experience with at least 1 year solid supervisory experience in operations team, preferably in insurance industry\nPassed IIQE Paper 1 & 2 will be an advantage\nSound knowledge in general insurance products is preferred\nStrong analytical skills, multi-tasking and time management\nTeam player with good communication, presentation, interpersonal and management skills\nAbility to adapt to a continuously evolving system and work-flow environment\nAble to work under pressure and independently\nExcellent command of written and spoken English and Cantonese\nHighly PC literate in Microsoft Word, Excel, Powerpoint, etc.\nCandidates with less experience will be considered as UA Lead / Supervisor\nPlease click \"Apply now\" to submit your application.\n\n\nPersonal data collected will be used for recruitment purpose only.", "employment_types": ["Full Time", "Permanent"], "selling_points": ["entry level for Investment role", "prepare reports and manage process for investment", "Good working environment & culture"], "locations": ["Southern Area"], "categories": ["Banking / Finance", "Analyst", "Investment", "Insurance", "Others"], "post_time": "2022-01-13T12:16:59Z", "salary": {"currency": null, "max": null, "min": null, "period": "monthly", "term": null}, "salary_visible": false, "title_keywords": ["analyst", "assistant"], "responsibilities": ["guidance", "reporting", "uat", "conduct quality control", "data", "review", "teams", "procedures", "checking", "monitor", "maintain", "quality control", "sme", "manage daily operations", "administration"], "requirements": {"degrees": ["degree or above", "bachelor"], "majors": ["finance", "economics", "accounting", "business"], "languages": ["cantonese", "english"], "language_level": ["excellent"], "hard_skills": ["excel", "microsoft word", "powerpoint", "analytical skills", "iiqe paper", "pc literate"], "soft_skills": ["independently", "interpersonal", "analytical skills", "communication", "multi-tasking", "team player", "time management", "presentation", "work under pressure"], "languages_combined": [{"language": "cantonese", "language_level": ["excellent"]}, {"language": "english", "language_level": ["excellent"]}]}, "experience_required": {"duration": ["at least 5 years", "at least 1 year"], "field": ["insurance industry", "relevant working experience", "team", "supervisory experience"]}}, {"job_id": "100003009036881", "location_code": "hk", "company": "Liberty International Insurance Limited", "job_title": "Senior Officer, Business Development  (Partnership Channel Management)", "description": "Responsibilities:\n\n\nAssist superior to carry out various operations tasks and projects, especially in areas of system enhancement and/ or data analysis\nPrepare user requirements, conduct UAT and user trainings.\nEnhance communication/ work-flow with clinics.\nFollow up problem investigation with IT, teammates and related parties.\n\n\u00a0Requirements:\n\nUniversity graduate, with 3 years working experiences\nExperience on Business Analyst will be an advantage\nDetail-oriented, flexible, independent and able to meet deadlines\nTeam player with good communication skills and customer services\nNative in Cantonese, good command in verbal and written English.\nImmediate available is preferable\n\n14 days Annual Leave & 1-day Birthday Leave\nMedical & Dental Benefit\nOffice Location: Tsim Sha Tsui / Kwun Tong\n\n\u00a0Personal data will be used for recruitment purpose only.", "employment_types": ["Full Time", "Permanent"], "selling_points": ["growth mindset", "manage renewal portfolio", "achieve annual growth plan"], "locations": ["Quarry Bay"], "categories": ["Insurance", "Others", "Sales, CS & Business Devpt", "Account Servicing", "Sales Administration"], "post_time": "2022-01-10T17:19:08Z", "salary": {"currency": null, "max": null, "min": null, "period": "monthly", "term": null}, "salary_visible": false, "title_keywords": ["senior officer"], "responsibilities": ["uat", "operations", "investigation", "data analysis", "communication"], "requirements": {"degrees": ["university graduate"], "majors": [], "languages": ["cantonese", "english"], "language_level": ["native", "good command"], "hard_skills": [], "soft_skills": ["flexible", "communication skills", "independent", "detail-oriented", "team player", "meet deadlines"], "languages_combined": [{"language": "cantonese", "language_level": ["native", "good command"]}, {"language": "english", "language_level": ["good command"]}]}, "experience_required": {"duration": ["3 years"], "field": ["business"]}}, {"job_id": "100003009038396", "location_code": "hk", "company": "China Taiping Life Insurance (Hong Kong) Company Limited", "job_title": "System Analyst (Life Insurance)", "description": "Be creative in driving customer centricity and steer the relevant business functions for the development and delivery of customer strategy and proposition for existing and new customers.\n\nResponsibilities\n\nDrive Segmentation Research and regular satisfaction survey from research agency management, questionnaire development, result analysis to identify and justify the selection of target segments and project the target market size\nIdentify the potential segments within FTLife and across the New World Group\u2019s eco-system, and design the entire customer journey of each segment by understanding the customer lifecycle with FTLife and identifying the moment of truth\nRecommend proposition to support customer retention and acquisition of target segments and key customer engagement measurements\nManage and grow target segments, \u00a0track segment trends and dynamics, competitive analysis and investment recommendations to institutionalize segmentation and drive sustainable business & profitability growth\nSupport to define the strategic customer segment needs, formulate growth strategies and execute customer value proposition and plans to penetrate new market opportunities with optimized product solutions and execute key priorities\nOptimize omni-channel customer experience, identify online and offline touchpoints along the end-to-end customer engagement journey\nCollaborate with distribution channels to develop segment-driven sales enablement materials and sales pitch to facilitate channel-customer engagement\nSupport the integration of Customer Relationship Management (CRM) solution to foster customer engagement, loyalty, retention and potentially new business opportunities\nDrive the culture of on-going improvement, innovation and customer centricity, act as an internal customer advocate\nKeep abreast of market development and needs of customers/ distributors to develop sound customer experience proposition strategy\n\n\u00a0Requirements\n\nBachelor\u2019s degree in Business Administration, Marketing, Finance, Economics, or related fields\nMinimum 10 years of work experience in marketing strategy, market research, customer experience, and/or digital business transformation within financial services, preferably in insurance industry. Candidate with less experience will be considered as Manager\nExperience in converting data and analytics to track performance, define and execute customer experience strategy\nAbility to build strong relationship and communicate effectively across stakeholder groups, internally and externally\nProven ability to influence across functional teams\nGood command of both written and spoken English and Chinese", "employment_types": ["Full Time", "Permanent"], "selling_points": ["Business applications development and enhancement", "Degree with 3 years solid relevant experience", "Attractive remuneration package"], "locations": ["North Point"], "categories": ["Information Technology (IT)", "Product Management / Business Analyst", "Software Development", "Insurance", "Others"], "post_time": "2022-01-11T06:46:19Z", "salary": {"currency": null, "max": null, "min": null, "period": "monthly", "term": null}, "salary_visible": false, "title_keywords": ["system analyst"], "responsibilities": ["collaborate with", "management", "analysis", "business opportunities", "design", "develop", "questionnaire", "plans"], "requirements": {"degrees": ["degree", "bachelor"], "majors": ["economics", "finance", "marketing", "business administration"], "languages": ["english", "chinese"], "language_level": ["good command"], "hard_skills": [], "soft_skills": [], "languages_combined": [{"language": "english", "language_level": ["good command"]}, {"language": "chinese", "language_level": ["good command"]}]}, "experience_required": {"duration": ["minimum 10 years"], "field": ["market research", "insurance industry", "business", "marketing", "financial services", "digital"]}}, {"job_id": "100003009038514", "location_code": "hk", "company": "China Taiping Life Insurance (Hong Kong) Company Limited", "job_title": "Senior Officer, Project Management", "description": "Responsibilities:\n\nHandle inbound calls from internal and external customers for general enquiries & insurance\nHandle patient\u2019s insurance related administrative and clerical work including quotation, pre-approval form, medical voucher and claim form\nRegular contact with insurance company/hospital/clinic/doctor for following up of claims cases\nAssist in ad-hoc projects assigned\n\nRequirement:\n\nHKDSE or above\nMinimum 1 to 2 years working experience in insurance field preferred\nResponsible, proactive and well-organized\nGood interpersonal & communication skills\nGood command\u00a0of both written and spoken\u00a0English and Chinese, knowledge in Putonghua will be an advantage\nProficiency in PC applications including\u00a0MS\u00a0Word, Excel,\u00a0Powerpoint, Outlook and\u00a0Chinese Word Processing", "employment_types": ["Full Time", "Permanent"], "selling_points": ["Project management and support", "3 years or above exp. in large insurance company", "Attractive remuneration package"], "locations": ["North Point"], "categories": ["Transportation & Logistics", "Others", "Banking / Finance", "Others", "Insurance", "Others"], "post_time": "2022-01-11T07:12:09Z", "salary": {"currency": null, "max": null, "min": null, "period": "monthly", "term": null}, "salary_visible": false, "title_keywords": ["senior officer"], "responsibilities": ["internal and external customers", "quotation", "contact", "ad-hoc projects", "insurance"], "requirements": {"degrees": ["hkdse"], "majors": [], "languages": ["putonghua", "english", "chinese"], "language_level": ["advantage", "proficiency", "good command"], "hard_skills": ["excel", "chinese word processing", "powerpoint", "pc applications", "outlook", "ms word"], "soft_skills": ["communication skills", "responsible", "well-organized", "proactive", "interpersonal"], "languages_combined": [{"language": "putonghua", "language_level": ["advantage", "good command"]}, {"language": "english", "language_level": ["advantage", "good command"]}, {"language": "chinese", "language_level": ["advantage", "proficiency", "good command"]}]}, "experience_required": {"duration": ["minimum 1 to 2 years"], "field": ["insurance"]}}, {"job_id": "100003009037763", "location_code": "hk", "company": "Dah Sing Financial Group", "job_title": "Officer / Senior Officer, Claims (General Insurance)", "description": "Responsibilities:\n\nPerform credit research, and recommend internal rating for investment counterparties using both quantitative and qualitative assessments\nConduct due diligence on investments providers and products and present to managements\nAssess the instrument ratings for fixed-income investment, alternative investment and structured products\nConduct annual counterparty credit rating reviews as well as ad-hoc credit investments review, alert on significant credit deteriorations\nMaintain and advise the internal rating methodology for different investment products and industries periodically\nAssist in developing and maintaining internal credit rating policies and procedures\nOther relevant ad-hoc projects and duties as assigned\n\nRequirements:\n\nBachelor\u2019s degree in Business/ Economics/ Finance/ Accounting or related discipline a plus\nPreferably 1 to 3 years of credit analysis experience in international credit rating agencies or relevant roles in financial industry, experience in leading bond rating agencies of China is also welcomed\nDeep understanding of international credit rating agency\u2019s rating methodologies\nStrong credit analytical skill and good understanding of financial analysis and financial modelling\nProactive, analytical minded with attention to details and market sense\nExcellent communication skills with fluency in written and spoken English and Mandarin\n\nApplication\nInterested parties please send a detailed resume, stating current and expected salary to Human Resources Department.\n\nInformation supplied will be treated in strict confidence and used in accordance with the Personal Data (Privacy) Ordinance.\u00a0 Applicants not invited for interview within 6 weeks may consider their applications unsuccessful.", "employment_types": ["Permanent"], "selling_points": ["Assist in UAT", "Secondary education or above", "At least 2 years\u2019 relevant experience"], "locations": ["North Point"], "categories": ["Sales, CS & Business Devpt", "Customer Service - Supervisor / Officer", "Insurance", "Claims Officer", "Others"], "post_time": "2022-01-11T03:45:53Z", "salary": {"currency": null, "max": null, "min": null, "period": "monthly", "term": null}, "salary_visible": false, "title_keywords": ["officer", "senior officer"], "responsibilities": ["ad-hoc", "due diligence", "maintaining", "policies", "review", "procedures", "developing", "maintain", "fixed-income investment", "ad-hoc projects"], "requirements": {"degrees": ["degree", "bachelor"], "majors": ["finance", "economics", "business", "accounting"], "languages": ["english", "mandarin"], "language_level": ["fluency", "excellent"], "hard_skills": ["credit analysis", "plus", "financial analysis", "analytical skill"], "soft_skills": ["communication skills", "analytical skill", "deep", "attention to details", "proactive"], "languages_combined": [{"language": "english", "language_level": ["fluency", "excellent"]}, {"language": "mandarin", "language_level": ["fluency", "excellent"]}]}, "experience_required": {"duration": ["1 to 3 years"], "field": ["financial industry"]}}, {"job_id": "100003009041953", "location_code": "hk", "company": "Blue Cross (Asia-Pacific) Insurance Ltd", "job_title": "Medical Claims Assistant", "description": "Project management and support, including project monitoring and coordination, progress follow-up, risk monitoring.\n\nResponsibilities\n\nEstablish and continue to optimize company's project management system\uff0cproject workflow and project evaluation criteria\nEstablish and continue to optimize PMO workflow and rules and standards\nCollect project progress information and data regularly, and prepare project monthly report\nOrganize project review and report regularly\nOrganize project evaluation and assessment\nPublicize and promote the achievements of major projects\nOrganize and promote the training of professional management tools and methods, internal consultation and external liaison\nFinalize other tasks assigned by leaders at all levels\n\nRequirements\n\nFull time bachelor degree or above, major in management is preferred\nExperience in large-scale project implementation or management is preferred\nPMP or other professional qualifications in project management is preferred\nExperience in large-scale project implementation or management is preferred\nWorking experience over 3years in large insurance company is preferred\nGood at communication and coordination, excellent execution\nCandidate with less experience will be considered as Officer.\n\nApplications\nInterested parties please send a detailed resume, stating current and expected salary to Human Resources Department.\n\nInformation supplied will be treated in strict confidence and used in accordance with the Personal Data (Privacy) Ordinance.\u00a0 Applicants not invited for interview within 6 weeks may consider their applications unsuccessful.", "employment_types": ["Full Time", "Permanent"], "selling_points": [], "locations": ["Kwun Tong"], "categories": ["Insurance", "Others"], "post_time": "2022-01-12T04:48:14Z", "salary": {"currency": null, "max": null, "min": null, "period": "monthly", "term": null}, "salary_visible": false, "title_keywords": ["assistant"], "responsibilities": ["management", "data", "review", "project progress", "project management", "other tasks", "monthly report", "evaluation", "report"], "requirements": {"degrees": ["degree or above", "bachelor"], "majors": [], "languages": [], "language_level": [], "hard_skills": ["project management", "pmp", "professional qualifications"], "soft_skills": ["communication", "project management", "coordination"], "languages_combined": []}, "experience_required": {"duration": [], "field": ["management", "insurance"]}}, {"job_id": "100003009043267", "location_code": "hk", "company": "AXA Hong Kong", "job_title": "Accountant, Planning & Management Reporting (FP&A)", "description": "Primary Responsibilities\n\nResponsible for handling phone, email, fax, WhatsApp's\u00a0customer service enquiry and resolving customer/agents enquiries to ensure that client satisfaction is achieved\nResolve or escalate all client complaints in a timely fashion\nEnsure compliance with all relevant internal instructions and external regulatory requirement\nAttend relevant product and skill courses and passing on relevant points to other staff\nProviding clients with product knowledge to ensure optimum utilisation of the organisation's products\nFocus on delivering excellent customer service and provide an enjoyable customer experience\nDemonstrate the necessary technique and skills to perform the job\n\nQualifications\n\nCustomer service/operations experience\nCall center experience\nInsurance industry experience", "employment_types": ["Full Time", "Permanent"], "selling_points": ["Accounting FP&A position", "Management reporting functions", "Good working environment & culture"], "locations": ["Not Specified"], "categories": ["Accounting", "Accountant", "Others", "Insurance", "Others"], "post_time": "2022-01-12T10:26:08Z", "salary": {"currency": null, "max": null, "min": null, "period": "monthly", "term": null}, "salary_visible": false, "title_keywords": ["accountant"], "responsibilities": ["operations", "customer service", "insurance", "ensure compliance"], "requirements": {"degrees": [], "majors": [], "languages": [], "language_level": [], "hard_skills": ["whatsapp", "focus"], "soft_skills": ["responsible", "timely", "customer service", "organisation", "focus"], "languages_combined": []}, "experience_required": {"duration": [], "field": ["customer service", "call center", "insurance industry"]}}, {"job_id": "100003009034301", "location_code": "hk", "company": "BUPA Asia Limited", "job_title": "Senior Advisor, Case Management", "description": "Our Client:\n\nA fast growing Insurer in Hong Kong\n\nRole Overview:\n\nHandle AML regulatory compliance matters\nHandle IA projects\nProvide compliance advice and support to other business units\nReview and develop AML compliance related policies and procedures\n\nIdeal Profile:\n\nBachelor Degree holder\n3 years or above relevant experience", "employment_types": ["Full Time", "Permanent"], "selling_points": ["4 years\u2019 relevant working experience in medical", "Assess Preauthorization Application", "Lead a team"], "locations": ["Not Specified"], "categories": ["Insurance", "Claims Officer", "Others", "Medical Services", "Others"], "post_time": "2022-01-10T03:06:47Z", "salary": {"currency": null, "max": null, "min": null, "period": "monthly", "term": null}, "salary_visible": false, "title_keywords": ["advisor"], "responsibilities": ["aml", "policies", "review", "compliance", "procedures", "develop"], "requirements": {"degrees": ["bachelor degree holder"], "majors": [], "languages": [], "language_level": [], "hard_skills": ["aml"], "soft_skills": ["ideal"], "languages_combined": []}, "experience_required": {"duration": ["3 years"], "field": ["relevant experience"]}}, {"job_id": "100003009043477", "location_code": "hk", "company": "Page Personnel", "job_title": "Underwriting and Claims Officer- Top Reinsurer Firm!", "description": "Reporting to the Senior Manager / Manager (GI Actuarial, Policy and Development Division), the incumbent will undertake the following:\n\n\u00a0Key Responsibilities\n\nParticipate in developing the Risk-based Capital solvency regime and the monitoring approaches or analytical indicators for supervisory focus\nAssist in providing GI actuarial technical support and/or peer review across teams and divisions\nKeep abreast of the developments of insurance industry, conduct researches and conduct industry-wide reviews\nAssist in developing legislation, rules and guidelines on insurance supervision\nAssist in liaising with industry and professional bodies on actuarial topics relating to the regulation and development of the insurance industry\nAssist in coordination work in IA\u2019s information technology development projects\nPerform any other duties as assigned by senior management to facilitate the administration of the statutory functions of the IA\n\n\u00a0Requirements\n\n\nA Bachelor\u2019s degree in actuarial science, statistics, finance, insurance, computer science or related field\nPart-qualified actuary with a minimum of 3 years\u2019 relevant experience in GI actuarial practices\nExperience in reserving, underwriting, claims, risk management, data analytics and/or nat cat modelling will be valued\u00a0\nKnowledge of the local regulatory requirements, actuarial practices, insurance products, industry practices and market dynamics of insurance business\nProfessional, strong business acumen, open-minded, and able to work with a team in a collaborative environment\nStrong command of written and spoken English. Chinese language ability is an advantage\n\nRemuneration Package\nA competitive remuneration package commensurate with the successful candidate\u2019s experience and qualifications will be offered.\n\nApplication\nReview of the applications will start as soon as possible and continue until 20January 2022, or until the post is filled. Interested applicants may send a letter of application quoting the reference number in the heading, together with a full resume stating public examination and university academic results as well as current and expected salaries\u00a0by clicking \"Apply Now\".\n\nThe Insurance Authority is an equal opportunities employer. Applicants not invited for an interview within 2 months from the submission date may assume their applications unsuccessful. Applications may be considered for other suitable positions within IA. All applications will be handled in strict confidence and the information collected will only be used for recruitment purposes. All information on non-shortlisted applicants will be destroyed after 6 months from the submission of their applications.", "employment_types": ["Full Time", "Permanent"], "selling_points": ["International and dynamic working environment", "Huge exposure to juniors", "Competitive packages and benefits"], "locations": ["Not Specified"], "categories": ["Insurance", "Claims Officer", "Underwriter", "Others"], "post_time": "2022-01-12T13:26:42Z", "salary": {"currency": null, "max": null, "min": null, "period": "monthly", "term": null}, "salary_visible": false, "title_keywords": ["claims officer"], "responsibilities": ["any other duties", "technical support", "guidelines", "review", "monitoring", "teams", "developing", "liaising with", "coordination", "senior management", "insurance", "administration"], "requirements": {"degrees": ["degree", "bachelor"], "majors": ["actuarial science", "finance", "statistics", "computer science", "insurance"], "languages": ["english", "chinese"], "language_level": ["advantage"], "hard_skills": ["data analytics", "acumen"], "soft_skills": ["business acumen", "open-minded", "confidence", "collaborative"], "languages_combined": [{"language": "english", "language_level": []}, {"language": "chinese", "language_level": ["advantage"]}]}, "experience_required": {"duration": ["minimum of 3 years"], "field": ["underwriting", "risk management", "relevant experience"]}}, {"job_id": "100003009035137", "location_code": "hk", "company": "China Taiping Insurance (HK) Company Limited", "job_title": "Account Manager (Brokers Channel)", "description": "Job Responsibilities:\n\nAssess and process claims within delegated claims authority in accordance with the established procedures and guidelines;\nSupport the implementation of claims management strategies and objectives;\nReach benchmark of claims processing volume and turnaround time;\nAssist in handling enquiries or complaints from internal and external customers;\nIdentify and conduct thorough investigation of suspicious cases, including report to superior; and\nHandle ad-hoc duties as assigned by superior(s).\n\nJob Requirements:\n\nColleague graduated or above;\n3 years' relevant experience in insurance industry, preferably in medical claims;\nProfessional qualification in FLMI, FLHC, etc. will be an advantage;\nFamiliar with operation of medical claims and healthcare network providers;\nGood communication and interpersonal skills;\nFlexible and customer-oriented;\nDetail-minded with strong sense of responsibilities and well-organized;\nAble to handle multi-task and work under pressure in a fact paced enviornment;\nGood command of both written and spoken English and Chinese; and\nProficient in MS Office and Chinese Word Processing.\nWe offer excellent career prospects and attractive remuneration package including 5-day work week, year-end bonus, life, medical and dental coverage, birthday leave, volunteer leave, well-being time off, etc.\n\nPlease submit your application via our Company\u2019s\u00a0Career Opportunities webpage.\u00a0\u00a0Personal Data provided by applicants will only be used for recruitment purposes and be\u00a0handled in accordance with the Company's Privacy Policy Statement, which is available on our website. Applicants who are not\u00a0contacted for interview within six (6) weeks may consider their application unsuccessful. The Company will retain the applications for a maximum period of six (6) months and may reconsider the applicants for other suitable\u00a0vacancies within the Company, where appropriate.", "employment_types": ["Full Time", "Permanent"], "selling_points": ["General insurance products marketing", "Provide high quality after-sale service supports", "Welcome fresh graduates"], "locations": ["North Point"], "categories": ["Sales, CS & Business Devpt", "Business Development", "Insurance", "Insurance Agent / Broker", "Others"], "post_time": "2022-01-10T06:08:34Z", "salary": {"currency": null, "max": null, "min": null, "period": "monthly", "term": null}, "salary_visible": false, "title_keywords": ["account manager"], "responsibilities": ["internal and external customers", "management", "guidelines", "procedures", "implementation", "investigation", "ad-hoc duties", "report"], "requirements": {"degrees": [], "majors": [], "languages": ["english", "chinese"], "language_level": ["good command", "proficient"], "hard_skills": ["chinese word processing", "ms office"], "soft_skills": ["flexible", "detail-minded", "multi-task", "work under pressure", "well-organized", "customer-oriented", "communication and interpersonal skills", "sense of responsibilities"], "languages_combined": [{"language": "english", "language_level": ["good command"]}, {"language": "chinese", "language_level": ["good command", "proficient"]}]}, "experience_required": {"duration": ["3 years"], "field": ["relevant experience", "insurance industry", "medical"]}}, {"job_id": "100003009036964", "location_code": "hk", "company": "Generali Life (Hong Kong) Limited", "job_title": "Senior Manager, Customer Experience & Insights", "description": "Job Responsibilities:\n\nResponsible for one AXA monthly business reporting, analysis and budgeting, focusing on business volume analysis, channel drivers\nTo be a trusted partner to business finance and cultivate efficiency culture\nTo improve timeliness and quality of management reporting and provide insightful analytics to support management decision\nTo involve in streamlining and transforming the team to deliver the management report to different business functions\nSignificantly reduce lead time of management reporting process and improve quality of the report with insightful analysis\nStreamline and automate management report to drive efficiency\nDeliver the management business reporting, analysis and budgeting and to provide insights and recommendations to management\n\nJob Requirements:\n\nUniversity graduate with minimum of 4 years' experience in insurance industry.\nA minimum of 3 years' experience in management reporting (FP&A)\nExperience in Business Partnering and key stakeholders management\nClient oriented with strong business acumen and analytical skills\nExcellent communication skills in both English and Cantonese", "employment_types": ["Full Time", "Permanent"], "selling_points": [], "locations": ["Tai Koo"], "categories": ["Insurance", "Others", "Marketing / Public Relations", "Marketing - Market Research", "Digital Marketing"], "post_time": "2022-01-11T01:04:31Z", "salary": {"currency": null, "max": null, "min": null, "period": "monthly", "term": null}, "salary_visible": false, "title_keywords": ["senior manager"], "responsibilities": ["reporting", "management", "provide insights", "budgeting", "analysis", "quality", "management reporting", "management report", "report"], "requirements": {"degrees": ["university graduate"], "majors": ["insurance"], "languages": ["cantonese", "english"], "language_level": ["excellent"], "hard_skills": ["analytical skills", "acumen"], "soft_skills": ["business acumen", "communication skills", "analytical skills"], "languages_combined": [{"language": "cantonese", "language_level": ["excellent"]}, {"language": "english", "language_level": ["excellent"]}]}, "experience_required": {"duration": ["minimum of 4 years", "minimum of 3 years"], "field": ["management", "business", "insurance industry"]}}, {"job_id": "100003009039961", "location_code": "hk", "company": "Insurance Authority", "job_title": "Manager (Market Research)", "description": "Our client is one of the largest reinsurers in the world that provides insurance companies with a diversified and innovative range of solutions and services to control and manage risk. They are looking for a life underwriting and claims trainee to handle life underwriting and claims services and product development activities. The candidate should have 1-2 years of working experience in life underwriting, claims or policy admin within insurance industry.\n\nClient Details\n\nOur client is one of the leading tier 1 reinsurance companies, founded in 1970, providing life & health, property and casualty reinsurance solutions to its clients. They are now looking for a life underwriting and claims officer to join the underwriting and claims team to handle life and medical underwriting and claims services/ applications and product development initiatives. The specialist teams operate in over 120 countries and they provide a broad range of innovative reinsurance solutions and an underwriting policy founded on profitability to their clients mostly insurers and large corporations\n\nDescription\n\nResponsible for providing high quality underwriting and claims adjudication services and support on client servicing, underwriting and claims assessments and daily BAU business\nAssist in product development activities like product design, business development, medical research and defining terms for innovative insurance solution for various products including Critical Illness, Life, Group, and Medical Insurance\nHandle underwriting and claims applications and activities including screening, data entry on new business and providing decisions for both life and health products\nEnhance team activities including review of reinsurance treaty agreement terms and conditions and monthly case monitoring report\nMaintain accurate records of company information include treaties, provisions and guidelines\n\nProfile\n\nBachelor's degree with major in risk management, insurance management, biology science or relevant discipline\nAt least 1-2 years of working experience in life and medical underwriting, claims or policy admin for group and individual within insurance industry\nRelevant reinsurance internship experience to reinsurance products is preferred\nStrong product knowledge in life and health/ medical\nExcellent attitudes including being highly motivated, observant, confident and willing to learn\nStrong English, Cantonese verbal and written skills\n\nJob Offer\n\nInternational and dynamic working environment\nChallenging and stimulating job tasks\nCompetitive packages and benefits\nMedical benefits\n15 days AL\n\nTo apply online please click the 'Apply' button below. For a confidential discussion about this role please contact Esther Liu on +852 2258 3537", "employment_types": ["Full Time", "Permanent"], "selling_points": [], "locations": ["Southern Area"], "categories": ["Accounting", "Others", "Insurance", "Others", "Public / Civil", "Others"], "post_time": "2022-01-11T16:02:21Z", "salary": {"currency": null, "max": null, "min": null, "period": "monthly", "term": null}, "salary_visible": false, "title_keywords": ["manager"], "responsibilities": ["control", "management", "data entry", "guidelines", "review", "quality", "teams", "monitoring", "product design", "maintain", "insurance", "report"], "requirements": {"degrees": ["degree", "bachelor"], "majors": ["risk management", "biology", "insurance", "science"], "languages": ["cantonese", "english"], "language_level": [], "hard_skills": ["dynamic"], "soft_skills": ["confident", "accurate", "responsible", "willing to learn", "motivated", "dynamic", "innovative"], "languages_combined": [{"language": "cantonese", "language_level": []}, {"language": "english", "language_level": []}]}, "experience_required": {"duration": ["at least 1-2 years", "1-2 years"], "field": ["underwriting", "insurance industry", "life underwriting", "admin", "medical"]}}]