[{"job_id": "100003009055674", "location_code": "hk", "company": "Hutchmed Group (HK) Limited", "job_title": "Senior Product Manager", "description": "Located in HKSTP, the Drug Safety Testing Centre (DSC) aims to facilitate the translation of promising therapeutics and medical devices from the pre-clinical phase to the clinical stage.\u00a0 This first of its kind facility adheres to the highest international and industry standards, including AAALAC and Good Laboratory Practices (GLP), which is an international standard prescribing a set of rigid and quality criteria for conducting studies, data collection and reporting. \u00a0It defines how preclinical data is required and accepted by different regulatory authorities (for example, China NMPA, US FDA and OECD).\u00a0 The facility commits to provide the GLP-compliant preclinical services on toxicology, genotoxicity, toxicokinetics, safety pharmacology, reproductive toxicology, ADME etc for facilitating the development of new drug.\n\n\nResponsibilities:\nFully understand the importance of pre-clinical animal study for human medicine research and drug development process; ensure a high level of animal welfare and work to improve the quality of life for laboratory animals.\nCarry out rodent\u2019s GLP and non-GLP study according to the designed protocol. \u00a0Experimental \u00a0procedures would include, but not limited to, clinical observations, different routes of administration, blood collections and live data acquisition etc.\nComplete the experimental records in accordance with GLP specifications and related standard operating procedures (SOP) within the facility.\nWork in a team to undertake technical and staff supervision/ management duties in connection with the operation of the facility.\nOn-the-job training will be provided.\nQualifications:\nApplicants should possess a Bachelor\u2019s degree or equivalent;\nBe self-motivated, responsible, empathetic, and curious; excellent communication, analytical and problem-solving skills; an interest in laboratory animal science and technology; and demonstrated commitment to continuing professional development in the field.\nWilling to join the pharmaceutical research and development industry and contribute to the cause of human medicine and health.\nGood command of spoken and written English and Chinese; fluent in Putonghua would be an advantage.\nExperience in animal husbandry, operation and maintenance of equipment for sanitation and sterilisation (e.g. autoclave), or inventory/record keeping will be an advantage but not essential.", "employment_types": ["Full Time", "Permanent"], "selling_points": [], "locations": ["Hung Hom"], "categories": ["Marketing / Public Relations", "Marketing - Brand / Product Management", "Medical Services", "Pharmaceutical"], "post_time": "2022-01-18T02:50:41Z", "salary": {"currency": null, "max": null, "min": null, "period": "monthly", "term": null}, "salary_visible": false, "title_keywords": ["senior product manager"], "responsibilities": ["reporting", "management", "maintenance", "data", "inventory", "quality", "procedures", "testing", "communication", "specifications", "data collection", "administration"], "requirements": {"degrees": ["degree", "bachelor"], "majors": [], "languages": ["putonghua", "english", "chinese"], "language_level": ["advantage", "good command", "fluent"], "hard_skills": ["animal science", "maintenance", "animal husbandry", "animal welfare", "problem-solving skills", "translation"], "soft_skills": ["communication", "problem-solving skills", "self-motivated", "responsible"], "languages_combined": [{"language": "putonghua", "language_level": ["fluent", "advantage"]}, {"language": "english", "language_level": ["good command"]}, {"language": "chinese", "language_level": ["good command"]}]}, "experience_required": {"duration": [], "field": ["operation", "maintenance"]}}, {"job_id": "100003009054509", "location_code": "hk", "company": "PERSOL Hong Kong", "job_title": "QA Assistant (Pharmaceutical industry/ Kwai Tsing area/ Attractive package)", "description": "Tasks and Responsibilities\n\nResponsible for analyzing the market of HUTCHMED products and therapeutic areas.\u00a0 Analyze, coordinate and support the information needs of preparing new product launch;\nFormulate integrated go-to-market plan of HUTCHMED products and launch tactics to maximize overall opportunity;\nDefine, monitor and achieve key performance metrics in achieving milestone to inform strategy and support execution;\nIntellectual curiosity about all aspects of our customers and business with a strong desire to persist in finding opportunities to maximize our business;\nStructured thinker and critical problem-solver; ability to distill and synthesize complex information from various resources to actionable insights;\nAbility to anticipate and rapidly respond to market and competitive changes in developing and executing brand strategies;\nProactively monitor external data, publications and their impact on future treatment algorithms, as well as potential impact on guidelines and pathways;\nDevelop annual budget and track expenses through the year;\nExperience successfully working in\u00a0cross functional matrix teams;\u00a0\nAbility to challenge the status quo with good rationale and logic; being provocative and creative in a productive fashion;\nMaintain strong compliance with all relevant internal policies, compliance and legal requirements.\n\n\u00a0Experience & Requirements\n\nMinimum of 5 years solid experience in pharmaceutical industry with experience in new product launch;\nBachelor Degree or above in Science;\nMarketing experience including strategy development and tactical execution;\nExcellent interpersonal skill with the ability to build working relations both internally and externally;\nStrong verbal and written communications skills;\nStrong commercial orientation and business acumen;\nStrength managing complexity and multiple competing priorities;\nExperience influencing without direct authority and working successfully with cross-functional teams and multiple agency partners;\nA creative and dynamic team player with strategic and marketing sense;\nExperience in oncology (and immunology) areas is preferred;\nProficiency in both spoken and written English and Chinese;\nJob title is subjected to the candidate\u2019s qualification and experience.\n\n\n\nSalary and benefits will be commensurate with experience.\u00a0Please send detailed resume with\u00a0current and\u00a0expected salary\u00a0by clicking \u201cAPPLY NOW\u201d in the below.\n\nWe are an equal opportunity employer and welcome applications from all qualified candidates. The information provided will be treated in strict confidence and used only for consideration of application for relevant/similar post(s) within the CK Hutchison Group of Companies. Applicants not having heard from us within four weeks from the date of this advertisement may consider their application unsuccessful. All personal data of unsuccessful applicants will be destroyed after the recruitment exercise when no longer required.", "employment_types": ["Full Time", "Permanent"], "selling_points": ["Quality Assurance", "Passionate in Pharmaceutical/ FMCG industry", "Double pay/ bonus/ allowances"], "locations": ["Tsing Yi"], "categories": ["Sciences, Lab, R&D", "Chemical", "Medical Services", "Pharmaceutical", "Manufacturing", "Quality Assurance, Control & Testing / ISO"], "post_time": "2022-01-17T09:49:24Z", "salary": {"currency": null, "max": null, "min": null, "period": "monthly", "term": null}, "salary_visible": false, "title_keywords": ["qa assistant"], "responsibilities": ["data", "guidelines", "policies", "brand strategies", "monitor", "performance metrics", "developing", "develop", "coordinate", "budget", "expenses", "teams", "executing", "maintain", "plan", "compliance"], "requirements": {"degrees": ["degree or above", "bachelor"], "majors": ["science"], "languages": ["english", "chinese"], "language_level": ["proficiency"], "hard_skills": ["dynamic", "acumen"], "soft_skills": ["marketing sense", "interpersonal skill", "dynamic", "business acumen", "team player", "creative"], "languages_combined": [{"language": "english", "language_level": ["proficiency"]}, {"language": "chinese", "language_level": ["proficiency"]}]}, "experience_required": {"duration": ["minimum of 5 years"], "field": ["pharmaceutical", "development", "agency", "marketing"]}}, {"job_id": "100003009054380", "location_code": "hk", "company": "St. James' Settlement", "job_title": "Dispenser (Contract)\u3008Ref: PCP/07122\u3009", "description": "Our client, a Japanese company, is now seeking for a high caliber individual to join their team as\u00a0QA Assistant (Ref: #44478)\n\n\nJob Descriptions:\n\nSupport and communicate with the QA department to ensure smooth daily operations\nCheck and prepare testing reports for the management to review\nWork closely with Supervisor to monitor the lab testing progress\nMaintain close relationships with testing companies\u00a0\n\nRequirements:\n\nHigher Diploma or above, preferably in Chemistry or Biology related discipline\nAt least 2 years of QA/ QC related working experience\nWorking experience in pharmaceutical/ FMCG industry is a bonus\nSpeaks good command of English and Mandarin\nGood communication and time management skills\n\nBenefits:\n\n5 days work\nDouble pay\nDiscretionary bonus\nOT allowance\nTransportation allowance\nBanking holiday\nMedical insurance + body check\n\nInterested parties please quote\u00a0#44478\u00a0and send your application (please include your expected salary) via email to\u00a0Apply Now\u00a0or\u00a0gladys @persolhk.com.\u00a0For any enquiries, please do not hesitate to contact me at\u00a0(852) 2971-2551.\n\nPlease note that only short listed candidate will be notified.\n\nWe also have various job vacancies from our well-established clients in all kinds of fields, please feel free to contact us. We are always willing to give you support on your career development.\n\nOur company website:\u00a0http://www.persolhk.com\n\nAll information received will be treated in strict confidence and used for recruitment purpose only.", "employment_types": ["Full Time", "Contract"], "selling_points": ["Dip./Cert in Pharmaceutical Studies or relevant", "Relevant exp in drug Dispensing is preferable", "Good in both written & spoken Chinese & English"], "locations": ["Wan Chai"], "categories": ["Medical Services", "Pharmaceutical", "Public / Civil", "Social Services - Community / Non-profit Organization"], "post_time": "2022-01-17T09:19:01Z", "salary": {"currency": null, "max": null, "min": null, "period": "monthly", "term": null}, "salary_visible": false, "title_keywords": ["dispenser"], "responsibilities": ["communicate with", "management", "review", "monitor", "testing", "daily operations", "maintain", "reports"], "requirements": {"degrees": ["higher diploma or above"], "majors": ["biology", "chemistry"], "languages": ["english", "mandarin"], "language_level": ["good command"], "hard_skills": ["fmcg industry"], "soft_skills": ["communication", "time management skills"], "languages_combined": [{"language": "english", "language_level": ["good command"]}, {"language": "mandarin", "language_level": ["good command"]}]}, "experience_required": {"duration": ["at least 2 years"], "field": ["related", "pharmaceutical", "fmcg", "qa"]}}, {"job_id": "100003009055993", "location_code": "hk", "company": "KOS International Limited", "job_title": "Marketing Manager (Pharmaceuticals)", "description": "Charity Services\n\n\n\nRequirement:\n\nlPossess a Diploma or Certificate in Pharmaceutical Studies or Dispensing Practice\n\nlRelevant experience in drug Dispensing is preferable\n\nlPro-active, strong interest in providing outreach service in Philanthropic Community Pharmacy\n\nlExcellent communication skills\n\nlGood in both written & spoken Chinese & English\n\nJob Duties:\n\nlProvides Dispensing services under the supervision of Registered Pharmacist\n\nlJob related to pharmacy development such as system management, documentation, data analysis etc.\n\nInterested persons please apply with full resume via APPLY NOW\u00a0on or before 31/01/2022.\n**When recruiting staff for job positions relating to services for child or mentally incapacitated persons, we shall request applicants to undergo the Sexual Conviction Record Check.**\n\n\u300cPersonal data collected will be strictly used for the recruitment exercise only. Unsuccessful applications will be destroyed one year after the closing date.\u300d\n\n\n", "employment_types": ["Full Time", "Permanent"], "selling_points": ["Global pharmaceutical company", "Competitive Salary", "Pivotal leadership role"], "locations": ["Not Specified"], "categories": ["Medical Services", "Specialist", "Others", "Pharmaceutical"], "post_time": "2022-01-18T03:10:23Z", "salary": {"currency": null, "max": null, "min": null, "period": "monthly", "term": null}, "salary_visible": false, "title_keywords": ["marketing manager"], "responsibilities": ["management", "data analysis", "recruitment", "documentation", "personal data"], "requirements": {"degrees": ["certificate", "diploma"], "majors": [], "languages": ["english", "chinese"], "language_level": [], "hard_skills": [], "soft_skills": ["communication skills", "active"], "languages_combined": [{"language": "english", "language_level": []}, {"language": "chinese", "language_level": []}]}, "experience_required": {"duration": [], "field": []}}, {"job_id": "100003009055673", "location_code": "hk", "company": "Hutchmed Group (HK) Limited", "job_title": "Senior Manager / Manager of Sustainability", "description": "About the Client\n\nOur client is a listed pharmaceutical company with international presence, known for their innovative nutritional product pipeline that has been saving patient's lives. A rare opportunity has arisen and they are now looking for a Marketing Manager join their Hong Kong team.\n\nAbout the Role\n\nReporting to the General Manager and leading a marketing team, you are responsible for all marketing-related aspects for the ethical nutrition product pipeline for the company. This includes developing and implementing effective marketing strategies and tactics, sales training and education and executing marketing plans to ensure revenue goals are met. Key success of the Marketing Manager is the ability to develop successful partnerships with key opinion leaders, sales team and to modify strategies and tactics when needed based on the customers' demands and emerging trends. The role is responsible for new product launches and demonstrating commitment to patient safety and product quality by maintaining compliance with regulations.\n\nRequirements\n\nDegree holder in Science related discipline\nMinimum 8 years' product marketing experience working in a multinational pharmaceutical company, ideally with ethical nutrition marketing experience\nStrong market sense and knowledge, with previous experience lauching successful marketing campaigns to drive market and revenue share\nExcellent presentation and communication skills\n\nClick \"Apply Now\" to apply for this position or call Patsy Cheung at +852 3180 4917 for a confidential discussion. All information collected will be kept in strict confidence and will be used for recruitment purpose only.", "employment_types": ["Full Time", "Permanent"], "selling_points": [], "locations": ["Hung Hom"], "categories": ["Professional Services", "Business Analysis / Data Analysis", "Business Consultancy", "Medical Services", "Pharmaceutical"], "post_time": "2022-01-18T02:50:40Z", "salary": {"currency": null, "max": null, "min": null, "period": "monthly", "term": null}, "salary_visible": false, "title_keywords": ["senior manager", "manager"], "responsibilities": ["regulations", "reporting", "marketing strategies", "maintaining", "marketing plans", "compliance", "quality", "developing", "develop", "communication", "executing", "sales team", "marketing campaigns", "recruitment"], "requirements": {"degrees": ["degree holder"], "majors": ["science"], "languages": [], "language_level": [], "hard_skills": [], "soft_skills": ["communication skills", "confidence", "responsible", "ethical", "patient", "strong market sense", "innovative", "presentation"], "languages_combined": []}, "experience_required": {"duration": ["minimum 8 years"], "field": ["marketing", "pharmaceutical company"]}}, {"job_id": "100003009053796", "location_code": "hk", "company": "Hind Wing Company Limited", "job_title": "Pharmaceutical Warehouse Staff", "description": "Responsibilities\nSupport the development of corporate sustainability strategies that reflect the environmental, social, and governance issues important to HUTCHMED;\nCo-ordinate sustainability activities across Hong Kong, Shanghai, Suzhou and New Jersey operations;\nOversee implementation of sustainability goals and targ\u00adets across the R&D, manufacturing, China comm\u00adercial joint ventures and U.S. R&D / comm\u00adercial businesses;\nImprove implementation methodologies, set annual milestones, and establish reporting mechanisms to inform employees and executive leadership on progress;\nSupport communication with investors and investment analysts regarding HUTCHMED\u2019s sustainability position and progress (e.g. large mutual funds).\nCommunicate with ESG research firms and indices (e.g. MSCI, ISS Oekom, Sustainalytics);\nSupport the Board of Directors\u2019 Sustainability Committee in strategic discussions and the exec\u00adution of sustain\u00adability focus areas;\nProduce an annual corporate sustain\u00adability report, including data collection, measure\u00adment & analysis, stakeholder engagement and content devel\u00adopment;\nLiaise with the corporate public relations, investor rela\u00adtions, commercial, marketing, Human Resources technical teams (mainly China & U.S.) to coordinate and drive sustain\u00adability positioning and actions;\nOrganise internal sustainability events and other enga\u00adgements to promote and inspire staff.\nRequirements\n\n8 years minimum experience in a corporate environment in sustainability, compli\u00adance or finance, with some track record of delivering sustain\u00adability programmes;\nAbility to influence change with internal business part\u00adners without direct reporting relationships;\nComfortable working with all levels of employees, from senior executives to front-line individual contributors;\nStrong analytic, written and oral communication skills in English and preferably Mandarin Chinese;\nAbility to manage and work collaboratively with cross-functional and cross-geographical working groups;\nAbility to clearly articulate business value of sustain\u00adability investment.\nAbility to multi-task, set priorities, and meet tight deadlines;\nEntrepreneurial spirit to identify and act on new opportunities or improvements;\nEducated to degree level in a sustainability, or business-related subject, or relevant work experience;\nInterest or expertise in healthcare industry.\n\n\nSalary and benefits will be commensurate with experience.\u00a0Please send detailed resume with\u00a0current and\u00a0expected salary\u00a0by clicking \u201cAPPLY NOW\u201d in the below.\nWe are an equal opportunity employer and welcome applications from all qualified candidates. The information provided will be treated in strict confidence and used only for consideration of application for relevant/similar post(s) within the CK Hutchison Group of Companies. Applicants not having heard from us within four weeks from the date of this advertisement may consider their application unsuccessful. All personal data of unsuccessful applicants will be destroyed after the recruitment exercise when no longer required.", "employment_types": ["Full Time"], "selling_points": ["5-day working week", "medical insurance", "warehouse experience"], "locations": ["North Point"], "categories": ["Medical Services", "Pharmaceutical"], "post_time": "2022-01-17T07:31:28Z", "salary": {"currency": null, "max": null, "min": null, "period": "monthly", "term": null}, "salary_visible": false, "title_keywords": ["staff"], "responsibilities": ["communicate with", "reporting", "operations", "analysis", "teams", "implementation", "communication", "coordinate", "data collection", "liaise with", "report"], "requirements": {"degrees": ["degree"], "majors": ["business"], "languages": ["mandarin chinese", "english"], "language_level": [], "hard_skills": [], "soft_skills": ["communication skills", "oral", "meet tight deadlines", "multi-task", "articulate"], "languages_combined": [{"language": "mandarin chinese", "language_level": []}, {"language": "english", "language_level": []}]}, "experience_required": {"duration": ["8 years"], "field": ["related", "finance", "business", "sustainability"]}}, {"job_id": "100003009055239", "location_code": "hk", "company": "Karen Pharmaceutical Company Limited", "job_title": "Laboratory Assistant", "description": "Job Highlight\n\n-\u00a0 Support, Direct, Manage overall Warehouse & Logistics Operation in accordance to Pharmaceutical Warehouse Standard\n\n-\u00a0 Report/Work with to Senior Warehouse Manager & Management\n\n\u00a0Key Responsibilities\n\n-\u00a0 Manage the daily operation (includes logistics operations) of a pharmaceutical warehouse\n\n-\u00a0 Ensure accurate, smooth operation of the entire supply chain management from importation of stock, picking of goods to delivery to end users\n\n-\u00a0 Oversee and ensure accurate stock management in entire supply chain\n\n-\u00a0 Assist with and Handle routine warehouse audits\n\n-\u00a0 Work with warehouse, logistics and sales team on stock management, orders and shipment update.\n\nQualifications, Skills\n\nPrior Warehouse experience\nPrior pharmaceutical warehouse experience will be considered with highest priority\nForm 5 or DSE above\nBasic English\nBasic Computer Operation Knowledge\nAble to handle physical goods movement and fork lift\nGood problem solving skill, Team Player\nAble to work independently as well as with team members\n\nInterested parties please send full resume with current & expected salary", "employment_types": ["Full Time"], "selling_points": [], "locations": ["Tuen Mun Area"], "categories": ["Sciences, Lab, R&D", "Laboratory", "Medical Services", "Pharmaceutical", "Manufacturing", "Quality Assurance, Control & Testing / ISO"], "post_time": "2022-01-18T01:54:32Z", "salary": {"currency": null, "max": null, "min": null, "period": null, "term": null}, "salary_visible": false, "title_keywords": ["laboratory assistant"], "responsibilities": ["management", "stock management", "operations", "daily operation", "logistics", "sales team", "audits", "report"], "requirements": {"degrees": ["form 5", "dse"], "majors": [], "languages": ["english"], "language_level": ["basic"], "hard_skills": ["problem solving", "basic", "computer operation knowledge"], "soft_skills": ["work independently", "team player", "smooth", "problem solving skill", "accurate"], "languages_combined": [{"language": "english", "language_level": ["basic"]}]}, "experience_required": {"duration": [], "field": ["pharmaceutical"]}}, {"job_id": "100003009055183", "location_code": "hk", "company": "Karen Pharmaceutical Company Limited", "job_title": "QC Technician", "description": "Key Roles and Responsibilities\n\nPerform sampling and chemical testing on Purified water, Raw materials, intermediates, finished products and stability samples\nUndertake maintenance and calibration of related analytical instruments\nRevision of SOP documents\n\nQualifications and Experience\n\nIn Science subjects, preferably in Pharmaceutical Science/Chemistry related discipline\n1-2 years working experience in Quality Control of pharmaceutical or commercial laboratory is preferred\nFamiliar with pharmacopeia (BP/USP/CP) and GMP requirements as per FDA, PIC/S\nProficiency in MS Words and Excel\nSelf-motivated and responsible\nGood command of English and Chinese\nFresh graduates are also considered\n\nHow to Apply\n\nYou are invited to send in your application and CV stating the position\u00a0(with reference number)\u00a0you are applying for together with your current and expected salary, apply via JobsDB\u00a0on or before 17 February 2022.\n\nKaren Pharmaceutical Company Limited is an Equal Opportunities Employer. Personal data provided by job applicants will be used strictly in accordance with our personal data policy and for recruitment purposes only. We aim to respond to successful applicants within 8 weeks and related information will be kept in our file for up to 12 months for other suitable vacancies in our organization and thereafter destroyed.", "employment_types": ["Full Time"], "selling_points": [], "locations": ["Tuen Mun Area"], "categories": ["Sciences, Lab, R&D", "Laboratory", "Medical Services", "Pharmaceutical", "Manufacturing", "Quality Assurance, Control & Testing / ISO"], "post_time": "2022-01-18T01:41:36Z", "salary": {"currency": null, "max": null, "min": null, "period": null, "term": null}, "salary_visible": false, "title_keywords": ["qc technician"], "responsibilities": ["maintenance", "testing", "recruitment", "quality control", "personal data"], "requirements": {"degrees": [], "majors": [], "languages": ["english", "chinese"], "language_level": ["good command"], "hard_skills": ["excel", "maintenance", "ms words"], "soft_skills": ["self-motivated", "responsible"], "languages_combined": [{"language": "english", "language_level": ["good command"]}, {"language": "chinese", "language_level": ["good command"]}]}, "experience_required": {"duration": ["1-2 years"], "field": ["pharmaceutical", "quality control", "commercial laboratory"]}}, {"job_id": "100003009053306", "location_code": "hk", "company": "DKSH Hong Kong Limited", "job_title": "Manager, Operations Management (Healthcare / Supply Chain background)", "description": "Key Roles and Responsibilities\n\nPerform sampling and chemical testing on Purified water, Raw materials, intermediates, finished products and stability samples\nUndertake maintenance and calibration of related analytical instruments\nRevision of SOP documents\n\nQualifications and Experience\n\nIn Science subjects, preferably in Pharmaceutical Science/Chemistry related discipline\n1-2 years working experience in Quality Control of pharmaceutical or commercial laboratory is preferred\nFamiliar with pharmacopeia (BP/USP/CP) and GMP requirements as per FDA, PIC/S\nProficiency in MS Words and Excel\nSelf-motivated and responsible\nGood command of English and Chinese\nFresh graduates are also considered\n\nHow to Apply\n\nYou are invited to send in your application and CV stating the position\u00a0(with reference number)\u00a0you are applying for together with your current and expected salary, apply via JobsDB\u00a0on or before 17 February 2022.\n\nKaren Pharmaceutical Company Limited is an Equal Opportunities Employer. Personal data provided by job applicants will be used strictly in accordance with our personal data policy and for recruitment purposes only. We aim to respond to successful applicants within 8 weeks and related information will be kept in our file for up to 12 months for other suitable vacancies in our organization and thereafter destroyed.", "employment_types": ["Full Time", "Permanent"], "selling_points": ["Operations management", "Supply Chain Management", "Healthcare"], "locations": ["Southern Area"], "categories": ["Transportation & Logistics", "Supply Chain", "Medical Services", "Pharmaceutical"], "post_time": "2022-01-17T06:44:02Z", "salary": {"currency": null, "max": null, "min": null, "period": "monthly", "term": null}, "salary_visible": false, "title_keywords": ["operations", "manager"], "responsibilities": ["maintenance", "testing", "recruitment", "quality control", "personal data"], "requirements": {"degrees": [], "majors": [], "languages": ["english", "chinese"], "language_level": ["good command"], "hard_skills": ["excel", "maintenance", "ms words"], "soft_skills": ["self-motivated", "responsible"], "languages_combined": [{"language": "english", "language_level": ["good command"]}, {"language": "chinese", "language_level": ["good command"]}]}, "experience_required": {"duration": ["1-2 years"], "field": ["pharmaceutical", "quality control", "commercial laboratory"]}}, {"job_id": "100003009054916", "location_code": "hk", "company": "DCH Auriga (Hong Kong) Limited", "job_title": "Senior Manager - Medical Device / Diagnostics Equipment", "description": "About the job:\n\n\nAssist the Production Manager in organizing and coordinating daily operations of Production Department.\nPrepare Batch Production Records, Validation/Qualification documents and relevant SOPs.\nMonitor and check records & logbooks in production areas to ensure that they are properly and timely filled out and maintained.\nEnsure entire production flows and processes are strictly compliant with GMP requirements and internal policy.\nAssistant in developing, implementing and maintaining the documentation system, including the SOPs and other production documents.\nMonitor the equipment and cleanroom hygiene according to the approval GMP procedure.\nParticipate in induction and on-job training to production staff.\nOther ad-hoc tasks as assigned by supervisors.\n\nAbout the talent:\n\n\nHigher Diploma or above in Science / Pharmaceutical or related subjects.\nRelevant experience in Food or GMP pharmaceutical manufacturing is preferred but not essential.\nFamiliar with MS office and Chinese word processing.\nHardworking, initiative, self-motivated and fast learner.\nAble to work under pressure and willing to work overtime.\nGood interpersonal skill and communication skill.\nGood command in written and spoken Chinese and English.\n\nWhat we offer:\n\nCareer with the market leader in health product sector from Hong Kong.\nDynamic working culture with great team spirit.\nShuttle to/from Yau Tong, Kowloon Tong, Tai Wai, Taipo, Tsuen Wan, Tuen Mun, Tin Shui Wai and Causeway Bay.\nRapid growth opportunities for strong performers.\nStaff purchase discount.\nCasual attire at work.\n\nInterested parties, please send full resume with last & expected salary and date of available by clicking \u2018Apply Now\u2019\n\nPersonal data collected is for recruitment purpose only.\n\nFor corporate information, please visit:\u00a0www.vitagreen.com", "employment_types": ["Full Time", "Permanent"], "selling_points": [], "locations": ["Kwai Fong"], "categories": ["Sales, CS & Business Devpt", "Business Development", "Medical Services", "Pharmaceutical", "Sales - Sales Management"], "post_time": "2022-01-17T16:21:10Z", "salary": {"currency": null, "max": null, "min": null, "period": "monthly", "term": null}, "salary_visible": false, "title_keywords": ["senior manager"], "responsibilities": ["maintaining", "ad-hoc tasks", "monitor", "developing", "communication", "hygiene", "daily operations", "sops", "documentation", "work under pressure"], "requirements": {"degrees": ["higher diploma or above"], "majors": ["science"], "languages": ["english", "chinese"], "language_level": ["good command"], "hard_skills": ["documentation", "batch", "chinese word processing", "ms office"], "soft_skills": ["self-motivated", "work overtime", "timely", "communication skill", "interpersonal skill", "fast learner", "initiative", "hardworking", "work under pressure"], "languages_combined": [{"language": "english", "language_level": ["good command"]}, {"language": "chinese", "language_level": ["good command"]}]}, "experience_required": {"duration": [], "field": ["pharmaceutical", "food", "manufacturing", "relevant experience"]}}, {"job_id": "100003009053071", "location_code": "hk", "company": "Li Chung Shing Tong (Holdings) Limited", "job_title": "Assistant QA Officer/QA Assistant", "description": "Responsibilities:\n\nBe responsible for overseeing the implementation of the assigned cluster (Hong Kong and Macau) sales strategy through the provision of leadership and direction to the sales team\nManaging and developing growth of business and for coordinating company activity within a designated territory for both active client accounts and prospective accounts.\nIdentifying key decision makers and stakeholders across each account and effectively implement our sales cycle to ensure positive tender outcome\nWorking closely with internal business partners to develop and implement specific marketing strategies.\nBuild and maintain sustainable strategic business relationships with key clients\nOptimize the use of resources to cover market potential to achieve the operating plan\nMonitor performance objectives on a regular and timely basis in accordance with agreed time-frame.\nManage, develop, coach and motivate the sales force to develop their skill to ensure that a high professional standard is achieved and monthly sales target and KPI target are met\nAnalyse month end sales results by product, cluster; Review reports to detect sales, market share and activity trends for sales team\nIdentify business opportunities through analysis of clients and trends within the area.\nRequirements:\n\nUniversity graduate in Science or related disciplines\nMinimum 6 years' proven sales experience within medical devices industry with at least 3 years' managment experience; experience in Macau healthcare industry will be adavantage\nSolid technical background with understanding and /or hands-on experience in the Life Science and/or Medical Device market\nAdvanced negotiation, problem solving and influencing skills\nDemonstration of strong team-working, especially in a matrix environment\nGood Persuasive ability and planning & organizing skills\nProficiency in written and spoken English, Cantonese and Mandarin\nAll applications received will be used exclusively for recruitment purposes only. Applicants who are not contacted within 8 weeks should consider their application unsuccessful for the position advertised. Data supplied by applicants will be kept for 6 months.", "employment_types": ["Full Time"], "selling_points": [], "locations": ["Tai Po Area"], "categories": ["Medical Services", "Pharmaceutical", "Manufacturing", "Quality Assurance, Control & Testing / ISO"], "post_time": "2022-01-17T05:34:57Z", "salary": {"currency": null, "max": null, "min": null, "period": null, "term": null}, "salary_visible": false, "title_keywords": ["assistant qa officer", "qa assistant"], "responsibilities": ["sales results", "marketing strategies", "identify business opportunities", "monitor performance", "market potential", "sales target", "review", "implementation", "developing", "develop", "analysis", "maintain", "sales team", "reports", "tender", "plan", "analyse"], "requirements": {"degrees": ["university graduate"], "majors": ["related disciplines", "science"], "languages": ["cantonese", "english", "mandarin"], "language_level": ["proficiency"], "hard_skills": ["problem solving"], "soft_skills": ["persuasive", "negotiation", "advanced", "problem solving", "hands-on"], "languages_combined": [{"language": "cantonese", "language_level": ["proficiency"]}, {"language": "english", "language_level": ["proficiency"]}, {"language": "mandarin", "language_level": ["proficiency"]}]}, "experience_required": {"duration": ["at least 3 years", "minimum 6 years"], "field": ["healthcare industry", "medical devices industry", "medical device"]}}, {"job_id": "100003009053070", "location_code": "hk", "company": "Li Chung Shing Tong (Holdings) Limited", "job_title": "Assistant Engineer", "description": "Key roles and Responsibilities:\n\nTo support the routine QA operations, includes the implementation, review and maintenance of the QA system\nTo prepare SOP and GMP documents for the compliance of GMP standard\nTo assist in product registration, GMP training and records implementation.\u00a0\nTo perform ad hoc projects as assigned\u00a0\n\nQualifications and Experience\n\nHigher Diploma or Degree in Chinese Medicine/ Pharmaceutical/Food Science or related disciplines \u00a0\n2-3 yeas relevant working experience preferably in Chinese medicine/health/ pharmaceutical industry\u00a0\nSelf- motivated, willing to learn and a good team player\nGood interpersonal and communication skills\u00a0\nGood command in spoken and written English and Chinese\nCandidate with less experience will be considered as QA Assistant", "employment_types": ["Full Time"], "selling_points": [], "locations": ["Tai Po Area"], "categories": ["Engineering", "Manufacturing & Production", "Manufacturing", "Others", "Medical Services", "Pharmaceutical"], "post_time": "2022-01-17T05:34:57Z", "salary": {"currency": null, "max": null, "min": null, "period": "monthly", "term": null}, "salary_visible": false, "title_keywords": ["assistant engineer"], "responsibilities": ["maintenance", "operations", "review", "compliance", "implementation", "communication", "ad hoc projects", "prepare sop"], "requirements": {"degrees": ["diploma", "degree"], "majors": ["related disciplines", "food science"], "languages": ["english", "chinese"], "language_level": ["good command"], "hard_skills": ["maintenance"], "soft_skills": ["communication skills", "good team player", "willing to learn", "motivated", "interpersonal"], "languages_combined": [{"language": "english", "language_level": ["good command"]}, {"language": "chinese", "language_level": ["good command"]}]}, "experience_required": {"duration": [], "field": ["pharmaceutical", "relevant working experience", "qa"]}}, {"job_id": "100003009050333", "location_code": "hk", "company": "Healthcore Consultancy Limited", "job_title": "Regulatory Affairs Specialist (pharmaceutical company)", "description": "\u00a0Key roles and Responsibilities:\nResponsible for engineering activities, include machinery maintenance, repairing, installation and testing.\nPrepare machinery documentation in a GMP Pharmaceutical facility.\nMonitor and review daily operations of building services system and manufacturing machineries.\nAssist in negotiation and coordination with contractors, vendors and consultants.\nPerform ad-hoc duties as required.\n\nQualifications and Experience:\n\nBachelor's Degree in Engineering/Mechanical Engineering or related.\n2-3 years relevant experience in E & M service and machinery maintenance.\nHolder of\u00a0Registered Electrical Worker Certificate (Grade A) is preferred\nExperience in Practice of Occupational Safety and Health is preferred\nExperience in Good Manufacturing Practice and Cleanroom operation are preferred.\nGood communication and problem-solving skill\nProficient in MS Office and AutoCAD\nProficiency in both spoken and written English and Chinese\nHow to Apply\nYou are invited to send in your application and CV stating your latest and expected salary\u00a0 by Clicking \"Apply Now\". \u00a0\nLi Chung Shing Tong (Holdings) Limited is an equal opportunities employer. The information provided will be treated in strict confidence and used only for consideration of application for relevant/similar post(s).\u00a0 All personal data of unsuccessful applicants will be destroyed within 6 months.", "employment_types": ["Full Time"], "selling_points": ["Regulatory Affairs Specialist", "Pharmaceuticals", "Multi-National company"], "locations": ["Not Specified"], "categories": ["Professional Services", "Legal & Compliance", "Sciences, Lab, R&D", "Life Science", "Medical Services", "Pharmaceutical"], "post_time": "2022-01-14T10:08:54Z", "salary": {"currency": null, "max": null, "min": null, "period": "monthly", "term": null}, "salary_visible": false, "title_keywords": ["specialist"], "responsibilities": ["installation", "maintenance", "review", "monitor", "coordination with", "testing", "communication", "daily operations", "ad-hoc duties", "documentation", "personal data"], "requirements": {"degrees": ["certificate", "degree", "bachelor"], "majors": ["engineering", "mechanical engineering"], "languages": ["english", "chinese"], "language_level": ["proficiency"], "hard_skills": ["maintenance", "problem-solving", "documentation", "ms office", "autocad"], "soft_skills": ["confidence", "negotiation", "responsible", "problem-solving", "communication", "coordination", "ad-hoc duties"], "languages_combined": [{"language": "english", "language_level": ["proficiency"]}, {"language": "chinese", "language_level": ["proficiency"]}]}, "experience_required": {"duration": ["2-3 years"], "field": ["operation", "manufacturing", "relevant experience", "maintenance"]}}, {"job_id": "100003009055699", "location_code": "hk", "company": "Vital Base International Ltd", "job_title": "Senior Sales executive  & Sales Executive   - Medical Industry", "description": "HealthCore is a professional recruitment company specializing in the healthcare & life science industry. HealthCore is currently helping one of its clients, a multi-national pharmaceutical company, to recruit a Regulatory Affairs Specialist.\n\nGeneral\u00a0Job Responsibilities:\n\nManage and ensure compliance for all regulatory affairs / product registration related issues & activities\nMeet expected\u00a0product registration timelines\nKeep updated with regulatory affairs trend & development; evaluate, design and implement effective strategies\nMaintain excellent communication and relation with related external authorities and internal parties\nKeep proper and updated documentation and records\u00a0\n\nQualifications / Skills:\n\n1+ year related work experience\u00a0\nUniversity degree holder\nExcellent communication and organizational skills\nGood command of English and Chinese\u00a0\n\nInterested candidates please send CV\u00a0via the \"Apply Now\" button. Personal data collected will be used for recruitment purposes only.", "employment_types": ["Full Time"], "selling_points": ["Science-related degree holder", "Experience in pharmaceutical sales/PR company", "Project management; Business Development;"], "locations": ["Kwai Tsing Area"], "categories": ["Sales, CS & Business Devpt", "Business Development", "Marketing / Public Relations", "Marketing - Brand / Product Management", "Medical Services", "Pharmaceutical"], "post_time": "2022-01-18T02:52:04Z", "salary": {"currency": null, "max": null, "min": null, "period": "monthly", "term": null}, "salary_visible": false, "title_keywords": ["senior sales executive", "sales executive"], "responsibilities": ["design", "ensure compliance", "evaluate", "communication", "maintain", "recruitment", "documentation", "internal parties"], "requirements": {"degrees": ["university degree"], "majors": [], "languages": ["english", "chinese"], "language_level": ["good command"], "hard_skills": ["documentation"], "soft_skills": ["communication", "organizational skills"], "languages_combined": [{"language": "english", "language_level": ["good command"]}, {"language": "chinese", "language_level": ["good command"]}]}, "experience_required": {"duration": ["1+ year"], "field": ["related"]}}, {"job_id": "100003009054357", "location_code": "hk", "company": "Zimmer Asia (HK) Limited", "job_title": "Sales Representatives / Senior Sales Representative / Sales Supervisor", "description": "Requirements:\n\nTertiary graduate in Science or related field\nAt least 2 years working experience in marketing, sales or event management, preferable in pharmaceutical industry or PR field\nStrong presentation and communication skill\nGood command of both spoken and written in English, preferable to comprehend clinical papers.\nSelf-motivated, sales-oriented and a good team-player\n\n\u00a0Responsibilities:\n\nReport to Senior Project Manager\nExplore new marketing opportunities in pharmaceutical industry\nDevelop and maintain good rapport with pharmaceutical clients\nLiaise closely with internal editorial team and in-house production team to ensure high quality projects are delivered as scheduled\nDevelop and implement clients\u2019 PR events, campaigns and promotion plans\nAchieve individual sales target\n\nAttractive remuneration package will be offered to the right candidate with MPF and medical insurance. Interested parties, please send us your CV together with current and expected salary and the earliest available date.\n\n\u00a0If you have any queries regarding this position, please feel free to contact us through email. Information provided by applicants will be treated in strict confidence and used solely for recruitment purposes.", "employment_types": ["Full Time", "Permanent"], "selling_points": [], "locations": ["Cheung Sha Wan"], "categories": ["Sales, CS & Business Devpt", "Business Development", "Medical Services", "Pharmaceutical", "Sales - Sales Management"], "post_time": "2022-01-17T09:15:53Z", "salary": {"currency": null, "max": null, "min": null, "period": "monthly", "term": null}, "salary_visible": false, "title_keywords": ["senior sales", "representative", "sales supervisor", "sales"], "responsibilities": ["liaise", "mpf", "sales target", "quality", "develop", "maintain", "plans", "insurance", "report"], "requirements": {"degrees": [], "majors": [], "languages": ["english"], "language_level": ["good command"], "hard_skills": [], "soft_skills": ["team-player", "self-motivated", "communication skill", "presentation"], "languages_combined": [{"language": "english", "language_level": ["good command"]}]}, "experience_required": {"duration": ["at least 2 years"], "field": ["pharmaceutical", "management", "marketing", "pr"]}}, {"job_id": "100003009048321", "location_code": "hk", "company": "DKSH Hong Kong Limited", "job_title": "Manager, Regulatory Affairs", "description": "\u00a0DUTIES AND RESPONSIBILITIES:\n\n\u00a0Career Level: Junior / Mid Level\n\nPromote & provide product knowledge to healthcare professionals\nProvide in-service technical support to healthcare professionals in operating theatre\nDrive sales growth & customer relationship management in assigned territories\nDevelop strategic plans to achieve sales objectives and other qualitative objectives\nManage and support sales & market analysis and operations in assigned territories\nAssist to execute marketing activities, campaign, medical educations programs and projects\u00a0\u00a0\n\nKEY REQUIREMENTS:\n\n\nUniversity graduate,\u00a0preferably degree holder in science or registered nurse\u00a0Minimum 1 year solid experience in the medical device field.\u00a0New graduate would be considered\nStrong team work\u00a0and interpersonal skills\nExcellent communication skill\nProficiency in English\nSpecial Requirements: Science / Nursing / Medical-related background is preferred qualifications see above\u00a0\u00a0\n\nAn attractive remuneration package will be given to the qualified candidate.\u00a0 Interest parties, please send your full resume with current and expected salary\u00a0by clicking Apply Now\u00a0\u00a0", "employment_types": ["Full Time", "Permanent"], "selling_points": ["People management experience", "Minimum of 10 years\u2019 relevant experience", "Degree holder in Pharmaceutical Science"], "locations": ["Tsing Yi"], "categories": ["Medical Services", "Pharmaceutical"], "post_time": "2022-01-14T06:13:54Z", "salary": {"currency": null, "max": null, "min": null, "period": "monthly", "term": null}, "salary_visible": false, "title_keywords": ["manager"], "responsibilities": ["management", "strategic plans", "technical support", "operations", "develop", "market analysis", "drive sales"], "requirements": {"degrees": ["university graduate", "degree holder"], "majors": ["science"], "languages": ["english"], "language_level": ["proficiency"], "hard_skills": [], "soft_skills": ["communication skill", "interpersonal skills"], "languages_combined": [{"language": "english", "language_level": ["proficiency"]}]}, "experience_required": {"duration": ["minimum 1 year"], "field": ["medical device field"]}}, {"job_id": "100003009050336", "location_code": "hk", "company": "Abbott Laboratories Ltd.", "job_title": "Medical Representative / Senior Sales Specialist", "description": "Key Responsibilities:\n\nSafety & Security Compliance\nImplementation of the Group\u2019s/Company\u2019s industrial management system, quality management system, and safety & health policies and procedures\nMonitor regularly the staff compliance on the Safety & Security rules and carry out internal quality and safety check and audits\nDevelop and conduct training to staff and coach all staff to develop further awareness on health & safety work practices\nRisk and Accident Investigation and Prevention\nManage product recall and product registration according to regulatory and legal requirements\nMonitor and coordinate any accident investigation and proactively introduce preventive action\nQuality System & Audit Management\nConduct internal audit periodically and communication of audit findings to the relevant personnel for action\nEnsure the Company\u2019s quality system is properly implemented in accordance with ISO 9001:2015 and liaise with external parties on matters relating to the improvement the ISO system\nManage and improve ISO based Quality Management System documentation according to the group\u2019s guidelines and maintain proper quality records\nRequirements:\n\nDegree holder in Quality / Safety Management or related disciplines\n2 to 3 years solid experience in ISO Quality Management System; preferably with experience in healthcare industry\nSolid experience in handling medical device regulatory and product recall\nA certified internal auditor with experience in managing ISO internal audit\nGood planning, organization and project management skills\nStrong research, analytical, interpersonal and communication skills\nGood team player and able to work independently under tight deadlines\nFluent English and Chinese with strong computer skills\nImmediate available is highly preferred\nWe offer competitive remuneration and on-the-job coaching with a good career development to the right candidate.\u00a0Interested parties please send us a full resume stating current and expected salary and availability\u00a0for job application.\n\n\nPlease visit our website:\u00a0http://www.celki.com\u00a0for further information of our Company.\n\nData collected will be used for recruitment purpose only.", "employment_types": ["Full Time", "Permanent"], "selling_points": [], "locations": ["Eastern Area"], "categories": ["Medical Services", "Pharmaceutical", "Sales, CS & Business Devpt", "Account Servicing", "Others"], "post_time": "2022-01-15T03:50:59Z", "salary": {"currency": null, "max": null, "min": null, "period": "monthly", "term": null}, "salary_visible": false, "title_keywords": ["specialist", "medical representative", "senior sales"], "responsibilities": ["internal audit", "external parties", "quality", "audit", "communication", "maintain", "liaise with", "system documentation", "compliance", "monitor", "implementation", "develop", "management", "procedures", "investigation", "audits", "guidelines", "policies", "coordinate"], "requirements": {"degrees": ["degree holder"], "majors": ["related disciplines"], "languages": ["english", "chinese"], "language_level": ["fluent"], "hard_skills": ["project management", "computer skills"], "soft_skills": ["communication skills", "good team player", "work independently", "project management skills", "interpersonal"], "languages_combined": [{"language": "english", "language_level": ["fluent"]}, {"language": "chinese", "language_level": ["fluent"]}]}, "experience_required": {"duration": ["2 to 3 years"], "field": ["healthcare industry", "audit", "quality management", "medical device"]}}, {"job_id": "100003009049503", "location_code": "hk", "company": "Icon Clinical Research Hong Kong Limited", "job_title": "Clinical Research Associate-Hong Kong", "description": "Job Responsibilities:\n\nOversee the regulatory applications of pharmaceutical products, Advance Therapeutic products, Chinese medicinal products, medical devices\nCoordinate and manage simple and complex regulatory submissions in accordance with applicable regulations; this includes ability to translate regulatory requirements, into practical, workable submission plans; develop & maintain timelines; coordinate internal/ external authoring/ review/ comment adjudication and finalization (submission and archival)\nProvide leadership to Regulatory Team by ensuring that appropriate structures, systems, competencies and values are developed\nActively participate, analyze, follow-up and discuss with clients on relevant issues.\nEstablish ongoing liaison with key government officials and ensure that significant developments in the field are identified and monitored\nEnsure effective team communication throughout Regulatory Team through the application of suitable reporting systems, structures and the\nidentification and provision of appropriate training.\nTo have overall responsibility for ensuring that all regulatory requirements are addressed, are dealt with in accordance with company SOPs and international standard.\nReview promotional materials to ensure compliance with regulations and company standards\nCollaborate with clients and internal marketing teams on regulatory submission and product variation management\nAct as the point of contact between local regulatory authority and the company on regulatory affairs matters\nJob Requirements:\n\nDegree holder in Pharmaceutical Science, Life Science with or related discipline\nMinimum of 10 years\u2019 relevant experience in people management position in pharmaceutical industry\nWell-versed in the Hong Kong pharmaceuticals regulatory requirement\nIndependent, self-motivated, proactive, reliable and organized with attention to detail\nExcellent command of both written and spoken English and Chinese\nOffice location: Tsing Yi\n\n\nWe offer 5-day work week, performance bonus and attractive benefits including medical insurance. Please apply with full particulars, contact number and current/ expected salary to Human Resources Department, DKSH Hong Kong Limited, 23rd Floor, Tower A, Southmark, 11 Yip Hing Street, Wong Chuk Hang, Hong Kong or fax:2895 9711.\n\nAll personal data collected will be used for recruitment purpose only. Candidates will be contacted within 2 weeks if the background and experience are closely relevant to the job requirement.\nDrive Growth. Be the Difference. Join DKSH.\nDKSH\u2019s strength lies in our great diversity of services, industries, clients, products, regions and employees from various nationalities. We are proud of our people: they are the reason we are successful. Our people are the best in the industry. They are passionate about their career growth and about business success. They work as part of an energetic and committed team, positively impacting millions of lives through the products and services we provide.\u00a0Join us today if you are ready to \u201cDrive growth. Be the Difference.\u201d\u00a0With DKSH, you will experience a world of learning and development, own your career and take business responsibility and have a positive impact that touches people\u2019s lives.", "employment_types": ["Full Time"], "selling_points": ["Attractive Salary Compensation", "Focus on Global Top 5 pharma trials", "Client Based"], "locations": ["Causeway Bay"], "categories": ["Medical Services", "Medical Services Technician", "Nursing", "Pharmaceutical"], "post_time": "2022-01-14T08:45:51Z", "salary": {"currency": null, "max": null, "min": null, "period": "monthly", "term": null}, "salary_visible": false, "title_keywords": ["research associate"], "responsibilities": ["regulations", "collaborate with", "management", "regulatory requirements", "review", "systems", "teams", "develop", "coordinate", "communication", "ensure compliance", "maintain", "reporting systems", "promotional materials", "sops", "contact", "plans"], "requirements": {"degrees": ["degree holder"], "majors": ["science"], "languages": ["english", "chinese"], "language_level": ["excellent"], "hard_skills": [], "soft_skills": ["organized", "self-motivated", "independent", "reliable", "attention to detail", "proactive"], "languages_combined": [{"language": "english", "language_level": ["excellent"]}, {"language": "chinese", "language_level": ["excellent"]}]}, "experience_required": {"duration": ["minimum of 10 years"], "field": ["pharmaceutical", "people management", "relevant experience"]}}, {"job_id": "100003009052742", "location_code": "hk", "company": "Quality HealthCare Medical Services Ltd", "job_title": "Assistant Officer, Operation Process", "description": "\nYou will be responsible for the sales within a defined territory of Pharmaceuticals Products in Established Pharmaceuticals Division, organizes and implements selling activities in line with the plan for business in private sector. To achieve or exceed the annual and quarterly sales objectives through the use of professional selling skills, time and territory management and the efficient use of promotional material consistent with marketing objectives.\n\u00a0\nRequirements:\n\nBachelor\u2019s Degree, preferably in Science and related disciplines\nMinimum 2 years of experience in sales\nAggressive and able to work under pressure\nResult oriented to achieve/exceed job expectations\nGood communication and interpersonal skills\nCandidates with more experience may be considered as Senior Sales Specialist\n\n\n\nInterested parties, please send your profile with present and expected salary by clicking 'Apply Now'.\n\u00a0\nPersonal data collected will be used for recruitment purposes only.", "employment_types": ["Full Time", "Permanent"], "selling_points": ["Administrative Support", "Clinic Operations", "Good Interpersonal Skills"], "locations": ["Kowloon Bay"], "categories": ["Admin & HR", "Clerical / Admin Staff", "Medical Services", "Others", "Pharmaceutical"], "post_time": "2022-01-17T03:52:57Z", "salary": {"currency": null, "max": null, "min": null, "period": "monthly", "term": null}, "salary_visible": false, "title_keywords": ["assistant officer"], "responsibilities": ["communication", "management", "plan", "work under pressure"], "requirements": {"degrees": ["degree", "bachelor"], "majors": ["related disciplines", "science"], "languages": [], "language_level": [], "hard_skills": [], "soft_skills": ["efficient", "responsible", "result oriented", "communication and interpersonal skills", "work under pressure"], "languages_combined": []}, "experience_required": {"duration": ["minimum 2 years"], "field": []}}, {"job_id": "100003009047203", "location_code": "hk", "company": "Servier Hong Kong Ltd", "job_title": "Medical Representative / Executive Medical Representative", "description": "ICON plc is a world-leading healthcare intelligence and clinical research organisation. From molecule to medicine, we advance clinical research providing outsourced services to pharmaceutical, biotechnology, medical device and government and public health organisations.\n\nWith our patients at the centre of all that we do, we help to accelerate the development of drugs and devices that save lives and improve quality of life.\n\nOur people are our greatest strength, are at the core of our culture, and the driving force behind our success. ICON people have a mission to succeed and a passion that ensures what we do, we do well.\n\nHere at ICON we want our employees to succeed and we enable this success through consistent training, development and support. To be successful in this position you will have:\u00a0\n\nA proven track record as a highly motivated and dynamic project management professional\nAbility and skills to manage end to end performance for assigned protocols in a country, processes (and controls), productivity, quality and project delivery\nProficiency in written and spoken English and local language. The incumbent must be competent and effective in written and verbal communication.\nAbility to identify problems, conflicts and opportunities early and lead, analyse and prepare mitigation plans and drive conflict resolution is critical\n\nYou are:\n\nPassionate, innovative and committed.\n\nHere at ICON we want our employees to succeed and ensure that they are set up for this success through constant training, development and support. To enable success in this position you will have:\n\nPrior experience of working in investigator site management, including conducting monitoring visits, from either a pharmaceutical company or a CRO environment.\nA working knowledge of ICH-GCP guidelines and local and international regulatory requirements is essential.\nYou will be educated to degree level in a life science discipline or be a licensed healthcare professional.\nExperience working on Oncology trials or complex studies would be an advantage for this role.\u00a0\n\nBenefits of Working in ICON:\n\nOur success depends on the knowledge, capabilities and quality of our people. That\u2019s why we are committed to developing our employees in a continuous learning culture \u2013 one where we challenge you with engaging work and where every experience adds to your professional development.\n\nAt ICON, our focus is to provide you with a comprehensive and competitive total reward package that comprises, not only an excellent level of base pay, but also a wide range of variable pay and recognition programs. In addition, our best in class employee benefits, supportive policies and wellbeing initiatives are tailored to support you and your family at all stages of your career - both now, and into the future.", "employment_types": ["Full Time", "Permanent"], "selling_points": [], "locations": ["Wan Chai Area"], "categories": ["Medical Services", "Pharmaceutical", "Sales, CS & Business Devpt", "Others", "Sciences, Lab, R&D", "Others"], "post_time": "2022-01-14T02:34:59Z", "salary": {"currency": null, "max": null, "min": null, "period": "monthly", "term": null}, "salary_visible": false, "title_keywords": ["executive", "medical representative"], "responsibilities": ["guidelines", "regulatory requirements", "monitoring", "quality", "site management", "communication", "project management", "resolution", "plans", "analyse"], "requirements": {"degrees": ["degree"], "majors": ["science"], "languages": ["english"], "language_level": ["proficiency"], "hard_skills": ["icon", "dynamic", "plc", "project management professional"], "soft_skills": ["passionate", "competent", "communication", "project management", "committed", "dynamic", "motivated", "organisation", "innovative"], "languages_combined": [{"language": "english", "language_level": ["proficiency"]}]}, "experience_required": {"duration": [], "field": ["management", "pharmaceutical company"]}}, {"job_id": "100003009050536", "location_code": "hk", "company": "Celki Medical Company", "job_title": "Safety & Compliance Officer", "description": "In the heart of the role:\n\n\n\nHandle departmental administration work and operational support to clinics\nSupport UAT process on mobile portal and internal systems\nSupport new system training to frontline stakeholder\n\nDesired Qualification & Experience:\n\n\n\nHKDSE or above\nAt least 1 year experience in related experience\nResponsive and self-motivated with good problem solving techniques\nProficiency in Microsoft Office including Ms Word, Excel and PowerPoint\nGood communication skills\n\n(All applications will be treated in strict confidence and data collected will be used for recruitment purposes only)", "employment_types": ["Full Time", "Permanent"], "selling_points": ["Responsible for overall Safety & Quality matters", "Certified internal auditor, manage ISO 9001:2015", "Exp. in medical device regulatory & product recall"], "locations": ["Cheung Sha Wan"], "categories": ["Medical Services", "Others", "Pharmaceutical", "Manufacturing", "Quality Assurance, Control & Testing / ISO"], "post_time": "2022-01-14T10:39:39Z", "salary": {"currency": null, "max": null, "min": null, "period": "monthly", "term": null}, "salary_visible": false, "title_keywords": ["compliance officer"], "responsibilities": ["operational support", "uat", "data", "communication", "recruitment", "internal systems", "administration"], "requirements": {"degrees": ["hkdse"], "majors": [], "languages": [], "language_level": [], "hard_skills": ["excel", "microsoft office", "powerpoint", "problem solving", "mobile", "ms word"], "soft_skills": ["communication skills", "self-motivated", "confidence", "problem solving", "responsive"], "languages_combined": []}, "experience_required": {"duration": ["at least 1 year"], "field": ["related"]}}, {"job_id": "100003009050339", "location_code": "hk", "company": "Hong Kong Science & Technology Parks Corporation", "job_title": "Manager/Assistant Manager (Clinical Translation Catalyst), Institute for Translational Research", "description": "A well-established European pharmaceutical company certified Great Place To Work is looking for a Medical Representative\u00a0 / Executive Medical Representative\u00a0to\u00a0promote specialized pharmaceutical products.\n\nThe followings are expected from the candidates:\n\nPharmacy or Science University degree\nEnthusiasm,\u00a0team spirit and result-oriented.\nGood communication and selling skills\nStrategic mindset: market analysis, objective setting, action plans development and implementation\nIdeally, previous\u00a0selling experience in pharmaceutical industry\u00a0(senior position considered if 3 years +)\n\nRemuneration will be commensurate with qualification and experience.\u00a0 Employment conditions include basic salary + allowance + incentive scheme, life & medical insurance, annual leave and\u00a0provident fund.\u00a0 Proper product training will be provided.\u00a0 Good prospects of advancement are available for the right candidates.", "employment_types": ["Full Time"], "selling_points": [], "locations": ["Shatin Area"], "categories": ["Sciences, Lab, R&D", "Life Science", "Medical Services", "Others", "Pharmaceutical"], "post_time": "2022-01-14T10:09:49Z", "salary": {"currency": null, "max": null, "min": null, "period": "monthly", "term": null}, "salary_visible": false, "title_keywords": ["assistant manager", "manager"], "responsibilities": ["implementation", "communication", "market analysis", "plans", "insurance"], "requirements": {"degrees": ["university degree"], "majors": ["science"], "languages": [], "language_level": [], "hard_skills": ["analysis", "basic", "scheme"], "soft_skills": ["communication", "team spirit", "result-oriented"], "languages_combined": []}, "experience_required": {"duration": ["3 years +"], "field": ["pharmaceutical"]}}, {"job_id": "100003009048315", "location_code": "hk", "company": "DKSH Hong Kong Limited", "job_title": "Specialist, Quality Assurance - Healthcare", "description": "[JDB/M_AMCTCITR/220114]\n\n\n\nResponsibilities:\n\nSupport the management of the new Clinical Translational Catalyst initiative which provides funding and regulatory support for biotech companies to catalyze the translation of their pipeline from pre-clinical to clinical stage;\nEstablish and maintain collaborative relationships with key stakeholders in the clinical translational path including Principal Investigators for Clinical Studies, Regulatory Professionals, Contract Research Organizations, Contract Manufacturing Organizations, and domain experts focusing in the fields of therapeutics and medical devices;\nImplement and organize the overall administrative process for admission, assessment panel meeting and disbursement;\nPromote the new HKSTP initiative within and outside of Hong Kong Science Park to attract qualified companies to participate in the initiative;\nInteract with partner companies to understand their business/technical requirements and develop effective solutions;\nReview and update Standard Operating Procedures, Programme Guide, protocols, flow charts, etc.;\nWork collaboratively with other ITR teams and HKSTP organizational units; and\nPerform any other duties as assigned by supervisors and management.\n\n\u00a0Requirements:\n\nMaster degree in Pharmacology, Pharmaceutical Sciences, Pharmacy, Biomedical Sciences, Biochemistry, Biology, Biomedical Engineering and related clinical science or medicine disciplines;\u00a0 A Clinical or PhD degree would be an advantage;\nMinimum of 8 years of experience in R&D of therapeutics or medical devices with focus in IND or PMA regulatory submissions (e.g. FDA, NMPA), GMP manufacturing and QC/QA;\nExperience in regulatory submission, clinical trial and marketing approval of small molecules, biologics, regenerative medicine, gene therapy or medical devices would be a plus;\nGood analytical, interpersonal, presentation and communication skills;\nSelf-driven and work effectively in a highly collaborative environment;\nAbility to manage up, down and across different functional teams will be crucial;\nProficient in MS office (Words, Excel and PowerPoint); and\nProficient in both written and spoken English and Chinese (Putonghua and Cantonese).\nCandidate with higher qualification but less experience will also be considered.\n\n[This position is open for referral by Recruitment agencies. The profile should be sent to our HR email address\u00a0a g e n c y c v @ h k s t p . o r g ]\n\nWe offer market competitive compensation, 5-day work week and generous benefits including medical and life insurance.\u00a0 To apply, please send your full resume with current and expected salary to the Human Resources & Office Administration Department, Hong Kong Science and Technology Parks Corporation, 5/F, Building 5E, 5 Science Park East Avenue, Hong Kong Science Park, Hong Kong or, by email on or before 27 January 2022. Please quote the reference number on the email subject/envelope and the application letter.\u00a0\n\n\u00a0Personal data provided will be treated in strict confidence and used for recruitment purpose only. All personal data collected will be used strictly in accordance with employer\u2019s personal data policies, you can access to HKSTP\u2019s Personal Information Collection Statement at\u00a0https://www.hkstp.org/hkstp_web/en/hkstp/personal-information-collection-statement-recruitment\u00a0\n\nApplicants not invited for interview within four weeks after application deadline may consider their applications unsuccessful. Personal data of unsuccessful applicants will be retained for a maximum of two years.\u00a0\n\nwww.hkstp.org", "employment_types": ["Full Time", "Permanent"], "selling_points": ["Diploma or Degree holder in science related course", "Experience in working with pharmaceutical industry", "Registered AP / QAO (Secondary Packaging)"], "locations": ["Tsing Yi"], "categories": ["Medical Services", "Others", "Pharmaceutical", "Manufacturing", "Quality Assurance, Control & Testing / ISO"], "post_time": "2022-01-14T06:13:18Z", "salary": {"currency": null, "max": null, "min": null, "period": "monthly", "term": null}, "salary_visible": false, "title_keywords": ["specialist"], "responsibilities": ["any other duties", "management", "review", "procedures", "teams", "develop", "maintain"], "requirements": {"degrees": ["degree", "master degree"], "majors": ["pharmacology", "biomedical engineering", "biology", "science"], "languages": ["cantonese", "putonghua", "english", "chinese"], "language_level": ["proficient"], "hard_skills": ["r&d", "small", "plus", "excel", "words", "powerpoint", "c", "r", "focus", "ms office"], "soft_skills": ["work effectively", "communication skills", "driven", "collaborative", "focus", "interpersonal", "presentation"], "languages_combined": [{"language": "cantonese", "language_level": []}, {"language": "putonghua", "language_level": []}, {"language": "english", "language_level": ["proficient"]}, {"language": "chinese", "language_level": ["proficient"]}]}, "experience_required": {"duration": ["minimum of 8 years"], "field": ["marketing", "clinical", "medical"]}}, {"job_id": "100003009051792", "location_code": "hk", "company": "Purapharm Corporation Limited", "job_title": "Medical Sales Executive (Chinese Medicine) \u4e2d\u91ab\u85e5\u92b7\u552e\u4ee3\u8868", "description": "Job Responsibilities:\n\nSupport the design and development of quality assurance procedures, processes and standards to ensure alignment to global DKSH quality policy and local regulatory guidelines\nPrepare and assist in designing quality assurance systems, including the development of SOPs, quality checklists, supporting tools and techniques\nAssist in qualification, validation of equipment and facility\nAssist in handling of complaints, deviations, and change control\nAnalyze data to identify areas for improvement in practices and processes\nMaintain all controlled document files and quality records in a timely and accurate manner\nProvide training to employees on quality awareness and offer technical assistance to production on quality and process improvements as well as trouble shooting when necessary\n\nJob Requirements:\n\nDegree/Diploma holder in science related courses\nRegistered Authorized Person / Quality Assurance Officer (Secondary Packaging) would be an advantage\nExperience in working with pharmaceutical industry\u00a0\nCertificate in quality management system is preferred\nKnowledge in ISO 9001, ISO 13485, GDP and PIC/S GMP practices, standards\nGood communication skills in both English and Chinese\nProficient in MS Office applications\nCandidate with more experience will be considered as Senior Specialist\nWorking location:\u00a0Mapletree, Tsing Yi\n\n\nWe offer performance bonus and attractive benefits including medical insurance and company shuttle bus services to the right candidate. Interested parties please apply in full resume with current and expected salaries to Human Resources Department , DKSH Hong Kong Limited, 23rd Floor, Tower A, Southmark, 11 Yip Hing Street, Wong Chuk Hang, Hong Kong or by clicking \"Apply Now\"\n\nAll personal data collected will be used for recruitment purposes only. \u00a0Candidates will be contacted within 2 weeks if the background and experience are closely relevant to the job requirement.\n\nDrive Growth. Be the Difference. Join DKSH.\n\nDKSH\u2019s strength lies in our great diversity of services, industries, clients, products, regions and employees from various nationalities. We are proud of our people: they are the reason we are successful. Our people are the best in the industry. They are passionate about their career growth and about business success. They work as part of an energetic and committed team, positively impacting millions of lives through the products and services we provide.\u00a0Join us today if you are ready to \u201cDrive growth. Be the Difference.\u201d\u00a0With DKSH, you will experience a world of learning and development, own your career and take business responsibility and have a positive impact that touches people\u2019s lives.", "employment_types": ["Full Time", "Permanent"], "selling_points": ["Promote company products and develop sales", "2 years\u2019 sales experience", "Excellent interpersonal & communication skills"], "locations": ["Tai Po Area"], "categories": ["Medical Services", "Specialist", "Pharmaceutical", "Sales, CS & Business Devpt", "Account Servicing"], "post_time": "2022-01-17T01:12:46Z", "salary": {"currency": null, "max": null, "min": null, "period": "monthly", "term": null}, "salary_visible": false, "title_keywords": ["sales executive"], "responsibilities": ["provide training", "control", "guidelines", "systems", "quality", "procedures", "design", "maintain", "sops", "designing", "analyze data", "technical assistance"], "requirements": {"degrees": ["diploma holder", "certificate", "degree"], "majors": ["science", "quality management"], "languages": ["english", "chinese"], "language_level": ["good"], "hard_skills": ["ms office"], "soft_skills": ["communication skills"], "languages_combined": [{"language": "english", "language_level": ["good"]}, {"language": "chinese", "language_level": ["good"]}]}, "experience_required": {"duration": [], "field": ["pharmaceutical"]}}, {"job_id": "100003009050350", "location_code": "hk", "company": "Abbott Laboratories Ltd.", "job_title": "Tender Manager", "description": "Job Descriptions:\n\nPromote company products and develop sales in Chinese Medicine Clinic, Hospitals & NGO sectors.\n\u63a8\u92b7\u7522\u54c1\u5230\u4e0d\u540c\u4e2d\u91ab\u85e5\u5ba2\u6236\u3001\u91ab\u9662\u53ca\u5404\u6148\u5584\u7d44\u7e54\u7b49\nIdentify business opportunities, expand client base and create new accounts to achieve sales target.\n\u64f4\u5c55\u92b7\u552e\u7db2\u7d61\u3001\u5c0b\u627e\u65b0\u5ba2\u6236\u53ca\u64f4\u5c55\u73fe\u6709\u5ba2\u6236\u7fa4\u4ee5\u9054\u5230\u92b7\u552e\u6307\u6a19\nManage and follow up orders from customers, and visit customers regularly.\n\u8ddf\u9032\u5ba2\u6236\u8a02\u8cfc\u55ae\u7b49\u3001\u9700\u8981\u5916\u52e4\u5de5\u4f5c\n\n\u00a0Job Requirements:\n\nHigher Diploma or above; Professional Diploma in Chinese Institutes are also welcome\n\u9ad8\u7d1a\u6587\u6191\u6216\u4ee5\u4e0a\u5b78\u6b77, \u570b\u5167\u9ad8\u7b49\u5c08\u79d1\u6216\u5927\u5b78\u5b78\u6b77\u4ea6\u53ef\n\n\nAt least 2 years\u2019 solid field sales experience\n\u6700\u5c112\u5e74\u76f8\u95dc\u92b7\u552e\u7d93\u9a57\n\nExcellent interpersonal & communication skills\n\u826f\u597d\u7684\u6e9d\u901a\u53ca\u8868\u9054\u6280\u5de7\nIndependent, aggressive, hardworking and able to work under pressure\n\u7368\u7acb\u3001\u9032\u53d6\u3001\u80fd\u5920\u5728\u58d3\u529b\u4e0b\u5de5\u4f5c", "employment_types": ["Full Time", "Permanent"], "selling_points": [], "locations": ["Eastern Area"], "categories": ["Sales, CS & Business Devpt", "Business Development", "Medical Services", "Pharmaceutical", "Sales - Sales Management"], "post_time": "2022-01-15T03:51:01Z", "salary": {"currency": null, "max": null, "min": null, "period": "monthly", "term": null}, "salary_visible": false, "title_keywords": ["manager"], "responsibilities": ["follow up orders", "identify business opportunities", "sales target", "develop", "client base"], "requirements": {"degrees": ["diploma", "higher diploma or above"], "majors": [], "languages": ["chinese"], "language_level": [], "hard_skills": [], "soft_skills": ["communication skills", "independent", "interpersonal", "hardworking", "work under pressure"], "languages_combined": [{"language": "chinese", "language_level": []}]}, "experience_required": {"duration": ["at least 2 years"], "field": []}}, {"job_id": "100003009050038", "location_code": "hk", "company": "Hillman Ross", "job_title": "Brand Manager (Medical)", "description": "Responsibilities:\n\nCoordinate and perform activities in evaluation, initiation, monitoring and close-out of investigational sites in compliance with standards set by the Company, ICH/Good Clinical Practice (GCP) and local regulatory requirements.\nMaintain a good relationship with investigators and other site staff.\n\nRequirements:\n\nUniversity degree, preferably life sciences degree.\nGood knowledge of ICH/GCP requirements.\nGood command of both written and verbal English and Chinese.\nStrong communicational, interpersonal, organizational and time management skills.\nAbility to work independently under pressure with attention to details.\nCandidate with more experience will be considered as Senior CRA.\nFresh graduates are most welcome to apply and will be considered as Clinical Research Associate - Trainee\n\nInterested parties please send detailed resume and expected salary to, General Manager, Novo Nordisk Hong Kong Ltd., Room 928, 9/F., Trade Square, 681 Cheung Sha Wan Road, Kowloon, Hong Kong. Or by clicking 'Apply Now'.\n\nAll Personal data collected will be used for recruitment purpose only.", "employment_types": ["Full Time", "Permanent"], "selling_points": ["Regional exposure", "People management", "Drive global branding"], "locations": ["Not Specified"], "categories": ["Marketing / Public Relations", "Marketing - Brand / Product Management", "Medical Services", "Pharmaceutical"], "post_time": "2022-01-14T09:40:07Z", "salary": {"currency": null, "max": null, "min": null, "period": "monthly", "term": null}, "salary_visible": false, "title_keywords": ["manager"], "responsibilities": ["regulatory requirements", "compliance", "monitoring", "coordinate", "good relationship", "maintain", "evaluation"], "requirements": {"degrees": ["university degree", "degree"], "majors": [], "languages": ["english", "chinese"], "language_level": ["good command"], "hard_skills": [], "soft_skills": ["work independently", "under pressure", "time management skills", "organizational", "attention to details", "interpersonal"], "languages_combined": [{"language": "english", "language_level": ["good command"]}, {"language": "chinese", "language_level": ["good command"]}]}, "experience_required": {"duration": [], "field": []}}, {"job_id": "100003009047259", "location_code": "hk", "company": "SinoMab BioScience Ltd", "job_title": "Research Associate / Research Assistant", "description": "We are looking for a dynamic Tender Manager to develop and grow their career. Joining the medicines business in Abbott is an opportunity to be tested and learn in different ways. We love a good challenge and we like to win. If this sounds like a match for your interests and skills, be part of the journey to do phenomenal things with your career.\n\nThis position is responsible for driving a profitable business growth through the tender/bidding channel. Enable market access and perform strategic management of the tender business in the Hong Kong & Macau. Key responsibilities are as follows:\nUnderstand tender landscape in the region with respect to public vs private, types of tender (price-based, volume based, market access-empanelment) and systematically track and monitor ongoing and expected tenders across all levels\nUnderstand the policy and regulatory requirements for tender programs. Knowledge of tender contractual obligations (e.g. penalties)\nEstablish and manage relationships with external stakeholders (hospital procurement, industry associations, doctors at govt institutions) involved in the process of tender bidding\nFacilitate improvement of tender specifications, tender process to optimize overall healthcare outcomes for community and government\nIdentify full scope of tender opportunities in the region\nStructure market access strategy for Abbott based on expected tenders at all levels\nManage and utilize data for tracking tenders, the results, competitor information and changing compliances\nDevelop strategy to maximize participation, revenue and profitability from tender sales through decisions with respect to which tenders to participate, must-win based on internal capabilities and market dynamics\nDrive the tender business to optimize revenue and profitability\nClassify high-low probability tender win rates based on market access, ability to fulfil tenders\nDrive tender process to ensure accurate documentation and timely and quality submissions and follow-ups for rebidding, negotiations\nEnsure timely implementation for winning bids e.g., additional documentation/financial obligations, sales to individual hospitals for quota fulfilment, on-time in full supplies, timely collections\nCo-ordinate with cross functional teams at country, regional and global level for tender fulfillment\nRequirements:\nUniversity degree in Science, Health Sciences or Business, Medical Professional\nMinimum of 3 to 5 years of tenders contracting/commercial/sales/marketing in healthcare sector.\nStrong analytical mind to resolve business challenges and able to work under pressure\nStrong sense of responsibilities, self-motivated\nPassion for the business and willing to go for extra mile\nProficiency in Chinese and English\n\nInterested parties, please send your profile with present and expected salary by clicking \"Apply Now\".\n\nPersonal data collected will be used for recruitment purposes only.", "employment_types": ["Full Time", "Permanent"], "selling_points": ["Plan, Design and Perform Experiments", "Purchase and Maintenance of Laboratory Reagents", "Opportunity to engage at the forefront of Biopharm"], "locations": ["Shatin Area"], "categories": ["Sciences, Lab, R&D", "Laboratory", "Medical Services", "Pharmaceutical", "Research & Development (R&D)"], "post_time": "2022-01-14T02:41:05Z", "salary": {"currency": null, "max": null, "min": null, "period": "monthly", "term": null}, "salary_visible": false, "title_keywords": ["research associate", "research assistant"], "responsibilities": ["data", "co-ordinate with", "regulatory requirements", "fulfillment", "monitor", "quality", "implementation", "develop", "teams", "specifications", "tender", "documentation", "optimize revenue", "tracking"], "requirements": {"degrees": ["university degree"], "majors": ["science", "business"], "languages": ["english", "chinese"], "language_level": ["proficiency"], "hard_skills": ["go"], "soft_skills": ["self-motivated", "passion for", "work under pressure", "analytical mind", "sense of responsibilities"], "languages_combined": [{"language": "english", "language_level": ["proficiency"]}, {"language": "chinese", "language_level": ["proficiency"]}]}, "experience_required": {"duration": [], "field": []}}, {"job_id": "100003009047065", "location_code": "hk", "company": "Vickmans Laboratories Limited", "job_title": "Quality Assurance Assistant", "description": "Our client is looking for a potential Brand Manager to join their company\n\nResponsibilities\n\nPlan and implement brand strategies to cope with the business objective\nMaximizing brand awareness and brand positioning in the regional market\nLead a marketing team and create positive synergy in the team\nManage ROI, brand building and conduct market research\n\nRequirements\n\nDegree or above in Marketing, Business Administration or related disciplines.\nOver 6 years brand marketing experience preferred in Healthcare sector\nWith over 3 years people management experience\nGood command in spoken and written in English and Chinese\n\nAPPLY FOR THIS JOB\n\nInterested candidate please CLICK apply button to apply online or send your resume in MS word format to Hillman Ross Recruitment Solution Professional\n\nPlease note that only shortlisted candidate will be notified. All information will be treated in strict confidence and solely used for recruitment purposes.", "employment_types": ["Full Time", "Permanent"], "selling_points": [], "locations": ["Ngau Tau Kok"], "categories": ["Manufacturing", "Production Planning / Control", "Medical Services", "Pharmaceutical", "Quality Assurance, Control & Testing / ISO"], "post_time": "2022-01-14T02:13:31Z", "salary": {"currency": null, "max": null, "min": null, "period": null, "term": null}, "salary_visible": false, "title_keywords": ["quality assurance assistant"], "responsibilities": ["conduct market research", "brand strategies", "plan"], "requirements": {"degrees": ["degree or above"], "majors": ["related disciplines", "marketing", "business administration"], "languages": ["english", "chinese"], "language_level": ["good command"], "hard_skills": ["ms word"], "soft_skills": ["confidence"], "languages_combined": [{"language": "english", "language_level": ["good command"]}, {"language": "chinese", "language_level": ["good command"]}]}, "experience_required": {"duration": ["6 years", "3 years"], "field": ["healthcare", "marketing", "brand", "people management"]}}, {"job_id": "100003009051389", "location_code": "hk", "company": "Asia Page Recruitment Company", "job_title": "Graduate Management Trainee", "description": "We are now seeking a potential incumbent to join our expanding company with the following responsibilities:\n\n\n\nResponsibilities:\n\nAssist in the execution of different experiments assigned by the team leader.\nEngage in scientific discussions entailing innovative ideas, current literature research and experimental design.\nData logging and analysis\nOrganize and report experiments progress to the corresponding supervisor and senior management.\nEnsure the laboratory equipment and reagents are in good condition and assist in purchase when required.\n\nRequirements:\n\nDegree or Master in Biochemistry, Biomedical Science, Biotechnology or equivalent disciplines.\nWith 1 -2 years relevant working experience\u00a0\nCandidates who process\u00a0MPhil education level will be considered as associate position.\u00a0\nPossess experience in Molecular Cloning, Western Blot, PCR, Antibody Production, or Cell Culturing is preferred.\nGood commands of written and spoken English and Chinese (Mandarin).\nProficiency in Microsoft Word and Excel.\n\n\nWe offer 5-day Work Week, Bank Holiday, Medical & Dental insurance, 13-Month Salary, Promising Career Path and Competitive Remuneration\u00a0Package to the right candidate. Interested parties please send your detailed resume with current and expected salary, contact number and email address by clicking \"Apply Now\".\n(We regret only shortlisted candidates will be notified, personal data collected will be treated as confidential and for recruitment purpose only.)", "employment_types": ["Full Time", "Contract"], "selling_points": ["Five-day work week", "Excellent career path development and mentoring", "Fresh Graduate is an advantage"], "locations": ["Tsim Sha Tsui"], "categories": ["Medical Services", "Pharmaceutical", "Others", "Student / Fresh Graduate / No Experience", "Banking / Finance", "Risk Management"], "post_time": "2022-01-15T13:36:02Z", "salary": {"currency": "HKD", "max": 24999, "min": 17000, "period": "monthly", "term": null}, "salary_visible": true, "title_keywords": ["graduate management trainee"], "responsibilities": ["ideas", "data", "analysis", "purchase", "experimental design", "senior management", "report"], "requirements": {"degrees": ["degree", "master"], "majors": ["biomedical science"], "languages": ["english", "chinese", "mandarin"], "language_level": ["good"], "hard_skills": ["excel", "microsoft word"], "soft_skills": [], "languages_combined": [{"language": "english", "language_level": ["good"]}, {"language": "chinese", "language_level": ["good"]}, {"language": "mandarin", "language_level": ["good"]}]}, "experience_required": {"duration": ["1 -2 years"], "field": ["relevant working experience"]}}, {"job_id": "100003009056627", "location_code": "hk", "company": "ZSHK Laboratories Limited", "job_title": "Laboratory Animal Technician", "description": "Located in HKSTP, the Drug Safety Testing Centre (DSC) aims to facilitate the translation of promising therapeutics and medical devices from the pre-clinical phase to the clinical stage.\u00a0 This first of its kind facility adheres to the highest international and industry standards, including AAALAC and Good Laboratory Practices (GLP), which is an international standard prescribing a set of rigid and quality criteria for conducting studies, data collection and reporting. \u00a0It defines how preclinical data is required and accepted by different regulatory authorities (for example, China NMPA, US FDA and OECD).\u00a0 The facility commits to provide the GLP-compliant preclinical services on toxicology, genotoxicity, toxicokinetics, safety pharmacology, reproductive toxicology, ADME etc for facilitating the development of new drug.\n\n\nResponsibilities:\nFully understand the importance of pre-clinical animal study for human medicine research and drug development process; ensure a high level of animal welfare and work to improve the quality of life for laboratory animals.\nCarry out rodent\u2019s GLP and non-GLP study according to the designed protocol. \u00a0Experimental \u00a0procedures would include, but not limited to, clinical observations, different routes of administration, blood collections and live data acquisition etc.\nComplete the experimental records in accordance with GLP specifications and related standard operating procedures (SOP) within the facility.\nWork in a team to undertake technical and staff supervision/ management duties in connection with the operation of the facility.\nOn-the-job training will be provided.\nQualifications:\nApplicants should possess a Bachelor\u2019s degree or equivalent;\nBe self-motivated, responsible, empathetic, and curious; excellent communication, analytical and problem-solving skills; an interest in laboratory animal science and technology; and demonstrated commitment to continuing professional development in the field.\nWilling to join the pharmaceutical research and development industry and contribute to the cause of human medicine and health.\nGood command of spoken and written English and Chinese; fluent in Putonghua would be an advantage.\nExperience in animal husbandry, operation and maintenance of equipment for sanitation and sterilisation (e.g. autoclave), or inventory/record keeping will be an advantage but not essential.", "employment_types": ["Full Time", "Permanent", "Contract"], "selling_points": [], "locations": ["Shatin Area"], "categories": ["Sciences, Lab, R&D", "Laboratory", "Medical Services", "Pharmaceutical", "Research & Development (R&D)"], "post_time": "2022-01-18T05:14:31Z", "salary": {"currency": null, "max": null, "min": null, "period": "monthly", "term": null}, "salary_visible": false, "title_keywords": ["technician"], "responsibilities": ["reporting", "management", "maintenance", "data", "inventory", "quality", "procedures", "testing", "communication", "specifications", "data collection", "administration"], "requirements": {"degrees": ["degree", "bachelor"], "majors": [], "languages": ["putonghua", "english", "chinese"], "language_level": ["advantage", "good command", "fluent"], "hard_skills": ["animal science", "maintenance", "animal husbandry", "animal welfare", "problem-solving skills", "translation"], "soft_skills": ["communication", "problem-solving skills", "self-motivated", "responsible"], "languages_combined": [{"language": "putonghua", "language_level": ["fluent", "advantage"]}, {"language": "english", "language_level": ["good command"]}, {"language": "chinese", "language_level": ["good command"]}]}, "experience_required": {"duration": [], "field": ["operation", "maintenance"]}}, {"job_id": "100003009054285", "location_code": "hk", "company": "Vita Green Pharmaceutical (H.K.) Limited", "job_title": "Production Planning Officer", "description": "About the job:\n\n\nAssist the Production Manager in organizing and coordinating daily operations of Production Department.\nPrepare Batch Production Records, Validation/Qualification documents and relevant SOPs.\nMonitor and check records & logbooks in production areas to ensure that they are properly and timely filled out and maintained.\nEnsure entire production flows and processes are strictly compliant with GMP requirements and internal policy.\nAssistant in developing, implementing and maintaining the documentation system, including the SOPs and other production documents.\nMonitor the equipment and cleanroom hygiene according to the approval GMP procedure.\nParticipate in induction and on-job training to production staff.\nOther ad-hoc tasks as assigned by supervisors.\n\nAbout the talent:\n\n\nHigher Diploma or above in Science / Pharmaceutical or related subjects.\nRelevant experience in Food or GMP pharmaceutical manufacturing is preferred but not essential.\nFamiliar with MS office and Chinese word processing.\nHardworking, initiative, self-motivated and fast learner.\nAble to work under pressure and willing to work overtime.\nGood interpersonal skill and communication skill.\nGood command in written and spoken Chinese and English.\n\nWhat we offer:\n\nCareer with the market leader in health product sector from Hong Kong.\nDynamic working culture with great team spirit.\nShuttle to/from Yau Tong, Kowloon Tong, Tai Wai, Taipo, Tsuen Wan, Tuen Mun, Tin Shui Wai and Causeway Bay.\nRapid growth opportunities for strong performers.\nStaff purchase discount.\nCasual attire at work.\n\nInterested parties, please send full resume with last & expected salary and date of available by clicking \u2018Apply Now\u2019\n\nPersonal data collected is for recruitment purpose only.\n\nFor corporate information, please visit:\u00a0www.vitagreen.com", "employment_types": ["Full Time", "Permanent"], "selling_points": ["PIC/s GMP manufacturer", "Pharmaceutical production materials planning", "Great career opportunity"], "locations": ["Tai Po Area"], "categories": ["Manufacturing", "General / Production Workers", "Production Planning / Control", "Medical Services", "Pharmaceutical"], "post_time": "2022-01-17T09:03:01Z", "salary": {"currency": null, "max": null, "min": null, "period": "monthly", "term": null}, "salary_visible": false, "title_keywords": ["officer"], "responsibilities": ["maintaining", "ad-hoc tasks", "monitor", "developing", "communication", "hygiene", "daily operations", "sops", "documentation", "work under pressure"], "requirements": {"degrees": ["higher diploma or above"], "majors": ["science"], "languages": ["english", "chinese"], "language_level": ["good command"], "hard_skills": ["documentation", "batch", "chinese word processing", "ms office"], "soft_skills": ["self-motivated", "work overtime", "timely", "communication skill", "interpersonal skill", "fast learner", "initiative", "hardworking", "work under pressure"], "languages_combined": [{"language": "english", "language_level": ["good command"]}, {"language": "chinese", "language_level": ["good command"]}]}, "experience_required": {"duration": [], "field": ["pharmaceutical", "food", "manufacturing", "relevant experience"]}}, {"job_id": "100003009046649", "location_code": "hk", "company": "Novo Nordisk Hong Kong Limited", "job_title": "Senior/Clinical Research Associate/Clinical Research Associate - Trainee (CRA)", "description": "Responsibilities:\n\nCoordinate and perform activities in evaluation, initiation, monitoring and close-out of investigational sites in compliance with standards set by the Company, ICH/Good Clinical Practice (GCP) and local regulatory requirements.\nMaintain a good relationship with investigators and other site staff.\n\nRequirements:\n\nUniversity degree, preferably life sciences degree.\nGood knowledge of ICH/GCP requirements.\nGood command of both written and verbal English and Chinese.\nStrong communicational, interpersonal, organizational and time management skills.\nAbility to work independently under pressure with attention to details.\nCandidate with more experience will be considered as Senior CRA.\nFresh graduates are most welcome to apply and will be considered as Clinical Research Associate - Trainee\n\nInterested parties please send detailed resume and expected salary to, General Manager, Novo Nordisk Hong Kong Ltd., Room 928, 9/F., Trade Square, 681 Cheung Sha Wan Road, Kowloon, Hong Kong. Or by clicking 'Apply Now'.\n\nAll Personal data collected will be used for recruitment purpose only.", "employment_types": ["Full Time", "Permanent"], "selling_points": [], "locations": ["Cheung Sha Wan"], "categories": ["Medical Services", "Pharmaceutical", "Sciences, Lab, R&D", "Research & Development (R&D)"], "post_time": "2022-01-13T18:54:02Z", "salary": {"currency": null, "max": null, "min": null, "period": "monthly", "term": null}, "salary_visible": false, "title_keywords": ["research associate", "trainee"], "responsibilities": ["regulatory requirements", "compliance", "monitoring", "coordinate", "good relationship", "maintain", "evaluation"], "requirements": {"degrees": ["university degree", "degree"], "majors": [], "languages": ["english", "chinese"], "language_level": ["good command"], "hard_skills": [], "soft_skills": ["work independently", "under pressure", "time management skills", "organizational", "attention to details", "interpersonal"], "languages_combined": [{"language": "english", "language_level": ["good command"]}, {"language": "chinese", "language_level": ["good command"]}]}, "experience_required": {"duration": [], "field": []}}, {"job_id": "100003009044439", "location_code": "hk", "company": "Hugh Source (International) Ltd", "job_title": "Regulatory Affairs Associate /Executive (5 Days Work)", "description": "Key Roles and Responsibilities:\n\nAssist in developing, implementing and maintaining the documentation system and quality management system;\nPerform routine inspection on products at various stages on the production line to implement the GMP policy;\nAssist in performing ad hoc project and\u00a0other\u00a0QA-related duties.\n\nRequirements:\n\nHigher Diploma or Degree holder in Pharmaceutical Studies or other science related discipline;\nHands-on GMP experience in pharmaceutical industry will be an definite advantage;\nHardworking, initiative, self-motivated and fast learner;\nStrong communication skill, good command of English and Chinese;\nGood knowledge of MS Office and Chinese word processing;\nFresh graduates are\u00a0also considered.\n\n\n\nWe offer to the right candidates with competitive remuneration package including 12-16 day annual leave, marriage leave, maternity leave, paternity leave, compassionate leave, Public Holidays, medical and dental insurance, educational sponsorship, overtime allowance, performance bonus, MPF and other fringe benefits.\n\nHow to Apply\n\nYou are invited to send in your application and CV stating the position you are applying for together with your current and expected salary by clicking the \"apply button\".\n\n\u00a0\nVickmans LaboratoriesLimited is an Equal Opportunities Employer. Personal data provided by job applicants will be used strictly in accordance with our personal data policy and for recruitment purposes only. We aim to respond to successful applicants within 8 weeks and related information will be kept in our file for up to 12 months for other suitable vacancies in our organization and thereafter destroyed", "employment_types": ["Full Time"], "selling_points": [], "locations": ["Tsim Sha Tsui"], "categories": ["Professional Services", "Legal & Compliance", "Sciences, Lab, R&D", "Life Science", "Medical Services", "Pharmaceutical"], "post_time": "2022-01-13T04:07:22Z", "salary": {"currency": null, "max": null, "min": null, "period": "monthly", "term": null}, "salary_visible": false, "title_keywords": ["executive", "regulatory affairs associate"], "responsibilities": ["management", "ad hoc", "maintaining", "quality", "developing", "inspection", "documentation"], "requirements": {"degrees": ["diploma", "degree holder"], "majors": ["science"], "languages": ["english", "chinese"], "language_level": ["good command", "good"], "hard_skills": ["chinese word processing", "ms office"], "soft_skills": ["self-motivated", "communication skill", "hands-on", "fast learner", "initiative", "hardworking"], "languages_combined": [{"language": "english", "language_level": ["good command", "good"]}, {"language": "chinese", "language_level": ["good command", "good", "good"]}]}, "experience_required": {"duration": [], "field": ["pharmaceutical"]}}, {"job_id": "100003009047901", "location_code": "hk", "company": "Gemini Personnel Limited", "job_title": "Clinical Research Associate / Assistant HK$23K to HK$30K , Wanchai (KMO-J078097)", "description": "Responsibilities:\n\nThis incumbent will be responsible to promote the pharmaceutical products to\u00a0public hospitals according to the company policies and strategies in Hong Kong.\u00a0\n\nRequirements:\n\nl\u00a0 Bachelor degree in science, nursing or medical related discipline\n\nl\u00a0 1 year or above sales experience in pharmaceutical industry\n\nl\u00a0 Excellent interpersonal and communication skills\n\nl\u00a0 Fluency in both spoken and written English & Cantonese\n\nl\u00a0 Smart, self-motivate, hard-working, independent, result-oriented and with positive attitude\n\nl\u00a0 Proficiency in MS Office\n\nInterested parties please send detailed resume with present and expected salary to, Sales Manager, Novo Nordisk Hong Kong Ltd., Room 928, 9/F., Trade Square, 681 Cheung Sha Wan Road, Kowloon, Hong Kong or email it to \"Apply Now\"\n\n\u00a0(Candidate with sound academic background and relevant experience may be offered the post of Senior Medical Representative)\n\n(Personal data collected will be used for recruitment purpose only)", "employment_types": ["Full Time", "Permanent"], "selling_points": ["To perform clinical tasks", "To prepare the research document", "To design database design and data entry"], "locations": ["Not Specified"], "categories": ["Medical Services", "Specialist", "Others", "Pharmaceutical"], "post_time": "2022-01-14T04:10:53Z", "salary": {"currency": null, "max": null, "min": null, "period": "monthly", "term": null}, "salary_visible": false, "title_keywords": ["research associate", "assistant"], "responsibilities": ["policies"], "requirements": {"degrees": ["degree", "bachelor"], "majors": ["science", "nursing"], "languages": ["cantonese", "english"], "language_level": ["fluency"], "hard_skills": ["ms office"], "soft_skills": ["communication skills", "independent", "positive attitude", "hard-working", "interpersonal", "result-oriented"], "languages_combined": [{"language": "cantonese", "language_level": ["fluency"]}, {"language": "english", "language_level": ["fluency"]}]}, "experience_required": {"duration": ["1 year"], "field": ["pharmaceutical"]}}, {"job_id": "100003009046695", "location_code": "hk", "company": "Novo Nordisk Hong Kong Limited", "job_title": "Medical Representative / Senior Medical Representative", "description": "Managing a team of event managers at various levels on their daily projects' execution and deliveries\n\nYour new company\nYour new company is a leading MNC which specialized in medical conference and education. They are now looking for a Head of Event to manage a team of conference managers. You will be responsible for professional event management services.\n\nYour new role\n\nExecution of Regional/local physical virtual events\nMeet with client to obtain a detailed brief and understanding of requirements\nVenue-searching to meet client expectations\nProvision of proposed venue report, with detailed comparison chart Liaison with hotel regarding contract & arrangements\nPreparation of action plan, including detailed timelines and budget planning\nCommunication with regional & local offices of client company re delegate attendance\nProvision of regular status report to client, including delegate registration Liaison with invited speakers & VIP guests (travel, accommodation, special requirements)\nLiaison with internal editorial, design and production teams to produce event materials (invitations, backdrop, quick-stands, abstract books)\nLiaison with contractors for physical events/technical contractors for virtual events\nOn-site leadership of team, including internal and external briefings\nProvision of budget report upon completion of event\n\n\n\nWhat you'll need to succeed\n\n\nUniversity degree or above\n7 years+ working experience in event management\n5 years' experience in organizing regional and international meetings/conferences\nPreferably with pharmaceutical event background\nExcellent communication and negotiation skills\nExperience in preparation of budget reports\nFlexibility in working hours\nAbility and willingness to travel\n\n\nWhat you need to do now\nIf you're interested in this role, click 'apply now' to forward an up-to-date copy of your CV, or email to Melanie Fung at melanie.fung@hays.com.hk.\nIf this job isn't quite right for you but you are looking for a new position, please contact us for a confidential discussion on your career.", "employment_types": ["Full Time"], "selling_points": [], "locations": ["Cheung Sha Wan"], "categories": ["Medical Services", "Pharmaceutical", "Sales, CS & Business Devpt", "Direct Sales"], "post_time": "2022-01-13T18:54:25Z", "salary": {"currency": null, "max": null, "min": null, "period": "monthly", "term": null}, "salary_visible": false, "title_keywords": ["medical representative"], "responsibilities": ["attendance", "budget planning", "management", "budget reports", "budget", "teams", "design", "communication", "conferences", "contact", "plan", "managing a team", "report"], "requirements": {"degrees": ["degree or above"], "majors": [], "languages": [], "language_level": [], "hard_skills": ["briefings"], "soft_skills": ["responsible", "interested in", "communication", "negotiation skills", "leadership", "detailed"], "languages_combined": []}, "experience_required": {"duration": ["5 years"], "field": ["management"]}}, {"job_id": "100003009050091", "location_code": "hk", "company": "Hays", "job_title": "Head of Event", "description": "Work type:\u00a0Full-time\nDepartment:\u00a0LKS Faculty of Medicine - HKU Health System (00105)\nCategories:\u00a0Professional & Management\n\nApplications are invited for appointment as\u00a0General Manager (Clinical Pharmacy and Pharmaceutical Services)\u00a0to be seconded to The University of Hong Kong (Shenzhen) Teaching Hospital Limited (THL) and assigned to work in the HKU-Shenzhen Hospital (Ref.: 508941), to commence as soon as possible, on a three-year fixed-term basis, with the possibility of renewal.\n\nThe University of Hong Kong (HKU) has been collaborating with Shenzhen Government to develop the HKU-Shenzhen Hospital as a teaching hospital of HKU. With the presence of HKU, a new operation model for the Hospital has been introduced, aiming at providing high-quality services from primary to tertiary levels to patients in the region, whilst sustaining a teaching and training mission well supported by a robust research component. The Hospital has commenced operation since October 2012. As the Hospital is located in Shenzhen, travelling to Mainland China is required.\n\nApplicants should possess a good university degree in Pharmacy, relevant postgraduate training or qualification, a certificate of registration and a valid practicing certificate issued by the Pharmacy and Poisons Board of Hong Kong, and at least 10 years\u2019 experience working at senior management level in major hospitals. They should also have:\n\nsound professional knowledge and extensive experience in planning and management of all aspects of outpatient and hospital-based clinical pharmacy and pharmaceutical services, including but not limited to pharmaceutical procurement, logistic and supplies management;\nsubstantial expertise in formulating and implementing strategies, policies and guidelines on clinical pharmacy services, and in promoting and enhancing medication safety with introduction and use of incident reporting, quality assurance and risk management systems;\nextensive experience in monitoring and conducting spend analysis/review on pharmaceutical consumption and expenditures, formulating appropriate drug formulary for various clinical settings and advising clinicians on alternative treatment protocols to ensure cost-effective and efficacious use of pharmaceuticals across different specialties; and\nexcellent interpersonal and communication skills, with good command of written English and Chinese as well as spoken English and Putonghua.\n\nThe appointee is expected to:\n\nprovide professional leadership and management of the clinical pharmacists for the continual development and implementation of clinical pharmacy strategies and policies that meet the needs of the hospital\u2019s long-term goals and vision;\ndevelop and establish pharmaceutical care plans and services through multidisciplinary efforts;\nlead, encourage and cultivate an environment of clinical and practice based research and audit;\ndevelop and contribute to current and future research and audit projects associated with the use of medicine use process;\nplan, formulate and organize structured educational initiatives to enhance pharmacy and healthcare practitioners\u2019 knowledge and skill in pharmacotherapy; and\ncontribute to departmental continuous improvement process by leading, developing and reviewing clinical governance arrangements relating to medicines safety and clinical risks.\n\nA highly competitive salary commensurate with qualifications and experience will be offered, in addition to annual leave and medical benefits. The appointment will attract a contract-end gratuity and University contribution to a retirement benefits scheme, totalling up to 15% of basic salary.\n\nApplicants who have responded to the previous advertisement (Ref.: 508344) need not re-apply.\n\nThe University only accepts online application for the above post. Applicants should apply online and upload an up-to-date C.V[via APPLY NOW]. Review of applications will start as soon as possible and continue until\u00a0January 31, 2022, or until the post is filled, whichever is earlier.\n\nAdvertised:Nov 11, 2021 (HK Time)\nApplications close:Jan 31, 2022 (HK Time)", "employment_types": ["Full Time", "Permanent"], "selling_points": ["Listed MNC in medical / pharmaceutical", "Flexible working hours", "Dynamic & Energetic Culture"], "locations": ["Not Specified"], "categories": ["Marketing / Public Relations", "Marketing - Marketing Communication", "Public Relations - Event Management", "Medical Services", "Pharmaceutical"], "post_time": "2022-01-14T09:46:07Z", "salary": {"currency": null, "max": null, "min": null, "period": "monthly", "term": null}, "salary_visible": false, "title_keywords": [], "responsibilities": ["quality", "audit", "communication", "plan", "plans", "senior management", "implementation", "developing", "develop", "reporting", "management", "cost", "monitoring", "review", "guidelines", "policies", "analysis", "systems", "planning"], "requirements": {"degrees": ["certificate", "university degree"], "majors": [], "languages": ["putonghua", "english", "chinese"], "language_level": ["excellent", "good command"], "hard_skills": ["analysis"], "soft_skills": ["communication skills", "robust", "extensive", "structured", "leadership", "interpersonal"], "languages_combined": [{"language": "putonghua", "language_level": ["excellent", "good command"]}, {"language": "english", "language_level": ["excellent", "good command"]}, {"language": "chinese", "language_level": ["excellent", "good command"]}]}, "experience_required": {"duration": ["at least 10 years"], "field": ["management", "training", "pharmaceutical", "planning", "procurement", "clinical"]}}, {"job_id": "100003009050814", "location_code": "hk", "company": "Vita Green Pharmaceutical (H.K.) Limited", "job_title": "Production Officer", "description": "About the job:\n\n\nAssist the Production Manager in organizing and coordinating daily operations of Production Department.\nPrepare Batch Production Records, Validation/Qualification documents and relevant SOPs.\nMonitor and check records & logbooks in production areas to ensure that they are properly and timely filled out and maintained.\nEnsure entire production flows and processes are strictly compliant with GMP requirements and internal policy.\nAssistant in developing, implementing and maintaining the documentation system, including the SOPs and other production documents.\nMonitor the equipment and cleanroom hygiene according to the approval GMP procedure.\nParticipate in induction and on-job training to production staff.\nOther ad-hoc tasks as assigned by supervisors.\n\nAbout the talent:\n\n\nHigher Diploma or above in Science / Pharmaceutical or related subjects.\nRelevant experience in Food or GMP pharmaceutical manufacturing is preferred but not essential.\nFamiliar with MS office and Chinese word processing.\nHardworking, initiative, self-motivated and fast learner.\nAble to work under pressure and willing to work overtime.\nGood interpersonal skill and communication skill.\nGood command in written and spoken Chinese and English.\n\nWhat we offer:\n\nCareer with the market leader in health product sector from Hong Kong.\nDynamic working culture with great team spirit.\nShuttle to/from Yau Tong, Kowloon Tong, Tai Wai, Taipo, Tsuen Wan, Tuen Mun, Tin Shui Wai and Causeway Bay.\nRapid growth opportunities for strong performers.\nStaff purchase discount.\nCasual attire at work.\n\nInterested parties, please send full resume with last & expected salary and date of available by clicking \u2018Apply Now\u2019\n\nPersonal data collected is for recruitment purpose only.\n\nFor corporate information, please visit:\u00a0www.vitagreen.com", "employment_types": ["Full Time", "Permanent"], "selling_points": ["PIC/s GMP manufacturer", "Pharmaceutical production", "Great career opportunity"], "locations": ["Tai Po Area"], "categories": ["Manufacturing", "General / Production Workers", "Production Planning / Control", "Medical Services", "Pharmaceutical"], "post_time": "2022-01-14T11:26:59Z", "salary": {"currency": null, "max": null, "min": null, "period": "monthly", "term": null}, "salary_visible": false, "title_keywords": ["production officer"], "responsibilities": ["maintaining", "ad-hoc tasks", "monitor", "developing", "communication", "hygiene", "daily operations", "sops", "documentation", "work under pressure"], "requirements": {"degrees": ["higher diploma or above"], "majors": ["science"], "languages": ["english", "chinese"], "language_level": ["good command"], "hard_skills": ["documentation", "batch", "chinese word processing", "ms office"], "soft_skills": ["self-motivated", "work overtime", "timely", "communication skill", "interpersonal skill", "fast learner", "initiative", "hardworking", "work under pressure"], "languages_combined": [{"language": "english", "language_level": ["good command"]}, {"language": "chinese", "language_level": ["good command"]}]}, "experience_required": {"duration": [], "field": ["pharmaceutical", "food", "manufacturing", "relevant experience"]}}, {"job_id": "100003009054018", "location_code": "hk", "company": "Hong Kong Baptist University", "job_title": "\u52a9\u7406\u4e2d\u85e5\u914d\u85e5\u54e1 (\u4e2d\u91ab\u85e5\u8a3a\u6240) (PR0479/21-22)", "description": "\u4e2d \u91ab \u85e5 \u5b78 \u9662 \u81e8 \u5e8a \u90e8\n\n\u52a9\u7406\u4e2d\u85e5\u914d\u85e5\u54e1 (\u4e2d\u91ab\u85e5\u8a3a\u6240) (PR0479/21-22)\n\n\u8077\u8cac\u5305\u62ec\u53c3\u8207\u914d\u85e5\u3001\u714e\u85e5\u3001\u85e5\u623f\u7684\u65e5\u5e38\u5de5\u4f5c\u53ca\u8a3a\u6240\u90e8\u5206\u5176\u4ed6\u5de5\u4f5c\u3002\n\n\u7533\u8acb\u4eba\u9808\u6301\u6709\u8a8d\u53ef\u4e4b\u4e2d\u85e5\u57f9\u8a13\u8cc7\u6b77\uff0c\u4e26\u5177\u6709\u4e0d\u5c11\u65bc\u4e09\u5e74\u7684\u6709\u95dc\u5de5\u4f5c\u7d93\u9a57\u3002\u53e6\u9700\u719f\u8b58\u96fb\u8166\u64cd\u4f5c\uff0c\u80fd\u64cd\u6d41\u5229\u7cb5\u8a9e\u53ca\u7c21\u55ae\u82f1\u8a9e\uff0c\u61c2\u666e\u901a\u8a71\u8005\u66f4\u4f73\u3002\n\n\u6b64\u5916\uff0c\u61c9\u5fb5\u8005\u9808\u5b8c\u6210\u4e2d\u5b78\u8ab2\u7a0b\uff0c\u4e26\u65bc\u9999\u6e2f\u4e2d\u5b78\u6703\u8003\u53d6\u5f97\u6700\u5c11\u4e94\u79d1\u5408\u683c\uff0c\u6216\u65bc\u9999\u6e2f\u4e2d\u5b78\u6587\u6191\u8003\u8a66\u53d6\u5f97\u6700\u5c11\u4e94\u79d1\u90542\u7d1a\u6216\u4ee5\u4e0a\u6210\u7e3e\u3002\n\n\u5de5\u4f5c\u6642\u9593\u53ca\u5730\u9ede\uff1a\u9031\u4e00\u81f3\u9031\u516d\u5de5\u4f5c\u4e94\u5929\uff0c\u6bcf\u661f\u671f\u8f2a\u4f11\u65e5\u4e0d\u56fa\u5b9a\uff0c\u7531\u81e8\u5e8a\u90e8\u5b89\u6392\u3002\u5730\u9ede\u70ba\u81e8\u5e8a\u90e8\u8f44\u4e0b\u5404\u4e2d\u91ab\u85e5\u8a3a\u6240\uff0c\u6309\u5de5\u4f5c\u9700\u8981\u800c\u5b9a\u3002\n\n\u85aa\u916c\u53ca\u8077\u7d1a\u5c07\u6309\u8cc7\u6b77\u53ca\u6709\u95dc\u5de5\u4f5c\u7d93\u9a57\u800c\u5b9a\u3002\n\n\u7533\u8acb\u7a0b\u5e8f\uff1a\n\n\u7533\u8acb\u4eba\u53ef\u900f\u904e\u9999\u6e2f\u6d78\u6703\u5927\u5b78\u7db2\u4e0a\u6c42\u8077\u7cfb\u7d71(jobs.hkbu.edu.hk)\u905e\u4ea4\u7533\u8acb\u3002\u5982\u622a\u6b62\u7533\u8acb\u65e5\u671f\u5f8c8\u661f\u671f\u5167\u672a\u7372\u9762\u8a66\u901a\u77e5\u5247\u4f5c\u843d\u9078\u8ad6\u3002\u6709\u95dc\u5927\u5b78\u300c\u6536\u96c6\u500b\u4eba\u8cc7\u6599\u8072\u660e\u300d\u7684\u8cc7\u6599\u53ef\u700f\u89bdhttp://hro.hkbu.edu.hk/pics\u3002\u5927\u5b78\u4fdd\u7559\u6b0a\u5229\u53d6\u6d88\u62db\u8058\u4ee5\u4e0a\u6240\u520a\u767b\u7684\u8077\u4f4d\uff0c\u800c\u8058\u7528\u689d\u6b3e\u6703\u6309\u8058\u7528\u6642\u4e4b\u60c5\u6cc1\u800c\u5b9a\u3002\n\n\u622a\u6b62\u65e5\u671f\uff1a2022\u5e741\u670829\u65e5", "employment_types": ["Full Time"], "selling_points": ["\u6301\u6709\u8a8d\u53ef\u4e4b\u4e2d\u85e5\u57f9\u8a13\u8cc7\u6b77", "\u4e0d\u5c11\u65bc\u4e09\u5e74\u7684\u6709\u95dc\u5de5\u4f5c\u7d93\u9a57", "\u9808\u5b8c\u6210\u4e2d\u5b78\u8ab2\u7a0b"], "locations": ["Kowloon City"], "categories": ["Medical Services", "Specialist", "Others", "Pharmaceutical"], "post_time": "2022-01-17T08:05:14Z", "salary": {"currency": null, "max": null, "min": null, "period": "monthly", "term": null}, "salary_visible": false, "title_keywords": [], "responsibilities": [], "requirements": {"degrees": [], "majors": [], "languages": [], "language_level": [], "hard_skills": [], "soft_skills": [], "languages_combined": []}, "experience_required": {"duration": [], "field": []}}, {"job_id": "100003009050763", "location_code": "hk", "company": "Vita Green Pharmaceutical (H.K.) Limited", "job_title": "Quality Inspector", "description": "The Role:\n\nQuality Management plays a vital role in production while Vita Green Group is committed to serve our customers with the-highest-quality products in order to meet our customer satisfaction. We are now looking for candidates who are passionate in the discipline of quality control. You will be participating in the inspection of the whole production process, working closely with Production team and providing clerical support. Moreover, you are given opportunities to explore an international standard of food and drugs production by undertaking regular programs and calibrations.\n\u00a0\n\nIf you are ...\u00a0\n\na fresh graduate or the holder of Higher Diploma or above, preferably in Science, Chinese Medicine, Biotechnology, Biochemistry, Food Production, Manufacturing, Catering or Retail Industry.\nself motivated, flexible and interested in developing your career in a stable manufacturing environment and well known company.\na person who strives for renewal and improvement.\na team player\u00a0and willing to learn to develop yourself.\u00a0\n\n\n\nWe will offer you...\n\n\u00a0 \u00a0 \u00a0 \u00a0A career opportunity with the market leader in health product sector.\n\u00a0 \u00a0 \u00a0 \u00a0Casual wear everyday to enjoy your work.\n\u00a0 \u00a0 \u00a0 \u00a0Free shuttles from various locations.\n\u00a0 \u00a0 \u00a0 \u00a0Many opportunities\u00a0to learn and grow together.\n\u00a0 \u00a0 \u00a0 \u00a0Rapid growth opportunities for strong performers.\u202f\u00a0\n\u00a0 \u00a0 \u00a0 \u00a0Attractive staff purchase discount to experience our quality products.\n\nInterested parties, please send full resume with last & expected salary and date of available by clicking \u2018Apply\u2019.\n\nPersonal data collected is for recruitment purpose only.\n\nFor corporate information, please visit:\u00a0www.vitagreen.com", "employment_types": ["Full Time", "Permanent"], "selling_points": ["PIC/S GMP manufacturer", "Great career opportunity", "Performing inspection of production process"], "locations": ["Tai Po Area"], "categories": ["Medical Services", "Pharmaceutical", "Manufacturing", "Quality Assurance, Control & Testing / ISO", "Sciences, Lab, R&D", "Others"], "post_time": "2022-01-14T11:18:14Z", "salary": {"currency": null, "max": null, "min": null, "period": "monthly", "term": null}, "salary_visible": false, "title_keywords": [], "responsibilities": ["management", "production process", "quality", "clerical support", "developing", "inspection", "develop", "purchase", "quality control", "catering"], "requirements": {"degrees": ["higher diploma or above", "fresh graduate"], "majors": ["science", "manufacturing"], "languages": ["chinese"], "language_level": [], "hard_skills": ["rapid"], "soft_skills": ["passionate", "flexible", "interested in", "willing to learn", "self motivated", "committed", "team player", "stable"], "languages_combined": [{"language": "chinese", "language_level": []}]}, "experience_required": {"duration": [], "field": []}}, {"job_id": "100003009049396", "location_code": "hk", "company": "Hays", "job_title": "Product Specialist (Fresh Grad and CS background are Welcome!)", "description": "\u8077\u8cac:\n\n\u8ca0\u8cac\u5be9\u6838\u6295\u8cc7\u6587\u4ef6\uff0c\u7af6\u8abf\u6750\u6599\uff0c\u5f9e\u6cd5\u5f8b\u53ca\u5408\u898f\u98a8\u96aa\u7b49\u65b9\u9762\u51fa\u5177\u5167\u90e8\u6cd5\u5f8b\u610f\u898b\n\u8ca0\u8cac\u8207\u5916\u8058\u5f8b\u5e2b\u5354\u8abf\u548c\u6e9d\u901a\n\u53c3\u8207\u6295\u8cc7\u9805\u76ee\u6d89\u53ca\u53ca\u6cd5\u5f8b\u6587\u4ef6\u9032\u884c\u8d77\u8349\u3001\u5be9\u6838\uff0c\u51fa\u5177\u5167\u90e8\u6cd5\u5f8b\u610f\u898b\uff0c\u5fc5\u8981\u6642\u53c3\u8207\u6e9d\u901a\u548c\u8ac7\u5224\u3002\n\u4e0a\u7d1a\u4ea4\u8fa6\u7684\u5176\u4ed6\u4e8b\u52d9\u3002\n\n\u8981\u6c42:\n\n\n\u6cd5\u5b78\u5c08\u696d\uff0c\u5177\u6709\u4e2d\u570b\u5167\u5730\u6cd5\u5f8b\u8077\u696d\u8cc7\u683c\uff0c\u5982\u517c\u5177\u666e\u901a\u6cd5\u570b\u5bb6\u6216\u5730\u5340\u5f8b\u5e2b\u8cc7\u683c\u512a\u5148\n\u67093\u5e74\u4ee5\u4e0a\u5f9e\u4e8b\u5883\u5167\u5916\u6295\u8cc7\u4f75\u8cfc\u9805\u76ee\u7684\u6cd5\u5f8b\u5de5\u4f5c\u7d93\u9a57\u512a\u5148\n\u5177\u6709\u5feb\u901f\u5b78\u7fd2\u80fd\u529b\uff0c\u826f\u597d\u7684\u6e9d\u901a\u5354\u8abf\u80fd\u529b\u53ca\u5718\u968a\u5408\u4f5c\u7cbe\u795e\n\u5177\u5099\u512a\u79c0\u7684\u5206\u6790\uff0c\u89e3\u6c7a\u554f\u984c\u80fd\u529b\u53ca\u624e\u5be6\u7684\u6cd5\u5f8b\u6587\u66f8\u8d77\u8349\u529f\u5e95\uff0c\u826f\u597d\u7684\u4e2d\u82f1\u6587\u6e9d\u901a\u80fd\u529b\n\u5177\u6709\u516c\u53f8\u6cd5\u52d9\u5de5\u4f5c\u7d93\u9a57\u512a\u5148", "employment_types": ["Full Time", "Permanent"], "selling_points": ["Top 10 MNC Pharma", "Products of Market Leader", "Competitive salary package"], "locations": ["Not Specified"], "categories": ["Sciences, Lab, R&D", "Life Science", "Medical Services", "Pharmaceutical"], "post_time": "2022-01-14T08:33:06Z", "salary": {"currency": "HKD", "max": 34999, "min": 14000, "period": "monthly", "term": null}, "salary_visible": true, "title_keywords": ["product specialist"], "responsibilities": [], "requirements": {"degrees": [], "majors": [], "languages": [], "language_level": [], "hard_skills": [], "soft_skills": [], "languages_combined": []}, "experience_required": {"duration": [], "field": []}}, {"job_id": "100003009052659", "location_code": "hk", "company": "Ansen Company", "job_title": "Clinic Assistant (\u8a3a\u6240\u52a9\u8b77)", "description": "Key Roles and Responsibilities:\n\nSampling and testing of pharmaceutical products\nCalibration and maintenance of equipment\nDocumentation and other quality control activities\n\n\nQualifications and Experience:\n\nDegree or above in Chemistry or other related science disciplines\n1 year above experience is preferred\nFamiliar with testing instrumental analysis in HPLC, UV & FTIR\nFamiliar with GMP and ISO is a definite advantage\nHardworking, initiative, self-motivated and fast learner\nGood problem solving skills\nGood command in both written and spoken Cantonese and English\n\n\nWe offer to the right candidates with competitive remuneration package including 12-16 day annual leave, marriage leave, maternity leave, paternity leave, compassionate leave, Public Holidays, medical and dental insurance, educational sponsorship, overtime allowance, performance bonus, MPF and other fringe benefits.\n\nHow to Apply\n\nYou are invited to send in your application and CV stating the position you are applying for together with your current and expected salary by clicking the \"apply button\".\n\n\nVickmans Laboratories Limited is an Equal Opportunities Employer. Personal data provided by job applicants will be used strictly in accordance with our personal data policy and for recruitment purposes only. We aim to respond to successful applicants within 8 weeks and related information will be kept in our file for up to 12 months for other suitable vacancies in our organization and thereafter destroyed", "employment_types": ["Full Time", "Permanent"], "selling_points": [], "locations": ["Sheung Shui"], "categories": ["Medical Services", "Medical Services Technician", "Nursing", "Pharmaceutical"], "post_time": "2022-01-17T03:39:28Z", "salary": {"currency": null, "max": null, "min": null, "period": "monthly", "term": null}, "salary_visible": false, "title_keywords": ["clinic assistant", "\u8a3a\u6240\u52a9\u8b77"], "responsibilities": ["mpf", "maintenance", "analysis", "testing", "recruitment", "quality control", "documentation", "personal data", "insurance"], "requirements": {"degrees": ["degree or above"], "majors": ["science", "chemistry"], "languages": ["cantonese", "english"], "language_level": ["good command"], "hard_skills": ["documentation", "analysis", "problem solving skills", "maintenance"], "soft_skills": ["self-motivated", "fast learner", "problem solving skills", "instrumental", "initiative", "hardworking"], "languages_combined": [{"language": "cantonese", "language_level": ["good command"]}, {"language": "english", "language_level": ["good command"]}]}, "experience_required": {"duration": ["1 year"], "field": []}}, {"job_id": "100003009046780", "location_code": "hk", "company": "Europharm Laboratoires Company Limited", "job_title": "Senior / Regulatory Affairs Assistant", "description": "Top 10 biopharmaceutical focusing on research, development, and commercialization of prescription medicines\n\nYour new company\nA global leading biopharmaceutical focusing on the research, development, and commercialization of prescription medicines that is global, science-led, and patient-centered.\n\nYour new role\nResponsible for sales activities in assigned accounts or regions. Managed quality and consistency of product and service delivery.\n\n\nPromoting key products to current and new clients in the private and public sectors\nIdentify potential clients and collect market intelligence\nActively manage and grow dedicated sales territory in product pipeline\nResponsible for sales proposal\nCo-operate with marketing team to do promotion for growth of business\nBuild and maintain a good relationship with medical and pharmaceutical KOLs.\n\n\n\nWhat you'll need to succeed\n\nBachelor's degree or above in life science related disciplines (CS background are welcome!)\n2 to 3 years sales experience in pharmaceutical or medical company (fresh grad also welcome)\nStrong communication, interpersonal and presentation skills\nSales driven and customer focus to enhance good relationship with different parties\nProactive, self-motivated with passion to overcome challenges\nFluent in English and Cantonese, fluent in Mandarin will be an advantage\n\n\nWhat you need to do now\nIf you are interested in the above opportunity, please forward your latest resume to rooney.wu@hays.com.hk or contact +852 Rooney at 2230 7913 for more information.\n\nIf this role isn't quite right for you but you are looking to explore new opportunities in the life science sector, please contact Rooney for a confidential discussion about your options.", "employment_types": ["Full Time", "Permanent"], "selling_points": [], "locations": ["Tai Po Area"], "categories": ["Sciences, Lab, R&D", "Life Science", "Medical Services", "Pharmaceutical", "Manufacturing", "Quality Assurance, Control & Testing / ISO"], "post_time": "2022-01-14T01:03:57Z", "salary": {"currency": null, "max": null, "min": null, "period": "monthly", "term": null}, "salary_visible": false, "title_keywords": ["regulatory affairs assistant"], "responsibilities": ["service delivery", "sales activities", "quality", "good relationship", "communication", "commercialization", "co-operate with", "maintain", "contact"], "requirements": {"degrees": ["degree or above", "bachelor"], "majors": ["related disciplines", "science"], "languages": ["cantonese", "english", "mandarin"], "language_level": ["advantage", "fluent"], "hard_skills": ["focus"], "soft_skills": ["self-motivated", "responsible", "interested in", "driven", "communication", "presentation skills", "customer focus", "patient", "proactive", "interpersonal"], "languages_combined": [{"language": "cantonese", "language_level": ["advantage"]}, {"language": "english", "language_level": ["advantage"]}, {"language": "mandarin", "language_level": ["fluent", "advantage"]}]}, "experience_required": {"duration": ["2 to 3 years"], "field": ["pharmaceutical", "medical"]}}, {"job_id": "100003009046799", "location_code": "hk", "company": "Wai Yuen Tong Medicine Co Ltd", "job_title": "QC Officer / Senior QC Officer", "description": "Research Assistant I/II in the Department of Pharmacology and Pharmacy\u00a0(Ref.: 509215)\u00a0(to commence as soon as possible for one year, with the possibility of renewal)\n\nApplicants should possess a Bachelor\u2019s degree in pharmacy, pharmaceutical science, biomedical engineering, biology, biochemistry or related disciplines.\u00a0 Experience in cellular and in-vivo studies will be an advantage.\u00a0 The appointee will conduct research in nanoparticle-based drug delivery systems.\u00a0 Enquiries about the duties of the post should be sent to Dr. Aviva Chow at\u00a0[via APPLY NOW]\n\nA competitive salary commensurate with qualifications and experience will be offered, in addition to annual leave and medical benefits.\n\nThe University only accepts online application for the above post.\u00a0 Applicants should apply online and upload an up-to-date C.V.\u00a0 Review of applications will start on December 28, 2021 and continue until\u00a0February 28, 2022, or until the post is filled, whichever is earlier.\n\n\u6709\u610f\u7533\u8acb\u8005\u8acb \u6309 APPLY NOW\u7533\u8acb\n\n", "employment_types": ["Full Time", "Permanent"], "selling_points": ["Mini 2 yrs experience in GMP pharmaceutical plant", "Higher Diploma or above", "operating ICP / HPLC / UV / Microbial Testing"], "locations": ["Yuen Long"], "categories": ["Sciences, Lab, R&D", "Chemical", "Medical Services", "Pharmaceutical"], "post_time": "2022-01-14T01:12:46Z", "salary": {"currency": null, "max": null, "min": null, "period": "monthly", "term": null}, "salary_visible": false, "title_keywords": ["qc officer"], "responsibilities": ["systems", "conduct research"], "requirements": {"degrees": ["degree", "bachelor"], "majors": ["related disciplines", "science", "biology", "biomedical engineering"], "languages": [], "language_level": [], "hard_skills": [], "soft_skills": [], "languages_combined": []}, "experience_required": {"duration": [], "field": []}}, {"job_id": "100003009045938", "location_code": "hk", "company": "The University of Hong Kong", "job_title": "Post-doctoral Fellow (509007)", "description": "Key Roles and Responsibilities:\n\n\nResponsible for assisting the Head of Regulatory Affairs as well as the General Manager in maintaining the operation of the Regulatory Affairs and Pharmacovigilance Department\u00a0to handle all regulatory related matters;\nCommunicate with Department of Health and respond to their queries;\nLiaise closely with our Production and Quality Control Department regarding documentation and product files for pharmaceutical products;\nCoordinate prompt registration of new pharmaceutical products in Hong Kong, application for change of particulars of products and renewal of product registration certificates;\nMaintain product registration files and monitor submission timeline; &\nSupport any other special tasks as assigned by the Head of Regulatory Affairs and the General Manager.\n\n\nQualifications and Experience\n\n\nDegree-holder in Life Science, Pharmacology or Medical related field, or Language Studies who studied Sciences in Secondary School;\nExcellent communication and interpersonal skills to work with people of different levels and cultures;\nAble to work independently with good organization skills, highly self-motivated and detail oriented;\nProficiency in both written and spoken English;\n\nCandidate with relevant work experience in RA / Pharmaceutical industry will be considered as Senior Regulatory Affairs Assistant;\n\nImmediately available is highly preferred.\n\u00a0\n\n\nYou are invited to send in your application and CV stating your expected salary (please remember to mention your expected salary), either by Clicking \"Apply Now\".\n\nEuropharm Laboratoires Company Limited is an equal opportunities employer. The information provided will be treated in strict confidence and used only for consideration of application for relevant/similar post(s).\u00a0 All personal data of unsuccessful applicants will be destroyed within 6 months.", "employment_types": ["Full Time"], "selling_points": [], "locations": ["Pok Fu Lam"], "categories": ["Medical Services", "Medical Services Technician", "Others", "Pharmaceutical"], "post_time": "2022-01-13T09:11:25Z", "salary": {"currency": null, "max": null, "min": null, "period": "monthly", "term": null}, "salary_visible": false, "title_keywords": [], "responsibilities": ["communicate with", "liaise", "maintaining", "monitor", "coordinate", "communication", "maintain", "quality control", "documentation", "personal data"], "requirements": {"degrees": ["degree"], "majors": ["pharmacology", "science"], "languages": ["english"], "language_level": ["proficiency"], "hard_skills": ["documentation"], "soft_skills": ["work independently", "self-motivated", "confidence", "responsible", "prompt", "detail oriented", "communication and interpersonal skills", "organization skills"], "languages_combined": [{"language": "english", "language_level": ["proficiency"]}]}, "experience_required": {"duration": [], "field": ["pharmaceutical", "regulatory affairs"]}}, {"job_id": "100003009046797", "location_code": "hk", "company": "Wai Yuen Tong Medicine Co Ltd", "job_title": "QC Technician", "description": "Responsibilities:\n\nLead a team of technicians and provide technical and managing supervision in the QC laboratory\nSupervise routine sampling, inspection and testing on starting materials, in-process samples and finished products to fulfill GMP's requirement\nManage the lab routine operation\nAssist QC related documents set up, such as specification, method, SOP\nCo-ordinate and participate in calibration, method validation, equipment qualification\nAssist in Batch Production Record reviewing\n\nRequirements:\n\nHigher Diploma holder or above in Chemistry / Pharmaceutical/ Biology Studies or related disciplines\nMinimum 2 year\u00a0supervisory\u00a0experience in\u00a0commercial laboratory / GMP certified pharmaceutical plant\nHands-on experience in operating ICP / HPLC / UV / Microbial Testing\nGood leadership and teambuilding skill\nComputer knowledge in MS Office and Chinese Word Processing\nProactive, attentive to details with good communication and interpersonal skills\nMore experience will be consider as Senior QC Officer\n\nInterested parties please send full resume with present and expected salary to Human Resources Department by clicking \"APPLY NOW\".\n\n(Information provided will be treated in strict confidence and will only be used for recruitment-related purposes.)", "employment_types": ["Full Time", "Permanent"], "selling_points": ["1 yrs experience in GMP pharmaceutical plant", "Higher Diploma or above", "operating ICP / HPLC / UV / Microbial Testing"], "locations": ["Yuen Long"], "categories": ["Sciences, Lab, R&D", "Chemical", "Medical Services", "Pharmaceutical"], "post_time": "2022-01-14T01:11:56Z", "salary": {"currency": null, "max": null, "min": null, "period": "monthly", "term": null}, "salary_visible": false, "title_keywords": ["qc technician"], "responsibilities": ["related documents", "lead a team", "testing", "inspection"], "requirements": {"degrees": ["higher diploma holder"], "majors": ["related disciplines", "biology", "chemistry"], "languages": ["chinese"], "language_level": [], "hard_skills": ["chinese word processing", "ms office"], "soft_skills": ["attentive to details", "hands-on", "communication and interpersonal skills", "proactive", "leadership"], "languages_combined": [{"language": "chinese", "language_level": []}]}, "experience_required": {"duration": ["minimum 2 year"], "field": ["commercial laboratory", "pharmaceutical", "testing", "supervisory experience"]}}, {"job_id": "100003009048836", "location_code": "hk", "company": "Efficiency Medical Products Company Limited", "job_title": "Sales Executive", "description": "Applications are invited for appointment as\u00a0Post-doctoral Fellow in the Department of Medicine\u00a0(Ref.: 509007), to commence as soon as possible for one year, with the possibility of renewal, subject to satisfactory performance.\n\nApplicants should possess a Ph.D. degree or equivalent, and fluency in written and spoken English and Chinese.\u00a0 They should be experienced in tissue cultures, molecular works, animal handling (zebrafish or mouse) as well as big data analysis.\u00a0 The appointee will be engaged in translational research projects in human leukemia and hematopoiesis in a highly interactive environment.\n\nThose who have responded to the previous advertisement (Ref.: 508431) need not re-apply.\n\nA highly competitive salary commensurate with qualifications and experience will be offered, in addition to annual leave and medical benefits.\n\nThe University only accepts online application for the above post.\u00a0 Applicants should apply online and upload an up-to-date C.V.\u00a0 Review of applications will start on December 1, 2021 and continue until\u00a0February 28, 2022, or until the post is filled, whichever is earlier.\n\nAdvertised:Nov 23, 2021 (HK Time)\nApplications close:Feb 28, 2022 (HK Time)\n\n\u6709\u610f\u7533\u8acb\u8005\u8acb \u6309 APPLY NOW\u7533\u8acb\n\n", "employment_types": ["Full Time"], "selling_points": [], "locations": ["Kwun Tong"], "categories": ["Medical Services", "Medical Services Technician", "Pharmaceutical", "Sales, CS & Business Devpt", "Account Servicing"], "post_time": "2022-01-14T09:53:51Z", "salary": {"currency": null, "max": null, "min": null, "period": "monthly", "term": null}, "salary_visible": false, "title_keywords": ["sales executive"], "responsibilities": ["analysis", "big data", "research projects"], "requirements": {"degrees": ["degree"], "majors": [], "languages": ["english", "chinese"], "language_level": ["fluency"], "hard_skills": ["mouse", "analysis", "animal handling"], "soft_skills": [], "languages_combined": [{"language": "english", "language_level": ["fluency"]}, {"language": "chinese", "language_level": ["fluency"]}]}, "experience_required": {"duration": [], "field": []}}, {"job_id": "100003009037810", "location_code": "hk", "company": "Hong Kong Regen Medtech Limited", "job_title": "Production Manager", "description": "Responsibilities:\n\nConduct physical / chemical / microbial testing on TCM products;\nPerform equipment calibration and performance checking;\nAssist in monitoring routine sampling, inspection and testing on starting materials, intermediate and finished products as per GMP\u2019s requirement;\nAssist in establishing Standard Operating Procedures and specifications for starting materials, intermediate and finished products;\nConduct other relevant duties as assigned by Head of QC.\n\nRequirements:\n\nHigher Diploma or above in Chemical/ Pharmaceutical or related disciplines;\nHands-on experience in operating ICP / HPLC / UV / Microbial Testing is an absolute advantage;\nProactive, attentive to details with good communication and interpersonal skills;\nComputer knowledge in MS Office and Chinese Word Processing\nFresh graduated will also be considered\n\nInterested parties please send full resume with present and expected salary to Human Resources Department by clicking \"APPLY NOW\".\n\n(Information provided will be treated in strict confidence and will only be used for recruitment-related purposes.)", "employment_types": ["Full Time"], "selling_points": [], "locations": ["Shatin Area"], "categories": ["Manufacturing", "Production Planning / Control", "Medical Services", "Pharmaceutical"], "post_time": "2022-01-11T03:55:34Z", "salary": {"currency": null, "max": null, "min": null, "period": "monthly", "term": null}, "salary_visible": false, "title_keywords": ["production manager"], "responsibilities": ["monitoring", "procedures", "checking", "inspection", "testing", "specifications"], "requirements": {"degrees": ["higher diploma or above"], "majors": ["related disciplines"], "languages": ["chinese"], "language_level": [], "hard_skills": ["chinese word processing", "ms office"], "soft_skills": ["hands-on", "proactive", "communication and interpersonal skills", "attentive to details"], "languages_combined": [{"language": "chinese", "language_level": []}]}, "experience_required": {"duration": [], "field": ["testing"]}}, {"job_id": "100003009043824", "location_code": "hk", "company": "Hong Kong Adventist Hospital - Stubbs Road", "job_title": "Dispenser II (Full-time) Adventist Medical Center", "description": "Job Requirements:\n\n- Diploma or above with previous experience in sales (preferrable in medical equipment field)\n\n- Strong communication and presentation skills in fluent Cantonese and English. Mandarin is an advantage.\n\n-\u00a0Excellent written and spoken skills in Chinese and English.\n\n- Outgoing and willing to learn about medical equipment knowledge and technology\n\n- Fresh graduate will also be considered.\n\nKey Responsibilities:\n\n- Responsible for sales\u00a0of medical equipment to medical professionals\n\n- Visit existing clients, follow up orders, and develop new accounts\n\n- Provide product demonstration and assist in trade show and workshop\n\n- On the job training\u00a0will be provided\n\nStable\u00a0career, \u00a0long-term\u00a0development\u00a0in medical industry and good remuneration package will be offered to the right candidate.\n\nInterested candidates, please email resume and expected salary to Ms. Chau", "employment_types": ["Full Time"], "selling_points": [], "locations": ["Not Specified"], "categories": ["Medical Services", "Others", "Pharmaceutical"], "post_time": "2022-01-13T02:08:35Z", "salary": {"currency": null, "max": null, "min": null, "period": "monthly", "term": null}, "salary_visible": false, "title_keywords": ["dispenser"], "responsibilities": ["follow up orders", "workshop", "develop"], "requirements": {"degrees": ["fresh graduate", "diploma or above"], "majors": [], "languages": ["cantonese", "english", "chinese", "mandarin"], "language_level": ["advantage", "excellent", "fluent"], "hard_skills": [], "soft_skills": ["communication", "outgoing", "presentation skills", "willing to learn"], "languages_combined": [{"language": "cantonese", "language_level": ["fluent"]}, {"language": "english", "language_level": ["fluent", "excellent"]}, {"language": "chinese", "language_level": ["fluent", "excellent"]}, {"language": "mandarin", "language_level": ["advantage"]}]}, "experience_required": {"duration": [], "field": ["medical equipment"]}}, {"job_id": "100003009047925", "location_code": "hk", "company": "The University of Hong Kong", "job_title": "Post-doctoral Fellow (508841)", "description": "Applications are invited for appointment as\u00a0Post-doctoral Fellow in the Department of Pharmacology and Pharmacy\u00a0(Ref.: 509153), to commence as soon as possible for two years, with the possibility of renewal.\n\nApplicants should possess a Ph.D. degree in biological/medical sciences, pharmaceutical analysis or a related discipline.\u00a0 Preference will be given to those with experience in pharmacology research, animal studies and chemical analysis.\u00a0 Applicants should be organized, self-motivated, able to multi-task, and able to work independently as well as in a team.\u00a0 The appointee will work on research projects related to herbal medicine under the supervision of Dr. George Leung.\u00a0\u00a0 Enquiries about the duties of the post should be sent to Dr. Leung at\u00a0\u00a0[via APPLY NOW]\n\nA competitive salary commensurate with qualifications and experience will be offered, in addition to annual leave and medical benefits.\n\nThe University only accept online application for the post.\u00a0 Applicants should apply online and upload an up-to-date C.V.\u00a0together with a research publication list.\u00a0 Review of applications will start on December 23, 2021 and continue until\u00a0February 28, 2022, or until the post is filled, whichever is earlier.\n\nAdvertised:Dec 9, 2021 (HK Time)\nApplications close:Feb 28, 2022 (HK Time)\n\n\u6709\u610f\u7533\u8acb\u8005\u8acb \u6309 APPLY NOW\u7533\u8acb\n\n", "employment_types": ["Full Time"], "selling_points": ["work under the supervision of Professor Z.J. Zhang", "Ph.D. degree, with laboratory research experience", "have a track record of publication"], "locations": ["Pok Fu Lam"], "categories": ["Medical Services", "Doctor / Practitioner / Surgeon", "Specialist", "Pharmaceutical"], "post_time": "2022-01-14T04:16:42Z", "salary": {"currency": null, "max": null, "min": null, "period": "monthly", "term": null}, "salary_visible": false, "title_keywords": [], "responsibilities": ["analysis", "research projects"], "requirements": {"degrees": ["degree"], "majors": [], "languages": [], "language_level": [], "hard_skills": ["george", "analysis", "animal studies"], "soft_skills": ["organized", "self-motivated", "multi-task", "work independently"], "languages_combined": []}, "experience_required": {"duration": [], "field": ["research"]}}, {"job_id": "100003009046875", "location_code": "hk", "company": "SYNCO (H.K.) Ltd", "job_title": "QA Assistant / Assistant QA Officer", "description": "Research Assistant I/II in the Department of Pharmacology and Pharmacy\u00a0(Ref.: 509152)\u00a0(to commence as soon as possible on a two-year fixed-term basis with contract-end gratuity and University contribution to a retirement benefits scheme, totalling up to 10% of basic salary, and with the possibility of renewal)\n\nApplicants should possess a Bachelor\u2019s degree or equivalent in biological/medical sciences, chemistry or a related field.\u00a0 They should be highly motivated and able to work independently. Preference will be given to those with experience in pharmacology research, cell culture, animal studies and chemical analysis.\u00a0 The appointee will conduct studies related to herbal medicine.\u00a0 Enquiries about the duties of the post should be sent to Dr. George Leung at\u00a0[via APPLY NOW]\n\nA highly competitive salary commensurate with qualifications and experience will be offered, in addition to annual leave and medical benefits.\n\nThe University only accepts online applications for the above post.\u00a0 Applicants should apply online and upload an up-to-date C.V. Review of applications will start on December 23, 2021 and continue until\u00a0February 28, 2022, or until the post is filled, whichever is earlier.\n\n\u6709\u610f\u7533\u8acb\u8005\u8acb \u6309 APPLY NOW\u7533\u8acb\n\n", "employment_types": ["Full Time", "Permanent"], "selling_points": [], "locations": ["Tai Po Area"], "categories": ["Hospitality / F & B", "Others", "Medical Services", "Pharmaceutical", "Manufacturing", "Quality Assurance, Control & Testing / ISO"], "post_time": "2022-01-14T01:33:41Z", "salary": {"currency": null, "max": null, "min": null, "period": null, "term": null}, "salary_visible": false, "title_keywords": ["qa assistant", "assistant qa officer"], "responsibilities": ["analysis"], "requirements": {"degrees": ["degree", "bachelor"], "majors": ["chemistry"], "languages": [], "language_level": [], "hard_skills": ["george", "basic", "analysis", "scheme", "animal studies"], "soft_skills": ["work independently", "motivated"], "languages_combined": []}, "experience_required": {"duration": [], "field": ["research"]}}, {"job_id": "100003009038407", "location_code": "hk", "company": "Athenex HK Innovative Limited", "job_title": "Associate Scientist/Scientist", "description": "Product Manager position from a global leading pharmaceutical.\n\nYour new company\nYou will be working with a global leading pharmaceutical. To further expand their business in the Hong Kong team, they are now looking for a bright candidate to join their marketing team.\n\nYour new role\nResponsible for marketing activities in assigned specialty drugs (Speciality Care). To lead, plan and execute the marketing strategy and activity.\n\nResponsible for launching the new star product in HK & Macau markets\nAccountable for the strategic plan that maximizes patient impact and the financial objects for the specialty drugs\nExecute marketing plan in a correct direction through timely cross-functional\nConduct market research to understand the market and competitors to collect more information and adjust the strategic plan for the product\nLead the portfolio team, monitoring its effectiveness and performance and collaboration with Sales and Medial departments to achieve business objectives\nBy designing and implementing promotional materials\nPlan and manage the annual budget\nBuild long term relationships with key account customers and external stakeholders to gain new insights and ideas\n\n\nWhat you'll need to succeed\nYou will need 5 years' marketing experience in the pharmaceutical industry with at least 2 years of brand management experience\n\nAn excellent understanding of product strategy and good commercial acumen\nBachelor degree holder or above, preferred in Science or Business related disciplines\nStrong collaboration working with a wide variety of key stakeholders\nExcellent communication and interpersonal skills; self-motivated\nGood command of both English & Chinese language, fluent in Mandarin is a plus\n\n\nWhat you need to do now\nIf you are interested in the above opportunity, please forward your latest resume to Turby.ho@hays.com.hk or contact Turby at 2101 0042 for more information.\n\nIf this role isn't quite right for you but you are looking to explore new opportunities in the life science sector, please contact Turby for a confidential discussion about your options.", "employment_types": ["Full Time"], "selling_points": ["Global Specialty Oncology Pharmaceutical Group", "Novel Pharmaceutical Formulations", "Group Medical Insurance, 5 days work week"], "locations": ["Tsim Sha Tsui"], "categories": ["Medical Services", "Pharmaceutical"], "post_time": "2022-01-12T02:01:12Z", "salary": {"currency": null, "max": null, "min": null, "period": "monthly", "term": null}, "salary_visible": false, "title_keywords": ["associate", "scientist"], "responsibilities": ["management", "ideas", "conduct market research", "monitoring", "budget", "communication", "marketing plan", "promotional materials", "contact", "plan", "designing"], "requirements": {"degrees": ["bachelor degree holder"], "majors": ["related disciplines", "science", "business"], "languages": ["english", "chinese", "mandarin"], "language_level": ["good command", "fluent"], "hard_skills": ["plus", "acumen"], "soft_skills": ["self-motivated", "responsible", "timely", "interested in", "accountable", "communication and interpersonal skills", "patient"], "languages_combined": [{"language": "english", "language_level": ["good command"]}, {"language": "chinese", "language_level": ["good command"]}, {"language": "mandarin", "language_level": ["fluent", "good command"]}]}, "experience_required": {"duration": ["5 years", "at least 2 years"], "field": ["pharmaceutical", "management", "marketing", "brand"]}}, {"job_id": "100003009049630", "location_code": "hk", "company": "New Beta Innovation Limited", "job_title": "Manager - R&D (Protein Purification Development/ Scale-up)", "description": "Sales Careers\n\nWe take pride in helping our employees to build a career for themselves by giving opportunities to learn, perform and grow.\n\nWe also provide a training and attractive rewards to encourage our employees working with full dedication and moving to a higher advancement.\n\nNow, we are on a constant hunt for the talented and enthusiastic professional as follow:\n\nPrivate Clinics Sales Representatives.\nDrugstores/ Pharmacies Sales Representatives.\n\nIf you are an experienced sales professional in the same field or a new beginner who wishes to enter pharmaceutical industry. Please drop-in your full resume at : APPLY NOW", "employment_types": ["Full Time", "Permanent"], "selling_points": ["Research Job in Professional firm", "Attractive remuneration and benefits", "5 days work and location closed to MTR"], "locations": ["Kowloon Bay"], "categories": ["Sciences, Lab, R&D", "Life Science", "Medical Services", "Pharmaceutical", "Research & Development (R&D)"], "post_time": "2022-01-14T08:59:48Z", "salary": {"currency": null, "max": null, "min": null, "period": "monthly", "term": null}, "salary_visible": false, "title_keywords": ["manager"], "responsibilities": [], "requirements": {"degrees": [], "majors": [], "languages": [], "language_level": [], "hard_skills": [], "soft_skills": ["enthusiastic"], "languages_combined": []}, "experience_required": {"duration": [], "field": []}}, {"job_id": "100003009046714", "location_code": "hk", "company": "Julius Chen & Company (HK) Limited", "job_title": "Pharma Sales Representatives", "description": "Complete registration under the Medical Registration Ordinance of Hong Kong\n\u00a0LMC or\u00a0fresh grad\u00a0will also be considered\n\u00a0Excellent interpersonal and communication skill\n\u00a0Working location: Central / Mongkok / Causeway Bay\n\u00a0Sunday and Public holidays off, no night shift duty required\u00a0\n\nWe offer attractive remuneration.\u00a0 Please send a detailed resume and expected salary to HR Dept, 2/F., Bonaventure House, 91 Leighton Road, Causeway Bay, Hong Kong.", "employment_types": ["Full Time"], "selling_points": [], "locations": ["Not Specified"], "categories": ["Medical Services", "Pharmaceutical", "Sales, CS & Business Devpt", "Wholesale"], "post_time": "2022-01-13T22:52:47Z", "salary": {"currency": null, "max": null, "min": null, "period": "monthly", "term": null}, "salary_visible": false, "title_keywords": ["pharma sales representatives"], "responsibilities": ["communication", "complete registration"], "requirements": {"degrees": [], "majors": [], "languages": [], "language_level": [], "hard_skills": ["no"], "soft_skills": ["communication skill", "interpersonal"], "languages_combined": []}, "experience_required": {"duration": [], "field": []}}, {"job_id": "100003009051416", "location_code": "hk", "company": "Medifast (Hong Kong) Limited", "job_title": "Medical Practitioners / Medical Doctor (Full/Part Time)", "description": "Hughs has increased its focus on the healthcare business with the belief that has opportunities in global markets. \u00a0Hughs has utilized its broad network of consultants and scientists to identify potential pharmaceutical products and exports these products to global markets.\nBTXA\u2122 is a global brand of botulinum toxin type A with outstanding efficacy and guaranteed safety. She has registered in more than 30 countries worldwide and have a decade of famed history.\n\nWe are now looking for a Regulatory\u00a0Affairs Associate/Executive to join our dynamic team.\n\nWebsite: www.btxa.com\n\nResponsibilities:\n\nKey liaison person for the Department of Health, oversea distributors and\u00a0suppliers\nSupport dossier compilation to ensure ready to submit dossier is available as local /global requirements\nReview the packaging and marketing materials for our products to ensure the compliance to Laws and Regulations\nLead and conduct regular internal and external audit to maintain ISO standard\nAssist in Good Distribution Practice and warehouse monitory\nWell document the copies record of submitted dossiers with accuracy and good filing practice.\n\nSpecial requirements:\n\n\n\nDegree holder in health-related science, life science, Pharmacy or Medical degree desirable\u00a0\nAt least\u00a01 year experiences in QA and Regulatory affairs of Pharmaceutical/Drug registration or other equivalent quality system.\nKnowledge in regulatory affairs and drug registration for Hong Kong and overseas markets is highly preferred\nCandidate with less experience will be considered as Regulatory Affairs Associate\nBenefits\n\nFive-day-work\nBank Holidays\nPerformance bonus\nMedical Insurance\nMarriage Leave\nStaff Purchase Discount\n\u00a0", "employment_types": ["Full Time", "Part Time", "Permanent", "Temporary"], "selling_points": [], "locations": ["Causeway Bay"], "categories": ["Beauty Care / Health", "Others", "Medical Services", "Doctor / Practitioner / Surgeon", "Pharmaceutical"], "post_time": "2022-01-15T15:14:06Z", "salary": {"currency": null, "max": null, "min": null, "period": "monthly", "term": null}, "salary_visible": false, "title_keywords": ["medical doctor", "medical practitioners"], "responsibilities": ["regulations", "compliance", "review", "audit", "maintain", "marketing materials"], "requirements": {"degrees": ["degree", "degree holder"], "majors": ["science"], "languages": [], "language_level": [], "hard_skills": [], "soft_skills": [], "languages_combined": []}, "experience_required": {"duration": ["at least 1 year"], "field": ["pharmaceutical", "drug registration", "regulatory affairs", "qa"]}}, {"job_id": "100003009045856", "location_code": "hk", "company": "Quality HealthCare Medical Services Ltd", "job_title": "Pharmacist", "description": "In the heart of the role:\n\n\n\nTo support central pharmacy department in delivering an efficient and effective advisory service to clinics / business units in relation to dispensary drug inventory management, dispensing, drug administration and prescribing\nTo provide expert advice to internal and external stakeholders on the safe and effective use of medicines\nTo identify and verify any discrepancies with clinics as necessary\nTo assist in drug management IT system enhancement\nTo assist in the review and update of agreed drug fees\nTo demonstrate a working knowledge of clinical governance and relevant legislations to ensure compliance on regulatory and legal requirements\nTo work in a collaborative manner with other health care professionals to ensure the pharmaceutical and dispensing services meet the needs of corporate client and patient expectations\nTo assist in the development of tools for the delivery of safe and optimal patient care\nTo contribute in the development and implementation of medicine management related policies and standard operating procedures\nTo deliver education and training for dispensary staff, other health care professionals and business units\nTo undertake audits of dispensary services, prescription trends and generate reports\nTo assist in drug formulary and inventory management\nTo contribute to the development and implementation of contract specific formularies and prescribing guidelines/information\nTo assist in supervising staff\nTo undertake any other duties and initiatives as assigned by senior\u00a0\n\nDesired Qualification & Experience:\n\n\n\nDegree in Pharmacy\nPostgraduate clinical pharmacy qualification is desirable\nHolder of Certificate of Registration and a valid Practicing Certificate issued by the Pharmacy and Poisons Board of Hong Kong\nA minimum of 2 year postgraduate pharmacy experience\nSelf motivated; committed to continuing professional development and learning\nGood organising skill\nGood verbal and written communication skills\nGood interpersonal and influencing skills\nFluency in English and Chinese\nProficient in Microsoft Office applications\nAbility to prioritize own work\nAbility to work under pressure and meet deadline\nAbility to work well independently and as part of a team\nFlexible in approach to meet service needs\n\n(All applications will be treated in strict confidence and data collected will be used for recruitment purposes only)", "employment_types": ["Full Time", "Permanent"], "selling_points": ["Able to work with different stakeholders", "Strong communications skills", "Minimum of 2 year postgraduate pharmacy experience"], "locations": ["Kowloon Bay"], "categories": ["Medical Services", "Pharmaceutical"], "post_time": "2022-01-13T08:55:45Z", "salary": {"currency": null, "max": null, "min": null, "period": "monthly", "term": null}, "salary_visible": false, "title_keywords": ["pharmacist"], "responsibilities": ["any other duties", "supervising", "data", "inventory management", "communication", "work under pressure", "administration", "implementation", "reports", "legislations", "management", "review", "procedures", "expert advice", "audits", "guidelines", "policies", "ensure compliance", "recruitment"], "requirements": {"degrees": ["certificate", "degree"], "majors": [], "languages": ["english", "chinese"], "language_level": ["fluency"], "hard_skills": ["safe", "microsoft office"], "soft_skills": ["efficient", "communication skills", "flexible", "independently", "confidence", "collaborative", "prioritize", "self motivated", "committed", "learning", "patient", "interpersonal", "work under pressure"], "languages_combined": [{"language": "english", "language_level": ["fluency"]}, {"language": "chinese", "language_level": ["fluency"]}]}, "experience_required": {"duration": ["minimum of 2 year"], "field": []}}, {"job_id": "100003009044327", "location_code": "hk", "company": "Quality HealthCare Medical Services Ltd", "job_title": "Dispenser II (Sha Tin)", "description": "Our client, a biotechnology company\u00a0is looking for\u00a0Clinical Research Associate / Assistant to join their Team.\u00a0\n\n\u00a0Responsibilities:\n\nDatabase design and data entry, and simple statistic.\nLiaise with multiple units including wards and clinics;\nPerform clinical tasks such as dispensing study products\nCoordinating and monitoring sponsored clinical research projects with the investigators and research teams.\nResearch documents preparation and research ethics application.\n\nRequirements:\n\nUniversity degree,\u00a0life sciences degree.\nHaving solid clinical research experience\nGood command of both written and verbal English and Chinese. Putonghua\nAbility to work independently under pressure with attention to details.\nStrong communicational, interpersonal, organizational and time management skills.\nStrong organizational, analytical and multitasking skills\nAble to work in flexible hours and on irregular days.", "employment_types": ["Full Time", "Permanent"], "selling_points": ["HD in Dispensing Studies or related subjects", "Dispense drugs, counel patients, drugs management", "Shift duty is required (No night shift)"], "locations": ["Shatin Area"], "categories": ["Medical Services", "Medical Services Technician", "Others", "Pharmaceutical"], "post_time": "2022-01-13T03:45:37Z", "salary": {"currency": null, "max": null, "min": null, "period": "monthly", "term": null}, "salary_visible": false, "title_keywords": ["dispenser"], "responsibilities": ["data entry", "research projects", "monitoring", "teams", "design", "database", "liaise with"], "requirements": {"degrees": ["university degree", "degree"], "majors": [], "languages": ["putonghua", "english", "chinese"], "language_level": ["good command"], "hard_skills": [], "soft_skills": ["flexible", "work independently", "under pressure", "time management skills", "organizational", "attention to details", "interpersonal"], "languages_combined": [{"language": "putonghua", "language_level": []}, {"language": "english", "language_level": ["good command"]}, {"language": "chinese", "language_level": ["good command"]}]}, "experience_required": {"duration": [], "field": ["research", "clinical"]}}, {"job_id": "100003009044330", "location_code": "hk", "company": "Quality HealthCare Medical Services Ltd", "job_title": "Dispenser II (Tsim Sha Tsui)", "description": "Applications are invited for appointment as\u00a0Post-doctoral Fellow in the Department of Medicine\u00a0(Ref.: 509134), to commence as soon as possible for two years, with the possibility of renewal subject to satisfactory performance.\n\nApplicants should possess a Ph.D. degree or equivalent. \u00a0They should have relevant experience in neuroscience research, cell and molecular biology, histological techniques, confocal microscopy, and animal (mouse) experimentation; and good communication and presentation skills.\u00a0 They should also be self-motivated, organized, and able to work independently and in a team. \u00a0Prior experience in molecular cloning and protein purification is an advantage.\n\nThe appointee will join a friendly, dynamic and dedicated research team using state-of-the-art equipment with the opportunity to work in a highly collaborative and international environment.\u00a0 He/She will explore molecular mechanisms and novel therapeutic strategies of Parkinson's disease (PD). \u00a0The project involves phenotypic and behavioral studies of mutant (LRRK2 knock-in) mouse model of PD, as well as establishing human PD patient-specific induced pluripotent stem cells (iPSCs) for pathophysiological studies. \u00a0Applicants who have responded to the previous advertisement (Ref.: 508183) need not re-apply.\n\nA highly competitive salary commensurate with qualifications and experience will be offered, in addition to annual leave and medical benefits.\n\nThe University only accepts online application for the above post.\u00a0 Applicants should apply online and upload an up-to-date C.V. with the name of at least two referees and a statement of research interests.\u00a0 Review of applications will start from as soon as possible and continue until\u00a0February 28, 2022, or until the post is filled, whichever is earlier.\n\nAdvertised:Dec 8, 2021 (HK Time)\nApplications close:Feb 28, 2022 (HK Time)\n\n\u6709\u610f\u7533\u8acb\u8005\u8acb \u6309 APPLY NOW\u7533\u8acb\n\n", "employment_types": ["Full Time", "Permanent"], "selling_points": ["HD in Dispensing Studies or related subjects", "Dispense drugs, counel patients, drugs management", "Shift duty is required (No night shift)"], "locations": ["Tsim Sha Tsui"], "categories": ["Medical Services", "Medical Services Technician", "Others", "Pharmaceutical"], "post_time": "2022-01-13T03:45:38Z", "salary": {"currency": null, "max": null, "min": null, "period": "monthly", "term": null}, "salary_visible": false, "title_keywords": ["dispenser"], "responsibilities": ["communication"], "requirements": {"degrees": ["degree"], "majors": [], "languages": [], "language_level": [], "hard_skills": ["mouse", "dynamic"], "soft_skills": ["organized", "work independently", "self-motivated", "collaborative", "communication", "presentation skills", "dynamic", "friendly", "patient", "novel"], "languages_combined": []}, "experience_required": {"duration": [], "field": ["research", "relevant experience"]}}, {"job_id": "100003009044329", "location_code": "hk", "company": "Quality HealthCare Medical Services Ltd", "job_title": "Dispenser II (Kowloon Bay/ Kwun Tong)", "description": "\u8077\u8cac :\n\n- \u8ca0\u8cac\u76e3\u7ba1\u5009\u5eab\u8ca8\u7269\u5b58\u5009\u3001\u51fa\u5009\u670d\u52d9\u6d41\u7a0b\n\n- \u8655\u7406\u5009\u5eab\u7684\u65e5\u5e38\u696d\u52d9\n\n- \u5354\u52a9\u5206\u914d\u5009\u5eab\u4eba\u54e1\u5de5\u4f5c\n\n- \u76e3\u7763\u5916\u5305\u88dd\u5de5\u5e8f\n\n\u8981\u6c42\u8cc7\u6b77 :\n\n- \u4e2d\u5b78/\u5c08\u4e0a\u5b78\u6b77\uff0c\u6709\u5009\u5eab\u53ca\u76e3\u7763\u5305\u88dd\u7d93\u9a57\u512a\u5148\n\n- \u826f\u597d\u7cb5\u8a9e\u512a\u5148; \u4e00\u822c\u666e\u901a\u8a71; \u4e00\u822c\u82f1\u8a9e; \u61c2\u8b80\u5beb\u4e2d\u6587\u82f1\u6587\n\n- \u5177\u6709\u57fa\u672c\u96fb\u8166\u64cd\u4f5c\u77e5\u8b58\n\n\u6709\u610f\u6c42\u8077\u8005\u53ef\u96fb\u90f5 (Apply Now) \u5c65\u6b77\u8868\u7d66\u5eb7\u548c\u91ab\u85e5\u79d1\u6280\u6709\u9650\u516c\u53f8\u3002\u5982\u8981\u7d22\u53d6\u6536\u96c6\u500b\u4eba\u8cc7\u6599\u8072\u660e\uff0c\u8acb\u8207\u674e\u5c0f\u59d0 (Email) \u806f\u7d61\u3002", "employment_types": ["Full Time", "Permanent"], "selling_points": ["HD in Dispensing Studies or related subjects", "Dispense drugs, counel patients, drugs management", "Shift duty is required (No night shift)"], "locations": ["Kowloon Bay"], "categories": ["Medical Services", "Medical Services Technician", "Others", "Pharmaceutical"], "post_time": "2022-01-13T03:45:38Z", "salary": {"currency": null, "max": null, "min": null, "period": "monthly", "term": null}, "salary_visible": false, "title_keywords": ["dispenser"], "responsibilities": [], "requirements": {"degrees": [], "majors": [], "languages": [], "language_level": [], "hard_skills": [], "soft_skills": [], "languages_combined": []}, "experience_required": {"duration": [], "field": []}}, {"job_id": "100003009044331", "location_code": "hk", "company": "Quality HealthCare Medical Services Ltd", "job_title": "Dispenser II (Relieving, with allowance)", "description": "\u8077\u4f4d\u8077\u8cac:\n\n\u8a08\u5283\u4e26\u57f7\u884c\u92b7\u552e\u7b56\u7565\uff0c\u4ee5\u78ba\u4fdd\u696d\u52d9\u589e\u9577\n\u8207\u5927\u578b\u4fdd\u5065\u53ca\u7f8e\u5bb9\u7522\u54c1\u9023\u9396\u5e97\u4fdd\u6301\u826f\u597d\u95dc\u4fc2\uff0c\u4ee5\u64f4\u5927\u5e02\u4f54\u7387\n\u6fc0\u52f5\u92b7\u552e\u5718\u968a\uff0c\u5be6\u73fe\u92b7\u552e\u76ee\u6a19\n\u7ba1\u7406\u548c\u8655\u7406\u65e5\u5e38\u92b7\u552e\u71df\u904b\n\u5206\u6790\u92b7\u552e\u696d\u7e3e\u3001\u767c\u73fe\u554f\u984c\u4e26\u5236\u5b9a\u8a08\u5283\uff0c\u4ee5\u78ba\u4fdd\u696d\u52d9\u7684\u9806\u5229\u904b\u884c\n\u7de8\u5236\u5b9a\u671f\u92b7\u552e\u5831\u544a\uff0c\u5411\u7ba1\u7406\u5c64\u532f\u5831\u53ca\u5206\u6790\n\u8077\u4f4d\u8981\u6c42:\n\n\u5927\u5c08\u6216\u4ee5\u4e0a\u7a0b\u5ea6\n3\u5e74\u6216\u4ee5\u4e0a\u7ba1\u7406FMCG/\u4fdd\u5065\u98df\u54c1/\u5927\u578b\u4fdd\u5065\u7f8e\u5bb9\u7522\u54c1\u9023\u9396\u5e97\u5de5\u4f5c\u7d93\u9a57\uff0c\u5177\u96fb\u5b50\u5546\u52d9\u5e73\u53f0\u7d93\u9a57\u512a\u5148\u8003\u616e\n\u826f\u597d\u7684\u92b7\u552e\u696d\u7e3e\u8a18\u9304\n\u512a\u826f\u7684\u4eba\u54e1\u7ba1\u7406\u53ca\u5206\u6790\u80fd\u529b\n\u826f\u597d\u7cb5\u8a9e\u3001\u82f1\u8a9e\u53ca\u666e\u901a\u8a71\n\u5373\u6642\u4e0a\u73ed\u8005\u53ef\u7372\u512a\u5148\u8003\u616e\n\u61c9\u5fb5\u8005\u8acb\u6309Apply Now\u63d0\u4ea4\u500b\u4eba\u4e2d\u6587\u5c65\u6b77\u3001\u73fe\u6642\u85aa\u91d1\u53ca\u8981\u6c42\u85aa\u91d1\u7b49\u3002", "employment_types": ["Full Time", "Permanent"], "selling_points": ["HD in Dispensing Studies or related subjects", "Dispense drugs, counel patients, drugs management", "Relieving & Shift duty required (No night shift)"], "locations": ["Not Specified"], "categories": ["Medical Services", "Medical Services Technician", "Others", "Pharmaceutical"], "post_time": "2022-01-13T03:45:38Z", "salary": {"currency": null, "max": null, "min": null, "period": "monthly", "term": null}, "salary_visible": false, "title_keywords": ["dispenser"], "responsibilities": [], "requirements": {"degrees": [], "majors": [], "languages": [], "language_level": [], "hard_skills": [], "soft_skills": [], "languages_combined": []}, "experience_required": {"duration": [], "field": []}}, {"job_id": "100003009040312", "location_code": "hk", "company": "Galderma Hong Kong Limited", "job_title": "Sales Manager (Medical Device / Aesthetics)", "description": "Key Roles and Responsibilities:\n\nTo support in developing, implementing and maintaining the documentation and quality assurance system of the company;\nTo ensure the adequate records are maintained for controlling and monitoring conformity to specified GMP and statutory requirements;\nTo support the routine QA Department functions, including self-inspection, regulatory affairs, products complaints/returns/recalls, etc.\nTo assist ad-hoc projects and administrative tasks assigned by the Manager;\nKnowledge in Quality Management System (e.g change control, risk assessment and CAPA) is an advantage.\n\nQualifications and Experience:\n\nBachelor Degree or above in Pharmacy or related discipline;\nWork independently with good analytical skills and attention to detail;\nStrong communication skill, good command of English and Chinese;\nFresh graduates may also be considered.\n\nWe offer to the right candidates with competitive remuneration package including 12-16 day annual leave, marriage leave, maternity leave, paternity leave, compassionate leave, Public Holidays, medical and dental insurance, educational sponsorship, overtime allowance, performance bonus, MPF and other fringe benefits.\n\nHow to Apply\n\nYou are invited to send in your application and CV stating the position you are applying for together with your current and expected salary by clicking the \"apply button\".\n\n\u00a0\nVickmans LaboratoriesLimited is an Equal Opportunities Employer. Personal data provided by job applicants will be used strictly in accordance with our personal data policy and for recruitment purposes only. We aim to respond to successful applicants within 8 weeks and related information will be kept in our file for up to 12 months for other suitable vacancies in our organization and thereafter destroyed", "employment_types": ["Full Time", "Permanent"], "selling_points": ["Leading international dermatology company", "Sales Manager of Team of 4", "Experienced with Aesthetic Industry"], "locations": ["Quarry Bay"], "categories": ["Beauty Care / Health", "Others", "Marketing / Public Relations", "Management", "Medical Services", "Pharmaceutical"], "post_time": "2022-01-12T02:15:57Z", "salary": {"currency": null, "max": null, "min": null, "period": "monthly", "term": null}, "salary_visible": false, "title_keywords": ["sales manager"], "responsibilities": ["management", "control", "mpf", "maintaining", "monitoring", "quality", "developing", "inspection", "communication", "statutory requirements", "recruitment", "insurance", "personal data", "documentation", "ad-hoc projects", "administrative tasks"], "requirements": {"degrees": ["degree or above", "bachelor"], "majors": [], "languages": ["english", "chinese"], "language_level": ["good command"], "hard_skills": ["documentation", "analytical skills"], "soft_skills": ["work independently", "communication skill", "attention to detail", "analytical skills"], "languages_combined": [{"language": "english", "language_level": ["good command"]}, {"language": "chinese", "language_level": ["good command"]}]}, "experience_required": {"duration": [], "field": []}}, {"job_id": "100003009045098", "location_code": "hk", "company": "The University of Hong Kong", "job_title": "Post-doctoral (509134)", "description": "\u8077\u8cac\u6982\u89bd:\n\n\u5728\u91ab\u7642\u4e2d\u5fc3\u63d0\u4f9b\u826f\u597d\u5ba2\u6236\u670d\u52d9\u4ee5\u7b26\u5408\u516c\u53f8\u7684\u670d\u52d9\u6a19\u6e96\n\u8ca0\u8cac\u8a3a\u6240\u4e00\u5207\u65e5\u5e38\u904b\u4f5c\uff0c\u5305\u62ec\u8655\u7406\u75c5\u4eba\u8a62\u554f\u4e26\u5b89\u6392\u9810\u7d04\u3001\u63a5\u5f85\u8207\u5354\u52a9\u91ab\u751f\u61c9\u8a3a\u3001\u75c5\u4eba\u7684\u96e2\u958b\u624b\u7e8c\u53ca\u7dad\u6301\u7cfb\u7d71\u7d00\u9304\u7b49\u7b49\n\u8ca0\u8cac\u6aa2\u67e5\u548c\u6574\u7406\u91ab\u7642\u7528\u54c1\u5b58\u8ca8\uff0c\u6309\u6642\u8a02\u8cfc\u91ab\u7642\u7528\u54c1\n\u5354\u52a9\u8a3a\u6240\u884c\u653f\uff0c\u4e00\u822c\u4e2d\u82f1\u6587\u6587\u66f8\u5de5\u4f5c\n\u8655\u7406\u91ab\u751f\u6216\u8a3a\u6240\u7d93\u7406\u6240\u5206\u914d\u7684\u5176\u4ed6\u81e8\u6642\u5de5\u4f5c\n\n\u8981\u6c42\uff1a\n\n\u5df2\u64c1\u6709\u62bd\u8840\u548c\u6ce8\u5c04\u7684\u8a8d\u53ef\u724c\u7167\u00a0(\u6216\u5176\u4e2d\u4e00\u9805\u4e5f\u8003\u616e)\n\u64c1\u6709\u9ad4\u6aa2\u4e2d\u5fc3\u6216\u91ab\u7642\u5e02\u5834\u7b56\u5283\u5de5\u4f5c\u7d93\u9a57\u8005\u512a\u5148\n\u6301\u6709\u9999\u6e2f\u4e2d\u5b78\u6587\u6191/\u9999\u6e2f\u4e2d\u5b78\u6703\u8003\u6216\u4ee5\u4e0a\u5b78\u6b77\n\u5177\u5099\u826f\u597d\u5ba2\u6236\u670d\u52d9\u548c\u4eba\u969b\u95dc\u4fc2\u6280\u5de7\n\u61c2\u5f97\u4f7f\u7528MS office\uff0c\u7565\u61c2\u5e73\u9762\u8a2d\u8a08\u512a\u5148\u8003\u616e\n\u80fd\u5920\u807d\u8aaa\u6d41\u5229\u7684\u7cb5\u8a9e\u548c\u666e\u901a\u8a71\n\u6b61\u8fce\u6709\u5167\u5730\u80cc\u666f\u4eba\u58eb\u7533\u8acb", "employment_types": ["Full Time"], "selling_points": [], "locations": ["Pok Fu Lam"], "categories": ["Sciences, Lab, R&D", "Chemical", "Medical Services", "Medical Services Technician", "Pharmaceutical"], "post_time": "2022-01-13T07:09:25Z", "salary": {"currency": null, "max": null, "min": null, "period": "monthly", "term": null}, "salary_visible": false, "title_keywords": [], "responsibilities": [], "requirements": {"degrees": [], "majors": [], "languages": [], "language_level": [], "hard_skills": [], "soft_skills": [], "languages_combined": []}, "experience_required": {"duration": [], "field": []}}, {"job_id": "100003009048176", "location_code": "hk", "company": "Hong Wo Pharmaceutical Company Limited", "job_title": "\u5009\u52d9\u53ca\u5916\u5305\u88dd\u4e3b\u4efb", "description": "Responsibilities:\n\n\nHandle license application and renewal including certificate for manufacturer, wholesaler of Chinese herbal medicines, wholesaler of proprietary Chinese medicines, food factory\nHandle applications for license to import, introduce from the sea, export, re-export endangered species, import and export of Chinese medicines\nSupport application and renewal of HACCP certification\nAssist in audit and surprise check by government department\nManage the document control system, such as generating, filing and archiving of controlled documents for GMP/TGA/Food GMP/HACCP system\nEnsure the QA system and procedures are operated throughout quality system operations\nAssist in maintaining the training program\nUndertake routine quality assurance monitoring program\nAssist in handling and following up on quality incidents\nAssist in carrying out internal audits\nAssist in maintaining inspection readiness for external audits\n\nRequirements:\n\nHigher Diploma or above in science related subjects, e.g. Chinese Medicine, Food Science, Chemistry, Biochemistry, Chemical Engineering, Microbiology, Pharmacy, Pharmaceutical Science or related disciplines\nMinimum 3 year solid experience in food or pharmaceutical area\nProactive, attention to details, hard-working\nGood interpersonal and communication skills\nProficiency in computer application such as MS Office and Chinese word processing\nFamiliar with HACCP/Food GMP would be an advantage\nGood command in written and spoken English and Chinese, knowledge of Putonghua is an advantage\nProficiency in using Microsoft applications including Excel, PowerPoint and English & Chinese Word Processing\nApplicant with more experience will be considered as Senior QA Officer\n\nInterested parties please send full resume with present and expected salary to Human Resources Department by clicking \"APPLY NOW\".\n\n(Information provided will be treated in strict confidence and will only be used for recruitment-related purposes.)", "employment_types": ["Full Time"], "selling_points": ["\u5009\u52d9\u4e3b\u4efb", "\u76e3\u7763\u5916\u5305\u88dd\u5de5\u5e8f", "\u5009\u5eab\u7269\u6d41"], "locations": ["Sheung Wan"], "categories": ["Transportation & Logistics", "Fulfillment", "Inventory / Warehousing", "Medical Services", "Pharmaceutical"], "post_time": "2022-01-14T05:41:32Z", "salary": {"currency": null, "max": null, "min": null, "period": "monthly", "term": null}, "salary_visible": false, "title_keywords": [], "responsibilities": ["control", "maintaining", "operations", "monitoring", "quality", "procedures", "audit", "inspection", "license application", "audits"], "requirements": {"degrees": ["higher diploma or above"], "majors": ["science"], "languages": ["putonghua", "english", "chinese"], "language_level": ["advantage", "proficiency", "good command"], "hard_skills": ["excel", "chinese word processing", "microsoft applications", "powerpoint", "ms office"], "soft_skills": ["communication skills", "hard-working", "attention to details", "proactive", "interpersonal"], "languages_combined": [{"language": "putonghua", "language_level": ["good command"]}, {"language": "english", "language_level": ["advantage", "proficiency", "good command"]}, {"language": "chinese", "language_level": ["advantage", "proficiency", "proficiency", "good command"]}]}, "experience_required": {"duration": ["minimum 3 year"], "field": ["pharmaceutical", "food", "qa"]}}, {"job_id": "100003009044328", "location_code": "hk", "company": "Quality HealthCare Medical Services Ltd", "job_title": "Dispenser II (Admiralty)", "description": "Our client is a global leading medical device company with fast growth in business track record, they are looking for a high calibre candidate to join the team:\n\nResponsibilities:\n\nProduct promote to HA, private hospital and laboratories.\nMaximum sales opportunity and meet the sales target\nBuild up good relationship with HCPs.\nImplement sales promotion activities.\n\nRequirements:\n\nDegree in Science or related discipline\nOver 2 years' experience in Medical sales field\nStrong communication and analytical skill\nImmediate available preferred\n\nAPPLY FOR THIS JOB\n\nInterested candidate please CLICK apply button to apply online or send your resume in MS word format to Hillman Ross Recruitment Solution Professional\n\nPlease note that only shortlisted candidate will be notified. All information will be treated in strict confidence and solely used for recruitment purposes.", "employment_types": ["Full Time", "Permanent"], "selling_points": ["HD in Dispensing Studies or related subjects", "Dispense drugs, counel patients, drugs management", "Shift duty is required (No night shift)"], "locations": ["Admiralty"], "categories": ["Medical Services", "Medical Services Technician", "Others", "Pharmaceutical"], "post_time": "2022-01-13T03:45:37Z", "salary": {"currency": null, "max": null, "min": null, "period": "monthly", "term": null}, "salary_visible": false, "title_keywords": ["dispenser"], "responsibilities": ["good relationship", "sales target"], "requirements": {"degrees": ["degree"], "majors": ["science"], "languages": [], "language_level": [], "hard_skills": ["analytical skill", "ms word"], "soft_skills": ["communication", "analytical skill", "confidence"], "languages_combined": []}, "experience_required": {"duration": ["2 years"], "field": ["medical"]}}, {"job_id": "100003009044265", "location_code": "hk", "company": "Concord Alliance Limited", "job_title": "Nutritionist", "description": "Applications are invited for appointment as\u00a0Post-doctoral Fellow in the Department of Pharmacology and Pharmacy\u00a0(Ref.: 509172), to commence as soon as possible for two to three years.\n\nApplicants should possess a Ph.D. degree or equivalent, with relevant experience in big data analysis, pharmacoepidemiology, epidemiology, statistics, data science, or a related field.\u00a0 They should be self-motivated, organized, creative, energetic, and able to work independently and in a team. Experience in analysing large and complex datasets is required.\u00a0 The appointee will join a research team led by Dr. Carlos K.H. Wong to conduct high-impact research related to big data analytics and pharmacoepidemiology using electronic health records and population-based cohort databases.\u00a0 Enquiries about the duties of the post should be sent to Dr. Wong at [via APPLY NOW] \u00a0 Those who have responded to the previous advertisement (Ref.: 503942) need not re-apply.\n\nA competitive salary commensurate with qualifications and experience will be offered, in addition to annual leave and medical benefits.\n\nThe University only accept online application for the post.\u00a0 Applicants should apply online and upload an up-to-date C.V.\u00a0 Review of applications will start as soon as possible and continue until\u00a0March 31, 2022, or until the post is filled, whichever is earlier.\n\nAdvertised:Dec 3, 2021 (HK Time)\nApplications close:Mar 31, 2022 (HK Time)\n\n\u6709\u610f\u7533\u8acb\u8005\u8acb \u6309 APPLY NOW\u7533\u8acb\n\n", "employment_types": ["Full Time", "Permanent"], "selling_points": ["Degree in Nutrition and / or Food science", "At least 3 years exp. in Health Care Industry", "Double Pay"], "locations": ["Tsim Sha Tsui"], "categories": ["Sciences, Lab, R&D", "Food Science", "Beauty Care / Health", "Nutritionist", "Medical Services", "Pharmaceutical"], "post_time": "2022-01-13T03:35:43Z", "salary": {"currency": null, "max": null, "min": null, "period": "monthly", "term": null}, "salary_visible": false, "title_keywords": ["nutritionist"], "responsibilities": ["analysis", "big data", "databases", "data"], "requirements": {"degrees": ["degree"], "majors": ["data science", "epidemiology", "statistics"], "languages": [], "language_level": [], "hard_skills": ["data analytics", "analysis", "databases"], "soft_skills": ["organized", "self-motivated", "work independently", "creative", "energetic"], "languages_combined": []}, "experience_required": {"duration": [], "field": ["data analysis", "statistics", "relevant experience", "related"]}}, {"job_id": "100003009047439", "location_code": "hk", "company": "Wright Life Pharmaceutical Limited", "job_title": "Sales Officer \u92b7\u552e\u4e3b\u4efb", "description": "Key Roles and Responsibilities\u00a0\n\nPerform routine lines inspection and in-process control at various stages of pharmaceutical manufacturing processes;\nAssist in implementing and maintaining the documentation system and quality management system; &\nOther ad hoc projects as assigned.\n\nQualifications and Experience \u00a0\u00a0\u00a0\n\nEducation: \u00a0Diploma level or above in Sciences studies;\nFresh graduates are also welcome for applying this position;\nCandidate with more relevant experience will be considered as Assistant Quality Assurance Officer;\nProficient in MS Office application (Excel, Word & PowerPoint) and Chinese Word Processing;\nFamiliar with GMP environment is an advantage;\n\nImmediate available is highly preferable; &\n\nAble and willing to work on Saturday or Sunday (5 days work per week).\n\nHow to Apply\n\nYou are invited to send in your application and CV stating the position you are applying for together with your current and expected salary, either by\u00a0Clicking\u00a0\"Apply Now\".\u00a0\u00a0\n\n\nEuropharm Laboratoires Company Limited\u00a0is an equal opportunities employer. The information provided will be treated in strict confidence and used only for consideration of application for relevant/similar post(s).\u00a0 All personal data of unsuccessful applicants will be destroyed within 6 months.", "employment_types": ["Full Time"], "selling_points": ["5\u5929\u5de5\u4f5c+\u9280\u884c\u5047\u671f+\u96d9\u7ce7", "\u5177\u4fdd\u5065\u98df\u54c1\u92b7\u552e\u7ba1\u7406\u7d93\u9a57", "\u826f\u597d\u92b7\u552e\u696d\u7e3e\u8a18\u9304"], "locations": ["Tsuen Wan Area"], "categories": ["Sales, CS & Business Devpt", "Business Development", "Medical Services", "Pharmaceutical", "Sales - Sales Management"], "post_time": "2022-01-14T10:07:20Z", "salary": {"currency": null, "max": null, "min": null, "period": "monthly", "term": null}, "salary_visible": false, "title_keywords": ["sales officer"], "responsibilities": ["control", "management", "maintaining", "quality", "inspection", "ad hoc projects", "documentation", "personal data"], "requirements": {"degrees": ["diploma"], "majors": [], "languages": ["chinese"], "language_level": ["proficient"], "hard_skills": ["excel", "chinese word processing", "word", "powerpoint", "documentation", "ms office"], "soft_skills": ["confidence"], "languages_combined": [{"language": "chinese", "language_level": ["proficient"]}]}, "experience_required": {"duration": [], "field": ["relevant experience", "quality assurance"]}}, {"job_id": "100003009040111", "location_code": "hk", "company": "Vickmans Laboratories Limited", "job_title": "Quality Assurance Officer", "description": "In this role, you will be leading Aesthetic BU by implementing and executing the company's integrated dermatology strategy to deliver the growth of the business.\n\nJob Responsibilities:\n\nLead the Aesthetics Business Unit commercial operation to ensure the Company achieves its mission and objectives for the business\nResponsible for the budget and P&L delivery for the Aesthetics Business Unit.\nDevelop and successfully execute end-to-end successful marketing, channel, commercial and sales plans in accordance with corporate/ company strategy\nDevelop HCP training, communication and promotional campaigns\nDevelop and successfully execute end-to-end marketing, channel, commercial and sales plans including ATL/BTL brand building, product detailing and HCP/customer engagement.\nProduces and analyzes local market data, identifies, and tracks industry market trends\nWork with internal stakeholders to ensure smooth daily business operation.\nManages the relationships with the local advertising and communication agencies\nManages relationships with opinion leaders and dermatologist's community to support the company's brand & product.\nBuild strong collaboration with Regulatory Affairs, Pharmacovigilance, Medical Affair and Compliance team.\nAdhere to all company policies, procedures and business ethics codes and ensure that they are communicated and implemented with the team\nIdentifies and analyzes local customer needs and market opportunities\nProvide market intelligence and able to create and execute strategic plans to win over competition\nCreate a positive team environment through the demonstration of strong leadership behaviors, including communicating expectations clearly, installing an atmosphere of trust and respect, and leading by example.\nUse a mix of coaching and development tools to help each team member to realize their full potential\nProvide significant input and support to accomplish management team goals which will benefit Galderma Hong Kong in the long term.\n\nJob Requirements:\n\nUniversity Graduate with proven track record of 10+ years of experience ideally in the Aesthetic or Pharmaceutical industry.\nProficient English and Cantonese writing and conversation\nAbility to effectively present information to management, public, doctors or sales forces in oral and written form.\nAbility to read, analyze and interpret common scientific and technical information\nAbility to interpret an extensive variety of technical instructions in mathematical or diagram form and deal with several abstract and concrete variables.\nIdeally, the candidate should be in a managerial position in an Aesthetic /pharmaceutical company with strong connections and know-how within the industry.", "employment_types": ["Full Time", "Permanent"], "selling_points": [], "locations": ["Ngau Tau Kok"], "categories": ["Manufacturing", "Production Planning / Control", "Medical Services", "Pharmaceutical", "Quality Assurance, Control & Testing / ISO"], "post_time": "2022-01-12T01:27:55Z", "salary": {"currency": null, "max": null, "min": null, "period": null, "term": null}, "salary_visible": false, "title_keywords": ["quality assurance officer"], "responsibilities": ["business operation", "management team", "advertising", "strategic plans", "policies", "budget", "compliance", "procedures", "p&l", "develop", "communication", "installing", "sales plans", "market data"], "requirements": {"degrees": ["university graduate"], "majors": [], "languages": ["cantonese", "english"], "language_level": ["proficient"], "hard_skills": [], "soft_skills": ["oral", "extensive"], "languages_combined": [{"language": "cantonese", "language_level": ["proficient"]}, {"language": "english", "language_level": ["proficient"]}]}, "experience_required": {"duration": ["of 10+ years"], "field": ["pharmaceutical", "aesthetic"]}}, {"job_id": "100003009049005", "location_code": "hk", "company": "Hillman Ross", "job_title": "Sales Specialist (Medical device)", "description": "Responsibilities:\n\n\nPlan, organize and lead the production department to achieve the company\u2019s business objectives\n\u00a0Act as a key person of a PIC/S standard pharmaceutical company\n\u00a0Ensure compliance to the regulatory requirements of all products manufactured\n\u00a0Monitor the equipment, cleanroom, and warehouse according to the approved PIC/S GMP procedures\nInvolve in the design of various manufacturing process flows and monitoring of Process Validation & Cleaning Validation processes;\nManage GMP documents e.g. batch production records, manufacturing instructions, SOPs, etc.\nWork closely with QA, QC, and R&D departments to achieve the company\u2019s goals on productivity and quality\nStem cell product manufacturing and packaging\nOther duties as assigned by Authorized Person and/or management team.\n\nRequirements:\n\n\nBachelor or above biotechnology, biochemistry, chemistry and medical laboratory science or science degree with relevant to cell therapy, gene therapy, regenerative medicines or tissue engineering, or other similar sciences disciplines;\nAt least 4 years significant experience of managing a production/manufacturing team in a PIC/S GMP compliant organization\nGood organization, communication, management, and training skills.\nBe accountable and able to solve practical problems in manufacturing;\nIndependent, enthusiastic, and a good team player\nProficiency in English and Chinese.\n\nWe offer an attractive remuneration package including group medical insurance, discretionary year-end performance bonus, and an energetic, fun work environment.\n\nInterested parties please send your resume with current, expected salary and availability to the HR Department.\n\n(All personal data provided will be treated in strict confidence and be used for recruitment purposes.)\n", "employment_types": ["Full Time", "Permanent"], "selling_points": ["Global medical device manufacturer", "Dynamic team", "Good career development"], "locations": ["Not Specified"], "categories": ["Medical Services", "Specialist", "Pharmaceutical", "Sales, CS & Business Devpt", "Direct Sales"], "post_time": "2022-01-14T07:54:07Z", "salary": {"currency": null, "max": null, "min": null, "period": "monthly", "term": null}, "salary_visible": false, "title_keywords": ["sales specialist"], "responsibilities": ["management team", "other duties", "regulatory requirements", "monitoring", "monitor", "procedures", "design", "ensure compliance", "quality", "plan", "cleaning", "sops"], "requirements": {"degrees": ["degree", "bachelor"], "majors": ["science", "chemistry", "engineering", "medical laboratory science"], "languages": ["english", "chinese"], "language_level": ["proficiency"], "hard_skills": ["fun"], "soft_skills": ["good team player", "independent", "accountable", "communication", "enthusiastic", "energetic"], "languages_combined": [{"language": "english", "language_level": ["proficiency"]}, {"language": "chinese", "language_level": ["proficiency"]}]}, "experience_required": {"duration": ["at least 4 years"], "field": ["manufacturing", "team"]}}, {"job_id": "100003009046781", "location_code": "hk", "company": "Europharm Laboratoires Company Limited", "job_title": "Quality Assurance Assistant / Assistant Quality Assurance Officer", "description": "about the company.\n\nOur client is a well-established medical device distributor and stable working environment. They are now looking for a young and energetic sales candidate for their big family in Hong Kong. If you are looking for an opportunity to enter the medical device industry or excellent working environment, please apply!\n\nabout the team.\n\nThere are around 30 people in the office. You would be working in the medical device team and working closely with 3 sales colleagues.\n\nabout the job.\n\nAs a Medical Device Sales, you are responsible for\n\ndevelop and executes business plans for the assigned territory\nmaintain existing clients and create new potential clients\nresponsible for selling assigned medical device products and delivery academic knowledges to professionals\nprepare sales report and action plans to Sales manager\nprovide solutions to customers' enquiries\nother ad-hoc duties assigned by Sales manager\n\nskills & experiences required.\n\nbachelor Degree of Science, Business, Marketing or any related discipline\nwith 1-4 years of experience in medical device industry would be highly preferred\nexcellent communication and interpersonal skills\nproficiency in PC applications such as MS Word, Excel and PowerPoint\nfresh graduates in 2021 are also welcome!\n\nInterested parties, please apply directly with your current and expected salary.", "employment_types": ["Full Time", "Permanent"], "selling_points": [], "locations": ["Tai Po Area"], "categories": ["Sciences, Lab, R&D", "Chemical", "Medical Services", "Pharmaceutical", "Manufacturing", "Quality Assurance, Control & Testing / ISO"], "post_time": "2022-01-14T01:03:57Z", "salary": {"currency": null, "max": null, "min": null, "period": "monthly", "term": null}, "salary_visible": false, "title_keywords": ["assistant quality assurance officer", "quality assurance assistant"], "responsibilities": ["prepare sales", "business plans", "develop", "provide solutions", "communication", "maintain", "ad-hoc duties", "plans", "report"], "requirements": {"degrees": ["degree", "bachelor"], "majors": ["science", "business", "marketing"], "languages": [], "language_level": [], "hard_skills": ["ms word", "excel", "powerpoint", "pc applications"], "soft_skills": ["responsible", "communication and interpersonal skills", "ad-hoc duties", "stable", "energetic"], "languages_combined": []}, "experience_required": {"duration": ["1-4 years"], "field": ["medical device"]}}, {"job_id": "100003009044734", "location_code": "hk", "company": "Randstad Hong Kong Limited", "job_title": "Medical Device Sales (Fresh Graduate Welcome)", "description": "Primary responsibilities:\n\nDevelop novel pharmaceutical formulations.\nEstablish and validate analytical infrastructure for drug development (e.g. assay, related substances, dissolution etc.).\nManage relevant research programs related to CMC, non-clinical studies and GMP manufacture.\nPossess a basic understanding of regulatory requirements appropriate for pharmaceutical development.\nHandle ad-hoc tasks as assigned.\n\n\u00a0Education Requirement:\n\nMaster or Doctoral degree holder in Chemistry (analytical/organic), Biochemistry, Pharmaceutical Sciences or related disciplines.\n\nDescription:\n\nHands-on experience in key analytical instruments, such as U/HPLC & LC/MS is preferred.\nExperience in drug formulation development and PK/PD studies would definitely be an advantage.\nFluent in written and spoken English and Mandarin, with excellent presentation skills.\nStrong desire to develop a career in Biotechnology/ Pharmaceutical Industry\nStrong leadership skills and a demonstrated team player with a dynamic and hardworking approach to their work.\nStrong ethics, integrity, and credibility.\nWillingness to travel.\n\n\n\nWe offer competitive remuneration package and excellent career prospects to qualified candidates.\n\n\n\nInterested parties please send your resume together with present and expected salaries with contact details to the Human Resources Manager by clicking apply now.\n\nPersonal data provided will be used for recruitment and related purposes only and strictly in accordance with the relevant Personal Data Policy for Employment. \u00a0Applicants who are not contacted within 6 weeks may consider their application unsuccessful and the personal data collected will be destroyed in due course.", "employment_types": ["Full Time", "Permanent"], "selling_points": ["Local Medical device Distributor", "Fresh Graduate Welcome", "Exposure in both clinical support and consumables"], "locations": ["Not Specified"], "categories": ["Sales, CS & Business Devpt", "Business Development", "Medical Services", "Pharmaceutical", "Direct Sales"], "post_time": "2022-01-13T05:57:50Z", "salary": {"currency": "HKD", "max": 24999, "min": 20000, "period": "monthly", "term": null}, "salary_visible": true, "title_keywords": ["sales"], "responsibilities": ["regulatory requirements", "ad-hoc tasks", "infrastructure", "develop"], "requirements": {"degrees": ["degree holder", "master"], "majors": ["related disciplines", "chemistry"], "languages": ["english", "mandarin"], "language_level": ["excellent", "fluent"], "hard_skills": ["dynamic"], "soft_skills": ["leadership skills", "integrity", "hands-on", "presentation skills", "dynamic", "team player", "hardworking"], "languages_combined": [{"language": "english", "language_level": ["excellent", "fluent"]}, {"language": "mandarin", "language_level": ["excellent", "fluent"]}]}, "experience_required": {"duration": [], "field": ["development", "analytical"]}}, {"job_id": "100003009037812", "location_code": "hk", "company": "Hong Kong Regen Medtech Limited", "job_title": "Quality Control Manager", "description": "\u8077\u8cac:\n\n\n\n\u6839\u64da\u92b7\u552e\u8a08\u5283\uff0c\u914d\u5408\u696d\u52d9\u7d93\u7406\u5b8c\u6210\u92b7\u552e\u6307\u6a19\uff0c\u5305\u62ec\u63a5\u6536\u8a02\u55ae\u3001\u5408\u540c\u88fd\u4f5c\u3001\u5354\u8abf\u767c\u8ca8\u3001\u50ac\u6536\u8cec\u6b3e\u7b49;\n\u92b7\u552e\u5408\u540c\u7ba1\u7406\uff0c\u7d93\u92b7\u5546\u6a94\u6848\u7ba1\u7406;\n\u5c0d\u63a5\u806f\u7e6b\u7d93\u92b7\u5546\uff0c\u7dad\u8b77\u8207\u7d93\u92b7\u5546\u7684\u95dc\u4fc2;\n\u5b9a\u671f\u5c0d\u5e02\u5834\u50f9\u683c\u9032\u884c\u8abf\u7814\uff0c\u76e3\u63a7\u7522\u54c1\u5e02\u5834\u50f9\u683c;\n\n\u8981\u6c42:\n\n\n\n\u5927\u5b78\u5b78\u58eb\u5b78\u6b77\uff0c\u5177\u50991\u81f33\u5e74\u76f8\u95dc\u5de5\u4f5c\u7d93\u9a57;\n\u5177\u6709\u4e2d\u91ab\u85e5\u76f8\u95dc\u5c08\u696d\u77e5\u8b58\u8005\uff0c\u512a\u5148\u9304\u7528;\n\u7cbe\u901a\u4f7f\u7528\u6d41\u5229\u4e2d\u3001\u82f1\u6587\u53e3\u982d\u53ca\u66f8\u9762\u8868\u9054\u80fd\u529b;\n\u719f\u7df4\u5730\u4f7f\u7528\u76f8\u95dc\u7684\u8fa6\u516c\u8edf\u9ad4;\n\u826f\u597d\u7684\u5167\u5916\u5354\u8abf\u53ca\u6e9d\u901a\u80fd\u529b\u3002", "employment_types": ["Full Time"], "selling_points": [], "locations": ["Shatin Area"], "categories": ["Sciences, Lab, R&D", "Laboratory", "Medical Services", "Pharmaceutical", "Manufacturing", "Quality Assurance, Control & Testing / ISO"], "post_time": "2022-01-11T03:56:06Z", "salary": {"currency": null, "max": null, "min": null, "period": "monthly", "term": null}, "salary_visible": false, "title_keywords": ["manager"], "responsibilities": [], "requirements": {"degrees": [], "majors": [], "languages": [], "language_level": [], "hard_skills": [], "soft_skills": [], "languages_combined": []}, "experience_required": {"duration": [], "field": []}}, {"job_id": "100003009048235", "location_code": "hk", "company": "Beijing Tong Ren Tang Chinese Medicine Company Limited", "job_title": "\u696d\u52d9\u5c08\u54e1 Business Assistant", "description": "Degree holder or above\nAt least 3 years of experience in administrative work\nProficient in English & Chinese\nResult of English: IELTS 7.0 or above\nComputer literacy with advanced knowledge of MS Office applications\nSelf-motivated, well-organized and multi-tasking\nInterested candidates please download the Job Application Form on www.union.org (quote the \"Ref No.\") and send to: HR Department, Union Hospital, 18 Fu Kin Street, Tai Wai, Shatin, N.T. or by fax at 2697 5028 or by e-mail via \"Apply Now\"\nDue to the implementation of the Sexual Conviction Record Check (SCRC) Scheme, the Hospital may request the prospective employees of relevant positions to undergo SCRC.\n(Applicants not hearing from us within 2 months may consider their applications unsuccessful. Applicants who have applied for the same position within half year need not re-apply.)\n*Data collected will be used for recruitment purpose only", "employment_types": ["Full Time", "Permanent"], "selling_points": [], "locations": ["Wan Chai"], "categories": ["Sales, CS & Business Devpt", "Business Development", "Medical Services", "Pharmaceutical", "Account Servicing"], "post_time": "2022-01-14T06:13:32Z", "salary": {"currency": null, "max": null, "min": null, "period": "monthly", "term": null}, "salary_visible": false, "title_keywords": ["assistant"], "responsibilities": ["administrative work"], "requirements": {"degrees": ["degree holder"], "majors": [], "languages": ["english", "chinese"], "language_level": ["proficient"], "hard_skills": ["ms office"], "soft_skills": ["self-motivated", "advanced", "well-organized", "computer literacy", "multi-tasking"], "languages_combined": [{"language": "english", "language_level": ["proficient"]}, {"language": "chinese", "language_level": ["proficient"]}]}, "experience_required": {"duration": ["at least 3 years"], "field": ["administrative"]}}, {"job_id": "100003009045051", "location_code": "hk", "company": "Union Hospital", "job_title": "Executive Assistant (Pharmacy) (Ref: JDB/130122/PHA_EA)", "description": "Job Responsibilities\nPrepare and dispense drugs accurately\u00a0and efficiently according to the prescriptions\nConduct patients\u00a0counseling\u00a0by explaining dosage, precautions and side effects of the medicine to the patients\nManage the pharmacy of medical center by keeping the\u00a0stock\u00a0of drugs\u00a0at an optimum level, maintaining a\u00a0safe and secure storage of drugs\nHandle\u00a0various kind of drugs\u00a0properly and according to regulatory requirements\nAssist in\u00a0handling payment transactions\nAnswer patient's inquiry on drugs related and contract-related inquiries\nWork with medical professionals\u00a0from multi-disciplines\u00a0to deliver the best customer services\nJob Requirements\nHigher Diploma in Dispensing Studies\u00a0/\u00a0Pharmaceutical Technology equivalent, or BSc in Pharmacy\nCompleted Dispenser related course\nGood command of spoken English and Chinese (Mandarin will be advantageous)\nProactive, customer-oriented and a good team player\nShift duty is required (No night shift)\nFresh graduate and oversea Pharmacist are welcome to join us\n\nWe offer\u00a0competitive pay\u00a0and fringe benefits. Interested parties please send your full resume with\u00a0current salary and expected salary\u00a0 to\u00a0Human Resources Department, Quality HealthCare Medical Services Limited, 3/F, Skyline Tower, 39 Wang Kwong Road, Kowloon Bay, Kowloon\u00a0or by clicking 'Apply Now\".\n\n(All applications will be treated in strict confidence and data collected will be used for recruitment) purposes only)", "employment_types": ["Full Time", "Permanent"], "selling_points": ["Degree holder or above", "At least 3 years of experience", "Result of English: IELTS 7.0 or above"], "locations": ["Not Specified"], "categories": ["Admin & HR", "Clerical / Admin Staff", "Personal / Executive Assistant", "Medical Services", "Pharmaceutical"], "post_time": "2022-01-13T07:47:29Z", "salary": {"currency": null, "max": null, "min": null, "period": "monthly", "term": null}, "salary_visible": false, "title_keywords": ["executive assistant"], "responsibilities": ["regulatory requirements", "payment transactions", "maintaining", "customer services"], "requirements": {"degrees": ["fresh graduate", "diploma", "bsc"], "majors": [], "languages": ["english", "chinese", "mandarin"], "language_level": ["good command"], "hard_skills": ["no"], "soft_skills": ["good team player", "customer-oriented", "proactive"], "languages_combined": [{"language": "english", "language_level": ["good command"]}, {"language": "chinese", "language_level": ["good command"]}, {"language": "mandarin", "language_level": ["good command"]}]}, "experience_required": {"duration": [], "field": []}}, {"job_id": "100003009038807", "location_code": "hk", "company": "Karen Pharmaceutical Company Limited", "job_title": "QA Officer", "description": "Key Roles and Responsibilities\u00a0\n\nAssist\u00a0Q.A. Manager\u00a0in developing the quality management systems and processes in line with Hong Kong GMP and PIC/S standard\nHandle routine quality management work including preparation of SOP, follow up of deviation, risk assessment and change control\nEnsure all\u00a0regular quality reviews\u00a0are carried out in accordance\u00a0to schedule, e.g. product quality review, mock recall, self-inspection\nSupport\u00a0Q.A. Manager\u00a0during statutory inspection/ principal audit by facilitating the preparation for such audits\nTo Assist ad-hoc Q.A. projects and other tasks as assigned by the Q.A. Manager\n\nQualifications and Experience\n\nHigher Diploma or above\u00a0in science related\u00a0disciplines\u00a0e.g.\u00a0quality management, pharmaceutical, chemical engineer, chemistry,\u00a0bio-medical science, food science\u00a0and validations\n1-2 years working experience in\u00a0Quality Assurance of pharmaceutical or food industry\nKnowledge of GMP is essential, QMS and validation activities will be an\u00a0advantage\nProactive, willing to learn and able to work independently\nGood command of written and spoken in English and Chinese\nFresh graduates are also considered\n\nHow to Apply\n\nYou are invited to send in your application and CV stating the position\u00a0(with reference number)\u00a0you are applying for together with your current and expected salary, apply via JobsDB\u00a0on or before 9 February 2022.\n\nKaren Pharmaceutical Company Limited is an Equal Opportunities Employer. Personal data provided by job applicants will be used strictly in accordance with our personal data policy and for recruitment purposes only. We aim to respond to successful applicants within 8 weeks and related information will be kept in our file for up to 12 months for other suitable vacancies in our organization and thereafter destroyed.", "employment_types": ["Full Time"], "selling_points": [], "locations": ["Tuen Mun Area"], "categories": ["Medical Services", "Pharmaceutical", "Manufacturing", "Quality Assurance, Control & Testing / ISO", "Sciences, Lab, R&D", "Others"], "post_time": "2022-01-11T07:51:13Z", "salary": {"currency": null, "max": null, "min": null, "period": null, "term": null}, "salary_visible": false, "title_keywords": ["officer"], "responsibilities": ["ad-hoc", "management", "control", "systems", "quality", "developing", "review", "inspection", "audit", "other tasks", "recruitment", "schedule", "audits", "personal data"], "requirements": {"degrees": ["higher diploma or above"], "majors": ["related disciplines", "science"], "languages": ["english", "chinese"], "language_level": ["good command"], "hard_skills": [], "soft_skills": ["work independently", "proactive", "willing to learn"], "languages_combined": [{"language": "english", "language_level": ["good command"]}, {"language": "chinese", "language_level": ["good command"]}]}, "experience_required": {"duration": ["1-2 years"], "field": ["pharmaceutical", "food industry", "quality assurance"]}}, {"job_id": "100003009039575", "location_code": "hk", "company": "Hutchmed Group (HK) Limited", "job_title": "Senior Product Manager", "description": "Job Responsibilities\nPrepare and dispense drugs accurately\u00a0and efficiently according to the prescriptions\nConduct patients\u00a0counseling\u00a0by explaining dosage, precautions and side effects of the medicine to the patients\nManage the pharmacy of medical center by keeping the\u00a0stock\u00a0of drugs\u00a0at an optimum level, maintaining a\u00a0safe and secure storage of drugs\nHandle\u00a0various kind of drugs\u00a0properly and according to regulatory requirements\nAssist in\u00a0handling payment transactions\nAnswer patient's inquiry on drugs related and contract-related inquiries\nWork with medical professionals\u00a0from multi-disciplines\u00a0to deliver the best customer services\nJob Requirements\nHigher Diploma in Dispensing Studies\u00a0/\u00a0Pharmaceutical Technology equivalent, or BSc in Pharmacy\nCompleted Dispenser related course\nGood command of spoken English and Chinese (Mandarin will be advantageous)\nProactive, customer-oriented and a good team player\nShift duty is required (No night shift)\nFresh graduate and oversea Pharmacist are welcome to join us\n\nWe offer\u00a0competitive pay\u00a0and fringe benefits. Interested parties please send your full resume with\u00a0current salary and expected salary\u00a0 to\u00a0Human Resources Department, Quality HealthCare Medical Services Limited, 3/F, Skyline Tower, 39 Wang Kwong Road, Kowloon Bay, Kowloon\u00a0or by clicking 'Apply Now\".\n\n(All applications will be treated in strict confidence and data collected will be used for recruitment) purposes only)", "employment_types": ["Full Time", "Permanent"], "selling_points": [], "locations": ["Hung Hom"], "categories": ["Marketing / Public Relations", "Marketing - Brand / Product Management", "Medical Services", "Pharmaceutical"], "post_time": "2022-01-11T10:09:23Z", "salary": {"currency": null, "max": null, "min": null, "period": "monthly", "term": null}, "salary_visible": false, "title_keywords": ["senior product manager"], "responsibilities": ["regulatory requirements", "payment transactions", "maintaining", "customer services"], "requirements": {"degrees": ["fresh graduate", "diploma", "bsc"], "majors": [], "languages": ["english", "chinese", "mandarin"], "language_level": ["good command"], "hard_skills": ["no"], "soft_skills": ["good team player", "customer-oriented", "proactive"], "languages_combined": [{"language": "english", "language_level": ["good command"]}, {"language": "chinese", "language_level": ["good command"]}, {"language": "mandarin", "language_level": ["good command"]}]}, "experience_required": {"duration": [], "field": []}}, {"job_id": "100003009041245", "location_code": "hk", "company": "Guosen Securities (HK) Financial Holdings Company, Limited", "job_title": "Research Analyst - Pharmaceutical & Healthcare", "description": "Job Responsibilities\nPrepare and dispense drugs accurately\u00a0and efficiently according to the prescriptions\nConduct patients\u00a0counseling\u00a0by explaining dosage, precautions and side effects of the medicine to the patients\nManage the pharmacy of medical center by keeping the\u00a0stock\u00a0of drugs\u00a0at an optimum level, maintaining a\u00a0safe and secure storage of drugs\nHandle\u00a0various kind of drugs\u00a0properly and according to regulatory requirements\nAssist in\u00a0handling payment transactions\nAnswer patient's inquiry on drugs related and contract-related inquiries\nWork with medical professionals\u00a0from multi-disciplines\u00a0to deliver the best customer services\nJob Requirements\nHigher Diploma in Dispensing Studies\u00a0/\u00a0Pharmaceutical Technology equivalent, or BSc in Pharmacy\nCompleted Dispenser related course\nGood command of spoken English and Chinese (Mandarin will be advantageous)\nProactive, customer-oriented and a good team player\nShift duty is required (No night shift)\nFresh graduate and oversea Pharmacist are welcome to join us\n\nWe offer\u00a0competitive pay\u00a0and fringe benefits. Interested parties please send your full resume with\u00a0current salary and expected salary\u00a0 to\u00a0Human Resources Department, Quality HealthCare Medical Services Limited, 3/F, Skyline Tower, 39 Wang Kwong Road, Kowloon Bay, Kowloon\u00a0or by clicking 'Apply Now\".\n\n(All applications will be treated in strict confidence and data collected will be used for recruitment) purposes only)", "employment_types": ["Full Time", "Permanent"], "selling_points": ["Pharmaceutical & Healthcare", "prepare in-depth research report", "follow up with the fundamental info of the company"], "locations": ["Admiralty"], "categories": ["Banking / Finance", "Analyst", "Others", "Medical Services", "Pharmaceutical"], "post_time": "2022-01-12T03:38:43Z", "salary": {"currency": null, "max": null, "min": null, "period": "monthly", "term": null}, "salary_visible": false, "title_keywords": ["research analyst"], "responsibilities": ["regulatory requirements", "payment transactions", "maintaining", "customer services"], "requirements": {"degrees": ["fresh graduate", "diploma", "bsc"], "majors": [], "languages": ["english", "chinese", "mandarin"], "language_level": ["good command"], "hard_skills": ["no"], "soft_skills": ["good team player", "customer-oriented", "proactive"], "languages_combined": [{"language": "english", "language_level": ["good command"]}, {"language": "chinese", "language_level": ["good command"]}, {"language": "mandarin", "language_level": ["good command"]}]}, "experience_required": {"duration": [], "field": []}}, {"job_id": "100003009048349", "location_code": "hk", "company": "Beijing Tong Ren Tang Chinese Medicine Company Limited", "job_title": "\u696d\u52d9\u5c08\u54e1 Business Assistant", "description": "Job Responsibilities\nPrepare and dispense drugs accurately\u00a0and efficiently according to the prescriptions\nConduct patients\u00a0counseling\u00a0by explaining dosage, precautions and side effects of the medicine to the patients\nManage the pharmacy of medical center by keeping the\u00a0stock\u00a0of drugs\u00a0at an optimum level, maintaining a\u00a0safe and secure storage of drugs\nHandle\u00a0various kind of drugs\u00a0properly and according to regulatory requirements\nAssist in\u00a0handling payment transactions\nAnswer patient's inquiry on drugs related and contract-related inquiries\nWork with medical professionals\u00a0from multi-disciplines\u00a0to deliver the best customer services\nWork at different clinics according to roster duty, with relieving allowance per month\nJob Requirements\nHigher Diploma in Dispensing Studies\u00a0/\u00a0Pharmaceutical Technology equivalent, or BSc in Pharmacy\nCompleted Dispenser related course\nGood command of spoken English and Chinese (Mandarin will be advantageous)\nProactive, customer-oriented and a good team player\nShift duty is required (No night shift)\nFresh graduate and oversea Pharmacist are welcome to join us\n\nWe offer\u00a0competitive pay\u00a0and fringe benefits. Interested parties please send your full resume with\u00a0current salary and expected salary\u00a0 to\u00a0Human Resources Department, Quality HealthCare Medical Services Limited, 3/F, Skyline Tower, 39 Wang Kwong Road, Kowloon Bay, Kowloon\u00a0or by clicking 'Apply Now\".\n\n(All applications will be treated in strict confidence and data collected will be used for recruitment) purposes only)", "employment_types": ["Full Time", "Permanent"], "selling_points": [], "locations": ["Wan Chai"], "categories": ["Admin & HR", "Clerical / Admin Staff", "Sales, CS & Business Devpt", "Business Development", "Medical Services", "Pharmaceutical"], "post_time": "2022-01-14T06:23:45Z", "salary": {"currency": null, "max": null, "min": null, "period": "monthly", "term": null}, "salary_visible": false, "title_keywords": ["assistant"], "responsibilities": ["regulatory requirements", "payment transactions", "maintaining", "customer services"], "requirements": {"degrees": ["fresh graduate", "diploma", "bsc"], "majors": [], "languages": ["english", "chinese", "mandarin"], "language_level": ["good command"], "hard_skills": ["no"], "soft_skills": ["good team player", "customer-oriented", "proactive"], "languages_combined": [{"language": "english", "language_level": ["good command"]}, {"language": "chinese", "language_level": ["good command"]}, {"language": "mandarin", "language_level": ["good command"]}]}, "experience_required": {"duration": [], "field": []}}, {"job_id": "100003009037759", "location_code": "hk", "company": "Novartis Pharmaceuticals (HK) Ltd", "job_title": "Senior/Sales Executive", "description": "In this role, you will be managing and leading the Aesthetics sales team to achieve a sustainable growth of the portfolio for HK & Macau market in line with company vision and values. Also, work synergistically across business units, functional teams from global, regional and local on an integrated dermatology strategy.\n\nJob Responsibilities:\n\nManage and lead the sales team to achieve the company's assigned sales, coverage expansion and engagement targets.\nFormulate and execute sales plans and go-to-market strategies for assigned Aesthetic channel.\nCall management and sales performance management for the sales team.\nPrepare sales forecast, demand planning input and analysis as well as ensure smooth operation of the sales team.\nInitiate, plan and execute customers programs and promotions within company's assigned budget and guidelines.\nFrequent visits of customers including HCPs and Customers.\nSupport Healthcare Professional engagement events including detailing, training, communication and marketing campaigns to support the company's brand & product campaign.\nBuild strong collaboration with internal key stakeholders to ensure smooth daily business operation.\nAdhere to all company policies, procedures and business ethics codes and ensure that they are communicated and implemented with the team\nProvide industry & market intelligence and ability to create and execute strategic plans to win over competition\nCreate a positive team environment through the demonstration of strong leadership behaviors, including communicating expectations clearly, installing an atmosphere of trust and respect, and leading by example\nHelp to develop each sales team member to realize their full potential\n\nJob Requirements:\n\nUniversity Graduate with a proven track record of 8+ years of experience ideally in the Aesthetic or pharmaceutical industry.\nProficient in English and Cantonese conversation & writing\nAbility to effectively present information to management, public, doctors or sales forces in oral and written form.\nAbility to read, analyze and interpret common scientific and technical information\nIdeally, the candidate should be in a senior sales position with hands-on experience in an aesthetic/ pharmaceutical company with strong connections and know-how especially within the industry.", "employment_types": ["Full Time", "Permanent"], "selling_points": ["Competitive incentive scheme", "Flexible working hours", "Free shuttle bus service"], "locations": ["Ngau Tau Kok"], "categories": ["Medical Services", "Specialist", "Pharmaceutical", "Sales, CS & Business Devpt", "Direct Sales"], "post_time": "2022-01-11T03:45:17Z", "salary": {"currency": null, "max": null, "min": null, "period": "monthly", "term": null}, "salary_visible": false, "title_keywords": ["sales executive"], "responsibilities": ["demand planning", "budget", "communication", "plan", "sales performance", "prepare sales", "develop", "forecast", "marketing campaigns", "management", "procedures", "installing", "business operation", "strategic plans", "guidelines", "policies", "analysis", "sales team", "sales plans"], "requirements": {"degrees": ["university graduate"], "majors": [], "languages": ["cantonese", "english"], "language_level": ["proficient"], "hard_skills": [], "soft_skills": ["oral", "hands-on"], "languages_combined": [{"language": "cantonese", "language_level": ["proficient"]}, {"language": "english", "language_level": ["proficient"]}]}, "experience_required": {"duration": ["of 8+ years"], "field": ["pharmaceutical", "aesthetic", "pharmaceutical company"]}}, {"job_id": "100003009042771", "location_code": "hk", "company": "Kerry Pharma (Hong Kong) Limited", "job_title": "Medical Representative (for a well-established US Pharma MNC)", "description": "Job Responsibilities\nPrepare and dispense drugs accurately\u00a0and efficiently according to the prescriptions\nConduct patients\u00a0counseling\u00a0by explaining dosage, precautions and side effects of the medicine to the patients\nManage the pharmacy of medical center by keeping the\u00a0stock\u00a0of drugs\u00a0at an optimum level, maintaining a\u00a0safe and secure storage of drugs\nHandle\u00a0various kind of drugs\u00a0properly and according to regulatory requirements\nAssist in\u00a0handling payment transactions\nAnswer patient's inquiry on drugs related and contract-related inquiries\nWork with medical professionals\u00a0from multi-disciplines\u00a0to deliver the best customer services\nJob Requirements\nHigher Diploma in Dispensing Studies\u00a0/\u00a0Pharmaceutical Technology equivalent, or BSc in Pharmacy\nCompleted Dispenser related course\nGood command of spoken English and Chinese (Mandarin will be advantageous)\nProactive, customer-oriented and a good team player\nShift duty is required (No night shift)\nFresh graduate and oversea Pharmacist are welcome to join us\n\nWe offer\u00a0competitive pay\u00a0and fringe benefits. Interested parties please send your full resume with\u00a0current salary and expected salary\u00a0 to\u00a0Human Resources Department, Quality HealthCare Medical Services Limited, 3/F, Skyline Tower, 39 Wang Kwong Road, Kowloon Bay, Kowloon\u00a0or by clicking 'Apply Now\".\n\n(All applications will be treated in strict confidence and data collected will be used for recruitment) purposes only)", "employment_types": ["Full Time", "Permanent"], "selling_points": [], "locations": ["Kwai Fong"], "categories": ["Medical Services", "Others", "Pharmaceutical", "Sales, CS & Business Devpt", "Others"], "post_time": "2022-01-12T08:45:43Z", "salary": {"currency": null, "max": null, "min": null, "period": "monthly", "term": null}, "salary_visible": false, "title_keywords": ["medical representative"], "responsibilities": ["regulatory requirements", "payment transactions", "maintaining", "customer services"], "requirements": {"degrees": ["fresh graduate", "diploma", "bsc"], "majors": [], "languages": ["english", "chinese", "mandarin"], "language_level": ["good command"], "hard_skills": ["no"], "soft_skills": ["good team player", "customer-oriented", "proactive"], "languages_combined": [{"language": "english", "language_level": ["good command"]}, {"language": "chinese", "language_level": ["good command"]}, {"language": "mandarin", "language_level": ["good command"]}]}, "experience_required": {"duration": [], "field": []}}, {"job_id": "100003009039904", "location_code": "hk", "company": "Online Marketing Genius Company Limited", "job_title": "Scientific content / medical writer", "description": "Provide professional nutrition consultation and dietary advice to clients\nProvide excellent customer service, establish, and maintain excellent customer relationship\nIntroduce and detail health supplements and provide appropriate product suggestions and advices\nOrganize and conduct public health education, seminars and workshops\nConduct health supplement market research and assist in product development\nEmbrace company culture and core values and actively participate in CSR activities and volunteer work\nParticipate and support daily operations and work closely with other departments on different projects\nExciting opportunities to develop career based on interests and talents and equip with the skills and knowledge required for success\n\nRequirement\n\nDegree in Nutrition and / or Food science or other relevant disciplines\nAt least 3 years' working experience in healthcare / pharmaceutical industry is preferred. Experience in retail / service industry is an advantage\nExcellent command of both written & spoken English, Mandarin and Cantonese\nPleasant, out-going with strong communication, interpersonal & presentation skill\nAble to work independently and under pressure\nOn-job training will be provided\n\nWe offer competitive remuneration package to the right candidate. Interested parties please send your application together with a detailed resume, current & expected salary and availability by clicking the \"APPLY NOW\" button below.", "employment_types": ["Full Time", "Permanent"], "selling_points": ["Excellent in English and Chinese writing", "Strong science/research background", "Degree in Pharmacy/Bio-Science /Public Health"], "locations": ["Kwai Hing"], "categories": ["Sciences, Lab, R&D", "Life Science", "Medical Services", "Pharmaceutical", "Research & Development (R&D)"], "post_time": "2022-01-11T14:34:58Z", "salary": {"currency": null, "max": null, "min": null, "period": "monthly", "term": null}, "salary_visible": false, "title_keywords": [], "responsibilities": ["market research", "work closely with other departments", "develop", "communication", "daily operations", "maintain", "customer service"], "requirements": {"degrees": ["degree"], "majors": ["food science"], "languages": ["cantonese", "english", "mandarin"], "language_level": ["excellent"], "hard_skills": ["workshops", "presentation skill"], "soft_skills": ["presentation skill", "work independently", "under pressure", "pleasant", "communication", "customer service", "interpersonal"], "languages_combined": [{"language": "cantonese", "language_level": ["excellent"]}, {"language": "english", "language_level": ["excellent"]}, {"language": "mandarin", "language_level": ["excellent"]}]}, "experience_required": {"duration": ["at least 3 years"], "field": ["pharmaceutical", "healthcare", "retail", "service industry"]}}, {"job_id": "100003009042984", "location_code": "hk", "company": "Healthlink Holdings Limited", "job_title": "Marketing Assistant", "description": "(Oncology & Biosimilar focused)\n\n\n\nResponsibilities\n\nExecute the action plans and strategies to achieve sales target of oncology and biosimilar products in assigned sector & territories\nFollow through on customer commitment and requests in a timely fashion\nProfessional product trainings and sales & marketing trainings provided\nCollect and feedback market intelligence\nEnsure compliance to company policies and business ethics and follow HKAPI Code of Practice\n\n\u00a0Requirements\n\nDegree holder in Science or related discipline\nExcellence interpersonal and communication skills\nPrior sales experience in pharmaceutical or medical related industry is an advantage\nExperience in one or more of the following customer groups including but not limited to Oncologists\u00a0and rheumatologists\n\nGood command in both\u00a0spoken and written English and Chinese\nCandidate with more experience will be considered as Senior Medical Representative\n\nIf you have the energy and qualifications to add to our velocity,\u00a0Please visit\u00a0Kerry Logistics Network Company Webpage\u00a0to apply or\u00a0send your CV with your present and expected salary to the\u00a0Group Director of\u00a0Human Resources & Administration, Kerry Logistics by clicking APPLY NOW\u00a0or by fax to +852 2614 8517\u00a0.\n\n(We are an equal opportunity employer and welcomes applications from all qualified candidates.\u00a0All personal data will be kept in the strictest confidence and will be used for recruitment purpose only. All applicants maybe considered for other suitable positions in the Kerry Group and its members. All personal data of unsuccessful candidates will be destroyed.)", "employment_types": ["Full Time", "Permanent"], "selling_points": ["Entry level for medical technology business", "5 Day Work, Fresh Graduates will be considered", "Friendly working environment"], "locations": ["Wong Tai Sin Area"], "categories": ["Marketing / Public Relations", "Marketing - General / Support", "Public Relations - Event Management", "Medical Services", "Pharmaceutical"], "post_time": "2022-01-12T09:25:39Z", "salary": {"currency": null, "max": null, "min": null, "period": "monthly", "term": null}, "salary_visible": false, "title_keywords": ["marketing assistant"], "responsibilities": ["plans", "sales target", "policies", "ensure compliance"], "requirements": {"degrees": ["degree holder"], "majors": ["science"], "languages": ["english", "chinese"], "language_level": ["good command"], "hard_skills": [], "soft_skills": ["communication skills", "confidence", "interpersonal"], "languages_combined": [{"language": "english", "language_level": ["good command"]}, {"language": "chinese", "language_level": ["good command"]}]}, "experience_required": {"duration": [], "field": ["pharmaceutical", "related", "medical"]}}, {"job_id": "100003009035784", "location_code": "hk", "company": "Astellas Pharma Hong Kong Co Ltd", "job_title": "Product Specialist (Metabolic)", "description": "Responsibilities:\n\n\nContent development for promotional materials including prints and multimedia projects\nSymposium highlight or case sharing with reference support\nEngage in writing, editing and cross checking materials both in English and Chinese\nScientific support for multimedia project and creative storyboard for patient education program\nWork with teams to ensure all the projects/materials are accurate and on time\nFresh graduates are welcome\nRequirements:\n\nExcellent in English and Chinese writing\nFluent in English and Cantonese\nWilling to share knowledge or expereince and work as a team\nStrong background in science and pharmaceutical knowledge\nIndependent and able to work multi-task\nGood interpersonal skills to work with clients, healthcare professional and medical societies\nBenefit:\n\n5 days' work\nFlexible working hours\nBank holiday\nYear-end bonus\nOn the job training will be provided\n\nPlease email your CV and expected salary, as well as their earliest availability date if you are interested.\u00a0", "employment_types": ["Full Time", "Permanent"], "selling_points": ["Global R&D Pharma Company", "Thorough selling skills & product/medical training", "Responsible for Metabolic Product"], "locations": ["Mong Kok"], "categories": ["Medical Services", "Pharmaceutical"], "post_time": "2022-01-10T08:25:08Z", "salary": {"currency": null, "max": null, "min": null, "period": "monthly", "term": null}, "salary_visible": false, "title_keywords": ["product specialist"], "responsibilities": ["editing", "promotional materials", "teams", "checking"], "requirements": {"degrees": [], "majors": [], "languages": ["cantonese", "english", "chinese"], "language_level": ["excellent", "fluent"], "hard_skills": [], "soft_skills": ["multi-task", "independent", "work as a team", "interpersonal skills"], "languages_combined": [{"language": "cantonese", "language_level": ["fluent"]}, {"language": "english", "language_level": ["excellent", "fluent"]}, {"language": "chinese", "language_level": ["excellent"]}]}, "experience_required": {"duration": [], "field": []}}, {"job_id": "100003009040822", "location_code": "hk", "company": "Yang Memorial Methodist Social Service", "job_title": "\u4e00\u7d1a\u7269\u7406\u6cbb\u7642\u5e2b (\u5168\u8077 / \u517c\u8077) (\u5230\u6821\u5b78\u524d\u5eb7\u5fa9\u670d\u52d9)", "description": "Key Responsibility:\n\n\nTo follow up on the production of marketing materials,\u00a0such as\u00a0brochures, leaflets, newsletters, e-materials for on-line and off-line channels\nAssist in the maintenance of social media account and website\nCoordinate with\u00a0internal teams\u00a0and external parties to meet objectives and deadlines of different projects and events\nProvide\u00a0administrative\u00a0support and operational support to the sales and marketing division\nSupport ad-hoc tasks as assigned\nCandidates with more experience will be considered as marketing executive\n\nJob Requirement:\n\nExcellent communication and problem-solving skills\nGood computer skills including MS Word, Excel, PowerPoint and Chinese word processing\nGood command in both written and spoken English and Chinese\nAnalytical-minded, independent, self-motivated and able to work under pressure\nKnowledge in ERP such as Epicor and Oracle will be a bonus\n\nWe offer competitive salary, 5-day workweek, medical scheme and other fringe benefits such as Birthday Leave to the successful applicants. Interested parties please send your CV with current and expected salary. For more information about us, please visit our website at\u00a0www.healthlinkholdings.com.\u00a0\n\n\nPersonal data will be used for recruitment purpose only.", "employment_types": ["Part Time"], "selling_points": [], "locations": ["Not Specified"], "categories": ["Medical Services", "Medical Services Technician", "Specialist", "Pharmaceutical"], "post_time": "2022-01-12T03:07:16Z", "salary": {"currency": null, "max": null, "min": null, "period": "hourly", "term": null}, "salary_visible": false, "title_keywords": [], "responsibilities": ["social media", "operational support", "maintenance", "leaflets", "ad-hoc tasks", "external parties", "coordinate with", "website", "teams", "marketing materials", "provide administrative support"], "requirements": {"degrees": [], "majors": [], "languages": ["english", "chinese"], "language_level": ["good command", "good"], "hard_skills": ["excel", "oracle", "chinese word processing", "powerpoint", "erp", "computer skills", "problem-solving skills", "ms word"], "soft_skills": ["self-motivated", "independent", "communication", "problem-solving skills", "work under pressure"], "languages_combined": [{"language": "english", "language_level": ["good command", "good"]}, {"language": "chinese", "language_level": ["good command", "good", "good"]}]}, "experience_required": {"duration": [], "field": []}}, {"job_id": "100003009043626", "location_code": "hk", "company": "Pfizer Corporation Hong Kong Limited", "job_title": "Hong Kong Trainer", "description": "Key Roles & Responsibilities\n\nResponsible for promoting a highly technical and innovative product portfolio to physician in both private and hospital sectors\n\nDevelop relationships and maintaining an active presence with most productive doctors in the community and associated organizations\n\nContribute positively to the Sales and Marketing team through co-operative relationships and collaborative efforts to achieve team and company objectives\n\nImplement Plan of Action adherence to all marketing and compliance policies as well as issued company and sales procedures at ethical standards\n\nResponsible for achieving sales target of the assigned territories\n\nSupport marketing activities and events\n\nQualifications:\n\nUniversity graduate with life science background\n\n2 years working experience in pharmaceutical field\u00a0would be an advantage\n\nSelf-directed, independent in a fast paced and high growth environment\n\nStrong communicative and interpersonal skills and analytical skills\n\nStrong understanding and grasp of market analysis, planning, development and management\n\nCandidates with more experience will be considered as Senior Product Specialist\n\nWe offer a highly competitive remuneration package to the successful candidates. Interested parties please send full resume with current & expected salary (please quote our job reference code) to: Human Resources Department, Astellas Pharma Hong Kong Co., Ltd., Unit 1103-08, 11/F., Tower 1, Grand Century Place, 193 Prince Edward Road West, Mongkok, Kowloon, Hong Kong or click \"Apply Now\".\n\n(Our company is an equal opportunity employer and welcomes application from all qualified candidates. The data provided will be used only for consideration of the applied position in our company. All information received will be kept in strict confidence and only for recruitment purpose. Applicants who are not invited for interview within 2 months may consider their applications unsuccessful.)", "employment_types": ["Full Time", "Permanent"], "selling_points": ["At least 5 years' relevant experience", "Ability to work on multiple projects simultaneous", "Cross-functional working experience"], "locations": ["Quarry Bay"], "categories": ["Admin & HR", "Training & Development", "Medical Services", "Pharmaceutical"], "post_time": "2022-01-13T01:05:07Z", "salary": {"currency": null, "max": null, "min": null, "period": "monthly", "term": null}, "salary_visible": false, "title_keywords": [], "responsibilities": ["management", "maintaining", "policies", "sales target", "compliance", "procedures", "develop", "market analysis", "plan", "planning"], "requirements": {"degrees": ["university graduate"], "majors": ["science"], "languages": [], "language_level": [], "hard_skills": ["analysis", "analytical skills"], "soft_skills": ["productive", "independent", "responsible", "collaborative", "innovative", "analytical skills", "interpersonal skills", "ethical", "active"], "languages_combined": []}, "experience_required": {"duration": ["2 years"], "field": ["pharmaceutical"]}}, {"job_id": "100003009039574", "location_code": "hk", "company": "Hutchmed Group (HK) Limited", "job_title": "Senior Manager / Manager of Sustainability", "description": "Why Patients Need You\u00a0\n\nWe expect our sales team to be experts on our product lines and the conditions the drugs have been developed to treat. As Hong Kong Trainer, you'll be responsible for ensuring the seamless delivery of evolved and enhanced learning experiences for Pfizer customer facing colleagues to create and sustain a competitive advantage for Pfizer.\u00a0 You will also collaborate with their Digital Client Partner to effectively engage with Business Unit clients to define and deliver learning initiatives that have quantifiable value and impact.\n\nWhat You Will Achieve\n\nYou will provide support to sales representatives(sales staff and sales management) and channel partners by developing,\u00a0planning,\u00a0and conducting training on techniques of selling the organization's products and services. You will be responsible for developing and delivering training programs that focus on sales techniques and presentations, product information, group referencing\u00a0\u00a0and role play. You may also work with Product Managers or marketing teams to develop a sales strategy and incorporate this strategy into the training programs.\u00a0\n\nHow You Will Achieve It\n\u00a0\nYou will be accountable for implementing Learning at local level by:\n\n\nCollaborating with the Digital Client Partner to effectively engage with Business Unit clients to define and deliver learning initiatives that have quantifiable value and impact\nEnsuring the uniform delivery of learning at country level (including product knowledge, marketing and selling skills training, sustainability programs, innovative learning assets, virtual tools, etc.)\nMonitoring the adherence to streamlined local review and approval of learning materials\nCollecting and providing country specific learnings and performance metrics that support continuous improvement\u00a0\u00a0\n\nQualifications\u00a0\n\nA recognized Bachelor\u2019s degree\nAt least 5 years' relevant experience; people leadership experience with evidence of high emotional intelligence would be an advantage\nCommercial training experience including delivery of blended and distance learning curricula and content is essential\nUnderstanding of the pharma industry / Pfizer\u2019s business\nExperience in evaluating Learning programs and materials to ensure client and learner needs are met\nAbility to work on multiple projects simultaneously and manage competing priorities\nCross-functional working experience and collaboration\nMinimum of a Bachelor\u2019s degree required", "employment_types": ["Full Time", "Permanent"], "selling_points": [], "locations": ["Hung Hom"], "categories": ["Professional Services", "Business Analysis / Data Analysis", "Business Consultancy", "Medical Services", "Pharmaceutical"], "post_time": "2022-01-11T10:09:23Z", "salary": {"currency": null, "max": null, "min": null, "period": "monthly", "term": null}, "salary_visible": false, "title_keywords": ["senior manager", "manager"], "responsibilities": ["collaborate with", "provide support", "monitoring", "teams", "developing", "presentations", "develop", "review", "performance metrics", "sales team", "multiple projects", "sales management", "planning"], "requirements": {"degrees": ["degree", "bachelor"], "majors": [], "languages": [], "language_level": [], "hard_skills": ["focus", "presentations"], "soft_skills": ["responsible", "accountable", "learning", "focus", "innovative", "leadership"], "languages_combined": []}, "experience_required": {"duration": ["at least 5 years"], "field": ["commercial", "relevant experience", "training"]}}, {"job_id": "100003009038045", "location_code": "hk", "company": "Hind Wing Company Limited", "job_title": "Pharmaceutical Warehouse Staff", "description": "Responsible for the promotion of medical and pharmaceuticals products to private doctors and clinics in private sector.\u00a0\nDevelop new accounts to expand company data base.\nBuild and maintain strong relationships with key customers across multiple settings.\nMonitor and analyze data and market conditions to identify competitive advantage.\nProvide product information.\u00a0\nJob Requirements :\u00a0\n\nPrevious work experience as a Pharmaceutical Sales Representative for 1-2 year(s)\nA proven track record of successful sales\nIn-depth knowledge of databases, statistics, product lines\nOutstanding communication, negotiation and sales skills\nExcellent organisational and time management skills\nHighly ethical with a strong sense of integrity.\nWe will provide product training, attractive remuneration package with high commission pay & good promotion prospects to the right candidate. Please kindly send your resume and expected salary by clicking 'Apply Now'.\n\nPersonal data collected will be used for recruitment purpose only.", "employment_types": ["Full Time"], "selling_points": ["5-day working week", "medical insurance", "warehouse experience"], "locations": ["North Point"], "categories": ["Medical Services", "Pharmaceutical"], "post_time": "2022-01-11T04:43:07Z", "salary": {"currency": null, "max": null, "min": null, "period": "monthly", "term": null}, "salary_visible": false, "title_keywords": ["staff"], "responsibilities": ["management", "data", "monitor", "develop", "communication", "maintain", "recruitment", "databases", "analyze data", "personal data"], "requirements": {"degrees": [], "majors": [], "languages": [], "language_level": [], "hard_skills": ["databases"], "soft_skills": ["negotiation", "responsible", "time management skills", "integrity", "communication", "ethical"], "languages_combined": []}, "experience_required": {"duration": [], "field": ["pharmaceutical"]}}, {"job_id": "100003009046874", "location_code": "hk", "company": "SYNCO (H.K.) Ltd", "job_title": "Assistant Production Officer", "description": "Key Roles and Responsibilities\n\nUpdate and maintain validation plan\nEnsure the qualification and validation activities are carried out according to schedule\nAssist in planning and executing qualification and validation activities\nAssist in ad-hoc projects assigned by Assistant Q.A Manager\n\n\u00a0Qualification and Experience\u00a0\n\nHigher Diploma, Associate Degree or\u00a0Degree holder in Science, Pharmaceutical,Engineering,\u00a0 or related discipline\nWith good communication skill, hard-working, willing to learn\nGood\u00a0communication skills in both written and spoken English and Cantonese\u00a0\nCandidates with less experience will be considered as Assistant Q.A. Validation Officer/Engineer\nRelevant work experience is preferred but not essential\nFresh graduates are welcome\n\n\n\nWe offer to the right candidates with competitive remuneration package including 12-16 day annual leave, marriage leave, maternity leave, paternity leave, compassionate leave, Public Holidays, medical and dental insurance, educational sponsorship, overtime allowance, performance bonus, MPF and other fringe benefits.\n\nHow to Apply\n\nYou are invited to send in your application and CV stating the position you are applying for together with your current and expected salary by clicking the \"apply button\".\n\nVickmans\u00a0Laboratories\u00a0Limited is an Equal Opportunities Employer. Personal data provided by job applicants will be used strictly in accordance with our personal data policy and for recruitment purposes only. We aim to respond to successful applicants within 8 weeks and related information will be kept in our file for up to 12 months for other suitable vacancies in our organization and thereafter destroyed", "employment_types": ["Full Time", "Permanent"], "selling_points": [], "locations": ["Tai Po Area"], "categories": ["Manufacturing", "Production Planning / Control", "Medical Services", "Pharmaceutical", "Quality Assurance, Control & Testing / ISO"], "post_time": "2022-01-14T01:33:40Z", "salary": {"currency": null, "max": null, "min": null, "period": null, "term": null}, "salary_visible": false, "title_keywords": ["assistant production officer"], "responsibilities": ["mpf", "communication", "maintain", "executing", "schedule", "plan", "personal data", "recruitment", "ad-hoc projects", "insurance", "planning"], "requirements": {"degrees": ["associate degree", "diploma", "degree holder"], "majors": ["science", "engineering"], "languages": ["cantonese", "english"], "language_level": ["good"], "hard_skills": [], "soft_skills": ["communication skills", "communication skill", "hard-working", "willing to learn"], "languages_combined": [{"language": "cantonese", "language_level": ["good"]}, {"language": "english", "language_level": ["good"]}]}, "experience_required": {"duration": [], "field": []}}, {"job_id": "100003009040110", "location_code": "hk", "company": "Vickmans Laboratories Ltd", "job_title": "Validation Engineer", "description": "Job Responsibilities:\n\nPrepare and review protocols and other associated PIC/S GMP documentation.\nAnalysis of raw material, in-process and final bulk cell therapy/gene product samples according to Standard Operating Procedures (SOP) and test methods.\nExperience in one or more of the following analytical techniques: Flow Cytometry, Blood Culture test, Cell Culture, sterility test, endotoxin test, mycoplasma test, and tests specific to cell-based products.\nSupervise and perform the qualification, maintenance, and calibration for all QC equipment and instrument.\nReview and fine-tuning of quality control workflow.\nOther duties as assigned by Authorized Person and/or management team.\n\nQualification and Experience:\n\nBachelor\u2019s degree or above in biotechnology, biomedical engineering, medical laboratory science or science degree with relevant to cell therapy, gene therapy, regenerative medicines or tissue engineering, or other similar sciences disciplines;\nAt least 3 years of working experience at managerial or supervisory level in GMP manufacturing or quality control of ATPs;\nExperience for PIC/S GMP QC is highly preferred;\nWith practical experience in PIC/S GMP QC testing of sterile products is highly preferred;\nExcellent communication, problem-solving, time management, and prioritization skills.\nSelf-motivated and a good team player, attention to detail.\nProficiency in English and Chinese.\n\nWe offer an attractive remuneration package including group medical insurance, discretionary year-end performance bonus, and an energetic, fun work environment.\n\nInterested parties please send your resume with current, expected salary and availability to the HR Department.\n\n(All personal data provided will be treated in strict confidence and be used for recruitment purposes.)", "employment_types": ["Full Time"], "selling_points": [], "locations": ["Ngau Tau Kok"], "categories": ["Manufacturing", "Production Planning / Control", "Medical Services", "Pharmaceutical", "Quality Assurance, Control & Testing / ISO"], "post_time": "2022-01-12T01:27:54Z", "salary": {"currency": null, "max": null, "min": null, "period": null, "term": null}, "salary_visible": false, "title_keywords": ["engineer"], "responsibilities": ["management team", "management", "year-end", "maintenance", "other duties", "analysis", "review", "procedures", "testing", "communication", "quality control", "documentation", "insurance"], "requirements": {"degrees": ["degree", "degree or above", "bachelor"], "majors": ["biomedical engineering", "engineering", "medical laboratory science", "science"], "languages": ["english", "chinese"], "language_level": ["proficiency"], "hard_skills": ["fun", "maintenance", "analysis", "problem-solving", "documentation"], "soft_skills": ["good team player", "self-motivated", "problem-solving", "communication", "energetic", "attention to detail", "time management"], "languages_combined": [{"language": "english", "language_level": ["proficiency"]}, {"language": "chinese", "language_level": ["proficiency"]}]}, "experience_required": {"duration": ["at least 3 years"], "field": ["managerial", "gmp manufacturing", "analytical", "testing", "quality control", "supervisory level"]}}, {"job_id": "100003009043090", "location_code": "hk", "company": "Advance Pharmaceutical Company Limited", "job_title": "Quality Control Technician", "description": "1)\u00a0\u00a0\u00a0\u00a0 Sampling and chemical testing of raw material, intermediate samples, stability samples and\u00a0 finished products;\n\n2)\u00a0\u00a0\u00a0\u00a0 Perform calibration and maintenance of laboratory instrument;\n\n3)\u00a0\u00a0\u00a0\u00a0 Prepare the testing report and GMP document;\n\n4)\u00a0 \u00a0 \u00a0Ad hoc tasks as assigned by manager;\n\n\n5)\u00a0\u00a0\u00a0\u00a0 University graduate in Applied Chemistry, Chemical Technology or related disciplines;\n\n6)\u00a0\u00a0\u00a0\u00a0 Hands on experience in HPLC, GC, UV, IR or other testing instrument is an advantage;\n\n7)\u00a0\u00a0\u00a0\u00a0 Hardworking, self-motivated, fast learner and able to work under pressure and overtime;\n\n8)\u00a0\u00a0\u00a0\u00a0 Knowledge of PIC/s GMP, ISO 17025 or other quality system would be an advantage;\n\n9)\u00a0\u00a0\u00a0\u00a0 Proficient in MS Word and Excel;\n\n10)\u00a0 \u00a0 Good verbal and written communication skills in English.\n\n\n", "employment_types": ["Full Time"], "selling_points": [], "locations": ["Tai Po Area"], "categories": ["Sciences, Lab, R&D", "Laboratory", "Medical Services", "Pharmaceutical", "Others", "Technician"], "post_time": "2022-01-12T09:47:46Z", "salary": {"currency": null, "max": null, "min": null, "period": "monthly", "term": null}, "salary_visible": false, "title_keywords": ["quality control technician"], "responsibilities": ["maintenance", "ad hoc tasks", "quality", "testing", "communication", "report", "work under pressure"], "requirements": {"degrees": ["university graduate"], "majors": ["related disciplines", "chemistry"], "languages": ["english"], "language_level": ["good"], "hard_skills": ["excel", "maintenance", "ms word"], "soft_skills": ["communication skills", "self-motivated", "hands on", "fast learner", "hardworking", "work under pressure"], "languages_combined": [{"language": "english", "language_level": ["good"]}]}, "experience_required": {"duration": [], "field": ["testing"]}}, {"job_id": "100003009035933", "location_code": "hk", "company": "4iCreative Limited", "job_title": "Project Manager/Executive/Co-ordinator", "description": "Responsibilities:\n\nResearch field: Analysis of researching industrial innovation development, closely follow up with industry trends, prepare in-depth research report\nIn-depth research on key companies/segmented fields: analysis of the specific industry of target companies\nAnalysis of business models, core competitiveness, field/company growth and risks, establish dynamic adjustment valuation models\nClosely follow up with the fundamental information of companies in target industries, and conduct researches on major announcements and important information\nConduct research and analysis of industries/companies independently and provide analysis reports\nTo perform ad hoc projects\n\nRequirements:\n\nMaster degree or above in science and engineering, biomedical background preferred\nMinimum 2 years of relevant experience in investment institutions or related relevant experience in the pharmaceutical industry, knowledge of key issues and developments in pharmaceutical industries\nPossess financial basic knowledge, familiar with various research methods, outstanding data processing ability\nWith strong analytical mind, strong ability of gathering information independently and logical thinking, research and analysis\nExcellent in written and spoken English and Chinese (Cantonese & Putonghua)\n\nAttractive remuneration will be offered to the right candidate.\u00a0 Interested parties please email your full resume with present & expected salary and date of availability to hrm @guosen.com.hk or via \"Apply Now\".\n\nPersonal data collected would be used for recruitment purpose only.", "employment_types": ["Full Time", "Permanent"], "selling_points": [], "locations": ["Wong Tai Sin Area"], "categories": ["Sales, CS & Business Devpt", "Business Development", "Medical Services", "Pharmaceutical"], "post_time": "2022-01-10T08:51:35Z", "salary": {"currency": null, "max": null, "min": null, "period": "monthly", "term": null}, "salary_visible": false, "title_keywords": ["project manager", "executive"], "responsibilities": ["valuation", "analysis reports", "analysis", "ad hoc projects", "conduct research", "report"], "requirements": {"degrees": ["degree or above", "master"], "majors": ["science", "engineering"], "languages": ["cantonese", "putonghua", "english", "chinese"], "language_level": ["excellent"], "hard_skills": ["analysis", "processing", "basic"], "soft_skills": ["analytical mind", "independently"], "languages_combined": [{"language": "cantonese", "language_level": ["excellent"]}, {"language": "putonghua", "language_level": ["excellent"]}, {"language": "english", "language_level": ["excellent"]}, {"language": "chinese", "language_level": ["excellent"]}]}, "experience_required": {"duration": ["minimum 2 years"], "field": ["related", "pharmaceutical", "relevant experience", "investment"]}}, {"job_id": "100003009040186", "location_code": "hk", "company": "Fortune Pharmacal Company Limited", "job_title": "Administrative Assistant (Production)", "description": "Responsibilities:\n\nContribute to our organisations\u2019 continued rapid growth by:-\n\n\u2022 Developing new client relationships\n\n\u2022 Servicing existing client base\n\n\u2022 Project management working with multiple internal departments\n\nRequirements:\n\n\u2022 Science Degree holder\n\n\n\u2022 Good interpersonal skills\n\n\n\u2022 Action orientated\n\n\u2022 Team player\n\n(Candidates not fully meeting the requirements may be considered for Business Development Executive)\n\nThe successful candidate will be mentored and can expect a competitive salary with incentives, MPF and medical coverage, in a 5 day working week. Interested parties should email their CV, stating their current and expected remuneration, as well as their earliest availability date. All information will be kept strictly for employment purposes only.", "employment_types": ["Full Time"], "selling_points": ["Knowledge in ERP system is an advantage", "Administrative support", "New manufacturing plant at Yuen Long"], "locations": ["Yuen Long"], "categories": ["Admin & HR", "Clerical / Admin Staff", "Manufacturing", "Others", "Medical Services", "Pharmaceutical"], "post_time": "2022-01-12T01:47:45Z", "salary": {"currency": null, "max": null, "min": null, "period": "monthly", "term": null}, "salary_visible": false, "title_keywords": ["administrative assistant"], "responsibilities": ["project management", "client base", "developing"], "requirements": {"degrees": ["degree holder"], "majors": ["science"], "languages": [], "language_level": [], "hard_skills": [], "soft_skills": ["team player", "interpersonal skills"], "languages_combined": []}, "experience_required": {"duration": [], "field": []}}, {"job_id": "100003009034182", "location_code": "hk", "company": "", "job_title": "Drugs Project Supervisor/Senior Project Specialists \u85e5\u54c1\u5c08\u6848\u4e3b\u7ba1/\u9ad8\u7d1a\u5c08\u6848\u5c08\u54e1", "description": "Job Purpose:\n\nExperienced sales professionals responsible (directly or indirectly) for achieving sales targets and promoting the products to medical practitioners and allied health care professionals; for a specific account, product or a given territory.\n\nResponsibilities:\n\nAccountable for achieving agreed sales, productivity and performance targets within agreed budgets and timescales -Develop business plans and implement related activities like customer events, sales and marketing campaigns, sales presentations necessary to achieve agreed objectives\nProvide Key account/hospital network support, market access support; including referral networks\nHave a deep understanding in the respective area and priority products. Maintain and enhance knowledge of products, product strategy, positioning, key messages, programs, company developments, customers, and competitors\nAchieve agreed contact, coverage and frequency targets through various communication channels\nEnsure customer satisfaction and best in class customer relationship\nEnsure the accurate and timely completion of all reports\nHandle enquiries and complaints quickly and professionally and in accordance with company procedures.\nContribute positively to the Sales and Marketing team through co-operative relationships and collaborative efforts to achieve team and company objectives.\nProvide input into effective use of promotional funds and territory sales forecasting.\nFollow all adverse events guidelines, and Code of Conduct Guidelines as promoted by Novartis. Demonstrate Behavior in accordance with Novartis code of practice.\nIn case of a Manager/ Leader; the person is responsible for the sales planning; target; reporting; and knowledge of the team/account and of himself/herself.\nQualifications:\n\n\nSales in Healthcare / Pharma / related business\u00a0\nEstablished Network to target Customer Group desirable English\n\nYou\u2019ll receive:\n\nCompetitive salary, double pay, annual bonus, health and life insurance, flexible working arrangements. Find out more about Novartis: https://www.novartis.com/\n\nJoin us and help us reimagine medicine.\n\nNovartis are an equal opportunities employer and welcome applications from all suitably qualified applicants", "employment_types": ["Full Time", "Permanent"], "selling_points": ["Regulatory Affairs  NDC/FDA", "drug regulatory requirements", "registration of export pharmaceuticals products"], "locations": ["Tin Shui Wai"], "categories": ["Transportation & Logistics", "Inventory / Warehousing", "Shipping", "Medical Services", "Pharmaceutical"], "post_time": "2022-01-10T02:54:32Z", "salary": {"currency": null, "max": null, "min": null, "period": "monthly", "term": null}, "salary_visible": false, "title_keywords": ["project supervisor"], "responsibilities": ["budgets", "reporting", "guidelines", "procedures", "handle enquiries and complaints", "presentations", "business plans", "communication", "maintain", "reports", "contact", "marketing campaigns", "insurance", "forecasting", "planning"], "requirements": {"degrees": [], "majors": [], "languages": ["english"], "language_level": [], "hard_skills": ["code", "presentations"], "soft_skills": ["flexible", "responsible", "timely", "deep", "accountable", "collaborative", "communication", "accurate"], "languages_combined": [{"language": "english", "language_level": []}]}, "experience_required": {"duration": [], "field": []}}, {"job_id": "100003009039333", "location_code": "hk", "company": "Advance Pharmaceutical Company Limited", "job_title": "Production Officer", "description": "Responsibilities\n\nMaintain a documentation system in order to comply with GMP requirements, e.g batch production record, logbooks, labels & documents related to production\nUpdate data in ERP system in a timely and accurate manner\nMonitor and maintain inventory stock of production consumables\nAssist in scheduling and arrangement of the staff annual medical checkup\nPerforms administrative work including staff leave balance\nAny other production related duties that may be assigned if necessary.\nRequirements\n\nForm 5 or DSE or equivalent. Vocational Training Council in clerical position or job\u2013related experience is an advantage.\nAble to read and write in Chinese and English.\nFamiliar with Microsoft office e.g. MS Excel, MS Word", "employment_types": ["Full Time"], "selling_points": [], "locations": ["Tai Po Area"], "categories": ["Manufacturing", "Manufacturing Management", "Product Development / Management", "Medical Services", "Pharmaceutical"], "post_time": "2022-01-11T09:27:01Z", "salary": {"currency": null, "max": null, "min": null, "period": "monthly", "term": null}, "salary_visible": false, "title_keywords": ["production officer"], "responsibilities": ["administrative work", "data", "inventory", "monitor", "scheduling", "maintain", "documentation", "staff leave"], "requirements": {"degrees": ["form 5", "dse"], "majors": [], "languages": ["english", "chinese"], "language_level": [], "hard_skills": ["ms word", "ms excel", "microsoft office"], "soft_skills": [], "languages_combined": [{"language": "english", "language_level": []}, {"language": "chinese", "language_level": []}]}, "experience_required": {"duration": [], "field": ["related", "training", "clerical"]}}, {"job_id": "100003009046876", "location_code": "hk", "company": "SYNCO (H.K.) Ltd", "job_title": "\u54c1\u8cea\u4fdd\u8b49\u52a9\u7406(\u517c\u8077) QA Assistant (Part-Time)", "description": "To assist in developing, implementing and maintaining the documentation system, including the Standard Operating Procedures (SOPs) and other production documents\nTo ensure and maintain the adequate and accurate records for controlling and monitoring conformity to specified GMP and statutory requirements\nTo assist monitor the production process according to the production plan\nTo assist in performing investigation to production deviation\nTo perform the daily operation and ad-hoc functions of Production Department\nTo assist the head of production to monitor the daily production workflow", "employment_types": ["Part Time"], "selling_points": [], "locations": ["Tai Po Area"], "categories": ["Manufacturing", "Others", "Medical Services", "Pharmaceutical", "Quality Assurance, Control & Testing / ISO"], "post_time": "2022-01-14T01:33:41Z", "salary": {"currency": null, "max": null, "min": null, "period": null, "term": null}, "salary_visible": false, "title_keywords": ["qa assistant"], "responsibilities": ["ad-hoc", "production process", "maintaining", "monitoring", "procedures", "developing", "monitor", "investigation", "daily operation", "statutory requirements", "maintain", "sops", "plan", "documentation"], "requirements": {"degrees": [], "majors": [], "languages": [], "language_level": [], "hard_skills": ["documentation"], "soft_skills": ["accurate"], "languages_combined": []}, "experience_required": {"duration": [], "field": []}}, {"job_id": "100003009036228", "location_code": "hk", "company": "Karen Pharmaceutical Company Limited", "job_title": "Laboratory Assistant", "description": "\u00a0Job Responsibility\n\nResponsible for monitoring of QA Department's daily operations.\nApproval of cleanroom/utilities/equipment DQ/IQ/OQ/PQ protocols and reports, and various validation Protocols and reports.\nPerform initial assessment of Product Quality Review and Management Review Reports and submit to Authorized Person and management.\nBe a key member in conducting self-inspections and external audits.\nProvide coaching and training to QA staff, and advanced training on PIC/S GMP standards.\nApproval of SOPs related to the QA Department.\nPlan and provide practical and compliant solutions in change controls, deviation investigations, OOS investigation, CAPA, quality risk assessments, qualification and validation, supplier evaluations, and continual improvement.\nRaise quality issues to the Authorized Person and management in a timely manner.\nWork with the Authorized Person to develop and monitor quality KPI.\nOther duties as assigned by Authorized Person and/or management team.\n\nQualification and Experience\n\nBachelor's degree or above in biotechnology, biochemistry, chemistry, and medical laboratory science or science degree with relevant to cell therapy, gene therapy, regenerative medicines or tissue engineering, or other similar sciences disciplines;\nAt least 4 years of experience in a quality managerial role in a pharmaceutical GMP environment.\nKnowledge of PIC/S GMP and other quality system/quality assurance principles is highly preferred.\nReceived formal training on Quality Management System e.g. ISO 9001 Internal Auditor is highly preferred.\nWith knowledge and/or experience in GMP operations of sterile pharmaceutical products, biological substances or products, or cell-based products.\nExcellent communication, problem-solving, time management, and prioritization skills.\nSelf-motivated and a good team player, attention to detail.\nProficiency in English and Chinese.\n\nWe offer an attractive remuneration package including group medical insurance, discretionary year-end performance bonus, and an energetic, fun work environment.\n\nInterested parties please send your resume with current, expected salary and availability to the HR Department.\n\n(All personal data provided will be treated in strict confidence and be used for recruitment purposes.)", "employment_types": ["Full Time"], "selling_points": [], "locations": ["Tuen Mun Area"], "categories": ["Sciences, Lab, R&D", "Laboratory", "Medical Services", "Pharmaceutical", "Manufacturing", "Quality Assurance, Control & Testing / ISO"], "post_time": "2022-01-10T09:44:42Z", "salary": {"currency": null, "max": null, "min": null, "period": null, "term": null}, "salary_visible": false, "title_keywords": ["laboratory assistant"], "responsibilities": ["operations", "quality", "communication", "plan", "management review", "management team", "other duties", "monitor", "develop", "reports", "management", "review", "monitoring", "investigation", "daily operations", "sops", "audits", "year-end", "a timely manner", "insurance"], "requirements": {"degrees": ["degree", "degree or above", "bachelor"], "majors": ["science", "chemistry", "engineering", "medical laboratory science"], "languages": ["english", "chinese"], "language_level": ["proficiency"], "hard_skills": ["problem-solving", "fun"], "soft_skills": ["self-motivated", "good team player", "advanced", "responsible", "problem-solving", "timely", "communication", "energetic", "attention to detail", "time management"], "languages_combined": [{"language": "english", "language_level": ["proficiency"]}, {"language": "chinese", "language_level": ["proficiency"]}]}, "experience_required": {"duration": ["at least 4 years"], "field": ["pharmaceutical", "managerial"]}}, {"job_id": "100003009037141", "location_code": "hk", "company": "Health Care & Co.", "job_title": "Medical Representative / Medical Product Specialist", "description": "\nPost Date: 07 Jan 2022\n\nFunctions: Health Care / Medical\nTypes: -\nEducation: Certificate / Diploma\nSalary: -\nLocation: -\nWebsite: http://www.yang.org.hk\n\n\u8077\u4f4d\u7de8\u865f\uff1aOPRS/PTI\n\n\u2022 \u8a3b\u518a\u7269\u7406\u6cbb\u7642\u5e2b\u53ca\u6301\u6709\u6548\u57f7\u696d\u8b49\u66f8\n\u2022 \u70ba\u5b78\u524d\u7279\u6b8a\u9700\u8981\u5e7c\u5152\u63d0\u4f9b\u500b\u4eba / \u5c0f\u7d44\u6cbb\u7642\u3001\u5bb6\u9577\u57f9\u8a13\u3001\u6559\u5e2b\u57f9\u8a13\u7b49\u5de5\u4f5c\n\u2022 \u5177 5 \u5e74\u6216\u4ee5\u4e0a\u5152\u7ae5\u5fa9\u5eb7\u5de5\u4f5c\u7d93\u9a57\n\u2022 \u90e8\u4efd\u5de5\u4f5c\u5305\u62ec\u652f\u63f4\u6a5f\u69cb\u5176\u4ed6\u55ae\u4f4d\u7684\u7269\u7406\u6cbb\u7642\u670d\u52d9\n\u2022 \u6bcf\u9031\u5de5\u4f5c 44 \u5c0f\u6642\uff0c\u9700\u8de8\u5340\u53ca\u9694\u9031\u516d\u5de5\u4f5c\n\n\u4e0a\u8ff0\u8077\u4f4d\u4ee5\u5408\u7d04\u5236\u8058\u8acb\u3002\nEnquiries\n\u6709\u610f\u8005\u8acb\u9644\u5c65\u6b77\u4e26\u8a3b\u660e\u8981\u6c42\u5f85\u9047\u96fb\u90f5\u81f3 Apply Now \u6216\u90f5\u5bc4\u5230\u4e5d\u9f8d\u7aa9\u6253\u8001\u9053 54 \u865f\u884c\u653f\u90e8\u6536 (\u4fe1\u5c01\u9762\u5fc5\u9808\u8a3b\u660e\u7533\u8acb\u8077\u4f4d\u540d\u7a31 / \u7de8\u865f\uff0c\u5408\u5247\u7d04\u898b)\u3002\n\n\u7db2\u5740 : http://www.yang.org.hk\n\n\u7533\u8acb\u4eba\u63d0\u4f9b\u4e4b\u5168\u90e8\u8cc7\u6599\u7d55\u5c0d\u4fdd\u5bc6\u53ca\u50c5\u4f9b\u62db\u8058\u4e4b\u7528\u3002\u53ea\u6709\u5165\u570d\u7684\u7533\u8acb\u8005\u5c07\u88ab\u9080\u8acb\u53c3\u52a0\u9762\u8a66\u3002\u7533\u8acb\u4eba\u5982\u5728\u5169\u500b\u6708\u5167\u672a\u7372\u672c\u6a5f\u69cb\u56de\u8986\uff0c\u8acb\u8996\u4f5c\u8a72\u9805\u7533\u8acb\u4e0d\u88ab\u63a5\u7d0d\uff0c\u672c\u6a5f\u69cb\u53ea\u4fdd\u7559\u7533\u8acb\u4eba\u4e4b\u5168\u90e8\u8cc7\u6599\u6700\u591a\u516d\u500b\u6708\u3002\n\n", "employment_types": ["Full Time", "Permanent"], "selling_points": ["Promotion of physio / rehab products", "Prospective career development and training", "Flexible working hour, near MTR, 5 days work"], "locations": ["Kwai Hing"], "categories": ["Medical Services", "Pharmaceutical", "Sales, CS & Business Devpt", "Wholesale", "Others", "Student / Fresh Graduate / No Experience"], "post_time": "2022-01-11T01:53:07Z", "salary": {"currency": null, "max": null, "min": null, "period": "monthly", "term": null}, "salary_visible": false, "title_keywords": ["product specialist", "medical representative"], "responsibilities": ["website"], "requirements": {"degrees": ["certificate", "diploma"], "majors": [], "languages": [], "language_level": [], "hard_skills": [], "soft_skills": [], "languages_combined": []}, "experience_required": {"duration": [], "field": []}}, {"job_id": "100003009033650", "location_code": "hk", "company": "ACP Medication Management Centre", "job_title": "Dispenser / Pharmacy Assistant \u914d\u85e5\u54e1 / \u85e5\u623f\u52a9\u7406", "description": "\u5de5\u4f5c\u8077\u8cac:\n\n\u76e3\u6e2c\u751f\u7522\u6d41\u7a0b\u53ca\u7522\u54c1\u8cea\u91cf\n\u586b\u5beb\u76f8\u95dc\u8a18\u9304\u53ca\u4e00\u822c\u6587\u66f8\u5de5\u4f5c\n\n\u5165\u8077\u689d\u4ef6:\n\n\u4e2d\u4e94\u7a0b\u5ea6\n\u61c2\u8b80\u5beb\u4e2d\u6587\n\u7565\u61c2\u8b80\u5beb\u82f1\u6587\n\u5177\u98df\u54c1\u88fd\u9020\u696d\u6216GMP\u7d93\u9a57\u512a\u5148\n\u4e94\u5929\u5de5\u4f5c, \u65e9\u66f4 (\u5de5\u4f5c\u6642\u9593: 8:30-13:00)\n\nJob responsibilities:\n\nPerform routine inspection on various stages of the production line to implement GMP policy\nAssist in maintaining the documentation system\nAssist in other ad-hoc project and other QA-related duties\n\nRequirements:\n\nF.5 or above\nAttention to details, hard-working and being able to work under pressure;\nStrong communication skill\nMinimum of 2\u00a0years relevant experience;\nExperience in\u00a0pharmaceutical\u00a0is preferred;\n5 days work week, morning Shift (Working time: 8:30-13:00)\n\n\n\u6709\u610f\u8005\u8acb\u5c07\u5c65\u6b77\u53ca\u671f\u671b\u5f85\u9047\u3001\u53ef\u5230\u4efb\u65e5\u671f\u6309APPLY NOW\u7533\u8acb\u3002\n\n\u6240\u6536\u96c6\u7684\u500b\u4eba\u8cc7\u6599\u53ea\u9069\u7528\u65bc\u62db\u8058\u53ca\u7504\u9078\u7528\u9014\u3002\u5728\u4f7f\u7528\u6c42\u8077\u8005\u6240\u63d0\u4f9b\u7684\u500b\u4eba\u8cc7\u6599\u6642\uff0c\u50f1\u4e3b\u6703\u56b4\u683c\u9075\u5b88\u5176\u500b\u4eba\u8cc7\u6599\u653f\u7b56\u7684\u898f\u5b9a\u3002\u6839\u64da<<\u500b\u4eba\u8cc7\u6599(\u79c1\u4eba)\u689d\u4f8b>>\u4f60\u6709\u6b0a\u8981\u6c42\u67e5\u95b1\u6216\u66f4\u6539\u4f60\u7684\u500b\u4eba\u8cc7\u6599\u3002\u5982\u4f60\u6b32\u884c\u4f7f\u9019\u9805\u6b0a\u5229\uff0c\u8acb\u5c07\u4f60\u7684\u8981\u6c42\u4ee5\u66f8\u9762\u5411\u4eba\u529b\u8cc7\u6e90\u90e8\u63d0\u51fa\u3002\n\nWe offer attractive remuneration package including medical scheme, discretionary year-end bonus etc. Interested parties please send full resume with salary expectation and availability by click \"Apply Now\". Only shortlisted candidates will be interviewed.\n\nSynco (H.K.) Ltd\u00a0is an Equal Opportunities Employer. Personal data provided by job applicants will be used strictly in accordance with our personal data policy and for recruitment purposes only. We aim to respond to successful applicants within 8 weeks and related information will be kept in our file for up to 12 months for other suitable vacancies in our organization and thereafter destroyed.\u00a0", "employment_types": ["Full Time", "Permanent"], "selling_points": [], "locations": ["Shatin Area"], "categories": ["Medical Services", "Others", "Pharmaceutical", "Others", "Student / Fresh Graduate / No Experience"], "post_time": "2022-01-10T01:28:37Z", "salary": {"currency": null, "max": null, "min": null, "period": "monthly", "term": null}, "salary_visible": false, "title_keywords": ["dispenser", "\u914d\u85e5\u54e1", "assistant"], "responsibilities": ["documentation", "ad-hoc", "maintaining", "inspection"], "requirements": {"degrees": [], "majors": [], "languages": [], "language_level": [], "hard_skills": [], "soft_skills": ["communication skill", "hard-working", "attention to details", "work under pressure"], "languages_combined": []}, "experience_required": {"duration": ["minimum of 2 years"], "field": ["pharmaceutical", "relevant experience"]}}, {"job_id": "100003009036217", "location_code": "hk", "company": "Zuellig Pharma Limited", "job_title": "Order Admin Coordinator", "description": "Job Highlight\n\n-\u00a0 Support, Direct, Manage overall Warehouse & Logistics Operation in accordance to Pharmaceutical Warehouse Standard\n\n-\u00a0 Report/Work with to Senior Warehouse Manager & Management\n\n\u00a0Key Responsibilities\n\n-\u00a0 Manage the daily operation (includes logistics operations) of a pharmaceutical warehouse\n\n-\u00a0 Ensure accurate, smooth operation of the entire supply chain management from importation of stock, picking of goods to delivery to end users\n\n-\u00a0 Oversee and ensure accurate stock management in entire supply chain\n\n-\u00a0 Assist with and Handle routine warehouse audits\n\n-\u00a0 Work with warehouse, logistics and sales team on stock management, orders and shipment update.\n\nQualifications, Skills\n\nPrior Warehouse experience\nPrior pharmaceutical warehouse experience will be considered with highest priority\nForm 5 or DSE above\nBasic English\nBasic Computer Operation Knowledge\nAble to handle physical goods movement and fork lift\nGood problem solving skill, Team Player\nAble to work independently as well as with team members\n\nInterested parties please send full resume with current & expected salary", "employment_types": ["Full Time", "Permanent"], "selling_points": [], "locations": ["Tsing Yi"], "categories": ["Sales, CS & Business Devpt", "Customer Service - Supervisor / Officer", "Transportation & Logistics", "Inventory / Warehousing", "Medical Services", "Pharmaceutical"], "post_time": "2022-01-10T09:41:44Z", "salary": {"currency": null, "max": null, "min": null, "period": "monthly", "term": null}, "salary_visible": false, "title_keywords": ["coordinator", "admin"], "responsibilities": ["management", "stock management", "operations", "daily operation", "logistics", "sales team", "audits", "report"], "requirements": {"degrees": ["form 5", "dse"], "majors": [], "languages": ["english"], "language_level": ["basic"], "hard_skills": ["problem solving", "basic", "computer operation knowledge"], "soft_skills": ["work independently", "team player", "smooth", "problem solving skill", "accurate"], "languages_combined": [{"language": "english", "language_level": ["basic"]}]}, "experience_required": {"duration": [], "field": ["pharmaceutical"]}}, {"job_id": "100003009034766", "location_code": "hk", "company": "Health Plus Physiotherapy Centre", "job_title": "\u8a3b\u518a\u7269\u7406\u6cbb\u7642\u5e2b", "description": "Key Roles and Responsibilities\n\nPerform sampling and chemical testing on Purified water, Raw materials, intermediates, finished products and stability samples\nUndertake maintenance and calibration of related analytical instruments\nRevision of SOP documents\n\nQualifications and Experience\n\n\u00a0In Science subjects, preferably in Pharmaceutical Science/Chemistry related discipline\n1-2 years working experience in Quality Control of pharmaceutical or commercial laboratory is preferred\nFamiliar with pharmacopeia (BP/USP/CP) and GMP requirements as per FDA, PIC/S\nProficiency in MS Words and Excel\nSelf-motivated and responsible\nGood command of English and Chinese\nFresh graduates are also considered\n\nHow to Apply\n\nYou are invited to send in your application and CV stating the position\u00a0(with reference number)\u00a0you are applying for together with your current and expected salary, apply via JobsDB\u00a0on or before 9 February 2022.\n\nKaren Pharmaceutical Company Limited is an Equal Opportunities Employer. Personal data provided by job applicants will be used strictly in accordance with our personal data policy and for recruitment purposes only. We aim to respond to successful applicants within 8 weeks and related information will be kept in our file for up to 12 months for other suitable vacancies in our organization and thereafter destroyed.", "employment_types": ["Full Time"], "selling_points": [], "locations": ["Yuen Long"], "categories": ["Medical Services", "Specialist", "Others", "Pharmaceutical"], "post_time": "2022-01-10T04:12:06Z", "salary": {"currency": null, "max": null, "min": null, "period": "monthly", "term": null}, "salary_visible": false, "title_keywords": [], "responsibilities": ["maintenance", "testing", "recruitment", "quality control", "personal data"], "requirements": {"degrees": [], "majors": [], "languages": ["english", "chinese"], "language_level": ["good command"], "hard_skills": ["excel", "maintenance", "ms words"], "soft_skills": ["self-motivated", "responsible"], "languages_combined": [{"language": "english", "language_level": ["good command"]}, {"language": "chinese", "language_level": ["good command"]}]}, "experience_required": {"duration": ["1-2 years"], "field": ["pharmaceutical", "quality control", "commercial laboratory"]}}, {"job_id": "100003009046699", "location_code": "hk", "company": "Healthlink Holdings Limited", "job_title": "Product Specialist / Medical Sales Executive - Medical Device", "description": "Job Descriptions:\n\nActively pursue growth opportunities, by developing new customers and maintaining good relationships with existing customers.\nPreparing customer quotations, sales plans, reports and implement marketing and sales strategies.\nTo conduct specific sales and marketing activities of consumer health care products / rehabilitation equipments / medical devices to target clients.\nResponsible for marketing, sales and after sales service of medical, rehabilitation and health products.\nMaintain and establish good relationship with clients.\nHelp organized seminars and exhibitions for the promotion of the products.\n\n\u00a0Job Requirements:\n\nUniversity graduate (Science subjects preferable) OR lower academic level but solid sales working experience.\nExperience not essential.\nGood command of both spoken and written in English and Chinese (Cantonese and Mandarin)\nGood communication and presentation skills\nCan work independently and under pressure\nResponsible, well organized, willing to learn, hardworking and a good team player\n\nWe offer attractive salary package, commission, 5 days work week, flexible working hours, discretionary bonus, traveling allowance, continuous professional training, medical scheme, staff purchase discount and education allowance etc.\n\nInterested parties, please send\u00a0CV with current & expected salary (is a must)\u00a0and our ref. no. to email to us (Attention:\u00a0Ms. Annie Tse) by clicking \u2018Apply Now\u2019.\n\nAll\u00a0personal data collected will be treated in strict confidence and used for recruitment purpose only.", "employment_types": ["Full Time", "Permanent"], "selling_points": ["Work with high-end medical technology", "5 Days work, Birthday Leave, Flexible working time", "Exposure with multiple European companies"], "locations": ["Wong Tai Sin Area"], "categories": ["Sales, CS & Business Devpt", "Business Development", "Medical Services", "Pharmaceutical", "Direct Sales"], "post_time": "2022-01-13T18:54:27Z", "salary": {"currency": "HKD", "max": 29999, "min": 20000, "period": "monthly", "term": null}, "salary_visible": true, "title_keywords": ["product specialist", "sales executive"], "responsibilities": ["rehabilitation", "maintaining", "developing", "good relationship", "maintain", "reports", "sales plans"], "requirements": {"degrees": ["university graduate"], "majors": ["science"], "languages": ["cantonese", "english", "chinese", "mandarin"], "language_level": ["good command"], "hard_skills": ["scheme"], "soft_skills": ["flexible", "work independently", "good team player", "under pressure", "responsible", "well organized", "willing to learn", "communication", "presentation skills", "hardworking"], "languages_combined": [{"language": "cantonese", "language_level": ["good command"]}, {"language": "english", "language_level": ["good command"]}, {"language": "chinese", "language_level": ["good command"]}, {"language": "mandarin", "language_level": ["good command"]}]}, "experience_required": {"duration": [], "field": []}}, {"job_id": "100003009031056", "location_code": "hk", "company": "Guerbet Asia Pacific Limited", "job_title": "Regulatory Affairs Specialist", "description": "\u5982\u679c\u60a8\u52c7\u65bc\u63a5\u53d7\u8001\u4eba\u8907\u96dc\u85e5\u7642\u7684\u6311\u6230\uff0c\u8207\u7d93\u9a57\u8c50\u5bcc\u7684\u85e5\u5291\u5e2b\u4e26\u80a9\u505a\u597d\u85e5\u7269\u7ba1\u7406\uff0c\u6b61\u8fce\u60a8\u52a0\u5165\u660e\u5fc3\uff0c\u6211\u5011\u6703\u7d66\u60a8\u4e00\u5957\u6709\u7cfb\u7d71\u7684\u57f9\u8a13\uff0c\u78e8\u7df4\u60a8\u6210\u70ba\u7cbe\u82f1\uff0c\u4ec0\u81f3\u63a8\u85a6\u53ca\u8cc7\u52a9\u60a8\u5230\u570b\u5916\u9032\u4fee\uff0c\u6210\u70ba\u85e5\u5291\u5e2b\uff0c\u70ba\u4eba\u53e3\u8001\u5316\u7684\u9999\u6e2f\u4f5c\u51fa\u6b63\u9762\u7684\u8ca2\u737b\u3002\n\n\u6b61\u8fce\u7562\u696d\u751f\u6216\u6709\u5fd7\u4eba\u58eb\u52a0\u660e\u5fc3\uff0c\u6709\u4ee5\u4e0b\u5176\u4e2d\u4e00\u500b\u5c08\u696d\u8cc7\u683c\u53ef\u7372\u512a\u5148\u8003\u616e:\n\nIVE / Caritas HDPD, or\nBPharm/MPharm/PharmD, or\nAn overseas qualified pharmacy technician\n\n\u5982\u5de5\u4f5c\u671f\u9593\u8868\u73fe\u51fa\u8272\uff0c\u6c92\u6709\u5c08\u696d\u8cc7\u683c\u7684\u54e1\u5de5\u4e5f\u6709\u6a5f\u6703\u88ab\u63a8\u85a6\u53bb\u63a5\u53d7\u5c08\u696d\u6559\u80b2\uff0c\u6210\u70ba\u6b63\u898f\u914d\u85e5\u54e1\u3002\n\n\u660e\u5fc3\u6240\u6709\u6b63\u8077\u54e1\u5de5\u90fd\u6703\u4eab\u6709\u91ab\u7642\u4fdd\u969c\uff0c\u5e74\u5047\uff0c\u9032\u4fee\u6d25\u8cbc\uff0c\u53ca\u5176\u5b83\u798f\u5229\u3002\u00a0\n\n\u6709\u5fd7\u8005\u8acb\u96fb\u90f5\u5c65\u6b77\u81f3\u7c21\u5c0f\u59d0\u6536\u3002", "employment_types": ["Full Time", "Permanent"], "selling_points": ["MNC & international working environment", "Flexible working hour & work life balance", "Drug & medical device registrations"], "locations": ["Hung Hom"], "categories": ["Sciences, Lab, R&D", "Life Science", "Medical Services", "Pharmaceutical", "Others"], "post_time": "2022-01-07T08:53:27Z", "salary": {"currency": null, "max": null, "min": null, "period": "monthly", "term": null}, "salary_visible": false, "title_keywords": ["specialist"], "responsibilities": [], "requirements": {"degrees": [], "majors": [], "languages": [], "language_level": [], "hard_skills": [], "soft_skills": [], "languages_combined": []}, "experience_required": {"duration": [], "field": []}}]