[{"job_id": "100003009053827", "location_code": "hk", "company": "Louis Vuitton Hong Kong", "job_title": "Stylist", "description": "PRIMARY OBJECTIVE\n\nThis position will partner closely with our retail team to elevate the Louis Vuitton client experience through styling services and support them in exploring our different categories as a lifestyle connoisseur. As a trusted partner to the retail leaders, you will deliver strong business partnership through trend analysis, styling advice and training.\n\nJOB DUTIES & RESPONSIBILITIES\n\nSupport the retail team in delivering genuine and excellent client experience through on-the-floor styling advice to complete the Louis Vuitton silhouette.\nDeliver engaging, interactive training to our retail team on fashion trends and styling methodology.\nUnderstand and study our client base unique to each store to become a powerful partner to our retail team.\nPartner with Retail and Client Development teams to provide on-site styling support during exclusive events.\nDeliver frequent updates on trends and news on the current fashion landscape, maintain the market knowledge of our retail team.\u00a0\nShare best practices, resources, and inspirational stories amongst stores to create excitement and raise awareness on our products.\nAct as the ambassador of Vuitton products and maintain deep knowledge of our design inspiration by our designers.\n\nKEY REQUIREMENTS & COMPETENCIES\n\nPassion in Louis Vuitton, and deep knowledge of the fashion industry\nExcellent interpersonal and communication skills, confident in sharing conviction\nAgile, detailed-oriented and a team-player\nStrong business acumen\nFluent in English, Cantonese and Mandarin an advantage", "employment_types": ["Full Time", "Permanent"], "selling_points": ["Passionate in Louis Vuitton", "Deep knowledge of the fashion industry", "Deliver genuine and excellent client experience"], "locations": ["Not Specified"], "categories": ["Design", "Fashion", "Sales, CS & Business Devpt", "Others"], "post_time": "2022-01-17T07:35:22Z", "salary": {"currency": null, "max": null, "min": null, "period": "monthly", "term": null}, "salary_visible": false, "title_keywords": [], "responsibilities": ["maintain", "client base", "teams", "design"], "requirements": {"degrees": [], "majors": [], "languages": ["cantonese", "english", "mandarin"], "language_level": ["advantage", "fluent"], "hard_skills": ["agile", "acumen"], "soft_skills": ["confident", "communication skills", "agile", "passion in", "team-player", "deep", "business acumen", "interpersonal", "detailed"], "languages_combined": [{"language": "cantonese", "language_level": ["advantage", "fluent"]}, {"language": "english", "language_level": ["advantage", "fluent"]}, {"language": "mandarin", "language_level": ["advantage", "fluent"]}]}, "experience_required": {"duration": [], "field": []}}, {"job_id": "100003009054879", "location_code": "hk", "company": "Orienta Lab Limited", "job_title": "Graphic Designer", "description": "Business Sector:\u00a0\u00a0Crypto Art & NFT\u00a0\n\n\nLooking for .....\n\nFull-time/Part-time :\u00a0 \u00a0 \u00a0Graphic Designer\n\nJob Description:\n\nWe\u2019re looking for a creative and enthusiastic Graphic Designer to help us with all kinds of materials designing work.\n\nIn this role, you will be responsible for the design of various types of digital artworks, posters and other project propaganda visual materials. You will participate in brand crossover, promote the project, do the time and cost control and risk management. Work closely with the company's brand to efficiently implement the creative ideas and designs of the projects and planning requirements.\n\nThe role requires a passion for our mission and an eagerness to roll up your sleeves. Besides, it involves the creativity of activity planning, certain understanding of crypto art and popular culture.\n\nRequirements:\nMust have:\n\n1\u3001Major in visual art related fields or rich experience in visual design;\n\n2\u3001Love design, rich imagination, and keen on current design trends.\n\n3\u3001Have certain design ability and good visual aesthetics, and can skillfully use PS, AI and other design software;\n\n4\u3001Familiar with digital art, good marketing and brand building ability, cost control and management awareness, and unique understanding of brand marketing.\n\n5\u3001Strong learning ability, innovation ability, teamwork ability and pressure resistance.\n\n6\u3001Good communication skills, punctual, detailed-minded, hardworking and responsible\u00a0\n\nPlease attach your portfolio when submitting your resume.\n\nNice to have:\nExtra:\n\n-Design experience in other NFT projects\n-Familiarity with nowdays NFTs\n\n-Outstanding performance in one or more abilities such as illustration, animation ,etc. are preferred\n\n________________________________________________________________________\n\u00a0Salary:\u00a0Negotiable\n\nWatsapp: 63671819 / 56912649\nWechat: TYJBRIAN /\u00a054302895\n\nCompany address: 10/F Infotech Centre, 21 Hung To Road, Kwun Tong, HK", "employment_types": ["Full Time", "Part Time", "Permanent", "Temporary", "Contract", "Internship", "Freelance"], "selling_points": ["Creative contents and marketing purpose", "After effects, Illustrator, Premier Pro, Photoshop", "Experience in sci-fi, anime, fantasy"], "locations": ["Ngau Tau Kok"], "categories": ["Design", "Fashion", "Graphics", "Multi-media"], "post_time": "2022-01-17T16:21:10Z", "salary": {"currency": null, "max": null, "min": null, "period": "monthly", "term": null}, "salary_visible": false, "title_keywords": ["graphic designer"], "responsibilities": ["management", "creative ideas", "designing", "design", "cost control", "visual", "planning"], "requirements": {"degrees": [], "majors": [], "languages": [], "language_level": [], "hard_skills": ["ai", "nice", "wechat", "visual design", "illustration"], "soft_skills": ["communication skills", "learning ability", "responsible", "keen", "teamwork", "unique", "hardworking", "detailed"], "languages_combined": []}, "experience_required": {"duration": [], "field": ["related", "design"]}}, {"job_id": "100003009052534", "location_code": "hk", "company": "BW Global (HK) Limited", "job_title": "3D Technical Support and Training Specialist (Fashion Software)", "description": "About Us:\n\nBrowzwear is the leading provider of 3D fashion design, development, and merchandising solutions. Our mission is to revolutionize the apparel industry with our truly disruptive 3D technology, providing the tools needed to achieve that goal. We work with some of the biggest and most well-known global companies in the industry.\n\nOur Global Learning and Technical Support Department turn 2D patterns into 3D garments and problems into solutions. Members of our team have achieved expert user status in our Browzwear suite of tools and are excited to share their passion and technical knowledge with others. Our purpose is to help users onboard into 3D technology and maximize their productivity when it comes to Browzwear 3D product creation.\n\nWe are looking for a 3D Technical Support and Training Specialist to join our team.\n\nWhat We Do:\n\nAssist our clients with their technical questions, concerns, issues and celebrations via email, phone or chat\nDeliver fun and inspiring technical training via web, e-learning or in-person\nMaintain continuous mastery of our software products, constantly learning and incorporating new features/functions and new products into our daily work and expertise\nCollaborate with our Product Managers and Developers to share user insights, bugs and feature requests that will influence our products\u2019 future\nWork closely with our Sales and Client Success teams to understand our client's needs, prepare the right technical service, and deliver engaging experiences\n\u00a0Participate in client and internal professional services projects including fabric digitization, 3D garment creation and custom avatar creation\nAssist sales presentation and follow up being the technical expert who provides technical information, rational analysis, problem-solving, and business case to convince buyers that Browzwear products and services meet their business needs.\n\nWho You Are:\n\nCreative & persistent problem solver, easily thinking outside the box for new solutions\nExcellent communicator via verbal, written or visual methods remotely or in-person\nPassionate about customer satisfaction, have extra empathy for our software users and willing to go the extra mile to help them\nAffinity for technology and quick to pick up new software and tools\nStrong attention to detail while still seeing the big picture\nHigh standards for personal quality of work\nPatient & collected under pressure with a strong ability to multi-task and work in a fast-paced environment\nTeam player with initiative, willingness to listen and learn, and drive to collaborate and share among teammates, contributing to an inspiring team culture\n\nRequirements:\n\n1-3 years relevant fashion industry experience, understanding the design and development process OR 1-3 years relevant customer service/support experience, understanding issue and relationship management\nDiploma or Bachelor\u2019s Degree in Fashion Design, Apparel Technical Design, 3D Design or related field\nExperience with VStitcher or any apparel 3D technology\nProficiency English and Mandarin language preferred\nAbility and willingness for frequent travel\n\nExtra Credit:\n\nExperience with 2D apparel pattern making software\nExperience with 3D design software and production pipeline\nRelevant customer service experience, understanding issue and relationship management\n%MCEPASTEBIN%", "employment_types": ["Full Time"], "selling_points": ["Fashion/Customer Support/Relationship Management", "Education: Fashion, Apparel Technical or 3D Design", "1-3 years relevant industry experience"], "locations": ["Lai Chi Kok"], "categories": ["Design", "Fashion", "Information Technology (IT)", "Support", "Sales, CS & Business Devpt", "Technical Sales / Sales Engineer"], "post_time": "2022-01-17T03:19:50Z", "salary": {"currency": null, "max": null, "min": null, "period": "monthly", "term": null}, "salary_visible": false, "title_keywords": ["technical support", "specialist"], "responsibilities": ["collaborate with", "collaborate", "management", "software", "technical support", "analysis", "customer service experience", "merchandising", "teams", "design", "quality", "maintain", "customer service", "visual"], "requirements": {"degrees": ["diploma", "degree", "bachelor"], "majors": ["design"], "languages": ["english", "mandarin"], "language_level": ["proficiency"], "hard_skills": ["web", "fun", "problem-solving", "analysis", "goal", "go"], "soft_skills": ["initiative", "under pressure", "problem solver", "multi-task", "fast-paced environment", "persistent", "problem-solving", "learning", "team player", "inspiring", "attention to detail", "customer service", "patient", "communicator", "creative", "empathy", "presentation", "passionate about"], "languages_combined": [{"language": "english", "language_level": ["proficiency"]}, {"language": "mandarin", "language_level": ["proficiency"]}]}, "experience_required": {"duration": ["1-3 years"], "field": ["development", "management", "customer service", "design"]}}, {"job_id": "100003009053511", "location_code": "hk", "company": "Bape Hong Kong Limited", "job_title": "Fashion Designer", "description": "Accountabilities \u2013 Key Result Areas\n\n\nAssist Senior Designer in completing the whole process of the development from themes and concept, presentation of styling, sketches, fitting session until pre-production sample\nResearch of seasonal themes, fabrications and material and colors etc.\nWork closely with merchandising and factories to facilitate development processes and schedules from product development, sourcing of fabrics and trims, sample fitting, etc.\nAssist preparations of seasonal design presentations to buyer and frontline operations\nExperience / Qualification Requirements\n\n\nDegree holder in design related discipline\n3-4 years solid experience in fashion design\nBe passionate about the brand\u2019s identity, with personal charisma and visions in international fashion trend\nAbility to research and apply market information\nCreative, communicative and be able to collaborate with business teams to achieve brand objectives\n\nCompetitive remuneration and benefit package will be offered to the right candidate. Please submit your application by clicking \"Apply Now\" below.\n\n\n\nAll data collected is for recruitment purpose only.", "employment_types": ["Full Time"], "selling_points": ["3-4 years solid experience in fashion design", "Complete the whole process of the development", "Fresh graduate will also be considered"], "locations": ["Southern Area"], "categories": ["Design", "Fashion", "Graphics", "Others"], "post_time": "2022-01-17T07:04:31Z", "salary": {"currency": null, "max": null, "min": null, "period": "monthly", "term": null}, "salary_visible": false, "title_keywords": ["fashion designer"], "responsibilities": ["collaborate with", "market information", "data", "schedules", "operations", "merchandising", "teams", "sketches", "design", "presentations", "recruitment", "pre-production"], "requirements": {"degrees": ["degree holder"], "majors": ["design"], "languages": [], "language_level": [], "hard_skills": ["presentations"], "soft_skills": ["creative", "presentation", "passionate about"], "languages_combined": []}, "experience_required": {"duration": ["3-4 years"], "field": ["fashion design"]}}, {"job_id": "100003009052716", "location_code": "hk", "company": "Sportsdirect.com (Asia) Limited", "job_title": "Graphics Designer", "description": "SportsDirect.com (Asia) Limited is the newly established division of the Sports Direct International Plc Group. Looking to replicate their success in the EMEA region, the new division is looking to recruit an experienced Graphics Designer.\n\nSportsDirect.com is the UK\u2019s largest sporting goods retailer by revenue. We are proud to operate a diverse portfolio of sports, fitness, fashion and lifestyle retail fascia\u2019s throughout Europe, the U.S and Malaysia and are looking to expand on our success across Asia. We aspire to be a leading sports and lifestyle retailer internationally and need committed and capable candidates to help us achieve our long term strategy.\n\nWe are currently searching for an experienced Graphics Designer to join us in our Hong Kong Division. Working as a Graphics Designer, you would be required to liaise with relevant Group departments in the UK and suppliers across China and Asia.\n\nJob Responsibilities:\n\nResponsible for creative concept development and handle all stages of design includes but is not limited to the following:\n\nBrand Guides;\n\nCorporate website;\n\nSocial media content (Facebook, Instagram, eDM, Google ad, etc.);\n\nSales kit and POP materials;\n\nProducts retouching and mock-ups;\n\nOnline store visual (Web banner, products page, etc.);\n\nManage ad-hoc projects as assigned.\n\nHandle brand performance and deal with designs on:\n\nRenovate based on the market trend and consumer insights\n\nCommunicate with internal and external teams to ensure the great performance of campaigns, advertisements and joint promotion opportunities and POP development\n\nJob Requirements:\n\nDiploma or above in Graphic Design/ Multimedia/ Creative Media or other related disciplines;\n\n5yrs+ graphics and web development experience is preferred;\n\nExceptional skills in Adobe Suite (Illustrator, Photoshop, InDesign) in Mac environment;\n\nExcellent at preparing presentations and guidelines;\n\nProficient in animation and video editing is a plus;\n\nVisual merchandising experience is an advantage;\n\nFluency in English, both written and verbal;\n\nSomeone not afraid to raise up and explore different possibilities;\n\nProven great communication skills knows how to cooperate with different team members and between different departments;\n\nAbility to work in a fast-paced, always shifting environment and taking on new challenges.\n\nIf you are a team player with excellent attention to detail and plenty of initiative, this is an excellent opportunity to develop your career within our Group.\u00a0", "employment_types": ["Full Time"], "selling_points": ["Lifestyle & Sports", "Gaphics Design", "Sportswear Design"], "locations": ["Kowloon Bay"], "categories": ["Design", "Fashion"], "post_time": "2022-01-17T03:47:14Z", "salary": {"currency": null, "max": null, "min": null, "period": "monthly", "term": null}, "salary_visible": false, "title_keywords": ["designer"], "responsibilities": ["communicate with", "retouching", "pop materials", "consumer insights", "edm", "advertisements", "mock-ups", "teams", "website", "design", "social media content", "visual", "facebook", "ad-hoc projects", "sales kit"], "requirements": {"degrees": ["diploma or above"], "majors": ["related disciplines", "graphic design", "creative media"], "languages": ["english"], "language_level": ["fluency"], "hard_skills": ["graphics", "web development", "mac environment", "plus", "visual merchandising", "indesign", "illustrator", "presentations", "adobe", "multimedia", "animation and video editing", "photoshop"], "soft_skills": ["communication skills", "attention to detail", "team player", "creative", "initiative"], "languages_combined": [{"language": "english", "language_level": ["fluency"]}]}, "experience_required": {"duration": [], "field": ["development", "merchandising"]}}, {"job_id": "100003009053941", "location_code": "hk", "company": "Lai's Knitters Limited", "job_title": "FASHIION DESIGNER / KNITWEAR DESIGNER", "description": "Job Description:\n\nManage and develop the in-house collection\nResearch on the fashion and colour trend\nDevelop and design new stitches\nReview and comment on samples\nKeep track on sample and development status to ensure on-time delivery\nCoordinate necessary materials for sampling\nDevelop trend board for presentation\nAd-hoc brand related duties\n\nJob Requirements:\n\nPolyU, HKDI or CITA\u00a0graduate in Fashion Design or related discipline, majoring in knit would be an advantage.\u00a0\nMinimum 3 years\u2019 solid experience in sweater design or merchandising\nStrong technical knowledge in sweater knit\nGood sense of styling\u00a0and\u00a0fitting\nGood command in English and Mandarin\nWilling to travel to China\nStrong organizing and analytical skills, energetics and willing to work as a team\nAmbitious in sweater knit\nFresh graduate will also be considered as Assistant Fashion Designer\n\nInterested parties please send your full resume with current and expected salary by\u00a0fax to 2325 3225 or by email via jobsdb.\n\n\n\n\nPersonal data will be used for recruitment purpose only.", "employment_types": ["Full Time", "Permanent"], "selling_points": [], "locations": ["Kowloon City Area"], "categories": ["Design", "Fashion", "Manufacturing", "Garment / Textile", "Merchandising & Purchasing", "Sweater"], "post_time": "2022-01-17T07:48:37Z", "salary": {"currency": null, "max": null, "min": null, "period": "monthly", "term": null}, "salary_visible": false, "title_keywords": ["designer"], "responsibilities": ["ad-hoc", "review", "design", "develop", "coordinate"], "requirements": {"degrees": ["fresh graduate"], "majors": [], "languages": ["english", "mandarin"], "language_level": ["good command"], "hard_skills": ["analytical skills"], "soft_skills": ["work as a team", "analytical skills"], "languages_combined": [{"language": "english", "language_level": ["good command"]}, {"language": "mandarin", "language_level": ["good command"]}]}, "experience_required": {"duration": ["minimum 3 years"], "field": ["merchandising", "design"]}}, {"job_id": "100003009052210", "location_code": "hk", "company": "Prudential Hong Kong Limited", "job_title": "Sales & Marketing Executive - 5 Days - Excellent Benefits - (14-25K)", "description": "Requirements :\n\nHigher Dip / Bachelor degree holder or above in all disciplines\nThose with lesser qualification will also be considered\nFresh Graduate will also be considered\nExcellent communication and presentation skills\nSelf-disciplined, self-motivated, proactive and hardworking\n\nResponsibilities :\n\nTo assist the Sales Department to implement after-sales support service\nBasic salary plus commission offered\nProactively identify clients\u2019 needs and development\nMaintain good account relationship with existing and potential clients;\n\nWe Offer :\n\nAttractive remuneration package and staff benefits\nOpportunities for professional and personal development\nCreative & friendly working environment\nFive-days work\nDouble Pay\nAnnual Leave\nPaid Sick Leave, Medical Benefits, Year End Bonus\n\nInterested parties please send your applicant letter or resume by clicking \" Apply Now \" button.", "employment_types": ["Full Time", "Permanent"], "selling_points": [], "locations": ["Not Specified"], "categories": ["Design", "Fashion", "Education", "Tutor / Instructor", "Hospitality / F & B", "Hospitality / Hotel Services"], "post_time": "2022-01-17T02:28:25Z", "salary": {"currency": null, "max": null, "min": null, "period": "monthly", "term": null}, "salary_visible": false, "title_keywords": ["sales & marketing executive"], "responsibilities": ["maintain", "assist the sales"], "requirements": {"degrees": ["dip", "fresh graduate", "bachelor degree holder"], "majors": [], "languages": [], "language_level": [], "hard_skills": [], "soft_skills": ["self-motivated", "communication", "presentation skills", "proactive", "hardworking"], "languages_combined": []}, "experience_required": {"duration": [], "field": []}}, {"job_id": "100003009051227", "location_code": "hk", "company": "Easy Job Centre", "job_title": "Fashion Design / Senior Fashion Designer", "description": "1 Post for Intimate\n1 Post for Woven / Knit / Sweater\n1 Post for Ladies\n1 Post for Men's\n1 Post for Sportswear\n\nResponsibilities\n\n\nResponsible for design and development of apparel items\nProvide directions and ideas on all design issues including costing, fashion trend research on colors, fabrication and accessories, etc.\nFollow up the entire workflow of the development from themes and concept, presentation of styling, sketches, fitting session and sampling\nCoordinate and work closely with Buyers, Merchandisers and other related parties\n\nRequirements\n\nDegree or Diploma holder in Fashion Design or related discipline\nMinimum 2-6 years of fashion design experience\nStrong awareness of market needs and fashion trend\nStrong creativity with good fashion color sense and knowledge of seasonal trends, themes, color, materials, styling and fit\nSelf-motivated, energetic, creative, with good design sense and with the ability to work independently\nProficiency in Photoshop, Illustrator, InDesign, after effect\nExcellent command in both spoken and written English and Chinese including Mandarin\n\nInterested parties, please send your resume with expected salary to \"apply now\". You can also click on the website www.easyjobhk.com for more details about the company", "employment_types": ["Full Time"], "selling_points": [], "locations": ["Yau Tsim Mong Area"], "categories": ["Design", "Fashion", "Graphics", "Others"], "post_time": "2022-01-15T05:19:57Z", "salary": {"currency": null, "max": null, "min": null, "period": "monthly", "term": null}, "salary_visible": false, "title_keywords": ["fashion designer"], "responsibilities": ["coordinate", "ideas", "sketches", "design"], "requirements": {"degrees": ["diploma holder", "degree"], "majors": ["design"], "languages": ["english", "chinese", "mandarin"], "language_level": ["excellent"], "hard_skills": ["after effect", "indesign", "illustrator", "photoshop"], "soft_skills": ["self-motivated", "energetic", "creative", "work independently"], "languages_combined": [{"language": "english", "language_level": ["excellent"]}, {"language": "chinese", "language_level": ["excellent"]}, {"language": "mandarin", "language_level": ["excellent"]}]}, "experience_required": {"duration": ["minimum 2-6 years"], "field": ["fashion design"]}}, {"job_id": "100003009043936", "location_code": "hk", "company": "Yangtzekiang Garment Ltd", "job_title": "Clerk (Part-time)", "description": "Requirements\n\n-F. 5/DSE or above;\n\n-Fluent in spoken and written in English and Mandarin;\n\n-Familiar with MS Excel and MS Word\n\n\nSalary\n\nHK$60.00 per hour\n\nInterested parties, please send your full resume, with expected salary and availability by email or fax to (852) 2726 7590.\n\nCollected information is strictly for recruitment purpose.", "employment_types": ["Part Time", "Temporary"], "selling_points": [], "locations": ["Not Specified"], "categories": ["Admin & HR", "Clerical / Admin Staff", "Design", "Fashion", "Merchandising & Purchasing", "Woven / Knit"], "post_time": "2022-01-15T03:49:16Z", "salary": {"currency": null, "max": null, "min": null, "period": "hourly", "term": null}, "salary_visible": false, "title_keywords": ["clerk"], "responsibilities": [], "requirements": {"degrees": ["dse"], "majors": [], "languages": ["english", "mandarin"], "language_level": [], "hard_skills": ["ms excel", "ms word"], "soft_skills": [], "languages_combined": [{"language": "english", "language_level": []}, {"language": "mandarin", "language_level": []}]}, "experience_required": {"duration": [], "field": []}}, {"job_id": "100003009043926", "location_code": "hk", "company": "Hong Kong Knitters Limited", "job_title": "Merchandising Assistant", "description": "\u00a0Requirements\n\n- Higher Diploma or above;\n\n- Minimum\u00a02 years cut and sewn knit experience;\n\n- Fluent in spoken and written in English and Mandarin;\n\n- Familiar with MS Office\n\n- Fresh graduates will be considered\n\n- More experience will be Junior Merchandiser\n\nWe offer attractive remuneration packages including 13 months payment, medical insurance, annual leave (10~16 days), 10 days wedding leave, education allowance and good career prospects to the right candidate(s). Interested parties, please send your full resume, with expected salary and availability, fax to (852) 2726 7590.\n\nCollected information is strictly for recruitment purpose.", "employment_types": ["Full Time", "Permanent"], "selling_points": [], "locations": ["Not Specified"], "categories": ["Design", "Fashion", "Manufacturing", "Garment / Textile", "Merchandising & Purchasing", "Woven / Knit"], "post_time": "2022-01-15T03:49:16Z", "salary": {"currency": null, "max": null, "min": null, "period": "monthly", "term": null}, "salary_visible": false, "title_keywords": ["merchandising assistant"], "responsibilities": ["payment", "insurance"], "requirements": {"degrees": ["higher diploma or above"], "majors": [], "languages": ["english", "mandarin"], "language_level": ["fluent"], "hard_skills": ["ms office"], "soft_skills": [], "languages_combined": [{"language": "english", "language_level": ["fluent"]}, {"language": "mandarin", "language_level": ["fluent"]}]}, "experience_required": {"duration": ["minimum 2 years"], "field": []}}, {"job_id": "100003009045146", "location_code": "hk", "company": "G2000 (Apparel) Ltd", "job_title": "Fashion Designer - Menswear", "description": "Do you want to work in a\u00a0Young,\u00a0Fun,\u00a0and\u00a0Dynamic\u00a0Team Environment?\n\n\u00a0Do you have the\u00a0DNA\u00a0to succeed?\u00a0\n\nBe part of an Iconic \u2013 Hong Kong Brand\n\nResponsibilities:\u00a0\n\n\nDesign the line Architecture & Balance the line and upkeep a consistent brand position aiming at achieving sales growth.\n\nOversee all design, merchandising, and fabric development aspects of the line, including theme, color, fabrication, finishing, styles, price point, etc.\nConfirm styling and design details in the initial fitting session, and follow-through in subsequent fitting sessions until the pre-production sample stage.\nIdentify and serve the needs of various key markets both from a style preference and climate perspective, providing commercial yet in-trend designs.\nApprove the required Colour Standard, Lab Dip & Hand-feel\u00a0\nProvide comments on styling, concept, and color selection.\nApprove trim and accessories for bulk order production.\nPrepare Trends Script and presentation\u00a0of the collection\n\nRequirements:\n\nHigher Diploma in Fashion Design, Textile or Clothing\n\n5 years relevant experience in designing and product development of a comprehensive product range, preferably well-versed in knits or woven.\u00a0\nBe able to handle woven or knitwear collection design independently, have good fashion sense, fabric knowledge & market-oriented\nUnderstand market trends, lifestyles and customer needs for both HK and overseas markets (mainly in Asia)\nCreative with a fashion flair, yet pragmatic and highly\u00a0results-oriented\nGood communication & presentation skills as well as a leadership skill\nGood command of Cantonese, English & Putonghua\n\n\u00a0We offer:\n\nAttractive salary package\nDiscretionary Performance Bonus\nMedical Insurance\nStaff Discounts on Purchases\n5-day work week with flexible work options\nVoluntary MPF Contributions\u00a0\u00a0\n\nJOIN OUR JOURNEY.\u00a0\n\n\u00a0Experience being part\u00a0of becoming the world\u2019s most-loved apparel brand.\n\n\u00a0Only shortlisted candidates will be notified. If you are not contacted by us within\u00a02 weeks, please consider your application unsuccessful. All personal data collected would be used for recruitment purposes only.\u00a0\n\nPlease visit our website for more information:\u00a0www.G2000.com.hk", "employment_types": ["Full Time", "Permanent"], "selling_points": ["Exp. in menswear design & development", "Good communication and coordination skills", "Good understanding of Asia markets"], "locations": ["Kwai Fong"], "categories": ["Design", "Fashion", "Others", "Merchandising & Purchasing", "Woven / Knit"], "post_time": "2022-01-13T07:18:33Z", "salary": {"currency": null, "max": null, "min": null, "period": "monthly", "term": null}, "salary_visible": false, "title_keywords": ["fashion designer"], "responsibilities": ["comments", "merchandising", "design", "pre-production", "architecture"], "requirements": {"degrees": ["diploma"], "majors": ["design"], "languages": ["cantonese", "putonghua", "english"], "language_level": ["good command"], "hard_skills": [], "soft_skills": ["independently", "communication", "presentation skills", "comprehensive", "leadership skill", "creative"], "languages_combined": [{"language": "cantonese", "language_level": ["good command"]}, {"language": "putonghua", "language_level": ["good command"]}, {"language": "english", "language_level": ["good command"]}]}, "experience_required": {"duration": ["5 years"], "field": ["product development", "relevant experience"]}}, {"job_id": "100003009043942", "location_code": "hk", "company": "Hong Kong Knitters Limited", "job_title": "Merchandiser (5 Days Work)", "description": "Requirements\n\n-Dipolma or above in Fashion & Textiles, Merchandising & Retailing is preferred;\n\n-Minimum 4 years cut and sewn knit or woven garment merchandising experience;\n\n-Previous experience in high fashion and casual wear is definitely advantage;\n\n-Excellent communication and interpersonal skill with all levels in working with customers, staff and\u00a0vendors;\n\n-Fluent in spoken and written in English, Chinese and Mandarin;\n\n-Familiar with MS Office operation\n\n-Less experience will be consider to be a Junior Merchandiser\n\nWe offer attractive remuneration packages including 13 months payment, 5 days' work, medical insurance, annual leave, wedding leave, education allowance, meal allowance and good career prospects to the right candidate(s). Interested parties, please send your full resume, with expected salary and availability, fax to (852) 2726 7590.\n\nCollected information is only for recruitment purpose.", "employment_types": ["Full Time", "Permanent"], "selling_points": [], "locations": ["Not Specified"], "categories": ["Design", "Fashion", "Manufacturing", "Garment / Textile", "Merchandising & Purchasing", "Woven / Knit"], "post_time": "2022-01-15T03:49:17Z", "salary": {"currency": null, "max": null, "min": null, "period": "monthly", "term": null}, "salary_visible": false, "title_keywords": ["merchandiser"], "responsibilities": ["communication", "payment", "insurance", "merchandising"], "requirements": {"degrees": [], "majors": [], "languages": ["english", "chinese", "mandarin"], "language_level": [], "hard_skills": ["ms office"], "soft_skills": ["communication", "interpersonal skill"], "languages_combined": [{"language": "english", "language_level": []}, {"language": "chinese", "language_level": []}, {"language": "mandarin", "language_level": []}]}, "experience_required": {"duration": ["4 years"], "field": ["garment", "merchandising"]}}, {"job_id": "100003009044436", "location_code": "hk", "company": "Max Mara Fashion Group", "job_title": "Full Time / Part Time Tailor \u5168\u8077 / \u517c\u8077\u88c1\u7e2b", "description": "\u8077\u8cac:\n\n\u8ca0\u8cac\u65e5\u5e38\u670d\u88dd\u7de8\u91dd\u548c\u6539\u8863\u670d\u52d9\n\u6309\u5de5\u4f5c\u9700\u8981, \u524d\u5f80\u5e97\u8216\u70ba\u5ba2\u4eba\u63d0\u4f9b\u5ea6\u8eab\u670d\u52d9\u53ca\u5c08\u696d\u6539\u8863\u610f\u898b\n\n\u8077\u4f4d\u8981\u6c42:\n\n\n\u4e00\u5e74\u6216\u4ee5\u4e0a\u88c1\u7e2b\u7d93\u9a57\uff0c\u7d93\u9a57\u8f03\u591a\u8005\u6703\u512a\u5148\u8003\u616e\n\u6709\u8cac\u4efb\u611f\u3001\u6709\u8010\u6027\u3001\u7d30\u5fc3\u53ca\u5b88\u6642\n\u5de5\u4f5c\u5730\u9ede:\u00a0\u7063\u4ed4 /\u00a0\u5c16\u6c99\u5480\u00a0\n\n\u54e1\u5de5\u798f\u5229:\n\n\n10-15 \u5929\u6709\u85aa\u5e74\u5047\n\u82b1\u7d05\n\u8868\u73fe\u82b1\u7d05\n\u4ecb\u7d39\u4eba\u734e\u91d1\n\u91ab\u7642(\u9580\u8a3a\u53ca\u4f4f\u9662)\u798f\u5229\n\u5c08\u696d\u5728\u8077\u57f9\u8a13\n\u54e1\u5de5\u8cfc\u7269\u512a\u60e0\n\u751f\u65e5\u79ae\u7269\n\u6559\u80b2\u6d25\u8cbc\n\u7fa9\u5de5\u670d\u52d9\u5047\n\u5168\u85aa\u7522\u5047\n\u5168\u85aa\u4f8d\u7522\u5047\n\u5168\u85aa\u75c5\u5047\n\u5a5a\u5047\n\u6069\u6064\u5047\n\u9810\u9632\u5b63\u7bc0\u6027\u6d41\u611f\u75ab\u82d7\u6ce8\u5c04\n\n\u6709\u610f\u61c9\u5fb5\u8005\u8acbWhatsapp 9249 7312 / \u9ede\u9078\u00a0APPLY NOW\u00a0\u7533\u8acb\u3002\n\n\u00a0(\u6c42\u8077\u8005\u905e\u4ea4\u500b\u4eba\u8cc7\u6599\uff0c\u53ea\u4f5c\u62db\u8058\u7528\u9014\uff0c\u6240\u6709\u8cc7\u6599\u7d55\u5c0d\u4fdd\u5bc6\u3002)", "employment_types": ["Full Time", "Permanent"], "selling_points": ["\u4e00\u5e74\u6216\u4ee5\u4e0a\u88c1\u7e2b\u7d93\u9a57", "\u5c08\u696d\u5728\u8077\u57f9\u8a13\u53ca\u5b8c\u5584\u54e1\u5de5\u798f\u5229", "\u5de5\u4f5c\u8207\u751f\u6d3b\u5e73\u8861"], "locations": ["Wan Chai"], "categories": ["Sales, CS & Business Devpt", "Customer Service - Supervisor / Officer", "Design", "Fashion", "Others"], "post_time": "2022-01-13T04:03:46Z", "salary": {"currency": null, "max": null, "min": null, "period": "monthly", "term": null}, "salary_visible": false, "title_keywords": [], "responsibilities": [], "requirements": {"degrees": [], "majors": [], "languages": [], "language_level": [], "hard_skills": [], "soft_skills": [], "languages_combined": []}, "experience_required": {"duration": [], "field": []}}, {"job_id": "100003009044025", "location_code": "hk", "company": "I.T Apparels Limited", "job_title": "Assistant Visual Merchandiser (REF: JDB-IT-AVM)", "description": "Accountabilities \u2013 Key Result Areas\n\nDesign, develop and execute all visual merchandising and promotional displays for promotional program, seasonal change and ad-hoc events\nMaintain and upkeep all visual merchandising materials at stores regularly\nAssist in sourcing, negotiation\u00a0and liaison with suppliers for the ordering, delivering and producing of materials,\u00a0and set up\u00a0relating to all visual merchandising\nAssist in setting up and coordinates new store opening and store upgrading\nWork closely in team for concept development, execution and all creative deliberationSupport graphic design\u00a0and development of artwork for various marketing materials such as print ad, brochure, packaging, POP, flyer, poster and etc.\nLiaise and coordinate with external agencies and vendors for print/production and quality control.\nProject management of all VM initiatives including windows, seasonal brand imagery, LED screens, POS and merchandise presentations all to be delivered in store, on time and on budget\nEnhance aesthetic appeal of shop front windows and in-store displays to promote new product launches, festive and seasonal themes including deliver regular floor moves, window installations, and mannequins styling, etc.\nExperience / Qualification Requirements\nDegree holder in visual merchandising and design related discipline\nAt least 1 - 2 years experience in fashion industry, with solid experience in visual design, window set up, interior displays and space utilization\nProficient design software skills such as Illustrator, Photoshop, AutoCAD, etc.\nCreative and possess good knowledge and sense of fashion, accessories, color trends and styling\nBe passionate about the brand\u2019s identity, with personal charisma and good understanding of the dynamics of the fashion industry\nCommunicative and be able to collaborate with business teams to achieve brand objectives\nCandidates with less experience will be considered as Visual Merchandising Coordinator.\n\nCompetitive remuneration and benefit package will be offered to the right candidate. Please submit your application by clicking \"Apply Now\" below.\n\nAll data collected is for recruitment purpose only.\n\nSure you want to know more about our company and brands, simply follow our\n\nWEBSITE at\u00a0http://www.ithk.com\u00a0 \u00a0 \u00a0 \u00a0 \u00a0 \u00a0 \u00a0 \u00a0 \u00a0 \u00a0 \u00a0 \u00a0 \u00a0 \u00a0 \u00a0 \u00a0 \u00a0 \u00a0 \u00a0 \u00a0 \u00a0 \u00a0 \u00a0 \u00a0 \u00a0 \u00a0 \u00a0 \u00a0 \u00a0 \u00a0 \u00a0 \u00a0 \u00a0 \u00a0\n\nFACEBOOK at\u00a0http://www.facebook.com/I.Ttheofficialpage\u00a0 \u00a0 \u00a0 \u00a0 \u00a0 \u00a0 \u00a0 \u00a0 \u00a0 \u00a0 \u00a0 \u00a0 \u00a0 \u00a0\u00a0\n\nINSTAGRAM at\u00a0http://instagram.com/ithk\u00a0 \u00a0 \u00a0 \u00a0 \u00a0 \u00a0 \u00a0 \u00a0 \u00a0 \u00a0 \u00a0 \u00a0 \u00a0 \u00a0 \u00a0 \u00a0 \u00a0 \u00a0 \u00a0 \u00a0 \u00a0 \u00a0 \u00a0 \u00a0 \u00a0 \u00a0 \u00a0 \u00a0\n\nWEIBO at\u00a0http://e.weibo.com/ithongkong", "employment_types": ["Full Time"], "selling_points": ["Visual Merchandising", "Promotional Displays", "1-2 years of Visual Merchandising experience"], "locations": ["Not Specified"], "categories": ["Design", "Fashion", "Graphics", "Visual Merchandising"], "post_time": "2022-01-13T02:49:39Z", "salary": {"currency": null, "max": null, "min": null, "period": "monthly", "term": null}, "salary_visible": false, "title_keywords": ["assistant visual merchandiser"], "responsibilities": ["liaise", "collaborate with", "software", "data", "budget", "merchandising", "website", "design", "maintain", "facebook", "ad-hoc events", "teams", "presentations", "develop", "visual", "promotional program", "coordinate with", "graphic design", "project management", "recruitment", "quality control", "marketing materials"], "requirements": {"degrees": ["degree holder"], "majors": ["design"], "languages": [], "language_level": [], "hard_skills": ["pos", "visual merchandising", "illustrator", "presentations", "project management", "visual design", "autocad", "facebook", "photoshop"], "soft_skills": ["project management", "creative", "negotiation", "passionate about"], "languages_combined": []}, "experience_required": {"duration": ["at least 1 - 2 years"], "field": ["merchandising", "design"]}}, {"job_id": "100003009038256", "location_code": "hk", "company": "Wadhsons (HK) Ltd", "job_title": "Fashion Graphic and CAD Designer (Casual Wear)", "description": "Responsibilities:\u00a0\n\n\nDevelop men\u2019s and ladies casual wear styles in the form of CADs\nDevelop story board and designs for mass production\nDesign accessories according to latest market trends\nTo conduct seasonal fashion and market trend research\nHandle ad hoc projects as required\u00a0\n\nRequirements:\n\nDiploma holder in Design or equivalent\nWith at least 2 years solid experience in men\u2019s and ladies casual fashion wear\nExperience for South American market would be an advantage\nExperienced in Photoshop and Illustrator\nSelf-motivated, independent and good team player\nCreative and with a sensible marketing mind-set\nGood command of spoken and written English and Chinese\nFresh graduate will also be considered\nNeeds to be up to date with current fast fashion trends\nGood command of spoken and written English and Chinese\n\n\u00a0\u00a0Benefit:\n\nDouble-Pay\nMedical Insurance\nBank\u00a0Holiday\n5-Day Work Week\nInterested parties please\u00a0send your full resume stating salary expected\u00a0by clicking the \"Apply Now\" button.\u00a0\n", "employment_types": ["Full Time", "Permanent"], "selling_points": [], "locations": ["Tsim Sha Tsui"], "categories": ["Design", "Fashion"], "post_time": "2022-01-11T06:22:20Z", "salary": {"currency": null, "max": null, "min": null, "period": "monthly", "term": null}, "salary_visible": false, "title_keywords": ["designer"], "responsibilities": ["ad hoc projects", "design", "develop"], "requirements": {"degrees": ["diploma holder", "fresh graduate"], "majors": ["design"], "languages": ["english", "chinese"], "language_level": ["good command"], "hard_skills": ["illustrator", "photoshop"], "soft_skills": ["good team player", "self-motivated", "creative", "independent"], "languages_combined": [{"language": "english", "language_level": ["good command", "good command"]}, {"language": "chinese", "language_level": ["good command", "good command"]}]}, "experience_required": {"duration": ["at least 2 years"], "field": []}}, {"job_id": "100003009043149", "location_code": "hk", "company": "Vocational Training Council", "job_title": "\u4e09\u7d1a\u6a5f\u68b0\u5de5 (\u670d\u98fe)", "description": "\u9999\u6e2f\u77e5\u5c08\u8a2d\u8a08\u5b78\u9662\u53ca\u9999\u6e2f\u5c08\u696d\u6559\u80b2\u5b78\u9662 (\u674e\u60e0\u5229)\n\u00a0\nDepartment / Section : \u6642\u88dd\u53ca\u5f62\u8c61\u8a2d\u8a08\u5b78\u7cfb\nRef. no : C/HKDI-FID/MEC3/01/22-AP1\n\u00a0\n\u4e3b\u8981\u8077\u8cac\uff1a\n(a) \u00a0\u00a0 \u00a0\u64cd\u4f5c\u3001\u5b89\u88dd\u3001\u6e2c\u8a66\u3001\u4fdd\u990a\u53ca\u7dad\u4fee\u5be6\u9a57\u5ba4\u53ca\u5de5\u5834\u5167\u7684\u76f8\u95dc\u6280\u8853\u5100\u5668\u53ca\u6a5f\u5668\u7b49\u914d\u5099\uff1b\n(b) \u00a0\u00a0 \u00a0\u6e96\u5099\u6559\u5b78\u8f14\u52a9\u7528\u5177\u3001\u6240\u9700\u7684\u7269\u6599\u3001\u5100\u5668\u53ca\u914d\u5099\u4f5c\u8a13\u7df4\u4e4b\u7528\uff1b\n(c) \u00a0\u00a0 \u00a0\u5354\u52a9\u7ba1\u7406\u6709\u95dc\u5668\u6750\u53ca\u7269\u8cc7\u7684\u6536\u767c\u5b58\u53d6\uff0c\u4e26\u6aa2\u67e5\u662f\u5426\u640d\u58de\uff1b\n(d) \u00a0\u00a0 \u00a0\u642c\u904b\u6559\u5b78\u8a2d\u5099\u3001\u5100\u5668\u53ca\u7269\u8cc7\uff0c\u4e26\u4fdd\u6301\u5de5\u5834\u7684\u5b89\u5168\u53ca\u6574\u6f54\uff1b\u53ca\n(e) \u00a0\u00a0 \u00a0\u652f\u63f4\u5b78\u9662\u8209\u8fa6\u4e4b\u6d3b\u52d5\u3001\u5c55\u89bd\u548c\u8868\u6f14\u3002\n\u00a0\n\u5165\u8077\u689d\u4ef6\uff1a\n(a) \u00a0\u00a0 \u00a0(i) \u00a0\u00a0 \u00a0\u5b8c\u6210\u76f8\u95dc\u8a8d\u53ef\u8a13\u7df4\u8ab2\u7a0b (\u5305\u62ec\u5b78\u5f92\u53ca\u6280\u5de5\u8a13\u7df4) ; \u6216\n\u00a0 \u00a0\u00a0 \u00a0(ii) \u00a0\u00a0 \u00a0\u901a\u904e\u6280\u80fd\u6e2c\u8a66\u6216\u76f8\u7b49\u6c34\u5e73\u6e2c\u8a66\uff1b\n(b) \u00a0\u00a0 \u00a0\u5177\u5099\u4e0b\u5217\u6280\u80fd\uff1a\n\u00a0 \u00a0\u00a0 \u00a0(i) \u00a0\u00a0 \u00a0\u68ad\u7e54\u8eca\u9593\u7f1d\u7d09\u6280\u8853\uff1b\n\u00a0 \u00a0\u00a0 \u00a0(ii) \u00a0\u00a0 \u00a0\u68ad\u7e54\u6a5f\u5668\u6e05\u6f54\u3001\u7dad\u4fee\u53ca\u4fdd\u990a\uff1b\u53ca / \u6216\n\u00a0 \u00a0\u00a0 \u00a0(iii) \u00a0\u00a0 \u00a0\u68ad\u7e54\u6280\u8853 (\u5982\u61c9\u7528\u548c\u4fee\u88dc\u7b49)\uff1b\n(c) \u00a0\u00a0 \u00a0\u61c2\u57fa\u672c\u96fb\u8166\u64cd\u4f5c\uff1b\n(d) \u00a0\u00a0 \u00a0\u80fd\u95b1\u8b80\u53ca\u66f8\u5beb\u4e2d\u6587\u548c\u7c21\u55ae\u82f1\u8a9e\uff1b\u53ca\n(e) \u00a0\u00a0 \u00a0\u5177\u5099\u61c2\u5f97\u64cd\u4f5c/\u7dad\u4fee\u4ee5\u4e0b\u6a5f\u5668 / \u5de5\u5177\u7684\u7533\u8acb\u4eba\u53ef\u7372\u512a\u5148\u8003\u616e\uff1a\n\u00a0 \u00a0\u00a0 \u00a0(i) \u00a0\u00a0 \u00a0\u5de5\u696d\u8863\u8eca (\u5e73\u8eca)\uff1b\n\u00a0 \u00a0\u00a0 \u00a0(ii) \u00a0\u00a0 \u00a0\u9212\u9aa8\u8eca\uff1b\n\u00a0 \u00a0\u00a0 \u00a0(iii) \u00a0\u00a0 \u00a0\u6311\u8173\u8eca\uff1b\n\u00a0 \u00a0\u00a0 \u00a0(iv) \u00a0\u00a0 \u00a0\u91d8\u9215\u53ca\u958b\u9215\u9580\u8eca\uff1b\n\u00a0 \u00a0\u00a0 \u00a0(v) \u00a0\u00a0 \u00a0\u9ecf\u6734\u6a5f\uff1b\n\u00a0 \u00a0\u00a0 \u00a0(vi) \u00a0\u00a0 \u00a0\u5047\u7f1d\u8eca\uff1b\n\u00a0 \u00a0\u00a0 \u00a0(vii) \u00a0\u00a0 \u00a0\u57cb\u593e\u8eca\uff1b\n\u00a0 \u00a0\u00a0 \u00a0(viii) \u00a0\u00a0 \u00a0\u519a\u8eca\uff1b\n\u00a0 \u00a0\u00a0 \u00a0(ix) \u00a0\u00a0 \u00a0\u5277\u76ae\u6a5f\uff1b\n\u00a0 \u00a0\u00a0 \u00a0(x) \u00a0\u00a0 \u00a0\u9ad8\u982d\u6a5f\uff1b\n\u00a0 \u00a0\u00a0 \u00a0(xi) \u00a0\u00a0 \u00a0\u4eba\u5b57 / \u4e09\u91dd\u8eca\u3002\n\u00a0 \u00a0\u00a0 \u00a0 \u00a0\u00a0\u00a0 \u00a0\n\u5099\u8a3b\uff1a\n(1) \u00a0\u00a0 \u00a0\u7533\u8acb\u8005\u82e5\u5177\u5169\u5e74\u6216\u4ee5\u4e0a\u76f8\u95dc\u5de5\u4f5c\u7d93\u9a57\uff0c\u6216\u6703\u88ab\u8003\u616e\u70ba\u4e8c\u7d1a\u6a5f\u68b0\u5de5\u3002\n(2)\n\u00a0 \u00a0\u00a0 \u00a0\u8a72\u7a7a\u7f3a\u73fe\u65bc\u9999\u6e2f\u77e5\u5c08\u8a2d\u8a08\u5b78\u9662\u53ca\u9999\u6e2f\u5c08\u696d\u6559\u80b2\u5b78\u9662\uff08\u674e\u60e0\u5229\uff09\uff0c\u70ba\u914d\u5408\u904b\u4f5c\u9700\u8981\uff0c\u53d7\u8058\u8005\u65e5\u5f8c\u53ef\u80fd\u6703\u88ab\u8abf\u6d3e\u81f3\u5176\u4ed6\u5730\u9ede\u5de5\u4f5c\u3002\n(3) \u00a0\u00a0 \u00a0\u8acb\u65bc\u7533\u8acb\u8868\u300c(VII) \u5176\u4ed6\u8cc7\u6599\u300d\u6b04\u5167\u5217\u51fa\u80fd\u64cd\u4f5c\u4e4b\u76f8\u95dc\u6a5f\u5668\u8a2d\u5099\u548c\u6280\u80fd\u3002\n(4) \u00a0\u00a0 \u00a0\u7533\u8acb\u8005\u9700\u8981\u53c3\u52a0\u6280\u80fd\u6e2c\u8a66\u3002\n(5) \u00a0\u00a0 \u00a0\u53d7\u8058\u8005\u53ef\u80fd\u9700\u8981\u8f2a\u73ed\u5de5\u4f5c\uff0c\u5305\u62ec\u591c\u73ed\uff0c\u4e26\u65bc\u661f\u671f\u516d\u3001\u65e5\u53ca\u516c\u773e\u5047\u671f\u5de5\u4f5c\uff0c\u4ea6\u53ef\u80fd\u6703\u5728\u4e0d\u540c\u5de5\u5834\u5167\u5de5\u4f5c\u3002\n\n\u7533\u8acb\u8fa6\u6cd5\uff1a\n\u586b\u59a5\u7684\u7533\u8acb\u8868\u683c [VTC-1 (Rev. 1/2018)] \u9023\u540c\u500b\u4eba\u5c65\u6b77\uff0c\u9808\u5bc4\u56de\u9999\u6e2f\u7063\u4ed4\u6d3b\u905327\u865f\uff0c\u8077\u696d\u8a13\u7df4\u5c40\u5927\u6a1318\u6a13\uff0c\u4eba\u529b\u8cc7\u6e90\u79d1\u3002\u8acb\u5728\u4fe1\u5c01\u9762\u8a3b\u660e\u6240\u7533\u8acb\u7684\u8077\u4f4d\u53ca\u53c3\u8003\u7de8\u865f\u3002\n\u00a0\n\u622a\u6b62\u7533\u8acb\u65e5\u671f\uff1a2022\u5e741\u670825\u65e5\n\u00a0\n\u5982\u5728\u622a\u6b62\u7533\u8acb\u5f8c\u7684\u5341\u661f\u671f\u5167\u672a\u6709\u6536\u5230\u9762\u8a66\u901a\u77e5\uff0c\u5373\u8868\u793a\u9019\u9805\u7533\u8acb\u4e0d\u7372\u63a5\u7d0d\u3002\n\u00a0\n\u672c\u5c40\u4fdd\u7559\u4e0d\u586b\u88dc\u4e0a\u8ff0\u8077\u4f4d\u7684\u6b0a\u5229\u3002\n\u00a0\n\u7533\u8acb\u4eba\u7684\u8cc7\u6599\u53ea\u6703\u7528\u65bc\u6709\u95dc\u672c\u5c40\u7684\u4eba\u4e8b\u62db\u8058\u4e8b\u5b9c\u3002\u5728\u4e00\u822c\u60c5\u6cc1\u4e0b\uff0c\u672a\u7372\u53d6\uf93f\u7533\u8acb\u4eba\u7684\u8cc7\uf9be\u5c07\u65bc\u62db\u8058\u5de5\u4f5c\u5b8c\u6210\u5341\u4e8c\u500b\u6708\u5f8c\u5168\u90e8\u92b7\u6bc0\u3002\n\n", "employment_types": ["Full Time"], "selling_points": ["\u64cd\u4f5c\u3001\u5b89\u88dd\u3001\u6e2c\u8a66\u3001\u4fdd\u990a\u53ca\u7dad\u4fee\u5be6\u9a57\u5ba4\u53ca\u5de5\u5834\u5167\u7684\u76f8\u95dc\u6280\u8853\u5100\u5668\u53ca\u6a5f\u5668\u7b49\u914d\u5099", "\u5b8c\u6210\u76f8\u95dc\u8a8d\u53ef\u8a13\u7df4\u8ab2\u7a0b (\u5305\u62ec\u5b78\u5f92\u53ca\u6280\u5de5\u8a13\u7df4)", "\u7533\u8acb\u8005\u82e5\u5177\u5169\u5e74\u6216\u4ee5\u4e0a\u76f8\u95dc\u5de5\u4f5c\u7d93\u9a57\uff0c\u6216\u6703\u88ab\u8003\u616e\u70ba\u4e8c\u7d1a\u6a5f\u68b0\u5de5"], "locations": ["Not Specified"], "categories": ["Design", "Fashion", "Manufacturing", "Garment / Textile", "Merchandising & Purchasing", "Textiles"], "post_time": "2022-01-12T09:59:55Z", "salary": {"currency": null, "max": null, "min": null, "period": "monthly", "term": null}, "salary_visible": false, "title_keywords": [], "responsibilities": [], "requirements": {"degrees": [], "majors": [], "languages": [], "language_level": [], "hard_skills": ["no", "c"], "soft_skills": [], "languages_combined": []}, "experience_required": {"duration": [], "field": []}}, {"job_id": "100003009037768", "location_code": "hk", "company": "Heng Lee Pearl Company Limited", "job_title": "Jewellery Designer / Senior Jewellery Designer", "description": "Jewellery Designer / Senior Jewellery Designer\n\nResponsibilities:\n\nJewelry design\nConduct research & analysis on product trends and work closely with sales & marketing teams and related parties by transforming the designs into marketable products\nHandle & manage product development projects on time from ideas to finished samples\nCommunicate and collaborate with inter-departments to facilitate work process\nProvide design direction / training to China design team\nTake part in exhibition if needed\nWilling to travel to China factory\n\nRequirements:\n\nDegree / Diploma holder in jewellery design or equivalent\nAt least 3 years experience in silver/brass/K-gold jewellery in designs\nStrong sense of creativity and ability to convert trends or seed concept to products\nExcellent & efficient hand sketching & familiar with 3D rendering skills\nFlexibility to work under pressure to meet challenging deadlines\nFamiliar of jewellery manufacturing process is a plus\nGood communications skills in verbal and written Chinese , English & Mandarin \u00a0\nPositive, diligent and self-motivated with good team player mindset\nCandidate with less experience will be considered as Jewellery Designer\n\nTST Area", "employment_types": ["Full Time"], "selling_points": [], "locations": ["Tsim Sha Tsui"], "categories": ["Design", "Fashion"], "post_time": "2022-01-11T03:47:07Z", "salary": {"currency": null, "max": null, "min": null, "period": "monthly", "term": null}, "salary_visible": false, "title_keywords": ["designer"], "responsibilities": ["collaborate with", "ideas", "analysis", "teams", "design", "conduct research"], "requirements": {"degrees": ["diploma holder", "degree"], "majors": ["design"], "languages": ["english", "chinese", "mandarin"], "language_level": ["good"], "hard_skills": ["plus"], "soft_skills": ["efficient", "self-motivated", "good team player", "diligent", "positive", "work under pressure"], "languages_combined": [{"language": "english", "language_level": ["good"]}, {"language": "chinese", "language_level": ["good"]}, {"language": "mandarin", "language_level": ["good"]}]}, "experience_required": {"duration": ["at least 3 years"], "field": ["designer"]}}, {"job_id": "100003009043724", "location_code": "hk", "company": "HRnet One Limited", "job_title": "Apparel Design Developer (other openings incl Merchandisers)", "description": "Accountabilities \u2013 Key Result Areas\n\nResponsible for the development of Men\u2019s collection from trend research, product concept, theme board and sketch creation to tech pack and sample follow up\nCoordinate trend presentation and product trainings\nWork closely with sourcing and follow through production and fitting\n\nExperience / Qualification Requirements\n\nDiploma or degree holder in Fashion Design or related discipline\nPossess 1-2 years' fashion design experience\nWith strong sense of fashion trend, and graphic\nBe passionate and enthusiastic for fashions & lifestyle\nProficiency in using Mac design software including Illustrator and Photoshop\nRecent graduates will be considered\n\nCompetitive remuneration and benefit package will be offered to the right candidate. Please submit your application by clicking \"Apply Now\" below.\n\nAll data collected is for recruitment purpose only.\n\nSure you want to know more about our company and brands, simply follow our\n\nWEBSITE at\u00a0http://www.ithk.com\u00a0 \u00a0 \u00a0 \u00a0 \u00a0 \u00a0 \u00a0 \u00a0 \u00a0 \u00a0 \u00a0 \u00a0 \u00a0 \u00a0 \u00a0 \u00a0 \u00a0 \u00a0 \u00a0 \u00a0 \u00a0 \u00a0 \u00a0 \u00a0 \u00a0 \u00a0 \u00a0 \u00a0 \u00a0 \u00a0 \u00a0 \u00a0 \u00a0 \u00a0\u00a0\n\nFACEBOOK at\u00a0http://www.facebook.com/I.Ttheofficialpage\u00a0 \u00a0 \u00a0 \u00a0 \u00a0 \u00a0 \u00a0 \u00a0 \u00a0 \u00a0 \u00a0 \u00a0 \u00a0 \u00a0\u00a0\n\nINSTAGRAM at\u00a0http://instagram.com/ithk\u00a0 \u00a0 \u00a0 \u00a0 \u00a0 \u00a0 \u00a0 \u00a0 \u00a0 \u00a0 \u00a0 \u00a0 \u00a0 \u00a0 \u00a0 \u00a0 \u00a0 \u00a0 \u00a0 \u00a0 \u00a0 \u00a0 \u00a0 \u00a0 \u00a0 \u00a0 \u00a0 \u00a0\u00a0\n\nWEIBO at\u00a0http://e.weibo.com/ithongkong", "employment_types": ["Full Time", "Permanent"], "selling_points": ["Double pay, Year end incentive", "growing MNC with strong track record", "Stable working environment, practical leadership"], "locations": ["Kwun Tong"], "categories": ["Design", "Fashion", "Manufacturing", "Garment / Textile"], "post_time": "2022-01-13T01:40:29Z", "salary": {"currency": null, "max": null, "min": null, "period": "monthly", "term": null}, "salary_visible": false, "title_keywords": ["developer"], "responsibilities": ["product concept", "software", "data", "website", "design", "coordinate", "recruitment", "facebook"], "requirements": {"degrees": ["diploma", "degree holder"], "majors": ["design"], "languages": [], "language_level": [], "hard_skills": ["facebook", "illustrator", "photoshop"], "soft_skills": ["passionate", "presentation", "responsible", "enthusiastic"], "languages_combined": []}, "experience_required": {"duration": ["1-2 years"], "field": ["fashion design"]}}, {"job_id": "100003009037102", "location_code": "hk", "company": "Rag United Works Limited", "job_title": "Clothing & Footwear designer (5 Days work)", "description": "We are looking for an enthusiastic person to join an international business , which requires an proactive attitude and entrepreneurial\u00a0spirit. Passionate in casual or active wear.\u00a0\n\nBase on the business expansion purpose of the brand, we welcome Designers, PDs, Merchandisers as other openings are also available.\u00a0\nAssist PD Head & HQ in mock up , fixing sketches in developing products\u00a0\nCreate a record of all developments in work and communicate the progress and updates to ensure regional teams are aligned.\nEnsure timelines are met and samples are prepared for style reviews\u00a0\nAct as main contact window in region for status updates\u00a0\nWork closely with HQ, and Asia team in development\u00a0tracking, oversee TNA together\u00a0with Head of PD\nProvide support on aesthetic and intent of the garment.\nSpecification:\u00a0\n\nAdobe Illustrator /\u00a0Photoshop\nPLM experience is a plus\nRelevant Bachelor Degree in Fashion Textile is a plus\u00a0", "employment_types": ["Full Time", "Permanent"], "selling_points": [], "locations": ["Tsim Sha Tsui"], "categories": ["Design", "Fashion", "Graphics", "Merchandising & Purchasing", "Footwear"], "post_time": "2022-01-11T02:14:55Z", "salary": {"currency": null, "max": null, "min": null, "period": "monthly", "term": null}, "salary_visible": false, "title_keywords": ["designer"], "responsibilities": ["provide support", "teams", "developing", "sketches", "contact", "tracking"], "requirements": {"degrees": ["degree", "bachelor"], "majors": [], "languages": [], "language_level": [], "hard_skills": ["plus", "photoshop", "adobe illustrator"], "soft_skills": ["passionate", "active", "proactive", "enthusiastic"], "languages_combined": []}, "experience_required": {"duration": [], "field": []}}, {"job_id": "100003009039681", "location_code": "hk", "company": "I.T Apparels Limited", "job_title": "Assistant Designer (REF:JDB-IT-AD)", "description": "Responsibilities:\nCreate sketches/Illustrator CADs and spec/detail technical specifications\nCollaborate and clearly communicate with\u00a0 factories to ensure design objectives are reflected in the creation and execution of the product\nStay abreast of competitive brands and market trends\nWork closely with executive team to develop and execute product designs for Ladies Footwear.\nAdhere to design calendar and deadlines.\nGenerate detailed tech packs/specs for pass off to factories\nHave a thorough understanding of footwear construction, sampling and manufacturing\nPossess superior multitasking and time management skills\nEffectively balance creative thinking with commercial viability\nMust be a collaborative, team player with excellent interpersonal and communication skills\nRequirements:\nBachelor\u2019s degree in fashion or related field, or equivalent combination of education and experience in footwear design required\n5-7 years industry experience designing women\u2019s fashion footwear is a must; fast fashion experience a plus!\nExperience developing product directly with Asia based factories preferred\nDemonstrated proficiency in illustrator/Photoshop/Google Suite as well as hand sketching\nProviding a digital portfolio or examples of work strongly recommended for serious consideration\nGood interpersonal and listening skills; Excellent written & oral English & Chinese including Putonghua is a plus\nThis position is based in Hong Kong\n\n\n\nBenefits:\n\nDouble Pay\nAnnual leave 11 days\nPaid sick leave\n5 days work", "employment_types": ["Full Time"], "selling_points": ["Diploma or degree holder in Fashion Design", "1-2 years' fashion design experience", "Recent graduates will be considered"], "locations": ["Southern Area"], "categories": ["Design", "Fashion", "Graphics", "Sales, CS & Business Devpt", "Retail Sales"], "post_time": "2022-01-11T10:28:28Z", "salary": {"currency": null, "max": null, "min": null, "period": "monthly", "term": null}, "salary_visible": false, "title_keywords": ["assistant designer"], "responsibilities": ["collaborate", "communicate with", "management", "sketches", "design", "develop", "communication", "specifications"], "requirements": {"degrees": ["degree", "bachelor"], "majors": ["design"], "languages": ["putonghua", "english", "chinese"], "language_level": ["excellent"], "hard_skills": ["plus", "illustrator", "photoshop"], "soft_skills": ["oral", "interpersonal"], "languages_combined": [{"language": "putonghua", "language_level": []}, {"language": "english", "language_level": ["excellent"]}, {"language": "chinese", "language_level": ["excellent"]}]}, "experience_required": {"duration": ["5-7 years"], "field": ["related", "developing", "design", "education"]}}, {"job_id": "100003009042144", "location_code": "hk", "company": "", "job_title": "Senior Graphic Designer (BR-SGD)", "description": "Key responsibilities:\n\n\nGuide and deliver multi-purpose graphic design initiatives, including product development, packaging, iconography, illustrations, infographics, video, and fashion graphics\nDevelop creative concepts, layouts and artworks in various platforms such as websites, social media visuals, Facebook applications, mobile\nDesign engaging and differentiating content experiences that uphold brand guidelines and values, and within the pre-set timelines and budget\nProvide art direction in photo / video shooting, and responsible for video graphics\nBrainstorm initiatives to support the team\u2019s creative delivery\nOffer continuous insight into industry best practice, design trends and content generation idea\n\nQualifications:\n\nDegree holder in graphic design related discipline\nAt least 6-8 years solid experience in graphic design in creative agency or in house environment\nExperience working on a variety of projects, including brand identity, illustration, infographics, patterns and packaging\nExperience in web design, mobile apps or online video production is an added advantage\nHas high standards and takes pride in quality of work, with great attention to detail\nBe passionate about the brand\u2019s identity, with personal charisma and visions in international design trend\nAbility to research and apply market information\nCreative, communicative and be able to collaborate with business teams to achieve brand objectives\n\nInterested parties please apply below with your resume for a private discussion. All information collected will be kept in strict confidentiality.\u00a0", "employment_types": ["Full Time"], "selling_points": ["Multi-purpose graphic design", "Develop creative concepts, layouts and artworks", "6-8 years solid experience in graphic design"], "locations": ["Not Specified"], "categories": ["Design", "Fashion", "Graphics", "Others"], "post_time": "2022-01-12T06:23:11Z", "salary": {"currency": null, "max": null, "min": null, "period": "monthly", "term": null}, "salary_visible": false, "title_keywords": ["senior graphic designer"], "responsibilities": ["graphics", "social media", "collaborate with", "market information", "video production", "graphic design", "budget", "quality", "teams", "design", "video shooting", "brand guidelines", "design trends", "facebook", "develop creative concepts", "support the team"], "requirements": {"degrees": ["degree holder"], "majors": ["graphic design"], "languages": [], "language_level": [], "hard_skills": ["graphics", "web design", "mobile", "facebook", "illustration"], "soft_skills": ["creative", "attention to detail", "responsible", "passionate about"], "languages_combined": []}, "experience_required": {"duration": ["at least 6-8 years"], "field": ["brand", "agency", "graphic design", "video production", "design"]}}, {"job_id": "100003009038454", "location_code": "hk", "company": "I.T Apparels Limited", "job_title": "Interior Designer (REF: JDB-IT-ID)", "description": "\u00a0Accountabilities \u2013 Key Result Areas\n\nCarry out design concept and development, assist preparation of detailed and construction drawings, sourcing and selection of materials and preparation of quotations\nHandle various design documentation and presentation work\u00a0\nCoordinate and liaise with contractors, vendors and project team members to collect business and project requirements to ensure effective and satisfactory project completion\n\nExperience / Qualification Requirements\n\nDiploma / Degree holder in Architecture or Interior Design or equivalent\nWith at least 3 years of experience, with retail fit-out and large scale project experience is preferred\nFamiliar with AutoCAD, Photoshop, Adobe illustrator, 3D Max and other relevant graphic and design tools\n\nCompetitive remuneration and benefit package will be offered to the right candidate. Please submit your application by clicking \"Apply Now\" below.\n\nAll data collected is for recruitment purpose only.\n\nSure you want to know more about our company and brands, simply follow our\n\nWEBSITE at http://www.ithk.com\u00a0 \u00a0 \u00a0 \u00a0 \u00a0 \u00a0 \u00a0 \u00a0 \u00a0 \u00a0 \u00a0 \u00a0 \u00a0 \u00a0 \u00a0 \u00a0 \u00a0 \u00a0 \u00a0 \u00a0 \u00a0 \u00a0 \u00a0 \u00a0 \u00a0 \u00a0 \u00a0 \u00a0 \u00a0 \u00a0 \u00a0 \u00a0 \u00a0 \u00a0\u00a0\n\nFACEBOOK at\u00a0http://www.facebook.com/I.Ttheofficialpage \u00a0 \u00a0 \u00a0 \u00a0 \u00a0 \u00a0 \u00a0 \u00a0 \u00a0 \u00a0 \u00a0 \u00a0 \u00a0 \u00a0\n\nINSTAGRAM at http://instagram.com/ithk\u00a0 \u00a0 \u00a0 \u00a0 \u00a0 \u00a0 \u00a0 \u00a0 \u00a0 \u00a0 \u00a0 \u00a0 \u00a0 \u00a0 \u00a0 \u00a0 \u00a0 \u00a0 \u00a0 \u00a0 \u00a0 \u00a0 \u00a0 \u00a0 \u00a0 \u00a0 \u00a0 \u00a0\n\nWEIBO at\u00a0http://e.weibo.com/ithongkong", "employment_types": ["Full Time", "Permanent"], "selling_points": ["Carry out design concept and development", "Familiar with AutoCAD and 3D Max", "With at least 3 years of experience"], "locations": ["Southern Area"], "categories": ["Design", "Fashion", "Interior", "Others"], "post_time": "2022-01-11T06:55:30Z", "salary": {"currency": null, "max": null, "min": null, "period": "monthly", "term": null}, "salary_visible": false, "title_keywords": ["interior designer"], "responsibilities": ["project requirements", "data", "design concept", "website", "design", "drawings", "coordinate", "recruitment", "documentation", "facebook", "liaise with contractors", "architecture"], "requirements": {"degrees": ["diploma", "degree holder"], "majors": ["architecture", "design"], "languages": [], "language_level": [], "hard_skills": ["adobe illustrator", "autocad", "documentation", "max", "facebook", "photoshop"], "soft_skills": ["presentation", "detailed"], "languages_combined": []}, "experience_required": {"duration": ["at least 3 years"], "field": ["retail"]}}, {"job_id": "100003009034864", "location_code": "hk", "company": "The Brand Agency Limited", "job_title": "Senior Graphic Designer / Graphic Designer", "description": "To cope with our business expansion, we are now inviting candidates of high caliber for the following position:\n\n\u00a0\u00a0Senior Graphic Designer / Graphic Designer\u00a0\n\nJob Responsibilities:\n\n\nResponsible from concept development, artwork output and production for brands and corporate projects\nDevelop and execute graphic, digital and VM design to support marketing campaigns, online and offline stores\nMonitor design and VM budget\nWork closely with Principal, internal, and external parties to ensure design and production are properly delivered as per guidelines and timelines\nSupport ad-hoc projects when required\n\nJob Requirements:\n\n\nHigher Diploma or above in Design or other related disciplines\nMin 3 years related experience\nExposure in retail brand and eCommerce will be definite advantage\nProficient in MAC software including InDesign, Illustrator, Photoshop etc\nIndependent, Detail-oriented, Great communication skills and can work under pressure\nGood command of English and Chinese\u00a0\nCandidate with less experience will be considered as Graphic Designer\nWe offer a 5-day work week, health Insurance and an attractive remuneration package with career development opportunities.\n\n\nInterested parties please send your CV and portfolio with salary history and expected salary through APPLY NOW. Any applications without a portfolio will not be considered.\n\n(All personal data collected will be used for recruitment purpose only)", "employment_types": ["Full Time"], "selling_points": ["Develop and execute creative concept", "Design to support online and offline stores", "Higher Diploma or above in Design"], "locations": ["North Point"], "categories": ["Design", "Fashion", "Graphics", "Visual Merchandising"], "post_time": "2022-01-10T04:26:40Z", "salary": {"currency": null, "max": null, "min": null, "period": "monthly", "term": null}, "salary_visible": false, "title_keywords": ["senior graphic designer", "graphic designer"], "responsibilities": ["guidelines", "budget", "monitor", "external parties", "design", "develop", "marketing campaigns", "ad-hoc projects", "artwork output"], "requirements": {"degrees": ["higher diploma or above"], "majors": ["related disciplines", "design"], "languages": ["english", "chinese"], "language_level": ["good command"], "hard_skills": ["indesign", "illustrator", "photoshop"], "soft_skills": ["work under pressure", "communication skills", "independent", "detail-oriented"], "languages_combined": [{"language": "english", "language_level": ["good command"]}, {"language": "chinese", "language_level": ["good command"]}]}, "experience_required": {"duration": ["min 3 years"], "field": ["related", "graphic", "designer"]}}, {"job_id": "100003009038187", "location_code": "hk", "company": "Lauris Walton International Limited", "job_title": "Junior Industrial Designer / Junior Product Designer - MNC - Excellent Opportunity!", "description": "Lauris Walton is partnering with a fast-growing brand to seek a junior industrial / product designer based in Hong Kong! This job is an excellent opportunity for young design professionals to gain global exposure and a fast-growing brand with a friendly culture and working environment.\u00a0\n\nKey Benefits:\n\nLearning & Development Opportunity\u00a0\nFriendly and multinational work environment\u00a0\nCareer progression opportunity\nGlobal / Regional Exposure\nConvenient working location and excellent office environment\u00a0\n\nRole requirements:\n\nDegree or higher diploma in industrial design or product design\nFamiliar with\u00a0Rhinoceros 3D, Adobe Photoshop, Adobe Illustrator, Adobe InDesign AutoCAD\nGood communications skills in Chinese and English is essential\nFriendly, enjoy working as a team, detail-minded, multi-tasking\n\nYoung Design Pros! Don't miss this excellent opportunity and apply today!\n\nInterested applicants, please apply with your resume with current and expected salary, notice period, and portfolio. Due to the high volume of applications, only shortlisted candidates will be notified.\u00a0\n\nFor more job opportunities, please visit our website at\u00a0www.lauriswalton.com/jobs.\n", "employment_types": ["Full Time", "Permanent"], "selling_points": [], "locations": ["Central"], "categories": ["Design", "Fashion", "Industrial / Product", "Others"], "post_time": "2022-01-11T05:56:56Z", "salary": {"currency": null, "max": null, "min": null, "period": "monthly", "term": null}, "salary_visible": false, "title_keywords": ["product designer", "designer", "junior"], "responsibilities": ["design"], "requirements": {"degrees": [], "majors": [], "languages": [], "language_level": [], "hard_skills": [], "soft_skills": ["friendly"], "languages_combined": []}, "experience_required": {"duration": [], "field": []}}, {"job_id": "100003009039541", "location_code": "hk", "company": "I.T Apparels Limited", "job_title": "Assistant Graphic Designer - E-Commerce (REF: JDB-IT-AGD)", "description": "Accountabilities \u2013 Key Result Areas\n\nAssist development of multi-purpose graphic design initiatives and visual content for online and offline communication channels that uphold brand guidelines and values, and within the pre-set timelines and budget\nDesign a wide range of corporate promotional / marketing materials, including but not limited to advertisements, posters, flyers, marketing collaterals, catalogues, DM and EDM\nLiaise with suppliers and clients to obtain competitive quotes and ensure print quality of the highest standards\n\nExperience / Qualification Requirements\n\nDegree holder in graphic design related discipline\nWith 1-2 years solid experience in graphic design in creative agency or in house environment\nExperience working on a variety of projects, including brand identity, illustration, infographics, patterns and packaging is an added advantage\nPassion for design, with a keen eye for detail\nCreative, communicative and be able to collaborate with business teams to achieve brand objectives\n\nCompetitive remuneration and benefit package will be offered to the right candidate. Please submit your application by clicking \"Apply Now\" below.\n\nAll data collected is for recruitment purpose only.\n\nSure you want to know more about our company and brands, simply follow our\n\nWEBSITE at http://www.ithk.com\u00a0 \u00a0 \u00a0 \u00a0 \u00a0 \u00a0 \u00a0 \u00a0 \u00a0 \u00a0 \u00a0 \u00a0 \u00a0 \u00a0 \u00a0 \u00a0 \u00a0 \u00a0 \u00a0 \u00a0 \u00a0 \u00a0 \u00a0 \u00a0 \u00a0 \u00a0 \u00a0 \u00a0 \u00a0 \u00a0 \u00a0 \u00a0 \u00a0 \u00a0\n\nFACEBOOK at\u00a0http://www.facebook.com/I.Ttheofficialpage\u00a0 \u00a0 \u00a0 \u00a0 \u00a0 \u00a0 \u00a0 \u00a0 \u00a0 \u00a0 \u00a0 \u00a0 \u00a0 \u00a0\u00a0\n\nINSTAGRAM at http://instagram.com/ithk\u00a0 \u00a0 \u00a0 \u00a0 \u00a0 \u00a0 \u00a0 \u00a0 \u00a0 \u00a0 \u00a0 \u00a0 \u00a0 \u00a0 \u00a0 \u00a0 \u00a0 \u00a0 \u00a0 \u00a0 \u00a0 \u00a0 \u00a0 \u00a0 \u00a0 \u00a0 \u00a0 \u00a0\n\nWEIBO at\u00a0http://e.weibo.com/ithongkong", "employment_types": ["Full Time", "Permanent"], "selling_points": ["2-3 years' relevant experience for fashion brands", "Design a wide range of corporate promotional", "Graphic design house background is welcome"], "locations": ["Southern Area"], "categories": ["Design", "Fashion", "Graphics", "Multi-media"], "post_time": "2022-01-11T10:01:59Z", "salary": {"currency": null, "max": null, "min": null, "period": "monthly", "term": null}, "salary_visible": false, "title_keywords": ["assistant", "graphic designer"], "responsibilities": ["collaborate with", "advertisements", "edm", "graphic design", "data", "budget", "marketing collaterals", "quality", "design", "teams", "communication", "website", "brand guidelines", "recruitment", "visual", "marketing materials", "facebook", "liaise with suppliers"], "requirements": {"degrees": ["degree holder"], "majors": ["graphic design"], "languages": [], "language_level": [], "hard_skills": ["facebook", "illustration"], "soft_skills": ["passion for", "keen", "communication", "eye for detail", "creative"], "languages_combined": []}, "experience_required": {"duration": ["1-2 years"], "field": ["agency", "graphic design", "brand"]}}, {"job_id": "100003009029716", "location_code": "hk", "company": "KEO.W International Limited", "job_title": "Graphic Designer", "description": "Responsibility:\n\n\nResponsible for concept development, graphic design & artwork adaptation\nHandle projects independently from creative concept to final artwork\nProvide creative direction and able to conceptualize and develop ideas into visual image and design and assist Creative Director to develop artwork layout\nPerform ad hoc tasks as assigned\nRequirement:\n\n\nProficiency in PC, Photoshop and Illustrator\nStrong creativity with good fashion sense and knowledge of seasonal trends, themes, color, materials, styling and fit\nAble to withstand pressure & meet tight working schedule\nGood photography skill would be a plus\nHigh emotional intelligence\nGood team player and willing to work with team members\nGood communication skills, creative with strong aesthetic, self-motivated and attentive to details\nStrong problem-solving ability, good presentation skill and organized work style, with passion in design\nGood command in Chinese and English\nImmediately available is preferred\nFor interested parties, please submit your resume with the following information by clicking the button \"Apply Now\" as below:\n\n\nPhotograph (Portrait)\nWork Portfolio*\nCurrent Salary\nExpected Salary\nDate of Availability\n*The work portfolio must be submitted for the job application.\n\nAll information received will be kept strictly confidential and used for recruitment purposes only. The shortlisted candidates will be contacted via telephone.", "employment_types": ["Full Time"], "selling_points": ["Proficiency in PC, Photoshop and Illustrator", "Strong creativity with good fashion sense", "Immediately available is preferred"], "locations": ["Kwun Tong Area"], "categories": ["Design", "Fashion", "Graphics", "Multi-media"], "post_time": "2022-01-07T06:01:09Z", "salary": {"currency": null, "max": null, "min": null, "period": "monthly", "term": null}, "salary_visible": false, "title_keywords": ["graphic designer"], "responsibilities": ["ideas", "graphic design", "ad hoc tasks", "design", "develop", "visual", "develop artwork"], "requirements": {"degrees": [], "majors": [], "languages": ["english", "chinese"], "language_level": ["good command"], "hard_skills": ["presentation skill", "plus", "problem-solving", "illustrator", "pc", "photoshop"], "soft_skills": ["presentation skill", "communication skills", "good team player", "self-motivated", "organized", "attentive to details", "passion in", "problem-solving", "creative"], "languages_combined": [{"language": "english", "language_level": ["good command"]}, {"language": "chinese", "language_level": ["good command"]}]}, "experience_required": {"duration": [], "field": []}}, {"job_id": "100003009026208", "location_code": "hk", "company": "Farfetch HK Production Limited", "job_title": "Fashion Stylist (Full Time/Freelance)", "description": "THE ROLE\n\nReporting to the Assistant Studio Manager, you will prepare the outfit rails each day ready for the shoot and ensure they achieve their daily targets. Using your fashion and brand knowledge, you will develop the Farfetch visual aesthetic and image quality.\n\nWHAT YOU'LL DO\nYou'll style and shoot inspiring on brand, on trend looks daily\nYou'll work with photographer on set to direct model and select best poses/imagery\nYou'll work with the Studio coordinator to try and find ways to improve the process and make it more efficient whilst ensuring the quality is maintained\nYou'll ensure all 'crucial' new brands are researched before being shot\nWHO YOU ARE\n2 +years of experience as a Stylist, either in-house or as a freelancer\nExtensive knowledge of styling luxury brands\nAbility to maintain a calm and composed temperament in a frenetic environment, and ensure issues are deflected from the studio\nFlexible 'can-do', up-beat attitude\nRunway, trend and brand knowledge\nUnderstanding of needs from both a creative and production perspective\nEQUAL OPPORTUNITIES STATEMENT\nFARFETCH is an equal opportunities employer ensuring that all applicants are treated equally and fairly throughout our recruitment process. We are determined that no applicant experiences discrimination on the basis of sex, race, ethnicity, religion or belief, disability, age, gender identity, ancestry, sexual orientation, veteran status, marriage and civil partnership, pregnancy and maternity, or any other basis prohibited by applicable law. We continue to build our consciously inclusive culture as part of our Positively FARFETCH strategy throughout our business, partnerships and communities.", "employment_types": ["Full Time", "Permanent"], "selling_points": ["High Volume In-House Product Shooting- Model&Still", "Collaboration & Exchange w/ International Studios", "Vibrant, Energetic Start-Up Team Environment"], "locations": ["Ngau Tau Kok"], "categories": ["Media & Advertising", "Production", "Design", "Fashion", "E-commerce", "Others"], "post_time": "2022-01-07T13:41:53Z", "salary": {"currency": null, "max": null, "min": null, "period": "monthly", "term": null}, "salary_visible": false, "title_keywords": [], "responsibilities": ["reporting", "quality", "develop", "maintain", "visual", "recruitment process"], "requirements": {"degrees": [], "majors": [], "languages": [], "language_level": [], "hard_skills": ["make", "no"], "soft_skills": ["efficient", "flexible", "determined", "calm", "inspiring", "can-do", "creative", "extensive"], "languages_combined": []}, "experience_required": {"duration": ["2 +years"], "field": []}}, {"job_id": "100003009031029", "location_code": "hk", "company": "Hop Lun (HK) Ltd", "job_title": "Senior Brands Manager", "description": "The job incumbent will have full profit and loss responsibility of assigned brands including existing and upcoming brands.\n\nResponsibilities:\n\nSet brand strategy, including setting of brand positioning, brand vision and value proposition\nLead strategic product research, design, development and production, pricing, place / channel, proposition and project implementation\nDrive sales to achieve and exceed an annual plan based on sales, margin and profit for each market / channel\nFormulate the media & communications strategy and monitor all relevant performance and directions\nManage the budget for branding, staff costs and other overheads\nMonitor margin, profit or other key performance indicators on a regular basis\nPrepare relevant presentations and support materials for any potential buyers\nDevelop brand positioning, distribution, marketing and pricing strategy for new upcoming brands\nHandle ad-hoc tasks as assigned\nRequirements:\n\nDegree or above in Business, Marketing or discipline that focus on Brand Management\nStrong at communication, presentation, marketing and planning skills\nExcellent business acumen and strong at analyzing business trends and numbers\nProactive in initiating new ideas\nKnowledge of different marketing tools and other social media platforms is preferable\nHigh proficiency in English and Chinese\nGood knowledge in Microsoft Excel, Word and PowerPoint\nKnowledge in AI and/or Photoshop will be an advantage\nWell organized and able to work independently under pressure\nMay require occasional business travels when possible\nWe are an equal opportunity employer and welcome applications from all qualified candidates. Personal data collected will be treated in strict confidence and be used solely for recruitment purposes within Hop Lun Group. Applicants who are not contacted within one month may consider their applications unsuccessful and their information will be destroyed after one year.", "employment_types": ["Full Time", "Permanent"], "selling_points": ["Set brand strategies e.g. marketing, pricing", "Lead product design, assortment, production team", "5 days work, AL 20 days, Medical, Flextime"], "locations": ["Lai Chi Kok"], "categories": ["Design", "Fashion", "Marketing / Public Relations", "Marketing - Brand / Product Management", "Merchandising & Purchasing", "Woven / Knit"], "post_time": "2022-01-07T08:50:50Z", "salary": {"currency": null, "max": null, "min": null, "period": "monthly", "term": null}, "salary_visible": false, "title_keywords": ["manager"], "responsibilities": ["ad-hoc tasks", "budget", "monitor", "implementation", "design", "presentations", "develop", "plan", "drive sales", "costs"], "requirements": {"degrees": ["degree or above"], "majors": ["business", "marketing"], "languages": ["english", "chinese"], "language_level": ["proficiency"], "hard_skills": ["ai", "hop", "word", "powerpoint", "microsoft excel", "photoshop", "focus", "acumen"], "soft_skills": ["planning skills", "work independently", "confidence", "under pressure", "well organized", "communication", "business acumen", "focus", "proactive", "presentation"], "languages_combined": [{"language": "english", "language_level": ["proficiency"]}, {"language": "chinese", "language_level": ["proficiency"]}]}, "experience_required": {"duration": [], "field": []}}, {"job_id": "100003009026200", "location_code": "hk", "company": "Farfetch HK Production Limited", "job_title": "Part Time Fitting Assistant", "description": "THE ROLE\n\nReport to Assistant Studio Manager, you will work with stylists, photographers, and models in the studios to provide accurate and appropriate fit information to the customer. By providing the best fitting advice, customers will make online purchases easier and reducing the returns which are caused by the wrong fitting.\nWHAT YOU'LL DO\nYou'll provide accurate fit information to the customer through the Size and Fit copy.\nYou'll meet daily studio targets while maintaining a high-level of consistency.\nYou'll share any relevant brand, category or model fit advice necessary with the team leader so it can be shared with the team.\nYou'll work with stylists and photographers to keep a smooth workflow.\nYou'll ensure the correct size is being shot on the model while balancing the stylist's creative direction.\nYou'll attend global fitting team meetings and supporting global project, contribute to the team's growth and awareness through brand and competitor analysis.\nYou'll update the potential fitting phrases will increase the customer shopping experience\nYou'll provide weekly report to align the team quality and for training purpose\nYou'll work with the Model and support the model coating process.\nWHO YOU ARE\nHigher Diploma or above in Fashion Design or related discipline\nUnderstand Women and Menswear international sizing.\nA sound knowledge of Women and Menswear brands, trends, technical terms and fabric knowledge for both RTW and accessories.\nHave experience in a studio environment, in retail, customer service, garment technology, fashion design or similar areas would be advantage\nA proven ability to work quickly and efficiently with accuracy and attention to detail.\nYou must be dedicated, proactive, have a can-do attitude and happy being hands-on.\nExcellent sense of prioritization and timing\nEQUAL OPPORTUNITIES STATEMENT\nFARFETCH is an equal opportunities employer ensuring that all applicants are treated equally and fairly throughout our recruitment process. We are determined that no applicant experiences discrimination on the basis of sex, race, ethnicity, religion or belief, disability, age, gender identity, ancestry, sexual orientation, veteran status, marriage and civil partnership, pregnancy and maternity, or any other basis prohibited by applicable law. We continue to build our consciously inclusive culture as part of our Positively FARFETCH strategy throughout our business, partnerships and communities.", "employment_types": ["Full Time", "Permanent"], "selling_points": ["Leading online luxury fashion retail platform", "Collaboration & Exchange w/ International Studios", "Vibrant, Energetic Start-Up Team Environment"], "locations": ["Ngau Tau Kok"], "categories": ["Design", "Fashion", "E-commerce", "Others"], "post_time": "2022-01-07T13:42:22Z", "salary": {"currency": null, "max": null, "min": null, "period": "monthly", "term": null}, "salary_visible": false, "title_keywords": ["assistant"], "responsibilities": ["maintaining", "analysis", "quality", "design", "customer service", "recruitment process", "report"], "requirements": {"degrees": ["higher diploma or above"], "majors": ["design"], "languages": [], "language_level": [], "hard_skills": ["no", "make", "analysis"], "soft_skills": ["proactive", "creative", "determined", "can-do attitude", "hands-on", "customer service", "attention to detail", "smooth", "accurate"], "languages_combined": []}, "experience_required": {"duration": [], "field": ["garment", "retail", "customer service", "fashion design"]}}, {"job_id": "100003009033999", "location_code": "hk", "company": "Alexis Services Limited", "job_title": "Lead - Technical (Textile & Manufacturing)", "description": "Responsibilities:\n\nPrepare regular analysis reports\nRespond to customers\u2019 queries and complaints effectively\nCoordinate regular stock take replenishment\nAssist in organizing company\u2019s activities and social activities\nProvide general clerical support including data entry and assisting in preparation of documents\nLiaising effectively with internet and external parties to ensure smooth operations\nCoordinate ad-hoc duties as assigned\n\nRequirements:\n\nExperienced candidates will be considered as brand executive\nFresh graduates will also be considered\nGood common sense, Good reporting skills\nGood command of spoken and written Chinese and English\nExcellent communication skills\nDetailed oriented, responsible, multi tasking, work under pressure, self-motivated, open-minded\nKnowledge in different social media platforms\nProficient in MS Office especially Excel, PowerPoint and computer knowledge\n\nCompany Benefits:\n\n5-days work\nPaid annual leave\nBirthday holiday\nBank holiday\nYear end bonus\nShopping discount\nOn job training\nGreat promotion opportunities\n\nCompetitive remuneration and benefit package will be offered to the right candidate. Please send your full resume with expected salary to Human Resources Department by clicking \"Apply Now\"\n\nAll information collected will be kept strictly confidential and will only be used for recruitment purpose.", "employment_types": ["Full Time"], "selling_points": ["Experience in developing 3D solution", "Agile software development with Scrum or Agile", "Oversee technology task, technical & architectural"], "locations": ["Cheung Chau Area"], "categories": ["Design", "Fashion", "Information Technology (IT)", "IT Project Management / Team Lead", "Merchandising & Purchasing", "Textiles"], "post_time": "2022-01-10T02:21:46Z", "salary": {"currency": null, "max": null, "min": null, "period": "monthly", "term": null}, "salary_visible": false, "title_keywords": ["lead"], "responsibilities": ["data entry", "analysis reports", "external parties", "clerical support", "replenishment", "stock take", "coordinate", "ensure smooth operations", "ad-hoc duties"], "requirements": {"degrees": [], "majors": [], "languages": ["english", "chinese"], "language_level": ["good command"], "hard_skills": ["excel", "powerpoint", "ms office"], "soft_skills": ["communication skills", "self-motivated", "detailed oriented", "responsible", "open-minded", "work under pressure"], "languages_combined": [{"language": "english", "language_level": ["good command"]}, {"language": "chinese", "language_level": ["good command"]}]}, "experience_required": {"duration": [], "field": []}}, {"job_id": "100003009032189", "location_code": "hk", "company": "aalis", "job_title": "Brand Assistant (Fresh Graduate Welcome)", "description": "\u00a0Job Duties\n\nPattern making, approve the basic size & shape of mold cups\nApprove the full sizes of foam pads based on the pre-approved fit-size\nCheck and measure sample based on full-size grading\nGenerate the measurement specification and mold chart for production\nAssist in fitting and make any change if required\nIssue sample order sheet to sewing team and follow up the status\nMeet with relevant department and customer in style review and pre-production meeting\nWork with sourcing team to solve issues related to materials\n\nJob Requirements\n\nTertiary-educated, preferably with certificates in pattern-making for intimate apparel\nMinimum\u00a08 years relevant experience in Pattern Making/ Technical Design\u00a0or lingerie's' fitting\nPossessing some knowledge\u00a0in computer pattern making and grading is an advantage\nProficient in MS Office Application, Photoshop and Illustrator\nGood spoken & written English and Chinese, knowledge in Mandarin\n\nWe offer competitive remuneration package including 5-day work, discretionary bonus, medical & group life insurance to the right candidate. Interested parties please send your full resume with current & expected salary by clicking \"APPLY NOW\"\n\nFor more details on Clover Group, please visit our website: http://www.clover.com.hk\u00a0\u00a0\n\nWe are an equal opportunity employer and we welcome applications from all qualified candidates. Information provided will be treated in strict confidence and used for recruitment purposes within our Group and our related companies only. Applicants not having heard from us within 6 weeks from the date of this advertisement may consider their application unsuccessful. All personal data of unsuccessful applications will be destroyed after one full calendar year.", "employment_types": ["Full Time", "Permanent"], "selling_points": ["Provide administrative support", "Prepare regular analysis reports", "Advanced computer knowledge is a plus"], "locations": ["Not Specified"], "categories": ["Design", "Fashion", "Marketing / Public Relations", "Marketing - Brand / Product Management", "Public Relations - Event Management"], "post_time": "2022-01-07T10:25:14Z", "salary": {"currency": null, "max": null, "min": null, "period": "monthly", "term": null}, "salary_visible": false, "title_keywords": ["brand assistant"], "responsibilities": ["pre-production", "review", "measurement"], "requirements": {"degrees": [], "majors": [], "languages": ["english", "chinese", "mandarin"], "language_level": ["good"], "hard_skills": ["illustrator", "photoshop", "ms office"], "soft_skills": [], "languages_combined": [{"language": "english", "language_level": ["good"]}, {"language": "chinese", "language_level": ["good"]}, {"language": "mandarin", "language_level": ["good"]}]}, "experience_required": {"duration": ["minimum 8 years"], "field": ["relevant experience", "design"]}}, {"job_id": "100003009026216", "location_code": "hk", "company": "Farfetch HK Production Limited", "job_title": "Photographer (Freelance)", "description": "TI/Dip in Fashion Design / Product Design / Graphic Design / Interior Design\nMin\u00a01 yr experience in either one of below:\n\no\u00a0\u00a0\u00a0\u00a0\u00a0\u00a0\u00a0\u00a0\u00a0 Fashion Designer / Senior Fashion Designer / Chief Fashion Designer / Fashion Design Manager for Ladywear / Menswear / Kidswear - Woven / Denim / Cut & Sewn Knit / Sweater Garment -\u00a0Fashion /\u00a0Casual Wear /\u00a0Executive Suit /\u00a0Formal Wear /\u00a0Suit / Shirt /\u00a0Kidswear / Babywear / Underwear / Lingerie / Sportsbra / Sportswear/ Outerwear / Pants / Jeans / Swimwear / Sleepwear / Costume.\n\n\u00a0\u00a0\u00a0\u00a0 or\n\no\u00a0\u00a0\u00a0\u00a0\u00a0\u00a0\u00a0\u00a0\u00a0 3D Fashion Designer / Senior 3D Fashion Designer \u00a0\n\u00a0\u00a0 Dip, 3-8 yrs experience in 3D Fashion Design (CLO/Keyshot/Optitex/ViZoo/Stage 3D) for Ladies / Men Fashion or Casual Wear or Underwear.\n\n\n\u00a0\u00a0\u00a0\u00a0\u00a0 or\n\no\u00a0\u00a0\u00a0\u00a0\u00a0Technical Designer / Senior Technical Designer / Technical Design Manager\u00a0for Underwear / Sportsbra / Sportswear / Swimwear / Sleepwear / Outerwear.\n\n\u00a0\u00a0\u00a0\u00a0\u00a0 or\n\no\u00a0\u00a0\u00a0\u00a0\u00a0 Fashion Graphic Designer / Senior Fashion Graphic Designer for Fashion / Casual Wear / Kidswear / Sweater / T-Shirt / Fabric Print.\n\n\u00a0\u00a0\u00a0\u00a0\u00a0 or\n\no\u00a0 \u00a0\u00a0 Product Designer / Senior Product Designer / Product Design Manager for\u00a0Eyeglasses / Watch / Handbag / Backpack / Luggage /\u00a0Shoes / Fashion Accessories / Garment Trims / Fashion Jewellery /\u00a0Toys / Pre-School Products / Gift & Premium / Electronic Game / Internet Game / Fashion Dolls / Consumer Electronic Products / Audio Products / Electrical Appliance / LED / Lighting / Gardening / Gift & Premium / Handbag / Backpack / Luggage /\u00a0Shoes / Houseware / Kitchenware / Garment Accessories / Furniture / Home Decoration /\u00a0Home Textile / Smoking Accessories / Lighter / Sports Goods / Pet Accessories / Seasonal Items / Stationery / PC Acc / Charger / Mobile Acc / Home Care Products / Elec Alarm .\n\n\u00a0\u00a0\u00a0\u00a0\u00a0\u00a0or\n\n\u00a0o\u00a0 Draftsman / Asst / Interior Designer / Visual Merchandiser\u00a0/\u00a0Project Manager for Fashion\u00a0Chain\u00a0Shops / Shoes Chain Shops / Window Display / Residential / Commerical Bldg / Office / Eyewear Chain Shops / Furniture Chain Shops / Exhibition.\u00a0\u00a0\u00a0\u00a0\n\n\u00a0\u00a0\u00a0\u00a0\u00a0 or\n\no\u00a0\u00a0Graphic Designer / Digital Graphic Designer / Senior Graphic Designer for\u00a0Advertising / Packaging / Handtag / Label / Promotion Matters / Online Selling / Window Display / Fashion Shop / Exhibition / Digital Graphic preferred.\u00a0\u00a0\u00a0\u00a0\n\n\u00a0\u00a0\u00a0\u00a0\u00a0 or\n\n\u00a0o\u00a0\u00a0Web Designer / Web Developer / Multimedia Designer for Online Advisement / Internet Service / Website / E-Commerce/ Rebranding / Flash / HTML .\n\n\n\u00a0Familiar with HK / China / USA / EU / South America Markets preferred.\n\nFamiliar with Illustrator / Photoshop / Optitex / Apex / Mac preferred\nWork in HK / PRC Trip / PRC Stay\n\nSalary Range: HK$12K-$60K / Month\u00a0\u00a0\n\n*** Please send your detailed resume in \u201cword format\u201d including \" Expected Salary \", \u201cCompany Nature & Product\u201d & \u201cAvailability Date\u201d to our \u201cE-mail Address\u201d shown above or fax to \u201c2780 2672\u201d or by clicking \u201cApply Now\u201d.", "employment_types": ["Full Time", "Permanent"], "selling_points": ["High Volume In-House Product Shooting- Model&Still", "Collaboration & Exchange w/ International Studios", "Vibrant, Energetic Start-Up Team Environment"], "locations": ["Ngau Tau Kok"], "categories": ["Media & Advertising", "Others", "Design", "Fashion", "Photography / Video"], "post_time": "2022-01-07T13:41:22Z", "salary": {"currency": null, "max": null, "min": null, "period": "monthly", "term": null}, "salary_visible": false, "title_keywords": ["photographer"], "responsibilities": ["advertising", "graphic design", "stationery", "design", "website", "product design", "visual", "audio"], "requirements": {"degrees": ["dip"], "majors": ["graphic design", "design"], "languages": [], "language_level": [], "hard_skills": ["acc", "apex", "web", "e-commerce", "illustrator", "html", "word", "mobile", "multimedia", "flash", "pc", "photoshop"], "soft_skills": ["detailed"], "languages_combined": []}, "experience_required": {"duration": [], "field": ["fashion design"]}}, {"job_id": "100003009025575", "location_code": "hk", "company": "Win Paradise Limited", "job_title": "ASST DESIGNER / DESIGNER / SR DESIGNER / DESIGN MANAGER", "description": "Lauris Walton is partnering with a fast-growing brand to seek a Product Designer / Fashion Designer based in Hong Kong! This job is an excellent opportunity for young design professionals to gain global exposure and a fast-growing brand with a friendly culture and working environment.\n\nKey Benefits:\n\nGreat opportunity to train up your creativity and design skills\nLearning & Development Opportunity\nFriendly and multinational work environment\nCareer progression opportunity\nGlobal / Regional Exposure\nConvenient working location and excellent office environment\n\nRole requirements:\n\nDegree or higher diploma in industrial design or product design\nFamiliar with Rhinoceros 3D, Adobe Photoshop, Adobe Illustrator, Adobe InDesign AutoCAD\n2-4 years work experience in product design / industrial design\nExperience in retail/eyewear is a plus\nFluent in English is essential (Chinese is a plus)\nFriendly, enjoy working as a team, detail-minded, multi-tasking\n\nYoung Design Pros! Don\u2019t miss this excellent opportunity and apply today!\n\nInterested applicants, please apply with your resume with current and expected salary, notice period, and portfolio. Due to the high volume of applications, only shortlisted candidates will be notified. For more job opportunities, please visit our website at\u00a0www.lauriswalton.com/jobs.", "employment_types": ["Full Time", "Permanent"], "selling_points": ["- Dip in Fashion/Product/Graphic/Interior Design", "- 1-8  yrs relevant exp.", "- Garment/Fashion Acc/Hdbag/Elec/Watch/Eyewear/VM."], "locations": ["Not Specified"], "categories": ["Design", "Fashion", "Industrial / Product", "Interior"], "post_time": "2022-01-09T16:25:41Z", "salary": {"currency": null, "max": null, "min": null, "period": "monthly", "term": null}, "salary_visible": false, "title_keywords": ["designer", "design manager"], "responsibilities": ["design"], "requirements": {"degrees": [], "majors": [], "languages": [], "language_level": [], "hard_skills": [], "soft_skills": ["friendly"], "languages_combined": []}, "experience_required": {"duration": [], "field": []}}, {"job_id": "100003009026602", "location_code": "hk", "company": "Lauris Walton International Limited", "job_title": "Fashion Designer / Product Designer \u2013 MNC \u2013 Excellent Opportunity!", "description": "Responsibilities:\n\nTo support the design functions of apparel from analyzing market trend, formulating creative direction to transforming the creative design into marketable collections to our customers\nIdentifying the market / style needs and creating complete tech packs for fitting / production\nAttend\u00a0overseas fair as well as conduct market visits to obtain the most innovative information\nSupport the product team to ensure the design is brand appropriate for different region, fashion vision, fit, fabric, color and prints across all categories\n\nRequirements:\n\nDegree holder or above in Fashion Design, Textile & Clothing or related disciplines;\nAt least 5 years solid experience in apparel (women), with exposure in sports wear will be an advantage;\nWith strong sense of fashion, materials and yarn, garment technical know-how and graphic artwork application knowledge\nExcellent communication & presentation skills;\nStrong in handling MAC software, particularly in Illustrator;\nGood command in spoken and written Chinese, English and Putonghua;\nFrequent travel to China is required\n\nPlease\u00a0 email your CV\u00a0 for application with expected salary by clicking 'Apply Now'.\n\n(All personal data collected will be used for recruitment purpose only.)", "employment_types": ["Full Time", "Permanent"], "selling_points": [], "locations": ["Central"], "categories": ["Design", "Fashion", "Industrial / Product", "Others"], "post_time": "2022-01-06T08:23:31Z", "salary": {"currency": null, "max": null, "min": null, "period": "monthly", "term": null}, "salary_visible": false, "title_keywords": ["product designer", "fashion designer"], "responsibilities": ["design"], "requirements": {"degrees": ["degree holder"], "majors": ["related disciplines", "design"], "languages": ["putonghua", "english", "chinese"], "language_level": ["good command"], "hard_skills": ["illustrator"], "soft_skills": ["communication", "presentation skills"], "languages_combined": [{"language": "putonghua", "language_level": ["good command"]}, {"language": "english", "language_level": ["good command"]}, {"language": "chinese", "language_level": ["good command"]}]}, "experience_required": {"duration": ["at least 5 years"], "field": []}}, {"job_id": "100003009031050", "location_code": "hk", "company": "BW Global (HK) Limited", "job_title": "Technical Support Manager (Fashion Technology)", "description": "About us:\n\nBrowzwear is the leading provider of 3D fashion design, development, and merchandising solutions. Our mission is to revolutionize the apparel industry with our truly disruptive 3D technology, providing the tools needed to achieve that goal. We work with some of the biggest and most well-known global companies in the industry.\n\nWe\u2019re looking for a talented individual to manage and lead our Hong Kong Technical Support and Training Team in its ongoing quest to provide top quality support to our growing client base in Asia.\u00a0\u00a0\n\nYou are:\n\nAn experienced and professional support team leader, well versed in the challenges of working with remotely located team members and stakeholders. You have the necessary management, communication, organizational, and people skills to inspire and motivate your colleagues. You are cool, calm, and collected under pressure, able to prioritize tasks, and passionate about the overall customer service experience.\n\nUltimately, you would have to lead and manage support team professionals to deliver outstanding customer support. In detail, the Technical Support Manager will:\u00a0\n\nManage, direct, and monitor the day-to-day activities of the Hong Kong Technical Support and Training Team as well as working with team members in the setting and review of goals and personal development plans.\nBe responsible for hiring and onboarding new team members. You will be responsible for leading the department to meet regional business and operation targets.\nGuide the relevant team to resolve technical support issues by identifying solutions, collaborating with the applicable internal teams, and handling client and internal technical escalations.\nIdentify and communicate potential product improvements; collect and share metrics about technical support performance.\nGuide the relevant team to provide customer training, including scheduling and resourcing training sessions and leading the team in updating training materials to keep pace with all product releases.\u00a0\nEvaluate and enhance regional training methodology and delivery and collect feedback on trainers to determine the effectiveness and identify areas for growth.\u00a0\nCollaborate with the Global Learning Team and Product Development Team about the development of e-learning content.\u00a0\nWork directly with our customers, building and maintaining good relationships as well as coaching the Support Team to do so as part of the overall customer experience.\n\nREQUIREMENTS\n\n5 years of relevant experience in a support team leadership/management role in the fashion technology industry\u00a0\nFull fluency in English, Mandarin and Cantonese\u00a0\nPossesses excellent leadership, analytical, and people skills\nOrganization, project management, and time management skills\nExperienced with VStitcher, apparel 3D technology, 3D design software and production pipeline\u00a0\nPossesses relevant customer service experience, understanding issue and relationship management\nExcellent written and verbal communication skills\nComputer proficiency, including (but not limited to) Microsoft 365", "employment_types": ["Full Time"], "selling_points": ["Be part of disruptive 3D fashion technology", "Interact with global fashion and apparel companies", "Lead technical support team"], "locations": ["Lai Chi Kok"], "categories": ["Design", "Fashion", "Information Technology (IT)", "Support", "Technical / Functional Consulting"], "post_time": "2022-01-07T08:51:48Z", "salary": {"currency": null, "max": null, "min": null, "period": "monthly", "term": null}, "salary_visible": false, "title_keywords": ["technical support", "manager"], "responsibilities": ["collaborate with", "management", "software", "maintaining", "technical support", "customer service experience", "quality", "merchandising", "design", "monitor", "communication", "review", "teams", "client base", "scheduling", "evaluate", "project management", "plans"], "requirements": {"degrees": [], "majors": [], "languages": ["cantonese", "english", "mandarin"], "language_level": ["fluency"], "hard_skills": ["goal", "cool", "project management"], "soft_skills": ["communication skills", "under pressure", "able to prioritize", "responsible", "time management skills", "organizational", "calm", "communication", "project management", "customer service", "learning", "leadership", "passionate about"], "languages_combined": [{"language": "cantonese", "language_level": ["fluency"]}, {"language": "english", "language_level": ["fluency"]}, {"language": "mandarin", "language_level": ["fluency"]}]}, "experience_required": {"duration": ["5 years"], "field": ["management", "customer service", "relevant experience", "team"]}}, {"job_id": "100003009024074", "location_code": "hk", "company": "Farfetch HK Production Limited", "job_title": "Styling Intern", "description": "Job Requirements:\n\n\nDegree holder in Fashion, Textiles or Graphic Design\n2-3 years of relevant design experience, preferred in Garment\nWith knowledge in software Browzwear is preferred\nGood command of written and spoken, English and Chinese\nProficiency in Illustrator, Photoshop and MS Office\nStrong research and analysis skills\nCreative with ability to explore assemble methods and material used\nIndependent, from research, design to supervision of samples made\nCandidate with less experience will be considered as Assistant Designer\nImmediately available is preferred\n\n\n\nWe offer attractive remuneration package and career development opportunities for the right candidate.\n\nFor qualified candidates, please send your application with\u00a0full resume, stating salary expectations\u00a0to the HR Department by e-mail to \u201chr at hk.bogartlingerie.com\u201d, or by \u201cApply Now\u201d via JobsDB for interview.\n\nPersonal data provided by job applicants will be used for recruitment purposes only. Applicants who are not invited for interviews within six weeks may consider their applications unsuccessful. All personal data of unsuccessful applicants will be destroyed.", "employment_types": ["Part Time", "Temporary", "Freelance"], "selling_points": ["APAC Production House of Luxury Ecommerce Platform", "High Volume In-House Product Shooting- Model&Still", "Small Team in Proactive StartUp Studio Environment"], "locations": ["Aberdeen"], "categories": ["Design", "Fashion", "Manufacturing", "Garment / Textile", "Quality Assurance, Control & Testing / ISO"], "post_time": "2022-01-07T13:43:18Z", "salary": {"currency": null, "max": null, "min": null, "period": "hourly", "term": null}, "salary_visible": false, "title_keywords": ["intern"], "responsibilities": ["graphic design", "analysis", "software", "design"], "requirements": {"degrees": ["degree holder"], "majors": ["graphic design"], "languages": ["english", "chinese"], "language_level": ["good command"], "hard_skills": ["analysis", "ms office", "illustrator", "photoshop"], "soft_skills": ["creative", "independent"], "languages_combined": [{"language": "english", "language_level": ["good command"]}, {"language": "chinese", "language_level": ["good command"]}]}, "experience_required": {"duration": ["2-3 years"], "field": ["garment", "designer", "design"]}}, {"job_id": "100003009029077", "location_code": "hk", "company": "Bestseller United China Limited", "job_title": "3D Artist NBT", "description": "The incumbent will be responsible for the design and/or special make-up of a selective range of our Sport & Lifestyle apparel line. He/she should be able to identify and provide the latest trend, design new collection, and work closely with our merchandisers to ensure proper fitting and silhouette for samples production.\n\nJob duties:\n\nResponsible for design functions of our brand from trend analysis, creative direction projection, design of marketable collections to completion of specification for fitting and production\nResearch latest fashion trend, material and trim sourcing, colors, theme boards\nTranslate design directions and concepts to technical drawings & size fitting\nFollow up the progress and communication with merchandiser on fabric development and sampling\nSupport in tradeshow preparation and presentation\n\nRequirements:\n\nDiploma graduate in Fashion Design, Graphic Design or related disciplines\nMinimum 2 years\u2019 solid experience in Lifestyle / Sportswear for Women\u2019s and Men\u2019s\nGood knowledge in sourcing of fabric and trim, creative and strong fashion sense\nPreferably with strong participation in sports\nProficient in illustrator, Freehand and Photoshop\nGood command of spoken & written English and Chinese\nGraphical skills and knowledge is preferred\n\nWe offer competitive remuneration package with\u00a0a wide range of fringe benefits including\n\n5-day work week\nDiscretionary Bonus\nComprehensive Medical Coverage\nStaff Shopping Discount\nNon-contributory Retirement Benefits Scheme\nBirthday Leave\n\nInterested parties please send resume with present and expected salary to Human Resources Department, Swire Resources Limited,\u00a012/F Kingston International Centre,\u00a019 Wang Chiu Road Kowloon Bay,\u00a0Hong Kong\u00a0or by\u00a0clicking the below \"Apply Now\" button.\n\nSwire Resources Limited is Equal Opportunity Employer\n", "employment_types": ["Internship"], "selling_points": [], "locations": ["Tsim Sha Tsui"], "categories": ["Design", "Fashion"], "post_time": "2022-01-07T03:55:32Z", "salary": {"currency": null, "max": null, "min": null, "period": "monthly", "term": null}, "salary_visible": false, "title_keywords": [], "responsibilities": ["communication", "analysis", "technical drawings", "design"], "requirements": {"degrees": ["diploma"], "majors": ["related disciplines", "graphic design", "design"], "languages": ["english", "chinese"], "language_level": ["good command"], "hard_skills": ["illustrator", "photoshop"], "soft_skills": ["creative"], "languages_combined": [{"language": "english", "language_level": ["good command"]}, {"language": "chinese", "language_level": ["good command"]}]}, "experience_required": {"duration": ["minimum 2 years"], "field": []}}, {"job_id": "100003009027223", "location_code": "hk", "company": "Swire Resources Ltd", "job_title": "Fashion Graphic Designer", "description": "Responsibilities\n\nOversee the technology stack, technical and architectural design, and solution of the digital products. Enforcing technical and architectural design guidelines\nLead & manage the technical team internal or / and external resources, mentoring, and enhancing and maintaining a best in class digital development team\nContributes to technical delivery plans and timelines with effective planning skills\nUnderstand and design network infrastructure of on-premises or cloud deployment of applications\nReview the design, implementation and quality of vendor\u2019s deliverables. Ensure they meet the company requirements and development standard\nCommunicate with upstream and downstream system teams for any planned technical deliveries\nActively contributes to technology engineering practice by sharing subject matter expertise from their area of specialism, best practice and learnings\nDevelop and maintain documentation and deliver communication sessions to different stakeholders\nWork collaboratively and effectively in virtual teams across Hong Kong and China\n\nRequirements:\n\nBachelor\u2019s degree in Computer Science, IT or equivalent required\n10 years of Digital Product Development & management experience in B2B/B2C domain\nSolid experience in developing enterprise level of web and mobile applications (iOS/Android) with track record\nProficiency in, at least, one modern programming language and framework such as Java, PHP, Swift/Objective-C, HTML5/CSS, React Native, Kotlin, vue.js/react.js, node.js, etc.\nExperience in DevOps Continuous Integration and Continuous Deployment, Code Analysis and Test Automation\nExperience in designing, developing and deploying solutions using container technologies in Cloud (eg. AWS, Azure, AliCloud)\nExposure to Docker, Kubernetes Container Orchestration is a plus\nExperience in Agile software development with Scrum or other Agile methodologies/frameworks\nExperience in developing 3D solution is an advantage\nExperience and ability to coach, develop, motivate and manage a team\nDemonstrated leadership, relationship management and change management experience and skills gained is a diversified organization\nExcellent communication, interpersonal, planning and organization skills\nExperience in textile and manufacturing industry is an advantage", "employment_types": ["Full Time", "Permanent"], "selling_points": ["Diploma graduate in Fashion Design/ Graphic Design", "2 yrs\u2019 relevant exp in Sportswear & Lifestyle", "Proficient in illustrator, Photoshop and freehand"], "locations": ["Kowloon Bay"], "categories": ["Design", "Fashion", "Graphics", "Others"], "post_time": "2022-01-06T09:24:45Z", "salary": {"currency": null, "max": null, "min": null, "period": "monthly", "term": null}, "salary_visible": false, "title_keywords": ["fashion graphic designer"], "responsibilities": ["network infrastructure", "communicate with", "maintaining", "guidelines", "review", "quality", "implementation", "design", "teams", "develop", "communication", "maintain documentation", "plans", "planning"], "requirements": {"degrees": ["degree", "bachelor"], "majors": ["it", "computer science"], "languages": [], "language_level": [], "hard_skills": ["plus", "azure", "agile", "web", "react native", "java", "css", "integration", "kotlin", "devops", "objective-c", "aws", "container", "php", "react", "analysis", "mobile", "deployment", "programming", "swift", "code", "android"], "soft_skills": ["agile", "communication", "organization skills", "leadership", "interpersonal"], "languages_combined": []}, "experience_required": {"duration": ["10 years"], "field": ["management", "devops", "developing", "software development", "textile", "digital", "product development", "manufacturing industry", "team"]}}, {"job_id": "100003009029753", "location_code": "hk", "company": "EVISU Group Limited", "job_title": "Senior Fashion Graphic Designer / Fashion Graphic Designer", "description": "Job Responsibilities:\u00a0\n\nResearch and execution on seasonal graphic concepts and trends for seasonal marketable collections\nPropose visual communication materials for apparel collection\nWorking closely with Fashion Design Team and product development team in graphics executions to ensure a smooth work flow\nParticipation in seasonal and exclusive projects with graphic support\n\n\u00a0Job Requirements:\u00a0\n\nDegree or Diploma holder in Graphic Design, Clothing or related discipline\n4 years or above solid experience in Fashion Graphic Design\nFamiliar with fashion graphic applications and techniques\nInterest in Japanese culture and drawings is an preferred\nGood interpersonal skills, independent and self-motivated\nCandidate with less experience will be considered as Fashion Graphic Designer\u00a0\n\nWe offer a 5-days work, MPF, medical and dental insurance, bank holiday\u00a0and competitive remuneration package to the right candidates. Interested parties please send your\u00a0full resume,\u00a0portfolio\u00a0with expected salary and availability\u00a0by clicking \"Apply Now\".\n\nAll information collected will be used for recruitment related purpose only and will be treated in strict confidence. Applicants who are not notified within 8 weeks may consider their application unsuccessful. All applications will be retained for maximum 6 months and will be destroyed.", "employment_types": ["Full Time", "Permanent"], "selling_points": ["Fashion graphic design, graphic concept, trends", "Denim brand, Japanese culture & Graphics", "Casual Wear / Street Wear / Sports Wear Experience"], "locations": ["Kwun Tong"], "categories": ["Design", "Fashion", "Graphics", "Manufacturing", "Garment / Textile"], "post_time": "2022-01-07T06:06:37Z", "salary": {"currency": null, "max": null, "min": null, "period": "monthly", "term": null}, "salary_visible": false, "title_keywords": ["fashion graphic designer", "senior fashion graphic designer"], "responsibilities": ["communication", "graphics", "design", "visual"], "requirements": {"degrees": ["diploma holder", "degree"], "majors": ["graphic design"], "languages": ["japanese"], "language_level": [], "hard_skills": [], "soft_skills": ["independent", "interpersonal skills", "self-motivated"], "languages_combined": [{"language": "japanese", "language_level": []}]}, "experience_required": {"duration": ["4 years"], "field": ["graphic design", "graphic", "designer"]}}, {"job_id": "100003009027615", "location_code": "hk", "company": "Casetagram Limited", "job_title": "Product Graphic Designer", "description": "Purpose of Position\n\nCASETiFY is one of the leading global lifestyle brands to offer customizable tech accessories.. We're industry leaders when it comes to trend forecasting and protecting what matters most; the community platform for creativity and self-expression. We\u2019ve reached 1 in 7 millennials and are expanding our team in order to deliver the best-in-market engagement and products for our growing community.\u00a0\nCASETiFY is looking for a Brand Product Designer who will hit the ground running, thrive in a fast paced environment to join our team. He/ she will be a part of the leads in CASETiFY\u2019s branding and product innovation/design in driving CASETiFY\u2019s product portfolio growth and expansion\nJob Description\n\nKeep a finger on the pulse of the fashion & gadget accessories market\nResearch and identify fashion, color and material trends\nDrive graphic design for new products\u00a0\nVisualize product concept from product manager/brand director\nPropose color themes and stories that reflect market trends\nDrive packaging structure and design\nSupport product development team with various tech pack and CMF documents\nCollaborate with product developers to follow through the product sample development process\nRequirement\n\n3+ years of solid experience in graphic design\u00a0\nCreative agency or in-house fashion/lifestyle brands experience is a plus\nStrong sense in fashion and trend, passion for fashion and culture\u00a0\nProficient in Adobe Creative Suite\nCreative problem solving, multi-tasking skills, and attention to details\nSelf-motivated and proactive\nGood communication and presentation skills in both English and Chinese\n\n", "employment_types": ["Full Time", "Permanent"], "selling_points": ["Market Research & Insight", "Product Design", "Product Development"], "locations": ["Kwun Tong"], "categories": ["Design", "Fashion", "Industrial / Product", "Sciences, Lab, R&D", "Research & Development (R&D)"], "post_time": "2022-01-06T10:37:46Z", "salary": {"currency": null, "max": null, "min": null, "period": "monthly", "term": null}, "salary_visible": false, "title_keywords": ["graphic designer"], "responsibilities": ["product concept", "graphic design", "collaborate with", "design"], "requirements": {"degrees": [], "majors": [], "languages": ["english", "chinese"], "language_level": ["good"], "hard_skills": ["problem solving", "plus", "adobe creative suite"], "soft_skills": ["self-motivated", "proactive", "passion for", "problem solving", "communication", "presentation skills", "attention to details", "multi-tasking skills", "creative"], "languages_combined": [{"language": "english", "language_level": ["good"]}, {"language": "chinese", "language_level": ["good"]}]}, "experience_required": {"duration": ["3+ years"], "field": ["agency", "graphic design"]}}, {"job_id": "100003009026273", "location_code": "hk", "company": "Clot Co. Limited", "job_title": "Senior Graphic Designer", "description": "Job Duties:\n\nHigh level of communication through visual content\nAssist and create\u00a0graphics\u00a0for the Marketing Team. Visuals for both instore and digital uses\u00a0\nWork independently and cooperatively on multiple projects with the marketing team\nWork on a wide range of projects and media, visualising and developing innovative\u00a0graphic\u00a0designs that meet business goals\nObtain input from management, ensuring designs meet organizational standards and brand expectations\nExpress ideas accurately, and represent the brand appropriately\u00a0\nMeeting deadlines and scheduling project implementation based on workload\nUpdate and maintain internal databases of designs, photography, and related materials\n\nRequirements:\n\nDiploma/degree holder in art/design/visual merchandising or related discipline\u00a0\nMinimum 3-5 yrs of relevant working experience preferably in retail / fashion accessories industry\u00a0\nFamiliar with Mac, In-design, AI, PhotoShop, Flash, Dreamweaver, etc\nKnowledge of web page design / After Effects / \u00a0Microsoft Word is in advantage\ncreative, energetic with strong fashion sense\u00a0\nSelf-motivated, independent, responsible, good team player with good communication skills\u00a0\nGood command of written and spoken English and Chinese, Mandarin is an advantage\nImmediate availability is preferred\u00a0\n\nBenefits : Five-day work week, Medical\n\nWe offer medical insurance to the right candidates.\n\nAll applications received will be used strictly for selection purposes only.", "employment_types": ["Full Time", "Permanent"], "selling_points": ["Degree or above in design", "5 years relevant experience", "Handle graphics, trims & packaging update"], "locations": ["Aberdeen"], "categories": ["Design", "Fashion", "Graphics", "Industrial / Product"], "post_time": "2022-01-06T07:49:48Z", "salary": {"currency": null, "max": null, "min": null, "period": "monthly", "term": null}, "salary_visible": false, "title_keywords": ["senior graphic designer"], "responsibilities": ["graphics", "business goals", "management", "ideas", "graphic designs", "developing", "implementation", "communication", "scheduling", "maintain", "databases", "visual", "multiple projects"], "requirements": {"degrees": ["diploma", "degree holder"], "majors": ["art", "design"], "languages": ["english", "chinese", "mandarin"], "language_level": ["advantage", "good command"], "hard_skills": ["microsoft word", "web", "ai", "visual merchandising", "in-design", "after effects", "flash", "dreamweaver", "photoshop"], "soft_skills": ["communication skills", "self-motivated", "good team player", "independent", "creative", "responsible", "energetic"], "languages_combined": [{"language": "english", "language_level": ["advantage", "good command"]}, {"language": "chinese", "language_level": ["advantage", "good command"]}, {"language": "mandarin", "language_level": ["advantage", "good command"]}]}, "experience_required": {"duration": [], "field": ["retail", "relevant working experience"]}}, {"job_id": "100003009030312", "location_code": "hk", "company": "City Contemporary Dance Co Ltd", "job_title": "\u52a9\u7406\u670d\u88dd\u7d93\u7406 (Assistant Wardrobe Manager)", "description": "Assistant Wardrobe Manager (CCDC)\n\nReport directly to the Wardrobe Manager,and is responsible for the followings:\n\nTo assist the Wardrobe Manager to control the budget and time for manufacturing the costume under the instruction of Wardrobe Manager/ Production Manager.\nTo assist the Wardrobe Manager to co-ordinate with choreographer on costume/ image details for performance\nTo assist costume/ image designer on materials and make up products sourcing under the instruction of Wardrobe Manager\nTo perform the drawing and cutting procedures according to the costume design\nTo act as the bridge between choreographer and costume/ image designer\nTo act as the bridge between choreographer and dancers on costume/ image details\nTo co-ordinate with client on costume details, drawing out the concept in the hire engagement eventsunder the instruction of Wardrobe Manager\nTo assist the Wardrobe Managerto provide costume/image design to the client under the instruction ofWardrobe Manager in the hire engagement events\nTo initiate, negotiate and manage costume design and production for commercial \u00a0engagementunder the instruction of Wardrobe Manager\n\u00a0To assist the Wardrobe Managerto control and monitor the daily operation of\u00a0\u00a0\u00a0 the wardrobe department.\n\u00a0To supervise a group of wardrobe workers.\nAny other business assigned by company.", "employment_types": ["Permanent"], "selling_points": ["5 days work", "Medical Insurance", "5+ years related experience"], "locations": ["Tsuen Wan Area"], "categories": ["Design", "Fashion", "Others", "Others"], "post_time": "2022-01-07T07:12:31Z", "salary": {"currency": null, "max": null, "min": null, "period": "monthly", "term": null}, "salary_visible": false, "title_keywords": ["manager", "assistant"], "responsibilities": ["control", "co-ordinate with", "budget", "procedures", "monitor", "design", "daily operation", "report"], "requirements": {"degrees": [], "majors": [], "languages": [], "language_level": [], "hard_skills": ["make"], "soft_skills": ["responsible"], "languages_combined": []}, "experience_required": {"duration": [], "field": []}}, {"job_id": "100003009028089", "location_code": "hk", "company": "Walters People (HK)", "job_title": "Graphic Designer (Retail; Up to 25k)", "description": "Remedios Studio is looking for an FF&E Designer to join our studio in HongKongdue to our strategic growth. We believe talent is our biggest asset and our strength.\n\nThe successful candidates will work closely with the Principal to establish design direction and work with the design team from concept through project completion. We are looking for candidates who have the ability to develop and execute the FF&E direction for overall project. He/She will also work closely with clients to ensure that both the aesthetic and operational requirements are met.\n\n\nResponsibilities\n\nDevelop and execute the FF&E direction for overall project\nDesigning, sourcing, budgeting and documenting FF&E from concept through to finished details\nPrepare mood boards, FF&E specifications, presentation materials and in coordinating FF&E designs with vendors and other resources\nAssume an assistant role in design presentations in communicating with clients and ensure that format is compatible with office and client standards/requirements\nAssist with project record keeping\nLiaising with contractors and suppliers to ensure FF&E is delivered on time and on budget\nAttend site meetings and assist in the process of reviewing the project\nParticipate in the establishment and maintenance of FF&E design standards for the company\nKeep abreast of new trends that may influence FF&E design scheme\nPerforms ad-hoc duties assigned by the Principals\nQualifications\nDesign talent\nDegree or above in Interior Design or related field\n2+Years high-end interior design experience, preferably in hospitality or other high-end type projects\nExperience in full project cycles from concept to documentation and construction\nGood knowledge of materials, details, construction methods, and standards\nAbility to work independently and work well under pressure\nExceptional time management and strong organizational skills\nProficiency in Microsoft Word, Excel, PowerPoint, Acrobat DC, Photoshop, InDesign, AutoCAD, mood boards and presentation materials\nGood command of written and spoken English (Mandarin is desirable but not essential)\n\nCandidates with less experience will be considered for junior positions. The ideal candidate must be a highly motivated and results oriented individual with a positive attitude and strong communication skills. Must be willing to travel and be comfortable with working in a multi-cultural environment.\n\nWe offer an attractive remuneration package and 5-day work week to the right candidates. Interested parties please send your CV with expected salary, availability and portfolio (under 10MB) by clicking \u201cApply Now\u201d.\n\nAll personal information collected would be used for recruitment purposes only.", "employment_types": ["Full Time", "Permanent"], "selling_points": ["Social media; Website", "Retail store promotion", "Min. 2 yrs exp. Up to 25k"], "locations": ["Not Specified"], "categories": ["Design", "Fashion", "Graphics"], "post_time": "2022-01-07T01:29:40Z", "salary": {"currency": "HKD", "max": 24999, "min": 20000, "period": "monthly", "term": null}, "salary_visible": true, "title_keywords": ["graphic designer"], "responsibilities": ["management", "maintenance", "ad-hoc duties", "budgeting", "budget", "liaising with", "design", "develop", "presentations", "communication", "specifications", "communicating with", "designing", "documentation", "attend site meetings"], "requirements": {"degrees": ["degree or above"], "majors": ["design"], "languages": ["english", "mandarin"], "language_level": ["good command"], "hard_skills": ["excel", "microsoft word", "acrobat", "maintenance", "indesign", "dc", "scheme", "presentations", "powerpoint", "autocad", "documentation", "photoshop"], "soft_skills": ["organizational skills", "work independently", "communication skills", "under pressure", "positive attitude", "motivated", "ad-hoc duties", "time management", "presentation", "ideal"], "languages_combined": [{"language": "english", "language_level": ["good command"]}, {"language": "mandarin", "language_level": ["good command"]}]}, "experience_required": {"duration": [], "field": ["construction", "design"]}}, {"job_id": "100003009023952", "location_code": "hk", "company": "Remedios Studio (Hong Kong) Limited", "job_title": "FF&E Designer (5 day work)", "description": "My client is an international premium fashion group with a portfolio of brands and they are looking for a Fashion Designer to join their team.\n\nResponsibilities:\n\nInitiate design and product ideas\nDesign\u00a0products (hand-sketches, illustrations, technical drawings, color concepts, story boards, merchandising boards etc.)\nCreate detailed design sketches, BOM, tech packages\nAttend fit and prototype review sessions\nMake revisions to artwork and tech packages\nResearch competitors and trends within apparel, lifestyle\nTranslate seasonal concepts to products\nParticipate in product development/sourcing in all issues regarding the realization of products form concept to samples\n\nRequirements:\n\nBachelor\u2019s Degree in Fashion Design\nStrong fashion aesthetic and creativity\nKnowledge of technical design, fabrics and other materials\nGood interpersonal and communication abilities\nKnowledge of design-related applications and software (eg Illustrator, Photoshop, 3D sketch)\nSkilful in technical /CAD sketching\nProficient in English and Chinese", "employment_types": ["Full Time", "Permanent"], "selling_points": ["5 Day Work", "Medical Insurance", "2+ years experience in Interior Design"], "locations": ["Southern Area"], "categories": ["Design", "Fashion", "Industrial / Product", "Interior"], "post_time": "2022-01-06T09:10:45Z", "salary": {"currency": null, "max": null, "min": null, "period": "monthly", "term": null}, "salary_visible": false, "title_keywords": ["designer"], "responsibilities": ["ideas", "review", "merchandising", "sketches", "design", "technical drawings"], "requirements": {"degrees": ["degree", "bachelor"], "majors": ["design"], "languages": ["english", "chinese"], "language_level": ["proficient"], "hard_skills": ["cad", "illustrator", "photoshop"], "soft_skills": ["communication", "interpersonal"], "languages_combined": [{"language": "english", "language_level": ["proficient"]}, {"language": "chinese", "language_level": ["proficient"]}]}, "experience_required": {"duration": [], "field": []}}, {"job_id": "100003009020277", "location_code": "hk", "company": "WilliamSELECT", "job_title": "Senior Fashion Designer (Premium Fashion, womenswear, woven)", "description": "Please attach your portfolio \uff01\n\n\u5c97\u4f4d\u804c\u8d23\uff1a\n1.\u70ba\u516c\u53f8\u6d88\u8cbb\u54c1\u985e\u7522\u54c1\u6784\u601d\u53ca\u8bbe\u8ba1\u5ba3\u50b3\u79ae\u54c1\u5305\u88dd,\u4f5c\u63a8\u5ee3\u53ca\u5ba3\u50b3\u4e4b\u7528,\u8d1f\u8d23\u9879\u76ee\u4e2d\u6d89\u53ca\u5230\u7684\u521b\u610f\u8bbe\u8ba1\u3001\u7ed8\u5236\u76f8\u5173\u6982\u5ff5\u56fe\u3001\u8bbe\u8ba1\u65b9\u6848\u548c\u6548\u679c\u56fe\u3001\u5236\u4f5c\u6a21\u578b\u53ca\u76f8\u5173\u73af\u8282\u7684\u63a8\u8fdb\u3002\n2.\u8207\u54c1\u724c\u53ca\u7522\u54c1\u90e8\u9580\u53c3\u8207\u8a2d\u8a08\u6703\u8b70, \u5c55\u793a\u8a2d\u8a08\u53ca\u8ddf\u9032\u610f\u898b\u3002\n\n\u5c97\u4f4d\u8981\u6c42\uff1a\n1.\u5169\u5e74\u4ee5\u4e0a\u79ae\u54c1\u985e\u5305\u88dd\u8a2d\u8ba1\u5de5\u4f5c\u7ecf\u9a8c\uff0c\u7cbe\u901a\u719f\u7ec3\u64cd\u4f5c\u8bbe\u8ba1\u8f6f\u4ef6\u3002\n2.\u5177\u5907\u826f\u597d\u6c9f\u901a\u53ca\u6642\u9593\u7ba1\u7406\u80fd\u529b,\u5177\u56e2\u961f\u534f\u4f5c\u610f\u8bc6,\u5177\u72ec\u7acb\u601d\u8003\u4e0e\u89e3\u51b3\u95ee\u9898\u80fd\u529b\u3002\n3.\u4e86\u89e3\u570b\u5167\u7db2\u7d61\u3001\u751f\u6d3b\u6f6e\u6d41\u6587\u5316\u548c\u6d88\u8cbb\u54c1\u5e02\u573a\u8d8b\u52bf\u3002\n4.\u57fa\u672c\u82f1\u8a9e\u6e9d\u901a\u80fd\u529b\u3002", "employment_types": ["Full Time"], "selling_points": ["hand-sketches, illustrations, techn drawings etc.", "3D Sketch", "Create detailed design sketches, BOM, tech package"], "locations": ["Not Specified"], "categories": ["Design", "Fashion"], "post_time": "2022-01-04T10:21:17Z", "salary": {"currency": null, "max": null, "min": null, "period": "monthly", "term": null}, "salary_visible": false, "title_keywords": ["fashion designer"], "responsibilities": [], "requirements": {"degrees": [], "majors": [], "languages": [], "language_level": [], "hard_skills": [], "soft_skills": [], "languages_combined": []}, "experience_required": {"duration": [], "field": []}}, {"job_id": "100003009014390", "location_code": "hk", "company": "Time Art Development Limited", "job_title": "Fashion Designer", "description": "We are looking for a highly motivated and organised individual to join our E-commerce team. This is an exciting opportunity for people passionate about fashion, and looking to grow their career within a dynamic brand. The candidate will be responsible to manage, develop and operate our sales channels.\n\nResponsibilities include but not limited to:\n\nResponsible for daily operations of our sales channels - logistics, customer service and inventory control\u00a0\nMonitor and optimise performance of sales channels via design updates, campaigns, content\u00a0\nCarry out market research on e-commerce trends, features, customer behaviour in order to optimise sales channels for conversions\u00a0\nAnalyse and report on channels performance; provide enhancement suggestions\u00a0\nWork closely with product team and marketing team on brand growth strategy\u00a0\n\nRequirements:\u00a0\n\n1+ years working experience \u00a0 \u00a0\nEnergetic and passionate about fashion\nAbility to work in a small team and work independently in a fast-paced environment\nExcellent organisational skills, detail oriented, analytical\u00a0\nStrong communicator; Fluent in Chinese and English\u00a0\nExperience in using Shopify or similar e-commerce providers is an advantage\nBachelor degree holder\u00a0", "employment_types": ["Full Time"], "selling_points": [], "locations": ["Lai Chi Kok"], "categories": ["Design", "Fashion", "Graphics"], "post_time": "2022-01-03T03:21:36Z", "salary": {"currency": null, "max": null, "min": null, "period": "monthly", "term": null}, "salary_visible": false, "title_keywords": ["fashion designer"], "responsibilities": ["monitor", "market research", "design", "daily operations", "customer service", "logistics", "inventory control", "report", "analyse"], "requirements": {"degrees": ["bachelor degree holder"], "majors": [], "languages": ["english", "chinese"], "language_level": ["fluent"], "hard_skills": ["small", "shopify", "e-commerce"], "soft_skills": ["work independently", "fast-paced environment", "detail oriented", "organisational skills", "communicator", "energetic", "passionate about"], "languages_combined": [{"language": "english", "language_level": ["fluent"]}, {"language": "chinese", "language_level": ["fluent"]}]}, "experience_required": {"duration": ["1+ years"], "field": ["e-commerce"]}}, {"job_id": "100003009019645", "location_code": "hk", "company": "Takara Personnel Consultancy", "job_title": "AM/ M/ SM/ Fashion Designer/Multimedia Designer   - Urgent", "description": "Lauris Walton\u00ae is a global recruitment specialist in the Creative & Design industry. We\u2019re partnering with a fast-growing MNC in the online fashion industry to seek a few product designers due to their business expansion plan.\n\nProduct Designer x 2-3 (Junior Designer or Expat welcome to apply)\n\nPrepare technical drawings using AI and assist the\u00a0Design team in Hong Kong and Europe regularly\nParticipate in creative design projects, including marketing research, trend analysis etc.\nAssist in business development projects, e.g. showroom opening, coordination and project management\nEnjoy working in a fast-paced, multinational, dynamic environment with a can-do attitude\nSolid experience in AI and other design tools (please specify) is essential\nFluent in English is a must\nEyewear / Sports Accessories Designer\nWork closely with Design team in Hong Kong and Europe on product design, drawing and development\nPrior experience in eyewear/sports accessories design with a creative mindset\nSolid experience in using AI and other design tools\nInterested candidates, please apply with your resume and portfolio or reach us at 2153 3833 for\u00a0enquiries. For more design roles, please visit our website at www.lauriswalton.com.", "employment_types": ["Full Time", "Permanent"], "selling_points": [], "locations": ["Central & Western Area"], "categories": ["Design", "Fashion", "Multi-media", "Merchandising & Purchasing", "Textiles"], "post_time": "2022-01-04T08:13:03Z", "salary": {"currency": null, "max": null, "min": null, "period": "monthly", "term": null}, "salary_visible": false, "title_keywords": ["fashion designer", "multimedia designer"], "responsibilities": ["analysis", "design", "project management", "marketing research", "product design", "recruitment", "technical drawings", "plan", "coordination"], "requirements": {"degrees": [], "majors": [], "languages": ["english"], "language_level": ["fluent"], "hard_skills": ["creative design", "ai", "analysis", "project management", "dynamic"], "soft_skills": ["dynamic environment", "can-do attitude", "enjoy working", "creative mindset", "project management", "coordination", "creative"], "languages_combined": [{"language": "english", "language_level": ["fluent"]}]}, "experience_required": {"duration": [], "field": ["design"]}}, {"job_id": "100003009025732", "location_code": "hk", "company": "Lauris Walton International Limited", "job_title": "Product Designers x 3-5 (Eyewear / Accessories / Sportswear)", "description": "Provide up to date Shoes Fashion trend advise to customers\n\nAchieve sales targets set by Store Managers in order to earn attractive commission\n\nClient Details\n\nOur client is a luxury shoes brand and is looking for someone that has strong passion in shoes/fashion.\n\nDescription\n\nAdvise customers on styling of total looks by providing shoes and fashion trends\nBuild the relationship with/new and existing Consumers/Customers\nMaximise sales opportunities to achieve monthly sales targets\nOperate the Retail Management system, in all areas relating to sales transactions, payment, stock inquiry and customers database input\nProvide Visual Merchandising set-up of store windows and displays\n\nProfile\n\n1 - 2 years working experience in Luxury Retail industry\nProactive, energetic with positive attitude, passionate in retail\nGood Team Player with ability to cooperate with colleagues\nGood communication skills\n\nJob Offer\n\nPaid annual leave\nTop-up bonus; Incentive bonus; Event bonus; Year end bonus\nBirthday day off\nProducts discount/ Clothing allowance\nCareer Advancement\n\nInterested applicant please send me your resume to Marcochong@michaelpage com hk Or please call Marco @ 52909990 for enquiries\n\nTo apply online please click the 'Apply' button below. For a confidential discussion about this role please contact Marco Chong on +852 3476 6336", "employment_types": ["Full Time", "Permanent"], "selling_points": [], "locations": ["Central"], "categories": ["Design", "Fashion", "Industrial / Product", "Others"], "post_time": "2022-01-06T06:24:44Z", "salary": {"currency": null, "max": null, "min": null, "period": "monthly", "term": null}, "salary_visible": false, "title_keywords": [], "responsibilities": ["management", "merchandising", "transactions", "communication", "payment", "contact", "database", "visual", "cooperate with"], "requirements": {"degrees": [], "majors": [], "languages": [], "language_level": [], "hard_skills": ["marco", "visual merchandising"], "soft_skills": ["passionate", "communication skills", "good team player", "proactive", "passion in", "positive attitude", "energetic"], "languages_combined": []}, "experience_required": {"duration": ["1 - 2 years"], "field": ["luxury retail"]}}, {"job_id": "100003009023805", "location_code": "hk", "company": "Michael Page", "job_title": "Senior/Fashion Advisor (Luxury Fashion & Shoes) @ High Basic", "description": "We are looking for candidates with vision, energy and a strong fashion sense who want to be part of a dynamic team and create value. We offer career development as well as regional and local advancement opportunities.\n\nResponsibilities\u00a0\u00a0\n\nParticipate in new season collection from sketching, technical drawing, coloring, positioning, trim design, print & pattern graphic illustration, artwork, fitting to sample development stage;\nResearch and analyze market trends and commercial needs by keeping a consistent brand image and positioning;\nAssist in sourcing, selecting and purchasing of fabric for production and color matching for seasonal collection;\nWork closely with product development team.\n\nRequirements\n\nDiploma or above in Fashion Design or related discipline;\nAt least 5 years' relevant experience in ladies' wear Fashion Design in HK or China retail industry;\nCreative and respond effectively to the ever-changing consumers\u2019 fashion needs;\nStrong passion and sense of fashion;\nGood communication and presentation skills;\nAble to work independently and good team player;\nProficiency in Photoshop, Illustrator and MS Office applications;\nGood command of spoken and written English, Mandarin and Cantonese;\nCandidates with less experience will be considered as\u00a0Fashion Designer.\nInterested parties please send your\u00a0resume with expected salary and portfolio\u00a0to Human Resources Department via Apply Now.\n\nAll information provided will be treated in strict confidence and used solely for recruitment purposes.\u00a0\n\n", "employment_types": ["Full Time", "Permanent"], "selling_points": ["Friendly working environment", "Attractive basic salary with competitive comm.", "8 rest days per month"], "locations": ["Not Specified"], "categories": ["Sales, CS & Business Devpt", "Customer Service - Supervisor / Officer", "Design", "Fashion", "Retail Sales"], "post_time": "2022-01-05T09:50:18Z", "salary": {"currency": null, "max": null, "min": null, "period": "monthly", "term": null}, "salary_visible": false, "title_keywords": ["fashion advisor"], "responsibilities": [], "requirements": {"degrees": [], "majors": [], "languages": [], "language_level": [], "hard_skills": [], "soft_skills": [], "languages_combined": []}, "experience_required": {"duration": [], "field": []}}, {"job_id": "100003009015291", "location_code": "hk", "company": "Balenciaga Asia Pacific", "job_title": "BALENCIAGA Buyer, Hong Kong & Macau (Leather Goods & Shoes)", "description": "Summary\n\nThe position is responsible for executing all merchandising functions, including managing sales, seasonal purchase, inventory, product delivery and training, so as to achieve sales and profit targets based on the seasonal business plan.\n\nJob Description\n\nHow you will contribute\n\nBuying\n\nCollaborate with Global Merchandising team to determine HK/MO seasonal buying guidelines\n\nOversee buying activities during the sales campaign based on analysis and allocation done during the year (selection, quantities, assortment by store)\n\nManage the Open-to-Buy seasonally\n\nMarket and competitor's analysis in terms of product and pricing positioning in the different markets\n\nOperation\n\nOversee weekly & monthly reporting results and analyze the business accordingly\n\nExecute proactive consolidations to ensure profitability and satisfy market\u2019s needs\n\nMonitor inventory, delivery and replenishment situation to ensure a healthy and appropriate mix and stock level are maintained\n\nCommunicate and provide direction to store management regarding product feedback and selling trends in order to ensure successful sales and inventory levels for each market\n\nPartner with Retail/ VM/ Press in order to align CRM activities, trainings, execute visual directives and marketing focus\n\nCommunicate with logistics team and Inventory Control in pricing and stock flow management\n\nManage inventory levels, merchandise flow and pricing for outlet locations\n\nWho you are\n\nBachelor degree in fashion, textiles or other related disciplines\n\nMinimum 6-8 years experience in fashion merchandising/buying with international luxury retail companies, preferably with leather goods & shoes experience\n\nStrong fashion and market sense\n\nWell organized, self-initiative, excellent analytical, presentation, and communication skills\n\nGood team player with strong sense of responsibility\n\nFluent in spoken and written English, Cantonese and Mandarin\n\nGood PC skills such as MS Office\n\nOverseas travel is required\n\nCandidate with less experience will be considered as Junior Buyer\n\nWhy work with us?\n\nThis is an exciting opportunity to contribute to the Balenciaga philosophy and to become part of a team that offers possibilities to learn and grow.\u00a0\u00a0\u00a0\n\nBalenciaga is committed to thriving your professional development within the House or in the Kering group. We empower leaders to create, build and sustain high performing teams that excel in execution. We guide every employee to reach their full potential in a stimulating and fulfilling workplace environment.\n\nDiversity Commitment\n\nBalenciaga is committed to fostering a diverse workforce. We believe that diversity in all its forms - gender, age, nationality, culture, disability, sexual orientation\u2026 - enriches the workplace and our client experience. As an Equal Opportunity Employer, we welcome all applications and select our talents based on competencies and in alignment with our brand behaviors. Setting people for success is what we live for. It is part of our interview process to discuss with you how to excel in our company.\n\nJob Type\n\nRegular\n\nStart Date\n\n2021-11-08\n\nSchedule\n\nFull time\n\nOrganization\n\nBALENCIAGA ASIA PACIFIC LTD", "employment_types": ["Full Time"], "selling_points": ["Responsible for Hong Kong & Macau market", "Leather goods & shoes focus", "Occasional travel is required"], "locations": ["Quarry Bay"], "categories": ["Design", "Fashion", "Merchandising & Purchasing"], "post_time": "2022-01-03T06:26:26Z", "salary": {"currency": null, "max": null, "min": null, "period": "monthly", "term": null}, "salary_visible": false, "title_keywords": [], "responsibilities": ["collaborate with", "reporting", "management", "communicate with", "open-to-buy", "provide direction", "guidelines", "analysis", "inventory", "merchandising", "monitor", "replenishment", "inventory control", "logistics", "visual"], "requirements": {"degrees": ["degree", "bachelor"], "majors": ["related disciplines"], "languages": ["cantonese", "english", "mandarin"], "language_level": ["fluent"], "hard_skills": ["excel", "pc skills", "ms office"], "soft_skills": ["communication skills", "good team player", "sense of responsibility", "well organized", "committed", "diverse", "self-initiative", "presentation"], "languages_combined": [{"language": "cantonese", "language_level": ["fluent"]}, {"language": "english", "language_level": ["fluent"]}, {"language": "mandarin", "language_level": ["fluent"]}]}, "experience_required": {"duration": ["minimum 6-8 years"], "field": ["luxury retail", "merchandising"]}}, {"job_id": "100003009000690", "location_code": "hk", "company": "P.H.Garment Manufacturing Co Ltd", "job_title": "Designer/ Junior Designer(5-Day work)", "description": "A reputable lingerie manufacturer in the region is now looking for dynamic and competent candidate to fill in the following vacancy to cope with our growing business.\n\nJob Requirements\n\n- Diploma or Certificate holder in Fashion Design/ Fashion & Textiles/ Lingerie Design or Related discipline;\n\n- Candidate must have strong knowledge on knitted textiles for Lingerie Industry;\n\n- Fresh graduate is welcomed;\n\n\n\nJob Responsibilities\n\n- Diploma in Lingerie Design or related discipline;\n\n- Familiar with Photoshop, Power Point and adobe illustrator\n\n- Developing seasonal collection from concept development, sketching, preparation and sample development;\n\n- Trend book design;\n\n- Capable to write and communicate in English and Mandarin;\n\n- Willing travel to China 1-2 days/week and work with crew in China\n\n\nInterested parties, please send your resume with expected salary to P.H. Garment Mfg. Co. Ltd..\n\n(Data collected will be used for recruitment purpose only.)", "employment_types": ["Full Time"], "selling_points": [], "locations": ["Kwai Fong"], "categories": ["Design", "Fashion", "Industrial / Product", "Manufacturing", "Product Development / Management"], "post_time": "2022-01-02T22:53:29Z", "salary": {"currency": null, "max": null, "min": null, "period": "monthly", "term": null}, "salary_visible": false, "title_keywords": ["designer", "junior"], "responsibilities": ["developing", "design"], "requirements": {"degrees": ["certificate", "diploma", "fresh graduate"], "majors": ["design"], "languages": [], "language_level": [], "hard_skills": [], "soft_skills": [], "languages_combined": []}, "experience_required": {"duration": [], "field": []}}, {"job_id": "100003009016520", "location_code": "hk", "company": "P.H.Garment Manufacturing Co Ltd", "job_title": "Technical Designer(5-Day work)", "description": "A reputable lingerie manufacturer in the region is now looking for dynamic and competent candidate to fill in the following vacancy to cope with our growing business.\n\n\u00a0Job Requirements\n\n\u00b2\u00a0Diploma or Certificate holder in Textiles or Design Studies, candidate must have strong knowledge on knitted textiles for Lingerie Industry;\n\n\u00b2\u00a0Minimum 5 years of successful and progressive experience in \"lingerie\" Product Development;\n\n\u00b2\u00a0Knowledge in pattern making and garment construction, able to fit, \u00a0approve and comment proto type;\n\n\u00b2\u00a0Knowledge in grading is not a must but preference;\n\n\u00b2\u00a0Strong sense of lingerie design & fashion;\n\n\u00b2\u00a0Proficient in MS Office application, Photoshop and Illustrator;\n\n\u00b2\u00a0Strong communication skill with overseas customer and development / production team in China;\n\n\u00b2\u00a0Mainland China travel is required, sometimes, overseas travel could be required;\n\n\u00b2\u00a0Ability to speak / communicate English, Cantonese and Mandarin.\n\nJob Duties\n\n\u00b2\u00a0Worked with overseas customers from concept stage, including material sourcing, garment construction;\n\n\u00b2\u00a0Commercially focused with excellent understanding of costs and material prices;\n\n\u00b2\u00a0Manages the development process of company product line / customer design as assigned;\n\n\u00b2\u00a0Plans and tracks the development schedule of all products to ensure a timely completion following the predetermined product development calendar;\n\n\u00b2\u00a0Responsible for the product lifestyle management from concept to development;\n\n\u00b2\u00a0Meet with relevant department and customer in style review and pre-production meeting;\n\n\u00b2\u00a0Work independent with R&D team / Product Development team for any innovation idea / new finishing required from customer.\n\nWe offer attractive remuneration package including discretionary bonus and medical insurance to the right candidate.\u00a0 Interested parties, please send your resume with expected salary to P.H. Garment Mfg. Co. Ltd..\n\n(Data collected will be used for recruitment purpose only.)", "employment_types": ["Full Time"], "selling_points": [], "locations": ["Kwai Fong"], "categories": ["Design", "Fashion", "Industrial / Product", "Manufacturing", "Product Development / Management"], "post_time": "2022-01-03T09:16:54Z", "salary": {"currency": null, "max": null, "min": null, "period": "monthly", "term": null}, "salary_visible": false, "title_keywords": [], "responsibilities": ["management", "pre-production", "review", "design", "schedule", "plans", "costs"], "requirements": {"degrees": ["certificate", "diploma"], "majors": ["design"], "languages": ["cantonese", "english", "mandarin"], "language_level": [], "hard_skills": ["illustrator", "photoshop", "ms office"], "soft_skills": ["progressive", "communication skill"], "languages_combined": [{"language": "cantonese", "language_level": []}, {"language": "english", "language_level": []}, {"language": "mandarin", "language_level": []}]}, "experience_required": {"duration": ["minimum 5 years"], "field": ["product development"]}}, {"job_id": "100003009014305", "location_code": "hk", "company": "Otto International (HK) Ltd", "job_title": "Merchandiser - Swimwear", "description": "We are looking for a passionate Merchandiser to join our HK team, working as a mediator between one of our largest key account customers and vendors for the highest standard of service. The person will deliver various merchandising activities with full autonomy and ensure that they are well looked after from product development to production.\nHow will you make a difference?\nSupport with the delivery of daily merchandising activities through product development, costing, data analysis, and in production follow up\nAssist in presenting new season collections during the buying season, review outstanding issues on production status\nTroubleshoot with vendors and present alternative solutions to the customer proactively\nManage the external partners\u2019 relationships by partnering, communicating on seasonal strategy, production, products, costing challenges, initiatives and capacity planning\nCarry out visits to trade fairs or suppliers to manage and develop the supplier pool continually\nMaintain compliance at all times with social and quality requirements\nWho are we looking for?\n\nDiploma or Degree holder in Merchandising, Textile, Clothing or related disciplines\nMinimum 3 years of garment merchandising experience in a sizable buying office, preferably working with swimwear\nProficiency in MS Office programmes \u2013 Word, Excel, Office 365\nDetail-oriented, well-organised, and good team player\nGood communication skills in English (written and spoken) with additional fluency in Cantonese and Mandarin\nWhy work with us?\n\nCollaborative, fun and challenging work environment\nOpen, transparent and diverse culture with locations worldwide\nDouble-pay, performance bonus, flexible working hours\nFull health insurance coverage\nAll data provided by applicants will be treated in strict confidence and used solely for recruitment purposes.", "employment_types": ["Full Time", "Part Time", "Permanent", "Temporary"], "selling_points": ["Swimwear products", "Passionate about retail and merchandising", "Enjoy collaborating with a team"], "locations": ["Hung Hom"], "categories": ["Design", "Fashion", "Merchandising & Purchasing", "Woven / Knit", "Procurement / Purchasing / Sourcing"], "post_time": "2022-01-03T03:15:37Z", "salary": {"currency": null, "max": null, "min": null, "period": "monthly", "term": null}, "salary_visible": false, "title_keywords": ["merchandiser"], "responsibilities": ["data", "review", "merchandising", "compliance", "quality", "develop", "data analysis", "communication", "maintain", "recruitment", "troubleshoot", "insurance", "planning"], "requirements": {"degrees": ["diploma", "degree holder"], "majors": ["related disciplines"], "languages": ["cantonese", "english", "mandarin"], "language_level": ["fluency", "good"], "hard_skills": ["excel", "office 365", "fun", "analysis", "word", "make", "ms office"], "soft_skills": ["passionate", "communication skills", "good team player", "flexible", "confidence", "collaborative", "detail-oriented", "diverse", "troubleshoot", "well-organised"], "languages_combined": [{"language": "cantonese", "language_level": ["fluency", "good"]}, {"language": "english", "language_level": ["fluency", "good"]}, {"language": "mandarin", "language_level": ["fluency", "good"]}]}, "experience_required": {"duration": ["minimum 3 years"], "field": ["garment", "merchandising"]}}, {"job_id": "100003009012111", "location_code": "hk", "company": "Grown-Up Manufactory Limited", "job_title": "Lifestyle Products & Graphic Designer", "description": "OUR COMPANY\u00a0\u00a0\u00a0\u00a0\n\n\nGROWN UP GROUP (Listed at the Hong Kong Stock Exchange, HKEX: 1842) is one of the world\u2019s leading companies within the bags and luggage industry.\n\nWe offer manufacturing services and design solutions to a wide range of international brands, such as Adidas, Samsonite, Wilson and a strong portfolio of licensed and own brands like LEGO, Caterpillar, New Balance and Ellehammer.\n\nWe manufacture at both our own factories and with our numerous partner factories in Southeast Asia and serve our customers from our global head office in Hong Kong, our R&D center in Shenzhen and our sales and design offices in Asia and Europe.\n\n\nYOUR ROLE\n\nYou will be a member of our Design Team and report directly to Head of Product Development, Merchandising, Sourcing and Design.\n\nYou have some prior knowledge and experience of handling soft stitched goods and hard goods made in fabric and plastics.\n\n\n\nYour key work includes:\n\n-\u00a0\u00a0\u00a0\u00a0\u00a0\u00a0\u00a0 Concept design for travel goods.\n\n-\u00a0\u00a0\u00a0\u00a0 Preparing working drawings for variety of travel and sport products including backpacks, school bags, trolley bags, soft luggage, accessories and tools bag.\n\n-\u00a0\u00a0\u00a0\u00a0\u00a0\u00a0\u00a0 Making Sample Instruction sheets / technical specification drawings.\n\n-\u00a0\u00a0\u00a0\u00a0 Developing graphics, logo edits, prints, patterns and related design artworks to facilitate your original or client\u2019s design concept.\n\n-\u00a0\u00a0\u00a0\u00a0\u00a0\u00a0 Preparing presentation with product and design proposition concepts with appropriate graphical edits for facilitating business.\n\n-\u00a0\u00a0\u00a0\u00a0\u00a0\u00a0 Completion of design work and convert client\u2019s design concept into drawing for production.\n\n-\u00a0\u00a0\u00a0\u00a0\u00a0\u00a0\u00a0\u00a0 Liaison with marketing/branding department and product development team to facilitate design development.\n\n-\u00a0\u00a0\u00a0\u00a0\u00a0\u00a0\u00a0 Follow the direction from brand marketing and sales team to generate concepts and drawings for development and sampling.\n\n-\u00a0\u00a0\u00a0\u00a0\u00a0\u00a0\u00a0 Regular interaction with merchandising and product development team for sample readiness and improvement until final.\n\nYou must have:\n\nProficiency in Product Design, Graphics and Illustration Software including Adobe Illustrator, Photoshop, CorelDraw, AutoCad.\nExperience in 3D modelling and rendering software will be an advantage.\nDiploma or above in design or related discipline.\n3 - 5 years of design experience, preferably in various travel goods, bags & luggage industry.\nDetailed-minded, flexible and be able to work well under pressure and meet strict deadlines.\nGood team spirit, problem solving, interpersonal and communication skills.\nFluent in English and Chinese (Putonghua)\nMay required to travel to Mainland China.\n\nWe offer you\n\no\u00a0\u00a0 Competitive salary\n\no\u00a0\u00a0 5-day work week\n\no\u00a0\u00a0 Medical insurance\n\no\u00a0\u00a0 Annual leave starting from 14 days\n\no\u00a0\u00a0 Work experience with exposure to European markets\n\no\u00a0\u00a0 A friendly work environment\n\nYOUR APPLICATION\n\nPlease send your application, CV with salary expected and portfolio today.", "employment_types": ["Full Time", "Permanent"], "selling_points": [], "locations": ["Tai Po Area"], "categories": ["Design", "Fashion", "Graphics"], "post_time": "2021-12-31T09:29:09Z", "salary": {"currency": null, "max": null, "min": null, "period": "monthly", "term": null}, "salary_visible": false, "title_keywords": ["graphic designer"], "responsibilities": ["graphics", "design work", "software", "design solutions", "design concept", "merchandising", "developing", "design", "drawings", "facilitate design", "communication", "product design", "sales team", "report"], "requirements": {"degrees": ["diploma or above"], "majors": ["design"], "languages": ["putonghua", "english", "chinese"], "language_level": ["fluent"], "hard_skills": ["r&d", "graphics", "illustration", "3d modelling", "adobe illustrator", "problem solving", "autocad", "photoshop", "logo", "exchange"], "soft_skills": ["flexible", "communication skills", "team spirit", "under pressure", "problem solving", "interpersonal", "presentation", "detailed"], "languages_combined": [{"language": "putonghua", "language_level": []}, {"language": "english", "language_level": ["fluent"]}, {"language": "chinese", "language_level": ["fluent"]}]}, "experience_required": {"duration": ["3 - 5 years"], "field": ["design"]}}, {"job_id": "100003009008094", "location_code": "hk", "company": "Bape Hong Kong Limited", "job_title": "Assistant Visual Merchandiser", "description": "Accountabilities \u2013 Key Result Areas\n\n\nPrepare and set-up all visual merchandising and promotional displays for promotional program, seasonal change and ad-hoc events\nMaintain and upkeep all visual merchandising materials at stores regularly\nAssist in sourcing and liaison with suppliers for the ordering, delivering and producing of materials relating to all visual merchandising\nAssist in setting up and coordinates new store opening and store upgrading\nWork closely in team for concept development, execution and all creative deliberation\nSupport the development of artwork for various marketing materials such as print ad, brochure, packaging, POP, flyer, poster and etc.\nLiaise and coordinate with external agencies, vendors and etc for print/production and quality control.\nProject management of all VM initiatives including windows, seasonal brand imagery, LED screens, POS and merchandise presentations all to be delivered in store, on time and on budget\nEnhance aesthetic appeal of shop front windows and in-store displays to promote new product launches, festive and seasonal themes including deliver regular floor moves, window installations, and mannequins styling, etc.\nExperience / Qualification Requirements\n\n\nDegree holder in visual merchandising and design related discipline\nAt least 1-2 years or above experience in fashion industry, with solid experience in visual design, window set up, interior displays and space utilization\nCreative and possess good knowledge of fashion, accessories, color trends and styling.\nBe passionate about the brand\u2019s identity, with personal charisma and good understanding of the dynamics of the fashion industry\nCommunicative and be able to collaborate with business teams to achieve brand objectives\nCompetitive remuneration and benefit package will be offered to the right candidate. Please submit your application by clicking \"Apply Now\" below.\n\n\n\nAll data collected is for recruitment purpose only.", "employment_types": ["Full Time"], "selling_points": ["1-2 years relevant experience in fashion industry", "Uphold standards and guidelines", "Deliver creative results for strategic"], "locations": ["Southern Area"], "categories": ["Design", "Fashion", "Graphics", "Visual Merchandising"], "post_time": "2021-12-30T06:45:10Z", "salary": {"currency": null, "max": null, "min": null, "period": "monthly", "term": null}, "salary_visible": false, "title_keywords": ["assistant visual merchandiser"], "responsibilities": ["ad-hoc events", "liaise", "collaborate with", "data", "budget", "merchandising", "coordinate with", "presentations", "design", "teams", "project management", "maintain", "recruitment", "quality control", "visual", "marketing materials", "promotional program"], "requirements": {"degrees": ["degree holder"], "majors": ["design"], "languages": [], "language_level": [], "hard_skills": ["pos", "visual merchandising", "presentations", "project management", "visual design"], "soft_skills": ["project management", "creative", "passionate about"], "languages_combined": []}, "experience_required": {"duration": ["at least 1-2 years"], "field": ["design"]}}, {"job_id": "100003009000689", "location_code": "hk", "company": "P.H.Garment Manufacturing Co Ltd", "job_title": "Designer/ Junior Designer(5-Day work)", "description": "A reputable lingerie manufacturer in the region is now looking for dynamic and competent candidate to fill in the following vacancy to cope with our growing business.\n\nJob Requirements\n\n- Diploma or Certificate holder in Fashion Design/ Fashion & Textiles/ Lingerie Design or Related discipline;\n\n- Candidate must have strong knowledge on knitted textiles for Lingerie Industry;\n\n- Fresh graduate is welcomed;\n\n\n\nJob Responsibilities\n\n- Diploma in Lingerie Design or related discipline;\n\n- Familiar with Photoshop, Power Point and adobe illustrator\n\n- Developing seasonal collection from concept development, sketching, preparation and sample development;\n\n- Trend book design;\n\n- Capable to write and communicate in English and Mandarin;\n\n- Willing travel to China 1-2 days/week and work with crew in China\n\n\nInterested parties, please send your resume with expected salary to P.H. Garment Mfg. Co. Ltd..\n\n(Data collected will be used for recruitment purpose only.)", "employment_types": ["Full Time"], "selling_points": [], "locations": ["Kwai Fong"], "categories": ["Design", "Fashion", "Industrial / Product", "Manufacturing", "Product Development / Management"], "post_time": "2021-12-29T16:11:01Z", "salary": {"currency": null, "max": null, "min": null, "period": "monthly", "term": null}, "salary_visible": false, "title_keywords": ["designer", "junior"], "responsibilities": ["developing", "design"], "requirements": {"degrees": ["certificate", "diploma", "fresh graduate"], "majors": ["design"], "languages": [], "language_level": [], "hard_skills": [], "soft_skills": [], "languages_combined": []}, "experience_required": {"duration": [], "field": []}}, {"job_id": "100003009007852", "location_code": "hk", "company": "Clot Co. Limited", "job_title": "Fashion Graphic Designer / Senior Fashion Graphic Designer", "description": "Job Duties:\n\nFollow up seasonal graphic trend, fashion graphics techniques/application research, line sheet and theme board presentation\nHandle graphics, trims & packaging update\nCreate tech pack & output files to merchandising team for sampling & production\nAssist comment on all printing strike off and samples etc\nAssist ad hoc duties as required.\n\nRequirements:\n\nDegree or above in fashion design / graphic design or related discipline\nMin. 5 years relevant experience in fashion retail industry\nFamiliar with fashion graphics, printing process, embroideries and garment construction in Mens & Ladies casual wear\nGood knowledge in Adobe Photoshop CC, Illustrator CC, InDesign CC is a must\nWith knowledge in video editing is preferable\nStrong market sense and good creativity\nWith good fashion sense and knowledge of international fashion brands is preferable\nSuccessful candidates must be able to work independently, under pressure and meet dead-lines\nGood interpersonal and communication skills, well-organized, self-initiative, responsible & good team player\nGood command of both written and spoken English, Chinese & Mandarin\nCandidate with more experience will be considered as\u00a0Senior Fashion Graphic Designer\n\nWe offer medical insurance to the right candidates. Please send full \"Resume with your Portfolio and expected salary\" by clicking 'Apply Now'.\n\nAll applications received will be used strictly for selection purposes only.", "employment_types": ["Full Time", "Permanent"], "selling_points": ["Degree or above in fashion design", "Min. 3 years relevant experience", "Handle graphics, trims & packaging update"], "locations": ["Aberdeen"], "categories": ["Design", "Fashion", "Graphics", "Industrial / Product"], "post_time": "2021-12-30T04:46:48Z", "salary": {"currency": null, "max": null, "min": null, "period": "monthly", "term": null}, "salary_visible": false, "title_keywords": ["fashion graphic designer", "senior fashion graphic designer"], "responsibilities": ["graphics", "merchandising", "ad hoc duties"], "requirements": {"degrees": ["degree or above"], "majors": ["graphic design", "design"], "languages": ["english", "chinese", "mandarin"], "language_level": ["good command"], "hard_skills": ["graphics", "adobe photoshop", "indesign", "illustrator", "video editing"], "soft_skills": ["communication skills", "work independently", "good team player", "under pressure", "responsible", "well-organized", "self-initiative", "strong market sense", "interpersonal"], "languages_combined": [{"language": "english", "language_level": ["good command"]}, {"language": "chinese", "language_level": ["good command"]}, {"language": "mandarin", "language_level": ["good command"]}]}, "experience_required": {"duration": ["5 years"], "field": ["retail industry", "graphic", "relevant experience", "designer"]}}, {"job_id": "100003009008988", "location_code": "hk", "company": "Eternity Consultants (HK) Ltd", "job_title": "Fashion Designer / Senior Designer / Design Manager (Lingerie / Active Wear)", "description": "Requirements:\n\nDiploma or above in Fashion Design\nWith 3 years or above in\u00a0fashion design experience for lingerie or active wear\nResponsible for design and development of apparel items\nProvide directions and ideas on all design issues including costing, fashion trend research on colors, fabrication and accessories, etc.\nLiaise with buyers, merchandising team and China factory\nFollow up the entire workflow of the development from themes and concept, presentation of styling, sketches, fitting session and sampling\nFamiliar with USA and Europe fashion trends\nMore experience will consider to be Senior Designer or Design Manager\nGood command of English and Mandarin\n\n*Interested parties, please send full resume with current & expected salary & date available in MS WORD FORMAT ONLY to email: \u00a0jobs@HKETERNITY. com \u00a0\u00a0\u00a0or fax to 3527 0634\n\nHotline: (852) 3542 5082\n\nFor more jobs, please visit our website: www.hketernity.com\n\nWe are welcome applicants resend resumes to us even you have applied jobs in our company before.\n\n(Personal data submitted are for recruitment purpose only.)\u00a0", "employment_types": ["Full Time", "Permanent"], "selling_points": ["Lingerie or active wear fashion design experience", "Follow up the entire workflow", "Familiar with USA & Europe fashion trends"], "locations": ["Not Specified"], "categories": ["Design", "Fashion", "Manufacturing", "Garment / Textile", "Merchandising & Purchasing", "Woven / Knit"], "post_time": "2021-12-30T09:49:05Z", "salary": {"currency": null, "max": null, "min": null, "period": "monthly", "term": null}, "salary_visible": false, "title_keywords": ["senior designer", "fashion designer", "design manager"], "responsibilities": ["ideas", "merchandising", "sketches", "design", "liaise with"], "requirements": {"degrees": ["diploma or above"], "majors": ["design"], "languages": ["english", "mandarin"], "language_level": ["good command"], "hard_skills": [], "soft_skills": ["active", "presentation", "responsible"], "languages_combined": [{"language": "english", "language_level": ["good command"]}, {"language": "mandarin", "language_level": ["good command"]}]}, "experience_required": {"duration": ["3 years"], "field": ["designer", "fashion design", "design"]}}, {"job_id": "100003008995243", "location_code": "hk", "company": "Manson Precision Industrial Limited", "job_title": "Watch Designer", "description": "A sizable garment retails firm is \u201cUrgently\u201d seeking for :\n\nFashion Design Manager ~ Ladies\u2019 Casual Wear & Denim\n\nResponsibilities:\n\n\nAssistant to Director\nTo develop design ideas & sketching up design for top & bottoms in line for women\u2019s full, product range including denim items\nWork closely with Design Director to create and input on submissions during development process to sign off finishing\n\n\nRequirement:\n\n\nDegree holder in Fashion Design or related disciplines\nWith at least 8 years experiences in designing ladies casual wear and denim\nProficient in computer design programming, (e.g. Illustrator, Photoshop, Macintosh)\nGood knowledge in Hong Kong and China market (fashion trend)\nStation in Mainland China\n\n*Interested parties, please send full resume with current & expected salary & date available in MS WORD FORMAT ONLY to email: \u00a0jobs@HKETERNITY. com \u00a0\u00a0\u00a0or fax to 3527 0634\n\nHotline: (852) 3542 5082\n\nFor more jobs, please visit our website: www.hketernity.com\n\nWe are welcome applicants resend resumes to us even you have applied jobs in our company before.\n\n(Personal data submitted are for recruitment purpose only.)\u00a0", "employment_types": ["Full Time", "Permanent"], "selling_points": [], "locations": ["Tsuen Wan Area"], "categories": ["Design", "Fashion", "Graphics", "Merchandising & Purchasing", "Watch"], "post_time": "2021-12-29T01:44:39Z", "salary": {"currency": null, "max": null, "min": null, "period": "monthly", "term": null}, "salary_visible": false, "title_keywords": ["designer"], "responsibilities": ["ideas", "design", "develop"], "requirements": {"degrees": ["degree holder"], "majors": ["related disciplines", "design"], "languages": [], "language_level": [], "hard_skills": ["illustrator", "programming", "photoshop"], "soft_skills": [], "languages_combined": []}, "experience_required": {"duration": ["at least 8 years"], "field": []}}, {"job_id": "100003009008375", "location_code": "hk", "company": "ConnectedGroup Limited", "job_title": "Designer (Mens Casualwear) - contract", "description": "Responsibilities:\n\nResponsible for graphic design of watches and packaging.\nGood sketching and drafting technique.\nBasic knowledge of design techniques, tools and construction.\nCan handle design project independently.\nBe able to cooperate with other teams (e.g. sales & Engineering)\nRequirements:\n\nCertificate/ Diploma in Design or related discipline.\n3 + years of watch design experience.\nProficient in 2D/3D software: Adobe Illustrator, CorelDraw, Microsoft Office, Adobe Photoshop, Rhinoceros and KeyShot or equivalent.\nInnovative and creative.\nSelf-motivated, highly organized and strong conceptual rendering skills and presentation skills of 2D & 3D design.\nGood command of English, Cantonese and Mandarin\nImmediately available is preferred.", "employment_types": ["Full Time", "Permanent"], "selling_points": ["EU retailer", "Mens casualwear", "2 years+ experience"], "locations": ["Not Specified"], "categories": ["Design", "Fashion", "Merchandising & Purchasing", "Woven / Knit", "Textiles"], "post_time": "2021-12-30T07:48:19Z", "salary": {"currency": null, "max": null, "min": null, "period": "monthly", "term": null}, "salary_visible": false, "title_keywords": ["designer"], "responsibilities": ["graphic design", "teams", "cooperate with", "design"], "requirements": {"degrees": ["certificate", "diploma"], "majors": ["design"], "languages": ["cantonese", "english", "mandarin"], "language_level": ["good command"], "hard_skills": ["microsoft office", "3d software", "adobe photoshop", "adobe illustrator"], "soft_skills": ["organized", "self-motivated", "creative", "presentation skills", "innovative"], "languages_combined": [{"language": "cantonese", "language_level": ["good command"]}, {"language": "english", "language_level": ["good command"]}, {"language": "mandarin", "language_level": ["good command"]}]}, "experience_required": {"duration": ["3 + years"], "field": ["design"]}}, {"job_id": "100003009001379", "location_code": "hk", "company": "High Fashion Group", "job_title": "Design & Product Developer (Cut & Sewn / Woven)", "description": "Roles & Responsibilities\nMarket Research & Insight\n- Keep a finger on the pulse of the fashion/tech accessories market\n- Drive consumers and competitors analysis to identify business opportunities\n- Drive market research to identify color and material trends\nProduct Design - manage and run fashion/tech accessories collection design projects from start to finish in collaboration with brand manager\n- Concept Generation and Mood board preparation\n- Produced product design drawings, from first sketches to photorealistic 3D renders\n- Propose color themes and offerings that reflect market trends\n- Packaging Structure and Design\u00a0\n- Communicate design concepts and principles through visual presentation\u00a0\nProduct Development\n- Support product development team with various tech pack and CMF documents\n- Collaborate with product developers to follow through prototype/sample development process, give comments where appropriate to ensure the final product is well executed and delivers on the design intent.\nQualifications & Requirements\u202f\nUniversity degree / higher diploma in Fashion Design or related discipline.\n5+ years of\u00a0 knowledge in Adobe creative suite (Illustrator, Photoshop) and related design software & tools.\nCredible experience and technical knowledge in fashion accessories / bags design (experience in leather product design is a plus)\nA good understanding of fashion, color and material trends\nExcellent planning, prioritizing and organizational skills to ensure key deadlines are met\nAble to multitask and solve problems creatively\u00a0\nA high level of attention to details\nHighly self-motivated and proactive, with excellent presentation and communication skills\nGreat team player. Looking forward to new challenges of different categories.\nGood communication skills in both English and Chinese\nWe offer an attractive salary + benefits package including occasional outing with teams. Ready to join the team? Apply with your\u00a0portfolio in resume\u00a0& expected salary to us!\nAny personal data provided will be used for recruitment related purposes only and will be treated in strict confidence.", "employment_types": ["Full Time", "Permanent"], "selling_points": ["5 days, bonus, medical & life insurance", "Lunch allowance, birthday leave", "Flexible working hours"], "locations": ["Kwai Fong"], "categories": ["Design", "Fashion", "Merchandising & Purchasing", "Woven / Knit", "Textiles"], "post_time": "2021-12-28T02:23:08Z", "salary": {"currency": null, "max": null, "min": null, "period": "monthly", "term": null}, "salary_visible": false, "title_keywords": ["product developer"], "responsibilities": ["collaborate with", "design concepts", "identify business opportunities", "analysis", "comments", "market research", "design", "drawings", "mood board", "sketches", "product design", "visual presentation"], "requirements": {"degrees": ["university degree", "diploma"], "majors": ["design"], "languages": ["english", "chinese"], "language_level": ["good"], "hard_skills": ["illustrator", "plus", "adobe creative suite", "photoshop"], "soft_skills": ["organizational skills", "self-motivated", "proactive", "communication skills", "multitask", "solve problems", "attention to details", "team player", "creative", "presentation", "prioritizing"], "languages_combined": [{"language": "english", "language_level": ["good"]}, {"language": "chinese", "language_level": ["good"]}]}, "experience_required": {"duration": [], "field": ["product design", "design"]}}, {"job_id": "100003009006888", "location_code": "hk", "company": "Bape Hong Kong Limited", "job_title": "Head of Project & Interior Design", "description": "Responsibilities:\n\nDevelop clothing product design, fabrics and accessories sourcing, color and prints selection\nConduct marketing research and fashion trend analysis\nCollaborate closely with merchandise planning, production, and marketing teams from product concept, planning, production to marketing\nPrepare product presentation materials\n\nRequirements:\n\nMinimum two-year experience in C&S knit\u00a0R&D.\nProficiency in\u00a0 AI, Photoshop, 3D software: Browzwear or CLO, Basic Video edit skill\nA creative and passionate person with good fashion sense and design knowledge\nGood team player and able to work independently;\nWilling to travel and able to work under pressure.\nFluent in Cantonese, Mandarin, and English\n\nWe offer an attractive package, good prospects and fringe benefits to the right candidate. Interested parties, please apply with full resume, current and expected salary to: Group Human Resources Manager of High Fashion Group. By click below \"APPLY NOW\"(in MS Word format), or by mail: 11/F., High Fashion Centre, 1-11 Kwai Hei Street, Kwai Chung, New Territories\n\n(The information received will be used for consideration of employment only and all personal data supplied will be destroyed within 6 months.)", "employment_types": ["Full Time", "Permanent"], "selling_points": ["Overall monitoring and project management", "Lead and follow up construction site", "With at least 12-15 years of experience"], "locations": ["Overseas"], "categories": ["Building & Construction", "Architectural Services", "Design", "Fashion", "Interior"], "post_time": "2021-12-29T11:38:37Z", "salary": {"currency": null, "max": null, "min": null, "period": "monthly", "term": null}, "salary_visible": false, "title_keywords": [], "responsibilities": ["collaborate", "product concept", "analysis", "teams", "develop", "marketing research", "product design", "planning"], "requirements": {"degrees": [], "majors": [], "languages": ["cantonese", "english", "mandarin"], "language_level": ["fluent"], "hard_skills": ["r&d", "3d software", "basic", "ai", "photoshop"], "soft_skills": ["passionate", "good team player", "work independently", "creative", "work under pressure"], "languages_combined": [{"language": "cantonese", "language_level": ["fluent"]}, {"language": "english", "language_level": ["fluent"]}, {"language": "mandarin", "language_level": ["fluent"]}]}, "experience_required": {"duration": [], "field": []}}, {"job_id": "100003009004409", "location_code": "hk", "company": "International Fashion Group", "job_title": "Assistant / Product Developer - sportswear / casual wear", "description": "One of our clients (Luxury Jewellery) is now looking for a high calibre candidate to fill the following position:\n\n2 years experience in graphic design in Jewelry/ Fashion Industry is a must (please mark in your CV next to the company name);\nResponsible for different graphic design & digital marketing, including Instagram etc.;\nResponsible for product photo shooting;\nWilling to learn and team work;\nProficient in Adobe Illustrator, Photoshop and InDesign;\nGood command of both spoken and written English and Chinese.\n\nRemarks:\n\nMonthly salary: Open to discuss (depends on experience/ skill);\n5.5 day (Mon-Fri: 11am-8pm / Alt. Sat: 11am-5pm);\nWorking location:\u00a0Grade A Commercial Building, Causeway Bay;\nCo. background: Luxury Jewellery (Own Brand);\nGood fringe benefits will be provided.\n\nIf the above position is not suitable for you, please also feel free to send your CV to us for our job matching.\n\nInterested parties please click \"APPLY NOW\"\u00a0or send to\u00a0OUR EMAIL\u00a0and attach your updated resume with expected salary in \"MS WORD\" format.\n\nPlease quote the\u00a0Job Ref. No.\u00a0and\u00a0Applied Post\u00a0on the subject of your application.\n\nInterest to know our candidates' and clients' comments about our service? Please click\u00a0HERE.\n\nCompany website:\u00a0www.kek.com.hk\n\nThe information provided will only be used for recruitment related purposes.", "employment_types": ["Full Time", "Permanent"], "selling_points": ["Strong English communication skill", "3D garment software knowledge", "Higher Diploma / Degree holder in fashion design"], "locations": ["Not Specified"], "categories": ["Design", "Fashion", "Engineering", "Manufacturing & Production", "Merchandising & Purchasing", "Woven / Knit"], "post_time": "2021-12-29T02:20:34Z", "salary": {"currency": null, "max": null, "min": null, "period": "monthly", "term": null}, "salary_visible": false, "title_keywords": ["product developer", "assistant"], "responsibilities": ["product photo shooting", "graphic design", "digital marketing", "sat"], "requirements": {"degrees": [], "majors": [], "languages": ["english", "chinese"], "language_level": ["good command"], "hard_skills": ["indesign", "photoshop", "adobe illustrator"], "soft_skills": ["willing to learn", "responsible"], "languages_combined": [{"language": "english", "language_level": ["good command"]}, {"language": "chinese", "language_level": ["good command"]}]}, "experience_required": {"duration": ["2 years"], "field": ["graphic design"]}}, {"job_id": "100003009006646", "location_code": "hk", "company": "KEK Consultancy Company Limited", "job_title": "Senior/ Graphic designer  \u2013  Luxury Jewellery \u2013 Ref. 1960", "description": "Browzwear is the leading provider of 3D fashion design, development, and merchandising solutions. Our mission is to revolutionize the apparel industry with our truly disruptive 3D technology, providing the exact tools needed to exploit the extensive opportunities in the market to achieve that goal. We work with some of the biggest and most well-known global companies in the industry.\n\nWe are looking for a talented full-time Client Success Manager to join our growing team.\n\nClient Success Manager (Hong Kong)\n\nDrive retention and growth among our Clients by understanding their business needs and helping them succeed\nCollaborate closely with Sales to support pilot customers, renewals, and expansion opportunities\nIdentify and develop multi-level relationships with key decision makers and decision influencers to ensure retention and relationship stability\nDevelop scalable digital transformation plans that will deliver value by embedding 3D into daily workflows, including sharing relevant use cases, best practices, and ensuring business and user readiness\nPrepare, mobilize, and work with internal teams (across our regional and global teams), customer technical teams, client executives, and partners to manage and deliver successful solutions as needed to support the Client\u2019s needs\nEnsure deliverables fall within desired project scope and budget, report progress and identify potential risk to larger business targets\nMaintain a cadence of communicating with Clients about their adoption trends, sentiment, and exploring opportunities for deeper engagement\nIdentify opportunities for customers to act as Browzwear advocates (e.g. testimonials, case studies)\nBe a trusted technology advisor to customers and solve complex technical challenges, and establish credibility & build deep relationships with decision-makers and stakeholders within customers\u2019 organization\n\nWhat we are looking for:\n\n5+ years in a Relationship Management, Account Management, Digital Transformation or similar role, preferably with background in fashion/garment/sourcing/manufacturing/supply chain industries\nExceptional communication and presentation skills needed to liaison and network with a range of stakeholders including Clients, colleagues, and partner organizations\nExperience building and maintaining strong relationships, navigating political environments, and managing conflict\nProven track record of excellent verbal and written customer interaction and account development skills; having managed global customers directly and at senior levels.\nAbility to balance both big picture strategy while planning and executing critical details, mapping project milestones to broader business targets, defining key performance metrics, and validating desired value and appropriate experience delivered\nEmpathetic, positive attitude with a passion to help our Clients reach their digital goals\n\nSkills\n\nFull fluency in English, Mandarin and Cantonese\nStrong business acumen with relational awareness and counterintuitive thinking\nExperience in product creation.\nAbility to anticipate, discover, and define any challenges that the Client may encounter and design a solution with relevant teams\nComfortable presenting, consulting and advising at all levels of an organization\nAbility to effectively negotiate directly with the Client and internally on their behalf\nStrong problem solving and analytical skills, with the ability to translate data into insights\nResults-driven, highly organized, collaborative and detail-oriented\nTechnical acumen to learn Browzwear solutions\nProficient in PowerPoint/Keynote and Microsoft 365\nAbility and willingness to travel", "employment_types": ["Full Time", "Permanent"], "selling_points": ["Salary open to discuss", "Experience in graphic design in Jewelry/ Fashion", "Good company culture"], "locations": ["Causeway Bay"], "categories": ["Design", "Fashion", "Graphics", "Others"], "post_time": "2021-12-29T09:44:05Z", "salary": {"currency": null, "max": null, "min": null, "period": "monthly", "term": null}, "salary_visible": false, "title_keywords": ["graphic designer"], "responsibilities": ["collaborate", "management", "maintaining", "consulting", "data", "budget", "merchandising", "teams", "design", "develop", "communication", "performance metrics", "maintain", "communicating with", "planning", "executing", "plans", "report"], "requirements": {"degrees": [], "majors": [], "languages": ["cantonese", "english", "mandarin"], "language_level": ["fluency"], "hard_skills": ["powerpoint", "analytical skills", "problem solving", "goal", "pilot", "acumen"], "soft_skills": ["organized", "exact", "deep", "collaborative", "detail-oriented", "communication", "positive attitude", "presentation skills", "problem solving and analytical skills", "business acumen", "extensive", "driven"], "languages_combined": [{"language": "cantonese", "language_level": ["fluency"]}, {"language": "english", "language_level": ["fluency"]}, {"language": "mandarin", "language_level": ["fluency"]}]}, "experience_required": {"duration": [], "field": ["business", "planning"]}}, {"job_id": "100003008991168", "location_code": "hk", "company": "BW Global (HK) Limited", "job_title": "Client Success Manager", "description": "Responsibilities:\n\nCommunicating with oversea buyer to handle the whole design process from theme board preparation, styling confirmation, fitting sessions to pre-production stage;\nResearching of seasonal themes, material and colors;\nProduct analysis on materials, consumption, sewing structure.\nWork closely with merchandising and factories to facilitate development processes;\nPreparing for seasonal collection and related projects;\nMeeting with buyers and working closely with merchandisers and production team to ensure proper fitting and production of samples.\nProducts 3D rendering by computer 3D software if necessary.\u00a0\n\n\u00a0Requirements:\n\nDegree holder in Fashion Design, Textiles & Clothing or related disciplines;\n1-4 year experience of product development in sportswear/ active wear / casual wear.\n\nAdaptable to system and strong in computer skill.\u00a0\nSelf-motivated, good interpersonal skills and detail-oriented;\nGood command of English, Chinese & Mandarin;\nFamiliar with Photoshop, Illustrator, MS Office - Word, Excel, PowerPoint.\u00a0\nSkillful in apparel 3D software - such as Browzwear, CLO, Optitex is preferable.\u00a0\nImmediate available is preferred.\n\n\u00a05-day work and attractive salary package will be offered to the right candidates, interested parties please contact Human Resources Manager by email:\u00a0 hrdept @aroma.com for application", "employment_types": ["Full Time"], "selling_points": ["Be part of disruptive 3D fashion technology", "Interact with global fashion and apparel companies", "Develop best practices in digital transformation"], "locations": ["Lai Chi Kok"], "categories": ["Design", "Fashion", "Information Technology (IT)", "Technical / Functional Consulting", "Sales, CS & Business Devpt", "Account Servicing"], "post_time": "2021-12-22T03:03:39Z", "salary": {"currency": null, "max": null, "min": null, "period": "monthly", "term": null}, "salary_visible": false, "title_keywords": ["manager"], "responsibilities": ["software", "3d rendering", "analysis", "merchandising", "design", "communicating with", "pre-production"], "requirements": {"degrees": ["degree holder"], "majors": ["related disciplines", "design"], "languages": ["english", "chinese", "mandarin"], "language_level": ["good command"], "hard_skills": ["excel", "3d software", "illustrator", "word", "powerpoint", "computer skill", "photoshop", "ms office"], "soft_skills": ["self-motivated", "adaptable", "detail-oriented", "interpersonal skills", "active"], "languages_combined": [{"language": "english", "language_level": ["good command"]}, {"language": "chinese", "language_level": ["good command"]}, {"language": "mandarin", "language_level": ["good command"]}]}, "experience_required": {"duration": ["1-4 year"], "field": ["product development"]}}, {"job_id": "100003008998461", "location_code": "hk", "company": "I.T Apparels Limited", "job_title": "Visual Merchandiser (REF: JDB-IT-VM)", "description": "Accountabilities \u2013 Key Result Areas\n\nDesign, develop and execute all visual merchandising and promotional displays for promotional program, seasonal change and ad-hoc events\nMaintain and upkeep all visual merchandising materials at stores regularly\nAssist in sourcing, negotiation\u00a0and liaison with suppliers for the ordering, delivering and producing of materials,\u00a0and set up\u00a0relating to all visual merchandising\nAssist in setting up and coordinates new store opening and store upgrading\nWork closely in team for concept development, execution and all creative deliberationSupport graphic design\u00a0and development of artwork for various marketing materials such as print ad, brochure, packaging, POP, flyer, poster and etc.\nLiaise and coordinate with external agencies and vendors for print/production and quality control.\nProject management of all VM initiatives including windows, seasonal brand imagery, LED screens, POS and merchandise presentations all to be delivered in store, on time and on budget\nEnhance aesthetic appeal of shop front windows and in-store displays to promote new product launches, festive and seasonal themes including deliver regular floor moves, window installations, and mannequins styling, etc.\nExperience / Qualification Requirements\nDegree holder in visual merchandising and design related discipline\nAt least 3 years experience in fashion industry, with solid experience in visual design, window set up, interior displays and space utilization\nProficient design software skills such as Illustrator, Photoshop, AutoCAD, etc.\nCreative and possess good knowledge and sense of fashion, accessories, color trends and styling\nBe passionate about the brand\u2019s identity, with personal charisma and good understanding of the dynamics of the fashion industry\nCommunicative and be able to collaborate with business teams to achieve brand objectives\nCandidates with less experience will be considered as Visual Merchandising Coordinator.\n\nCompetitive remuneration and benefit package will be offered to the right candidate. Please submit your application by clicking \"Apply Now\" below.\n\nAll data collected is for recruitment purpose only.\n\nSure you want to know more about our company and brands, simply follow our\n\nWEBSITE at\u00a0http://www.ithk.com\u00a0 \u00a0 \u00a0 \u00a0 \u00a0 \u00a0 \u00a0 \u00a0 \u00a0 \u00a0 \u00a0 \u00a0 \u00a0 \u00a0 \u00a0 \u00a0 \u00a0 \u00a0 \u00a0 \u00a0 \u00a0 \u00a0 \u00a0 \u00a0 \u00a0 \u00a0 \u00a0 \u00a0 \u00a0 \u00a0 \u00a0 \u00a0 \u00a0 \u00a0\n\nFACEBOOK at\u00a0http://www.facebook.com/I.Ttheofficialpage\u00a0 \u00a0 \u00a0 \u00a0 \u00a0 \u00a0 \u00a0 \u00a0 \u00a0 \u00a0 \u00a0 \u00a0 \u00a0 \u00a0\u00a0\n\nINSTAGRAM at\u00a0http://instagram.com/ithk\u00a0 \u00a0 \u00a0 \u00a0 \u00a0 \u00a0 \u00a0 \u00a0 \u00a0 \u00a0 \u00a0 \u00a0 \u00a0 \u00a0 \u00a0 \u00a0 \u00a0 \u00a0 \u00a0 \u00a0 \u00a0 \u00a0 \u00a0 \u00a0 \u00a0 \u00a0 \u00a0 \u00a0\n\nWEIBO at\u00a0http://e.weibo.com/ithongkong", "employment_types": ["Full Time"], "selling_points": ["Visual Merchandising", "Promotional Displays", "3 years of Visual Merchandising experience"], "locations": ["Not Specified"], "categories": ["Design", "Fashion", "Graphics", "Visual Merchandising"], "post_time": "2021-12-24T03:35:24Z", "salary": {"currency": null, "max": null, "min": null, "period": "monthly", "term": null}, "salary_visible": false, "title_keywords": ["visual merchandiser"], "responsibilities": ["liaise", "collaborate with", "software", "data", "budget", "merchandising", "website", "design", "maintain", "facebook", "ad-hoc events", "teams", "presentations", "develop", "visual", "promotional program", "coordinate with", "graphic design", "project management", "recruitment", "quality control", "marketing materials"], "requirements": {"degrees": ["degree holder"], "majors": ["design"], "languages": [], "language_level": [], "hard_skills": ["pos", "visual merchandising", "illustrator", "presentations", "project management", "visual design", "autocad", "facebook", "photoshop"], "soft_skills": ["project management", "creative", "negotiation", "passionate about"], "languages_combined": []}, "experience_required": {"duration": ["at least 3 years"], "field": ["merchandising", "design"]}}, {"job_id": "100003008988790", "location_code": "hk", "company": "High Fashion Group", "job_title": "Product Developer", "description": "Responsibilities:\n\nDevelop clothing product design, fabrics and accessories sourcing, color and prints selection\nConduct marketing research and fashion trend analysis\nCollaborate closely with merchandise planning, production, and marketing teams from product concept, planning, production to marketing\nPrepare product presentation materials\n\nRequirements:\n\nMinimum two-year experience in C&S knit\u00a0/ Woven R&D.\nProficiency in\u00a0 AI, Photoshop, 3D software: Browzwear or CLO, Basic Video edit skill\nA creative and passionate person with good fashion sense and design knowledge\nGood team player and able to work independently;\nWilling to travel and able to work under pressure.\nFluent in Cantonese, Mandarin, and English\n\nWe offer an attractive package, good prospects and fringe benefits to the right candidate. Interested parties, please apply with full resume, current and expected salary to: Group Human Resources Manager of High Fashion Group. By click below \"APPLY NOW\"(in MS Word format), or by mail: 11/F., High Fashion Centre, 1-11 Kwai Hei Street, Kwai Chung, New Territories\n\n(The information received will be used for consideration of employment only and all personal data supplied will be destroyed within 6 months.)", "employment_types": ["Full Time", "Permanent"], "selling_points": ["5 days, bonus, medical & life insurance", "Lunch allowance, birthday leave", "Flexible working hours"], "locations": ["Kwai Fong"], "categories": ["Design", "Fashion", "Merchandising & Purchasing", "Woven / Knit", "Textiles"], "post_time": "2021-12-21T01:19:41Z", "salary": {"currency": null, "max": null, "min": null, "period": "monthly", "term": null}, "salary_visible": false, "title_keywords": ["product developer"], "responsibilities": ["collaborate", "product concept", "analysis", "teams", "develop", "marketing research", "product design", "planning"], "requirements": {"degrees": [], "majors": [], "languages": ["cantonese", "english", "mandarin"], "language_level": ["fluent"], "hard_skills": ["r&d", "3d software", "basic", "ai", "photoshop"], "soft_skills": ["passionate", "good team player", "work independently", "creative", "work under pressure"], "languages_combined": [{"language": "cantonese", "language_level": ["fluent"]}, {"language": "english", "language_level": ["fluent"]}, {"language": "mandarin", "language_level": ["fluent"]}]}, "experience_required": {"duration": [], "field": []}}, {"job_id": "100003008988471", "location_code": "hk", "company": "Hong Kong Disneyland", "job_title": "Costumer", "description": "Career with a Difference\nHong Kong Disneyland delivers world-class service and lifetime memories for our Guests. As a Cast Member, you will be an important part of the Disney Show. Working at Hong Kong Disneyland offers you the opportunity to participate in comprehensive training and experience excellent career development opportunities. Interested in a career with a difference? Join us now!\n\n\nResponsibilities:\nWork closely with vendors and suppliers to obtain bids, estimates and work plans for costume projects/manufacturing\nCoordinate the acquisition and delivery of raw materials from the suppliers and make sure they are delivered to the garment manufacturer in a timely basis\nPrepare project budgets and cash flow plans, monitor spending against plans providing reports to management as necessary, and meet all financial targets\nIdentify ongoing costume improvements which will improve Cast comfort and the Costume Distribution Department efficiency\nCreate production and manufacturing plans that provide adequate time for work flow and maximize the use of existing resources while reducing the need to deploy additional resources at a premium\nDesign and Image outfits for the new projects/events and execute all new designs to become products for performance and operation needs\nComply with all Company policies and Hong Kong legal codes\nBasic Qualifications:\nBachelor of Arts/Science in costume design, textiles, fashion merchandising, fashion design, fine arts\nAt least 5 years of relevant working experience\nExperience in Pattern making, textile construction/composition\nStrong leadership skills and interpersonal skills to communicate well internally and externally, ability to work independently\nFluent spoken and written skills in both Chinese (Cantonese, Mandarin) and English\nProficiency in computer skills\nCandidates with less experience will be considered as Associate Costumer\nAdditional Information:\nSUBMITTING YOUR APPLICATION\nAfter clicking \u201cApply for this job\u201d below, the employment application will open in a new window. Please complete ALL pages of the application in ENGLISH by clicking \u201cNext\u201d on each page, then \u201cSubmit\u201d on the final page.", "employment_types": ["Full Time"], "selling_points": ["Create production and manufacturing plans", "Bachelor of Arts/Science in costume design", "At least 5 years of relevant working experience"], "locations": ["Lantau Island"], "categories": ["Design", "Fashion", "Others"], "post_time": "2021-12-20T10:52:30Z", "salary": {"currency": null, "max": null, "min": null, "period": "monthly", "term": null}, "salary_visible": false, "title_keywords": [], "responsibilities": ["budgets", "management", "policies", "monitor", "merchandising", "design", "coordinate", "cash flow", "reports", "deploy", "career development", "plans"], "requirements": {"degrees": ["bachelor"], "majors": ["science", "fine arts", "design"], "languages": ["cantonese", "english", "chinese", "mandarin"], "language_level": ["fluent"], "hard_skills": ["make", "basic", "computer skills", "codes"], "soft_skills": ["work independently", "timely", "interested in", "leadership skills", "comprehensive", "interpersonal skills", "world-class"], "languages_combined": [{"language": "cantonese", "language_level": ["fluent"]}, {"language": "english", "language_level": ["fluent"]}, {"language": "chinese", "language_level": ["fluent"]}, {"language": "mandarin", "language_level": ["fluent"]}]}, "experience_required": {"duration": ["at least 5 years"], "field": ["training", "development", "relevant working experience", "textile", "construction"]}}, {"job_id": "100003008986965", "location_code": "hk", "company": "", "job_title": "Fashion Design Manager (Ladies' casual wear)", "description": "Responsibilities\n\nResponsible for the full collection of ladies' casual wear from the design concepts, styling, mood boards, coloring, fabric and wash direction\n\nCollaborates with different parties including designers, sales, supplier or other key strategic business partners to achieve product execution and maintain design integrity\nLead a small design team to execute according to seasonal calendars on a timely basis\nQualifications\n\nDegree or above in Fashion Design or related discipline\nStrong creativity with good fashion sense and knowledge of seasonal trends, especially in PRC market\n8 years' or above working experience in ladies' casual wear design, with at least 3 years' managerial experience preferable\nGood command of spoken and written Chinese & English including Mandarin\nFamiliar with Freehand, Photoshop & Illustrator\nStation in Guangdong province, PRC is a MUST\nCandidate with less experience could apply for the post of Assistant Fashion Design Manager (ladies' casual wear)\n\n\n\nInterested parties please send to email: nice_8888@yahoo.com to obtain the form and for enquiries.\n\nOnly short-list candidates will be contacted.\u00a0\u00a0 All information will be kept in strict confidence and personal data collected will be used for recruitment purpose only.", "employment_types": ["Full Time"], "selling_points": [], "locations": ["Others - China"], "categories": ["Design", "Fashion"], "post_time": "2021-12-20T04:14:45Z", "salary": {"currency": null, "max": null, "min": null, "period": "monthly", "term": null}, "salary_visible": false, "title_keywords": ["design manager"], "responsibilities": ["design concepts", "maintain", "design"], "requirements": {"degrees": ["degree or above"], "majors": ["design"], "languages": ["english", "chinese", "mandarin"], "language_level": ["good command"], "hard_skills": ["small", "illustrator", "photoshop"], "soft_skills": ["timely", "integrity", "responsible"], "languages_combined": [{"language": "english", "language_level": ["good command"]}, {"language": "chinese", "language_level": ["good command"]}, {"language": "mandarin", "language_level": ["good command"]}]}, "experience_required": {"duration": ["at least 3 years", "8 years"], "field": ["managerial", "fashion design", "design"]}}, {"job_id": "100003008988523", "location_code": "hk", "company": "I.T Apparels Limited", "job_title": "Graphic Designer (REF: JDB-IT-GD)", "description": "Accountabilities \u2013 Key Result Areas\n\nAssist development of multi-purpose graphic design initiatives and visual content for online and offline communication channels that uphold brand guidelines and values, and within the pre-set timelines and budget\nDesign a wide range of corporate promotional / marketing materials, including but not limited to advertisements, posters, flyers, marketing collaterals, catalogues, DM and EDM\nLiaise with suppliers and clients to obtain competitive quotes and ensure print quality of the highest standards\n\nExperience / Qualification Requirements\n\nDegree holder in graphic design related discipline\nWith 3 years solid experience in graphic design in creative agency or in house environment\nExperience working on a variety of projects, including brand identity, illustration, infographics, patterns and packaging is an added advantage\nPassion for design, with a keen eye for detail\nCreative, communicative and be able to collaborate with business teams to achieve brand objectives\n\nCompetitive remuneration and benefit package will be offered to the right candidate. Please submit your application by clicking \"Apply Now\" below.\n\nAll data collected is for recruitment purpose only.\n\nSure you want to know more about our company and brands, simply follow our\n\nWEBSITE at http://www.ithk.com\u00a0 \u00a0 \u00a0 \u00a0 \u00a0 \u00a0 \u00a0 \u00a0 \u00a0 \u00a0 \u00a0 \u00a0 \u00a0 \u00a0 \u00a0 \u00a0 \u00a0 \u00a0 \u00a0 \u00a0 \u00a0 \u00a0 \u00a0 \u00a0 \u00a0 \u00a0 \u00a0 \u00a0 \u00a0 \u00a0 \u00a0 \u00a0 \u00a0 \u00a0\n\nFACEBOOK at\u00a0http://www.facebook.com/I.Ttheofficialpage\u00a0 \u00a0 \u00a0 \u00a0 \u00a0 \u00a0 \u00a0 \u00a0 \u00a0 \u00a0 \u00a0 \u00a0 \u00a0 \u00a0\u00a0\n\nINSTAGRAM at http://instagram.com/ithk\u00a0 \u00a0 \u00a0 \u00a0 \u00a0 \u00a0 \u00a0 \u00a0 \u00a0 \u00a0 \u00a0 \u00a0 \u00a0 \u00a0 \u00a0 \u00a0 \u00a0 \u00a0 \u00a0 \u00a0 \u00a0 \u00a0 \u00a0 \u00a0 \u00a0 \u00a0 \u00a0 \u00a0\n\nWEIBO at\u00a0http://e.weibo.com/ithongkong", "employment_types": ["Full Time", "Permanent"], "selling_points": ["3 years' relevant experience for fashion brands", "Design a wide range of corporate promotional", "Graphic design house background is welcome"], "locations": ["Southern Area"], "categories": ["Design", "Fashion", "Graphics", "Multi-media"], "post_time": "2021-12-20T11:19:29Z", "salary": {"currency": null, "max": null, "min": null, "period": "monthly", "term": null}, "salary_visible": false, "title_keywords": ["graphic designer"], "responsibilities": ["collaborate with", "advertisements", "edm", "graphic design", "data", "budget", "marketing collaterals", "quality", "design", "teams", "communication", "website", "brand guidelines", "recruitment", "visual", "marketing materials", "facebook", "liaise with suppliers"], "requirements": {"degrees": ["degree holder"], "majors": ["graphic design"], "languages": [], "language_level": [], "hard_skills": ["facebook", "illustration"], "soft_skills": ["passion for", "keen", "communication", "eye for detail", "creative"], "languages_combined": []}, "experience_required": {"duration": ["3 years"], "field": ["agency", "graphic design", "brand"]}}, {"job_id": "100003008992570", "location_code": "hk", "company": "Prosperity Textile (H.K.) Limited", "job_title": "\u6210\u8863\u6a23\u7248\u6280\u5e2b**", "description": "\n\u8077\u8cac :\u8ca0\u8cac\u6210\u8863\u526a\u88c1, \u8eca\u7e2b, \u71a8\u71d9\u53ca\u7522\u54c1\u8cbc\u6a19\u5236\u4f5c, \u6574\u7406\u7248\u623f\u7269\u6599, \u8ddf\u9032\u5c55\u5ef3\u7522\u54c1\u9673\u5217\u53ca\u66f4\u65b0, \u7c21\u55ae\u5831\u8868\u66f4\u65b0\u5de5\u4f5c\n\n\u8cc7\u6b77 :\u5c0f\u4e00\u7a0b\u5ea6; 5\u5e74\u7d93\u9a57; \u826f\u597d\u7cb5\u8a9e; \u7565\u61c2\u8b80\u5beb\u4e2d\u6587; \u61c2\u8eca\u8863; \u61c2MS Excel; \u51775\u5e74\u6216\u4ee5\u4e0a\u8eca\u8863\u5de5\u4f5c\u7d93\u9a57(\u5305\u62ec\u8863\u8eca\u53ca\u9aa8\u8eca),\u4e86\u89e3\u7d19\u6a23\u7d50\u69cb\n\n\u5f85\u9047 :\u6bcf\u6708$9,000 - $12,000, \u6709\u9280\u884c\u5047\u671f, \u91ab\u7642\u4fdd\u96aa \u53ca\u5e74\u7d42\u734e\u91d1, \u661f\u671f\u4e00\u81f3\u4e94: \u4e0a\u53489\u6642\u81f3\u4e0b\u53486\u6642\u53ca\u661f\u671f\u516d: \u4e0a\u53488\u6642\u81f3\u4e0b\u53481\u6642, \u6bcf\u9031\u5de5\u4f5c5\u5929\u81f35\u5929\u534a, \u6bcf\u5929\u5de5\u4f5c 8 \u5c0f\u6642\n\n\u7533\u8acb\u9808\u77e5 :\u6c42\u8077\u8005\u53ef\u81f4\u96fb37507325\u8207\u5317\u6c5f\u7d21\u7e54(\u9999\u6e2f)\u6709\u9650\u516c\u53f8\u6881\u5148\u751f\u806f\u7d61\u3002\n\n", "employment_types": ["Full Time"], "selling_points": [], "locations": ["Tsuen Wan Area"], "categories": ["Design", "Fashion", "Manufacturing", "Garment / Textile", "Product Development / Management"], "post_time": "2021-12-22T05:17:31Z", "salary": {"currency": null, "max": null, "min": null, "period": "monthly", "term": null}, "salary_visible": false, "title_keywords": [], "responsibilities": [], "requirements": {"degrees": [], "majors": [], "languages": [], "language_level": [], "hard_skills": ["excel"], "soft_skills": [], "languages_combined": []}, "experience_required": {"duration": [], "field": []}}]