[{"job_id": "100003009054574", "location_code": "hk", "company": "Taste of Asia Group Limited", "job_title": "Graphic Designer", "description": "Responsibilities\n\n\nPropose design concepts & develop visuals based on images of the group and brands\nResponsible for all graphic design and production of marketing materials including advertisement, menu, e-marketing and packaging etc.\nResponsible for product photo-shooting\nAssist in ad-hoc duties and projects\n\nRequirements\n\n\nHigher Diploma in Graphic Design or related disciplines\nMinimum 3 year\u2019s relevant working experiences. Experience in F&B industry is an advantage\nProficiency in Mac software, AI, Photoshop, InDesign\nInnovative, imaginative and creative, able to show strong initiative\nSelf-motivated and able to work independently under tight deadline\nAttention to detail, good team-player and good time management skill\nMore experience may consider as Senior Position\nImmediate available is preferred\n\nJob location: San Po Kong\n\n\n\u00a0Competitive remuneration package and benefits as below:\n\n5-Day Work Week\n\nMarriage leave\n\nStaff discount\n\nMedical & dental allowance\n\nPerformance bonus\n\nIn-service training course\n\n5 days paternity leave\n\nCompassionate Leave\n\nPromotion opportunities\n\n\u00a0Interested parties may send your detailed resume with expected salary and notice period to:By clicking Apply Now\u00a0\n\nAll information collected will be used for recruitment purpose only.", "employment_types": ["Full Time"], "selling_points": ["5-Day Work Week", "Medical & dental allowance", "Performance bonus"], "locations": ["Wong Tai Sin Area"], "categories": ["Design", "Graphics", "Others"], "post_time": "2022-01-17T10:03:19Z", "salary": {"currency": null, "max": null, "min": null, "period": "monthly", "term": null}, "salary_visible": false, "title_keywords": ["graphic designer"], "responsibilities": ["design concepts", "graphic design", "develop", "photo-shooting", "ad-hoc duties", "marketing materials"], "requirements": {"degrees": ["diploma"], "majors": ["related disciplines", "graphic design"], "languages": [], "language_level": [], "hard_skills": ["indesign", "photoshop", "ai"], "soft_skills": ["self-motivated", "work independently", "team-player", "innovative", "imaginative", "attention to detail", "time management skill", "creative", "initiative"], "languages_combined": []}, "experience_required": {"duration": ["minimum 3 year"], "field": ["f&b"]}}, {"job_id": "100003009053805", "location_code": "hk", "company": "freeD Group Limited", "job_title": "Graphic Designer", "description": "About FreeD Group:\n\nFreeD Group, a holding company of TravelFlan, ARA Buddy and FreeD Technologies, is an award-winning, proprietary end2end AI Digital and Smart Merchandising Solution provider, one of the fastest growing tech innovation start-ups based in Hong Kong with operations in South Korea, China, Singapore and UAE, expanding into South East Asia and Europe. FreeD Group is the winner of 2021 UNWTO Global Start-up Competition, Deloitte Rising Star 2021 and 2018 APAC ICT Grand Award.\n\nJob Description:\n\n- Creation of aesthetic and effective visual designs for campaigns, both offline and online mediums and other ad hoc internal design requirements.\n\n- Possess a strong ability to work autonomously as well as part of a team.\n\n- Needs to be proactive enough to always be on top of all the branding activities being executed, ensuring that there is always that indelible stamp of Travelflan on every touch point of the brand.\n\n- Work on and extend the Travelflan brand guidelines into all the design work going out to create a strong and comprehensive visual identity for the brand.\n\nDesired Skills:\n\n- Have 1-2 yrs of relevant expertise in the mentioned profile\n\n- Have impeccable taste and a compulsive eye for detail.\n\n- Be able to quickly deliver strong designs during rapid, iterative processes and multitask in a fast-paced environment.\n\n- Have a passion for creating new and creative branding units and marketing collateral.\n\n- Have in-depth knowledge of Adobe Photoshop and Illustrator.\n\n- Bonus: Being able to illustrate.", "employment_types": ["Full Time", "Permanent"], "selling_points": [], "locations": ["Tsim Sha Tsui"], "categories": ["Design", "Graphics"], "post_time": "2022-01-17T07:32:30Z", "salary": {"currency": null, "max": null, "min": null, "period": "monthly", "term": null}, "salary_visible": false, "title_keywords": ["graphic designer"], "responsibilities": ["design work", "ad hoc", "operations", "merchandising", "design", "brand guidelines", "visual"], "requirements": {"degrees": [], "majors": [], "languages": [], "language_level": [], "hard_skills": ["visual identity", "ai", "adobe photoshop", "illustrator", "rapid"], "soft_skills": ["creative", "passion for", "fast-paced environment", "multitask", "comprehensive", "eye for detail", "proactive"], "languages_combined": []}, "experience_required": {"duration": [], "field": []}}, {"job_id": "100003009054603", "location_code": "hk", "company": "Kingmaker Limited", "job_title": "Graphic Designer", "description": "About Peeba\n\nPeeba is a wholesale marketplace that makes discovering and buying wholesale from exciting brands from around the world easy and risk-free. We\u2019re backed by multiple prominent venture capital funds in the world and we are seeking an aesthetic and responsible Graphic Designer to join our growing organization.\n\nSince our product launch in June 2020, we have partnered up with over 1,300 unique brands with over 50,000 products to bring them into Asian retail stores, and developed machine learning algorithms to connect retailers with brands that we guarantee will sell.\n\nDiscover an exciting career opportunity at a rapidly growing rocket ship startup that will give you the environment and the freedom to excel. Join us on our mission to become the intelligent operating system that powers the future of commerce, and transform the way local retailers buy for their stores.\n\nAbout this role\n\nAs a Graphic Designer, you will be collaborating closely with marketing, digital and sales teams to bring Peeba\u2019s long term vision to life.\n\nWhat you\u2019ll do\n\nUnderstand the creative vision of the brand and deliver effective design solutions\nTake responsibility and be able to deliver graphic design solutions in social media communication (posts, banners, ads), and other multimedia marketing material where necessary (digital, email, poster, brochure)\nEnsure effective visual presentation down into execution at market level with reference to brand image consistency and guidelines provided\nAct as the key contact person for all graphic issues across the H.K. head office and regional subsidiaries\n\nQualifications\n\nMinimum 2 - 3 years\u2019 work experience in Graphic Design, preferably in Tech, e-Commerce or Lifestyle industry\nDiploma holder or above in Graphic Design or related disciplines\nProficient in AI, InDesign and Photoshop\nAble to work independently with a can-do attitude to meet multiple project deadlines with quality\nGreat team player, communicate and collaborate effectively with teammates cross-functionally in a fast-paced work environment\nExperience in working at a high-growth startup is a plus\nImmediate available would be a definite advantage\n\nInterested parties please send us a full resume with your portfolio.\n\nThis position is full-time and will be based in Hong Kong. Pay will be competitive and based on talent and experience.\n\nPlease send in your application through this link:\n\nhttps://airtable.com/shrOsCYczJ4hUiVUU\n\nNote: Only shortlisted candidates will be contacted.", "employment_types": ["Full Time"], "selling_points": ["Graphic Designer", "Excellent development opportunities", "Startup work environment"], "locations": ["Kwun Tong Area"], "categories": ["Design", "Graphics"], "post_time": "2022-01-17T10:13:06Z", "salary": {"currency": null, "max": null, "min": null, "period": "monthly", "term": null}, "salary_visible": false, "title_keywords": ["graphic designer"], "responsibilities": ["collaborate", "social media", "design solutions", "guidelines", "graphic design", "teams", "quality", "communication", "banners", "contact", "visual presentation", "marketing material"], "requirements": {"degrees": ["diploma holder"], "majors": ["related disciplines", "graphic design"], "languages": [], "language_level": [], "hard_skills": ["excel", "plus", "ai", "e-commerce", "indesign", "multimedia", "venture capital", "photoshop"], "soft_skills": ["work independently", "responsible", "can-do attitude", "unique", "communication", "learning", "team player", "creative", "presentation"], "languages_combined": []}, "experience_required": {"duration": ["minimum 2 - 3 years"], "field": ["graphic design", "tech", "e-commerce"]}}, {"job_id": "100003009053931", "location_code": "hk", "company": "Nissin Foods (HK) Management Co Ltd", "job_title": "Graphic Designer", "description": "Job Description\n\n\nWork closely with Marketing and R&D teams to create and modify designs of brands and product packages\nDevelop marketing collaterals from conceptualization to completion of graphic designs, including key visuals, in-store POP, advertisements, online promotion materials and social media content etc.\nSupport in printing of product package and marketing collaterals\nExecute food shot and product photo shooting and retouching\nDevelop graphic / multimedia design and support in photography for corporate and brands\u2019 promotional events and activities\nInitiate creative ideas to promote brands and products\nPerform other ad-hoc projects and tasks as required\n\nJob Specification\n\nTertiary educated or above in Graphic Design, Multimedia or related discipline\n3-4 years relevant experience in Graphic Design. Experience in FMCG package design or food industry is an advantage\nProficiency in Mac OS and Adobe Creative Suite\nGood at drawing or illustration is an advantage\nGood command in both written and spoken English and Chinese, Mandarin is preferred\nOccasional business trip is required when necessary\nImmediate available is preferred\n\n\u00a0Applicant please email\u00a0DETAILED RESUME\u00a0with\u00a0present and expected salary\u00a0to Human Resources Dept.\n\n(All personal data collected will be used for recruitment purpose only)", "employment_types": ["Full Time", "Permanent"], "selling_points": [], "locations": ["Tai Po Area"], "categories": ["Design", "Graphics", "Industrial / Product", "Multi-media"], "post_time": "2022-01-17T07:47:45Z", "salary": {"currency": null, "max": null, "min": null, "period": "monthly", "term": null}, "salary_visible": false, "title_keywords": ["graphic designer"], "responsibilities": ["multimedia design", "marketing collaterals", "graphic designs", "design", "promote brands and products", "social media content", "ad-hoc projects", "personal data", "key visuals", "online promotion materials", "teams", "develop", "occasional business trip", "designs of brands", "food shot", "initiate creative ideas", "printing of product package", "retouching", "advertisements", "graphic design", "in-store pop", "product photo shooting", "support in photography", "recruitment"], "requirements": {"degrees": [], "majors": [], "languages": ["english", "chinese", "mandarin"], "language_level": ["good command"], "hard_skills": ["r&d", "mac os", "multimedia", "illustration", "adobe creative suite"], "soft_skills": ["creative", "detailed"], "languages_combined": [{"language": "english", "language_level": ["good command"]}, {"language": "chinese", "language_level": ["good command"]}, {"language": "mandarin", "language_level": ["good command"]}]}, "experience_required": {"duration": ["3-4 years"], "field": ["fmcg", "graphic design", "food industry", "design", "relevant experience"]}}, {"job_id": "100003009047654", "location_code": "hk", "company": "Creative Choice Limited", "job_title": "Graphic Designer", "description": "Job Specification / Responsibilities\n\n1. Monitor and guide brand art direction\n\n2. Take care of photo, video and copy writing for all marketing collateral\n\n3. Responsible for different graphic design & artwork adaptation including poster, leaflets, banners, Facebook, in-store graphic etc.\n\n4. Coordinate internal and external party for advertising and promotion activityCandidate's Requirement\n\n1. over 2 years of working experience\n\n2. proficient in Adobe Illustrator, Adobe Photoshop and Adobe Acrobat\n\n3. Work experience in advertising agent is an advantage\u00a0", "employment_types": ["Full Time"], "selling_points": ["Monitor and guide brand art direction", "Take care of all marketing collateral", "Responsible for different graphic design & artwork"], "locations": ["Lai Chi Kok"], "categories": ["Design", "Graphics"], "post_time": "2022-01-17T07:50:13Z", "salary": {"currency": null, "max": null, "min": null, "period": "monthly", "term": null}, "salary_visible": false, "title_keywords": ["graphic designer"], "responsibilities": ["advertising", "leaflets", "graphic design", "monitor", "coordinate", "banners", "facebook"], "requirements": {"degrees": [], "majors": [], "languages": [], "language_level": [], "hard_skills": ["facebook", "adobe photoshop", "adobe acrobat", "adobe illustrator"], "soft_skills": ["responsible"], "languages_combined": []}, "experience_required": {"duration": ["2 years"], "field": ["advertising"]}}, {"job_id": "100003009053408", "location_code": "hk", "company": "The Hebe Haven Yacht Club Ltd", "job_title": "Graphic Designer", "description": "Job Description\n\nReports to the PR & Communications Manager, the incumbent is responsible for a variety of duties involving: designing newsletters, articles, posters, brochures, video filming and editing, online marketing materials development and other support services.\n\nResponsibilities\n\nResponsible for photos touch-ups, poster editing and offline/online marketing materials development (menus, posters, banners, eDM ads, etc)\u00a0\u00a0\u00a0\u00a0\u00a0\u00a0\u00a0\u00a0\u00a0\nProvide creative insights to scale up the club's image and maintain brand standards\nSupport in-house photo-shoots and event management when required\nStay current in design trends and styles in various media, including digital and social channels\nUse a variety of tools, applications and computer software to generate new images\nCreate print-ready files to send to printer\nSupport video production and editing when required\nOvertime or non-office hours work might be required according to business needs (esp. during events)\n\nRequirements\n\nGraduate from design school with creative media related background\nWith 2-3 years related working experience (preferably 5 years or above)\nExcellent interpersonal skills\nProficiency in Mac software, AI, Photoshop, InDesign, ideally Premiere Pro\nKnowledge of aesthetic sense of art and detail-minded, willing to accommodate ad-hoc requests from different stakeholders\nAble to effectively communicate in English & Chinese, in both written and spoken forms\nExcellent organisational skills to function effectively under tight time constraints to meet \u00a0established deadlines, with particular attention to detail\nGood computer knowledge (Word, Excel, PowerPoint and Chinese Word Processing)\n\nWe offer a competitive employment package to the right candidate, including free staff meals, additional MPF contributions, 13-month salary and medical benefits.\n\nRemuneration shall be commensurate with the candidate\u2019s qualifications and experience. To apply for the above jobs, please send your resume and a one-page sample and your design to our Human Resources Manager by clicking \"Apply Now\"\n\nAll information received will be used for recruitment purpose only.", "employment_types": ["Full Time"], "selling_points": ["5 days work per week", "Free staff meals, additional MPF contribution", "2-3 years related working experience"], "locations": ["Sai Kung Area"], "categories": ["Design", "Graphics", "Multi-media"], "post_time": "2022-01-17T07:01:38Z", "salary": {"currency": null, "max": null, "min": null, "period": "monthly", "term": null}, "salary_visible": false, "title_keywords": ["graphic designer"], "responsibilities": ["management", "software", "edm", "video production", "support services", "design trends", "banners", "maintain", "reports", "designing", "marketing materials", "editing"], "requirements": {"degrees": [], "majors": [], "languages": ["english", "chinese"], "language_level": ["good"], "hard_skills": ["excel", "chinese word processing", "ai", "indesign", "word", "powerpoint", "premiere pro", "photoshop"], "soft_skills": ["detail-minded", "organisational skills", "interpersonal skills", "attention to detail", "creative"], "languages_combined": [{"language": "english", "language_level": []}, {"language": "chinese", "language_level": ["good"]}]}, "experience_required": {"duration": ["5 years", "2-3 years"], "field": ["related"]}}, {"job_id": "100003009052627", "location_code": "hk", "company": "Telford International Co Ltd", "job_title": "Graphic Designer", "description": "JOB DESCRIPTION\n\nResponsible for product creative design from concept to final artwork\nPrepare engaging content such as graphics, photos, imagery and video to drive traffic conversion and brand awareness\nPerform daily management of social media accounts and media planning.\nTo perform other duties assigned by management\n\nQUALIFICATIONS\n\nDegree holder of Graphic Design, Visual Communication, Marketing, Communications, e-Commerce etc.\nSolid knowledge with one (or more) of these creative and digital tools is a MUST: Photoshop / Illustrator / InDesign /Final Cut Pro/ video editing skills\nGood writing skill in editorial & marketing materials with media angle\nGood sense of social media platforms and passionate to initiate digital creative ideas\nProactive and energetic team player with self-motivation, creativity and positive working attitude\nAbility to achieve results and willing to contribute beyond basic responsibilities\nExcellent communications in English and Chinese\n\nWHY YOU SHOULD JOIN US\n\nWe provide constant guidance, training and mentorship to polish your business mindset. We care about your personal and professional growth\nFlat operating structure, you will be able to work independently, make your own judgement and make a direct impact to the company\nWe work in an open, collaborative, and respectful culture where we empower every single person to grow and play to their strengths\nFlexible work hours. Our priority is on getting the job done\nYou\u2019ll be working in a fast-paced environment\n\nPlease send your CV together with the expected salary to us.\nShortlisted candidates will be invited to a first round interview and notified by email or phone.", "employment_types": ["Full Time", "Permanent"], "selling_points": ["3 years or above relevant experience", "Strong portfolio of illustrations or other graphic", "Familiar with design software and technologies"], "locations": ["Kwai Hing"], "categories": ["Design", "Graphics", "Industrial / Product", "Multi-media"], "post_time": "2022-01-17T03:35:59Z", "salary": {"currency": null, "max": null, "min": null, "period": "monthly", "term": null}, "salary_visible": false, "title_keywords": ["graphic designer"], "responsibilities": ["graphics", "social media", "management", "perform other duties", "creative ideas", "graphic design", "social media platforms", "design", "communication", "video editing", "visual", "marketing materials", "planning"], "requirements": {"degrees": ["degree holder"], "majors": ["graphic design", "marketing", "communications", "e-commerce"], "languages": ["english", "chinese"], "language_level": ["excellent"], "hard_skills": ["creative design", "graphics", "final cut pro", "basic", "e-commerce", "indesign", "illustrator", "writing skill", "video editing", "visual communication", "photoshop"], "soft_skills": ["passionate", "proactive", "responsible", "writing skill", "communication", "positive working attitude", "energetic", "self-motivation", "team player", "creative"], "languages_combined": [{"language": "english", "language_level": ["excellent"]}, {"language": "chinese", "language_level": ["excellent"]}]}, "experience_required": {"duration": [], "field": []}}, {"job_id": "100003009054126", "location_code": "hk", "company": "Fairwood Fast Food Ltd", "job_title": "Graphic Designer, Specialty Restaurant", "description": "Requirements:\n\nDiploma or above in relevant disciplines;\nAt least 3 years relevant experience in arts and design fields;\nProficient in Photoshop, Illustrator and other related design software with good output knowledge;\nHandle graphics design and production for advertising, social media content and other marketing collateral;\nStrong in graphic sense, creative and conceptual skills;\nGood command of written & spoken English and Mandarin;\nSelf-motivated & Independent;\nGood interpersonal skills and willing to learn;\nBasic knowledge in Interior Design would be a plus;\n\nWe offer competitive package and promising career prospect to the right candidate.\nInterested parties please send detailed resume, portfolio and expected salary quoting the corresponding position by clicking \u201cApply Now\u201d.", "employment_types": ["Full Time", "Permanent"], "selling_points": ["Collateral design in printed and digital", "English/Chinese translation & copywriting", "Diploma holder with min 2-year relevant experience"], "locations": ["North Point"], "categories": ["Design", "Graphics", "Hospitality / F & B", "Food & Beverage", "Marketing / Public Relations", "Digital Marketing"], "post_time": "2022-01-17T08:29:20Z", "salary": {"currency": null, "max": null, "min": null, "period": "monthly", "term": null}, "salary_visible": false, "title_keywords": ["graphic designer"], "responsibilities": ["graphics", "advertising", "software", "design", "social media content"], "requirements": {"degrees": ["diploma or above"], "majors": [], "languages": ["english", "mandarin"], "language_level": ["good command"], "hard_skills": ["graphics", "plus", "basic", "illustrator", "photoshop"], "soft_skills": ["self-motivated", "independent", "willing to learn", "interpersonal skills", "creative"], "languages_combined": [{"language": "english", "language_level": ["good command"]}, {"language": "mandarin", "language_level": ["good command"]}]}, "experience_required": {"duration": ["at least 3 years"], "field": ["relevant experience", "design"]}}, {"job_id": "100003009054207", "location_code": "hk", "company": "Mindmad Creation Limited", "job_title": "Graphic Designer (Stage/ Graphic Design)", "description": "\nWe are looking for a talented graphic to create engaging and on-brand graphics for a variety of media. The Graphic Designer job description includes the entire process of defining requirements, visualizing and creating graphics including illustrations, logos, layouts and photos. You\u2019ll be the one to shape the visual aspects of web banners, leaflets, Posters, product packaging and more.\n\nResponsibilities\n\n\nStudy design briefs and determine requirements\nConceptualize visuals based on requirements\nPrepare rough drafts and present ideas\nDevelop illustrations, logos and other designs using software or by hand\nUse the appropriate colors and layouts for each graphic\nWork with marketing\u00a0 to produce suitable design\nAmend designs after feedback\nEnsure final graphics and layouts are visually appealing and on-brand\n\nRequirements\n\n\n3 years or above related working experience\nA strong portfolio of illustrations or other graphics\nFamiliar with design software and technologies (Such as Photoshop, Illustrator, Premiere, After Effect)\nA keen eye for aesthetics and details\nExcellent communication skills\nAbility to work methodically and meet deadlines\nGood team player, multi-tasking, willing to learn, open-minded, independent and responsible\nWilling to work overtime\nWe offer attractive remuneration package and career prospects plus 5-day week and medical insurance. Interested parties please send your full resume with expected salary & Portfolio to us.\u00a0\nAll data collected shall be solely for recruitment purpose.\nWebsite: www.telford.com.hk", "employment_types": ["Full Time", "Permanent"], "selling_points": [], "locations": ["Quarry Bay"], "categories": ["Media & Advertising", "Creative / Design", "Design", "Graphics", "Marketing / Public Relations", "Marketing - General / Support"], "post_time": "2022-01-17T08:49:12Z", "salary": {"currency": null, "max": null, "min": null, "period": "monthly", "term": null}, "salary_visible": false, "title_keywords": ["graphic designer"], "responsibilities": [], "requirements": {"degrees": [], "majors": [], "languages": [], "language_level": [], "hard_skills": ["graphics", "illustrator", "premiere", "after effect", "photoshop"], "soft_skills": ["communication skills", "good team player", "work overtime", "independent", "responsible", "keen", "open-minded", "willing to learn", "multi-tasking", "meet deadlines"], "languages_combined": []}, "experience_required": {"duration": ["3 years"], "field": ["related"]}}, {"job_id": "100003009053839", "location_code": "hk", "company": "LifeHub Limited", "job_title": "Marketing Executive / Graphic designer", "description": "Responsibilities:\n\nExecute graphic design tasks, includes a full range of different collaterals both printed and digital\nLiaise with external parties e.g. printers, agencies, vendors and external designers\nAssist in photo and video shooting and retouch\nConstantly keep an eye on collaterals in shops and restaurants to ensure the appropriateness of content and design, good in quality, initiate replacement where needed\nAssist in English and Chinese translations and copy writing (marketing collaterals and social media)\n\n\n\nRequirements:\n\n\nDiploma / Degree holder in Graphic Design or related disciplines\nMinimum 2-year relevant working experience in Graphic Design, preferably in F&B / restaurant / retail / hospitality industry\nSound technical knowledge in design needs\nSkillful at photography and videography is preferred but not mandatory\nFluent in both spoken and written English, Chinese and Mandarin\nProficient in Photoshop / Illustrator & MS Office applications including Word, Excel, PowerPoint and Chinese Processing\n\nCompetitive remuneration package will be offered to the right candidate. Interested parties please click\u00a0\"Apply Now\"\u00a0or send full resume with expected salary by email to\u00a0 recruitoffice@ fairwood.com.hk\u00a0or 2) direct mail to HR Manager, 2/F TRP Commercial Centre, 18 Tanner Road, North Point, Hong Kong.\n\n(Data collected will be used for recruitment purpose only)", "employment_types": ["Full Time"], "selling_points": [], "locations": ["Central"], "categories": ["Design", "Graphics", "Marketing / Public Relations", "Marketing - Marketing Communication", "Digital Marketing"], "post_time": "2022-01-17T07:36:17Z", "salary": {"currency": null, "max": null, "min": null, "period": "monthly", "term": null}, "salary_visible": false, "title_keywords": ["graphic designer", "marketing executive"], "responsibilities": ["social media", "graphic design", "external parties", "quality", "marketing collaterals", "design", "video shooting", "liaise with"], "requirements": {"degrees": ["diploma", "degree holder"], "majors": ["related disciplines", "graphic design"], "languages": ["english", "chinese", "mandarin"], "language_level": ["proficient", "fluent"], "hard_skills": ["excel", "illustrator", "word", "powerpoint", "photoshop", "processing", "ms office"], "soft_skills": [], "languages_combined": [{"language": "english", "language_level": ["fluent"]}, {"language": "chinese", "language_level": ["proficient", "fluent"]}, {"language": "mandarin", "language_level": ["fluent"]}]}, "experience_required": {"duration": ["minimum 2-year"], "field": ["graphic design", "restaurant", "relevant working experience", "hospitality industry", "f&b", "retail"]}}, {"job_id": "100003008993855", "location_code": "hk", "company": "Tranthink Technology Service Limited", "job_title": "Graphic Designer", "description": "Requirements:\n\nPost-secondary (Diploma/Certificate) in Art, Design, Graphic, Advertising or other related disciplines\nAt least 2~3 years of commercial graphic design experience;\nA design portfolio is a must - Fluent in Adobe Creative Suite\u00a0\nProficient in Adobe Illustrator, Photoshop and InDesign;\nFluent in Adobe CS, in particular, Photoshop, Illustrator and InDesign. Knowledge and experience in Cinema 4D, After Effects and Premiere Pro a bonus.\nCreative, detail-minded, responsible with constant innovation and work dynamic\nProficient in PhotoShop and Illustrator, venue decoration familiar with MAC would be an advantage\nGood command of written and spoken English & Chinese (Mandarin & Cantonese)\nFresh Graduates are welcome to apply\u00a0\nGood communication skills with customers\nImmediate available is preferred\nHave a positive and passionate approach with a can-do attitude.\nMeticulous planning and organizational skills.\n\nJob Descriptions:\n\nCreate graphic design & layout for various design projects\nCollaborate with team to deliver innovative creative concepts that meet client business objectives\nDevelop effective, brand-appropriate marketing and promotional layouts for digital and print media\nKnowledge in Output process\nCreative, strong sense\u00a0at\u00a0good typography, layout, good color\u00a0and\u00a0marketing sense\nSelf-motivating, creative, energetic, a positive attitude with strong interpersonal skills, able to work independently and as an integral part of the team, share ideas openly and work towards the common goal of the team\nMust be open to new ideas and enjoy working with a creative team\nStrong sense of responsibility, attention to details and a good team player, creative, energetic and independent with excellent critical thinking and interpersonal skills\nCommunicate and collaborate closely with internal clients and stakeholders to facilitate the creative process\nDevelop creative ideas and concepts, often in partnership with other creative team members.\nBeing a problem solver and have a creative mindset\nAssist in planning and implementation of marketing activities, public relations, events management, online marketing and loyalty marketing;\nLiaise and maintain good relationship with strategic partners and tenants for coordinating effective marketing collaborations;\u00a0\nWork closely with internal and external parties to achieve marketing goals;\u00a0\nParticipate in ad hoc projects as assigned;\u00a0\nSelf-motivated & independent, responsible and able to work under tight schedule and pressure.\nHandle idea and project related to art with creativity\nOversee profitability, deliverables, timelines and budgets\nMotion graphic, and video editing skills is a huge plus\u00a0\nProduce clear and concise verbal and written communications.\nCommunicate with internal parties on the design requirement for projects ( e.g. leaflets and printed materials design and publishing. )\nProducing graphic layout and production output", "employment_types": ["Full Time", "Permanent"], "selling_points": ["5 Days Work, Double Pay, Medical Insurance", "Flexible working hours, Free snack", "Designing promotional materials"], "locations": ["Not Specified"], "categories": ["Design", "Graphics", "Web Designer", "Information Technology (IT)", "Others"], "post_time": "2022-01-16T21:50:01Z", "salary": {"currency": null, "max": null, "min": null, "period": "monthly", "term": null}, "salary_visible": false, "title_keywords": ["graphic designer"], "responsibilities": ["collaborate with", "liaise", "ideas", "graphic layout", "internal and external parties", "design", "video editing", "collaborate", "implementation", "develop", "maintain good relationship", "schedule", "communicate with internal parties", "develop creative ideas", "management", "leaflets", "motion graphic", "budgets", "graphic design", "facilitate the creative process", "ad hoc projects", "planning"], "requirements": {"degrees": ["certificate", "diploma"], "majors": ["related disciplines", "art", "design"], "languages": ["cantonese", "english", "chinese", "mandarin"], "language_level": ["good command"], "hard_skills": ["indesign", "illustrator", "adobe illustrator", "after effects", "dynamic", "premiere pro", "adobe cs", "adobe creative suite", "photoshop"], "soft_skills": ["detail-minded", "communication skills", "passionate", "meticulous", "organizational skills", "responsible", "can-do attitude", "dynamic", "creative", "positive"], "languages_combined": [{"language": "cantonese", "language_level": ["good command"]}, {"language": "english", "language_level": ["good command"]}, {"language": "chinese", "language_level": ["good command"]}, {"language": "mandarin", "language_level": ["good command"]}]}, "experience_required": {"duration": ["at least 2~3 years"], "field": ["commercial", "graphic design"]}}, {"job_id": "100003009042751", "location_code": "hk", "company": "ISS-Vision Events Limited", "job_title": "Graphic Designer", "description": "Job Description\n\nRoles & Responsibilities\nResponsible for creative concept development and handle all stages of design include but not limited to the following:\n\u2022 Social media visual and feed designs (Facebook, Instagram, eDM, Google ad, etc.)\n\u2022 Online store visual (Web banner, product page, etc)\n\u2022 Sales kit and POP materials\n\u2022 Product retouching and mock-ups\n\u2022 Presentation powerpoint\n\u2022 Printing\nAssisting in all marketing campaigns\nAssisting in all marketing materials in line with marketing plans\nAssisting in website updates\nImplementing promotional campaigns\nSupport clinical team on updating marketing materials, screens etc\nAssisting in handling different marketing promotion materials\nAd hoc projects as assigned by management\n\nSkills & Qualifications\nFluent in English & Chinese\n2-3 years relevant working experience in graphic design\nNeed to be highly organised and attention to detail\nWith passion, creativity and imagination in design\nEager to learn and to participate in marketing projects\nFresh graduates are welcome\n\nPlease send your CV with 3-5 examples of recent artwork job reference.", "employment_types": ["Full Time", "Permanent"], "selling_points": ["Exhibitions and Events", "Creative design", "Concept development"], "locations": ["Wong Tai Sin Area"], "categories": ["Design", "Graphics", "Others"], "post_time": "2022-01-16T21:50:12Z", "salary": {"currency": "HKD", "max": 29999, "min": 20000, "period": "monthly", "term": null}, "salary_visible": true, "title_keywords": ["graphic designer"], "responsibilities": ["pop materials", "management", "edm", "marketing plans", "graphic design", "product retouching", "mock-ups", "social media visual and feed designs", "design", "website", "marketing projects", "ad hoc projects", "marketing campaigns", "visual", "marketing materials", "facebook", "sales kit"], "requirements": {"degrees": [], "majors": [], "languages": ["english", "chinese"], "language_level": ["fluent"], "hard_skills": ["powerpoint", "facebook", "web"], "soft_skills": ["responsible", "eager to learn", "attention to detail", "organised", "creative", "presentation"], "languages_combined": [{"language": "english", "language_level": ["fluent"]}, {"language": "chinese", "language_level": ["fluent"]}]}, "experience_required": {"duration": ["2-3 years"], "field": ["graphic design", "relevant working experience"]}}, {"job_id": "100003009054425", "location_code": "hk", "company": "Celestial Asia Securities Holdings Ltd", "job_title": "Senior Graphic Designer", "description": "Job responsibilities:\nDesign web pages for corporate branding and work on interface solutions\nSupport senior designers to create and convey design solutions\nAnalysis and improvement for the design projects (wireframe, mockup and prototype)\nDesign for the advertising material and relevant graphics when needed\nHandle ad-hoc tasks or projects as assigned\nRequirements:\nHigher Diploma or Degree in Web Design/ Graphic Design or related discipline;\nAt least 2 years working experience in Website/ Graphic Design/ UI/UX work, with experience of a full cycle project in mobile/web;\nCurrent experience in web design, digital promotion, graphic design with promotion material etc;\nSolid experience in designing Corporate Branding / commercial website/marketing material etc;\nProficient in Adobe Creative, Photoshop, Illustrator, XD etc;\nA portfolio to demonstrate design work;\nWork independently and good team player;\nGood in spoken and writing in English and Chinese\nPlease click \"Apply Now\" to submit your application.\n\n\nPersonal data collected will be used for recruitment purpose only.\n", "employment_types": ["Full Time"], "selling_points": ["Higher Diploma in Graphic Design/Commercial Arts", "At least 5 years relevant experience", "Immediate availability preferred"], "locations": ["Kowloon Bay"], "categories": ["Design", "Graphics", "Industrial / Product", "Multi-media"], "post_time": "2022-01-17T09:29:54Z", "salary": {"currency": null, "max": null, "min": null, "period": "monthly", "term": null}, "salary_visible": false, "title_keywords": ["senior graphic designer"], "responsibilities": ["graphics", "advertising", "design solutions", "analysis", "ad-hoc tasks", "design"], "requirements": {"degrees": ["diploma", "degree"], "majors": ["web design", "graphic design"], "languages": ["english", "chinese"], "language_level": ["good"], "hard_skills": ["web design", "web", "illustrator", "mobile", "adobe", "photoshop"], "soft_skills": ["good team player", "work independently", "creative"], "languages_combined": [{"language": "english", "language_level": ["good"]}, {"language": "chinese", "language_level": ["good"]}]}, "experience_required": {"duration": ["at least 2 years"], "field": ["graphic design", "design", "commercial", "marketing", "digital"]}}, {"job_id": "100003009053010", "location_code": "hk", "company": "Challenger Auto Services Limited", "job_title": "Graphic Designer / Senior Graphic Designer", "description": "- Creating event design. Execute from concept to design, artwork output and print production.\n\n- Concept development, visualization and hands on design for key visual.\n\n\n- Degree holder in visual communication related disciplines;\n\n- Experience in design research, divergent exploration, conceptual development;\n\n- Strong graphic and art sense, creative and passionate;\n\n- Proficiency in Adobe Illustrator, Photoshop, InDesign, affect effect\u2026etc.\n\n- Experience in storyboard, photo & video shooting technique with editing;\n\n- Experience in event decoration design is a plus;\n\n- Self-motivated, energetic, with the ability to work independently;\n\n- Good communication skills in English, Cantonese and Mandarin;\n\n- Able to work under pressure with tight deadline and multi-task;\n\n- Less experience will be considered as Graphic Designer.", "employment_types": ["Full Time"], "selling_points": [], "locations": ["Tsuen Wan Area"], "categories": ["Design", "Graphics", "Multi-media"], "post_time": "2022-01-17T05:03:16Z", "salary": {"currency": null, "max": null, "min": null, "period": "monthly", "term": null}, "salary_visible": false, "title_keywords": ["senior graphic designer", "graphic designer"], "responsibilities": ["visualization", "conceptual development", "event decoration", "design", "communication", "video shooting", "visual", "editing", "artwork output", "work under pressure"], "requirements": {"degrees": ["degree holder"], "majors": ["related disciplines"], "languages": ["cantonese", "english", "mandarin"], "language_level": ["good"], "hard_skills": ["plus", "indesign", "adobe illustrator", "visual communication", "photoshop"], "soft_skills": ["passionate", "communication skills", "self-motivated", "work independently", "multi-task", "communication", "energetic", "hands on", "creative", "work under pressure"], "languages_combined": [{"language": "cantonese", "language_level": ["good"]}, {"language": "english", "language_level": ["good"]}, {"language": "mandarin", "language_level": ["good"]}]}, "experience_required": {"duration": [], "field": ["photo", "research", "designer", "development", "design", "video shooting", "graphic", "editing"]}}, {"job_id": "100003009054086", "location_code": "hk", "company": "i-CABLE Communications Limited", "job_title": "Senior Visual Designer", "description": "Reporting to the General Manager of Group Public Affairs, you will be responsible for developing all corporate visual and creative ideas and concepts, from layout development through to the production of final products and activities, such as print, web, videos, brand building, photography and exhibition. In addition to routine brand maintenance works, ad hoc projects will be required for various of our business groups as and when required.\u00a0\n\n\nRequirements\n\nHigher Diploma or above in Graphic Design, Commercial Arts or other related disciplines\nAt least 5 years relevant experience in design field\nProficiency in using design softwares such as Adobe Photoshop, Illustrator, InDesign and Dreamweaver, familiar with PC Microsoft Office i.e. Powerpoint & Word\nStrong knowledge in logo and branding, web, multi-media design, photography, printing and production\nBe highly creative and sensitive to designs and trends\nBe passionate and take initiatives and ownership of the visual elements of creative work\nHave excellent interpersonal and communication skills and be able to work well as part of a team, with a range of people, well organized, mature and self-motivated\nImmediate availability preferred\nPlease apply in confidence with full resume, current and expected salary, quoting reference by clicking \u201cAPPLY NOW\".\n\nThe information provided will be used for selection purpose only. All information of unsuccessful applicants will be destroyed within six months.", "employment_types": ["Full Time", "Permanent"], "selling_points": [], "locations": ["Tsuen Wan Area"], "categories": ["Design", "Graphics", "Media & Advertising", "Editorial / Journalism", "Broadcasting - TV / Radio"], "post_time": "2022-01-17T08:21:10Z", "salary": {"currency": null, "max": null, "min": null, "period": null, "term": null}, "salary_visible": false, "title_keywords": ["designer"], "responsibilities": ["reporting", "creative ideas", "maintenance", "graphic design", "developing", "design", "communication", "ad hoc projects", "visual"], "requirements": {"degrees": ["higher diploma or above"], "majors": ["related disciplines", "graphic design"], "languages": [], "language_level": [], "hard_skills": ["maintenance", "web", "design softwares", "microsoft office", "adobe photoshop", "indesign", "illustrator", "powerpoint", "word", "dreamweaver", "pc", "logo"], "soft_skills": ["passionate", "communication skills", "self-motivated", "confidence", "responsible", "well organized", "mature", "sensitive to", "creative", "interpersonal"], "languages_combined": []}, "experience_required": {"duration": ["at least 5 years"], "field": ["relevant experience", "design"]}}, {"job_id": "100003009054911", "location_code": "hk", "company": "Bastille Post Company Limited \u300a\u5df4\u58eb\u7684\u5831\u300b", "job_title": "Art Designer \u2013 Online Marketing", "description": "Job Responsibilities:\n\nHandle day to day graphics design for advertising, marketing, social media content;\nDesign and production for event decoration and promotional items;\nCreate concept and artwork as company branding;\nany ad-hoc projects that maybe assigned by manager;\n\nJob Requirement:\n\nAt least 3 years working experience in media, advertising agency preferred;\nDiploma or above in in Art, Graphic Design, Multimedia or related\u00a0disciplines in Graphic Design;\u00a0 \u00a0\u00a0\nAble to handle multiple tasks with tight schedule and work under pressure;\nDetail-oriented, responsible, independent and can work in a team;\nRelevant experience/ enthusiast in the automobile or eSport project\u00a0is\u00a0preferred; \u00a0 \u00a0 \u00a0 \u00a0 \u00a0 \u00a0 \u00a0\u00a0\nProficient in Photoshop, Adobe Illustrator of Mac environment is a MUST;\nGood command of written and spoken Cantonese and English;\nImmediate availability is highly preferred\n\nInterested candidates, please send your full resume stating with contact details, current & expected salary email to HR Department.\u00a0\n\nAll applications will be treated in strict confidence and be used solely for recruitment purpose.", "employment_types": ["Full Time", "Permanent"], "selling_points": [], "locations": ["Kwun Tong"], "categories": ["Design", "Graphics", "Multi-media", "Others"], "post_time": "2022-01-18T02:04:05Z", "salary": {"currency": null, "max": null, "min": null, "period": "monthly", "term": null}, "salary_visible": false, "title_keywords": ["designer"], "responsibilities": ["graphics", "advertising", "event decoration", "design", "social media content", "ad-hoc projects"], "requirements": {"degrees": ["diploma or above"], "majors": ["related disciplines", "graphic design", "art"], "languages": ["cantonese", "english"], "language_level": ["good command"], "hard_skills": ["adobe illustrator", "mac environment", "multimedia", "photoshop"], "soft_skills": ["independent", "responsible", "detail-oriented", "handle multiple tasks", "work under pressure"], "languages_combined": [{"language": "cantonese", "language_level": ["good command"]}, {"language": "english", "language_level": ["good command"]}]}, "experience_required": {"duration": ["at least 3 years"], "field": ["relevant experience", "media", "advertising agency"]}}, {"job_id": "100003009052723", "location_code": "hk", "company": "Imagine Lab Limited", "job_title": "Designer", "description": "On-Air Promotion\u00a0Department\nTo be responsible for producing on-air promos; following up with non-linear editing and post production work; providing creative ideas on all promotional campaigns and projects; initiating motion graphic design for promotion video\u00a0\nProficient in After Effects, Illustrator, Final Cut Pro, Maya, 3Ds Max and Photoshop\u00a0\nUniversity graduate with minimum 2 years experience in TV or creative industry\nGood command of both spoken and written English and Chinese\nAlert to deadlines with Can-do attitude\nGood interpersonal and communication skills\n\nWe offer 5-day work week, competitive remuneration packages and advancement opportunities. Interested parties, please write with full resume to Director, Human Resources, Human Resources Department, i-CABLE Communications Limited, 4/F Cable TV Tower, 9 Hoi Shing Road Tsuen Wan, N.T. or fax to 2112 7841 or via Apply Now (Please quote reference number and position applied for). For other information, please visit our website http://www.i-cable.com.\n\nYour application may be forwarded to any affiliate companies and successful applicant may be seconded to work at any office as assigned.\u00a0 The information received will be used for consideration of employment only and all personal data supplied will be destroyed within 3 months.\n\n\nWe are an equal opportunity employer.", "employment_types": ["Full Time", "Permanent"], "selling_points": [], "locations": ["Others"], "categories": ["Media & Advertising", "Others", "Design", "Graphics", "Multi-media"], "post_time": "2022-01-17T03:48:35Z", "salary": {"currency": null, "max": null, "min": null, "period": "monthly", "term": null}, "salary_visible": false, "title_keywords": ["designer"], "responsibilities": ["communication", "editing", "creative ideas", "motion graphic design"], "requirements": {"degrees": ["university graduate"], "majors": [], "languages": ["english", "chinese"], "language_level": ["good command"], "hard_skills": ["final cut pro", "maya", "3ds max", "illustrator", "after effects", "photoshop"], "soft_skills": ["communication skills", "responsible", "can-do attitude", "creative", "interpersonal"], "languages_combined": [{"language": "english", "language_level": ["good command"]}, {"language": "chinese", "language_level": ["good command"]}]}, "experience_required": {"duration": ["minimum 2 years"], "field": []}}, {"job_id": "100003009054029", "location_code": "hk", "company": "Shepherd Communications Limited", "job_title": "Senior Graphic Designer", "description": "Roles and Responsibilities:\n\nDesign and produce graphics, online banners, storyboards, website layouts and animated infographics\nDevelop after effects for video production\u00a0\n\n\nJob Requirement:\n\nDegree/Diploma/ Certificate in Graphic Design or related disciplines;\nMinimum 5 years graphic design experience preferred;\nSelf motivated, responsible, mature and able to handle multiple projects independently;\nProficiency in PC, experience in using Photoshop, Illustrator, Indesign and After Effect etc.;\nGood presentation skill and strong creativity;\nAble to work under pressure, meet tight deadline and willing to work overtime if needed;\nDrawing skill is an advantage;\nKnowledge in video shooting, recording, editing & post-production for all kinds of video is an advantage;\n5.5 days\u2019 work per week\n\nInterested parties please click \u201cApply Now\" to submit your complete resume with\u00a0compensation history, expected salary and REFERENCE NUMBER or by\u00a0fax to\u00a02798 2925.\n\nWe are an equal opportunity employer and welcome applications from all qualified candidates. Information provided will be treated in strict confidence and only be used for recruitment related purpose. Applicant who is not invited for an interview within 6 weeks may consider their application not successful. All personal data of unsuccessful applicants will be destroyed within 6 months.", "employment_types": ["Full Time", "Permanent"], "selling_points": ["Senior Graphic Designer", "Graphic design", "Motion Graphics"], "locations": ["Sai Ying Pun"], "categories": ["Media & Advertising", "Creative / Design", "Design", "Graphics", "Multi-media"], "post_time": "2022-01-17T09:16:34Z", "salary": {"currency": null, "max": null, "min": null, "period": "monthly", "term": null}, "salary_visible": false, "title_keywords": ["senior graphic designer"], "responsibilities": ["graphics", "video production", "website", "design", "develop", "banners", "storyboards"], "requirements": {"degrees": ["certificate", "diploma", "degree"], "majors": ["related disciplines", "graphic design"], "languages": [], "language_level": [], "hard_skills": ["presentation skill", "indesign", "illustrator", "pc", "after effect", "photoshop"], "soft_skills": ["presentation skill", "work overtime", "independently", "responsible", "mature", "self motivated", "meet tight deadline", "work under pressure"], "languages_combined": []}, "experience_required": {"duration": ["minimum 5 years"], "field": ["graphic design"]}}, {"job_id": "100003009053221", "location_code": "hk", "company": "CEMG Management Limited", "job_title": "Senior Graphic Designer", "description": "Responsibilities:\n\n\nDeveloping creative concepts, visual and artwork for event, coordination of production, social media, campaign, leaflet, poster, packaging, website, etc.\nHandling 2D and 3D design work\nAbility to demonstrate excellence in creativity across multiple media\nImplementation of marketing plans & promotion and supporting Event & Marketing team on product launching\nWorking closely with the project team to ensure smooth daily operations\n\nRequirements:\n\n\nDegree/higher diploma holder in a relevant design discipline\n1-2 years or above working experience in graphic design for print ads, booklets, event backdrops, exhibition, mall decoration, etc.\nHands-on experience in using Adobe CS, particularly in Photoshop and Illustrator\nGood hand drawing skill is preferable\nWith knowledge in multi-media & web design\nGood layout and presentation skill\nProficient in 3D Max/C4D/3D software\nSelf-motivated, creative, independent, be able to work under pressure and meet deadlines\nHaving positive and passionate approach with a can-do attitude\nWilling to work overtime and outside normal office hours\nImmediately is preferable\n\nOffice location: Yau Tong\n\nInterested parties please send your detailed resume, portfolio and expected salary to\u00a0us.\u00a0(All personal data collected will be used for recruitment purpose only)\u00a0", "employment_types": ["Full Time"], "selling_points": ["5 days work", "Graphic Design", "Strong in Photoshop, AfterEffect"], "locations": ["Tin Hau"], "categories": ["Design", "Graphics", "Industrial / Product", "Beauty Care / Health", "Others"], "post_time": "2022-01-17T06:28:18Z", "salary": {"currency": null, "max": null, "min": null, "period": "monthly", "term": null}, "salary_visible": false, "title_keywords": ["senior graphic designer"], "responsibilities": ["design work", "social media", "marketing plans", "leaflet", "developing", "website", "implementation", "daily operations", "coordination", "visual"], "requirements": {"degrees": ["degree", "higher diploma holder"], "majors": ["design"], "languages": [], "language_level": [], "hard_skills": ["presentation skill", "web design", "c4d", "3d software", "illustrator", "adobe cs", "max", "photoshop"], "soft_skills": ["presentation skill", "passionate", "self-motivated", "work overtime", "independent", "can-do attitude", "hands-on", "meet deadlines", "creative", "positive", "work under pressure"], "languages_combined": []}, "experience_required": {"duration": ["1-2 years"], "field": ["graphic design", "print", "cs"]}}, {"job_id": "100003009053141", "location_code": "hk", "company": "Harmonic Scene Limited", "job_title": "Multimedia Designer (5-Day Work)", "description": "Job Responsibilities\n\n\nResponsible for graphic design from concept creative to final artwork.\nWide range of graphic design jobs including Advertising, Corporate Identity, digital games & moving images.\nDevelop 2D layouts for Animation, AR & VR Games.\nGenerate idea and create storyboard for TVC, Micro Films, Corporate Video & Animation.\nQualifications, Skills and Other Requirement\n\n\nDiploma in Graphic Design or related discipline.\n4 years solid experience;\u00a0at least 2 years in the same capacity.\nHighly Proficiency in Adobe Illustrator and vector graphics. Knowledge of Adobe Photoshop in output standard.\nExcellent in Graphic Design, perfectionist in design details.\nAccuracy in output - online and printing.\nKnowledge in 2D animation and film editing (After Effect or\u00a0Adobe Premiere).\nUnderstanding digital marketing, content marketing, SEO,\u00a0UI and UX, and mobile responsive is a bonus.\nExcellent work attitude,\u00a0highly responsible and able to\u00a0handle multiple projects.\nAble to complete project under tight deadlines.\nAttractive salary & 5-day work per week. Interested parties please email full CV with Present & Expected Salary by clicking \u201cAPPLY NOW\u201d.\n\n\nAll personal data collected will be kept confidential and used for recruitment purpose only.\n\n", "employment_types": ["Full Time", "Permanent"], "selling_points": [], "locations": ["Kwai Hing"], "categories": ["Media & Advertising", "Creative / Design", "Design", "Graphics", "Multi-media"], "post_time": "2022-01-17T06:04:33Z", "salary": {"currency": null, "max": null, "min": null, "period": "monthly", "term": null}, "salary_visible": false, "title_keywords": ["multimedia designer"], "responsibilities": ["graphics", "advertising", "ar", "seo", "graphic design", "design", "develop", "digital marketing", "multiple projects", "editing", "ui", "animation"], "requirements": {"degrees": ["diploma"], "majors": ["graphic design"], "languages": [], "language_level": [], "hard_skills": ["graphics", "seo", "ar", "adobe photoshop", "adobe illustrator", "mobile", "adobe premiere", "after effect"], "soft_skills": ["creative", "responsive", "responsible"], "languages_combined": []}, "experience_required": {"duration": ["4 years"], "field": []}}, {"job_id": "100003009054877", "location_code": "hk", "company": "Dragon Creative Media Limited", "job_title": "Multimedia Graphic Designer / Graphic Designer", "description": "Key Responsibilities\n\nCreate graphic and multimedia design from concept to finished artwork development in print and digital communications.\nMonitor the design and production quality of marketing materials.\nWork closely with Marketing and Creative and Game Departments.\n\nRequirements\n\nDiploma or Degree holder in Multimedia/ Creative Media/ Design or related disciplines.\nMinimum 3 years' solid experience in Multimedia Design/ Advertising/ Graphic Design and Printing Production.\nCreative, excellent drawing and concept skills.\nProficiency in Creative Cloud (Photoshop, Illustrator, InDesign, After Effect, Premiere Pro, HTML5, etc.) and Maya on Mac environment.\nStrong sense of responsibility and work independently.\nKnowledge of Web Design, Animation and Video Production is an advantage.\n\nInterested parties please submit your detailed CV (with current and expected salary) by clicking \"Apply Now\".\u00a0\u00a0\n\nData collected will be used for recruitment purpose only.", "employment_types": ["Full Time"], "selling_points": ["5 days work", "At least 1 year multimedia experience", "Strong creative sense"], "locations": ["Southern Area"], "categories": ["Design", "Graphics", "Multi-media", "Web Designer"], "post_time": "2022-01-17T12:18:24Z", "salary": {"currency": null, "max": null, "min": null, "period": "monthly", "term": null}, "salary_visible": false, "title_keywords": ["graphic designer"], "responsibilities": ["multimedia design", "artwork development", "quality", "monitor", "design", "marketing materials"], "requirements": {"degrees": ["diploma", "degree holder"], "majors": ["related disciplines", "creative media", "design"], "languages": [], "language_level": [], "hard_skills": ["web design", "maya", "mac environment", "indesign", "illustrator", "multimedia", "premiere pro", "after effect", "photoshop"], "soft_skills": ["work independently", "creative", "sense of responsibility"], "languages_combined": []}, "experience_required": {"duration": ["minimum 3 years"], "field": ["graphic design", "advertising", "design"]}}, {"job_id": "100003009052772", "location_code": "hk", "company": "Imagine Lab Limited", "job_title": "Senior 3D Designer", "description": "Job Description\n\n- Certificate / Diploma in Multimedia Design with 1-2 year multimedia experience\n\n- Proficiency in Photoshop, Illustrator, After Effects, MAYA, 3DMax & AutoCAD\n\n- To handle multimedia projects [text, sound, images, 3D-modelling, animation & rendering]\n\n- Creative, strong sense in multimedia design, self-motivated and self-disciplined", "employment_types": ["Full Time", "Permanent"], "selling_points": [], "locations": ["Others"], "categories": ["Media & Advertising", "Others", "Design", "Graphics", "Multi-media"], "post_time": "2022-01-17T06:45:53Z", "salary": {"currency": null, "max": null, "min": null, "period": "monthly", "term": null}, "salary_visible": false, "title_keywords": ["senior 3d designer"], "responsibilities": ["multimedia design", "animation"], "requirements": {"degrees": ["certificate", "diploma"], "majors": ["multimedia design"], "languages": [], "language_level": [], "hard_skills": ["maya", "illustrator", "after effects", "autocad", "3dmax", "multimedia", "photoshop"], "soft_skills": ["self-motivated", "creative"], "languages_combined": []}, "experience_required": {"duration": ["1-2 year"], "field": ["design"]}}, {"job_id": "100003009052271", "location_code": "hk", "company": "Lubuds F&B Group", "job_title": "Graphics Designer", "description": "Job Duties:\u00a0\n\nDesign and create digital creatives for eCommerce websites\nAssist in adapting existing graphic to different languages and for different target markets\u00a0\n\n\u00a0Job Requirements:\u00a0\n\nFormal training in design (Diploma holder in graphic design) with solid understanding on website marketing and Ecommerce websites\nExpert knowledge of Photoshop, Illustrator\nKnowledge in Premiere is preferred\nEffective time management\nWork well with the team\nStrong written English and communication skills\nImmediately availability preferred\nWork in office for 2-3 days per week\u00a0\n\nWe offered a fun and friendly team environment.\u00a0The right candidates or interested parties should\u00a0apply with samples of your past work (online portfolio or in PDF no more than 5MB), a CV, your current and expected salary and availability\u00a0by clicking \u201cApply Now\u201d for an interview.", "employment_types": ["Full Time", "Permanent"], "selling_points": [], "locations": ["Aberdeen"], "categories": ["Design", "Graphics", "Others"], "post_time": "2022-01-17T02:37:33Z", "salary": {"currency": null, "max": null, "min": null, "period": "monthly", "term": null}, "salary_visible": false, "title_keywords": ["designer"], "responsibilities": ["design"], "requirements": {"degrees": ["diploma holder"], "majors": ["ecommerce", "graphic design", "marketing", "design"], "languages": ["english"], "language_level": [], "hard_skills": ["illustrator", "premiere", "photoshop"], "soft_skills": ["communication skills", "time management"], "languages_combined": [{"language": "english", "language_level": []}]}, "experience_required": {"duration": [], "field": []}}, {"job_id": "100003009054212", "location_code": "hk", "company": "Sedgwick Richardson (Hong Kong) Ltd", "job_title": "Designer (Publishing)", "description": "Responsibilities:\n\nGenerate design concept, structural design, environment design & space planning for events & exhibitions\nHandle 3D rendering projects, technical drawing and floor plan for production\nComplete 3D design drawing in full set for events and exhibitions, photo retouch technique is required.\nRequirements:\n\nDegree / Diploma or above in related courses (space design/ exhibition design/ multimedia design. etc)\nGood at handling 2D and 3D software (e.g. 3Ds Max, Cine 4D, Illustrator, Photoshop)\nHands-on experience in working on 3D, graphic, artwork, and output production independently is essential\n2 years\u2019 experience or above in exhibition/event design/production house/interior decoration will be an advantage\nImmediately is preferable\n\n\u00a0Office location: Yau Tong\n\nInterested parties please send your detailed resume and expected salary to\u00a0us.\n(All personal data collected will be used for recruitment purpose only)\u00a0", "employment_types": ["Full Time"], "selling_points": [], "locations": ["Central"], "categories": ["Design", "Graphics", "Multi-media", "Web Designer"], "post_time": "2022-01-17T08:49:51Z", "salary": {"currency": null, "max": null, "min": null, "period": "monthly", "term": null}, "salary_visible": false, "title_keywords": ["designer"], "responsibilities": ["3d rendering", "design concept", "design", "photo retouch", "planning", "plan", "technical drawing"], "requirements": {"degrees": ["degree", "diploma or above"], "majors": ["multimedia design", "design"], "languages": [], "language_level": [], "hard_skills": ["3d software", "3ds max", "illustrator", "multimedia", "photoshop"], "soft_skills": ["hands-on", "independently"], "languages_combined": []}, "experience_required": {"duration": ["2 years"], "field": ["graphic", "design"]}}, {"job_id": "100003009053039", "location_code": "hk", "company": "Tech Nine Limited", "job_title": "Graphic Designer (Mobile App/Web) (5 days work)", "description": "Responsibilities:\nResponsible for in-house design projects from concept creative to final production independently\nLiaise and coordinate with suppliers / production house to ensure all promotional materials are produced up to company standard\nProvide graphic design for promotion materials, such as advertisement, POP and visual merchandise from conception to production\nAd hoc assignments as per management\u2019s request\nRequirements:\nDiploma\u00a0or above in graphic design or related disciplines\nMinimum\u00a03\u00a0years relevant working experience, preferably in F&B industries\nProficient in Photoshop, Illustrator, InDesign, and other design software\nExperience in photography, video editing and filming is an advantage\nSelf-motivated, independent, creative\nAble to work under pressure and perform multi-tasks with tight timescales\u00a0\nDetailed minded, well organized and good communication skills\nGood command of both spoken and written English and Chinese\nPortfolio is required for interview reference\nApplicant with less experience would be considered as Junior Graphics Designer\n\n\n\nWe offer attractive remuneration package and excellent career opportunities to the right candidate. Interested parties,\u00a0please click on below button \u201cApply Now\u201d.\n\nInformation collected will be treated in strict confidence and used for recruitment purposes only.\u00a0 Only suitable candidates will be notified.", "employment_types": ["Full Time", "Permanent"], "selling_points": ["Looking for passionate and talented designer", "Website, Mobile Application, Marketing Collateral", "Friendly and energetic working environment"], "locations": ["Lai Chi Kok"], "categories": ["Design", "Graphics", "Multi-media", "Information Technology (IT)", "UI/UX Designer"], "post_time": "2022-01-17T16:20:58Z", "salary": {"currency": null, "max": null, "min": null, "period": "monthly", "term": null}, "salary_visible": false, "title_keywords": ["graphic designer"], "responsibilities": ["liaise", "management", "graphic design", "coordinate with", "design", "promotional materials", "ad hoc assignments", "visual"], "requirements": {"degrees": ["diploma or above"], "majors": ["related disciplines", "graphic design"], "languages": ["english", "chinese"], "language_level": ["good command"], "hard_skills": ["graphics", "indesign", "illustrator", "video editing", "photoshop"], "soft_skills": ["communication skills", "self-motivated", "independent", "multi-tasks", "well organized", "detailed", "creative", "work under pressure"], "languages_combined": [{"language": "english", "language_level": ["good command"]}, {"language": "chinese", "language_level": ["good command"]}]}, "experience_required": {"duration": ["minimum 3 years"], "field": ["video", "designer", "relevant working experience", "f&b", "editing"]}}, {"job_id": "100003009054870", "location_code": "hk", "company": "Nu Skin Enterprises Hong Kong, LLC", "job_title": "Designer (Web and Graphic Design)", "description": "ABOUT SEDGWICK RICHARDSON\n\nWe\u2019re a regional team of strategists, designers and sustainability specialists who are passionate about building brands that have a positive impact on our world. We are a new kind of company that is changing how brands are created. We fuse sustainability principles into brand building to create relevant brands that thrive.\n\nTogether, we Build Belief in the Future.\n\nAbout You\n\nYou work in a \u2018concept first\u2019 mode and think holistically about brands and publications. You understand that today they need to be designed to live across multiple channels and formats, and that this often means taking a digital first approach.\n\nYou want to work with a team truly committed to improving the world we live in. You want to learn about how sustainability thinking applies to brand design.\n\n\n\nYour responsibilities\n\nGenerate brilliant creative concepts and fresh ideas\nExtraordinary aesthetic sense and taste\nHighly sensitive to typography, imagery, layout hierarchy\nPay attention to the quality and every detail of design execution\nConsult internally with Creative Director and the Account Management team to agree on the theme, creative direction, other design parameters\nSupport in the creation of presentations and marketing content & materials\nDeliver design solutions within specified, approved schedules and resources\nSee designs through to final artwork and delivery\nManage the printing process for publications\n\nYour skills\n\nYou\u2019re able to articulate and visualise your ideas and concepts clearly\nFluency in spoken and written English required, Cantonese and Mandarin a big plus.\nYou\u2019ll have 3+ years of experience in publication design\nYou have intimate working knowledge of Adobe Photoshop, Illustrator, InDesign.\nYou\u2019re self-motivated, organised, accountable and thrive in a multi-cultural environment\nYour attitude is respectful, collaborative and positive\nYou are passionate about typography and understand typographic hierarchy\nYou have experience in data visualisation and information design\nYou can demonstrate an understanding of pagination planning\nYou have rigorous file management skills\n\nPlease send us a short email with your r\u00e9sum\u00e9 (and a link to your online portfolio) explaining why you are interested to join our team. This must include previous and expected salary.", "employment_types": ["Full Time", "Permanent"], "selling_points": ["Support design tasks and projects", "Produce creative media online campaigns", "Knowledge in Adobe Creative Suite"], "locations": ["Causeway Bay"], "categories": ["Design", "Graphics", "Multi-media", "Web Designer"], "post_time": "2022-01-17T12:14:08Z", "salary": {"currency": null, "max": null, "min": null, "period": "monthly", "term": null}, "salary_visible": false, "title_keywords": ["designer"], "responsibilities": ["management team", "ideas", "design solutions", "schedules", "data", "quality", "presentations", "design", "file management", "publication", "planning"], "requirements": {"degrees": [], "majors": [], "languages": ["cantonese", "english", "mandarin"], "language_level": ["fluency"], "hard_skills": ["plus", "indesign", "adobe photoshop", "illustrator", "presentations"], "soft_skills": ["self-motivated", "passionate about", "accountable", "collaborative", "committed", "sensitive to", "organised", "articulate", "creative", "positive", "respectful"], "languages_combined": [{"language": "cantonese", "language_level": ["fluency"]}, {"language": "english", "language_level": ["fluency"]}, {"language": "mandarin", "language_level": ["fluency"]}]}, "experience_required": {"duration": ["3+ years"], "field": ["design"]}}, {"job_id": "100003009052667", "location_code": "hk", "company": "Love Design Production Limited", "job_title": "Graphic Designer (16K-18K depends on experience)", "description": "You should keep watching...\n\nIf you are interested in the website and mobile app graphic design, enjoying a flexible culture and would like to join an energetic team, which is led and supervised by IT experts and to work with Millennial professionals, this is exactly what you are looking for!\nYou'll responsible for...\n\nHandle design project, including mobile and web application graphics, icons and\u00a0 UI elements\nWork independently to develop and produce artwork for mobile application, desktop application & website\nBrainstorm innovative ideas and prepare proposal/presentation materials\nWork with design managers to ensure timely completion and quality of design elements\nClosely communicate with the project team and product team to ensure final graphics and layouts aligns with project requirements\nSupport projects' task assigned by Manager & Director\nRight fit if you are...\n\nDiploma or above in Graphic Design or related disciplines\n3 year or above working experience in Graphic Design\nProficiency in using Photoshop & Illustrator, Figma and Sketch\nExperience in Website/ Mobile App graphic design is a plus\nWith strong creative and design sense\nAble to work independently, willing to meet new challenges under a tight schedule\nImmediately available is highly preferred\nWe offer...\n\nProject Bonus\n5-days Work + Bank Holiday\nEducation Allowance, Medical Allowance\nSnacks and drinks\nLess than 5 mins walk from Lai Chi Kok MTR Station\nGood Career Prospect in the growing IT Industry\n\nApply now! Do not miss this opportunity to join us!\n\nInterested parties, please apply with full resume, portfolio that will demonstrate our required fields as mentioned above, current and expected salary.\n\nRemarks: Data collected would be used for recruitment purposes only. Applicants who do not hear from us within 8 weeks may consider their application unsuccessful and their data will be destroyed within 24 months of receipt.", "employment_types": ["Full Time"], "selling_points": [], "locations": ["Shatin Area"], "categories": ["Design", "Graphics", "Multi-media", "Web Designer"], "post_time": "2022-01-17T03:40:45Z", "salary": {"currency": null, "max": null, "min": null, "period": "monthly", "term": null}, "salary_visible": false, "title_keywords": ["graphic designer"], "responsibilities": ["graphics", "communicate with", "project requirements", "support projects", "mobile app", "ideas", "graphic design", "quality", "website", "design", "develop", "schedule", "ui"], "requirements": {"degrees": ["diploma or above"], "majors": ["related disciplines", "graphic design"], "languages": [], "language_level": [], "hard_skills": ["graphics", "plus", "web", "illustrator", "mobile", "photoshop"], "soft_skills": ["flexible", "work independently", "creative", "responsible", "timely", "interested in", "innovative", "energetic", "presentation"], "languages_combined": []}, "experience_required": {"duration": ["3 year"], "field": ["graphic design"]}}, {"job_id": "100003009054879", "location_code": "hk", "company": "Orienta Lab Limited", "job_title": "Graphic Designer", "description": "Business Sector:\u00a0\u00a0Crypto Art & NFT\u00a0\n\n\nLooking for .....\n\nFull-time/Part-time :\u00a0 \u00a0 \u00a0Graphic Designer\n\nJob Description:\n\nWe\u2019re looking for a creative and enthusiastic Graphic Designer to help us with all kinds of materials designing work.\n\nIn this role, you will be responsible for the design of various types of digital artworks, posters and other project propaganda visual materials. You will participate in brand crossover, promote the project, do the time and cost control and risk management. Work closely with the company's brand to efficiently implement the creative ideas and designs of the projects and planning requirements.\n\nThe role requires a passion for our mission and an eagerness to roll up your sleeves. Besides, it involves the creativity of activity planning, certain understanding of crypto art and popular culture.\n\nRequirements:\nMust have:\n\n1\u3001Major in visual art related fields or rich experience in visual design;\n\n2\u3001Love design, rich imagination, and keen on current design trends.\n\n3\u3001Have certain design ability and good visual aesthetics, and can skillfully use PS, AI and other design software;\n\n4\u3001Familiar with digital art, good marketing and brand building ability, cost control and management awareness, and unique understanding of brand marketing.\n\n5\u3001Strong learning ability, innovation ability, teamwork ability and pressure resistance.\n\n6\u3001Good communication skills, punctual, detailed-minded, hardworking and responsible\u00a0\n\nPlease attach your portfolio when submitting your resume.\n\nNice to have:\nExtra:\n\n-Design experience in other NFT projects\n-Familiarity with nowdays NFTs\n\n-Outstanding performance in one or more abilities such as illustration, animation ,etc. are preferred\n\n________________________________________________________________________\n\u00a0Salary:\u00a0Negotiable\n\nWatsapp: 63671819 / 56912649\nWechat: TYJBRIAN /\u00a054302895\n\nCompany address: 10/F Infotech Centre, 21 Hung To Road, Kwun Tong, HK", "employment_types": ["Full Time", "Part Time", "Permanent", "Temporary", "Contract", "Internship", "Freelance"], "selling_points": ["Creative contents and marketing purpose", "After effects, Illustrator, Premier Pro, Photoshop", "Experience in sci-fi, anime, fantasy"], "locations": ["Ngau Tau Kok"], "categories": ["Design", "Fashion", "Graphics", "Multi-media"], "post_time": "2022-01-17T16:21:10Z", "salary": {"currency": null, "max": null, "min": null, "period": "monthly", "term": null}, "salary_visible": false, "title_keywords": ["graphic designer"], "responsibilities": ["management", "creative ideas", "designing", "design", "cost control", "visual", "planning"], "requirements": {"degrees": [], "majors": [], "languages": [], "language_level": [], "hard_skills": ["ai", "nice", "wechat", "visual design", "illustration"], "soft_skills": ["communication skills", "learning ability", "responsible", "keen", "teamwork", "unique", "hardworking", "detailed"], "languages_combined": []}, "experience_required": {"duration": [], "field": ["related", "design"]}}, {"job_id": "100003009055560", "location_code": "hk", "company": "\u82b1\u4e4b\u6ef4\u6709\u9650\u516c\u53f8", "job_title": "\u5e73\u9762\u8a2d\u8a08\u5e2b Graphic Designer", "description": "JOB DESCRIPTION\n\nResponsible for product creative design from concept to final artwork\nPrepare engaging content such as graphics, photos, imagery and video to drive traffic conversion and brand awareness\nPerform daily management of social media accounts and media planning.\nTo perform other duties assigned by management\n\nQUALIFICATIONS\n\nDegree holder of Graphic Design, Visual Communication, Marketing, Communications, e-Commerce etc.\nSolid knowledge with one (or more) of these creative and digital tools is a MUST: Photoshop / Illustrator / InDesign /Final Cut Pro/ video editing skills\nGood writing skill in editorial & marketing materials with media angle\nGood sense of social media platforms and passionate to initiate digital creative ideas\nProactive and energetic team player with self-motivation, creativity and positive working attitude\nAbility to achieve results and willing to contribute beyond basic responsibilities\nExcellent communications in English and Chinese\n\nWHY YOU SHOULD JOIN US\n\nWe provide constant guidance, training and mentorship to polish your business mindset. We care about your personal and professional growth\nFlat operating structure, you will be able to work independently, make your own judgement and make a direct impact to the company\nWe work in an open, collaborative, and respectful culture where we empower every single person to grow and play to their strengths\nFlexible work hours. Our priority is on getting the job done\nYou\u2019ll be working in a fast-paced environment\n\nPlease send your CV together with the expected salary to us.\nShortlisted candidates will be invited to a first round interview and notified by email or phone.", "employment_types": ["Full Time", "Permanent"], "selling_points": [], "locations": ["Chai Wan"], "categories": ["Design", "Graphics", "Industrial / Product", "Multi-media"], "post_time": "2022-01-18T02:43:23Z", "salary": {"currency": "HKD", "max": 19999, "min": 14000, "period": "monthly", "term": null}, "salary_visible": true, "title_keywords": ["graphic designer"], "responsibilities": ["graphics", "social media", "management", "perform other duties", "creative ideas", "graphic design", "social media platforms", "design", "communication", "video editing", "visual", "marketing materials", "planning"], "requirements": {"degrees": ["degree holder"], "majors": ["graphic design", "marketing", "communications", "e-commerce"], "languages": ["english", "chinese"], "language_level": ["excellent"], "hard_skills": ["creative design", "graphics", "final cut pro", "basic", "e-commerce", "indesign", "illustrator", "writing skill", "video editing", "visual communication", "photoshop"], "soft_skills": ["passionate", "proactive", "responsible", "writing skill", "communication", "positive working attitude", "energetic", "self-motivation", "team player", "creative"], "languages_combined": [{"language": "english", "language_level": ["excellent"]}, {"language": "chinese", "language_level": ["excellent"]}]}, "experience_required": {"duration": [], "field": []}}, {"job_id": "100003009055556", "location_code": "hk", "company": "Matter Interiors Limited", "job_title": "GRAPHIC DESIGNER", "description": "Requirements:\n\nDiploma or above in relevant disciplines;\nAt least 3 years relevant experience in arts and design fields;\nProficient in Photoshop, Illustrator and other related design software with good output knowledge;\nHandle graphics design and production for advertising, social media content and other marketing collateral;\nStrong in graphic sense, creative and conceptual skills;\nGood command of written & spoken English and Mandarin;\nSelf-motivated & Independent;\nGood interpersonal skills and willing to learn;\nBasic knowledge in Interior Design would be a plus;\n\nWe offer competitive package and promising career prospect to the right candidate.\nInterested parties please send detailed resume, portfolio and expected salary quoting the corresponding position by clicking \u201cApply Now\u201d.", "employment_types": ["Full Time", "Permanent"], "selling_points": [], "locations": ["Tsim Sha Tsui"], "categories": ["Design", "Graphics"], "post_time": "2022-01-18T02:43:24Z", "salary": {"currency": null, "max": null, "min": null, "period": "monthly", "term": null}, "salary_visible": false, "title_keywords": ["graphic designer"], "responsibilities": ["graphics", "advertising", "software", "design", "social media content"], "requirements": {"degrees": ["diploma or above"], "majors": [], "languages": ["english", "mandarin"], "language_level": ["good command"], "hard_skills": ["graphics", "plus", "basic", "illustrator", "photoshop"], "soft_skills": ["self-motivated", "independent", "willing to learn", "interpersonal skills", "creative"], "languages_combined": [{"language": "english", "language_level": ["good command"]}, {"language": "mandarin", "language_level": ["good command"]}]}, "experience_required": {"duration": ["at least 3 years"], "field": ["relevant experience", "design"]}}, {"job_id": "100003009054404", "location_code": "hk", "company": "KREW LIMITED", "job_title": "Associate Creative Director (Art-Based) / Assistant Digital Creative Director", "description": "Company Background\n\nKREW Digital\u00a0is the\u00a0No.1\u00a0Social Media Agency and Content Marketing Agency recognized by Marketing Magazine*. We won the\u00a0Agency of the Year 2021 (6 Gold, 6 Local Hero, 3 Bronze).\u00a0KREW is a fast-growing digital agency, mainly focusing on social media, digital campaigns and content marketing. Our team is formed by veterans of first-tier digital agencies, consultancies and the mass media. Our client list includes some of the most respected and admired names in Hong Kong and worldwide, including leading property developer, hospitality group, luxury retailer and world-class travelware brand.\n\nWith self-developed tool \"KREWatch\", its analytic approach help craft persona insight for our creative ideas, it's the core reason for us to win Marketing Excellence Awards in Categories of Retail Marketing and Loyalty Marketing.\u00a0\n\nTo cope with our expansion, we would like to invite high-calibre talents to join our energetic team for an exciting career in digital marketing.\n\nThe ideal candidate will formulate online / digital / social media / content marketing strategies for our clients by planning and executing digital marketing campaigns. Candidate will also plan and launch digital advertisements and create content. He / she will also be able to monitor clients\u2019 social media presences.\n\n*KREW is the Gold Winner of Social Media Agency of the Year 2021 and Content Marketing Agency of the Year 2021 organized by Marketing Magazine.\u00a0\n\nFollow Us\u00a0\n\n\u25baW:\u00a0https://www.krewdigital.com/\u00a0\n\u25baF:\u00a0https://www.facebook.com/krewdigital/\n\u25baL:\u00a0https://www.linkedin.com/company/krewdigital/\n\n\nRequirements\n\nDirectly report to Directors to lead creative team for digital and social media strategy.\nIn charge of overseeing digital creative direction and quality control of all projects.\u00a0\nWork closely with account servicing and creative to in charge of proposals and ad hoc projects.\nVeteran in digital and social media advertising and creative industry.\u00a0\nCraft ideas with award-winning approach.\u00a0\n\nQualifications\n\nDiploma holder or above in Graphic / Multimedia Design\n3 to 5 year Digital Agency background in well-known 4As/web/multi-media/interactive fields is a plus\nPresentable and good command of Cantonese and English\nProficiency in HTML, AI, AE, PS, PR\nExperience on handling Finance, Banking, Insurance, Shopping Malls is a plus\nCreative, Can-Do attitude, Proactive, independent and a good team leader and player\nCapable in manage multiple projects to meet tight deadlines\nStrong Sense of belongings to the projects of client and team\n\nInterested parties please send CV to us!", "employment_types": ["Full Time"], "selling_points": ["3 - 5 year ex. 4As agency background is a plus", "Creative. Digital marketing & social media veteran", "Stunning agency office environment"], "locations": ["Tsuen Wan Area"], "categories": ["Media & Advertising", "Creative / Design", "Design", "Graphics", "Multi-media"], "post_time": "2022-01-17T09:23:31Z", "salary": {"currency": null, "max": null, "min": null, "period": "monthly", "term": null}, "salary_visible": false, "title_keywords": ["creative director", "associate", "assistant"], "responsibilities": ["multimedia design", "ideas", "plan", "facebook", "advertising", "digital marketing campaigns", "monitor", "manage multiple projects", "digital campaigns", "banking", "report", "social media", "marketing strategies", "digital marketing", "executing", "creative ideas", "advertisements", "ad hoc projects", "quality control", "insurance", "planning"], "requirements": {"degrees": ["diploma holder"], "majors": ["multimedia design"], "languages": ["cantonese", "english"], "language_level": ["good command"], "hard_skills": ["no", "plus", "web", "ai", "html", "reason", "multimedia", "facebook"], "soft_skills": ["organized", "meet tight deadlines", "proactive", "independent", "creative", "capable", "can-do attitude", "world-class", "presentable", "good team leader", "energetic", "ideal"], "languages_combined": [{"language": "cantonese", "language_level": ["good command"]}, {"language": "english", "language_level": ["good command"]}]}, "experience_required": {"duration": [], "field": ["finance", "insurance", "banking"]}}, {"job_id": "100003009051843", "location_code": "hk", "company": "Stylevana", "job_title": "Part-time Digital and Graphic Designer", "description": "Job Duties:\u00a0\n\nDesign and create digital creatives for eCommerce websites\nAssist in adapting existing graphic to different languages and for different target markets\u00a0\n\n\u00a0Job Requirements:\u00a0\n\nFormal training in design (Diploma holder in graphic design) with solid understanding on website marketing and Ecommerce websites\nExpert knowledge of Photoshop, Illustrator\nKnowledge in Premiere is preferred\nEffective time management\nWork well with the team\nStrong written English and communication skills\nImmediately availability preferred\nWork in office for 2-3 days per week\u00a0\n\nWe offered a fun and friendly team environment.\u00a0The right candidates or interested parties should\u00a0apply with samples of your past work (online portfolio or in PDF no more than 5MB), a CV, your current and expected salary and availability\u00a0by clicking \u201cApply Now\u201d for an interview.", "employment_types": ["Part Time"], "selling_points": ["Design & create online content for eCom", "knowledge of Photoshop, Illustrator & Premiere", "Work in office for 2-3 days per week"], "locations": ["Kwai Hing"], "categories": ["Design", "Graphics", "Web Designer", "E-commerce", "Others"], "post_time": "2022-01-17T01:20:54Z", "salary": {"currency": null, "max": null, "min": null, "period": "hourly", "term": null}, "salary_visible": false, "title_keywords": ["digital and graphic designer"], "responsibilities": ["design"], "requirements": {"degrees": ["diploma holder"], "majors": ["ecommerce", "graphic design", "marketing", "design"], "languages": ["english"], "language_level": [], "hard_skills": ["illustrator", "premiere", "photoshop"], "soft_skills": ["communication skills", "time management"], "languages_combined": [{"language": "english", "language_level": []}]}, "experience_required": {"duration": [], "field": []}}, {"job_id": "100003009054619", "location_code": "hk", "company": "K11 Concepts Limited", "job_title": "Multimedia/ Graphic/3D Designer", "description": "Responsibility:\n\nEffectively help on the design tasks and projects to meet deadlines\nMaintain and update web content by using Adobe Experience Manager\nProducing rich and creative media online campaigns include eDM, web banners, etc.\n\nRequirement:\n\n2-year experience in graphic design, with passion in graphic design and creating user-friendly web interfaces\nKnowledge in Adobe Creative Suite. E.g. Adobe Creative Suite, e.g. Photoshop, illustrator, Dreamweaver, etc\nKnowledge in HTML and CSS is a must.\nExcellent communication skills and attention to detail\n\n\nWe offer 5 days work, excellent career development with on/off-the-job trainings, competitive compensation including incentive bonus & annual performance bonus, medical benefits, life & accidental insurance, annual leave & product benefits.\n\nIf you are ready for a new challenge in your career, please send your detailed resume with\u00a0Current and Expected Salary and Your Availability\u00a0by clicking Apply Now.\n\n\n\nALL PERSONAL INFORMATION WE COLLECTED IS FOR THE PURPOSE OF RECRUITMENT ONLY\n\n\n\nPlease visit\u00a0www.nuskin.com\u00a0to find out more about us!", "employment_types": ["Full Time", "Permanent"], "selling_points": ["Support K11 campaigns and creative initiatives", "After effects, Illustrator, Premier Pro, Photoshop", "Experience in Luxury, Art, Fashion or Retail"], "locations": ["Tsim Sha Tsui"], "categories": ["Design", "Graphics", "Multi-media"], "post_time": "2022-01-17T10:15:43Z", "salary": {"currency": null, "max": null, "min": null, "period": "monthly", "term": null}, "salary_visible": false, "title_keywords": ["designer"], "responsibilities": ["banners", "maintain", "design", "edm"], "requirements": {"degrees": [], "majors": [], "languages": [], "language_level": [], "hard_skills": ["web", "illustrator", "html", "dreamweaver", "css", "adobe creative suite", "photoshop"], "soft_skills": ["communication skills", "passion in", "friendly", "attention to detail", "creative", "detailed"], "languages_combined": []}, "experience_required": {"duration": ["2-year"], "field": ["graphic design"]}}, {"job_id": "100003009052672", "location_code": "hk", "company": "Refuel Digital Marketing Limited", "job_title": "Web & Graphic Designer [Salary range: 20K -25K (depends on exp.) ]", "description": "(Only\u00a0those candidates who submit a\u00a0portfolio / assessible link(s) will be\u00a0considered)\n\nResponsibilities\n\nResponsible for conceptualisation and implementation of design solutions that meet marketing strategies from concept, creative design to artwork production\nEnsure that all creative is in line with brand character and reinforce brand domination.\nCo-work with different departments on mall marketing events and campaigns\nStay up to date on latest creative trends, transmedia applications and competitive business environment\n\nRequirements\n\nDiploma/ Degree holder in Graphic Design or in a related field from a recognized institution\nMinimum 3 years solid working experience in graphic design and artwork production\nExperience in Luxury, Art, Fashion or Retail Industry is an advantage\nStrong layout and typography skill is essential\nHigh level of proficiency in design software and applications, such as Adobe Creative Suite\nExperience with print design, sound knowledge of print procedures,\u00a0animation and video production.\nAbility to pay attention to detail and grasp project needs and consider practical solutions\nAbility to imbibe good time management and balance work on multiple projects simultaneously\nGood command of written and spoken English and Chinese, Mandarin is an advantage\n\n\u00a0Personal Attributes\n\nAn entrepreneur who is able to think out of the box\nA team player and a relationship builder\nable to work independently and handle multiple projects\nWell motivated, organized, and good interpersonal skill\nInquisitive and able to work a fast-paced and dynamic working environment\nProactive and with good problem solving skills\nPassion for creating outstanding quality of original works and openness to innovative ways of doing things", "employment_types": ["Full Time"], "selling_points": [], "locations": ["Shatin Area"], "categories": ["Design", "Graphics", "Multi-media", "Web Designer"], "post_time": "2022-01-17T03:41:00Z", "salary": {"currency": null, "max": null, "min": null, "period": "monthly", "term": null}, "salary_visible": false, "title_keywords": ["graphic designer"], "responsibilities": ["marketing events", "marketing strategies", "design solutions", "artwork production", "implementation", "design"], "requirements": {"degrees": ["diploma", "degree holder"], "majors": ["graphic design"], "languages": ["english", "chinese", "mandarin"], "language_level": ["advantage", "good command"], "hard_skills": ["problem solving skills", "dynamic", "adobe creative suite"], "soft_skills": ["organized", "work independently", "proactive", "creative", "passion for", "interpersonal skill", "innovative", "problem solving skills", "motivated", "dynamic", "attention to detail", "team player", "time management"], "languages_combined": [{"language": "english", "language_level": ["advantage", "good command"]}, {"language": "chinese", "language_level": ["advantage", "good command"]}, {"language": "mandarin", "language_level": ["advantage", "good command"]}]}, "experience_required": {"duration": ["minimum 3 years"], "field": ["retail industry", "video production", "graphic design", "print", "design"]}}, {"job_id": "100003009050803", "location_code": "hk", "company": "iDance International Limited", "job_title": "Graphic Designer", "description": "The Role\nWe are looking for a creative and passionate Graphic Designer to join our team.\u00a0\u00a0You will have a chance to work at a fast-paced mission driven company that brings material science to life and benefit the mass.\u00a0 We are bringing business disruption and new hygiene standard to the world with the introduction of new photocatalyst products and services. With the continuous R&D and business innovation, we are thrilled to develop the next generation technology that safeguards everyday life.\u00a0 Raze Technology is the world's leading photocatalyst solution company, developing a long-lasting disinfectant coating.\n\nResponsibilities\nResponsible for creative concept development and handle all stages of design include but not limited to the following:\u00a0\n\n\nSocial media visual and feed designs (Facebook, Instagram, eDM, Google ad, etc.);\u00a0\nOnline store visual (Web banner, product page, etc);\u00a0\nSales kit and POP materials;\nProduct retouching and mock-ups;\u00a0\nPerform ad-hoc projects as assigned.\n\nRequirements\n\n\nDiploma or above in Graphic Design/ Multimedia/ Creative Media or other related disciplines;\nAt least 3 years relevant working experience in graphic design, FMCG or digital marketing agency experience is preferred;\nProficient in using Adobe Illustrator, Photoshop in Mac environment;\u00a0\nProficient in animation and video editing is a plus;\nGood team player, multi-tasking and responsible;\nVisual merchandising experience is an advantage;\u00a0\nImmediate availability is highly preferable.\n\nWe offer the right candidate attractive remuneration package and outstanding prospects for career advancement and development.\u00a0 The right candidate will progress career in a forward thinking and dynamic business with exciting growth plans.\u00a0 If you are qualified and interested, please send your full resume with current & expected salary and availability by clicking \"APPLY\".\n\nAll information collected will be treated as strictly confidential and used for recruitment purposes only. (Only shortlisted candidates will be notified)", "employment_types": ["Full Time", "Permanent"], "selling_points": [], "locations": ["Ngau Tau Kok"], "categories": ["Design", "Graphics", "Others", "Manufacturing", "Others"], "post_time": "2022-01-14T11:26:04Z", "salary": {"currency": null, "max": null, "min": null, "period": "monthly", "term": null}, "salary_visible": false, "title_keywords": ["graphic designer"], "responsibilities": ["pop materials", "edm", "product retouching", "mock-ups", "social media visual and feed designs", "design", "visual", "facebook", "ad-hoc projects", "sales kit"], "requirements": {"degrees": ["diploma or above"], "majors": ["related disciplines", "graphic design", "creative media"], "languages": [], "language_level": [], "hard_skills": ["plus", "mac environment", "visual merchandising", "adobe illustrator", "multimedia", "animation and video editing", "photoshop"], "soft_skills": ["good team player", "creative", "multi-tasking", "responsible"], "languages_combined": []}, "experience_required": {"duration": ["at least 3 years"], "field": ["fmcg", "agency", "graphic design", "merchandising", "relevant working experience", "digital marketing"]}}, {"job_id": "100003009046465", "location_code": "hk", "company": "TLB Hong Kong Limited", "job_title": "Junior Graphic Designer (Full-time / Part-time)", "description": "Job Description\nResponsible for the creation, design, development, and maintenance of the corporate websites of individual businesses.\nCreate graphic and animated design for our website, social media, and branding assets for marketing campaigns\nApply best practices to increase page speed & ratings, and SEO ranking\nRequirement\n\nDiploma holder or above in web, graphic design, or related field\nAt least 2 years of relevant working experience\nKnowledge in\u00a0SEO, CSS, HTML5, Java\u00a0and WordPress\nKnowledge in Adobe Photoshop, Fireworks, Illustrator, Flash, Dreamweaver\nExperience in video shooting and production is an advantage\nStrong sense of responsibility, a good team player while being able to work independently to meet project deadlines\nGood communication skills\nGood command of written and spoken Chinese, Mandarin & English\nPortfolio attachment is a MUST\nImmediate availability is highly preferred\nCandidate with more experiences would also be considered as Senior Web & Graphic Designer\n\nBenefit\n\nMedical insurance\nDental\u00a0insurance\nDiscretionary bonus\nAttractive performance bonus\nFriendly and collaborative work environment\n\nWe offer competitive remuneration package and good prospects to the right candidates.\n\n*For more details, please visit our official website:\u00a0https://refueldigital.com.hk/\n\n*Interested parties please send your full resume with expected salary by clicking \u201cApply now\u201d\n\n*The information provided by applicants will be kept confidential and will be\u00a0used solely for recruitment purpose only.\u00a0All the applications will be destroyed after 6-month.", "employment_types": ["Full Time", "Part Time", "Contract", "Internship"], "selling_points": ["Graphic Designer", "Fresh graduate", "Design career in beauty and cosmetics industry"], "locations": ["Kwai Hing"], "categories": ["Media & Advertising", "Creative / Design", "Design", "Graphics", "Industrial / Product"], "post_time": "2022-01-15T03:27:47Z", "salary": {"currency": null, "max": null, "min": null, "period": "monthly", "term": null}, "salary_visible": false, "title_keywords": ["junior graphic designer"], "responsibilities": ["social media", "seo", "maintenance", "website", "design", "marketing campaigns"], "requirements": {"degrees": ["diploma holder"], "majors": ["graphic design"], "languages": ["english", "chinese", "mandarin"], "language_level": ["good command"], "hard_skills": ["java", "seo", "web", "adobe photoshop", "illustrator", "wordpress", "flash", "dreamweaver", "css"], "soft_skills": ["communication skills", "good team player", "work independently", "sense of responsibility"], "languages_combined": [{"language": "english", "language_level": ["good command"]}, {"language": "chinese", "language_level": ["good command"]}, {"language": "mandarin", "language_level": ["good command"]}]}, "experience_required": {"duration": ["at least 2 years"], "field": ["graphic", "video shooting", "designer", "relevant working experience"]}}, {"job_id": "100003009046376", "location_code": "hk", "company": "Tomoe Electronics Ltd", "job_title": "GRAPHIC DESIGNER", "description": "Responsibilities:\n\nDesign original graphics with unique colours, shapes and typography fonts\nMake rendering from our 3D file\nWork closely with internal teams and suppliers to deliver printing matters\nComplete routine and special tasks as assigned by superiors\nDesktop publishing for making user manual\n\nRequirements:\n\nDiploma or above in Graphic Design or related disciplines\n3 - 5 years of solid experience in silkscreen artwork, printing artwork, desktop publishing, product photo shooting and 3D rendering design\nHigh proficiency in AI, Photoshop, In-Design and 3D Rendering Design\nGood knowledge of product photo retouching, packaging artwork and printing\nCreative, self-motivated and enjoy working in a fast-paced environment and able to work independently.\nImmediate available preferred", "employment_types": ["Full Time"], "selling_points": ["Prefer immediate available, near Kwun Tong MTR", "Good at AI/Photoshop/In-Design/3D Rendering Design", "3-5 years of solid Graphic Designer experience"], "locations": ["Kwun Tong"], "categories": ["Design", "Graphics"], "post_time": "2022-01-13T10:49:08Z", "salary": {"currency": null, "max": null, "min": null, "period": "monthly", "term": null}, "salary_visible": false, "title_keywords": ["graphic designer"], "responsibilities": ["graphics", "teams", "desktop publishing", "design"], "requirements": {"degrees": ["diploma or above"], "majors": ["related disciplines", "graphic design"], "languages": [], "language_level": [], "hard_skills": ["in-design", "photoshop", "ai"], "soft_skills": ["self-motivated", "work independently", "fast-paced environment", "enjoy working", "creative"], "languages_combined": []}, "experience_required": {"duration": ["3 - 5 years"], "field": ["photo shooting", "publishing", "design"]}}, {"job_id": "100003008993846", "location_code": "hk", "company": "Tranthink Technology Service Limited", "job_title": "2D Graphic Assistant (UI)", "description": "We are a consumer electronics trading company which located at Kwun Tong area and we are now seeking for the following position to cope our company expansion.\n\nGRAPHIC DESIGNER\n\nResponsibilities:\n\u2022 Wide range of design jobs, such as Brand, Packaging, P.O.P. Advertising, Company Brochure and Promotion Materials\n\u2022 Assist marketing events and perform ad-hoc projects as assigned\n\nRequirements:\n\u2022 Diploma in Graphic Design or Related Discipline\n\u2022\u00a0Min. 3 years or above solid experience in Graphic Design background\n\u2022\u00a0Strong creative senses, well organized, mature, highly responsible and independent\n\u2022\u00a0Full PC and Macintosh skill is a must, proficient in Photoshop, Illustrator, InDesign, PowerPoint\n\u2022\u00a0Product photo shoot and photo retouch\n\u2022\u00a0Familiar with output and print production\n\u2022\u00a0Good command of Chinese and English\n\u2022 Immediately available is preferred\n\nInterested candidates, kindly send your detailed resume including Expected Salary.\n\n(All personal data will be collected for recruitment purposes only.)\u00a0", "employment_types": ["Full Time", "Permanent"], "selling_points": ["5 Days Work, Double Pay, Medical Insurance", "Flexible working hours, Free snack", "Immediately availability preferred"], "locations": ["Not Specified"], "categories": ["Design", "Graphics", "Others"], "post_time": "2022-01-16T21:50:01Z", "salary": {"currency": null, "max": null, "min": null, "period": "monthly", "term": null}, "salary_visible": false, "title_keywords": ["graphic assistant"], "responsibilities": ["marketing events", "ad-hoc projects", "advertising", "design"], "requirements": {"degrees": ["diploma"], "majors": ["graphic design"], "languages": ["english", "chinese"], "language_level": ["good command"], "hard_skills": ["indesign", "illustrator", "powerpoint", "pc", "photoshop"], "soft_skills": ["independent", "responsible", "well organized", "mature", "creative"], "languages_combined": [{"language": "english", "language_level": ["good command"]}, {"language": "chinese", "language_level": ["good command"]}]}, "experience_required": {"duration": ["3 years"], "field": ["graphic design"]}}, {"job_id": "100003009053511", "location_code": "hk", "company": "Bape Hong Kong Limited", "job_title": "Fashion Designer", "description": "Responsibilities\n\n\n\u00a0 Provide creative design and production supports\n\u00a0 Designing visuals for branding materials, online banners, packaging and other marketing materials, etc\n\u00a0 Handle ad hoc assignments as required\n\nRequirements\n\n\u00a0 Degree or diploma in design or related discipline\n\u00a0 Experience in Adobe AI and Photoshop\n\u00a0 Knowledge in photography and video editing will be advantage\n\u00a0 Self-motivated, creative and able to work independently\n\u00a0 Welcome students and fresh grad\n\u00a0 Immediate available would be in a high priority", "employment_types": ["Full Time"], "selling_points": ["3-4 years solid experience in fashion design", "Complete the whole process of the development", "Fresh graduate will also be considered"], "locations": ["Southern Area"], "categories": ["Design", "Fashion", "Graphics", "Others"], "post_time": "2022-01-17T07:04:31Z", "salary": {"currency": null, "max": null, "min": null, "period": "monthly", "term": null}, "salary_visible": false, "title_keywords": ["fashion designer"], "responsibilities": ["design", "banners", "ad hoc assignments", "designing", "marketing materials"], "requirements": {"degrees": ["diploma", "degree"], "majors": ["design"], "languages": [], "language_level": [], "hard_skills": ["video editing", "adobe", "photoshop", "ai"], "soft_skills": ["self-motivated", "creative", "work independently"], "languages_combined": []}, "experience_required": {"duration": [], "field": []}}, {"job_id": "100003009047542", "location_code": "hk", "company": "Society Of Genesis Limited", "job_title": "\u5e73\u9762\u8a2d\u8a08\u54e1Graphic Designer", "description": "Job Description:\nEager to learn new things, and have a strong appetite for iterating, measuring and learning quickly.\nCreate layout and UI assets.\nExcellent communication skills and a positive attitude are essential.\nImmediately availability preferred\nAttention to details\nJob Requirements:\nExperience in the graphic programme, eg. Adobe Illustrator, Photoshop\nWork independently and self-motivation\nExperience in Adobe XD in advantage\nPlease click \"Apply Now\" to submit your application.\nPersonal data collected will be used for recruitment purpose only.", "employment_types": ["Full Time"], "selling_points": [], "locations": ["North Point"], "categories": ["Design", "Graphics"], "post_time": "2022-01-14T03:25:09Z", "salary": {"currency": "HKD", "max": 13999, "min": 11000, "period": "monthly", "term": null}, "salary_visible": true, "title_keywords": ["designer"], "responsibilities": ["communication", "ui"], "requirements": {"degrees": [], "majors": [], "languages": [], "language_level": [], "hard_skills": ["adobe xd", "photoshop", "adobe illustrator"], "soft_skills": ["work independently", "self-motivation"], "languages_combined": []}, "experience_required": {"duration": [], "field": ["graphic"]}}, {"job_id": "100003009054835", "location_code": "hk", "company": "Mattel Asia Pacific Sourcing Ltd", "job_title": "Product Designer", "description": "Accountabilities \u2013 Key Result Areas\n\n\nAssist Senior Designer in completing the whole process of the development from themes and concept, presentation of styling, sketches, fitting session until pre-production sample\nResearch of seasonal themes, fabrications and material and colors etc.\nWork closely with merchandising and factories to facilitate development processes and schedules from product development, sourcing of fabrics and trims, sample fitting, etc.\nAssist preparations of seasonal design presentations to buyer and frontline operations\nExperience / Qualification Requirements\n\n\nDegree holder in design related discipline\n3-4 years solid experience in fashion design\nBe passionate about the brand\u2019s identity, with personal charisma and visions in international fashion trend\nAbility to research and apply market information\nCreative, communicative and be able to collaborate with business teams to achieve brand objectives\n\nCompetitive remuneration and benefit package will be offered to the right candidate. Please submit your application by clicking \"Apply Now\" below.\n\n\n\nAll data collected is for recruitment purpose only.", "employment_types": ["Full Time", "Permanent"], "selling_points": ["Degree in Product or Industrial Design", "3-5 years of product design experience", "With toys design experience a plus"], "locations": ["Tsim Sha Tsui"], "categories": ["Design", "Graphics", "Industrial / Product", "Others"], "post_time": "2022-01-17T11:33:10Z", "salary": {"currency": null, "max": null, "min": null, "period": "monthly", "term": null}, "salary_visible": false, "title_keywords": ["product designer"], "responsibilities": ["collaborate with", "market information", "data", "schedules", "operations", "merchandising", "teams", "sketches", "design", "presentations", "recruitment", "pre-production"], "requirements": {"degrees": ["degree holder"], "majors": ["design"], "languages": [], "language_level": [], "hard_skills": ["presentations"], "soft_skills": ["creative", "presentation", "passionate about"], "languages_combined": []}, "experience_required": {"duration": ["3-4 years"], "field": ["fashion design"]}}, {"job_id": "100003009053459", "location_code": "hk", "company": "Kidulteam Limited", "job_title": "Product / GraphicDesigner", "description": "\u8a8d\u53ef\u7684\u5c08\u4e0a\u6559\u80b2\uff0c\u526f\u5b78\u58eb\u5b78\u4f4d\uff0c\u4e3b\u4fee\u8a2d\u8a08\u6216\u52d5\u756b\u88fd\u4f5c\u76f8\u95dc\u5b78\u79d1\u512a\u5148\n\n\u30021\u5e74\u6216\u4ee5\u4e0a\u76f8\u95dc\u5de5\u4f5c\u7d93\u9a57\uff0c\u7d93\u9a57\u8f03\u6dfa\u8005\u4ea6\u53ef\u70ba\u898b\u7fd2\u8a2d\u8a08\u54e1\n\n\u3002\u4e86\u89e3Adobe\u7cfb\u5217\u8edf\u4ef6\uff0c\u64c5\u9577Photoshop, After Effects, Premiere Pro, AU etc\n\n\u3002\u66ff\u5152\u7ae5\u66f8\u520a\u7e6a\u756b\u63d2\u5716\u53ca\u6392\u7248\n\n\u3002\u6bcf\u6708\u85aa\u91d1\uff1a$12,000 (\u7d93\u9a57\u8c50\u5bcc\u8005\u53ef\u8b70)\n\n\u3002\u4e00\u5e74\u5408\u7d04\uff0c\u5982\u8868\u73fe\u826f\u597d\u53ef\u7372\u7e8c\u7d04\u8abf\u85aa\n\n\u3002\u6bcf\u90315\u5929\u5de5\u4f5c\n\u4e0a\u73ed\u6642\u9593\uff1a\u661f\u671f\u4e00\u81f3\u56db\uff1a09:00-18:00, \u661f\u671f\u4e94\uff1a09:00-17:00\n\n*\u4e0a\u8ff0\u8077\u4f4d\u7684\u5de5\u4f5c\u5730\u5740\u70ba\u65e9\u6167\u5152\u7ae5\u6559\u80b2\u4e2d\u5fc3\u5317\u89d2\u5206\u6821\uff0c\u50f1\u54e1\u9808\u9075\u5b88\u90e8\u4efd\u76f8\u95dc\u7684\u54e1\u5de5\u5b88\u5247\n\n\u3002\u54e1\u5de5\u798f\u5229\uff1a\n\u6709\u85aa\u75c5\u5047\u3001\u5a5a\u5047\u3001\u4f8d\u7522\u5047\u3001\u91ab\u7642\u4fdd\u969c(\u9580\u8a3a\u6d25\u8cbc+\u4f4f\u9662\u4fdd\u96aa)\u3001\u52e4\u5de5\u734e\u3001\u751f\u65e5\u798f\u5229\u3001\u5728\u8077\u57f9\u8a13\u3002\u672c\u6a5f\u69cb\u5177\u7a69\u5b9a\u67b6\u69cb\uff0c\u80fd\u63d0\u4f9b\u826f\u597d\u6649\u5347\u6a5f\u6703\u3002", "employment_types": ["Full Time"], "selling_points": [], "locations": ["Not Specified"], "categories": ["Design", "Graphics", "Interior", "Others"], "post_time": "2022-01-17T07:00:39Z", "salary": {"currency": null, "max": null, "min": null, "period": "monthly", "term": null}, "salary_visible": false, "title_keywords": [], "responsibilities": [], "requirements": {"degrees": [], "majors": [], "languages": [], "language_level": [], "hard_skills": ["after effects", "premiere pro"], "soft_skills": [], "languages_combined": []}, "experience_required": {"duration": [], "field": []}}, {"job_id": "100003009048862", "location_code": "hk", "company": "G.A. Operations Hong Kong Limited", "job_title": "Graphic Designer", "description": "Responsibilities:\n\n\nDesign and develop toys from concept, idea sketch, presentation to production\u00a0for the Dolls Team\nGenerate sketches, renderings, control drawings, fabric art creation to conduct model reviews and artwork directions\nConduct researches on new technologies, materials, production processes and trends so as to support product development process\nWork with various parties and ensure efficient design and development processes\n\nRequirements:\n\nDegree in Product Design, Industrial Design\u00a0or any related disciplines\n3-5 years of product design experience preferably from toys industry\nWith good sketching, rendering and drafting techniques\nHands on experience in 2D and 3D design software such as Photoshop and Illustrator\nGood command of written and spoken English and Chinese\n\nWho Should Join Us:\n\nWe are not only looking for the right experience and skill set, but also for attitude, potential & cultural fit.\n\nIf you are creative, energetic, passionate with a growth mindset and devoted to developing your future career in the world\u2019s leading toy company, you are welcome to be a part of our team and we will play & grow together!\u00a0\n\nWhat We Offer:\n\nAs a caring company, we are committed to providing engaging and work-life balance environment, competitive remuneration, comprehensive fringe benefits, and progressive career opportunities to our people.\u00a0 \u00a0\n\nOur benefits include:\n\nHalf-Day off every Friday\nFlexi Working Hours\nAnnual Leave and Company Holidays\nGroup Medical and Life Insurance\nMPF\nComprehensive Wellness Programs\u00a0\nHow To Apply:\n\nInterested parties please click \u201cApply Now\u201d to send your full resume (in Microsoft Word or PDF format), current and expected salary to us for review.\n\nApplicants not invited for interview within 6 weeks may assume their application unsuccessful. All information will be treated in strictest confidence and used solely for recruitment purpose.", "employment_types": ["Full Time", "Permanent"], "selling_points": [], "locations": ["Kowloon Bay"], "categories": ["Design", "Graphics"], "post_time": "2022-01-14T07:30:11Z", "salary": {"currency": null, "max": null, "min": null, "period": "monthly", "term": null}, "salary_visible": false, "title_keywords": ["graphic designer"], "responsibilities": ["control", "design and develop", "design", "sketches", "drawings"], "requirements": {"degrees": ["degree"], "majors": ["related disciplines", "design"], "languages": ["english", "chinese"], "language_level": ["good command"], "hard_skills": ["illustrator", "photoshop"], "soft_skills": ["passionate", "creative", "hands on", "devoted", "energetic"], "languages_combined": [{"language": "english", "language_level": ["good command"]}, {"language": "chinese", "language_level": ["good command"]}]}, "experience_required": {"duration": ["3-5 years"], "field": ["toys", "product design", "design"]}}, {"job_id": "100003009048690", "location_code": "hk", "company": "North Viet Catering Group Limited", "job_title": "Graphic Designer", "description": "\nKidulteam Ltd. is a character merchandise company which engaged in design, manufacturing, distributing and retailing of gifts and confectionery in Hong Kong and Mainland China. To copy with our business expansion, we are now looking for:\n\u2022 Degree or Higher Diploma in Graphic Design or related disciplines.\n\u2022 At least 3 years experiences in plush and giftware design.\n\u2022 Proficient and able to be hands-on with Illustrator, Freehand, Photoshop and Corel Draw etc.\nProduct design in bag/premium/3D skills/Comics experience a plus (not necessary).\nWe offer competitive salary and fringe benefits to the right candidate. Interested parties please forward your detailed resume stating your availability, current and expected salary to [via\u00a0 Apply Now ]\n\n", "employment_types": ["Full Time", "Permanent"], "selling_points": [], "locations": ["Chai Wan"], "categories": ["Media & Advertising", "Creative / Design", "Design", "Graphics", "Hospitality / F & B", "Food & Beverage"], "post_time": "2022-01-14T07:02:53Z", "salary": {"currency": null, "max": null, "min": null, "period": "monthly", "term": null}, "salary_visible": false, "title_keywords": ["graphic designer"], "responsibilities": ["graphic design", "product design", "design"], "requirements": {"degrees": ["diploma", "degree"], "majors": ["related disciplines", "graphic design"], "languages": [], "language_level": [], "hard_skills": ["plus", "illustrator", "photoshop"], "soft_skills": ["hands-on"], "languages_combined": []}, "experience_required": {"duration": ["at least 3 years"], "field": ["product design", "design"]}}, {"job_id": "100003009051313", "location_code": "hk", "company": "Miramar Hotel and Investment Company, Limited", "job_title": "Designer", "description": "We are seeking for a dynamic Graphic Designer who is passionate about fashion to join our HK team and support the Italian Style Office.\u00a0\n\nKey Responsibilities:\n\nResearch and proposal of seasonal prints & collection (allover & placement)\nHand sketching and the digital sketch of artworks\nConstant interaction with the Chief Designer & the merchandising team on all aspects of product line plans, briefs, color palette, pricing, themes, graphics, and strategies.\nAdhere to the product calendar, ensuring development projects are on track\nKeep update knowledge of competitors top sellers, technologies, styling, colors, strategies and pricing\u00a0\n\nJob Requirements:\n\nDiploma or above in in Fashion Design or Graphic Design\nMust possess 2 to 3 years of experience in fashion/graphic design\nAbility to sketch accurately and proportionately & provide detailed specifications\nHave some knowledge in the clothing production process\nGood knowledge of various design soft wares & must have advanced skills in Photoshop / Illustrator and 3-D design\nExcellent communication, a team player and work well with others; able to communicate in English effectively", "employment_types": ["Full Time", "Permanent"], "selling_points": [], "locations": ["Tsim Sha Tsui"], "categories": ["Media & Advertising", "Creative / Design", "Design", "Graphics", "Multi-media"], "post_time": "2022-01-15T08:04:11Z", "salary": {"currency": null, "max": null, "min": null, "period": "monthly", "term": null}, "salary_visible": false, "title_keywords": ["designer"], "responsibilities": ["graphics", "plans", "merchandising"], "requirements": {"degrees": ["diploma or above"], "majors": ["graphic design", "design"], "languages": ["english"], "language_level": [], "hard_skills": ["illustrator", "photoshop"], "soft_skills": ["communication", "team player", "advanced", "detailed"], "languages_combined": [{"language": "english", "language_level": []}]}, "experience_required": {"duration": ["2 to 3 years"], "field": ["graphic design"]}}, {"job_id": "100003009052064", "location_code": "hk", "company": "Eagle Sky Media Limited", "job_title": "Digital Marketing Officer (Advertising Agency , Digital Marketing, Social media)", "description": "Responsibilities\n\nDesign menu, promotion material, poster for both offline and online platform;\nProduce printing material & visual for outlets;\nProduct photo shooting & retouch for design works;\nPrepare artwork for IG & Facebook thread;\nAssist management to update company website, IG & Facebook of various brands;\nProvide support to distribute printing material;\nOccasionally outing may be required\nRequirements\n\nDiploma in graphic design or related disciplines\nMinimum 3 years relevant experience, solid experience in F&B industry is a must\nKnowledge in Web Site design & editing and Photography will be a definite advantage\nProficient in\u00a0Illustrator, Photoshop & MS Office is a must\nSelf-motivated, independent, well-organized and detail-minded\n\nWe offer\u00a0competitive\u00a0remuneration package for suitable candidates.\u00a0For interested parties, please click \"Apply Now\" to apply with your\u00a0resume\u00a0and\u00a0expected\u00a0salary.\u00a0\u00a0\n\nAll personal data collected will be used for recruitment purpose only and will be kept strictly confidential. Only short-listed candidates will be notified.", "employment_types": ["Full Time", "Permanent"], "selling_points": ["CONTENT Marketing", "Advertising Agency", "designer"], "locations": ["Tsuen Wan Area"], "categories": ["Media & Advertising", "Creative / Design", "Design", "Graphics", "Marketing / Public Relations", "Public Relations - Copy-writing"], "post_time": "2022-01-17T08:45:18Z", "salary": {"currency": null, "max": null, "min": null, "period": "monthly", "term": null}, "salary_visible": false, "title_keywords": ["digital marketing officer", "digital marketing"], "responsibilities": ["management", "provide support", "product photo shooting", "design", "visual", "facebook", "company website"], "requirements": {"degrees": ["diploma"], "majors": ["related disciplines", "graphic design"], "languages": [], "language_level": [], "hard_skills": ["ms office", "illustrator", "web", "photoshop"], "soft_skills": ["detail-minded", "self-motivated", "independent", "well-organized"], "languages_combined": []}, "experience_required": {"duration": ["minimum 3 years"], "field": ["f&b", "relevant experience"]}}, {"job_id": "100003009048929", "location_code": "hk", "company": "Fresh Up Group Limited", "job_title": "Graphic Designer", "description": "The Job\n\nCreate innovative solutions for Group and Business Units from concept generation, layout design and final artwork production including F&B photo shooting art direction, mall campaign setup idea, hotel sophisticated layout designs and corporate communicating materials to convey the distinctive messages\nDesign and execute all the assigned design tasks from research, concept generation, layout design and final artwork production in a wide range of media platforms\nWork with supervisor and other teammates to adhere to user\u2019s requests and meet deadlines to retain the company brand consistency and the specific promotions\nLiaise and follow up with printing companies and suppliers to ensure the timely delivery\nThe Requirement\n\nHigher diploma or above in Graphic Design or related disciplines\n2 years or above experience in design/advertising and/or digital campaign\nExperience in graphic, multimedia design, layout and typography\nKnowledge on Adobe Suite and video editing software i.e. Illustrator, Photoshop, InDesign, Premiere & Aftereffect etc.\nGood team player, willing to learn, open-minded, independent and responsible\n\nAttractive remuneration would be offered to the right candidates.\nPlease send your application with portfolio and expected salary to\u00a0Human Resources Manager:\n\nBy WhatsApp: 6388-3034 or\nBy Fax: 2722-5555\n\nPersonal data collected will be used for recruitment purpose only.\u00a0 We are an equal opportunity employer.", "employment_types": ["Full Time"], "selling_points": ["Solid experience in Illustrator & After Effects", "1-2 years relevant experience", "Immediate Available"], "locations": ["Kwai Fong"], "categories": ["Design", "Graphics", "Multi-media", "Others"], "post_time": "2022-01-14T07:44:02Z", "salary": {"currency": null, "max": null, "min": null, "period": "monthly", "term": null}, "salary_visible": false, "title_keywords": ["graphic designer"], "responsibilities": ["liaise", "artwork production", "layout design", "design", "brand consistency", "setup"], "requirements": {"degrees": ["higher diploma or above"], "majors": ["related disciplines", "graphic design"], "languages": [], "language_level": [], "hard_skills": ["indesign", "illustrator", "premiere", "video editing", "whatsapp", "adobe", "multimedia", "photoshop"], "soft_skills": ["good team player", "independent", "responsible", "open-minded", "willing to learn"], "languages_combined": []}, "experience_required": {"duration": ["2 years"], "field": ["digital", "graphic", "advertising", "design"]}}, {"job_id": "100003009051527", "location_code": "hk", "company": "Ma Belle Jewellery Co Ltd", "job_title": "Designer/ Web Designer/ Digital Designer", "description": "Responsibilities:\nSocial media management including content development & consumer engagement\nCommunicate and extent good relationships with on-line media, KOL, vendors & platform partners\nAnalyze market trends and explore new marketing techniques & business opportunities\nParticipate and support internal teams for different marketing campaign and operation needs\nPrepare marketing proposal for client\nPrepare regular reports for management review\nParticipate & support in all new business initiatives and all ad hoc projects\nGood content writer\nStrong Creative Designer is much preferred\n\nRequirements:\n\nDegree holder in Marketing / Communication / Multi-media Design preferred\nMin. 2 years\u2019 experienced in marketing\nExcellent interpersonal, presentation and communication skills\nProficient in MS Word, Excel, PowerPoint and Chinese Word Processing\nFluency in written and spoken Chinese and English\nExperience in CMS (Wordpress) ,graphic design tools (Adobe Photoshop and Adobe Illustrator)\nDetail-minded, tech-savvy, outgoing, and flexible to work\nHard-working, willing to learn and able to handle multi-task, work under pressure and meet deadlines\nCandidate with more experienced will be considered as Senior Marketing Executive", "employment_types": ["Full Time", "Permanent"], "selling_points": ["multimedia/online advertising/video editing", "Adobe Photoshop ,Illustrator, After Effects", "Knowledge in HTML, CSS, UI/UX design"], "locations": ["Tin Hau"], "categories": ["Design", "Graphics", "Multi-media", "Web Designer"], "post_time": "2022-01-16T08:05:51Z", "salary": {"currency": null, "max": null, "min": null, "period": null, "term": null}, "salary_visible": false, "title_keywords": ["digital designer", "designer"], "responsibilities": ["social media", "management", "business initiatives", "business opportunities", "review", "teams", "regular reports for management", "ad hoc projects"], "requirements": {"degrees": ["degree holder"], "majors": ["marketing", "design"], "languages": ["english", "chinese"], "language_level": ["fluency", "proficient"], "hard_skills": ["excel", "chinese word processing", "adobe photoshop", "powerpoint", "adobe illustrator", "wordpress", "ms word"], "soft_skills": ["detail-minded", "communication skills", "outgoing", "flexible", "multi-task", "willing to learn", "communication", "hard-working", "meet deadlines", "interpersonal", "presentation", "work under pressure"], "languages_combined": [{"language": "english", "language_level": ["fluency"]}, {"language": "chinese", "language_level": ["fluency", "proficient"]}]}, "experience_required": {"duration": [], "field": ["graphic design"]}}, {"job_id": "100003009052049", "location_code": "hk", "company": "China Mobile International Limited", "job_title": "Assistant UI/UX Design Manager (Ref: CMIJD-1213-AUIUXMPMHK)", "description": "Job Duties:\n\n\nTo contribute creative ideas and innovative multimedia solutions, develop and produce e-learning packages, animated, audio and visual videos, interactive video games and animated PowerPoint presentation, etc.;\nTo write scripts, design and produce the department\u2019s training and presentation materials in diversified visual content including photo and video shooting, editing and retouching with a view to achieving better audio and visual appeal to audiences;\nTo handle graphic design and artwork output for departmental publications and e-cards, etc.\nEmployment Terms\n\n\nWork Hours: 8.8 hours a day between 0900 and 1800, Monday to Friday, off on Sat, Sun and Public Holidays\n\nSalary: HK$20,000 per month\nWork Location: Shamshuipo\n\nCandidates Requirement:\n\nHave bachelor degree/higher diploma in Creative Writing for Film, TV and New Media, or Creative/Digital Media, or Multimedia Technologies and Innovation or similar subjects from a local university/institute, or equivalent;\n\nLevel 3 or above in Chinese Language and English Language in HKDSE or HKCEE, or equivalent;\nProficient in scriptwriting, operating AV equipment and various computer software related to digital and image-sound media, photo and video editing and production including Windows 10, Microsoft Office 2016, Adobe Premier, Adobe Audition, Adobe After Effects, Adobe Illustrator, Adobe InDesign, Adobe Animate CC, Adobe Captivate 2019, Flash, Digital Animation and PhotoShop; and\nPossess some working experiences in scriptwriting and producing interactive video games and PowerPoint with audio and visual effects;\nHave at least one dose of Covid-19 vaccine.\nHow to Apply:\n\nInterested candidates please send in your CV (including all grades attained in public exam) stating clearly your academic qualifications with working experience, and earliest date available.\n\nPlease state ref no: JB-RVD-0117 as header in your application\n\nAll personal information collected will be solely for use in recruitment and will be kept in strict confidentiality\n\nWe apologize that only shortlisted candidates will be contacted for interviews", "employment_types": ["Full Time", "Permanent"], "selling_points": ["Bachelor's degree or above", "UI/UX Design of mCloud Platform", "Proficient in design software"], "locations": ["Kwai Hing"], "categories": ["Design", "Graphics", "Industrial / Product", "Web Designer"], "post_time": "2022-01-17T01:57:11Z", "salary": {"currency": null, "max": null, "min": null, "period": "monthly", "term": null}, "salary_visible": false, "title_keywords": ["design manager", "assistant"], "responsibilities": ["sat", "retouching", "creative ideas", "editing", "graphic design", "design", "develop", "video shooting", "visual", "audio", "artwork output"], "requirements": {"degrees": [], "majors": [], "languages": [], "language_level": [], "hard_skills": [], "soft_skills": [], "languages_combined": []}, "experience_required": {"duration": [], "field": []}}, {"job_id": "100003009053424", "location_code": "hk", "company": "Wams Design Limited", "job_title": "Senior Designer/Interior Designer/Assistant Designer", "description": "Responsibilities:\n\n\nResponsible for digital graphic design creatives and executions;\nDesign and execute compelling creative for digital channels by mobile / desktop in a wide range of media platforms;\nCreating and editing animation / motion graphic for informative and promotional videos.\n\n\nRequirements:\n\n\nDiploma or above in Multimedia Design, Graphic Design, Creative Media or related discipline;\n1-2 years relevant experience;\nProficient in Adobe Creative skills; Illustrator, Photoshop, InDesign, Premiere, After Effects etc.\nKnowledge in photography and video editing are preferred;\nGood written and verbal communication skills in both English and Chinese;\nSelf-motivated, responsible, able to work independently and adapt to different environment;\nPortfolio is required for interview.\n\nBenefits:\n\n\n5days work / Bank Holidays / Annual Leaves / Medical Insurance / Birthday Leave, Maternity Leave, Funeral Leave / Promotion Opportunities etc.\n\nWe offer competitive remuneration including career prospects to the right candidate. Interested parties please send your portfolio and resume with current & expected salary by clicking 'Apply Now' for application.\n\n(Data collected will only be used for job application processing. All related information will be kept up to 6 months and all personal data will be destroyed afterwards.)\n\n", "employment_types": ["Full Time", "Permanent"], "selling_points": [], "locations": ["Wan Chai"], "categories": ["Design", "Graphics", "Interior", "Visual Merchandising"], "post_time": "2022-01-17T06:58:05Z", "salary": {"currency": null, "max": null, "min": null, "period": "monthly", "term": null}, "salary_visible": false, "title_keywords": ["senior designer", "interior designer", "assistant designer"], "responsibilities": ["graphic design", "design", "editing", "motion graphic", "animation"], "requirements": {"degrees": ["diploma or above"], "majors": ["multimedia design", "graphic design", "creative media"], "languages": ["english", "chinese"], "language_level": ["good"], "hard_skills": ["indesign", "illustrator", "premiere", "video editing", "after effects", "adobe", "multimedia", "photoshop"], "soft_skills": ["communication skills", "self-motivated", "work independently", "responsible", "creative"], "languages_combined": [{"language": "english", "language_level": ["good"]}, {"language": "chinese", "language_level": ["good"]}]}, "experience_required": {"duration": ["1-2 years"], "field": ["relevant experience"]}}, {"job_id": "100003009051314", "location_code": "hk", "company": "List Sotheby's International Realty", "job_title": "Graphic Designer", "description": "We are looking for high caliber candidates to fill the following positions:\n\n\u00a0\nAssistant Marketing Manager\n\n\u00a0Job duty:\n\nProvide good account servicing to clients\nExpand company business and explore new business opportunity\nExecute retail redemption programs / exhibition & event activities\nA keen attention to detail and budgetary restraints\nAbility to think strategically and execute tactically\nProvide innovative and collaborative experience for clients, suppliers and business partners\nAble to work under pressure and meet deadlines\n\n\u00a0Requirement:\n\nDegree holder in any disciplines\nMinimum 5 years\u2019 relevant experience in sales and marketing field\nExperience in advertising account service or retail operation is an asset\nEnergetic, self-motivated, presentable, detail-minded and able to work independently\nGood communication, presentation and interpersonal skill\nFluency in spoken & written English, Cantonese and Mandarin\nPC knowledge in MS Excel, Word & PowerPoint and Chinese Processing\n\n(Less experience will be considered as Marketing Executive)\n\nMerchandisers\n\n\u00a0\u00a0Requirement:\n\nTertiary education with min. 3 years solid experience\u00a0\nProficient in manufacturing process, sourcing and quality control, able to handle order independently\nResponsible for order follow up from sample development to delivery, including product presentations and cost analysis\nExperience in licensing products would be an advantage\nFamiliar to the rules of trading in Mainland China would be an advantage\nMature, hard-working, well organized, willing to work under pressure and independently\u00a0\u00a0\n\n(More experience will be considered as Senior Merchandiser)\n\n\u00a0Product / Graphic Designers\u00a0\n\n\u00a0\u00a0Requirement:\n\nDiploma / Degree Holder in Product / Graphic Design or related discipline\nMin. 5 years product design experience\nGood illustration skill is an asset\nCreative, self-initiative, independent, good market and fashion sense\nProficient in PC computer, Photoshop / Illustrator\nAbility to work with cross-functional team\nMature, hard-working, willing to work under pressure and independently\u00a0\n\n\u00a0\u00a0Immediate availability is preferred\n\n\u00a0\u00a0Interested parties, please email your full CV and expected salary\u00a0by clicking APPLY NOW", "employment_types": ["Full Time", "Permanent"], "selling_points": ["Real Estate Industry", "Marketing / Company Branding", "Competence with Adobe Creative Suite"], "locations": ["Central"], "categories": ["Design", "Graphics", "Multi-media"], "post_time": "2022-01-15T08:10:49Z", "salary": {"currency": null, "max": null, "min": null, "period": "monthly", "term": null}, "salary_visible": false, "title_keywords": ["graphic designer"], "responsibilities": ["advertising", "graphic design", "presentations", "communication", "product design", "quality control", "cost analysis", "work under pressure"], "requirements": {"degrees": ["diploma", "degree holder"], "majors": ["graphic design", "any disciplines"], "languages": ["cantonese", "english", "chinese", "mandarin"], "language_level": ["fluency"], "hard_skills": ["analysis", "illustration", "word", "powerpoint", "presentations", "illustrator", "ms excel", "pc", "pc knowledge", "processing", "photoshop"], "soft_skills": ["collaborative", "communication", "hard-working", "work under pressure", "detail-minded", "independent", "keen", "mature", "presentable", "self-initiative", "meet deadlines", "creative", "presentation", "work independently", "interpersonal skill", "attention to detail", "think strategically", "energetic", "self-motivated", "independently", "responsible", "well organized", "innovative"], "languages_combined": [{"language": "cantonese", "language_level": ["fluency"]}, {"language": "english", "language_level": ["fluency"]}, {"language": "chinese", "language_level": []}, {"language": "mandarin", "language_level": ["fluency"]}]}, "experience_required": {"duration": ["3 years", "5 years", "minimum 5 years"], "field": ["advertising", "business", "relevant experience", "marketing", "operation", "product design", "retail"]}}, {"job_id": "100003009053480", "location_code": "hk", "company": "Untitled Limited", "job_title": "Senior 3D Designer (5 days work)", "description": "Designer/ Web Designer/ Digital Designer\n\nThe Job\n\nprepare various online and offline marketing materials including but not limited to graphic/ video promotion materials, social media post, web design, photo retouching etc.\nwork closely with different teams and external parties to develop and execute cross-platform marketing\u00a0 campaign visuals and concepts\n\n\u00a0The Person\n\nDiploma or above in in Graphic/ Multimedia/ Animation/ Web Design or related discipline\nAt least 3 years of experience in e-Commerce, Graphic, Multimedia and Web Design\nexperienced in graphic/ multimedia/ online advertising/ web design/ video editing/ production skills is preferred\nproficient in Adobe Photoshop, Illustrator, After Effects and Premiere, Dreamweaver, XD and related software.\nhighly technical skills in motion graphic design and animation\nstrong sense on graphic, layout. colouring and usability on graphics\nknowledge in HTML, CSS, UI/UX design\nexperience in jQuery, Javascript and 3D rendering will be a plus\ncreative, detail-minded and well-organized working behavior\nwork independently and under pressure with tight schedule\ngood player with excellent communications skills\nWe offer 5-day week, attractive remuneration, career advancement opportunity, medical benefit, discretionary bonus, staff purchase privileges to the right candidate. Interested parties, please\u00a0send us your full resume with current and expected salary.\n\n\nPersonal data collected will be used for recruitment purposes only and will be treated in strict confidence.\u00a0 Applicants not invited for interview within\u00a04 months\u00a0may consider their applications unsuccessful.", "employment_types": ["Full Time"], "selling_points": ["Five-day work week", "Double pay", "Performance bonus"], "locations": ["Quarry Bay"], "categories": ["Media & Advertising", "Creative / Design", "Design", "Graphics", "Visual Merchandising"], "post_time": "2022-01-17T07:02:15Z", "salary": {"currency": null, "max": null, "min": null, "period": "monthly", "term": null}, "salary_visible": false, "title_keywords": ["senior 3d designer"], "responsibilities": ["social media", "photo retouching", "external parties", "teams", "design", "develop", "marketing materials"], "requirements": {"degrees": ["diploma or above"], "majors": ["web design", "animation"], "languages": [], "language_level": [], "hard_skills": ["graphics", "web design", "plus", "e-commerce", "jquery", "adobe photoshop", "illustrator", "premiere", "html", "video editing", "after effects", "javascript", "multimedia", "dreamweaver", "css"], "soft_skills": ["detail-minded", "work independently", "under pressure", "well-organized", "technical skills", "creative"], "languages_combined": []}, "experience_required": {"duration": ["at least 3 years"], "field": ["graphic", "design", "e-commerce"]}}, {"job_id": "100003009047641", "location_code": "hk", "company": "Formex Financial Press Limited", "job_title": "Graphic Designer", "description": "Degree holder or Diploma in interior design\u00a0\nProficient in CAD (Photoshop, Sketch Up, 3D Max are bonus)\nGood team-player who is initiative, creative, self-motivated, willing to work in a fast paced and demanding environment\nGood in presentation skills\nGood Leadership Skills\nAt least 3 year working experience\u00a0 **Less experience consider as Assistant Interior Designer**\nStrong sense of design and be able to handle full set of drawing with detailing design\nWork independent", "employment_types": ["Full Time", "Permanent"], "selling_points": [], "locations": ["Central"], "categories": ["Media & Advertising", "Creative / Design", "Design", "Graphics"], "post_time": "2022-01-14T03:38:44Z", "salary": {"currency": null, "max": null, "min": null, "period": "monthly", "term": null}, "salary_visible": false, "title_keywords": ["graphic designer"], "responsibilities": ["design"], "requirements": {"degrees": ["diploma", "degree holder"], "majors": ["design"], "languages": [], "language_level": [], "hard_skills": ["sketch up", "cad", "max", "photoshop"], "soft_skills": ["self-motivated", "independent", "team-player", "leadership skills", "presentation skills", "creative", "initiative"], "languages_combined": []}, "experience_required": {"duration": ["at least 3 year"], "field": ["designer"]}}, {"job_id": "100003009016680", "location_code": "hk", "company": "Play Concept Limited", "job_title": "Architect 5 days work in Lai Chi Kok", "description": "Work closely with the marketing team to create company branding, designs and continuous content for users and the platform (Website/social media)\nAble to create strategic and creative ideas with a fresh mindset, result oriented, and able to drive the process within a given deadline\nExperience with online advertising/ social media platforms (Facebook, WeChat, Linkedin, Instagram)\nPassionate about seeking out-of-the-box ideas related to design and content\n\nThe Successful Applicant\n\nDiploma in Graphic Design, or Marketing-related discipline\nMinimum 2 years of related experience\nImmediate availability preferred\nCompetence with Adobe Creative Suite (particularly Photoshop, Illustrator, InDesign), and Powerpoint\nResponsible, detail minded,\u00a0efficient, well organized, proactive,\u00a0independent\u00a0and able to work under pressure\nStrong communication and interpersonal skills\nInterested parties please send your\u00a0full resume with expected salary\u00a0and\u00a0your availability\u00a0to us.\n\n\nAll personal data collected will be treated strictly confidential and used for recruitment purposes only.", "employment_types": ["Full Time", "Permanent"], "selling_points": ["Degree / Diploma holder in Architectural Design", "1-2 years experience", "Strong Analytical Skills in Planning & Design"], "locations": ["Lai Chi Kok"], "categories": ["Building & Construction", "Architectural Services", "Design", "Graphics", "Interior"], "post_time": "2022-01-17T16:20:51Z", "salary": {"currency": null, "max": null, "min": null, "period": "monthly", "term": null}, "salary_visible": false, "title_keywords": [], "responsibilities": ["social media", "creative ideas", "ideas", "graphic design", "social media platforms", "website", "design", "communication", "facebook", "online advertising", "work under pressure"], "requirements": {"degrees": ["diploma"], "majors": ["graphic design", "marketing"], "languages": [], "language_level": [], "hard_skills": ["indesign", "illustrator", "powerpoint", "wechat", "facebook", "adobe creative suite", "photoshop"], "soft_skills": ["efficient", "proactive", "independent", "responsible", "well organized", "result oriented", "communication and interpersonal skills", "creative", "passionate about", "work under pressure"], "languages_combined": []}, "experience_required": {"duration": ["minimum 2 years"], "field": ["related", "social media", "advertising"]}}, {"job_id": "100003009048878", "location_code": "hk", "company": "Prenetics Limited", "job_title": "Graphic Designer", "description": "Requirements:\n\n\n2 years minimum experience in event production / exhibition field / shopping mall decorations\nCompetency in adobe illustrator / Photoshop / 3D studio max, Auto CAD\nPreparing studies, layouts, and construction drawing.\nSeasonal-Decoration, Event Design experience will be an absolute advantage\nExhibition, or environmental design qualification in degree or diploma level\nFresh Graduate will be considered\nAble to handle projects from concept design through to completion\nMust be a team player and willing to work overtime, self initiative & motivated, strong sense of responsibitity and able to work under pressure\n\n\nWe offer attractive package to the right candidate.\n\nInterested parties please send full resume with salary expected, to Fax No. 3426 9709\n\nhttp://www.facebook.com/pages/untitled-limited/336303970488", "employment_types": ["Full Time", "Permanent"], "selling_points": ["Help create mobile and web applications", "Present and review designs", "Conduct layout adjustment"], "locations": ["Quarry Bay"], "categories": ["Design", "Graphics", "Industrial / Product", "Web Designer"], "post_time": "2022-01-14T07:33:42Z", "salary": {"currency": null, "max": null, "min": null, "period": "monthly", "term": null}, "salary_visible": false, "title_keywords": ["graphic designer"], "responsibilities": ["design", "work under pressure"], "requirements": {"degrees": ["diploma", "degree", "fresh graduate"], "majors": ["design"], "languages": [], "language_level": [], "hard_skills": ["max", "auto cad", "photoshop", "adobe illustrator"], "soft_skills": ["work overtime", "motivated", "team player", "initiative", "work under pressure"], "languages_combined": []}, "experience_required": {"duration": ["2 years"], "field": ["design"]}}, {"job_id": "100003009046440", "location_code": "hk", "company": "PressLogic Limited", "job_title": "Graphic Designer", "description": "Job Duties\n\n-\u00a0 \u00a0 \u00a0 \u00a0Responsible for graphic design and artwork production for printing, advertising & promotion purposes\n-\u00a0\u00a0\u00a0\u00a0\u00a0\u00a0 Support the sales / marketing team to develop graphic design in annual report, brochure, leaflet etc.\n-\u00a0\u00a0\u00a0\u00a0\u00a0\u00a0 Communicate with sales team and project management team in order to cope with design requirements of different jobs\n-\u00a0\u00a0\u00a0\u00a0\u00a0\u00a0 Provide useful and constructive proposal for company project design\n-\u00a0\u00a0\u00a0\u00a0\u00a0\u00a0 Ad-hoc duties when required\n\nJob requirement\n\n-\u00a0\u00a0\u00a0\u00a0\u00a0\u00a0 Diploma or above in Graphic Design or other related disciplines\n-\u00a0\u00a0\u00a0\u00a0\u00a0\u00a0 1-2 years relevant working experience; Candidate with less experience shall be considered for the junior positions; Fresh graduates will be considered as Trainee\n-\u00a0\u00a0\u00a0\u00a0\u00a0\u00a0 Proficiency in Design related software, such as Adobe InDesign, Illustrator and Photoshop, MS Office etc.\n-\u00a0\u00a0\u00a0\u00a0\u00a0\u00a0 Able to work independently, hardworking, creative, self-motivated and responsible\n-\u00a0\u00a0\u00a0\u00a0\u00a0\u00a0 Good organizational and interpersonal skills\n\nAttractive remuneration package will be offered to the right candidate. Interested parties, please send us your resume with current and expected salary (with reference number quoted)\u00a0by clicking \"APPLY NOW\".\n\nPersonal data collected would be used for recruitment purpose only.", "employment_types": ["Full Time", "Permanent"], "selling_points": ["Birthday Leave & Work Anniversary Leave", "Fun, young and joyful office environment", "Social Media Graphic Design - Branding Development"], "locations": ["Lai Chi Kok"], "categories": ["Media & Advertising", "Creative / Design", "Design", "Graphics", "Web Designer"], "post_time": "2022-01-13T11:11:32Z", "salary": {"currency": null, "max": null, "min": null, "period": "monthly", "term": null}, "salary_visible": false, "title_keywords": ["graphic designer"], "responsibilities": ["communicate with", "advertising", "graphic design", "artwork production", "leaflet", "design", "develop", "project management", "sales team", "ad-hoc duties", "report"], "requirements": {"degrees": ["diploma or above"], "majors": ["related disciplines", "graphic design"], "languages": [], "language_level": [], "hard_skills": ["ms office", "adobe indesign", "illustrator", "photoshop"], "soft_skills": ["work independently", "self-motivated", "responsible", "organizational", "interpersonal skills", "creative", "hardworking"], "languages_combined": []}, "experience_required": {"duration": ["1-2 years"], "field": ["relevant working experience"]}}, {"job_id": "100003009047115", "location_code": "hk", "company": "Asia Marine Yacht Services limited", "job_title": "Digital Graphic Designer", "description": "Degree / Diploma holder in Architectural Design or equivalent with a\u00a0passion for design and creativity.\nMust demonstrate initiative and willing to develop.\nFresh graduate/ final year student preferred but not exclusive.\nSome experience preferred (1-2 years).\nStrong Analytical Skills in Planning & Design with Site Experience is\u00a0Preferred.\nUnderstands the art of guiding a project from concept to implementation\nProficiency in AutoCAD, SketchUp (VRay), Photoshop is a MUST.\nResponsibilities will include site visits, production of drawing packages,\u00a0design development, coordination with clients, and consultants.\n\u00a0We offer five-day work, comfortable good working environment, attractive salary, bonus, annual holiday. Interested parties are invited to send their applications with full employment history, current and expected salary in the subject and by clicking \"Apply Now\"", "employment_types": ["Full Time"], "selling_points": ["Immediately available is preferred", "Good and harmonious working environment", "Luxury brand / 5-day works"], "locations": ["Aberdeen"], "categories": ["Design", "Graphics", "Marketing / Public Relations", "Marketing - General / Support", "Digital Marketing"], "post_time": "2022-01-14T02:22:33Z", "salary": {"currency": null, "max": null, "min": null, "period": "monthly", "term": null}, "salary_visible": false, "title_keywords": ["digital graphic designer"], "responsibilities": ["coordination with", "implementation", "design", "develop", "planning"], "requirements": {"degrees": ["diploma holder", "degree", "fresh graduate"], "majors": ["design"], "languages": [], "language_level": [], "hard_skills": ["autocad", "sketchup", "photoshop", "analytical skills"], "soft_skills": ["coordination", "initiative", "analytical skills", "passion for"], "languages_combined": []}, "experience_required": {"duration": ["1-2 years"], "field": ["design", "analytical", "planning"]}}, {"job_id": "100003009054984", "location_code": "hk", "company": "Royal Kitchen Design Co. Ltd", "job_title": "Assistant kitchen Designer", "description": "Responsibilities:\n\nCreate optimized social media graphic design for branding development and daily content in different topic\nResponsible for concept development, visualization and hands on design for key visual, social media posts and promotion collateral, etc\nWork closely with editorial team to ensure concept's achievability and present accurately\u00a0\nAdjust and revise on project goals and design style accordingly as required from time to time\nFollow through project from concept development, executing layouts, artwork design independently\nStaying abreast of current marketing trends among digital, social media platform to develop a cutting edge among the advertisement industry\nSupport any ad-hoc job tasks assigned, including but not limited to client ad related tasks\n\nRequirements:\n\nDegree in multimedia design / graphic design or other relative disciplines\nAt least 3 years of experience in marketing design\nExperience in create optimized social media design is preferred\nFamiliar with social media operations is preferred\nGood verbal and written communications in English and Chinese\nCapable of drawing storyboards\u00a0\nWith website design experience is a plus\nAdvance users of Photoshop, illustrator, and video editing tools\nStrong sense in aesthetics design\n\nWe Offer:\n\n5 Days work\nFlexible Working Hour\nBirthday Leave & Work Anniversary Leave\u00a0\nMedical Coverage\nFun, young and joyful office environment\u00a0\n\nInterested candidates, please email full resume with 1.) EXPECTED SALARY 2.) AVAILABILITY 3.)\u00a0WORK REFERENCE\u00a0 to the HR department by clicking 'Apply Now'.\n\nFor company information, please refer to the website http://www.presslogic.com/.\n\nAll information received will be kept in strict confidence and only for employment-related purposes.", "employment_types": ["Full Time"], "selling_points": ["Diploma Holder in interior design", "Fresh Graduate Welcome", "Double Pay, employee discount"], "locations": ["Wan Chai"], "categories": ["Design", "Graphics", "Interior", "Others"], "post_time": "2022-01-17T16:22:45Z", "salary": {"currency": "HKD", "max": 24999, "min": 17000, "period": "monthly", "term": null}, "salary_visible": true, "title_keywords": ["designer", "assistant"], "responsibilities": ["ad-hoc", "social media", "visualization", "graphic design", "design", "develop", "executing", "visual"], "requirements": {"degrees": ["degree"], "majors": ["multimedia design", "graphic design"], "languages": ["english", "chinese"], "language_level": ["good"], "hard_skills": ["plus", "illustrator", "video editing", "multimedia", "photoshop"], "soft_skills": ["capable"], "languages_combined": [{"language": "english", "language_level": ["good"]}, {"language": "chinese", "language_level": ["good"]}]}, "experience_required": {"duration": ["at least 3 years"], "field": ["social media", "marketing", "design"]}}, {"job_id": "100003009045659", "location_code": "hk", "company": "Mindcluster Limited", "job_title": "Brand & Graphic Designer", "description": "Responsibilities:\n\nConducting user research, testing and report\nDeveloping wireframes and user flows based on user needs\nCollaborating with product management and engineering to define and implement innovative solutions for the product direction, visuals and experience\nExecuting all visual design stages from concept to final hand-off to engineering\nConduct user research and evaluate user feedback\n\nRequirements:\n\nTo qualify for the role you must have:\n\n\nProven experience as a UX Designer, UI Designer or similar role\nPortfolio of related design projects is a must\nFamiliarity with interaction design and information architecture\nFamiliarity with design software and technologies (e.g. Photoshop, Illustrator, Sketch, Figma... etc.)\nAbility to work methodically and meet deadlines\nKnowledge of prototyping\nKnowledge of HTML/CSS; JavaScript is a plus\nExcellent communication skills in English and Chinese.\nDegree in Design or a related field\n\nWhat working at EY offers:\n\nSupport, coaching and feedback from some of the most engaging colleagues around\nOpportunities to develop new skills and progress your career\nThe freedom and flexibility to handle your role in a way that\u2019s right for you\n\nIf you can confidently demonstrate that you meet the criteria above, please contact us as soon as possible.\n\nJoin us in building a better working world.\n\nApply now.", "employment_types": ["Full Time"], "selling_points": ["Step ahead and work on future-crafting projects", "Boundless opportunities & Fast-tracked career path", "Grow with us & Embark your bespoke venture journey"], "locations": ["Kwun Tong"], "categories": ["Design", "Graphics"], "post_time": "2022-01-14T10:14:06Z", "salary": {"currency": null, "max": null, "min": null, "period": "monthly", "term": null}, "salary_visible": false, "title_keywords": ["graphic designer"], "responsibilities": ["management", "developing", "design", "testing", "evaluate", "executing", "visual", "report"], "requirements": {"degrees": ["degree"], "majors": ["design"], "languages": ["english", "chinese"], "language_level": ["excellent"], "hard_skills": ["plus", "illustrator", "html", "javascript", "css", "photoshop"], "soft_skills": ["communication skills", "meet deadlines"], "languages_combined": [{"language": "english", "language_level": ["excellent"]}, {"language": "chinese", "language_level": ["excellent"]}]}, "experience_required": {"duration": [], "field": ["designer"]}}, {"job_id": "100003009051021", "location_code": "hk", "company": "Harvey Nichols (Hong Kong) Limited", "job_title": "Graphic / Multimedia Designer", "description": "Responsibilities :\n\n\n\nPrepare drawing packages and details for design projects\nPrepare of 2D/ 3D drawings and familiar with CAD modeling, preferably with\u00a0\u00a0Interior Design project experience\u00a0\nResponsible for site supervision and coordination\nAble to work independently\n\nRequirements:\n\nMinimum 1-2 years' relevant experience / Fresh Graduate also Welcome\u00a0\nResidential project experience preferred\nDiploma in Interior Designer\nGood communication skill\nGood command in AutoCAD, photoshop\u00a0\nAble to work under tight schedule\nImmediate availability is preferred\n\nPlease send full CV with expected salary by clicking \u2018Apply Now\u2019.\n\n\n(Data collected will be used for recruitment purpose only)", "employment_types": ["Full Time", "Permanent"], "selling_points": ["Provide creative direction&execute graphic design", "Excellent in design tools and PC / Mac application", "Min 3 yrs\u2019 experience in online and offline design"], "locations": ["Tsim Sha Tsui"], "categories": ["Design", "Graphics", "Multi-media", "Others"], "post_time": "2022-01-15T01:12:40Z", "salary": {"currency": null, "max": null, "min": null, "period": "monthly", "term": null}, "salary_visible": false, "title_keywords": ["multimedia designer"], "responsibilities": ["coordination", "site supervision", "design", "drawings"], "requirements": {"degrees": ["diploma", "fresh graduate"], "majors": [], "languages": [], "language_level": [], "hard_skills": ["photoshop", "autocad"], "soft_skills": ["communication skill"], "languages_combined": []}, "experience_required": {"duration": ["minimum 1-2 years"], "field": ["relevant experience"]}}, {"job_id": "100003009051362", "location_code": "hk", "company": "Raze Technology Limited", "job_title": "Art Director", "description": "Want to work in a venture studio with boundless opportunities and future-crafting projects? Join Us!\n\nHere we have a cluster of passionate and goal-oriented talents who strive for the acceleration of economies in the decentralized future.\u00a0With extensive business networks, profound market insights and comprehensive capabilities in Digital Assets, Blockchain, Fintech and AI, we\u00a0are inviting you to join our ambitious team to embark your bespoke venture journey and make a real impact with your expertise.\n\nWho will love this job? Someone who:\n\nWants to work on branding and graphics design for the most hyped ventures and products\nIs willing to challenge themselves in a fast-paced environment\nHappy to work in a flexible and dynamic team with strong bonding\nIs not afraid of failure, and love to explore different possibilities\nHas great communication skills, knows how to cooperate with different team members and between different departments\n\nYour responsibilities\n\nHandle brand performance and deal with the branding and design on new product launches\u00a0\nRenovate based on the market trend and consumer insights\u00a0\nCommunicate with internal and external teams to ensure great performance of campaigns, advertisements and joint promotion opportunities and POP development\nConduct business review presentations regularly as well as present our design ideas to our clients\nHelp with our brand management P&L\nJob requirements\nBachelor degree in relevant field such as marketing, design and business related disciplines\nHave experience in branding and graphic design not exclusive to any industries\nKeep track and maintain success in brand building\nProactive, self-motivated and cooperative team player with can-do attitude\nGood at presentation and communication, with design skills and branding sense\nGood command of written and spoken English and Chinese\n\nIf you are interested, please apply at\u00a0https://careers.mindcluster.io\u00a0or email us~", "employment_types": ["Full Time", "Permanent", "Contract", "Freelance"], "selling_points": [], "locations": ["Southern Area"], "categories": ["Media & Advertising", "Creative / Design", "Design", "Graphics", "Multi-media"], "post_time": "2022-01-15T11:12:04Z", "salary": {"currency": null, "max": null, "min": null, "period": "monthly", "term": null}, "salary_visible": false, "title_keywords": ["art director"], "responsibilities": ["communicate with", "management", "consumer insights", "ideas", "advertisements", "review", "teams", "design", "presentations", "p&l"], "requirements": {"degrees": ["degree", "bachelor"], "majors": ["business", "related disciplines", "marketing", "design"], "languages": ["english", "chinese"], "language_level": ["good command"], "hard_skills": ["io"], "soft_skills": ["self-motivated", "can-do attitude", "cooperative", "communication", "team player", "proactive", "presentation"], "languages_combined": [{"language": "english", "language_level": ["good command"]}, {"language": "chinese", "language_level": ["good command"]}]}, "experience_required": {"duration": [], "field": ["graphic design"]}}, {"job_id": "100003009042144", "location_code": "hk", "company": "", "job_title": "Senior Graphic Designer (BR-SGD)", "description": "Responsibilities:\n\nResponsible for design brand materials from online to offline channels e.g. social media, website, leaflet, brochure, posters etc.\nResponsible for photo/video shooting and editing, as well as live streaming, from concept to implementation.\nCreative & independent from design, concept and final output in alignment with the brand strategies\nOther ad hoc assignments and project as required.\n\nRequirements:\n\nDiploma or above in Graphic Design/ Multimedia Design or related discipline.\nMinimum 3 years of solid working experience in commercial design field, experience in F&B industry will be an advantage\nProficient in Adobe Creative Series \u2013\u00a0Photoshop, Illustrator, InDesign, Premier Pro, After Effects etc.\nCreative with passion, willing to work under pressure and tight schedule.\nProactive, responsible and able to work independently.\n\nInterested parties, please click \"Apply Now\" to submit your\u00a0resume (including current and expected salary, availability).\n\nPersonal data collected will be used for recruitment purpose only.", "employment_types": ["Full Time"], "selling_points": ["Multi-purpose graphic design", "Develop creative concepts, layouts and artworks", "6-8 years solid experience in graphic design"], "locations": ["Not Specified"], "categories": ["Design", "Fashion", "Graphics", "Others"], "post_time": "2022-01-12T06:23:11Z", "salary": {"currency": null, "max": null, "min": null, "period": "monthly", "term": null}, "salary_visible": false, "title_keywords": ["senior graphic designer"], "responsibilities": ["social media", "leaflet", "brand strategies", "website", "design", "implementation", "brand materials", "video shooting", "ad hoc assignments", "editing"], "requirements": {"degrees": ["diploma or above"], "majors": ["multimedia design", "graphic design"], "languages": [], "language_level": [], "hard_skills": ["indesign", "illustrator", "after effects", "adobe", "multimedia", "photoshop"], "soft_skills": ["work independently", "proactive", "responsible", "creative", "work under pressure"], "languages_combined": []}, "experience_required": {"duration": ["minimum 3 years"], "field": ["commercial", "f&b", "design"]}}, {"job_id": "100003009046739", "location_code": "hk", "company": "Jollymap", "job_title": "Design and Marketing Assistant (Partime)", "description": "What\u2019s the role about?\n\n\nUnderstand the creative vision of our brands and deliver effective design solutions\nTake responsibility and ably deliver graphic design solutions in advertising layout preparation, POS material development and production, and marketing material development\nEnsure effective visual presentation down into execution at market level with reference to brand image consistency and guidelines provided by our license sources\nAct as the key contact person for all graphic issues across the U.S. head office, our license sources and subsidiaries\nDevelop and maintain a cohesive work relationship with key stakeholders\nMake an impact daily through essential administrative support\n\nWhat we are looking for:\n\nMinimum 4 - 5 years\u2019 work experience in Graphic Design, preferably in Fashion or Fashion Accessories industry\nDiploma holder or above in Graphic Design or related disciplines\nCapability to deliver execution with commercial sense of different markets\nAble to work independently with a can-do attitude to meet multiple project deadlines with quality\nGreat team player, communicate and collaborate effectively with stakeholders cross-functionally and in a multi-cultural work environment\nStrong problem-solving skill with detailed-oriented professional, self-supervising, and able to work under pressure\nProficient in AI or InDesign, Photoshop, and preferably After Effects and XD\nCompetent in Microsoft Excel, Word and PowerPoint\nGood command of spoken and written English and Chinese\n\nTogether, we make great things happen.\n\nApply now and be part of our tomorrow.\n\nInterested parties please send us your full resume with contact details, preferably with your current and expected salary.\n\nFossil Group is an Equal Opportunity employer. All qualified applicants will receive consideration of employment without regard to race, disability, gender, religion, family status, marital status, national origin, sexual orientation, veteran status, gender identity or expression or any other basis protected by local, state, or national law. This policy applies with regard to all aspects of one\u2019s employment, including hiring, transfer, promotion, compensation, eligibility for benefits and termination.\n\nOnly short-listed candidate will be notified. All information received will be kept in strict confidence and only for employment-related purpose.", "employment_types": ["Part Time", "Permanent"], "selling_points": ["Funny working environment", "Exposure full range of ecommerce and social media", "Graphic design and video editing"], "locations": ["Kwun Tong"], "categories": ["Design", "Graphics", "Multi-media", "Marketing / Public Relations", "Digital Marketing"], "post_time": "2022-01-14T00:23:25Z", "salary": {"currency": null, "max": null, "min": null, "period": "hourly", "term": null}, "salary_visible": false, "title_keywords": ["marketing assistant"], "responsibilities": ["collaborate", "supervising", "advertising", "design solutions", "guidelines", "graphic design", "administrative support", "quality", "develop", "maintain", "contact", "visual presentation", "marketing material", "work under pressure"], "requirements": {"degrees": ["diploma holder"], "majors": ["related disciplines", "graphic design"], "languages": ["english", "chinese"], "language_level": ["good command"], "hard_skills": ["pos", "ai", "problem-solving", "indesign", "word", "powerpoint", "microsoft excel", "make", "after effects", "photoshop"], "soft_skills": ["work independently", "can-do attitude", "work under pressure", "competent", "problem-solving", "cohesive", "team player", "creative", "presentation", "detailed"], "languages_combined": [{"language": "english", "language_level": ["good command"]}, {"language": "chinese", "language_level": ["good command"]}]}, "experience_required": {"duration": ["minimum 4 - 5 years"], "field": ["graphic design"]}}, {"job_id": "100003009042123", "location_code": "hk", "company": "Tomato Club Food Limited", "job_title": "Graphic Designer", "description": "Our client, a leading global bank, is looking for a DTP specialist.\n\nKey Responsibilities:\n\u2022 Produces a variety of marketing materials (e.g. covers, templates, newsletters, deal toy designs, invites, posters, flyers, HTML newsletters, etc.) using relevant graphic applications to an advanced level\n\u2022 Traces and produces logos, maps and illustrations\n\u2022 Creates concept and artwork for 2D and 3D tombstones (lucites)\n\u2022 Assists with the production of pitchbook materials and offers conceptual and visual solutions to enhance client materials\n\u2022 Ensures all materials produced are correctly branded as per\u00a0company\u00a0standards and advises clients on the use of the\u00a0company brand\n\u2022 Liaises directly with workflow staff and clients to determine deadlines, job instructions and design requirements\n\u2022 Completes related admin for accurate work billing and job tracking purposes\n\u2022 Assists with Intake coordination when required\n\u2022 Responsible for quality control of own work, as well as assisting colleagues with QC tasks\n\u2022 Buddies new joiners post-training\n\u2022 Contributes to best production practices through internal initiatives and programs\n\nRequirements:\n\u2022 3 years or above of admin/operational support in a corporate, service-oriented environment, ideally in a financial institution\n\u2022 Advanced knowledge of industry standard graphic design applications\u00a0\n\u2022 Advanced knowledge of Adobe Creative Suite (i.e. Illustrator, Photoshop, InDesign, Acrobat Professional)\n\u2022 Advanced knowledge of Microsoft Office (PowerPoint, Excel and Word)\n\u2022\u00a0Knowledge in Dreamweaver and Blender and external print processes is desirable\n\nQualifications:\n\u2022 Bachelor\u2019s degree or Diploma in Graphic Design with 3 years or above of relevant work experience in a corporate, service-oriented environment OR demonstrated ability to meet the job requirements through a comparable work experience\n\u2022 Must be able to provide a portfolio / samples of recent work\n\nInterested parties please email your resume (MS Word format) to\u00a0yan.chan@manpowergrc.hk\u00a0or clicking \"Apply Now\".", "employment_types": ["Full Time"], "selling_points": ["Graphic Designer", "Leaflet design", "photo shooting"], "locations": ["Kwai Hing"], "categories": ["Design", "Graphics", "Industrial / Product", "Multi-media"], "post_time": "2022-01-12T06:18:16Z", "salary": {"currency": null, "max": null, "min": null, "period": "monthly", "term": null}, "salary_visible": false, "title_keywords": ["graphic designer"], "responsibilities": ["design", "coordination", "visual", "marketing materials", "quality control", "tracking"], "requirements": {"degrees": ["diploma", "degree", "bachelor"], "majors": ["graphic design"], "languages": [], "language_level": [], "hard_skills": ["excel", "acrobat", "microsoft office", "indesign", "illustrator", "powerpoint", "word", "dreamweaver", "adobe creative suite", "photoshop"], "soft_skills": ["service-oriented", "creative", "advanced"], "languages_combined": []}, "experience_required": {"duration": ["3 years"], "field": ["graphic design"]}}, {"job_id": "100003009043932", "location_code": "hk", "company": "Fimmick Limited", "job_title": "Senior Graphic Designer / Graphic Designer", "description": "Job Description\n\nDeveloping 2D graphics for products\nSupport the graphic design for social media\nHandle the development of the new project\nRequirements:\n\nMinimum 2-year experience in Graphic Designing\nExperienced in designing licensed product, IP product or animation related product is an advantage\nHave understanding in animation\nGraphic design experience in one of the below areas is an advantage:\nSundries\nDecoration\nSouvenirs\nDIY Items / Toys\nIP products\nElectronic items / Lighting\nSporting items\nPaper & gift items\nKnowledge in video editing and photography is also an advantage\nCreative and innovative, quality work with detail-minded and meet tight deadline\nKnowledgeable in production process from artwork to production is preferred", "employment_types": ["Full Time", "Permanent"], "selling_points": ["Execute top-quality design", "2+ years interactive design experience", "Develop digital storyboards and animation"], "locations": ["Kwun Tong"], "categories": ["Media & Advertising", "Creative / Design", "Design", "Graphics", "Multi-media"], "post_time": "2022-01-13T02:30:11Z", "salary": {"currency": null, "max": null, "min": null, "period": "monthly", "term": null}, "salary_visible": false, "title_keywords": ["senior graphic designer", "graphic designer"], "responsibilities": ["graphics", "graphic design", "social media", "developing"], "requirements": {"degrees": [], "majors": [], "languages": [], "language_level": [], "hard_skills": ["video editing", "ip"], "soft_skills": ["detail-minded", "creative", "meet tight deadline", "innovative"], "languages_combined": []}, "experience_required": {"duration": ["minimum 2-year"], "field": ["graphic design", "graphic"]}}, {"job_id": "100003009049989", "location_code": "hk", "company": "Manpower Services (Hong Kong) Limited", "job_title": "DTP Specialist (27.5K)", "description": "Responsibilities:\n\nDevelop design concept, layouts and material board\nPrepare presentation with concept pictures, drawings and other tools to showcase the design\nLiaise with construction team members, suppliers and contractors\u00a0\nHandle projects with our on-site supervisor, communication with construction team\n\nRequirements:\u00a0\n\nPassion for design, willing to go for extra miles to accomplish the smallest details in your design\nHave your own unique style, have the guts to challenge the status quo / what is trendy / what the customers want\nAble to handle multi-tasks under deadline and lead tasks with different members of the team\nGood command of AutoCAD, Photoshop, 3D Max is an advantage\nDegree or diploma holder in Interior Design or Architecture is great but not a must\nAt least 3-5 years of design experience in residential / commercial field, less experience can be considered as assistant designer\n\nInterested candidates please send us the followings by email or click \"Apply Now'.\n\nFull resume\nPersonal portfolio if any\nPresent / expected salary\nAnything you would like to share with us\n\nWe offer flexible working hours, attractive remuneration package, career advancement, various project opportunities to the right candidate.\n\n(Personal data collected will be used for recruitment purpose only.) Please visit our facebook page for more information: www.facebook.com/bokadesignhk", "employment_types": ["Contract"], "selling_points": ["Marketing materials", "Graphic design", "Banking industry"], "locations": ["Central"], "categories": ["Media & Advertising", "Creative / Design", "Design", "Graphics", "Multi-media"], "post_time": "2022-01-14T09:36:06Z", "salary": {"currency": null, "max": null, "min": null, "period": "monthly", "term": null}, "salary_visible": false, "title_keywords": ["specialist"], "responsibilities": ["design concept", "design", "drawings", "develop", "communication", "liaise with"], "requirements": {"degrees": ["diploma holder", "degree"], "majors": ["architecture", "design"], "languages": [], "language_level": [], "hard_skills": ["max", "go", "photoshop", "autocad"], "soft_skills": ["multi-tasks", "unique", "passion for"], "languages_combined": []}, "experience_required": {"duration": ["at least 3-5 years"], "field": ["commercial", "designer", "design"]}}, {"job_id": "100003009044460", "location_code": "hk", "company": "\u59ff\u66fc\u570b\u969b\u6709\u9650\u516c\u53f8", "job_title": "Graphic Designer / Senior Graphic Designer", "description": "Job Duties & Responsibilities:\n- Strong ability to develop compelling visuals and ideas\n- Responsible for design from concept creative to supervise production\n- Experience on wide range of works, such as event production, printing materials, POSM, etc.\n\nRequirements:\n- Diploma in Graphic Design or Related Discipline\n- Experience in advertising agency/ graphic house is preferred.\u00a0 Fresh graduate will be also considered.\n- With art senses, well organised, mature, highly responsible and independent\n- Willing to complete project under tight deadlines\n-\u00a0Work at holiday and even in overnight is required\n- Proficiency in Photoshop, Illustrator with Mac Experience", "employment_types": ["Full Time", "Permanent"], "selling_points": ["Minimum 2-year experience in Graphic Designing", "Fast growing company with room for creativity", "Handle the development of the new project"], "locations": ["Mong Kok"], "categories": ["Design", "Graphics", "Industrial / Product", "Multi-media"], "post_time": "2022-01-13T04:09:54Z", "salary": {"currency": null, "max": null, "min": null, "period": "monthly", "term": null}, "salary_visible": false, "title_keywords": ["senior graphic designer", "graphic designer"], "responsibilities": ["ideas", "design", "develop"], "requirements": {"degrees": ["diploma", "fresh graduate"], "majors": ["graphic design"], "languages": [], "language_level": [], "hard_skills": ["illustrator", "photoshop"], "soft_skills": ["independent", "responsible", "mature", "organised"], "languages_combined": []}, "experience_required": {"duration": [], "field": ["graphic", "advertising agency"]}}, {"job_id": "100003009053444", "location_code": "hk", "company": "BOKA Design", "job_title": "Interior Designer / Assistant Interior Designer", "description": "Job Description\nJob\u00a0Responsibilities:\n\nAssist Sales and Marketing Team to complete design and drawings according to clients\u2019 requirements\nPrepare 3D design and CAD drawings\nResponsible for handling advertising and graphic related design projects such as catalogs, leaflets and posters\n\nJob\u00a0Requirements:\n\n\nDiploma/ Degree in graphic design, interior design or equivalent\nAt least 1 year or above experience in related fields\nHigh proficiency in AutoCAD, SketchUp and Adobe software (Illustrator, Photoshop and Indesign)\nGraduates/ Students from Architectural/ Graphic Design are welcome to apply\n\nFor details of our group, please visit our website:\u00a0https://www.amk-international.com/\n\nPlease click \"Apply now\"\u00a0to submit your\u00a0RESUME\u00a0with\u00a0EXPECTED SALARY.\n\nPersonal data collected will be used for recruitment purpose only.", "employment_types": ["Full Time", "Permanent"], "selling_points": ["Passion for design, have your own unique style", "Proficiency in AutoCAD, Photoshop, 3D Max", "Develop design concept and presentation"], "locations": ["Kwun Tong"], "categories": ["Building & Construction", "Architectural Services", "Design", "Graphics", "Interior"], "post_time": "2022-01-17T06:59:39Z", "salary": {"currency": null, "max": null, "min": null, "period": "monthly", "term": null}, "salary_visible": false, "title_keywords": ["interior designer", "assistant interior designer"], "responsibilities": ["leaflets", "advertising", "design", "drawings"], "requirements": {"degrees": ["diploma", "degree"], "majors": ["graphic design", "design"], "languages": [], "language_level": [], "hard_skills": ["indesign", "sketchup", "illustrator", "autocad", "adobe software", "photoshop"], "soft_skills": [], "languages_combined": []}, "experience_required": {"duration": ["at least 1 year"], "field": ["related"]}}, {"job_id": "100003009044441", "location_code": "hk", "company": "Oasis Brand Communications Company Limited", "job_title": "Designer", "description": "We are a young marketing agency determined to bring together our expertise and creativity to our counterparts. We believe that every individual's potential can create a huge impact. Being part of Ozaru is more than just a job - it\u2019s an adventure. Interact with various departments across the globe that form the unique Ozaru team. We take chances on technology we believe can have a positive impact on the world by empowering people and have the unique mix of talents which has brought and will continue to bring that idea into life.\n\nAbout The Role\nThis is a full-time role that require drawing skills. We are looking for a 2D Game artist to assist in the development projects.\u00a0\n\n\u00a0What You\u2019ll Do\n\nCreate and edit 2D characters for Game\nShort animation for 2D characters\nProvide art and design support to the sales and marketing team\nAssist in ad hoc tasks assigned by the company\u00a0\n\nWhat You\u2019ll Need\n\nHigher Diploma or Degree holder, preferably in multimedia, design, animation or related discipline\nProficient in\u00a0Photoshop\nFamiliar with Illustrator, After Effect, and Premiere\nGood understanding of\u00a02D character design, good range of artistic sense\nHave to be very humble and willing to learn\u00a0new techniques and styles continuously\nPositive and flexible attitude towards our unconventional workflow\nAmbitious and passionate about our software\n\nPluses\n\nExperience in developing games\nA passion for developing games\nExperience in\u00a0Unity\u00a0engine\u00a0\n\nEmployees First, Company Second --- What We Offer\n\nA competitive remuneration package that includes 5-day work, birthday leave, seasonal incentive bonus.\n\u00a0Unlimited coffee, drinks, snacks and more\nA vibrant and dynamic office environment\nFlexible working hours and a flat hierarchical structure\u00a0\n\nOzaru is committed to a policy of equal employment opportunities and does not discriminate in the terms, conditions, or privileges of employment on account of race, age, color, sex, national origin, physical or mental disability, or religion.\n\n\n\n", "employment_types": ["Full Time"], "selling_points": ["all-rounded design knowledge", "fresh graduate will be considered", "willing to work overnight & holiday"], "locations": ["Kwun Tong"], "categories": ["Media & Advertising", "Creative / Design", "Design", "Graphics", "Others"], "post_time": "2022-01-13T04:04:50Z", "salary": {"currency": null, "max": null, "min": null, "period": "monthly", "term": null}, "salary_visible": false, "title_keywords": ["designer"], "responsibilities": ["software", "ad hoc tasks", "developing", "design", "animation"], "requirements": {"degrees": ["diploma", "degree holder"], "majors": ["animation", "design"], "languages": [], "language_level": [], "hard_skills": ["illustrator", "premiere", "multimedia", "unity", "after effect", "photoshop"], "soft_skills": ["flexible", "passionate about", "determined", "passion for", "willing to learn", "unique", "positive"], "languages_combined": []}, "experience_required": {"duration": [], "field": ["developing"]}}, {"job_id": "100003009047444", "location_code": "hk", "company": "Ozaru Limited", "job_title": "2D Game Artist", "description": "Our\u00a0Client, a\u00a0Chinese\u00a0multinational\u00a0e-commerce, retail, Internet, AI and technology conglomerate, is seeking a\u00a0Mobile App UI Designer to support their team.\n\nJob Responsibilities:\n\nSpecialized in graphic, visual communication with knowledge of marketing\nLiaise with internal parties and initiate brainstorming/creative sessions to translate marketing objectives into compelling creative strategies and solutions\nWork closely and support UED team for ongoing and ad hoc promotion or activities\nResponsible for Mobile Application's Design.\nDevelop and standardized the design template for all creative promotion materials for both online and offline channels including POSM, mobile ad banner, etc.\nResponsible for the maintenance of design materials and inventory\n\nJob Requirements:\n\nNeed to be Hong Kong Resident\nGraphic or Digital Design or other related field\nMore 3 years of working experience in design related field, preferable with\u00a0exposure in mobile/ web product/ advertising industry and design studio company\nStrong creative view and ability to communicate and present ideas in a clear\nHigh level of initiative and ability to work under tight deadlines in a fast-paced, team-oriented environment\nGood command of both English and Chinese and proficiency in Putonghua\nApplicants are required to submit the creative design portfolio\n\nGood to have:\n\nExperience in financial or banking products will be advantages\nExperience in animation / UI will be advantages\nTo apply for this position, please click on \u201cApply Now\u201d bottom.\u00a0 All applications will be treated in strict confidence, and used for recruitment purposes only in accordance with PERSOLKELLY Hong Kong Limited\u2019s Privacy Notice.\u00a0", "employment_types": ["Full Time", "Permanent"], "selling_points": ["Familiar with Illustrator/After Effect/Premier", "Experience in Unity engine", "Create and edit 2D characters for Game"], "locations": ["Tsim Sha Tsui"], "categories": ["Design", "Graphics"], "post_time": "2022-01-14T03:06:50Z", "salary": {"currency": null, "max": null, "min": null, "period": "monthly", "term": null}, "salary_visible": false, "title_keywords": [], "responsibilities": ["ad hoc", "maintenance", "creative promotion materials", "inventory", "design", "develop", "communication", "visual", "liaise with", "internal parties"], "requirements": {"degrees": [], "majors": [], "languages": ["putonghua", "english", "chinese"], "language_level": ["proficiency", "good command"], "hard_skills": ["creative design", "mobile", "web"], "soft_skills": ["clear", "confidence", "creative", "initiative"], "languages_combined": [{"language": "putonghua", "language_level": ["good command"]}, {"language": "english", "language_level": ["proficiency", "good command"]}, {"language": "chinese", "language_level": ["proficiency", "good command"]}]}, "experience_required": {"duration": ["3 years"], "field": ["related", "design", "banking", "advertising industry", "financial"]}}, {"job_id": "100003009048718", "location_code": "hk", "company": "PERSOLKELLY Hong Kong Limited", "job_title": "UI Designer (E-commerce)(Mobile App)", "description": "Benefits:\n\n5 days Work + Bank Holidays\nFull Medical Coverage\nPerformance Bonus\nBirthday Leave, Wedding Leave\nTraining Subsidy\nOvertime Meal and Transportation allowance\nProfessional Training + Good Career Prospect in the Growing Digital Marketing Industry\n\nResponsibilities include:\n\nResponsible for artworks and design for digital marketing including banner display, video, campaign and website;\nInvolve in pitching for new projects;\nWorking with our online marketing team, implement and roll out online marketing strategy with the use of Facebook and other social media platforms.\n\nRequirements :\n\nHigher diploma or above in Graphic/ Multimedia Design or related disciplines;\nPossessing 2 years of working experience in Graphic Design, Advertising or Website Design ; experience in digital marketing agencies is preferred.\nPossessing experience in pitching;\nUnderstanding on branding / art direction is a plus;\nGood team player with effective interpersonal and communication skills;\nAble to work with tight deadlines and under pressure;\nInternet savvy, keen interest in internet marketing and social media.\nCandidate with more experience may be considered for Senior role.\n\nTo Apply:\n\nFor more information about You Find Ltd., please visit www.youfind.hk.\nWe offer attractive package to the right candidate. Interested parties please send your application together with Current Salary, Expected Salary & Availability by clicking \"Apply Now\".\nAll information received will be used for recruitment purpose only and will be kept in strict confidential.\n\nYouFind is an Equal Opportunity Employer and prohibits discrimination and harassment of any kind. All employment decisions at YouFind are based on business needs, job requirements and individual qualifications, without regard to race; family status; gender; disability status or any other status protected by the laws or regulations in Hong Kong.", "employment_types": ["Full Time", "Contract"], "selling_points": ["5 day working", "Competitive salary", "Multinational Corporation"], "locations": ["Causeway Bay"], "categories": ["Design", "Graphics", "Multi-media", "Web Designer"], "post_time": "2022-01-14T07:08:04Z", "salary": {"currency": null, "max": null, "min": null, "period": "monthly", "term": null}, "salary_visible": false, "title_keywords": ["ui designer"], "responsibilities": [], "requirements": {"degrees": [], "majors": [], "languages": [], "language_level": [], "hard_skills": [], "soft_skills": [], "languages_combined": []}, "experience_required": {"duration": [], "field": []}}, {"job_id": "100003009048109", "location_code": "hk", "company": "HKT Consumer Group", "job_title": "Motion Graphic Designer / Animator", "description": "Job Highlights\n\nCertificate/Diploma/Degree holder in Creative Media, Multimedia Design, Motion Graphics or Animation.\nWelcome Fresh Grad in related disciplines.\n\n\u00a0\n\nYour role:\n\nResponsible for the develop creative ideas whole set of video editing, motion graphic, and infographic design for corporate video, animation, and event promo.\nWork closely with the marketing team and design team to facilitate the creative process.\n\u00a0\n\nTo succeed in this role:\n\nGood understanding of Motion graphics & Visual Production, design thinking.\nAdditional knowledge in Graphic design, video filming & editing is preferable.\nRelevant work portfolio is a must.\nKnowledge in Adobe Illustrator, Photoshop, Premiere Pro & After Effect is a must, additional adobe creative cloud-related software\nCreative, passionate, positive-thinking, willing to work under great pressure and tight deadlines", "employment_types": ["Full Time"], "selling_points": [], "locations": ["Quarry Bay"], "categories": ["Design", "Graphics", "Multi-media"], "post_time": "2022-01-14T04:57:02Z", "salary": {"currency": null, "max": null, "min": null, "period": "monthly", "term": null}, "salary_visible": false, "title_keywords": ["animator", "graphic designer"], "responsibilities": ["multimedia design", "software", "animation", "graphic design", "design", "facilitate the creative process", "video editing", "motion graphics", "visual", "editing", "motion graphic", "develop creative ideas"], "requirements": {"degrees": ["certificate", "diploma", "degree holder"], "majors": ["multimedia design", "creative media", "motion graphics", "animation"], "languages": [], "language_level": [], "hard_skills": ["graphics", "adobe illustrator", "video editing", "adobe", "multimedia", "premiere pro", "after effect", "photoshop"], "soft_skills": ["passionate", "creative", "positive", "responsible"], "languages_combined": []}, "experience_required": {"duration": [], "field": []}}, {"job_id": "100003009040170", "location_code": "hk", "company": "Hellotoby Technology (HK) Limited", "job_title": "Graphic Designer (Part Time)", "description": "Job Description\n\nImprove and be the gate keeper of print production quality for all our brands.\nSet standards, Implement state of the art tools, processes, best practices and due diligence compliance check list.\nArrange print testing, briefing supplier for print test, and keep log and record\nReview and approve print tests, color proofs and samples and manage related process, budget and timeline.\nCoordinate with artwork / designer with correct AI file to proceed print test\nCommunicate with supplier pass/failure/improvement of print test\nManager supplier to deliver print proof as per schedule\nOrganise, supervise and monitor quality production of all printed materials, from prototype to mass production.\nUnderstand the project and design\u2019s vision, needs and requirements to provide the advice and print solutions, techniques, vendors, effects to designers to achieve what the desired outcome.\nEvaluate and negociate costs and manage timelines, to ensure quality service is provided to the other teams.\nReview output files\nSource, select and recommend appropriate materials, techniques, factories.\nControl and approve mass-production on site if necessary.\nInvestigate vendors and new print technologies, develop our vendor network.\nCoordinate with factories and maintain relationships, evaluate suppliers.\nConduct project post-mortem evaluations with the stakeholders, recap issues faced and propose solutions for improvement.\n\nRequirements\n\nExpert in printing\n6-8 years in printing (packaging a plus) from small volumes to mass production\nFamiliar and eager about the latest color and quality monitoring tools and technology\nFamiliar with high end packaging and its standards\nKnowledge in softwares: Asana, MsTeams, Adobe Creative Suite is an advantage\nFluent Cantonese / English / Mandarin", "employment_types": ["Part Time"], "selling_points": ["Graphic design and build design assets", "Develop unique brand system, highly readable story", "Photoshop, Illustrator and InDesign"], "locations": ["Sheung Wan"], "categories": ["Design", "Graphics"], "post_time": "2022-01-12T01:57:57Z", "salary": {"currency": null, "max": null, "min": null, "period": "monthly", "term": null}, "salary_visible": false, "title_keywords": ["graphic designer"], "responsibilities": ["communicate with", "due diligence", "control", "maintain relationships", "review", "compliance", "quality", "budget", "testing", "coordinate with", "monitor", "design", "evaluate", "teams", "schedule", "develop", "costs"], "requirements": {"degrees": [], "majors": [], "languages": ["cantonese", "english", "mandarin"], "language_level": ["fluent"], "hard_skills": ["small", "plus", "adobe creative suite"], "soft_skills": ["creative"], "languages_combined": [{"language": "cantonese", "language_level": ["fluent"]}, {"language": "english", "language_level": ["fluent"]}, {"language": "mandarin", "language_level": ["fluent"]}]}, "experience_required": {"duration": [], "field": []}}, {"job_id": "100003009044456", "location_code": "hk", "company": "GP Acoustics International Limited", "job_title": "Print Production Specialist", "description": "Responsibilities:\n\nWork for marketing team to initiate creative concepts and maintain brand consistency across all channels\nExecute full spectrum of multimedia design, including but not limited to photo shooting and retouching, video editing and production, as well as graphic design for website, social media (FB, IG, LinkedIn, WeChat etc.), e-mail marketing and printed materials\nLayout design and artwork production of marketing materials to support brand/promotion campaigns\nContent development and post design for social media platform\nPerform ad-hoc tasks as assigned\n\n\u00a0Requirements:\n\nDegree or diploma in Multimedia / Graphic Design / Creative Media or related disciplines\nMinimum of 6-8 years\u2019 relevant working experience in creative agency / digital marketing/ in-house marketing team\nProficient in Adobe Creative Suite, including Premiere Pro, After Effects, Animate, Illustrator, InDesign and Photoshop\nSkilled in various social media platforms (e.g. Facebook, Instagram, LinkedIn, WeChat)\nExperienced in video production, motion graphic and photography\nAn excellent team player with good communication skills and the ability to multitask\nCreative and pro-active, responsible, well-organized, detail-oriented with a strong sense of responsibility and team work\nKnowledge in HTML5, CSS, Action script is a plus\nExperience in copywriting/editing in English & Chinese is a plus\nWe offer an attractive remuneration package and excellent career prospects to the right candidate. Please send full resume including the current, expected salary, the portfolio with video works, photography, design layouts and finished marketing materials\u00a0and the contact information by clicking \"Apply Now\"\n\n\n\n(The personal data provided will be used for recruitment purpose only. \u00a0All data of unsuccessful applications will be destroyed.)", "employment_types": ["Full Time", "Permanent"], "selling_points": ["Science Park", "6-8 years in printing (packaging a plus)", "5 days works and flexible working hour"], "locations": ["Shatin Area"], "categories": ["Design", "Graphics", "Manufacturing", "Manufacturing Management", "Printing"], "post_time": "2022-01-13T04:09:14Z", "salary": {"currency": null, "max": null, "min": null, "period": "monthly", "term": null}, "salary_visible": false, "title_keywords": ["specialist"], "responsibilities": ["multimedia design", "retouching", "social media", "graphic design", "artwork production", "layout design", "ad-hoc tasks", "website", "design", "video editing", "maintain", "promotion campaigns", "marketing materials", "brand consistency"], "requirements": {"degrees": ["diploma", "degree"], "majors": ["related disciplines", "graphic design", "creative media"], "languages": ["english", "chinese"], "language_level": [], "hard_skills": ["plus", "animate", "css", "indesign", "illustrator", "wechat", "after effects", "premiere pro", "multimedia", "facebook", "adobe creative suite", "photoshop"], "soft_skills": ["communication skills", "responsible", "sense of responsibility", "well-organized", "detail-oriented", "team player", "pro-active", "ability to multitask", "creative"], "languages_combined": [{"language": "english", "language_level": []}, {"language": "chinese", "language_level": []}]}, "experience_required": {"duration": ["minimum of 6-8 years"], "field": ["agency", "relevant working experience", "marketing", "digital marketing", "copywriting", "editing", "team"]}}, {"job_id": "100003009045705", "location_code": "hk", "company": "Humansa", "job_title": "Multimedia Designer", "description": "We look for true TALENTS and outstanding personalities!\n\nJoin our team as\n\nProduct & Graphic Designer\n\n\u00a0Job Location\n\n\nTsim Sha Tsui East, Kowloon, Hong Kong\n\nLanguages\u00a0\nMinimum oral and written proficiency in English, other languages are welcome\n\nEducation\u00a0 \u00a0\nTertiary or Diploma level in Graphic & Packaging / Product Design and or Design for consumer goods.\u00a0\nExperienced in working with international companies.\n\n\nMost important Requirements\nAT LEAST 2 YEARS OF EXPEREINCE IN SIMILAR POSITION;\n\nCREATIVE-OUTSIDE OF THE BOX THINKING PERSONALITY;\nKNOWLEDGE OF 3D SOFTWARE AND 3D PRINTING SYSTEMS (SLA);\n\nCAPABLE TO FULLY USE:\u00a0RHINO, KEYSHOT, PHOTOSHOP, ILLUSTRATOR, INDESIGN, POWERPOINT;\n\nCAPABLE FOR FREE HAND DESIGN;\n\nCAPABLE TO IN-CHARGE OFFICE SHOWROOM & INTERNATIONAL FAIRS;\n\nCAPABLE TO INDEPENDENTLY WORK UNDER PRESSURE;\n\nCAPABLE TO EXECUTE IN A FAST-PACED PROFESSIONAL ENVIRONMENT TO REDUCE ANY ALARMING DEADLINES.\n\nWe offer \u2026true challenges and for sure you will\u2026\u00a0\nMAKE CONCEPT PRESENTATIONS IN MULTI MEDIA FORMAT AND/OR POWERPOINT CREATE GREAT PACKAGING AND GRAPHICS;\n\nHELP TO DEVELOP NEW PRODUCTS TOGETHER WITH A PROFESSIONAL TEAM YOU WILL MAKE PROTOTYPES (3D PRINTING AND MODELLING).\u00a0\n\n*WE CAN ALSO OFFER APPLICATION ON HK WORKING VISA FOR APPROPRIATE CANDIDATE*\n\n\nAvailability: Negotiable\n\n\nSalary: Fair and based on the experience and the qualification\n\n\nPlease send full resume and\u00a0DESIGN PORTFOLIO\u00a0with the above reference quoted via email indicating current and expected salary and visit our homepage.\n\nwww.joker-group.net\n\n*APPLICATION WITHOUT PROPER PORTFOLIO INCLUDED WILL NOT BE CONSIDERED*\n\n\nPersonal data collected will be used for recruitment purpose only.", "employment_types": ["Full Time", "Permanent"], "selling_points": ["Solid 6-8 years of experience in multimedia", "Creative with good art sense", "Experience in copywriting/editing is a plus"], "locations": ["Lai Chi Kok"], "categories": ["Design", "Graphics", "Multi-media", "Marketing / Public Relations", "Public Relations - Copy-writing"], "post_time": "2022-01-13T08:24:22Z", "salary": {"currency": null, "max": null, "min": null, "period": "monthly", "term": null}, "salary_visible": false, "title_keywords": ["multimedia designer"], "responsibilities": [], "requirements": {"degrees": [], "majors": [], "languages": [], "language_level": [], "hard_skills": [], "soft_skills": [], "languages_combined": []}, "experience_required": {"duration": [], "field": []}}, {"job_id": "100003009044106", "location_code": "hk", "company": "JOKER (FAR EAST) LTD.", "job_title": "Product & Graphic Designer (Ref. PGD_Jan2022)", "description": "Responsibilities:\n\nManagement of around 10,000 design and packaging orders\n\nLeading and managing a team of 14 graphic Designers\u00a0\n\nQuality assurance and improvement of packaging design\u00a0\n\nOrganize photo shoots including sample handling\u00a0\n\nCoordination of brand concepts\u00a0\u00a0\n\nDirect communication with German Headquarter\n\nCoordination of Artwork Team\u00a0and administration related tasks\u00a0(Packaging Design\u00a0Non-Food)\n\n\nRequirements:\n\nPeople management experience\u00a0\nExperience in Brand strategy\u00a0\u00a0\nDesign background recommended but not mandatory\nExcellent communication skills, ability to engage and communicate effectively across different departments\u00a0\nExcellent organizational skills and detail oriented\nStrong time management skills, able to work with tight deadlines\nStrong leadership skills\u00a0\nFluent in German and English\nInterested applicants please send your English application letter and resume with expected salary \u00a0by clicking \"Apply Now\".\n\n\nAll information received will be kept in strict confidential and only for employment related purpose.", "employment_types": ["Full Time", "Permanent"], "selling_points": [], "locations": ["Tsim Sha Tsui"], "categories": ["Design", "Graphics", "Industrial / Product", "Manufacturing", "Others"], "post_time": "2022-01-13T03:04:51Z", "salary": {"currency": null, "max": null, "min": null, "period": "monthly", "term": null}, "salary_visible": false, "title_keywords": ["graphic designer"], "responsibilities": ["management", "packaging design", "quality", "design", "communication", "coordination", "managing a team", "administration"], "requirements": {"degrees": [], "majors": [], "languages": ["german", "english"], "language_level": ["fluent"], "hard_skills": [], "soft_skills": ["communication skills", "organizational skills", "time management skills", "detail oriented", "leadership skills"], "languages_combined": [{"language": "german", "language_level": ["fluent"]}, {"language": "english", "language_level": ["fluent"]}]}, "experience_required": {"duration": [], "field": ["people management", "brand"]}}, {"job_id": "100003009039364", "location_code": "hk", "company": "AllRightsReserved Limited", "job_title": "Graphic Designer", "description": "Job Description\n\n- Certificate / Diploma in Multimedia Design with 1-2 year multimedia experience\n\n- Proficiency in Photoshop, Illustrator, After Effects, MAYA, 3DMax & AutoCAD\n\n- To handle multimedia projects [text, sound, images, 3D-modelling, animation & rendering]\n\n- Creative, strong sense in multimedia design, self-motivated and self-disciplined", "employment_types": ["Full Time"], "selling_points": [], "locations": ["Wan Chai"], "categories": ["Design", "Graphics"], "post_time": "2022-01-11T09:30:27Z", "salary": {"currency": null, "max": null, "min": null, "period": "monthly", "term": null}, "salary_visible": false, "title_keywords": ["graphic designer"], "responsibilities": ["multimedia design", "animation"], "requirements": {"degrees": ["certificate", "diploma"], "majors": ["multimedia design"], "languages": [], "language_level": [], "hard_skills": ["maya", "illustrator", "after effects", "autocad", "3dmax", "multimedia", "photoshop"], "soft_skills": ["self-motivated", "creative"], "languages_combined": []}, "experience_required": {"duration": ["1-2 year"], "field": ["design"]}}, {"job_id": "100003009051227", "location_code": "hk", "company": "Easy Job Centre", "job_title": "Fashion Design / Senior Fashion Designer", "description": "Responsibilities\n\nResponsible for conceptualising and visualising products/advertising/event ideas\nHandle projects independently from concept to final production\nPerform ad hoc tasks as assigned\n\nRequirement\n\nMinimum 3-5 years relevant experience\nProficiency in Mac Adobe design software is a must\nGreat team player, self-supervising and able to work under pressure\nHighly creative with a strong sense of aesthetics and design as well as being detailed-oriented\nGood time management and work efficiency with quality\nGreat communication skills and positive attitude\nPortfolio of work\n\nWe offer attractive remuneration package including 5 days work, performance bonus and medical scheme to the right candidate.\n\n\u00a0", "employment_types": ["Full Time"], "selling_points": [], "locations": ["Yau Tsim Mong Area"], "categories": ["Design", "Fashion", "Graphics", "Others"], "post_time": "2022-01-15T05:19:57Z", "salary": {"currency": null, "max": null, "min": null, "period": "monthly", "term": null}, "salary_visible": false, "title_keywords": ["fashion designer"], "responsibilities": ["ad hoc tasks", "advertising", "ideas"], "requirements": {"degrees": [], "majors": [], "languages": [], "language_level": [], "hard_skills": ["adobe"], "soft_skills": ["communication skills", "creative", "work under pressure", "positive attitude", "team player", "time management", "detailed"], "languages_combined": []}, "experience_required": {"duration": ["minimum 3-5 years"], "field": ["relevant experience"]}}, {"job_id": "100003009044305", "location_code": "hk", "company": "Wong Tung & Partners Ltd", "job_title": "GRAPHIC DESIGNER", "description": "1 Post for Intimate\n1 Post for Woven / Knit / Sweater\n1 Post for Ladies\n1 Post for Men's\n1 Post for Sportswear\n\nResponsibilities\n\n\nResponsible for design and development of apparel items\nProvide directions and ideas on all design issues including costing, fashion trend research on colors, fabrication and accessories, etc.\nFollow up the entire workflow of the development from themes and concept, presentation of styling, sketches, fitting session and sampling\nCoordinate and work closely with Buyers, Merchandisers and other related parties\n\nRequirements\n\nDegree or Diploma holder in Fashion Design or related discipline\nMinimum 2-6 years of fashion design experience\nStrong awareness of market needs and fashion trend\nStrong creativity with good fashion color sense and knowledge of seasonal trends, themes, color, materials, styling and fit\nSelf-motivated, energetic, creative, with good design sense and with the ability to work independently\nProficiency in Photoshop, Illustrator, InDesign, after effect\nExcellent command in both spoken and written English and Chinese including Mandarin\n\nInterested parties, please send your resume with expected salary to \"apply now\". You can also click on the website www.easyjobhk.com for more details about the company", "employment_types": ["Full Time"], "selling_points": ["Graphic Designer", "1 years of graphic design experience", "Responsible for hotel and residential projects"], "locations": ["Tai Koo"], "categories": ["Building & Construction", "Architectural Services", "Design", "Graphics"], "post_time": "2022-01-13T03:43:00Z", "salary": {"currency": null, "max": null, "min": null, "period": "monthly", "term": null}, "salary_visible": false, "title_keywords": ["graphic designer"], "responsibilities": ["coordinate", "ideas", "sketches", "design"], "requirements": {"degrees": ["diploma holder", "degree"], "majors": ["design"], "languages": ["english", "chinese", "mandarin"], "language_level": ["excellent"], "hard_skills": ["after effect", "indesign", "illustrator", "photoshop"], "soft_skills": ["self-motivated", "energetic", "creative", "work independently"], "languages_combined": [{"language": "english", "language_level": ["excellent"]}, {"language": "chinese", "language_level": ["excellent"]}, {"language": "mandarin", "language_level": ["excellent"]}]}, "experience_required": {"duration": ["minimum 2-6 years"], "field": ["fashion design"]}}, {"job_id": "100003009037154", "location_code": "hk", "company": "Wondersky Online Limited", "job_title": "Graphic Designer (Full Time or Part Time)", "description": "Diploma holder or above in Graphic Design\nProficiency at Adobe InDesign, Photoshop and Illustrator\nKnowledge of web page design / After Effects / \u00a0Microsoft Word is in advantage\nThe ability to create graphic designs and layouts for architectural presentation, brochure and various design projects\nResponsible, self-motivated and good time management to meet tight deadline and be good team player\nFluent in Chinese and English\n\nWe offer competitive remuneration package to the right candidate. Interested parties, please send your application with career details, qualification, current and expected salary via \"Apply Now\" OR by mail to: Human Resources Department, Wong Tung & Partners Limited, 18th Floor, Cityplaza 3, Taikoo Shing, Hong Kong.", "employment_types": ["Full Time", "Permanent"], "selling_points": [], "locations": ["Sheung Wan"], "categories": ["Design", "Graphics", "Multi-media", "Web Designer"], "post_time": "2022-01-11T01:56:48Z", "salary": {"currency": null, "max": null, "min": null, "period": "monthly", "term": null}, "salary_visible": false, "title_keywords": ["graphic designer"], "responsibilities": ["graphic design", "management", "graphic designs", "design"], "requirements": {"degrees": ["diploma holder"], "majors": ["graphic design"], "languages": ["english", "chinese"], "language_level": ["fluent"], "hard_skills": ["microsoft word", "web", "adobe indesign", "illustrator", "after effects", "photoshop"], "soft_skills": ["self-motivated", "good team player", "responsible", "meet tight deadline", "time management", "presentation"], "languages_combined": [{"language": "english", "language_level": ["fluent"]}, {"language": "chinese", "language_level": ["fluent"]}]}, "experience_required": {"duration": [], "field": []}}, {"job_id": "100003009040314", "location_code": "hk", "company": "A-1 Bakery Co., (HK) Limited", "job_title": "Senior Graphic Designer / Graphic Designer", "description": "\u517c\u8077\u9867\u5ba2\u670d\u52d9\u54e1Part Time Customer Service Representative (\u89c0\u5858\uff0c\u534a\u65e5)\n\n\n\n\u516c\u53f8\u7c21\u4ecb\nJollymap\u5f9e\u6559\u6388\u8ab2\u7a0b\u5230\u5f9e\u4e8b\u92b7\u552e\u55ae\u8eca\u3001\u5e73\u8861\u8eca\u3001\u6ed1\u677f\u8eca\u5230\u53ca\u4fdd\u8b77\u88dd\u5099\uff0c\u6211\u5011\u53ea\u6709\u4e00\u500b\u4f7f\u547d\uff0c\u5c31\u662f\u300c\u4e00\u8d77\u63a2\u904a\u6210\u5c31\u5feb\u6a02\u7ae5\u5e74!\u300d\u73fe\u6642\u901a\u904e\u4f54\u5730\u8d85\u904e1\u842c\u5c3a\u7684\u5169\u9593\u9580\u5e02\u53ca\u6559\u5b78\u4e2d\u5fc3\uff0c\u5df2\u670d\u52d9\u8d853\u842c\u4f4d\u5c0f\u670b\u53cb\u3002Jollymap\u88abInside Retail Asia\u9078\u70ba2017\u5e74\u6700\u5275\u65b0\u96f6\u552e\u696d\u8005\u4e4b\u4e00\uff0c\u73fe\u5728\u6b63\u62db\u52df\u5fd7\u540c\u9053\u5408\u7684\u4eba\u52a0\u5165\u6211\u5011\u7684\u5927\u5bb6\u5ead\u3002\u4f60\u5f97\u5230\u7684\uff0c\u4e0d\u55ae\u53ea\u662f\u85aa\u916c\uff0c\u4e5f\u662f\u770b\u8457\u4e00\u5f35\u5f35\u7b11\u81c9\u7684\u90a3\u4efd\u6210\u529f\u611f\u3002\n\n\u516c\u53f8\u596c\u9805\u53ca\u8cc7\u683c\nTop 50 Most innovative Retailer in Hong Kong 2017 (Inside Retail Asia)\n\u5546\u754c\u5c55\u95dc\u61f7\u4f01\u696d (Caring Company) 2017-2021\n\u9999\u6e2f\u96f6\u552e\u696d\u5354\u6703\u6703\u54e1\n\nwww.jollymap.com\n\n\nResponsibilities:\n\nOperations and Marketing support of e-shop and physical stores and training center\nPhoto and video taking and editing\nBasic graphic design (use Canva or AI)\nExposure and assist in full range of online marketing such as SEO, SEM, social media (Facebook, YouTube &IG) , email marketing and content marketing.\nParticipate in event and activities management\nHandle administrative task and ad hoc projects.\n\nRequirements:\n\nOutgoing personality and love outdoor activities like cycling or camping\nDesign / Media or related academic disciplines\nPassionate in e-Commerce and Online Marketing. Related experience will an advantage but not necessary\nKnowledge of graphic design, Photo editing, video editing and HTML will be an advantage\nGood follow-through, organized and proactive working attitudes\nGood command of both spoken and written English & Chinese\nWork around 8 hours per day, 2-3 days a week and may need to work on Weekend occasionally (4-5 days work during summer period)\nHourly Rate starting from $60\n\nPlease email your resume to us.\u00a0Any questions welcome to call us at 23420780.", "employment_types": ["Full Time", "Permanent"], "selling_points": ["4 years food packaging design working experience", "5 days Work", "Photograph products and edit video"], "locations": ["Shatin Area"], "categories": ["Design", "Graphics", "Industrial / Product", "Hospitality / F & B", "Food & Beverage"], "post_time": "2022-01-12T02:16:28Z", "salary": {"currency": null, "max": null, "min": null, "period": "monthly", "term": null}, "salary_visible": false, "title_keywords": ["senior graphic designer", "graphic designer"], "responsibilities": ["social media", "management", "seo", "e-shop", "operations", "graphic design", "ad hoc projects", "sem", "facebook", "editing"], "requirements": {"degrees": [], "majors": [], "languages": ["english", "chinese"], "language_level": ["good command"], "hard_skills": ["video editing", "html", "e-commerce"], "soft_skills": ["outgoing personality", "organized", "passionate", "proactive"], "languages_combined": [{"language": "english", "language_level": ["good command"]}, {"language": "chinese", "language_level": ["good command"]}]}, "experience_required": {"duration": [], "field": ["related"]}}, {"job_id": "100003009044025", "location_code": "hk", "company": "I.T Apparels Limited", "job_title": "Assistant Visual Merchandiser (REF: JDB-IT-AVM)", "description": "Responsibilities:\nSocial media management including content development & consumer engagement\nCommunicate and extent good relationships with on-line media, KOL, vendors & platform partners\nAnalyze market trends and explore new marketing techniques & business opportunities\nParticipate and support internal teams for different marketing campaign and operation needs\nPrepare marketing proposal for client\nPrepare regular reports for management review\nParticipate & support in all new business initiatives and all ad hoc projects\nGood content writer\nStrong Creative Designer is much preferred\n\nRequirements:\n\nDegree holder in Marketing / Communication / Multi-media Design preferred\nMin. 2 years\u2019 experienced in marketing\nExcellent interpersonal, presentation and communication skills\nProficient in MS Word, Excel, PowerPoint and Chinese Word Processing\nFluency in written and spoken Chinese and English\nExperience in CMS (Wordpress) ,graphic design tools (Adobe Photoshop and Adobe Illustrator)\nDetail-minded, tech-savvy, outgoing, and flexible to work\nHard-working, willing to learn and able to handle multi-task, work under pressure and meet deadlines\nCandidate with more experienced will be considered as Senior Marketing Executive", "employment_types": ["Full Time"], "selling_points": ["Visual Merchandising", "Promotional Displays", "1-2 years of Visual Merchandising experience"], "locations": ["Not Specified"], "categories": ["Design", "Fashion", "Graphics", "Visual Merchandising"], "post_time": "2022-01-13T02:49:39Z", "salary": {"currency": null, "max": null, "min": null, "period": "monthly", "term": null}, "salary_visible": false, "title_keywords": ["assistant visual merchandiser"], "responsibilities": ["social media", "management", "business initiatives", "business opportunities", "review", "teams", "regular reports for management", "ad hoc projects"], "requirements": {"degrees": ["degree holder"], "majors": ["marketing", "design"], "languages": ["english", "chinese"], "language_level": ["fluency", "proficient"], "hard_skills": ["excel", "chinese word processing", "adobe photoshop", "powerpoint", "adobe illustrator", "wordpress", "ms word"], "soft_skills": ["detail-minded", "communication skills", "outgoing", "flexible", "multi-task", "willing to learn", "communication", "hard-working", "meet deadlines", "interpersonal", "presentation", "work under pressure"], "languages_combined": [{"language": "english", "language_level": ["fluency"]}, {"language": "chinese", "language_level": ["fluency", "proficient"]}]}, "experience_required": {"duration": [], "field": ["graphic design"]}}, {"job_id": "100003009048927", "location_code": "hk", "company": "Eagle Sky Media Limited", "job_title": "Digital Marketing Officer (Advertising Agency , Digital Marketing, Social media)", "description": "Provide creative product and graphic designs\nResponsible for the product design including market research, trend analysis, design drawing, prototype development, material sourcing, sample inspection, product photo, artwork output, etc.\nWork closely with internal teams, suppliers and customers to deliver the best products for different markets\nComplete routine and special tasks as assigned by superiors\nHandle ad-hoc assignments from management\n\nRequirements\n\nDiploma or above in product design related discipline\nAt least 3 years working experience in product and packaging design\nPositive working attitude, self-motivated, responsible, good communication skill and a good team player, strong in problem solving\nProactive working attitude, mature, independent, details-oriented and self-motivated\nResult-oriented, able to work independently and under pressure\nFluency in both written and spoken English, Chinese and Mandarin\n\n\u00a0Benefits\n\nPerformance bonus\n14 days annual leave\nBank holidays", "employment_types": ["Full Time", "Permanent"], "selling_points": ["Socail media management", "Advertising Agency", "designer"], "locations": ["Tsuen Wan Area"], "categories": ["Media & Advertising", "Creative / Design", "Design", "Graphics", "Marketing / Public Relations", "Public Relations - Copy-writing"], "post_time": "2022-01-14T07:43:38Z", "salary": {"currency": null, "max": null, "min": null, "period": "monthly", "term": null}, "salary_visible": false, "title_keywords": ["digital marketing officer", "digital marketing"], "responsibilities": ["management", "packaging design", "ad-hoc assignments", "analysis", "graphic designs", "market research", "design", "inspection", "teams", "communication", "product design", "artwork output"], "requirements": {"degrees": ["diploma or above"], "majors": ["design"], "languages": ["english", "chinese", "mandarin"], "language_level": ["fluency"], "hard_skills": ["problem solving", "analysis"], "soft_skills": ["self-motivated", "good team player", "proactive", "independent", "responsible", "work independently", "under pressure", "communication skill", "mature", "problem solving", "positive working attitude", "creative", "result-oriented"], "languages_combined": [{"language": "english", "language_level": ["fluency"]}, {"language": "chinese", "language_level": ["fluency"]}, {"language": "mandarin", "language_level": ["fluency"]}]}, "experience_required": {"duration": ["at least 3 years"], "field": ["packaging design"]}}, {"job_id": "100003009041980", "location_code": "hk", "company": "TV Products (HK) Limited", "job_title": "Product and Graphic Designer", "description": "\nResponsibilities:\n\u2022 Drive consumers and competitor analysis to identify business opportunities\n\u2022 Drive market research to identify colour and material trends\n\u2022 Lead bags and accessories design projects from start to finish collaborating closely with management\n\u2022 Organize and communicate the design concept using mood boards\n\u2022 Prepare technical spec packs : line drawings, materials, colours and construction for prototyping\n\u2022 Oversee the full product cycle from concept to design, product development, production and market launch\n\u2022 Communicate and collaborate with cross-functional teams to bridge design specifications and production viability\n\u2022 Work closely with production team to comment on prototypes and track development progress\n\nRequirements:\n\u2022 University degree / high diploma in Fashion Design or related field.\n\u2022 At least 5 years of credible experience in bags and fashion accessories design.\n\u2022 Possess knowledge on bags and accessories market, design trends, brand identity, target customer and competitive landscape. Strong understanding of the importance of commercial value of designs.\n\u2022 Proficient in Illustrator, Photoshop and Adobe packages.\nHighly self-motivated and proactive with excellent written and verbal communication skills (English & Chinese).\n\u2022 Creative, attentive and detail minded\n\nWe offer competitive salary & benefit package. Ready to join the team? Please email us your resume and work examples.\n\n", "employment_types": ["Full Time", "Permanent"], "selling_points": ["Performance bonus", "Work location in TST", "Immediate available is preferred"], "locations": ["Tsim Sha Tsui"], "categories": ["Design", "Graphics"], "post_time": "2022-01-12T04:59:53Z", "salary": {"currency": null, "max": null, "min": null, "period": "monthly", "term": null}, "salary_visible": false, "title_keywords": ["graphic designer"], "responsibilities": ["collaborate with", "management", "identify business opportunities", "design concept", "analysis", "market research", "design", "drawings", "design specifications", "cross-functional teams"], "requirements": {"degrees": ["high diploma", "university degree"], "majors": ["design"], "languages": ["english", "chinese"], "language_level": ["excellent"], "hard_skills": ["adobe", "illustrator", "photoshop"], "soft_skills": ["attentive", "communication skills", "self-motivated", "creative", "proactive"], "languages_combined": [{"language": "english", "language_level": ["excellent"]}, {"language": "chinese", "language_level": ["excellent"]}]}, "experience_required": {"duration": ["at least 5 years"], "field": ["design"]}}, {"job_id": "100003009045200", "location_code": "hk", "company": "\u701f\u96f2\u96c6\u5718\u6709\u9650\u516c\u53f8", "job_title": "Senior Product Designer", "description": "Job description\n\nHandle day to day graphics design and production for advertising, marketing, social media content and EDM editing;\nResponsible for web design on banners, layout, graphics, and user interface;\nPost-processing photography image, models, product, etc.;\nHandle other digital and print design duties as assigned;\n\nQualification\n\nDiploma or above in multimedia or graphic design;\n1-2 year working experience or above in graphic design/ web design/ advertising (experience in online or fashion industry is a plus);\nProficiency in In Adobe Creative Suite (Photoshop, Illustrator) etc.;\nDetail-minded and creative;\nAbility to understand and handle tasks independently\u00a0;\n\nBenefits:\n\n5-day work week\nMedical insurance & dental care\nPublic Holiday\n12 \u2013 17 days paid Annual Leave\n5 days Marriage Leave\nBirthday Leave\nStaff purchase discount\n\nInterested parties, please press \"Apply Now\".\n(Data collected will be used as recruitment related purpose only.)", "employment_types": ["Full Time"], "selling_points": [], "locations": ["Not Specified"], "categories": ["Design", "Graphics", "Interior", "Others"], "post_time": "2022-01-13T07:25:34Z", "salary": {"currency": null, "max": null, "min": null, "period": "monthly", "term": null}, "salary_visible": false, "title_keywords": ["senior product designer"], "responsibilities": ["graphics", "advertising", "edm", "graphic design", "design", "banners", "user interface", "social media content", "editing"], "requirements": {"degrees": ["diploma or above"], "majors": ["graphic design"], "languages": [], "language_level": [], "hard_skills": ["graphics", "web design", "plus", "illustrator", "multimedia", "processing", "adobe creative suite", "photoshop"], "soft_skills": ["detail-minded", "creative", "responsible", "independently"], "languages_combined": []}, "experience_required": {"duration": ["1-2 year"], "field": ["graphic design", "advertising", "design"]}}, {"job_id": "100003009038836", "location_code": "hk", "company": "Rue Madame Retail Limited", "job_title": "Graphic Designer", "description": "Duties:\n\nResponsible for\u00a0game graphic design including characters(\u7537\u6027\u5411\u4e8c\u6b21\u5143), items, user interface and effects\nParticipation in concept development and innovation for our games\nWork closely with art lead, game designers and programmers\n\nRequirement:\n\nDiploma or above in Media Art / Design or related disciplines\nGood skill of drawing, illustration, colors, lighting and composition\nStrong sense of game character design\nProficient in Photoshop\n1-5 years game design experience\nWith great passion for games development\nGood team player with mature working attitude\n\nBenefits:\n\n\n5-day work\nPaid birthday leave\nBirthday pocket money\nPerformance bonus\nMedical insurance\nDental subsidy\nFree snack and beverage\nFriendly working environment\n\nInterested parties please apply with the following details:\n\nResume\nExpected Salary\nEarliest Availability\nPortfolio", "employment_types": ["Full Time", "Permanent"], "selling_points": ["Flexible working hours", "Young and energetic environment", "Open-minded and creative culture"], "locations": ["Sheung Wan"], "categories": ["Design", "Graphics"], "post_time": "2022-01-11T07:56:11Z", "salary": {"currency": null, "max": null, "min": null, "period": "monthly", "term": null}, "salary_visible": false, "title_keywords": ["graphic designer"], "responsibilities": ["graphic design", "user interface"], "requirements": {"degrees": ["diploma or above"], "majors": ["related disciplines", "art", "design"], "languages": [], "language_level": [], "hard_skills": ["illustration", "photoshop"], "soft_skills": ["good team player", "mature", "passion for"], "languages_combined": []}, "experience_required": {"duration": ["1-5 years"], "field": ["design"]}}, {"job_id": "100003009045897", "location_code": "hk", "company": "Qookia Limited", "job_title": "Junior / Senior 2D Game Artist - \u904a\u6232\u539f\u756b\u8a2d\u8a08\u5e2b", "description": "We are hiring!\nCome to join our team of professionals passionate to games!\n\nWhat you will be doing:\n\nAssist on creative development and layout adaptation\nHandle day to day graphics design and production for advertising, social media content, and website\nResearch and consolidate insight of new games/ apps, best practices of design and advertising across the market\nGenerate ideas and create content for feeds on social media\nPerform ad hoc assignments by management\u00a0\n\nWhat you need for this position:\n\nHigher diploma in Graphic Design or related discipline\nAt least 2 years of relevant experience in graphic design\nExperienced user of Adobe Photoshop and Adobe Illustrator\nKnowledge in social media management is an advantage\nProficient in spoken and written Chinese (both Cantonese and Mandarin) and English Independent, highly self-motivated, enjoy new challenges, and able to think out of the box\nA good team player and attention to detail\nCandidate with less experience would also be considered as Graphic Designer\u00a0\n\nWorking Location & Hours:\u00a0\nHong Kong Science Park\n5-day work, 10:00 \u2013 19:00 (Lunch hour 13:45 \u2013 15:00)\n\nWe Offer:\n\n\nAttractive Performance Bonus\nIn-game staff reward\nGood Career Prospects\nGroup Medical Insurance & Body-Check\nBirthday Leave, Marriage Leave, Compassionate Leave\nApplication method:\n\n\nInterested candidates please click the \"Apply Now\" button to apply and provide your portfolio for our review.\n\nWe are an equal opportunity employer and welcome applications from all qualified candidates. All information provided will be treated in strict confidence and used for recruitment purposes only.", "employment_types": ["Full Time", "Permanent"], "selling_points": ["5-day work / Flexible working hours", "Performance bonus and medical insurance", "Joyful working environment with free snacks/drinks"], "locations": ["Kwai Fong"], "categories": ["Design", "Graphics", "Multi-media", "Others"], "post_time": "2022-01-13T09:03:06Z", "salary": {"currency": null, "max": null, "min": null, "period": "monthly", "term": null}, "salary_visible": false, "title_keywords": ["junior"], "responsibilities": ["graphics", "social media", "management", "advertising", "ideas", "graphic design", "website", "design", "social media content", "ad hoc assignments"], "requirements": {"degrees": ["diploma"], "majors": ["graphic design"], "languages": ["cantonese", "english", "chinese", "mandarin"], "language_level": ["proficient"], "hard_skills": ["graphics", "adobe photoshop", "adobe illustrator"], "soft_skills": ["passionate", "good team player", "self-motivated", "independent", "attention to detail", "creative"], "languages_combined": [{"language": "cantonese", "language_level": ["proficient"]}, {"language": "english", "language_level": ["proficient"]}, {"language": "chinese", "language_level": ["proficient"]}, {"language": "mandarin", "language_level": ["proficient"]}]}, "experience_required": {"duration": ["at least 2 years"], "field": ["graphic design", "graphic", "relevant experience", "designer"]}}, {"job_id": "100003009042392", "location_code": "hk", "company": "Wang On Group", "job_title": "Assistant Graphic Designer", "description": "Responsibilities:\n\nTo create concepts, update and maintain the standard of work\nPrepare and facilitate documents, creative material and concepts\nWork closely with operations and marketing team\n\nRequirements:\n\nHigher Diploma or above in graphic design, creative media design or related disciplines\nMinimum 2 years of relevant working experience in graphic design / creative industry\nProficiency in Photoshop, Premiere, After Effect, Adobe Suite / Adobe Illustrator and other design tools.\nGood command in both spoken and written English and Chinese\nAble to work independently under fast-paced working environment\nSelf-motivated, analytical, passionate in helping people find solutions, detail-oriented, and good team player\nFresh graduates with relevant degree/ skillsets are welcomed\nImmediate availability is preferred\nWe offer a competitive remuneration package, our benefits include:\nPerformance bonus\nEducation subsidy\nProfessional membership fee sponsorship\nLife & medical insurance\nMarriage Leave, Compassionate Leave, Examination Leave etc.\nPublic holidays\nStaff purchase discount\n\n\nInterested parties please send full resume with present and expected salary to Human Resources Department by clicking \"APPLY NOW\" or via email recruit @wangon.com.\n\n(Information provided will be treated in strict confidence and will only be used for recruitment-related purposes.)", "employment_types": ["Full Time", "Permanent"], "selling_points": [], "locations": ["Kowloon Bay"], "categories": ["Design", "Graphics", "Multi-media", "Others"], "post_time": "2022-01-12T07:18:24Z", "salary": {"currency": null, "max": null, "min": null, "period": "monthly", "term": null}, "salary_visible": false, "title_keywords": ["assistant", "graphic designer"], "responsibilities": ["operations", "maintain"], "requirements": {"degrees": ["higher diploma or above", "degree"], "majors": ["related disciplines", "graphic design", "creative media", "design"], "languages": ["english", "chinese"], "language_level": ["good command"], "hard_skills": ["premiere", "adobe illustrator", "adobe", "after effect", "photoshop"], "soft_skills": ["passionate", "work independently", "self-motivated", "good team player", "detail-oriented", "creative"], "languages_combined": [{"language": "english", "language_level": ["good command"]}, {"language": "chinese", "language_level": ["good command"]}]}, "experience_required": {"duration": ["minimum 2 years"], "field": ["graphic design", "relevant working experience"]}}, {"job_id": "100003009044066", "location_code": "hk", "company": "China  First Capital Group Limited", "job_title": "(Assistant) Manager \u2013 Corporate Communication (based in Hong Kong Head-office)", "description": "Key Responsibilities:\n\nResponsible for the corporate communication strategies and implementation of ad hoc projects, event organization, road show, online platforms management, graphic design, translation, etc. to promote the corporate image and client relationship\nPromote the reputation of the UK universities under management\nOverall in charge of the global recruitment, selection and admission of the undergraduate students for the three universities in UK\nParticipation in other projects as assigned \u00a0\n\nMinimum Requirements:\n\nDegree holder in communications, journalism, translation, arts, design or related discipline or above;\nAt least 1 year relevant working experience in investor relations or corporate communication; knowledge of the social and financial business in Hong Kong, China and UK; sound understanding in school operation in UK an advantage;\nSkillful in graphic design, photographing a must;\nExcellent in spoken and written English and Chinese (Cantonese and Putonghua) ; proficient English writing, translation and proof-reading skills;\nInnovative, a good team player and able to work independently, eager to learn, self-motivated, independent and willing to take new challenges, occasional business travel may be required\n\nQualified applicants please send your CV together with current and expected salary for the application. All information gathered will be handled in strict confidence and used solely for recruitment purpose only.", "employment_types": ["Full Time", "Permanent"], "selling_points": [], "locations": ["Central"], "categories": ["Design", "Graphics", "Education", "Others", "Professional Services", "Translation"], "post_time": "2022-01-13T02:57:05Z", "salary": {"currency": null, "max": null, "min": null, "period": "monthly", "term": null}, "salary_visible": false, "title_keywords": ["manager", "assistant"], "responsibilities": ["management", "graphic design", "implementation", "communication", "ad hoc projects", "recruitment"], "requirements": {"degrees": ["degree holder"], "majors": ["journalism", "communications", "design"], "languages": ["cantonese", "putonghua", "english", "chinese"], "language_level": ["excellent", "proficient"], "hard_skills": ["translation"], "soft_skills": ["good team player", "work independently", "self-motivated", "independent", "confidence", "communication", "eager to learn", "innovative"], "languages_combined": [{"language": "cantonese", "language_level": ["excellent"]}, {"language": "putonghua", "language_level": ["excellent"]}, {"language": "english", "language_level": ["excellent", "proficient"]}, {"language": "chinese", "language_level": ["excellent"]}]}, "experience_required": {"duration": ["at least 1 year"], "field": ["corporate communication", "relevant working experience"]}}, {"job_id": "100003009050149", "location_code": "hk", "company": "Hypebeast Hong Kong Limited", "job_title": "E-commerce Photo Retoucher", "description": "HBX (previously known as HYPEBEAST Store) commenced business in May 2012, is a one-stop news source for internet-savvy fashion enthusiasts and cultural tastemakers. HBX is the global e-commerce platform that targets male and female online shoppers between the age of 18 and 35, and primarily sells third-party branded clothing, shoes and accessories to customers.\n\nResponsibilities:\n\nResponsible for product shot retouching.\nResponsible for model shot retouching.\nProduce photo retouching, colour correction and composition to company standard.\nEnsure the quality and style is within company standard and expectation.\nResponsible for other ad hoc duties as assigned.\nRequirements:\n\nExperienced in Product Photo Retouching.\nExcellent with Adobe Creative Suite (Photoshop).\nUnderstand Photoshop action sets, image resolution, colour space and image file formats.\nProficient in MAC operations.\nBasic skill in Fashion and Model Photography.\nGood spoken command of Cantonese and English.\nStrong team player with ability to work independently.\nAbility to multitask, and perform well under pressure to meet deadlines in a fast-paced environment.\nGood attitude and willingness to learn.\nIf you think you\u2019ve got what it takes, please provide your CV, expected salary and a portfolio with relevant examples for retail/fashion.\n\nThis position is based and located in Hong Kong. Candidate must be eligible to work in Hong Kong.\n\nPersonal data collected is for recruitment purpose only.", "employment_types": ["Full Time"], "selling_points": ["Rapidly expanding international e-commerce", "Creative, young and energetic team members", "Multi-cultural with harmonious working environment"], "locations": ["Tsuen Wan Area"], "categories": ["Design", "Graphics", "Multi-media"], "post_time": "2022-01-14T09:52:39Z", "salary": {"currency": null, "max": null, "min": null, "period": "monthly", "term": null}, "salary_visible": false, "title_keywords": [], "responsibilities": ["ad hoc duties", "retouching", "photo retouching", "quality"], "requirements": {"degrees": [], "majors": [], "languages": ["cantonese", "english"], "language_level": ["good"], "hard_skills": ["basic", "adobe creative suite", "photoshop"], "soft_skills": ["work independently", "fast-paced environment", "team player", "ability to multitask", "creative", "meet deadlines", "perform well under pressure"], "languages_combined": [{"language": "cantonese", "language_level": ["good"]}, {"language": "english", "language_level": ["good"]}]}, "experience_required": {"duration": [], "field": []}}, {"job_id": "100003009042694", "location_code": "hk", "company": "New Media Group Publishing Limited", "job_title": "Visual & Graphic Designer", "description": "We are looking for a talented visual & graphic designer to enhance our online presence with eye-catching and professional graphic designs. You will consult with the different function teams to determine design requirements, submit draft concepts for approval, and develop similar design prototypes for our products.\u00a0\n\nJob Description:\n\nDesign original graphics with unique colours, shapes, and typography fonts.\nSubmit graphic & visual design concepts for brainstorming and approval in a timely manner.\nCollaborate with the Project team and IT developers in aligning visual designs with website functionalities.\nDevelop prototypes to uniformly integrate logos and brand images to other products and platforms, including social media.\n\nRequirements:\n\nBachelor\u2019s or associate degree in graphic design, visual arts, or similar.\n1-3 years of experience as a graphic visual designer is preferred\nAdvanced proficiency in design software, such as Adobe Creative Suite's InDesign, Photoshop, and Illustrator.\nKnowledge of programming languages such as HTML and JavaScript would be advantageous.\nExtensive experience in determining visual design preferences and meeting deadlines.\nProficiency in keeping up with visual design technologies and industry trends.\nGood communication skills.\n\nWe offer competitive salary and benefits package( 5 days work, 14 days AL up, birthday leave, medical & dental insurance) with great opportunity for career development to the successful candidate.\n\nFor applications, please send the resume to us, specify in email title \u201cJob Application for\u00a0Visual & Graphic Designer\"", "employment_types": ["Full Time", "Permanent"], "selling_points": ["Design original graphics", "1-3 years of experience as a graphic designer", "Great development opportunity, competitive package"], "locations": ["Kwun Tong"], "categories": ["Media & Advertising", "Creative / Design", "Design", "Graphics", "Others"], "post_time": "2022-01-12T08:25:06Z", "salary": {"currency": null, "max": null, "min": null, "period": null, "term": null}, "salary_visible": false, "title_keywords": ["graphic designer"], "responsibilities": ["graphics", "design concepts", "collaborate with", "social media", "a timely manner", "website", "design", "develop", "visual"], "requirements": {"degrees": ["associate degree", "bachelor"], "majors": ["graphic design"], "languages": [], "language_level": [], "hard_skills": ["indesign", "illustrator", "html", "visual design", "javascript", "programming", "adobe creative suite", "photoshop"], "soft_skills": ["communication skills", "creative", "extensive", "advanced"], "languages_combined": []}, "experience_required": {"duration": ["1-3 years"], "field": ["graphic", "designer", "design"]}}, {"job_id": "100003009037675", "location_code": "hk", "company": "FZN International Ltd", "job_title": "Graphic Designer", "description": "Responsibility:\n\n- Handle advertising, event related graphic design projects\n\n- Design and production for event decoration and promotional items\n\n- Supervise and liaise with print vendors\n\n- Provide client servicing and manage projects independently\n\nRequirement:\n\n- Minimum 1 year of related design experiences in agency or production house\n\n- Detail-oriented, responsible, independent and can work in a team\n\n- Strong Drawing Skills and Creative Sense\n\n- Proficient in Adobe Illustrator, Photoshop\n\n-\u00a0Knowledge of 3D and video editing software (Cinema 4D, AfterEffects, Premier Pro) would\u00a0 \u00a0 be an advantage.\n\n- Candidate with no experience will be considered as Design Assistant\n\n- Immediate available is preferable\n\n\u00a0Please send your full resume with current and expected salary and indicate your applied job title to HR\n\n\u00a0\u00a0(Personal data collected will be used for recruitment purpose only.)", "employment_types": ["Full Time", "Permanent"], "selling_points": [], "locations": ["Kowloon Bay"], "categories": ["Design", "Graphics", "Multi-media", "Marketing / Public Relations", "Public Relations - Event Management"], "post_time": "2022-01-11T03:33:40Z", "salary": {"currency": null, "max": null, "min": null, "period": "monthly", "term": null}, "salary_visible": false, "title_keywords": ["graphic designer"], "responsibilities": ["advertising", "graphic design", "event decoration", "design", "manage projects", "liaise with"], "requirements": {"degrees": [], "majors": [], "languages": [], "language_level": [], "hard_skills": ["video editing", "no", "photoshop", "adobe illustrator"], "soft_skills": ["creative", "independent", "responsible", "detail-oriented"], "languages_combined": []}, "experience_required": {"duration": ["minimum 1 year"], "field": ["related", "agency", "design"]}}, {"job_id": "100003009041299", "location_code": "hk", "company": "SGS Asia Pacific Limited", "job_title": "Art Director / Senior Designer", "description": "\nwww.makemarks.com\nWe are a dynamic brand design & packaging agency that delivers impactful ideas & experiences that build brand momentum.\n\nWe are looking for talented & passionate Art Director, 3D/CGI Designers .......who's really creative talent with strong design execution skills with aesthetic sensibility.\nWorking across our global iconic brands accounts, the perfect candidate will have an eye for detail, a passion for problem-solving and be able to create insight-driven, innovative, strategic approaches to deliver the highest level of design.\u2028\u2028\nThis is a rewarding role for a team player with a positive attitude, working in a friendly and relaxed, yet focused and hard-working environment.\n\n*Responsibilities: \u00a0 \u00a0 \u00a0 \u00a0\u00a0\nGraphic design and brand development\nConcept, visualization and hands on design\nConcept development and design preparation of packaging, key visual, POSM and promotion collaterals\nWork closely with\u00a0senior creative personnel to ensure concept's achievability and accurate presentation\nFollow through project from concept development, executing layouts, artwork\u00a0design independently\nSupport any Ad-hoc job tasks assigned.\nWorking with the Creative Team to adjust project goals and design revisions on the fly as necessary to adapt to changing situations to meet established schedules\nIdentifying potential problems in the creative pipeline and working with the Creative Team to prevent them\nAttend client meetings with account team to discuss brief and give creative feedback when required\nKeep up with latest digital, social and mobile trends in advertising\nStaying abreast of current market and industry trends to aid in the development of cutting edge marketing, design concepts, with the secondary goal of educating the team\nMeeting and exceeding client and department head expectations\nMeet deadlines\nEnsure client satisfaction at all levels\nEnsure all creative work is completed within time and on budget\n*Requirements:\n5-7 years experience in graphic design\nHigh proficiency in Macintosh and Adobe Creative Suite (Illustrator, Photoshop, InDesign)\nKnowledge of 3D rendering and visualizing an advantage\nProficiency in hand drawing, sketching and illustrating\nWide interest in the visual arts\nCreative with a good art sense\nAbility to effectively prioritize workload and exercise time management skills\nAble to demonstrate a strong creative sense, good typographic and layout sense, strong conceptual and execution skills and typographic sense\nStrong aesthetics, originality, outstanding visual performance capability, and extremely sensitive to color\nSelf-motivated, mature, good communication and able to handle projects independently\nSolid experience in handling production\nCustomer focused\nFlexibility and problem solving skills", "employment_types": ["Full Time", "Permanent", "Contract"], "selling_points": ["Branding, Packaging, Campaign, Digital Marketing", "Work with people who love what they do", "Friendly, relaxed and hard-working environment"], "locations": ["Mong Kok"], "categories": ["Design", "Graphics"], "post_time": "2022-01-12T03:42:53Z", "salary": {"currency": null, "max": null, "min": null, "period": "monthly", "term": null}, "salary_visible": false, "title_keywords": ["art director", "senior designer"], "responsibilities": ["ad-hoc", "design concepts", "advertising", "visualization", "schedules", "graphic design", "budget", "design", "executing", "visual"], "requirements": {"degrees": [], "majors": [], "languages": [], "language_level": [], "hard_skills": ["indesign", "illustrator", "problem solving skills", "adobe creative suite", "photoshop"], "soft_skills": ["self-motivated", "independently", "focused", "time management skills", "prioritize", "mature", "communication", "sensitive to", "problem solving skills", "creative"], "languages_combined": []}, "experience_required": {"duration": ["5-7 years"], "field": ["graphic design"]}}, {"job_id": "100003009040215", "location_code": "hk", "company": "Atelier Pacific Ltd", "job_title": "Assistant Designer (Environmental Graphics)", "description": "Duties:\n\nCreating unique, creative and competitive design concepts under a tight schedule\nAnalyzing trends in fabrics, colors and functions\nWell organizing the whole design procedure including market, fabric and trim research, prototype request preparation and sample production follow-up\nCollaborating closely with the team from design process, concept inception to finalization\n\nRequirements:\n\nDegree in Fashion Design or related disciplines\nMinimum 5 years' relevant\u00a0working experience, preferably with multinational sports\ncompanies\nWell understand the trends and the development of China sports apparel industry\nExcellent communication skills\nWell-versed in Mac software, particularly in Illustrator and Photoshop\nPassion for sports especially basketball\nProficiency in spoken and written Chinese and English, including Mandarin\nA strong team player, able to work independently and\u00a0willing to travel frequently", "employment_types": ["Full Time", "Permanent"], "selling_points": ["5 days work", "Environmental Graphic Design", "Fringe Benefits"], "locations": ["North Point"], "categories": ["Design", "Graphics", "Industrial / Product", "Interior"], "post_time": "2022-01-12T01:54:56Z", "salary": {"currency": null, "max": null, "min": null, "period": "monthly", "term": null}, "salary_visible": false, "title_keywords": ["assistant designer"], "responsibilities": ["design concepts", "schedule", "design"], "requirements": {"degrees": ["degree"], "majors": ["related disciplines", "design"], "languages": ["english", "chinese", "mandarin"], "language_level": ["proficiency"], "hard_skills": ["illustrator", "photoshop"], "soft_skills": ["communication skills", "team player", "work independently", "passion for"], "languages_combined": [{"language": "english", "language_level": ["proficiency"]}, {"language": "chinese", "language_level": ["proficiency"]}, {"language": "mandarin", "language_level": ["proficiency"]}]}, "experience_required": {"duration": ["minimum 5 years"], "field": ["relevant working experience"]}}, {"job_id": "100003009042296", "location_code": "hk", "company": "Li Ning Sports Technology Development (HK) Co Ltd", "job_title": "Sr. Graphic Designer in Sports Apparel  (Stationed in Beijing)", "description": "We are\u00a0Toby\u00a0- the largest platform for services in Hong Kong! To strive for continuous improvement on both user experience and service quality, we are looking for talented individuals to grow our business with us! If you are ambitious and love working with a funny team, JOIN us!\n\nYou will work with\u00a0Graphic Design team\u00a0who are providing valuable graphic design for all marketing platform. You are required to provide graphic/branding material, concept presentation and readable storyboards.\n\n\nResponsibilities\n\nProvide graphic design and build design assets in a wide range of marketing platform\nDevelop unique brand system, highly readable storyboards, smooth user flows to pursue audience satisfaction\nWork closely with other team members for effective and efficient product delivery.\nRequirements\n\nDegree or Diploma holder in Communication, Design or similar discipline. University students are welcomed\nHigh proficiency in using Photoshop, Illustrator and InDesign, with knowledge and experience in video editing suite is a plus\nCreative, detail-oriented, well-organized, independent with strong layout, graphic sense and typography\n\nWhat we can offer\n\nJoyful working environment - you will work with a funny team!\u00a0\nHigh level of autonomy - we adopt any good ideas from all employees\nRegular Birthday Party\nHappy Friday\nStaff Discount\n\nJoyful and flexible start-up culture with friendly co-workers who are always willing to provide advice and assistance.\u00a0We also hold regular lunch gathering, festive party for our staff. We are a FUN, YOUNG and ENERGETIC team with good learning and career development opportunities. Come join and excel with us!", "employment_types": ["Full Time"], "selling_points": ["Degree in Fashion Design or related disciplines", "Minimum 5 years' relevant working experience", "Well-versed in Mac software"], "locations": ["Mong Kok"], "categories": ["Design", "Graphics"], "post_time": "2022-01-12T06:55:10Z", "salary": {"currency": null, "max": null, "min": null, "period": "monthly", "term": null}, "salary_visible": false, "title_keywords": ["graphic designer"], "responsibilities": ["graphic design", "storyboards", "design", "develop"], "requirements": {"degrees": ["diploma holder", "degree"], "majors": ["design"], "languages": [], "language_level": [], "hard_skills": ["plus", "indesign", "illustrator", "video editing", "photoshop"], "soft_skills": ["independent", "well-organized", "detail-oriented", "communication", "creative"], "languages_combined": []}, "experience_required": {"duration": [], "field": ["editing", "video"]}}, {"job_id": "100003009040331", "location_code": "hk", "company": "I-Skincare Company Limited", "job_title": "Graphic Designer (Tsim Sha Tsui / 5 Days work)", "description": "\u00a0Drafting Clerk \u00a0\u7e52\u5716\u6587\u54e1\n\n\u4e2d\u4e94\u7a0b\u5ea6\n\u826f\u597d\u7684\u4e2d\u82f1\u6587\n\u80fd\u7d14\u719f\u4f7f\u7528 Illustrator \u7e52\u756b\u5e73\u9762\u5716\uff0c\u719f\u6089 Photoshop \u66f4\u4f73\uff0c\u7c21\u55ae\u88dd\u914d\u5de5\u4f5c\n\u9700\u7528\u96fb\u90f5\u53ca\u96fb\u8a71\u8ddf\u5ba2\u4eba\u6e9d\u901a\u8ddf\u9032\u7a3f\u4ef6\u53ca\u8a02\u55ae\n\u80fd\u719f\u6089\u4f7f\u7528 MS Office (Excel and Word).\n\u7368\u7acb\uff0c\u7a4d\u6975\uff0c\u505a\u4e8b\u8a8d\u771f\n\u9280\u884c\u5047\u671f\n\u8475\u9752\u5340\u5de5\u4f5c\n\u6709\u610f\u8005\u8acb\u96fb\u90f5\u5c65\u6b77\u53ca\u8981\u6c42\u5f85\u9047\u7d66\u672c\u516c\u53f8\n\nAll personal data provided by job applicants will be used for recruitment purpose only.", "employment_types": ["Full Time", "Permanent", "Contract"], "selling_points": ["Visual creation and video editing", "Min. 3 years of design experience", "Proficient in Illustratior and Photoshop"], "locations": ["Tsim Sha Tsui"], "categories": ["Design", "Graphics", "Multi-media", "Web Designer"], "post_time": "2022-01-12T02:18:27Z", "salary": {"currency": null, "max": null, "min": null, "period": "monthly", "term": null}, "salary_visible": false, "title_keywords": ["graphic designer"], "responsibilities": ["personal data", "recruitment"], "requirements": {"degrees": [], "majors": [], "languages": [], "language_level": [], "hard_skills": ["excel", "illustrator", "word", "photoshop", "ms office"], "soft_skills": [], "languages_combined": []}, "experience_required": {"duration": [], "field": []}}, {"job_id": "100003009039834", "location_code": "hk", "company": "Kingly Agents Limited", "job_title": "Drafting Clerk  \u7e52\u5716\u6587\u54e1", "description": "Responsibilities\n\nResponsible for developing concept and executing designs for marketing/ communication brochures, website and social media graphics, posters, flyers, and other marketing materials as needed.\nCoordinate with external parties such as printers and production house.\nResponsible for photo shooting and re-touching.\nResponsible for designing the whole set of motion graphic for informative and promotional videos etc.\nSupport video production team in developing visual effects or infographics for videos.\nCreate engaging contents for marketing and communications purposes.\nWork closely with Marketing Team for promotional materials and ad-hoc tasks on creatives.\n\nRequirements:\n\nDiploma graduate or above in graphic design or related disciplines.\nAt least 8 years of working experience in graphic design prefer in health industry.\nStrong proficiency in Photoshop, Illustrator, In-Design, AI, Premiere and after effect.\nA good team player, with passion in design, innovative, efficient, self-motivated and able to meet tight schedule.\nFamiliar with output process & printing materials.\nKnowledge of web graphics is an advantage.\nKnowledge and experience in digital content production.\n\nWe offer attractive compensation package plus career opportunities to the right candidates. Please send your detailed resume, with latest and\u00a0expected salary\u00a0to our Human Resources Department by clicking \"Apply Now\".\n\nAll data collected will be used for recruitment purpose only.", "employment_types": ["Full Time"], "selling_points": [], "locations": ["Kwai Tsing Area"], "categories": ["Design", "Graphics", "Others", "Others", "Others"], "post_time": "2022-01-11T11:47:26Z", "salary": {"currency": null, "max": null, "min": null, "period": "monthly", "term": null}, "salary_visible": false, "title_keywords": ["clerk"], "responsibilities": ["graphics", "social media", "video production", "ad-hoc tasks", "external parties", "coordinate with", "developing", "website", "communication", "re-touching", "contents", "promotional materials", "executing", "visual", "designing", "marketing materials", "motion graphic"], "requirements": {"degrees": ["diploma"], "majors": ["related disciplines", "graphic design"], "languages": [], "language_level": [], "hard_skills": ["ai", "illustrator", "premiere", "in-design", "web graphics", "after effect", "photoshop"], "soft_skills": ["efficient", "good team player", "self-motivated", "passion in", "innovative"], "languages_combined": []}, "experience_required": {"duration": ["at least 8 years"], "field": ["graphic design", "digital content"]}}, {"job_id": "100003009042060", "location_code": "hk", "company": "CEMG Management Limited", "job_title": "Senior Graphic Designer", "description": "Provide support to Marketing team in designing, developing and executing promotional materials to achieve designated business goals\nAssist management in executing marketing strategies and marketing plan to achieve business objectives\nMaintain close relationship with bloggers/ KOLs/ influencers\nContent planning and copywriting for a range of materials including product information on eShop and website, press release and communications on social media\nResponsible for eCommerce business including product update, campaign performance review and customers\u2019 inquiry handling\nLiaise with internal departments and external agencies to ensure the smooth execution of marketing programs\nParticipate in other ad-hoc marketing activities\n\nRequirements:\n\nDegree holder in Communications, Marketing or related disciplines\nMinimum 2 years of working experience in Marketing, eCommerce or related fields, preferably in F&B / FMCG industry\nProficiency in photoshop or illustrator is a plus\nGood marketing sense, multi-tasking, can-do attitude, independent, detail-minded and able to work under pressure\nGood command of both written and spoken English and Chinese\nProficiency in MS Office and Chinese Word Processing\nInterested parties please send your CV,\u00a0expected salary & availability by clicking \"APPLY NOW\" button or contact Human Resources Department at\u00a03656 1388\u00a0for enquiries. Personal data collected will be used for recruitment related purpose only.", "employment_types": ["Full Time"], "selling_points": ["5 days work", "Graphic Design", "Strong in Photoshop, AfterEffect"], "locations": ["Tin Hau"], "categories": ["Design", "Graphics", "Industrial / Product", "Beauty Care / Health", "Others"], "post_time": "2022-01-12T05:47:33Z", "salary": {"currency": null, "max": null, "min": null, "period": "monthly", "term": null}, "salary_visible": false, "title_keywords": ["senior graphic designer"], "responsibilities": ["ad-hoc", "social media", "provide support", "business goals", "management", "marketing strategies", "work under pressure", "review", "developing", "website", "marketing plan", "promotional materials", "executing", "maintain", "designing", "liaise with", "planning"], "requirements": {"degrees": ["degree holder"], "majors": ["related disciplines", "marketing", "communications"], "languages": ["english", "chinese"], "language_level": ["proficiency", "good command"], "hard_skills": ["plus", "chinese word processing", "fmcg industry", "illustrator", "photoshop", "ms office"], "soft_skills": ["detail-minded", "marketing sense", "independent", "responsible", "can-do attitude", "multi-tasking", "smooth", "work under pressure"], "languages_combined": [{"language": "english", "language_level": ["good command"]}, {"language": "chinese", "language_level": ["proficiency", "good command"]}]}, "experience_required": {"duration": ["minimum 2 years"], "field": ["ecommerce", "fmcg", "related", "f&b", "marketing"]}}, {"job_id": "100003009033732", "location_code": "hk", "company": "Dickie Toys Hong Kong Limited", "job_title": "Graphic Designer", "description": "THE ROLE\u00a0\nWe are looking for a passionately user and outcome-oriented designer to join the MoneyHero Marketing team. If you are the person who is observant to the big picture and has good attention to details, obsessed with aesthetics and uncomfortable with bad typography or bad alignments, believe in having fun while achieving results, then you are exactly the candidate who we want to welcome to our team!\n\nYOUR TASK\nAssist design research and material preparation\nProduce digital designs\u00a0 as assigned such as banner ads, social posts, infographics\nUse various techniques to create drafts, models and prototypes\nPitch creative ideas\nCollaborate with team members to launch projects\nTake on special design tasks (e.g. color correction)\nUse feedback from other designers to improve\nSKILLS & REQUIREMENTS\n1-2 years of experiences\u00a0\nStrong graphic sense including typography, colors, graphics and layout\nPassionate in creative and design with an eye for detail\u00a0\nA team player with good track record of time management and communication skills\u00a0\u00a0\nPreferably majoring in Design, Creative Media, Digital Media, Visual Comm or related disciplines\nProficient in the use of Mac & Adobe Creative Suite\nFluent in written and spoken English and Chinese", "employment_types": ["Full Time", "Permanent"], "selling_points": ["Responsible for graphic design, conceptual", "Must be willing to take responsibility", "Capable to work independently under pressure"], "locations": ["Tsim Sha Tsui"], "categories": ["Design", "Graphics", "Industrial / Product", "Merchandising & Purchasing", "Toy"], "post_time": "2022-01-10T02:14:30Z", "salary": {"currency": null, "max": null, "min": null, "period": "monthly", "term": null}, "salary_visible": false, "title_keywords": ["graphic designer"], "responsibilities": ["collaborate with", "graphics", "creative ideas", "management", "design", "communication", "visual"], "requirements": {"degrees": [], "majors": [], "languages": ["english", "chinese"], "language_level": ["fluent"], "hard_skills": ["graphics", "adobe creative suite", "fun"], "soft_skills": ["passionate", "communication skills", "time management", "eye for detail", "attention to details", "team player", "creative"], "languages_combined": [{"language": "english", "language_level": ["fluent"]}, {"language": "chinese", "language_level": ["fluent"]}]}, "experience_required": {"duration": ["1-2 years"], "field": []}}, {"job_id": "100003009042287", "location_code": "hk", "company": "Leader Marine Products Trading Limited", "job_title": "Marketing Officer (Graphic Design)", "description": "Freelance Graphic Designer required ASAP\n\nWrapology design and manufacture luxury packaging for brands.\u00a0\n\nWe require a freelance graphic designer to come to our office 1 x per week to work on the below areas of our marketing and branding.\u00a0\n\n1. Setting monthly e-mail blast\n- The content and images will be supplied\n- You will need to set and make it look engaging and nice.\u00a0\n- We use \"Hubspot\" as the software to send out the e-mails\n\n2. Updating Website\n- Update our website (Squarespace) with content such as project of the month, material of the month etc\n- Entering blog entries\n\n3. Updating and improving our digital Look Book\n- Using Indesign to update our digital look book with latest content\n\n4. Instagram/Social Media\n- Preparing images ready to send out on our social media channels\n\nWe would agree a day rate and a contract period.\u00a0\nOur office is located on Wyndam Street, LFK\n\nPlease submit your portfolio on the application\n\n", "employment_types": ["Full Time", "Permanent"], "selling_points": [], "locations": ["Aberdeen"], "categories": ["Design", "Graphics", "Marketing / Public Relations", "Marketing - Marketing Communication", "Public Relations - Copy-writing"], "post_time": "2022-01-12T06:52:11Z", "salary": {"currency": null, "max": null, "min": null, "period": "monthly", "term": null}, "salary_visible": false, "title_keywords": ["marketing officer"], "responsibilities": ["social media", "website", "software", "design"], "requirements": {"degrees": [], "majors": [], "languages": [], "language_level": [], "hard_skills": ["make", "nice", "indesign", "squarespace"], "soft_skills": [], "languages_combined": []}, "experience_required": {"duration": [], "field": []}}]