[{"job_id": "100003009054650", "location_code": "hk", "company": "Samsonwong Design Group Limited", "job_title": "Senior Interior Designer / Interior Designer", "description": "Degree or diploma holder in design/ architecture or related disciplines\nMinimum\u00a03-5 years solid working experience\nFresh graduates or less experienced applicants are welcome\nExposure in the field of furniture & graphic is a plus\nCompetency in Auto CAD;\u00a0 Photoshop and 3Ds Max are added advantage\nCreative and responsible\nProactive, a team player with good presentation and communication skills\nAbility to work independently\nAvailable: immediate\n\nWe offer a 5-day work week, including 12 days annual leave and double pay.\n\nInterested parties please send full resume with date of availability, present & expected salary and portfolio to email by clicking \"Apply Now\".\n\nPersonal data will be used for recruitment purposes only.", "employment_types": ["Full Time", "Permanent"], "selling_points": [], "locations": ["Lai Chi Kok"], "categories": ["Design", "Interior", "Building & Construction", "Building / Construction / QS", "Others"], "post_time": "2022-01-17T10:24:30Z", "salary": {"currency": null, "max": null, "min": null, "period": "monthly", "term": null}, "salary_visible": false, "title_keywords": ["interior designer", "senior interior designer"], "responsibilities": ["communication", "architecture", "design"], "requirements": {"degrees": ["diploma holder", "degree"], "majors": ["related disciplines", "architecture", "design"], "languages": [], "language_level": [], "hard_skills": ["plus", "auto cad", "3ds max", "photoshop"], "soft_skills": ["communication skills", "work independently", "proactive", "responsible", "team player", "creative", "presentation"], "languages_combined": []}, "experience_required": {"duration": ["minimum 3-5 years"], "field": []}}, {"job_id": "100003009054898", "location_code": "hk", "company": "Mindscape Interior Architecture Limited", "job_title": "(Assistant) Interior designer (5-day work & double pay)", "description": "BTR (HK) Ltd specializes in design projects, is now seeking candidates for the following post(s):\n\nInterior Designer\n\n\nThe Job\n\nClient: Property Developers\nPosition:\u00a0Interior Designer\nProjects: Luxurious Residence &\u00a0Clubhouses / Residential Show\u00a0 Flats & Sales offices / Shopping Malls\n\nRequirements\n\nDiploma or Degree\u00a0in interiors design or equivalent\nMinimum 3 years solid experience in residential project\nProficiency in PowerPoint, AutoCAD, Photoshop, & PC software\n(Skills in free hand perspectives and sketching is favorable)\nStrong experience/sense in space planning/conceptual design/sketching/technical coordination and drawing production\nAbility to handle multi tasks under pressure and dynamic environment, ability to meet tight schedule with confidence and willing to work overtime when necessary.\nSelf-motivated with good interpersonal, presentation and communication skills\nProficiency in written and spoken English\nImmediate availability is preferable\n\nResponsibilities\n\nAssist and report to design manager\nDeveloping design concepts and consequent images, drawings, FF&E selections and construction details\nProvide support and guidance to other team members to deliver full set construction drawings\nInterface and co-ordinations with clients, contractors and other third parties\nAbility to handle multiple projects simultaneously\n\nInterested parties should send full resume with work portfolio, availability, expected salary to BTR for consideration.", "employment_types": ["Full Time", "Permanent"], "selling_points": ["Degree or diploma holder in design/ architecture", "Assistant interior designer", "5-day work week"], "locations": ["North Point"], "categories": ["Building & Construction", "Architectural Services", "Design", "Interior", "Others"], "post_time": "2022-01-17T13:11:38Z", "salary": {"currency": null, "max": null, "min": null, "period": "monthly", "term": null}, "salary_visible": false, "title_keywords": ["interior designer", "assistant"], "responsibilities": [], "requirements": {"degrees": ["diploma", "degree"], "majors": ["design"], "languages": ["english"], "language_level": ["proficiency"], "hard_skills": ["powerpoint", "dynamic", "autocad", "pc", "photoshop"], "soft_skills": ["communication skills", "dynamic environment", "confidence", "under pressure", "work overtime", "self-motivated", "presentation", "coordination", "interpersonal"], "languages_combined": [{"language": "english", "language_level": ["proficiency"]}]}, "experience_required": {"duration": ["minimum 3 years"], "field": ["design", "planning"]}}, {"job_id": "100003009052693", "location_code": "hk", "company": "BTR (HK) Limited", "job_title": "Interior Designer", "description": "Responsibilities:\n\nAssist project managers and designers to coordinate project matters, schedule and report problems.\nTo manage, control and monitor of daily project works, instructions and progress\nCoordinate and liaise with sub-contractors, suppliers, and third party companies\nPrepare weekly progress report for project team and client\u2019s record\nAssist in other ad-hoc assignment\n\nRequirements:\u00a0\n\nDegree / Diploma in Building Studies / Construction Management / Engineering\u00a0or related discipline is an advantage but not a must\nAble to handle multi-tasks under pressure and deadline\nWilling to learn and attention to details\nGood computer literate (AutoCAD, Microsoft Word, Excel)\u00a0is a plus\nCandidates with less experience / Fresh Graduates are also considered\n\nInterested candidates please send us the followings by email or click \"Apply Now'.\n\nFull resume\nPresent / expected salary\nAnything you would like to share with us\n\nWe offer attractive remuneration package, career advancement, various project opportunities to the right candidate.\n\nPlease visit our interior design brand BOKA Design facebook page for more information: www.facebook.com/bokadesignhk\n\n(Personal data collected will be used for recruitment purpose only.)\n", "employment_types": ["Full Time", "Permanent"], "selling_points": ["Medical benefit", "Diploma or Above, 3 Year Relevant Experience", "5 Days Working, Competitive Remuneration Package"], "locations": ["Kwun Tong"], "categories": ["Building & Construction", "Architectural Services", "Design", "Interior"], "post_time": "2022-01-17T03:43:22Z", "salary": {"currency": null, "max": null, "min": null, "period": "monthly", "term": null}, "salary_visible": false, "title_keywords": ["interior designer"], "responsibilities": ["ad-hoc", "control", "monitor", "coordinate", "schedule", "liaise with", "third party", "report"], "requirements": {"degrees": ["diploma", "degree"], "majors": ["construction management", "building studies", "engineering"], "languages": [], "language_level": [], "hard_skills": ["excel", "plus", "microsoft word", "autocad"], "soft_skills": ["willing to learn", "under pressure", "attention to details", "multi-tasks"], "languages_combined": []}, "experience_required": {"duration": [], "field": []}}, {"job_id": "100003009054656", "location_code": "hk", "company": "SEN Construction Company Limited", "job_title": "Interior Designer / Assistant Interior Designer", "description": "Job Description\n\nMy client is an interior design firm based in Hong Kong. They are specializing an international brand including retail and commercial design projects. The boutique locate for K11 MUSEA, 1881 Heritage, Ocean Terminal, Element Shop, Macau and China.\n\nWelcome to join our team to cope with our rapid expansion in both mainland China and Hong Kong.\n\nRequirements\n\nDiploma holder or above in Interior Design\nBasic\u00a0computer knowledge in AutoCAD\u00a0and\u00a0Photoshop are\u00a0preferable\nCapable in handling project independently for interior designer\n\nResponsible of site management, site survey,\u00a0 site staff supervision, etc.\u00a0for interior designer\n\nBasic Cantonese, English & Putonghua\nTraveling to overseas/ PRC is required\nMin 2 years site experience for interior designer\u00a0\n\nResponsibilities:\u00a0\n\nAssist the Senior Interior Designer\nDealing with clients, contractors, architectures, vendors and project team members\nResponsible for design drawings and documentation including concept design and development, construction drawing, materials sourcing and selection\nIdentify and understand clients\u2019 needs and provide customer services\n\nWe offer\u00a0double pay,\u00a0bank holidays, 5 1/2day work,\u00a0annual leave and MPF. Interested candidates please send your application letter with CV, portfolio and salary expectations by clicking 'Apply Now'", "employment_types": ["Full Time"], "selling_points": ["\u505a\u5927\u54c1\u724c\u5e97\u8216\u88dd\u4fee\u8a2d\u8a08, \u589e\u52a0\u500b\u4eba\u7d93\u9a57\u503c", "Double pay", "\u7531\u4e2d\u74b0\u6e2f\u9435\u5230\u516c\u53f8, \u53ea\u8981\u6b65\u884c5\u5206\u9418"], "locations": ["Central"], "categories": ["Design", "Interior", "Visual Merchandising", "Others"], "post_time": "2022-01-17T10:25:13Z", "salary": {"currency": "HKD", "max": 34999, "min": 14000, "period": "monthly", "term": null}, "salary_visible": true, "title_keywords": ["interior designer", "assistant interior designer"], "responsibilities": ["design"], "requirements": {"degrees": ["diploma holder"], "majors": ["design"], "languages": ["cantonese", "putonghua", "english"], "language_level": ["basic"], "hard_skills": ["documentation", "basic", "photoshop", "autocad"], "soft_skills": ["independently", "capable", "responsible"], "languages_combined": [{"language": "cantonese", "language_level": ["basic"]}, {"language": "putonghua", "language_level": []}, {"language": "english", "language_level": []}]}, "experience_required": {"duration": ["min 2 years"], "field": ["designer"]}}, {"job_id": "100003009054899", "location_code": "hk", "company": "News-D Limited", "job_title": "Interior designer", "description": "Boutique design firm with large scale mixed use project portfolio, offering the sustainable and energetic platform for young designers to grow.\nJob Highlights\nhave passion for design\nDegree holders in Interior Design\n\u00a0Responsibilities:\u00a0\nCandidate must have passion for design \u2013 you are expected to work on reputable mixed use projects and others\nRequirements:\nDegree holders in Interior Design or relevant ;\nPast working experiences in retail mall, notable hotel, office, service apartments, club houses and or residential development would be an advantage\nPast experiences in communicating mainland china client would be an advantage\nProficiency in design presentations, AutoCAD, Photoshop, Sketchup, Rhino, Indesign, Enscape.\nProficient in written and spoken English and Chinese including Putonghua\nTravel to Mainland China would be required from time to time\nTeam player and multi-task oriented\nWe work 5 days a week\uff0c remuneration package including medical scheme to the successful candidates.\u00a0 Please send full resume with expected salary and work portfolio.\n(Data collected would be used for recruitment purpose only.)", "employment_types": ["Full Time"], "selling_points": ["Passion for design", "Work on reputable mixed use projects", "Past experience would be an advantage"], "locations": ["Lai Chi Kok"], "categories": ["Design", "Interior"], "post_time": "2022-01-17T13:12:24Z", "salary": {"currency": null, "max": null, "min": null, "period": "monthly", "term": null}, "salary_visible": false, "title_keywords": ["interior designer"], "responsibilities": ["design"], "requirements": {"degrees": ["degree"], "majors": ["design"], "languages": ["putonghua", "english", "chinese"], "language_level": ["proficient"], "hard_skills": ["rhino", "indesign", "scheme", "presentations", "autocad", "photoshop", "sketchup"], "soft_skills": ["team player", "multi-task oriented"], "languages_combined": [{"language": "putonghua", "language_level": ["proficient"]}, {"language": "english", "language_level": ["proficient"]}, {"language": "chinese", "language_level": ["proficient"]}]}, "experience_required": {"duration": [], "field": ["development", "retail"]}}, {"job_id": "100003009053426", "location_code": "hk", "company": "Vinoti Living Co Limited", "job_title": "Assistant Project Manager / Interior Designer", "description": "F.5 or above\nAt least 2 years or above relevant experience in interior design field.\nAt least 3 years design experience in commercial preferably.\nProficient In AutoCAD, 3D Studio Max, Photoshop.\nResponsible, aggressive, hard working & willing to learn.\nF&B design experience and immediate available is preferred.\nCandidates with less experience will be considered for Interior Designer.\n\nInterested parties please send CV with expected salary to us by clicking apply now.\n\n(Personal data will be used for recruitment purpose only)", "employment_types": ["Full Time", "Permanent"], "selling_points": [], "locations": ["Lai Chi Kok"], "categories": ["Design", "Interior", "Building & Construction", "Building / Construction / QS"], "post_time": "2022-01-17T06:58:26Z", "salary": {"currency": null, "max": null, "min": null, "period": "monthly", "term": null}, "salary_visible": false, "title_keywords": ["assistant project manager", "interior designer"], "responsibilities": ["design"], "requirements": {"degrees": [], "majors": [], "languages": [], "language_level": [], "hard_skills": ["max", "photoshop", "autocad"], "soft_skills": ["hard working", "willing to learn", "responsible"], "languages_combined": []}, "experience_required": {"duration": ["at least 2 years", "at least 3 years"], "field": ["designer", "design", "commercial", "f&b", "relevant experience"]}}, {"job_id": "100003009054095", "location_code": "hk", "company": "Taste of Asia Group Limited", "job_title": "Interior Designer / Assistant Interior Designer", "description": "Responsibilities\u00a0\n\nProduce 2D & 3D interior design drawings including layout plan, renderings and product list\nPrepare full set of design and construction drawings / proposal for residential project and commercial project as well as F&B project\nInsight for new brand image development is preferable\nCommunicate with customers, contractors and vendors including follow up calls or emails\nResponsible materials selection and sourcing of the project\n\nRequirements\n\nHigher Diploma holder or above in Interior Design or related disciplines\nAt least 5 years interior design experience on restaurant or residential renovation project experience\nProficient in handling full set of construction drawings and relevant technical drawings\nWith experience of fitting out document preparation for Landlord Submission\nStrong site supervision with good time management and quality control skills\nGood planning and project execution control skills\nStrong interpersonal and communication skills\nGood computer knowledge in AutoCAD, SketchUp, Adobe Creative Suite and MS Office\n\u00a0Good command in spoken and written English and Cantonese\nCandidates with less experience will be considered as\u00a0Assistant Interior Designer\n\nJob location: San Po Kong\n\nCompetitive remuneration package and benefits as below:\n\nMarriage leave\n\nStaff discount\n\nMedical & dental allowance\n\nPerformance bonus\n\nIn-service training course\n\n5 days paternity leave\n\nCompassionate Leave\n\nPromotion opportunities\n\n\n\nA\u00a0competitive package and promising career prospect will be offered to the right candidate. Interested parties please send detailed resume with expected salary and availability by clicking \"Apply Now\" to submit your application.", "employment_types": ["Full Time"], "selling_points": ["Medical & dental allowance", "Performance bonus", "Promotion opportunities"], "locations": ["Wong Tai Sin Area"], "categories": ["Design", "Interior", "Others", "Others"], "post_time": "2022-01-17T08:22:20Z", "salary": {"currency": null, "max": null, "min": null, "period": "monthly", "term": null}, "salary_visible": false, "title_keywords": ["interior designer", "assistant interior designer"], "responsibilities": ["communicate with", "design drawings", "design", "drawings", "plan"], "requirements": {"degrees": ["higher diploma holder"], "majors": ["related disciplines", "design"], "languages": ["cantonese", "english"], "language_level": ["good command"], "hard_skills": ["ms office", "sketchup", "adobe creative suite", "autocad"], "soft_skills": ["creative", "communication skills", "time management", "interpersonal"], "languages_combined": [{"language": "cantonese", "language_level": ["good command"]}, {"language": "english", "language_level": ["good command"]}]}, "experience_required": {"duration": ["at least 5 years"], "field": ["restaurant", "designer", "design"]}}, {"job_id": "100003009053424", "location_code": "hk", "company": "Wams Design Limited", "job_title": "Senior Designer/Interior Designer/Assistant Designer", "description": "Requirements:\n\nDegree or diploma holder in interior design, architecture or\u00a0equivalent;\nAt least 3 years relevant experience in design and construction (office, retail, F&B & residential etc.);\nProficiency in AutoCAD / Sketch up / Photoshop / Enscape3D is a must;\nCreative design concept, strong presentation and drawing skills are essential;\nTake charge of delivering full set of interior design drawings, from concept, details, tender document to construction documents and relevant materials;\nPartake in presentations and meetings to interpret design direction and requirements of projects;\nManages time and workload of own work efforts and those of others to meet project task deadlines and commitments, with occasional interaction and direction from team leaders while guiding and teaching less experienced staff, with leadership skill to lead design team to meet deadlines of projects in timely manner and assist design director to set out project goals and design directives;\nClosely coordinate with stakeholders, such as end users, internal team members, senior management, contractors, suppliers, vendors and sub-contractors to ensure the project is executed smoothly;\nFamiliar with Hong Kong building regulations, and able to prepare interior drawings and tender sets would be an advantage;\nOpen-minded as well as having excellent communication and interpersonal skills and with high level of aesthetic flair;\nSite experience and immediate availability is preferred;\n\nCandidates with less experience in interior design will be considered as Assistant Interior Designer/ Draftsman.\nWe offer competitive package and promising career prospect to the right candidate.\nInterested parties please send detailed resume, portfolio and expected salary quoting the corresponding position by clicking \u201cApply Now\u201d.", "employment_types": ["Full Time", "Permanent"], "selling_points": [], "locations": ["Wan Chai"], "categories": ["Design", "Graphics", "Interior", "Visual Merchandising"], "post_time": "2022-01-17T06:58:05Z", "salary": {"currency": null, "max": null, "min": null, "period": "monthly", "term": null}, "salary_visible": false, "title_keywords": ["senior designer", "interior designer", "assistant designer"], "responsibilities": ["regulations", "design drawings", "design concept", "design", "presentations", "drawings", "communication", "architecture", "coordinate with stakeholders", "tender", "senior management", "tender document"], "requirements": {"degrees": ["diploma holder", "degree"], "majors": ["architecture", "design"], "languages": [], "language_level": [], "hard_skills": ["creative design", "presentations", "autocad", "sketch up", "photoshop"], "soft_skills": ["open-minded", "timely", "communication and interpersonal skills", "leadership skill", "creative", "meet deadlines", "presentation"], "languages_combined": []}, "experience_required": {"duration": ["at least 3 years"], "field": ["designer", "design", "f&b", "relevant experience", "retail", "construction"]}}, {"job_id": "100003009031271", "location_code": "hk", "company": "IF Interior Designs & Contracting Co", "job_title": "Senior Interior Designer  /  Designer  /  Assistant Designer", "description": "Degree holder or Diploma in interior design\u00a0\nProficient in CAD (Photoshop, Sketch Up, 3D Max are bonus)\nGood team-player who is initiative, creative, self-motivated, willing to work in a fast paced and demanding environment\nGood in presentation skills\nGood Leadership Skills\nAt least 3 year working experience\u00a0 **Less experience consider as Assistant Interior Designer**\nStrong sense of design and be able to handle full set of drawing with detailing design\nWork independent", "employment_types": ["Full Time", "Permanent"], "selling_points": [], "locations": ["Causeway Bay"], "categories": ["Design", "Interior", "Others"], "post_time": "2022-01-17T07:43:03Z", "salary": {"currency": null, "max": null, "min": null, "period": "monthly", "term": null}, "salary_visible": false, "title_keywords": ["designer", "senior interior designer", "assistant designer"], "responsibilities": ["design"], "requirements": {"degrees": ["diploma", "degree holder"], "majors": ["design"], "languages": [], "language_level": [], "hard_skills": ["sketch up", "cad", "max", "photoshop"], "soft_skills": ["self-motivated", "independent", "team-player", "leadership skills", "presentation skills", "creative", "initiative"], "languages_combined": []}, "experience_required": {"duration": ["at least 3 year"], "field": ["designer"]}}, {"job_id": "100003009048555", "location_code": "hk", "company": "INO Design Limited", "job_title": "Interior Designer", "description": "Requirements:\n\n2 \u2013 6 years of experience in Retail, Commercial or Residential design experience\nProficiency in AutoCAD, 3D Max, Photoshop or Sketch up\nCapability of handling and producing of full set drawings\nMust be detail oriented and show leadership qualities\nHardworking, self-motivated, organized, independent and able to meet deadlines\nResponsible and able to work under pressure\nImmediate availability preferred\nCandidate with less experience will be considered as Assistant Designer\n\nResponsibilities:\n\nPreparation of all presentation materials, including design concept, space planning for all layout and selection of materials\nResponsible for all design drawings, detail drawings & time schedule planning\nCommunicate and coordinate with clients and sub-contractors\nCoordination of site handover and supervise fitting-out progress\n\nFor Interested candidates, please send full resume with expected salary via email or by clicking \u201cApply Now\u201d or contact Ms Wong at 2513-5112 for interview arrangement.\n\nWelcome to visit our website www.ifinterior.com.hk for more information.\n\nPersonal data collected will be used for recruitment purpose only.", "employment_types": ["Full Time", "Permanent"], "selling_points": [], "locations": ["Wan Chai Area"], "categories": ["Building & Construction", "Architectural Services", "Design", "Interior", "Others"], "post_time": "2022-01-16T21:50:00Z", "salary": {"currency": null, "max": null, "min": null, "period": "monthly", "term": null}, "salary_visible": false, "title_keywords": ["interior designer"], "responsibilities": ["detail drawings", "design drawings", "design concept", "coordinate with clients", "schedule", "coordination", "planning"], "requirements": {"degrees": [], "majors": [], "languages": [], "language_level": [], "hard_skills": ["sketch up", "max", "photoshop", "autocad"], "soft_skills": ["organized", "self-motivated", "independent", "responsible", "detail oriented", "meet deadlines", "leadership", "hardworking", "work under pressure"], "languages_combined": []}, "experience_required": {"duration": ["6 years"], "field": ["commercial", "retail", "designer", "design"]}}, {"job_id": "100003009047677", "location_code": "hk", "company": "Greyscale Limited", "job_title": "Assistant Interior Designer / Interior Designer / Design Graduate", "description": "Diploma / Degree in Interior or Architectural Design\nMinimum 5 - 8 years relevant experience\nExperience in design will be an advantage Office, Retail and Restaurant\u00a0\nProficiency in AutoCAD, Photoshop, PowerPoint, Microsoft Office, 3D\nSelf-motivate and work independent, good communication with client, familiar to project procedure\nAvailable immediately\n\nBenefits:\n\n5 Days work\u00a0\nDouble Pay\nPerformance bonus\n12 days Annual Leave \u00a0\n\nInterested parties please send your resume in details with last/current and expected salary\u00a0by \"Clicking Apply Now\" or by clicking \u201cApply Now\u201d.\n\nPersonal data will be used for recruitment purpose only.", "employment_types": ["Full Time", "Permanent"], "selling_points": ["Interior design", "Designer", "Project designer"], "locations": ["Lai Chi Kok"], "categories": ["Building & Construction", "Architectural Services", "Design", "Interior"], "post_time": "2022-01-16T21:50:20Z", "salary": {"currency": null, "max": null, "min": null, "period": "monthly", "term": null}, "salary_visible": false, "title_keywords": ["interior designer", "assistant interior designer"], "responsibilities": ["communication", "design"], "requirements": {"degrees": ["diploma", "degree"], "majors": ["design"], "languages": [], "language_level": [], "hard_skills": ["microsoft office", "photoshop", "powerpoint", "autocad"], "soft_skills": ["communication", "independent"], "languages_combined": []}, "experience_required": {"duration": ["minimum 5 - 8 years"], "field": ["restaurant", "retail", "relevant experience", "design"]}}, {"job_id": "100003009053444", "location_code": "hk", "company": "BOKA Design", "job_title": "Interior Designer / Assistant Interior Designer", "description": "We are looking for a young and enthusiastic Assistant Interior Designer / Interior Designer / Design Graduate with the following requirements:-\n\nCalibre\n\nA team player with a can-do attitude\nWilling to learn, self-motivated, and able to work independently under pressure\nGood presentation skills\nMature, independent, strong problem solving and analytical skills\nLast of all, passionate about interiors !\u00a0\n\nRequirements\n\nDegree / Diploma in Interior Design/ Architecture / Interior Architecture\u00a0\nMinimum 0 -3 years of interior design experience in commercial\u00a0 projects\nProficient in Revit, AutoCAD, Sketchup, Photoshop, Endscape.\u00a0\u00a0\nProficient in spoken and written English and Chinese\n\nWe offer great working hour flexibility and attractive remuneration packages commensurate with experience and qualifications. If you aspire to an exciting and adventurous career, send your resume immediately, quoting your present and expected salaries to our email address.\u00a0\n\nApplicants not hearing from us within six weeks from the date of advertisement may consider their applications unsuccessful. Information provided by applicants will be treated in strict confidence and used for recruitment purposes only.", "employment_types": ["Full Time", "Permanent"], "selling_points": ["Passion for design, have your own unique style", "Proficiency in AutoCAD, Photoshop, 3D Max", "Develop design concept and presentation"], "locations": ["Kwun Tong"], "categories": ["Building & Construction", "Architectural Services", "Design", "Graphics", "Interior"], "post_time": "2022-01-17T06:59:39Z", "salary": {"currency": null, "max": null, "min": null, "period": "monthly", "term": null}, "salary_visible": false, "title_keywords": ["interior designer", "assistant interior designer"], "responsibilities": ["architecture", "design"], "requirements": {"degrees": ["diploma", "degree"], "majors": ["architecture", "design"], "languages": ["english", "chinese"], "language_level": ["proficient"], "hard_skills": ["sketchup", "analytical skills", "problem solving", "autocad", "photoshop", "revit"], "soft_skills": ["self-motivated", "work independently", "under pressure", "independent", "can-do attitude", "willing to learn", "mature", "problem solving and analytical skills", "presentation skills", "enthusiastic", "team player", "passionate about"], "languages_combined": [{"language": "english", "language_level": ["proficient"]}, {"language": "chinese", "language_level": ["proficient"]}]}, "experience_required": {"duration": ["minimum 0 -3 years"], "field": ["commercial", "design"]}}, {"job_id": "100003009051563", "location_code": "hk", "company": "Hong Kong Interior Design Architecture Limited", "job_title": "Interior design Instructor (Part time)", "description": "The Role\n\nAs an\u00a0Incredible\u00a0Interior Designer in Interspace, you will work with the senior members of our company to prepare presentation packages and attend presentations for our workplace design bidding, specify materials and references, and develop plans and drawings for our ongoing projects. You will work collaboratively with our Assistant Designers to deliver amazing workplace designs for our clients.\n\nThis mid to senior-level position offers the potential to manage the design process for mid-sized (or larger) projects independently. Candidates with less experience may be offered an Assistant Interior Designer position. Career progression to a Project Designer/Design Manager position is the next step for ambitious teammates.\n\nSince we are a Design & Build company with our own fitting out team, you will gain unique experience unavailable at typical design consultancies: bid estimation, construction project management, materials sourcing and procurement, and a deep understanding of technical/shop drawings for all trades.\u00a0\n\nThe Hard Part\n\nDo you have what it takes to join our team?\n\n1 -\u00a0 \u00a0 You graduated from a university-level program with a bachelor's degree in Interior Design or Architecture and you have at least 5 full years experience working in the interior design field handing workplace projects in Hong Kong. Exceptional candidates without degrees will still be considered.\n\n2 -\u00a0 \u00a0 You can communicate in English confidently. We would prefer if you can also speak Cantonese and Mandarin.\n\n3 -\u00a0 \u00a0\u00a0You have plenty of practical experience using both AutoCAD and SketchUp in a team/collaborative studio (there are no solo warriors here).\n\n4 -\u00a0 \u00a0 You are an over achiever with above-average intelligence and a highly creative sense of design.\n\n5 -\u00a0 \u00a0 You ask questions constantly and aren't afraid to defend your belief/position, but you can also accept when you're wrong and learn from it!\n\nIf you can say \"yes\" to all five of the qualifications above, then Apply now\u00a0for a chance to interview with our Creative Director and visit our amazing studio!\u00a0\n\nPlease note, we are committed to running an inclusive, healthy, and safe workplace -- every one of our teammates has been vaccinated against COVID-19, and we expect the same from all new team members.\n", "employment_types": ["Full Time", "Part Time"], "selling_points": [], "locations": ["Mong Kok"], "categories": ["Building & Construction", "Architectural Services", "Design", "Interior", "Others"], "post_time": "2022-01-16T10:49:54Z", "salary": {"currency": null, "max": null, "min": null, "period": "hourly", "term": null}, "salary_visible": false, "title_keywords": [], "responsibilities": ["presentations", "drawings", "design", "project management", "develop plans", "architecture"], "requirements": {"degrees": ["degree", "bachelor"], "majors": ["architecture", "design"], "languages": ["cantonese", "english", "mandarin"], "language_level": [], "hard_skills": ["no", "presentations", "project management", "safe", "autocad", "sketchup"], "soft_skills": ["independently", "deep", "collaborative", "unique", "project management", "committed", "creative", "presentation"], "languages_combined": [{"language": "cantonese", "language_level": []}, {"language": "english", "language_level": []}, {"language": "mandarin", "language_level": []}]}, "experience_required": {"duration": [], "field": ["designer", "procurement", "design", "project management", "construction", "team"]}}, {"job_id": "100003009054984", "location_code": "hk", "company": "Royal Kitchen Design Co. Ltd", "job_title": "Assistant kitchen Designer", "description": "Responsibilities:\n\nDevelop design concept, layouts and material board\nPrepare presentation with concept pictures, drawings and other tools to showcase the design\nLiaise with construction team members, suppliers and contractors\u00a0\nHandle projects with our on-site supervisor, communication with construction team\n\nRequirements:\u00a0\n\nPassion for design, willing to go for extra miles to accomplish the smallest details in your design\nHave your own unique style, have the guts to challenge the status quo / what is trendy / what the customers want\nAble to handle multi-tasks under deadline and lead tasks with different members of the team\nGood command of AutoCAD, Photoshop, 3D Max is an advantage\nDegree or diploma holder in Interior Design or Architecture is great but not a must\nAt least 3-5 years of design experience in residential / commercial field, less experience can be considered as assistant designer\n\nInterested candidates please send us the followings by email or click \"Apply Now'.\n\nFull resume\nPersonal portfolio if any\nPresent / expected salary\nAnything you would like to share with us\n\nWe offer flexible working hours, attractive remuneration package, career advancement, various project opportunities to the right candidate.\n\n(Personal data collected will be used for recruitment purpose only.) Please visit our facebook page for more information: www.facebook.com/bokadesignhk", "employment_types": ["Full Time"], "selling_points": ["Diploma Holder in interior design", "Fresh Graduate Welcome", "Double Pay, employee discount"], "locations": ["Wan Chai"], "categories": ["Design", "Graphics", "Interior", "Others"], "post_time": "2022-01-17T16:22:45Z", "salary": {"currency": "HKD", "max": 24999, "min": 17000, "period": "monthly", "term": null}, "salary_visible": true, "title_keywords": ["designer", "assistant"], "responsibilities": ["design concept", "design", "drawings", "develop", "communication", "liaise with"], "requirements": {"degrees": ["diploma holder", "degree"], "majors": ["architecture", "design"], "languages": [], "language_level": [], "hard_skills": ["max", "go", "photoshop", "autocad"], "soft_skills": ["multi-tasks", "unique", "passion for"], "languages_combined": []}, "experience_required": {"duration": ["at least 3-5 years"], "field": ["commercial", "designer", "design"]}}, {"job_id": "100003009053602", "location_code": "hk", "company": "Manly-Tech Engineering Limited", "job_title": "BIM Modeller / Senior BIM Modeller / BIM Co-ordinator / BIM Engineer", "description": "Job responsibilities:\n\n\nConduct tutorial lessons\nPrepare materials for classes\n\nJob requirements:\n\nDegree holder in related disciplines\nAt least three years working experience in the field\n\nGood knowledge in Hand sketch / AutoCAD / Sketchup + V-Ray / 3DsMax + V-Ray (at least two of them)\nFamilier with all drawing software is highly preferred\nPatient, positive and passionate about education\nBe enthusiastic and dynamic\nExcellent presentation and communication skill\nAble to teaching in English or Mandarin is a plus\nImmediate availability is preferred\n\nCampus:\u00a0Mongkok Campus\n\nWebsite: www.hkiai.com.hk\n\nInterested candidates should send us academic background, portfolio and expected salary.\u00a0", "employment_types": ["Full Time", "Permanent", "Contract"], "selling_points": ["Preferably 1-2 years BIM working experience", "Passionate learner will also be considered", "5 days work & Bonus"], "locations": ["Kwun Tong"], "categories": ["Design", "Interior", "Engineering", "Draftsman", "Building & Construction", "Others"], "post_time": "2022-01-17T07:13:15Z", "salary": {"currency": null, "max": null, "min": null, "period": "monthly", "term": null}, "salary_visible": false, "title_keywords": ["bim modeller", "engineer"], "responsibilities": [], "requirements": {"degrees": ["degree holder"], "majors": ["related disciplines"], "languages": ["english", "mandarin"], "language_level": [], "hard_skills": ["plus", "dynamic", "sketchup", "autocad"], "soft_skills": ["communication skill", "dynamic", "positive", "enthusiastic", "patient", "presentation", "passionate about"], "languages_combined": [{"language": "english", "language_level": []}, {"language": "mandarin", "language_level": []}]}, "experience_required": {"duration": ["at least three years"], "field": []}}, {"job_id": "100003009051650", "location_code": "hk", "company": "MAD Studio Limited", "job_title": "Interior Designer", "description": "Responsibilities :\n\n\n\nPrepare drawing packages and details for design projects\nPrepare of 2D/ 3D drawings and familiar with CAD modeling, preferably with\u00a0\u00a0Interior Design project experience\u00a0\nResponsible for site supervision and coordination\nAble to work independently\n\nRequirements:\n\nMinimum 1-2 years' relevant experience / Fresh Graduate also Welcome\u00a0\nResidential project experience preferred\nDiploma in Interior Designer\nGood communication skill\nGood command in AutoCAD, photoshop\u00a0\nAble to work under tight schedule\nImmediate availability is preferred\n\nPlease send full CV with expected salary by clicking \u2018Apply Now\u2019.\n\n\n(Data collected will be used for recruitment purpose only)", "employment_types": ["Full Time", "Permanent"], "selling_points": ["minimum 3 years of interior design experience", "flexible working hours", "exposure of handling a whole design project"], "locations": ["Aberdeen"], "categories": ["Design", "Interior"], "post_time": "2022-01-16T20:19:38Z", "salary": {"currency": null, "max": null, "min": null, "period": "monthly", "term": null}, "salary_visible": false, "title_keywords": ["interior designer"], "responsibilities": ["coordination", "site supervision", "design", "drawings"], "requirements": {"degrees": ["diploma", "fresh graduate"], "majors": [], "languages": [], "language_level": [], "hard_skills": ["photoshop", "autocad"], "soft_skills": ["communication skill"], "languages_combined": []}, "experience_required": {"duration": ["minimum 1-2 years"], "field": ["relevant experience"]}}, {"job_id": "100003009016680", "location_code": "hk", "company": "Play Concept Limited", "job_title": "Architect 5 days work in Lai Chi Kok", "description": "Job Responsibilities:\n\n\nResponsible for technical project drawing, create, maintain or amend BIM models of different disciplines. (Architectural, Structural & MEP).\nCollaborate and coordinate with clients and consultants on BIM issues,\u00a0design changes and model changes\nAttend and assist in project coordination meetings\nModify and advise on altering design, variations and changes\nClash Analysis & Detection\n\nRequirements:\n\nDegree/Diploma holders in Building Services / Electrical / Mechanical / Architecture or any other related discipline\n\nPassionate in Architectural/Structural/MEP Engineering field\nGood knowledge of AutoCAD, Revit, Civil 3D and Navisworks\nPreferably 1-2 years BIM working experience\nPassionate learner without experience will also be considered\nAssociate of HKIBIM is preferred\nMust be organised, results driven and proactive.\nExcellent interpersonal and negotiation skills", "employment_types": ["Full Time", "Permanent"], "selling_points": ["Degree / Diploma holder in Architectural Design", "1-2 years experience", "Strong Analytical Skills in Planning & Design"], "locations": ["Lai Chi Kok"], "categories": ["Building & Construction", "Architectural Services", "Design", "Graphics", "Interior"], "post_time": "2022-01-17T16:20:51Z", "salary": {"currency": null, "max": null, "min": null, "period": "monthly", "term": null}, "salary_visible": false, "title_keywords": [], "responsibilities": ["collaborate", "project coordination", "analysis", "design", "coordinate with clients", "maintain"], "requirements": {"degrees": ["diploma", "degree"], "majors": ["building services", "architecture"], "languages": [], "language_level": [], "hard_skills": ["revit", "bim", "autocad"], "soft_skills": ["passionate", "driven", "negotiation skills", "organised", "proactive", "interpersonal"], "languages_combined": []}, "experience_required": {"duration": ["1-2 years"], "field": []}}, {"job_id": "100003009054119", "location_code": "hk", "company": "Hong Kong Baptist University", "job_title": "Assistant Officer (Project Management and Development Planning) (PR0476/21-22)", "description": "MAD Studio Limited\n\nWong Chuk Hang\n\nSalary negotiable\n\nImmediate available will be an advantage\n\nMAD Studio Limited is an architectural interior design studio focusing on residential, commercial and educational projects. We are based in Hong Kong where we have projects going on both in Hong Kong and China.\n\nWe are looking for motivated, experienced and talented candidate to join our team for company expansion.\n\nResponsibilities:\n\n- Conceptual design\n\n- Produce or assist in construction drawing sets\n\n- Materials Board assembly\n\n- Liaison with suppliers and follow through with Ordering\n\n- Site visits and follow up with communication with contractors\n\n- Assist in presentation with Clients\n\nSkills and Qualifications:\n\n- Degree / Higher Diploma in interior design or related field\n\n- Proficient in AutoCAD, ArchiCAD, SketchUp, Rhino, Microsoft Office, Photoshop, and rendering with Vray or 3Ds Max. Extra skill sets would be considered as an advantage\n\n- Good command of spoken and written English and Chinese (including Cantonese and Mandarin)\n\n- Min. 3 years relevant working experience, suitable candidates with less experience will be considered as Assistant Interior Designer.\n\nCharacteristics we are looking for:\n\n- A team player\n\n- Problem solving and responsible with given tasks\n\n- Deadline orientated\n\nFive-day\u2019s work a week, birthday leave, MPF contribution and performance bonus will be provided to the right candidate.\n\nInterested candidates please submit your application by clicking \u201cAPPLY NOW\u201d with Full Resume (PDF format), Expected Salary and Availability to us.\u00a0", "employment_types": ["Full Time"], "selling_points": ["A degree in Architectural Design", "Proficiency in computer applications", "Support the PMDP Section on design"], "locations": ["Kowloon City"], "categories": ["Building & Construction", "Architectural Services", "Design", "Interior"], "post_time": "2022-01-17T08:28:01Z", "salary": {"currency": null, "max": null, "min": null, "period": "monthly", "term": null}, "salary_visible": false, "title_keywords": ["assistant officer"], "responsibilities": ["communication", "design"], "requirements": {"degrees": ["diploma", "degree"], "majors": ["design"], "languages": ["cantonese", "english", "chinese", "mandarin"], "language_level": ["good command"], "hard_skills": ["3ds max", "rhino", "educational projects", "microsoft office", "problem solving", "autocad", "photoshop", "mad", "sketchup"], "soft_skills": ["responsible", "communication", "problem solving", "motivated", "team player", "presentation"], "languages_combined": [{"language": "cantonese", "language_level": ["good command"]}, {"language": "english", "language_level": ["good command"]}, {"language": "chinese", "language_level": ["good command"]}, {"language": "mandarin", "language_level": ["good command"]}]}, "experience_required": {"duration": ["3 years"], "field": ["designer", "relevant working experience"]}}, {"job_id": "100003009051388", "location_code": "hk", "company": "Codeco Technology Limited", "job_title": "Junior Interior Designer (high commission)", "description": "Degree / Diploma holder in Architectural Design or equivalent with a\u00a0passion for design and creativity.\nMust demonstrate initiative and willing to develop.\nFresh graduate/ final year student preferred but not exclusive.\nSome experience preferred (1-2 years).\nStrong Analytical Skills in Planning & Design with Site Experience is\u00a0Preferred.\nUnderstands the art of guiding a project from concept to implementation\nProficiency in AutoCAD, SketchUp (VRay), Photoshop is a MUST.\nResponsibilities will include site visits, production of drawing packages,\u00a0design development, coordination with clients, and consultants.\n\u00a0We offer five-day work, comfortable good working environment, attractive salary, bonus, annual holiday. Interested parties are invited to send their applications with full employment history, current and expected salary in the subject and by clicking \"Apply Now\"", "employment_types": ["Full Time", "Permanent"], "selling_points": ["Start-up environment, fun and challenging", "We redefine renovation with tech and creativity", "Medical, birthday, training benefits, etc."], "locations": ["Hung Hom"], "categories": ["Design", "Interior", "Sales, CS & Business Devpt", "Technical Sales / Sales Engineer", "Direct Sales"], "post_time": "2022-01-15T13:32:21Z", "salary": {"currency": null, "max": null, "min": null, "period": "monthly", "term": null}, "salary_visible": false, "title_keywords": ["interior designer", "junior"], "responsibilities": ["coordination with", "implementation", "design", "develop", "planning"], "requirements": {"degrees": ["diploma holder", "degree", "fresh graduate"], "majors": ["design"], "languages": [], "language_level": [], "hard_skills": ["autocad", "sketchup", "photoshop", "analytical skills"], "soft_skills": ["coordination", "initiative", "analytical skills", "passion for"], "languages_combined": []}, "experience_required": {"duration": ["1-2 years"], "field": ["design", "analytical", "planning"]}}, {"job_id": "100003009054652", "location_code": "hk", "company": "T.O.P Contracting Limited", "job_title": "Draftsman", "description": "ESTATES OFFICE\n\nAssistant Officer (Project Management and Development Planning) (PR0476/21-22)\n\nThe University is seeking a dynamic, focused professional in built environment to join the Estates Office.\n\nThe appointee will join a team of professionals under the Project Management and Development Planning Section (PMDP) for the implementation of the University\u2019s capital projects, as well as alteration, addition and improvement works that often require inhouse design involvement.\u00a0 He/She, representing the Estates Office, will liaise with end-user departments, consultants and other outside bodies on matters relating to project execution and campus planning and development.\n\nResponsibilities:\n\nSupport the PMDP Section on design and feasibility studies and take part in design presentation including drawings, rendering and data visualisation as well as production of working drawings, specifications, tender documents and other project-control documents for campus improvement works;\nLiaise with end-user departments to understand their spatial needs for project delivery;\nAssist the Section with project management duties, including coordination with consultants, contractors and suppliers for execution of works contracts for the University; and\nCoordinate with the Cost and Contract Management Section of the Estates Office and internal departments regarding cost/budget-related issues.\nRequirements:\n\nA degree in Architectural Design, Interior Design or related disciplines with at least two years of relevant experience;\nProficiency in computer applications for design presentation including AutoCAD, Photoshop and SketchUp; with knowledge of Revit being an advantage;\nStrong communication skills in both written and spoken English and Chinese; and\nCreative, pleasant, service-orientated, responsible, self-motivated, and able to work collaboratively and independently.\nApplicants with less experience/qualification or year-out intern of architectural course with demonstrably strong aptitude will also be considered for appointment.\n\nShortlisted candidates will be invited to sit for a written/drawing skills test.\n\nInitial appointment will be offered on a fixed-term contract of two years. Re-appointment thereafter will be subject to mutual agreement and availability of funding.\n\nSalary will be commensurate with qualifications and experience.\n\nApplication Procedure:\n\nApplicants are invited to submit their applications at the HKBU e-Recruitment System (jobs.hkbu.edu.hk). Those not invited for interview 8 weeks after the closing date may consider their applications unsuccessful. Details of the University\u2019s Personal Information Collection Statement can be found at\u00a0http://hro.hkbu.edu.hk/pics.\n\nThe University reserves the right not to make an appointment for the post advertised, and the appointment will be made according to the terms and conditions then applicable at the time of offer.\n\nClosing date: 31 January 2022", "employment_types": ["Full Time", "Permanent"], "selling_points": [], "locations": ["Kowloon Bay"], "categories": ["Design", "Interior", "Building & Construction", "Building / Construction / QS", "Engineering", "Engineering Project Management"], "post_time": "2022-01-17T10:24:55Z", "salary": {"currency": null, "max": null, "min": null, "period": "monthly", "term": null}, "salary_visible": false, "title_keywords": ["draftsman"], "responsibilities": ["control", "cost", "design presentation", "data", "tender documents", "contracts", "coordination with", "coordinate with", "contract management", "design", "drawings", "budget", "project management", "specifications", "liaise with"], "requirements": {"degrees": ["degree"], "majors": ["related disciplines", "design"], "languages": ["english", "chinese"], "language_level": [], "hard_skills": ["sketchup", "make", "autocad", "photoshop", "revit"], "soft_skills": ["communication skills", "self-motivated", "independently", "responsible", "pleasant", "creative", "presentation"], "languages_combined": [{"language": "english", "language_level": []}, {"language": "chinese", "language_level": []}]}, "experience_required": {"duration": ["at least two years"], "field": ["related", "relevant experience", "design"]}}, {"job_id": "100003009052567", "location_code": "hk", "company": "The Hong Kong Jockey Club", "job_title": "Project Support Manager", "description": "Responsibilities\n\nPrepare 2D technical CAD drawings, 3D knowledge is an advantage;\nIndependently handle full set of residential and commercial construction drawings;\nOrganise and prepare interior design presentation;\nFollow up client's requirements and convert the leads into orders;\nBuild and enhance customer relationship;\nLiaise with internal parties to maximise sales performance and smooth operations;\nAssist in other ad-hoc assignments as required;\nDirect report to Sales Director.\nRequirements\n\nDiploma / Associate / Bachelor of Interior Design or equivalent;\nGood command in AutoCAD, Sketch up and common office software;\nGood presentation and communication skills;\nCustomer-oriented and responsible;\nSelf-motivated, hardworking, organised, outgoing;\nAble to work under pressure and independently;\n5-day work week on roster is required, including weekends;\nAble to standby anytime in responding to customers;\nGood command of Cantonese, Mandarin and English;\nImmediate available is preferred.", "employment_types": ["Full Time", "Contract"], "selling_points": ["Degree in interior design / building studies", "10 years experience in project management", "Knowledge in AutoCAD and MS Project"], "locations": ["Causeway Bay"], "categories": ["Building & Construction", "Architectural Services", "Design", "Interior", "Building / Construction / QS"], "post_time": "2022-01-17T03:26:08Z", "salary": {"currency": null, "max": null, "min": null, "period": null, "term": null}, "salary_visible": false, "title_keywords": ["project support manager"], "responsibilities": ["design presentation", "sales performance", "operations", "ad-hoc assignments", "drawings", "liaise with", "internal parties", "report"], "requirements": {"degrees": ["diploma", "bachelor"], "majors": ["design"], "languages": ["cantonese", "english", "mandarin"], "language_level": ["good command"], "hard_skills": ["sketch up", "office software", "autocad"], "soft_skills": ["outgoing", "communication skills", "self-motivated", "independently", "responsible", "customer-oriented", "organised", "presentation", "hardworking", "work under pressure"], "languages_combined": [{"language": "cantonese", "language_level": ["good command"]}, {"language": "english", "language_level": ["good command"]}, {"language": "mandarin", "language_level": ["good command"]}]}, "experience_required": {"duration": [], "field": []}}, {"job_id": "100003009052316", "location_code": "hk", "company": "Charlotte Tilbury Beauty Asia Pacific Limited", "job_title": "Store Designer APAC", "description": "Form 5 / DSE\u00a0 or Higher Certificate holder\nMinimum\u00a01-2 years\u00a0drafting experience or above\nProficient in Auto CAD is a must\nGood knowledge of shop drawing & detailed drawing preparation\nSelf-motivated, well-organized and able to work under pressure\nGood communications skills with clients & sub-contractors\nWith general knowledge on computer operation Microsoft Office.\nImmediate available is preferred\nFresh graduate will also be considered\n\n\nWe offer an attractive remuneration packages (Basis salary + Bonus + Medical Scheme) to successful candidates with various promotion opportunities.\n\nInterested parties please apply with full resume that stated your expected salary and date of availability by mail to\u00a0Administration Department, Unit 08-09, 1/F, Fook Hong Industral Building, 19 Sheung Yuet Road, Kowloon Bay, Hong Kong\u00a0or visit our homepage http://www.topcontracting.com.hk or by clicking \"Apply Now\".\n\nPersonal data collected will be used for recruitment purpose only.", "employment_types": ["Full Time", "Permanent"], "selling_points": [], "locations": ["Central"], "categories": ["Design", "Interior", "Visual Merchandising"], "post_time": "2022-01-17T02:44:04Z", "salary": {"currency": null, "max": null, "min": null, "period": "monthly", "term": null}, "salary_visible": false, "title_keywords": ["designer"], "responsibilities": ["work under pressure"], "requirements": {"degrees": ["fresh graduate", "form 5", "higher certificate", "dse"], "majors": [], "languages": [], "language_level": [], "hard_skills": ["auto cad", "microsoft office"], "soft_skills": ["work under pressure", "self-motivated", "well-organized", "detailed"], "languages_combined": []}, "experience_required": {"duration": ["minimum 1-2 years"], "field": []}}, {"job_id": "100003009047149", "location_code": "hk", "company": "SEN Construction Company Limited", "job_title": "Interior Designer / Assistant Interior Designer", "description": "The Department\n\nOur Property Department commits to provide integrated, customer-centric, sustainable and cost effective asset management, development management, project management and facilities management services to the key Business Units in the Club.\n\nThe Job\nYou will:\n\n\nAssist the Facilities Services Manager (Corporate) to lead the project team comprising of external consultants, contractors and suppliers as well as internal cross-divisional groups\nProvide professional advice on alternations and renovations of existing facilities, and construction of new facilities under the surveillance of the Corporate Team\nUnderstand the needs and operational requirement from relevant stakeholders. Liaison with drawing office / design consultants to ensure the design fulfills these needs and requirements\nCoordinate the office restacking project arrangement and ensure the compliance with the project timeline, internal and external regulations and Corporate Workplace Standard\nConduct feasibility studies and evaluations to identify possible project strategies and solutions\nAssist in the preparation of design briefs, Terms of Reference and tender documents for recruitment of consultants and vendors\nProvide assistance on preparation of expenditure authorisation proposal, approval memo, variation work(s) application and other approval paper / document\nMonitor and control project progress and expenditures against approved programmes and budgets to ensure that the projects are accomplished in time, within budget and to required quality\nManage and supervise contractors and suppliers during all stages of a project to ensure that quality and safety standards are met\nManage and supervise members of the project team to ensure effective and efficient deployment of resources\nPrepare timely and accurate management reports to keep Facilities Services Manager (Corporate) informed on the operational performance of the Project Team with the goal of ensuring continuous improvement\nAbout You\nYou should have:\n\n\na degree in interior design / building studies / construction management / engineering / architectural or related discipline\nminimum 10 years relevant experience in project management, prior working experience in Corporate Office renovation projects will be an advantage\nknowledge in AutoCAD and MS Project with hands-on experience in using MS Office applications\ngood communication and coordination skills\nexcellent command of spoken and written English and Chinese\nTerms of Employment\nThe level of appointment will be commensurate with qualifications and experience.\nHow to Apply\nPlease send your resume, complete with expected salary and job reference by clicking the Apply Now button or to:\u00a0\nFax: 2966-7002\nMail: The Human Resources Department, The Hong Kong Jockey Club, 1 Sports Road, Happy Valley, Hong Kong\n\nWe are an equal opportunity employer. Personal data provided by job applicants will be used strictly in accordance with the Club's notice to employees and prospective employees relating to the Personal Data (Privacy) Ordinance. A copy of which will be provided immediately upon request.", "employment_types": ["Full Time"], "selling_points": ["\u505a\u5927\u54c1\u724c\u5e97\u8216\u88dd\u4fee\u8a2d\u8a08, \u589e\u52a0\u500b\u4eba\u7d93\u9a57\u503c", "Double pay", "\u7531\u4e2d\u74b0\u6e2f\u9435\u5230\u516c\u53f8, \u53ea\u8981\u6b65\u884c5\u5206\u9418"], "locations": ["Central"], "categories": ["Design", "Interior", "Visual Merchandising", "Others"], "post_time": "2022-01-14T02:28:08Z", "salary": {"currency": "HKD", "max": 34999, "min": 14000, "period": "monthly", "term": null}, "salary_visible": true, "title_keywords": ["interior designer", "assistant interior designer"], "responsibilities": ["regulations", "supervise contractors", "memo", "budget", "quality", "renovation", "design", "communication", "personal data", "control", "tender documents", "compliance", "monitor", "project progress", "provide assistance", "cost", "management", "construction management", "budgets", "coordinate", "project management", "design briefs", "management reports", "recruitment", "coordination", "safety standards", "asset management"], "requirements": {"degrees": ["degree"], "majors": ["construction management", "building studies", "engineering", "design"], "languages": ["english", "chinese"], "language_level": ["excellent"], "hard_skills": ["project management", "management reports", "goal", "facilities management", "deployment", "ms office", "autocad"], "soft_skills": ["efficient", "coordination skills", "timely", "communication", "project management", "hands-on", "accurate"], "languages_combined": [{"language": "english", "language_level": ["excellent"]}, {"language": "chinese", "language_level": ["excellent"]}]}, "experience_required": {"duration": ["minimum 10 years"], "field": ["project management", "relevant experience"]}}, {"job_id": "100003009050650", "location_code": "hk", "company": "\u5fae.\u5de5\u4f5c\u5ba4", "job_title": "Interior Design Assistant / Interior Designer \u5ba4\u5167\u8a2d\u8a08\u52a9\u7406 / \u5ba4\u5167\u8a2d\u8a08\u5e2b M.Studio \u5fae.\u5de5\u4f5c\u5ba4", "description": "The Role\n\nAs an\u00a0Awesome\u00a0Project Manager\u00a0in Interspace, you will work with our Directors to organize, manage, and build amazing workplace interiors for our demanding clients.\u00a0You will also communicate frequently with our sub-contractors, Site Supervisors, and designers to ensure that we stay on budget, on time, with top quality workmanship and safety. It will be your responsibility to ensure that our project delivery exceeds every metric for client satisfaction and profitability for our company.\n\nYou will have full\u00a0exposure to all aspects of the design and build process and have the opportunity to progress to a Senior Project Manager role or even become a Project Director in our team. Our cutting-edge \"co-working studio\" is the perfect place to develop your career and shape the future growth of our practice.\n\nThe Package\n\nSalary:\u00a0Subject to negotiation, depending on your experience and ability\n\nRaises/Promotions:\u00a0Assessed by the Directors on your employment anniversary\n\nBonus:\u00a0Performance-based (company + individual)\n\nWorking Days/Hours:\u00a0Monday to Friday, 9:00 AM to 6:00 PM\n\nAnnual Leave:\u00a012 days (same for everyone in Interspace)\n\nCompany Holidays:\u00a0Standard \"Bank Holidays\" (i.e. General Holidays)\n\nThe Hard Part\n\nDo you have what it takes to join our team?\n\n1 -\u00a0 \u00a0 You graduated from a university-level program with a bachelor's degree in a related field and you have at least 5\u00a0full years experience\u00a0working as a PM in the Design/Architecture Industry in Hong Kong. Exceptional candidates without degrees will still be considered. If you don't have sufficient experience, you may be offered an interview for Assistant Project Manager.\n\n2 -\u00a0 \u00a0 You can communicate in English and Cantonese\u00a0confidently in both spoken and written forms.\n\n\n3 -\u00a0 \u00a0\u00a0You have plenty of practical experience using\u00a0Microsoft Project\u00a0or any cloud-based project management application\u00a0in a team/collaborative environment (there are no solo warriors here).\n\n4 -\u00a0 \u00a0 You are an over achiever with above-average intelligence and a highly creative approach to problem solving.\n\n5 -\u00a0 \u00a0 You ask questions constantly and aren't afraid to defend your belief/position, but you can also accept when you're wrong and learn from it!\n\nIf you can say\u00a0\"yes\"\u00a0to all five of the qualifications above, then\u00a0Apply now\u00a0for a chance to interview and visit our amazing studio!\u00a0", "employment_types": ["Full Time"], "selling_points": [], "locations": ["Lai Chi Kok"], "categories": ["Design", "Interior"], "post_time": "2022-01-15T03:51:13Z", "salary": {"currency": null, "max": null, "min": null, "period": "monthly", "term": null}, "salary_visible": false, "title_keywords": ["interior designer", "assistant", "\u5ba4\u5167\u8a2d\u8a08\u52a9\u7406"], "responsibilities": ["budget", "quality", "design", "develop", "project management", "architecture"], "requirements": {"degrees": ["degree", "bachelor"], "majors": ["architecture", "design"], "languages": ["cantonese", "english"], "language_level": [], "hard_skills": ["problem solving", "project management", "no", "microsoft project"], "soft_skills": ["negotiation", "cutting-edge", "collaborative", "problem solving", "project management", "creative"], "languages_combined": [{"language": "cantonese", "language_level": []}, {"language": "english", "language_level": []}]}, "experience_required": {"duration": [], "field": ["related", "project management", "design", "team"]}}, {"job_id": "100003009053794", "location_code": "hk", "company": "IMY Media Limited", "job_title": "\u63d2\u82b1\u5e2b", "description": "Degree or diploma holder in design or related disciplines\nMinimum\u00a01-3 years solid working experience\nFresh graduates or less experienced applicants may be considered as Junior designer\nExposure in the field of interior & graphic is a plus\nCompetency in Auto CAD, Photoshop and 3Ds Max or related\u00a0softwares\nGood visualization and presentation skills\nCreative and responsible\nProactive, a team player with good presentation\u00a0 and communication skills\nAbility to work independently\n\nWe offer a 5-day work week, including 12 days annual leave and double pay.\u00a0\u00a0\n\nInterested parties please send full resume with date of availability, present & expected salary and portfolio to email by clicking \"Apply Now\".\n\nPersonal data will be used for recruitment purposes only.", "employment_types": ["Part Time"], "selling_points": [], "locations": ["Tin Hau"], "categories": ["Others", "Agriculture / Forestry / Fishing", "Design", "Interior", "Others"], "post_time": "2022-01-17T07:31:32Z", "salary": {"currency": null, "max": null, "min": null, "period": "hourly", "term": null}, "salary_visible": false, "title_keywords": [], "responsibilities": ["communication", "visualization", "design"], "requirements": {"degrees": ["diploma holder", "degree"], "majors": ["related disciplines", "design"], "languages": [], "language_level": [], "hard_skills": ["plus", "auto cad", "3ds max", "photoshop"], "soft_skills": ["communication skills", "work independently", "proactive", "responsible", "presentation skills", "team player", "creative", "presentation"], "languages_combined": []}, "experience_required": {"duration": ["minimum 1-3 years"], "field": []}}, {"job_id": "100003008657115", "location_code": "hk", "company": "Egoart Design Workshop Limited", "job_title": "Senior Interior Designer / Interior Designer/Assistant", "description": "\u8077\u8cac:\n\n\u00a0\u00a0\u00a0\u00a0\u00a0\u00a0\u00a0\u00a0 \u5411\u4e0a\u7d1a/\u8a2d\u8a08\u7e3d\u76e3\u532f\u5831\u5de5\u4f5c\u9032\u5ea6\n\u00a0\u00a0\u00a0\u00a0\u00a0\u00a0\u00a0\u00a0 \u5ba4\u5167\u8a2d\u8a08\u76f8\u95dc\u5de5\u4f5c,\u00a0\u4e3b\u8981\u5354\u52a9\u8a2d\u8a08\u5e2b\u7e6a\u5236\u50a2\u4fec\u5716\u53ca\u5e73\u9762\u64fa\u4f4d\u5716\n\u00a0 \u00a0 \u00a0 \u00a0 \u00a0\u8655\u7406\u50a2\u4fec\u5716\u53ca\u65bd\u5de5\u5716\u7b49\u7e6a\u5716\u5de5\u4f5c\n\n\u8077\u4f4d\u8981\u6c42:\n\n\u00a0\u00a0\u00a0\u00a0\u00a0\u00a0\u00a0\u00a0 \u826f\u597d\u64cd\u4f5c\u00a0AutoCAD, MsOffice,\u00a0SketchUp, 3D Rendering\u00a0\n\u00a0\u00a0\u00a0\u00a0\u00a0\u00a0\u00a0\u00a0 \u6709\u7d44\u7e54\u529b\uff0c\u7368\u7acb\uff0c\u6ce8\u91cd\u7d30\u7bc0\uff0c\u8b19\u865b\u4e26\u4e14\u80fd\u5920\u5728\u5718\u968a\u4e2d\u826f\u597d\u5730\u5de5\u4f5c\n\u00a0\u00a0\u00a0\u00a0\u00a0\u00a0\u00a0\u00a0 \u5c0d\u8a2d\u8a08\u5145\u6eff\u71b1\u60c5\u00a0\n\u00a0 \u00a0 \u00a0 \u00a0 \u00a0\u6b61\u8fce\u61c9\u5c46\u7562\u696d\u751f\u7533\u8acb\n\n\u512a\u5148\u8003\u616e:\n\n\u00a0\u00a0\u00a0\u00a0\u00a0\u00a0\u00a0\u00a0 \u5ba4\u5167\u8a2d\u8a08\u8ab2\u7a0b\u7562\u696d\n\u00a0\u00a0\u00a0\u00a0\u00a0\u00a0\u00a0\u00a0 \u5ba4\u5167\u8a2d\u8a08\u76f8\u95dc\u5de5\u4f5c\u7d93\u9a57\n\u00a0 \u00a0 \u00a0 \u00a0 \u00a0\u66fe\u65bc\u50a2\u4fec\u8216\u5de5\u4f5c\u512a\u5148\n\u00a0\u00a0\u00a0\u00a0\u00a0\u00a0\u00a0\u00a0 \u61c23D Rendering\n\u00a0\u00a0\u00a0\u00a0\u00a0\u00a0\u00a0\u00a0 \u80fd\u7368\u7acb\u8655\u7406\u50a2\u4ff1\u65bd\u5de5\u5716\n\n\u5f85\u9047\u53ca\u798f\u5229:\n\n\u00a0\u00a0\u00a0\u00a0\u00a0\u00a0\u00a0\u00a0 \u6708\u85aa\u5f85\u9047\u00a0: $12,000-$30,000 (\u8996\u4e4e\u5de5\u4f5c\u7d93\u9a57\u800c\u5b9a)\n\u00a0\u00a0\u00a0\u00a0\u00a0\u00a0\u00a0\u00a0 \u516c\u53f8\u798f\u5229\u00a0:\u00a0\u9280\u884c\u5047\u671f,\u00a0\u826f\u597d\u6649\u5347\u6a5f\u6703\n\u00a0\u00a0\u00a0\u00a0\u00a0\u00a0\u00a0\u00a0 \u4e0a\u73ed\u5730\u9ede\u00a0:\u00a0\u8354\u679d\u89d2\n\u00a0\u00a0\u00a0\u00a0\u00a0\u00a0\u00a0\u00a0 \u5de5\u4f5c\u6642\u9593\u00a0: \u661f\u671f\u4e00\u81f3\u4e94\u53ca\u90e8\u5206\u661f\u671f\u516d 10:30 -19:30", "employment_types": ["Full Time"], "selling_points": [], "locations": ["Kwun Tong"], "categories": ["Building & Construction", "Architectural Services", "Design", "Graphics", "Interior"], "post_time": "2022-01-14T08:16:44Z", "salary": {"currency": null, "max": null, "min": null, "period": "monthly", "term": null}, "salary_visible": false, "title_keywords": ["interior designer", "senior interior designer", "assistant"], "responsibilities": ["3d rendering"], "requirements": {"degrees": [], "majors": [], "languages": [], "language_level": [], "hard_skills": ["sketchup", "msoffice", "autocad"], "soft_skills": [], "languages_combined": []}, "experience_required": {"duration": [], "field": []}}, {"job_id": "100003009045130", "location_code": "hk", "company": "Furniture Factory Limited", "job_title": "Interior Designer \u5ba4\u5167\u8a2d\u8a08\u5e2b", "description": "The Role\n\nAs an\u00a0Awesome\u00a0Site Supervisor\u00a0in Interspace, you will work with our project team and designers to manage site works, ensure quality workmanship, control site safety, and build amazing workplace interiors for our demanding clients. You will control the use of project site resources (e.g. cleaners, debris removal, demolition, movers), handle procurement for expendable site resources (e.g. protection materials, hoarding, safety gear, tools), and take leadership on daily and weekly scheduling of skilled labour.\u00a0\n\nYou will have full\u00a0exposure to all aspects of the design and build process and have the opportunity to progress to a Senior Site Supervisor / Site Manager and eventually a Construction Manager role in our team.\u00a0\n\nThe Package\n\nSalary:\u00a0HK$18,000\u00a0to\u00a0HK$26,000\u00a0per month, depending on experience and ability (exceptionally qualified Site Managers may be offered a higher salary subject to experience and references/referrals)\n\nRaises/Promotions:\u00a0Assessed by the Directors on your employment anniversary\n\nBonus:\u00a0Performance-based (company + individual)\n\nWorking Days/Hours:\u00a0Monday to Saturday (or alternative 6-days) , 9:00 AM to 6:00 PM\n\nAnnual Leave:\u00a012 days\n\nHolidays:\u00a0Statutory Holidays\n\nThe Hard Part\n\nDo you have what it takes to join our team?\n\n1 -\u00a0 \u00a0 You completed your\u00a0secondary school education and have earned a diploma in Building Services or any other related field, and you have at least\u00a03 full years experience\u00a0working in a general contracting company, design and build practise, or PM consultancy in Hong Kong as a Site Supervisor.\n\n2 -\u00a0 \u00a0 You can communicate in English and Cantonese\u00a0confidently.\n\n3 -\u00a0 \u00a0\u00a0You have plenty of practical experience reading and amending construction drawings.\n\n4 -\u00a0 \u00a0 You are an over achiever with above-average intelligence and a highly creative approach to problem solving.\n\n5 -\u00a0 \u00a0 You ask questions constantly and aren't afraid to defend your belief/position, but you can also accept when you're wrong and learn from it!\n\nIf you can say\u00a0\"yes\"\u00a0to all five of the qualifications above, then\u00a0Apply now\u00a0for a chance to interview and visit our amazing studio!\u00a0\n\nPlease note, we are committed to running an inclusive, healthy, and safe workplace -- every one of our teammates has been vaccinated against COVID-19, and we expect the same from all new team members.\n", "employment_types": ["Full Time"], "selling_points": ["$45000+", "\u5275\u65b0\uff0c\u6709\u5275\u9020\u529b\uff0c\u5c0d\u8a2d\u8a08\u5145\u6eff\u71b1\u60c5", "\u6709\u7d44\u7e54\u529b\uff0c\u7368\u7acb\uff0c\u6ce8\u91cd\u7d30\u7bc0\uff0c\u8b19\u865b\u4e26\u4e14\u80fd\u5920\u5728\u5718\u968a\u4e2d\u826f\u597d\u5730\u5de5\u4f5c"], "locations": ["Kwun Tong"], "categories": ["Design", "Interior"], "post_time": "2022-01-14T03:32:59Z", "salary": {"currency": null, "max": null, "min": null, "period": "monthly", "term": null}, "salary_visible": false, "title_keywords": ["interior designer"], "responsibilities": ["control", "quality", "design", "drawings", "scheduling", "contracting"], "requirements": {"degrees": ["diploma"], "majors": ["building services", "design"], "languages": ["cantonese", "english"], "language_level": [], "hard_skills": ["problem solving", "safe"], "soft_skills": ["problem solving", "committed", "creative", "leadership"], "languages_combined": [{"language": "cantonese", "language_level": []}, {"language": "english", "language_level": []}]}, "experience_required": {"duration": [], "field": ["related", "design", "education", "building services", "construction"]}}, {"job_id": "100003009044202", "location_code": "hk", "company": "J. Candice Interior Architects", "job_title": "Interior Designer / Junior Interior Designer / Draftsman", "description": "\n\u8077\u8cac :\u8ca0\u8cac\u63d2\u82b1\u53ca\u92b7\u552e\u82b1\u54c1\n\n\u8cc7\u6b77 :\u5c0f\u516d\u7a0b\u5ea6; 2\u5e74\u7d93\u9a57; \u4e00\u822c\u7cb5\u8a9e; \u4e00\u822c\u666e\u901a\u8a71; \u4e00\u822c\u82f1\u8a9e\n\n\u5f85\u9047 :\u6bcf\u5c0f\u6642$80.00 - $100.00, \u4e0a\u53489\u6642\u81f3\u4e0b\u534811\u6642, \u6bcf\u9031\u5de5\u4f5c5\u5929\u81f36\u5929,\u8f2a\u4f11, \u6bcf\u5929\u5de5\u4f5c 5 - 10 \u5c0f\u6642\n\n\u7533\u8acb\u9808\u77e5 :\u6c42\u8077\u8005\u53ef\u81f4\u96fb56143678\u8207\u570b\u4ed5\u5ee3\u544a\u50b3\u5a92\u6709\u9650\u516c\u53f8\u90ed\u5c0f\u59d0\u806f\u7d61\u3002\n\n", "employment_types": ["Full Time"], "selling_points": ["Good location - Kwun Tong (2mins walk from MTR)", "Good work environment and work-life balance", "Great opportunities in commercial F&B projects"], "locations": ["Kwun Tong"], "categories": ["Building & Construction", "Architectural Services", "Design", "Graphics", "Interior"], "post_time": "2022-01-13T03:51:19Z", "salary": {"currency": null, "max": null, "min": null, "period": "monthly", "term": null}, "salary_visible": false, "title_keywords": ["interior designer", "draftsman", "junior"], "responsibilities": [], "requirements": {"degrees": [], "majors": [], "languages": [], "language_level": [], "hard_skills": [], "soft_skills": [], "languages_combined": []}, "experience_required": {"duration": [], "field": []}}, {"job_id": "100003009048887", "location_code": "hk", "company": "Paliburg Group", "job_title": "Senior Interior Designer / Interior Designer", "description": "Egoart Design Workshop Limited\n\nWe are an expanding interior design firm, specialized on commercial and Shopping Mall projects. To cope with our continuous business growth and development, we are looking for smart and talented person to CREAT A New Design Team.\n\nSenior Interior Designer/ Interior Designer /Assistant\n\nResponsibilities\n\nResponsible for handling design and project development of design & built projects from concept stage to construction completion\nHandle full set of design presentation(i.e. space planning, conceptual design, sketching, material board and colour perspective drawings\nSite coordination with clients, contractors and sub-contractors\nGood knowledge on building material product.\nProficiency in communication and STRONG PRESENTATION SKILLS\nTechnical drawings with practical details in construction and quotation preparation is in advantage\nCreative, independent, self-motivated, responsible and good team player\u00a0\n\nRequirement:\n\nDegree or Higher Diploma in interior design or related disciplines\nAt least 8 years or above of working experience in interior design and fitting-out of shopping mall, residential, commercial projects etc.\nCreative, independent, self-motivated, good team player\nProficiency in both spoken and written English and Chinese; Mandarin is a definite advantage (project in China)\nProficient in AutoCAD & Sketch up, freehand perspectives and sketching is a MUST.\nStrong presentation skill to due with client\nImmediately available is preferred\n\nLess experience will be considered as Assistant Interior Designer\nAttractive remuneration package with annual bonus, group medical insurance and study allowance rewarding career prospects to the right candidate.\u00a0 Interested candidates please send full resume with current & expected salary (MUST) to us.", "employment_types": ["Full Time", "Permanent"], "selling_points": ["Experience in Hospitality and residential design", "AutoCad, Photoshop, 3D Studio Max", "Work independently"], "locations": ["Causeway Bay"], "categories": ["Building & Construction", "Architectural Services", "Design", "Interior"], "post_time": "2022-01-14T07:49:08Z", "salary": {"currency": null, "max": null, "min": null, "period": "monthly", "term": null}, "salary_visible": false, "title_keywords": ["interior designer", "senior interior designer"], "responsibilities": ["quotation", "design", "drawings", "communication", "site coordination", "technical drawings", "planning"], "requirements": {"degrees": ["diploma", "degree"], "majors": ["related disciplines", "design"], "languages": ["english", "chinese", "mandarin"], "language_level": ["advantage", "proficiency"], "hard_skills": ["sketch up", "presentation skill", "autocad"], "soft_skills": ["presentation skill", "good team player", "self-motivated", "independent", "creative"], "languages_combined": [{"language": "english", "language_level": ["proficiency"]}, {"language": "chinese", "language_level": ["proficiency"]}, {"language": "mandarin", "language_level": ["advantage"]}]}, "experience_required": {"duration": ["at least 8 years"], "field": ["commercial", "designer", "design"]}}, {"job_id": "100003009053404", "location_code": "hk", "company": "Hing Yip Engineering (International) Company Limited", "job_title": "Assistant Project Coordinator (Interior Design)", "description": "Responsibilities:\n\nAssist project managers and designers to coordinate project matters, schedule and report problems.\nTo manage, control and monitor of daily project works, instructions and progress\nCoordinate and liaise with sub-contractors, suppliers, and third party companies\nPrepare weekly progress report for project team and client\u2019s record\nAssist in other ad-hoc assignment\n\nRequirements:\u00a0\n\nDegree / Diploma in Building Studies / Construction Management / Engineering\u00a0or related discipline is an advantage but not a must\nAble to handle multi-tasks under pressure and deadline\nWilling to learn and attention to details\nGood computer literate (AutoCAD, Microsoft Word, Excel)\u00a0is a plus\nCandidates with less experience / Fresh Graduates are also considered\n\nInterested candidates please send us the followings by email or click \"Apply Now'.\n\nFull resume\nPresent / expected salary\nAnything you would like to share with us\n\nWe offer attractive remuneration package, career advancement, various project opportunities to the right candidate.\n\nPlease visit our interior design brand BOKA Design facebook page for more information: www.facebook.com/bokadesignhk\n\n(Personal data collected will be used for recruitment purpose only.)\n", "employment_types": ["Full Time"], "selling_points": ["Manage project fields, work schedule, reporting", "Liaise with designers, contractors, suppliers", "Prepare weekly progress report to project team"], "locations": ["Kwun Tong"], "categories": ["Design", "Interior", "Building & Construction", "Building / Construction / QS", "Engineering", "Engineering Project Management"], "post_time": "2022-01-17T06:55:51Z", "salary": {"currency": null, "max": null, "min": null, "period": "monthly", "term": null}, "salary_visible": false, "title_keywords": ["assistant project coordinator"], "responsibilities": ["ad-hoc", "control", "monitor", "coordinate", "schedule", "liaise with", "third party", "report"], "requirements": {"degrees": ["diploma", "degree"], "majors": ["construction management", "building studies", "engineering"], "languages": [], "language_level": [], "hard_skills": ["excel", "plus", "microsoft word", "autocad"], "soft_skills": ["willing to learn", "under pressure", "attention to details", "multi-tasks"], "languages_combined": []}, "experience_required": {"duration": [], "field": []}}, {"job_id": "100003009055445", "location_code": "hk", "company": "Matter Interiors Limited", "job_title": "PROJECT DESIGNER / INTERIOR DESIGNER", "description": "Requirements:\n\nDegree or diploma holder in interior design, architecture or\u00a0equivalent;\nAt least 3 years relevant experience in design and construction (office, retail, F&B & residential etc.);\nProficiency in AutoCAD / Sketch up / Photoshop / Enscape3D is a must;\nCreative design concept, strong presentation and drawing skills are essential;\nTake charge of delivering full set of interior design drawings, from concept, details, tender document to construction documents and relevant materials;\nPartake in presentations and meetings to interpret design direction and requirements of projects;\nManages time and workload of own work efforts and those of others to meet project task deadlines and commitments, with occasional interaction and direction from team leaders while guiding and teaching less experienced staff, with leadership skill to lead design team to meet deadlines of projects in timely manner and assist design director to set out project goals and design directives;\nClosely coordinate with stakeholders, such as end users, internal team members, senior management, contractors, suppliers, vendors and sub-contractors to ensure the project is executed smoothly;\nFamiliar with Hong Kong building regulations, and able to prepare interior drawings and tender sets would be an advantage;\nOpen-minded as well as having excellent communication and interpersonal skills and with high level of aesthetic flair;\nSite experience and immediate availability is preferred;\n\nCandidates with less experience in interior design will be considered as Assistant Interior Designer/ Draftsman.\nWe offer competitive package and promising career prospect to the right candidate.\nInterested parties please send detailed resume, portfolio and expected salary quoting the corresponding position by clicking \u201cApply Now\u201d.", "employment_types": ["Full Time", "Permanent"], "selling_points": [], "locations": ["Tsim Sha Tsui"], "categories": ["Design", "Interior"], "post_time": "2022-01-18T02:40:34Z", "salary": {"currency": null, "max": null, "min": null, "period": null, "term": null}, "salary_visible": false, "title_keywords": ["interior designer", "project designer"], "responsibilities": ["regulations", "design drawings", "design concept", "design", "presentations", "drawings", "communication", "architecture", "coordinate with stakeholders", "tender", "senior management", "tender document"], "requirements": {"degrees": ["diploma holder", "degree"], "majors": ["architecture", "design"], "languages": [], "language_level": [], "hard_skills": ["creative design", "presentations", "autocad", "sketch up", "photoshop"], "soft_skills": ["open-minded", "timely", "communication and interpersonal skills", "leadership skill", "creative", "meet deadlines", "presentation"], "languages_combined": []}, "experience_required": {"duration": ["at least 3 years"], "field": ["designer", "design", "f&b", "relevant experience", "retail", "construction"]}}, {"job_id": "100003009055026", "location_code": "hk", "company": "Interspace Limited", "job_title": "Interior Designer / Senior Interior Designer - Office / Workplace Design", "description": "The Role\n\nAs an\u00a0Incredible\u00a0Interior Designer in Interspace, you will work with the senior members of our company to prepare presentation packages and attend presentations for our workplace design bidding, specify materials and references, and develop plans and drawings for our ongoing projects. You will work collaboratively with our Assistant Designers to deliver amazing workplace designs for our clients.\n\nThis mid to senior-level position offers the potential to manage the design process for mid-sized (or larger) projects independently. Candidates with less experience may be offered an Assistant Interior Designer position. Career progression to a Project Designer/Design Manager position is the next step for ambitious teammates.\n\nSince we are a Design & Build company with our own fitting out team, you will gain unique experience unavailable at typical design consultancies: bid estimation, construction project management, materials sourcing and procurement, and a deep understanding of technical/shop drawings for all trades.\u00a0\n\nThe Hard Part\n\nDo you have what it takes to join our team?\n\n1 -\u00a0 \u00a0 You graduated from a university-level program with a bachelor's degree in Interior Design or Architecture and you have at least 5 full years experience working in the interior design field handing workplace projects in Hong Kong. Exceptional candidates without degrees will still be considered.\n\n2 -\u00a0 \u00a0 You can communicate in English confidently. We would prefer if you can also speak Cantonese and Mandarin.\n\n3 -\u00a0 \u00a0\u00a0You have plenty of practical experience using both AutoCAD and SketchUp in a team/collaborative studio (there are no solo warriors here).\n\n4 -\u00a0 \u00a0 You are an over achiever with above-average intelligence and a highly creative sense of design.\n\n5 -\u00a0 \u00a0 You ask questions constantly and aren't afraid to defend your belief/position, but you can also accept when you're wrong and learn from it!\n\nIf you can say \"yes\" to all five of the qualifications above, then Apply now\u00a0for a chance to interview with our Creative Director and visit our amazing studio!\u00a0\n\nPlease note, we are committed to running an inclusive, healthy, and safe workplace -- every one of our teammates has been vaccinated against COVID-19, and we expect the same from all new team members.\n", "employment_types": ["Full Time", "Permanent"], "selling_points": ["Design awesome workplaces to *WOW* our clients!", "Dynamic, intelligent, and happy colleagues.", "Crazy-cool design studio with chill BGM vibes."], "locations": ["Causeway Bay"], "categories": ["Building & Construction", "Architectural Services", "Design", "Interior"], "post_time": "2022-01-17T23:45:59Z", "salary": {"currency": null, "max": null, "min": null, "period": "monthly", "term": null}, "salary_visible": false, "title_keywords": ["interior designer", "senior interior designer"], "responsibilities": ["presentations", "drawings", "design", "project management", "develop plans", "architecture"], "requirements": {"degrees": ["degree", "bachelor"], "majors": ["architecture", "design"], "languages": ["cantonese", "english", "mandarin"], "language_level": [], "hard_skills": ["no", "presentations", "project management", "safe", "autocad", "sketchup"], "soft_skills": ["independently", "deep", "collaborative", "unique", "project management", "committed", "creative", "presentation"], "languages_combined": [{"language": "cantonese", "language_level": []}, {"language": "english", "language_level": []}, {"language": "mandarin", "language_level": []}]}, "experience_required": {"duration": [], "field": ["designer", "procurement", "design", "project management", "construction", "team"]}}, {"job_id": "100003009055028", "location_code": "hk", "company": "Interspace Limited", "job_title": "Project Manager - Interior Fitting Out / Office Design", "description": "The Role\n\nAs an\u00a0Awesome\u00a0Project Manager\u00a0in Interspace, you will work with our Directors to organize, manage, and build amazing workplace interiors for our demanding clients.\u00a0You will also communicate frequently with our sub-contractors, Site Supervisors, and designers to ensure that we stay on budget, on time, with top quality workmanship and safety. It will be your responsibility to ensure that our project delivery exceeds every metric for client satisfaction and profitability for our company.\n\nYou will have full\u00a0exposure to all aspects of the design and build process and have the opportunity to progress to a Senior Project Manager role or even become a Project Director in our team. Our cutting-edge \"co-working studio\" is the perfect place to develop your career and shape the future growth of our practice.\n\nThe Package\n\nSalary:\u00a0Subject to negotiation, depending on your experience and ability\n\nRaises/Promotions:\u00a0Assessed by the Directors on your employment anniversary\n\nBonus:\u00a0Performance-based (company + individual)\n\nWorking Days/Hours:\u00a0Monday to Friday, 9:00 AM to 6:00 PM\n\nAnnual Leave:\u00a012 days (same for everyone in Interspace)\n\nCompany Holidays:\u00a0Standard \"Bank Holidays\" (i.e. General Holidays)\n\nThe Hard Part\n\nDo you have what it takes to join our team?\n\n1 -\u00a0 \u00a0 You graduated from a university-level program with a bachelor's degree in a related field and you have at least 5\u00a0full years experience\u00a0working as a PM in the Design/Architecture Industry in Hong Kong. Exceptional candidates without degrees will still be considered. If you don't have sufficient experience, you may be offered an interview for Assistant Project Manager.\n\n2 -\u00a0 \u00a0 You can communicate in English and Cantonese\u00a0confidently in both spoken and written forms.\n\n\n3 -\u00a0 \u00a0\u00a0You have plenty of practical experience using\u00a0Microsoft Project\u00a0or any cloud-based project management application\u00a0in a team/collaborative environment (there are no solo warriors here).\n\n4 -\u00a0 \u00a0 You are an over achiever with above-average intelligence and a highly creative approach to problem solving.\n\n5 -\u00a0 \u00a0 You ask questions constantly and aren't afraid to defend your belief/position, but you can also accept when you're wrong and learn from it!\n\nIf you can say\u00a0\"yes\"\u00a0to all five of the qualifications above, then\u00a0Apply now\u00a0for a chance to interview and visit our amazing studio!\u00a0", "employment_types": ["Full Time", "Permanent"], "selling_points": ["Are you an AWESOME Project Manager w/fit out exp?", "Want to work in the COOLEST workplace in HK?", "Be part of the winning team. Apply Now!"], "locations": ["Causeway Bay"], "categories": ["Building & Construction", "Architectural Services", "Design", "Interior", "Building / Construction / QS"], "post_time": "2022-01-17T23:51:38Z", "salary": {"currency": null, "max": null, "min": null, "period": "monthly", "term": null}, "salary_visible": false, "title_keywords": ["project manager"], "responsibilities": ["budget", "quality", "design", "develop", "project management", "architecture"], "requirements": {"degrees": ["degree", "bachelor"], "majors": ["architecture", "design"], "languages": ["cantonese", "english"], "language_level": [], "hard_skills": ["problem solving", "project management", "no", "microsoft project"], "soft_skills": ["negotiation", "cutting-edge", "collaborative", "problem solving", "project management", "creative"], "languages_combined": [{"language": "cantonese", "language_level": []}, {"language": "english", "language_level": []}]}, "experience_required": {"duration": [], "field": ["related", "project management", "design", "team"]}}, {"job_id": "100003009055240", "location_code": "hk", "company": "Mindscape Interior Architecture Limited", "job_title": "Furniture designer (5-day work & double pay)", "description": "Degree or diploma holder in design or related disciplines\nMinimum\u00a01-3 years solid working experience\nFresh graduates or less experienced applicants may be considered as Junior designer\nExposure in the field of interior & graphic is a plus\nCompetency in Auto CAD, Photoshop and 3Ds Max or related\u00a0softwares\nGood visualization and presentation skills\nCreative and responsible\nProactive, a team player with good presentation\u00a0 and communication skills\nAbility to work independently\n\nWe offer a 5-day work week, including 12 days annual leave and double pay.\u00a0\u00a0\n\nInterested parties please send full resume with date of availability, present & expected salary and portfolio to email by clicking \"Apply Now\".\n\nPersonal data will be used for recruitment purposes only.", "employment_types": ["Full Time", "Permanent"], "selling_points": ["Degree or diploma holder in design", "junior designer", "5-day work week"], "locations": ["North Point"], "categories": ["Building & Construction", "Architectural Services", "Design", "Interior", "Others"], "post_time": "2022-01-18T01:54:40Z", "salary": {"currency": null, "max": null, "min": null, "period": "monthly", "term": null}, "salary_visible": false, "title_keywords": ["designer"], "responsibilities": ["communication", "visualization", "design"], "requirements": {"degrees": ["diploma holder", "degree"], "majors": ["related disciplines", "design"], "languages": [], "language_level": [], "hard_skills": ["plus", "auto cad", "3ds max", "photoshop"], "soft_skills": ["communication skills", "work independently", "proactive", "responsible", "presentation skills", "team player", "creative", "presentation"], "languages_combined": []}, "experience_required": {"duration": ["minimum 1-3 years"], "field": []}}, {"job_id": "100003009055030", "location_code": "hk", "company": "Interspace Limited", "job_title": "Site Supervisor (\u5730\u76e4\u7ba1\u5de5) / Site Manager - Interior Fit Out for Offices", "description": "The Role\n\nAs an\u00a0Awesome\u00a0Site Supervisor\u00a0in Interspace, you will work with our project team and designers to manage site works, ensure quality workmanship, control site safety, and build amazing workplace interiors for our demanding clients. You will control the use of project site resources (e.g. cleaners, debris removal, demolition, movers), handle procurement for expendable site resources (e.g. protection materials, hoarding, safety gear, tools), and take leadership on daily and weekly scheduling of skilled labour.\u00a0\n\nYou will have full\u00a0exposure to all aspects of the design and build process and have the opportunity to progress to a Senior Site Supervisor / Site Manager and eventually a Construction Manager role in our team.\u00a0\n\nThe Package\n\nSalary:\u00a0HK$18,000\u00a0to\u00a0HK$26,000\u00a0per month, depending on experience and ability (exceptionally qualified Site Managers may be offered a higher salary subject to experience and references/referrals)\n\nRaises/Promotions:\u00a0Assessed by the Directors on your employment anniversary\n\nBonus:\u00a0Performance-based (company + individual)\n\nWorking Days/Hours:\u00a0Monday to Saturday (or alternative 6-days) , 9:00 AM to 6:00 PM\n\nAnnual Leave:\u00a012 days\n\nHolidays:\u00a0Statutory Holidays\n\nThe Hard Part\n\nDo you have what it takes to join our team?\n\n1 -\u00a0 \u00a0 You completed your\u00a0secondary school education and have earned a diploma in Building Services or any other related field, and you have at least\u00a03 full years experience\u00a0working in a general contracting company, design and build practise, or PM consultancy in Hong Kong as a Site Supervisor.\n\n2 -\u00a0 \u00a0 You can communicate in English and Cantonese\u00a0confidently.\n\n3 -\u00a0 \u00a0\u00a0You have plenty of practical experience reading and amending construction drawings.\n\n4 -\u00a0 \u00a0 You are an over achiever with above-average intelligence and a highly creative approach to problem solving.\n\n5 -\u00a0 \u00a0 You ask questions constantly and aren't afraid to defend your belief/position, but you can also accept when you're wrong and learn from it!\n\nIf you can say\u00a0\"yes\"\u00a0to all five of the qualifications above, then\u00a0Apply now\u00a0for a chance to interview and visit our amazing studio!\u00a0\n\nPlease note, we are committed to running an inclusive, healthy, and safe workplace -- every one of our teammates has been vaccinated against COVID-19, and we expect the same from all new team members.\n", "employment_types": ["Full Time", "Permanent"], "selling_points": ["Supervise fit-out for commercial offices", "Control site health, safety, and work schedule", "Incredible experience and future career growth!"], "locations": ["Causeway Bay"], "categories": ["Building & Construction", "Architectural Services", "Design", "Interior", "Building / Construction / QS"], "post_time": "2022-01-17T23:52:17Z", "salary": {"currency": null, "max": null, "min": null, "period": "monthly", "term": null}, "salary_visible": false, "title_keywords": ["manager", "site supervisor"], "responsibilities": ["control", "quality", "design", "drawings", "scheduling", "contracting"], "requirements": {"degrees": ["diploma"], "majors": ["building services", "design"], "languages": ["cantonese", "english"], "language_level": [], "hard_skills": ["problem solving", "safe"], "soft_skills": ["problem solving", "committed", "creative", "leadership"], "languages_combined": [{"language": "cantonese", "language_level": []}, {"language": "english", "language_level": []}]}, "experience_required": {"duration": [], "field": ["related", "design", "education", "building services", "construction"]}}, {"job_id": "100003009053223", "location_code": "hk", "company": "Spazio Design Studio Limited", "job_title": "Sales & Marketing Manager (Interior Design)", "description": "Furniture Factory \u50a2\u4fec\u62fc\u62fc\n\nInterior Designer \u5ba4\u5167\u8a2d\u8a08\u5e2b\n\n\u6708\u5165$15000 - $45000+\n\n\n\n\n\u5de5\u4f5c\u91cd\u9ede\n\n\u2022 \u826f\u597d\u6649\u5347\u6a5f\u6703\n\n\u2022 \u975e\u5e38\u512a\u8cea\u5de5\u4f5c\u74b0\u5883\n\n\u2022 \u5718\u968a\u5de5\u4f5c\n\n\n\n\n\u5d17\u4f4d\u8077\u8cac\n\n\u2022 \u5411\u4e0a\u7d1a / \u8a2d\u8a08\u7e3d\u76e3\u532f\u5831\u5de5\u4f5c\u9032\u5ea6\n\n\u2022 \u5ba4\u5167\u8a2d\u8a08\u76f8\u95dc\u5de5\u4f5c\uff0c\u5305\u62ec\u8207\u5ba2\u6703\u9762\uff0c\u7e6a\u5716\uff0c\u5de5\u7a0b\u8ddf\u9032\n\n\n\n\n\u8077\u4f4d\u8981\u6c42\n\n\u2022 \u4e2d\u4e94\u6703\u8003\u7562\u696d / \u4e2d\u516d\u6587\u6191\u8a66\u7562\u696d\n\n\u2022 \u6d41\u66a2\u5ee3\u6771\u8a71\uff1b \u4e00\u822c\u82f1\u8a9e\uff1b\u7565\u61c2\u8b80\u5beb\u4e2d\u6587\uff1b\u7565\u61c2\u8b80\u5beb\u82f1\u6587\n\n\u2022 2-3 \u5e74\u6216\u4ee5\u4e0a\u76f8\u95dc\u5de5\u4f5c\u7d93\u9a57\n\n\u2022 \u826f\u597d\u64cd\u4f5c AutoCAD, OFFICE, SketchUp, 3D Rendering\n\n\u2022 \u6709\u7d44\u7e54\u529b\uff0c\u7368\u7acb\uff0c\u6ce8\u91cd\u7d30\u7bc0\uff0c\u8b19\u865b\u4e26\u4e14\u80fd\u5920\u5728\u5718\u968a\u4e2d\u826f\u597d\u5730\u5de5\u4f5c\n\n\u2022 \u5275\u65b0\uff0c\u6709\u5275\u9020\u529b\uff0c\u5c0d\u8a2d\u8a08\u5145\u6eff\u71b1\u60c5\n\n\n\n\n\u512a\u5148\u8003\u616e\n\n\u2022 \u5ba4\u5167\u8a2d\u8a08\u8ab2\u7a0b\u7562\u696d\n\n\u2022 \u5ba4\u5167\u8a2d\u8a08\u76f8\u95dc\u5de5\u4f5c\u7d93\u9a57\n\n\u2022 \u61c23D Rendering\n\n\u2022 \u80fd\u7368\u7acb\u8655\u7406\u50a2\u4ff1\u65bd\u5de5\u5716\n\n\n\n\n\u5f85\u9047\u53ca\u798f\u5229\n\n\u2022 \u6708\u85aa\u5f85\u9047 : $15000 - $18000\n\n\u2022 \u4f63\u91d1\u5b89\u6392 : \u9762\u8b70\uff08$0 - $30000+\uff09\n\n\u2022 \u5de5\u4f5c\u6642\u9593 : 9:30 - 18:30\n\n\u2022 \u6bcf\u6708\u4f8b\u5047\uff1a6\u5929\n\n\u2022 \u516c\u53f8\u798f\u5229 : \u751f\u65e5\u5047\uff0c\u9280\u884c\u5047\u671f\uff0c\u516c\u53f8\u5b9a\u671f\u6d3b\u52d5\uff0c\u826f\u597d\u6649\u5347\u6a5f\u6703\n\n\u2022 \u4e0a\u73ed\u5730\u9ede : \u89c0\u5858\n\n\n\n\n\u8077\u4f4d\u7533\u8acb\u8005\u8acb\u63d0\u4ea4\u3008\u500b\u4eba\u5c65\u6b77\u3009\u53ca\u3008\u4f5c\u54c1\u96c6\u3009\n\n\n\n\n\u50f1\u4e3b\u540d\u7a31 : \u50a2\u4fec\u62fc\u62fc\u6709\u9650\u516c\u53f8\n\n----------------------------------------------\n\nInterior Designer\n\nMonthly income $15000 - $45000+\n\nMLA\n\n\u2022 Good promotion opportunities\n\n\u2022 Very high quality work environment\n\n\u2022 teamwork\n\nJob Responsibilities\n\n\u2022 Report work progress to superior/design director\n\n\u2022 Interior design related work, including client meeting, drawing, project follow-up\n\nJob Requirements\n\n\u2022 Graduated from Secondary Form 5 or above\n\n\u2022 Fluent in Speaking Cantonese; General English; Slightly fluent in reading and writing Chinese / English\n\n\u2022 2-3 years or more of relevant work experience\n\n\u2022 Good operation with AutoCAD, OFFICE, SketchUp, 3D Rendering\n\n\u2022 Organized, independent, detail-oriented, humble and able to work well in teams\n\n\u2022 Innovative, creative and passionate about design\n\npriority\n\n\u2022 Graduated interior design program\n\n\u2022 Interior design related work experience\n\n\u2022 Understand 3D Rendering\n\n\u2022 Able to handle furniture construction drawings independently\n\nTreatment and benefits\n\n\u2022 Monthly Salary: $15000 - $18000\n\n\u2022 Commission Arrangement: Negotiable ($0 - $30000+)\n\n\u2022 Working hours : 9:30 - 18:30\n\n\u2022 Monthly leave: 6 days\n\n\u2022 Company benefits : Bonus, birthday leave, bank holidays, regular company events, good promotion opportunities\n\n\u2022 Working place : Kwun Tong\n\nJob applicants please submit with \"CV\" and \"portfolio\"\n\nName of Employer : Furniture Factory Co., Ltd.", "employment_types": ["Full Time", "Permanent"], "selling_points": ["Sales & Marketing, Business Development", "Interior Design, B2B", "1-3 years experince"], "locations": ["Wan Chai"], "categories": ["Sales, CS & Business Devpt", "Business Development", "Design", "Interior", "Building & Construction", "Building / Construction / QS"], "post_time": "2022-01-17T06:28:50Z", "salary": {"currency": null, "max": null, "min": null, "period": "monthly", "term": null}, "salary_visible": false, "title_keywords": ["sales & marketing manager"], "responsibilities": ["design", "report"], "requirements": {"degrees": ["form 5 or above"], "majors": [], "languages": ["cantonese", "english", "chinese"], "language_level": ["fluent"], "hard_skills": ["sketchup", "autocad"], "soft_skills": ["organized", "independently", "independent", "creative", "detail-oriented", "innovative", "passionate about"], "languages_combined": [{"language": "cantonese", "language_level": ["fluent"]}, {"language": "english", "language_level": ["fluent"]}, {"language": "chinese", "language_level": ["fluent"]}]}, "experience_required": {"duration": ["2-3 years"], "field": ["related", "design"]}}, {"job_id": "100003009053459", "location_code": "hk", "company": "Kidulteam Limited", "job_title": "Product / GraphicDesigner", "description": "\nJ. Candice Interior Architects\n\nInterior Designer /\u00a0Junior Interior\u00a0Designer\u00a0/ Draftsman\n\nJOB DESCRIPTION:\n\nConceptual design and detailing\nPrepare full set of construction drawings and detailed drawings\nCreate 3D model in SketchUp / 3D Max\nPrepare presentation boards and brochure\nMaterial and furniture selections\n\nJOB REQUIREMENT:\n\nF.5/ Diploma holder/ University Degree in Interior Design or related discipline\nAt least 3 years or above experience in interior design field\nHigh proficiency in AutoCAD, SketchUp, Photoshop, Illustrator, Freehand, Detailed Drawings (3D Max is a plus)\nAbility to hand sketch is an advantage\nGood command of written English and Chinese\nGood spoken English,\u00a0Cantonese\u00a0and Mandarin\nStrong creative and layout sense\nResponsible, SELF-DRIVEN, good communication skill, well organised, hardworking with TEAM\u00a0SPIRIT\nGood communication and organisation skill\nAble to work under pressure and INDEPENDENTLY\nAvailable: Immediate\u00a0\n\nInterested candidates please click\u00a0APPLY NOW\u00a0to send letter, portfolio, resume and expected salary to J. Candice interior architects.", "employment_types": ["Full Time"], "selling_points": [], "locations": ["Not Specified"], "categories": ["Design", "Graphics", "Interior", "Others"], "post_time": "2022-01-17T07:00:39Z", "salary": {"currency": null, "max": null, "min": null, "period": "monthly", "term": null}, "salary_visible": false, "title_keywords": [], "responsibilities": ["design", "drawings"], "requirements": {"degrees": ["diploma holder", "university degree"], "majors": ["design"], "languages": ["cantonese", "english", "chinese", "mandarin"], "language_level": ["good command", "good"], "hard_skills": ["plus", "illustrator", "autocad", "photoshop", "max", "sketchup"], "soft_skills": ["team spirit", "organisation skill", "independently", "responsible", "work under pressure", "communication skill", "communication", "organised", "creative", "driven", "hardworking", "detailed"], "languages_combined": [{"language": "cantonese", "language_level": ["good"]}, {"language": "english", "language_level": ["good command", "good", "good"]}, {"language": "chinese", "language_level": ["good command", "good"]}, {"language": "mandarin", "language_level": ["good"]}]}, "experience_required": {"duration": ["at least 3 years"], "field": ["design"]}}, {"job_id": "100003009051452", "location_code": "hk", "company": "City Chain Company Limited", "job_title": "Senior Project Officer", "description": "Degree or Diploma holder in Interior Design\nMinimum 3 to 8 years relevant experience\nExperience in Hospitality and residential design\nExcellent conceptual design and presentation skills\nProficiency in AutoCad, Photoshop, 3D Studio Max and proficiency in sketch-up\nAble to prepare full set of construction drawings independently\nExperience in site coordination and able to control projects on schedule\nSkilful in designing hospitality carpet and pattern is a merit\nAble to design with freehand sketch is an advantage\nStrong self-motivation, reliability & good organization skill\nFluent written and spoken in English & Chinese\nCandidate with more experience will be considered as Senior Interior Designer\nWe offer attractive remuneration package to the right candidate. Please click \u201cApply Now\u201d to submit your full resume with present and expected salaries.\nAll personal data / information provided by applicants to the Paliburg Group is used for recruitment and related purpose(s) only.\nWe are an Equal Opportunities Employer.", "employment_types": ["Full Time"], "selling_points": ["Responsible for store project", "Prioritize manage and track multiple", "3 years solid experience"], "locations": ["Wong Tai Sin Area"], "categories": ["Design", "Interior", "Visual Merchandising"], "post_time": "2022-01-16T00:29:46Z", "salary": {"currency": null, "max": null, "min": null, "period": null, "term": null}, "salary_visible": false, "title_keywords": ["senior project officer"], "responsibilities": ["control", "design", "drawings", "site coordination", "schedule", "designing"], "requirements": {"degrees": ["diploma holder", "degree"], "majors": ["design"], "languages": ["english", "chinese"], "language_level": ["fluent"], "hard_skills": ["max", "photoshop", "autocad"], "soft_skills": ["independently", "organization skill", "presentation skills", "self-motivation", "coordination"], "languages_combined": [{"language": "english", "language_level": ["fluent"]}, {"language": "chinese", "language_level": ["fluent"]}]}, "experience_required": {"duration": ["minimum 3 to 8 years"], "field": ["relevant experience", "designer", "design"]}}, {"job_id": "100003009047749", "location_code": "hk", "company": "PTang Studio Ltd", "job_title": "Senior Interior Designer", "description": "Job Responsibilities:\nIdentify and explore new business opportunities to achieve business target\nCreate workplace strategies and engage clients to increase business growth by delivering sales presentations and preparing business proposal\nFocus on developing and maintaining strong relationship with existing and new clients\nCoordinate closely with design and project team during each phase of the project & implementation process\nUnderstand the requirements of clients to ensure their needs are being met\n\nRequirement:\n\nDiploma holder or above in Business, Marketing or related discipline\u00a0\nMinimum 1-3 years experience in related field\nSelf-motivated and able to work under pressure; Good interpersonal, presentation and communication skills\nOutgoing, good at building business relationship with\u00a0potential client\nAble to work under tight schedule and willing to work overtime\nProficiency in Word, Excel and PowerPoint\nFluent in English, Cantonese and Mandarin will be an advantage\nApplicants with less experience will be considered as Assistant Sales & Marketing Manager\nImmediate availability preferred\n\nWe offer an attractive remuneration\u00a0package including 5 days work\u00a0and a long-term career opportunities to the right candidate.\u00a0Interested parties please send your resume and portfolio with expected salary to Spazio Studio\u00a0by clicking \"Apply Now\".\u00a0 All information received will be used for recruitment purpose only.", "employment_types": ["Full Time"], "selling_points": ["Commercial & Residential Project", "Minimum 5 years relevant experience", "5 days work a week"], "locations": ["Shatin Area"], "categories": ["Building & Construction", "Architectural Services", "Design", "Interior"], "post_time": "2022-01-14T03:51:07Z", "salary": {"currency": null, "max": null, "min": null, "period": "monthly", "term": null}, "salary_visible": false, "title_keywords": ["senior interior designer"], "responsibilities": ["maintaining", "explore new business opportunities", "developing", "presentations", "design", "coordinate", "implementation"], "requirements": {"degrees": ["diploma holder"], "majors": ["business", "marketing"], "languages": ["cantonese", "english", "mandarin"], "language_level": ["advantage", "fluent"], "hard_skills": ["excel", "word", "powerpoint"], "soft_skills": ["outgoing", "communication skills", "self-motivated", "work overtime", "interpersonal", "presentation", "work under pressure"], "languages_combined": [{"language": "cantonese", "language_level": ["advantage", "fluent"]}, {"language": "english", "language_level": ["advantage", "fluent"]}, {"language": "mandarin", "language_level": ["advantage", "fluent"]}]}, "experience_required": {"duration": ["minimum 1-3 years"], "field": ["related", "marketing"]}}, {"job_id": "100003009049377", "location_code": "hk", "company": "ADO Limited", "job_title": "Interior Designer / Senior Interior Designer", "description": "\nKidulteam Ltd. is a character merchandise company which engaged in design, manufacturing, distributing and retailing of gifts and confectionery in Hong Kong and Mainland China. To copy with our business expansion, we are now looking for:\n\u2022 Degree or Higher Diploma in Graphic Design or related disciplines.\n\u2022 At least 3 years experiences in plush and giftware design.\n\u2022 Proficient and able to be hands-on with Illustrator, Freehand, Photoshop and Corel Draw etc.\nProduct design in bag/premium/3D skills/Comics experience a plus (not necessary).\nWe offer competitive salary and fringe benefits to the right candidate. Interested parties please forward your detailed resume stating your availability, current and expected salary to [via\u00a0 Apply Now ]\n\n", "employment_types": ["Full Time", "Permanent"], "selling_points": ["Interior design & Build, Architecture", "Have at least 2 years of Interior design", "Experience in high quality residential / office"], "locations": ["Tsuen Wan Area"], "categories": ["Building & Construction", "Architectural Services", "Design", "Interior"], "post_time": "2022-01-14T08:31:47Z", "salary": {"currency": null, "max": null, "min": null, "period": "monthly", "term": null}, "salary_visible": false, "title_keywords": ["interior designer", "senior interior designer"], "responsibilities": ["graphic design", "product design", "design"], "requirements": {"degrees": ["diploma", "degree"], "majors": ["related disciplines", "graphic design"], "languages": [], "language_level": [], "hard_skills": ["plus", "illustrator", "photoshop"], "soft_skills": ["hands-on"], "languages_combined": []}, "experience_required": {"duration": ["at least 3 years"], "field": ["product design", "design"]}}, {"job_id": "100003009040211", "location_code": "hk", "company": "Atelier Pacific Ltd", "job_title": "Project Designer / Assistant Designer", "description": "Responsibilities:\u00a0\n\n\nIndependently handle commercial / residential projects from design concept to construction completion.\nDevelop design concept, layouts, mood board, material sourcing & selection.\nHandle full sets of presentation & tender documentations.\nCoordinate & liaise with clients, contractors, vendors & project team members.\nResponsible, creative, independent, self-motivated & able to work under pressure.\nAble to work under tight schedule & meet deadlines.\n\nRequirements:\n\n\nDegree in Interior Design or Architectural Design.\nMinimum 5 years of experience or above in relevant field.\nStrong leadership experience & problem solving.\nIndependent, responsible, strong presentation & communication skills.\nProficiency in AutoCAD, Photoshop, PowerPoint & PC Software.\nMust handle full set of Design and Construction drawings.\nSite supervision and inspection.\nProficiency Spoken & Written in English, Chinese & Mandarin.\nWilling to travel .\nWork 5 days a week.\nImmediately available.\n\nWe offer attractive remuneration package and fringe benefit, good prospect and\u00a0to the right candidate.\u00a0Personal data collected will be used for recruitment purposes only.\n\nwww.ptangstudio.com\n\n", "employment_types": ["Full Time", "Permanent"], "selling_points": ["5 days works", "16 days annual leave", "Annual company outing"], "locations": ["North Point"], "categories": ["Building & Construction", "Architectural Services", "Design", "Interior", "Others"], "post_time": "2022-01-12T01:53:04Z", "salary": {"currency": null, "max": null, "min": null, "period": "monthly", "term": null}, "salary_visible": false, "title_keywords": ["assistant designer", "project designer"], "responsibilities": ["liaise with clients", "design concept", "tender documentations", "mood board", "coordinate", "develop", "schedule", "work under pressure"], "requirements": {"degrees": ["degree"], "majors": ["design"], "languages": ["english", "chinese", "mandarin"], "language_level": ["proficiency"], "hard_skills": ["powerpoint", "problem solving", "autocad", "pc", "photoshop"], "soft_skills": ["communication skills", "independent", "responsible", "problem solving", "leadership", "presentation"], "languages_combined": [{"language": "english", "language_level": ["proficiency"]}, {"language": "chinese", "language_level": ["proficiency"]}, {"language": "mandarin", "language_level": ["proficiency"]}]}, "experience_required": {"duration": ["minimum 5 years"], "field": []}}, {"job_id": "100003009039194", "location_code": "hk", "company": "Clifton Leung Design Workshop (CLDW)", "job_title": "Assistant Interior Designer (5-day)", "description": "\u00a0INTERIOR DESIGNER / SENIOR INTERIOR DESIGNER\n\nResponsibilities &\u00a0Requirements:\n\n\nExperience in high quality residential / office design & build projects would be a definite advantage\nGraduated with relevant academic qualifications\nHave at least 2 years of interior design / project management experience\nStrong in project management and communication with clients, consultants and contractors is a must\nBe able to handle full set of construction drawings with practical detailing & site co-ordination\nExperience on site supervision and able to handle site management independently\nBe able to work on CAD, 3D rendering, Photoshop and Powerpoint\nGood command in written and spoken Cantonese, Mandarin and English\nImmediately available is preferred\nCandidates with more working experience will be considered as Senior Interior Designer\n\n\nApplication Method:\n\nAttractive remuneration (including 5-day work, medical and MPF) will be offered to the successful candidate. Interested parties please email your full resume and portfolio completed with present and expected salaries and date available by clicking \u201cAPPLY NOW\u201d.\n\n(All personal data collected will be used for recruitment purpose only)", "employment_types": ["Full Time", "Permanent"], "selling_points": ["Attractive offer, 5-day work, Sketchup, AutoCAD", "Educational & travel allowance, performance bonus", "Responsible, fast learning, passion in design"], "locations": ["Central"], "categories": ["Design", "Interior", "Others", "Building & Construction", "Building / Construction / QS"], "post_time": "2022-01-12T23:26:08Z", "salary": {"currency": null, "max": null, "min": null, "period": "monthly", "term": null}, "salary_visible": false, "title_keywords": ["assistant interior designer"], "responsibilities": [], "requirements": {"degrees": [], "majors": [], "languages": ["cantonese", "english", "mandarin"], "language_level": ["good command"], "hard_skills": ["project management", "photoshop", "powerpoint", "cad"], "soft_skills": ["communication", "project management", "independently"], "languages_combined": [{"language": "cantonese", "language_level": ["good command"]}, {"language": "english", "language_level": ["good command"]}, {"language": "mandarin", "language_level": ["good command"]}]}, "experience_required": {"duration": ["at least 2 years"], "field": ["project management", "management", "designer", "design"]}}, {"job_id": "100003009047706", "location_code": "hk", "company": "Hero Design Studio Limited", "job_title": "Junior/Assistant Interior Designer", "description": "We are looking for a driven, passionate superstar to join Team Tilbury as our Store Designer.\u00a0 You will be involved in all aspects of creative store design and project manage \u2013 from design to approvals to suppliers recruitment to technical drawings development to production and installation. You will be part of a growing Store Design and VM team responsible for all APAC countries excluding China. You will thrive on the challenge of a fast-paced environment, and you will be able to use your previous experience as a Store Designer and Project Manager either in house or at an advertising agency to make great effect in our team. In your role, you will report to our Senior Store Design Manager and work cross functionally with the APAC & Global teams.\n\nKey Responsibility\n\nTo design new stores & renovations of existing stores following global design guidelines and standards.\nTo design in-store shopping experiences that fits local customers\u2019 needs & keep up with fast-changing retail market trend\nTo manage the design requirements from Landlord and other functions\nTo follow up approvals internally and externally\nTo update design drawings and work with suppliers on technical drawings.\nTo anticipate design issues and provide solutions to ensure stores are open as per timeline and budget\nTo work closely with internal teams on special projects such as Pop up stores, temporary stores in accordance with overall commercial strategy.\nTo control strictly and keep in line with budget planning.\nTo summarize & establish APAC store design guideline and keep update accordingly.\nTo carry out market trend studies\nTo develop & propose local store innovations to create increased customer relevance and optimize in-store experience\n\nSome attributes we are looking for:\n\nCreative thinking and agile to new ideas and ways of working\nBroad knowledge of M & E, technical details in production\nExperience of managing workflow between Global and Regional teams\nStrong teamwork and communication skills to feedback to stalk holders\nExperience of handling multiple projects and requests simultaneously.\nExperience of project management from design to supplier recruitment to TD to production and installation\nExperience of on-site supervision & snagging solutions\nStrong sense of time management and cost control\n\nJob Qualification\n\nRequirements\n\n\nArchitecture or interior design major\nProficient in using Auto CAD/ 3D Max/ Sketch up/Illustration/ Photo shop and Microsoft office\nFrequently in English and Chinese.\nMore than 5 years working experience in beauty brand company.", "employment_types": ["Full Time"], "selling_points": ["Diploma/Degree in Interior or Architectural Design", "Min. 1 year relevant exp. Proficiency in AutoCAD", "Passion for innovative and creative design"], "locations": ["Mong Kok"], "categories": ["Design", "Interior", "Sales, CS & Business Devpt", "Account Servicing"], "post_time": "2022-01-14T03:47:27Z", "salary": {"currency": null, "max": null, "min": null, "period": "monthly", "term": null}, "salary_visible": false, "title_keywords": ["assistant interior designer", "junior"], "responsibilities": ["ideas", "budget", "design", "communication", "technical drawings", "control", "budget planning", "teams", "develop", "installation", "management", "design drawings", "provide solutions", "on-site supervision", "guidelines", "project management", "recruitment", "cost control", "multiple projects"], "requirements": {"degrees": [], "majors": [], "languages": ["english", "chinese"], "language_level": [], "hard_skills": ["microsoft office", "auto cad", "sketch up", "max", "illustration"], "soft_skills": [], "languages_combined": [{"language": "english", "language_level": []}, {"language": "chinese", "language_level": []}]}, "experience_required": {"duration": ["5 years"], "field": ["brand", "beauty"]}}, {"job_id": "100003009051722", "location_code": "hk", "company": "S & J Interior Design Limited", "job_title": "Designer\u7d50\u69cb\u57f7\u884c\u8a2d\u8a08\u5e2b", "description": "Job Description\n\nDiploma / Degree in Interior or Architectural Design\nMinimum 1 year relevant experience\nExperience in high-end commercial and/or residential projects\nExcellent design skills and experience to manage design presentation and prepare technical drawing\nCoordinate with client and project management team from design stage to job completion\nFluent English, Cantonese and Mandarin is preferred;\nProficiency in AutoCAD and Photoshop, knowledge in PowerPoint and Microsoft Office is a plus\nCandidate with less working experience will consider as a designer\n\nWe offer attractive salaries, with discretionary bonus and other fringe benefits\n\nInterested parties please click\u00a0\u201cApply Now\u201d\u00a0to apply job with your full resume, current and expected salary.\n\nYou are welcome to visit our website:\u00a0https://www.hero-ds.com/\u00a0to have more understanding of our company.\n\nAll personal data collected will be used for recruitment purpose only", "employment_types": ["Full Time"], "selling_points": ["\u85aa\u91d1\uff1a3\u842c-7\u842c\u4e0d\u7b49", "\u5e95\u85aa+\u4f63\u91d1+\u734e\u91d1+\u5206\u7d05", "\u61c2\u5f97\u65bd\u5de5\u5716\u548c\u7d50\u69cb\u5716\u7684\u904b\u7528"], "locations": ["Quarry Bay"], "categories": ["Building & Construction", "Architectural Services", "Design", "Interior", "Others"], "post_time": "2022-01-16T21:51:08Z", "salary": {"currency": null, "max": null, "min": null, "period": "monthly", "term": null}, "salary_visible": false, "title_keywords": [], "responsibilities": ["design presentation", "coordinate with", "design", "project management", "technical drawing"], "requirements": {"degrees": ["diploma", "degree"], "majors": ["design"], "languages": ["cantonese", "english", "mandarin"], "language_level": ["fluent"], "hard_skills": ["plus", "microsoft office", "powerpoint", "project management", "autocad", "photoshop"], "soft_skills": ["project management", "presentation"], "languages_combined": [{"language": "cantonese", "language_level": ["fluent"]}, {"language": "english", "language_level": ["fluent"]}, {"language": "mandarin", "language_level": ["fluent"]}]}, "experience_required": {"duration": ["minimum 1 year"], "field": ["commercial", "relevant experience", "designer", "design"]}}, {"job_id": "100003009049688", "location_code": "hk", "company": "Area-17 Limited", "job_title": "Assistant Interior Project Manager / Interior Designer", "description": "5\u5e74\u5de5\u4f5c\u7d93\u9a57\u6216\u4ee5\u4e0a\n\n\u61c2\u5f97\u65bd\u5de5\u5716\u548c\u7d50\u69cb\u5716\u7684\u904b\u7528\n\n\u85aa\u91d1\uff1a3\u842c-7\u842c\u4e0d\u7b49\uff08\u5e95\u85aa+\u4f63\u91d1+\u734e\u91d1+\u5206\u7d05\uff09\n\n\u6642\u9593\uff1a\u661f\u671f\u4e00-\u661f\u671f\u516d 11:30-20:30", "employment_types": ["Full Time"], "selling_points": ["Exposure to international projects & luxury retail", "Good career prospect in a growing company", "Minimum 3 to 4 years of experience in the field"], "locations": ["Sheung Wan"], "categories": ["Building & Construction", "Architectural Services", "Design", "Interior", "Management", "General Management"], "post_time": "2022-01-14T09:05:32Z", "salary": {"currency": null, "max": null, "min": null, "period": "monthly", "term": null}, "salary_visible": false, "title_keywords": ["interior project manager", "interior designer", "assistant"], "responsibilities": [], "requirements": {"degrees": [], "majors": [], "languages": [], "language_level": [], "hard_skills": [], "soft_skills": [], "languages_combined": []}, "experience_required": {"duration": [], "field": []}}, {"job_id": "100003009054412", "location_code": "hk", "company": "Sanbase Interior Contracting Limited", "job_title": "Quantity Surveyor / Assistant Quantity Surveyor (Fitting Out)", "description": "Job Description\n\nMy client is an interior design firm based in Hong Kong. They are specializing an international brand including retail and commercial design projects. The boutique locate for K11 MUSEA, 1881 Heritage, Ocean Terminal, Element Shop, Macau and China.\n\nWelcome to join our team to cope with our rapid expansion in both mainland China and Hong Kong.\n\nRequirements\n\nDiploma holder or above in Interior Design\nBasic\u00a0computer knowledge in AutoCAD\u00a0and\u00a0Photoshop are\u00a0preferable\nCapable in handling project independently for interior designer\n\nResponsible of site management, site survey,\u00a0 site staff supervision, etc.\u00a0for interior designer\n\nBasic Cantonese, English & Putonghua\nTraveling to overseas/ PRC is required\nMin 2 years site experience for interior designer\u00a0\n\nResponsibilities:\u00a0\n\nAssist the Senior Interior Designer\nDealing with clients, contractors, architectures, vendors and project team members\nResponsible for design drawings and documentation including concept design and development, construction drawing, materials sourcing and selection\nIdentify and understand clients\u2019 needs and provide customer services\n\nWe offer\u00a0double pay,\u00a0bank holidays, 5 1/2day work,\u00a0annual leave and MPF. Interested candidates please send your application letter with CV, portfolio and salary expectations by clicking 'Apply Now'", "employment_types": ["Full Time", "Permanent"], "selling_points": ["HD / Degree in Quantity Surveying", "2-5 yrs. exp. (high-end interior / fitting-out)", "Experienced in tendering preferred"], "locations": ["Sheung Wan"], "categories": ["Design", "Interior", "Building & Construction", "Building / Construction / QS", "Others"], "post_time": "2022-01-17T09:26:16Z", "salary": {"currency": null, "max": null, "min": null, "period": "monthly", "term": null}, "salary_visible": false, "title_keywords": ["assistant quantity surveyor", "quantity surveyor"], "responsibilities": ["design"], "requirements": {"degrees": ["diploma holder"], "majors": ["design"], "languages": ["cantonese", "putonghua", "english"], "language_level": ["basic"], "hard_skills": ["documentation", "basic", "photoshop", "autocad"], "soft_skills": ["independently", "capable", "responsible"], "languages_combined": [{"language": "cantonese", "language_level": ["basic"]}, {"language": "putonghua", "language_level": []}, {"language": "english", "language_level": []}]}, "experience_required": {"duration": ["min 2 years"], "field": ["designer"]}}, {"job_id": "100003009044251", "location_code": "hk", "company": "\u601d\u5f62\u5275\u4f5c\u6709\u9650\u516c\u53f8", "job_title": "Interior Designer", "description": "Responsibilities:\n\nResponsible for handling pre and post contract stages, including tender analysis, preparing pricing document of tender, subletting, valuation of variation, final account settlement etc.\nResponsible for measurement of works and contract administration\nAssist QS team to function in project control, including but not limited to formulate project budget cost planning, monitoring of project expense and etc.\nCommunicate and coordinate with internal and external parties regarding material and pricing issues\nAssist the project management team in contractual and commercial issues\nRequirements:\n\nHigher Diploma or Degree in Quantity Surveying/Building Studies or equivalent\n2 - 5 years relevant experience in high-end interior/fitting-out projects\nExperience in tendering or subletting will be an advantage\nStrong numerical sense, well organized and mature with good communication & interpersonal skills\nGood team player and able to work under tight schedule and high pressure\nGood command of written and spoken English and Chinese\nProficient in MS Office and Program Applications (e.g. Bluebeam etc.)\nCandidate with less experience will be considered as Assistant Quantity Surveyor\nImmediate available is preferred\n\nWe offer attractive remuneration package to the right candidate. Interested parties, please send your full resume with current & expected salary and availability to :\n\nSanbase Interior Contracting Limited\nHuman Resources Department\n16/F, Loon Kee Building,\n267-275 Des Voeux Road Central, Hong Kong\n\nOR click \u201cApply Now\u201d to submit your online application (http://www.sanbase.com.hk)\n\nThose who are not interviewed within four weeks may consider their applications unsuccessful. All personal data provided will be retained and considered for other position(s) which may subsequently become available within the Sanbase Group if you do not indicate your dissent. All information received will be kept in strict confidential and only used for employment-related purposes.", "employment_types": ["Full Time"], "selling_points": ["Proficient in AutoCAD", "At least 3-4 yrs related experiences", "Salary negotiable"], "locations": ["Tsuen Wan Area"], "categories": ["Design", "Interior"], "post_time": "2022-01-13T03:33:16Z", "salary": {"currency": "HKD", "max": 29999, "min": 20000, "period": "monthly", "term": null}, "salary_visible": true, "title_keywords": ["interior designer"], "responsibilities": ["valuation", "control", "contract administration", "budget", "measurement", "monitoring", "coordinate with", "internal and external parties", "tender analysis", "project management", "cost planning", "tender"], "requirements": {"degrees": ["diploma", "degree"], "majors": ["building studies", "surveying"], "languages": ["english", "chinese"], "language_level": ["good command"], "hard_skills": ["ms office"], "soft_skills": ["good team player", "well organized", "mature", "communication", "interpersonal skills"], "languages_combined": [{"language": "english", "language_level": ["good command"]}, {"language": "chinese", "language_level": ["good command"]}]}, "experience_required": {"duration": ["2 - 5 years"], "field": ["relevant experience"]}}, {"job_id": "100003009042452", "location_code": "hk", "company": "One Production Holding Limited", "job_title": "Project Coordinator", "description": "At FCS Interior Design Consultant Ltd, we focus greatly on our people, providing them with opportunities to grow and develop professionally. We offer competitive compensation including one of the best benefits plans in the market. Most importantly- when you join FCS Interior Design Consultant Ltd.\n\nAttractive Performance Bonus\nRoom for your creative design ability\nEntrepreneurial work environment and good career prospect\nOpportunities working with multi-national clients\nAssociate profit sharing to staff with proven abilities\nLearning & Experience Opportunity\nAre you ready to work in an open-minded and collaborative working environment? Let\u2019s join\n\n\nFCS INTERIOR DESIGN CONSULTANT LTD!!\n\nSENIOR INTERIOR DESIGNER / INTERIOR DESIGNER\n\nRESPONSIBILITIES:\u00a0\n\nLead the strategy efforts in multiple projects\nResearch and analyze global shifts and trends in work behaviours to develop and improve recommendations with respect to physical, digital and social workplaces\nCreate and execute commercial office design concepts through schematic planning\nDesign office environments to achieve client\u2019s brand identity and develop unique design concepts\nManage construction documents from designers and consultants\nProvide detailed and innovative designs according to different guidelines\nIdentify\u00a0exceptional design obstacles and resolve\nHandle commercial projects independently from design concept, project development, and materials application to project completion.\n\nREQUIREMENTS:\n\nRelevant technical Interior Design experiences\nRelevant\u00a0experiences in workplace design is preferred\nExcellent presentation and\u00a0communication skills\nAble to work independently and mentoring the team\nPassionate about Interior Design as long-term career field\nProficient in AutoCAD and Photoshop; SketchUP and 3ds Max is preferred\nExcellent in English and Chinese, both spoken and written\nCandidates with less experience or new graduated will be considered as Assistant Designer", "employment_types": ["Full Time", "Permanent"], "selling_points": ["Monthly Performance Bonus", "Group Medical & Birthday Leave", "Excellent Career Development Path"], "locations": ["Kwun Tong"], "categories": ["Design", "Interior", "Building & Construction", "Building / Construction / QS", "Others"], "post_time": "2022-01-16T21:50:23Z", "salary": {"currency": null, "max": null, "min": null, "period": "monthly", "term": null}, "salary_visible": false, "title_keywords": ["project coordinator"], "responsibilities": [], "requirements": {"degrees": [], "majors": [], "languages": [], "language_level": [], "hard_skills": [], "soft_skills": [], "languages_combined": []}, "experience_required": {"duration": [], "field": []}}, {"job_id": "100003009050504", "location_code": "hk", "company": "Touch Consultancy Limited", "job_title": "Interior Designer - F&B/retail projects", "description": "Job Description\nQualifications:\n\u2022 Diploma / Degree holder in Interior Design accredited institutes\n\u2022 Minimum 3-4 years of experience in Interior design or related field\n\nResponsibilities / Skills:\n\u2022 Auto-Cad drawing and Sketchup is a MUST\n\u2022 Independently handle design projects\n\u2022 Good command of Cantonese and English\n\u2022 Communicate with customers, contractors and vendors including follow up calls or emails\n\u2022 Responsible, self-motivated, initiative and able to work under pressure\n\u2022 Perform ad-hoc tasks as assigned and willing to pay site visit\n\u2022 Immediate availability is preferred (After CNY)\n\nIf you are interested in applying for a job, please send your resume, job references, and portfolio in PDF.", "employment_types": ["Full Time", "Permanent"], "selling_points": ["Attractive salary package + benefit", "5-day Work, flexible working environment", "Aesthetic F&B/ retail Projects"], "locations": ["Central & Western Area"], "categories": ["Building & Construction", "Architectural Services", "Design", "Interior"], "post_time": "2022-01-16T21:50:25Z", "salary": {"currency": null, "max": null, "min": null, "period": "monthly", "term": null}, "salary_visible": false, "title_keywords": ["interior designer"], "responsibilities": ["communicate with", "ad-hoc tasks", "design", "work under pressure"], "requirements": {"degrees": ["diploma", "degree holder"], "majors": ["design"], "languages": ["cantonese", "english"], "language_level": ["good command"], "hard_skills": ["cad", "sketchup"], "soft_skills": ["self-motivated", "independently", "responsible", "interested in", "initiative", "work under pressure"], "languages_combined": [{"language": "cantonese", "language_level": ["good command"]}, {"language": "english", "language_level": ["good command"]}]}, "experience_required": {"duration": ["minimum 3-4 years"], "field": ["related", "design"]}}, {"job_id": "100003009045669", "location_code": "hk", "company": "Regent Building Material Supplies Company Limited", "job_title": "\u92b7\u552e\u54e1/\u5e97\u52d9\u54e1  Shop Sales / Assisstant", "description": "About this role\n\nAs a Project Coordinator, you will be responsible for covering from per contact to final account preparation and handling loose furniture projects. There will be many opportunities for you to develop yourself to be capable of facilitating a project.\n\nWhat we are looking for...?\u00a0\n\nAn energetic person which loves to communicate with others.\nEager to learn new things and agile to changes.\nA well-organized, stress-handling person and see projects through to completion.\nA good team player with strong interpersonal communication and relationship-building skills.\n\nWhat you will do\u2026?\u00a0\u00a0\n\nAssist project manager in all aspect of project follow up such as material planning, logistics and transportation coordination etc.\nSupervise and monitor all site work\nLiaise and coordinate with sub-contractors and ensure the work progress meet schedule\nAssist to handle the tender, sub-contractor assignment, contract drafting, and contract negotiation\nAssist the QS work from pre-contract to post-contract works\n\nAre you ready for the opportunity\u2026?\u00a0\n\nDiploma or above in Quantity Surveying, Building Services, Interior Design, Occupational Safety and Health or related disciplines\nMinimum 2 years relevant experience in fitting out industry\nCandidates with solid experience in handling large scale projects are highly preferred\u00a0\n\nOne Production Perk\u00a0\n\nLearning and development stipend, because we value lifelong learning and believe the best way to invest in our employees is to encourage them to continue to learn\nWork hard and laugh lots (team buildings, Afternoon teas and parties, etc.) with a high-performing, fun and diverse team\nConveniently location, surrounded by diverse and delicious lunch options\nOpen office with a great environment, even a grand dining hall.\nFun extracurricular activities with your colleagues like hiking, yoga, badminton, boxing, photography, etc.\nBirthday leave and red packet, marriage and newborn baby blessing and more\n\n\n\nWe offer a competitive remuneration package and career prospects to the right candidate. Interested parties please send full resume with current and expected salary.\n\n*All personal data collected will be used for recruitment purposes only.", "employment_types": ["Full Time"], "selling_points": ["\u4e2d\u4e94\u7a0b\u5ea6; 1\u5e74\u7d93\u9a57", "\u8ca0\u8cac\u9580\u5e02\u92b7\u552e  \u8ca8\u54c1\u9673\u5217  \u8a02\u55ae\u8ddf\u9032", "\u6bcf\u6708$14,000 - $18,000"], "locations": ["Mong Kok"], "categories": ["Design", "Interior", "Sales, CS & Business Devpt", "Retail Sales", "Wholesale"], "post_time": "2022-01-17T02:20:28Z", "salary": {"currency": null, "max": null, "min": null, "period": "monthly", "term": null}, "salary_visible": false, "title_keywords": ["sales", "\u92b7\u552e\u54e1", "\u5e97\u52d9\u54e1"], "responsibilities": ["communicate with", "liaise", "project follow up", "monitor", "coordinate with", "design", "develop", "communication", "logistics", "contact", "coordination", "schedule", "tender", "planning"], "requirements": {"degrees": ["diploma or above"], "majors": ["related disciplines", "building services", "surveying", "design"], "languages": [], "language_level": [], "hard_skills": ["red", "agile", "fun"], "soft_skills": ["good team player", "agile", "capable", "responsible", "negotiation", "well-organized", "communication", "eager to learn", "diverse", "learning", "coordination", "energetic", "interpersonal"], "languages_combined": []}, "experience_required": {"duration": ["minimum 2 years"], "field": ["relevant experience"]}}, {"job_id": "100003009049498", "location_code": "hk", "company": "Atelier Global Limited", "job_title": "Experienced Interior Designers", "description": "Our client is an interior design company with an excellent portfolio in F&B/retail projects. They are looking for a proficient & enthusiastic interior designer to join them.\n\n\n\nWhat you do:\n\nWork closely with design & project directors\nManage full sets of conceptual design to construction administration\nDiscuss design ideas and provide advice to clients\nSource materials and products included in plans\nInspect design after completion to determine whether client goals have been met\n\n\n\nWhat you need:\u00a0\n\nDegree / Diploma Holder in interior design or architectural design field\nMin 4 years' relevant experience in\u00a0 F&B/ retail brand store projects\nExcellent communication and\u00a0presentation skills\nUtilize computer applications(Sketch Up, AutoCAD) well, Rhino is a plus\nFluent in spoken and written\u00a0 English and Chinese\n\n\n\nIf you are keen to know more about this position, please submit a copy of your updated CV & portfolio to shirley @ touchrecruiting.com for a confidential discussion. All data will only be treated for recruitment purposes.\n\nSuccessful applicants will be contacted within 2 working days.", "employment_types": ["Full Time"], "selling_points": ["large scale commercial retail design", "willing to travel in China", "passion in design"], "locations": ["Wan Chai"], "categories": ["Design", "Interior"], "post_time": "2022-01-14T08:45:20Z", "salary": {"currency": null, "max": null, "min": null, "period": "monthly", "term": null}, "salary_visible": false, "title_keywords": [], "responsibilities": ["ideas", "data", "design", "communication", "provide advice", "recruitment", "plans", "administration"], "requirements": {"degrees": ["diploma holder", "degree"], "majors": ["design"], "languages": ["english", "chinese"], "language_level": ["fluent"], "hard_skills": ["rhino", "plus", "autocad"], "soft_skills": ["communication", "keen", "presentation skills", "enthusiastic"], "languages_combined": [{"language": "english", "language_level": ["fluent"]}, {"language": "chinese", "language_level": ["fluent"]}]}, "experience_required": {"duration": ["min 4 years"], "field": ["f&b", "retail", "relevant experience", "brand"]}}, {"job_id": "100003009011490", "location_code": "hk", "company": "Team H C Limited", "job_title": "Interior Designer / Assistant Interior Designer", "description": "ATELIER GLOBAL is always looking for talented INTERIOR DESINGERS. Any data you send us with your application, including your portfolio, will be stored in a database, which is cleared once a year.\n\nABOUT ATELIER GLOBAL\n\nATELIER GLOBAL is a young leading interior, architecture and urbanism practice based in Hong Kong with offices in Hong Kong and Shenzhen. \u00a0It was founded in 2007. Atelier Global is an aspiring studio strongly believes in the power of design and creativity. We are\u00a0 dynamic and fast-growing design firm with currently 100 staff and has received numerous design awards from the United States, Europe and Hong Kong.\n\nREQUIREMENTS\n\nBachelor Degree in Interior Design or equivalent\n4 years of relevant working experience for large scale commercial retail design\nSolid experience in construction drawings and on-site experience\nStrong conceptual talent in spatial planning, graphic and design skills\nStrong Revit, AutoCAD, Rhino, Enscape, InDesign, Adobe suite and rendering skills\nGood team player and working closely with Shenzhen office\nFrequent travel to Shenzhen office and China\nEnglish and Mandarin language skills are required\n\nHOW TO APPLY\n\nPlease send your motivation letter, CV, recommendation and portfolio preferably as PDF not larger than 5mb. Let us know your preferred starting date and expected salary to our company email address.\n\nFor questions, call our HR department at 3547 2111", "employment_types": ["Full Time", "Permanent", "Freelance"], "selling_points": [], "locations": ["Aberdeen"], "categories": ["Building & Construction", "Architectural Services", "Design", "Interior"], "post_time": "2022-01-13T18:54:41Z", "salary": {"currency": null, "max": null, "min": null, "period": "monthly", "term": null}, "salary_visible": false, "title_keywords": ["interior designer", "assistant interior designer"], "responsibilities": ["data", "hr", "design", "drawings", "database", "architecture", "planning"], "requirements": {"degrees": ["degree", "bachelor"], "majors": ["design"], "languages": ["english", "mandarin"], "language_level": [], "hard_skills": ["rhino", "revit", "indesign", "dynamic", "adobe", "autocad"], "soft_skills": ["good team player", "dynamic"], "languages_combined": [{"language": "english", "language_level": []}, {"language": "mandarin", "language_level": []}]}, "experience_required": {"duration": ["4 years"], "field": ["relevant working experience", "design", "commercial", "retail", "construction"]}}, {"job_id": "100003009050581", "location_code": "hk", "company": "STA Pacific Limited", "job_title": "Senior CAD Draftsman ($30k \u2013 In-house role)", "description": "We are hiring! Looking for passionate and enthusiastic designers (experienced or not so much) to join our team. If you love design and like to think outside the box, give us a shout!\n\n\u00a0Responsibilities\n\n\n\u00a0Create designs and layouts for various projects\n\u00a0Prepare presentations\n\u00a0Drawing documentation\n\u00a0Maintain industry knowledge in order to stay relevant\n\u00a0Site coordination\n\u00a0Give a shit about what you are doing!\n\u00a0Skills\nAutoCad, Sketchup, Photoshop, 3D Max - not necessary but if you know it, it's a plus\nStrong creative and communication skills\nDemonstrated ability to think logically\nSelf-motivate\n\u00a0Requirement\n\nDesign Institute graduate or Degree Holder in Interior Design or Architecture\ngood command of both spoken and written English and Chinese\nHong Kong permanent resident\nImmediate available is absolutely advantage\n\n\u00a0Yes. we only work 5 days. Weekend is for fun.\nConvenience location, just next to MTR station.\u00a0\n\nInterested parties, please send your detailed Resume with expected salary plus Portfolio\u00a0via Apply Now.\n\n\nPersonal details collected for recruitment purpose only.", "employment_types": ["Full Time", "Permanent"], "selling_points": ["High Pay with limited drawings", "Luxury Retail Firm", "Career Exposure"], "locations": ["Central"], "categories": ["Design", "Interior", "Building & Construction", "Civil / Structural", "Engineering", "Draftsman"], "post_time": "2022-01-15T03:51:12Z", "salary": {"currency": null, "max": null, "min": null, "period": "monthly", "term": null}, "salary_visible": false, "title_keywords": ["cad draftsman"], "responsibilities": ["presentations", "communication", "maintain", "site coordination", "documentation"], "requirements": {"degrees": ["degree holder"], "majors": ["architecture", "design"], "languages": ["english", "chinese"], "language_level": ["good command"], "hard_skills": ["fun"], "soft_skills": [], "languages_combined": [{"language": "english", "language_level": ["good command"]}, {"language": "chinese", "language_level": ["good command"]}]}, "experience_required": {"duration": [], "field": []}}, {"job_id": "100003009049687", "location_code": "hk", "company": "Lead8 Hong Kong Limited", "job_title": "Architectural Assistant", "description": "Duties\n\nWork with Store Planning Manager with design-oriented studies/schematic diagram\nEnsure the achievable design studies to meet with the local regulation(s) and the brand identity\nPerform coloured concept drawings (in CAD) in order to submit them to landlord\nEnsure the diagrams are in accord with the schedule of rates for works\nMake certain the drawings are easy to read and explain to others\nPrepare clear tender package drawings to company\u2019s stores and the quantity surveyor\nReview the building/unit technical/architectural restriction after finished the drawings\nCoordinate the renderings with the vendors\n\nRequirements\n\nHigher Diploma or Degree Holder in Architectural Design Technology or related disciplines\nWith 5 - 8 years\u2019 relevant experience in the drawings and utilizing AutoCAD & Photoshop/Illustrator\u00a0\nExperience in working for Luxury & Jewelry retail would be highly preferred\nStrong in drawing skills and colour arrangements\nStrong in presentation & communication skills in English and Chinese\nCapable to follow up multiple projects of various size and concept at the same period \u00a0\nAble to work independently or work with a team \u00a0\n\nAPPLY now or email your CV at career3@ stapacific.com as long as you are interested in this role.", "employment_types": ["Full Time"], "selling_points": [], "locations": ["Quarry Bay"], "categories": ["Building & Construction", "Architectural Services", "Design", "Interior", "Building / Construction / QS"], "post_time": "2022-01-14T09:05:09Z", "salary": {"currency": null, "max": null, "min": null, "period": "monthly", "term": null}, "salary_visible": false, "title_keywords": ["architectural assistant"], "responsibilities": ["review", "design", "drawings", "coordinate", "schedule", "tender", "store planning"], "requirements": {"degrees": ["diploma", "degree holder"], "majors": ["related disciplines", "design"], "languages": ["english", "chinese"], "language_level": [], "hard_skills": ["illustrator", "photoshop", "autocad"], "soft_skills": ["communication skills", "work independently", "capable", "interested in", "presentation"], "languages_combined": [{"language": "english", "language_level": []}, {"language": "chinese", "language_level": []}]}, "experience_required": {"duration": ["5 - 8 years"], "field": ["retail", "relevant experience"]}}, {"job_id": "100003009053864", "location_code": "hk", "company": "BAMBOO Consultants Limited", "job_title": "HOSPITALITY INTERIOR DESIGNERS, All Levels (HK, Beijing, Shanghai, Singapore)", "description": "What You Will Do\u2026\n\nYou will be working on exciting Mixed-Use, Retail and Commercial projects for our Top Tier Clients\nYou will get involved in projects across Asia Pacific\nYou will brainstorm with a team of young, bright, and truly creative architects to create unique architectural designs\nYou will be given the freedom to fully express your creative genius\nYou will design all forms of visual materials in the architectural process from concept imagery to marketing material\nYou will assist with client presentations and attend project meetings\nYou will be expected to speak up, give the team your opinion and insights\nYou will be mentored, coached and trained to ensure your career success\n\nWhat You Will Need\u2026\n\nAt least 2 years\u2019 relevant working experience in Architecture (exceptionally talented fresh graduates will also be considered)\nA passion to be truly creative and a strong desire to work in a team with great architects and designers\nA strong command of AutoCAD and other graphic presentation software\nFluent communication skills in English and Mandarin\n\nLead8 is an equal opportunity employer and welcomes applications from all qualified candidates\n\n(Excellent learning environment with the freedom to be creative)\n\nInterested parties please send portfolio, full resume giving details of qualifications, experience, expected salary and date available by clicking \"Apply Now\"", "employment_types": ["Full Time", "Permanent"], "selling_points": ["Singapore, HK, BJ, SH hospitality design roles", "Fluency in English, Mandarin preferred", "Hospitality, residential, or F&B"], "locations": ["Not Specified"], "categories": ["Design", "Interior", "Others", "Building & Construction", "Others"], "post_time": "2022-01-17T07:38:54Z", "salary": {"currency": null, "max": null, "min": null, "period": "monthly", "term": null}, "salary_visible": false, "title_keywords": [], "responsibilities": ["software", "presentations", "design", "communication", "visual", "marketing material", "architecture"], "requirements": {"degrees": [], "majors": [], "languages": ["english", "mandarin"], "language_level": ["fluent"], "hard_skills": ["presentations", "autocad"], "soft_skills": ["communication skills", "unique", "learning", "creative", "presentation"], "languages_combined": [{"language": "english", "language_level": ["fluent"]}, {"language": "mandarin", "language_level": ["fluent"]}]}, "experience_required": {"duration": ["at least 2 years"], "field": ["relevant working experience"]}}, {"job_id": "100003009047125", "location_code": "hk", "company": "Sanderson Solutions International (Hong Kong) Limited", "job_title": "Project Designer", "description": "Let\u2019s work together\n\n\nExperience in-store visual merchandising, store project management, furniture design and fitting out works\nPrioritize manage and track multiple, simultaneous projects in terms of timing and budget\nGather market intelligence regarding interior and store design trends\nOrganize the standard design of furniture and fixture\nManage Hong Kong and Macau store projects\nMake site visits\nManage external contractors\n\n\u00a0We are looking for\n\n\nUniversity graduate in\u00a0Interior Design, Architecture, Project management, Project Construction preferred\nMinimum 3 years experience in retail projects preferably\nCandidates with retail industry experience will be at an advantage\nExperienced in international and local firms\nStrong grasp of VM, interior and store design as well as store project management capabilities\nStrong business sense, analytical and problem-solving skills\nExcellent leadership and communication skills\nProficient in AutoCAD, Photoshop, AI and other design skills, MS Word and Excel\nGood command of written and spoken English, Mandarin and Cantonese\nImmediate availability will be an advantage\n\n\u00a0\u00a0Join us now:\n\nPlease send\u00a0full resume stating your academic qualifications, career history, availability with current and expected salary\u00a0to: The\u00a0Human Resources Manager\n\n\u00a0On offer is a competitive package\n\nAttractive\u00a0Remuneration\n5 Days Work\nAnnual Leave\nFamily Leave\nMonthly Early Release\u00a0\n\n\n\nBirthday Leave with gifts\nMarriage Leave with red packets\nExamination Leave\nMedical Scheme\nStaff Discount\n\n\n\nWebsite:\u00a0www.citychain.com\n", "employment_types": ["Full Time", "Temporary", "Contract", "Internship", "Freelance"], "selling_points": ["Handle full set of tender drawings", "Adobe photoshop/InDesign/Illustrator", "Coordinate with suppliers and contractors"], "locations": ["Sheung Wan"], "categories": ["Design", "Interior"], "post_time": "2022-01-14T02:23:51Z", "salary": {"currency": null, "max": null, "min": null, "period": "monthly", "term": null}, "salary_visible": false, "title_keywords": ["project designer"], "responsibilities": ["budget", "merchandising", "website", "design", "communication", "project management", "visual", "design trends", "architecture"], "requirements": {"degrees": ["university graduate"], "majors": ["project management", "architecture", "design"], "languages": ["cantonese", "english", "mandarin"], "language_level": ["good command"], "hard_skills": ["excel", "ai", "ms word", "visual merchandising", "scheme", "project management", "make", "photoshop", "problem-solving skills", "red", "autocad"], "soft_skills": ["communication skills", "business sense", "prioritize", "project management", "problem-solving skills", "leadership"], "languages_combined": [{"language": "cantonese", "language_level": ["good command"]}, {"language": "english", "language_level": ["good command"]}, {"language": "mandarin", "language_level": ["good command"]}]}, "experience_required": {"duration": ["minimum 3 years"], "field": ["retail industry", "design", "store visual merchandising", "project management", "retail"]}}, {"job_id": "100003009042333", "location_code": "hk", "company": "Vinoti Living Co Limited", "job_title": "Assistant Project Manager / Interior Designer", "description": "F.5 or above\nAt least 2 years or above relevant experience in interior design field.\nAt least 3 years design experience in commercial preferably.\nProficient In AutoCAD, 3D Studio Max, Photoshop.\nResponsible, aggressive, hard working & willing to learn.\nF&B design experience and immediate available is preferred.\nCandidates with less experience will be considered for Interior Designer.\n\nInterested parties please send CV with expected salary to us by clicking apply now.\n\n(Personal data will be used for recruitment purpose only)", "employment_types": ["Full Time", "Permanent"], "selling_points": [], "locations": ["Lai Chi Kok"], "categories": ["Design", "Interior", "Building & Construction", "Building / Construction / QS"], "post_time": "2022-01-12T07:05:56Z", "salary": {"currency": null, "max": null, "min": null, "period": "monthly", "term": null}, "salary_visible": false, "title_keywords": ["assistant project manager", "interior designer"], "responsibilities": ["design"], "requirements": {"degrees": [], "majors": [], "languages": [], "language_level": [], "hard_skills": ["max", "photoshop", "autocad"], "soft_skills": ["hard working", "willing to learn", "responsible"], "languages_combined": []}, "experience_required": {"duration": ["at least 2 years", "at least 3 years"], "field": ["designer", "design", "commercial", "f&b", "relevant experience"]}}, {"job_id": "100003009050449", "location_code": "hk", "company": "Touch Consultancy Limited", "job_title": "Technical Designer - F&B/Retail (Interior)", "description": "OUR CLIENT:\nThis is a boutique Architecture & Interior Design Company with strong portfolio of f&b & retail projects.\n\n\n\nRESPONSIBILITIES:\n\nCoordinate with interior design team & project team member.\nSite meeting with clients/ contractors/ consultants.\nOversee the DD/ Tender package.\nResolve any technical issue.\n\nREQUIREMENT:\n\nMinimum 6\u00a0years of relevant experience.\nDegree / Diploma Holder in interior design or relevant.\nF&B/ Retail/ Commercial\u00a0project experiences is a must.\nFluent in Cantonese/English/Chinese.\nProficiency in AutoCad, SketchUp, 3Dmax,\u00a0Photoshop.\nGood time management to meet tight schedule.\nA good team player.\n\n\n\nIf you are keen to know more about this position, please submit a copy of updated CV to jack @touchrecruiting.com for a confidential discussion. All data will only be treated for recruitment purpose.\n\nSuccessful applicants will be contacted within 2 working days.\n\nFor more live vacancies, please visit our company website at\u00a0https://touchrecruiting.com/", "employment_types": ["Full Time"], "selling_points": ["Interesting working environment", "Team work", "Attractive Package"], "locations": ["Central & Western Area"], "categories": ["Design", "Interior", "Building & Construction", "Others"], "post_time": "2022-01-14T10:27:16Z", "salary": {"currency": null, "max": null, "min": null, "period": "monthly", "term": null}, "salary_visible": false, "title_keywords": ["designer"], "responsibilities": ["tender", "coordinate with", "design"], "requirements": {"degrees": ["diploma holder", "degree"], "majors": ["design"], "languages": ["cantonese", "english", "chinese"], "language_level": ["fluent"], "hard_skills": ["photoshop", "sketchup", "3dmax", "autocad"], "soft_skills": ["keen", "good team player", "time management"], "languages_combined": [{"language": "cantonese", "language_level": ["fluent"]}, {"language": "english", "language_level": ["fluent"]}, {"language": "chinese", "language_level": ["fluent"]}]}, "experience_required": {"duration": ["minimum 6 years"], "field": ["commercial", "f&b", "retail", "relevant experience"]}}, {"job_id": "100003009037420", "location_code": "hk", "company": "Novus Penetralis Limited", "job_title": "Interior Designer", "description": "\u5730\u5340 :\u00a0 \u00a0\u65fa\u89d2 / \u7063\u4ed4\n\u884c\u696d :\u00a0 \u00a0\u5bb6\u5c45\u6982\u5ff5\u96f6\u552e\u5e97\n\n\u8077\u8cac :\n-\u00a0 \u00a0\u8ca0\u8cac\u9580\u5e02\u92b7\u552e\uff0c\u8ca8\u54c1\u9673\u5217\n-\u00a0 \u00a0\u8a02\u55ae\u8ddf\u9032\uff0c\u63d0\u4f9b\u5c08\u696d\u610f\u898b\uff0c\u5354\u52a9\u5e97\u8216\u65e5\u5e38\u904b\u4f5c\n\n\u8981\u6c42:\n-\u00a0 \u00a0\u4e2d\u4e94\u4ee5\u4e0a\u7a0b\u5ea6\uff0c\u5099\u6709\u826f\u597d\u4e2d\u6587\u53ca\u7c21\u55ae\u82f1\u6587\n-\u00a0 \u00a0\u5177\u6709\u57fa\u672c\u96fb\u8166\u64cd\u4f5c\u77e5\u8b58\n-\u00a0 \u00a0\u6709\u8cac\u4efb\u611f\u3001\u5b88\u6642\u3001\u8aa0\u5be6\n\n\u5f85\u9047 :\n-\u00a0 \u00a0\u6bcf\u6708$14,000 - $18,000, \u6709\u4f63\u91d1 \u53ca\u5728\u8077\u57f9\u8a13,\n-\u00a0 \u00a0\u661f\u671f\u4e00\u81f3\u516d: \u4e0a\u53489\u6642\u534a\u81f3\u4e0b\u53487\u6642\u534a\uff0c\u661f\u671f\u65e5:\u4e0b\u53481\u6642\u81f3\u4e0b\u53486\u6642\u534a\uff0c\u6bcf\u9031\u5de5\u4f5c5\u5929\u534a\uff0c\u8f2a\u4f11\n\u6c42\u8077\u8005\u53ef\u96fb\u90f5\u5c65\u6b77\u8868\u7d66\u6216Whatsapp: 6826 7978\u8207\u674e\u5c0f\u59d0\u806f\u7d61", "employment_types": ["Full Time", "Permanent"], "selling_points": ["Higher Diploma / Degree in Interior Design.", "Handling design & project development.", "Able to handle full set of design presentation"], "locations": ["Tsim Sha Tsui"], "categories": ["Design", "Interior", "Others"], "post_time": "2022-01-11T02:46:22Z", "salary": {"currency": null, "max": null, "min": null, "period": "monthly", "term": null}, "salary_visible": false, "title_keywords": ["interior designer"], "responsibilities": [], "requirements": {"degrees": [], "majors": [], "languages": [], "language_level": [], "hard_skills": [], "soft_skills": [], "languages_combined": []}, "experience_required": {"duration": [], "field": []}}, {"job_id": "100003009039099", "location_code": "hk", "company": "City Super Ltd", "job_title": "Interior Designer", "description": "Responsibilities:\n\n\nTransform user requirement into the design concepts presentation for Retail stores / F&B / supporting facilities\nPartner with Project Manager to assess the tender offers\nCommunicate and monitor the workmanship of contractors in new stores / renovation projects\nSetup the store design principle for oversea market\nPresent the design works to landlord\nAssist the Project Manager to carry out the defect inspection\nDevelop outsourcing strategy to cope with the extra demand\n\nRequirements:\n\n\nDegree in Interior Design or related discipline with at least 3 years\u2019 related working experience\nSelf-motivated with ability to plan and organize own work load\nHaving a sense of key priorities and deadlines\nProficiency in AutoCAD,\u00a0Sketchup, 3D rendering software\nKnowledge of FEHD licenses regulations, Building Services Regulations, Building Ordinance is a plus\nA well communication and presentation skill in English, Mandarin, and Cantonese.\nWe offer competitive remuneration package and good prospects to the right candidates. Interested parties please send your full resume with expected salary to apply.\n\n\n*Data collected will be kept confidential and used for recruitment purposes only.", "employment_types": ["Full Time"], "selling_points": ["Interior Designer", "Renovation projects", "Setup the store design"], "locations": ["Tsim Sha Tsui"], "categories": ["Design", "Interior"], "post_time": "2022-01-12T09:02:02Z", "salary": {"currency": null, "max": null, "min": null, "period": "monthly", "term": null}, "salary_visible": false, "title_keywords": ["interior designer"], "responsibilities": ["user requirement", "design concepts", "renovation", "monitor", "design", "inspection", "develop", "tender", "setup"], "requirements": {"degrees": ["degree"], "majors": ["design"], "languages": ["cantonese", "english", "mandarin"], "language_level": [], "hard_skills": ["presentation skill", "plus", "sketchup", "autocad"], "soft_skills": ["communication", "self-motivated", "presentation skill"], "languages_combined": [{"language": "cantonese", "language_level": []}, {"language": "english", "language_level": []}, {"language": "mandarin", "language_level": []}]}, "experience_required": {"duration": ["at least 3 years"], "field": ["related", "design"]}}, {"job_id": "100003009050981", "location_code": "hk", "company": "Hong Kong Science & Technology Parks Corporation", "job_title": "Project Manager [JDB/PM/220114]", "description": "Responsibilities:\n\nAssist Associate Project Director in managing and planning proposals on Park Revamp, Connectivity Enhancement, Art Tech and Talent Nurturing Programs to ensure projects are accomplished within the planned schedule and budget as well as meeting the required quality and safety standards;\nOversee the improvement and minor works including term contracts, defects-rectification works, fitting out works, alteration and addition works;\nWork closely with the project teams to produce preliminary and detailed designs, tender/construction documents, and to manage the procurement and construction process;\nHandle the design drawing/graphics for presentation as well as tender and procurement documents for consultants selection/appointment by following up their subsequent management and monitoring their performance;\nLiaison with various consultants, government departments, education institutions, park companies and relevant organizations on project planning, design and implementation as well as coordinate internally with Marketing Team, Clusters, Facility Management Team, Project Team on all related matters;\nResponsible for the design management in coordination with end users (e.g. F&B tenants etc.), implementation and delivery of the approved strategies; \u00a0\u00a0\nPrepare papers and reports for seeking approval by the Board, Committees and Task Force of the Corporation;\nEnsure compliance with the Corporation\u2019s guidelines and Delegation Authority for capital works projects; and\nPerform any other duties as assigned by supervisor.\n\nRequirements:\n\nA bachelor\u2019s degree or above in Architecture, Interior Design, Surveying or related discipline;\nMinimum 8 years\u2019 relevant work experience with strong design and commercial sense in project management of building, interior design and A&A projects;\nProven connection with Hong Kong marketing / event organizers, F&B operators, etc.\nExperience in managing projects from inception to completion including handover;\nExperience in procuring and managing consultants, contract administration of large-scale projects, claim and EOT assessment as well as supervision of minor works contracts and term contracts;\nKnowledge of statutory requirements and procedures for development projects in Hong Kong;\nConversant with graphics presentation tools. Skill on graphic software such as Adobe Photoshop, Adobe Illustrator, AutoCAD, Primavera, Microsoft Project, Revit and project management / design related computer application will be an advantage;\nSelf-driven, independent, problem solving with good interpersonal skill; and\nGood command in both spoken and written English and Chinese. Proficiency in Putonghua will be an advantage.\n\nCandidate with less experience will be considered for lower position.\n\nWe offer market competitive compensation, 5-day work week, and generous benefits including medical and life insurance; and voluntary contribution in addition to the legal minimum MPF.\u00a0 To apply, please send your full resume with current and expected salary to the Human Resources & Office Administration Department, Hong Kong Science and Technology Parks Corporation, 5/F, Building 5E, 5 Science Park East Avenue, Hong Kong Science Park, Hong Kong or, by email via Apply Now\"\u00a0on or before 27 January 2022.\u00a0 \u00a0Please quote the reference number on the email subject/envelope and the application letter.\u00a0\n\nPersonal data provided will be treated in strict confidence and used for recruitment purpose only.\u00a0 All personal data collected will be used strictly in accordance with employer\u2019s personal data policies, you can access to HKSTP\u2019s Personal Information Collection Statement at https://www.hkstp.org/hkstp_web/en/hkstp/personal-information-collection-statement-recruitment\n\nApplicants not invited for interview within four weeks after application deadline may consider their applications unsuccessful.\u00a0 Personal data of unsuccessful applicants will be retained for a maximum of two years.\u00a0\n\nwww.hkstp.org", "employment_types": ["Full Time"], "selling_points": [], "locations": ["Shatin Area"], "categories": ["Building & Construction", "Architectural Services", "Design", "Interior", "Others"], "post_time": "2022-01-14T12:28:50Z", "salary": {"currency": null, "max": null, "min": null, "period": "monthly", "term": null}, "salary_visible": false, "title_keywords": ["project manager"], "responsibilities": ["any other duties", "budget", "quality", "coordination with", "design", "graphics", "management team", "contracts", "teams", "implementation", "reports", "schedule", "tender", "design management", "management", "rectification", "monitoring", "project planning", "revamp", "guidelines", "ensure compliance", "coordinate", "safety standards", "planning"], "requirements": {"degrees": ["degree or above", "bachelor"], "majors": ["architecture", "surveying", "design"], "languages": ["putonghua", "english", "chinese"], "language_level": ["advantage", "proficiency", "good command"], "hard_skills": ["graphics", "microsoft project", "revit", "adobe photoshop", "adobe illustrator", "problem solving", "project management", "autocad"], "soft_skills": ["independent", "presentation", "interpersonal skill", "problem solving", "project management", "driven"], "languages_combined": [{"language": "putonghua", "language_level": ["proficiency", "advantage"]}, {"language": "english", "language_level": ["good command"]}, {"language": "chinese", "language_level": ["good command"]}]}, "experience_required": {"duration": ["minimum 8 years"], "field": ["commercial", "project management", "design", "administration"]}}, {"job_id": "100003009049376", "location_code": "hk", "company": "ADO Limited", "job_title": "Project Manager", "description": "Responsibilities:\n\n\nMaintain Project documentations including specifications, tender documents, progress & cost reports, and site records, etc\nMonitor\u00a0\u00a0material orderings and logistics to meet project\u00a0progress, by onsite inspection, status update meetings/calls, etc\nCoordinate internally both with\u00a0Hong Kong and China working teams, externally with\u00a0subcontractors,\u00a0vendors, service providers, designers, clients, etc\nProvide supports to sales / marketing teams when the\u00a0need arises\n\nRequirements:\n\n\nGraduated with relevant academic qualifications\n3 years or above experience\nExperience in high quality residential / office, clubhouse\u00a0design & build projects would be a definite advantage\nPrevious experiences in related industry, including construction or material companies is a plus\nBe able to handle full set of construction drawings with practical detailing & site co-ordination\nGood command of spoken and written English and Chinese (including\u00a0both Cantonese and Putonghua)\nExperience on site supervision and able to handle site management independently\nSkills in\u00a0AutoCadand\u00a0Adobe Illustrator\u00a0is a plus\nStrong in project management and communication with clients, consultants and contractors\nDetail-oriented, willing to learn and able to work under pressure\nOccasional travel to PRC\u00a0and\u00a0other locations", "employment_types": ["Full Time"], "selling_points": ["Monitor project progress", "Experience in site supervision", "3 years or above experience"], "locations": ["Tsuen Wan Area"], "categories": ["Design", "Interior", "Building & Construction", "Building / Construction / QS"], "post_time": "2022-01-14T08:31:47Z", "salary": {"currency": null, "max": null, "min": null, "period": "monthly", "term": null}, "salary_visible": false, "title_keywords": ["project manager"], "responsibilities": ["cost", "tender documents", "monitor", "project progress", "teams", "inspection", "coordinate", "specifications", "maintain", "reports", "logistics"], "requirements": {"degrees": [], "majors": [], "languages": ["cantonese", "putonghua", "english", "chinese"], "language_level": ["good command"], "hard_skills": ["project management", "plus", "adobe illustrator"], "soft_skills": ["independently", "willing to learn", "detail-oriented", "communication", "project management", "work under pressure"], "languages_combined": [{"language": "cantonese", "language_level": ["good command"]}, {"language": "putonghua", "language_level": ["good command"]}, {"language": "english", "language_level": ["good command"]}, {"language": "chinese", "language_level": ["good command"]}]}, "experience_required": {"duration": ["3 years"], "field": ["related", "management", "construction", "design"]}}, {"job_id": "100003009041992", "location_code": "hk", "company": "Vast Step Consultants Limited", "job_title": "SENIOR INTERIOR DESIGNER  / INTERIOR DESIGNER / ASSISTANT INTERIOR DESIGNER", "description": "Vast step consultants Limited is an Architecture & Interior Design firm. We specialize in F&B and commercial projects. We are hiring an Senior interior designer / Interior designer / Assistant Interior designer.\n\n\nRequirements:\n\nHigh Diploma/Degree in interior design or equivalent.\nProficient in AutoCAD, Adobe Photoshop and SketchUp.\nHard- working, confident, self- motivated creative.\nFluent in English, Cantonese and mandarin.\n\nResponsibilities:\n\nHandle full set of construction and detail drawings.\nResponsible for site supervision and coordination.\nExperience on site management is an advantage.\n\nWhat We offer:\n\n\n5 days-work per week\nPerformance bonus\nDiscretionary Yearend bonus\n\nImmediate availability.\u00a0We are waiting for you!\n\nInterested candidates please send us the followings by email: Full resume with expected salary and date of availability", "employment_types": ["Full Time"], "selling_points": [], "locations": ["Kwun Tong"], "categories": ["Building & Construction", "Architectural Services", "Design", "Interior"], "post_time": "2022-01-12T06:02:23Z", "salary": {"currency": null, "max": null, "min": null, "period": null, "term": null}, "salary_visible": false, "title_keywords": ["interior designer", "senior interior designer", "assistant interior designer"], "responsibilities": ["detail drawings", "site management", "site supervision", "coordination"], "requirements": {"degrees": ["high diploma", "degree"], "majors": ["design"], "languages": ["cantonese", "english", "mandarin"], "language_level": ["fluent"], "hard_skills": ["adobe photoshop", "sketchup", "autocad"], "soft_skills": ["confident", "motivated", "creative"], "languages_combined": [{"language": "cantonese", "language_level": ["fluent"]}, {"language": "english", "language_level": ["fluent"]}, {"language": "mandarin", "language_level": ["fluent"]}]}, "experience_required": {"duration": [], "field": []}}, {"job_id": "100003009043115", "location_code": "hk", "company": "Maven Furniture (Hong Kong) Limited", "job_title": "Project Manager/Assistant Project Manager", "description": "Responsibilities\n\nreport to Project Director to manage assigned account\nmanage project team with size of 10~20 staff\nliaise with client/designer/factory on luxury retail millwork supply\n\nRequirements\n\nDiploma in design, project management or related disciplines\n5 years or above experience within retail millwork/bespoke furniture/fitting-out industry\nKnowledge with wooden, glass and metal materials are necessary\nAble to tackle problems on drawing and furniture fitting\nHard working and able to handle pressure\nStrong communication and interpersonal skills\nGood command of English, Mandarin and Cantonese\nKnowledge in AutoCAD is preferred but not necessary\nFrequent travel and station in Dongguan is REQUIRED\nLess experience will consider as Assistant Project Manager\n\nWe offer competitive remuneration package to the right candidate. Interested parties are invited to send full resume, present and expected salary to\u00a0email address by clicking \"Apply Now\"\n\n\nPersonal data will be used for recruitment purpose only.\n", "employment_types": ["Full Time", "Permanent"], "selling_points": ["Diploma in design, project management", "5 years or above experience within retail millwork", "5 days work"], "locations": ["Mong Kok"], "categories": ["Design", "Interior", "Engineering", "Engineering Project Management", "Merchandising & Purchasing", "Furniture"], "post_time": "2022-01-12T09:50:34Z", "salary": {"currency": null, "max": null, "min": null, "period": "monthly", "term": null}, "salary_visible": false, "title_keywords": ["project manager", "assistant project manager"], "responsibilities": ["liaise with client", "report"], "requirements": {"degrees": ["diploma"], "majors": ["related disciplines", "project management", "design"], "languages": ["cantonese", "english", "mandarin"], "language_level": ["good command"], "hard_skills": ["project management", "autocad"], "soft_skills": ["project management", "hard working", "communication and interpersonal skills"], "languages_combined": [{"language": "cantonese", "language_level": ["good command"]}, {"language": "english", "language_level": ["good command"]}, {"language": "mandarin", "language_level": ["good command"]}]}, "experience_required": {"duration": ["5 years"], "field": ["retail"]}}, {"job_id": "100003009048988", "location_code": "hk", "company": "E F Design Limited", "job_title": "Project Assistant", "description": "We are looking for a caliber candidate to provide the administrative support to sales and marketing team.\n\nResponsibilities:\n\nProvide administrative and project support to the department, including preparation contracts,\u00a0quotations, working schedules, presentation materials and meeting minutes\nAssist the account manager to coordinate with internal and external project teams to ensure the smooth progress of project development\nMaintain filing system\nPerform other\u00a0ad hoc duties as assigned\n\nRequirements:\n\nDiploma holder with 1 year relevant working experience\nProficient in\u00a0MS Office applications, including MS Excel and PowerPoint. Chinese word processing is a MUST.\nCan-do attitude, detail minded, good multitasking and strong interpersonal skills\nGood command of spoken and written English and Chinese\n\nWe offer 5 days' work and attractive compensation package to the right candidates.\u00a0 Please click \"Apply Now\" to submit your full resume with expected salary.", "employment_types": ["Full Time", "Permanent"], "selling_points": ["Five-day work week", "Near Fortress Hill MTR station", "1 year relevant working experience"], "locations": ["Causeway Bay"], "categories": ["Design", "Interior", "Sales, CS & Business Devpt", "Sales Administration"], "post_time": "2022-01-14T07:50:22Z", "salary": {"currency": null, "max": null, "min": null, "period": "monthly", "term": null}, "salary_visible": false, "title_keywords": ["project assistant"], "responsibilities": ["ad hoc duties", "schedules", "contracts", "teams", "coordinate with", "maintain"], "requirements": {"degrees": ["diploma holder"], "majors": [], "languages": ["english", "chinese"], "language_level": ["good command"], "hard_skills": ["ms excel", "chinese word processing", "powerpoint", "ms office"], "soft_skills": ["interpersonal skills", "can-do attitude"], "languages_combined": [{"language": "english", "language_level": ["good command"]}, {"language": "chinese", "language_level": ["good command"]}]}, "experience_required": {"duration": ["1 year"], "field": ["relevant working experience"]}}, {"job_id": "100003009038032", "location_code": "hk", "company": "via architecture limited", "job_title": "INTERIOR DESIGNER / ASSISTANT INTERIOR DESIGNER", "description": "We are looking for self-motivated individuals to join our team of multi-disciplinary designers working on a variety of high-end interior design projects in Hong Kong, Macau and the Mainland.\n\nQualifications:\n\nDiploma / Degree holder in Interior Design or Architecture from accredited institutes\nMinimum 3-5 years of relevant local experience, in design and management of private residential / large scale residential / hospitality / commercial projects, including standard provisions, public areas and clubhouse\n\nResponsibilities / Skills:\n\nCapable of handling projects independently from design, presentations, tender, site works to completion, coordinating with clients, consultants and contractors to ensure timely and quality project execution\u00a0\nFluent in verbal and written English and Cantonese. Proficiency in Putonghua is an advantage\nProficient in AutoCAD, Photoshop, InDesign, Sketchup, Microsoft Office, Excel and PowerPoint\nStrong sense for graphic design, FF&E, art and / or decoration\n\nCharacter:\n\nSelf-motivated and a good team player\nPunctual, organized and disciplined\nCommunicates and collaborates with people, inside and outside of the Studio, from clients, consultants to craftspeople\nCreative, with a sense of functionality and practicality\n\nCandidate with less experience would be considered for the Assistant Interior Designer position.\n\nWe offer a 5-day work week and competitive remuneration package to suitable candidates. Interested parties please send your CV, portfolio and expected salary by clicking \"Apply Now\". All information collected shall be used for recruitment purposes only.\n", "employment_types": ["Full Time", "Permanent"], "selling_points": [], "locations": ["Kwun Tong"], "categories": ["Design", "Interior"], "post_time": "2022-01-11T04:40:40Z", "salary": {"currency": null, "max": null, "min": null, "period": "monthly", "term": null}, "salary_visible": false, "title_keywords": ["interior designer", "assistant interior designer"], "responsibilities": ["management", "graphic design", "quality", "presentations", "design", "tender", "architecture"], "requirements": {"degrees": ["diploma", "degree holder"], "majors": ["architecture", "design"], "languages": ["cantonese", "putonghua", "english"], "language_level": ["advantage", "proficiency", "fluent"], "hard_skills": ["excel", "microsoft office", "indesign", "presentations", "powerpoint", "autocad", "photoshop", "sketchup"], "soft_skills": ["organized", "good team player", "self-motivated", "independently", "capable", "timely", "creative"], "languages_combined": [{"language": "cantonese", "language_level": ["fluent"]}, {"language": "putonghua", "language_level": ["proficiency", "advantage"]}, {"language": "english", "language_level": ["fluent"]}]}, "experience_required": {"duration": ["minimum 3-5 years"], "field": ["commercial", "management", "designer", "design"]}}, {"job_id": "100003009034035", "location_code": "hk", "company": "Designcomefirst Limited", "job_title": "Assistant Interior Designer", "description": "Job Description:\n\nAssist the Project Manager to monitor the progress of interior decoration\u00a0and renovation works\nAssist to prepare tenders and contracts for the works\nLiaise and co-ordinate with internal and external parties on repairs, renovation and minor A&A projects\n\nRequirements:\n\nHolder of\u00a0Diploma /\u00a0Certificate in Surveying/\u00a0Architectural Design\u00a0/\u00a0Interior Design\nMinimum 1 year of relevant experience\nPractical skills in use of AUTOCAD\nKnowledge of construction and related ordinance\n\nInterested parties please apply with detailed resume stating salary expectation and available date. Applicants who do not hear from us within one month may consider their applications unsuccessful.\n\nPlease be assured that all personal information collected will solely be used for recruitment purpose. Those unsuccessful applications will be destroyed after three months.", "employment_types": ["Full Time"], "selling_points": ["5 days work, Bank holiday, Discretionary bonus", "Graduated in Interior Design Discipline", "Medical allowance"], "locations": ["Chai Wan"], "categories": ["Design", "Interior", "Others"], "post_time": "2022-01-10T02:29:03Z", "salary": {"currency": null, "max": null, "min": null, "period": "monthly", "term": null}, "salary_visible": false, "title_keywords": ["assistant interior designer"], "responsibilities": ["liaise", "co-ordinate with", "contracts", "renovation", "monitor", "internal and external parties"], "requirements": {"degrees": ["certificate", "diploma"], "majors": ["surveying", "design"], "languages": [], "language_level": [], "hard_skills": ["autocad"], "soft_skills": [], "languages_combined": []}, "experience_required": {"duration": ["minimum 1 year"], "field": ["relevant experience"]}}, {"job_id": "100003009049546", "location_code": "hk", "company": "lui design Ltd.", "job_title": "Design and Project Manager (Luxury Retail Design Project)", "description": "Our Clients are looking for Interior Designers. Great opportunities on new and existing projects that offer competitive remuneration packages and fringe benefits.\n\nResponsibilities:\n\nAssist the Senior Interior Designer\nDealing with clients, contractors, architectures, vendors, and project team members\nResponsible for design drawings and documentation including concept design and development, construction drawing, materials sourcing, and selection\nIdentify and understand clients\u2019 needs and provide customer services\n\nRequirements\n\nDiploma / Degree in Interior Design or Architecture or related field\nStrong Software Skills\nExperiences architecture / interior design / design works in residential / commercial / exhibition properties is preferred\nGood design ability and knowledge\nFluency in both written and spoken English and Cantonese. Fluency in Mandarin is a plus\n\nFor any interested parties, please kindly email a copy of your CV to\u00a0Lambert\u00a0lazur @ goughrecruitment.com.hk\u00a0for further discussion.", "employment_types": ["Full Time", "Permanent"], "selling_points": [], "locations": ["Sheung Wan"], "categories": ["Building & Construction", "Architectural Services", "Design", "Interior", "Building / Construction / QS"], "post_time": "2022-01-14T08:51:49Z", "salary": {"currency": null, "max": null, "min": null, "period": "monthly", "term": null}, "salary_visible": false, "title_keywords": ["project manager"], "responsibilities": [], "requirements": {"degrees": [], "majors": [], "languages": [], "language_level": [], "hard_skills": [], "soft_skills": [], "languages_combined": []}, "experience_required": {"duration": [], "field": []}}, {"job_id": "100003009050490", "location_code": "hk", "company": "Touch Consultancy Limited", "job_title": "3D Designer (Enscape) - Interior design", "description": "Our clients are well-established architectural practices with projects in HK and Greater Bay Area. They are currently offering attractive packages for Architectural professionals with strong experience\u00a0\n\nJob Details:\n\n\nMaster Degree holder in Architecture\nMember of HKIA / RIBA, Registered Architect\nAuthorized Person would be a bonus\nMinimum 3-6 years\u2019 post-qualification experience in delivering architectural projects in HK\nExperience in Institutional / Residential / Commercial / Healthcare / Education / projects experience are preferred\nTrack record of managing projects from design concept through to project completion\nStrong in project management and contract administration\nFamiliar with HK Architectural statutory requirements\nProficient in spoken and written Chinese and English\nMore experience will be considered as an Associate / Chief Architect\nImmediate preferred", "employment_types": ["Full Time", "Permanent"], "selling_points": ["Immediately available is preferable", "Proficient in 3D design software", "Attractive salary package"], "locations": ["Central & Western Area"], "categories": ["Building & Construction", "Architectural Services", "Design", "Graphics", "Interior"], "post_time": "2022-01-14T10:31:05Z", "salary": {"currency": null, "max": null, "min": null, "period": "monthly", "term": null}, "salary_visible": false, "title_keywords": ["designer"], "responsibilities": ["contract administration", "design concept", "project management", "statutory requirements", "architecture"], "requirements": {"degrees": ["master degree"], "majors": ["architecture"], "languages": ["english", "chinese"], "language_level": ["proficient"], "hard_skills": ["project management"], "soft_skills": ["project management"], "languages_combined": [{"language": "english", "language_level": ["proficient"]}, {"language": "chinese", "language_level": ["proficient"]}]}, "experience_required": {"duration": ["minimum 3-6 years"], "field": ["commercial", "healthcare", "post-qualification", "education"]}}, {"job_id": "100003009038176", "location_code": "hk", "company": "Goudie Associates", "job_title": "Interior Designer / Senior Interior Designer, Workplace", "description": "\nResponsibilities:\n\u2022 Drive consumers and competitor analysis to identify business opportunities\n\u2022 Drive market research to identify colour and material trends\n\u2022 Lead bags and accessories design projects from start to finish collaborating closely with management\n\u2022 Organize and communicate the design concept using mood boards\n\u2022 Prepare technical spec packs : line drawings, materials, colours and construction for prototyping\n\u2022 Oversee the full product cycle from concept to design, product development, production and market launch\n\u2022 Communicate and collaborate with cross-functional teams to bridge design specifications and production viability\n\u2022 Work closely with production team to comment on prototypes and track development progress\n\nRequirements:\n\u2022 University degree / high diploma in Fashion Design or related field.\n\u2022 At least 5 years of credible experience in bags and fashion accessories design.\n\u2022 Possess knowledge on bags and accessories market, design trends, brand identity, target customer and competitive landscape. Strong understanding of the importance of commercial value of designs.\n\u2022 Proficient in Illustrator, Photoshop and Adobe packages.\nHighly self-motivated and proactive with excellent written and verbal communication skills (English & Chinese).\n\u2022 Creative, attentive and detail minded\n\nWe offer competitive salary & benefit package. Ready to join the team? Please email us your resume and work examples.\n\n", "employment_types": ["Full Time", "Permanent"], "selling_points": [], "locations": ["Sai Ying Pun"], "categories": ["Building & Construction", "Architectural Services", "Design", "Graphics", "Interior"], "post_time": "2022-01-11T05:52:27Z", "salary": {"currency": null, "max": null, "min": null, "period": "monthly", "term": null}, "salary_visible": false, "title_keywords": ["interior designer", "senior interior designer"], "responsibilities": ["collaborate with", "management", "identify business opportunities", "design concept", "analysis", "market research", "design", "drawings", "design specifications", "cross-functional teams"], "requirements": {"degrees": ["high diploma", "university degree"], "majors": ["design"], "languages": ["english", "chinese"], "language_level": ["excellent"], "hard_skills": ["adobe", "illustrator", "photoshop"], "soft_skills": ["attentive", "communication skills", "self-motivated", "creative", "proactive"], "languages_combined": [{"language": "english", "language_level": ["excellent"]}, {"language": "chinese", "language_level": ["excellent"]}]}, "experience_required": {"duration": ["at least 5 years"], "field": ["design"]}}, {"job_id": "100003009045278", "location_code": "hk", "company": "Lucky Pet Limited", "job_title": "Graphic Designer", "description": "Job Duties:\n\nFloorplan and Fa\u00e7ade Design\n\n\nProvide preliminary layout showing the main zoning directions and the best circulation possibilities\nDesign colored floorplan & fa\u00e7ade options, on CAD & Photoshop, in line with store concept\nSelect the materials to be used within the range of availabilities among boutique concept\nDesign or outsource the 3D renderings of the two design options (external and internal views).\nProvide mood boards or sample boards when required\nDesign new furniture and showcases when required\n\nCall for tenders Management\n\n\nSupervise and check carefully the accuracy of the tender drawings.\nProvide sketch to draftsman when required (eg: door schedule\u2026) and ensure all the details are technically achievable.\nCoordinate the tender drawings specifications with lighting design, M&E design, security, IT, and visual merchandising teams\nSupervise and check carefully the accuracy of the SOR and T&C\nLead the call for tenders, answers the RFI's, analyze bid returns and award contractor.\n\nConstruction Management\n\n\nImplement an organization chart for each project. Who does what?\nBe fully involved on every steps of a store construction, from A to Z - Full 360\nEnsure the design, details and dimensions are respected. Any changes must go through your review and approval.\nReview rigorously the local contractor's shop drawings, ensure it matches with original design intent\nReview and comment the local contractor's samples and mock-ups\nAttend weekly site meetings I zoom calls and ensure the site technical decisions match with company quality requirements\nBe attentive to the functionality of the store and the quality of the lighting\nControl the construction schedule and monitor it\nE-Inspect the fa\u00e7ade, furniture and materials production in factory\nEnsure communication is smooth between all parties at all times: LL, GC, IT, Security, VM\u2026..\nBe a problem solver and find solution to technical issues or production issues\nEnsure handover is smooth and that VM, products and flowers are all well in place prior to the opening.\n\nRequirements:\n\n\nMaster degree in architecture or interior architecture\n8 to 10 years' experience in luxury jewellery retail\nSense for perfection\nWell organized and hands on\nGood communication skills\nGood capacity to synthetize\nAbility to endorse responsibilities\nAbility to work with different cultures and time difference\nAbility to work under pressure and to meet deadlines\nExcellent skills in autocad and photoshop,\nPerfect English speaking and writing - French, Mandarin, or Japanese is a plus", "employment_types": ["Full Time"], "selling_points": [], "locations": ["Tsim Sha Tsui"], "categories": ["Design", "Graphics", "Interior", "Others"], "post_time": "2022-01-13T07:32:22Z", "salary": {"currency": null, "max": null, "min": null, "period": "monthly", "term": null}, "salary_visible": false, "title_keywords": ["graphic designer"], "responsibilities": ["management", "construction management", "control", "site meetings", "review", "merchandising", "teams", "design", "drawings", "coordinate", "mock-ups", "quality", "specifications", "monitor", "schedule", "tender", "visual", "communication"], "requirements": {"degrees": ["master degree"], "majors": ["architecture"], "languages": ["japanese", "english", "french", "mandarin"], "language_level": [], "hard_skills": ["plus", "photoshop", "autocad"], "soft_skills": ["communication skills", "well organized", "hands on", "meet deadlines", "work under pressure"], "languages_combined": [{"language": "japanese", "language_level": []}, {"language": "english", "language_level": []}, {"language": "french", "language_level": []}, {"language": "mandarin", "language_level": []}]}, "experience_required": {"duration": ["8 to 10 years"], "field": ["retail"]}}, {"job_id": "100003009033523", "location_code": "hk", "company": "Innex Interiors Limited", "job_title": "Interior Designer / Assistant Project Manager", "description": "Responsibilities:\n\nTo monitor and control site progress\nTo ensure all construction activities comply with contractual and statutory requirement\nTo monitor overall financial, commercial, contractual and technical matters for\u00a0current projects.\nTo control and supervise overall site activities and liaise with client's representatives and subcontractors\nTo gather and analyse data relating to work progress, adequacy and effectiveness\n\nRequirements:\n\nDiploma or above\u00a0in interior design / building studies / architecture or equivalent\nAt least 10 years solid experience in\u00a0FITTING-OUT projects of residential, offices, hotel etc\nAt least 3 years experience in managerial level\nStrong technical background and site experience\nGood communication and sound relationship with cooperation parties including clients and subcontractors\nConversant with interior fit-out nature, A&A work and contractual documents\nStrong in leadership/management and can work under pressure\nGood computer literacy, especially in MS Word, MS Excel and MS Project\nGood command in written and spoken in English & Chinese\nLess experience will be considered as Assistant Project Manager\n\nWe offer competitive remuneration package (14 days Annual Leave, Double Pay, Discretionary Bonus, Group Medical Insurance, Bank Holidays, Education Assistance) to the right candidate.\u00a0Interested parties please send full resume with current and expected salary, and availability\u00a0to our HR manager.\u00a0 \u00a0(Please quote reference number.)\n\n*Personal data collected will be used strictly for recruitment purposes only.", "employment_types": ["Full Time"], "selling_points": [], "locations": ["Mong Kok"], "categories": ["Design", "Interior", "Building & Construction", "Building / Construction / QS", "Engineering", "Engineering Project Management"], "post_time": "2022-01-10T00:24:13Z", "salary": {"currency": null, "max": null, "min": null, "period": "monthly", "term": null}, "salary_visible": false, "title_keywords": ["assistant project manager", "interior designer"], "responsibilities": ["control", "site activities", "data", "monitor", "liaise with client", "analyse"], "requirements": {"degrees": ["diploma or above"], "majors": ["building studies", "architecture", "design"], "languages": ["english", "chinese"], "language_level": ["good command"], "hard_skills": ["ms excel", "ms word"], "soft_skills": ["communication", "computer literacy", "leadership", "work under pressure"], "languages_combined": [{"language": "english", "language_level": ["good command"]}, {"language": "chinese", "language_level": ["good command"]}]}, "experience_required": {"duration": ["at least 10 years", "at least 3 years"], "field": ["managerial"]}}, {"job_id": "100003009043123", "location_code": "hk", "company": "Maven Furniture (Hong Kong) Limited", "job_title": "Project Coordinator", "description": "Diploma / Degree in Interior or Architectural Design\nRelevant experience in hospitality design will be an advantage\nProficiency in AutoCAD, Photoshop, PowerPoint, Microsoft Office (Sketchup and Bluebeam Revu will be an advantage)\nGood design ability and knowledge of production drawings and interior detailing\nGood command of spoken and written English and Chinese (including Cantonese and Mandarin)\nAbility to communicate with design team through hand sketch or 3D program will be an advantage\nFresh graduate welcome\n\nWe work on a 5-day week and offer attractive salaries, with year-end bonus and other fringe benefits including group medical insurance and MPF contribution.\n\nInterested parties please click\u00a0\u201cApply Now\u201d\u00a0to apply job with your full resume, current and expected salary.\n\nYou are welcome to visit our website:\u00a0www.sldgroup.com\u00a0to have more understanding of our company.\n\nAll personal data collected will be used for recruitment purpose only.\u00a0", "employment_types": ["Full Time", "Permanent"], "selling_points": ["Diploma in design, project management", "Experience within retail millwork", "5 days work"], "locations": ["Mong Kok"], "categories": ["Design", "Interior", "Engineering", "Engineering Project Management", "Merchandising & Purchasing", "Furniture"], "post_time": "2022-01-12T09:51:10Z", "salary": {"currency": null, "max": null, "min": null, "period": "monthly", "term": null}, "salary_visible": false, "title_keywords": ["project coordinator"], "responsibilities": ["communicate with", "year-end", "mpf", "design", "drawings", "insurance"], "requirements": {"degrees": ["diploma", "degree", "fresh graduate"], "majors": ["design"], "languages": ["cantonese", "english", "chinese", "mandarin"], "language_level": ["good command"], "hard_skills": ["microsoft office", "powerpoint", "autocad", "photoshop", "sketchup"], "soft_skills": [], "languages_combined": [{"language": "cantonese", "language_level": ["good command"]}, {"language": "english", "language_level": ["good command"]}, {"language": "chinese", "language_level": ["good command"]}, {"language": "mandarin", "language_level": ["good command"]}]}, "experience_required": {"duration": [], "field": ["relevant experience", "design"]}}, {"job_id": "100003009049497", "location_code": "hk", "company": "Atelier Global Limited", "job_title": "Registered Architect", "description": "Requirements\n\nFor Goudie Associates Hong Kong harbour front design studio\nMinimum 3 years\u00a0(for senior interior designer, min 8 years)\u00a0quality international interior design and project management experience of workplace / corporate office, exhibition and retail projects including space planning and conceptual design with strong presentation\u00a0and rendering skills, strong interest in and understanding of current trends.\n\nHong Kong based, resident or with visa\nRecognised qualifications or equivalent experience in architecture and / or interior design\nGood command of written and spoken English and Cantonese.\u00a0 Mandarin an advantage\nProficient in AutoCAD, SketchUp,\u00a0Photoshop and PowerPoint.\u00a0 3Ds Max and Enscape is an advantage\nPleasant, proactive, a good team leader and player, responsible and self-motivated\nOccasional travel may be required\n\nBenefits\n\nBank holidays, 10 - 20 days annual leave, birthday leave, paternity leave, medical allowance, paid sick leave, dental allowance, overtime allowance, study allowance\n\nInterested parties please email your full resume with portfolio, availability, latest salary and expected salary to our HR Director.", "employment_types": ["Full Time"], "selling_points": ["large scale commercial development projects", "interested in China projects & willing to travel", "Registered Architect with HKIA or equivalent"], "locations": ["Wan Chai"], "categories": ["Building & Construction", "Architectural Services", "Design", "Interior"], "post_time": "2022-01-14T08:45:20Z", "salary": {"currency": null, "max": null, "min": null, "period": "monthly", "term": null}, "salary_visible": false, "title_keywords": [], "responsibilities": ["quality", "design", "project management", "architecture", "planning"], "requirements": {"degrees": [], "majors": [], "languages": ["cantonese", "english", "mandarin"], "language_level": ["advantage", "good command"], "hard_skills": ["harbour", "3ds max", "powerpoint", "project management", "autocad", "photoshop", "sketchup"], "soft_skills": ["self-motivated", "responsible", "pleasant", "project management", "good team leader", "proactive", "presentation"], "languages_combined": [{"language": "cantonese", "language_level": ["good command"]}, {"language": "english", "language_level": ["good command"]}, {"language": "mandarin", "language_level": ["advantage"]}]}, "experience_required": {"duration": ["min 8 years", "minimum 3 years"], "field": ["designer", "design", "project management", "retail", "planning"]}}, {"job_id": "100003009050932", "location_code": "hk", "company": "Bank of Communications Hong Kong Branch", "job_title": "Chief Dealer, Interest Rate Derivatives", "description": "\nGraphic Designer\nJob Highlight\nBranding, Graphic Design, Print advertising\nManage social media post FB, IG\nJob Description\n\u2022 2 years relevant experience\n\u2022 Proficiency in Mac Adobe design software is a must\n\u2022 Handle projects independently from concept to final production\n\u2022 Great team player, self-supervising and able to work under pressure\n\u2022 Highly creative with detailed-oriented professional\n\u2022 With passion for graphic design and advertising\n\u2022 Good time management and work efficiency with quality\n\u2022 Great communication skills and positive attitude\n\u5de5\u4f5c\u985e\u578b: Full-time, Permanent\n\u85aa\u916c: $13,000.00\u81f3$15,000.00(\u6bcf\u6708)\n\u6642\u9593:\n\u2022 Monday to Friday\nExperience:\nIllustrator: 1 year (Preferred)\nPhotoshop: 1 year (Preferred)\nInDesign: 1 year (Preferred)\n\n", "employment_types": ["Full Time"], "selling_points": ["SFO", "Interest Rate Derivatives", "Treasury"], "locations": ["Wan Chai"], "categories": ["Design", "Graphics", "Interior", "Others"], "post_time": "2022-01-14T11:51:11Z", "salary": {"currency": null, "max": null, "min": null, "period": "monthly", "term": null}, "salary_visible": false, "title_keywords": ["dealer"], "responsibilities": ["social media", "management", "supervising", "advertising", "software", "graphic design", "quality", "design", "communication", "work under pressure"], "requirements": {"degrees": [], "majors": [], "languages": [], "language_level": [], "hard_skills": ["indesign", "adobe", "illustrator", "photoshop"], "soft_skills": ["communication skills", "independently", "passion for", "work under pressure", "time management", "positive attitude", "team player", "creative", "detailed"], "languages_combined": []}, "experience_required": {"duration": ["2 years"], "field": ["relevant experience"]}}, {"job_id": "100003009033781", "location_code": "hk", "company": "SEN Construction Company Limited", "job_title": "Interior Designer / Assistant Interior Designer", "description": "Responsibilities\n\nreport to Project Director and assist Project Manager on assigned project\ncoordinate with factory production, visit site to coordinate with all other contractor\n\nRequirements\n\nDiploma or above in design, project management or related disciplines\nExperience from retail millwork manufacturer or fitting out contractor is preferred\nGood command of spoken/written English and Mandarin\nFamiliar with words, excels, outlook, Chinese input is necessary\nIndependent, mature, responsible and self-motivated\nKnowledge in AutoCAD is preferred but not necessary\nFrequent travel and station in Dongguan is REQUIRED\n\nWe offer competitive remuneration package to the right candidate. Interested parties are invited to send full resume, present and expected salary to email address\u00a0by clicking \"Apply Now\"\n\n\nPersonal data will be used for recruitment purpose only.\n", "employment_types": ["Full Time"], "selling_points": ["\u505a\u5927\u54c1\u724c\u5e97\u8216\u88dd\u4fee\u8a2d\u8a08, \u589e\u52a0\u500b\u4eba\u7d93\u9a57\u503c", "Double pay", "\u7531\u4e2d\u74b0\u6e2f\u9435\u5230\u516c\u53f8, \u53ea\u8981\u6b65\u884c5\u5206\u9418"], "locations": ["Central"], "categories": ["Design", "Interior", "Visual Merchandising", "Others"], "post_time": "2022-01-10T01:47:33Z", "salary": {"currency": "HKD", "max": 34999, "min": 14000, "period": "monthly", "term": null}, "salary_visible": true, "title_keywords": ["interior designer", "assistant interior designer"], "responsibilities": ["coordinate with", "report"], "requirements": {"degrees": ["diploma or above"], "majors": ["related disciplines", "project management", "design"], "languages": ["english", "chinese", "mandarin"], "language_level": ["good command"], "hard_skills": ["chinese input", "words", "project management", "outlook", "autocad"], "soft_skills": ["self-motivated", "independent", "responsible", "mature", "project management"], "languages_combined": [{"language": "english", "language_level": ["good command"]}, {"language": "chinese", "language_level": []}, {"language": "mandarin", "language_level": ["good command"]}]}, "experience_required": {"duration": [], "field": ["retail"]}}, {"job_id": "100003009040204", "location_code": "hk", "company": "Atelier Pacific Ltd", "job_title": "CAD Designer", "description": "\n\u2022 Lead a team to generate trading profit through dealing with Interest Rate products\n\u2022 Provide market information and/or pricing services to Treasury Market Sales\n\u2022 Degree holder or above with minimum 6 years\u2019 relevant experience in financial institutions\n\u2022 Familiar with trading system/software and qualified under SFO for handling Regulated Activities Types 1, 4 & 9 with TMA Full Member qualification are a must\nCandidates with less experience may be considered for the post of Deputy Chief Dealer, Interest Rate Derivatives\n\n", "employment_types": ["Full Time", "Permanent"], "selling_points": ["5 days work", "16 days annual leave", "Annual company outing"], "locations": ["North Point"], "categories": ["Building & Construction", "Architectural Services", "Design", "Interior", "Engineering", "Draftsman"], "post_time": "2022-01-12T01:52:04Z", "salary": {"currency": null, "max": null, "min": null, "period": "monthly", "term": null}, "salary_visible": false, "title_keywords": ["designer"], "responsibilities": ["lead a team", "market information", "software"], "requirements": {"degrees": ["degree holder"], "majors": [], "languages": [], "language_level": [], "hard_skills": ["sfo"], "soft_skills": [], "languages_combined": []}, "experience_required": {"duration": ["minimum 6 years"], "field": ["financial institutions", "relevant experience"]}}, {"job_id": "100003009039757", "location_code": "hk", "company": "T & T Interior Design Co.", "job_title": "Senior Interior Designer/ Interior Designer", "description": "Job duties:\n\nHandle full set of drawing including production drawings, interior detailing, material usage and FF& E\nAble to produce and communicate with design team though hand sketch or 3D program\u00a0\nSite work experiences & furniture prototype review will be an advantage\nLiaise with contractors, vendors and clients\u00a0\u00a0\n\nRequirements:\n\nDiploma/Degree in interior or Architectural design\nMinimum 5 years of relevant experience in hospitality, corporate office or/and luxury residential projects will be an advantage\nAble to handle projects independently\nProficiency in of AutoCAD, Sketchup, InDesign, Photoshop, Bluebeam Revu & MS Office Applications is an advantage\nGood command of spoken and written English and Chinese\n\n\n", "employment_types": ["Full Time", "Permanent"], "selling_points": ["Minimum 5 years of solid experience", "Diploma/Degree in interior or Architectural design", "Good design ability & knowledge"], "locations": ["Kowloon Bay"], "categories": ["Design", "Interior"], "post_time": "2022-01-11T11:32:17Z", "salary": {"currency": null, "max": null, "min": null, "period": "monthly", "term": null}, "salary_visible": false, "title_keywords": ["interior designer", "senior interior designer"], "responsibilities": ["communicate with", "review", "design", "drawings", "liaise with contractors"], "requirements": {"degrees": ["diploma", "degree"], "majors": ["design"], "languages": ["english", "chinese"], "language_level": ["good command"], "hard_skills": ["indesign", "sketchup", "autocad", "photoshop", "ms office"], "soft_skills": ["independently"], "languages_combined": [{"language": "english", "language_level": ["good command"]}, {"language": "chinese", "language_level": ["good command"]}]}, "experience_required": {"duration": ["minimum 5 years"], "field": ["relevant experience"]}}, {"job_id": "100003009042383", "location_code": "hk", "company": "Madison (Hong Kong) Limited", "job_title": "Senior Draftsman/ Assistant Designer", "description": "The Madison Group was founded in 1996 in Hong Kong as a company representing premium lifestyle brands like bulthaup, Sub-Zero, WOLF and Rimadesio. Through the years, The Madison Group has collaborated with the region's leading property developers on residential projects that have become the benchmark of luxury of living. Today, the group has operations and retail outlets in Singapore, Shanghai, Beijing and Hangzhou. Its newly launched concept store, House of Madison, is an expression of its retail ambitions.\n\nLaunched in October 2014, House of Madison is a groundbreaking retail experience by The Madison Group, a global company representing luxury lifestyle brands. The sprawling three-storey, 12,000 square foot space serves as a retail playground for tinkers and tinkerers, artists and artisans exploring the intersection of design, gastronomy and the art of expressive living.\n\nTo cope with the company's expansion and market demands, we are now looking for high calibre to join our winning team.\n\nResponsibilities:\n\nl\u00a0\u00a0Produce design drawings including layouts and elevations\n\nl\u00a0\u00a0oordinate with sales team and site team to ensure project completion\n\nl\u00a0\u00a0 Provide modification and advices on altering design changes\n\nl\u00a0\u00a0 Handle full set of Auto CAD drawings for production independently\n\nl\u00a0\u00a0 Complete ad hoc assignments as assigned by superiors\n\nRequirements:\n\nl\u00a0\u00a0 Diploma/Certificate or above with related internal design/Graphic studies, with minimum 4 years working experience in Interior or Architecture field\n\nl\u00a0\u00a0 Good proficiency in AutoCAD 2-D drawings, 3-D would be a plus\n\nl\u00a0\u00a0 Experience in kitchen design is preferred\n\nl\u00a0\u00a0 Knowledge of Photoshop, Illustrator will be an advantage\n\nl\u00a0\u00a0 Responsible, mature and able to work independently\n\nl\u00a0\u00a0 Strong communication skills and Fluent in spoken and written English, Cantonese and Mandarin\n\nl\u00a0\u00a0 Immediate available is highly preferred", "employment_types": ["Full Time"], "selling_points": ["Wanchai", "Immediate available", "5 days work"], "locations": ["Central"], "categories": ["Design", "Interior"], "post_time": "2022-01-12T07:15:39Z", "salary": {"currency": null, "max": null, "min": null, "period": "monthly", "term": null}, "salary_visible": false, "title_keywords": ["draftsman", "assistant designer"], "responsibilities": ["design drawings", "design", "drawings", "sales team", "ad hoc assignments"], "requirements": {"degrees": ["certificate", "diploma"], "majors": ["architecture", "design"], "languages": ["cantonese", "english", "mandarin"], "language_level": ["fluent"], "hard_skills": ["illustrator", "plus", "photoshop", "autocad"], "soft_skills": ["mature", "communication skills", "work independently", "responsible"], "languages_combined": [{"language": "cantonese", "language_level": ["fluent"]}, {"language": "english", "language_level": ["fluent"]}, {"language": "mandarin", "language_level": ["fluent"]}]}, "experience_required": {"duration": ["minimum 4 years"], "field": ["related", "graphic", "design"]}}, {"job_id": "100003009038454", "location_code": "hk", "company": "I.T Apparels Limited", "job_title": "Interior Designer (REF: JDB-IT-ID)", "description": "\u00a0Accountabilities \u2013 Key Result Areas\n\nCarry out design concept and development, assist preparation of detailed and construction drawings, sourcing and selection of materials and preparation of quotations\nHandle various design documentation and presentation work\u00a0\nCoordinate and liaise with contractors, vendors and project team members to collect business and project requirements to ensure effective and satisfactory project completion\n\nExperience / Qualification Requirements\n\nDiploma / Degree holder in Architecture or Interior Design or equivalent\nWith at least 3 years of experience, with retail fit-out and large scale project experience is preferred\nFamiliar with AutoCAD, Photoshop, Adobe illustrator, 3D Max and other relevant graphic and design tools\n\nCompetitive remuneration and benefit package will be offered to the right candidate. Please submit your application by clicking \"Apply Now\" below.\n\nAll data collected is for recruitment purpose only.\n\nSure you want to know more about our company and brands, simply follow our\n\nWEBSITE at http://www.ithk.com\u00a0 \u00a0 \u00a0 \u00a0 \u00a0 \u00a0 \u00a0 \u00a0 \u00a0 \u00a0 \u00a0 \u00a0 \u00a0 \u00a0 \u00a0 \u00a0 \u00a0 \u00a0 \u00a0 \u00a0 \u00a0 \u00a0 \u00a0 \u00a0 \u00a0 \u00a0 \u00a0 \u00a0 \u00a0 \u00a0 \u00a0 \u00a0 \u00a0 \u00a0\u00a0\n\nFACEBOOK at\u00a0http://www.facebook.com/I.Ttheofficialpage \u00a0 \u00a0 \u00a0 \u00a0 \u00a0 \u00a0 \u00a0 \u00a0 \u00a0 \u00a0 \u00a0 \u00a0 \u00a0 \u00a0\n\nINSTAGRAM at http://instagram.com/ithk\u00a0 \u00a0 \u00a0 \u00a0 \u00a0 \u00a0 \u00a0 \u00a0 \u00a0 \u00a0 \u00a0 \u00a0 \u00a0 \u00a0 \u00a0 \u00a0 \u00a0 \u00a0 \u00a0 \u00a0 \u00a0 \u00a0 \u00a0 \u00a0 \u00a0 \u00a0 \u00a0 \u00a0\n\nWEIBO at\u00a0http://e.weibo.com/ithongkong", "employment_types": ["Full Time", "Permanent"], "selling_points": ["Carry out design concept and development", "Familiar with AutoCAD and 3D Max", "With at least 3 years of experience"], "locations": ["Southern Area"], "categories": ["Design", "Fashion", "Interior", "Others"], "post_time": "2022-01-11T06:55:30Z", "salary": {"currency": null, "max": null, "min": null, "period": "monthly", "term": null}, "salary_visible": false, "title_keywords": ["interior designer"], "responsibilities": ["project requirements", "data", "design concept", "website", "design", "drawings", "coordinate", "recruitment", "documentation", "facebook", "liaise with contractors", "architecture"], "requirements": {"degrees": ["diploma", "degree holder"], "majors": ["architecture", "design"], "languages": [], "language_level": [], "hard_skills": ["adobe illustrator", "autocad", "documentation", "max", "facebook", "photoshop"], "soft_skills": ["presentation", "detailed"], "languages_combined": []}, "experience_required": {"duration": ["at least 3 years"], "field": ["retail"]}}, {"job_id": "100003009038313", "location_code": "hk", "company": "Interspace Limited", "job_title": "Interior Designer / Senior Interior Designer - Office / Workplace Design", "description": "The Role\n\nAs an\u00a0Incredible\u00a0Interior Designer in Interspace, you will work with the senior members of our company to prepare presentation packages and attend presentations for our workplace design bidding, specify materials and references, and develop plans and drawings for our ongoing projects. You will work collaboratively with our Assistant Designers to deliver amazing workplace designs for our clients.\n\nThis mid to senior-level position offers the potential to manage the design process for mid-sized (or larger) projects independently. Candidates with less experience may be offered an Assistant Interior Designer position. Career progression to a Project Designer/Design Manager position is the next step for ambitious teammates.\n\nSince we are a Design & Build company with our own fitting out team, you will gain unique experience unavailable at typical design consultancies: bid estimation, construction project management, materials sourcing and procurement, and a deep understanding of technical/shop drawings for all trades.\u00a0\n\nThe Hard Part\n\nDo you have what it takes to join our team?\n\n1 -\u00a0 \u00a0 You graduated from a university-level program with a bachelor's degree in Interior Design or Architecture and you have at least 5 full years experience working in the interior design field handing workplace projects in Hong Kong. Exceptional candidates without degrees will still be considered.\n\n2 -\u00a0 \u00a0 You can communicate in English confidently. We would prefer if you can also speak Cantonese and Mandarin.\n\n3 -\u00a0 \u00a0\u00a0You have plenty of practical experience using both AutoCAD and SketchUp in a team/collaborative studio (there are no solo warriors here).\n\n4 -\u00a0 \u00a0 You are an over achiever with above-average intelligence and a highly creative sense of design.\n\n5 -\u00a0 \u00a0 You ask questions constantly and aren't afraid to defend your belief/position, but you can also accept when you're wrong and learn from it!\n\nIf you can say \"yes\" to all five of the qualifications above, then Apply now\u00a0for a chance to interview with our Creative Director and visit our amazing studio!\u00a0\n\nPlease note, we are committed to running an inclusive, healthy, and safe workplace -- every one of our teammates has been vaccinated against COVID-19, and we expect the same from all new team members.\n", "employment_types": ["Full Time", "Permanent"], "selling_points": ["Design awesome workplaces to *WOW* our clients!", "Dynamic, intelligent, and happy colleagues.", "Crazy-cool design studio with chill BGM vibes."], "locations": ["Causeway Bay"], "categories": ["Building & Construction", "Architectural Services", "Design", "Interior"], "post_time": "2022-01-11T06:31:07Z", "salary": {"currency": null, "max": null, "min": null, "period": "monthly", "term": null}, "salary_visible": false, "title_keywords": ["interior designer", "senior interior designer"], "responsibilities": ["presentations", "drawings", "design", "project management", "develop plans", "architecture"], "requirements": {"degrees": ["degree", "bachelor"], "majors": ["architecture", "design"], "languages": ["cantonese", "english", "mandarin"], "language_level": [], "hard_skills": ["no", "presentations", "project management", "safe", "autocad", "sketchup"], "soft_skills": ["independently", "deep", "collaborative", "unique", "project management", "committed", "creative", "presentation"], "languages_combined": [{"language": "cantonese", "language_level": []}, {"language": "english", "language_level": []}, {"language": "mandarin", "language_level": []}]}, "experience_required": {"duration": [], "field": ["designer", "procurement", "design", "project management", "construction", "team"]}}, {"job_id": "100003009042096", "location_code": "hk", "company": "Global Virtual Design And Construction Limited", "job_title": "Junior Media Producer/ Trainee", "description": "Responsibilities\nResponsible for creating the motion of CG characters or objects\nResponsible for the technical execution of animating CG characters or objects\nRequirements\n0-2 years of experience in Animation/CG Graphics\nKnowledge of 3D character setup is preferred\nProficient in XSI, Maya or 3ds Max\nKnowledge of Photoshop, After Effects or other relative software\nAbility to modeling, animation, texturing and lighting\nStrong art and design sense and creative\nDetail-minded and a good team player\nWilling to learn and work under pressure and tight schedule\nOutdoor work is required\nLess experience will be considered as Trainee\nWe offer competitive remuneration package with comprehensive fringe benefits to the right candidates.\u00a0 Interested parties, please send your full resume, with current and expected salary, date of availability to email by clicking \"Apply Now\"", "employment_types": ["Full Time", "Permanent"], "selling_points": ["Responsible for creating the motion", "Responsible for the technical execution", "0-2 years of experience in Animation/CG Graphics"], "locations": ["Not Specified"], "categories": ["Media & Advertising", "Creative / Design", "Design", "Graphics", "Interior"], "post_time": "2022-01-12T06:05:58Z", "salary": {"currency": null, "max": null, "min": null, "period": "monthly", "term": null}, "salary_visible": false, "title_keywords": ["producer", "trainee", "junior"], "responsibilities": [], "requirements": {"degrees": [], "majors": [], "languages": [], "language_level": [], "hard_skills": ["graphics", "maya", "cg", "3ds max", "after effects", "photoshop"], "soft_skills": ["detail-minded", "good team player", "willing to learn", "creative", "work under pressure"], "languages_combined": []}, "experience_required": {"duration": ["0-2 years"], "field": []}}, {"job_id": "100003009037868", "location_code": "hk", "company": "Wecon Limited", "job_title": "Technical Assistant (Works)", "description": "Roles and Responsibilities:\u00a0\nTo prepare, check and update structural drawings, sketches and details;\nTo liaise with professionals, technical officers and site staff of the Housing Department;\nTo work at Housing Department.\nRequirements:\nLevel 2 or Grade E or above in five subjects (including Chinese, English and Mathematics) in HKDSE / HKCEE or equivalent;\nDiploma in Building Studies or Architectural Studies is a must;\nMinimum 3 years draftsman experience in architectural or interior design firms;\nProficiency in PC applications including MS Office and AutoCAD, SketchUp, Photoshop, Acrobat, etc.\nGood command of written & Spoken English and Chinese.\nWe offer very attractive remuneration package and career advancement opportunities for the right candidates.\u00a0 Interested parties please send a covering letter and detailed resume including current and expected salary to the Head of HR & Admin., 18/F., Tung Hip Commercial Building, 244-252 Des Voeux Road Central, Hong Kong or by email via clicking \"Apply Now\".\nPersonal data collected will be treated in strictest confidence and handled confidentially by authorized personnel for recruitment-related purposes only.\u00a0\u00a0", "employment_types": ["Full Time", "Permanent"], "selling_points": [], "locations": ["Not Specified"], "categories": ["Building & Construction", "Architectural Services", "Design", "Interior", "Engineering", "Draftsman"], "post_time": "2022-01-11T04:06:12Z", "salary": {"currency": null, "max": null, "min": null, "period": "monthly", "term": null}, "salary_visible": false, "title_keywords": ["technical assistant"], "responsibilities": ["liaise with", "sketches", "drawings"], "requirements": {"degrees": ["diploma", "hkdse"], "majors": ["mathematics", "building studies"], "languages": ["english", "chinese"], "language_level": ["good command"], "hard_skills": ["acrobat", "pc applications", "autocad", "photoshop", "ms office", "sketchup"], "soft_skills": [], "languages_combined": [{"language": "english", "language_level": ["good command"]}, {"language": "chinese", "language_level": ["good command"]}]}, "experience_required": {"duration": ["minimum 3 years"], "field": ["design"]}}, {"job_id": "100003009050132", "location_code": "hk", "company": "Gough Recruitment (Hong Kong) Pty Limited", "job_title": "Project Manager / Assistant Project Manager - Client-side", "description": "Our client is a developer & operator in Hong Kong who is currently seeking a\u00a0Project Manager / Assistant Project Manager to help expanding their portfolio in Hong Kong.\u00a0\n\nResponsibilities:\n\nResponsible for full-spectrum support in overall monitoring and project management of redevelopment\u00a0 projects in Hong Kong,\nPlan, monitor and control various aspects in different phases of A&A, interior fitting-out works for residential building / boutique hotel renovation projects.\nEnsure project completion within satisfactory quality, saftery standards, cost & time\nEnsure all works are compliance with statutory regulations\u00a0\nLiaise and collaborate with external consultants and relevant government departments to achieve objectives with architectural works.\nConduct feasibility studies, technical due diligence studies\n\nRequirements\n\nDegree / Master's in Architecture, Building Services or related background.\nAt least 4 years working in consultancy firm / property developers.\nRegistered Architect with HKIA would be an advantage.\nExperienced in managing\u00a0A&A, fitting-out projects in offices / residential / commercial / hotels preferred.\nExcellent communication skills with fluency in English and Cantonese\nProficient in both written and spoken English and Chinese\nLess experience will be considered as Assistant Project Manager.", "employment_types": ["Full Time", "Permanent"], "selling_points": ["A&A, Fitting-out, Redevelopment Projects in HK", "Architect / Building Surveyor -> PM Experience", "MNC, Fluency in English & Cantonese"], "locations": ["Central & Western Area"], "categories": ["Building & Construction", "Architectural Services", "Design", "Interior"], "post_time": "2022-01-14T09:53:02Z", "salary": {"currency": null, "max": null, "min": null, "period": "monthly", "term": null}, "salary_visible": false, "title_keywords": ["project manager", "assistant project manager"], "responsibilities": ["liaise", "collaborate with", "control", "cost", "due diligence", "monitoring", "monitor", "renovation", "quality", "compliance with statutory regulations", "project management", "plan"], "requirements": {"degrees": ["degree", "master"], "majors": ["building services", "architecture"], "languages": ["cantonese", "english", "chinese"], "language_level": ["fluency", "excellent", "proficient"], "hard_skills": [], "soft_skills": ["communication skills"], "languages_combined": [{"language": "cantonese", "language_level": ["fluency", "excellent"]}, {"language": "english", "language_level": ["proficient", "fluency", "excellent"]}, {"language": "chinese", "language_level": ["proficient"]}]}, "experience_required": {"duration": [], "field": []}}, {"job_id": "100003009008045", "location_code": "hk", "company": "", "job_title": "Senior Interior Designer (5 days work week)", "description": "Certificate / Diploma holder in interior design\nAt least 5 years residential/hospitality projects experience preferable\nGood command of written and spoken English and Chinese\nGood design sense.\nAble to handle full set of working drawing with design detailing experience\nAble to handle quotation deal with client, manage project and prepare drawings independently\nProficient in AutoCAD, Sketchup, Photoshop,AI\nGood team player with mature working attitude, stable and organized\nWilling to work under pressure, overtime and able to work independently\nImmediate availability is\u00a0preferable", "employment_types": ["Full Time", "Permanent"], "selling_points": ["Bank holidays, Performance bonus, 12 days of AL", "Diploma or above, 4 years' relevant exp.", "Immediately available is preferred"], "locations": ["Yuen Long"], "categories": ["Design", "Interior", "Others"], "post_time": "2022-01-10T16:52:32Z", "salary": {"currency": "HKD", "max": 34999, "min": 20000, "period": "monthly", "term": null}, "salary_visible": true, "title_keywords": ["senior interior designer"], "responsibilities": ["work under pressure", "quotation", "design", "drawings"], "requirements": {"degrees": ["diploma holder", "certificate"], "majors": ["design"], "languages": ["english", "chinese"], "language_level": ["good command"], "hard_skills": ["ai", "sketchup", "photoshop", "autocad"], "soft_skills": ["organized", "good team player", "independently", "work independently", "mature", "stable", "work under pressure"], "languages_combined": [{"language": "english", "language_level": ["good command"]}, {"language": "chinese", "language_level": ["good command"]}]}, "experience_required": {"duration": ["at least 5 years"], "field": ["design"]}}, {"job_id": "100003009035110", "location_code": "hk", "company": "Century Technology & Consultant Limited", "job_title": "Interior Designer / Assistant Interior Designer", "description": "The Role:\nWe are now looking to expand our team with talented and well rounded individuals that are capable of self management. Ability to take responsibility for a project from concept to completion is expected of candidates for the role of Senior Interior Designer. Candidates with less experience will be considered for the role of Interior Designer. Ongoing projects include caf\u00e9\u2019s, restaurants, residential and office designs among others.\n\nJob description:\n\nTo lead a number of high-end projects and\u00a0supervising less experienced staff\nPerform concept design, developing design directions at the early stages of projects\u00a0\nTo attend site visits, delegate meetings, coordinate with contractors on site\nFollow up with material and FF&E suppliers\n\n\u00a0Job requirements:\n\nDiploma or above in Architecture/ interior design or equivalent\n4 years' relevant experience in interior design\nExperienced in AutoCAD / Sketchup / Photoshop / Powerpoint\nProficient in spoken and written English & Cantonese\u00a0\nImmediately available is preferred\nInterested candidates, please contact us at 94586344 for company details before applying.", "employment_types": ["Full Time"], "selling_points": ["Fresh graduate / 1-3 years Working Experience", "Diploma Holder in Interior Design", "5-day work week"], "locations": ["Shatin Area"], "categories": ["Design", "Interior"], "post_time": "2022-01-10T06:01:54Z", "salary": {"currency": null, "max": null, "min": null, "period": "monthly", "term": null}, "salary_visible": false, "title_keywords": ["interior designer", "assistant interior designer"], "responsibilities": ["supervising", "coordinate with", "developing", "design"], "requirements": {"degrees": ["diploma or above"], "majors": ["architecture", "design"], "languages": ["cantonese", "english"], "language_level": ["proficient"], "hard_skills": ["sketchup", "photoshop", "powerpoint", "autocad"], "soft_skills": [], "languages_combined": [{"language": "cantonese", "language_level": ["proficient"]}, {"language": "english", "language_level": ["proficient"]}]}, "experience_required": {"duration": ["4 years"], "field": ["relevant experience", "design"]}}, {"job_id": "100003009033432", "location_code": "hk", "company": "Zinc Studio Limited", "job_title": "interior designer / assistant interior designer", "description": "\nResponsibilities:\n\u2022 Handle design drawings, design documentation & presentation work including concept design and development, construction drawing, materials sourcing\n\u2022 Coordinate and liaise with clients, contractors, vendors and project team members for the assigned project to ensure project effectiveness and competition\n\u2022 Complete routine and special tasks as assigned by superiors\n\nRequirements:\n\u2022 Diploma or above in Interior Design\n\u2022 Minimum 1-3 years solid working experience in all phases of design & documentation in interiors projects\n\u2022 Proficiency in AutoCAD, SketchUp, Photoshop and MS Applications\n\u2022 Good conceptual design, detailed working drawing and presentation skills\n\u2022 Knowledge in 3D Studio Max or AI is a plus\n\u2022 Good communication in both spoken & written English, Cantonese & Mandarin\n\u2022 Able to meet tight schedule, handle multiple tasks and work independently with good communication and organization skills\n\u2022 Team orientated, responsible, self-motivated and creative\u00a0\n\u2022\u00a0Position would be offered depends on experiences\n\u2022 Available immediately is highly preferred\n\n\n\nInterested Candidates please send us\u00a0full resume with current & expected salary by clicking \u201cAPPLY NOW\u201d button. If you have any queries, please feel free to contact us at 3612 4550. We are looking forward to hear from you soon.\n\nPersonal data will be used for recruitment purpose only.\n", "employment_types": ["Full Time", "Contract"], "selling_points": ["Bank Holiday", "5/ 5.5 day work week", "Special Bonus"], "locations": ["Chai Wan"], "categories": ["Design", "Interior"], "post_time": "2022-01-09T16:20:59Z", "salary": {"currency": null, "max": null, "min": null, "period": "monthly", "term": null}, "salary_visible": false, "title_keywords": ["interior designer", "assistant interior designer"], "responsibilities": ["liaise with clients", "design drawings", "design", "coordinate", "documentation"], "requirements": {"degrees": ["diploma or above"], "majors": ["design"], "languages": ["cantonese", "english", "mandarin"], "language_level": ["good"], "hard_skills": ["plus", "ms applications", "ai", "autocad", "photoshop", "documentation", "max", "sketchup"], "soft_skills": ["work independently", "self-motivated", "responsible", "communication", "handle multiple tasks", "presentation skills", "organization skills", "creative", "detailed"], "languages_combined": [{"language": "cantonese", "language_level": ["good"]}, {"language": "english", "language_level": ["good"]}, {"language": "mandarin", "language_level": ["good"]}]}, "experience_required": {"duration": ["minimum 1-3 years"], "field": ["design"]}}, {"job_id": "100003008935874", "location_code": "hk", "company": "", "job_title": "Lighting Designer Assistant / Lighting Designer", "description": "requirements:\n\nDiploma / Degree in interior design\uff1b\nPassion for design\uff1b\n0-3\u00a0years\u2019 experience\uff1b\n\nGood communication and good time management\uff1b\nWell-organized and responsible\uff1b\nFluent in English, Cantonese and mandarin\uff1b\nWell-organized ;\nAutoCad & Sketch-Up is a\u00a0MUST\uff1b\nnear chai wan MTR station;\n\n\nCandidates with less experience and\u00a0 will be considered as the post of assistant interior designer\n\nIf you are interested, please \"Apply\" or contact Shin Ng by phone at\u00a0+852 3990-5433 for more information / sent your updated resume with expected salary\u00a0and portfolio to\u00a0info.zincstudio(a)gmail. com\n\nwelcome to visit our website: http://www.zincstudio.co/ or facebook: https://www.facebook.com/zincstudioco to have more understanding of our studio.", "employment_types": ["Full Time", "Part Time", "Permanent"], "selling_points": [], "locations": ["Causeway Bay"], "categories": ["Design", "Industrial / Product", "Interior", "Others"], "post_time": "2022-01-13T18:54:40Z", "salary": {"currency": null, "max": null, "min": null, "period": "monthly", "term": null}, "salary_visible": false, "title_keywords": ["designer", "assistant"], "responsibilities": ["management", "website", "design", "communication", "contact", "facebook"], "requirements": {"degrees": ["diploma", "degree"], "majors": ["design"], "languages": ["cantonese", "english", "mandarin"], "language_level": ["fluent"], "hard_skills": ["facebook", "wan", "autocad"], "soft_skills": ["responsible", "passion for", "well-organized", "communication", "time management"], "languages_combined": [{"language": "cantonese", "language_level": ["fluent"]}, {"language": "english", "language_level": ["fluent"]}, {"language": "mandarin", "language_level": ["fluent"]}]}, "experience_required": {"duration": ["0-3 years"], "field": ["designer"]}}, {"job_id": "100003009040355", "location_code": "hk", "company": "COMODO Interior & Furniture Design Co Limited", "job_title": "Marketing Executive (Interior Design)", "description": "Benefits\n\nHospitalize + Medical Insurance\n5 days work\nPerformance Bonus\n\nRequirements\n\no\u00a0\u00a0\u00a0\u00a0experiences in lighting design would be mostly concerned, or architectural practice, interior, landscape, urban planning or related field\n\no\u00a0\u00a0\u00a0\u00a0excellent skill in autocad ,ps ,dialux ,ppt ,3d modeling ,ms office & other graphic presentation software\n\no\u00a0\u00a0\u00a0\u00a0proficient in both written and spoken English and Chinese- Cantonese & Mandarin\n\no\u00a0\u00a0\u00a0\u00a0with passion in lighting design\n\no\u00a0\u00a0\u00a0\u00a0require for business travels when necessary\n\nResponsibilities\n\no\u00a0\u00a0\u00a0\u00a0good time manner and motivated\n\no\u00a0\u00a0\u00a0\u00a0detailing and creative with excellent design coordination skills\n\no\u00a0\u00a0\u00a0\u00a0assistance for architectural lighting projects and coordination works with a responsible performance for variety tasks\n\no\u00a0\u00a0\u00a0\u00a0participate in coordination meetings\n\nminimum of 4 years and above lighting design experiences would consider as designer\n\nwith less experience would consider as assistant\n\nfresh graduate also welcome\n\ninterested parties \u2018APPLY NOW\u2019 please provide- cover letter & cv\n\nportfolio, current & expected salary, date available", "employment_types": ["Full Time"], "selling_points": [], "locations": ["Tsuen Wan Area"], "categories": ["Sales, CS & Business Devpt", "Business Development", "Design", "Interior", "Marketing / Public Relations", "Marketing - General / Support"], "post_time": "2022-01-12T02:24:55Z", "salary": {"currency": null, "max": null, "min": null, "period": "monthly", "term": null}, "salary_visible": false, "title_keywords": ["marketing executive"], "responsibilities": [], "requirements": {"degrees": [], "majors": [], "languages": [], "language_level": [], "hard_skills": [], "soft_skills": [], "languages_combined": []}, "experience_required": {"duration": [], "field": []}}, {"job_id": "100003009037875", "location_code": "hk", "company": "Wecon Limited", "job_title": "Technical Assistant (Architectural)", "description": "Requirements :\nDiploma or above in Interior Design, Construction Management or equivalent;\n3 years experience in handling interior design details and shop drawings;\nResidential design coordination experience would be an advantage;\nProficiency in AutoCAD, Photoshop and MS office;\nHard working, obligation, teamwork, willing to take up new challenges and work under pressure;\nGood command of written and spoken English and Chinese.\nWe Offer 5-day workweek, bank holiday and attractive remuneration package to the right candidate.\nInterested parties please send your full resume with current and expected salary by clicking \"APPLY NOW\"\nPlease visit www.innex.hk to learn more about us", "employment_types": ["Full Time", "Permanent"], "selling_points": [], "locations": ["Not Specified"], "categories": ["Building & Construction", "Architectural Services", "Design", "Interior", "Others"], "post_time": "2022-01-11T04:06:50Z", "salary": {"currency": null, "max": null, "min": null, "period": "monthly", "term": null}, "salary_visible": false, "title_keywords": ["technical assistant"], "responsibilities": ["construction management", "design", "drawings", "coordination", "work under pressure"], "requirements": {"degrees": ["diploma or above"], "majors": ["construction management", "design"], "languages": ["english", "chinese"], "language_level": ["good command"], "hard_skills": ["ms office", "photoshop", "autocad"], "soft_skills": ["hard working", "teamwork", "coordination", "work under pressure"], "languages_combined": [{"language": "english", "language_level": ["good command"]}, {"language": "chinese", "language_level": ["good command"]}]}, "experience_required": {"duration": ["3 years"], "field": ["design"]}}, {"job_id": "100003009040215", "location_code": "hk", "company": "Atelier Pacific Ltd", "job_title": "Assistant Designer (Environmental Graphics)", "description": "Roles and Responsibilities:\u00a0\nTo prepare, check and update structural drawings, submission drawings, presentation drawings, survey plans & schedules\nTo liaise / coordinate with professional, technical officers and site staff where appropriate.\u00a0\nRequirements:\nLevel 2 or Grade E or above in five subjects (including Chinese, English and Mathematics) in HKDSE / HKCEE or equivalent;\nDiploma or Higher Certificate in either Building Studies or Architectural Studies;\nGood in PC applications including MS Office and AutoCAD, SketchUp, Photoshop, Acrobat, MicroStation etc;\nGood command of written & Spoken English and Chinese.\nWe offer very attractive remuneration package and career advancement opportunities for the right candidates.\u00a0 Interested parties please send a covering letter and detailed resume including current and expected salary to the Head of HR & Admin., 18/F., Tung Hip Commercial Building, 244-252 Des Voeux Road Central, Hong Kong or by clicking \"Apply Now\"\nPersonal data collected will be treated in strictest confidence and handled confidentially by authorized personnel for recruitment-related purposes only.\u00a0", "employment_types": ["Full Time", "Permanent"], "selling_points": ["5 days work", "Environmental Graphic Design", "Fringe Benefits"], "locations": ["North Point"], "categories": ["Design", "Graphics", "Industrial / Product", "Interior"], "post_time": "2022-01-12T01:54:56Z", "salary": {"currency": null, "max": null, "min": null, "period": "monthly", "term": null}, "salary_visible": false, "title_keywords": ["assistant designer"], "responsibilities": ["liaise", "schedules", "coordinate with", "drawings", "plans"], "requirements": {"degrees": ["higher certificate", "diploma", "hkdse"], "majors": ["mathematics", "building studies"], "languages": ["english", "chinese"], "language_level": ["good command"], "hard_skills": ["acrobat", "pc applications", "autocad", "photoshop", "ms office", "sketchup"], "soft_skills": [], "languages_combined": [{"language": "english", "language_level": ["good command"]}, {"language": "chinese", "language_level": ["good command"]}]}, "experience_required": {"duration": [], "field": []}}, {"job_id": "100003009034129", "location_code": "hk", "company": "The Key Design Limited", "job_title": "\u5ba4\u5167\u8a2d\u8a08\u5e2b Interior Designer", "description": "To handle full set design drawing of exhibition and event.\nTo drawing 3D rendering, technical drawing and floor plan for production.\nTo provide the design concept, space planning & structural design for exhibitions & other special events\nTo design solution relevant to the nature of the event and requirements of individual projects\n\nRequirements:\n\nIVE graduate / Diploma or above in\u00a0Interior\u00a0/ Graphic\u00a0/\u00a0Exhibition\nProficient in 3D software (e.g. 3Ds Max, Illustrator, Photoshop, AutoCAD)\nWell experienced hands-on working in 3D, graphic, artwork, and output production independently is essential\n2 years experience in Exhibition / Event Design/ Production House\u00a0will be an advantage\nImmediate available preferred\n\n\n\nWe offer competitive remuneration package to the successful candidates. Applicants please submit your full CV with expected salary, availability & project portfolio for interview.\n\nPersonal data will be used for recruitment purpose only.\n", "employment_types": ["Full Time"], "selling_points": ["\u5168\u8077, \u5de5\u4f5c\u6642\u9593 (\u4e0a\u534811:30\u5206\u81f3\u4e0b\u53489\u6642\u6b63), \u6bcf\u661f\u671f\u5de5\u4f5c6\u5929, \u9700\u8981\u8f2a\u4f11", "\u4e2d\u4e94\u7a0b\u5ea6, \u61c2\u8b80\u5beb\u4e2d\u6587\u53ca\u82f1\u6587, \u6700\u5c112\u5e74\u76f8\u95dc\u5de5\u4f5c\u7d93\u9a57", "\u7cbe\u901a SKETCHUP\u3002AUTOCAD\u3002PHOTOSHOP"], "locations": ["Kowloon Bay"], "categories": ["Building & Construction", "Architectural Services", "Design", "Interior", "Others"], "post_time": "2022-01-10T02:45:27Z", "salary": {"currency": "HKD", "max": 29999, "min": 11000, "period": "monthly", "term": null}, "salary_visible": true, "title_keywords": ["interior designer"], "responsibilities": ["software", "3d rendering", "design concept", "design", "planning", "plan", "output production", "technical drawing"], "requirements": {"degrees": ["diploma or above"], "majors": [], "languages": [], "language_level": [], "hard_skills": ["3d software", "3ds max", "illustrator", "photoshop", "autocad"], "soft_skills": ["hands-on", "independently"], "languages_combined": []}, "experience_required": {"duration": ["2 years"], "field": ["design"]}}, {"job_id": "100003009039975", "location_code": "hk", "company": "AES-Adliger Exhibition Service Ltd", "job_title": "3D Designer (Exhibition / Event Design) \u2013 (Full Time / Part Time / Work From Home )", "description": "To support our continuous growth and expansion in Hong Kong, Aedas Interiors is now seeking a high calibre candidate for the following position:\n\n\nRequirements:\n\nMinimum 3 years post design qualification experience;\nInterior Design qualification and background;\nExperience in Retail design preferred;\nFluency in written and spoken English and Mandarin is mandatory;\nAble to provide creative and well thought through design solutions;\nRhino and related rendering software experience required;\nAutoCAD and related technology experience required;\nMore experienced candidate will be considered as Senior Interior Designer.\n\n\nAedas Interiors provides opportunities for long term career development with an expanding international practice. We offer attractive compensation and benefit packages. Interested parties please send detailed CV, current & expected salary, availability by clicking the Apply now.\n\nAedas Interiors is an Equal Opportunity Employer\n(Data collected will be used for recruitment purpose only)", "employment_types": ["Full Time", "Part Time", "Freelance"], "selling_points": ["Experience in exhibition or interior decoration", "Good knowledge in 3Ds Max, Photoshop", "Strong graphic design sense"], "locations": ["Kowloon Bay"], "categories": ["Design", "Graphics", "Interior", "Others"], "post_time": "2022-01-11T16:02:29Z", "salary": {"currency": null, "max": null, "min": null, "period": "monthly", "term": null}, "salary_visible": false, "title_keywords": ["designer"], "responsibilities": ["career development", "software", "design", "design solutions"], "requirements": {"degrees": [], "majors": [], "languages": ["english", "mandarin"], "language_level": ["fluency"], "hard_skills": ["autocad", "rhino"], "soft_skills": ["creative"], "languages_combined": [{"language": "english", "language_level": ["fluency"]}, {"language": "mandarin", "language_level": ["fluency"]}]}, "experience_required": {"duration": ["minimum 3 years"], "field": ["related", "retail", "design"]}}, {"job_id": "100003009039462", "location_code": "hk", "company": "Aedas Interiors Limited", "job_title": "Retail Interior Designer", "description": "If you have strong desire to look for challenges, development of creativity and personal growth, this is a good opportunity for you to develop your career in CLDW. We offer rewarding career opportunity and attractive package. For further information about us, please visit www.cldw.com.hk.\n\nMain Job Duties:\n\nResponsible for account servicing, project management from budgeting, Client & Contractor coordination, production implementation, on-site set-up and dismantle supervision;\nTo supervise and manage the production of projects, e.g. monitor and QC production progress;\nTo liaise with sub-contractors, vendors, production team and design team for project preparation;\nImmediate available\nRequirement:\n\nForm 6 or above, diploma holder of business administration, project management or other related courses\n2+ years solid experience in interior design or architectural firm or construction company is advantage;\nProficient knowledge in the Use of material and finishing, construction, supervise design and working drawing, and other related reports;\nAble to handle clients, sub-contractors and vendor independently;\nPresentable, proactive, self-initiative, independent, patient, multi-task skills and able to work overnight & under pressure;\nGood command of written & spoken English and Mandarin\nGood knowledge in MS office\nApplicants with less than 1 year experience but with good potential will also be considered.\nInterested parties please send full resume with date of availability, present & expected salary and portfolio to email by clicking \"Apply Now\".\nIf you do feel you possess the qualities we have mentioned above, and would like to work with a brilliant group of people, please do not hesitate to send us your full resume with present and expected salaries.\nAs an equal opportunity employer, we welcome applications from all qualified candidates. Please note that only shortlisted candidates will be notified. Applicants not hearing from us within 4 weeks from the date of advertisement may consider their applications unsuccessful. All personal data of unsuccessful applicants will be treated in strict confidentiality and used for recruitment purposes only, and will be destroyed immediately upon completion of the recruitment exercise", "employment_types": ["Full Time", "Permanent"], "selling_points": ["Interior Design qualification", "Creative with retail design experience", "Rhino & AutoCAD and related technology experience"], "locations": ["Quarry Bay"], "categories": ["Building & Construction", "Architectural Services", "Design", "Interior", "Others"], "post_time": "2022-01-11T09:51:15Z", "salary": {"currency": null, "max": null, "min": null, "period": "monthly", "term": null}, "salary_visible": false, "title_keywords": ["interior designer"], "responsibilities": [], "requirements": {"degrees": [], "majors": [], "languages": [], "language_level": [], "hard_skills": [], "soft_skills": [], "languages_combined": []}, "experience_required": {"duration": [], "field": []}}, {"job_id": "100003009033316", "location_code": "hk", "company": "Linkus Concept Studio Limited", "job_title": "Assistant Interior Design / Interior Designer", "description": "Requirements:\n2-5years experience in residential projects;\u00a0\nGood in communication and time management;\nStrong self-disciplines, well organized and responsible;\nProactive thinking/ planning;\nSite co-ordination & project management experience is a preferred;\nProficient in AutoCAD,\u00a0 SketchUp, Vray, Enscape, PS, MS Office;\nAble to handle full set of working drawings independently;\nGood command of spoken and written English and Chinese;\nImmediate availability is highly preferred ;\nCandidate with less experience will consider as Assistant Interior Designer.\nJob Description:\n\nFlexible working hour;\nPerformance bonus;\nHandle meeting, on site coordination & presentation documents;\nProduce construction and details drawings.\n\ninterested candidates please send your\u00a0full resume with portfolio, current & expected salary and earliest available date\u00a0by clicking \" APPLY NOW\"", "employment_types": ["Full Time"], "selling_points": [], "locations": ["Central"], "categories": ["Design", "Interior"], "post_time": "2022-01-09T16:25:52Z", "salary": {"currency": null, "max": null, "min": null, "period": "monthly", "term": null}, "salary_visible": false, "title_keywords": ["interior designer", "assistant"], "responsibilities": ["site coordination", "drawings"], "requirements": {"degrees": [], "majors": [], "languages": ["english", "chinese"], "language_level": ["good command"], "hard_skills": ["project management", "ms office", "sketchup", "autocad"], "soft_skills": ["proactive", "independently", "responsible", "well organized", "communication", "project management", "time management"], "languages_combined": [{"language": "english", "language_level": ["good command"]}, {"language": "chinese", "language_level": ["good command"]}]}, "experience_required": {"duration": [], "field": ["project management", "designer"]}}, {"job_id": "100003009033975", "location_code": "hk", "company": "Lubuds F&B Group", "job_title": "Interior Designer / Assistant Interior Designer", "description": "Job Description\n\nMy client is an interior design firm based in Hong Kong. They are specializing an international brand including retail and commercial design projects. The boutique locate for K11 MUSEA, 1881 Heritage, Ocean Terminal, Element Shop, Macau and China.\n\nWelcome to join our team to cope with our rapid expansion in both mainland China and Hong Kong.\n\nRequirements\n\nDiploma holder or above in Interior Design\nBasic\u00a0computer knowledge in AutoCAD\u00a0and\u00a0Photoshop are\u00a0preferable\nCapable in handling project independently for interior designer\n\nResponsible of site management, site survey,\u00a0 site staff supervision, etc.\u00a0for interior designer\n\nBasic Cantonese, English & Putonghua\nTraveling to overseas/ PRC is required\nMin 2 years site experience for interior designer\u00a0\n\nResponsibilities:\u00a0\n\nAssist the Senior Interior Designer\nDealing with clients, contractors, architectures, vendors and project team members\nResponsible for design drawings and documentation including concept design and development, construction drawing, materials sourcing and selection\nIdentify and understand clients\u2019 needs and provide customer services\n\nWe offer\u00a0double pay,\u00a0bank holidays, 5 1/2day work,\u00a0annual leave and MPF. Interested candidates please send your application letter with CV, portfolio and salary expectations by clicking 'Apply Now'", "employment_types": ["Full Time", "Permanent"], "selling_points": [], "locations": ["Southern Area"], "categories": ["Building & Construction", "Architectural Services", "Design", "Interior", "Others"], "post_time": "2022-01-10T02:18:53Z", "salary": {"currency": null, "max": null, "min": null, "period": "monthly", "term": null}, "salary_visible": false, "title_keywords": ["interior designer", "assistant interior designer"], "responsibilities": ["design"], "requirements": {"degrees": ["diploma holder"], "majors": ["design"], "languages": ["cantonese", "putonghua", "english"], "language_level": ["basic"], "hard_skills": ["documentation", "basic", "photoshop", "autocad"], "soft_skills": ["independently", "capable", "responsible"], "languages_combined": [{"language": "cantonese", "language_level": ["basic"]}, {"language": "putonghua", "language_level": []}, {"language": "english", "language_level": []}]}, "experience_required": {"duration": ["min 2 years"], "field": ["designer"]}}, {"job_id": "100003009034755", "location_code": "hk", "company": "FCS Interior Design Consultant Limited", "job_title": "Senior Designer / Interior Designer / Sales & Marketing Manager", "description": "Sound knowledge\u00a0of Auto-CAD, Photoshop, Sketchup and MS software.\nIntermediate and advanced knowledge of Revit is an advantage.\nExperience in the set-up and production of tender and construction documents is a must.\nShould be organised and able to work independently, as well as to handle multiple projects\u00a0\nMust be willing to take initiative.\nKnowledge of IT system is an advantage\n\nWhat We Offer:\n\n16 days annual leave, increasing to 21 days with long service\nBirthday leave & Marriage leave\nComprehensive medical and dental insurance\u00a0\nDiscretionary performance bonus\nAnnual salary review\nAnnual company outing\nExcellent career prospect\u00a0\n\nInterested parties please click \"APPLY NOW\" to submit your application.\n\n*Personal data collected will be used for recruitment purposes only.", "employment_types": ["Full Time"], "selling_points": [], "locations": ["Wan Chai"], "categories": ["Design", "Interior", "Others", "Marketing / Public Relations", "Marketing - Market Research"], "post_time": "2022-01-10T04:09:32Z", "salary": {"currency": null, "max": null, "min": null, "period": "monthly", "term": null}, "salary_visible": false, "title_keywords": ["senior designer", "interior designer", "sales & marketing manager"], "responsibilities": ["multiple projects", "software", "tender"], "requirements": {"degrees": [], "majors": [], "languages": [], "language_level": [], "hard_skills": ["cad", "revit", "sketchup", "photoshop"], "soft_skills": ["work independently", "initiative", "advanced", "organised"], "languages_combined": []}, "experience_required": {"duration": [], "field": ["construction"]}}, {"job_id": "100003009045961", "location_code": "hk", "company": "Smart Will Engineering Limited", "job_title": "\u9ad8\u7d1a\u5ba4\u5167\u8a2d\u8a08\u5e2b", "description": "Entry Pathway:\n\nAre you ready to work in an open-minded, fun and different working environment?\nLet\u2019s join FCS\u00a0Interior Design Consultant Ltd\n\nI\u00a0\u00a0\u00a0\u00a0 \u00a0\u2013\u00a0 Bachelor's degree / Higher Diploma\u00a0in Interior Design or\u00a0\n\u00a0 \u00a0 \u00a0 \u00a0 \u00a0 \u00a0Architecture with over 5 years working experience in corporate\n\u00a0 \u00a0 \u00a0 \u00a0 \u00a0 \u00a0interior design sector.\n\nII\u00a0\u00a0\u00a0 \u00a0\u2013\u00a0Good communication and confident to speak in English, Cantonese and\n\u00a0 \u00a0 \u00a0 \u00a0 \u00a0 Mandarin are essential.\n\nIII\u00a0 \u00a0 \u00a0\u00a0\u2013\u00a0Experience in space planning / conceptual design / sketching and\n\u00a0 \u00a0 \u00a0 \u00a0 \u00a0 \u00a0Strong experience in technical integration and drawing production\n\u00a0 \u00a0 \u00a0 \u00a0 \u00a0 \u00a0with AutoCAD, SketcuUp, and 3ds Max.,\n\nIIII\u00a0\u00a0 \u00a0\u2013\u00a0Passionate about Interior Design and willing to learn from the\n\u00a0 \u00a0 \u00a0 \u00a0 \u00a0 \u00a0mistake to level up\n\nV \u00a0\u00a0\u00a0\u00a0\u2013\u00a0when you decide to become one of our core member, the most\n\u00a0 \u00a0 \u00a0 \u00a0 \u00a0 \u00a0Important is:\u00a0\u00a0\n\nPROFIT SHARING\u00a0 to staff with proven abilities\n\nEntrepreneurial work environment and good career prospect\nOpportunities working with multi-national clients\n\nIf you are interested in this exciting opportunity, please catch up the chance and click \u201cApply Now\u201d to\u00a0submit your application with CV, portfolio in PDF (less than 8MB) and\u00a0current & expected salary.\n\nWe looking forward to hearing from you!\n\n*** (All information collected will be treated in strict confidence for recruitment purpose only.)\n\n\n\nAttractive Performance Bonus\nInterested in designing and creative thinking\nDesign \u201cSMART\u201dworking environment\nEncourage\u00a0to participate in interior design competitions\u00a0\u00a0\nBrave to have the challenge and innovative\n\nSenior Designer / Interior Designer\nResponsibilities:\nLeading role in design, ensures clients\u2019 values are approximately, business needs are integrated and the design is executed holistically.\nWorking with multi-disciplines specialist articulate client\u2019s aspiration and strive to provide bespoke solutions.\nCollaborate and Work with the team to create ideas to prepare the presentation and make them happen.\n\n\u00a0*****Remarks: Candidate with less experience will be considered for the position of\u00a0Designer.\n\n\n\nSales & Marketing Manager\nResponsibilities:\n\nIdentify and explore new business opportunities\nMaintaining an awareness of interior industry news, best practices, and trends\nDeveloping, maintaining and improve relationships with existing and new clients\nCoordinating with leadership, design and consultant teams to develop and produce proposal package.\nResearch and analyze global shifts and trends in work behaviours to develop and improve recommendations with respect to physical, digital and social workplaces\nCreate and execute commercial office design concepts through schematic planning\nDesign office environments to achieve client\u2019s brand identity and develop unique design concepts\nManage construction documents from designers and consultants\n\nRequirements:\u00a0\n\nRelevant corporate interior design and fitting out, office furniture or real estate experience\nExcellent presentation and communication skills\nProficient in Word, Excel and Power point\nExcellent in English, Chinese and Mandarin, both spoken and written\nGood time management and organization and ability to maintenance accuracy when working towards deadlines\nDesigner\u2019s proficient in AutoCAD, Photoshop, Sketch up and 3Ds Max is preferred", "employment_types": ["Full Time"], "selling_points": [], "locations": ["Wan Chai"], "categories": ["Building & Construction", "Architectural Services", "Design", "Interior", "Building / Construction / QS"], "post_time": "2022-01-13T09:14:29Z", "salary": {"currency": "HKD", "max": 34999, "min": 25000, "period": "monthly", "term": null}, "salary_visible": true, "title_keywords": [], "responsibilities": ["collaborate", "design concepts", "ideas", "explore new business opportunities", "maintaining", "teams", "developing", "design", "develop", "planning"], "requirements": {"degrees": [], "majors": [], "languages": ["english", "chinese", "mandarin"], "language_level": ["excellent"], "hard_skills": ["excel", "3ds max", "maintenance", "sketch up", "word", "photoshop", "power point", "autocad"], "soft_skills": ["communication skills", "time management", "presentation"], "languages_combined": [{"language": "english", "language_level": ["excellent"]}, {"language": "chinese", "language_level": ["excellent"]}, {"language": "mandarin", "language_level": ["excellent"]}]}, "experience_required": {"duration": [], "field": ["design"]}}, {"job_id": "100003009041128", "location_code": "hk", "company": "Creativo Design & Contracting Company Limited", "job_title": "\u5de5\u5834\u52a9\u7406/\u96dc\u5de5", "description": "\u5de5\u4f5c\u5167\u5bb9\u00a0: \u4e00\u822c\u5ba4\u5167\u8a2d\u8a08\u5e2b\u5de5\u4f5c(\u8ca0\u8cac\u8655\u7406\u5168\u5957\u5ba4\u5167\u8a2d\u8a08\u9805\u76ee,\u8ca0\u8cac\u7e6a\u5716\u5de5\u4f5c\u3001\u65bd\u5de5\u5716\u3001\u900f\u8996\u5716\u3001\u96fb\u5716\u53ca\u4e0a\u5ee0\u5716\u7b49) ,\u719f\u6089\u96fb\u8166\u8edf\u4ef6\u64cd\u4f5c\u5305\u62ec Sketchup, AutoCAD, PHOTOSHOP\u53caMSOFFICE\u7b49\u512a\u5148\n\n\u8981\u6c42\u5b78\u6b77\u00a0: \u4e2d\u4e94\u7a0b\u5ea6; 5\u5e74\u7d93\u9a57; \u826f\u597d\u7cb5\u8a9e; \u4e00\u822c\u666e\u901a\u8a71; \u4e00\u822c\u82f1\u8a9e; \u61c2\u8b80\u5beb\u4e2d\u6587; \u61c2\u8b80\u5beb\u82f1\u6587; \u9700\u6700\u5c113-5\u5e74\u4f4f\u5b85\u8a2d\u8a08\u7d93\u9a57,\u80fd\u7368\u7acb\u9762\u5c0d\u5ba2\u6236\n\n\u4e0a\u73ed\u6642\u9593\u00a0: \u6bcf\u6708$25,000-$35,000(\u8996\u4e4e\u5de5\u4f5c\u7d93\u9a57\u800c\u5b9a), \u4e0a\u534810\u664230\u5206\u81f3\u4e0b\u53488\u6642, \u6bcf\u9031\u5de5\u4f5c5.5\u5929,\u8f2a\u4f11, \u6bcf\u5929\u5de5\u4f5c 8 .5\u5c0f\u6642\n\n\u4e0a\u73ed\u5730\u5740\u00a0: \u7063\u4ed4,\u77f3\u9580", "employment_types": ["Full Time"], "selling_points": [], "locations": ["Kwun Tong"], "categories": ["Design", "Interior", "Transportation & Logistics", "Inventory / Warehousing", "Building & Construction", "Others"], "post_time": "2022-01-12T03:29:25Z", "salary": {"currency": null, "max": null, "min": null, "period": "monthly", "term": null}, "salary_visible": false, "title_keywords": [], "responsibilities": [], "requirements": {"degrees": [], "majors": [], "languages": [], "language_level": [], "hard_skills": ["autocad", "sketchup"], "soft_skills": [], "languages_combined": []}, "experience_required": {"duration": [], "field": []}}, {"job_id": "100003009044932", "location_code": "hk", "company": "Touch Consultancy Limited", "job_title": "Interior Designer -Hong Kong", "description": "\n\u5730\u5340 : \u89c0\u5858\n\u8077\u8cac : \u4e00\u822c\u5009\u5eab\u5de5\u4f5c, \u5354\u52a9\u5e2b\u5085\u958b\u6599, \u5165\u8ca8\u51fa\u8ca8, \u4e00\u822c\u96dc\u5de5\u5de5\u4f5c, \u6e05\u6f54\u5730\u65b9\n\u8cc7\u6b77 : \u4e2d\u4e09\u7a0b\u5ea6; 1\u5e74\u7d93\u9a57; \u826f\u597d\u7cb5\u8a9e; \u4e00\u822c\u666e\u901a\u8a71; \u4e00\u822c\u82f1\u8a9e; \u61c2\u8b80\u5beb\u4e2d\u6587; \u7565\u61c2\u8b80\u5beb\u82f1\u6587; \u6709\u8cac\u4efb\u611f,\u5de5\u4f5c\u52e4\u596e,\u5de5\u4f5c\u4e3b\u52d5,\u5177\u826f\u597d\u6e9d\u901a\u6280\u5de7,\u5b88\u6642,\u8aa0\u5be6,\u80fd\u7368\u7acb\u5de5\u4f5c\n\u5f85\u9047 : \u6bcf\u6708$11,000 - $13,000, \u6709\u96d9\u7ce7, \u52e4\u5de5\u734e\u91d1, \u8d85\u6642\u5de5\u4f5c\u6d25\u8cbc, \u7537\u58eb\u4f8d\u7522\u50477\u5929 \u53ca\u4ea4\u901a\u6d25\u8cbc, \u661f\u671f\u4e00\u81f3\u516d: \u4e0a\u53489\u6642\u81f3\u4e0b\u53486\u6642, \u6bcf\u9031\u5de5\u4f5c6\u5929\n\u7533\u8acb\u9808\u77e5 : \u6c42\u8077\u8005\u53ef\u50b3\u771f(31571896)\u6216\u96fb\u90f5(Apply Now)\u5c65\u6b77\u8868\u7d66\u6d3b\u85dd\u8853\u88dd\u98fe\u6709\u9650\u516c\u53f8\u3002\u5982\u8981\u7d22\u53d6\u6536\u96c6\u500b\u4eba\u8cc7\u6599\u8072\u660e, \u8acb\u8207\u5289\u5c0f\u59d0(Email)\u806f\u7d61\u3002\n\n", "employment_types": ["Full Time"], "selling_points": ["International Interior Designer opportunity", "To work on high end hospitality projects in Asia", "Westernized team culture"], "locations": ["Central & Western Area"], "categories": ["Design", "Interior"], "post_time": "2022-01-13T06:40:48Z", "salary": {"currency": "HKD", "max": 44999, "min": 30000, "period": "monthly", "term": null}, "salary_visible": true, "title_keywords": ["interior designer"], "responsibilities": [], "requirements": {"degrees": [], "majors": [], "languages": [], "language_level": [], "hard_skills": [], "soft_skills": [], "languages_combined": []}, "experience_required": {"duration": [], "field": []}}]