[{"job_id": "100003009054879", "location_code": "hk", "company": "Orienta Lab Limited", "job_title": "Graphic Designer", "description": "Business Sector:\u00a0\u00a0Crypto Art & NFT\u00a0\n\n\nLooking for .....\n\nFull-time/Part-time :\u00a0 \u00a0 \u00a0Graphic Designer\n\nJob Description:\n\nWe\u2019re looking for a creative and enthusiastic Graphic Designer to help us with all kinds of materials designing work.\n\nIn this role, you will be responsible for the design of various types of digital artworks, posters and other project propaganda visual materials. You will participate in brand crossover, promote the project, do the time and cost control and risk management. Work closely with the company's brand to efficiently implement the creative ideas and designs of the projects and planning requirements.\n\nThe role requires a passion for our mission and an eagerness to roll up your sleeves. Besides, it involves the creativity of activity planning, certain understanding of crypto art and popular culture.\n\nRequirements:\nMust have:\n\n1\u3001Major in visual art related fields or rich experience in visual design;\n\n2\u3001Love design, rich imagination, and keen on current design trends.\n\n3\u3001Have certain design ability and good visual aesthetics, and can skillfully use PS, AI and other design software;\n\n4\u3001Familiar with digital art, good marketing and brand building ability, cost control and management awareness, and unique understanding of brand marketing.\n\n5\u3001Strong learning ability, innovation ability, teamwork ability and pressure resistance.\n\n6\u3001Good communication skills, punctual, detailed-minded, hardworking and responsible\u00a0\n\nPlease attach your portfolio when submitting your resume.\n\nNice to have:\nExtra:\n\n-Design experience in other NFT projects\n-Familiarity with nowdays NFTs\n\n-Outstanding performance in one or more abilities such as illustration, animation ,etc. are preferred\n\n________________________________________________________________________\n\u00a0Salary:\u00a0Negotiable\n\nWatsapp: 63671819 / 56912649\nWechat: TYJBRIAN /\u00a054302895\n\nCompany address: 10/F Infotech Centre, 21 Hung To Road, Kwun Tong, HK", "employment_types": ["Full Time", "Part Time", "Permanent", "Temporary", "Contract", "Internship", "Freelance"], "selling_points": ["Creative contents and marketing purpose", "After effects, Illustrator, Premier Pro, Photoshop", "Experience in sci-fi, anime, fantasy"], "locations": ["Ngau Tau Kok"], "categories": ["Design", "Fashion", "Graphics", "Multi-media"], "post_time": "2022-01-17T16:21:10Z", "salary": {"currency": null, "max": null, "min": null, "period": "monthly", "term": null}, "salary_visible": false, "title_keywords": ["graphic designer"], "responsibilities": ["management", "creative ideas", "designing", "design", "cost control", "visual", "planning"], "requirements": {"degrees": [], "majors": [], "languages": [], "language_level": [], "hard_skills": ["ai", "nice", "wechat", "visual design", "illustration"], "soft_skills": ["communication skills", "learning ability", "responsible", "keen", "teamwork", "unique", "hardworking", "detailed"], "languages_combined": []}, "experience_required": {"duration": [], "field": ["related", "design"]}}, {"job_id": "100003009054619", "location_code": "hk", "company": "K11 Concepts Limited", "job_title": "Multimedia/ Graphic/3D Designer", "description": "(Only\u00a0those candidates who submit a\u00a0portfolio / assessible link(s) will be\u00a0considered)\n\nResponsibilities\n\nResponsible for conceptualisation and implementation of design solutions that meet marketing strategies from concept, creative design to artwork production\nEnsure that all creative is in line with brand character and reinforce brand domination.\nCo-work with different departments on mall marketing events and campaigns\nStay up to date on latest creative trends, transmedia applications and competitive business environment\n\nRequirements\n\nDiploma/ Degree holder in Graphic Design or in a related field from a recognized institution\nMinimum 3 years solid working experience in graphic design and artwork production\nExperience in Luxury, Art, Fashion or Retail Industry is an advantage\nStrong layout and typography skill is essential\nHigh level of proficiency in design software and applications, such as Adobe Creative Suite\nExperience with print design, sound knowledge of print procedures,\u00a0animation and video production.\nAbility to pay attention to detail and grasp project needs and consider practical solutions\nAbility to imbibe good time management and balance work on multiple projects simultaneously\nGood command of written and spoken English and Chinese, Mandarin is an advantage\n\n\u00a0Personal Attributes\n\nAn entrepreneur who is able to think out of the box\nA team player and a relationship builder\nable to work independently and handle multiple projects\nWell motivated, organized, and good interpersonal skill\nInquisitive and able to work a fast-paced and dynamic working environment\nProactive and with good problem solving skills\nPassion for creating outstanding quality of original works and openness to innovative ways of doing things", "employment_types": ["Full Time", "Permanent"], "selling_points": ["Support K11 campaigns and creative initiatives", "After effects, Illustrator, Premier Pro, Photoshop", "Experience in Luxury, Art, Fashion or Retail"], "locations": ["Tsim Sha Tsui"], "categories": ["Design", "Graphics", "Multi-media"], "post_time": "2022-01-17T10:15:43Z", "salary": {"currency": null, "max": null, "min": null, "period": "monthly", "term": null}, "salary_visible": false, "title_keywords": ["designer"], "responsibilities": ["marketing events", "marketing strategies", "design solutions", "artwork production", "implementation", "design"], "requirements": {"degrees": ["diploma", "degree holder"], "majors": ["graphic design"], "languages": ["english", "chinese", "mandarin"], "language_level": ["advantage", "good command"], "hard_skills": ["problem solving skills", "dynamic", "adobe creative suite"], "soft_skills": ["organized", "work independently", "proactive", "creative", "passion for", "interpersonal skill", "innovative", "problem solving skills", "motivated", "dynamic", "attention to detail", "team player", "time management"], "languages_combined": [{"language": "english", "language_level": ["advantage", "good command"]}, {"language": "chinese", "language_level": ["advantage", "good command"]}, {"language": "mandarin", "language_level": ["advantage", "good command"]}]}, "experience_required": {"duration": ["minimum 3 years"], "field": ["retail industry", "video production", "graphic design", "print", "design"]}}, {"job_id": "100003009052060", "location_code": "hk", "company": "eMotionLab Limited", "job_title": "Account Servicing Manager/ Project Manager", "description": "If you are a\u00a0Account Servicing Manager (AM) / Project Manager (PM)\u00a0who aspire to plan, oversee and lead meaningful storytelling video projects from ideation to completion,\n\nWe should meet!\n\nWe are looking for high caliber talents to join our\u00a0growing team\u00a0\n... in our\u00a0new spacious office\n\u2026 and to chill out with us in our\u00a0amazing balcony!\n\nAM Responsibilities:\n\nTo develop and maintain good relationship with potential and current clients\nTo accurately identify client needs and provide professional advice\nTo build and maintain harmonized agency-client relationship at all levels\nPrepare and present engaging creative proposal with creative team\nPreparing pricing proposal that engage business while also profitable\n\nPM Responsibilities:\n\nTo manage and utilize resources effectively\u00a0and keep track of multiple works and project status to ensure timely delivery\nTo carry out all duties in planning, coordination, organization and implementation of productions and projects\nTo develop excellent communication with all parties involved (the creative, production team & the client)\nTo coordinate on logistical arrangement for productions\n\nJob Requirements:\n\nUniversity graduate and relevant working experience in agency\nUnderstanding of design, production, motion graphic and animation fundamentals\nWith active network in CG animation, motion graphic & multimedia production industry is an advantage, but not essential\nGood communication and interpersonal skills\nExcellent communication in both written and oral presentations (English and Chinese).\nWell-organized, detail minded and able to work independently\nProficiency in English, Mandarin and Cantonese\nAble to work under pressure\nFresh graduates\u00a0/ candidates with less experience can be considered as Account Servicing Executive/ Production assistant\n\nInterested candidates please include your current and expected salary, website/ samples of your work in your application.\n\nPlease include\u00a0[Account Servicing Manager/ Project Manager]\u00a0in the subject line.\n\nPersonal data collected will be handled strict confidence for recruitment related purpose only.\n", "employment_types": ["Full Time"], "selling_points": ["Account Servicing Manager/ Project Manager", "Convenient location", "5 days work and dynamic working environment"], "locations": ["Wong Tai Sin Area"], "categories": ["Media & Advertising", "Account Servicing", "Strategic Planning", "Design", "Multi-media"], "post_time": "2022-01-17T02:01:19Z", "salary": {"currency": null, "max": null, "min": null, "period": "monthly", "term": null}, "salary_visible": false, "title_keywords": ["project manager", "manager"], "responsibilities": ["implementation", "maintain good relationship", "develop", "communication", "coordinate", "maintain", "coordination", "planning"], "requirements": {"degrees": ["university graduate"], "majors": [], "languages": ["cantonese", "english", "chinese", "mandarin"], "language_level": ["excellent", "proficiency"], "hard_skills": ["cg", "multimedia", "presentations"], "soft_skills": ["oral", "work independently", "well-organized", "communication", "communication and interpersonal skills", "active", "work under pressure"], "languages_combined": [{"language": "cantonese", "language_level": ["proficiency"]}, {"language": "english", "language_level": ["excellent", "proficiency"]}, {"language": "chinese", "language_level": ["excellent"]}, {"language": "mandarin", "language_level": ["proficiency"]}]}, "experience_required": {"duration": [], "field": ["agency", "relevant working experience", "account servicing"]}}, {"job_id": "100003009054911", "location_code": "hk", "company": "Bastille Post Company Limited \u300a\u5df4\u58eb\u7684\u5831\u300b", "job_title": "Art Designer \u2013 Online Marketing", "description": "Roles and Responsibilities:\n\nDesign and produce graphics, online banners, storyboards, website layouts and animated infographics\nDevelop after effects for video production\u00a0\n\n\nJob Requirement:\n\nDegree/Diploma/ Certificate in Graphic Design or related disciplines;\nMinimum 5 years graphic design experience preferred;\nSelf motivated, responsible, mature and able to handle multiple projects independently;\nProficiency in PC, experience in using Photoshop, Illustrator, Indesign and After Effect etc.;\nGood presentation skill and strong creativity;\nAble to work under pressure, meet tight deadline and willing to work overtime if needed;\nDrawing skill is an advantage;\nKnowledge in video shooting, recording, editing & post-production for all kinds of video is an advantage;\n5.5 days\u2019 work per week\n\nInterested parties please click \u201cApply Now\" to submit your complete resume with\u00a0compensation history, expected salary and REFERENCE NUMBER or by\u00a0fax to\u00a02798 2925.\n\nWe are an equal opportunity employer and welcome applications from all qualified candidates. Information provided will be treated in strict confidence and only be used for recruitment related purpose. Applicant who is not invited for an interview within 6 weeks may consider their application not successful. All personal data of unsuccessful applicants will be destroyed within 6 months.", "employment_types": ["Full Time", "Permanent"], "selling_points": [], "locations": ["Kwun Tong"], "categories": ["Design", "Graphics", "Multi-media", "Others"], "post_time": "2022-01-18T02:04:05Z", "salary": {"currency": null, "max": null, "min": null, "period": "monthly", "term": null}, "salary_visible": false, "title_keywords": ["designer"], "responsibilities": ["graphics", "video production", "website", "design", "develop", "banners", "storyboards"], "requirements": {"degrees": ["certificate", "diploma", "degree"], "majors": ["related disciplines", "graphic design"], "languages": [], "language_level": [], "hard_skills": ["presentation skill", "indesign", "illustrator", "pc", "after effect", "photoshop"], "soft_skills": ["presentation skill", "work overtime", "independently", "responsible", "mature", "self motivated", "meet tight deadline", "work under pressure"], "languages_combined": []}, "experience_required": {"duration": ["minimum 5 years"], "field": ["graphic design"]}}, {"job_id": "100003009051577", "location_code": "hk", "company": "Tsangs Group", "job_title": "Intern - Video Editing", "description": "Responsibilities:\n\nHandle various design projects, mainly focusing on video editing and animation, visual and graphic artwork design\nEdit video, effect composition, motion graphic and animations\nGenerate ideas and creative concepts for digital campaigns and social media posts\nTo draft both English and Chinese press and publication copies;\nManaging social media platforms;\nOther ad-hoc copywriting tasks required to facilitate various marketing activities;\nManage other ad hoc projects as assigned\nRequirements:\n\n\nDegree holder in Creative Media, Marketing, translation or relevant disciplines: communications, journalism or advertising;\nExcellent knowledge of photography/videography within the digital domain;\nExcel in Adobe Premiere and Adobe Photoshop;\nExcellent command of written, spoken English, Mandarin, and Cantonese;\nFamiliar with various social media platforms;\nMust possess outstanding proofreading skills;\nProficient in Microsoft Word, Excel, PowerPoint, and Chinese Word Processing;\nSelf-motivated and proactive team player with good communication skills.", "employment_types": ["Full Time"], "selling_points": ["Familiar with various social media platforms", "5-day working", "Handle design projects, such as video editing"], "locations": ["Central"], "categories": ["Design", "Multi-media", "Media & Advertising", "Editorial / Journalism", "Photography / Video"], "post_time": "2022-01-16T11:38:35Z", "salary": {"currency": null, "max": null, "min": null, "period": "monthly", "term": null}, "salary_visible": false, "title_keywords": ["intern"], "responsibilities": ["ad-hoc", "social media", "ideas", "social media platforms", "design", "publication", "video editing", "ad hoc projects", "animations", "digital campaigns", "visual", "motion graphic", "animation"], "requirements": {"degrees": ["degree holder"], "majors": ["journalism", "creative media", "marketing", "communications"], "languages": ["cantonese", "english", "chinese", "mandarin"], "language_level": ["excellent", "proficient"], "hard_skills": ["excel", "microsoft word", "chinese word processing", "adobe photoshop", "powerpoint", "adobe premiere", "translation"], "soft_skills": ["communication skills", "self-motivated", "proactive", "team player", "creative"], "languages_combined": [{"language": "cantonese", "language_level": ["excellent"]}, {"language": "english", "language_level": ["excellent"]}, {"language": "chinese", "language_level": ["proficient"]}, {"language": "mandarin", "language_level": ["excellent"]}]}, "experience_required": {"duration": [], "field": []}}, {"job_id": "100003009054029", "location_code": "hk", "company": "Shepherd Communications Limited", "job_title": "Senior Graphic Designer", "description": "Job Responsibilities\n\n\nResponsible for graphic design from concept creative to final artwork.\nWide range of graphic design jobs including Advertising, Corporate Identity, digital games & moving images.\nDevelop 2D layouts for Animation, AR & VR Games.\nGenerate idea and create storyboard for TVC, Micro Films, Corporate Video & Animation.\nQualifications, Skills and Other Requirement\n\n\nDiploma in Graphic Design or related discipline.\n4 years solid experience;\u00a0at least 2 years in the same capacity.\nHighly Proficiency in Adobe Illustrator and vector graphics. Knowledge of Adobe Photoshop in output standard.\nExcellent in Graphic Design, perfectionist in design details.\nAccuracy in output - online and printing.\nKnowledge in 2D animation and film editing (After Effect or\u00a0Adobe Premiere).\nUnderstanding digital marketing, content marketing, SEO,\u00a0UI and UX, and mobile responsive is a bonus.\nExcellent work attitude,\u00a0highly responsible and able to\u00a0handle multiple projects.\nAble to complete project under tight deadlines.\nAttractive salary & 5-day work per week. Interested parties please email full CV with Present & Expected Salary by clicking \u201cAPPLY NOW\u201d.\n\n\nAll personal data collected will be kept confidential and used for recruitment purpose only.\n\n", "employment_types": ["Full Time", "Permanent"], "selling_points": ["Senior Graphic Designer", "Graphic design", "Motion Graphics"], "locations": ["Sai Ying Pun"], "categories": ["Media & Advertising", "Creative / Design", "Design", "Graphics", "Multi-media"], "post_time": "2022-01-17T09:16:34Z", "salary": {"currency": null, "max": null, "min": null, "period": "monthly", "term": null}, "salary_visible": false, "title_keywords": ["senior graphic designer"], "responsibilities": ["graphics", "advertising", "ar", "seo", "graphic design", "design", "develop", "digital marketing", "multiple projects", "editing", "ui", "animation"], "requirements": {"degrees": ["diploma"], "majors": ["graphic design"], "languages": [], "language_level": [], "hard_skills": ["graphics", "seo", "ar", "adobe photoshop", "adobe illustrator", "mobile", "adobe premiere", "after effect"], "soft_skills": ["creative", "responsive", "responsible"], "languages_combined": []}, "experience_required": {"duration": ["4 years"], "field": []}}, {"job_id": "100003009053141", "location_code": "hk", "company": "Harmonic Scene Limited", "job_title": "Multimedia Designer (5-Day Work)", "description": "Key Responsibilities\n\nCreate graphic and multimedia design from concept to finished artwork development in print and digital communications.\nMonitor the design and production quality of marketing materials.\nWork closely with Marketing and Creative and Game Departments.\n\nRequirements\n\nDiploma or Degree holder in Multimedia/ Creative Media/ Design or related disciplines.\nMinimum 3 years' solid experience in Multimedia Design/ Advertising/ Graphic Design and Printing Production.\nCreative, excellent drawing and concept skills.\nProficiency in Creative Cloud (Photoshop, Illustrator, InDesign, After Effect, Premiere Pro, HTML5, etc.) and Maya on Mac environment.\nStrong sense of responsibility and work independently.\nKnowledge of Web Design, Animation and Video Production is an advantage.\n\nInterested parties please submit your detailed CV (with current and expected salary) by clicking \"Apply Now\".\u00a0\u00a0\n\nData collected will be used for recruitment purpose only.", "employment_types": ["Full Time", "Permanent"], "selling_points": [], "locations": ["Kwai Hing"], "categories": ["Media & Advertising", "Creative / Design", "Design", "Graphics", "Multi-media"], "post_time": "2022-01-17T06:04:33Z", "salary": {"currency": null, "max": null, "min": null, "period": "monthly", "term": null}, "salary_visible": false, "title_keywords": ["multimedia designer"], "responsibilities": ["multimedia design", "artwork development", "quality", "monitor", "design", "marketing materials"], "requirements": {"degrees": ["diploma", "degree holder"], "majors": ["related disciplines", "creative media", "design"], "languages": [], "language_level": [], "hard_skills": ["web design", "maya", "mac environment", "indesign", "illustrator", "multimedia", "premiere pro", "after effect", "photoshop"], "soft_skills": ["work independently", "creative", "sense of responsibility"], "languages_combined": []}, "experience_required": {"duration": ["minimum 3 years"], "field": ["graphic design", "advertising", "design"]}}, {"job_id": "100003009053572", "location_code": "hk", "company": "ANKH \u6a5f\u80fd\u518d\u751f \u75db\u75c7\u5065\u5eb7\u96c6\u5718", "job_title": "Producer / Videographer", "description": "Job Description:\n\nResponsible in video production, video shooting and editing\nEnsure videos are well-edited, color / sound graded and produced according to brand guidelines\nMaterial preparation for shooting including products, scenes, lightings, props and backgrounds\nRecord, mix and post produce audio recordings\nCreate motion graphic design, including insert subtitles and aftereffects to the videos\nCollaborate with Creative and Marketing team\nPerform other ad-hoc tasks as assigned\n\nRequirements:\n\nDiploma in Film\u00a0/\u00a0Television Production / Video Production / Multimedia or related discipline\n3 years above related experiences\nProficient in video shooting and editing including software likes Premiere, Photoshop, After Effects is necessary\nStrong visual storytelling skills, and interpersonal & communication skills\nKnowledge of Graphic Design\nCreative, eager to learn, self-initiative & motivated, responsible, supportive\nAble\u00a0to work under pressure, independently, collaboratively and under tight schedule\nImmediately available is highly preferred\nCandidate without Portfolio (job reference / link) will\u00a0NOT\u00a0be\u00a0considered\n\nWe offer competitive salary package and fringe benefits to the right candidate.\u00a0\n\nInterested parties please send cover letter and full resume with current and expected salary to\u00a0Human Resources Department\u00a0by clicking 'APPLY NOW'.\u00a0\n\nFor more information, please visit our website https://www.ankh.com.hk\n\nPersonal data collected will be used for recruitment purpose only.", "employment_types": ["Full Time"], "selling_points": ["video production, video shooting and editing", "3 years related experiences", "Candidates must provide Portfolio"], "locations": ["Tsim Sha Tsui"], "categories": ["Media & Advertising", "Creative / Design", "Design", "Multi-media", "Photography / Video"], "post_time": "2022-01-17T07:10:45Z", "salary": {"currency": null, "max": null, "min": null, "period": "monthly", "term": null}, "salary_visible": false, "title_keywords": ["producer", "videographer"], "responsibilities": ["audio", "collaborate with", "video production", "ad-hoc tasks", "video shooting", "brand guidelines", "editing", "motion graphic design"], "requirements": {"degrees": ["diploma"], "majors": [], "languages": [], "language_level": [], "hard_skills": ["after effects", "multimedia", "premiere", "photoshop"], "soft_skills": ["communication skills", "supportive", "independently", "responsible", "eager to learn", "motivated", "self-initiative", "creative", "interpersonal", "work under pressure"], "languages_combined": []}, "experience_required": {"duration": ["3 years"], "field": ["related"]}}, {"job_id": "100003009054560", "location_code": "hk", "company": "SampsonStore.com Limited", "job_title": "Video Content Specialist (FMCG - sexual wellness products)", "description": "Do you have a passion in this interesting business arena and to liberate the general view on sexual wellness products? Yet to face the challenge in teasing customers on condoms, personal lubricants and even adult toys in the modern retail trade outlets? A bigger challenge yet, we will work it on a global scale, working in markets including at least Hong Kong, Taiwan, Singapore and the UK. The successful candidate will join our team to develop and enhance our market-focused in the emerging sexual wellness products.\n\nDuties\n\nMarket sexual wellness items - condoms, lubricants and adult toys.\nSpeak on camera to create compelling and engaging videos used for brand-building and social media campaigns.\nResponsible for planning the shoot, shooting, editing, and distributing video via company websites and social media platforms.\nCommunicate with internal teams to combine knowledge into video content and ensure videos meet brand standards/guidelines before being published.\nSuggest and implement YouTube/Podcast channel collaborations to build and reinforce brand image.\nTransform content outlines into intriguing stories and write concise and engaging scripts.\nWork on Hong Kong, Taiwan, Singapore and the UK markets. Regular travelling is required.\nWork with suppliers from Japan, Germany, Malaysia, US and China.\nPerform any ad-hoc duties as required.\n\nRequirements\n\nMust be a Hong Kong resident.\nGood command of English and Putonghua.\nAbility to be comfortable and confident in front of cameras.\nAdvanced knowledge of Adobe Premiere Pro.\nGood working knowledge of After Effects, color grading, and Audition.\nExcellent verbal Cantonese storytelling and communication skills. Fluent in Mandarin or English is a plus.\nExperience in executing multi-camera shoots.\nGood organizational and detail-oriented skills to ensure the quality of deliverables and timely completion.\nExperience with SEO\u00a0is an advantage.\nCreative and thinking out-of-the-box, yet with strong execution ability.\n\nOur working environment\n\nSmall team, close relationship.\nFlexible working hours.\nWork only with the best talent in town. Only sharp applicants with a passion in mind will be invited for an interview.\nWork only for the result, non-commission based, We share success with a year-end performance bonus.\n\nPlease send your CV, expected annual package, your portfolio,\u00a0and the answer of \"What month of the year has 28 days?\"\u00a0for application.", "employment_types": ["Full Time"], "selling_points": ["Sexual wellness products: Sagami, Tenga, Sampson", "Video production from A to Z", "Responsible for HK, TW, SG and UK markets"], "locations": ["Lai Chi Kok"], "categories": ["Design", "Multi-media", "Media & Advertising", "Photography / Video", "Marketing / Public Relations", "Digital Marketing"], "post_time": "2022-01-17T09:59:19Z", "salary": {"currency": null, "max": null, "min": null, "period": "monthly", "term": null}, "salary_visible": false, "title_keywords": ["specialist"], "responsibilities": ["company websites", "communicate with", "social media campaigns", "guidelines", "social media platforms", "teams", "ad-hoc duties", "editing", "planning"], "requirements": {"degrees": [], "majors": [], "languages": ["cantonese", "putonghua", "english", "mandarin"], "language_level": ["excellent", "good command", "fluent"], "hard_skills": ["small", "plus", "seo", "adobe premiere pro", "after effects"], "soft_skills": ["confident", "communication skills", "flexible", "advanced", "passion in", "organizational", "timely", "detail-oriented", "creative"], "languages_combined": [{"language": "cantonese", "language_level": ["excellent"]}, {"language": "putonghua", "language_level": ["good command"]}, {"language": "english", "language_level": ["good command", "fluent"]}, {"language": "mandarin", "language_level": ["fluent"]}]}, "experience_required": {"duration": [], "field": []}}, {"job_id": "100003009054877", "location_code": "hk", "company": "Dragon Creative Media Limited", "job_title": "Multimedia Graphic Designer / Graphic Designer", "description": "Job Description\n\n- Certificate / Diploma in Multimedia Design with 1-2 year multimedia experience\n\n- Proficiency in Photoshop, Illustrator, After Effects, MAYA, 3DMax & AutoCAD\n\n- To handle multimedia projects [text, sound, images, 3D-modelling, animation & rendering]\n\n- Creative, strong sense in multimedia design, self-motivated and self-disciplined", "employment_types": ["Full Time"], "selling_points": ["5 days work", "At least 1 year multimedia experience", "Strong creative sense"], "locations": ["Southern Area"], "categories": ["Design", "Graphics", "Multi-media", "Web Designer"], "post_time": "2022-01-17T12:18:24Z", "salary": {"currency": null, "max": null, "min": null, "period": "monthly", "term": null}, "salary_visible": false, "title_keywords": ["graphic designer"], "responsibilities": ["multimedia design", "animation"], "requirements": {"degrees": ["certificate", "diploma"], "majors": ["multimedia design"], "languages": [], "language_level": [], "hard_skills": ["maya", "illustrator", "after effects", "autocad", "3dmax", "multimedia", "photoshop"], "soft_skills": ["self-motivated", "creative"], "languages_combined": []}, "experience_required": {"duration": ["1-2 year"], "field": ["design"]}}, {"job_id": "100003009052667", "location_code": "hk", "company": "Love Design Production Limited", "job_title": "Graphic Designer (16K-18K depends on experience)", "description": "Job Description\n\nResponsible for the creation, design, development of graphic design\nResponsible for design tasks including but not limited to leaflet, poster, banner, etc.\nPerform any other tasks assigned by supervisor\n\nRequirement:\n\nDiploma holder or above in web, graphic design, or related field\nKnowledge in Adobe Software, website design, video shooting & editing\nExperience in Solidworks, 3Dmax, Keyshot, Autocad would be an advantage\nExperience in IT support and help desk on PC and Mac\nStrong sense of responsibility, a good team player while being able to work independently to meet project deadlines\nGood communication skills\nGood command of written and spoken Chinese\nPortfolio attachment is a MUST\nImmediate availability is highly preferred\nFresh graduates would also be considered\n\nBenefit:\n\nDiscretionary bonus\nAttractive performance bonus\nFriendly and collaborative work environment\n\nWe offer competitive remuneration package and good prospects to the right candidates. Interested parties please send your full resume with expected salary by clicking \u201cApply now\u201d\n\n*Data collected will be kept confidential and used for recruitment purposes only. All the applications will be destroyed after 6-month.", "employment_types": ["Full Time"], "selling_points": [], "locations": ["Shatin Area"], "categories": ["Design", "Graphics", "Multi-media", "Web Designer"], "post_time": "2022-01-17T03:40:45Z", "salary": {"currency": null, "max": null, "min": null, "period": "monthly", "term": null}, "salary_visible": false, "title_keywords": ["graphic designer"], "responsibilities": ["graphic design", "other tasks", "leaflet", "design"], "requirements": {"degrees": ["diploma holder"], "majors": ["graphic design"], "languages": ["chinese"], "language_level": ["good command"], "hard_skills": ["web", "3dmax", "adobe software", "pc", "solidworks", "autocad"], "soft_skills": ["communication skills", "good team player", "work independently", "sense of responsibility"], "languages_combined": [{"language": "chinese", "language_level": ["good command"]}]}, "experience_required": {"duration": [], "field": ["it support"]}}, {"job_id": "100003009052723", "location_code": "hk", "company": "Imagine Lab Limited", "job_title": "Designer", "description": "Responsibilities:\n\n\nDeveloping creative concepts, visual and artwork for event, coordination of production, social media, campaign, leaflet, poster, packaging, website, etc.\nHandling 2D and 3D design work\nAbility to demonstrate excellence in creativity across multiple media\nImplementation of marketing plans & promotion and supporting Event & Marketing team on product launching\nWorking closely with the project team to ensure smooth daily operations\n\nRequirements:\n\n\nDegree/higher diploma holder in a relevant design discipline\n1-2 years or above working experience in graphic design for print ads, booklets, event backdrops, exhibition, mall decoration, etc.\nHands-on experience in using Adobe CS, particularly in Photoshop and Illustrator\nGood hand drawing skill is preferable\nWith knowledge in multi-media & web design\nGood layout and presentation skill\nProficient in 3D Max/C4D/3D software\nSelf-motivated, creative, independent, be able to work under pressure and meet deadlines\nHaving positive and passionate approach with a can-do attitude\nWilling to work overtime and outside normal office hours\nImmediately is preferable\n\nOffice location: Yau Tong\n\nInterested parties please send your detailed resume, portfolio and expected salary to\u00a0us.\u00a0(All personal data collected will be used for recruitment purpose only)\u00a0", "employment_types": ["Full Time", "Permanent"], "selling_points": [], "locations": ["Others"], "categories": ["Media & Advertising", "Others", "Design", "Graphics", "Multi-media"], "post_time": "2022-01-17T03:48:35Z", "salary": {"currency": null, "max": null, "min": null, "period": "monthly", "term": null}, "salary_visible": false, "title_keywords": ["designer"], "responsibilities": ["design work", "social media", "marketing plans", "leaflet", "developing", "website", "implementation", "daily operations", "coordination", "visual"], "requirements": {"degrees": ["degree", "higher diploma holder"], "majors": ["design"], "languages": [], "language_level": [], "hard_skills": ["presentation skill", "web design", "c4d", "3d software", "illustrator", "adobe cs", "max", "photoshop"], "soft_skills": ["presentation skill", "passionate", "self-motivated", "work overtime", "independent", "can-do attitude", "hands-on", "meet deadlines", "creative", "positive", "work under pressure"], "languages_combined": []}, "experience_required": {"duration": ["1-2 years"], "field": ["graphic design", "print", "cs"]}}, {"job_id": "100003008964815", "location_code": "hk", "company": "eMotionLab Limited", "job_title": "Creative Copywriter/ Strategist", "description": "If you are a\u00a0Copywriter who aspire to to give life and new meanings to what matters now with words for brands, corporates and even government agencies & public organizations...\u00a0\nWe should meet!\n\nWe are looking for high caliber talents to join our growing team\n... in our new spacious office\n\u2026 and to chill out with us in our amazing balcony!\n\nThe Ideal candidate shall have the following qualities:\n\ngood language and written skills\npresentable and good interpersonal skills\nhave an eye for detail and interest in new advertising trends and techniques\nPassionate, Motivated and Proactive Working Attitude\nBe able to meet tight schedule\nwork well in a team\n\n*\u00a0Fresh graduates are welcomed to apply\n\nInterested candidates please include your current and expected salary, website/ samples of your work in your application.\n\nPlease include [Creative Copywriter/ Strategist] in the subject line.\n\nPersonal data collected will be handled strict confidence for recruitment related purpose only.", "employment_types": ["Full Time"], "selling_points": ["Creative Copywriter/ Strategist", "Aspire to innovate", "5 days work and dynamic working environment"], "locations": ["Wong Tai Sin Area"], "categories": ["Media & Advertising", "Creative / Design", "Production", "Design", "Multi-media"], "post_time": "2022-01-17T02:04:37Z", "salary": {"currency": null, "max": null, "min": null, "period": "monthly", "term": null}, "salary_visible": false, "title_keywords": ["creative copywriter"], "responsibilities": ["advertising", "schedule"], "requirements": {"degrees": [], "majors": [], "languages": [], "language_level": [], "hard_skills": ["chill", "words"], "soft_skills": ["passionate", "presentable", "motivated", "interpersonal skills", "eye for detail", "proactive", "ideal"], "languages_combined": []}, "experience_required": {"duration": [], "field": []}}, {"job_id": "100003009052111", "location_code": "hk", "company": "Joyway Management Limited", "job_title": "Assistant Multimedia Designer", "description": "Job Duties:\n\n\nTo contribute creative ideas and innovative multimedia solutions, develop and produce e-learning packages, animated, audio and visual videos, interactive video games and animated PowerPoint presentation, etc.;\nTo write scripts, design and produce the department\u2019s training and presentation materials in diversified visual content including photo and video shooting, editing and retouching with a view to achieving better audio and visual appeal to audiences;\nTo handle graphic design and artwork output for departmental publications and e-cards, etc.\nEmployment Terms\n\n\nWork Hours: 8.8 hours a day between 0900 and 1800, Monday to Friday, off on Sat, Sun and Public Holidays\n\nSalary: HK$20,000 per month\nWork Location: Shamshuipo\n\nCandidates Requirement:\n\nHave bachelor degree/higher diploma in Creative Writing for Film, TV and New Media, or Creative/Digital Media, or Multimedia Technologies and Innovation or similar subjects from a local university/institute, or equivalent;\n\nLevel 3 or above in Chinese Language and English Language in HKDSE or HKCEE, or equivalent;\nProficient in scriptwriting, operating AV equipment and various computer software related to digital and image-sound media, photo and video editing and production including Windows 10, Microsoft Office 2016, Adobe Premier, Adobe Audition, Adobe After Effects, Adobe Illustrator, Adobe InDesign, Adobe Animate CC, Adobe Captivate 2019, Flash, Digital Animation and PhotoShop; and\nPossess some working experiences in scriptwriting and producing interactive video games and PowerPoint with audio and visual effects;\nHave at least one dose of Covid-19 vaccine.\nHow to Apply:\n\nInterested candidates please send in your CV (including all grades attained in public exam) stating clearly your academic qualifications with working experience, and earliest date available.\n\nPlease state ref no: JB-RVD-0117 as header in your application\n\nAll personal information collected will be solely for use in recruitment and will be kept in strict confidentiality\n\nWe apologize that only shortlisted candidates will be contacted for interviews", "employment_types": ["Full Time", "Temporary", "Contract"], "selling_points": [], "locations": ["Sham Shui Po"], "categories": ["Media & Advertising", "Creative / Design", "Design", "Graphics", "Multi-media"], "post_time": "2022-01-17T02:07:16Z", "salary": {"currency": "HKD", "max": 24999, "min": 20000, "period": "monthly", "term": null}, "salary_visible": true, "title_keywords": ["multimedia designer", "assistant"], "responsibilities": ["sat", "retouching", "creative ideas", "editing", "graphic design", "design", "develop", "video shooting", "visual", "audio", "artwork output"], "requirements": {"degrees": [], "majors": [], "languages": [], "language_level": [], "hard_skills": [], "soft_skills": [], "languages_combined": []}, "experience_required": {"duration": [], "field": []}}, {"job_id": "100003009052672", "location_code": "hk", "company": "Refuel Digital Marketing Limited", "job_title": "Web & Graphic Designer [Salary range: 20K -25K (depends on exp.) ]", "description": "Job Description\nResponsible for the creation, design, development, and maintenance of the corporate websites of individual businesses.\nCreate graphic and animated design for our website, social media, and branding assets for marketing campaigns\nApply best practices to increase page speed & ratings, and SEO ranking\nRequirement\n\nDiploma holder or above in web, graphic design, or related field\nAt least 2 years of relevant working experience\nKnowledge in\u00a0SEO, CSS, HTML5, Java\u00a0and WordPress\nKnowledge in Adobe Photoshop, Fireworks, Illustrator, Flash, Dreamweaver\nExperience in video shooting and production is an advantage\nStrong sense of responsibility, a good team player while being able to work independently to meet project deadlines\nGood communication skills\nGood command of written and spoken Chinese, Mandarin & English\nPortfolio attachment is a MUST\nImmediate availability is highly preferred\nCandidate with more experiences would also be considered as Senior Web & Graphic Designer\n\nBenefit\n\nMedical insurance\nDental\u00a0insurance\nDiscretionary bonus\nAttractive performance bonus\nFriendly and collaborative work environment\n\nWe offer competitive remuneration package and good prospects to the right candidates.\n\n*For more details, please visit our official website:\u00a0https://refueldigital.com.hk/\n\n*Interested parties please send your full resume with expected salary by clicking \u201cApply now\u201d\n\n*The information provided by applicants will be kept confidential and will be\u00a0used solely for recruitment purpose only.\u00a0All the applications will be destroyed after 6-month.", "employment_types": ["Full Time"], "selling_points": [], "locations": ["Shatin Area"], "categories": ["Design", "Graphics", "Multi-media", "Web Designer"], "post_time": "2022-01-17T03:41:00Z", "salary": {"currency": null, "max": null, "min": null, "period": "monthly", "term": null}, "salary_visible": false, "title_keywords": ["graphic designer"], "responsibilities": ["social media", "seo", "maintenance", "website", "design", "marketing campaigns"], "requirements": {"degrees": ["diploma holder"], "majors": ["graphic design"], "languages": ["english", "chinese", "mandarin"], "language_level": ["good command"], "hard_skills": ["java", "seo", "web", "adobe photoshop", "illustrator", "wordpress", "flash", "dreamweaver", "css"], "soft_skills": ["communication skills", "good team player", "work independently", "sense of responsibility"], "languages_combined": [{"language": "english", "language_level": ["good command"]}, {"language": "chinese", "language_level": ["good command"]}, {"language": "mandarin", "language_level": ["good command"]}]}, "experience_required": {"duration": ["at least 2 years"], "field": ["graphic", "video shooting", "designer", "relevant working experience"]}}, {"job_id": "100003009053010", "location_code": "hk", "company": "Challenger Auto Services Limited", "job_title": "Graphic Designer / Senior Graphic Designer", "description": "Job Responsibilities:\n\nHandle day to day graphics design for advertising, marketing, social media content;\nDesign and production for event decoration and promotional items;\nCreate concept and artwork as company branding;\nany ad-hoc projects that maybe assigned by manager;\n\nJob Requirement:\n\nAt least 3 years working experience in media, advertising agency preferred;\nDiploma or above in in Art, Graphic Design, Multimedia or related\u00a0disciplines in Graphic Design;\u00a0 \u00a0\u00a0\nAble to handle multiple tasks with tight schedule and work under pressure;\nDetail-oriented, responsible, independent and can work in a team;\nRelevant experience/ enthusiast in the automobile or eSport project\u00a0is\u00a0preferred; \u00a0 \u00a0 \u00a0 \u00a0 \u00a0 \u00a0 \u00a0\u00a0\nProficient in Photoshop, Adobe Illustrator of Mac environment is a MUST;\nGood command of written and spoken Cantonese and English;\nImmediate availability is highly preferred\n\nInterested candidates, please send your full resume stating with contact details, current & expected salary email to HR Department.\u00a0\n\nAll applications will be treated in strict confidence and be used solely for recruitment purpose.", "employment_types": ["Full Time"], "selling_points": [], "locations": ["Tsuen Wan Area"], "categories": ["Design", "Graphics", "Multi-media"], "post_time": "2022-01-17T05:03:16Z", "salary": {"currency": null, "max": null, "min": null, "period": "monthly", "term": null}, "salary_visible": false, "title_keywords": ["senior graphic designer", "graphic designer"], "responsibilities": ["graphics", "advertising", "event decoration", "design", "social media content", "ad-hoc projects"], "requirements": {"degrees": ["diploma or above"], "majors": ["related disciplines", "graphic design", "art"], "languages": ["cantonese", "english"], "language_level": ["good command"], "hard_skills": ["adobe illustrator", "mac environment", "multimedia", "photoshop"], "soft_skills": ["independent", "responsible", "detail-oriented", "handle multiple tasks", "work under pressure"], "languages_combined": [{"language": "cantonese", "language_level": ["good command"]}, {"language": "english", "language_level": ["good command"]}]}, "experience_required": {"duration": ["at least 3 years"], "field": ["relevant experience", "media", "advertising agency"]}}, {"job_id": "100003009054404", "location_code": "hk", "company": "KREW LIMITED", "job_title": "Associate Creative Director (Art-Based) / Assistant Digital Creative Director", "description": "Company Background\n\nKREW Digital\u00a0is the\u00a0No.1\u00a0Social Media Agency and Content Marketing Agency recognized by Marketing Magazine*. We won the\u00a0Agency of the Year 2021 (6 Gold, 6 Local Hero, 3 Bronze).\u00a0KREW is a fast-growing digital agency, mainly focusing on social media, digital campaigns and content marketing. Our team is formed by veterans of first-tier digital agencies, consultancies and the mass media. Our client list includes some of the most respected and admired names in Hong Kong and worldwide, including leading property developer, hospitality group, luxury retailer and world-class travelware brand.\n\nWith self-developed tool \"KREWatch\", its analytic approach help craft persona insight for our creative ideas, it's the core reason for us to win Marketing Excellence Awards in Categories of Retail Marketing and Loyalty Marketing.\u00a0\n\nTo cope with our expansion, we would like to invite high-calibre talents to join our energetic team for an exciting career in digital marketing.\n\nThe ideal candidate will formulate online / digital / social media / content marketing strategies for our clients by planning and executing digital marketing campaigns. Candidate will also plan and launch digital advertisements and create content. He / she will also be able to monitor clients\u2019 social media presences.\n\n*KREW is the Gold Winner of Social Media Agency of the Year 2021 and Content Marketing Agency of the Year 2021 organized by Marketing Magazine.\u00a0\n\nFollow Us\u00a0\n\n\u25baW:\u00a0https://www.krewdigital.com/\u00a0\n\u25baF:\u00a0https://www.facebook.com/krewdigital/\n\u25baL:\u00a0https://www.linkedin.com/company/krewdigital/\n\n\nRequirements\n\nDirectly report to Directors to lead creative team for digital and social media strategy.\nIn charge of overseeing digital creative direction and quality control of all projects.\u00a0\nWork closely with account servicing and creative to in charge of proposals and ad hoc projects.\nVeteran in digital and social media advertising and creative industry.\u00a0\nCraft ideas with award-winning approach.\u00a0\n\nQualifications\n\nDiploma holder or above in Graphic / Multimedia Design\n3 to 5 year Digital Agency background in well-known 4As/web/multi-media/interactive fields is a plus\nPresentable and good command of Cantonese and English\nProficiency in HTML, AI, AE, PS, PR\nExperience on handling Finance, Banking, Insurance, Shopping Malls is a plus\nCreative, Can-Do attitude, Proactive, independent and a good team leader and player\nCapable in manage multiple projects to meet tight deadlines\nStrong Sense of belongings to the projects of client and team\n\nInterested parties please send CV to us!", "employment_types": ["Full Time"], "selling_points": ["3 - 5 year ex. 4As agency background is a plus", "Creative. Digital marketing & social media veteran", "Stunning agency office environment"], "locations": ["Tsuen Wan Area"], "categories": ["Media & Advertising", "Creative / Design", "Design", "Graphics", "Multi-media"], "post_time": "2022-01-17T09:23:31Z", "salary": {"currency": null, "max": null, "min": null, "period": "monthly", "term": null}, "salary_visible": false, "title_keywords": ["creative director", "associate", "assistant"], "responsibilities": ["multimedia design", "ideas", "plan", "facebook", "advertising", "digital marketing campaigns", "monitor", "manage multiple projects", "digital campaigns", "banking", "report", "social media", "marketing strategies", "digital marketing", "executing", "creative ideas", "advertisements", "ad hoc projects", "quality control", "insurance", "planning"], "requirements": {"degrees": ["diploma holder"], "majors": ["multimedia design"], "languages": ["cantonese", "english"], "language_level": ["good command"], "hard_skills": ["no", "plus", "web", "ai", "html", "reason", "multimedia", "facebook"], "soft_skills": ["organized", "meet tight deadlines", "proactive", "independent", "creative", "capable", "can-do attitude", "world-class", "presentable", "good team leader", "energetic", "ideal"], "languages_combined": [{"language": "cantonese", "language_level": ["good command"]}, {"language": "english", "language_level": ["good command"]}]}, "experience_required": {"duration": [], "field": ["finance", "insurance", "banking"]}}, {"job_id": "100003009054425", "location_code": "hk", "company": "Celestial Asia Securities Holdings Ltd", "job_title": "Senior Graphic Designer", "description": "Reporting to the General Manager of Group Public Affairs, you will be responsible for developing all corporate visual and creative ideas and concepts, from layout development through to the production of final products and activities, such as print, web, videos, brand building, photography and exhibition. In addition to routine brand maintenance works, ad hoc projects will be required for various of our business groups as and when required.\u00a0\n\n\nRequirements\n\nHigher Diploma or above in Graphic Design, Commercial Arts or other related disciplines\nAt least 5 years relevant experience in design field\nProficiency in using design softwares such as Adobe Photoshop, Illustrator, InDesign and Dreamweaver, familiar with PC Microsoft Office i.e. Powerpoint & Word\nStrong knowledge in logo and branding, web, multi-media design, photography, printing and production\nBe highly creative and sensitive to designs and trends\nBe passionate and take initiatives and ownership of the visual elements of creative work\nHave excellent interpersonal and communication skills and be able to work well as part of a team, with a range of people, well organized, mature and self-motivated\nImmediate availability preferred\nPlease apply in confidence with full resume, current and expected salary, quoting reference by clicking \u201cAPPLY NOW\".\n\nThe information provided will be used for selection purpose only. All information of unsuccessful applicants will be destroyed within six months.", "employment_types": ["Full Time"], "selling_points": ["Higher Diploma in Graphic Design/Commercial Arts", "At least 5 years relevant experience", "Immediate availability preferred"], "locations": ["Kowloon Bay"], "categories": ["Design", "Graphics", "Industrial / Product", "Multi-media"], "post_time": "2022-01-17T09:29:54Z", "salary": {"currency": null, "max": null, "min": null, "period": "monthly", "term": null}, "salary_visible": false, "title_keywords": ["senior graphic designer"], "responsibilities": ["reporting", "creative ideas", "maintenance", "graphic design", "developing", "design", "communication", "ad hoc projects", "visual"], "requirements": {"degrees": ["higher diploma or above"], "majors": ["related disciplines", "graphic design"], "languages": [], "language_level": [], "hard_skills": ["maintenance", "web", "design softwares", "microsoft office", "adobe photoshop", "indesign", "illustrator", "powerpoint", "word", "dreamweaver", "pc", "logo"], "soft_skills": ["passionate", "communication skills", "self-motivated", "confidence", "responsible", "well organized", "mature", "sensitive to", "creative", "interpersonal"], "languages_combined": []}, "experience_required": {"duration": ["at least 5 years"], "field": ["relevant experience", "design"]}}, {"job_id": "100003009053931", "location_code": "hk", "company": "Nissin Foods (HK) Management Co Ltd", "job_title": "Graphic Designer", "description": "Job Description\n\n\nWork closely with Marketing and R&D teams to create and modify designs of brands and product packages\nDevelop marketing collaterals from conceptualization to completion of graphic designs, including key visuals, in-store POP, advertisements, online promotion materials and social media content etc.\nSupport in printing of product package and marketing collaterals\nExecute food shot and product photo shooting and retouching\nDevelop graphic / multimedia design and support in photography for corporate and brands\u2019 promotional events and activities\nInitiate creative ideas to promote brands and products\nPerform other ad-hoc projects and tasks as required\n\nJob Specification\n\nTertiary educated or above in Graphic Design, Multimedia or related discipline\n3-4 years relevant experience in Graphic Design. Experience in FMCG package design or food industry is an advantage\nProficiency in Mac OS and Adobe Creative Suite\nGood at drawing or illustration is an advantage\nGood command in both written and spoken English and Chinese, Mandarin is preferred\nOccasional business trip is required when necessary\nImmediate available is preferred\n\n\u00a0Applicant please email\u00a0DETAILED RESUME\u00a0with\u00a0present and expected salary\u00a0to Human Resources Dept.\n\n(All personal data collected will be used for recruitment purpose only)", "employment_types": ["Full Time", "Permanent"], "selling_points": [], "locations": ["Tai Po Area"], "categories": ["Design", "Graphics", "Industrial / Product", "Multi-media"], "post_time": "2022-01-17T07:47:45Z", "salary": {"currency": null, "max": null, "min": null, "period": "monthly", "term": null}, "salary_visible": false, "title_keywords": ["graphic designer"], "responsibilities": ["multimedia design", "marketing collaterals", "graphic designs", "design", "promote brands and products", "social media content", "ad-hoc projects", "personal data", "key visuals", "online promotion materials", "teams", "develop", "occasional business trip", "designs of brands", "food shot", "initiate creative ideas", "printing of product package", "retouching", "advertisements", "graphic design", "in-store pop", "product photo shooting", "support in photography", "recruitment"], "requirements": {"degrees": [], "majors": [], "languages": ["english", "chinese", "mandarin"], "language_level": ["good command"], "hard_skills": ["r&d", "mac os", "multimedia", "illustration", "adobe creative suite"], "soft_skills": ["creative", "detailed"], "languages_combined": [{"language": "english", "language_level": ["good command"]}, {"language": "chinese", "language_level": ["good command"]}, {"language": "mandarin", "language_level": ["good command"]}]}, "experience_required": {"duration": ["3-4 years"], "field": ["fmcg", "graphic design", "food industry", "design", "relevant experience"]}}, {"job_id": "100003009053408", "location_code": "hk", "company": "The Hebe Haven Yacht Club Ltd", "job_title": "Graphic Designer", "description": "Job Description\n\nReports to the PR & Communications Manager, the incumbent is responsible for a variety of duties involving: designing newsletters, articles, posters, brochures, video filming and editing, online marketing materials development and other support services.\n\nResponsibilities\n\nResponsible for photos touch-ups, poster editing and offline/online marketing materials development (menus, posters, banners, eDM ads, etc)\u00a0\u00a0\u00a0\u00a0\u00a0\u00a0\u00a0\u00a0\u00a0\nProvide creative insights to scale up the club's image and maintain brand standards\nSupport in-house photo-shoots and event management when required\nStay current in design trends and styles in various media, including digital and social channels\nUse a variety of tools, applications and computer software to generate new images\nCreate print-ready files to send to printer\nSupport video production and editing when required\nOvertime or non-office hours work might be required according to business needs (esp. during events)\n\nRequirements\n\nGraduate from design school with creative media related background\nWith 2-3 years related working experience (preferably 5 years or above)\nExcellent interpersonal skills\nProficiency in Mac software, AI, Photoshop, InDesign, ideally Premiere Pro\nKnowledge of aesthetic sense of art and detail-minded, willing to accommodate ad-hoc requests from different stakeholders\nAble to effectively communicate in English & Chinese, in both written and spoken forms\nExcellent organisational skills to function effectively under tight time constraints to meet \u00a0established deadlines, with particular attention to detail\nGood computer knowledge (Word, Excel, PowerPoint and Chinese Word Processing)\n\nWe offer a competitive employment package to the right candidate, including free staff meals, additional MPF contributions, 13-month salary and medical benefits.\n\nRemuneration shall be commensurate with the candidate\u2019s qualifications and experience. To apply for the above jobs, please send your resume and a one-page sample and your design to our Human Resources Manager by clicking \"Apply Now\"\n\nAll information received will be used for recruitment purpose only.", "employment_types": ["Full Time"], "selling_points": ["5 days work per week", "Free staff meals, additional MPF contribution", "2-3 years related working experience"], "locations": ["Sai Kung Area"], "categories": ["Design", "Graphics", "Multi-media"], "post_time": "2022-01-17T07:01:38Z", "salary": {"currency": null, "max": null, "min": null, "period": "monthly", "term": null}, "salary_visible": false, "title_keywords": ["graphic designer"], "responsibilities": ["management", "software", "edm", "video production", "support services", "design trends", "banners", "maintain", "reports", "designing", "marketing materials", "editing"], "requirements": {"degrees": [], "majors": [], "languages": ["english", "chinese"], "language_level": ["good"], "hard_skills": ["excel", "chinese word processing", "ai", "indesign", "word", "powerpoint", "premiere pro", "photoshop"], "soft_skills": ["detail-minded", "organisational skills", "interpersonal skills", "attention to detail", "creative"], "languages_combined": [{"language": "english", "language_level": []}, {"language": "chinese", "language_level": ["good"]}]}, "experience_required": {"duration": ["5 years", "2-3 years"], "field": ["related"]}}, {"job_id": "100003009051665", "location_code": "hk", "company": "Nu Life International (Asia) Limited", "job_title": "Multi Media Graphic Designer", "description": "We are an international corporation in health food industry for over 30 years located in Tsim Sha Tsui and are seeking creative and high caliber candidates to fill the following positions:\n\nResponsibilities\n\n-\u00a0\u00a0\u00a0\u00a0\u00a0\u00a0\u00a0\u00a0\u00a0 Support Business Development team in developing concept design of marketing materials\n\n-\u00a0\u00a0\u00a0\u00a0\u00a0\u00a0\u00a0\u00a0\u00a0 Handle photo shooting and retouching for product shot, launch campaign and events\n\n-\u00a0\u00a0\u00a0\u00a0\u00a0\u00a0\u00a0\u00a0\u00a0 Assist in designing print advertisement, packaging, catalog, banner, leaflet and retail outlet decoration\u2026 etc\n\nRequirements:\n\n-\u00a0\u00a0\u00a0\u00a0\u00a0\u00a0\u00a0\u00a0\u00a0 Diploma or High Certificate in Graphic Design or related disciplines\n\n-\u00a0\u00a0\u00a0\u00a0\u00a0\u00a0\u00a0\u00a0\u00a0 1-2 years experience in graphic design\n\n-\u00a0\u00a0\u00a0\u00a0\u00a0\u00a0\u00a0\u00a0\u00a0 Proficiency in Adobe Photoshop, Illustrator, Flash, InDesign on Mac and PC\n\n-\u00a0\u00a0\u00a0\u00a0\u00a0\u00a0\u00a0\u00a0\u00a0 Video Editing Knowledge is a MUST\n\n-\u00a0\u00a0\u00a0\u00a0\u00a0\u00a0\u00a0\u00a0\u00a0 Knowledge in\u00a0photo taking and artwork output\u00a0is an advantage\n\n-\u00a0\u00a0\u00a0\u00a0\u00a0\u00a0\u00a0\u00a0\u00a0 Experience and knowledge in maintaining company website and social media is a plus\n\n-\u00a0\u00a0\u00a0\u00a0\u00a0\u00a0\u00a0\u00a0\u00a0 Work closely with Marketing & Design\n\n-\u00a0\u00a0\u00a0\u00a0\u00a0\u00a0\u00a0\u00a0\u00a0 Self-motivated, able to work independently and under pressure\n\n-\u00a0\u00a0\u00a0\u00a0\u00a0\u00a0\u00a0\u00a0\u00a0 Willing to work overtime and meet tight deadlines\n\n-\u00a0\u00a0\u00a0\u00a0\u00a0\u00a0\u00a0\u00a0\u00a0 Immediate availability is preferable\n\n-\u00a0\u00a0\u00a0\u00a0\u00a0\u00a0\u00a0\u00a0\u00a0 Applicants must enclose proven portfolio\n\nWe offer 5 days work, medical insurance and attractive remuneration packages. Interested parties please apply with full resume indicating expected salary and availability.\n\nApproved by:\n\nEffective date: 2 Jul 2021", "employment_types": ["Full Time"], "selling_points": [], "locations": ["Tsim Sha Tsui"], "categories": ["Design", "Multi-media"], "post_time": "2022-01-16T21:50:36Z", "salary": {"currency": null, "max": null, "min": null, "period": "monthly", "term": null}, "salary_visible": false, "title_keywords": ["graphic designer"], "responsibilities": ["retouching", "leaflet", "developing", "design", "designing", "marketing materials"], "requirements": {"degrees": ["certificate", "diploma"], "majors": ["related disciplines", "graphic design"], "languages": [], "language_level": [], "hard_skills": ["plus", "indesign", "adobe photoshop", "illustrator", "video editing", "flash", "pc"], "soft_skills": ["self-motivated", "work overtime", "under pressure", "work independently", "meet tight deadlines"], "languages_combined": []}, "experience_required": {"duration": ["1-2 years"], "field": ["graphic design", "social media"]}}, {"job_id": "100003009052142", "location_code": "hk", "company": "eMotionLab Limited", "job_title": "Producer / Creative Assistant / Production Assistant", "description": "If you are a\u00a0Producer who aspire to plan, oversee and lead meaningful storytelling video projects from ideation to completion,\n\nWe should meet!\n\nWe are looking for high caliber talents to join our\u00a0growing team\u00a0\n... in our\u00a0new spacious office\n\u2026 and to chill out with us in our\u00a0amazing balcony!\n\nResponsibilities:\n\nTo manage and utilize resources effectively and keep track of multiple works and project status to ensure timely delivery\nTo carry out all duties in planning, coordination, organization and implementation of productions and projects\nTo develop excellent communication with all parties involved (the creative, production team & the client)\nTo coordinate on logistical arrangement for productions\n\nJob Requirements:\n\nSolid experience in video with vfx production\nUnderstanding of design, production, motion graphic and animation fundamentals\nWith active network in CG animation, motion graphic & multimedia production industry is an advantage, but not essential\nGood communication and interpersonal skills\nWell-organized, detail minded and able to work independently\nProficiency in English, Mandarin and Cantonese\nAble to work under pressure\nFresh graduates / candidate with less experience can be considered as creative assistant / production assistant\n\nInterested candidates please include your current and expected salary, website/ samples of your work in your application.\n\nPlease include\u00a0[Producer / Creative Assistant / Production Assistant]\u00a0in the subject line.\n\nPersonal data collected will be handled strict confidence for recruitment related purpose only.\n", "employment_types": ["Full Time"], "selling_points": ["Producer / Creative Assistant", "Aspire to innovate", "5 days work and dynamic working environment"], "locations": ["Wong Tai Sin Area"], "categories": ["Media & Advertising", "Creative / Design", "Design", "Multi-media"], "post_time": "2022-01-17T02:15:55Z", "salary": {"currency": null, "max": null, "min": null, "period": "monthly", "term": null}, "salary_visible": false, "title_keywords": ["producer", "production assistant", "creative", "assistant"], "responsibilities": ["implementation", "develop", "communication", "coordinate", "coordination", "planning"], "requirements": {"degrees": [], "majors": [], "languages": ["cantonese", "english", "mandarin"], "language_level": ["proficiency"], "hard_skills": ["cg", "multimedia"], "soft_skills": ["work independently", "creative", "well-organized", "communication and interpersonal skills", "active", "work under pressure"], "languages_combined": [{"language": "cantonese", "language_level": ["proficiency"]}, {"language": "english", "language_level": ["proficiency"]}, {"language": "mandarin", "language_level": ["proficiency"]}]}, "experience_required": {"duration": [], "field": ["video"]}}, {"job_id": "100003009052627", "location_code": "hk", "company": "Telford International Co Ltd", "job_title": "Graphic Designer", "description": "\nWe are looking for a talented graphic to create engaging and on-brand graphics for a variety of media. The Graphic Designer job description includes the entire process of defining requirements, visualizing and creating graphics including illustrations, logos, layouts and photos. You\u2019ll be the one to shape the visual aspects of web banners, leaflets, Posters, product packaging and more.\n\nResponsibilities\n\n\nStudy design briefs and determine requirements\nConceptualize visuals based on requirements\nPrepare rough drafts and present ideas\nDevelop illustrations, logos and other designs using software or by hand\nUse the appropriate colors and layouts for each graphic\nWork with marketing\u00a0 to produce suitable design\nAmend designs after feedback\nEnsure final graphics and layouts are visually appealing and on-brand\n\nRequirements\n\n\n3 years or above related working experience\nA strong portfolio of illustrations or other graphics\nFamiliar with design software and technologies (Such as Photoshop, Illustrator, Premiere, After Effect)\nA keen eye for aesthetics and details\nExcellent communication skills\nAbility to work methodically and meet deadlines\nGood team player, multi-tasking, willing to learn, open-minded, independent and responsible\nWilling to work overtime\nWe offer attractive remuneration package and career prospects plus 5-day week and medical insurance. Interested parties please send your full resume with expected salary & Portfolio to us.\u00a0\nAll data collected shall be solely for recruitment purpose.\nWebsite: www.telford.com.hk", "employment_types": ["Full Time", "Permanent"], "selling_points": ["3 years or above relevant experience", "Strong portfolio of illustrations or other graphic", "Familiar with design software and technologies"], "locations": ["Kwai Hing"], "categories": ["Design", "Graphics", "Industrial / Product", "Multi-media"], "post_time": "2022-01-17T03:35:59Z", "salary": {"currency": null, "max": null, "min": null, "period": "monthly", "term": null}, "salary_visible": false, "title_keywords": ["graphic designer"], "responsibilities": [], "requirements": {"degrees": [], "majors": [], "languages": [], "language_level": [], "hard_skills": ["graphics", "illustrator", "premiere", "after effect", "photoshop"], "soft_skills": ["communication skills", "good team player", "work overtime", "independent", "responsible", "keen", "open-minded", "willing to learn", "multi-tasking", "meet deadlines"], "languages_combined": []}, "experience_required": {"duration": ["3 years"], "field": ["related"]}}, {"job_id": "100003009054870", "location_code": "hk", "company": "Nu Skin Enterprises Hong Kong, LLC", "job_title": "Designer (Web and Graphic Design)", "description": "Responsibility:\n\nEffectively help on the design tasks and projects to meet deadlines\nMaintain and update web content by using Adobe Experience Manager\nProducing rich and creative media online campaigns include eDM, web banners, etc.\n\nRequirement:\n\n2-year experience in graphic design, with passion in graphic design and creating user-friendly web interfaces\nKnowledge in Adobe Creative Suite. E.g. Adobe Creative Suite, e.g. Photoshop, illustrator, Dreamweaver, etc\nKnowledge in HTML and CSS is a must.\nExcellent communication skills and attention to detail\n\n\nWe offer 5 days work, excellent career development with on/off-the-job trainings, competitive compensation including incentive bonus & annual performance bonus, medical benefits, life & accidental insurance, annual leave & product benefits.\n\nIf you are ready for a new challenge in your career, please send your detailed resume with\u00a0Current and Expected Salary and Your Availability\u00a0by clicking Apply Now.\n\n\n\nALL PERSONAL INFORMATION WE COLLECTED IS FOR THE PURPOSE OF RECRUITMENT ONLY\n\n\n\nPlease visit\u00a0www.nuskin.com\u00a0to find out more about us!", "employment_types": ["Full Time", "Permanent"], "selling_points": ["Support design tasks and projects", "Produce creative media online campaigns", "Knowledge in Adobe Creative Suite"], "locations": ["Causeway Bay"], "categories": ["Design", "Graphics", "Multi-media", "Web Designer"], "post_time": "2022-01-17T12:14:08Z", "salary": {"currency": null, "max": null, "min": null, "period": "monthly", "term": null}, "salary_visible": false, "title_keywords": ["designer"], "responsibilities": ["banners", "maintain", "design", "edm"], "requirements": {"degrees": [], "majors": [], "languages": [], "language_level": [], "hard_skills": ["web", "illustrator", "html", "dreamweaver", "css", "adobe creative suite", "photoshop"], "soft_skills": ["communication skills", "passion in", "friendly", "attention to detail", "creative", "detailed"], "languages_combined": []}, "experience_required": {"duration": ["2-year"], "field": ["graphic design"]}}, {"job_id": "100003009052772", "location_code": "hk", "company": "Imagine Lab Limited", "job_title": "Senior 3D Designer", "description": "Responsibilities:\n\nGenerate design concept, structural design, environment design & space planning for events & exhibitions\nHandle 3D rendering projects, technical drawing and floor plan for production\nComplete 3D design drawing in full set for events and exhibitions, photo retouch technique is required.\nRequirements:\n\nDegree / Diploma or above in related courses (space design/ exhibition design/ multimedia design. etc)\nGood at handling 2D and 3D software (e.g. 3Ds Max, Cine 4D, Illustrator, Photoshop)\nHands-on experience in working on 3D, graphic, artwork, and output production independently is essential\n2 years\u2019 experience or above in exhibition/event design/production house/interior decoration will be an advantage\nImmediately is preferable\n\n\u00a0Office location: Yau Tong\n\nInterested parties please send your detailed resume and expected salary to\u00a0us.\n(All personal data collected will be used for recruitment purpose only)\u00a0", "employment_types": ["Full Time", "Permanent"], "selling_points": [], "locations": ["Others"], "categories": ["Media & Advertising", "Others", "Design", "Graphics", "Multi-media"], "post_time": "2022-01-17T06:45:53Z", "salary": {"currency": null, "max": null, "min": null, "period": "monthly", "term": null}, "salary_visible": false, "title_keywords": ["senior 3d designer"], "responsibilities": ["3d rendering", "design concept", "design", "photo retouch", "planning", "plan", "technical drawing"], "requirements": {"degrees": ["degree", "diploma or above"], "majors": ["multimedia design", "design"], "languages": [], "language_level": [], "hard_skills": ["3d software", "3ds max", "illustrator", "multimedia", "photoshop"], "soft_skills": ["hands-on", "independently"], "languages_combined": []}, "experience_required": {"duration": ["2 years"], "field": ["graphic", "design"]}}, {"job_id": "100003009051779", "location_code": "hk", "company": "The Great Eagle Group of Companies", "job_title": "Multi-media Designer", "description": "Responsibilities:\n\nPlan and execute design but not limited to photo retouch, design layout and other marketing materials\nDevelop creative idea and concepts to various platform including digital positing with social media\nWork closely with internal and external stakeholders for the executive of projects\nCoordinate and manage progress tracking, resources and budget management\nHandle other ad hoc projects assigned\n\nRequirements:\n\nDegree holder in Multimedia Design, Arts, Visual Arts or any related disciplines\nMinimum 3 years\u2019 relevant working experience, preferably gained in advertising or branding agency with digital focus experience\nPositive, true team player, open-minded and a strong sense of responsibility are essential.\nProficient in Adobe Creative Suite, Photoshop, Illustrator and InDesign\nHands-on experience in UX design software such as Adobe XD, InVision and UXPin\nGood presentation, interpersonal and communication skills\nGood team player and self-motivated\nGood command of both written and spoken English and Chinese\n\nSalary and benefits will be commensurate with qualifications and experience.\u00a0 Interested parties, please send a full resume with present and expected salary, and date available to The Human Resources Department, 32/F., Great Eagle Centre, 23 Harbour Road, Wan chai, Hong Kong or e-mail to US.\u00a0(Please quote the reference no. on the envelope and the covering letter.)\n\nTo know more about us, please visit our website at http://www.greateagle.com.hk.\n\nWe are an equal opportunity employer and welcome applications from all qualified candidates.\n\nPersonal data collected will be treated in strict confidence and used only for recruitment-related purpose. Applicants who have not heard from us within four weeks may consider their applications unsuccessful. All personal data will be destroyed after 12 months.", "employment_types": ["Full Time", "Permanent"], "selling_points": ["Plan and execute design for marketing materials", "Digital positing", "Proficient in Adobe Creative Suite, Photoshop etc."], "locations": ["Wan Chai"], "categories": ["Design", "Multi-media", "Marketing / Public Relations", "Marketing - Marketing Communication", "Digital Marketing"], "post_time": "2022-01-17T01:04:00Z", "salary": {"currency": null, "max": null, "min": null, "period": "monthly", "term": null}, "salary_visible": false, "title_keywords": ["designer"], "responsibilities": ["social media", "management", "budget", "design", "develop", "coordinate", "photo retouch", "ad hoc projects", "plan", "marketing materials", "tracking"], "requirements": {"degrees": ["degree holder"], "majors": ["multimedia design", "related disciplines"], "languages": ["english", "chinese"], "language_level": ["good command"], "hard_skills": ["adobe xd", "indesign", "illustrator", "multimedia", "focus", "adobe creative suite", "photoshop"], "soft_skills": ["communication skills", "good team player", "self-motivated", "sense of responsibility", "interpersonal", "open-minded", "hands-on", "team player", "focus", "creative", "presentation", "positive"], "languages_combined": [{"language": "english", "language_level": ["good command"]}, {"language": "chinese", "language_level": ["good command"]}]}, "experience_required": {"duration": ["minimum 3 years"], "field": ["advertising", "agency", "relevant working experience", "design", "digital"]}}, {"job_id": "100003009053039", "location_code": "hk", "company": "Tech Nine Limited", "job_title": "Graphic Designer (Mobile App/Web) (5 days work)", "description": "You should keep watching...\n\nIf you are interested in the website and mobile app graphic design, enjoying a flexible culture and would like to join an energetic team, which is led and supervised by IT experts and to work with Millennial professionals, this is exactly what you are looking for!\nYou'll responsible for...\n\nHandle design project, including mobile and web application graphics, icons and\u00a0 UI elements\nWork independently to develop and produce artwork for mobile application, desktop application & website\nBrainstorm innovative ideas and prepare proposal/presentation materials\nWork with design managers to ensure timely completion and quality of design elements\nClosely communicate with the project team and product team to ensure final graphics and layouts aligns with project requirements\nSupport projects' task assigned by Manager & Director\nRight fit if you are...\n\nDiploma or above in Graphic Design or related disciplines\n3 year or above working experience in Graphic Design\nProficiency in using Photoshop & Illustrator, Figma and Sketch\nExperience in Website/ Mobile App graphic design is a plus\nWith strong creative and design sense\nAble to work independently, willing to meet new challenges under a tight schedule\nImmediately available is highly preferred\nWe offer...\n\nProject Bonus\n5-days Work + Bank Holiday\nEducation Allowance, Medical Allowance\nSnacks and drinks\nLess than 5 mins walk from Lai Chi Kok MTR Station\nGood Career Prospect in the growing IT Industry\n\nApply now! Do not miss this opportunity to join us!\n\nInterested parties, please apply with full resume, portfolio that will demonstrate our required fields as mentioned above, current and expected salary.\n\nRemarks: Data collected would be used for recruitment purposes only. Applicants who do not hear from us within 8 weeks may consider their application unsuccessful and their data will be destroyed within 24 months of receipt.", "employment_types": ["Full Time", "Permanent"], "selling_points": ["Looking for passionate and talented designer", "Website, Mobile Application, Marketing Collateral", "Friendly and energetic working environment"], "locations": ["Lai Chi Kok"], "categories": ["Design", "Graphics", "Multi-media", "Information Technology (IT)", "UI/UX Designer"], "post_time": "2022-01-17T16:20:58Z", "salary": {"currency": null, "max": null, "min": null, "period": "monthly", "term": null}, "salary_visible": false, "title_keywords": ["graphic designer"], "responsibilities": ["graphics", "communicate with", "project requirements", "support projects", "mobile app", "ideas", "graphic design", "quality", "website", "design", "develop", "schedule", "ui"], "requirements": {"degrees": ["diploma or above"], "majors": ["related disciplines", "graphic design"], "languages": [], "language_level": [], "hard_skills": ["graphics", "plus", "web", "illustrator", "mobile", "photoshop"], "soft_skills": ["flexible", "work independently", "creative", "responsible", "timely", "interested in", "innovative", "energetic", "presentation"], "languages_combined": []}, "experience_required": {"duration": ["3 year"], "field": ["graphic design"]}}, {"job_id": "100003009052106", "location_code": "hk", "company": "eMotionLab Limited", "job_title": "Senior/Junior Motion Designer/ Animator", "description": "If you are a\u00a0Motion Designer who aspire to give new meanings to what matters now with your visual stories,\nWe should meet!\n\nWe are looking for high caliber talents to join our growing team\u00a0\n... in our new spacious office\n\u2026 and to chill out with us in our amazing balcony!\n\nJob Responsibilities:\n\nMotion design and/or 2D&3D animation design developments and production\nParticipate in projects from conceptualisation to the finished products\n\nRequirements:\n\n2 - 5 years working experience in the industry\nFresh graduates and potential candidates will fewer experience will be considered as junior motion designer/animator\nExcellent sense in motion and strong animation skills\nProficient in Adobe AfterEffect, Photoshop, Illustrator & Editing Skills\nKnowledge in 2D and/or 3D animation, having both is an advantage.\nPassionate, Motivated and Proactive Working Attitude\nBe able to meet tight schedule\nPleasant and presentable, and enjoy working in a cozy and friendly environment\nInterested candidates please include your current and expected salary, website/ samples of your work in your application.\n\nPlease include [Senior/ Junior Motion Designer/ Animator] in the subject line.\n\nPersonal data collected will be handled strict confidence for recruitment related purpose only.", "employment_types": ["Full Time"], "selling_points": ["Senior/ Junior Motion Designer/ Animator", "Aspire to innovate", "5 days work and dynamic working environment"], "locations": ["Wong Tai Sin Area"], "categories": ["Media & Advertising", "Creative / Design", "Production", "Design", "Multi-media"], "post_time": "2022-01-17T02:06:05Z", "salary": {"currency": null, "max": null, "min": null, "period": "monthly", "term": null}, "salary_visible": false, "title_keywords": ["animator", "designer", "junior"], "responsibilities": ["animation", "design"], "requirements": {"degrees": [], "majors": [], "languages": [], "language_level": [], "hard_skills": ["adobe", "illustrator", "photoshop"], "soft_skills": ["passionate", "enjoy working", "presentable", "pleasant", "motivated", "friendly", "proactive"], "languages_combined": []}, "experience_required": {"duration": ["2 - 5 years"], "field": ["designer"]}}, {"job_id": "100003009055560", "location_code": "hk", "company": "\u82b1\u4e4b\u6ef4\u6709\u9650\u516c\u53f8", "job_title": "\u5e73\u9762\u8a2d\u8a08\u5e2b Graphic Designer", "description": "JOB DESCRIPTION\n\nResponsible for product creative design from concept to final artwork\nPrepare engaging content such as graphics, photos, imagery and video to drive traffic conversion and brand awareness\nPerform daily management of social media accounts and media planning.\nTo perform other duties assigned by management\n\nQUALIFICATIONS\n\nDegree holder of Graphic Design, Visual Communication, Marketing, Communications, e-Commerce etc.\nSolid knowledge with one (or more) of these creative and digital tools is a MUST: Photoshop / Illustrator / InDesign /Final Cut Pro/ video editing skills\nGood writing skill in editorial & marketing materials with media angle\nGood sense of social media platforms and passionate to initiate digital creative ideas\nProactive and energetic team player with self-motivation, creativity and positive working attitude\nAbility to achieve results and willing to contribute beyond basic responsibilities\nExcellent communications in English and Chinese\n\nWHY YOU SHOULD JOIN US\n\nWe provide constant guidance, training and mentorship to polish your business mindset. We care about your personal and professional growth\nFlat operating structure, you will be able to work independently, make your own judgement and make a direct impact to the company\nWe work in an open, collaborative, and respectful culture where we empower every single person to grow and play to their strengths\nFlexible work hours. Our priority is on getting the job done\nYou\u2019ll be working in a fast-paced environment\n\nPlease send your CV together with the expected salary to us.\nShortlisted candidates will be invited to a first round interview and notified by email or phone.", "employment_types": ["Full Time", "Permanent"], "selling_points": [], "locations": ["Chai Wan"], "categories": ["Design", "Graphics", "Industrial / Product", "Multi-media"], "post_time": "2022-01-18T02:43:23Z", "salary": {"currency": "HKD", "max": 19999, "min": 14000, "period": "monthly", "term": null}, "salary_visible": true, "title_keywords": ["graphic designer"], "responsibilities": ["graphics", "social media", "management", "perform other duties", "creative ideas", "graphic design", "social media platforms", "design", "communication", "video editing", "visual", "marketing materials", "planning"], "requirements": {"degrees": ["degree holder"], "majors": ["graphic design", "marketing", "communications", "e-commerce"], "languages": ["english", "chinese"], "language_level": ["excellent"], "hard_skills": ["creative design", "graphics", "final cut pro", "basic", "e-commerce", "indesign", "illustrator", "writing skill", "video editing", "visual communication", "photoshop"], "soft_skills": ["passionate", "proactive", "responsible", "writing skill", "communication", "positive working attitude", "energetic", "self-motivation", "team player", "creative"], "languages_combined": [{"language": "english", "language_level": ["excellent"]}, {"language": "chinese", "language_level": ["excellent"]}]}, "experience_required": {"duration": [], "field": []}}, {"job_id": "100003008966987", "location_code": "hk", "company": "Hong Kong QingHe Management Service Limited", "job_title": "Assistant Marketing Manager (Event & eCommerce)", "description": "Responsibilities:\u00a0\u00a0\u00a0\u00a0\u00a0\u00a0\u00a0\u00a0\u00a0\u00a0\u00a0\u00a0\u00a0\u00a0\u00a0\n\nManage daily E-shop and online platform order arrangement.\nOur E-shop: www.Kormawo.com\nTo assist to formulate and execute e-commerce strategies, including digital marketing, advertising activities and promotion campaigns to drive the sales and revenue.\nExecute all social and online advertising campaigns and updates, including create appealing and well-structured digital content and feeds\nAssist in overseeing assigned event and communicate with internal departments and external parties for the operation execution\nSupport event planning and ensure successful delivery of all venue services on time with quality and customer satisfaction\nAssist in managing budget planning and monitor event timeline\nProvide support on event planning provisions and general administration support\nCoordinate with sourcing and other internal teams regarding product availability, pricing, and stock levels\nPrepare regular analysis & reports for management review\n\nRequirements:\u00a0\n\nDSE or above with diploma in Business, E-Commerce, Marketing, IT or related discipline\nMinimum 5 years of solid experience with proven record in e-Commerce and/or digital marketing\n\u00a0Experience in membership recruitment and event management an advantage\n\u00a0Experience in HKTV, Carosell, Google Analytics, Google Adv, SEO/ SEM, FB/ IG ad placement\n\u00a0Experience in skincare/beauty product is an advantage\n\u00a0Proficient with graphic design tools, Adobe Illustrator and Photoshop & all MS Office Usage (esp. excel, word and powerpoint)\n\nBenefits:\n\n\n5 days work week\nbanking holidays\n12 days annual leave\nmonthly commission\nmedical insurance\nstaff purchase discount\nbirthday gift\u00a0\nfridge benefits\u00a0\nInterested parties please send your full resume and expected salary to our mailbox by clicking \"Apply Now\" below", "employment_types": ["Full Time", "Permanent"], "selling_points": ["Manage social media platform-Kormawo.com", "Experience in handle exhibition, events", "5 days work and monthly commission"], "locations": ["Tsuen Wan Area"], "categories": ["Design", "Multi-media", "E-commerce", "Business Development", "Marketing - Brand / Product Management"], "post_time": "2022-01-17T06:52:05Z", "salary": {"currency": null, "max": null, "min": null, "period": "monthly", "term": null}, "salary_visible": false, "title_keywords": ["assistant marketing manager"], "responsibilities": ["e-shop", "external parties", "quality", "promotion campaigns", "online advertising", "management review", "administration", "budget planning", "advertising", "monitor", "e-commerce strategies", "teams", "reports", "provide support", "coordinate with", "digital marketing", "communicate with", "analysis", "planning"], "requirements": {"degrees": ["diploma", "dse"], "majors": ["business", "marketing", "it", "e-commerce"], "languages": [], "language_level": [], "hard_skills": ["google analytics", "excel", "seo", "e-commerce", "word", "powerpoint", "adobe illustrator", "sem", "ms office", "photoshop"], "soft_skills": [], "languages_combined": []}, "experience_required": {"duration": ["minimum 5 years"], "field": ["management", "e-commerce", "recruitment", "digital marketing", "beauty"]}}, {"job_id": "100003009051305", "location_code": "hk", "company": "Miramar Hotel and Investment Company, Limited", "job_title": "Senior Multimedia Designer / Multimedia Designer (social media focus)", "description": "\n\nDevelop creative video content for social media campaigns and digital projects\nDirecting the whole shooting & video production\nResponsible for photo shooting & editing\nPromotional video / motion graphic video production including storyboard creation, pre-production, shooting, editing, subtitling and post-production\nCreate visual, video, animation and other graphic design contents which are consistent with brand\u00a0images, campaigns and corporate messages of our clients\nWork closely with the marketing team to develop creative design concept ideas\nRemarks : on-the-job training and mentorship shall be available for junior staff\n\nRequirements:\n\nDiploma or above in Multimedia/graphic design or equivalent\nSolid experience in Final Cut Pro, Premiere, After Effects, Photoshop, Illustrator,\nKnowledge in HTML and CSS an advantage\nCreative and design with marketing sense\nLove team work while manage well independent work tasks\n\n\nAre you interested?\n\nAttractive remuneration package will be offered to the right person. Please send full resume (with portfolio, availability, employment history, current/last & expected salaries) to us. Your personal information collected will be used for recruitment purposes only.", "employment_types": ["Full Time", "Permanent"], "selling_points": [], "locations": ["Tsim Sha Tsui"], "categories": ["Media & Advertising", "Creative / Design", "Design", "Multi-media", "Photography / Video"], "post_time": "2022-01-15T07:54:02Z", "salary": {"currency": null, "max": null, "min": null, "period": "monthly", "term": null}, "salary_visible": false, "title_keywords": ["multimedia designer"], "responsibilities": ["ideas", "social media campaigns", "video production", "promotional video", "graphic design", "design concept", "design", "develop", "contents", "recruitment", "visual", "pre-production", "editing", "motion graphic", "animation"], "requirements": {"degrees": ["diploma or above"], "majors": ["graphic design"], "languages": [], "language_level": [], "hard_skills": ["creative design", "final cut pro", "premiere", "illustrator", "html", "after effects", "multimedia", "css", "photoshop"], "soft_skills": ["independent", "creative", "marketing sense", "responsible"], "languages_combined": []}, "experience_required": {"duration": [], "field": []}}, {"job_id": "100003009051527", "location_code": "hk", "company": "Ma Belle Jewellery Co Ltd", "job_title": "Designer/ Web Designer/ Digital Designer", "description": "Responsibilities:\n\nAssist the development of annual report and other corporate communication publication material from copy writing, layout development, proof reading to printing output\nAssist the development of various marketing collateral, including project leaflet, factsheet, promotion poster, banner, event signage etc\nWeb site regular update and assist the development of mini page\nWork with supplier, including designer, print agency etc\nOther duties as assigned\n\nRequirements:\n\nDegree holder in Journalism, Translation, Public Relations or related disciplines\nAt least 1 year relevant working experience in corporate communication or journalism\nWell organized, responsible, attentive to details and able to work independently\nA self-motivated team player with good interpersonal, communications and presentation skills\nProficiency in MS word, Excel and PowerPoint (Chinese inputting is required)\nExcellent command of English and Chinese\nCandidates with\u00a0less experience will be considered as Corporate Communications Assistant\n\nInterested candidates please send the cover letter together with full resume indicating the expected salary by clicking \"Apply Now\"\n\n\nAll applications will be treated in strictest confidence.\u00a0 Personal data collected will be used for recruitment purposes only and unsuccessful applications will be destroyed upon completion of the recruitment exercise.\u00a0", "employment_types": ["Full Time", "Permanent"], "selling_points": ["multimedia/online advertising/video editing", "Adobe Photoshop ,Illustrator, After Effects", "Knowledge in HTML, CSS, UI/UX design"], "locations": ["Tin Hau"], "categories": ["Design", "Graphics", "Multi-media", "Web Designer"], "post_time": "2022-01-16T08:05:51Z", "salary": {"currency": null, "max": null, "min": null, "period": null, "term": null}, "salary_visible": false, "title_keywords": ["digital designer", "designer"], "responsibilities": ["other duties", "leaflet", "communication", "publication", "report"], "requirements": {"degrees": ["degree holder"], "majors": ["journalism", "related disciplines"], "languages": ["english", "chinese"], "language_level": ["proficiency", "excellent"], "hard_skills": ["powerpoint", "translation", "excel", "ms word"], "soft_skills": ["work independently", "self-motivated", "attentive to details", "responsible", "well organized", "communication", "presentation skills", "team player", "interpersonal"], "languages_combined": [{"language": "english", "language_level": ["excellent"]}, {"language": "chinese", "language_level": ["proficiency", "excellent"]}]}, "experience_required": {"duration": ["at least 1 year"], "field": ["corporate communication", "relevant working experience"]}}, {"job_id": "100003009054948", "location_code": "hk", "company": "Pearl Lam Galleries Limited", "job_title": "PR & Communications Executive / Manager", "description": "The Job\n\nProvide\u00a0creative solutions and mockups that meet the brand standards by translating concepts into digital and/ or print formats\nCreate\u00a0graphics, animations, and special effects, as well as edit\u00a0graphic design, photos retouching, audio, and video using Adobe Creative Suite\nDraw\u00a0storyboards for advertisements, video games, FB, IG and website etc.\nDesign\u00a0and execute\u00a0all the assigned design tasks from research, concept generation, layout design and final artwork production in a wide range of media platforms\nWork\u00a0closely with the photographers and designers to brainstorm creative concepts. Liaise and follow up with marketing team to ensure the timely delivery\nThe Requirement\n\nHigher diploma or above in Graphic/Multimedia Design or related disciplines\n5 years or above experience in design/advertising agency and/or digital campaign\nExperience in\u00a0graphic, multimedia design, layout, typography, photo/video shooting and editing\nStrong understanding of latest design trends and digital optimization technology\nKnowledge on Adobe Creative Suite \u2013 includes Photoshop, Illustrator, Indesign, Flash, Dreamweaver and several other programs\u00a0\nGood team player, multi-tasking, willing to learn, open-minded, independent and responsible\nCandidate with less experience will be considered as Multimedia Designer\n\nAttractive remuneration would be offered to the right candidates.\nPlease send your application with portfolio and expected salary to\u00a0Human Resources Manager:\n\nBy WhatsApp: 6388-3034 or\nBy Fax: 2722-5555\n\nPersonal data collected will be used for recruitment purpose only.\u00a0 We are an equal opportunity employer.", "employment_types": ["Full Time"], "selling_points": ["Young and good knowledge in social media platforms", "Excellent written English & Chinese", "Proficiency in Mac OS, MS Office, Adobe Pr/Ai/Ps"], "locations": ["Central & Western Area"], "categories": ["Media & Advertising", "Creative / Design", "Design", "Multi-media", "Marketing / Public Relations", "Marketing - General / Support"], "post_time": "2022-01-17T14:54:35Z", "salary": {"currency": null, "max": null, "min": null, "period": "monthly", "term": null}, "salary_visible": false, "title_keywords": ["executive", "manager"], "responsibilities": ["graphics", "retouching", "liaise", "advertisements", "graphic design", "artwork production", "layout design", "website", "design", "animations", "audio", "storyboards"], "requirements": {"degrees": ["higher diploma or above"], "majors": ["multimedia design", "related disciplines"], "languages": [], "language_level": [], "hard_skills": ["indesign", "illustrator", "whatsapp", "multimedia", "flash", "dreamweaver", "adobe creative suite", "photoshop"], "soft_skills": ["good team player", "independent", "responsible", "open-minded", "willing to learn", "multi-tasking", "creative"], "languages_combined": []}, "experience_required": {"duration": ["5 years"], "field": ["photo", "designer", "design", "graphic", "video shooting", "advertising agency", "digital", "editing"]}}, {"job_id": "100003009047548", "location_code": "hk", "company": "Online Marketing Genius Company Limited", "job_title": "Graphic Designer / Multimedia Designer", "description": "Designer/ Web Designer/ Digital Designer\n\nThe Job\n\nprepare various online and offline marketing materials including but not limited to graphic/ video promotion materials, social media post, web design, photo retouching etc.\nwork closely with different teams and external parties to develop and execute cross-platform marketing\u00a0 campaign visuals and concepts\n\n\u00a0The Person\n\nDiploma or above in in Graphic/ Multimedia/ Animation/ Web Design or related discipline\nAt least 3 years of experience in e-Commerce, Graphic, Multimedia and Web Design\nexperienced in graphic/ multimedia/ online advertising/ web design/ video editing/ production skills is preferred\nproficient in Adobe Photoshop, Illustrator, After Effects and Premiere, Dreamweaver, XD and related software.\nhighly technical skills in motion graphic design and animation\nstrong sense on graphic, layout. colouring and usability on graphics\nknowledge in HTML, CSS, UI/UX design\nexperience in jQuery, Javascript and 3D rendering will be a plus\ncreative, detail-minded and well-organized working behavior\nwork independently and under pressure with tight schedule\ngood player with excellent communications skills\nWe offer 5-day week, attractive remuneration, career advancement opportunity, medical benefit, discretionary bonus, staff purchase privileges to the right candidate. Interested parties, please\u00a0send us your full resume with current and expected salary.\n\n\nPersonal data collected will be used for recruitment purposes only and will be treated in strict confidence.\u00a0 Applicants not invited for interview within\u00a04 months\u00a0may consider their applications unsuccessful.", "employment_types": ["Full Time", "Permanent"], "selling_points": ["Highly creative, able to manage different styles", "5-day work, flexible working hour", "Medical benefit and year-end bonus"], "locations": ["Kwai Hing"], "categories": ["Media & Advertising", "Creative / Design", "Design", "Graphics", "Multi-media"], "post_time": "2022-01-14T03:26:25Z", "salary": {"currency": null, "max": null, "min": null, "period": "monthly", "term": null}, "salary_visible": false, "title_keywords": ["multimedia designer", "graphic designer"], "responsibilities": ["social media", "photo retouching", "external parties", "teams", "design", "develop", "marketing materials"], "requirements": {"degrees": ["diploma or above"], "majors": ["web design", "animation"], "languages": [], "language_level": [], "hard_skills": ["graphics", "web design", "plus", "e-commerce", "jquery", "adobe photoshop", "illustrator", "premiere", "html", "video editing", "after effects", "javascript", "multimedia", "dreamweaver", "css"], "soft_skills": ["detail-minded", "work independently", "under pressure", "well-organized", "technical skills", "creative"], "languages_combined": []}, "experience_required": {"duration": ["at least 3 years"], "field": ["graphic", "design", "e-commerce"]}}, {"job_id": "100003009043471", "location_code": "hk", "company": "New Page Communications Ltd", "job_title": "Junior Video Editor", "description": "Position overview:\n\nThe role of Communications\u00a0Executive / Manager\u00a0will be responsible for\u00a0managing and updating all our social media channels, PR and providing assist to Website. \u00a0As an independent and pro-active problem solver, this person will help to build the company\u2019s brand image and awareness as well as to expand client base and sales.\n\nYou will also be involving in design / graphics of evite, e-catalogue, video and photo shooting of events and art fairs / exhibition co-ordination works.\n\nAs one of the world's leading\u00a0contemporary\u00a0art galleries located in Hong Kong's Central district, we look for a candidate with a pleasant demeanor, and is able to multi-task under pressure. \u00a0Passion and/or experience in art scene would be highly advantageous. \u00a0A detail-oriented, fast-paced individual would surely thrive in this cultural environment.\n\nOur gallery in Shanghai is looking for the same position also.\n\nWorking Days: Mon-Sat\n\nWorking Hours: 10:00-19:00 (with one hour lunch time)\n\nResponsibilities include:\n\nPlan and set up company pages within various internal and external social media channels to increase visibility of the company\u2019s social content, build brand awareness and customer loyalty.\nCreate original, creative and engaging content for all social media channels.\nPlan and arrange social media contents following gallery\u2019s exhibition schedule.\nPlan and organize social media marketing campaigns, online advertising and events for customer engagement, customer service initiatives and drive new customers.\nWork with external parties for joint different exhibition news and announcements, content distribution, influencer marketing, etc\u2026\nEdit videos and images for social media updates\n\nRequirement skills/attributes include:\n\n1\u00a0years\u2019 experience in-house and hands on social media planning, development and operation for worldwide markets, NO FRESH GRAD\nKnowledge of website update, social media platforms including Facebook, Twitter, Google+, Pinterest, Instagram, Youtube, LinkedIn, Weibo, Wechat & Renren\u2026 etc.\nCopywriting or editorial experience in online media, PR, social media is strongly preferred;\nExcellent in written English & Chinese (Traditional & Simplified Chinese)\nProficiency in Apple Mac, Word, Adobe Photoshop, Illustrator, Premier\nGood typing skills in English and Chinese - accuracy and presentation is required\nExcellent writing and communication skills\nHighly organized & efficient with an ability to work across an organization\nDress Code - BLACK\n\nPlease send your CV under\u00a0subject \u201cApplication to the post of Communications\u00a0Executive / Manager\u201d for interview arrangement.", "employment_types": ["Full Time", "Permanent"], "selling_points": [], "locations": ["Kwun Tong Area"], "categories": ["Media & Advertising", "Creative / Design", "Production", "Design", "Multi-media"], "post_time": "2022-01-12T13:07:45Z", "salary": {"currency": null, "max": null, "min": null, "period": "monthly", "term": null}, "salary_visible": false, "title_keywords": ["video editor", "junior"], "responsibilities": ["social media", "external parties", "edit videos", "contents", "customer service", "schedule", "marketing campaigns", "plan", "online advertising"], "requirements": {"degrees": [], "majors": [], "languages": ["english", "chinese"], "language_level": ["excellent", "good"], "hard_skills": ["no", "adobe photoshop", "word", "illustrator", "wechat", "typing", "code", "facebook"], "soft_skills": ["efficient", "organized", "communication skills", "hands on", "presentation"], "languages_combined": [{"language": "english", "language_level": ["excellent", "good"]}, {"language": "chinese", "language_level": ["excellent", "good"]}]}, "experience_required": {"duration": ["1 years"], "field": ["social media", "pr", "development", "editorial", "operation", "copywriting", "media", "planning"]}}, {"job_id": "100003009051313", "location_code": "hk", "company": "Miramar Hotel and Investment Company, Limited", "job_title": "Designer", "description": "As our User Researcher of our Design Hub team in Hong Kong, your primary mission will be to understand the needs and product requirements and transform that understanding into user-focused and intuitive products and services.\n\nYou will:\n\nmanage and run all forms of requirement gathering, user research, UX workshop, customer interview, usability testing, focus group etc.\nfacilitate the product vision by researching, sketching, prototyping and user-testing experiences for digital products\ndesign experiences through human-centred-design\nensure that research findings and insights are translated into actionable product goals and direction and sharing insights with stakeholders\ncreate wireframes (from sketches to high-fidelity ones)\ntranslate concepts into user flows & wireframes\ncreate rapid prototypes to validate design concepts with stakeholders and customers\nrun workshops and other group activities\nContributing to on-going enhancement of customer experience and user experience methodologies\nstay abreast of UX and technology trends and look for inspiration\n\nRequirements:\n\nMinimum of 5 years relevant experience as a User Researcher, interaction designer or similar roles\nnative Cantonese speaker with strong local cultural understanding. Fluent and comfortable in English\nexperienced in user research, prototyping and user testing methodologies\nunderstand Agile / iterative project management methodologies\nable to handle a Mac and the usual tools (Adobe, Sketch)\nbe a self-motivated and resilient team player driving collaboration\nwith strong sense of personal accountability", "employment_types": ["Full Time", "Permanent"], "selling_points": [], "locations": ["Tsim Sha Tsui"], "categories": ["Media & Advertising", "Creative / Design", "Design", "Graphics", "Multi-media"], "post_time": "2022-01-15T08:04:11Z", "salary": {"currency": null, "max": null, "min": null, "period": "monthly", "term": null}, "salary_visible": false, "title_keywords": ["designer"], "responsibilities": ["design concepts", "workshop", "user experience", "sketches", "design", "testing", "project management"], "requirements": {"degrees": [], "majors": [], "languages": ["cantonese", "english"], "language_level": ["native", "fluent"], "hard_skills": ["agile", "project management", "adobe", "rapid", "workshops", "focus"], "soft_skills": ["self-motivated", "agile", "focused", "accountability", "project management", "team player", "focus"], "languages_combined": [{"language": "cantonese", "language_level": ["native"]}, {"language": "english", "language_level": ["fluent"]}]}, "experience_required": {"duration": ["minimum of 5 years"], "field": ["designer", "design", "testing", "relevant experience", "digital"]}}, {"job_id": "100003009054212", "location_code": "hk", "company": "Sedgwick Richardson (Hong Kong) Ltd", "job_title": "Designer (Publishing)", "description": "Responsibilities and Prerequisites\n\nWe are looking for a talented and enthusiastic\u00a0Junior Video Editor to work with our\u00a0post-production team in primarily video editing, composition, and studio recording.\n\nThe ideal candidate needs to have a creative flair, up-to-date knowledge of software used in the industry, and effective management of time, deadlines, and costs.\u00a0\n\nThe ability to manage multiple projects simultaneously, and work well under pressure is a pre-requisite.\n\nRequirements:\n\nUniversity or College graduate, major in multi-media design or equivalent\n1-2 years of above related working experience\nProficiency in multi-media applications including AVID, After-effect & Photoshop\nStrong communication and interpersonal skills, MUST be a team player\nShift duty is required\nImmediate availability is preferred\n\nSalary:\n\nNegotiable and commensurate with experience.\u00a0\n\nInterested parties please send full resume with present and expected salary and work samples (video link is preferable) by clicking \u201cApply Now\u201d.\n\nAll personal data collected will be used for recruitment purpose only.", "employment_types": ["Full Time"], "selling_points": [], "locations": ["Central"], "categories": ["Design", "Graphics", "Multi-media", "Web Designer"], "post_time": "2022-01-17T08:49:51Z", "salary": {"currency": null, "max": null, "min": null, "period": "monthly", "term": null}, "salary_visible": false, "title_keywords": ["designer"], "responsibilities": ["management", "software", "manage multiple projects", "video editing", "costs"], "requirements": {"degrees": [], "majors": [], "languages": [], "language_level": [], "hard_skills": ["photoshop"], "soft_skills": ["team player", "communication and interpersonal skills"], "languages_combined": []}, "experience_required": {"duration": ["1-2 years"], "field": ["related"]}}, {"job_id": "100003009051314", "location_code": "hk", "company": "List Sotheby's International Realty", "job_title": "Graphic Designer", "description": "The Job\n\nCreate innovative solutions for Group and Business Units from concept generation, layout design and final artwork production including F&B photo shooting art direction, mall campaign setup idea, hotel sophisticated layout designs and corporate communicating materials to convey the distinctive messages\nDesign and execute all the assigned design tasks from research, concept generation, layout design and final artwork production in a wide range of media platforms\nWork with supervisor and other teammates to adhere to user\u2019s requests and meet deadlines to retain the company brand consistency and the specific promotions\nLiaise and follow up with printing companies and suppliers to ensure the timely delivery\nThe Requirement\n\nHigher diploma or above in Graphic Design or related disciplines\n2 years or above experience in design/advertising and/or digital campaign\nExperience in graphic, multimedia design, layout and typography\nKnowledge on Adobe Suite and video editing software i.e. Illustrator, Photoshop, InDesign, Premiere & Aftereffect etc.\nGood team player, willing to learn, open-minded, independent and responsible\n\nAttractive remuneration would be offered to the right candidates.\nPlease send your application with portfolio and expected salary to\u00a0Human Resources Manager:\n\nBy WhatsApp: 6388-3034 or\nBy Fax: 2722-5555\n\nPersonal data collected will be used for recruitment purpose only.\u00a0 We are an equal opportunity employer.", "employment_types": ["Full Time", "Permanent"], "selling_points": ["Real Estate Industry", "Marketing / Company Branding", "Competence with Adobe Creative Suite"], "locations": ["Central"], "categories": ["Design", "Graphics", "Multi-media"], "post_time": "2022-01-15T08:10:49Z", "salary": {"currency": null, "max": null, "min": null, "period": "monthly", "term": null}, "salary_visible": false, "title_keywords": ["graphic designer"], "responsibilities": ["liaise", "artwork production", "layout design", "design", "brand consistency", "setup"], "requirements": {"degrees": ["higher diploma or above"], "majors": ["related disciplines", "graphic design"], "languages": [], "language_level": [], "hard_skills": ["indesign", "illustrator", "premiere", "video editing", "whatsapp", "adobe", "multimedia", "photoshop"], "soft_skills": ["good team player", "independent", "responsible", "open-minded", "willing to learn"], "languages_combined": []}, "experience_required": {"duration": ["2 years"], "field": ["digital", "graphic", "advertising", "design"]}}, {"job_id": "100003009052930", "location_code": "hk", "company": "DigiSalad Solutions Limited", "job_title": "UX Lead / (Senior) UX & UI Designer", "description": "The Role\nWe are looking for a creative and passionate Graphic Designer to join our team.\u00a0\u00a0You will have a chance to work at a fast-paced mission driven company that brings material science to life and benefit the mass.\u00a0 We are bringing business disruption and new hygiene standard to the world with the introduction of new photocatalyst products and services. With the continuous R&D and business innovation, we are thrilled to develop the next generation technology that safeguards everyday life.\u00a0 Raze Technology is the world's leading photocatalyst solution company, developing a long-lasting disinfectant coating.\n\nResponsibilities\nResponsible for creative concept development and handle all stages of design include but not limited to the following:\u00a0\n\n\nSocial media visual and feed designs (Facebook, Instagram, eDM, Google ad, etc.);\u00a0\nOnline store visual (Web banner, product page, etc);\u00a0\nSales kit and POP materials;\nProduct retouching and mock-ups;\u00a0\nPerform ad-hoc projects as assigned.\n\nRequirements\n\n\nDiploma or above in Graphic Design/ Multimedia/ Creative Media or other related disciplines;\nAt least 3 years relevant working experience in graphic design, FMCG or digital marketing agency experience is preferred;\nProficient in using Adobe Illustrator, Photoshop in Mac environment;\u00a0\nProficient in animation and video editing is a plus;\nGood team player, multi-tasking and responsible;\nVisual merchandising experience is an advantage;\u00a0\nImmediate availability is highly preferable.\n\nWe offer the right candidate attractive remuneration package and outstanding prospects for career advancement and development.\u00a0 The right candidate will progress career in a forward thinking and dynamic business with exciting growth plans.\u00a0 If you are qualified and interested, please send your full resume with current & expected salary and availability by clicking \"APPLY\".\n\nAll information collected will be treated as strictly confidential and used for recruitment purposes only. (Only shortlisted candidates will be notified)", "employment_types": ["Full Time", "Permanent"], "selling_points": ["UX-Driven Digital Agency", "Fun and Young Working Environment", "Birthday Leave and Medical Coverage"], "locations": ["Tsuen Wan Area"], "categories": ["Design", "Multi-media", "Web Designer", "Information Technology (IT)", "UI/UX Designer"], "post_time": "2022-01-17T04:34:39Z", "salary": {"currency": null, "max": null, "min": null, "period": "monthly", "term": null}, "salary_visible": false, "title_keywords": ["ui designer", "lead"], "responsibilities": ["pop materials", "edm", "product retouching", "mock-ups", "social media visual and feed designs", "design", "visual", "facebook", "ad-hoc projects", "sales kit"], "requirements": {"degrees": ["diploma or above"], "majors": ["related disciplines", "graphic design", "creative media"], "languages": [], "language_level": [], "hard_skills": ["plus", "mac environment", "visual merchandising", "adobe illustrator", "multimedia", "animation and video editing", "photoshop"], "soft_skills": ["good team player", "creative", "multi-tasking", "responsible"], "languages_combined": []}, "experience_required": {"duration": ["at least 3 years"], "field": ["fmcg", "agency", "graphic design", "merchandising", "relevant working experience", "digital marketing"]}}, {"job_id": "100003009046328", "location_code": "hk", "company": "Confident Lab", "job_title": "Graphic Designer", "description": "ABOUT SEDGWICK RICHARDSON\n\nWe\u2019re a regional team of strategists, designers and sustainability specialists who are passionate about building brands that have a positive impact on our world. We are a new kind of company that is changing how brands are created. We fuse sustainability principles into brand building to create relevant brands that thrive.\n\nTogether, we Build Belief in the Future.\n\nAbout You\n\nYou work in a \u2018concept first\u2019 mode and think holistically about brands and publications. You understand that today they need to be designed to live across multiple channels and formats, and that this often means taking a digital first approach.\n\nYou want to work with a team truly committed to improving the world we live in. You want to learn about how sustainability thinking applies to brand design.\n\n\n\nYour responsibilities\n\nGenerate brilliant creative concepts and fresh ideas\nExtraordinary aesthetic sense and taste\nHighly sensitive to typography, imagery, layout hierarchy\nPay attention to the quality and every detail of design execution\nConsult internally with Creative Director and the Account Management team to agree on the theme, creative direction, other design parameters\nSupport in the creation of presentations and marketing content & materials\nDeliver design solutions within specified, approved schedules and resources\nSee designs through to final artwork and delivery\nManage the printing process for publications\n\nYour skills\n\nYou\u2019re able to articulate and visualise your ideas and concepts clearly\nFluency in spoken and written English required, Cantonese and Mandarin a big plus.\nYou\u2019ll have 3+ years of experience in publication design\nYou have intimate working knowledge of Adobe Photoshop, Illustrator, InDesign.\nYou\u2019re self-motivated, organised, accountable and thrive in a multi-cultural environment\nYour attitude is respectful, collaborative and positive\nYou are passionate about typography and understand typographic hierarchy\nYou have experience in data visualisation and information design\nYou can demonstrate an understanding of pagination planning\nYou have rigorous file management skills\n\nPlease send us a short email with your r\u00e9sum\u00e9 (and a link to your online portfolio) explaining why you are interested to join our team. This must include previous and expected salary.", "employment_types": ["Full Time"], "selling_points": [], "locations": ["Tsim Sha Tsui"], "categories": ["Design", "Multi-media"], "post_time": "2022-01-13T10:31:12Z", "salary": {"currency": null, "max": null, "min": null, "period": "monthly", "term": null}, "salary_visible": false, "title_keywords": ["graphic designer"], "responsibilities": ["management team", "ideas", "design solutions", "schedules", "data", "quality", "presentations", "design", "file management", "publication", "planning"], "requirements": {"degrees": [], "majors": [], "languages": ["cantonese", "english", "mandarin"], "language_level": ["fluency"], "hard_skills": ["plus", "indesign", "adobe photoshop", "illustrator", "presentations"], "soft_skills": ["self-motivated", "passionate about", "accountable", "collaborative", "committed", "sensitive to", "organised", "articulate", "creative", "positive", "respectful"], "languages_combined": [{"language": "cantonese", "language_level": ["fluency"]}, {"language": "english", "language_level": ["fluency"]}, {"language": "mandarin", "language_level": ["fluency"]}]}, "experience_required": {"duration": ["3+ years"], "field": ["design"]}}, {"job_id": "100003009048929", "location_code": "hk", "company": "Fresh Up Group Limited", "job_title": "Graphic Designer", "description": "Work closely with the marketing team to create company branding, designs and continuous content for users and the platform (Website/social media)\nAble to create strategic and creative ideas with a fresh mindset, result oriented, and able to drive the process within a given deadline\nExperience with online advertising/ social media platforms (Facebook, WeChat, Linkedin, Instagram)\nPassionate about seeking out-of-the-box ideas related to design and content\n\nThe Successful Applicant\n\nDiploma in Graphic Design, or Marketing-related discipline\nMinimum 2 years of related experience\nImmediate availability preferred\nCompetence with Adobe Creative Suite (particularly Photoshop, Illustrator, InDesign), and Powerpoint\nResponsible, detail minded,\u00a0efficient, well organized, proactive,\u00a0independent\u00a0and able to work under pressure\nStrong communication and interpersonal skills\nInterested parties please send your\u00a0full resume with expected salary\u00a0and\u00a0your availability\u00a0to us.\n\n\nAll personal data collected will be treated strictly confidential and used for recruitment purposes only.", "employment_types": ["Full Time"], "selling_points": ["Solid experience in Illustrator & After Effects", "1-2 years relevant experience", "Immediate Available"], "locations": ["Kwai Fong"], "categories": ["Design", "Graphics", "Multi-media", "Others"], "post_time": "2022-01-14T07:44:02Z", "salary": {"currency": null, "max": null, "min": null, "period": "monthly", "term": null}, "salary_visible": false, "title_keywords": ["graphic designer"], "responsibilities": ["social media", "creative ideas", "ideas", "graphic design", "social media platforms", "website", "design", "communication", "facebook", "online advertising", "work under pressure"], "requirements": {"degrees": ["diploma"], "majors": ["graphic design", "marketing"], "languages": [], "language_level": [], "hard_skills": ["indesign", "illustrator", "powerpoint", "wechat", "facebook", "adobe creative suite", "photoshop"], "soft_skills": ["efficient", "proactive", "independent", "responsible", "well organized", "result oriented", "communication and interpersonal skills", "creative", "passionate about", "work under pressure"], "languages_combined": []}, "experience_required": {"duration": ["minimum 2 years"], "field": ["related", "social media", "advertising"]}}, {"job_id": "100003009047541", "location_code": "hk", "company": "Society Of Genesis Limited", "job_title": "2D\u52d5\u756b\u8a2d\u8a08\u54e1 2D Animator", "description": "Got tired of your boring work?\n\nWe have cool people. We deliver cool design. We are not a machine to work under long hours everyday with strict rules. We are not someone\u2019s pair of hands. We work in a creative, fun and flexible environment with no pressure.\n\nIf you think you are cool enough and ready to overcome challenges with supportive teammates to break your boundaries. Join us now!\n\nCheck out our new promotional video to find out who we are & why Digi is with Salad!\n\nResponsibilities:\n\nUtilize industry design standards and best practices to define and implement design criteria by a variety of methods to convey ideas and concepts (e.g. personas, user flow diagrams, wireframes, design prototypes, etc)\nDesign and specify UX and UI design for Responsive Web and Mobile application (iOS & Android)\nDeliver inventive, durable and thoughtful, solutions from concept to launch\nApply conceptual thinking to create desirable and feasible digital solutions across multiple platforms\nWork closely with a blended cross-functional team and tackle all aspects of the design process\nMaintain knowledge of design trends and assist with implementation of design innovations\u00a0\nLess Experience will be considered as Senior UX & UI Designer or UX & UI Designer\n\nRequirements:\n\nDegree or Diploma holder in visual design, interactive design, creative media or relevant discipline\nMinimum 3 years of experience in App and Responsive Web design\nStrong portfolio demonstrating proven UX workflow and strong design techniques\nProven ability in a variety of design tools such as Figma, Sketch, Invision, Photoshop, Illustrator and a bonus if you have experience with Adobe After Effects/ Flinto/ Principle\nBasic Knowledge in HTML production, HTML5, CSS3, JavaScript\nEffectively communicate research findings, conceptual ideas, detailed design, and design rationale both verbally and visually\nWilling to learn new trends and technology\nPositive attitude and motivation to deliver highest quality work\nDigital Agency Background is preferable but not a must\u00a0\n\nBenefit We Offer:\n\n5 days\u2019 work\nPerformance Bonus\nMedical Coverage\nFlexible Working Hours\nBirthday, Wedding, Maternity and Paternity leaves\nFun, young and joyful environment\u00a0\n\nWe're looking for talented individuals that want to do great work in a fun, creative, young and smart place. Attractive long term career prospect, along with competitive remuneration package and fringe benefits will be offered to the right candidate.\n\nJoin Us and Be a Cool People Now!\n\nInterested parties please click \"Apply Now\" to send a cover letter stating your expected salary, resume and a full set of your portfolio to us.\n\n*All information will be treated as confidential and used solely for recruitment purposes.\n", "employment_types": ["Full Time"], "selling_points": [], "locations": ["North Point"], "categories": ["Design", "Multi-media"], "post_time": "2022-01-14T03:25:09Z", "salary": {"currency": "HKD", "max": 13999, "min": 11000, "period": "monthly", "term": null}, "salary_visible": true, "title_keywords": ["animator"], "responsibilities": ["ideas", "implementation", "design", "maintain", "design trends", "ui"], "requirements": {"degrees": ["diploma holder", "degree"], "majors": ["creative media", "design"], "languages": [], "language_level": [], "hard_skills": ["web design", "basic", "illustrator", "html", "adobe after effects", "visual design", "javascript", "photoshop"], "soft_skills": ["willing to learn", "positive attitude", "creative", "responsive", "detailed"], "languages_combined": []}, "experience_required": {"duration": ["minimum 3 years"], "field": ["design"]}}, {"job_id": "100003009050698", "location_code": "hk", "company": "On Stage Production and Consultant Limited", "job_title": "Video Editor / Motion Graphics Designer", "description": "Proficiency in Adobe Photoshop and Illustrator\nKnowledge in video editing is an advantage\nWelcome fresh graduate\nResponsibilities:\u00a0\nResponsible for design shop materials from online to offline channels e.g. social media, website etc.\nCreate, edit and promote social media content in various formats including (but not limited to) feeds, videos, photos, etc.\nRequirements:\nGood\u00a0command\u00a0in\u00a0Chinese\u00a0and\u00a0English\nCreative, good attentive to details\nStrong team player and sense of responsibility\nMature, proactive working attitude\nWorking time:\u00a0\n5-days work (12:00-20:00)\nBenefit:\n17 days statutory holidays\u00a0\nBirthday leave\nMarriage leave\nSick leave compensation\n9-12 days annual leave\nStaff Discount\nOn-the-job training, good promotion opportunity\nInterested parties please send email with CV and portfolio via \u201cApply Now\u201d\n\u5e73\u9762\u8a2d\u8a08\u5e2b\n\u7d14\u719f\u904b\u7528Adobe Photoshop\u3001Illustrator\u7b49\u7cfb\u5217\u5e73\u9762\u8a2d\u8a08\u8edf\u4ef6\n\u719f\u6089\u77ed\u7247\u526a\u63a5\u512a\u5148\u8003\u616e\n\u7d93\u9a57\u4e0d\u62d8\n\u5de5\u4f5c\u8077\u8cac\uff1a\u00a0\n\u8ca0\u8cac\u5e97\u8216\u7db2\u7ad9\u53ca\u793e\u4ea4\u5a92\u9ad4\u7528\u4f5c\u5ba3\u50b3\u63a8\u5ee3\u7684\u7f8e\u8853\u8a2d\u8a08\n\u70ba\u5e97\u8216\u793e\u4ea4\u5e73\u53f0\u5275\u5efa\u5e16\u6587\uff0c\u5167\u6587\u6587\u6848\u5275\u4f5c\n\u8077\u4f4d\u8981\u6c42\uff1a\n\u5177\u4e2d\u3001\u82f1\u6587\u6e9d\u901a\u80fd\u529b\n\u5275\u65b0\uff0c\u6709\u5275\u9020\u529b\uff0c\u5c0d\u7ba1\u7406\u793e\u4ea4\u5a92\u9ad4\u611f\u8208\u8da3\n\u91cd\u8996\u5718\u9ad4\u5408\u4f5c\u7cbe\u795e\uff0c\u7a4d\u6975\u6709\u79ae\u3001\u5bcc\u8cac\u4efb\u5fc3\n\u6210\u719f\u4e3b\u52d5\u53ca\u64c1\u6709\u826f\u597d\u5de5\u4f5c\u614b\u5ea6\n\u5168\u8077, \u5de5\u4f5c\u6642\u9593 (\u4e0b\u534812\u6642\u81f3\u4e0b\u53488\u6642), 5\u5929\u5de5\u4f5c\n\u5168\u8077\u54e1\u5de5\u798f\u5229\uff1a\n* 17\u5929\u516c\u773e\u5047\u671f\n* \u751f\u65e5\u5047\u671f\n* \u7d50\u5a5a\u5047\n* \u6709\u85aa\u75c5\u5047\n* \u6709\u85aa\u5e74\u50479\u5929\uff0c\u53ef\u9577\u905412\u65e5\n* \u54e1\u5de5\u8cfc\u7269\u53ca\u7642\u7a0b\u512a\u60e0\n* \u6709\u85aa\u5728\u8077\u57f9\u8a13\u53ca\u826f\u597d\u6649\u5347\u6a5f\u6703\n\u6709\u610f\u61c9\u5fb5\u8005\u8acb\u9ede\u64ca\u201dApply Now\"\uff0c\u4e26\u9644\u4e0a\u8a73\u7d30\u5c65\u6b77\u53ca\u8a2d\u8a08\u4f5c\u54c1\u96c6", "employment_types": ["Full Time"], "selling_points": ["Certificate/Diploma/Degree holder", "Min 1 years solid experience in video editing", "motion graphic knowledge is preferable;"], "locations": ["Kwun Tong"], "categories": ["Design", "Multi-media"], "post_time": "2022-01-14T11:12:56Z", "salary": {"currency": null, "max": null, "min": null, "period": "monthly", "term": null}, "salary_visible": false, "title_keywords": ["designer", "video editor"], "responsibilities": ["social media", "social media content", "website", "design"], "requirements": {"degrees": [], "majors": [], "languages": ["english", "chinese"], "language_level": ["good command"], "hard_skills": [], "soft_skills": ["proactive", "attentive to details", "sense of responsibility", "mature", "team player", "creative"], "languages_combined": [{"language": "english", "language_level": ["good command"]}, {"language": "chinese", "language_level": ["good command"]}]}, "experience_required": {"duration": [], "field": []}}, {"job_id": "100003009049331", "location_code": "hk", "company": "Sitoy Group Holdings Limited", "job_title": "Creative Multimedia - Senior Designer", "description": "Responsibilities:\n\n\nResponsible for digital graphic design creatives and executions;\nDesign and execute compelling creative for digital channels by mobile / desktop in a wide range of media platforms;\nCreating and editing animation / motion graphic for informative and promotional videos.\n\n\nRequirements:\n\n\nDiploma or above in Multimedia Design, Graphic Design, Creative Media or related discipline;\n1-2 years relevant experience;\nProficient in Adobe Creative skills; Illustrator, Photoshop, InDesign, Premiere, After Effects etc.\nKnowledge in photography and video editing are preferred;\nGood written and verbal communication skills in both English and Chinese;\nSelf-motivated, responsible, able to work independently and adapt to different environment;\nPortfolio is required for interview.\n\nBenefits:\n\n\n5days work / Bank Holidays / Annual Leaves / Medical Insurance / Birthday Leave, Maternity Leave, Funeral Leave / Promotion Opportunities etc.\n\nWe offer competitive remuneration including career prospects to the right candidate. Interested parties please send your portfolio and resume with current & expected salary by clicking 'Apply Now' for application.\n\n(Data collected will only be used for job application processing. All related information will be kept up to 6 months and all personal data will be destroyed afterwards.)\n\n", "employment_types": ["Full Time"], "selling_points": ["Luxury\uff5cRetail \uff5cMultimedia Design", "5-day work, Performance Bonus, Medical Insurance", "Birthday Leave,Study&Exam. Leave,Graduation Leave"], "locations": ["Kwun Tong"], "categories": ["Design", "Graphics", "Multi-media", "Others"], "post_time": "2022-01-14T08:28:37Z", "salary": {"currency": null, "max": null, "min": null, "period": "monthly", "term": null}, "salary_visible": false, "title_keywords": ["senior designer", "creative"], "responsibilities": ["graphic design", "design", "editing", "motion graphic", "animation"], "requirements": {"degrees": ["diploma or above"], "majors": ["multimedia design", "graphic design", "creative media"], "languages": ["english", "chinese"], "language_level": ["good"], "hard_skills": ["indesign", "illustrator", "premiere", "video editing", "after effects", "adobe", "multimedia", "photoshop"], "soft_skills": ["communication skills", "self-motivated", "work independently", "responsible", "creative"], "languages_combined": [{"language": "english", "language_level": ["good"]}, {"language": "chinese", "language_level": ["good"]}]}, "experience_required": {"duration": ["1-2 years"], "field": ["relevant experience"]}}, {"job_id": "100003009048109", "location_code": "hk", "company": "HKT Consumer Group", "job_title": "Motion Graphic Designer / Animator", "description": "\u3002\u8a8d\u53ef\u7684\u5c08\u4e0a\u6559\u80b2\uff0c\u526f\u5b78\u58eb\u5b78\u4f4d\uff0c\u4e3b\u4fee\u8a2d\u8a08\u6216\u52d5\u756b\u88fd\u4f5c\u76f8\u95dc\u5b78\u79d1\u512a\u5148\n\n\u30021\u5e74\u6216\u4ee5\u4e0a\u76f8\u95dc\u5de5\u4f5c\u7d93\u9a57\uff0c\u7d93\u9a57\u8f03\u6dfa\u8005\u4ea6\u53ef\u70ba\u898b\u7fd2\u8a2d\u8a08\u54e1\n\n\u3002\u4e86\u89e3Adobe\u7cfb\u5217\u8edf\u4ef6\uff0c\u64c5\u9577Photoshop, After Effects, Premiere Pro, AU etc\n\n\u3002\u66ff\u5152\u7ae5\u6559\u6750\u88fd\u4f5c\u52d5\u756b\n\n\n\u3002\u6bcf\u6708\u85aa\u91d1\uff1a$12,000 (\u7d93\u9a57\u8c50\u5bcc\u8005\u53ef\u8b70)\n\n\u3002\u4e00\u5e74\u5408\u7d04\uff0c\u5982\u8868\u73fe\u826f\u597d\u53ef\u7372\u7e8c\u7d04\u8abf\u85aa\n\n\u3002\u6bcf\u90315\u5929\u5de5\u4f5c\n\u4e0a\u73ed\u6642\u9593\uff1a\u661f\u671f\u4e00\u81f3\u56db\uff1a09:00-18:00,\u00a0\u00a0\u661f\u671f\u4e94\uff1a09:00-17:00\n\n\n*\u4e0a\u8ff0\u8077\u4f4d\u7684\u5de5\u4f5c\u5730\u5740\u70ba\u65e9\u6167\u5152\u7ae5\u6559\u80b2\u4e2d\u5fc3\u5317\u89d2\u5206\u6821\uff0c\u50f1\u54e1\u9808\u9075\u5b88\u90e8\u4efd\u76f8\u95dc\u7684\u54e1\u5de5\u5b88\u5247\n\n\u3002\u54e1\u5de5\u798f\u5229\uff1a\n\u6709\u85aa\u75c5\u5047\u3001\u5a5a\u5047\u3001\u4f8d\u7522\u5047\u3001\u91ab\u7642\u4fdd\u969c(\u9580\u8a3a\u6d25\u8cbc+\u4f4f\u9662\u4fdd\u96aa)\u3001\u52e4\u5de5\u734e\u3001\u751f\u65e5\u798f\u5229\u3001\u5728\u8077\u57f9\u8a13\u3002\u672c\u6a5f\u69cb\u5177\u7a69\u5b9a\u67b6\u69cb\uff0c\u80fd\u63d0\u4f9b\u826f\u597d\u6649\u5347\u6a5f\u6703\u3002", "employment_types": ["Full Time"], "selling_points": [], "locations": ["Quarry Bay"], "categories": ["Design", "Graphics", "Multi-media"], "post_time": "2022-01-14T04:57:02Z", "salary": {"currency": null, "max": null, "min": null, "period": "monthly", "term": null}, "salary_visible": false, "title_keywords": ["animator", "graphic designer"], "responsibilities": [], "requirements": {"degrees": [], "majors": [], "languages": [], "language_level": [], "hard_skills": ["after effects", "premiere pro"], "soft_skills": [], "languages_combined": []}, "experience_required": {"duration": [], "field": []}}, {"job_id": "100003009047298", "location_code": "hk", "company": "You Find Limited", "job_title": "(Senior) Graphic/ Multimedia Designer", "description": "Job Duties\n\nResponsible for the whole set of video editing, motion graphic and infographic design for corporate video, animation and event promo.\n\nRequirements\n\nCertificate/Diploma/Degree holder in Creative Media, Multimedia Design, Motion Graphics or Animation;\nMin 1 years solid experience in video motion graphic design with Premiere, After Effects, Illustrator, Photoshop;\n3Ds Max knowledge is preferable;\nStrong creative, presentation layout, visual design and video production artwork;\nAble to work independently and under tight schedule;\nGood communication & interpersonal skills;", "employment_types": ["Full Time", "Permanent", "Contract"], "selling_points": ["Fast growing digital marketing industry", "Good career prospect; strong team spirit", "5 days work; fun & energetic working environment"], "locations": ["Ngau Tau Kok"], "categories": ["Media & Advertising", "Creative / Design", "Design", "Graphics", "Multi-media"], "post_time": "2022-01-14T02:47:42Z", "salary": {"currency": null, "max": null, "min": null, "period": "monthly", "term": null}, "salary_visible": false, "title_keywords": ["multimedia designer"], "responsibilities": ["video editing", "animation", "motion graphic", "design"], "requirements": {"degrees": ["certificate", "diploma", "degree holder"], "majors": ["multimedia design", "creative media", "motion graphics", "animation"], "languages": [], "language_level": [], "hard_skills": ["graphics", "3ds max", "illustrator", "premiere", "after effects", "visual design", "multimedia", "photoshop"], "soft_skills": ["work independently", "communication", "interpersonal skills", "creative", "presentation"], "languages_combined": []}, "experience_required": {"duration": ["min 1 years"], "field": ["video", "motion graphic", "design"]}}, {"job_id": "100003009054201", "location_code": "hk", "company": "Endeavour Search Limited", "job_title": "Senior Digital Designer (AM Grade) - Corporate Communication / MNC / Global Leading Brands", "description": "This person should have a strong creative mind set with a deep technical knowledge of the latest tools and technology to deliver finished end products independently. The position requires to work closely with Regional and local teams, Marketing and Merchandising team to produce relevant content for our target audience.\n\nResponsibilities:\n\nPlan, create, develop and execute multimedia content\u00a0 (social media, photography, video, graphics and website), to deliver key brand message to internal and external audiences\nPlan and coordinate the brand\u2019s seasonal advertising campaign\nCollaborates with marketing, sales, and design teams to produce relevant content for all stages of our sales and marketing processes.\nStay abreast of industry trends and technologies\nEnsure content meets brand guidelines and is on target\n\nRequirements:\n\n3 years or above of content management role / assistant manager role will be considered should candidate has more experience\nExperience working within creative team and regional offices\nProficiency in photo / graphic software \u2013 Adobe acrobat, photoshop, illustrator, indesign; video editing software \u2013 Adobe after effects, Final cut pro\nKeen eye for small details and exceptional problem-solving skills\nAbility to work in a fast-paced environment and meet targeted deadlines.\nMust be professional, organized, enthusiastic and a team player who can work independently.\n\nWe offer competitive remuneration package, 5-day work, performance bonus, medical insurance and paid leave.\u00a0 Interested parties please send your full resume \u00a0(Both of\u00a0Chinese and English Version ) with current and expected salary via email to us\u00a0or click \u201cApply Now\u201d. No expected salary mentioned in resume will not be considered.\n\nAll information collected will be kept in strict confidential and used for recruitment purpose only.\u00a0\n\n*We are an equal opportunities employer*", "employment_types": ["Full Time", "Permanent"], "selling_points": ["Lead & present digital design", "Familiar with UI / Web/ App design", "MNC, young and dynamic culture; Fluent Eng"], "locations": ["Not Specified"], "categories": ["Design", "Industrial / Product", "Multi-media", "Web Designer"], "post_time": "2022-01-17T08:47:25Z", "salary": {"currency": null, "max": null, "min": null, "period": "monthly", "term": null}, "salary_visible": false, "title_keywords": ["digital designer"], "responsibilities": ["graphics", "social media", "advertising", "teams", "website", "plan and coordinate", "develop", "design", "brand guidelines", "plan"], "requirements": {"degrees": [], "majors": [], "languages": [], "language_level": [], "hard_skills": ["final cut pro", "small", "indesign", "illustrator", "adobe after effects", "video editing", "problem-solving skills", "adobe acrobat", "photoshop"], "soft_skills": ["organized", "work independently", "fast-paced environment", "keen", "enthusiastic", "problem-solving skills", "team player", "creative"], "languages_combined": []}, "experience_required": {"duration": ["3 years"], "field": ["management", "team"]}}, {"job_id": "100003009050075", "location_code": "hk", "company": "\u8a66\u5413\u5566\u5e02\u5834\u63a8\u5ee3\u6709\u9650\u516c\u53f8", "job_title": "Graphic Designer (5 Days Work)", "description": "Job Highlights\n\nCertificate/Diploma/Degree holder in Creative Media, Multimedia Design, Motion Graphics or Animation.\nWelcome Fresh Grad in related disciplines.\n\n\u00a0\n\nYour role:\n\nResponsible for the develop creative ideas whole set of video editing, motion graphic, and infographic design for corporate video, animation, and event promo.\nWork closely with the marketing team and design team to facilitate the creative process.\n\u00a0\n\nTo succeed in this role:\n\nGood understanding of Motion graphics & Visual Production, design thinking.\nAdditional knowledge in Graphic design, video filming & editing is preferable.\nRelevant work portfolio is a must.\nKnowledge in Adobe Illustrator, Photoshop, Premiere Pro & After Effect is a must, additional adobe creative cloud-related software\nCreative, passionate, positive-thinking, willing to work under great pressure and tight deadlines", "employment_types": ["Full Time", "Permanent"], "selling_points": ["Higher Diploma in Web/ Graphic/ Multimedia Design", "2+ yrs exp. in graphic design", "Good design theory & insight on GUI design trends"], "locations": ["Lai Chi Kok"], "categories": ["Design", "Graphics", "Multi-media", "Web Designer"], "post_time": "2022-01-14T09:58:07Z", "salary": {"currency": null, "max": null, "min": null, "period": "monthly", "term": null}, "salary_visible": false, "title_keywords": ["graphic designer"], "responsibilities": ["multimedia design", "software", "animation", "graphic design", "design", "facilitate the creative process", "video editing", "motion graphics", "visual", "editing", "motion graphic", "develop creative ideas"], "requirements": {"degrees": ["certificate", "diploma", "degree holder"], "majors": ["multimedia design", "creative media", "motion graphics", "animation"], "languages": [], "language_level": [], "hard_skills": ["graphics", "adobe illustrator", "video editing", "adobe", "multimedia", "premiere pro", "after effect", "photoshop"], "soft_skills": ["passionate", "creative", "positive", "responsible"], "languages_combined": []}, "experience_required": {"duration": [], "field": []}}, {"job_id": "100003009051349", "location_code": "hk", "company": "3T6B Limited", "job_title": "Creative Director (Art) / Art Director (Digital)", "description": "Executive Summary:\n\nA Hong Kong blue-chip listed company with global business presence in Asia, American, Europe, Middle East and Africa\nWell established business culture (over 30 years) and renowned brands profiles \u2013 over 400 staffs in Hong Kong; annual global sales turnover rate over 6Billion USD; stable work culture and puts people first\nNewly created role due to the business demand\nStrong and solid designer teams, MNC cultures\nExcellent compensation & benefit for the right candidate; 5 minute walk to the office from MTR\nResponsibilities:\n\nLead and manage the corporate design team for digital design projects delivery and execution\nSupport the stakeholders/managers for assisting their creative project pitches and other creative input, presentations and proposal writings\nDesign user interfaces such as company websites, mobile applications, by using iterative design techniques, observational studies, stakeholder interviews, usability tests and other forms of requirement discovery\nAnalysis market trend and communicate research findings, conceptual ideas, detailed design and design rationale both verbally and visually\nConduct user requirement analysis, task analysis, information architecture design, interaction design and usability testing\n\nRequirements:\n\nDiploma or above in Digital Design or related disciplines\n5 years relevant experience in digital design and with experience in web and mobile application design development\nExperience in Adobe Photoshop, Premiere, After Effects, Illustrator, XD, Figma\nGood understanding of trends in digital design and branding\nVisual design skills with sensitivity to user-system interaction\nAbility to pay attention to detail, and to work under pressure and tight time constraints\nGood command of written and spoken English and Chinese, knowledge of Mandarin is an advantage\n\nTo apply, please send your CV in word document to gloria(a)endeavourasia.com or call Gloria at 3956-1829 for a confidential discussion.", "employment_types": ["Full Time"], "selling_points": ["Digital Media(\uff20DL.theVOC) + UI/UX \uff06 Graphic Design", "Good sense of art direction, graphic sense", "Working with Award winning Creatives"], "locations": ["Kwun Tong"], "categories": ["Design", "Graphics", "Multi-media", "Information Technology (IT)", "UI/UX Designer"], "post_time": "2022-01-15T10:39:17Z", "salary": {"currency": null, "max": null, "min": null, "period": "monthly", "term": null}, "salary_visible": false, "title_keywords": ["art director", "creative director"], "responsibilities": ["company websites", "user requirement", "ideas", "analysis", "presentations", "design", "testing", "architecture"], "requirements": {"degrees": ["diploma or above"], "majors": ["related disciplines", "design"], "languages": ["english", "chinese", "mandarin"], "language_level": ["advantage", "good command"], "hard_skills": ["web", "adobe photoshop", "premiere", "illustrator", "word", "mobile", "after effects", "visual design"], "soft_skills": ["sensitivity", "attention to detail", "work under pressure"], "languages_combined": [{"language": "english", "language_level": ["advantage", "good command"]}, {"language": "chinese", "language_level": ["advantage", "good command"]}, {"language": "mandarin", "language_level": ["good command"]}]}, "experience_required": {"duration": ["5 years"], "field": ["digital", "development", "relevant experience", "design"]}}, {"job_id": "100003009046902", "location_code": "hk", "company": "Dragon Creative Media Limited", "job_title": "Multimedia Graphic Designer / Graphic Designer", "description": "Responsibilities :\n\n\nVisual design of printed materials\u00a0including product brochures, sales and marketing collateral, promotion materials, \u00a0photo retouching and editing\nProduction of animations, motion graphics, graphic designs and basic videos for Webpage, EDM, Facebook, Instagram and Google Ads\nBrainstorm and collaborate innovative ideas with our sales & marketing team\nHandle ad-hoc tasks or projects as assigned\n\nRequirements:\n\n\nHigher Diploma or above in Web / Graphic / Multimedia Design or related disciplines\n2+ years experience in graphic design\nGood knowledge of design theory and insight on GUI design trends\nBasic Knowledge of Adobe Premiere & After Effect\nExperience in designing user interface for mobile-friendly webpages is an advantage\nCreative, independent, well organized, self-motivated and able to handle multiple projects under tight deadline\nGood interpersonal and communications skills\n\nWe offer 5 days work, 12 days annual leave, medical scheme, health incentive program, attractive remuneration package and bonus scheme. Interested parties please quote Employer Ref. No. and send detailed resume with\u00a0CURRENT & EXPECTED SALARIES\u00a0and available date\u00a0by\u00a0clicking the \"Apply Now\" button.\n\n\nFor company information, please visit our website :\u00a0https://tryhala.com/info/tryhala-about-us/\n\n\nAll information is collected for recruitment purpose only.", "employment_types": ["Full Time"], "selling_points": ["5 days work", "At least 1 year multimedia experience", "Strong creative sense"], "locations": ["Southern Area"], "categories": ["Design", "Graphics", "Multi-media", "Web Designer"], "post_time": "2022-01-14T01:40:36Z", "salary": {"currency": null, "max": null, "min": null, "period": "monthly", "term": null}, "salary_visible": false, "title_keywords": ["graphic designer"], "responsibilities": ["collaborate", "photo retouching", "ideas", "edm", "ad-hoc tasks", "graphic designs", "design", "motion graphics", "animations", "visual", "facebook", "editing"], "requirements": {"degrees": ["higher diploma or above"], "majors": ["multimedia design", "related disciplines"], "languages": [], "language_level": [], "hard_skills": ["basic", "web", "mobile", "adobe premiere", "multimedia", "after effect"], "soft_skills": ["self-motivated", "independent", "well organized", "friendly", "creative", "interpersonal"], "languages_combined": []}, "experience_required": {"duration": ["2+ years"], "field": ["graphic design"]}}, {"job_id": "100003009050425", "location_code": "hk", "company": "Ikigai Concepts Limited", "job_title": "Graphic Designer (F&B)", "description": "Job Highlights\u00a0\n\nDigital Media (DL.theVOC) + Technical Creative Projects + UI / UX Design\n\nGood sense of art direction, graphic sense\n\nWorking with Award winning Creatives\n\nJob Description:\u00a0\n\nProvide full creative, design, project art direction and production support;\n\nResponsible for social media OG design, GDN banner, graphics design, video editing, animation and other marketing materials;\n\nCreating different designs for marketing use purpose in different platform such as desktop, mobile as well as kiosk;\n\nKnowledge & experience in digital media industry is a plus;\u00a0\n\nRequirements:\n\nDiploma or above in Graphic / Multimedia / Web design or related fields;\n\nMinimum 2 years\u2019 relevant experience in graphic design, web design or advertising;\n\nPhotography and photo retouching, video post production, sound editing skills\n\nProficient in using PC / Mac Systems, Adobe Creative Cloud specifically Photoshop, Illustrator, Premiere, After Effects and other essential multimedia, interactive softwares, WordPress, Microsoft Office and other relevant software applications, familiar with HTML / HTML5 / CSS / JS is a plus;\n\nWorking knowledge of SEO best practice, GDN Display Ads, familiar with UI / UX design (Adobe XD, Figma, Sketch) is a big plus;\n\nStrong multimedia and web sense and understanding of digital technology trends;\n\nCreative, detail-oriented, enthusiastic, independent and self-motivated;\n\nGood written and spoken in English and Chinese;\n\nA perfect team player;\n\nPortfolio attachment is a MUST;\n\nCandidates with less experience would also be considered as Associate Art Director;\n\n\u00a0Benefits:\n\nAnnual Leave\n\nBirthday Leave\n\nPerformance Bonus\n\nMedical Insurance\n\nWe offer 5\u2013day work week, competitive salary and fringe benefits to the right candidate. For interested parties please send a cover letter stating your current salary and expected salary with Resume, Graduation Certification and Transcript to us.\n\nCandidates who are not contacted within 1 month from sending the resume should consider your applications filed for future opportunities. All applications will be treated in strict confidentiality and used for recruitment purpose only", "employment_types": ["Full Time", "Permanent"], "selling_points": ["Design artwork for F&B business", "Create content for social medial and website", "5 yrs exp in graphic / product design"], "locations": ["Kowloon Bay"], "categories": ["Design", "Graphics", "Industrial / Product", "Multi-media"], "post_time": "2022-01-14T10:23:50Z", "salary": {"currency": null, "max": null, "min": null, "period": null, "term": null}, "salary_visible": false, "title_keywords": ["graphic designer"], "responsibilities": ["graphics", "social media", "design", "video editing", "marketing materials", "animation"], "requirements": {"degrees": ["diploma or above"], "majors": ["web design"], "languages": ["english", "chinese"], "language_level": ["good"], "hard_skills": ["web design", "plus", "seo", "web", "microsoft office", "adobe xd", "css", "illustrator", "premiere", "html", "after effects", "wordpress", "adobe", "multimedia", "pc", "photoshop"], "soft_skills": ["self-motivated", "independent", "detail-oriented", "enthusiastic", "team player", "creative"], "languages_combined": [{"language": "english", "language_level": ["good"]}, {"language": "chinese", "language_level": ["good"]}]}, "experience_required": {"duration": ["minimum 2 years"], "field": ["art director", "advertising", "graphic design", "design", "relevant experience"]}}, {"job_id": "100003009051362", "location_code": "hk", "company": "Raze Technology Limited", "job_title": "Art Director", "description": "Responsibilities:\u00a0\nTo develop creative concept / design, and including the productions for all\u00a0the communications, inclusive, but not limited to the following:\nWeekly eDM \u2013 branding and tactical\nWebsite content image design\nSocial media graphic and/or motion picture design\nApp & Digital advertising\nOffline advertising\nPrinted materials\nSimple animated gif or videos\nIn term of the creative concept / design, will require to develop locally, as\u00a0well as to adapt the headquarter creative into local version.\n\nTo be the brand guardian for the Company \u2013 to ensure all the\ncommunication is on brand, and in-sync with the brand guideline;\nTo assist in finalizing design output, photo retouching and follow up\nproduction with vendors or other departments.\nRequirements:\u00a0\nDiploma or above in graphic/multi-media design or other related subject;\nMinimum 3 years\u2019 experience in online and offline design;\nExcellent in design tools and PC / Mac applications, such as Adobe\u00a0Photoshop, InDesign, Illustrator, i-movie, Flash, iOS etc. &amp; word processing\u00a0program: Keynotes, PowerPoint, Word, Excel etc.;\nKnowledge in print production and photography;\nGood command of spoken & written English and Chinese;\nGood organization skill and detail-oriented;\nA good team player and passionate in coming up with great creative\u00a0designs;\nImmediate available is preferred.\nWe offer excellent career prospects, competitive salary and fringe benefits to the right candidate. Please apply in strict confidence by sending\u00a0personal resume together with salary expected and date available\n\nby e-mail to:\u00a0\u00a0h r d _ h n @ h a r v e y n i c h o l s . c o m . h k\nWe are an equal opportunity employer and welcome applications from all qualified candidates. Personal data provided by job applicants will be used strictly in accordance with our personal data policy and for recruitment purposes only. Candidates not notified within eight weeks may consider their application unsuccessful. All related information will be kept in our file for up to 24 months. A copy of our Personal Information Collection Statement will be provided upon request by contacting our Human Resources Division.", "employment_types": ["Full Time", "Permanent", "Contract", "Freelance"], "selling_points": [], "locations": ["Southern Area"], "categories": ["Media & Advertising", "Creative / Design", "Design", "Graphics", "Multi-media"], "post_time": "2022-01-15T11:12:04Z", "salary": {"currency": null, "max": null, "min": null, "period": "monthly", "term": null}, "salary_visible": false, "title_keywords": ["art director"], "responsibilities": ["social media", "photo retouching", "advertising", "edm", "website", "design", "develop", "communication"], "requirements": {"degrees": ["diploma or above"], "majors": ["design"], "languages": ["english", "chinese"], "language_level": ["good command"], "hard_skills": ["excel", "adobe photoshop", "indesign", "illustrator", "word processing", "powerpoint", "word", "flash", "pc"], "soft_skills": ["passionate", "good team player", "organization skill", "detail-oriented", "creative"], "languages_combined": [{"language": "english", "language_level": ["good command"]}, {"language": "chinese", "language_level": ["good command"]}]}, "experience_required": {"duration": ["minimum 3 years"], "field": ["design"]}}, {"job_id": "100003009047433", "location_code": "hk", "company": "Teawood Taiwanese Dining Bar Limited", "job_title": "Senior Graphic Designer / Graphic Designer", "description": "The Role\nThe Art Director is required to work hand-in-hand with Head of Marketing, primarily to generate the original idea, lead the art direction and present campaigns to top management, secondly to groom and coach the juniors, help manage the execution and production.\n\nResponsibilities\n\nInterpret a creative brief and turn it into a compelling story;\nProduce innovative ideas for campaigns in line with the creative brief provided;\nTranslate marketing campaign \u2018Big Idea\u2019 into visual brand identity of our clients;\nProduce key visuals for pitches and marketing campaign;\nTranslate a briefing into a visual statement using presentation tools such as PowerPoint, Google slide or Keynote;\nAble to develop visual concepts which adhere to any brand style guideline and restrictions provided;\nWork resourcefully, offer variety of alternative solutions to creative problems;\nThe ability to present your work clearly and confidently in front of internal stakeholders;\nHands-on working is needed, be ready to jump in with the highest level of design quality.\n\nRequirements\n\nStrong conceptual skills with a passion for big ideas;\nHungry to produce high quality work;\nSolid technical art direction with a keen eye for detail;\nBe interested in popular culture, social media and be up to date with current advertising trends and techniques;\nExcellent command of English (native level would be an advantage) and Cantonese is required, both spoken and written;\nMinimum 5 years of art directing and design work experience;\nAbility to shift priorities and navigate between competing deadlines while managing multiple projects of varying sizes, topic and type;\nInnovative, energetic and proactive, proven self-starter and a strong team player;\nExceptional art/design and verbal communication skills, presentation skills and organisational skills;\nRegional experience is an advantage.\n\nWe offer the right candidate attractive remuneration package and outstanding prospects for career advancement and development.\u00a0 The right candidate will progress career in a forward thinking and dynamic business with exciting growth plans.\u00a0 If you are qualified and interested, please send your full resume with current & expected salary and availability by clicking \"APPLY \".\n\nAll information collected will be treated as strictly confidential and used for recruitment purposes only. (Only shortlisted candidates will be notified)", "employment_types": ["Full Time", "Permanent"], "selling_points": [], "locations": ["Shatin Area"], "categories": ["Design", "Graphics", "Multi-media", "Marketing / Public Relations", "Marketing - General / Support"], "post_time": "2022-01-14T03:04:02Z", "salary": {"currency": null, "max": null, "min": null, "period": "monthly", "term": null}, "salary_visible": false, "title_keywords": ["senior graphic designer", "graphic designer"], "responsibilities": ["ideas", "key visuals", "quality", "design", "develop", "visual"], "requirements": {"degrees": [], "majors": [], "languages": ["cantonese", "english"], "language_level": ["native", "excellent", "advantage"], "hard_skills": [], "soft_skills": ["communication skills", "proactive", "passion for", "keen", "interested in", "energetic", "presentation skills", "organisational skills", "eye for detail", "team player", "innovative"], "languages_combined": [{"language": "cantonese", "language_level": ["native", "excellent", "advantage"]}, {"language": "english", "language_level": ["native", "excellent", "advantage"]}]}, "experience_required": {"duration": ["minimum 5 years"], "field": ["design"]}}, {"job_id": "100003009045705", "location_code": "hk", "company": "Humansa", "job_title": "Multimedia Designer", "description": "LUSH\u00a0Fresh Handmade Cosmetics\u00a0Needs\u00a0YOU!\u00a0\u00a0LUSH is an international retailer of fresh handmade cosmetics that is known worldwide for changing the face, body and soul of the cosmetics industry. Our unique bath and beauty products, amazing skin and hair care, personalized customer service, environmental activism and fun and unique atmosphere make LUSH a truly unique and inspirational place to work.\n\nDRIVE SALES, TAKE OPPORTUNITIES, DEVELOP TEAMS\n\nWe are looking for a\u00a0Design Specialist, based in Hong Kong, to join the company and work with our brand communications team. If you\u2019re ambitious with a desire to succeed in a fast-paced, exciting environment then that\u2019ll help too!\u00a0\n\n\nKey responsibilities and duties\n\n\nCreative\n\nActively contributes creative ideas and briefs for all branded platforms.\nLead and drive a range of creative and branding projects together with the brand team, including PR and event, content, ethical campaigns, and marketing activities. Develop and execute creative concepts across print and video etc.\nWork closely with retail, digital, and brand teams to define the best way to communicate brand messages and content.\nLead the monthly retail shop window projects, creating impactful artwork that can attract attention, drive footfall into our stores and help develop a meaningful customer journey inside the store.\nPitch the creative brief for each design project effectively and take on feedback to refine the project scope.\u00a0\u00a0\nContribute to the review and evaluation of each design project and bring insight and learnings to the team.\u00a0\nBasic understanding of Lush Visual Merchandising Guidelines and the ability to contribute to store and pop-up displays.\nMarketing\n\nManage the Lush Times and any branded publication projects.\nDevelop and execute creative directions for marketing communications projects. Lead development of designs.\u00a0\nContribute ideas for retail marketing design and review the impact of these design works.\nTo work closely with the multimedia designer on any crossover projects for the brand.\nBrand Support\n\nWork closely with the global and regional designer to develop, update and manage visual/style guidelines for brand consistency.\nManage the budget of design discipline and contribute to the whole brand communications budget\u00a0\u00a0\nTo support the company on all design elements, including quotation, negotiation with vendors, budget, production for the internal and external company events, activities and projects.\u00a0\nTo work on any ad-hoc projects required by the senior management.\n\nTo be successful in this role, you will be expected to have the following attributes\n\nRequirement\u00a0\n\nDegree/Higher Diploma holder in Graphic/ Web Design/ Multimedia Design or related discipline\nFamiliar with Photoshop, Adobe Acrobat, Illustrator and Premiere Pro\nWell organized, mature, highly responsible and independent\nGood communication skills\nCreative mind with the ability to reflect on projects from both a practical and financial viewpoint.\nExcellent writing skills in both English & Chinese.\nMinimum 5 years of design work experience preferred.\nPortfolio link should be provided in the resume.\u00a0\u00a0\nSkills\nStrong communication and interpersonal skills\nBeing resilient at work\nSolutions focused mindset\nEffective time management\nQuick to adapt to new situations and directions\nBeing responsible and detail-minded\nExcellent feedback and coaching skills.\u00a0Able to take on and use developmental feedback\nConfidence in handling difficult conversations\nTreat all colleagues as equals and value all opinions\nProfessional performance management\nExcellent self discipline\nWhat we offer\n\n5-day per week\nA fun and dynamic place to work\nOpportunities to develop\nComprehensive training\nCompetitive salary\nMedical insurance coverage\n\nDoes this sound like you? Please apply by submitting a CV and covering letter to us.\n", "employment_types": ["Full Time", "Permanent"], "selling_points": ["Solid 6-8 years of experience in multimedia", "Creative with good art sense", "Experience in copywriting/editing is a plus"], "locations": ["Lai Chi Kok"], "categories": ["Design", "Graphics", "Multi-media", "Marketing / Public Relations", "Public Relations - Copy-writing"], "post_time": "2022-01-13T08:24:22Z", "salary": {"currency": null, "max": null, "min": null, "period": "monthly", "term": null}, "salary_visible": false, "title_keywords": ["multimedia designer"], "responsibilities": ["creative ideas", "merchandising guidelines", "ideas", "guidelines", "review", "teams", "budget", "design", "develop", "quotation", "visual", "evaluation", "brand consistency", "ad-hoc projects", "publication", "senior management"], "requirements": {"degrees": ["degree", "higher diploma holder"], "majors": ["multimedia design", "web design"], "languages": ["english", "chinese"], "language_level": ["excellent"], "hard_skills": ["web design", "illustrator", "writing skills", "multimedia", "premiere pro", "adobe acrobat", "photoshop"], "soft_skills": ["detail-minded", "communication skills", "confidence", "independent", "responsible", "focused", "well organized", "mature", "writing skills", "time management", "communication and interpersonal skills", "creative"], "languages_combined": [{"language": "english", "language_level": ["excellent"]}, {"language": "chinese", "language_level": ["excellent"]}]}, "experience_required": {"duration": ["minimum 5 years"], "field": ["design"]}}, {"job_id": "100003009050418", "location_code": "hk", "company": "Kingsmen Hong Kong Ltd", "job_title": "3D Designer \u2013 Multidisciplinary Design - Creative & Design", "description": "Responsibilities:\n\nWork for marketing team to initiate creative concepts and maintain brand consistency across all channels\nExecute full spectrum of multimedia design, including but not limited to photo shooting and retouching, video editing and production, as well as graphic design for website, social media (FB, IG, LinkedIn, WeChat etc.), e-mail marketing and printed materials\nLayout design and artwork production of marketing materials to support brand/promotion campaigns\nContent development and post design for social media platform\nPerform ad-hoc tasks as assigned\n\n\u00a0Requirements:\n\nDegree or diploma in Multimedia / Graphic Design / Creative Media or related disciplines\nMinimum of 6-8 years\u2019 relevant working experience in creative agency / digital marketing/ in-house marketing team\nProficient in Adobe Creative Suite, including Premiere Pro, After Effects, Animate, Illustrator, InDesign and Photoshop\nSkilled in various social media platforms (e.g. Facebook, Instagram, LinkedIn, WeChat)\nExperienced in video production, motion graphic and photography\nAn excellent team player with good communication skills and the ability to multitask\nCreative and pro-active, responsible, well-organized, detail-oriented with a strong sense of responsibility and team work\nKnowledge in HTML5, CSS, Action script is a plus\nExperience in copywriting/editing in English & Chinese is a plus\nWe offer an attractive remuneration package and excellent career prospects to the right candidate. Please send full resume including the current, expected salary, the portfolio with video works, photography, design layouts and finished marketing materials\u00a0and the contact information by clicking \"Apply Now\"\n\n\n\n(The personal data provided will be used for recruitment purpose only. \u00a0All data of unsuccessful applications will be destroyed.)", "employment_types": ["Full Time", "Permanent"], "selling_points": [], "locations": ["Shatin Area"], "categories": ["Design", "Multi-media", "Others"], "post_time": "2022-01-14T10:22:17Z", "salary": {"currency": null, "max": null, "min": null, "period": "monthly", "term": null}, "salary_visible": false, "title_keywords": ["creative", "designer"], "responsibilities": ["multimedia design", "retouching", "social media", "graphic design", "artwork production", "layout design", "ad-hoc tasks", "website", "design", "video editing", "maintain", "promotion campaigns", "marketing materials", "brand consistency"], "requirements": {"degrees": ["diploma", "degree"], "majors": ["related disciplines", "graphic design", "creative media"], "languages": ["english", "chinese"], "language_level": [], "hard_skills": ["plus", "animate", "css", "indesign", "illustrator", "wechat", "after effects", "premiere pro", "multimedia", "facebook", "adobe creative suite", "photoshop"], "soft_skills": ["communication skills", "responsible", "sense of responsibility", "well-organized", "detail-oriented", "team player", "pro-active", "ability to multitask", "creative"], "languages_combined": [{"language": "english", "language_level": []}, {"language": "chinese", "language_level": []}]}, "experience_required": {"duration": ["minimum of 6-8 years"], "field": ["agency", "relevant working experience", "marketing", "digital marketing", "copywriting", "editing", "team"]}}, {"job_id": "100003009040331", "location_code": "hk", "company": "I-Skincare Company Limited", "job_title": "Graphic Designer (Tsim Sha Tsui / 5 Days work)", "description": "Responsibilities:\nTo co-ordinate design requirements and work with team members, from creative development to final production.\nDesign & prepare rendering for presentation, artwork and technical drawing for production.\nSupervise on-site set construction if needed.\nRequirements:\nPolytechnic and Design Institute graduated or equivalent.\n3 years\u2019 experience in the related field.\nProficient in PC skills, AutoCAD, 3D Max, Sketchup, Vray, Photoshop, Illustrator.\nCreative mind and show evidence by work portfolio.\nIndependent, responsible, self-motivated and can work under pressure.\nKnowledge in production and provide artwork, shop drawing for build construction.\nSkills in multi-media software is an advantage.\nGood command of written and spoken English, Chinese.\n* Email your portfolio (either online or in PDF format) to us will be considered. *\nWe offer 5-days work and medical benefits to the right candidate. Interest party, please send your application with full resume, experience, expected salary and earliest date available to The HR & Admin Department via \"Apply Now\"\n\nWelcome to our website www.kingsmen-gc.com . Only shortlisted candidate will be notified for interview.", "employment_types": ["Full Time", "Permanent", "Contract"], "selling_points": ["Visual creation and video editing", "Min. 3 years of design experience", "Proficient in Illustratior and Photoshop"], "locations": ["Tsim Sha Tsui"], "categories": ["Design", "Graphics", "Multi-media", "Web Designer"], "post_time": "2022-01-12T02:18:27Z", "salary": {"currency": null, "max": null, "min": null, "period": "monthly", "term": null}, "salary_visible": false, "title_keywords": ["graphic designer"], "responsibilities": ["design", "technical drawing"], "requirements": {"degrees": [], "majors": [], "languages": ["english", "chinese"], "language_level": ["good command"], "hard_skills": ["illustrator", "autocad", "photoshop", "max", "pc skills", "sketchup"], "soft_skills": ["self-motivated", "independent", "responsible", "creative", "work under pressure"], "languages_combined": [{"language": "english", "language_level": ["good command"]}, {"language": "chinese", "language_level": ["good command"]}]}, "experience_required": {"duration": ["3 years"], "field": ["related"]}}, {"job_id": "100003009050639", "location_code": "hk", "company": "Sa Sa Cosmetic Co Ltd", "job_title": "Senior Graphic Designer", "description": "Job Responsibilities\n\nl\u00a0\u00a0 Responsible for creating, develop creative concepts to design, artwork and the final output to meet business objectives\n\nl\u00a0\u00a0 Create awesome and interesting illustration work for the characters\n\nl\u00a0\u00a0 Handle content creation, design and production assets for the character brand, including brand style guides and other design materials across Omni channels\n\nl\u00a0\u00a0 Support the team in other ad-hoc activities as required and necessary\n\nRequirements:\n\nl\u00a0\u00a0 Currently enrolled in a bachelor\u2019s degree, Higher Diploma or equivalent in Visual Arts / Design / Creative or other related disciplines, must be enrolled in an accredited university/college program to receive credit\n\nl\u00a0\u00a0 Creative and enthusiastic, strong in storytelling, visual communication and creating engaging experiences\n\nl\u00a0\u00a0 Strong sense on Graphic, Layout, Coloring and usability on graphics and images with inputting creative concepts and designs\n\nl\u00a0\u00a0 Proficient in design software such as Photoshop / Illustrator / Procreate\n\nl\u00a0\u00a0 Good command of English and Chinese\n\nl\u00a0\u00a0 Shows initiative, drive and a commitment to innovation\n\nl\u00a0\u00a0 Strong sense of responsibility, self-motivated and able to work independently as well as a good team player\n\nWe offer attractive remuneration and fringe benefits to the right candidates. Please send us the application by clicking the \"Apply Now\" button, together with a detailed resume,\u00a0current and expected salary.\n\n\u00a0We will only notify suitable candidates for an interview. Thank you!\n\nWe are an equal opportunity employer and welcome applications from all qualified candidates. Personal data provided by job applicants will be used only for recruitment purpose and will be kept strictly confidential. Information of unsuccessful candidates will be properly disposed within 6 months.", "employment_types": ["Full Time", "Permanent"], "selling_points": ["Design corporate online & offline mktg materials", "Dip. or above in Graphic Design/ Arts/ Visual Arts", "3 yr rel. exp. preferred in beauty industry"], "locations": ["Siu Sai Wan"], "categories": ["Design", "Graphics", "Industrial / Product", "Multi-media"], "post_time": "2022-01-14T11:03:58Z", "salary": {"currency": null, "max": null, "min": null, "period": null, "term": null}, "salary_visible": false, "title_keywords": ["senior graphic designer"], "responsibilities": ["ad-hoc", "develop creative concepts", "support the team", "design"], "requirements": {"degrees": ["diploma", "degree", "bachelor"], "majors": ["related disciplines", "design"], "languages": ["english", "chinese"], "language_level": ["good command"], "hard_skills": ["graphics", "visual communication", "illustrator", "photoshop"], "soft_skills": ["self-motivated", "work independently", "good team player", "sense of responsibility", "communication", "enthusiastic", "creative", "initiative"], "languages_combined": [{"language": "english", "language_level": ["good command"]}, {"language": "chinese", "language_level": ["good command"]}]}, "experience_required": {"duration": [], "field": []}}, {"job_id": "100003009046052", "location_code": "hk", "company": "Adhoc Fun Limited", "job_title": "Graphic Designer (Internship)", "description": "Passionate in graphic design and eager to take part in innovative projects for various industries?\nWe are looking for a graphic designer to join our small yet dynamic team. We welcome anyone with a passion for visual communication, digital design and the marketing field. You will be able to work in a flexible, fast-paced and creative environment.\n\nWHAT WE ARE LOOKING FOR:\n\n1. CHARACTER:\n\nHungry for challenges and achievements\nCreative with advanced problem-solving skills\nEager to explore new things\nProactive and able to work as a team player\n\n2. EDUCATION AND SKILLS:\n\nUniversity graduates with 1-2 years of relevant experience\u00a0in Design (fresh graduate with outstanding potential will also be considered)\nStrong sense in layout, typographic and graphic design\nExperience in \u00a0UX/UI design for web portal, e-commerce or mobile application will be an advantage\nHighly proficient in Adobe Creative Suite, including Photoshop, Illustrator, InDesign, XD, etc.\n\u00a0Language\nProficiency in Chinese and English writing and reading; Mandarin will be an advantage\nOrganization and multitasking\nAbility to organize and manage multiple projects simultaneously in a fast-paced environment\n\nWHAT WE OFFER:\n\nOpportunities to be involved in product branding and marketing designs\nExciting challenges and engaging projects including graphics for social media, logo design, UI/UX design, and etc.\nCreative work environment with little office hierarchy\nMarket-competitive rate\nA chance to work with a team of top notch web experts\n\nWHAT WHAT YOU WILL DO:\n\n30%:\u00a0Collaborate with the Development and Marketing Team to execute design solutions (web/print/social media) that comply with project specifications, brand identity and strategic marketing goals\n25%:\u00a0Visualize concepts into rough drafts as the foundation for future execution, establish standards for style, aesthetics and typeface; design preliminary layout.\n25%:\u00a0Contribute to brainstorming workshops in projects and product innovation\n20%:\u00a0Participate in other innovative projects and learning opportunities under the group\u2019s investments", "employment_types": ["Part Time", "Internship", "Freelance"], "selling_points": ["Interesting illustration work for the characters", "Currently enrolled in a bachelor\u2019s degree", "Student Internship, Freelance, work form home"], "locations": ["Kwun Tong"], "categories": ["Design", "Graphics", "Multi-media", "Web Designer"], "post_time": "2022-01-13T09:30:18Z", "salary": {"currency": null, "max": null, "min": null, "period": "hourly", "term": null}, "salary_visible": false, "title_keywords": ["graphic designer", "internship"], "responsibilities": ["graphic design", "manage multiple projects", "design", "communication", "visual", "ui"], "requirements": {"degrees": ["fresh graduate"], "majors": ["design"], "languages": ["english", "chinese", "mandarin"], "language_level": ["advantage", "proficiency"], "hard_skills": ["small", "web", "e-commerce", "indesign", "illustrator", "mobile", "visual communication", "dynamic", "problem-solving skills", "adobe creative suite", "photoshop"], "soft_skills": ["passionate", "flexible", "proactive", "manage multiple projects simultaneously", "creative", "advanced", "passion for", "work as a team", "fast-paced environment", "communication", "dynamic", "problem-solving skills", "innovative"], "languages_combined": [{"language": "english", "language_level": ["proficiency"]}, {"language": "chinese", "language_level": ["proficiency"]}, {"language": "mandarin", "language_level": ["advantage"]}]}, "experience_required": {"duration": ["1-2 years"], "field": ["relevant experience", "design", "e-commerce"]}}, {"job_id": "100003009043627", "location_code": "hk", "company": "Hip Shing Hong (Holdings) Company Limited", "job_title": "CREATIVE & MULTIMEDIA DESIGNER", "description": "Benefits:\n\n5 days Work + Bank Holidays\nFull Medical Coverage\nPerformance Bonus\nBirthday Leave, Wedding Leave\nTraining Subsidy\nOvertime Meal and Transportation allowance\nProfessional Training + Good Career Prospect in the Growing Digital Marketing Industry\n\nResponsibilities include:\n\nResponsible for artworks and design for digital marketing including banner display, video, campaign and website;\nInvolve in pitching for new projects;\nWorking with our online marketing team, implement and roll out online marketing strategy with the use of Facebook and other social media platforms.\n\nRequirements :\n\nHigher diploma or above in Graphic/ Multimedia Design or related disciplines;\nPossessing 2 years of working experience in Graphic Design, Advertising or Website Design ; experience in digital marketing agencies is preferred.\nPossessing experience in pitching;\nUnderstanding on branding / art direction is a plus;\nGood team player with effective interpersonal and communication skills;\nAble to work with tight deadlines and under pressure;\nInternet savvy, keen interest in internet marketing and social media.\nCandidate with more experience may be considered for Senior role.\n\nTo Apply:\n\nFor more information about You Find Ltd., please visit www.youfind.hk.\nWe offer attractive package to the right candidate. Interested parties please send your application together with Current Salary, Expected Salary & Availability by clicking \"Apply Now\".\nAll information received will be used for recruitment purpose only and will be kept in strict confidential.\n\nYouFind is an Equal Opportunity Employer and prohibits discrimination and harassment of any kind. All employment decisions at YouFind are based on business needs, job requirements and individual qualifications, without regard to race; family status; gender; disability status or any other status protected by the laws or regulations in Hong Kong.", "employment_types": ["Full Time", "Permanent"], "selling_points": ["Conceive, craft and execute digital ideas", "Handle graphic design in various digital platforms", "2 years' relevant working experience in Multimedia"], "locations": ["Central"], "categories": ["Media & Advertising", "Creative / Design", "Design", "Multi-media", "Marketing / Public Relations", "Digital Marketing"], "post_time": "2022-01-13T01:06:38Z", "salary": {"currency": null, "max": null, "min": null, "period": "monthly", "term": null}, "salary_visible": false, "title_keywords": ["creative", "multimedia designer"], "responsibilities": [], "requirements": {"degrees": [], "majors": [], "languages": [], "language_level": [], "hard_skills": [], "soft_skills": [], "languages_combined": []}, "experience_required": {"duration": [], "field": []}}, {"job_id": "100003009046604", "location_code": "hk", "company": "RollAngle", "job_title": "Graphic Designer", "description": "Responsibilities:\u00a0\n\nDevelop creative concepts and prepare marketing materials including but not limited to publication, advertising, trade show booths and shop displays\nResponsible for all kinds of graphic and motion graphic design projects, artwork production and graphic details preparation\nArt directing on photos/video shooting\nKeep track of design trends\n\nRequirements:\u00a0\n\nDegree/Diploma in graphic design or relevant discipline\nAt least 4 years of\u00a0experience in graphic and motion graphic design, preferably gained in Retail/ F&B industry\nFamiliar with Illustrator, Photoshop, Premiere, After Effects\nGood team player, creative, and passionate in graphic and motion graphic design\nAble to work under pressure with tight deadlines\nCandidate with more experience will be considered as Senior Graphic Designer/ Senior Motion Graphic Designer\nImmediate availability is highly preferred\n\nWe Offer:\n\n5-day work week\nCompetitive Salary Package\n13 months' Guaranteed Salary\nPerformance Incentives\nGroup Medical Scheme\nBirthday Leave\nFree Lunch\nEnergetic & Dynamic Culture\n\nInterested parties, please send your detailed resume, availability, present and expected salary to Human Resources Department by clicking \u201cApply Now\u201d.\n\nPersonal data collected will be used for recruitment purpose only.", "employment_types": ["Full Time", "Permanent"], "selling_points": ["Design > Graphics", "Design > Multi-media", "Design > Web Designer"], "locations": ["Kwun Tong"], "categories": ["Design", "Graphics", "Multi-media", "Web Designer"], "post_time": "2022-01-13T16:19:15Z", "salary": {"currency": null, "max": null, "min": null, "period": "monthly", "term": null}, "salary_visible": false, "title_keywords": ["graphic designer"], "responsibilities": ["graphic details preparation", "advertising", "keep track of design trends", "shop displays", "motion graphic design projects", "artwork production", "trade show booths", "video shooting", "art directing", "develop creative concepts", "publication", "prepare marketing materials"], "requirements": {"degrees": ["diploma", "degree"], "majors": ["graphic design"], "languages": [], "language_level": [], "hard_skills": ["after effects", "illustrator", "premiere", "photoshop"], "soft_skills": ["passionate", "good team player", "creative", "work under pressure"], "languages_combined": []}, "experience_required": {"duration": ["at least 4 years"], "field": ["designer", "design", "f&b", "graphic", "retail", "motion graphic"]}}, {"job_id": "100003009046281", "location_code": "hk", "company": "AMO Creative Limited", "job_title": "(Senior) Graphic Designer / Motion Graphic Designer", "description": "Job Description\n\n- Certificate / Diploma in Multimedia Design with 1-2 year multimedia experience\n\n- Proficiency in Photoshop, Illustrator, After Effects, MAYA, 3DMax & AutoCAD\n\n- To handle multimedia projects [text, sound, images, 3D-modelling, animation & rendering]\n\n- Creative, strong sense in multimedia design, self-motivated and self-disciplined", "employment_types": ["Full Time", "Permanent"], "selling_points": ["Graphic Design / Motion Graphic", "Artwork Production", "Illustrator, Photoshop"], "locations": ["Lai Chi Kok"], "categories": ["Design", "Graphics", "Multi-media", "Others"], "post_time": "2022-01-13T10:14:32Z", "salary": {"currency": null, "max": null, "min": null, "period": "monthly", "term": null}, "salary_visible": false, "title_keywords": ["graphic designer"], "responsibilities": ["multimedia design", "animation"], "requirements": {"degrees": ["certificate", "diploma"], "majors": ["multimedia design"], "languages": [], "language_level": [], "hard_skills": ["maya", "illustrator", "after effects", "autocad", "3dmax", "multimedia", "photoshop"], "soft_skills": ["self-motivated", "creative"], "languages_combined": []}, "experience_required": {"duration": ["1-2 year"], "field": ["design"]}}, {"job_id": "100003009044460", "location_code": "hk", "company": "\u59ff\u66fc\u570b\u969b\u6709\u9650\u516c\u53f8", "job_title": "Graphic Designer / Senior Graphic Designer", "description": "Job Description\n\nDeveloping 2D graphics for products\nSupport the graphic design for social media\nHandle the development of the new project\nRequirements:\n\nMinimum 2-year experience in Graphic Designing\nExperienced in designing licensed product, IP product or animation related product is an advantage\nHave understanding in animation\nGraphic design experience in one of the below areas is an advantage:\nSundries\nDecoration\nSouvenirs\nDIY Items / Toys\nIP products\nElectronic items / Lighting\nSporting items\nPaper & gift items\nKnowledge in video editing and photography is also an advantage\nCreative and innovative, quality work with detail-minded and meet tight deadline\nKnowledgeable in production process from artwork to production is preferred", "employment_types": ["Full Time", "Permanent"], "selling_points": ["Minimum 2-year experience in Graphic Designing", "Fast growing company with room for creativity", "Handle the development of the new project"], "locations": ["Mong Kok"], "categories": ["Design", "Graphics", "Industrial / Product", "Multi-media"], "post_time": "2022-01-13T04:09:54Z", "salary": {"currency": null, "max": null, "min": null, "period": "monthly", "term": null}, "salary_visible": false, "title_keywords": ["senior graphic designer", "graphic designer"], "responsibilities": ["graphics", "graphic design", "social media", "developing"], "requirements": {"degrees": [], "majors": [], "languages": [], "language_level": [], "hard_skills": ["video editing", "ip"], "soft_skills": ["detail-minded", "creative", "meet tight deadline", "innovative"], "languages_combined": []}, "experience_required": {"duration": ["minimum 2-year"], "field": ["graphic design", "graphic"]}}, {"job_id": "100003009043932", "location_code": "hk", "company": "Fimmick Limited", "job_title": "Senior Graphic Designer / Graphic Designer", "description": "HBX (previously known as HYPEBEAST Store) commenced business in May 2012, is a one-stop news source for internet-savvy fashion enthusiasts and cultural tastemakers. HBX is the global e-commerce platform that targets male and female online shoppers between the age of 18 and 35, and primarily sells third-party branded clothing, shoes and accessories to customers.\n\nResponsibilities:\n\nResponsible for product shot retouching.\nResponsible for model shot retouching.\nProduce photo retouching, colour correction and composition to company standard.\nEnsure the quality and style is within company standard and expectation.\nResponsible for other ad hoc duties as assigned.\nRequirements:\n\nExperienced in Product Photo Retouching.\nExcellent with Adobe Creative Suite (Photoshop).\nUnderstand Photoshop action sets, image resolution, colour space and image file formats.\nProficient in MAC operations.\nBasic skill in Fashion and Model Photography.\nGood spoken command of Cantonese and English.\nStrong team player with ability to work independently.\nAbility to multitask, and perform well under pressure to meet deadlines in a fast-paced environment.\nGood attitude and willingness to learn.\nIf you think you\u2019ve got what it takes, please provide your CV, expected salary and a portfolio with relevant examples for retail/fashion.\n\nThis position is based and located in Hong Kong. Candidate must be eligible to work in Hong Kong.\n\nPersonal data collected is for recruitment purpose only.", "employment_types": ["Full Time", "Permanent"], "selling_points": ["Execute top-quality design", "2+ years interactive design experience", "Develop digital storyboards and animation"], "locations": ["Kwun Tong"], "categories": ["Media & Advertising", "Creative / Design", "Design", "Graphics", "Multi-media"], "post_time": "2022-01-13T02:30:11Z", "salary": {"currency": null, "max": null, "min": null, "period": "monthly", "term": null}, "salary_visible": false, "title_keywords": ["senior graphic designer", "graphic designer"], "responsibilities": ["ad hoc duties", "retouching", "photo retouching", "quality"], "requirements": {"degrees": [], "majors": [], "languages": ["cantonese", "english"], "language_level": ["good"], "hard_skills": ["basic", "adobe creative suite", "photoshop"], "soft_skills": ["work independently", "fast-paced environment", "team player", "ability to multitask", "creative", "meet deadlines", "perform well under pressure"], "languages_combined": [{"language": "cantonese", "language_level": ["good"]}, {"language": "english", "language_level": ["good"]}]}, "experience_required": {"duration": [], "field": []}}, {"job_id": "100003009050149", "location_code": "hk", "company": "Hypebeast Hong Kong Limited", "job_title": "E-commerce Photo Retoucher", "description": "We are inviting high caliber to join us for an exciting career opportunity and be part of a company that believes in innovation and sustainability.\n\nResponsibilities:\n\n\n\nMultimedia production\u00a0\u2013 Develop and execute visual display such as\u00a0video, photos, graphic designs, presentation slides, webpage layouts etc.; assist in setting design directions and storyboards\nSocial media \u2013\u00a0Manage Group-level corporate social media accounts including but not limited to Facebook, Instagram, LinkedIn and YouTube; monitor channel performance; assist in content planning to drive engagement\nPR support\u00a0\u2013 Support routine media monitoring; maintain newsroom content\nKnowledge management \u2013\u00a0Maintain libraries of corporate materials and information to uphold good housekeeping and promote productivity\n\nRequirements:\n\n\nDegree or higher diploma preferably in design, creative media, communications, Fine arts, language or related disciplines\nAt least 1 year of related working experience, candidates with more experiences will be considered as Officer, Corporate Communications\nExperience preferred in Adobe suite (Premiere Pro, Photoshop, Illustrator) or other visual editing software\nFluent in spoken English, Mandarin and Cantonese\nGood command on written English and Chinese (Simplified and Traditional)\nAble to travel for business occasionally to mainland China and southeast Asia\nKeen eyes for aesthetics and attentive to details\nStrong sense of time management and priority\n\nLearn about Esquel and its eCulture values at\u00a0www.esquel.com\n\nData collected will be used for recruitment purpose only and will be kept for 24 months.\n\nAll applications will be treated in strict confidence.", "employment_types": ["Full Time"], "selling_points": ["Rapidly expanding international e-commerce", "Creative, young and energetic team members", "Multi-cultural with harmonious working environment"], "locations": ["Tsuen Wan Area"], "categories": ["Design", "Graphics", "Multi-media"], "post_time": "2022-01-14T09:52:39Z", "salary": {"currency": null, "max": null, "min": null, "period": "monthly", "term": null}, "salary_visible": false, "title_keywords": [], "responsibilities": ["social media", "management", "housekeeping", "monitoring", "graphic designs", "monitor", "design", "develop", "planning", "maintain", "visual", "facebook", "storyboards"], "requirements": {"degrees": ["diploma", "degree"], "majors": ["creative media", "fine arts", "design", "related disciplines", "communications"], "languages": ["cantonese", "english", "chinese", "mandarin"], "language_level": ["good command", "fluent"], "hard_skills": ["illustrator", "visual editing", "adobe", "premiere pro", "photoshop"], "soft_skills": ["confidence", "creative", "attentive to details", "keen", "time management"], "languages_combined": [{"language": "cantonese", "language_level": ["fluent"]}, {"language": "english", "language_level": ["good command", "fluent"]}, {"language": "chinese", "language_level": ["good command"]}, {"language": "mandarin", "language_level": ["fluent"]}]}, "experience_required": {"duration": ["at least 1 year"], "field": ["related", "editing"]}}, {"job_id": "100003009045316", "location_code": "hk", "company": "Esquel Enterprises Limited", "job_title": "Assistant Officer / Officer, Corporate Communications", "description": "Responsibilities:\n\nWe are looking for a talented and enthusiastic Junior Motion Graphic Designer to work with our\u00a0team to produce motion graphics for video.\n\nThe ideal individual will have a creative flair, up-to-date knowledge of industry software, and a professional approach to time, costs and deadlines.\u00a0\n\nAbility to manage multiple projects simultaneously, and work well under pressure is a pre-requisite.\n\nRequirements:\n\nSelf-motivated and capable of handling projects independently from concept design to project completion\nProficient in Adobe After Effect, Photoshop, InDesign & Illustrator\nStrong communication and interpersonal skills, MUST be a team player\nDiploma in Graphic Design, Multimedia Design or equivalent\n1-2 years or above related working experiences\n\nInterested parties please send full resume with present and expected salary and work samples (video link is preferable) by clicking \u201cApply Now\u201d.\n\nAll personal data collected will be used for recruitment purpose only.", "employment_types": ["Full Time", "Permanent"], "selling_points": ["Multimedia production", "Social media & PR support", "Premiere Pro, PS, Illustrator"], "locations": ["Wan Chai"], "categories": ["Design", "Multi-media", "Marketing / Public Relations", "Marketing - Marketing Communication", "Public Relations - Copy-writing"], "post_time": "2022-01-13T07:36:25Z", "salary": {"currency": null, "max": null, "min": null, "period": "monthly", "term": null}, "salary_visible": false, "title_keywords": ["assistant officer", "officer"], "responsibilities": ["software", "manage multiple projects", "motion graphics", "motion graphic", "costs"], "requirements": {"degrees": ["diploma"], "majors": ["multimedia design", "graphic design"], "languages": [], "language_level": [], "hard_skills": ["adobe after effect", "indesign", "illustrator", "multimedia", "photoshop"], "soft_skills": ["self-motivated", "independently", "capable", "communication and interpersonal skills", "team player"], "languages_combined": []}, "experience_required": {"duration": ["1-2 years"], "field": ["related"]}}, {"job_id": "100003009041978", "location_code": "hk", "company": "Belle Worldwide (Talent Management) Limited", "job_title": "Graphic Design (Multimedia Design)", "description": "Our client, a leading global bank, is looking for a DTP specialist.\n\nKey Responsibilities:\n\u2022 Produces a variety of marketing materials (e.g. covers, templates, newsletters, deal toy designs, invites, posters, flyers, HTML newsletters, etc.) using relevant graphic applications to an advanced level\n\u2022 Traces and produces logos, maps and illustrations\n\u2022 Creates concept and artwork for 2D and 3D tombstones (lucites)\n\u2022 Assists with the production of pitchbook materials and offers conceptual and visual solutions to enhance client materials\n\u2022 Ensures all materials produced are correctly branded as per\u00a0company\u00a0standards and advises clients on the use of the\u00a0company brand\n\u2022 Liaises directly with workflow staff and clients to determine deadlines, job instructions and design requirements\n\u2022 Completes related admin for accurate work billing and job tracking purposes\n\u2022 Assists with Intake coordination when required\n\u2022 Responsible for quality control of own work, as well as assisting colleagues with QC tasks\n\u2022 Buddies new joiners post-training\n\u2022 Contributes to best production practices through internal initiatives and programs\n\nRequirements:\n\u2022 3 years or above of admin/operational support in a corporate, service-oriented environment, ideally in a financial institution\n\u2022 Advanced knowledge of industry standard graphic design applications\u00a0\n\u2022 Advanced knowledge of Adobe Creative Suite (i.e. Illustrator, Photoshop, InDesign, Acrobat Professional)\n\u2022 Advanced knowledge of Microsoft Office (PowerPoint, Excel and Word)\n\u2022\u00a0Knowledge in Dreamweaver and Blender and external print processes is desirable\n\nQualifications:\n\u2022 Bachelor\u2019s degree or Diploma in Graphic Design with 3 years or above of relevant work experience in a corporate, service-oriented environment OR demonstrated ability to meet the job requirements through a comparable work experience\n\u2022 Must be able to provide a portfolio / samples of recent work\n\nInterested parties please email your resume (MS Word format) to\u00a0yan.chan@manpowergrc.hk\u00a0or clicking \"Apply Now\".", "employment_types": ["Full Time", "Permanent"], "selling_points": ["develop creative concepts, graphic and artworks", "multimedia design (video, motion graphic)", "2 years\u2019 relevant working experience"], "locations": ["Kwai Hing"], "categories": ["Design", "Graphics", "Multi-media", "Web Designer"], "post_time": "2022-01-12T04:58:56Z", "salary": {"currency": null, "max": null, "min": null, "period": "monthly", "term": null}, "salary_visible": false, "title_keywords": [], "responsibilities": ["design", "coordination", "visual", "marketing materials", "quality control", "tracking"], "requirements": {"degrees": ["diploma", "degree", "bachelor"], "majors": ["graphic design"], "languages": [], "language_level": [], "hard_skills": ["excel", "acrobat", "microsoft office", "indesign", "illustrator", "powerpoint", "word", "dreamweaver", "adobe creative suite", "photoshop"], "soft_skills": ["service-oriented", "creative", "advanced"], "languages_combined": []}, "experience_required": {"duration": ["3 years"], "field": ["graphic design"]}}, {"job_id": "100003009049989", "location_code": "hk", "company": "Manpower Services (Hong Kong) Limited", "job_title": "DTP Specialist (27.5K)", "description": "Big Leap Global - Your Trusted Partner in Blockchain APP Development\n\nIf the internet revolutionized the world in the 2000s, social media changed the game in 2010s, then in 2020s, blockchain and internet will be the winning factor for those adopt it to eliminate those do not.\u00a0\n\nWe are a blockchain and game mobile application firm with user-oriented mindsets.\n\nWith our expertise in UI/UX design, blockchain software development and marketing & user penetration, we provide solutions to CEO, CTO or product managers who are looking to outsource their blockchain development. We help companies not just to design and build great social media and blockchain apps but we help them to take it to the world!\n\nIf you see the future of technology like we do, and you are determined to fast track your career by entering one of the most rapidly growing industries in the 2020s, come join us.\u00a0\n\nWe are sure you can design something even nicer than a Shiba Inu on a coin. How about Corgi?\n\n\n\n\n\nHow you can create the next big thing:\n\nYou will be reporting to the senior designer and will be contributing your highly usable and intuitive interface creation for our mobile app and mobile game projects. Your design shall be easy for users to digest and trigger users to share the product with their friends.\u00a0\n\n\n\nDevelop intuitive, usable, and engaging interactions and visual designs for mobile.\nCreate wireframes, page flows, mockup / interactive prototypes across mobile and desktop to communicate interaction and design ideas\nCollaborate with cross-functional teams (executive suite, marketing, engineering, operation) throughout the design process\nParticipate in the full-cycle development process from definition, through design, build, test, release, and maintenance.\nResearch and track advancements in latest mobile application design patterns in the blockchain field and the several key competitors of each project.\u00a0\n\nWhat makes you a game changer:\n\n\n\n2-years or above solid experience in designing UI of mobile applications and mobile web pages.\u00a0\nDiploma or above in Web Design / Graphic / Multimedia design or related discipline\nExperience working with blockchain startup will be an advantage\nExperience in unity\u00a0\nIntermediate to knowledge of relevant technologies and tools (e.g., HTML/CSS,Photoshop, Illustrator)\nAble to work under pressure with tight deadlines with a strong sense of responsibility\nWhat\u2019s next?\n\n\nTo facilitate the recruitment process, remember to insert the followings in your resume,\u00a0\n\n\nLinks to your design portfolio\nYour current salary and expected salary\nYour availability for reporting duties\nThis will help us to choose your profile easier among the numerous applications.\u00a0\n", "employment_types": ["Contract"], "selling_points": ["Marketing materials", "Graphic design", "Banking industry"], "locations": ["Central"], "categories": ["Media & Advertising", "Creative / Design", "Design", "Graphics", "Multi-media"], "post_time": "2022-01-14T09:36:06Z", "salary": {"currency": null, "max": null, "min": null, "period": "monthly", "term": null}, "salary_visible": false, "title_keywords": ["specialist"], "responsibilities": ["collaborate with", "social media", "reporting", "multimedia design", "mobile app", "software", "ideas", "maintenance", "designing", "provide solutions", "design", "develop", "visual", "recruitment process", "ui", "cross-functional teams", "work under pressure"], "requirements": {"degrees": ["diploma or above"], "majors": ["multimedia design", "web design"], "languages": [], "language_level": [], "hard_skills": ["blockchain", "web design", "maintenance", "illustrator", "web pages", "html", "mobile", "factor", "multimedia", "css", "unity", "photoshop"], "soft_skills": ["sense of responsibility", "determined", "work under pressure"], "languages_combined": []}, "experience_required": {"duration": [], "field": []}}, {"job_id": "100003009051331", "location_code": "hk", "company": "Big Leap Global Limited", "job_title": "APP UI/UX Designer", "description": "\u517c\u8077\u9867\u5ba2\u670d\u52d9\u54e1Part Time Customer Service Representative (\u89c0\u5858\uff0c\u534a\u65e5)\n\n\n\n\u516c\u53f8\u7c21\u4ecb\nJollymap\u5f9e\u6559\u6388\u8ab2\u7a0b\u5230\u5f9e\u4e8b\u92b7\u552e\u55ae\u8eca\u3001\u5e73\u8861\u8eca\u3001\u6ed1\u677f\u8eca\u5230\u53ca\u4fdd\u8b77\u88dd\u5099\uff0c\u6211\u5011\u53ea\u6709\u4e00\u500b\u4f7f\u547d\uff0c\u5c31\u662f\u300c\u4e00\u8d77\u63a2\u904a\u6210\u5c31\u5feb\u6a02\u7ae5\u5e74!\u300d\u73fe\u6642\u901a\u904e\u4f54\u5730\u8d85\u904e1\u842c\u5c3a\u7684\u5169\u9593\u9580\u5e02\u53ca\u6559\u5b78\u4e2d\u5fc3\uff0c\u5df2\u670d\u52d9\u8d853\u842c\u4f4d\u5c0f\u670b\u53cb\u3002Jollymap\u88abInside Retail Asia\u9078\u70ba2017\u5e74\u6700\u5275\u65b0\u96f6\u552e\u696d\u8005\u4e4b\u4e00\uff0c\u73fe\u5728\u6b63\u62db\u52df\u5fd7\u540c\u9053\u5408\u7684\u4eba\u52a0\u5165\u6211\u5011\u7684\u5927\u5bb6\u5ead\u3002\u4f60\u5f97\u5230\u7684\uff0c\u4e0d\u55ae\u53ea\u662f\u85aa\u916c\uff0c\u4e5f\u662f\u770b\u8457\u4e00\u5f35\u5f35\u7b11\u81c9\u7684\u90a3\u4efd\u6210\u529f\u611f\u3002\n\n\u516c\u53f8\u596c\u9805\u53ca\u8cc7\u683c\nTop 50 Most innovative Retailer in Hong Kong 2017 (Inside Retail Asia)\n\u5546\u754c\u5c55\u95dc\u61f7\u4f01\u696d (Caring Company) 2017-2021\n\u9999\u6e2f\u96f6\u552e\u696d\u5354\u6703\u6703\u54e1\n\nwww.jollymap.com\n\n\nResponsibilities:\n\nOperations and Marketing support of e-shop and physical stores and training center\nPhoto and video taking and editing\nBasic graphic design (use Canva or AI)\nExposure and assist in full range of online marketing such as SEO, SEM, social media (Facebook, YouTube &IG) , email marketing and content marketing.\nParticipate in event and activities management\nHandle administrative task and ad hoc projects.\n\nRequirements:\n\nOutgoing personality and love outdoor activities like cycling or camping\nDesign / Media or related academic disciplines\nPassionate in e-Commerce and Online Marketing. Related experience will an advantage but not necessary\nKnowledge of graphic design, Photo editing, video editing and HTML will be an advantage\nGood follow-through, organized and proactive working attitudes\nGood command of both spoken and written English & Chinese\nWork around 8 hours per day, 2-3 days a week and may need to work on Weekend occasionally (4-5 days work during summer period)\nHourly Rate starting from $60\n\nPlease email your resume to us.\u00a0Any questions welcome to call us at 23420780.", "employment_types": ["Full Time", "Permanent"], "selling_points": ["Acquire valuable blockchain exposure", "Global projects", "Work closely within small teams"], "locations": ["Central & Western Area"], "categories": ["Design", "Multi-media", "Web Designer", "Information Technology (IT)", "UI/UX Designer"], "post_time": "2022-01-15T09:22:20Z", "salary": {"currency": null, "max": null, "min": null, "period": "monthly", "term": null}, "salary_visible": false, "title_keywords": ["ux designer"], "responsibilities": ["social media", "management", "seo", "e-shop", "operations", "graphic design", "ad hoc projects", "sem", "facebook", "editing"], "requirements": {"degrees": [], "majors": [], "languages": ["english", "chinese"], "language_level": ["good command"], "hard_skills": ["video editing", "html", "e-commerce"], "soft_skills": ["outgoing personality", "organized", "passionate", "proactive"], "languages_combined": [{"language": "english", "language_level": ["good command"]}, {"language": "chinese", "language_level": ["good command"]}]}, "experience_required": {"duration": [], "field": ["related"]}}, {"job_id": "100003009045897", "location_code": "hk", "company": "Qookia Limited", "job_title": "Junior / Senior 2D Game Artist - \u904a\u6232\u539f\u756b\u8a2d\u8a08\u5e2b", "description": "Duties:\n\nResponsible for\u00a0game graphic design including characters(\u7537\u6027\u5411\u4e8c\u6b21\u5143), items, user interface and effects\nParticipation in concept development and innovation for our games\nWork closely with art lead, game designers and programmers\n\nRequirement:\n\nDiploma or above in Media Art / Design or related disciplines\nGood skill of drawing, illustration, colors, lighting and composition\nStrong sense of game character design\nProficient in Photoshop\n1-5 years game design experience\nWith great passion for games development\nGood team player with mature working attitude\n\nBenefits:\n\n\n5-day work\nPaid birthday leave\nBirthday pocket money\nPerformance bonus\nMedical insurance\nDental subsidy\nFree snack and beverage\nFriendly working environment\n\nInterested parties please apply with the following details:\n\nResume\nExpected Salary\nEarliest Availability\nPortfolio", "employment_types": ["Full Time", "Permanent"], "selling_points": ["5-day work / Flexible working hours", "Performance bonus and medical insurance", "Joyful working environment with free snacks/drinks"], "locations": ["Kwai Fong"], "categories": ["Design", "Graphics", "Multi-media", "Others"], "post_time": "2022-01-13T09:03:06Z", "salary": {"currency": null, "max": null, "min": null, "period": "monthly", "term": null}, "salary_visible": false, "title_keywords": ["junior"], "responsibilities": ["graphic design", "user interface"], "requirements": {"degrees": ["diploma or above"], "majors": ["related disciplines", "art", "design"], "languages": [], "language_level": [], "hard_skills": ["illustration", "photoshop"], "soft_skills": ["good team player", "mature", "passion for"], "languages_combined": []}, "experience_required": {"duration": ["1-5 years"], "field": ["design"]}}, {"job_id": "100003009044469", "location_code": "hk", "company": "Cosway (HK) Limited", "job_title": "Sales & Training Executive", "description": "Responsibilities:\n\nCoordination of Sales activities such as Roadshow, Open Days, Exhibition, Product Event\nAssist in Training activities, seminars/Webinars, e.g. training program design, prepare training materials, PPT, test paper, setup of venue, equipment and control panel\nMaintain and update contents at social media platforms and corp site for business development, e.g. posts on social media, including Facebook, Instagram and YouTube\nSupport Department administration task, e.g. reporting, application, coordinating with key members and reimbursement of sales events etc.\nAny other ad hoc tasks as assigned by Supervisor\n\nRequirements:\n\nBachelor Degree in any discipline\n2 years or above related experience in Retail/Sales/FMCG/MLM Industry\nFluent in English, Cantonese, and Mandarin (spoken and written)\nProficiency in MS Excel and PowerPoint,\nKnowledge in Adobe Photoshop and illustrator is a plus\nSelf-motivated, presentation skills, good communication and interpersonal skills\nAttractive remuneration package together with a wide range of fringe benefits including 5-day week and medical coverage will be offered. Interested applicant please send full resume with your expected salary and available date by E-mail via \"Apply Now\n", "employment_types": ["Full Time"], "selling_points": [], "locations": ["Tsim Sha Tsui"], "categories": ["Admin & HR", "Clerical / Admin Staff", "Design", "Multi-media", "Media & Advertising", "Photography / Video"], "post_time": "2022-01-13T04:12:49Z", "salary": {"currency": null, "max": null, "min": null, "period": "monthly", "term": null}, "salary_visible": false, "title_keywords": ["training executive", "sales"], "responsibilities": ["sales activities", "control", "social media", "reporting", "training activities", "social media platforms", "ad hoc tasks", "design", "maintain", "coordination", "contents", "facebook", "setup", "administration"], "requirements": {"degrees": ["degree", "bachelor"], "majors": [], "languages": ["cantonese", "english", "mandarin"], "language_level": ["fluent"], "hard_skills": ["plus", "adobe photoshop", "illustrator", "powerpoint", "ms excel"], "soft_skills": ["self-motivated", "communication and interpersonal skills", "presentation skills"], "languages_combined": [{"language": "cantonese", "language_level": ["fluent"]}, {"language": "english", "language_level": ["fluent"]}, {"language": "mandarin", "language_level": ["fluent"]}]}, "experience_required": {"duration": ["2 years"], "field": ["related", "retail", "fmcg"]}}, {"job_id": "100003009037351", "location_code": "hk", "company": "Olens", "job_title": "Graphic Designer / Digital Designer - 5 days work", "description": "To cope with the rapid growth of our retail and salon business, we are looking for talent\u00a0with the following background to join our vibrant and inspiring marketing team.\n\nJob Duties:\n\nWork closely with marketing team to help translate the creative concept to visuals\nPhotos retouch, create motion video editing\nCreate graphic designs and animation for all artworks including but not limited to POSM, company website, social media platforms, EDMs, Google banner ads, eDM etc.\nIn charge of the production and ensure end products completed on schedule and high standard.\nAssist in planning and implementing marketing strategies for HK market including ATL, BTL, online & social media, CRM & PR\nAd-hoc project as assigned.\n\nRequirements:\n\nHigher diploma or university degree in Design or related disciplines.\nMinimum of 3 years\u2019 experience in graphic and / or multimedia design, experience in beauty industry is a plus.\nExperience with design software and graphics editing software, such as Illustrator and Photoshop\nKnowledge of design techniques\nMulti-tasking and good time management\nCreative, keen eyes for details, and open-minded\nInterested parties please use \"quick apply\" to submit your CV with a work portfolio link, expected salary and availability.\u00a0Only shortlisted candidates will be contacted, and all applications will be treated in strict confidentiality.", "employment_types": ["Full Time", "Permanent"], "selling_points": [], "locations": ["Kwai Hing"], "categories": ["Design", "Graphics", "Multi-media", "Web Designer"], "post_time": "2022-01-11T02:35:20Z", "salary": {"currency": null, "max": null, "min": null, "period": "monthly", "term": null}, "salary_visible": false, "title_keywords": ["digital designer", "graphic designer"], "responsibilities": ["ad-hoc", "social media", "edms", "marketing strategies", "edm", "social media platforms", "graphic designs", "video editing", "schedule", "company website", "animation", "planning"], "requirements": {"degrees": ["diploma", "university degree"], "majors": ["related disciplines", "design"], "languages": [], "language_level": [], "hard_skills": ["graphics", "plus", "illustrator", "multimedia", "photoshop"], "soft_skills": ["creative", "open-minded", "keen", "multi-tasking", "time management"], "languages_combined": []}, "experience_required": {"duration": ["minimum of 3 years"], "field": ["beauty industry", "graphic", "design", "editing"]}}, {"job_id": "100003009038523", "location_code": "hk", "company": "The Executive Centre Limited", "job_title": "Multimedia Designer", "description": "The\u00a0Multimedia Designer's is responsible for\u00a0the creation and delivery of a range of cross-platform work This can also include anything from marketing collateral, responsive sites and emails banners, mobile/tablet apps, microsites and social content.\u00a0It involves working closely with the ACD and marketing managers for our regional markets.\n\n\nJob Duties:\n\nCollaborate closely with the Associate Creative Director, Designers, Content Editor, Project Manager, and Product Manager in areas as diverse as digital content creation, motion graphics, UX & responsive design, branding and editing\nDesign and create assets for our social team including: motion graphics, illustrations, branding, assisting in the creation of video content, designing templates, layout across multiple platforms\nEnsure the company\u2019s brand guidelines are implemented consistently across all channels\nParticipate in discussions to clarify purposes and objectives that bring brand strategy and creative ideas to life\n\u00a0Assist the team with brainstorming campaign ideas, implementing design concepts, illustration, infographics, image creation, asset gathering, typesetting \u2013 this could range from flyers, social assets, presentation decks, landing pages etc.\nStay up to date on emerging digital trends and culture, attending events and engaging with the wider digital creative community\nArticulating and presenting any creative ideas/treatments to teams\nSkills and Requirements:\n\u00a0Minimum 2 years of design experience with portfolio or samples of work demonstrating smart, brand-building designs and executions\n\u00a0Solid experiences in the following areas:\ni)\u00a0 \u00a0Conceptualizing, storyboarding and producing videos in After Effects (or similar programs)\n\nii) Working with agencies in designing cutting-edge websites, apps, interfaces and/or digital campaigns (including banners, microsites, emails, social assets \u2013 Linkedin, Facebook, Instagram, & Wechat)\n\nExperience in Photography and Moving images is an huge advantage\nExpertise in Adobe Creative Suite (Photoshop, Illustrator, InDesign, and After Effects)\nGood knowledge/understanding of HTML and CSS\nProven understanding of typography, layout, colour and grid structures\nReceptive to feedback and have strong attention to detail\nStrong design and excellent communication skills\nOutstanding organizational, project management, file-organization and archiving skills\n\u00a0Proficiency of written and verbal English and is required;\u00a0 Chinese (Traditional/ Simplified) is a plus", "employment_types": ["Full Time"], "selling_points": ["4 + years of experience in UI/UX Design", "Agency experience", "Knowledge of Adobe After Effect"], "locations": ["Southern Area"], "categories": ["Design", "Multi-media"], "post_time": "2022-01-11T07:14:10Z", "salary": {"currency": null, "max": null, "min": null, "period": "monthly", "term": null}, "salary_visible": false, "title_keywords": ["multimedia designer"], "responsibilities": ["collaborate", "design concepts", "creative ideas", "ideas", "teams", "design", "motion graphics", "brand guidelines", "designing", "editing"], "requirements": {"degrees": [], "majors": [], "languages": ["english", "chinese"], "language_level": ["proficiency"], "hard_skills": ["plus", "css", "indesign", "illustrator", "html", "wechat", "after effects", "project management", "facebook", "adobe creative suite", "photoshop"], "soft_skills": ["communication skills", "cutting-edge", "organizational", "receptive", "project management", "attention to detail", "creative"], "languages_combined": [{"language": "english", "language_level": ["proficiency"]}, {"language": "chinese", "language_level": []}]}, "experience_required": {"duration": ["minimum 2 years"], "field": ["brand", "design"]}}, {"job_id": "100003009042123", "location_code": "hk", "company": "Tomato Club Food Limited", "job_title": "Graphic Designer", "description": "Responsibilities:\n\nResponsible for design brand materials from online to offline channels e.g. social media, website, leaflet, brochure, posters etc.\nResponsible for photo/video shooting and editing, as well as live streaming, from concept to implementation.\nCreative & independent from design, concept and final output in alignment with the brand strategies\nOther ad hoc assignments and project as required.\n\nRequirements:\n\nDiploma or above in Graphic Design/ Multimedia Design or related discipline.\nMinimum 3 years of solid working experience in commercial design field, experience in F&B industry will be an advantage\nProficient in Adobe Creative Series \u2013\u00a0Photoshop, Illustrator, InDesign, Premier Pro, After Effects etc.\nCreative with passion, willing to work under pressure and tight schedule.\nProactive, responsible and able to work independently.\n\nInterested parties, please click \"Apply Now\" to submit your\u00a0resume (including current and expected salary, availability).\n\nPersonal data collected will be used for recruitment purpose only.", "employment_types": ["Full Time"], "selling_points": ["Graphic Designer", "Leaflet design", "photo shooting"], "locations": ["Kwai Hing"], "categories": ["Design", "Graphics", "Industrial / Product", "Multi-media"], "post_time": "2022-01-12T06:18:16Z", "salary": {"currency": null, "max": null, "min": null, "period": "monthly", "term": null}, "salary_visible": false, "title_keywords": ["graphic designer"], "responsibilities": ["social media", "leaflet", "brand strategies", "website", "design", "implementation", "brand materials", "video shooting", "ad hoc assignments", "editing"], "requirements": {"degrees": ["diploma or above"], "majors": ["multimedia design", "graphic design"], "languages": [], "language_level": [], "hard_skills": ["indesign", "illustrator", "after effects", "adobe", "multimedia", "photoshop"], "soft_skills": ["work independently", "proactive", "responsible", "creative", "work under pressure"], "languages_combined": []}, "experience_required": {"duration": ["minimum 3 years"], "field": ["commercial", "f&b", "design"]}}, {"job_id": "100003009048718", "location_code": "hk", "company": "PERSOLKELLY Hong Kong Limited", "job_title": "UI Designer (E-commerce)(Mobile App)", "description": "Hip Shing Hong strives to fill work and life with positive energy, and crafts spaces that promote wellness.\n\nCome and join us to take on new challenges where your creativity is cherished.\n\nWe are looking for a talent to:\n\nConceive, craft and execute a variety of creative and digital ideas, artworks and copywriting for online and offline advertising & social campaigns\nHandle graphic design, creative solution, layout, script writing, artwork and video production in various digital platforms such as social media, eDM, online banner and webpage etc.\nHandle layout design for offline marketing materials such as leaflet, posters and banner etc.\n360 VR, video and photographic shooting, production and editing\nOrganize digital projects, create and support marketing assets for interactive mobile, web and desktop platform\n\nBasic requirements:\n\nHigher Diploma or above in Multimedia Design, Graphic Design, Digital Marketing, Marketing Communications, or related disciplines\n2 years' relevant working experience in Multimedia, Graphic design, UI/UX, Photography, Videography or related exposure\nCandidate with knowledge of animation or illustration is an advantage\n\n\nBenefits:\u00a0\u00a0\n\nMedical insurance\nDental insurance\nDiscretionary year-end bonus\nEducation and training allowance\nPaid marriage leave & gift\nPaid emergency leave\nPaid children's birthday leave\nPaid compassionate leave\nAcademic scholarship\n\nWe are constantly looking for talents who are proactive and dedicated to be part of our Hip Shing Hong\u2019s family. If you are ready for the next challenge, please apply now. For more information, please visit our Company's website\u00a0https://www.hshd.com.hk/en/career/.\n\nAll information provided by applicants will be treated in strict confidence and be used for recruitment purpose only.\u00a0", "employment_types": ["Full Time", "Contract"], "selling_points": ["5 day working", "Competitive salary", "Multinational Corporation"], "locations": ["Causeway Bay"], "categories": ["Design", "Graphics", "Multi-media", "Web Designer"], "post_time": "2022-01-14T07:08:04Z", "salary": {"currency": null, "max": null, "min": null, "period": "monthly", "term": null}, "salary_visible": false, "title_keywords": ["ui designer"], "responsibilities": [], "requirements": {"degrees": [], "majors": [], "languages": [], "language_level": [], "hard_skills": [], "soft_skills": ["positive"], "languages_combined": []}, "experience_required": {"duration": [], "field": []}}, {"job_id": "100003009041079", "location_code": "hk", "company": "Dialego Limited", "job_title": "Photographer/Videographer", "description": "Our\u00a0Client, a\u00a0Chinese\u00a0multinational\u00a0e-commerce, retail, Internet, AI and technology conglomerate, is seeking a\u00a0Mobile App UI Designer to support their team.\n\nJob Responsibilities:\n\nSpecialized in graphic, visual communication with knowledge of marketing\nLiaise with internal parties and initiate brainstorming/creative sessions to translate marketing objectives into compelling creative strategies and solutions\nWork closely and support UED team for ongoing and ad hoc promotion or activities\nResponsible for Mobile Application's Design.\nDevelop and standardized the design template for all creative promotion materials for both online and offline channels including POSM, mobile ad banner, etc.\nResponsible for the maintenance of design materials and inventory\n\nJob Requirements:\n\nNeed to be Hong Kong Resident\nGraphic or Digital Design or other related field\nMore 3 years of working experience in design related field, preferable with\u00a0exposure in mobile/ web product/ advertising industry and design studio company\nStrong creative view and ability to communicate and present ideas in a clear\nHigh level of initiative and ability to work under tight deadlines in a fast-paced, team-oriented environment\nGood command of both English and Chinese and proficiency in Putonghua\nApplicants are required to submit the creative design portfolio\n\nGood to have:\n\nExperience in financial or banking products will be advantages\nExperience in animation / UI will be advantages\nTo apply for this position, please click on \u201cApply Now\u201d bottom.\u00a0 All applications will be treated in strict confidence, and used for recruitment purposes only in accordance with PERSOLKELLY Hong Kong Limited\u2019s Privacy Notice.\u00a0", "employment_types": ["Full Time", "Permanent", "Freelance"], "selling_points": [], "locations": ["Shatin Area"], "categories": ["Media & Advertising", "Creative / Design", "Design", "Multi-media", "Photography / Video"], "post_time": "2022-01-12T03:25:26Z", "salary": {"currency": null, "max": null, "min": null, "period": "monthly", "term": null}, "salary_visible": false, "title_keywords": ["videographer", "photographer"], "responsibilities": ["ad hoc", "maintenance", "creative promotion materials", "inventory", "design", "develop", "communication", "visual", "liaise with", "internal parties"], "requirements": {"degrees": [], "majors": [], "languages": ["putonghua", "english", "chinese"], "language_level": ["proficiency", "good command"], "hard_skills": ["creative design", "mobile", "web"], "soft_skills": ["clear", "confidence", "creative", "initiative"], "languages_combined": [{"language": "putonghua", "language_level": ["good command"]}, {"language": "english", "language_level": ["proficiency", "good command"]}, {"language": "chinese", "language_level": ["proficiency", "good command"]}]}, "experience_required": {"duration": ["3 years"], "field": ["related", "design", "banking", "advertising industry", "financial"]}}, {"job_id": "100003009043055", "location_code": "hk", "company": "MoneyHero Global Limited", "job_title": "Designer (Visual Communications, Graphic, or Multimedia)", "description": "Job Responsibilities:\n\nWork closely with other department to execute the creative strategy in Brand Experience and new pitch projects\nExecute top-quality design from concept to delivery complying with brand standards in execution of marketing materials\nDevelop digital storyboards and animation as demanded\nIntegrate visually and enhance creative concept, architecture, UI and navigation design for web sites, online advertising and mobile\n\nRequirements:\n\nHigher Diploma holder preferably in Art, Design, Digital or related disciplines\n2+ years graphic design experience, strong creative portfolio in design, motion graphics and video in brand experience\nExperience in effective strategic brainstorming, campaign design and development\nHigh Proficiency in Photoshop, Illustrator and After Effect etc.\nKnowledge in 2D animation & Final Cut Pro is a plus\nPassion for new technologies and emerging trends\nGood communication skill\n\nBenefits:\n\nStaff Training\nFive-day work per week\nTeam Building Activities\nBirthday Leave, General Holiday and Medical Allowance\n\nWe offer attractive remuneration package, commensurate with candidates\u2019 qualification and experience. Interested parties, please send your application letter, detailed CV including date of availability and current and expected salary by clicking \"APPLY NOW\". Only short-listed candidates will be notified for an interview All information received will be kept in STRICT CONFIDENCE and only for employment related purpose.\n\nFor more information about Fimmick, please visit our website www.fimmick.com.", "employment_types": ["Full Time", "Permanent"], "selling_points": ["1-2 years of experiences", "Passionate in creative", "Proficient in the use of Mac &Adobe Creative Suite"], "locations": ["Tin Hau"], "categories": ["Design", "Graphics", "Multi-media", "Web Designer"], "post_time": "2022-01-12T09:40:45Z", "salary": {"currency": null, "max": null, "min": null, "period": "monthly", "term": null}, "salary_visible": false, "title_keywords": ["designer"], "responsibilities": ["enhance creative concept", "from concept to delivery", "online advertising", "web sites", "develop digital storyboards", "ui and navigation design", "architecture", "execution of marketing materials", "top-quality design", "animation"], "requirements": {"degrees": ["higher diploma holder"], "majors": ["related disciplines", "art", "design"], "languages": [], "language_level": [], "hard_skills": ["graphics", "final cut pro", "plus", "illustrator", "after effect", "photoshop"], "soft_skills": ["communication skill", "creative", "passion for"], "languages_combined": []}, "experience_required": {"duration": ["2+ years"], "field": ["video", "brand", "graphic design", "development", "design"]}}, {"job_id": "100003009044246", "location_code": "hk", "company": "Total Brand Activation Hong Kong Limited", "job_title": "Art Director (Job Ref. No: DES05)", "description": "Cheerland is a reputable brand of party and event decorative items. We are looking for an experienced Photographer/Videographer.\n\nThe position is responsible to:\n\n\nWork closely with design & marketing team to shoot product images and videos for online sales portals;\nDevelop high quality photo and video advertising images and video clips for promotion on website and social media;\nOrganize props, backdrop and set up shooting venues;\nTake care of all the post-shooting touch-up, editing and production work;\nAssist in graphics or multimedia design; and\nWork on other ad hoc projects assigned.\nSuitable candidate shall be/with:\n\n\nPassionate and skillful on photography and videography\nDiploma or Degree holder of relevant disciplines\nProfession in Photoshop, Illustrator, Premiere and After Effects.\nProficient in MS Word and Chinese input;\nGood command of English, Chinese and understand Putonghua.\nPosition and remuneration will commensurate with education, competencies and experience. 5 days week, medical, bonuses, office next to Shatin Shek Mun MTR Station.", "employment_types": ["Full Time", "Permanent"], "selling_points": ["Strong creative vision", "Proficiency with design software", "Interest in social and cultural trends & fashions"], "locations": ["Not Specified"], "categories": ["Media & Advertising", "Creative / Design", "Design", "Multi-media", "Marketing / Public Relations", "Public Relations - Event Management"], "post_time": "2022-01-13T03:31:31Z", "salary": {"currency": null, "max": null, "min": null, "period": null, "term": null}, "salary_visible": false, "title_keywords": ["art director"], "responsibilities": ["graphics", "social media", "multimedia design", "advertising", "quality", "website", "design", "develop", "ad hoc projects", "editing"], "requirements": {"degrees": ["diploma", "degree holder"], "majors": [], "languages": ["putonghua", "english", "chinese"], "language_level": ["good command", "proficient"], "hard_skills": ["clips", "graphics", "chinese input", "ms word", "illustrator", "premiere", "after effects", "multimedia", "photoshop"], "soft_skills": ["passionate", "responsible"], "languages_combined": [{"language": "putonghua", "language_level": ["good command"]}, {"language": "english", "language_level": ["good command"]}, {"language": "chinese", "language_level": ["good command", "proficient"]}]}, "experience_required": {"duration": [], "field": ["education"]}}, {"job_id": "100003009044995", "location_code": "hk", "company": "Kenal Group Limited", "job_title": "Game 3D Model Artist", "description": "THE ROLE\u00a0\nWe are looking for a passionately user and outcome-oriented designer to join the MoneyHero Marketing team. If you are the person who is observant to the big picture and has good attention to details, obsessed with aesthetics and uncomfortable with bad typography or bad alignments, believe in having fun while achieving results, then you are exactly the candidate who we want to welcome to our team!\n\nYOUR TASK\nAssist design research and material preparation\nProduce digital designs\u00a0 as assigned such as banner ads, social posts, infographics\nUse various techniques to create drafts, models and prototypes\nPitch creative ideas\nCollaborate with team members to launch projects\nTake on special design tasks (e.g. color correction)\nUse feedback from other designers to improve\nSKILLS & REQUIREMENTS\n1-2 years of experiences\u00a0\nStrong graphic sense including typography, colors, graphics and layout\nPassionate in creative and design with an eye for detail\u00a0\nA team player with good track record of time management and communication skills\u00a0\u00a0\nPreferably majoring in Design, Creative Media, Digital Media, Visual Comm or related disciplines\nProficient in the use of Mac & Adobe Creative Suite\nFluent in written and spoken English and Chinese", "employment_types": ["Full Time", "Permanent"], "selling_points": ["Serious passion for 3D games", "Produce high quality animated voxel assets", "Strong creative and technical design skills"], "locations": ["Kowloon Bay"], "categories": ["Design", "Multi-media", "Others"], "post_time": "2022-01-13T06:50:35Z", "salary": {"currency": null, "max": null, "min": null, "period": "monthly", "term": null}, "salary_visible": false, "title_keywords": ["model"], "responsibilities": ["collaborate with", "graphics", "creative ideas", "management", "design", "communication", "visual"], "requirements": {"degrees": [], "majors": [], "languages": ["english", "chinese"], "language_level": ["fluent"], "hard_skills": ["graphics", "adobe creative suite", "fun"], "soft_skills": ["passionate", "communication skills", "time management", "eye for detail", "attention to details", "team player", "creative"], "languages_combined": [{"language": "english", "language_level": ["fluent"]}, {"language": "chinese", "language_level": ["fluent"]}]}, "experience_required": {"duration": ["1-2 years"], "field": []}}, {"job_id": "100003009037216", "location_code": "hk", "company": "WilliamSELECT", "job_title": "Senior Digital / Multimedia Designer - Retail", "description": "TBA Hong Kong is driven by innovation and design. We\u2019re searching for an experienced art director to work with our Creative Directors to conceptualize experiential and through-the-line campaigns, apply expert art direction to the visual elements of creative projects, and inspire the agency\u2019s clients to be creatively progressive, through the application of fresh and inventive visual work.\n\nThe ideal art director will bring a mix of artistic, marketing, and business expertise to the position, promoting our company and that of our valued clients. We are looking for an experienced manager, who can inspire and be inspired by others to take our creative efforts to the next level. The ideal candidate will have a natural eye for design and a passion for delivering dynamic ideas that connect with any audience.\n\nDuties and Responsibilities:\n\nWorking from a brief to generate ideas to present to the client\nWork with the entire creative team to establish a unified brand understanding and voice for the company, helming a creative audit to elevate our innovation\nConceptualize campaign vision, harnessing original graphics, copy, content websites, social media, and other marketing materials\nWorking with specialists, such as video editors, 3D designers and photographers, to work on projects\nSupervise and mentor a team of graphic designers\nPresenting final layouts, storyboards, and illustrations, encouraging members to provide feedback, and responding to internal commentary and requests\nPresent to clients or oversee presentation of final concepts and coordinate production and dissemination for cross-organizational use\nAble to work on several projects at one time\n\nThe Person:\n\nHonest, open and not afraid to speak openly about their thoughts and ideas\nBachelor\u2019s degree in fine art, graphic design, or similar discipline\nAt least 3 years experience as an art director or designer within an agency is desired, with a strong desire to deliver \u2018best in class\u2019 creative work and be a creative leader.\nProficiency with design software, such as Adobe Creative Suite\nA strong command of branding principles, experiential design, consumer engagement and digital media, and an understanding of how they need to work together in developing on-brand, on-target solutions.\nExceptional capability with typography, layout, and prototyping\nWeb development and/or mobile development experience\nExperience with photography and video production and editing\nHave excellent interpersonal and communication skills and work well in a team.\nStrong creative vision with an understanding of business objectives\nhave an interest in social and cultural trends and fashions.\nhave a good understanding of exhibition, events, and digital campaigns.\nAbility to present and sell ideas effectively, and communicate our expertise and work both internally and externally.\nIf this sounds like you, then click\u00a0\"Apply Now\"\u00a0or\u00a0send us email\u00a0to forward your full resume with current & expected salary and job reference number to join us.\n\nAll personal data provided by job applicants will be used strictly in accordance with Company\u2019s personal data policies, a copy of which will be provided upon request.", "employment_types": ["Full Time"], "selling_points": ["International Retail Brand- Young & Energetic team", "Graphic & Multimedia Design for ecom / online", "Knowledge in 3D Max will be a plus, Welcome Agency"], "locations": ["Not Specified"], "categories": ["Design", "Graphics", "Multi-media", "E-commerce", "Marketing - Brand / Product Management"], "post_time": "2022-01-11T02:06:20Z", "salary": {"currency": "HKD", "max": 44999, "min": 30000, "period": "monthly", "term": null}, "salary_visible": true, "title_keywords": ["multimedia designer"], "responsibilities": ["graphics", "social media", "ideas", "audit", "coordinate", "marketing materials", "storyboards"], "requirements": {"degrees": ["degree", "bachelor"], "majors": ["graphic design", "fine art"], "languages": [], "language_level": [], "hard_skills": ["mobile", "web development", "adobe creative suite"], "soft_skills": ["communication skills", "creative", "interpersonal", "honest"], "languages_combined": []}, "experience_required": {"duration": ["at least 3 years"], "field": ["art director", "designer", "agency", "development", "video production", "editing"]}}, {"job_id": "100003009043403", "location_code": "hk", "company": "Wemine Limited", "job_title": "GRAPHIC & UX DESIGNER (Full Time)", "description": "Game 3D Model Artist\n\nAbout the Kenal Group www.kenalgroup.com\n\nKenal Group \u2013 Brand New Metalive.es in the Metaverse\u2026\n\nCome Flow with Us\u2026\n\nPANGU by Kenal - one of the #NFT #GameStudio @TheSandboxGame\nempowering brands with authentic, legendary and immersive assets & experiences in the #Metaverse\n\nThe Sandbox\u00a0- a virtual world where players can build, own and monetize their own 3D gaming experiences on the Ethereum blockchain. We are building a deeply immersive gaming virtual world metaverse where creators get the chance to make games next to gaming giants and brands such as Atari, Rollercoaster Tycoon, Shaun the Sheep and more gaming partners.\n\n- Website: www.sandbox.game\n\n- What is The Sandbox: https://medium.com/sandbox-game/what-is-the-sandbox-850de68d893e\n\n-\u00a0More Resources: http://resources.sandbox.game\n\n\n\nAbout the job\n\nThe\u00a0perfect fit will have to\u00a0create levels for our UGC virtual world, using our no-code The Sandbox Game Maker tool, which is a main component of The Sandbox decentralized gaming virtual world gaming platform, allowing to create voxel game experiences.\n\nThe position can be in-house alongside 3D Artists and Creators who produce 3D voxel assets to put these into context inside a voxel-based environment and implement the Behaviors and Components of the game maker to create compelling games with quests, rewards and more.\n\n\n\nRequirements\n\n- Knowledge about general Game Design and Level Design concepts\n\n- Experience designing avatar-centric 3D levels\n\n- Experience working with in-house editors (Unity or similar)\n\n- Experience working with MMO RPGs or Adventure games\n\n\n\nCommunication skills\n\nBasic programing or logic skills\n\nNice to Have\n\n- Played other UGC games where you create your own levels (including mechanics) such as Minecraft or Roblox\n\n- An eye for aesthetics, knowing what makes an environment appealing and a story compelling\n\n- Having coordinated a team in the past\n\n- Having been involved in UX processes for an editing tool\n\n- Knowledge about cryptogames", "employment_types": ["Full Time", "Permanent"], "selling_points": ["Create banging visuals for social media channels", "Bring innovation to UI/UX design", "Join a team of top-notch digital experts"], "locations": ["Kwun Tong"], "categories": ["Design", "Graphics", "Multi-media", "Web Designer"], "post_time": "2022-01-12T11:32:37Z", "salary": {"currency": null, "max": null, "min": null, "period": "monthly", "term": null}, "salary_visible": false, "title_keywords": ["ux designer"], "responsibilities": [], "requirements": {"degrees": [], "majors": [], "languages": [], "language_level": [], "hard_skills": ["nice", "basic", "unity"], "soft_skills": ["communication skills"], "languages_combined": []}, "experience_required": {"duration": [], "field": []}}, {"job_id": "100003009036855", "location_code": "hk", "company": "Wah Tat Hardware & Tools Limited", "job_title": "Multimedia Designer", "description": "We are looking for a graphic designer to join our dynamic team.\n\nPassionate in graphic design, and eager to take part in innovative projects for a startup company.\n\nWHAT WE ARE LOOKING FOR:\n\nHungry for challenges and achievements\nCreative and with the advancement of your problem-solving skills\nDegree holder\u00a0with graphic design experience, with the UX/UI design for Web portal, eCommerce platform or Mobile Application will be an advantage\nResponsible for the branding and marketing visuals for digital and offline channels\nSupport and work closely with developers, marketers\nConduct branding, design research and analysis\nStrong sense at layout/typographic and Graphic Design\nHighly proficient in Adobe Creative Suite e.g. Photoshop, illustrator, InDesign, XD, etc.\nStrong knowledge of HTML5, CSS3, will be an advantage\nProficiency in Chinese or English\nPortfolio links should be provided in the resume.\n\nWHAT WE OFFER:\n\nOpportunities to involve in product branding and marketing designs\nCreative working environment with little office hierarchy\nMarket-competitive rate\nA team of top notch web experts\u00a0\n\nWHAT WHAT YOU WILL DO:\n\n30%:\u00a0Collaborate with the Development and Marketing Team to execute design solutions (web/social media/UI & UX for APP) that comply with project specifications, brand identity and strategic marketing goals\n\n25%:\u00a0Visualize concepts into rough drafts as the foundation for future execution, establish standards for style, aesthetics and typeface; design preliminary layout.\n\n25%:\u00a0Contribute to brainstorming workshops in projects and product innovation\n\n20%:\u00a0Participate in other innovative projects and learning opportunities under the group\u2019s investments\u00a0\u00a0\u00a0\n\nResponsible for the branding and marketing visuals for social media channels; take part in APP development projects;\nConduct branding, design research and analysis\nSupport and work closely with developers and marketers\n\nAbout\u00a0WeMine Limited\n\nWeMine is a marketing technology (Mar-Tech) firm that specializes in developing an intelligent marketing suite* on WeChat (and other social media platforms soon). Being exploited to such a sophisticated multi-purpose open platform, we challenge ourselves to unearth the gem within every day.\n\nAs a rapidly growing startup, we are constantly looking for fresh and passionate talents who are never tired of being challenged, questioned, and indeed, inspired to build a universally friendly infrastructure for marketers and business operators.\n\nUp for it? Send us your CV.\n\n*Wanna know what's inside our intelligent suite? Watch the video here -\u00a0https://goo.gl/gY0AFf- as an example.", "employment_types": ["Full Time"], "selling_points": ["\u4e00\u822c\u96fb\u8166\u5716\u50cf\u8a2d\u8a08\u54e1\u5de5\u4f5c", "\u719f\u6089AI\u3001PS\u3001INDESIGN\u7b49\u8a2d\u8a08\u8edf\u4ef6", "\u5e74\u5c3e\u96d9\u7ce7, \u5a5a\u5047, \u7522\u5047/\u4f8d\u7522\u5047, \u81b3\u98df\u6d25\u8cbc"], "locations": ["Mong Kok"], "categories": ["Design", "Multi-media", "Others"], "post_time": "2022-01-10T16:52:20Z", "salary": {"currency": null, "max": null, "min": null, "period": "monthly", "term": null}, "salary_visible": false, "title_keywords": ["multimedia designer"], "responsibilities": ["graphic design", "analysis", "ui", "design"], "requirements": {"degrees": ["degree holder"], "majors": ["ecommerce", "graphic design", "design"], "languages": ["english", "chinese"], "language_level": ["proficiency"], "hard_skills": ["web", "analysis", "indesign", "illustrator", "mobile", "dynamic", "problem-solving skills", "adobe creative suite", "photoshop"], "soft_skills": ["passionate", "responsible", "innovative", "dynamic", "problem-solving skills", "creative"], "languages_combined": [{"language": "english", "language_level": ["proficiency"]}, {"language": "chinese", "language_level": ["proficiency"]}]}, "experience_required": {"duration": [], "field": ["ecommerce", "graphic design", "design"]}}, {"job_id": "100003009037624", "location_code": "hk", "company": "PixelMaxx Production Limited", "job_title": "Motion Graphics Designer", "description": "\u4e00\u822c\u96fb\u8166\u5716\u50cf\u8a2d\u8a08\u54e1\u5de5\u4f5c,\n\n\u88fd\u4f5c\u5e73\u9762\u53ca\u591a\u5a92\u9ad4\u8a2d\u8a08,\n\n\u526a\u8f2f\u53ca\u88fd\u4f5c\u5f71\u7247,\n\n\u8ca0\u8cac\u4e00\u822c\u5e73\u9762\u8a2d\u8a08\u5de5\u4f5c(\u5ee3\u544a\uff0c\u6d77\u5831\uff0c\u5ba3\u50b3\u55ae\u5f35\uff0c\u80cc\u5e55)\u5c55\u89bd\u8a2d\u8a08\u88fd\u4f5c\uff0c\u6392\u7248\uff0c\n\n\u719f\u6089AI\u3001PS\u3001INDESIGN\u7b49\u8a2d\u8a08\u8edf\u4ef6.\n\n\u4e3b\u52d5, \u8ca0\u8cac\u4efb, \u6709\u71b1\u8aa0.\n\n$18000-$22000\n\u653e\u52de\u5de5\u5047\n\n\u6709\u81b3\u98df\u6d25\u8cbc\n\n\u6709\u5e74\u5c3e\u96d9\u7ce7\n\n\u6709\u5a5a\u5047\n\n\u6709\u7522\u5047/\u4f8d\u7522\u5047\n\n\u5e74\u5047", "employment_types": ["Full Time"], "selling_points": [], "locations": ["Kowloon Bay"], "categories": ["Media & Advertising", "Creative / Design", "Design", "Multi-media", "Marketing / Public Relations", "Digital Marketing"], "post_time": "2022-01-11T03:19:14Z", "salary": {"currency": null, "max": null, "min": null, "period": "monthly", "term": null}, "salary_visible": false, "title_keywords": ["designer"], "responsibilities": [], "requirements": {"degrees": [], "majors": [], "languages": [], "language_level": [], "hard_skills": [], "soft_skills": [], "languages_combined": []}, "experience_required": {"duration": [], "field": []}}, {"job_id": "100003009038683", "location_code": "hk", "company": "AAStocks.com Limited", "job_title": "Digital Designer (Graphic & Multimedia) (5-day work)", "description": "Motion Graphics Designer:\n\nWe are looking for talented artist who has good experience in Motion Graphics / Video Production. Ideal candidates should have experience in motion graphics and video post production work flow, and the ability to create finish work to match our motion projects.\u00a0\n\nJob Duty & Responsibilities:\n- Design and create 2D/3D motion graphics/videos\n- Create storyboard\n\nJob Requirements:\n- Knowledge in Video Editing and Motion Graphics Design\n- Certificate/Diploma/Degree holder in Multi-Media, Motion Graphics or Video Production\n- Good command of presentation layout\n- Proficient in creative softwares such as After Effects, Premiere,\u00a0Photoshop\n- Knowledge of Cinema 4D is an advantage.\n- Self-motivated, creative and work independently\n- Responsible, good communication skills and team player", "employment_types": ["Full Time", "Permanent"], "selling_points": ["Develop creative concept to design, artwork", "Higher Diploma or above in Multimedia", "Minimum of 2 year solid working experience"], "locations": ["Not Specified"], "categories": ["Design", "Graphics", "Multi-media", "Others"], "post_time": "2022-01-11T07:38:12Z", "salary": {"currency": null, "max": null, "min": null, "period": "monthly", "term": null}, "salary_visible": false, "title_keywords": ["digital designer"], "responsibilities": ["motion graphics", "design"], "requirements": {"degrees": ["certificate", "diploma", "degree holder"], "majors": ["motion graphics"], "languages": [], "language_level": [], "hard_skills": ["graphics", "premiere", "video editing", "after effects", "photoshop"], "soft_skills": ["communication skills", "self-motivated", "work independently", "responsible", "team player", "creative", "presentation"], "languages_combined": []}, "experience_required": {"duration": [], "field": []}}, {"job_id": "100003009037154", "location_code": "hk", "company": "Wondersky Online Limited", "job_title": "Graphic Designer (Full Time or Part Time)", "description": "Job Responsibilities\nDevelop creative concept to design, artwork and the final output to meet business objectives\nResponsible for developing concept development, graphic design and artwork adaptation for online & offline materials (includes advertisements, website/mobile banners, newsletters, posters, leaflets, brochures, FB, IG, etc)\nHandle multiple projects, work under tight schedule and meet deadlines\nResponsible and creative, work well independently and also with teammates\nJob Requirements\nHigher Diploma or above in Multimedia/Interaction Design or other related discipline\nMinimum of 2 year solid working experience\nExperience in handling digital marketing solution is preferred\nStrong sense of visual presentation, composition, space and color management\nProficiency in using graphic & photo imaging software and web design tools is a MUST (e.g. Adobe Photoshop, Illustrator, After Effects, etc.)\nCreative, well-organized, detail-minded, independent, self-initiate, hardworking, aggressive and good personality\nKnowledge in HTML5, CSS, Action script will be an advantage\nGood command of both written and spoken English and Chinese\nPlease click \"Apply Now\" to submit your application.\nPersonal data collected will be used for recruitment purpose only.", "employment_types": ["Full Time", "Permanent"], "selling_points": [], "locations": ["Sheung Wan"], "categories": ["Design", "Graphics", "Multi-media", "Web Designer"], "post_time": "2022-01-11T01:56:48Z", "salary": {"currency": null, "max": null, "min": null, "period": "monthly", "term": null}, "salary_visible": false, "title_keywords": ["graphic designer"], "responsibilities": ["advertisements", "leaflets", "graphic design", "developing", "design", "develop", "website", "banners", "schedule", "multiple projects"], "requirements": {"degrees": ["higher diploma or above"], "majors": ["design"], "languages": ["english", "chinese"], "language_level": ["good command"], "hard_skills": ["web design", "adobe photoshop", "illustrator", "after effects", "multimedia", "css"], "soft_skills": ["detail-minded", "independent", "well-organized", "creative", "presentation", "hardworking"], "languages_combined": [{"language": "english", "language_level": ["good command"]}, {"language": "chinese", "language_level": ["good command"]}]}, "experience_required": {"duration": ["minimum of 2 year"], "field": ["digital marketing"]}}, {"job_id": "100003009035028", "location_code": "hk", "company": "\u5167\u598d\u7f8e\u6709\u9650\u516c\u53f8", "job_title": "\u5e73\u9762\u53ca\u591a\u5a92\u9ad4\u8a2d\u8a08\u5e2b", "description": "\u81ea2015\u5e74\u6210\u7acb\uff0cyanis beauty\u6fc0\u5149\u812b\u6bdb\u7642\u7a0b\uff0c\u7372\u7f8e\u570bFDA\u53ca\u6b50\u76dfCE\u8a8d\u8b49\u80fd\u5fb9\u5e95\u6839\u9664\u6bdb\u9aee\uff0c\u4e26\u4e0d\u65b7\u5f15\u5165\u5148\u9032\u6280\u8853\u3002\nYanis beauty \u5229\u7528Gentlelase pro 755\u6fc0\u5149\u6ce2\u9577\u812b\u6bdb\u6280\u8853\uff0c\u4f7f\u7528\u539f\u5ee0\u51b7\u51cd\u6280\u8853\u3002\n\n\u5e73\u9762\u53ca\u591a\u5a92\u9ad4\u8a2d\u8a08\u5e2b\n\n\u8077\u8cac:\n\u8ca0\u8cac\u5e73\u9762\u8a2d\u8a08\u3001\u591a\u5a92\u9ad4\u8a2d\u8a08\u3001FACEBOOK\u5ee3\u544a\u904b\u4f5c\u53ca\u526a\u7247\u7b49\u5de5\u4f5c\n\u5305\u62ec\u793e\u4ea4\u5a92\u9ad4\u3001\u5ee3\u544a\u3001\u7522\u54c1\u6587\u5b57\u8a2d\u8a08\u53ca\u63d2\u756b\u8a2d\u8a08\n\u8ca0\u8cac\u652f\u63f4\u5e02\u5834\u63a8\u5ee3\u90e8\u5de5\u4f5c\n\n\u8981\u6c42:\n\u9700\u8981\u4e00\u5e74\u6216\u4ee5\u4e0a\u76f8\u95dc\u5de5\u4f5c\u7d93\u9a57;\n\u826f\u597d\u7cb5\u8a9e\uff0c\u4e00\u822c\u82f1\u8a9e\n\u826f\u597d\u8b80\u5beb\u4e2d\u6587\uff0c\u61c2\u8b80\u5beb\u82f1\u6587\n\u719f\u6089PhotoShop , AfterEffect , Premiere Pro, AI , InDesign ,\n\u5c0d\u5de5\u4f5c\u8a8d\u771f\u8ca0\u8cac\uff0c\u5de5\u4f5c\u6548\u7387\u9ad8\n\u61c2\u82f1\u6587\u6253\u5b57 , \u4e2d\u82f1\u6587\u96fb\u8166\u64cd\u4f5c , \u4e2d\u6587\u6253\u5b57 , \u61c2\u651d\u5f71 , \u61c2\u62cd\u7247\u53ca\u61c2\u526a\u7247.\n\u91cd\u8996\u5718\u9ad4\u5408\u4f5c\u7cbe\u795e\uff0c\u7a4d\u6975\u6709\u79ae\u3001\u5bcc\u8cac\u4efb\u5fc3\u53ca\u5b88\u6642\n\n\u6709\u85aa\u5e74\u5047 7\u5929\u8d77\n\u751f\u65e5\u5047\u671f\n\u6bcf\u5929\u5de5\u4f5c9\u5c0f\u6642\n\u6709\u85aa\u5728\u8077\u57f9\u8a13\u53ca\u826f\u597d\u6649\u5347\u6a5f\u6703\n\u9ad8\u9054\u6a19\u734e\u91d1\n\u8d85\u6642\u88dc\u9418\n\u54e1\u5de5\u8cfc\u7269\u548c\u7642\u7a0b\u512a\u60e0\n\u54e1\u5de5\u65c5\u884c\n\n\u6709\u610f\u61c9\u5fb5\u8005\uff0c\u8acb\u5c07\u500b\u4eba\u5b8c\u6574\u7c21\u6b77\uff0c\u5305\u62ec\u60a8\u9810\u671f\u7684\u85aa\u916c Whatsapp 56026466 Ms Li\uff08\u6c42\u8077\u8005\u905e\u4ea4\u500b\u4eba\u8cc7\u6599\u53ea\u4f5c\u62db\u8058\u7528\u9014\uff0c\u6240\u6709\u8cc7\u6599\u7d55\u5c0d\u4fdd\u5bc6)", "employment_types": ["Full Time"], "selling_points": ["\u751f\u65e5\u5047\u671f", "\u8d85\u6642\u88dc\u9418", "PhotoShop , AfterEffect , Premiere Pro, AI , InDes"], "locations": ["Mong Kok"], "categories": ["Design", "Multi-media", "Visual Merchandising", "Beauty Care / Health", "Others"], "post_time": "2022-01-10T05:25:44Z", "salary": {"currency": null, "max": null, "min": null, "period": "monthly", "term": null}, "salary_visible": false, "title_keywords": [], "responsibilities": [], "requirements": {"degrees": [], "majors": [], "languages": [], "language_level": [], "hard_skills": ["whatsapp", "indesign", "premiere pro", "ai"], "soft_skills": [], "languages_combined": []}, "experience_required": {"duration": [], "field": []}}, {"job_id": "100003009043305", "location_code": "hk", "company": "Mad Head App Limited", "job_title": "Senior Graphic Designer", "description": "We are hiring!\nCome to join our team of professionals passionate to games!\n\nWhat you will be doing:\n\nAssist on creative development and layout adaptation\nHandle day to day graphics design and production for advertising, social media content, and website\nResearch and consolidate insight of new games/ apps, best practices of design and advertising across the market\nGenerate ideas and create content for feeds on social media\nPerform ad hoc assignments by management\u00a0\n\nWhat you need for this position:\n\nHigher diploma in Graphic Design or related discipline\nAt least 2 years of relevant experience in graphic design\nExperienced user of Adobe Photoshop and Adobe Illustrator\nKnowledge in social media management is an advantage\nProficient in spoken and written Chinese (both Cantonese and Mandarin) and English Independent, highly self-motivated, enjoy new challenges, and able to think out of the box\nA good team player and attention to detail\nCandidate with less experience would also be considered as Graphic Designer\u00a0\n\nWorking Location & Hours:\u00a0\nHong Kong Science Park\n5-day work, 10:00 \u2013 19:00 (Lunch hour 13:45 \u2013 15:00)\n\nWe Offer:\n\n\nAttractive Performance Bonus\nIn-game staff reward\nGood Career Prospects\nGroup Medical Insurance & Body-Check\nBirthday Leave, Marriage Leave, Compassionate Leave\nApplication method:\n\n\nInterested candidates please click the \"Apply Now\" button to apply and provide your portfolio for our review.\n\nWe are an equal opportunity employer and welcome applications from all qualified candidates. All information provided will be treated in strict confidence and used for recruitment purposes only.", "employment_types": ["Full Time", "Permanent", "Contract"], "selling_points": ["Graphic Design in Game Industry", "Self-motivated with a strong aesthetic sense", "Young, Creative & Energetic Team"], "locations": ["Shatin Area"], "categories": ["Design", "Graphics", "Multi-media", "Web Designer"], "post_time": "2022-01-12T10:36:16Z", "salary": {"currency": null, "max": null, "min": null, "period": "monthly", "term": null}, "salary_visible": false, "title_keywords": ["senior graphic designer"], "responsibilities": ["graphics", "social media", "management", "advertising", "ideas", "graphic design", "website", "design", "social media content", "ad hoc assignments"], "requirements": {"degrees": ["diploma"], "majors": ["graphic design"], "languages": ["cantonese", "english", "chinese", "mandarin"], "language_level": ["proficient"], "hard_skills": ["graphics", "adobe photoshop", "adobe illustrator"], "soft_skills": ["passionate", "good team player", "self-motivated", "independent", "attention to detail", "creative"], "languages_combined": [{"language": "cantonese", "language_level": ["proficient"]}, {"language": "english", "language_level": ["proficient"]}, {"language": "chinese", "language_level": ["proficient"]}, {"language": "mandarin", "language_level": ["proficient"]}]}, "experience_required": {"duration": ["at least 2 years"], "field": ["graphic design", "graphic", "relevant experience", "designer"]}}, {"job_id": "100003009042392", "location_code": "hk", "company": "Wang On Group", "job_title": "Assistant Graphic Designer", "description": "Graphic\u00a0Designer/Digital\u00a0Designer\n\nJob\u00a0Description\n\n\nResponsible\u00a0for\u00a0developing\u00a0concept\u00a0development,\u00a0graphic\u00a0design\u00a0&\u00a0artwork\u00a0adaptation for\u00a0online\u00a0&\u00a0offline\u00a0platforms\u00a0including\u00a0marketing\u00a0&\u00a0promotional\u00a0materials\u00a0includes\u00a0advertisements,\u00a0brochures,\u00a0leaflets,\u00a0banners,\u00a0posters,\u00a0newsletters,\u00a0website\u00a0banners,\u00a0FB,\u00a0IG\u00a0etc.\u00a0\nBrainstorm\u00a0and\u00a0collaborate\u00a0innovative\u00a0ideas\u00a0with\u00a0our\u00a0marketing\u00a0team\nDevelop\u00a0creative\u00a0concept\u00a0to\u00a0design,\u00a0structural\u00a0drawing,\u00a0artwork\u00a0and\u00a0the\u00a0final\u00a0output\u00a0to\u00a0meet\u00a0business\u00a0objectives\nHandle\u00a0regular\u00a0promotion\u00a0projects\u00a0and\u00a0ad\u00a0hoc\u00a0graphic\u00a0design\u00a0projects\n\u00a0\n\nRequirements\n\n\nDiploma\u00a0holder\u00a0in\u00a0graphics/\u00a0product\u00a0designs\nAt\u00a0least\u00a02-3\u00a0years\u00a0of\u00a0relevant\u00a0experience\nCreative\u00a0and\u00a0innovative\u00a0with\u00a0aesthetic\u00a0sense\nAttention\u00a0to\u00a0details\u00a0and\u00a0able\u00a0to\u00a0multi-tasking\u00a0and\u00a0meet\u00a0tight\u00a0deadlines\nProficient\u00a0in\u00a0using\u00a0Adobe\u00a0Illustrator,\u00a0Photoshop\u00a0in\u00a0Mac\u00a0environment\u00a0and\u00a0strong\u00a0knowledge\u00a0in\u00a0HTML\u00a0and\u00a0CSS\nExperience\u00a0in\u00a0graphic\u00a0design\u00a0in\u00a0fashion\u00a0&\u00a0beauty\u00a0&\u00a0digital\u00a0marketing\u00a0is\u00a0a\u00a0definite\u00a0advantage\nCan\u00a0work\u00a0independently,\u00a0well-organized,\u00a0responsible\u00a0and\u00a0a\u00a0good\u00a0team\u00a0player\nGood\u00a0command\u00a0in\u00a0Chinese\u00a0and\u00a0English\nLess\u00a0experienced\u00a0will\u00a0be\u00a0considered\u00a0as\u00a0Junior\u00a0Designer\n5-Day\u00a0work;\u00a0Bank\u00a0holiday;\u00a0Discretionary\u00a0bonus\n\nWorking\u00a0location\u00a0in\u00a0Kwai\u00a0Hing\u00a0(near\u00a0MTR\u00a0station).\n\nInterested\u00a0parties,\u00a0please\u00a0send\u00a0full\u00a0resume\u00a0with\u00a0expected\u00a0salary\u00a0to\u00a0us.\nImmediate\u00a0available\u00a0is\u00a0preferred", "employment_types": ["Full Time", "Permanent"], "selling_points": [], "locations": ["Kowloon Bay"], "categories": ["Design", "Graphics", "Multi-media", "Others"], "post_time": "2022-01-12T07:18:24Z", "salary": {"currency": null, "max": null, "min": null, "period": "monthly", "term": null}, "salary_visible": false, "title_keywords": ["assistant", "graphic designer"], "responsibilities": ["collaborate", "ideas", "ad hoc", "advertisements", "leaflets", "graphic design", "developing", "website", "develop", "design", "banners", "promotional materials"], "requirements": {"degrees": ["diploma holder"], "majors": [], "languages": ["english", "chinese"], "language_level": ["good command"], "hard_skills": ["graphics", "mac environment", "html", "adobe illustrator", "css", "photoshop"], "soft_skills": ["meet tight deadlines", "work independently", "good team player", "responsible", "well-organized", "innovative", "multi-tasking", "attention to details", "creative"], "languages_combined": [{"language": "english", "language_level": ["good command"]}, {"language": "chinese", "language_level": ["good command"]}]}, "experience_required": {"duration": ["at least 2-3 years"], "field": ["graphic design", "relevant experience", "beauty", "digital marketing"]}}, {"job_id": "100003009037092", "location_code": "hk", "company": "Rag United Works Limited", "job_title": "Photo /Video Editor (5 Days work)", "description": "Responsibilities:\n\nTo create concepts, update and maintain the standard of work\nPrepare and facilitate documents, creative material and concepts\nWork closely with operations and marketing team\n\nRequirements:\n\nHigher Diploma or above in graphic design, creative media design or related disciplines\nMinimum 2 years of relevant working experience in graphic design / creative industry\nProficiency in Photoshop, Premiere, After Effect, Adobe Suite / Adobe Illustrator and other design tools.\nGood command in both spoken and written English and Chinese\nAble to work independently under fast-paced working environment\nSelf-motivated, analytical, passionate in helping people find solutions, detail-oriented, and good team player\nFresh graduates with relevant degree/ skillsets are welcomed\nImmediate availability is preferred\nWe offer a competitive remuneration package, our benefits include:\nPerformance bonus\nEducation subsidy\nProfessional membership fee sponsorship\nLife & medical insurance\nMarriage Leave, Compassionate Leave, Examination Leave etc.\nPublic holidays\nStaff purchase discount\n\n\nInterested parties please send full resume with present and expected salary to Human Resources Department by clicking \"APPLY NOW\" or via email recruit @wangon.com.\n\n(Information provided will be treated in strict confidence and will only be used for recruitment-related purposes.)", "employment_types": ["Full Time", "Permanent"], "selling_points": [], "locations": ["Tsim Sha Tsui"], "categories": ["Design", "Graphics", "Multi-media", "Media & Advertising", "Photography / Video"], "post_time": "2022-01-11T02:12:32Z", "salary": {"currency": null, "max": null, "min": null, "period": "monthly", "term": null}, "salary_visible": false, "title_keywords": ["video editor"], "responsibilities": ["operations", "maintain"], "requirements": {"degrees": ["higher diploma or above", "degree"], "majors": ["related disciplines", "graphic design", "creative media", "design"], "languages": ["english", "chinese"], "language_level": ["good command"], "hard_skills": ["premiere", "adobe illustrator", "adobe", "after effect", "photoshop"], "soft_skills": ["passionate", "work independently", "self-motivated", "good team player", "detail-oriented", "creative"], "languages_combined": [{"language": "english", "language_level": ["good command"]}, {"language": "chinese", "language_level": ["good command"]}]}, "experience_required": {"duration": ["minimum 2 years"], "field": ["graphic design", "relevant working experience"]}}, {"job_id": "100003009044129", "location_code": "hk", "company": "Goodbye Dear Company Limited", "job_title": "UI UX designer", "description": "Job Highlights\n\nWebsite and mobile app user interface designs\nGraphic and digital design for banner\nWork with project and development team\n\nJob Responsibilities\n\nWebsite and mobile app user interface designs;\nProduce all kind of graphic and digital design for banner and other presentation materials;\nWork with project and development team; and\nManage any ad-hoc tasks or projects as assigned.\n\nJob Requirements:\n\nHigher Diploma or above in digital design, multimedia design, graphic communications or related field;\nMinimum 1 years' of working experience in design related field\nHands on skills in Adobe Photoshop, Illustrator, Sketch;\nKnowledge of UI design principles and techniques;\nDetail minded with can-do attitude and ability to multitask;\nProvide online portfolio link in addition to resume. *Immediate availability is preferred\n\nWorking location & hours\n\n5-days work\nWork in Kwun Tong", "employment_types": ["Full Time", "Contract"], "selling_points": [], "locations": ["Kwun Tong"], "categories": ["Design", "Multi-media", "Web Designer", "Information Technology (IT)", "UI/UX Designer"], "post_time": "2022-01-13T03:09:46Z", "salary": {"currency": null, "max": null, "min": null, "period": "monthly", "term": null}, "salary_visible": false, "title_keywords": ["ux designer"], "responsibilities": ["mobile app", "ad-hoc tasks", "website", "design", "user interface"], "requirements": {"degrees": ["higher diploma or above"], "majors": ["multimedia design", "communications", "design"], "languages": [], "language_level": [], "hard_skills": ["illustrator", "adobe photoshop", "multimedia"], "soft_skills": ["ability to multitask", "hands on", "can-do attitude"], "languages_combined": []}, "experience_required": {"duration": ["minimum 1 years"], "field": ["related", "design"]}}, {"job_id": "100003009037459", "location_code": "hk", "company": "430 Limited", "job_title": "Unity Interactive Developer", "description": "Job Highlights\n\nWorking in Video Game and Anime Industry and High Profile Licenses\n\n\nJob Description\n\nWe're First 4 Figures - First thing to do is to check out our YouTube Channel:\u00a0First4Figures We make awesome cool stuff from licenses such as Nintendo, SEGA, Capcom and Konami.\n\n\u00a0We are looking for someone with a passion for design and a keen interest in Statue/Toy Photography and Video for\u00a0social media. You will be working as part of a small team. Your time will be spent on filming, taking photographs and editing and preparing and running the behind the scenes production of pre-recorded videos and sometimes live streams. You need to be organised, creative and show initiative. You need to work with minimal direction and be comfortable taking the creative lead.\u00a0\n\n\u00a0Requirements\n\n- Experience in product shooting. Such as toy, food, luxury, watch, cosmetic...etc.\n- Good at non-linear video editing and has a good sense of pacing.\n- Good at creating visual motion graphic and info graphic effects\n- Proficient in using Adobe Suit. Including Premiere, After effect, photoshop.\n- Containing 3D skills is an advance\n- Experience in using studio light setting is an advance\n\n\u00a0Responsibilities:\n\n1. Organising high quality videography and photography shooting.\n\n2. Working as part of a team to produce promotional video for different platform of social media.\n\n3. Photo retouching\n\n4. Creating and improving 2D/3D visual effects on both photo and video footage.\n\n5. Researching and improving all sort of gears/tool for the team advance.\n\n6. Assisting with packaging and unpacking of our statues.\n\n7. Assisting with complete and improve our studio setup\n\n8. Audio recording for video production.\n\n9. Assisting with managing outsourced photographers, video editor, designers\n\n10. Assisting with installing and maintaining hardware and software\n\n11. Willing to learn and use job management software\n\n12. Conception and implementation of own creative idea\n\n13. Management of files archive system and cataloguing\n\n14. Copyright - learning about copyright infringement cases and registering images.\n\nPlease note that this list is not exhaustive and you may be required to undertake additional duties of a similar responsibility level as and when required.\n\n\u00a0Beneficial Skills / Experience / Qualities:\n\n\u00a0No formal qualifications required\n\u00a0Accuracy and consistency\n\u00a0Be practical with a keen eye for detail\n\u00a0Capacity for learning technical skills\n\u00a0An\u00a0aptitude\u00a0towards cameras and audio equipment is important\n\u00a0Ability to work independently and as part of a team.\n\u00a0Ability to work on multiple projects simultaneously.\n\u00a0Good organisational and time management skills.\n\u00a0Enthusiastic and motivated about all aspects of work\n\u00a0Positive attitude, persistent and resilient\n\u00a0Must be keen to progress, learn and adapt to new environments and challenging situations\n\u00a0Not afraid to get involved in a project outside of a traditional skill set\n\u00a0Interested in toy, anime and game industry.\n\u00a0Ability to work under pressure\nPerson Requirements:\n\nWe are looking for someone who has a keen interest in photography for print and web. We want someone who has experience using\u00a0camera\u00a0and editing software alike. We need someone with excellent communication skills and the desire to work hard, be creative, learn new things and develop their skill sets.\u00a0", "employment_types": ["Full Time", "Contract"], "selling_points": ["Work life balance", "No office politics", "Always choose kindness"], "locations": ["Mong Kok"], "categories": ["Design", "Multi-media"], "post_time": "2022-01-11T02:52:51Z", "salary": {"currency": null, "max": null, "min": null, "period": "monthly", "term": null}, "salary_visible": false, "title_keywords": ["developer"], "responsibilities": ["social media", "editing", "design"], "requirements": {"degrees": [], "majors": [], "languages": [], "language_level": [], "hard_skills": ["no", "web", "premiere", "video editing", "hardware", "adobe", "visual effects", "after effect", "photoshop"], "soft_skills": ["exhaustive", "communication skills", "work independently", "time management skills", "keen", "persistent", "interested in", "willing to learn", "positive attitude", "learning", "motivated", "eye for detail", "enthusiastic", "technical skills", "creative", "work under pressure"], "languages_combined": []}, "experience_required": {"duration": [], "field": ["editing"]}}, {"job_id": "100003009034939", "location_code": "hk", "company": "First 4 Figures Services Limited", "job_title": "Video Editor, Motion Graphic Designer and Photographer (Toy Industry)", "description": "The successful candidate will work closely with other designers to develop creative assets like imagery and graphics, diagrams, video, animated illustrations, etc. to support corporate branding and key marketing initiatives. He / she must have strong typography, composition and layout skills, a high ability to work under tight schedules while maintaining a high level of quality and accuracy.\n\n\nResponsibilities:\nCreate engaging designs for marketing assets ATL/TTL/BTL (posters, brochure, digital display, EDM, web and App banners etc)\nDevelop creative concepts, layouts and artworks for creative marketing campaign\nProvide art direction and liaise with vendors to deliver quality output\nAssist in development of brand and creative assets system\nUphold the branding guidelines to ensure all artworks and designs to the public are consistent to it\nTake, edit, retouch photos and videos\nPerform any other special projects as assigned\nRequirements:\nDiploma or Degree holder in Design, Creative Media, Multimedia Design or any related fields\n1-2 years of art direction & design experience, preferable in advertising & digital marketing industries. Agency experience is a plus. Fresh graduates are also welcome.\nProficient in Adobe Illustrator, InDesign, Photoshop, Premiere, and After Effect\nExcellent sense of art direction, graphic design, good skills on layout presentation and artwork production Strong creative and brainstorming capabilities\nPositive, true team player, open-minded and possess a strong sense of responsibility\nAbility to work in a team environment and collaborate with both designer and non-designers\nMust be proactive and able to reach out for required information in order to complete the job\nGood command of Chinese and English\nWe offer market competitive compensation, 5-day work week, and generous benefits including medical and life insurance; and voluntary contribution in addition to the legal minimum MPF.\u00a0 To apply, please send your full resume with current and expected salary to the Human Resources & Office Administration Department, Hong Kong Science and Technology Parks Corporation, 5/F, Building 5E, 5 Science Park East Avenue, Hong Kong Science Park, Hong Kong or, by email via \"Apply Now\"\u00a0on or before 24 January 2022.\u00a0 \u00a0Please quote the reference number on the email subject/envelope and the application letter.\u00a0\nPersonal data provided will be treated in strict confidence and used for recruitment purpose only.\u00a0 All personal data collected will be used strictly in accordance with employer\u2019s personal data policies, you can access to HKSTP\u2019s Personal Information Collection Statement at https://www.hkstp.org/hkstp_web/en/hkstp/personal-information-collection-statement-recruitment\nApplicants not invited for interview within four weeks after application deadline may consider their applications unsuccessful.\u00a0 Personal data of unsuccessful applicants will be retained for a maximum of two years.\u00a0", "employment_types": ["Full Time"], "selling_points": ["Experience in product shooting like toy, food etc", "Visual motion graphic experience", "Has a good sense of pacing for video editing"], "locations": ["Tsuen Wan Area"], "categories": ["Design", "Multi-media", "Media & Advertising", "Photography / Video"], "post_time": "2022-01-10T04:47:27Z", "salary": {"currency": "HKD", "max": 19999, "min": 14000, "period": "monthly", "term": null}, "salary_visible": true, "title_keywords": ["photographer", "graphic designer", "video editor"], "responsibilities": ["edm", "guidelines", "quality", "banners", "liaise with", "develop creative concepts"], "requirements": {"degrees": ["diploma", "degree holder"], "majors": ["multimedia design", "creative media", "design"], "languages": ["english", "chinese"], "language_level": ["good command"], "hard_skills": ["plus", "indesign", "premiere", "adobe illustrator", "multimedia", "after effect", "photoshop"], "soft_skills": ["proactive", "sense of responsibility", "open-minded", "team player", "creative", "presentation", "positive"], "languages_combined": [{"language": "english", "language_level": ["good command"]}, {"language": "chinese", "language_level": ["good command"]}]}, "experience_required": {"duration": ["1-2 years"], "field": ["agency", "advertising", "design", "digital marketing"]}}, {"job_id": "100003009039296", "location_code": "hk", "company": "Hong Kong Science & Technology Parks Corporation", "job_title": "Creative Designer [JDB/CD/220111]", "description": "Responsibilities:\n\nResponsible graphic design for marketing promotional and online/offline platforms\u00a0materials including advertisement, leaflets, posters, online banners, social media posts etc.\nResponsible in photo shooting, photo editing and retouching.\nMaintain daily operation of digital social media platforms such as Facebook, Instagram, WeChat and online shop etc.\nHandle ad-hoc tasks or projects as assigned.\n\nRequirements:\n\nDiploma or above in graphic/multi-media design relevant disciplines.\nAt least 1 year relevant experience, fresh graduate will also be considered.\nProficiency in Photoshop & Illustrator.\nAble to work independent, responsible and self-motivated\n\n\nWe offer 5 day work, 12 day annual leave and competitive salary to suitable candidate. For application, please send your resume with expected salary and availability by clicking \"Apply \".\n\nPersonal data will be treated in strict confidence and solely used for recruitment purposes.", "employment_types": ["Full Time"], "selling_points": [], "locations": ["Shatin Area"], "categories": ["Media & Advertising", "Creative / Design", "Design", "Graphics", "Multi-media"], "post_time": "2022-01-11T09:21:49Z", "salary": {"currency": null, "max": null, "min": null, "period": "monthly", "term": null}, "salary_visible": false, "title_keywords": ["creative", "designer"], "responsibilities": ["social media", "retouching", "leaflets", "graphic design", "ad-hoc tasks", "social media platforms", "daily operation", "banners", "maintain", "facebook", "editing"], "requirements": {"degrees": ["fresh graduate", "diploma or above"], "majors": ["design"], "languages": [], "language_level": [], "hard_skills": ["illustrator", "photoshop"], "soft_skills": ["self-motivated", "independent", "responsible"], "languages_combined": []}, "experience_required": {"duration": ["at least 1 year"], "field": ["relevant experience"]}}, {"job_id": "100003009038745", "location_code": "hk", "company": "Kate", "job_title": "Junior Graphic Designer / Graphic Designer (5 day work)", "description": "My client is an international retail brand with focus on technolody and they are looking for a Senior Multimedia Designer to join their team.\n\nResponsibilities:\n\nExecute creative solutions that meet the brand goals by translating concepts into exciting visuals.\nProduce sophisticated design aesthetic that lends well to online platforms, ecommerce &digital marketing media including, but not limited to site content, direct email marketing and social media, social media advertising and video / multimedia, across the brands\u2019 online presence\nResponsible for visual effects, editing and video production.\nMaintain strict personal and group goals and deadlines to ensure that the entire marketing development workflow is on schedule and brand standards\nRetouch product images achieved directly through agency or global images when needed\n\nRequirements:\n\nBachelor\u2019s Degree in Design / Graphic / Arts\nGood interpersonal and communication abilities\nKnowledge of design-related applications and software (eg Adobe Creative Suite, Final Cut Pro, Adobe After Effects, Adobe Premiere Pro, 3D Max, Cinema 4D etc.)\n3D Max knowledge would be a huge plus.\nKnowledge in Front-End Programming HTML, JavaScript, GIF Animation, Digital Banner etc. will be a plus\nProficient in English and Chinese", "employment_types": ["Full Time"], "selling_points": [], "locations": ["Lai Chi Kok"], "categories": ["Design", "Graphics", "Multi-media"], "post_time": "2022-01-11T07:43:11Z", "salary": {"currency": null, "max": null, "min": null, "period": "monthly", "term": null}, "salary_visible": false, "title_keywords": ["junior graphic designer", "graphic designer"], "responsibilities": ["social media", "advertising", "video production", "design", "maintain", "digital marketing", "schedule", "visual", "editing"], "requirements": {"degrees": ["degree", "bachelor"], "majors": ["design"], "languages": ["english", "chinese"], "language_level": ["proficient"], "hard_skills": ["final cut pro", "plus", "html", "adobe premiere pro", "adobe after effects", "javascript", "programming", "max", "adobe creative suite"], "soft_skills": ["communication", "creative", "interpersonal"], "languages_combined": [{"language": "english", "language_level": ["proficient"]}, {"language": "chinese", "language_level": ["proficient"]}]}, "experience_required": {"duration": [], "field": []}}, {"job_id": "100003009039941", "location_code": "hk", "company": "Chandler Macleod Group (HK) Limited", "job_title": "Graphic Designer - Banking (Up to 27K/mth)", "description": "Job Responsibilities\n\n\nProduce a variety of marketing materials using relevant graphic applications to an advanced level\nManage initial briefings and communication with internal stakeholders\nCreate concept and artwork as per company brand guidelines\nResponsible for overall quality and delivery of project outputs\n\nJob Requirements\n\n\nBachelor Degree or above in Graphic Design\nAt least 2 years relevant work experience preferably from banking/financial services industry, but not a must\nProficient in Adobe software, Microsoft Excel/PowerPoint\nExcellent command in written and spoken English\nStrong team player and sense of responsibility\nWilling to work overtime (with pay) with flexible hours", "employment_types": ["Full Time", "Contract"], "selling_points": ["A well-established financial services firm", "At least 2 years corporate design experience", "Kwun Tong work location"], "locations": ["Not Specified"], "categories": ["Design", "Graphics", "Multi-media", "Others"], "post_time": "2022-01-11T16:01:30Z", "salary": {"currency": null, "max": null, "min": null, "period": "monthly", "term": null}, "salary_visible": false, "title_keywords": ["graphic designer"], "responsibilities": ["marketing materials", "quality", "brand guidelines", "communication"], "requirements": {"degrees": ["degree or above", "bachelor"], "majors": ["graphic design"], "languages": ["english"], "language_level": ["excellent"], "hard_skills": ["adobe software", "powerpoint", "microsoft excel"], "soft_skills": ["flexible", "team player", "work overtime", "sense of responsibility"], "languages_combined": [{"language": "english", "language_level": ["excellent"]}]}, "experience_required": {"duration": ["at least 2 years"], "field": ["financial services industry", "banking"]}}, {"job_id": "100003009042863", "location_code": "hk", "company": "Casetagram Limited", "job_title": "Senior UXUI Designer", "description": "Casetify is looking for a Senior UXUI designer experienced in information architecture, interaction, and user testing to join our team. You will collaborate with the E-commerce team to design and build next generation Web/mobile applications. The right candidates will be excellent communicators, comfortable in a high-velocity startup, and passionate about creating products that transform people\u2019s lifestyle.\nResponsibilities:\nPrepare UX/UI design and materials including wire framing, mockup and rapid prototyping for various interfaces, including websites, mobile devices and apps for ecommerce site;\nAnalyze current user journey to understand motivation, expose pain points, issues and improvement opportunities;\nConduct user research, A/B testing, and propose solutions to optimize customer experience;\nCommunicate concepts and work collaboratively with project team / Tech team in order to develop the most efficient design schemas;\nSit with developers to do pixel-perfect reviews of frontend products before they are pushed in production;\nConsume our Design System library and contribute to its evolution.\nRequirements:\n\n\nBachelor Degree in Creative Media / Interactive Design / Web Design / Web Development;\n5+ years of experience building transactional website;\nSpecific experience in a fast growing ecommerce company;\nAbility to solve problems of complexity through smart design;\nBeing data-driven, and be able to back up your assertions with data, with proficiency in analytic tools - Hotjar, Google Analytics, Optimizely etc;\nA user-first attitude and ensure we consistently deliver a user-centric culture;\nStrong understanding of web grids and browser limitations;\nFamiliarity with usability testing, A/B testing methods;\nProficiency with Photoshop, Adobe XD, Webflow, HTML, CSS, PHP;\nBouns: Experience with Shopify site designs / SDK.\nPlease include 2 URLs of your Open Source, personal projects into your resume.\n\n", "employment_types": ["Full Time", "Permanent"], "selling_points": ["Websites/ Mobile/ Apps - Senior UXUI Designer", "E-commerce & Transactional Site Design", "Shopify Site Designs / SDK are advantageous"], "locations": ["Kwun Tong"], "categories": ["Design", "Multi-media", "Web Designer", "E-commerce", "Software Development"], "post_time": "2022-01-12T09:02:48Z", "salary": {"currency": null, "max": null, "min": null, "period": "monthly", "term": null}, "salary_visible": false, "title_keywords": ["designer"], "responsibilities": ["design", "develop", "testing", "mobile devices", "ui"], "requirements": {"degrees": ["degree", "bachelor"], "majors": ["creative media", "web design", "design"], "languages": [], "language_level": [], "hard_skills": ["web design", "web development", "google analytics", "web", "php", "adobe xd", "shopify", "html", "css", "photoshop"], "soft_skills": ["solve problems", "creative", "driven"], "languages_combined": []}, "experience_required": {"duration": ["5+ years"], "field": ["ecommerce"]}}, {"job_id": "100003009037691", "location_code": "hk", "company": "TG Human Resource Services Company Limited", "job_title": "Exhibition Designer (3D/ Digital Media) (HK Museum) (Over $30k)", "description": "Work location: Heritage Museum, Sha Tin\nWorking hours: 9am - 6pm (including 1-hour meal break), 5 days' workweek\n\nSalary: $170 per hour (plus SH pay based on HK Labour Ordinance)\n12 month's contract (renewable)\n\nScope of Works:\nTo render animation files to appropriate formats for presenting in different platforms;\nTo edit, retouch and manipulate digitized images for exhibition presentation and publicity uses;\nTo create 3D models of gallery plans by using\u00a0modeling and rendering software;\nTo simulate immersive preview for gallery layout\u00a0plans. To visualize and transform 2D graphical\u00a0ideas into 3D graphics for exhibition presentation\u00a0by applying appropriate textures and lighting\u00a0effects to 31) models;\nTo keep in schedules and be responsible for printing/production process as well as to monitor the quality control of various outputs and delivery schedule;\nTo carry out instant back and forth checking of color tone against various color matching systems for output accuracy;\nTo archive all digital files upon completion of design works for record purpose and to compile different files to prepare exhibition portfolios;\nRequirements:\n\n\nBachelor's Degree in design, preferably in visual communication, graphic design,\u00a0exhibition design or multi-media design (full-time);\nAt least 5 years full-time relevant working experience in graphic, multi-media or exhibition design;\nExperience in museums or cultural institutions is highly preferable;\n\u00a0Proficiency in Macintosh Adobe Photoshop, Adobe illustrator, Adobe InDesign, Adobe After Effects, Adobe Premiere Pro, Sketchup Pro, Form7, 3DMax and Vectorworks etc.\nExperience M desktop publishing;\nGood command of Chinese and English;\nCreative, self-motivated and with good communication skill;\nMature, able to work independently and under pressure;", "employment_types": ["Full Time", "Contract"], "selling_points": ["Good Exposure from Working at Museum", "Flexibility in Work Focus based on Skill Sets", "Experienced in Graphic, Multi-media Design"], "locations": ["Shatin Area"], "categories": ["Design", "Graphics", "Multi-media", "Others"], "post_time": "2022-01-11T03:31:16Z", "salary": {"currency": null, "max": null, "min": null, "period": "hourly", "term": null}, "salary_visible": false, "title_keywords": ["designer"], "responsibilities": [], "requirements": {"degrees": [], "majors": [], "languages": [], "language_level": [], "hard_skills": [], "soft_skills": [], "languages_combined": []}, "experience_required": {"duration": [], "field": []}}, {"job_id": "100003009037474", "location_code": "hk", "company": "DFS Hong Kong Limited", "job_title": "Digital Design Manager , Contract - DFS91121288", "description": "Job Highlights\n\nGraphic design for our magazine and Website\nLayout design of our magazine and our advertising\nArt direction for our photo shooting\n\nResponsibilities:\n\nDesign online/print material for marketing purpose\nWebsite Design\nSimple video shooting and editing\n\nRequirements:\n\n1-2 years related work experience\nBasic knowledge in beauty industry\nBasic html, css knowledge\nBasic video shooting & editing skills\nVideo Editing\n***Please send CV and Portfolio by email to Miss Ng.\n\n", "employment_types": ["Full Time", "Contract"], "selling_points": ["Work Life Balance, Five-day Work Week", "World's Leading Luxury Travel Retailer", "International & Dynamic Working Environment"], "locations": ["Quarry Bay"], "categories": ["Design", "Graphics", "Multi-media", "Web Designer"], "post_time": "2022-01-11T02:55:06Z", "salary": {"currency": null, "max": null, "min": null, "period": "monthly", "term": null}, "salary_visible": false, "title_keywords": ["design manager"], "responsibilities": ["editing", "video shooting", "website", "design"], "requirements": {"degrees": [], "majors": [], "languages": [], "language_level": [], "hard_skills": ["video editing", "css", "basic", "html"], "soft_skills": [], "languages_combined": []}, "experience_required": {"duration": ["1-2 years"], "field": ["related"]}}, {"job_id": "100003009039879", "location_code": "hk", "company": "Meiyume (Hong Kong) Limited", "job_title": "Senior Officer - Brand Marketing", "description": "Responsibilities:\n\nConceptualize, design, create, and edit relevant and engaging creative assets to use across the corporate social media and marketing channels. Including but not limited to storyboarding and creating pictorial and video content for Instagram, LinkedIn, YouTube, trade events and other events/platforms as required\nConceptualize from creative briefs, and create media assets as needed to best suit the campaign direction and intended platform(s)\nSupport the creation and aesthetic clean-up of visual digital communication materials (e.g., digital ad banners, EDM, animated display, social media posts, PowerPoint, etc.)\nBrainstorm and contribute in briefing sessions to drive relevant and trendy content output\nStay on top of trends and maintain awareness of the digital landscape; educate the broader team and key stakeholders of the evolving trends and work together to bring ideas to life\nIdentify visual opportunities for development and enhancement of channels\n\nRequirements:\n\nBachelor\u2019s degree in Design, Marketing or related field\nMinimum of 1 year experience in a similar role, with a passion for storytelling\nWell versed in social media including Instagram, LinkedIn, Tiktok/Douyin, Wechat, etc.\nAbility to ideate, conceptualize, and execute outstanding interactive designs, pictures, and videos with strong creative flair and create emotional engagement\nSolid hands-on experience in designing creative assets and making videos for digital marketing campaigns (e.g., digital ad banners, EDM, animated display and social media posts) with a portfolio to demonstrate your skills\nAdvanced skills and experience in using the Adobe Creative Suite and related programs\nExperience in photography and videography, with ability to operate camera, lighting, and audio equipment\nHighly organized, excellent communication and storytelling skills, with demonstrated ability to problem solve, multitask, and deliver high quality work with fast turnaround times\nExcellent verbal and written communications skills with fluency in written and spoken English\nExceptional attention to detail\nExperience with copywriting and B2B brand marketing is preferred but not a must\nIf you are interested in this opportunity, please apply with your design profolio and resume.", "employment_types": ["Full Time", "Permanent"], "selling_points": ["Exp. in brand marketing and storytelling", "Advance Skill in Adobe Creative Suite", "Well versed in social media account management"], "locations": ["Lai Chi Kok"], "categories": ["Design", "Multi-media", "Marketing / Public Relations", "Marketing - Marketing Communication"], "post_time": "2022-01-11T13:24:26Z", "salary": {"currency": null, "max": null, "min": null, "period": null, "term": null}, "salary_visible": false, "title_keywords": ["senior officer"], "responsibilities": ["social media", "ideas", "edm", "design", "communication", "banners", "maintain", "visual"], "requirements": {"degrees": ["degree", "bachelor"], "majors": ["marketing", "design"], "languages": ["english"], "language_level": ["fluency", "excellent"], "hard_skills": ["adobe creative suite", "wechat"], "soft_skills": ["organized", "advanced", "passion for", "problem solve", "interested in", "communication", "multitask", "hands-on", "attention to detail", "creative"], "languages_combined": [{"language": "english", "language_level": ["fluency", "excellent"]}]}, "experience_required": {"duration": ["minimum of 1 year"], "field": ["brand", "related", "marketing", "digital marketing", "copywriting"]}}, {"job_id": "100003009037675", "location_code": "hk", "company": "FZN International Ltd", "job_title": "Graphic Designer", "description": "Responsibility:\n\n- Handle advertising, event related graphic design projects\n\n- Design and production for event decoration and promotional items\n\n- Supervise and liaise with print vendors\n\n- Provide client servicing and manage projects independently\n\nRequirement:\n\n- Minimum 1 year of related design experiences in agency or production house\n\n- Detail-oriented, responsible, independent and can work in a team\n\n- Strong Drawing Skills and Creative Sense\n\n- Proficient in Adobe Illustrator, Photoshop\n\n-\u00a0Knowledge of 3D and video editing software (Cinema 4D, AfterEffects, Premier Pro) would\u00a0 \u00a0 be an advantage.\n\n- Candidate with no experience will be considered as Design Assistant\n\n- Immediate available is preferable\n\n\u00a0Please send your full resume with current and expected salary and indicate your applied job title to HR\n\n\u00a0\u00a0(Personal data collected will be used for recruitment purpose only.)", "employment_types": ["Full Time", "Permanent"], "selling_points": [], "locations": ["Kowloon Bay"], "categories": ["Design", "Graphics", "Multi-media", "Marketing / Public Relations", "Public Relations - Event Management"], "post_time": "2022-01-11T03:33:40Z", "salary": {"currency": null, "max": null, "min": null, "period": "monthly", "term": null}, "salary_visible": false, "title_keywords": ["graphic designer"], "responsibilities": ["advertising", "graphic design", "event decoration", "design", "manage projects", "liaise with"], "requirements": {"degrees": [], "majors": [], "languages": [], "language_level": [], "hard_skills": ["video editing", "no", "photoshop", "adobe illustrator"], "soft_skills": ["creative", "independent", "responsible", "detail-oriented"], "languages_combined": []}, "experience_required": {"duration": ["minimum 1 year"], "field": ["related", "agency", "design"]}}, {"job_id": "100003009038825", "location_code": "hk", "company": "Prestige Display Limited", "job_title": "Marketing and Graphic Design (Part-time)", "description": "Responsibility\n\nUpdate Marketing brochure and presentation.\nDigital Marketing update Website, Facebook, LinkedIn, YouTube and IG\nGenerate marketing design materials\nOther graphic design and marketing supporting functions.\nRequirements\n\nDiploma or above in Digital Marketing, Marketing, Multimedia, Communication or related disciplines\nA minimum of 3 years of solid experience\n\nGood communication and writing skills in Chinese and English\nExperience in Photoshop,AI, Premier Pro,Canva,Webflow\nFlexible working days, roughly 2-3 days per week\n\nInterested parties please send your detailed resume, past design references and expected salary to\u00a0us.", "employment_types": ["Part Time"], "selling_points": [], "locations": ["Sheung Wan"], "categories": ["Design", "Multi-media", "Marketing / Public Relations", "Digital Marketing"], "post_time": "2022-01-11T07:53:54Z", "salary": {"currency": null, "max": null, "min": null, "period": "monthly", "term": null}, "salary_visible": false, "title_keywords": [], "responsibilities": ["graphic design", "website", "design", "digital marketing", "facebook"], "requirements": {"degrees": ["diploma or above"], "majors": ["related disciplines", "marketing", "digital marketing"], "languages": ["english", "chinese"], "language_level": ["good"], "hard_skills": ["ai", "multimedia", "writing skills", "photoshop"], "soft_skills": ["communication", "flexible", "writing skills"], "languages_combined": [{"language": "english", "language_level": ["good"]}, {"language": "chinese", "language_level": ["good"]}]}, "experience_required": {"duration": ["minimum of 3 years"], "field": []}}]