[{"job_id": "100003009054574", "location_code": "hk", "company": "Taste of Asia Group Limited", "job_title": "Graphic Designer", "description": "Responsibilities\n\n\nPropose design concepts & develop visuals based on images of the group and brands\nResponsible for all graphic design and production of marketing materials including advertisement, menu, e-marketing and packaging etc.\nResponsible for product photo-shooting\nAssist in ad-hoc duties and projects\n\nRequirements\n\n\nHigher Diploma in Graphic Design or related disciplines\nMinimum 3 year\u2019s relevant working experiences. Experience in F&B industry is an advantage\nProficiency in Mac software, AI, Photoshop, InDesign\nInnovative, imaginative and creative, able to show strong initiative\nSelf-motivated and able to work independently under tight deadline\nAttention to detail, good team-player and good time management skill\nMore experience may consider as Senior Position\nImmediate available is preferred\n\nJob location: San Po Kong\n\n\n\u00a0Competitive remuneration package and benefits as below:\n\n5-Day Work Week\n\nMarriage leave\n\nStaff discount\n\nMedical & dental allowance\n\nPerformance bonus\n\nIn-service training course\n\n5 days paternity leave\n\nCompassionate Leave\n\nPromotion opportunities\n\n\u00a0Interested parties may send your detailed resume with expected salary and notice period to:By clicking Apply Now\u00a0\n\nAll information collected will be used for recruitment purpose only.", "employment_types": ["Full Time"], "selling_points": ["5-Day Work Week", "Medical & dental allowance", "Performance bonus"], "locations": ["Wong Tai Sin Area"], "categories": ["Design", "Graphics", "Others"], "post_time": "2022-01-17T10:03:19Z", "salary": {"currency": null, "max": null, "min": null, "period": "monthly", "term": null}, "salary_visible": false, "title_keywords": ["graphic designer"], "responsibilities": ["design concepts", "graphic design", "develop", "photo-shooting", "ad-hoc duties", "marketing materials"], "requirements": {"degrees": ["diploma"], "majors": ["related disciplines", "graphic design"], "languages": [], "language_level": [], "hard_skills": ["indesign", "photoshop", "ai"], "soft_skills": ["self-motivated", "work independently", "team-player", "innovative", "imaginative", "attention to detail", "time management skill", "creative", "initiative"], "languages_combined": []}, "experience_required": {"duration": ["minimum 3 year"], "field": ["f&b"]}}, {"job_id": "100003009031271", "location_code": "hk", "company": "IF Interior Designs & Contracting Co", "job_title": "Senior Interior Designer  /  Designer  /  Assistant Designer", "description": "Requirements:\n\n2 \u2013 6 years of experience in Retail, Commercial or Residential design experience\nProficiency in AutoCAD, 3D Max, Photoshop or Sketch up\nCapability of handling and producing of full set drawings\nMust be detail oriented and show leadership qualities\nHardworking, self-motivated, organized, independent and able to meet deadlines\nResponsible and able to work under pressure\nImmediate availability preferred\nCandidate with less experience will be considered as Assistant Designer\n\nResponsibilities:\n\nPreparation of all presentation materials, including design concept, space planning for all layout and selection of materials\nResponsible for all design drawings, detail drawings & time schedule planning\nCommunicate and coordinate with clients and sub-contractors\nCoordination of site handover and supervise fitting-out progress\n\nFor Interested candidates, please send full resume with expected salary via email or by clicking \u201cApply Now\u201d or contact Ms Wong at 2513-5112 for interview arrangement.\n\nWelcome to visit our website www.ifinterior.com.hk for more information.\n\nPersonal data collected will be used for recruitment purpose only.", "employment_types": ["Full Time", "Permanent"], "selling_points": [], "locations": ["Causeway Bay"], "categories": ["Design", "Interior", "Others"], "post_time": "2022-01-17T07:43:03Z", "salary": {"currency": null, "max": null, "min": null, "period": "monthly", "term": null}, "salary_visible": false, "title_keywords": ["designer", "senior interior designer", "assistant designer"], "responsibilities": ["detail drawings", "design drawings", "design concept", "coordinate with clients", "schedule", "coordination", "planning"], "requirements": {"degrees": [], "majors": [], "languages": [], "language_level": [], "hard_skills": ["sketch up", "max", "photoshop", "autocad"], "soft_skills": ["organized", "self-motivated", "independent", "responsible", "detail oriented", "meet deadlines", "leadership", "hardworking", "work under pressure"], "languages_combined": []}, "experience_required": {"duration": ["6 years"], "field": ["commercial", "retail", "designer", "design"]}}, {"job_id": "100003009053459", "location_code": "hk", "company": "Kidulteam Limited", "job_title": "Product / GraphicDesigner", "description": "\nKidulteam Ltd. is a character merchandise company which engaged in design, manufacturing, distributing and retailing of gifts and confectionery in Hong Kong and Mainland China. To copy with our business expansion, we are now looking for:\n\u2022 Degree or Higher Diploma in Graphic Design or related disciplines.\n\u2022 At least 3 years experiences in plush and giftware design.\n\u2022 Proficient and able to be hands-on with Illustrator, Freehand, Photoshop and Corel Draw etc.\nProduct design in bag/premium/3D skills/Comics experience a plus (not necessary).\nWe offer competitive salary and fringe benefits to the right candidate. Interested parties please forward your detailed resume stating your availability, current and expected salary to [via\u00a0 Apply Now ]\n\n", "employment_types": ["Full Time"], "selling_points": [], "locations": ["Not Specified"], "categories": ["Design", "Graphics", "Interior", "Others"], "post_time": "2022-01-17T07:00:39Z", "salary": {"currency": null, "max": null, "min": null, "period": "monthly", "term": null}, "salary_visible": false, "title_keywords": [], "responsibilities": ["graphic design", "product design", "design"], "requirements": {"degrees": ["diploma", "degree"], "majors": ["related disciplines", "graphic design"], "languages": [], "language_level": [], "hard_skills": ["plus", "illustrator", "photoshop"], "soft_skills": ["hands-on"], "languages_combined": []}, "experience_required": {"duration": ["at least 3 years"], "field": ["product design", "design"]}}, {"job_id": "100003009052271", "location_code": "hk", "company": "Lubuds F&B Group", "job_title": "Graphics Designer", "description": "Responsibilities:\n\n\nDesign and develop toys from concept, idea sketch, presentation to production\u00a0for the Dolls Team\nGenerate sketches, renderings, control drawings, fabric art creation to conduct model reviews and artwork directions\nConduct researches on new technologies, materials, production processes and trends so as to support product development process\nWork with various parties and ensure efficient design and development processes\n\nRequirements:\n\nDegree in Product Design, Industrial Design\u00a0or any related disciplines\n3-5 years of product design experience preferably from toys industry\nWith good sketching, rendering and drafting techniques\nHands on experience in 2D and 3D design software such as Photoshop and Illustrator\nGood command of written and spoken English and Chinese\n\nWho Should Join Us:\n\nWe are not only looking for the right experience and skill set, but also for attitude, potential & cultural fit.\n\nIf you are creative, energetic, passionate with a growth mindset and devoted to developing your future career in the world\u2019s leading toy company, you are welcome to be a part of our team and we will play & grow together!\u00a0\n\nWhat We Offer:\n\nAs a caring company, we are committed to providing engaging and work-life balance environment, competitive remuneration, comprehensive fringe benefits, and progressive career opportunities to our people.\u00a0 \u00a0\n\nOur benefits include:\n\nHalf-Day off every Friday\nFlexi Working Hours\nAnnual Leave and Company Holidays\nGroup Medical and Life Insurance\nMPF\nComprehensive Wellness Programs\u00a0\nHow To Apply:\n\nInterested parties please click \u201cApply Now\u201d to send your full resume (in Microsoft Word or PDF format), current and expected salary to us for review.\n\nApplicants not invited for interview within 6 weeks may assume their application unsuccessful. All information will be treated in strictest confidence and used solely for recruitment purpose.", "employment_types": ["Full Time", "Permanent"], "selling_points": [], "locations": ["Aberdeen"], "categories": ["Design", "Graphics", "Others"], "post_time": "2022-01-17T02:37:33Z", "salary": {"currency": null, "max": null, "min": null, "period": "monthly", "term": null}, "salary_visible": false, "title_keywords": ["designer"], "responsibilities": ["control", "design and develop", "design", "sketches", "drawings"], "requirements": {"degrees": ["degree"], "majors": ["related disciplines", "design"], "languages": ["english", "chinese"], "language_level": ["good command"], "hard_skills": ["illustrator", "photoshop"], "soft_skills": ["passionate", "creative", "hands on", "devoted", "energetic"], "languages_combined": [{"language": "english", "language_level": ["good command"]}, {"language": "chinese", "language_level": ["good command"]}]}, "experience_required": {"duration": ["3-5 years"], "field": ["toys", "product design", "design"]}}, {"job_id": "100003009054835", "location_code": "hk", "company": "Mattel Asia Pacific Sourcing Ltd", "job_title": "Product Designer", "description": "- Creating event design. Execute from concept to design, artwork output and print production.\n\n- Concept development, visualization and hands on design for key visual.\n\n\n- Degree holder in visual communication related disciplines;\n\n- Experience in design research, divergent exploration, conceptual development;\n\n- Strong graphic and art sense, creative and passionate;\n\n- Proficiency in Adobe Illustrator, Photoshop, InDesign, affect effect\u2026etc.\n\n- Experience in storyboard, photo & video shooting technique with editing;\n\n- Experience in event decoration design is a plus;\n\n- Self-motivated, energetic, with the ability to work independently;\n\n- Good communication skills in English, Cantonese and Mandarin;\n\n- Able to work under pressure with tight deadline and multi-task;\n\n- Less experience will be considered as Graphic Designer.", "employment_types": ["Full Time", "Permanent"], "selling_points": ["Degree in Product or Industrial Design", "3-5 years of product design experience", "With toys design experience a plus"], "locations": ["Tsim Sha Tsui"], "categories": ["Design", "Graphics", "Industrial / Product", "Others"], "post_time": "2022-01-17T11:33:10Z", "salary": {"currency": null, "max": null, "min": null, "period": "monthly", "term": null}, "salary_visible": false, "title_keywords": ["product designer"], "responsibilities": ["visualization", "conceptual development", "event decoration", "design", "communication", "video shooting", "visual", "editing", "artwork output", "work under pressure"], "requirements": {"degrees": ["degree holder"], "majors": ["related disciplines"], "languages": ["cantonese", "english", "mandarin"], "language_level": ["good"], "hard_skills": ["plus", "indesign", "adobe illustrator", "visual communication", "photoshop"], "soft_skills": ["passionate", "communication skills", "self-motivated", "work independently", "multi-task", "communication", "energetic", "hands on", "creative", "work under pressure"], "languages_combined": [{"language": "cantonese", "language_level": ["good"]}, {"language": "english", "language_level": ["good"]}, {"language": "mandarin", "language_level": ["good"]}]}, "experience_required": {"duration": [], "field": ["photo", "research", "designer", "development", "design", "video shooting", "graphic", "editing"]}}, {"job_id": "100003009054648", "location_code": "hk", "company": "Aeon Stores (Hong Kong) Co Ltd", "job_title": "Graphic Designer (Ref.: JDB/Design)", "description": "Responsibilities -\n\nSupport team members for research, benchmark, design and development of packaging construction in different product categories, i.e. Domestic Appliances, Consumer Electronic and Accessories\nProduce print ready artwork files and art direct photography\u00a0\nManage the packaging and artwork development from concept to production and fulfill all required administration\nEnsure the artwork meets design standards in line with sourcing strategy and brand guidelines\nCommunicate with suppliers to ensure accuracy in packaging construction, die-cuts, artwork and print-proofs (colour, material, artwork furnishing, presentation, bar code\nCollaborate with agencies to perform photo retouching and pre-press quality monitoring.\n\u00a0Requirements \u2013\nDiploma or above in Graphic Design or related disciplines\nAt least 1 year\u2019s hands-on graphic design experience\nFluent in adobe CS software\nGood communication skill in both spoken and written English, Mandarin will be bonus\nWe offer attractive remuneration package including work from home policy, 13-instalment salary, discretionary bonus,\u00a0life, medical, dental, eyecare insurances to the right candidate.\u00a0Interested applicants\u00a0please send\u00a0your detailed resume with portfolio, current and expected salary and the\u00a0availability to Human Resources Department, Currys Sourcing Limited\u00a0by clicking \"APPLY NOW\"\u00a0or by post:\nHuman Resources Department\nCurrys Sourcing Limited\n31/F, AXA Tower, Landmark East\n100 How Ming Street, Kwun Tong\nKowloon\nPersonal Data collected will be used for recruitment purposes only. Applicants who are not invited within 2 months may consider their application unsuccessful. Personal data of unsuccessful applicants will be retained for a period of up to 6 months from the date of rejecting applicants and will then be destroyed.", "employment_types": ["Full Time"], "selling_points": ["Assist in developing promotion materials", "Perform ad hoc projects as assigned", "Banner, poster, POP, leaflet"], "locations": ["Tsuen Wan Area"], "categories": ["Design", "Others"], "post_time": "2022-01-17T10:24:11Z", "salary": {"currency": null, "max": null, "min": null, "period": "monthly", "term": null}, "salary_visible": false, "title_keywords": ["graphic designer"], "responsibilities": ["product categories", "communicate with", "collaborate with", "photo retouching", "artwork development", "monitoring", "quality", "design", "brand guidelines", "administration"], "requirements": {"degrees": ["diploma or above"], "majors": ["related disciplines", "graphic design"], "languages": ["english", "mandarin"], "language_level": ["good"], "hard_skills": ["adobe cs"], "soft_skills": ["hands-on", "communication skill", "detailed"], "languages_combined": [{"language": "english", "language_level": ["good"]}, {"language": "mandarin", "language_level": ["good"]}]}, "experience_required": {"duration": ["at least 1 year"], "field": ["graphic design"]}}, {"job_id": "100003009054430", "location_code": "hk", "company": "Currys Sourcing Limited", "job_title": "Junior Packaging Designer", "description": "\n\u8077\u8cac :\u8ca0\u8cac\u63d2\u82b1\u53ca\u92b7\u552e\u82b1\u54c1\n\n\u8cc7\u6b77 :\u5c0f\u516d\u7a0b\u5ea6; 2\u5e74\u7d93\u9a57; \u4e00\u822c\u7cb5\u8a9e; \u4e00\u822c\u666e\u901a\u8a71; \u4e00\u822c\u82f1\u8a9e\n\n\u5f85\u9047 :\u6bcf\u5c0f\u6642$80.00 - $100.00, \u4e0a\u53489\u6642\u81f3\u4e0b\u534811\u6642, \u6bcf\u9031\u5de5\u4f5c5\u5929\u81f36\u5929,\u8f2a\u4f11, \u6bcf\u5929\u5de5\u4f5c 5 - 10 \u5c0f\u6642\n\n\u7533\u8acb\u9808\u77e5 :\u6c42\u8077\u8005\u53ef\u81f4\u96fb56143678\u8207\u570b\u4ed5\u5ee3\u544a\u50b3\u5a92\u6709\u9650\u516c\u53f8\u90ed\u5c0f\u59d0\u806f\u7d61\u3002\n\n", "employment_types": ["Full Time", "Permanent"], "selling_points": ["Attractive Remuneration Package", "Comprehensive Wellbeing Programme", "Work-life Balance"], "locations": ["Kwun Tong"], "categories": ["Design", "Others"], "post_time": "2022-01-17T09:30:37Z", "salary": {"currency": null, "max": null, "min": null, "period": "monthly", "term": null}, "salary_visible": false, "title_keywords": ["designer", "junior"], "responsibilities": [], "requirements": {"degrees": [], "majors": [], "languages": [], "language_level": [], "hard_skills": [], "soft_skills": [], "languages_combined": []}, "experience_required": {"duration": [], "field": []}}, {"job_id": "100003009052278", "location_code": "hk", "company": "Cathay Pacific Airways Ltd", "job_title": "Brand Manager", "description": "You will be joining our Project Management Team with an opportunity to build a career in jewellery creative aspect:\u00a0\n\nWhat You Do\n\nPerform in planning and execution of product development projects, including but not limited to set project brief, analysis sales data, implement schedule and monitor progress\nCoordinate with both internal and external parties for project progression\nResponsible for preparing internal reporting materials\nAssist in preparation and coordination of presentation materials\nHandle ad-hoc project as assigned by supervisor\nWho Will Thrive\n\nHigher diploma or above in business or related disciplines, with 1- 3 years of relevant experience. \u00a0Experience in retail jewellery will be advantage\nProficient in MS Word, Excel, PowerPoint and Chinese word processing\nWell-organized, meticulous and multi-tasking with strong sense of responsibility\nGood team player with strong interpersonal & communication skills\nGood command of written and spoken English, Cantonese and Mandarin\nImmediately available is highly preferred\n\u00a0Benefits\n5-day work\nCompetitive salary, staff meal,\u00a0medical and dental insurance, life insurance\nVarious types of leave, e.g. Family-friendly leave, self-development leave,\u00a0Examination leave, marriage leave, birthday\u00a0leave, volunteer service leave, etc\nWe offer excellent career opportunities, attractive remuneration package & benefits to the right candidate.\u00a0Interested parties please apply by clicking \"Apply Now\" with a full resume stating the latest and expected salary.\nAll information collected will be used for recruitment purposes only.", "employment_types": ["Full Time", "Permanent"], "selling_points": ["8 years\u2019 experience in Brand, Design", "Development of the Cathay\u2019s brand strategy", "Travel Benefits, 5-day work, Medical Benefits"], "locations": ["Lantau Island"], "categories": ["Design", "Others", "Marketing / Public Relations", "Management", "Marketing - Brand / Product Management"], "post_time": "2022-01-17T02:38:30Z", "salary": {"currency": null, "max": null, "min": null, "period": "monthly", "term": null}, "salary_visible": false, "title_keywords": ["manager"], "responsibilities": ["ad-hoc", "reporting", "monitor progress", "data", "analysis", "internal and external parties", "coordinate with", "communication", "project management", "schedule", "coordination", "planning"], "requirements": {"degrees": ["higher diploma or above"], "majors": ["related disciplines", "business"], "languages": ["cantonese", "english", "chinese", "mandarin"], "language_level": ["good command", "proficient"], "hard_skills": ["excel", "chinese word processing", "analysis", "powerpoint", "project management", "ms word"], "soft_skills": ["meticulous", "good team player", "communication skills", "responsible", "sense of responsibility", "interpersonal", "well-organized", "project management", "multi-tasking", "coordination", "creative", "presentation"], "languages_combined": [{"language": "cantonese", "language_level": ["good command"]}, {"language": "english", "language_level": ["good command"]}, {"language": "chinese", "language_level": ["proficient"]}, {"language": "mandarin", "language_level": ["good command"]}]}, "experience_required": {"duration": ["1- 3 years"], "field": ["related", "business", "relevant experience", "retail"]}}, {"job_id": "100003009053794", "location_code": "hk", "company": "IMY Media Limited", "job_title": "\u63d2\u82b1\u5e2b", "description": "Roles and Responsibilities:\n\nDesign and produce graphics, online banners, storyboards, website layouts and animated infographics\nDevelop after effects for video production\u00a0\n\n\nJob Requirement:\n\nDegree/Diploma/ Certificate in Graphic Design or related disciplines;\nMinimum 5 years graphic design experience preferred;\nSelf motivated, responsible, mature and able to handle multiple projects independently;\nProficiency in PC, experience in using Photoshop, Illustrator, Indesign and After Effect etc.;\nGood presentation skill and strong creativity;\nAble to work under pressure, meet tight deadline and willing to work overtime if needed;\nDrawing skill is an advantage;\nKnowledge in video shooting, recording, editing & post-production for all kinds of video is an advantage;\n5.5 days\u2019 work per week\n\nInterested parties please click \u201cApply Now\" to submit your complete resume with\u00a0compensation history, expected salary and REFERENCE NUMBER or by\u00a0fax to\u00a02798 2925.\n\nWe are an equal opportunity employer and welcome applications from all qualified candidates. Information provided will be treated in strict confidence and only be used for recruitment related purpose. Applicant who is not invited for an interview within 6 weeks may consider their application not successful. All personal data of unsuccessful applicants will be destroyed within 6 months.", "employment_types": ["Part Time"], "selling_points": [], "locations": ["Tin Hau"], "categories": ["Others", "Agriculture / Forestry / Fishing", "Design", "Interior", "Others"], "post_time": "2022-01-17T07:31:32Z", "salary": {"currency": null, "max": null, "min": null, "period": "hourly", "term": null}, "salary_visible": false, "title_keywords": [], "responsibilities": ["graphics", "video production", "website", "design", "develop", "banners", "storyboards"], "requirements": {"degrees": ["certificate", "diploma", "degree"], "majors": ["related disciplines", "graphic design"], "languages": [], "language_level": [], "hard_skills": ["presentation skill", "indesign", "illustrator", "pc", "after effect", "photoshop"], "soft_skills": ["presentation skill", "work overtime", "independently", "responsible", "mature", "self motivated", "meet tight deadline", "work under pressure"], "languages_combined": []}, "experience_required": {"duration": ["minimum 5 years"], "field": ["graphic design"]}}, {"job_id": "100003009054280", "location_code": "hk", "company": "CHOW TAI FOOK JEWELLERY CO LTD", "job_title": "Associate, Jewellery Creative Centre", "description": "Accountabilities \u2013 Key Result Areas\n\n\nAssist Senior Designer in completing the whole process of the development from themes and concept, presentation of styling, sketches, fitting session until pre-production sample\nResearch of seasonal themes, fabrications and material and colors etc.\nWork closely with merchandising and factories to facilitate development processes and schedules from product development, sourcing of fabrics and trims, sample fitting, etc.\nAssist preparations of seasonal design presentations to buyer and frontline operations\nExperience / Qualification Requirements\n\n\nDegree holder in design related discipline\n3-4 years solid experience in fashion design\nBe passionate about the brand\u2019s identity, with personal charisma and visions in international fashion trend\nAbility to research and apply market information\nCreative, communicative and be able to collaborate with business teams to achieve brand objectives\n\nCompetitive remuneration and benefit package will be offered to the right candidate. Please submit your application by clicking \"Apply Now\" below.\n\n\n\nAll data collected is for recruitment purpose only.", "employment_types": ["Full Time"], "selling_points": ["Project Management", "Jewellery Creative Projects", "5-day work"], "locations": ["Kwai Hing"], "categories": ["Admin & HR", "Clerical / Admin Staff", "Design", "Others"], "post_time": "2022-01-17T09:01:32Z", "salary": {"currency": null, "max": null, "min": null, "period": "monthly", "term": null}, "salary_visible": false, "title_keywords": ["associate", "creative"], "responsibilities": ["collaborate with", "market information", "data", "schedules", "operations", "merchandising", "teams", "sketches", "design", "presentations", "recruitment", "pre-production"], "requirements": {"degrees": ["degree holder"], "majors": ["design"], "languages": [], "language_level": [], "hard_skills": ["presentations"], "soft_skills": ["creative", "presentation", "passionate about"], "languages_combined": []}, "experience_required": {"duration": ["3-4 years"], "field": ["fashion design"]}}, {"job_id": "100003009054911", "location_code": "hk", "company": "Bastille Post Company Limited \u300a\u5df4\u58eb\u7684\u5831\u300b", "job_title": "Art Designer \u2013 Online Marketing", "description": "My client is from well-known cryptocurrency platform with global exposure.\u00a0\n\n\nResponsibilities:\n\nCreate compelling mobile app & Website user interface designs\nWork closely with product managers, project manager and engineers to validate, iterate and execute designs on time\nResponsible for all design process, from initial concept discovery, user journey mapping, and usability testing through to the execution of final UI design details\nProduce high quality UX design solutions through wireframes, visual and graphic designs, flow diagrams, storyboards, site maps, and prototypes\n\n\u00a0Requirements:\n\nHigher Diploma or above in Web Design / Multimedia Design / Graphic Design or related discipline.\nAt least 3 years solid experience in UI / UX design work, with experience of a full cycle project\nExperience in digital assets and cryptocurrency industry and basic knowledge in stock market would be an advantage\nKnowledgeable in design and wireframe tools like Adobe Creative Suite, Sketch, InVision or related UX/UI software\nA portfolio of professional UI/UX design work for mobile platforms\nUp to date with current trends and information within UI knowledge\nGood communication, detail orientated and organizational skill\nGood spoken and written English", "employment_types": ["Full Time", "Permanent"], "selling_points": [], "locations": ["Kwun Tong"], "categories": ["Design", "Graphics", "Multi-media", "Others"], "post_time": "2022-01-18T02:04:05Z", "salary": {"currency": null, "max": null, "min": null, "period": "monthly", "term": null}, "salary_visible": false, "title_keywords": ["designer"], "responsibilities": ["mobile app", "design solutions", "quality", "website", "design", "testing", "graphic designs", "user interface", "visual", "ui", "storyboards"], "requirements": {"degrees": ["higher diploma or above"], "majors": ["multimedia design", "web design", "graphic design"], "languages": ["english"], "language_level": ["good"], "hard_skills": ["web design", "basic", "mobile", "multimedia", "cryptocurrency", "adobe creative suite"], "soft_skills": ["communication", "creative", "organizational skill", "detail orientated"], "languages_combined": [{"language": "english", "language_level": ["good"]}]}, "experience_required": {"duration": ["at least 3 years"], "field": ["digital", "design"]}}, {"job_id": "100003009053511", "location_code": "hk", "company": "Bape Hong Kong Limited", "job_title": "Fashion Designer", "description": "- Creating event designs, drawings, and renderings;\n\n- Prepare full-set drawings and 2D production drawings;\n\n- Ensure venue specifications are well understood; maintain specs for floor plan, reflected ceiling plans, and elevations;\n\n- Degree or Diploma holder in Design;\n\n- Proficiency in AutoCAD, 3d Studio Max, Sketchup, Adobe Illustrator, Photoshop, InDesign\u2026etc.;\n\n- Self-motivated, energetic, with the ability to work independently;\n\n- Knowledge of materials, details, construction methods, and standards;\n\n- Experience in the retail, boutiques, stores and fixtures are advantages;\n\n- Experience in event decoration and exhibition design is a plus;\n\n- Able to work under pressure with tight deadline and multi-task;", "employment_types": ["Full Time"], "selling_points": ["3-4 years solid experience in fashion design", "Complete the whole process of the development", "Fresh graduate will also be considered"], "locations": ["Southern Area"], "categories": ["Design", "Fashion", "Graphics", "Others"], "post_time": "2022-01-17T07:04:31Z", "salary": {"currency": null, "max": null, "min": null, "period": "monthly", "term": null}, "salary_visible": false, "title_keywords": ["fashion designer"], "responsibilities": ["event decoration", "design", "drawings", "maintain", "specifications", "plan", "plans", "work under pressure"], "requirements": {"degrees": ["diploma holder", "degree"], "majors": ["design"], "languages": [], "language_level": [], "hard_skills": ["plus", "indesign", "sketchup", "adobe illustrator", "autocad", "max", "photoshop"], "soft_skills": ["self-motivated", "work independently", "multi-task", "energetic", "work under pressure"], "languages_combined": []}, "experience_required": {"duration": [], "field": ["retail", "design"]}}, {"job_id": "100003009053147", "location_code": "hk", "company": "One Arrow Consulting Asia Limited", "job_title": "UI Designer - Cryptocurrency", "description": "Professional member of the Hong Kong Institute of Landscape Architect (HKILA) elected on or after 1.1.1997, or revalidated by the HKILA if elected before 1.1.1997, or equivalent;\nGrade E (Level 2) or above in Chinese Language and English Language in HKCEE/HKDSE or equivalent;\nAt least 1 years' appropriate post-qualification experience;\nStrong interpersonal communication skills.\n\nWe offer competitive salary package and career development opportunity to the successful candidate. Interested parties may send your full resume, present and expected salary, available date and contact number by clicking \"Apply Now\".\n\n\n\nTo visit our website for more information: www.ableeng.com.hk\n\n(As an Equal Opportunities Employer, Able is committed to eliminating discrimination in employment. The vacancy advertised is open to all applicants meeting the basic entry requirement irrespective of their disability, sex, marital status, pregnancy, age, family status, sexual orientation or race etc. Applicants not hearing from us within 6 months may consider their applications unsuccessful. Personal data collected will be used for recruitment related purposes only.)", "employment_types": ["Full Time", "Permanent"], "selling_points": ["Global Exposure", "Digital Assets", "Attractive Package"], "locations": ["Central & Western Area"], "categories": ["Design", "Others", "Information Technology (IT)", "UI/UX Designer"], "post_time": "2022-01-17T06:07:13Z", "salary": {"currency": null, "max": null, "min": null, "period": "monthly", "term": null}, "salary_visible": false, "title_keywords": ["ui designer"], "responsibilities": ["communication"], "requirements": {"degrees": ["hkdse"], "majors": [], "languages": ["english", "chinese"], "language_level": [], "hard_skills": [], "soft_skills": ["communication skills", "interpersonal"], "languages_combined": [{"language": "english", "language_level": []}, {"language": "chinese", "language_level": []}]}, "experience_required": {"duration": ["at least 1 years"], "field": ["post-qualification"]}}, {"job_id": "100003009042766", "location_code": "hk", "company": "ISS-Vision Events Limited", "job_title": "3D Designer", "description": "Responsibilities:\nResponsible for in-house design projects from concept creative to final production independently\nLiaise and coordinate with suppliers / production house to ensure all promotional materials are produced up to company standard\nProvide graphic design for promotion materials, such as advertisement, POP and visual merchandise from conception to production\nAd hoc assignments as per management\u2019s request\nRequirements:\nDiploma\u00a0or above in graphic design or related disciplines\nMinimum\u00a03\u00a0years relevant working experience, preferably in F&B industries\nProficient in Photoshop, Illustrator, InDesign, and other design software\nExperience in photography, video editing and filming is an advantage\nSelf-motivated, independent, creative\nAble to work under pressure and perform multi-tasks with tight timescales\u00a0\nDetailed minded, well organized and good communication skills\nGood command of both spoken and written English and Chinese\nPortfolio is required for interview reference\nApplicant with less experience would be considered as Junior Graphics Designer\n\n\n\nWe offer attractive remuneration package and excellent career opportunities to the right candidate. Interested parties,\u00a0please click on below button \u201cApply Now\u201d.\n\nInformation collected will be treated in strict confidence and used for recruitment purposes only.\u00a0 Only suitable candidates will be notified.", "employment_types": ["Full Time", "Permanent"], "selling_points": ["Exhibitions and Events", "Prepare full-set drawings", "Event decoration and exhibition design"], "locations": ["Wong Tai Sin Area"], "categories": ["Design", "Industrial / Product", "Others"], "post_time": "2022-01-16T21:50:12Z", "salary": {"currency": "HKD", "max": 29999, "min": 17000, "period": "monthly", "term": null}, "salary_visible": true, "title_keywords": ["designer"], "responsibilities": ["liaise", "management", "graphic design", "coordinate with", "design", "promotional materials", "ad hoc assignments", "visual"], "requirements": {"degrees": ["diploma or above"], "majors": ["related disciplines", "graphic design"], "languages": ["english", "chinese"], "language_level": ["good command"], "hard_skills": ["graphics", "indesign", "illustrator", "video editing", "photoshop"], "soft_skills": ["communication skills", "self-motivated", "independent", "multi-tasks", "well organized", "detailed", "creative", "work under pressure"], "languages_combined": [{"language": "english", "language_level": ["good command"]}, {"language": "chinese", "language_level": ["good command"]}]}, "experience_required": {"duration": ["minimum 3 years"], "field": ["video", "designer", "relevant working experience", "f&b", "editing"]}}, {"job_id": "100003009053950", "location_code": "hk", "company": "Able Engineering Company Limited", "job_title": "Professional Landscape Designer", "description": "Degree or diploma holder in design or related disciplines\nMinimum\u00a01-3 years solid working experience\nFresh graduates or less experienced applicants may be considered as Junior designer\nExposure in the field of interior & graphic is a plus\nCompetency in Auto CAD, Photoshop and 3Ds Max or related\u00a0softwares\nGood visualization and presentation skills\nCreative and responsible\nProactive, a team player with good presentation\u00a0 and communication skills\nAbility to work independently\n\nWe offer a 5-day work week, including 12 days annual leave and double pay.\u00a0\u00a0\n\nInterested parties please send full resume with date of availability, present & expected salary and portfolio to email by clicking \"Apply Now\".\n\nPersonal data will be used for recruitment purposes only.", "employment_types": ["Full Time", "Permanent"], "selling_points": [], "locations": ["Not Specified"], "categories": ["Building & Construction", "Architectural Services", "Design", "Others", "Building / Construction / QS"], "post_time": "2022-01-17T07:49:34Z", "salary": {"currency": null, "max": null, "min": null, "period": "monthly", "term": null}, "salary_visible": false, "title_keywords": ["designer"], "responsibilities": ["communication", "visualization", "design"], "requirements": {"degrees": ["diploma holder", "degree"], "majors": ["related disciplines", "design"], "languages": [], "language_level": [], "hard_skills": ["plus", "auto cad", "3ds max", "photoshop"], "soft_skills": ["communication skills", "work independently", "proactive", "responsible", "presentation skills", "team player", "creative", "presentation"], "languages_combined": []}, "experience_required": {"duration": ["minimum 1-3 years"], "field": []}}, {"job_id": "100003009055240", "location_code": "hk", "company": "Mindscape Interior Architecture Limited", "job_title": "Furniture designer (5-day work & double pay)", "description": "What You Do\nYou will be joining our Strategic Planning Team with an opportunity to build a career that leads the development of jewellery creation:\u00a0\n\n\nContribute to the development of projects and responsible for researching, planning, executing, and preparing creative briefs in line with project needs & goals\nResponsible for leading, managing and planning social media content that aims to promote culture-inspired jewellery to a global audience\nAssist in interpreting market research and data analysis, and contribute to formulation of strategic goals\nBring new ideas to the team and convey them through effective presentation material to inspire relevant stakeholders\nPerform other ad-hoc tasks as assigned in an efficient and timely manner\nWho Will Thrive\n\nDegree holder in Art Administration / Management, Marketing, Jewellery or other relevant discipline with 1-3 years\u2019 experience in creative or jewellery industry. Basic knowledge of luxury jewellery brands & products is an advantage\nCreative, open-minded and a detail-oriented multitasker\nExcellent organizational and planning skills with the ability to coordinate multiple projects simultaneously\nA good team player with strong interpersonal skills and able to take initiative & work independently\nExcellent command in written and spoken English, Mandarin and Cantonese\nProficiency in PowerPoint and Microsoft Word; Photoshop and/or Excel a plus\nFresh graduates are also welcome\n\u00a0Benefits\n5-day work\nCompetitive salary, staff meal,\u00a0medical and dental insurance, life insurance\nVarious types of leave, e.g. Family-friendly leave, self-development leave,\u00a0Examination leave, marriage leave, birthday leave, volunteer service leave, etc\nWe offer excellent career opportunities, attractive remuneration package & benefits to the right candidate.\u00a0Interested parties please apply by clicking \"Apply Now\" with a full resume stating the latest and expected salary.\nAll information collected will be used for recruitment purposes only.", "employment_types": ["Full Time", "Permanent"], "selling_points": ["Degree or diploma holder in design", "junior designer", "5-day work week"], "locations": ["North Point"], "categories": ["Building & Construction", "Architectural Services", "Design", "Interior", "Others"], "post_time": "2022-01-18T01:54:40Z", "salary": {"currency": null, "max": null, "min": null, "period": "monthly", "term": null}, "salary_visible": false, "title_keywords": ["designer"], "responsibilities": ["administration", "management", "ideas", "strategic planning", "ad-hoc tasks", "market research", "data analysis", "coordinate", "social media content", "executing", "multiple projects", "planning"], "requirements": {"degrees": ["degree holder"], "majors": ["marketing", "art"], "languages": ["cantonese", "english", "mandarin"], "language_level": ["excellent"], "hard_skills": ["excel", "plus", "microsoft word", "basic", "analysis", "powerpoint", "photoshop"], "soft_skills": ["efficient", "initiative", "good team player", "work independently", "organizational and planning skills", "responsible", "open-minded", "timely", "detail-oriented", "interpersonal skills", "creative", "presentation"], "languages_combined": [{"language": "cantonese", "language_level": ["excellent"]}, {"language": "english", "language_level": ["excellent"]}, {"language": "mandarin", "language_level": ["excellent"]}]}, "experience_required": {"duration": ["1-3 years"], "field": ["management", "marketing", "administration"]}}, {"job_id": "100003009054261", "location_code": "hk", "company": "CHOW TAI FOOK JEWELLERY CO LTD", "job_title": "Associate \u2013 Jewellery Creative Centre (Strategic Planning Team)", "description": "The Job Scope\nYou will:\n\nSupport Customer Digital Experience Development Manager in delivering user centred digital application projects across the Club\u2019s range of digital channels, including mobile app, website, e-commerce and cross-media platforms.\nTransform business analysis, customer feedback and/or market research outcomes in to digital business insights and product requirement.\nResponsible for interaction design of various digital channels in the Club\u2019s\nExpert in user experience design from user\u2019s requirement analysis, through information architecture, wireframes, user flow, behavioural design and prototype for a variety of mobile/web products.\nHaving sophisticated experience in conducting agile research, including needs finding research, conceptual validation, usability testing etc.\nPassionate and skilful for translating research findings into tangible designs\nBe part of the scrum team, work closely with development team to maximize value of sprint deliveries\nDemonstrable experience with Agile methodologies such as Kanban, Scrum and tools such as Jira, Confluence and Slack.\n\nAbout You\nYou should have:\n\nA bachelor degree or above in interaction design, industrial design, computer science, psychology or other relevant disciplines.\nAt least 6 years of proven working experience in Consulting / Digital Solution / Technology project management\nSolid working experience within an agile team on digital products implementation\nStrong interpersonal skills with internal and external stakeholders. Easily understand people idea and turn it into action.\nExcellent written and verbal communication (English and Chinese).\nAn excellent working attitude, self-motivated and being a team player.\nProficiency in design and prototyping software (e.g. Adobe Creative Suite, Sketch, Axure) is a must\nKnowledge in Horse Racing and/or Football betting is a definite advantage\nUnderstanding in latest digital trend, including Gamification and Artificial Intelligence is a plus\nA portfolio demonstration during the interview.\nCandidate with less experience may consider as Senior Officer\n\n\nTerms of Employment\nThe level of appointment will be commensurate with qualifications and experience.\n\nHow to Apply\nPlease send your resume, complete with expected salary and job reference by clicking the Apply Now button\n\nWe are an equal opportunity employer. Personal data provided by job applicants will be used strictly in accordance with the Club's notice to employees and prospective employees relating to the Personal Data (Privacy) Ordinance. A copy of which will be provided immediately upon request.", "employment_types": ["Full Time"], "selling_points": ["Strategic Planning for Jewellery Development", "Academic & Market Research and Data Analysis", "Marketing"], "locations": ["Kwai Hing"], "categories": ["Design", "Others"], "post_time": "2022-01-17T08:59:14Z", "salary": {"currency": null, "max": null, "min": null, "period": "monthly", "term": null}, "salary_visible": false, "title_keywords": ["associate", "creative"], "responsibilities": ["mobile app", "software", "consulting", "analysis", "website", "design", "market research", "user experience", "testing", "project management", "implementation", "communication", "business analysis", "personal data", "architecture"], "requirements": {"degrees": ["degree or above", "bachelor"], "majors": ["psychology", "computer science", "design"], "languages": ["english", "chinese"], "language_level": ["excellent"], "hard_skills": ["plus", "agile", "e-commerce", "analysis", "web products", "mobile", "project management", "adobe creative suite"], "soft_skills": ["sophisticated", "passionate", "self-motivated", "agile", "responsible", "communication", "project management", "interpersonal skills", "team player", "creative"], "languages_combined": [{"language": "english", "language_level": ["excellent"]}, {"language": "chinese", "language_level": ["excellent"]}]}, "experience_required": {"duration": ["at least 6 years"], "field": ["research", "consulting", "e-commerce", "development", "design", "testing", "project management", "digital", "media", "team"]}}, {"job_id": "100003009052736", "location_code": "hk", "company": "The Hong Kong Jockey Club", "job_title": "Assistant Customer Digital Experience Development Manager (UX lead)", "description": "Job Description\n\nMy client is an interior design firm based in Hong Kong. They are specializing an international brand including retail and commercial design projects. The boutique locate for K11 MUSEA, 1881 Heritage, Ocean Terminal, Element Shop, Macau and China.\n\nWelcome to join our team to cope with our rapid expansion in both mainland China and Hong Kong.\n\nRequirements\n\nDiploma holder or above in Interior Design\nBasic\u00a0computer knowledge in AutoCAD\u00a0and\u00a0Photoshop are\u00a0preferable\nCapable in handling project independently for interior designer\n\nResponsible of site management, site survey,\u00a0 site staff supervision, etc.\u00a0for interior designer\n\nBasic Cantonese, English & Putonghua\nTraveling to overseas/ PRC is required\nMin 2 years site experience for interior designer\u00a0\n\nResponsibilities:\u00a0\n\nAssist the Senior Interior Designer\nDealing with clients, contractors, architectures, vendors and project team members\nResponsible for design drawings and documentation including concept design and development, construction drawing, materials sourcing and selection\nIdentify and understand clients\u2019 needs and provide customer services\n\nWe offer\u00a0double pay,\u00a0bank holidays, 5 1/2day work,\u00a0annual leave and MPF. Interested candidates please send your application letter with CV, portfolio and salary expectations by clicking 'Apply Now'", "employment_types": ["Full Time"], "selling_points": ["Demonstrable experience with Agile methodologies", "6 yr of Consulting / Digital Solution / Technology", "A portfolio demonstration during interview"], "locations": ["Causeway Bay"], "categories": ["Design", "Others", "Information Technology (IT)", "Others", "UI/UX Designer"], "post_time": "2022-01-17T03:52:14Z", "salary": {"currency": null, "max": null, "min": null, "period": null, "term": null}, "salary_visible": false, "title_keywords": ["manager", "lead", "assistant"], "responsibilities": ["design"], "requirements": {"degrees": ["diploma holder"], "majors": ["design"], "languages": ["cantonese", "putonghua", "english"], "language_level": ["basic"], "hard_skills": ["documentation", "basic", "photoshop", "autocad"], "soft_skills": ["independently", "capable", "responsible"], "languages_combined": [{"language": "cantonese", "language_level": ["basic"]}, {"language": "putonghua", "language_level": []}, {"language": "english", "language_level": []}]}, "experience_required": {"duration": ["min 2 years"], "field": ["designer"]}}, {"job_id": "100003009054656", "location_code": "hk", "company": "SEN Construction Company Limited", "job_title": "Interior Designer / Assistant Interior Designer", "description": "Responsibilities :\n\n\n\nPrepare drawing packages and details for design projects\nPrepare of 2D/ 3D drawings and familiar with CAD modeling, preferably with\u00a0\u00a0Interior Design project experience\u00a0\nResponsible for site supervision and coordination\nAble to work independently\n\nRequirements:\n\nMinimum 1-2 years' relevant experience / Fresh Graduate also Welcome\u00a0\nResidential project experience preferred\nDiploma in Interior Designer\nGood communication skill\nGood command in AutoCAD, photoshop\u00a0\nAble to work under tight schedule\nImmediate availability is preferred\n\nPlease send full CV with expected salary by clicking \u2018Apply Now\u2019.\n\n\n(Data collected will be used for recruitment purpose only)", "employment_types": ["Full Time"], "selling_points": ["\u505a\u5927\u54c1\u724c\u5e97\u8216\u88dd\u4fee\u8a2d\u8a08, \u589e\u52a0\u500b\u4eba\u7d93\u9a57\u503c", "Double pay", "\u7531\u4e2d\u74b0\u6e2f\u9435\u5230\u516c\u53f8, \u53ea\u8981\u6b65\u884c5\u5206\u9418"], "locations": ["Central"], "categories": ["Design", "Interior", "Visual Merchandising", "Others"], "post_time": "2022-01-17T10:25:13Z", "salary": {"currency": "HKD", "max": 34999, "min": 14000, "period": "monthly", "term": null}, "salary_visible": true, "title_keywords": ["interior designer", "assistant interior designer"], "responsibilities": ["coordination", "site supervision", "design", "drawings"], "requirements": {"degrees": ["diploma", "fresh graduate"], "majors": [], "languages": [], "language_level": [], "hard_skills": ["photoshop", "autocad"], "soft_skills": ["communication skill"], "languages_combined": []}, "experience_required": {"duration": ["minimum 1-2 years"], "field": ["relevant experience"]}}, {"job_id": "100003009054984", "location_code": "hk", "company": "Royal Kitchen Design Co. Ltd", "job_title": "Assistant kitchen Designer", "description": "Reports to:\u00a0Head of Brand & Content\nDepartment:\u00a0Brand, Insights & Marketing Communications\u00a0\u00a0\n\nRole Introduction\u00a0\n\nBecoming a brand-led organisation is core to Cathay Pacific strategy, thus placing the brand team at the heart of the company. \u00a0We ensure that we remain true to our brand \u2013 lighting it up at every opportunity; amplifying, enhancing and refining it across every customer and employee touchpoint. Every interaction that our customers and employees have with our brand influences their perception of it. We therefore work on a wonderfully diverse set of projects which will stimulate, challenge and reward any candidate deeply passionate about branding.\u00a0\n\nUnder our brand platform Move Beyond, our purpose is to move people forward in life through our ability to connect them to meaningful people, places and experiences. \u00a0\n\nThe brand team helps to translate this brand promise and strategy into everything that we do. We work with the insights team to really understand our targeted customers\u2019 needs, desires and behaviours, translating the insights into our brand strategy and associated experience.\u00a0\n\nWe are looking for an exceptionally talented Brand Manager, brimming with energy to help the Cathay Group of brands to strengthen over time, build a deeper connection with our customers and a sense of pride internally. This role presents an incredible opportunity to make a significant mark on the brand\u2019s future, the full customer and employee experience, as well as your own branding career.\n\nKey Responsibilities\n\nBrand strategy & translation\n\nSupport Head of Brand & Content on the development of the Cathay\u2019s brand strategy, including brand positioning, segmentation, definition and articulation\nLead a diverse set of projects, with multiple business areas to translate our brand into different parts of the customer and employee experience\nLead Cathay\u2019s brand partnership strategy\nEstablish new processes and guidelines to help define how different areas of the business should interact with and represent the brand\n\nBrand Measurements\n\nWork closely with the insights team to measure the performance of our brand across all customer touch-points, including the items we have rolled out, to identify areas to improve and inoculate our brand\n\nMerchandise & collaterals\n\nLead a team of product designers in the design and development of branded merchandise and collaterals, working closely with marketing and commercial teams from ideation to design\nWork closely with our content team to craft compelling stories to raise awareness on our branded products\n\nBrand identity\n\nManage and preserve the Cathay Pacific Group\u2019s brand identity system, developing new sub-brands as required\nManage aircraft livery design\u00a0\nManage and lead the implementation of our trademark protection strategy\n\nRequirements\n\nWe\u2019re seeking someone who has the experience, passion and drive to bring our brand purpose to life. Someone who is thrilled with ideas and prospects to build love for our brand. We\u2019re looking for someone who is deeply passionate about branding and is brave about ideas, whilst being clear-eyed about what it takes to achieve better work. Holding oneself, and those around you, to high standards and taking pride in the quality of work are prerequisites for this role.\u00a0\n\nThe candidate will have a strong understanding of brand and design, with an ability to clearly articulate design modifications and improvements in accordance with Cathay\u2019s brand proposition.\n\nIn terms of practical experience and qualifications, the candidate should have at least 8 years\u2019 experience in Brand, Design or a Customer Experience Design and hold a bachelor\u2019s degree in marketing, design or communications related field. We are looking for someone who has worked at a branding agency, helping numerous brands bring their brand purpose to life.\u00a0\n\nBeing an exceptional communicator in written and spoken English skills is a must, Chinese would be incredible.\u00a0\n\nFinally, we\u2019re a premium travel lifestyle brand so we\u2019re naturally looking for someone who shares our absolute love for all things travel.\n\nApplication Deadline: 28 January 2022\n\nPersonal & Application Information\n\nCathay Pacific is an Equal Opportunities Employer. Personal data provided by job applicants will be used strictly in accordance with our personal data policy and for recruitment purposes only. Candidates not notified within eight weeks may consider their application unsuccessful. All related information will be kept in our file for up to 24 months. A copy of our Personal Information Collection Statement will be provided upon request by contacting our Data Protection Officer.\n\nPlease note that with effect from 1 December 2021, all employees must be vaccinated in order to access Cathay City and all other Cathay Group Company premises in Hong Kong. Consideration will be given to those who are unable to get vaccinated for valid medical reasons.\n\nApplication Deadline: 28 January 2022", "employment_types": ["Full Time"], "selling_points": ["Diploma Holder in interior design", "Fresh Graduate Welcome", "Double Pay, employee discount"], "locations": ["Wan Chai"], "categories": ["Design", "Graphics", "Interior", "Others"], "post_time": "2022-01-17T16:22:45Z", "salary": {"currency": "HKD", "max": 24999, "min": 17000, "period": "monthly", "term": null}, "salary_visible": true, "title_keywords": ["designer", "assistant"], "responsibilities": ["guidelines", "teams", "developing", "design", "implementation", "lead a team"], "requirements": {"degrees": ["degree", "bachelor"], "majors": ["marketing", "communications", "design"], "languages": ["english", "chinese"], "language_level": [], "hard_skills": [], "soft_skills": ["clear", "articulate", "communicator", "passionate about"], "languages_combined": [{"language": "english", "language_level": []}, {"language": "chinese", "language_level": []}]}, "experience_required": {"duration": ["at least 8 years"], "field": ["related", "marketing", "brand", "design"]}}, {"job_id": "100003009047708", "location_code": "hk", "company": "F T GROUP LIMITED", "job_title": "\u651d\u5f71\u5e2b\u52a9\u7406 Photographer Assistant", "description": "\u5354\u52a9\u651d\u5f71\u5e2b\u5b8c\u6210\u6bcf\u5929\u62cd\u651d\u5de5\u4f5c\n\nAssist photographer to complete the daily work.\n\n\u559c\u6b61\u5c0f\u670b\u53cb,\u5f85\u4eba\u6709\u79ae,\u505a\u4e8b\u6709\u8010\u6027\n\nBe kind and patience, Love Kids.\n\n\u6027\u683c\u5916\u5411\uff0c\u958b\u6717\u6d3b\u6f51\n\nOutgoing, cheerful and lively.\n\n\u9700\u65bc\u5f71\u6a13\u53ca\u6236\u5916\u5de5\u4f5c\n\nNeed to work in Studio and Outdoor.\n\n\u7d93\u9a57\u4e0d\u9650, \u6b61\u8fce\u525b\u7562\u696d\u6709\u5fd7\u6210\u70ba\u651d\u5f71\u5e2b\u7684\u6c42\u8077\u8005\n\nExperience not limited, welcome fresh graduate.\n\n\u61c2Photoshop, Premiere \u64cd\u4f5c\u512a\u5148\u8003\u616e\n\nPhotoshop, Premiere knowledge will have priority.", "employment_types": ["Full Time"], "selling_points": ["\u559c\u6b61\u5c0f\u670b\u53cb,\u5f85\u4eba\u6709\u79ae,\u505a\u4e8b\u6709\u8010\u6027", "\u7d93\u9a57\u4e0d\u9650, \u6b61\u8fce\u525b\u7562\u696d\u6709\u5fd7\u6210\u70ba\u651d\u5f71\u5e2b\u7684\u6c42\u8077\u8005", "\u5354\u52a9\u651d\u5f71\u5e2b\u5b8c\u6210\u6bcf\u5929\u62cd\u651d\u5de5\u4f5c"], "locations": ["Not Specified"], "categories": ["Media & Advertising", "Others", "Design", "Others", "Photography / Video"], "post_time": "2022-01-14T03:47:35Z", "salary": {"currency": null, "max": null, "min": null, "period": "monthly", "term": null}, "salary_visible": false, "title_keywords": ["assistant", "photographer"], "responsibilities": [], "requirements": {"degrees": ["fresh graduate"], "majors": [], "languages": [], "language_level": [], "hard_skills": ["premiere", "photoshop"], "soft_skills": ["outgoing", "cheerful", "patience"], "languages_combined": []}, "experience_required": {"duration": [], "field": []}}, {"job_id": "100003009052621", "location_code": "hk", "company": "AESO Limited", "job_title": "Draftsman (Fitting out & A&A project)", "description": "\nResponsibilities:\n\nPrepare CAD drawings for variety of projects including club house / lobbies / retail shops / public lavatories / apartments etc.\nSupport the project teams for completion of design work or to covert clients\u2019 design concept / drawing into shop drawing / detailed drawing to sub-contractors for production.\nHandle ad hoc task as request\n\n\u00a0Requirements:\n\nDiploma or above in\u00a0design\u00a0or related disciplines\nRelevant 3-5 years experience in interior design or fit-out contracting firm\nProficient in AutoCAD, knowledge of BIM, AI and Photoshop\u00a0is an advantage\nGood knowledge of detailed drawing & shop drawing preparation is a MUST\nGood team spirit, detail-minded, self-motivated and willing to work overtime\nGood written English and Chinese\nImmediately available preferred\nMore\u00a0experience will be considered as Senior Draftsman\nWe offer competitive remuneration package to the right candidate.\u00a0\u00a0Interested parties please send full resume with current salary, expected salary and availability to HR Department by email.\n", "employment_types": ["Full Time"], "selling_points": [], "locations": ["Sheung Wan"], "categories": ["Building & Construction", "Architectural Services", "Design", "Others"], "post_time": "2022-01-17T03:34:43Z", "salary": {"currency": null, "max": null, "min": null, "period": "monthly", "term": null}, "salary_visible": false, "title_keywords": ["draftsman"], "responsibilities": ["design work", "ad hoc", "design concept", "teams", "drawings"], "requirements": {"degrees": ["diploma or above"], "majors": ["related disciplines", "design"], "languages": ["english", "chinese"], "language_level": ["good"], "hard_skills": ["ai", "bim", "photoshop", "autocad"], "soft_skills": ["detail-minded", "self-motivated", "team spirit", "work overtime", "detailed"], "languages_combined": [{"language": "english", "language_level": ["good"]}, {"language": "chinese", "language_level": ["good"]}]}, "experience_required": {"duration": ["3-5 years"], "field": ["design"]}}, {"job_id": "100003009054424", "location_code": "hk", "company": "LWK & Partners (HK) Ltd", "job_title": "Draftsman (BIM Modeller)", "description": "Responsibilities:\n\nAssist in developing, maintaining and amending BIM models for projects;\nAssistant in preparing data, drawings and presentation materials from BIM models conforming to project\u2019s requirements and instructions from project architects;\n\nAssist the team in relevant job duties, including clash analysis and BIM coordination;\nLiaise with internal and external parties for coordination of BIM matters.\n\nRequirements:\n\nDiploma or above in architecture, engineering, surveying, building, construction or equivalent;\n1-2 years working experience in BIM modelling would be an advantage;\nBasic knowledge of 3D modelling softwares e.g. Revit, Navisworks and AutoCAD;\nGood team player and willingness to learn BIM skills;\nOn-job training will be provided;\nFresh graduates will be considered.\n\nWe offer 5-day work week,\u00a0attractive remuneration package including medical scheme to successful candidates.\u00a0 Please send full resume with current and expected salary.\n\n(Data collected would be used for recruitment purpose only.)", "employment_types": ["Full Time", "Permanent"], "selling_points": ["5-day work week", "Attractive remuneration package including medical", "Basic knowledge of 3D modelling softwares"], "locations": ["Tsim Sha Tsui"], "categories": ["Building & Construction", "Architectural Services", "Design", "Others"], "post_time": "2022-01-17T09:29:24Z", "salary": {"currency": null, "max": null, "min": null, "period": "monthly", "term": null}, "salary_visible": false, "title_keywords": ["bim modeller", "draftsman"], "responsibilities": ["maintaining", "data", "analysis", "internal and external parties", "developing", "drawings", "coordination", "liaise with"], "requirements": {"degrees": ["diploma or above"], "majors": ["architecture", "engineering", "surveying"], "languages": [], "language_level": [], "hard_skills": ["basic", "bim modelling", "revit", "3d modelling", "bim", "autocad"], "soft_skills": ["good team player"], "languages_combined": []}, "experience_required": {"duration": ["1-2 years"], "field": []}}, {"job_id": "100003009054898", "location_code": "hk", "company": "Mindscape Interior Architecture Limited", "job_title": "(Assistant) Interior designer (5-day work & double pay)", "description": "Degree or diploma holder in design/ architecture or related disciplines\nMinimum\u00a03-5 years solid working experience\nFresh graduates or less experienced applicants are welcome\nExposure in the field of furniture & graphic is a plus\nCompetency in Auto CAD;\u00a0 Photoshop and 3Ds Max are added advantage\nCreative and responsible\nProactive, a team player with good presentation and communication skills\nAbility to work independently\nAvailable: immediate\n\nWe offer a 5-day work week, including 12 days annual leave and double pay.\n\nInterested parties please send full resume with date of availability, present & expected salary and portfolio to email by clicking \"Apply Now\".\n\nPersonal data will be used for recruitment purposes only.", "employment_types": ["Full Time", "Permanent"], "selling_points": ["Degree or diploma holder in design/ architecture", "Assistant interior designer", "5-day work week"], "locations": ["North Point"], "categories": ["Building & Construction", "Architectural Services", "Design", "Interior", "Others"], "post_time": "2022-01-17T13:11:38Z", "salary": {"currency": null, "max": null, "min": null, "period": "monthly", "term": null}, "salary_visible": false, "title_keywords": ["interior designer", "assistant"], "responsibilities": ["communication", "architecture", "design"], "requirements": {"degrees": ["diploma holder", "degree"], "majors": ["related disciplines", "architecture", "design"], "languages": [], "language_level": [], "hard_skills": ["plus", "auto cad", "3ds max", "photoshop"], "soft_skills": ["communication skills", "work independently", "proactive", "responsible", "team player", "creative", "presentation"], "languages_combined": []}, "experience_required": {"duration": ["minimum 3-5 years"], "field": []}}, {"job_id": "100003008993846", "location_code": "hk", "company": "Tranthink Technology Service Limited", "job_title": "2D Graphic Assistant (UI)", "description": "Job Description:\nEager to learn new things, and have a strong appetite for iterating, measuring and learning quickly.\nCreate layout and UI assets.\nExcellent communication skills and a positive attitude are essential.\nImmediately availability preferred\nAttention to details\nJob Requirements:\nExperience in the graphic programme, eg. Adobe Illustrator, Photoshop\nWork independently and self-motivation\nExperience in Adobe XD in advantage\nPlease click \"Apply Now\" to submit your application.\nPersonal data collected will be used for recruitment purpose only.", "employment_types": ["Full Time", "Permanent"], "selling_points": ["5 Days Work, Double Pay, Medical Insurance", "Flexible working hours, Free snack", "Immediately availability preferred"], "locations": ["Not Specified"], "categories": ["Design", "Graphics", "Others"], "post_time": "2022-01-16T21:50:01Z", "salary": {"currency": null, "max": null, "min": null, "period": "monthly", "term": null}, "salary_visible": false, "title_keywords": ["graphic assistant"], "responsibilities": ["communication", "ui"], "requirements": {"degrees": [], "majors": [], "languages": [], "language_level": [], "hard_skills": ["adobe xd", "photoshop", "adobe illustrator"], "soft_skills": ["work independently", "self-motivation"], "languages_combined": []}, "experience_required": {"duration": [], "field": ["graphic"]}}, {"job_id": "100003009051502", "location_code": "hk", "company": "Ellermann Limited", "job_title": "Senior Florist / Florist (Full-Time)", "description": "Ellermann Flower Boutique and Events Design Atelier are currently expanding the team, we look for passionate creative and dedicated specialists that are hard-working, with a positive attitude and creative flair.\n\nSenior Florist/Florist\n\nResponsibilities & Requirement:\n\n\nHandle online orders and enquiries, make bouquets and flower/plant arrangements\nConditioning and preparation of flowers\nAssist in flowers and operations supplies ordering\nMin. 2 years experience preferably in a retail or event environment\nKnowledge of flower sourcing & pricing\nFriendly personality and excellent customer service skills\nAbility to work weekends and public holidays\nFluent in Cantonese and English\nLess experience with talent and passions are considered as junior position\n\nTo apply please submit your cover letter, CV with a portfolio of relevant work and salary expectation. Only shortlisted candidates will be contacted.\n\nLearn more about us, please visit our website\u00a0http://www.ellermanndesign.com\n\nJoin us on facebook -\u00a0https://www.facebook.com/ellermannflowers/\n\nIG: ellermannflowers", "employment_types": ["Full Time", "Permanent"], "selling_points": [], "locations": ["Central & Western Area"], "categories": ["Design", "Others", "Sales, CS & Business Devpt", "Retail Sales", "Others", "Others"], "post_time": "2022-01-16T05:38:29Z", "salary": {"currency": null, "max": null, "min": null, "period": "monthly", "term": null}, "salary_visible": false, "title_keywords": [], "responsibilities": [], "requirements": {"degrees": [], "majors": [], "languages": ["cantonese", "english"], "language_level": ["fluent"], "hard_skills": ["make", "facebook"], "soft_skills": ["customer service skills", "friendly"], "languages_combined": [{"language": "cantonese", "language_level": ["fluent"]}, {"language": "english", "language_level": ["fluent"]}]}, "experience_required": {"duration": ["2 years"], "field": ["retail"]}}, {"job_id": "100003009047147", "location_code": "hk", "company": "Kaufland Hong Kong Limited", "job_title": "Office Administrator (Artwork Management)", "description": "Fantastic hospitality design roles are available in some of Asia's most vibrant cities!\u00a0\n\nGet in touch for more information about the different roles we are working on: Nina @ recruitbamboo.com\n\nCheck out our latest role below:\u00a0\n\nMid to Senior Interior Designer - Hong Kong\nA global design house is recruiting for mid to senior-level Designers for the bustling studio in Hong Kong. These are concept-led roles, ideally looking for 5 star hotel or F&B project experience.\n\n\nSPECIFIC REQUIREMENTS\n\nMinimum 15 years of experience\nDegree in Interior Design / Architecture or related studies\nLuxury hospitality project experience is a must, private clubhouse experience is also a plus\nSolid skills in Autocad, Sketchup, Photoshop \u2013 other design software a plus\nTeam leading and project leading experience\u00a0\nHands-on design skill, experience with international design studios\u00a0\nFluency in English, Cantonese & Mandarin preferred", "employment_types": ["Full Time"], "selling_points": [], "locations": ["Tsim Sha Tsui"], "categories": ["Design", "Graphics", "Others"], "post_time": "2022-01-14T02:27:46Z", "salary": {"currency": null, "max": null, "min": null, "period": "monthly", "term": null}, "salary_visible": false, "title_keywords": ["administrator"], "responsibilities": ["architecture", "software", "design"], "requirements": {"degrees": ["degree"], "majors": ["architecture", "design"], "languages": ["cantonese", "english", "mandarin"], "language_level": ["fluency"], "hard_skills": ["plus", "sketchup", "photoshop", "autocad"], "soft_skills": ["hands-on"], "languages_combined": [{"language": "cantonese", "language_level": ["fluency"]}, {"language": "english", "language_level": ["fluency"]}, {"language": "mandarin", "language_level": ["fluency"]}]}, "experience_required": {"duration": ["minimum 15 years"], "field": ["f&b", "design", "team"]}}, {"job_id": "100003009042751", "location_code": "hk", "company": "ISS-Vision Events Limited", "job_title": "Graphic Designer", "description": "- Creating event design. Execute from concept to design, artwork output and print production.\n\n- Concept development, visualization and hands on design for key visual.\n\n\n- Degree holder in visual communication related disciplines;\n\n- Experience in design research, divergent exploration, conceptual development;\n\n- Strong graphic and art sense, creative and passionate;\n\n- Proficiency in Adobe Illustrator, Photoshop, InDesign, affect effect\u2026etc.\n\n- Experience in storyboard, photo & video shooting technique with editing;\n\n- Experience in event decoration design is a plus;\n\n- Self-motivated, energetic, with the ability to work independently;\n\n- Good communication skills in English, Cantonese and Mandarin;\n\n- Able to work under pressure with tight deadline and multi-task;\n\n- Less experience will be considered as Graphic Designer.", "employment_types": ["Full Time", "Permanent"], "selling_points": ["Exhibitions and Events", "Creative design", "Concept development"], "locations": ["Wong Tai Sin Area"], "categories": ["Design", "Graphics", "Others"], "post_time": "2022-01-16T21:50:12Z", "salary": {"currency": "HKD", "max": 29999, "min": 20000, "period": "monthly", "term": null}, "salary_visible": true, "title_keywords": ["graphic designer"], "responsibilities": ["visualization", "conceptual development", "event decoration", "design", "communication", "video shooting", "visual", "editing", "artwork output", "work under pressure"], "requirements": {"degrees": ["degree holder"], "majors": ["related disciplines"], "languages": ["cantonese", "english", "mandarin"], "language_level": ["good"], "hard_skills": ["plus", "indesign", "adobe illustrator", "visual communication", "photoshop"], "soft_skills": ["passionate", "communication skills", "self-motivated", "work independently", "multi-task", "communication", "energetic", "hands on", "creative", "work under pressure"], "languages_combined": [{"language": "cantonese", "language_level": ["good"]}, {"language": "english", "language_level": ["good"]}, {"language": "mandarin", "language_level": ["good"]}]}, "experience_required": {"duration": [], "field": ["photo", "research", "designer", "development", "design", "video shooting", "graphic", "editing"]}}, {"job_id": "100003009054269", "location_code": "hk", "company": "CHOW TAI FOOK JEWELLERY CO LTD", "job_title": "Graduate Trainee, Operations Management", "description": "Develop your\u00a0Future\u00a0Career!\nAccelerate your Professional Development & Develop a Prosperous Future with Us\n\nOn-the-job Training\n\n\nExtensive on-the-job training in our Core Business Divisions\u00a0focuses on practical application with opportunities to train up diverse skillsets, solid and holistic know-how. You will be exposed to retail-related projects that support business strategic goals which allow you to widen your horizon and unleash your potential for development\n\nCoaching & Mentoring\nBuddies will share past experience & advice as well as providing guidance & insights to you during your professional development\n\n\u00a0Who Will Thrive\n\nUniversity graduates\u00a0from\u00a0any discipline. Degree holder in Business Administration, Hospitality, Supply Chain and Logistic, Jewellery Design and\u00a0Social Sciences\u00a0would be a plus\nLess than 3 years of experience, experience in sales management and product management will be an advantage\nPassionate with keen interest in pursuing career in luxury retail\u00a0/ jewellery industry\nStrong desire to take on challenges\nProactive,\u00a0result-driven with good analytical and\u00a0problem-solving\u00a0skills\nExcellent interpersonal and communication skills\nExcellent command of English and Chinese including Cantonese and Putonghua\n\nWe look on your potential to develop your Chow Tai Fook Global Competencies and have fun together:\u00a0\n\nGlobal Perspective\nCustomer Centricity\nBreakthrough Innovation\nResult Ownership\nShared Value\n\nBenefits\n\n5-day work\nCompetitive salary, staff meal, medical and dental insurance, life insurance\nVarious types of leave, e.g. Family-friendly leave, self-development leave,\u00a0Examination leave, marriage leave, birthday leave, volunteer service leave, etc\nWe offer excellent career opportunities, attractive remuneration package & benefits to the right candidate.\u00a0Interested parties please apply by clicking \"Apply Now\" with a full resume stating the latest and expected salary.\n\n\nAll information collected will be used for recruitment purposes only.", "employment_types": ["Full Time"], "selling_points": ["Graduate Trainee", "Less than 3 years of exp.", "On-the-job Training, Coaching & Mentoring"], "locations": ["Not Specified"], "categories": ["Admin & HR", "Others", "Design", "Others", "Sales, CS & Business Devpt", "Sales Administration"], "post_time": "2022-01-17T09:00:10Z", "salary": {"currency": null, "max": null, "min": null, "period": "monthly", "term": null}, "salary_visible": false, "title_keywords": ["operations", "graduate trainee"], "responsibilities": ["guidance", "management", "design", "develop", "communication", "sales management", "administration"], "requirements": {"degrees": ["degree holder"], "majors": ["hospitality", "business administration", "design", "social sciences"], "languages": ["cantonese", "putonghua", "english", "chinese"], "language_level": ["excellent"], "hard_skills": ["problem-solving skills", "plus", "fun"], "soft_skills": ["passionate", "communication skills", "interpersonal", "keen", "diverse", "problem-solving skills", "proactive", "extensive", "driven"], "languages_combined": [{"language": "cantonese", "language_level": ["excellent"]}, {"language": "putonghua", "language_level": ["excellent"]}, {"language": "english", "language_level": ["excellent"]}, {"language": "chinese", "language_level": ["excellent"]}]}, "experience_required": {"duration": ["3 years"], "field": ["product management", "development", "management"]}}, {"job_id": "100003009053864", "location_code": "hk", "company": "BAMBOO Consultants Limited", "job_title": "HOSPITALITY INTERIOR DESIGNERS, All Levels (HK, Beijing, Shanghai, Singapore)", "description": "Fantastic hospitality design roles are available in some of Asia's most vibrant cities!\u00a0\n\nGet in touch for more information about the different roles we are working on: Nina @ recruitbamboo.com\n\nCheck out our latest role below:\u00a0\n\nMid to Senior Interior Designer - Hong Kong\nA global design house is recruiting for mid to senior-level Designers for the bustling studio in Hong Kong. These are concept-led roles, ideally looking for 5 star hotel or F&B project experience.\n\n\nSPECIFIC REQUIREMENTS\n\nMinimum 15 years of experience\nDegree in Interior Design / Architecture or related studies\nLuxury hospitality project experience is a must, private clubhouse experience is also a plus\nSolid skills in Autocad, Sketchup, Photoshop \u2013 other design software a plus\nTeam leading and project leading experience\u00a0\nHands-on design skill, experience with international design studios\u00a0\nFluency in English, Cantonese & Mandarin preferred", "employment_types": ["Full Time", "Permanent"], "selling_points": ["Singapore, HK, BJ, SH hospitality design roles", "Fluency in English, Mandarin preferred", "Hospitality, residential, or F&B"], "locations": ["Not Specified"], "categories": ["Design", "Interior", "Others", "Building & Construction", "Others"], "post_time": "2022-01-17T07:38:54Z", "salary": {"currency": null, "max": null, "min": null, "period": "monthly", "term": null}, "salary_visible": false, "title_keywords": [], "responsibilities": ["architecture", "software", "design"], "requirements": {"degrees": ["degree"], "majors": ["architecture", "design"], "languages": ["cantonese", "english", "mandarin"], "language_level": ["fluency"], "hard_skills": ["plus", "sketchup", "photoshop", "autocad"], "soft_skills": ["hands-on"], "languages_combined": [{"language": "cantonese", "language_level": ["fluency"]}, {"language": "english", "language_level": ["fluency"]}, {"language": "mandarin", "language_level": ["fluency"]}]}, "experience_required": {"duration": ["minimum 15 years"], "field": ["f&b", "design", "team"]}}, {"job_id": "100003009048226", "location_code": "hk", "company": "Loving Game Limited", "job_title": "\u5287\u60c5\u7b56\u5283/\u6587\u6848\u7b56\u5283 (Editor)", "description": "Responsibilities:\nResponsible for creating the Building Information Models & providing necessary onsite support and advisory services to the operation team;\nCollaborate innovation initiatives to support the tender presentations and promote execution strategies at corporate level;\nManage BIM technology implementation and assuring the quality deliverables on construction projects;\nMaintain accurate data set in drawings, design specifications and project schedules;\nAssist in the research and facilitating the means of better BIM applications in order to improve the communication, co-ordination, management and delivery time, cost and quality throughout the building life cycle of the projects;\nCommunicate and co-ordinate with different stakeholders including consultants, architects and internal operation team in the smooth execution and delivery of projects with architectural designs and the usage of BIM models.\nRequirements:\nDiploma/Degree in\u00a0Electrical, Mechanical, Building Services, Engineering\u00a0or related disciplines;\n2\u00a0 years or above relevant experience\u00a0from construction industry and in tunnel project is preferred;\nHands-on BIM software / applications experience is preferred (Autodesk Revit, Navisworks, Solidworks)\nAbility to generate construction CSD & ISD drawing from Revit BIM model is preferred;\nGood interpersonal and communication skills.\nYou may apply via https://career.gammonconstruction.com/home/index?jobid=c6f40b7d-ec1d-4f6b-a784-56f6d02140b7&source=003, providing you full resume, current and expected salary.\nFor more information about Gammon Construction Limited, please visit our company's website at http://www.gammonconstruction.com.\nWe are an equal opportunity employer and welcome application from all qualified candidates. Information provided will be treated in strict confidence and only be used for consideration of your application for the relevant post within the Company. Applicants who are not invited for an interview within 6 weeks may consider their application unsuccessful.", "employment_types": ["Full Time"], "selling_points": [], "locations": ["Ngau Tau Kok"], "categories": ["Design", "Others", "Media & Advertising", "Editorial / Journalism", "Photography / Video"], "post_time": "2022-01-14T05:58:09Z", "salary": {"currency": null, "max": null, "min": null, "period": "monthly", "term": null}, "salary_visible": false, "title_keywords": ["editor"], "responsibilities": ["collaborate", "management", "cost", "data", "schedules", "co-ordinate with", "quality", "implementation", "presentations", "drawings", "design specifications", "communication", "maintain", "tender"], "requirements": {"degrees": ["diploma", "degree"], "majors": ["related disciplines", "building services", "engineering"], "languages": [], "language_level": [], "hard_skills": ["bim", "solidworks", "revit"], "soft_skills": ["communication skills", "hands-on", "confidence", "interpersonal"], "languages_combined": []}, "experience_required": {"duration": [], "field": ["construction industry", "relevant experience"]}}, {"job_id": "100003009048555", "location_code": "hk", "company": "INO Design Limited", "job_title": "Interior Designer", "description": "\u5d17\u4f4d\u8077\u8cac\uff1a\n1\u3001\u6839\u64da\u5c08\u6848\u7d44\u5206\u914d\u7684\u4efb\u52d9\uff0c\u4f9d\u8a17\u5df2\u6709\u4e16\u754c\u89c0\uff0c\u5b8c\u6210\u624b\u904a\u7522\u54c1\u7684\u5287\u60c5\u5beb\u4f5c\uff1b\n2\u3001\u7368\u7acb\u64b0\u5beb\u4e3b\u8981\u89d2\u8272\u7684\u5287\u60c5\u6545\u4e8b\u3001\u8a73\u7d30\u5c0d\u767d\uff1b\n3\u3001\u8207\u7f8e\u8853\u90e8\u9580\u914d\u5408\uff0c\u5b8c\u6210\u904a\u6232\u4e2d\u89d2\u8272\u3001\u5834\u666f\u3001\u9053\u5177\u7b49\u7684\u6587\u6848\u8a2d\u5b9a\uff0c\u8ddf\u9032\u8cc7\u6e90\u7684\u63d0\u4ea4\uff1b\n4\u3001\u5c0d\u904a\u6232\u5167\u5404\u500b\u7cfb\u7d71\u73a9\u6cd5\u7684\u6587\u6848\u8a2d\u8a08\u652f\u6490\n\n\u5d17\u4f4d\u8981\u6c42\uff1a\n1\u3001\u672c\u79d1\u53ca\u4ee5\u4e0a\u5b78\u6b77\uff0c\u6709\u6d41\u66a2\u7684\u6587\u6848\u5beb\u4f5c\u80fd\u529b\u8207\u8f03\u70ba\u8c50\u5bcc\u7684\u95b1\u8b80\u91cf\uff0c\u64c5\u9577\u5e7d\u9ed8\u71b1\u8840\u985e\u984c\u6750\uff1b\n2\u3001\u719f\u6089\u624b\u904a\uff0c\u5177\u5099\u8f03\u70ba\u8c50\u5bcc\u7684\u904a\u6232\u7d93\u6b77\uff0c\u5c0d\u904a\u6232\u7684\u5287\u60c5\u8868\u73fe\u6709\u81ea\u5df1\u7684\u898b\u89e3\uff1b\n3\u3001\u5177\u5099\u826f\u597d\u7684\u6e9d\u901a\u5354\u8abf\u80fd\u529b\u3001\u57f7\u884c\u80fd\u529b\uff0c\u6709\u8f03\u5f37\u7684\u5718\u968a\u5354\u4f5c\u7cbe\u795e\uff1b\n4\u3001\u67091\u5e74\u53ca\u4ee5\u4e0a\uff0c\u8207\u6545\u4e8b\u5beb\u4f5c\uff08\u542b\u5287\u672c\u3001\u5c0f\u8aaa\u7b49\uff09\u76f8\u95dc\u7684\u884c\u696d\u7d93\u6b77\u8005\u512a\u5148\uff1b\n5\u3001\u719f\u6089\u57fa\u790e\u7684\u7684\u93e1\u982d\u8a9e\u8a00\uff0c\u77ad\u89e3\u96fb\u5f71\u3001\u52d5\u756b\u7b49\u5f71\u8996\u8868\u73fe\u624b\u6cd5\u8005\u512a\u5148", "employment_types": ["Full Time", "Permanent"], "selling_points": [], "locations": ["Wan Chai Area"], "categories": ["Building & Construction", "Architectural Services", "Design", "Interior", "Others"], "post_time": "2022-01-16T21:50:00Z", "salary": {"currency": null, "max": null, "min": null, "period": "monthly", "term": null}, "salary_visible": false, "title_keywords": ["interior designer"], "responsibilities": [], "requirements": {"degrees": [], "majors": [], "languages": [], "language_level": [], "hard_skills": [], "soft_skills": [], "languages_combined": []}, "experience_required": {"duration": [], "field": []}}, {"job_id": "100003009050803", "location_code": "hk", "company": "iDance International Limited", "job_title": "Graphic Designer", "description": "Diploma / Degree in Interior or Architectural Design\nMinimum 5 - 8 years relevant experience\nExperience in design will be an advantage Office, Retail and Restaurant\u00a0\nProficiency in AutoCAD, Photoshop, PowerPoint, Microsoft Office, 3D\nSelf-motivate and work independent, good communication with client, familiar to project procedure\nAvailable immediately\n\nBenefits:\n\n5 Days work\u00a0\nDouble Pay\nPerformance bonus\n12 days Annual Leave \u00a0\n\nInterested parties please send your resume in details with last/current and expected salary\u00a0by \"Clicking Apply Now\" or by clicking \u201cApply Now\u201d.\n\nPersonal data will be used for recruitment purpose only.", "employment_types": ["Full Time", "Permanent"], "selling_points": [], "locations": ["Ngau Tau Kok"], "categories": ["Design", "Graphics", "Others", "Manufacturing", "Others"], "post_time": "2022-01-14T11:26:04Z", "salary": {"currency": null, "max": null, "min": null, "period": "monthly", "term": null}, "salary_visible": false, "title_keywords": ["graphic designer"], "responsibilities": ["communication", "design"], "requirements": {"degrees": ["diploma", "degree"], "majors": ["design"], "languages": [], "language_level": [], "hard_skills": ["microsoft office", "photoshop", "powerpoint", "autocad"], "soft_skills": ["communication", "independent"], "languages_combined": []}, "experience_required": {"duration": ["minimum 5 - 8 years"], "field": ["restaurant", "retail", "relevant experience", "design"]}}, {"job_id": "100003009051563", "location_code": "hk", "company": "Hong Kong Interior Design Architecture Limited", "job_title": "Interior design Instructor (Part time)", "description": "We are a consumer electronics trading company which located at Kwun Tong area and we are now seeking for the following position to cope our company expansion.\n\nGRAPHIC DESIGNER\n\nResponsibilities:\n\u2022 Wide range of design jobs, such as Brand, Packaging, P.O.P. Advertising, Company Brochure and Promotion Materials\n\u2022 Assist marketing events and perform ad-hoc projects as assigned\n\nRequirements:\n\u2022 Diploma in Graphic Design or Related Discipline\n\u2022\u00a0Min. 3 years or above solid experience in Graphic Design background\n\u2022\u00a0Strong creative senses, well organized, mature, highly responsible and independent\n\u2022\u00a0Full PC and Macintosh skill is a must, proficient in Photoshop, Illustrator, InDesign, PowerPoint\n\u2022\u00a0Product photo shoot and photo retouch\n\u2022\u00a0Familiar with output and print production\n\u2022\u00a0Good command of Chinese and English\n\u2022 Immediately available is preferred\n\nInterested candidates, kindly send your detailed resume including Expected Salary.\n\n(All personal data will be collected for recruitment purposes only.)\u00a0", "employment_types": ["Full Time", "Part Time"], "selling_points": [], "locations": ["Mong Kok"], "categories": ["Building & Construction", "Architectural Services", "Design", "Interior", "Others"], "post_time": "2022-01-16T10:49:54Z", "salary": {"currency": null, "max": null, "min": null, "period": "hourly", "term": null}, "salary_visible": false, "title_keywords": [], "responsibilities": ["marketing events", "ad-hoc projects", "advertising", "design"], "requirements": {"degrees": ["diploma"], "majors": ["graphic design"], "languages": ["english", "chinese"], "language_level": ["good command"], "hard_skills": ["indesign", "illustrator", "powerpoint", "pc", "photoshop"], "soft_skills": ["independent", "responsible", "well organized", "mature", "creative"], "languages_combined": [{"language": "english", "language_level": ["good command"]}, {"language": "chinese", "language_level": ["good command"]}]}, "experience_required": {"duration": ["3 years"], "field": ["graphic design"]}}, {"job_id": "100003009051384", "location_code": "hk", "company": "The Floristry", "job_title": "Freelance Florists (For Valentine's Day period)", "description": "Job responsibilities:\n\n\nConduct tutorial lessons\nPrepare materials for classes\n\nJob requirements:\n\nDegree holder in related disciplines\nAt least three years working experience in the field\n\nGood knowledge in Hand sketch / AutoCAD / Sketchup + V-Ray / 3DsMax + V-Ray (at least two of them)\nFamilier with all drawing software is highly preferred\nPatient, positive and passionate about education\nBe enthusiastic and dynamic\nExcellent presentation and communication skill\nAble to teaching in English or Mandarin is a plus\nImmediate availability is preferred\n\nCampus:\u00a0Mongkok Campus\n\nWebsite: www.hkiai.com.hk\n\nInterested candidates should send us academic background, portfolio and expected salary.\u00a0", "employment_types": ["Temporary"], "selling_points": ["Freelance Position", "Date: 11 - 14 Feb 2022", "Salary: $300/hr"], "locations": ["Sheung Wan"], "categories": ["Others", "Agriculture / Forestry / Fishing", "Design", "Others"], "post_time": "2022-01-15T13:21:59Z", "salary": {"currency": "HKD", "max": 369, "min": 290, "period": "hourly", "term": null}, "salary_visible": true, "title_keywords": [], "responsibilities": [], "requirements": {"degrees": ["degree holder"], "majors": ["related disciplines"], "languages": ["english", "mandarin"], "language_level": [], "hard_skills": ["plus", "dynamic", "sketchup", "autocad"], "soft_skills": ["communication skill", "dynamic", "positive", "enthusiastic", "patient", "presentation", "passionate about"], "languages_combined": [{"language": "english", "language_level": []}, {"language": "mandarin", "language_level": []}]}, "experience_required": {"duration": ["at least three years"], "field": []}}, {"job_id": "100003009050118", "location_code": "hk", "company": "Jaz Toys HK Limited", "job_title": "Senior Designer (Toy Packaging Development)", "description": "About Us\nThe Floristry is Hong Kong's leading floral lifestyle brand. We celebrate wild-inspired living and offer a curated assortment of flowers, homeware and lifestyle objects with a newly opened store and coffee bar in central.\u00a0\n\nWe're on the lookout for eager and passionate florists to join our friendly teams both in our studio and store for Valentine's Day period (11 - 14 Feb 2022).\n\nSalary: $300/hr + bonus\n\nThe position will include assisting in making bouquets, flower jars and general day-to-day florist duties.\n\nAPPLY\n\nInterested candidates please submit your CV by clicking Apply Now!\n\n*Due to the amount of applications we receive, we are not able to reply to every one. Unfortunately if you do not hear back from us, your application has not been successful.", "employment_types": ["Full Time", "Permanent"], "selling_points": ["Follow up toy product development", "8 years\u2019 relevant experience in the toy industry", "Knowledge of packaging design and development"], "locations": ["Chai Wan"], "categories": ["Design", "Industrial / Product", "Others", "Merchandising & Purchasing", "Toy"], "post_time": "2022-01-14T09:48:25Z", "salary": {"currency": null, "max": null, "min": null, "period": "monthly", "term": null}, "salary_visible": false, "title_keywords": ["senior designer"], "responsibilities": ["hr", "teams"], "requirements": {"degrees": [], "majors": [], "languages": [], "language_level": [], "hard_skills": [], "soft_skills": ["passionate", "friendly"], "languages_combined": []}, "experience_required": {"duration": [], "field": []}}, {"job_id": "100003009050932", "location_code": "hk", "company": "Bank of Communications Hong Kong Branch", "job_title": "Chief Dealer, Interest Rate Derivatives", "description": "Responsibilities:\n\nManagement of around 10,000 design and packaging orders\n\nLeading and managing a team of 14 graphic Designers\u00a0\n\nQuality assurance and improvement of packaging design\u00a0\n\nOrganize photo shoots including sample handling\u00a0\n\nCoordination of brand concepts\u00a0\u00a0\n\nDirect communication with German Headquarter\n\nCoordination of Artwork Team\u00a0and administration related tasks\u00a0(Packaging Design\u00a0Non-Food)\n\n\nRequirements:\n\nPeople management experience\u00a0\nExperience in Brand strategy\u00a0\u00a0\nDesign background recommended but not mandatory\nExcellent communication skills, ability to engage and communicate effectively across different departments\u00a0\nExcellent organizational skills and detail oriented\nStrong time management skills, able to work with tight deadlines\nStrong leadership skills\u00a0\nFluent in German and English\nInterested applicants please send your English application letter and resume with expected salary \u00a0by clicking \"Apply Now\".\n\n\nAll information received will be kept in strict confidential and only for employment related purpose.", "employment_types": ["Full Time"], "selling_points": ["SFO", "Interest Rate Derivatives", "Treasury"], "locations": ["Wan Chai"], "categories": ["Design", "Graphics", "Interior", "Others"], "post_time": "2022-01-14T11:51:11Z", "salary": {"currency": null, "max": null, "min": null, "period": "monthly", "term": null}, "salary_visible": false, "title_keywords": ["dealer"], "responsibilities": ["management", "packaging design", "quality", "design", "communication", "coordination", "managing a team", "administration"], "requirements": {"degrees": [], "majors": [], "languages": ["german", "english"], "language_level": ["fluent"], "hard_skills": [], "soft_skills": ["communication skills", "organizational skills", "time management skills", "detail oriented", "leadership skills"], "languages_combined": [{"language": "german", "language_level": ["fluent"]}, {"language": "english", "language_level": ["fluent"]}]}, "experience_required": {"duration": [], "field": ["people management", "brand"]}}, {"job_id": "100003009046281", "location_code": "hk", "company": "AMO Creative Limited", "job_title": "(Senior) Graphic Designer / Motion Graphic Designer", "description": "\u00a0 Responsibilities:\n\nFollow up toy product development (Material and Colour)\nFollow up packaging design and development process\nCreate highly competitive, innovative, contemporary packaging (graphics and structure) while providing feedback to internal teams and licensors\nCollaboration with communication with engineers PM and US team\nWork closely with licensor and follow each approval step\nWork closely with external parties, such as Factory, Vendors and Prototype markers..etc\nReport to HK Design Manager\n\n\u00a0Requirements:\n\nDegree or Diploma in Design or related disciplines\n8 years\u2019 relevant experience in the toy industry\nKnowledge of packaging design and development\nProficiency in 2D design Software (Photoshop, Illustrator)\nAbility to work in a fast paced environment and manage multiple projects independently\nTravel to China factory is must\nGood command of written and spoken English\u00a0\u00a0\u00a0\u00a0\u00a0\u00a0\u00a0\nMust speak either Cantonese and Mandarin\n\nAvailability\u00a0\u00a0 :\u00a0\u00a0 Immediate is preferred\n\nInterested parties please send detail resume and profoilo", "employment_types": ["Full Time", "Permanent"], "selling_points": ["Graphic Design / Motion Graphic", "Artwork Production", "Illustrator, Photoshop"], "locations": ["Lai Chi Kok"], "categories": ["Design", "Graphics", "Multi-media", "Others"], "post_time": "2022-01-13T10:14:32Z", "salary": {"currency": null, "max": null, "min": null, "period": "monthly", "term": null}, "salary_visible": false, "title_keywords": ["graphic designer"], "responsibilities": ["graphics", "packaging design", "external parties", "teams", "design", "communication", "report"], "requirements": {"degrees": ["diploma", "degree"], "majors": ["related disciplines", "design"], "languages": ["cantonese", "english", "mandarin"], "language_level": ["good command"], "hard_skills": ["illustrator", "photoshop"], "soft_skills": ["work in a fast paced environment", "independently"], "languages_combined": [{"language": "cantonese", "language_level": []}, {"language": "english", "language_level": ["good command"]}, {"language": "mandarin", "language_level": []}]}, "experience_required": {"duration": ["8 years"], "field": ["relevant experience"]}}, {"job_id": "100003009051192", "location_code": "hk", "company": "Milestone Architectural Service Studio Limited", "job_title": "CAD Draftsman / BIM Modeler \u96fb\u8166\u7e6a\u5716\u54e1", "description": "\n\u2022 Lead a team to generate trading profit through dealing with Interest Rate products\n\u2022 Provide market information and/or pricing services to Treasury Market Sales\n\u2022 Degree holder or above with minimum 6 years\u2019 relevant experience in financial institutions\n\u2022 Familiar with trading system/software and qualified under SFO for handling Regulated Activities Types 1, 4 & 9 with TMA Full Member qualification are a must\nCandidates with less experience may be considered for the post of Deputy Chief Dealer, Interest Rate Derivatives\n\n", "employment_types": ["Full Time", "Permanent", "Contract"], "selling_points": [], "locations": ["Wong Tai Sin Area"], "categories": ["Design", "Others", "Building & Construction", "Building / Construction / QS", "Engineering", "Draftsman"], "post_time": "2022-01-15T04:30:30Z", "salary": {"currency": null, "max": null, "min": null, "period": "monthly", "term": null}, "salary_visible": false, "title_keywords": ["cad draftsman"], "responsibilities": ["lead a team", "market information", "software"], "requirements": {"degrees": ["degree holder"], "majors": [], "languages": [], "language_level": [], "hard_skills": ["sfo"], "soft_skills": [], "languages_combined": []}, "experience_required": {"duration": ["minimum 6 years"], "field": ["financial institutions", "relevant experience"]}}, {"job_id": "100003009049310", "location_code": "hk", "company": "FCS Interior Design Consultant Limited", "job_title": "Senior Interior Designer / Assistant Interior Designer / Interior Designer", "description": "Responsibilities:\u00a0\n\nDevelop creative concepts and prepare marketing materials including but not limited to publication, advertising, trade show booths and shop displays\nResponsible for all kinds of graphic and motion graphic design projects, artwork production and graphic details preparation\nArt directing on photos/video shooting\nKeep track of design trends\n\nRequirements:\u00a0\n\nDegree/Diploma in graphic design or relevant discipline\nAt least 4 years of\u00a0experience in graphic and motion graphic design, preferably gained in Retail/ F&B industry\nFamiliar with Illustrator, Photoshop, Premiere, After Effects\nGood team player, creative, and passionate in graphic and motion graphic design\nAble to work under pressure with tight deadlines\nCandidate with more experience will be considered as Senior Graphic Designer/ Senior Motion Graphic Designer\nImmediate availability is highly preferred\n\nWe Offer:\n\n5-day work week\nCompetitive Salary Package\n13 months' Guaranteed Salary\nPerformance Incentives\nGroup Medical Scheme\nBirthday Leave\nFree Lunch\nEnergetic & Dynamic Culture\n\nInterested parties, please send your detailed resume, availability, present and expected salary to Human Resources Department by clicking \u201cApply Now\u201d.\n\nPersonal data collected will be used for recruitment purpose only.", "employment_types": ["Full Time"], "selling_points": [], "locations": ["Wan Chai"], "categories": ["Design", "Interior", "Others", "Building & Construction", "Others"], "post_time": "2022-01-14T08:27:56Z", "salary": {"currency": null, "max": null, "min": null, "period": "monthly", "term": null}, "salary_visible": false, "title_keywords": ["interior designer", "senior interior designer", "assistant interior designer"], "responsibilities": ["graphic details preparation", "advertising", "keep track of design trends", "shop displays", "motion graphic design projects", "artwork production", "trade show booths", "video shooting", "art directing", "develop creative concepts", "publication", "prepare marketing materials"], "requirements": {"degrees": ["diploma", "degree"], "majors": ["graphic design"], "languages": [], "language_level": [], "hard_skills": ["after effects", "illustrator", "premiere", "photoshop"], "soft_skills": ["passionate", "good team player", "creative", "work under pressure"], "languages_combined": []}, "experience_required": {"duration": ["at least 4 years"], "field": ["designer", "design", "f&b", "graphic", "retail", "motion graphic"]}}, {"job_id": "100003009050697", "location_code": "hk", "company": "On Stage Production and Consultant Limited", "job_title": "Senior Designer / Designer", "description": "Immediately available\nF.5 or T.I. graduates (CSD post - Diploma or above in Mech / Elect / Building Services Engg.)\nResident of Hong Kong & fair in English and Cantonese\n1 to 2 years Building drafting experience (CSD post - CSD drafting experience)\nKnowledge in MicroStation or AutoCAD\nKnowledge in PC networking an advantage\n\nInterested applicant please email your C.V. together with salary expected us.\n\nAll personal data will be used for recruitment purpose only.", "employment_types": ["Full Time"], "selling_points": ["Diploma or above in Graphic Design or relevant", "Proficient in graphic and design softwares", "Minimum 3 years experience"], "locations": ["Kwun Tong"], "categories": ["Design", "Graphics", "Others"], "post_time": "2022-01-14T11:12:56Z", "salary": {"currency": null, "max": null, "min": null, "period": "monthly", "term": null}, "salary_visible": false, "title_keywords": ["senior designer", "designer"], "responsibilities": ["personal data", "recruitment"], "requirements": {"degrees": ["diploma or above"], "majors": ["building services"], "languages": ["cantonese", "english"], "language_level": [], "hard_skills": ["pc", "c", "autocad"], "soft_skills": [], "languages_combined": [{"language": "cantonese", "language_level": []}, {"language": "english", "language_level": []}]}, "experience_required": {"duration": ["1 to 2 years"], "field": []}}, {"job_id": "100003009048929", "location_code": "hk", "company": "Fresh Up Group Limited", "job_title": "Graphic Designer", "description": "At FCS Interior Design Consultant Ltd, we focus greatly on our people, providing them with opportunities to grow and develop professionally. We offer competitive compensation including one of the best benefits plans in the market. Most importantly- when you join FCS Interior Design Consultant Ltd.\n\nAttractive Performance Bonus\nRoom for your creative design ability\nEntrepreneurial work environment and good career prospect\nOpportunities working with multi-national clients\nAssociate profit sharing to staff with proven abilities\nLearning & Experience Opportunity\nAre you ready to work in an open-minded and collaborative working environment? Let\u2019s join\n\n\nFCS INTERIOR DESIGN CONSULTANT LTD!!\n\nSENIOR INTERIOR DESIGNER / INTERIOR DESIGNER\n\nRESPONSIBILITIES:\u00a0\n\nLead the strategy efforts in multiple projects\nResearch and analyze global shifts and trends in work behaviours to develop and improve recommendations with respect to physical, digital and social workplaces\nCreate and execute commercial office design concepts through schematic planning\nDesign office environments to achieve client\u2019s brand identity and develop unique design concepts\nManage construction documents from designers and consultants\nProvide detailed and innovative designs according to different guidelines\nIdentify\u00a0exceptional design obstacles and resolve\nHandle commercial projects independently from design concept, project development, and materials application to project completion.\n\nREQUIREMENTS:\n\nRelevant technical Interior Design experiences\nRelevant\u00a0experiences in workplace design is preferred\nExcellent presentation and\u00a0communication skills\nAble to work independently and mentoring the team\nPassionate about Interior Design as long-term career field\nProficient in AutoCAD and Photoshop; SketchUP and 3ds Max is preferred\nExcellent in English and Chinese, both spoken and written\nCandidates with less experience or new graduated will be considered as Assistant Designer", "employment_types": ["Full Time"], "selling_points": ["Solid experience in Illustrator & After Effects", "1-2 years relevant experience", "Immediate Available"], "locations": ["Kwai Fong"], "categories": ["Design", "Graphics", "Multi-media", "Others"], "post_time": "2022-01-14T07:44:02Z", "salary": {"currency": null, "max": null, "min": null, "period": "monthly", "term": null}, "salary_visible": false, "title_keywords": ["graphic designer"], "responsibilities": [], "requirements": {"degrees": [], "majors": [], "languages": [], "language_level": [], "hard_skills": [], "soft_skills": [], "languages_combined": []}, "experience_required": {"duration": [], "field": []}}, {"job_id": "100003009045897", "location_code": "hk", "company": "Qookia Limited", "job_title": "Junior / Senior 2D Game Artist - \u904a\u6232\u539f\u756b\u8a2d\u8a08\u5e2b", "description": "Responsibilities:\u00a0\nTo develop creative concept / design, and including the productions for all\u00a0the communications, inclusive, but not limited to the following:\nWeekly eDM \u2013 branding and tactical\nWebsite content image design\nSocial media graphic and/or motion picture design\nApp & Digital advertising\nOffline advertising\nPrinted materials\nSimple animated gif or videos\nIn term of the creative concept / design, will require to develop locally, as\u00a0well as to adapt the headquarter creative into local version.\n\nTo be the brand guardian for the Company \u2013 to ensure all the\ncommunication is on brand, and in-sync with the brand guideline;\nTo assist in finalizing design output, photo retouching and follow up\nproduction with vendors or other departments.\nRequirements:\u00a0\nDiploma or above in graphic/multi-media design or other related subject;\nMinimum 3 years\u2019 experience in online and offline design;\nExcellent in design tools and PC / Mac applications, such as Adobe\u00a0Photoshop, InDesign, Illustrator, i-movie, Flash, iOS etc. &amp; word processing\u00a0program: Keynotes, PowerPoint, Word, Excel etc.;\nKnowledge in print production and photography;\nGood command of spoken & written English and Chinese;\nGood organization skill and detail-oriented;\nA good team player and passionate in coming up with great creative\u00a0designs;\nImmediate available is preferred.\nWe offer excellent career prospects, competitive salary and fringe benefits to the right candidate. Please apply in strict confidence by sending\u00a0personal resume together with salary expected and date available\n\nby e-mail to:\u00a0\u00a0h r d _ h n @ h a r v e y n i c h o l s . c o m . h k\nWe are an equal opportunity employer and welcome applications from all qualified candidates. Personal data provided by job applicants will be used strictly in accordance with our personal data policy and for recruitment purposes only. Candidates not notified within eight weeks may consider their application unsuccessful. All related information will be kept in our file for up to 24 months. A copy of our Personal Information Collection Statement will be provided upon request by contacting our Human Resources Division.", "employment_types": ["Full Time", "Permanent"], "selling_points": ["5-day work / Flexible working hours", "Performance bonus and medical insurance", "Joyful working environment with free snacks/drinks"], "locations": ["Kwai Fong"], "categories": ["Design", "Graphics", "Multi-media", "Others"], "post_time": "2022-01-13T09:03:06Z", "salary": {"currency": null, "max": null, "min": null, "period": "monthly", "term": null}, "salary_visible": false, "title_keywords": ["junior"], "responsibilities": ["social media", "photo retouching", "advertising", "edm", "website", "design", "develop", "communication"], "requirements": {"degrees": ["diploma or above"], "majors": ["design"], "languages": ["english", "chinese"], "language_level": ["good command"], "hard_skills": ["excel", "adobe photoshop", "indesign", "illustrator", "word processing", "powerpoint", "word", "flash", "pc"], "soft_skills": ["passionate", "good team player", "organization skill", "detail-oriented", "creative"], "languages_combined": [{"language": "english", "language_level": ["good command"]}, {"language": "chinese", "language_level": ["good command"]}]}, "experience_required": {"duration": ["minimum 3 years"], "field": ["design"]}}, {"job_id": "100003009051206", "location_code": "hk", "company": "Aecom Asia Company Limited", "job_title": "CAD Technician", "description": "On Stage is an award-winning events management company with over 30 years experience of world class productions.\u00a0 We specialize in producing corporate events for large organizations in HK and around the world. We are now inviting high caliber professionals to join our team.\n\nRequirements:\n\nDiploma or above\u00a0in graphic design\u00a0or\u00a0related\u00a0discipline\u00a0\nMinimum 3\u00a0years solid working experience in either event / exhibition / product launch / venue decoration\nStrong creative stage and backdrop design knowledge\nProficient in illustrator, photoshop\u00a0will be an advantage\nPassion in event industry and eager to participate in entire process from design to build\nStrong creative sense, detail-oriented, can meet tight deadline\n\n\n\nCandidates with less experience will be considered as Designer.\n", "employment_types": ["Full Time", "Permanent"], "selling_points": ["Minimum 5 years of experience in CAD Drafting", "Carry out CAD drafting for landscape projects", "Strong proficiency in AutoCAD"], "locations": ["Shatin Area"], "categories": ["Building & Construction", "Architectural Services", "Design", "Others"], "post_time": "2022-01-15T04:44:14Z", "salary": {"currency": null, "max": null, "min": null, "period": "monthly", "term": null}, "salary_visible": false, "title_keywords": ["technician"], "responsibilities": ["graphic design", "management", "design"], "requirements": {"degrees": ["diploma or above"], "majors": ["graphic design"], "languages": [], "language_level": [], "hard_skills": ["illustrator", "photoshop"], "soft_skills": ["detail-oriented", "creative", "meet tight deadline", "passion in"], "languages_combined": []}, "experience_required": {"duration": ["30 years", "minimum 3 years"], "field": ["management", "designer"]}}, {"job_id": "100003009044995", "location_code": "hk", "company": "Kenal Group Limited", "job_title": "Game 3D Model Artist", "description": "Responsibilities:\n\nKnowledge in fabrication, installation and site coordination;\nFamiliar with local Design Codes of Practice including submissions to government departments essential\n\nRequirements :\nGraduate of B.Sc/ Dip in Civil/ Mech. or other Engineering\nMin. 2 years of experience in Structural Steel, Glazing or Aluminum Works\u00a0\nWe offer :\n\nEarly leave on festive days\nPerformance Bonus\nBank Holiday\n\u7533\u8acb\u9808\u77e5 :\u6c42\u8077\u8005\u53ef\u50b3\u771f(25629951)\u6216\u96fb\u90f5(Apply Now)\u5c65\u6b77\u8868\u7d66\u611b\u9054\u5a01\u6709\u9650\u516c\u53f8\u3002\u5982\u8981\u7d22\u53d6\u6536\u96c6\u500b\u4eba\u8cc7\u6599\u8072\u660e, \u8acb\u8207\u53f8\u5f92\u5c0f\u59d0(Fax/Email)\u806f\u7d61\u3002", "employment_types": ["Full Time", "Permanent"], "selling_points": ["Serious passion for 3D games", "Produce high quality animated voxel assets", "Strong creative and technical design skills"], "locations": ["Kowloon Bay"], "categories": ["Design", "Multi-media", "Others"], "post_time": "2022-01-13T06:50:35Z", "salary": {"currency": null, "max": null, "min": null, "period": "monthly", "term": null}, "salary_visible": false, "title_keywords": ["model"], "responsibilities": ["installation", "site coordination", "design"], "requirements": {"degrees": ["dip"], "majors": [], "languages": [], "language_level": [], "hard_skills": [], "soft_skills": [], "languages_combined": []}, "experience_required": {"duration": ["2 years"], "field": ["structural"]}}, {"job_id": "100003009047149", "location_code": "hk", "company": "SEN Construction Company Limited", "job_title": "Interior Designer / Assistant Interior Designer", "description": "Responsibilities:\n\n\nResponsible for digital graphic design creatives and executions;\nDesign and execute compelling creative for digital channels by mobile / desktop in a wide range of media platforms;\nCreating and editing animation / motion graphic for informative and promotional videos.\n\n\nRequirements:\n\n\nDiploma or above in Multimedia Design, Graphic Design, Creative Media or related discipline;\n1-2 years relevant experience;\nProficient in Adobe Creative skills; Illustrator, Photoshop, InDesign, Premiere, After Effects etc.\nKnowledge in photography and video editing are preferred;\nGood written and verbal communication skills in both English and Chinese;\nSelf-motivated, responsible, able to work independently and adapt to different environment;\nPortfolio is required for interview.\n\nBenefits:\n\n\n5days work / Bank Holidays / Annual Leaves / Medical Insurance / Birthday Leave, Maternity Leave, Funeral Leave / Promotion Opportunities etc.\n\nWe offer competitive remuneration including career prospects to the right candidate. Interested parties please send your portfolio and resume with current & expected salary by clicking 'Apply Now' for application.\n\n(Data collected will only be used for job application processing. All related information will be kept up to 6 months and all personal data will be destroyed afterwards.)\n\n", "employment_types": ["Full Time"], "selling_points": ["\u505a\u5927\u54c1\u724c\u5e97\u8216\u88dd\u4fee\u8a2d\u8a08, \u589e\u52a0\u500b\u4eba\u7d93\u9a57\u503c", "Double pay", "\u7531\u4e2d\u74b0\u6e2f\u9435\u5230\u516c\u53f8, \u53ea\u8981\u6b65\u884c5\u5206\u9418"], "locations": ["Central"], "categories": ["Design", "Interior", "Visual Merchandising", "Others"], "post_time": "2022-01-14T02:28:08Z", "salary": {"currency": "HKD", "max": 34999, "min": 14000, "period": "monthly", "term": null}, "salary_visible": true, "title_keywords": ["interior designer", "assistant interior designer"], "responsibilities": ["graphic design", "design", "editing", "motion graphic", "animation"], "requirements": {"degrees": ["diploma or above"], "majors": ["multimedia design", "graphic design", "creative media"], "languages": ["english", "chinese"], "language_level": ["good"], "hard_skills": ["indesign", "illustrator", "premiere", "video editing", "after effects", "adobe", "multimedia", "photoshop"], "soft_skills": ["communication skills", "self-motivated", "work independently", "responsible", "creative"], "languages_combined": [{"language": "english", "language_level": ["good"]}, {"language": "chinese", "language_level": ["good"]}]}, "experience_required": {"duration": ["1-2 years"], "field": ["relevant experience"]}}, {"job_id": "100003009045959", "location_code": "hk", "company": "Smart Will Engineering Limited", "job_title": "\u5e73\u9762\u8a2d\u8a08\u5e2b (15K-20K)", "description": "Duties:\n\nResponsible for\u00a0game graphic design including characters(\u7537\u6027\u5411\u4e8c\u6b21\u5143), items, user interface and effects\nParticipation in concept development and innovation for our games\nWork closely with art lead, game designers and programmers\n\nRequirement:\n\nDiploma or above in Media Art / Design or related disciplines\nGood skill of drawing, illustration, colors, lighting and composition\nStrong sense of game character design\nProficient in Photoshop\n1-5 years game design experience\nWith great passion for games development\nGood team player with mature working attitude\n\nBenefits:\n\n\n5-day work\nPaid birthday leave\nBirthday pocket money\nPerformance bonus\nMedical insurance\nDental subsidy\nFree snack and beverage\nFriendly working environment\n\nInterested parties please apply with the following details:\n\nResume\nExpected Salary\nEarliest Availability\nPortfolio", "employment_types": ["Full Time"], "selling_points": [], "locations": ["Shatin Area"], "categories": ["Design", "Graphics", "Others"], "post_time": "2022-01-13T09:14:07Z", "salary": {"currency": "HKD", "max": 19999, "min": 14000, "period": "monthly", "term": null}, "salary_visible": true, "title_keywords": [], "responsibilities": ["graphic design", "user interface"], "requirements": {"degrees": ["diploma or above"], "majors": ["related disciplines", "art", "design"], "languages": [], "language_level": [], "hard_skills": ["illustration", "photoshop"], "soft_skills": ["good team player", "mature", "passion for"], "languages_combined": []}, "experience_required": {"duration": ["1-5 years"], "field": ["design"]}}, {"job_id": "100003009048792", "location_code": "hk", "company": "Active Way Ltd", "job_title": "Design Engineer / Assistant Design Engineer/ Draftsman", "description": "Job Highlight\n\nCarry out CAD drafting for landscape projects\nStrong proficiency in AutoCAD\nminimum 5 years of experience in CAD Drafting\nKnowledge in BIM, Rhino, Revit and 3D modelling software would be an advantage\nJob Description:\n\nWe help shape the world around us \u2014 from high-rise buildings to educational, cultural, research and transportation facilities. Our design process is based on energy-efficient building systems, and an appropriate selection of materials and form to maximize environmental conditions and long-term performance.\n\nWe are looking for\u00a0CAD Technician\u00a0to join our prestigious Landscape team in Hong Kong.\n\n\nResponsibilities:\n\u00a0\nPrepare detailed design, tender and construction drawings based on schematic design provided by landscape designers\nUpdate and manage office CAD Library\n\nRequirements:\n\u00a0\nMinimum 5 years practical experience in preparing landscape detailed design, tender and construction drawings\nCapable of translating schematic design to detailed design drawings\nGood knowledge in hard and soft landscape technical details\nStrong proficiency in AutoCAD and other tender/construction package drawing software\nKnowledge in BIM, Rhino, Revit and 3D modelling software would be an advantage\nWork independently and proactively with the project team", "employment_types": ["Full Time"], "selling_points": ["Knowledge in fabrication, installation, coordinate", "2 years of experience in Structural Steel, Glazing", "Graduate of B.Sc/ Dip in Civil/ Mech &Engineering"], "locations": ["Quarry Bay"], "categories": ["Design", "Others", "Building & Construction", "Civil / Structural", "Engineering", "Manufacturing & Production"], "post_time": "2022-01-14T07:24:57Z", "salary": {"currency": null, "max": null, "min": null, "period": "monthly", "term": null}, "salary_visible": false, "title_keywords": ["draftsman", "assistant", "design engineer"], "responsibilities": ["tender", "systems", "design", "drawings"], "requirements": {"degrees": [], "majors": [], "languages": [], "language_level": [], "hard_skills": ["rhino", "3d modelling", "bim", "autocad", "revit"], "soft_skills": ["work independently", "capable", "detailed"], "languages_combined": []}, "experience_required": {"duration": ["minimum 5 years"], "field": ["construction", "design"]}}, {"job_id": "100003009036952", "location_code": "hk", "company": "Eventist Hong Kong Limited", "job_title": "3D Designer / Senior 3D Designer", "description": "Game 3D Model Artist\n\nAbout the Kenal Group www.kenalgroup.com\n\nKenal Group \u2013 Brand New Metalive.es in the Metaverse\u2026\n\nCome Flow with Us\u2026\n\nPANGU by Kenal - one of the #NFT #GameStudio @TheSandboxGame\nempowering brands with authentic, legendary and immersive assets & experiences in the #Metaverse\n\nThe Sandbox\u00a0- a virtual world where players can build, own and monetize their own 3D gaming experiences on the Ethereum blockchain. We are building a deeply immersive gaming virtual world metaverse where creators get the chance to make games next to gaming giants and brands such as Atari, Rollercoaster Tycoon, Shaun the Sheep and more gaming partners.\n\n- Website: www.sandbox.game\n\n- What is The Sandbox: https://medium.com/sandbox-game/what-is-the-sandbox-850de68d893e\n\n-\u00a0More Resources: http://resources.sandbox.game\n\n\n\nAbout the job\n\nThe\u00a0perfect fit will have to\u00a0create levels for our UGC virtual world, using our no-code The Sandbox Game Maker tool, which is a main component of The Sandbox decentralized gaming virtual world gaming platform, allowing to create voxel game experiences.\n\nThe position can be in-house alongside 3D Artists and Creators who produce 3D voxel assets to put these into context inside a voxel-based environment and implement the Behaviors and Components of the game maker to create compelling games with quests, rewards and more.\n\n\n\nRequirements\n\n- Knowledge about general Game Design and Level Design concepts\n\n- Experience designing avatar-centric 3D levels\n\n- Experience working with in-house editors (Unity or similar)\n\n- Experience working with MMO RPGs or Adventure games\n\n\n\nCommunication skills\n\nBasic programing or logic skills\n\nNice to Have\n\n- Played other UGC games where you create your own levels (including mechanics) such as Minecraft or Roblox\n\n- An eye for aesthetics, knowing what makes an environment appealing and a story compelling\n\n- Having coordinated a team in the past\n\n- Having been involved in UX processes for an editing tool\n\n- Knowledge about cryptogames", "employment_types": ["Full Time"], "selling_points": ["Minimum 1 year experience", "Good career and attractive remuneration package", "San Po Kong, 5-day work"], "locations": ["Wong Tai Sin Area"], "categories": ["Design", "Graphics", "Visual Merchandising", "Others"], "post_time": "2022-01-11T00:58:45Z", "salary": {"currency": null, "max": null, "min": null, "period": "monthly", "term": null}, "salary_visible": false, "title_keywords": ["designer", "senior 3d designer"], "responsibilities": [], "requirements": {"degrees": [], "majors": [], "languages": [], "language_level": [], "hard_skills": ["nice", "basic", "unity"], "soft_skills": ["communication skills"], "languages_combined": []}, "experience_required": {"duration": [], "field": []}}, {"job_id": "100003009047625", "location_code": "hk", "company": "Welab Bank Limited", "job_title": "UI/UX Designer (Virtual Bank)", "description": "\u00a0\u8077\u8cac\u53ca\u8981\u6c42\n\n\u5e73\u9762\u8a2d\u8a08\u5de5\u4f5c\n\u5177\u5099\u5e73\u9762\u8a2d\u8a08\u5de5\u4f5c\u7d93\u9a57\n\u719f\u6089\u6709\u95dc\u8a2d\u8a08\u8edf\u4ef6\uff08Photoshop\u3001Illustrator ...\uff09\n\u8acb\u9644\u4e0a\u500b\u4eba\u4f5c\u54c1\n\u6bcf\u90315.5\u5929\u5de5\u4f5c(\u85aa\u91d1$15000-$20000\uff0c\u8996\u5de5\u4f5c\u7d93\u9a57\u800c\u5b9a)\n\u706b\u70ad\u5340\u5de5\u4f5c\n\n\u6211\u5011\u8aa0\u610f\u62db\u8058\u5c0d\u5de5\u4f5c\u5145\u6eff\u71b1\u8aa0\u7684\u60a8\u3002\u6709\u610f\u8005\u8acb\u5c07\u500b\u4eba\u5c65\u6b77\u3001\u8981\u6c42\u5f85\u9047\u53ca\u53ef\u4e0a\u73ed\u65e5\u671f\uff0c\u4e26\u8acb\u6ce8\u660e\u7533\u8acb\u8077\u4f4d\u3002", "employment_types": ["Full Time", "Permanent"], "selling_points": ["Take ownership of the entire user experience", "Develop and prototype design solutions", "Work with the team in strategic development"], "locations": ["Quarry Bay"], "categories": ["Banking / Finance", "Financial Services", "Design", "Others", "Information Technology (IT)", "UI/UX Designer"], "post_time": "2022-01-14T03:36:28Z", "salary": {"currency": null, "max": null, "min": null, "period": "monthly", "term": null}, "salary_visible": false, "title_keywords": ["ux designer"], "responsibilities": [], "requirements": {"degrees": [], "majors": [], "languages": [], "language_level": [], "hard_skills": [], "soft_skills": [], "languages_combined": []}, "experience_required": {"duration": [], "field": []}}, {"job_id": "100003009046446", "location_code": "hk", "company": "CHOW TAI FOOK JEWELLERY CO LTD", "job_title": "Jewellery Designer / Senior Jewellery Designer", "description": "WeLab is a leading fintech company in Asia, \u00a0which operates one of first licensed digital banks in Asia \u2013 WeLab Bank, as well as multiple leading online financial services businesses including WeLend and WeLab Bank in Hong Kong, WeLab Digital (\u6211\u6765\u6570\u79d1), Taoxinji (\u6dd8\u65b0\u673a), Wallet Gugu (\u94b1\u5939\u8c37\u8c37) and Tianmian Tech (\u5929\u5195\u79d1\u6280)\u00a0in Mainland China and Maucash in Indonesia. WeLab aims to bring joy to everyone\u2019s financial journey. We strive to improve people\u2019s lives by reinventing financial services through game-changing technology. We put our people first, whether it\u2019s our customers or our employees.\n\nAs the only homegrown Hong Kong fintech to receive a virtual banking license, we aim to reinvent and redefine the banking experience by building a bank we love.\n\nWe are an energetic and passionate team that can deliver and execute. We are looking for other intellectually curious, open-minded and smart-working individuals who are just as passionate as we are about making financial services enjoyable. Now you have the opportunity to join us on our journey to achieve our vision and be part of building a better financial future for everyone.\n\nAbout you:\n\nYou're a go-getter with mad juggling skills (or multiple hats) who can thrive in a fast-paced, agile environment\nYou have a strong thirst for knowledge and are driven to find solutions that don't exist yet\nYou are comfortable with ambiguity and extremely resourceful (in your past life you could've been a detective)\nYou always find a way to get things done without sacrificing the quality of your work, integrity and values. No task is off limits for you.\nYou are humble and prioritize the success of the team over your own with an eagerness to help those around you\nYou don't shy away from challenges and have the ability to bounce back from setbacks\n\nWhat you\u2019ll do and what success looks like in this role\n\nTake ownership of the entire user experience, including thinking about how UI/UX drives activation, engagement and retention in our products\nDevelop and prototype design solutions, not only to communicate ideas and concepts but to test with real customers to encourage collaboration and iterative processes\nWork with the team in strategic development, ongoing refinement and refinement of product roadmap\nDo user research, customer feedback, user testing, and usability findings to tailor your designs to the user in order to best solve their problems.\nCreate innovative experiences from high-level requirements and deliver process flows, wireframes, and product designs\nCombine creativity with an awareness of design elements, user-centered design, business objectives, and technical limitations\nWork with product, engineering, and data science to deliver the best solutions within a reasonable timeframe\n\nWhat is required and what we\u2019re looking for\n\nA minimum of 3+ years of designing digital products\nProficiency\u00a0in Figma, Sketch and/or Adobe Illustrator, Photoshop.\nExcellent visual sense to set up frameworks, brainstorm initial design concepts and development\nUnderstanding of interactivity, information architecture, hierarchy, layout, and usability principles\nExperience working with software engineers\nStrong communication skills and ability to influence counterparts/stakeholders at various levels\nPortfolio is required for application\n\nWeLab perks:\n\nCompetitive salary\nLearning and development stipend, because we value lifelong learning and believe the best way to invest in our employees is to encourage them to continue to learn\nWork hard and laugh lots (chicken wings and french toast, etc.) with a high-performing, fun and diverse team\nHappiness Dollars for spending on anything that makes you happy\nCoffee stipend\nConveniently located office surrounded by diverse and delicious lunch options\nLively office with gaming consoles and a ping pong table\nFun extracurricular activities with your colleagues like hiking, yoga, badminton, wine tasting, dragon boat racing, rock climbing, etc.\nEmployee referral bonuses\n\nAwards & recognition:\n\nFinancial Times (FT) 2020 Asia-Pacific High-Growth Companies \u2013 #2 ranked company\n2020 CNBC Disruptor 50 List \u2013 #11, only company included from Hong Kong and just one of five from Asia\n\nWe offer competitive salary package to the successful candidate.\u00a0 If you are interested in joining this exciting team, please apply with resume via the \"Apply\" button.\n\nAll information provided by applicants will be used for recruitment purposes only. Information of unsuccessful applicants will be destroyed within 24 months of receipt.", "employment_types": ["Full Time", "Contract"], "selling_points": ["Concept development, jewellery design", "Global vision of design, aesthetic, creative sense", "\u2022\tHand sketching, Illustrator, Photoshop"], "locations": ["Kwai Hing"], "categories": ["Design", "Others", "Manufacturing", "Jewelry"], "post_time": "2022-01-13T11:14:34Z", "salary": {"currency": null, "max": null, "min": null, "period": "monthly", "term": null}, "salary_visible": false, "title_keywords": ["designer"], "responsibilities": ["design concepts", "ideas", "software", "design solutions", "data", "quality", "user experience", "design", "develop", "testing", "designing", "communication", "visual", "banking", "architecture", "ui"], "requirements": {"degrees": [], "majors": [], "languages": ["french"], "language_level": [], "hard_skills": ["no", "joy", "agile", "fun", "adobe illustrator", "photoshop", "go", "mad"], "soft_skills": ["passionate", "communication skills", "agile", "resourceful", "open-minded", "integrity", "prioritize", "innovative", "diverse", "learning", "energetic", "driven"], "languages_combined": [{"language": "french", "language_level": []}]}, "experience_required": {"duration": [], "field": ["banking experience", "banking"]}}, {"job_id": "100003009044441", "location_code": "hk", "company": "Oasis Brand Communications Company Limited", "job_title": "Designer", "description": "What You Do\n\nDevelop design proposal for creative projects, collaborating with project manager and different business units\nConduct market research, analyze sales data to develop concept and create jewellery designs\n\u00a0Create presentation to visualize creative idea\nActively assist in prototyping process ensure high quality and completeness\nCommunicate closely with internal teams for completion of tasks within lead time\nHandle ad-hoc project as assigned by supervisor\n\nWho Will Thrive\n\n\u00a0Diploma\u00a0or above\u00a0in Design or related disciplines\nMin. 3 years\u2019experience in jewellery design (Candidates possess 5+ years of relevant experience can apply for senior jewellery designer)\nGood at hand sketching, mastery of Photoshop, Illustrator and Powerpoint\nKnowledge in jewellery production\nPassionate in art and design with global vision, aesthetic and creative sense\nIndependent, detail oriented, self-motivated and responsible\nStrong communication and presentation skill\nGood command of written and spoken English and Chinese\n\nBenefits:\n\n5-day work\nCompetitive salary, staff meal, medical and dental insurance, life insurance\nVarious types of leave, e.g. Family-friendly leave, self-development Leave, examination leave, marriage leave, birthday leave, volunteer service leave, etc\n\nWe offer excellent career opportunities, attractive remuneration package & benefits to the right candidate. Interested parties please click \"Apply Now\" below or apply with full resume with portfolio by stating latest and expected salaries to 22/F, Chow Tai Fook Centre, 580A-580F Nathan Road, Mongkok, Kowloon, Hong Kong.\n\nAll information collected for recruitment purpose only.", "employment_types": ["Full Time"], "selling_points": ["all-rounded design knowledge", "fresh graduate will be considered", "willing to work overnight & holiday"], "locations": ["Kwun Tong"], "categories": ["Media & Advertising", "Creative / Design", "Design", "Graphics", "Others"], "post_time": "2022-01-13T04:04:50Z", "salary": {"currency": null, "max": null, "min": null, "period": "monthly", "term": null}, "salary_visible": false, "title_keywords": ["designer"], "responsibilities": ["ad-hoc", "data", "conduct market research", "quality", "teams", "design", "develop", "communication"], "requirements": {"degrees": ["diploma or above"], "majors": ["related disciplines", "design"], "languages": ["english", "chinese"], "language_level": ["good command"], "hard_skills": ["presentation skill", "illustrator", "powerpoint", "photoshop"], "soft_skills": ["passionate", "presentation skill", "self-motivated", "independent", "responsible", "detail oriented", "communication", "creative", "presentation"], "languages_combined": [{"language": "english", "language_level": ["good command"]}, {"language": "chinese", "language_level": ["good command"]}]}, "experience_required": {"duration": ["5+ years"], "field": ["relevant experience", "designer", "design"]}}, {"job_id": "100003009043682", "location_code": "hk", "company": "Legato Technologies Limited", "job_title": "UI / UX Designer", "description": "Job Duties & Responsibilities:\n- Strong ability to develop compelling visuals and ideas\n- Responsible for design from concept creative to supervise production\n- Experience on wide range of works, such as event production, printing materials, POSM, etc.\n\nRequirements:\n- Diploma in Graphic Design or Related Discipline\n- Experience in advertising agency/ graphic house is preferred.\u00a0 Fresh graduate will be also considered.\n- With art senses, well organised, mature, highly responsible and independent\n- Willing to complete project under tight deadlines\n-\u00a0Work at holiday and even in overnight is required\n- Proficiency in Photoshop, Illustrator with Mac Experience", "employment_types": ["Full Time", "Part Time", "Permanent", "Contract", "Freelance"], "selling_points": [], "locations": ["Kowloon Bay"], "categories": ["Media & Advertising", "Creative / Design", "Design", "Others"], "post_time": "2022-01-13T01:28:01Z", "salary": {"currency": null, "max": null, "min": null, "period": "monthly", "term": null}, "salary_visible": false, "title_keywords": ["ux designer"], "responsibilities": ["ideas", "design", "develop"], "requirements": {"degrees": ["diploma", "fresh graduate"], "majors": ["graphic design"], "languages": [], "language_level": [], "hard_skills": ["illustrator", "photoshop"], "soft_skills": ["independent", "responsible", "mature", "organised"], "languages_combined": []}, "experience_required": {"duration": [], "field": ["graphic", "advertising agency"]}}, {"job_id": "100003009049331", "location_code": "hk", "company": "Sitoy Group Holdings Limited", "job_title": "Creative Multimedia - Senior Designer", "description": "This person should have a strong creative mind set with a deep technical knowledge of the latest tools and technology to deliver finished end products independently. The position requires to work closely with Regional and local teams, Marketing and Merchandising team to produce relevant content for our target audience.\n\nResponsibilities:\n\nPlan, create, develop and execute multimedia content\u00a0 (social media, photography, video, graphics and website), to deliver key brand message to internal and external audiences\nPlan and coordinate the brand\u2019s seasonal advertising campaign\nCollaborates with marketing, sales, and design teams to produce relevant content for all stages of our sales and marketing processes.\nStay abreast of industry trends and technologies\nEnsure content meets brand guidelines and is on target\n\nRequirements:\n\n3 years or above of content management role / assistant manager role will be considered should candidate has more experience\nExperience working within creative team and regional offices\nProficiency in photo / graphic software \u2013 Adobe acrobat, photoshop, illustrator, indesign; video editing software \u2013 Adobe after effects, Final cut pro\nKeen eye for small details and exceptional problem-solving skills\nAbility to work in a fast-paced environment and meet targeted deadlines.\nMust be professional, organized, enthusiastic and a team player who can work independently.\n\nWe offer competitive remuneration package, 5-day work, performance bonus, medical insurance and paid leave.\u00a0 Interested parties please send your full resume \u00a0(Both of\u00a0Chinese and English Version ) with current and expected salary via email to us\u00a0or click \u201cApply Now\u201d. No expected salary mentioned in resume will not be considered.\n\nAll information collected will be kept in strict confidential and used for recruitment purpose only.\u00a0\n\n*We are an equal opportunities employer*", "employment_types": ["Full Time"], "selling_points": ["Luxury\uff5cRetail \uff5cMultimedia Design", "5-day work, Performance Bonus, Medical Insurance", "Birthday Leave,Study&Exam. Leave,Graduation Leave"], "locations": ["Kwun Tong"], "categories": ["Design", "Graphics", "Multi-media", "Others"], "post_time": "2022-01-14T08:28:37Z", "salary": {"currency": null, "max": null, "min": null, "period": "monthly", "term": null}, "salary_visible": false, "title_keywords": ["senior designer", "creative"], "responsibilities": ["graphics", "social media", "advertising", "teams", "website", "plan and coordinate", "develop", "design", "brand guidelines", "plan"], "requirements": {"degrees": [], "majors": [], "languages": [], "language_level": [], "hard_skills": ["final cut pro", "small", "indesign", "illustrator", "adobe after effects", "video editing", "problem-solving skills", "adobe acrobat", "photoshop"], "soft_skills": ["organized", "work independently", "fast-paced environment", "keen", "enthusiastic", "problem-solving skills", "team player", "creative"], "languages_combined": []}, "experience_required": {"duration": ["3 years"], "field": ["management", "team"]}}, {"job_id": "100003009050418", "location_code": "hk", "company": "Kingsmen Hong Kong Ltd", "job_title": "3D Designer \u2013 Multidisciplinary Design - Creative & Design", "description": "Responsibilities:\nTo co-ordinate design requirements and work with team members, from creative development to final production.\nDesign & prepare rendering for presentation, artwork and technical drawing for production.\nSupervise on-site set construction if needed.\nRequirements:\nPolytechnic and Design Institute graduated or equivalent.\n3 years\u2019 experience in the related field.\nProficient in PC skills, AutoCAD, 3D Max, Sketchup, Vray, Photoshop, Illustrator.\nCreative mind and show evidence by work portfolio.\nIndependent, responsible, self-motivated and can work under pressure.\nKnowledge in production and provide artwork, shop drawing for build construction.\nSkills in multi-media software is an advantage.\nGood command of written and spoken English, Chinese.\n* Email your portfolio (either online or in PDF format) to us will be considered. *\nWe offer 5-days work and medical benefits to the right candidate. Interest party, please send your application with full resume, experience, expected salary and earliest date available to The HR & Admin Department via \"Apply Now\"\n\nWelcome to our website www.kingsmen-gc.com . Only shortlisted candidate will be notified for interview.", "employment_types": ["Full Time", "Permanent"], "selling_points": [], "locations": ["Shatin Area"], "categories": ["Design", "Multi-media", "Others"], "post_time": "2022-01-14T10:22:17Z", "salary": {"currency": null, "max": null, "min": null, "period": "monthly", "term": null}, "salary_visible": false, "title_keywords": ["creative", "designer"], "responsibilities": ["design", "technical drawing"], "requirements": {"degrees": [], "majors": [], "languages": ["english", "chinese"], "language_level": ["good command"], "hard_skills": ["illustrator", "autocad", "photoshop", "max", "pc skills", "sketchup"], "soft_skills": ["self-motivated", "independent", "responsible", "creative", "work under pressure"], "languages_combined": [{"language": "english", "language_level": ["good command"]}, {"language": "chinese", "language_level": ["good command"]}]}, "experience_required": {"duration": ["3 years"], "field": ["related"]}}, {"job_id": "100003009048342", "location_code": "hk", "company": "Polyfair Construction & Engineering Limited", "job_title": "Senior Design Engineer / Senior Design Manager (Fa\u00e7ade / Curtain Wall)", "description": "Responsibilities:\nDesign and review the curtain wall system, preparation of shop drawings and submittals to clients, consultants and Buildings Department for approval.\u00a0\n\nRequirements:\n- Degree/Diploma holder in Engineering or Building or equivalent\n- 8 years' related working experience\n- Familiar with design software\n- Good interpersonal and communication skills\n-\u00a0Good command of spoken and written English & Chinese\n- Strong planning and organizational skills and able to work under pressure\n\nInterested parties please send resume with the expected salary by clicking \"Apply Now\".\n", "employment_types": ["Full Time"], "selling_points": ["8 years' experience", "Degree/Diploma in Engineering or Building", "Double Pay, Medical Insurance, Bank Holiday"], "locations": ["North Point"], "categories": ["Design", "Industrial / Product", "Others", "Building & Construction", "Building / Construction / QS"], "post_time": "2022-01-14T06:22:48Z", "salary": {"currency": null, "max": null, "min": null, "period": "monthly", "term": null}, "salary_visible": false, "title_keywords": ["design manager", "design engineer"], "responsibilities": ["review", "design", "drawings"], "requirements": {"degrees": ["diploma holder", "degree"], "majors": ["engineering"], "languages": ["english", "chinese"], "language_level": ["good command"], "hard_skills": [], "soft_skills": ["communication skills", "interpersonal", "organizational skills", "work under pressure"], "languages_combined": [{"language": "english", "language_level": ["good command"]}, {"language": "chinese", "language_level": ["good command"]}]}, "experience_required": {"duration": ["8 years"], "field": ["related"]}}, {"job_id": "100003009042144", "location_code": "hk", "company": "", "job_title": "Senior Graphic Designer (BR-SGD)", "description": "Key responsibilities:\n\n\nGuide and deliver multi-purpose graphic design initiatives, including product development, packaging, iconography, illustrations, infographics, video, and fashion graphics\nDevelop creative concepts, layouts and artworks in various platforms such as websites, social media visuals, Facebook applications, mobile\nDesign engaging and differentiating content experiences that uphold brand guidelines and values, and within the pre-set timelines and budget\nProvide art direction in photo / video shooting, and responsible for video graphics\nBrainstorm initiatives to support the team\u2019s creative delivery\nOffer continuous insight into industry best practice, design trends and content generation idea\n\nQualifications:\n\nDegree holder in graphic design related discipline\nAt least 6-8 years solid experience in graphic design in creative agency or in house environment\nExperience working on a variety of projects, including brand identity, illustration, infographics, patterns and packaging\nExperience in web design, mobile apps or online video production is an added advantage\nHas high standards and takes pride in quality of work, with great attention to detail\nBe passionate about the brand\u2019s identity, with personal charisma and visions in international design trend\nAbility to research and apply market information\nCreative, communicative and be able to collaborate with business teams to achieve brand objectives\n\nInterested parties please apply below with your resume for a private discussion. All information collected will be kept in strict confidentiality.\u00a0", "employment_types": ["Full Time"], "selling_points": ["Multi-purpose graphic design", "Develop creative concepts, layouts and artworks", "6-8 years solid experience in graphic design"], "locations": ["Not Specified"], "categories": ["Design", "Fashion", "Graphics", "Others"], "post_time": "2022-01-12T06:23:11Z", "salary": {"currency": null, "max": null, "min": null, "period": "monthly", "term": null}, "salary_visible": false, "title_keywords": ["senior graphic designer"], "responsibilities": ["graphics", "social media", "collaborate with", "market information", "video production", "graphic design", "budget", "quality", "teams", "design", "video shooting", "brand guidelines", "design trends", "facebook", "develop creative concepts", "support the team"], "requirements": {"degrees": ["degree holder"], "majors": ["graphic design"], "languages": [], "language_level": [], "hard_skills": ["graphics", "web design", "mobile", "facebook", "illustration"], "soft_skills": ["creative", "attention to detail", "responsible", "passionate about"], "languages_combined": []}, "experience_required": {"duration": ["at least 6-8 years"], "field": ["brand", "agency", "graphic design", "video production", "design"]}}, {"job_id": "100003009045278", "location_code": "hk", "company": "Lucky Pet Limited", "job_title": "Graphic Designer", "description": "\nGraphic Designer\nJob Highlight\nBranding, Graphic Design, Print advertising\nManage social media post FB, IG\nJob Description\n\u2022 2 years relevant experience\n\u2022 Proficiency in Mac Adobe design software is a must\n\u2022 Handle projects independently from concept to final production\n\u2022 Great team player, self-supervising and able to work under pressure\n\u2022 Highly creative with detailed-oriented professional\n\u2022 With passion for graphic design and advertising\n\u2022 Good time management and work efficiency with quality\n\u2022 Great communication skills and positive attitude\n\u5de5\u4f5c\u985e\u578b: Full-time, Permanent\n\u85aa\u916c: $13,000.00\u81f3$15,000.00(\u6bcf\u6708)\n\u6642\u9593:\n\u2022 Monday to Friday\nExperience:\nIllustrator: 1 year (Preferred)\nPhotoshop: 1 year (Preferred)\nInDesign: 1 year (Preferred)\n\n", "employment_types": ["Full Time"], "selling_points": [], "locations": ["Tsim Sha Tsui"], "categories": ["Design", "Graphics", "Interior", "Others"], "post_time": "2022-01-13T07:32:22Z", "salary": {"currency": null, "max": null, "min": null, "period": "monthly", "term": null}, "salary_visible": false, "title_keywords": ["graphic designer"], "responsibilities": ["social media", "management", "supervising", "advertising", "software", "graphic design", "quality", "design", "communication", "work under pressure"], "requirements": {"degrees": [], "majors": [], "languages": [], "language_level": [], "hard_skills": ["indesign", "adobe", "illustrator", "photoshop"], "soft_skills": ["communication skills", "independently", "passion for", "work under pressure", "time management", "positive attitude", "team player", "creative", "detailed"], "languages_combined": []}, "experience_required": {"duration": ["2 years"], "field": ["relevant experience"]}}, {"job_id": "100003009044084", "location_code": "hk", "company": "Zoo", "job_title": "Senior Art Director", "description": "Responsibilities:\n\nResearch market and product trends.\nPropose directions and ideas to help develop and diversify product categories.\nIdea generation and concept development for both internal requirements and external customer consideration.\nGenerate presentation materials to communicate ideas.\nFollow-up designs through to production working with all parties of the product development cycle.\n\nRequirements:\n\nDegree or Diploma in Industrial / Product Design.\n1-3 year\u2019s relevant experience/ fresh graduate may also be considered.\nInnovative and creative design approach, combined with maturity\u00a0and sensitivity to design appropriately within brand and commercial considerations.\nGood sketch, presentation and communication skills.\nSoftware knowledge of Rhino, KeyShot, Photoshop and Illustrator.\nWork within a team as well as independently with self-motivation.\n\n\n\nWe offer attractive remuneration package including 5-day work, flexible work hours and other benefits to the right candidate. Interested parties please forward full resume with expected salary and quote job reference number to\n\n\nVTech Group of Companies,\nThe Human Resources and Administration Department,\n23/F, Tai Ping Industrial Centre, Block 1,\n57 Ting Kok Road, Tai Po, Hong Kong\n\nOR\u00a0apply on-line directly through our corporate website at www.vtech.com/en/careers/.\n\nFor more information about\u00a0us, please visit our website at\u00a0www.vtech.com.\n\nAll applications will be used for the purpose of recruitment only. Applicants not invited for interview within 4 weeks may consider their applications unsuccessful. We will retain the applications for a maximum period of six months and may refer them to suitable openings within our Group.", "employment_types": ["Full Time", "Permanent"], "selling_points": [], "locations": ["Kwun Tong"], "categories": ["Media & Advertising", "Creative / Design", "Design", "Others", "Marketing / Public Relations", "Digital Marketing"], "post_time": "2022-01-13T02:59:55Z", "salary": {"currency": null, "max": null, "min": null, "period": "monthly", "term": null}, "salary_visible": false, "title_keywords": ["senior art director"], "responsibilities": ["product categories", "ideas", "develop"], "requirements": {"degrees": ["diploma", "degree", "fresh graduate"], "majors": ["design"], "languages": [], "language_level": [], "hard_skills": ["creative design", "illustrator", "photoshop", "rhino"], "soft_skills": ["communication skills", "independently", "creative", "sensitivity", "self-motivation", "innovative", "presentation"], "languages_combined": []}, "experience_required": {"duration": ["1-3 year"], "field": ["relevant experience"]}}, {"job_id": "100003009047064", "location_code": "hk", "company": "Integrated Design Limited", "job_title": "BIM Position: BIM Coordinator / BIM Modeller", "description": "Responsibilities:\n\nWork with a team of developers to deliver the best UI/UX experience for Web and iOS/Android applications\nDesign graphics/interactions for UI/UX on Web and iOS/Android mobile applications\nCandidates with less experience maybe consider for Senior Graphics Designer\n\nRequirements:\n\nDegree or diploma in Web, Multimedia, Graphic Design, Visual Art, Commercial Art and/or expertise in related fields\nHands on experience in graphics design software, knowledge in using Mac and software such as Photoshop or Illustrator\nExperience in Web or mobile UX/UI design is an advantage\nKnowledge and experience in HTML is an advantage\nPortfolio is a must\n\nInterested parties should apply with academic qualifications, full resume, present and expected salary and availability date by click \"Apply Now\"\n\nAll information gathered will be treated in strict confidence and solely used for recruitment purposes.", "employment_types": ["Full Time"], "selling_points": [], "locations": ["Wan Chai Area"], "categories": ["Design", "Others", "Building & Construction", "Building / Construction / QS", "Engineering", "Engineering Project Management"], "post_time": "2022-01-14T02:13:27Z", "salary": {"currency": "HKD", "max": 44999, "min": 20000, "period": "monthly", "term": null}, "salary_visible": true, "title_keywords": ["bim modeller", "bim coordinator"], "responsibilities": ["graphics", "ui", "design graphics"], "requirements": {"degrees": ["diploma", "degree"], "majors": ["graphic design", "art"], "languages": [], "language_level": [], "hard_skills": ["graphics", "web", "illustrator", "html", "mobile", "multimedia", "photoshop"], "soft_skills": ["hands on"], "languages_combined": []}, "experience_required": {"duration": [], "field": ["design"]}}, {"job_id": "100003009049483", "location_code": "hk", "company": "VTech Telecommunications Limited", "job_title": "Product Designer (VTT268/J05)", "description": "Benefits\n\nHospitalize + Medical Insurance\n5 days work\nPerformance Bonus\n\nRequirements\n\no\u00a0\u00a0\u00a0\u00a0experiences in lighting design would be mostly concerned, or architectural practice, interior, landscape, urban planning or related field\n\no\u00a0\u00a0\u00a0\u00a0excellent skill in autocad ,ps ,dialux ,ppt ,3d modeling ,ms office & other graphic presentation software\n\no\u00a0\u00a0\u00a0\u00a0proficient in both written and spoken English and Chinese- Cantonese & Mandarin\n\no\u00a0\u00a0\u00a0\u00a0with passion in lighting design\n\no\u00a0\u00a0\u00a0\u00a0require for business travels when necessary\n\nResponsibilities\n\no\u00a0\u00a0\u00a0\u00a0good time manner and motivated\n\no\u00a0\u00a0\u00a0\u00a0detailing and creative with excellent design coordination skills\n\no\u00a0\u00a0\u00a0\u00a0assistance for architectural lighting projects and coordination works with a responsible performance for variety tasks\n\no\u00a0\u00a0\u00a0\u00a0participate in coordination meetings\n\nminimum of 4 years and above lighting design experiences would consider as designer\n\nwith less experience would consider as assistant\n\nfresh graduate also welcome\n\ninterested parties \u2018APPLY NOW\u2019 please provide- cover letter & cv\n\nportfolio, current & expected salary, date available", "employment_types": ["Full Time", "Permanent"], "selling_points": ["Generate ideas and design products", "Fresh graduate may also be considered", "5 day work, flexible working hour, double pay"], "locations": ["Tai Po Area"], "categories": ["Design", "Industrial / Product", "Others"], "post_time": "2022-01-14T08:44:23Z", "salary": {"currency": null, "max": null, "min": null, "period": "monthly", "term": null}, "salary_visible": false, "title_keywords": ["product designer"], "responsibilities": [], "requirements": {"degrees": [], "majors": [], "languages": [], "language_level": [], "hard_skills": [], "soft_skills": [], "languages_combined": []}, "experience_required": {"duration": [], "field": []}}, {"job_id": "100003009049505", "location_code": "hk", "company": "VTech Electronics Limited", "job_title": "Product Designer / Senior Product Designer (VTE300/J10)", "description": "Measurement Required\n\nWomenswear\n\nHeight : 166 - 168cm\nShoulder : 38 cm\u00a0/ 15\u201d\nChest : 85 cm\u00a0/ 33\u00bd\u201d\nWaist :\u00a067 cm\u00a0/ 26\u00bd\u201d\nHip:\u00a093 cm\u00a0/\u00a036\u00bd\u201d\nNeck width: 37 cm\u00a0/ 14\u215d\u201d\n\nInterested parties please send your RESUME with EXPECTED SALARY and YOUR MEASUREMENT to Human Resources Department via APPLY NOW.\n\nPlease visit our company website\u00a0http://www.initialfashion.com\u00a0for more company information.\n\nAll information received will be treated in strict confidence and for recruitment purpose only.", "employment_types": ["Full Time", "Permanent"], "selling_points": ["Design Toys for babies/infant/toddler/preschoolers", "Fresh Graduates with potential will be considered", "13-month pay, bonus and flexible working hours"], "locations": ["Tai Po Area"], "categories": ["Design", "Industrial / Product", "Others", "Manufacturing", "Product Development / Management"], "post_time": "2022-01-14T08:46:11Z", "salary": {"currency": null, "max": null, "min": null, "period": "monthly", "term": null}, "salary_visible": false, "title_keywords": ["product designer", "senior product designer"], "responsibilities": ["measurement"], "requirements": {"degrees": [], "majors": [], "languages": [], "language_level": [], "hard_skills": [], "soft_skills": [], "languages_combined": []}, "experience_required": {"duration": [], "field": []}}, {"job_id": "100003009044964", "location_code": "hk", "company": "Well In Technology Development Limited", "job_title": "Art Director / Senior Designer", "description": "\u8077\u8cac:\n\n\u8ca0\u8cac\u65e5\u5e38\u670d\u88dd\u7de8\u91dd\u548c\u6539\u8863\u670d\u52d9\n\u6309\u5de5\u4f5c\u9700\u8981, \u524d\u5f80\u5e97\u8216\u70ba\u5ba2\u4eba\u63d0\u4f9b\u5ea6\u8eab\u670d\u52d9\u53ca\u5c08\u696d\u6539\u8863\u610f\u898b\n\n\u8077\u4f4d\u8981\u6c42:\n\n\n\u4e00\u5e74\u6216\u4ee5\u4e0a\u88c1\u7e2b\u7d93\u9a57\uff0c\u7d93\u9a57\u8f03\u591a\u8005\u6703\u512a\u5148\u8003\u616e\n\u6709\u8cac\u4efb\u611f\u3001\u6709\u8010\u6027\u3001\u7d30\u5fc3\u53ca\u5b88\u6642\n\u5de5\u4f5c\u5730\u9ede:\u00a0\u7063\u4ed4 /\u00a0\u5c16\u6c99\u5480\u00a0\n\n\u54e1\u5de5\u798f\u5229:\n\n\n10-15 \u5929\u6709\u85aa\u5e74\u5047\n\u82b1\u7d05\n\u8868\u73fe\u82b1\u7d05\n\u4ecb\u7d39\u4eba\u734e\u91d1\n\u91ab\u7642(\u9580\u8a3a\u53ca\u4f4f\u9662)\u798f\u5229\n\u5c08\u696d\u5728\u8077\u57f9\u8a13\n\u54e1\u5de5\u8cfc\u7269\u512a\u60e0\n\u751f\u65e5\u79ae\u7269\n\u6559\u80b2\u6d25\u8cbc\n\u7fa9\u5de5\u670d\u52d9\u5047\n\u5168\u85aa\u7522\u5047\n\u5168\u85aa\u4f8d\u7522\u5047\n\u5168\u85aa\u75c5\u5047\n\u5a5a\u5047\n\u6069\u6064\u5047\n\u9810\u9632\u5b63\u7bc0\u6027\u6d41\u611f\u75ab\u82d7\u6ce8\u5c04\n\n\u6709\u610f\u61c9\u5fb5\u8005\u8acbWhatsapp 9249 7312 / \u9ede\u9078\u00a0APPLY NOW\u00a0\u7533\u8acb\u3002\n\n\u00a0(\u6c42\u8077\u8005\u905e\u4ea4\u500b\u4eba\u8cc7\u6599\uff0c\u53ea\u4f5c\u62db\u8058\u7528\u9014\uff0c\u6240\u6709\u8cc7\u6599\u7d55\u5c0d\u4fdd\u5bc6\u3002)", "employment_types": ["Full Time"], "selling_points": ["Work with a team of developers", "Deliver the UI/UX experience for Web & iOS/Android", "Portfolio is a must"], "locations": ["Mong Kok"], "categories": ["Design", "Others", "Information Technology (IT)", "UI/UX Designer"], "post_time": "2022-01-13T06:47:16Z", "salary": {"currency": null, "max": null, "min": null, "period": "monthly", "term": null}, "salary_visible": false, "title_keywords": ["art director", "senior designer"], "responsibilities": [], "requirements": {"degrees": [], "majors": [], "languages": [], "language_level": [], "hard_skills": [], "soft_skills": [], "languages_combined": []}, "experience_required": {"duration": [], "field": []}}, {"job_id": "100003008935874", "location_code": "hk", "company": "", "job_title": "Lighting Designer Assistant / Lighting Designer", "description": "Job Description\n\nMy client is an interior design firm based in Hong Kong. They are specializing an international brand including retail and commercial design projects. The boutique locate for K11 MUSEA, 1881 Heritage, Ocean Terminal, Element Shop, Macau and China.\n\nWelcome to join our team to cope with our rapid expansion in both mainland China and Hong Kong.\n\nRequirements\n\nDiploma holder or above in Interior Design\nBasic\u00a0computer knowledge in AutoCAD\u00a0and\u00a0Photoshop are\u00a0preferable\nCapable in handling project independently for interior designer\n\nResponsible of site management, site survey,\u00a0 site staff supervision, etc.\u00a0for interior designer\n\nBasic Cantonese, English & Putonghua\nTraveling to overseas/ PRC is required\nMin 2 years site experience for interior designer\u00a0\n\nResponsibilities:\u00a0\n\nAssist the Senior Interior Designer\nDealing with clients, contractors, architectures, vendors and project team members\nResponsible for design drawings and documentation including concept design and development, construction drawing, materials sourcing and selection\nIdentify and understand clients\u2019 needs and provide customer services\n\nWe offer\u00a0double pay,\u00a0bank holidays, 5 1/2day work,\u00a0annual leave and MPF. Interested candidates please send your application letter with CV, portfolio and salary expectations by clicking 'Apply Now'", "employment_types": ["Full Time", "Part Time", "Permanent"], "selling_points": [], "locations": ["Causeway Bay"], "categories": ["Design", "Industrial / Product", "Interior", "Others"], "post_time": "2022-01-13T18:54:40Z", "salary": {"currency": null, "max": null, "min": null, "period": "monthly", "term": null}, "salary_visible": false, "title_keywords": ["designer", "assistant"], "responsibilities": ["design"], "requirements": {"degrees": ["diploma holder"], "majors": ["design"], "languages": ["cantonese", "putonghua", "english"], "language_level": ["basic"], "hard_skills": ["documentation", "basic", "photoshop", "autocad"], "soft_skills": ["independently", "capable", "responsible"], "languages_combined": [{"language": "cantonese", "language_level": ["basic"]}, {"language": "putonghua", "language_level": []}, {"language": "english", "language_level": []}]}, "experience_required": {"duration": ["min 2 years"], "field": ["designer"]}}, {"job_id": "100003009031174", "location_code": "hk", "company": "initial Fashion Co Limited", "job_title": "Part-time Fitting Model (Womenswear)", "description": "1 Post for Intimate\n1 Post for Woven / Knit / Sweater\n1 Post for Ladies\n1 Post for Men's\n1 Post for Sportswear\n\nResponsibilities\n\n\nResponsible for design and development of apparel items\nProvide directions and ideas on all design issues including costing, fashion trend research on colors, fabrication and accessories, etc.\nFollow up the entire workflow of the development from themes and concept, presentation of styling, sketches, fitting session and sampling\nCoordinate and work closely with Buyers, Merchandisers and other related parties\n\nRequirements\n\nDegree or Diploma holder in Fashion Design or related discipline\nMinimum 2-6 years of fashion design experience\nStrong awareness of market needs and fashion trend\nStrong creativity with good fashion color sense and knowledge of seasonal trends, themes, color, materials, styling and fit\nSelf-motivated, energetic, creative, with good design sense and with the ability to work independently\nProficiency in Photoshop, Illustrator, InDesign, after effect\nExcellent command in both spoken and written English and Chinese including Mandarin\n\nInterested parties, please send your resume with expected salary to \"apply now\". You can also click on the website www.easyjobhk.com for more details about the company", "employment_types": ["Part Time", "Temporary", "Contract", "Freelance"], "selling_points": [], "locations": ["Kwun Tong Area"], "categories": ["Design", "Others", "Others", "Entertainment - Artists / Singers / Musicians", "Others"], "post_time": "2022-01-13T18:48:29Z", "salary": {"currency": null, "max": null, "min": null, "period": "hourly", "term": null}, "salary_visible": false, "title_keywords": ["model"], "responsibilities": ["coordinate", "ideas", "sketches", "design"], "requirements": {"degrees": ["diploma holder", "degree"], "majors": ["design"], "languages": ["english", "chinese", "mandarin"], "language_level": ["excellent"], "hard_skills": ["after effect", "indesign", "illustrator", "photoshop"], "soft_skills": ["self-motivated", "energetic", "creative", "work independently"], "languages_combined": [{"language": "english", "language_level": ["excellent"]}, {"language": "chinese", "language_level": ["excellent"]}, {"language": "mandarin", "language_level": ["excellent"]}]}, "experience_required": {"duration": ["minimum 2-6 years"], "field": ["fashion design"]}}, {"job_id": "100003009044436", "location_code": "hk", "company": "Max Mara Fashion Group", "job_title": "Full Time / Part Time Tailor \u5168\u8077 / \u517c\u8077\u88c1\u7e2b", "description": "Calling HK\u2019s best 3D design creatives - we\u2019ve got a great role for you at our Hong Kong office! Come join us and be your best. Be imaginative, be interpretive, be inspired.\n\nWe are currently looking for a 3D Designer to work across the number of international brands.\u00a0The chosen candidate, who will report directly to the Deputy Head of Design. Join our creative and dynamic team to get involved in exciting projects and work with inspired professionals.\n\n\u00a0RESPONSIBILITES\n\nA strong sense of design and aesthetics with the ability to conceptualize ideas and bring these to realization as 3D environments\nDemonstrate creative design concepts by producing 2D & 3D visual presentations and modelling of all thematic structures and event space\nEnsure all creative is up on communication channel and always answer to the brief and client\u2019s needs\nWork closely with account servicing and production team, to discuss the concept and design approach, as well as materials used and production details\n\n\u00a0REQUIREMENTS\n\nDiploma/Degree holder\u00a0in Design or related discipline\nMinimum 1 year experience\u00a0in the field of design, especially in Design Agency or Production House and preferred to be festival decoration, exhibition or events\u00a0related\nProficient in 3D Studio Max, Photoshop, Illustrator and related PC software\nSkillful in hand sketching,\u00a0technical drawing in AutoCAD and a knowledge of graphic applications are preferable\nGood team player, good communication and presentation skills\nAble to handle challenging situations, sense of responsibility and think smart\nCandidate with more experience will be considered as Senior 3D Designer\nImmediate available is preferred.\n\nWe offer good career prospect and attractive remuneration package (Performance Bonus,\u00a0Medical,\u00a0Dental,\u00a0Birthday Leave, Family Care Leave, Education allowance, Attractive Incentive Program, Overtime Compensation)\u00a0to the right candidates.\u00a0\n\nInterest parties, please click \u201cApply Now\u201d", "employment_types": ["Full Time", "Permanent"], "selling_points": ["\u4e00\u5e74\u6216\u4ee5\u4e0a\u88c1\u7e2b\u7d93\u9a57", "\u5c08\u696d\u5728\u8077\u57f9\u8a13\u53ca\u5b8c\u5584\u54e1\u5de5\u798f\u5229", "\u5de5\u4f5c\u8207\u751f\u6d3b\u5e73\u8861"], "locations": ["Wan Chai"], "categories": ["Sales, CS & Business Devpt", "Customer Service - Supervisor / Officer", "Design", "Fashion", "Others"], "post_time": "2022-01-13T04:03:46Z", "salary": {"currency": null, "max": null, "min": null, "period": "monthly", "term": null}, "salary_visible": false, "title_keywords": [], "responsibilities": ["design concepts", "ideas", "presentations", "design", "communication", "visual"], "requirements": {"degrees": ["diploma", "degree holder"], "majors": ["design"], "languages": [], "language_level": [], "hard_skills": ["max", "illustrator", "photoshop", "pc", "autocad"], "soft_skills": ["communication", "good team player", "presentation skills", "sense of responsibility"], "languages_combined": []}, "experience_required": {"duration": ["minimum 1 year"], "field": ["agency", "related", "designer", "design"]}}, {"job_id": "100003009040722", "location_code": "hk", "company": "Pricerite Home Ltd", "job_title": "Assistant Interior Designer", "description": "\u00a0Drafting Clerk \u00a0\u7e52\u5716\u6587\u54e1\n\n\u4e2d\u4e94\u7a0b\u5ea6\n\u826f\u597d\u7684\u4e2d\u82f1\u6587\n\u80fd\u7d14\u719f\u4f7f\u7528 Illustrator \u7e52\u756b\u5e73\u9762\u5716\uff0c\u719f\u6089 Photoshop \u66f4\u4f73\uff0c\u7c21\u55ae\u88dd\u914d\u5de5\u4f5c\n\u9700\u7528\u96fb\u90f5\u53ca\u96fb\u8a71\u8ddf\u5ba2\u4eba\u6e9d\u901a\u8ddf\u9032\u7a3f\u4ef6\u53ca\u8a02\u55ae\n\u80fd\u719f\u6089\u4f7f\u7528 MS Office (Excel and Word).\n\u7368\u7acb\uff0c\u7a4d\u6975\uff0c\u505a\u4e8b\u8a8d\u771f\n\u9280\u884c\u5047\u671f\n\u8475\u9752\u5340\u5de5\u4f5c\n\u6709\u610f\u8005\u8acb\u96fb\u90f5\u5c65\u6b77\u53ca\u8981\u6c42\u5f85\u9047\u7d66\u672c\u516c\u53f8\n\nAll personal data provided by job applicants will be used for recruitment purpose only.", "employment_types": ["Full Time", "Permanent"], "selling_points": ["AutoCAD, Sketchup, Photoshop", "Store visual presentation", "Furniture / household related industry"], "locations": ["Kowloon Bay"], "categories": ["Design", "Interior", "Visual Merchandising", "Others"], "post_time": "2022-01-12T02:59:04Z", "salary": {"currency": null, "max": null, "min": null, "period": "monthly", "term": null}, "salary_visible": false, "title_keywords": ["assistant interior designer"], "responsibilities": ["personal data", "recruitment"], "requirements": {"degrees": [], "majors": [], "languages": [], "language_level": [], "hard_skills": ["excel", "illustrator", "word", "photoshop", "ms office"], "soft_skills": [], "languages_combined": []}, "experience_required": {"duration": [], "field": []}}, {"job_id": "100003009051227", "location_code": "hk", "company": "Easy Job Centre", "job_title": "Fashion Design / Senior Fashion Designer", "description": "Do you want to work in a\u00a0Young,\u00a0Fun,\u00a0and\u00a0Dynamic\u00a0Team Environment?\n\n\u00a0Do you have the\u00a0DNA\u00a0to succeed?\u00a0\n\nBe part of an Iconic \u2013 Hong Kong Brand\n\nResponsibilities:\u00a0\n\n\nDesign the line Architecture & Balance the line and upkeep a consistent brand position aiming at achieving sales growth.\n\nOversee all design, merchandising, and fabric development aspects of the line, including theme, color, fabrication, finishing, styles, price point, etc.\nConfirm styling and design details in the initial fitting session, and follow-through in subsequent fitting sessions until the pre-production sample stage.\nIdentify and serve the needs of various key markets both from a style preference and climate perspective, providing commercial yet in-trend designs.\nApprove the required Colour Standard, Lab Dip & Hand-feel\u00a0\nProvide comments on styling, concept, and color selection.\nApprove trim and accessories for bulk order production.\nPrepare Trends Script and presentation\u00a0of the collection\n\nRequirements:\n\nHigher Diploma in Fashion Design, Textile or Clothing\n\n5 years relevant experience in designing and product development of a comprehensive product range, preferably well-versed in knits or woven.\u00a0\nBe able to handle woven or knitwear collection design independently, have good fashion sense, fabric knowledge & market-oriented\nUnderstand market trends, lifestyles and customer needs for both HK and overseas markets (mainly in Asia)\nCreative with a fashion flair, yet pragmatic and highly\u00a0results-oriented\nGood communication & presentation skills as well as a leadership skill\nGood command of Cantonese, English & Putonghua\n\n\u00a0We offer:\n\nAttractive salary package\nDiscretionary Performance Bonus\nMedical Insurance\nStaff Discounts on Purchases\n5-day work week with flexible work options\nVoluntary MPF Contributions\u00a0\u00a0\n\nJOIN OUR JOURNEY.\u00a0\n\n\u00a0Experience being part\u00a0of becoming the world\u2019s most-loved apparel brand.\n\n\u00a0Only shortlisted candidates will be notified. If you are not contacted by us within\u00a02 weeks, please consider your application unsuccessful. All personal data collected would be used for recruitment purposes only.\u00a0\n\nPlease visit our website for more information:\u00a0www.G2000.com.hk", "employment_types": ["Full Time"], "selling_points": [], "locations": ["Yau Tsim Mong Area"], "categories": ["Design", "Fashion", "Graphics", "Others"], "post_time": "2022-01-15T05:19:57Z", "salary": {"currency": null, "max": null, "min": null, "period": "monthly", "term": null}, "salary_visible": false, "title_keywords": ["fashion designer"], "responsibilities": ["comments", "merchandising", "design", "pre-production", "architecture"], "requirements": {"degrees": ["diploma"], "majors": ["design"], "languages": ["cantonese", "putonghua", "english"], "language_level": ["good command"], "hard_skills": [], "soft_skills": ["independently", "communication", "presentation skills", "comprehensive", "leadership skill", "creative"], "languages_combined": [{"language": "cantonese", "language_level": ["good command"]}, {"language": "putonghua", "language_level": ["good command"]}, {"language": "english", "language_level": ["good command"]}]}, "experience_required": {"duration": ["5 years"], "field": ["product development", "relevant experience"]}}, {"job_id": "100003009039834", "location_code": "hk", "company": "Kingly Agents Limited", "job_title": "Drafting Clerk  \u7e52\u5716\u6587\u54e1", "description": "\nEntry Pathway:\nAre you ready to work in an open-minded, fun and different working environment?\nLet\u2019s join FCS\u00a0 Interior Design Consultant Ltd\nI\u00a0 \u00a0 \u00a0 \u2013\u00a0 \u00a0Bachelor's degree / Higher Diploma\u00a0 \u00a0in Interior Design or\u00a0\n\u00a0 \u00a0 \u00a0 \u00a0 \u00a0 \u00a0Architecture with over 5 years working experience in corporate\n\u00a0 \u00a0 \u00a0 \u00a0 \u00a0 \u00a0interior design sector.\nII\u00a0 \u00a0 \u00a0\u2013\u00a0 \u00a0Good communication and confident to speak in English, Cantonese and\n\u00a0 \u00a0 \u00a0 \u00a0 \u00a0 Mandarin are essential.\nIII\u00a0 \u00a0 \u00a0 \u00a0 \u2013\u00a0 Experience in space planning / conceptual design / sketching and\n\u00a0 \u00a0 \u00a0 \u00a0 \u00a0 \u00a0Strong experience in technical integration and drawing production\n\u00a0 \u00a0 \u00a0 \u00a0 \u00a0 \u00a0with AutoCAD, SketcuUp, and 3ds Max.,\nIIII\u00a0 \u00a0 \u2013\u00a0 \u00a0Passionate about Interior Design and willing to learn from the\n\u00a0 \u00a0 \u00a0 \u00a0 \u00a0 \u00a0mistake to level up\n\nV\u00a0 \u00a0 \u00a0 \u00a0\u2013\u00a0 \u00a0when you decide to become one of our core member, the most\n\u00a0 \u00a0 \u00a0 \u00a0 \u00a0 \u00a0Important is:\u00a0\u00a0\n\u2022 PROFIT SHARING\u00a0 to staff with proven abilities\n\u2022 Entrepreneurial work environment and good career prospect\n\u2022 Opportunities working with multi-national clients\nIf you are interested in this exciting opportunity, please catch up the chance and click \u201c Apply Now \u201d to submit your application with CV, portfolio in PDF (less than 8MB) and current & expected salary.\nWe looking forward to hearing from you!\n*** (All information collected will be treated in strict confidence for recruitment purpose only.)\n\n\u2022 Attractive Performance Bonus\n\u2022 Interested in designing and creative thinking\n\u2022 Design \u201cSMART\u201dworking environment\n\u2022 Encourage to participate in interior design competitions\u00a0\u00a0\n\u2022 Brave to have the challenge and innovative\n\nSenior Designer / Interior Designer\nResponsibilities:\n\u2022 Leading role in design, ensures clients\u2019 values are approximately, business needs are integrated and the design is executed holistically.\n\u2022 Working with multi-disciplines specialist articulate client\u2019s aspiration and strive to provide bespoke solutions.\n\u2022 Collaborate and Work with the team to create ideas to prepare the presentation and make them happen.\n\u00a0*****Remarks: Candidate with less experience will be considered for the position of Designer.\n\nSales & Marketing Manager\nResponsibilities:\n\u2022 Identify and explore new business opportunities\n\u2022 Maintaining an awareness of interior industry news, best practices, and trends\n\u2022 Developing, maintaining and improve relationships with existing and new clients\n\u2022 Coordinating with leadership, design and consultant teams to develop and produce proposal package.\n\u2022 Research and analyze global shifts and trends in work behaviours to develop and improve recommendations with respect to physical, digital and social workplaces\n\u2022 Create and execute commercial office design concepts through schematic planning\n\u2022 Design office environments to achieve client\u2019s brand identity and develop unique design concepts\n\u2022 Manage construction documents from designers and consultants\nRequirements:\u00a0\n\u2022 Relevant corporate interior design and fitting out, office furniture or real estate experience\n\u2022 Excellent presentation and communication skills\n\u2022 Proficient in Word, Excel and Power point\n\u2022 Excellent in English, Chinese and Mandarin, both spoken and written\n\u2022 Good time management and organization and ability to maintenance accuracy when working towards deadlines\n\u2022 Designer\u2019s proficient in AutoCAD, Photoshop, Sketch up and 3Ds Max is preferred\n\n", "employment_types": ["Full Time"], "selling_points": [], "locations": ["Kwai Tsing Area"], "categories": ["Design", "Graphics", "Others", "Others", "Others"], "post_time": "2022-01-11T11:47:26Z", "salary": {"currency": null, "max": null, "min": null, "period": "monthly", "term": null}, "salary_visible": false, "title_keywords": ["clerk"], "responsibilities": ["collaborate", "design concepts", "ideas", "explore new business opportunities", "maintaining", "teams", "developing", "design", "develop", "planning"], "requirements": {"degrees": [], "majors": [], "languages": ["english", "chinese", "mandarin"], "language_level": ["excellent"], "hard_skills": ["excel", "3ds max", "maintenance", "sketch up", "word", "photoshop", "power point", "autocad"], "soft_skills": ["communication skills", "time management", "presentation"], "languages_combined": [{"language": "english", "language_level": ["excellent"]}, {"language": "chinese", "language_level": ["excellent"]}, {"language": "mandarin", "language_level": ["excellent"]}]}, "experience_required": {"duration": [], "field": ["design"]}}, {"job_id": "100003009045146", "location_code": "hk", "company": "G2000 (Apparel) Ltd", "job_title": "Fashion Designer - Menswear", "description": "Responsibilities:\n\n\nDesign digital and mobile projects, both individually and as a team\nDevelop UI mockups, components, and prototypes for mobile app, web, or other digital forms\nPartner with peers and stakeholders across UX, Project Managers, and Engineering to understand, challenge, and design digital projects\nStaying updated on interactive creative trends\nHave the ability to clearly communicate your design rationale to internal teams and stakeholders\nCreate wireframes, storyboards, user flows, process flows and site maps to communicate interaction and design ideas\nRequirements:\n\n\nBachelor's degree in Design - preferably in graphic, visual communications, digital, or a relevant technical subject(s)\nA portfolio that demonstrates your ability to produce user-centric, high-quality interfaces is required\nUnderstanding of user experience design principles, interaction patterns, and design fundamentals\nUnderstanding that digital is about designing systems and libraries\nComfortable working with design tools like Figma. (Sketch, Photoshop, or Illustrator is a bonus.)\nExperience in UX is a plus\nEager to learn, collaborate, and give & take feedback from clients and teammates (Project Managers, Technical Lead, Business Analysts)\nTeam spirit, strong interpersonal and communication skills\nGood command of spoken and written English and Cantonese\n1-2 years of related working experience\nFresh graduates will also be considered\nImmediate availability is preferred\nBenefits:\n\n\nFive-day work week (Flexible working hours)\nMedical allowance\nPerformance Bonus\nBirthday Leave\n\nInterested parties, please send full resume with availability and expected salary to us by clicking \"Apply Now\"\n\nPersonal data will be used for recruitment purposes only.\n", "employment_types": ["Full Time", "Permanent"], "selling_points": ["Exp. in menswear design & development", "Good communication and coordination skills", "Good understanding of Asia markets"], "locations": ["Kwai Fong"], "categories": ["Design", "Fashion", "Others", "Merchandising & Purchasing", "Woven / Knit"], "post_time": "2022-01-13T07:18:33Z", "salary": {"currency": null, "max": null, "min": null, "period": "monthly", "term": null}, "salary_visible": false, "title_keywords": ["fashion designer"], "responsibilities": ["mobile app", "ideas", "teams", "design", "develop", "ui", "storyboards"], "requirements": {"degrees": ["degree", "bachelor"], "majors": ["communications", "design"], "languages": ["cantonese", "english"], "language_level": ["good command"], "hard_skills": ["plus", "illustrator", "photoshop"], "soft_skills": ["communication skills", "eager to learn", "team spirit", "interpersonal"], "languages_combined": [{"language": "cantonese", "language_level": ["good command"]}, {"language": "english", "language_level": ["good command"]}]}, "experience_required": {"duration": ["1-2 years"], "field": ["related", "design"]}}, {"job_id": "100003009041912", "location_code": "hk", "company": "FCS Interior Design Consultant Limited", "job_title": "Senior Designer / Interior Designer / Sales & Marketing Manager", "description": "We are seeking an exceptional candidate for our post of Assistant Interior Designer to join our team to bring greater success to the company.\n\nIf you are a diploma holder in Interior Design / Architecture or related discipline(s) and preference will be given to those who have at least 1 year solid working experience in interior design for retail, office and residential projects in Hong Kong.\u00a0\n\nYou have:-\n\nCreative design talent\nSensitive about the design trends\nPassion in Work / Life balance\nhighly proficient in AutoCAD, Sketchup, 3D Max and other design basic software\n\nYou will be responsible for:-\n\nAssistant to prepare a creative design presentation for clients;\nHandling full set of detail working drawings;\nSearching design materials, site management and co-ordination;\nLiaising with relevant suppliers and contractors to ensure the project can be completed on time\n\nImmediate available is preferable. We offer attractive compensation packages, including annual leave, birthday leave, performance bonus, 5-day work\u2026.\n\nInterested parties please send full resume with date of availability, present & expected salary and portfolio to email by clicking \"Apply Now\".\n\nPersonal data will be used for recruitment purposes only.", "employment_types": ["Full Time"], "selling_points": [], "locations": ["Wan Chai"], "categories": ["Design", "Graphics", "Interior", "Others"], "post_time": "2022-01-12T04:39:40Z", "salary": {"currency": null, "max": null, "min": null, "period": "monthly", "term": null}, "salary_visible": false, "title_keywords": ["senior designer", "interior designer", "sales & marketing manager"], "responsibilities": ["architecture", "design"], "requirements": {"degrees": ["diploma holder"], "majors": ["architecture", "design"], "languages": [], "language_level": [], "hard_skills": [], "soft_skills": [], "languages_combined": []}, "experience_required": {"duration": ["at least 1 year"], "field": ["related", "retail", "design"]}}, {"job_id": "100003009041609", "location_code": "hk", "company": "Atelier Pacific Ltd", "job_title": "Project Architect (Authorized Person)", "description": "About the Role:\n\nCarry out art direction, layout execution and production for social media, digital campaign and ATL\nWork as a small team and follow through project from design concept, execution, and production independently\nCooperate with copywriter, internal video production and director with the support of account servicing team\n\nWe are looking for candidate with\n\nBachelor\u2019s degree or diploma in Design stream\nOver 5 years relevant experience in advertising or digital agency\nProficient in Photoshop, Illustrator, and\u00a0other relevant design programs\nStrong sense of art direction, graphic skills on layout development and artwork production for social media and video\nKnowledge of animation or skill set of illustration would be an advantage\nStay on top of all trends of creative, social media and digital innovation\n** Portfolio must be provided at the interview **\n\n\n\nWe will provide\u00a0\u00a0\n\nExcellent career development opportunity\nAttractive remuneration package\nComprehensive on-job training\n5 days' work, friendly and energetic environment\n\nIf you are creative, passionate, determined and you value team effort, then we\u2019d love to hear from you!\u00a0\n\nInterested parties please do not hesitate to apply with full resume with your\u00a0current salary, expected salary and available date.\u00a0\u00a0\n\nAll information provided will be treated in the strictest confidence and used solely for recruitment purpose. Only shortlisted candidates will be invited for interview.", "employment_types": ["Full Time", "Permanent"], "selling_points": ["5 days works", "16 days annual leave", "Annual company outing"], "locations": ["North Point"], "categories": ["Building & Construction", "Architectural Services", "Design", "Interior", "Others"], "post_time": "2022-01-12T09:37:54Z", "salary": {"currency": null, "max": null, "min": null, "period": "monthly", "term": null}, "salary_visible": false, "title_keywords": [], "responsibilities": ["social media", "advertising", "video production", "design concept", "artwork production", "design", "career development", "cooperate with", "animation"], "requirements": {"degrees": ["diploma", "degree", "bachelor"], "majors": ["design"], "languages": [], "language_level": [], "hard_skills": ["small", "illustration", "illustrator", "photoshop"], "soft_skills": ["passionate", "independently", "creative", "determined", "comprehensive", "friendly", "energetic"], "languages_combined": []}, "experience_required": {"duration": ["5 years"], "field": ["agency", "digital", "advertising", "relevant experience"]}}, {"job_id": "100003009042694", "location_code": "hk", "company": "New Media Group Publishing Limited", "job_title": "Visual & Graphic Designer", "description": "JOB TITLE: BIM Coordinator / BIM Modeller\n\nLOCATION: Hong Kong\n\nJOB DESCRIPTION\n\nWe are the BIM Consulting Company in HK and looking for BIM Coordinator & BIM Modeller to join us.\n\nKEY RESPONSIBILITIES\n\nBIM Coordinator:\n\nCoordinate internal and external project teams to fulfil project deliverables and meet client expectations.\nReview internal and externally developed BIM models for quality and completeness to schedule.\nConduct clash analysis, visual coordination exercises and design reviews routinely for project deliverables.\nDevelop Autodesk centric BIM models to specifications and standards internally and externally.\nDevelop Autodesk centric content to specifications and standards internally and externally.\nInterpret as-built, design and construction documentation to lead & contribute to development of BIM models.\nDocument control of digital and printed material. Including incoming and outgoing project documents.\nAbility to contribute or otherwise assist as required.\n\nBIM Modeller:\n\nDevelop Autodesk centric BIM models to specifications and standards internally and externally.\nDevelop Autodesk centric content to specifications and standards internally and externally.\nInterpret as-built, design and construction documentation to develop BIM models.\nWilling to work at project site offices\n\nEXPERIENCE & EDUCATION\n\n2 to 6 years working experience in a BIM environment.\u00a0 Candidate must possess a degree or higher diploma in one of the following fields or demonstrate previous experience in Architectural, Structural, Mechanical, Electrical, Plumbing or Civil Engineering.\n\nDESIRED TECHNICAL SKILLSET KEYWORDS\n\nAutodesk Navisworks\n\nSynchro Pro\n\nFuzor\n\nAdobe Creative Suite\n\nMicrosoft Office\n\nMicrosoft Project\n\nAfter Effects\n\nDynamo\n\nBluebeam\n\nBIM 360\n\nAutodesk Revit\n\nAutodesk Civil3D\n\nPremiere\n\n\u00a0", "employment_types": ["Full Time", "Permanent"], "selling_points": ["Design original graphics", "1-3 years of experience as a graphic designer", "Great development opportunity, competitive package"], "locations": ["Kwun Tong"], "categories": ["Media & Advertising", "Creative / Design", "Design", "Graphics", "Others"], "post_time": "2022-01-12T08:25:06Z", "salary": {"currency": null, "max": null, "min": null, "period": null, "term": null}, "salary_visible": false, "title_keywords": ["graphic designer"], "responsibilities": ["control", "consulting", "project deliverables", "analysis", "review", "teams", "quality", "design", "develop", "coordinate", "project documents", "specifications", "schedule", "coordination", "visual", "documentation"], "requirements": {"degrees": ["diploma", "degree"], "majors": ["civil engineering"], "languages": [], "language_level": [], "hard_skills": ["microsoft project", "microsoft office", "analysis", "premiere", "after effects", "bim", "dynamo", "documentation", "adobe creative suite", "revit"], "soft_skills": ["outgoing", "creative", "coordination"], "languages_combined": []}, "experience_required": {"duration": ["2 to 6 years"], "field": ["structural", "engineering", "plumbing", "education"]}}, {"job_id": "100003009040643", "location_code": "hk", "company": "Midland Holdings Limited", "job_title": "Photo Editor (1-yr contract renewable)", "description": "Reporting to the Director and Associates, you are expecting your major responsibilities to be the below:\n\nYou will be playing an important role to coordinate new fitting out for luxurious retails\nPrepare to act as AP\nTake charge of architectural design management to ensure projects are completed in a timely and quality manner\nInvolve in providing project management services, including cost control, quality inspection, and programme management\nCoordinate and work closely with relevant stakeholders, such as government authorities, internal teams, consultancies, and contractors\nRequirements & Qualifications:\n\nAuthorized Person\nPossess professional architectural qualification of recognized institute (e.g. MHKIA/RIBA/RA) is required\nAt least 5 years of post-graduate experience\nFlexible, detail-minded, energetic as well as having excellent communication and interpersonal skills\nStrong leadership, planning, and management skills with an analytical mind\nFluent spoken and written English, Cantonese, and Mandarin is a must\nWhat We Offer:\n\n16 days annual leave, increasing to 21 days with long service\nBirthday leave & Marriage leave\nComprehensive medical and dental insurance\nDiscretionary performance bonus\nAnnual salary review\nAnnual company outing\nExcellent career prospect\n\nInterested parties please click \"APPLY NOW\" to submit your application.\n\n*Personal data collected will be used for recruitment purposes only.", "employment_types": ["Full Time", "Contract"], "selling_points": ["Proficiency with Graphic Design and Photoshop", "Exp in photo-retouch and video editing", "Knowledge in Adobe Creative Cloud Suite"], "locations": ["Cheung Sha Wan"], "categories": ["Design", "Graphics", "Others", "Media & Advertising", "Photography / Video"], "post_time": "2022-01-12T02:53:49Z", "salary": {"currency": null, "max": null, "min": null, "period": "monthly", "term": null}, "salary_visible": false, "title_keywords": ["editor"], "responsibilities": ["ap", "reporting", "management", "quality", "teams", "inspection", "coordinate", "project management", "communication", "design management", "cost control", "planning"], "requirements": {"degrees": [], "majors": [], "languages": ["cantonese", "english", "mandarin"], "language_level": ["fluent"], "hard_skills": ["ap", "project management"], "soft_skills": ["flexible", "detail-minded", "timely", "project management", "communication and interpersonal skills", "analytical mind", "energetic", "leadership"], "languages_combined": [{"language": "cantonese", "language_level": ["fluent"]}, {"language": "english", "language_level": ["fluent"]}, {"language": "mandarin", "language_level": ["fluent"]}]}, "experience_required": {"duration": ["at least 5 years"], "field": []}}, {"job_id": "100003009045200", "location_code": "hk", "company": "\u701f\u96f2\u96c6\u5718\u6709\u9650\u516c\u53f8", "job_title": "Senior Product Designer", "description": "We are looking for a talented visual & graphic designer to enhance our online presence with eye-catching and professional graphic designs. You will consult with the different function teams to determine design requirements, submit draft concepts for approval, and develop similar design prototypes for our products.\u00a0\n\nJob Description:\n\nDesign original graphics with unique colours, shapes, and typography fonts.\nSubmit graphic & visual design concepts for brainstorming and approval in a timely manner.\nCollaborate with the Project team and IT developers in aligning visual designs with website functionalities.\nDevelop prototypes to uniformly integrate logos and brand images to other products and platforms, including social media.\n\nRequirements:\n\nBachelor\u2019s or associate degree in graphic design, visual arts, or similar.\n1-3 years of experience as a graphic visual designer is preferred\nAdvanced proficiency in design software, such as Adobe Creative Suite's InDesign, Photoshop, and Illustrator.\nKnowledge of programming languages such as HTML and JavaScript would be advantageous.\nExtensive experience in determining visual design preferences and meeting deadlines.\nProficiency in keeping up with visual design technologies and industry trends.\nGood communication skills.\n\nWe offer competitive salary and benefits package( 5 days work, 14 days AL up, birthday leave, medical & dental insurance) with great opportunity for career development to the successful candidate.\n\nFor applications, please send the resume to us, specify in email title \u201cJob Application for\u00a0Visual & Graphic Designer\"", "employment_types": ["Full Time"], "selling_points": [], "locations": ["Not Specified"], "categories": ["Design", "Graphics", "Interior", "Others"], "post_time": "2022-01-13T07:25:34Z", "salary": {"currency": null, "max": null, "min": null, "period": "monthly", "term": null}, "salary_visible": false, "title_keywords": ["senior product designer"], "responsibilities": ["graphics", "design concepts", "collaborate with", "social media", "a timely manner", "website", "design", "develop", "visual"], "requirements": {"degrees": ["associate degree", "bachelor"], "majors": ["graphic design"], "languages": [], "language_level": [], "hard_skills": ["indesign", "illustrator", "html", "visual design", "javascript", "programming", "adobe creative suite", "photoshop"], "soft_skills": ["communication skills", "creative", "extensive", "advanced"], "languages_combined": []}, "experience_required": {"duration": ["1-3 years"], "field": ["graphic", "designer", "design"]}}, {"job_id": "100003009042866", "location_code": "hk", "company": "Aedas Interiors Limited", "job_title": "Temporary Interior / FF&E Designers", "description": "CASETiFY is looking for a Motion Graphic to join our Design Team. The Motion Graphic Designer should have experience creating motion graphics, animation, a strong sense of graphic designs, branding layout and grid systems.\n\nAs part of our new team member, you will be responsible for in-store activation and campaigns digitally and physically.\u00a0\n\nResponsibilities:\n\nWorking in the design team developing design concepts through drawings, models, images, materials, mockups and mood boards.\nIn-Store Graphics and VM Layout Set up\u00a0\nPromotional Material and Product Packaging Development\u00a0\nCreating strong visuals for presentations and imagery, through 3D rendering, sketches and references.\nAd-hoc duties as assigned from time to time\nMentor and assist Junior Designers in their growth and development\nSkills and Experience:\n\nMinimum of 3-4 years working experience in Design Agency, In house brand or related industry.\nMinimum a bachelor\u2019s degree within Motion Graphic Design, Graphic Design, Visual Communication or related Design Degree\u00a0\nCreative, strong sense in multimedia design, self-motivated and self-disciplined\nStrong communication\nStrong creative thinking, exhibiting a range of varied styles and techniques\nGood skills in 3D Software with 3D modelling software such as 3DS Max, Cinema4D, Blender, Sketchup\nProficient in Adobe Creative Suite (Illustrator and Photoshop and InDesign)\nFamiliar with output and print production\nStrong Premiere Pro, After Effect skills with demonstrable experience in video editing or motion graphics\nYou are a generalist 3D and 2D designer comfortable in Cinema 4D or Blender and After Effects\nPreparing audio/video files to be edited and manipulated digitally\nFamiliar with output and print production\nWe offer an attractive salary + benefits package including occasional outing with teams. Ready to join the team? Email your resume, portfolio & expected salary to us!\nAny personal data provided will be used for recruitment related purposes only and will be treated in strict confidence.", "employment_types": ["Full Time", "Temporary"], "selling_points": ["Architectural or Interior Design qualification", "Retail, Corporate, Workplace & Hospitality Design", "AutoCAD and related technology experience"], "locations": ["Quarry Bay"], "categories": ["Building & Construction", "Architectural Services", "Design", "Interior", "Others"], "post_time": "2022-01-12T09:03:28Z", "salary": {"currency": null, "max": null, "min": null, "period": "monthly", "term": null}, "salary_visible": false, "title_keywords": [], "responsibilities": ["multimedia design", "software", "graphic designs", "design", "drawings", "communication", "video editing", "motion graphic design", "graphics", "3d rendering", "presentations", "motion graphics", "visual", "audio", "sketches", "ad-hoc duties", "product packaging", "motion graphic", "developing design concepts", "graphic design", "systems", "animation"], "requirements": {"degrees": ["degree", "bachelor"], "majors": ["graphic design", "design"], "languages": [], "language_level": [], "hard_skills": ["graphics", "3d software", "3ds max", "indesign", "illustrator", "presentations", "3d modelling", "video editing", "after effects", "visual communication", "after effect", "multimedia", "photoshop", "premiere pro", "adobe creative suite", "sketchup"], "soft_skills": ["self-motivated", "creative", "responsible", "communication", "ad-hoc duties", "team member"], "languages_combined": []}, "experience_required": {"duration": ["minimum of 3-4 years"], "field": ["designer", "brand", "video", "agency", "related", "design", "graphic", "editing", "motion graphic"]}}, {"job_id": "100003009042392", "location_code": "hk", "company": "Wang On Group", "job_title": "Assistant Graphic Designer", "description": "To support our continuous growth and expansion in Hong Kong, Aedas Interiors is now seeking a high calibre candidate for the following position:\n\n\nRequirements:\n\nArchitectural or Interior Design qualification and background;\nExperience in Hospitality / FF&E design;\nAble to provide creative and well thought through design solutions;\nExtensive knowledge of design detailing and construction methodology;\n3D Design and AutoCAD and related technology experience required.\nContract period: approximate 3 months\n\nAedas Interiors\u00a0provides opportunities for long term career development with an expanding international practice. We offer attractive compensation and benefit packages. Interested parties please send detailed CV, current & expected salary, availability by clicking the Apply now.\n\nAedas Interiors is an Equal Opportunity Employer\n(Data collected will be used for recruitment purpose only)\n\n\nAedas Interiors\u00a0provides opportunities for long term career development with an expanding international practice. We offer attractive compensation and benefit packages. Interested parties please send detailed CV, current & expected salary, availability by clicking the Apply now.\n\nAedas Interiors is an Equal Opportunity Employer\n(Data collected will be used for recruitment purpose only)", "employment_types": ["Full Time", "Permanent"], "selling_points": [], "locations": ["Kowloon Bay"], "categories": ["Design", "Graphics", "Multi-media", "Others"], "post_time": "2022-01-12T07:18:24Z", "salary": {"currency": null, "max": null, "min": null, "period": "monthly", "term": null}, "salary_visible": false, "title_keywords": ["assistant", "graphic designer"], "responsibilities": ["career development", "design", "design solutions"], "requirements": {"degrees": [], "majors": [], "languages": [], "language_level": [], "hard_skills": ["autocad"], "soft_skills": ["creative", "extensive"], "languages_combined": []}, "experience_required": {"duration": [], "field": ["related", "design"]}}, {"job_id": "100003009040211", "location_code": "hk", "company": "Atelier Pacific Ltd", "job_title": "Project Designer / Assistant Designer", "description": "Responsibilities:\n\nTo create concepts, update and maintain the standard of work\nPrepare and facilitate documents, creative material and concepts\nWork closely with operations and marketing team\n\nRequirements:\n\nHigher Diploma or above in graphic design, creative media design or related disciplines\nMinimum 2 years of relevant working experience in graphic design / creative industry\nProficiency in Photoshop, Premiere, After Effect, Adobe Suite / Adobe Illustrator and other design tools.\nGood command in both spoken and written English and Chinese\nAble to work independently under fast-paced working environment\nSelf-motivated, analytical, passionate in helping people find solutions, detail-oriented, and good team player\nFresh graduates with relevant degree/ skillsets are welcomed\nImmediate availability is preferred\nWe offer a competitive remuneration package, our benefits include:\nPerformance bonus\nEducation subsidy\nProfessional membership fee sponsorship\nLife & medical insurance\nMarriage Leave, Compassionate Leave, Examination Leave etc.\nPublic holidays\nStaff purchase discount\n\n\nInterested parties please send full resume with present and expected salary to Human Resources Department by clicking \"APPLY NOW\" or via email recruit @wangon.com.\n\n(Information provided will be treated in strict confidence and will only be used for recruitment-related purposes.)", "employment_types": ["Full Time", "Permanent"], "selling_points": ["5 days works", "16 days annual leave", "Annual company outing"], "locations": ["North Point"], "categories": ["Building & Construction", "Architectural Services", "Design", "Interior", "Others"], "post_time": "2022-01-12T01:53:04Z", "salary": {"currency": null, "max": null, "min": null, "period": "monthly", "term": null}, "salary_visible": false, "title_keywords": ["assistant designer", "project designer"], "responsibilities": ["operations", "maintain"], "requirements": {"degrees": ["higher diploma or above", "degree"], "majors": ["related disciplines", "graphic design", "creative media", "design"], "languages": ["english", "chinese"], "language_level": ["good command"], "hard_skills": ["premiere", "adobe illustrator", "adobe", "after effect", "photoshop"], "soft_skills": ["passionate", "work independently", "self-motivated", "good team player", "detail-oriented", "creative"], "languages_combined": [{"language": "english", "language_level": ["good command"]}, {"language": "chinese", "language_level": ["good command"]}]}, "experience_required": {"duration": ["minimum 2 years"], "field": ["graphic design", "relevant working experience"]}}, {"job_id": "100003009038683", "location_code": "hk", "company": "AAStocks.com Limited", "job_title": "Digital Designer (Graphic & Multimedia) (5-day work)", "description": "Job Responsibilities:\n\nConceptualize design and implement home furnishing solutions, sales support areas and point of sales materials at stores\nContribute to the creation of a Showroom matrix that reflects a wide variety of styles, living situations and price levels to create a good tempo with distinct visual impressions\nStay up to date and knowledgeable about home furnishing, retailing and trends in order to generate creative ideas\nTo work on continuous improvement of store visual presentation\nCommunicate with internal parties on the design requirements for projects\nHandle ad hoc projects assigned by management\n\nJob Requirements:\n\n\n\nHigher Diploma or above in Interior Design\u00a0or related discipline\n1 - 2 years' experience in interior design or home furnishing\u00a0\nProficiency in AutoCAD, Sketchup, Photoshop, Illustrator and MS office\nGood command of both written & spoken English and Chinese\nGood communication and presentation skill\nInnovative and able to work under pressure\nPassion for about home furnishing, design and how people live at home\nAble to work in a fast retail environment, generate new ideas and concepts\nFresh graduates are welcome\n\nWe offer an attractive package commensurate with your qualifications and experience.\u00a0 Please apply with\u00a0full resume, portfolio, present and expected salary, quoting the ref. no. to the Human Resources Department, Pricerite Home Limited, 28/F Manhattan Place, 23 Wang Tai Road, Kowloon Bay, Kowloon, HK; or fax to 2820 0651 or press \"APPLY NOW\"\u00a0\n\nAll information provided by applicants will be treated in strict confidentiality and used for recruitment purpose only.\u00a0 We will retain your application for a maximum period of 6 months and may refer it to other vacancies within the Group.", "employment_types": ["Full Time", "Permanent"], "selling_points": ["Develop creative concept to design, artwork", "Higher Diploma or above in Multimedia", "Minimum of 2 year solid working experience"], "locations": ["Not Specified"], "categories": ["Design", "Graphics", "Multi-media", "Others"], "post_time": "2022-01-11T07:38:12Z", "salary": {"currency": null, "max": null, "min": null, "period": "monthly", "term": null}, "salary_visible": false, "title_keywords": ["digital designer"], "responsibilities": ["creative ideas", "management", "design", "ad hoc projects", "visual", "communicate with internal parties", "visual presentation"], "requirements": {"degrees": ["higher diploma or above"], "majors": ["design"], "languages": ["english", "chinese"], "language_level": ["good command"], "hard_skills": ["presentation skill", "sketchup", "illustrator", "autocad", "photoshop", "ms office"], "soft_skills": ["presentation skill", "passion for", "communication", "innovative", "work under pressure"], "languages_combined": [{"language": "english", "language_level": ["good command"]}, {"language": "chinese", "language_level": ["good command"]}]}, "experience_required": {"duration": ["1 - 2 years"], "field": ["design"]}}, {"job_id": "100003009045554", "location_code": "hk", "company": "Genuine Treasure Access And Scaffolding Limited", "job_title": "Technical Assistant / Assistant Design Engineer", "description": "Job Responsibilities\nDevelop creative concept to design, artwork and the final output to meet business objectives\nResponsible for developing concept development, graphic design and artwork adaptation for online & offline materials (includes advertisements, website/mobile banners, newsletters, posters, leaflets, brochures, FB, IG, etc)\nHandle multiple projects, work under tight schedule and meet deadlines\nResponsible and creative, work well independently and also with teammates\nJob Requirements\nHigher Diploma or above in Multimedia/Interaction Design or other related discipline\nMinimum of 2 year solid working experience\nExperience in handling digital marketing solution is preferred\nStrong sense of visual presentation, composition, space and color management\nProficiency in using graphic & photo imaging software and web design tools is a MUST (e.g. Adobe Photoshop, Illustrator, After Effects, etc.)\nCreative, well-organized, detail-minded, independent, self-initiate, hardworking, aggressive and good personality\nKnowledge in HTML5, CSS, Action script will be an advantage\nGood command of both written and spoken English and Chinese\nPlease click \"Apply Now\" to submit your application.\nPersonal data collected will be used for recruitment purpose only.", "employment_types": ["Full Time", "Permanent"], "selling_points": ["Preparing formwork and falsework designs", "Supervising projects and monitoring progress", "AutoCAD operating Skill / Experience is essential"], "locations": ["Kwun Tong"], "categories": ["Design", "Others", "Building & Construction", "Civil / Structural", "Engineering", "Mechanical"], "post_time": "2022-01-13T08:04:09Z", "salary": {"currency": null, "max": null, "min": null, "period": "monthly", "term": null}, "salary_visible": false, "title_keywords": ["design engineer", "assistant", "technical assistant"], "responsibilities": ["advertisements", "leaflets", "graphic design", "developing", "design", "develop", "website", "banners", "schedule", "multiple projects"], "requirements": {"degrees": ["higher diploma or above"], "majors": ["design"], "languages": ["english", "chinese"], "language_level": ["good command"], "hard_skills": ["web design", "adobe photoshop", "illustrator", "after effects", "multimedia", "css"], "soft_skills": ["detail-minded", "independent", "well-organized", "creative", "presentation", "hardworking"], "languages_combined": [{"language": "english", "language_level": ["good command"]}, {"language": "chinese", "language_level": ["good command"]}]}, "experience_required": {"duration": ["minimum of 2 year"], "field": ["digital marketing"]}}, {"job_id": "100003009041669", "location_code": "hk", "company": "Studio 1618 Limited", "job_title": "Interior Designer", "description": "\u00a05.5 Day Work (alternate Saturday-off)\n\nWorking location: Kwun Tong (near MTR Station)\n\n\u00a0Job Responsibilities:\n\n\nPrepare formwork and falsework design of temporary works for various concrete/ steel structures;\nPerform the scaffold materials analysis, and ensure optimal design;\nCalculate cost of design and proposed scaffolding solutions with all kind of relative issues; and\nSupervise projects and monitor progress on site.\u00a0\n\nRequirements:\n\n\nDiploma / Higher Diploma / Degree in Civil / Structural Engineering is preferred;.\nAt least 2 years of post graduation experience for the position of Assistant Design Engineer;\nDegree in Applied Physics / Mathematics/ Mechanical Engineering, candidates who are interested in construction industry;\nSkills/ experience in AutoCAD are essential (Familiar with SAP2000/ ETABS/ REVIT is an advantage);\nComputer literate in MS Office (Advance skills in Excel is an advantage);\nAble to work independently, good communication skill, self-motivated, willing to learn, and working on-site required;\nGood command of written and spoken English & Chinese;\nImmediately available is an advantage; and\nFresh graduates are welcome to apply.\n\nRemarks :\n\nInterested parties please e-mail detailed resume with expected salary by clicking \"Apply Now\"\n\nAll information collected will be kept in strict confidence and used for recruitment related purpose only.", "employment_types": ["Full Time"], "selling_points": ["6-10 years experience", "AutoCAD experience", "Immediate availability"], "locations": ["Sheung Wan"], "categories": ["Design", "Interior", "Others"], "post_time": "2022-01-12T04:11:21Z", "salary": {"currency": null, "max": null, "min": null, "period": "monthly", "term": null}, "salary_visible": false, "title_keywords": ["interior designer"], "responsibilities": ["cost", "analysis", "monitor progress", "design"], "requirements": {"degrees": ["diploma", "degree"], "majors": ["mathematics", "structural engineering", "physics", "mechanical engineering"], "languages": ["english", "chinese"], "language_level": ["good command"], "hard_skills": ["etabs", "excel", "sap2000", "autocad", "ms office", "revit"], "soft_skills": ["work independently", "self-motivated", "communication skill", "interested in", "willing to learn"], "languages_combined": [{"language": "english", "language_level": ["good command"]}, {"language": "chinese", "language_level": ["good command"]}]}, "experience_required": {"duration": ["at least 2 years"], "field": ["design"]}}, {"job_id": "100003009015926", "location_code": "hk", "company": "Agnes b. HK Limited", "job_title": "\u77ed\u671f\u82b1\u85dd\u52a9\u7406 / \u77ed\u671f\u6587\u54e1 Temporary Helper / Temporary Clerk (Fleuriste)", "description": "To handle full set design drawing of exhibition and event.\nTo drawing 3D rendering, technical drawing and floor plan for production.\nTo provide the design concept, space planning & structural design for exhibitions & other special events\nTo design solution relevant to the nature of the event and requirements of individual projects\n\nRequirements:\n\nIVE graduate / Diploma or above in\u00a0Interior\u00a0/ Graphic\u00a0/\u00a0Exhibition\nProficient in 3D software (e.g. 3Ds Max, Illustrator, Photoshop, AutoCAD)\nWell experienced hands-on working in 3D, graphic, artwork, and output production independently is essential\n2 years experience in Exhibition / Event Design/ Production House\u00a0will be an advantage\nImmediate available preferred\n\n\n\nWe offer competitive remuneration package to the successful candidates. Applicants please submit your full CV with expected salary, availability & project portfolio for interview.\n\nPersonal data will be used for recruitment purpose only.\n", "employment_types": ["Part Time", "Temporary", "Contract", "Freelance"], "selling_points": ["\u77ed\u671f\u82b1\u85dd\u52a9\u7406 / \u77ed\u671f\u6587\u54e1 Temporary Helper / Temporary Clerk", "2022\u5e741\u670820\u65e5\u81f32\u670814\u65e5", "\u5de5\u4f5c\u5730\u9ede : \u4e2d\u74b0 / \u592a\u53e4\u57ce / \u5c16\u6c99\u5480 / \u4e5d\u9f8d\u5858"], "locations": ["Not Specified"], "categories": ["Others", "Agriculture / Forestry / Fishing", "Design", "Others", "Sales, CS & Business Devpt", "Retail Sales"], "post_time": "2022-01-10T02:26:55Z", "salary": {"currency": null, "max": null, "min": null, "period": null, "term": null}, "salary_visible": false, "title_keywords": ["temporary clerk", "helper"], "responsibilities": ["software", "3d rendering", "design concept", "design", "planning", "plan", "output production", "technical drawing"], "requirements": {"degrees": ["diploma or above"], "majors": [], "languages": [], "language_level": [], "hard_skills": ["3d software", "3ds max", "illustrator", "photoshop", "autocad"], "soft_skills": ["hands-on", "independently"], "languages_combined": []}, "experience_required": {"duration": ["2 years"], "field": ["design"]}}, {"job_id": "100003009039975", "location_code": "hk", "company": "AES-Adliger Exhibition Service Ltd", "job_title": "3D Designer (Exhibition / Event Design) \u2013 (Full Time / Part Time / Work From Home )", "description": "\u5de5\u4f5c\u6982\u8981:\u9999\u6e2f\u8fea\u58eb\u5c3c\u6a02\u5712\u70ba\u8cd3\u5ba2\u63d0\u4f9b\u4e16\u754c\u7d1a\u7684\u670d\u52d9\uff0c\u5275\u9020\u7562\u751f\u96e3\u5fd8\u7684\u9ad4\u9a57\u3002\u5728\u8fea\u58eb\u5c3c\u6f14\u51fa\u4e2d\uff0c\u6bcf\u4f4d\u6f14\u85dd\u4eba\u54e1\u90fd\u64d4\u6f14\u91cd\u8981\u7684\u89d2\u8272\u3002\u6211\u5011\u6703\u70ba\u6f14\u85dd\u4eba\u54e1\u63d0\u4f9b\u5168\u9762\u7684\u57f9\u8a13\u4ee5\u53ca\u826f\u597d\u7684\u4e8b\u696d\u767c\u5c55\u6a5f\u6703\u3002 \u73fe\u5728\u5c31\u52a0\u5165\u6211\u5011\u7684\u5718\u968a\uff0c\u5c55\u958b\u975e\u4e00\u822c\u7684\u4e8b\u696d\u4e4b\u65c5\uff01\u8077\u8cac:\n\u8ca0\u8cac\u6cb9\u6f06\u5de5\u5e8f\u7684\u524d\u671f\u6e96\u5099\u5de5\u4f5c (\u5305\u62ec\u9664\u92b9\u3001\u6e05\u6f54\u3001\u5c0f\u7bc4\u570d\u4fee\u88dc\u3001\u6279\u7070\u548c\u6253\u78e8)\u3001\u914d\u8272\u53ca\u4e0a\u8272\uff0c\u7bc4\u570d\u5305\u62ec\u904a\u6a02\u8a2d\u65bd\u7684\u5834\u666f\u3001\u9053\u5177\u3001\u5851\u50cf\u53ca\u8eca\u8f1b\n\u53c3\u8207\u5927\u578b\u7dad\u4fee\u9805\u76ee\u7684\u5674\u5857\u5de5\u4f5c\uff0c\u65e5\u5e38\u4fdd\u990a\u53ca\u9032\u884c\u4f8b\u884c\u6aa2\u67e5\n\u7dad\u6301\u5de5\u4f5c\u74b0\u5883\u6574\u6f54\uff0c\u7d00\u9304\u53ca\u5831\u544a\u7dad\u4fee\u9032\u5ea6\n\u57fa\u672c\u689d\u4ef6:\n\u200b\u6301\u6709\u95dc\u65bc\u7f8e\u8853\u7684\u8b49\u66f8\u6216\u540c\u7b49\u5b78\u6b77\n\u6700\u5c112\u5e74\u76f8\u95dc\u7d93\u9a57\n\u9808\u8f2a\u73ed\u5de5\u4f5c\n\u9808\u9ad8\u7a7a\u5de5\u4f5c\n\u80fd\u4ee5\u7c21\u55ae\u5ee3\u6771\u8a71\u3001\u82f1\u8a9e\u53ca\u666e\u901a\u8a71\u4f5c\u6e9d\u901a\n\u7a4d\u6975\u4e3b\u52d5\u4e26\u6709\u826f\u597d\u7684\u6e9d\u901a\u6280\u5de7\n#LI-DNI\n\u7406\u60f3\u689d\u4ef6:\n\u200b\u5177\u5c0d\u7f8e\u8853\u3001\u5de5\u696d\u6216\u6c7d\u8eca\u5674\u5857\u7684\u5de5\u5177\u3001\u7269\u6599\u7684\u57fa\u672c\u8a8d\u8b58\u53ca\u76f8\u95dc\u5de5\u4f5c\u7d93\u9a57\u6703\u512a\u5148\u8003\u616e\n\u6301\u6709\u9999\u6e2f\u99d5\u99db\u57f7\u7167\uff081\u62162\uff09\u8005\u512a\u5148\u8003\u616e\n\u5176\u4ed6\u8cc7\u8a0a:\u905e\u4ea4\u7533\u8acb\uff1a\u00a0\u9ede\u6483\u4e0b\u65b9\u7684\u300c\u7533\u8acb\u5de5\u4f5c\u300d\u9023\u7d50\uff0c\u6709\u95dc\u8077\u4f4d\u7533\u8acb\u8868\u683c\u5c07\u65bc\u65b0\u7684\u8996\u7a97\u958b\u5553\u3002\u5728\u586b\u5beb\u8868\u683c\u6642\uff0c\u8acb\u4ee5\u82f1\u6587\u586b\u5beb\uff0c\u4e26\u65bc\u5b8c\u6210\u6bcf\u4e00\u9801\u5f8c\u6309\u9801\u5e95\u7684\u300c\u4e0b\u4e00\u9801\u300d\u6309\u9215\uff0c\u4ee5\u7e7c\u7e8c\u586b\u5beb\u8868\u683c\u5167\u7684\u6240\u6709\u9801\u9762\u3002\u586b\u59a5\u5f8c\uff0c\u8a18\u7dca\u6309\u8868\u683c\u6700\u5f8c\u4e00\u9801\u7684\u300c\u7533\u8acb\u300d\u6309\u9215\uff0c\u4ee5\u905e\u4ea4\u7533\u8acb\u3002", "employment_types": ["Full Time", "Part Time", "Freelance"], "selling_points": ["Experience in exhibition or interior decoration", "Good knowledge in 3Ds Max, Photoshop", "Strong graphic design sense"], "locations": ["Kowloon Bay"], "categories": ["Design", "Graphics", "Interior", "Others"], "post_time": "2022-01-11T16:02:29Z", "salary": {"currency": null, "max": null, "min": null, "period": "monthly", "term": null}, "salary_visible": false, "title_keywords": ["designer"], "responsibilities": [], "requirements": {"degrees": [], "majors": [], "languages": [], "language_level": [], "hard_skills": [], "soft_skills": [], "languages_combined": []}, "experience_required": {"duration": [], "field": []}}, {"job_id": "100003009038034", "location_code": "hk", "company": "Hong Kong Disneyland", "job_title": "\u7f8e\u5de5\u6280\u8853\u54e1 / \u6cb9\u6f06\u6280\u8853\u54e1 - \u5168\u8077 (Ref:788141BR)", "description": "\u00a0Accountabilities \u2013 Key Result Areas\n\nCarry out design concept and development, assist preparation of detailed and construction drawings, sourcing and selection of materials and preparation of quotations\nHandle various design documentation and presentation work\u00a0\nCoordinate and liaise with contractors, vendors and project team members to collect business and project requirements to ensure effective and satisfactory project completion\n\nExperience / Qualification Requirements\n\nDiploma / Degree holder in Architecture or Interior Design or equivalent\nWith at least 3 years of experience, with retail fit-out and large scale project experience is preferred\nFamiliar with AutoCAD, Photoshop, Adobe illustrator, 3D Max and other relevant graphic and design tools\n\nCompetitive remuneration and benefit package will be offered to the right candidate. Please submit your application by clicking \"Apply Now\" below.\n\nAll data collected is for recruitment purpose only.\n\nSure you want to know more about our company and brands, simply follow our\n\nWEBSITE at http://www.ithk.com\u00a0 \u00a0 \u00a0 \u00a0 \u00a0 \u00a0 \u00a0 \u00a0 \u00a0 \u00a0 \u00a0 \u00a0 \u00a0 \u00a0 \u00a0 \u00a0 \u00a0 \u00a0 \u00a0 \u00a0 \u00a0 \u00a0 \u00a0 \u00a0 \u00a0 \u00a0 \u00a0 \u00a0 \u00a0 \u00a0 \u00a0 \u00a0 \u00a0 \u00a0\u00a0\n\nFACEBOOK at\u00a0http://www.facebook.com/I.Ttheofficialpage \u00a0 \u00a0 \u00a0 \u00a0 \u00a0 \u00a0 \u00a0 \u00a0 \u00a0 \u00a0 \u00a0 \u00a0 \u00a0 \u00a0\n\nINSTAGRAM at http://instagram.com/ithk\u00a0 \u00a0 \u00a0 \u00a0 \u00a0 \u00a0 \u00a0 \u00a0 \u00a0 \u00a0 \u00a0 \u00a0 \u00a0 \u00a0 \u00a0 \u00a0 \u00a0 \u00a0 \u00a0 \u00a0 \u00a0 \u00a0 \u00a0 \u00a0 \u00a0 \u00a0 \u00a0 \u00a0\n\nWEIBO at\u00a0http://e.weibo.com/ithongkong", "employment_types": ["Full Time"], "selling_points": ["\u8ca0\u8cac\u6cb9\u6f06\u5de5\u5e8f\u7684\u524d\u671f\u6e96\u5099\u5de5\u4f5c (\u5305\u62ec\u9664\u92b9\u3001\u6e05\u6f54\u3001\u5c0f\u7bc4\u570d\u4fee\u88dc\u3001\u6279\u7070\u548c\u6253\u78e8)\u3001\u914d\u8272\u53ca\u4e0a\u8272", "\u53c3\u8207\u5927\u578b\u7dad\u4fee\u9805\u76ee\u7684\u5674\u5857\u5de5\u4f5c\uff0c\u65e5\u5e38\u4fdd\u990a\u53ca\u9032\u884c\u4f8b\u884c\u6aa2\u67e5", "\u200b\u6301\u6709\u95dc\u65bc\u7f8e\u8853\u7684\u8b49\u66f8\u6216\u540c\u7b49\u5b78\u6b77 \u6700\u5c112\u5e74\u76f8\u95dc\u7d93\u9a57"], "locations": ["Lantau Island"], "categories": ["Design", "Others", "Hospitality / F & B", "Integrated Resort / Casino", "Others", "Technician"], "post_time": "2022-01-11T04:40:59Z", "salary": {"currency": null, "max": null, "min": null, "period": "monthly", "term": null}, "salary_visible": false, "title_keywords": [], "responsibilities": ["project requirements", "data", "design concept", "website", "design", "drawings", "coordinate", "recruitment", "documentation", "facebook", "liaise with contractors", "architecture"], "requirements": {"degrees": ["diploma", "degree holder"], "majors": ["architecture", "design"], "languages": [], "language_level": [], "hard_skills": ["adobe illustrator", "autocad", "documentation", "max", "facebook", "photoshop"], "soft_skills": ["presentation", "detailed"], "languages_combined": []}, "experience_required": {"duration": ["at least 3 years"], "field": ["retail"]}}, {"job_id": "100003009034124", "location_code": "hk", "company": "The Key Design Limited", "job_title": "\u96fb\u8166\u7e6a\u5716\u54e1/  Draftsman", "description": "To support our continuous growth and expansion in Hong Kong, Aedas Interiors is now seeking a high calibre candidate for the following position:\n\n\nRequirements:\n\nMinimum 3 years post design qualification experience;\nInterior Design qualification and background;\nExperience in Retail design preferred;\nFluency in written and spoken English and Mandarin is mandatory;\nAble to provide creative and well thought through design solutions;\nRhino and related rendering software experience required;\nAutoCAD and related technology experience required;\nMore experienced candidate will be considered as Senior Interior Designer.\n\n\nAedas Interiors provides opportunities for long term career development with an expanding international practice. We offer attractive compensation and benefit packages. Interested parties please send detailed CV, current & expected salary, availability by clicking the Apply now.\n\nAedas Interiors is an Equal Opportunity Employer\n(Data collected will be used for recruitment purpose only)", "employment_types": ["Full Time"], "selling_points": ["\u5168\u8077, \u5de5\u4f5c\u6642\u9593 (\u4e0a\u534811:30\u5206\u81f3\u4e0b\u53489\u6642\u6b63), \u6bcf\u661f\u671f\u5de5\u4f5c6\u5929, \u9700\u8981\u8f2a\u4f11", "\u4e2d\u4e94\u7a0b\u5ea6, \u61c2\u8b80\u5beb\u4e2d\u6587\u53ca\u82f1\u6587, 1\u5e74\u76f8\u95dc\u5de5\u4f5c\u7d93\u9a57", "\u7e6a\u5716(\u6548\u679c\u5716\u3001\u50a2\u4fec\u5716\u3001\u5de5\u7a0b\u5716)"], "locations": ["Kowloon Bay"], "categories": ["Design", "Interior", "Others", "Engineering", "Draftsman"], "post_time": "2022-01-10T02:44:55Z", "salary": {"currency": "HKD", "max": 19999, "min": 11000, "period": "monthly", "term": null}, "salary_visible": true, "title_keywords": ["draftsman"], "responsibilities": ["career development", "software", "design", "design solutions"], "requirements": {"degrees": [], "majors": [], "languages": ["english", "mandarin"], "language_level": ["fluency"], "hard_skills": ["autocad", "rhino"], "soft_skills": ["creative"], "languages_combined": [{"language": "english", "language_level": ["fluency"]}, {"language": "mandarin", "language_level": ["fluency"]}]}, "experience_required": {"duration": ["minimum 3 years"], "field": ["related", "retail", "design"]}}, {"job_id": "100003009038454", "location_code": "hk", "company": "I.T Apparels Limited", "job_title": "Interior Designer (REF: JDB-IT-ID)", "description": "Job Responsibilities\n\n\nProduce a variety of marketing materials using relevant graphic applications to an advanced level\nManage initial briefings and communication with internal stakeholders\nCreate concept and artwork as per company brand guidelines\nResponsible for overall quality and delivery of project outputs\n\nJob Requirements\n\n\nBachelor Degree or above in Graphic Design\nAt least 2 years relevant work experience preferably from banking/financial services industry, but not a must\nProficient in Adobe software, Microsoft Excel/PowerPoint\nExcellent command in written and spoken English\nStrong team player and sense of responsibility\nWilling to work overtime (with pay) with flexible hours", "employment_types": ["Full Time", "Permanent"], "selling_points": ["Carry out design concept and development", "Familiar with AutoCAD and 3D Max", "With at least 3 years of experience"], "locations": ["Southern Area"], "categories": ["Design", "Fashion", "Interior", "Others"], "post_time": "2022-01-11T06:55:30Z", "salary": {"currency": null, "max": null, "min": null, "period": "monthly", "term": null}, "salary_visible": false, "title_keywords": ["interior designer"], "responsibilities": ["marketing materials", "quality", "brand guidelines", "communication"], "requirements": {"degrees": ["degree or above", "bachelor"], "majors": ["graphic design"], "languages": ["english"], "language_level": ["excellent"], "hard_skills": ["adobe software", "powerpoint", "microsoft excel"], "soft_skills": ["flexible", "team player", "work overtime", "sense of responsibility"], "languages_combined": [{"language": "english", "language_level": ["excellent"]}]}, "experience_required": {"duration": ["at least 2 years"], "field": ["financial services industry", "banking"]}}, {"job_id": "100003009030886", "location_code": "hk", "company": "Meinhardt (Hong Kong) Limited", "job_title": "Asst. BIM Manager / BIM Coordinator (Ref: 88084)", "description": "Waison Design & Engineering Limited was established in 2011 by professionals with rich experiences in interior design. We devoted ourselves to the area of retail, corporate, residential and catering that developed diverse quality services in line with changing needs and client\u00a0expectation.\u00a0\n\nWe are currently looking for a experienced interior designer and its job requirement is as follows. Less experience will be considered as assistant interior designer.\n\nWhat you will be doing?...\n\nInitiative, creative and self-motivating with \u201ccan do\u201d attitude, good team player, able to handle challenging situations, sense of responsibility and smart.\nAble to develop innovative and good quality solutions.\nAble to work independently with minimal supervision, strong communication with colleagues, clients, labor and manufacturers, and good analytical ability.\nAble to handle full set of working drawing with good design detailing experience (\u00a0\u00a0Measuring,Sketching design plans and layouts,\u00a0Selecting materials and colour matching)\nAble to handle project independently and deliver project from design intent through to completion.\n\nWho are we looking for?...\n\nDiploma / degree in interior design or design related studies.\nAt least 1 year solid experience\u00a0in retail store, office design, hospitality, show flat and restaurant.\nPreferable with at least 1-year managerial level experience.\u00a0\nProficient in AutoCAD, Photoshop, Sketch Up and other relevant skills.\nHigh level of presentation and liaison skills .\nGood command of English and Cantonese.\nWilling to work overtimes, under pressure, meet tight schedule and multitasking.\n\nWhy you should consider this position?...\n\nWe offer competitive remuneration package (5 days work week, 10 days Annual Leave, Year End Bonus)\n\nOur office is in San Po Kong, provides a spacious teamwork environment.\u00a0Interested parties please mark in the email subject which post you apply for and send us your full resume, availability date.\n\n\u00a0** Personal data collected will be used for recruitment purpose only.", "employment_types": ["Full Time", "Permanent"], "selling_points": [], "locations": ["Aberdeen"], "categories": ["Design", "Others", "Building & Construction", "Building / Construction / QS", "Engineering", "Draftsman"], "post_time": "2022-01-07T08:32:05Z", "salary": {"currency": null, "max": null, "min": null, "period": "monthly", "term": null}, "salary_visible": false, "title_keywords": ["bim coordinator", "manager"], "responsibilities": ["quality", "design", "develop", "communication", "schedule", "plans", "catering"], "requirements": {"degrees": ["diploma", "degree"], "majors": ["design"], "languages": ["cantonese", "english"], "language_level": ["good command"], "hard_skills": ["sketch up", "photoshop", "autocad"], "soft_skills": ["good team player", "work independently", "independently", "under pressure", "sense of responsibility", "presentation", "innovative", "communication", "diverse", "devoted", "creative", "initiative"], "languages_combined": [{"language": "cantonese", "language_level": ["good command"]}, {"language": "english", "language_level": ["good command"]}]}, "experience_required": {"duration": ["at least 1 year", "at least 1-year"], "field": ["managerial", "designer", "engineering", "restaurant", "design", "retail"]}}, {"job_id": "100003009029703", "location_code": "hk", "company": "Lomography Asia Pacific Limited", "job_title": "Product Designer", "description": "Responsibilities:\n\nPropose and execute VM display on a weekly basis\nDeliver a high standard of visual display and align with the brand's guideline\nDesign and execute all graphic designs: eDMs, in-store signage, web banner, and social media graphics\nDesign and execution of Pop-Up Store, in-store set up, special events, and campaign launch\nNegotiate with vendors for cost efficiency\nSourcing of props & VM equipment for in-store display\nWork closely with headquarter for visual development and execution\n\nRequirement:\n\nDegree or diploma holder in Visual Merchandising, Art & Design or other design related discipline\nProficient in Photoshop, Illustrator, InDesign and Multimedia software\nMinimum 3-4 years\u2019 experience in visual merchandising and graphic design in shopping mall, department store and F&B will be an advantage\nPhotography, photo retouching and video editing skills will be an advantage\nStrong interpersonal and communication skills\nSelf-motivated, organized and able to work with tight schedule\nGood command of both written and spoken English and Chinese\nImmediate available is highly preferred\n\n\n\n\nWe offer attractive remuneration package to the right candidate. Please apply with full resume stating present and expected salaries to Group Human Resources Department, 11/F., 68 Yee Wo Street, Causeway Bay, Hong Kong or by fax to 2895 5766.\n\nAll personal data/information provided by applicants to 8D International Limited is used for recruitment and related purpose(s) only.\n\nWe are an equal Opportunities Employer.", "employment_types": ["Full Time"], "selling_points": [], "locations": ["Kwai Fong"], "categories": ["Design", "Others"], "post_time": "2022-01-07T05:58:27Z", "salary": {"currency": null, "max": null, "min": null, "period": null, "term": null}, "salary_visible": false, "title_keywords": ["product designer"], "responsibilities": ["graphics", "social media", "cost", "edms", "graphic designs", "design", "visual"], "requirements": {"degrees": ["diploma holder", "degree"], "majors": ["art", "design"], "languages": ["english", "chinese"], "language_level": ["good command"], "hard_skills": ["visual merchandising", "indesign", "illustrator", "video editing", "multimedia", "photoshop"], "soft_skills": ["organized", "communication skills", "self-motivated", "interpersonal"], "languages_combined": [{"language": "english", "language_level": ["good command"]}, {"language": "chinese", "language_level": ["good command"]}]}, "experience_required": {"duration": ["minimum 3-4 years"], "field": ["graphic design", "f&b", "merchandising"]}}, {"job_id": "100003009024882", "location_code": "hk", "company": "Sun Cheong Decoration Engineering Company Limited", "job_title": "Project Coordinator", "description": "Responsibilities:\n\nTo assist Project Manager and the team for works programming\nTo assist in detail/shop drawings preparation for site works\nTo liaise with contractors, suppliers and other consultants for timely completion\nTo coordinate sub-contractors and direct labour for works sequencing\nAny ad hoc tasks as required\n\n\u00a0Requirement:\n\nHigher Diploma holder or above in Interior Design / Building Studies / Project Management or any related field\nMinimum 3 years working experience in Interior Design / Fitting out works\nGood hand sketching and/or AutoCAD skills\nGood command of Written English; Fluent Speaking English and Mandarin is a definite advantage\nFresh graduates or candidates with less experience will also be considered\nPleasant, self-motivated, well organized, able to work independently and under pressure\n\nWork Location: Shatin (Office) and/or Job Sites\nSalary: \u00a0\u00a0\u00a0 Negotiable\n\nBenefits: Double pay, Performance bonus\u00a0\n\nInterested candidate please submit detailed resume with present & expected salary and available starting date to:---@@--\u00a0scltd@@scde.com.hk\u00a0 \u00a0\u00a0\n\n\nPlease caption \u201cApplication for Project Coordinator\u201d at your email or cover of application letter.\n\nPersonal data collected will be used for recruitment purpose only", "employment_types": ["Full Time"], "selling_points": ["Higher Diploma holder or above", "Good hand sketching and/or AutoCAD skills", "Double pay, Performance bonus, Medical"], "locations": ["Not Specified"], "categories": ["Design", "Graphics", "Others", "Building & Construction", "Building / Construction / QS"], "post_time": "2022-01-06T03:02:37Z", "salary": {"currency": null, "max": null, "min": null, "period": "monthly", "term": null}, "salary_visible": false, "title_keywords": ["project coordinator"], "responsibilities": ["coordinate", "liaise with contractors", "ad hoc tasks", "drawings"], "requirements": {"degrees": ["higher diploma holder"], "majors": ["project management", "building studies", "design"], "languages": ["english", "mandarin"], "language_level": ["advantage", "good command", "fluent"], "hard_skills": ["project management", "autocad"], "soft_skills": ["self-motivated", "work independently", "under pressure", "well organized", "pleasant", "project management"], "languages_combined": [{"language": "english", "language_level": ["fluent", "advantage", "good command"]}, {"language": "mandarin", "language_level": ["fluent", "advantage"]}]}, "experience_required": {"duration": ["minimum 3 years"], "field": ["design"]}}, {"job_id": "100003009026805", "location_code": "hk", "company": "St Legere Design International Ltd", "job_title": "Landscape Architect/ Landscape Designer (LA/LD) - Hong Kong", "description": "Job Description\n\nMonitor and management of construction projects to satisfaction within schedule through the project life cycle;\nAssist project manager in monitoring the design planning, programming and reporting works of the projects up to clients\u2019 requirements;\nResponsible for alternative design for project;\nProvide technical advice and guidance for the project.\n\nJob Requirement\n\nDegree or above\u00a0in Civil / Structural Engineering\u00a0or equivalent;\n7 years or above relevant experience in civil project;\nFamiliar with Primavera and Microsoft Project;\nGood communication skills and written skills in both English.\n\n***What we offer?\n\nCompetitive remuneration package\nAdditional leave (Family Care Leave, Exam Leave, Qualification Leave, etc.)\nDiscretionary bonus\nStudy Subsidies\nComprehensive training and professional career development\n\nInterested parties please apply by clicking \"APPLY NOW\" with detailed CV stating expected salary and date of availability.\n\nCompany Website: \u00a0http://www.pyengineering.com/\n\nAll personal data provided will be used strictly in accordance with our \u201cPersonal Information Collection Statement Pertaining to Recruitment\u201d, a copy of which is available upon written request to us by E-mail.", "employment_types": ["Full Time", "Permanent", "Contract"], "selling_points": ["We are a boutique Landscape firm in HKG & JKT", "We are looking for talented & calibrated Architect", "Join our team in Hong Kong"], "locations": ["Aberdeen"], "categories": ["Building & Construction", "Architectural Services", "Design", "Others"], "post_time": "2022-01-07T01:44:33Z", "salary": {"currency": null, "max": null, "min": null, "period": "monthly", "term": null}, "salary_visible": false, "title_keywords": ["designer"], "responsibilities": ["reporting", "management", "guidance", "technical advice", "monitoring", "monitor", "design", "schedule", "planning"], "requirements": {"degrees": ["degree or above"], "majors": ["structural engineering"], "languages": ["english"], "language_level": ["good"], "hard_skills": ["microsoft project"], "soft_skills": ["communication skills"], "languages_combined": [{"language": "english", "language_level": ["good"]}]}, "experience_required": {"duration": ["7 years"], "field": ["relevant experience"]}}, {"job_id": "100003009022403", "location_code": "hk", "company": "Conway Management Ltd", "job_title": "\u5eda\u6ac3\u8a2d\u8a08\u5e2b Designer", "description": "Product Designer recruitment descriptions:\nResponsibilities:\n- Product idea generations starting from research, strategy building and design concepts for in-house products\n- Project briefing setup and presentation\u00a0\n- Virtual and physical model building for development process and engineering executions\n- Supports on solving prototyping/ samples/ production problems\u00a0\nRequirements:\n- Degree or above in Industrial/ Product design or related disciplines\n- Good knowledge on analog photography and photographic equipments\u00a0\n- Proficiency in engineering 3D software modelling e.g. Solidwork/ Creo Parametric/ Fusion 360\n- Experience on handcrafting prototypes & 3D printing\u00a0\n- Good communication and presentation skill in English and Chinese\n- Proactive, detail-minded, energetic & willing to explore\n- Experience in plastic injection moulded product industry would be an advantage\n-\u00a0Knowledgeable\u00a0on mechanical and structural design, understanding on manufacturing processes would be an advantage\nLocation: Hong Kong\nStarts: immediate\u00a0\n5 days work week", "employment_types": ["Full Time"], "selling_points": [], "locations": ["Not Specified"], "categories": ["Design", "Graphics", "Interior", "Others"], "post_time": "2022-01-05T05:33:57Z", "salary": {"currency": null, "max": null, "min": null, "period": "monthly", "term": null}, "salary_visible": false, "title_keywords": ["designer"], "responsibilities": ["design concepts", "setup"], "requirements": {"degrees": ["degree or above"], "majors": ["related disciplines", "design"], "languages": ["english", "chinese"], "language_level": ["good"], "hard_skills": ["presentation skill", "3d software", "solidwork"], "soft_skills": ["presentation skill", "detail-minded", "communication", "energetic", "proactive"], "languages_combined": [{"language": "english", "language_level": ["good"]}, {"language": "chinese", "language_level": ["good"]}]}, "experience_required": {"duration": [], "field": []}}, {"job_id": "100003009031853", "location_code": "hk", "company": "SSL (Asia) Pacific Limited", "job_title": "Design Engineer/ Assistant Design Engineer", "description": "Key Responsibilities:\n\nDefine the creative strategy and manage the creative process from concept to completion by leading the team of marketing, interior design & visual merchandising\nDevelop marketing and communications plans to deliver excellent consumer experience\nCreate and maintain brand standards for interior design and in-store visual merchandising\nActively participate in cross department team communications to ensure the alignment of business objectives\n\u00a0Job Requirements\n\nDegree holder in marketing, visual communication, multimedia design or a related disciplines\nMinimum 10 years relevant experiencein creative design industry, fashion retail experience is preferable\nStrong communication, interpersonal & presentation skills\nAble to cope with tight schedule and ad hoc projects\nFluency in English, Cantonese, and Mandarin\n5 days work in\u00a0Guangzhou, PRC\n\nInterested parties, please send us detailed resume with stating current and expected salary by clicking the \u201cAPPLY NOW\u201d button below.\n\nBenefits:\n\n5-Day Work Week\nDouble Pay\nDiscretionary Bonus\nAccommodation provided\nGroup Medical\nDental Insurance\nChina Public Holidays\nBirthday Coupon\nStaff Discount\n\nData collected will be used for recruitment purpose only.", "employment_types": ["Full Time"], "selling_points": ["Degree / Higher diploma in Building", "Proficient in AutoCAD", "Team player with excellent interpersonal"], "locations": ["Kowloon Bay"], "categories": ["Design", "Industrial / Product", "Others", "Engineering", "Engineering Project Management"], "post_time": "2022-01-07T09:50:19Z", "salary": {"currency": null, "max": null, "min": null, "period": "monthly", "term": null}, "salary_visible": false, "title_keywords": ["assistant", "design engineer"], "responsibilities": ["merchandising", "design", "develop", "maintain", "visual", "plans"], "requirements": {"degrees": ["degree holder"], "majors": ["multimedia design", "related disciplines", "marketing"], "languages": ["cantonese", "english", "mandarin"], "language_level": ["fluency"], "hard_skills": ["creative design", "visual communication", "multimedia"], "soft_skills": ["communication", "presentation skills", "creative", "interpersonal"], "languages_combined": [{"language": "cantonese", "language_level": ["fluency"]}, {"language": "english", "language_level": ["fluency"]}, {"language": "mandarin", "language_level": ["fluency"]}]}, "experience_required": {"duration": ["minimum 10 years"], "field": ["retail", "design"]}}, {"job_id": "100003009024731", "location_code": "hk", "company": "United Asia Finance Limited", "job_title": "Graphic Designer / Multimedia Designer", "description": "\n\u6708\u5165\u53ef\u9054$40K\u6216\u4ee5\u4e0a (\u5e95\u85aa + \u8c50\u539a\u4f63\u91d1 + \u9054\u6a19\u734e\u91d1 + \u7279\u5225\u734e\u91d1 + \u52e4\u5de5\u734e)\n\u5177\u4e00\u5e74\u6216\u4ee5\u4e0a\u5eda\u6ac3\u92b7\u552e\u7d93\u9a57\uff0c\u80fd\u7368\u7acb\u8655\u7406\u7e6a\u5716\u5de5\u4f5c (AutoCAD\u3001sketchup & V-ray\u53ca\u624b\u7e6a)\n\u2022 \u5177\u826f\u597d\u6e9d\u901a\u6280\u5de7\u53ca\u614b\u5ea6\uff0c\u52e4\u596e\u4e3b\u52d5\uff0c\u6709\u8cac\u4efb\u5fc3\n\u2022 \u61c2\u82f1\u8a9e\u53ca\u666e\u901a\u8a71\u512a\u5148\u8003\u616e\n\n", "employment_types": ["Full Time"], "selling_points": ["Responsible for designing, developing & executing", "Higher Diploma or above in Graphic Design", "Proficient in Illustrator, Photoshop, AI"], "locations": ["Wan Chai"], "categories": ["Design", "Graphics", "Multi-media", "Others"], "post_time": "2022-01-06T02:21:09Z", "salary": {"currency": null, "max": null, "min": null, "period": "monthly", "term": null}, "salary_visible": false, "title_keywords": ["multimedia designer", "graphic designer"], "responsibilities": [], "requirements": {"degrees": [], "majors": [], "languages": [], "language_level": [], "hard_skills": [], "soft_skills": [], "languages_combined": []}, "experience_required": {"duration": [], "field": []}}, {"job_id": "100003009025046", "location_code": "hk", "company": "Hong Kong Technology Venture Company Limited", "job_title": "Graphic Designer", "description": "What You will be Doing\n\nWork closely with other designers, design management team, UI / UX team, video production team and in-house clients (marketing and other user departments) to design and execute all kinds of creative and quality promotion materials\nOpen-minded and flexible manner as an amoeba\nCreate and develop online and offline promotional materials such as web banners, eDM, promotional websites, online ads, leaflet and booklet publishing and retail shop promotion materials design, etc\n\nWho is Our Right Fit\n\nDegree or Higher Diploma in Graphic / Multimedia Design or related disciplines\nWorking experience requirement:\u00a01-3 years\nSolid working experiences in the graphic design industry (inhouse or design house) with hand-on project experience on online advertising, typographic and printing production are absolute advantages\nProficient in Photoshop, Illustrator, InDesign\u00a0and has knowledge in After Effect\u00a0is preferred\nAble to work independently with least supervisory and handle multiple projects simultaneously\nQuick learner and self-motivator with good interpersonal, presentation and communication skills\nGood & cheerful team player with different teams internally & externally\nApplication without portfolio will not be considered.\u00a0", "employment_types": ["Full Time", "Permanent"], "selling_points": ["Open-minded and flexible manner as an amoeba", "Create&develop online&offline promotional material", "Photoshop, Illustrator, InDesign, After Effect"], "locations": ["Tseung Kwan O"], "categories": ["Design", "Graphics", "Multi-media", "Others"], "post_time": "2022-01-06T03:15:40Z", "salary": {"currency": null, "max": null, "min": null, "period": "monthly", "term": null}, "salary_visible": false, "title_keywords": ["graphic designer"], "responsibilities": ["multimedia design", "edm", "video production", "graphic design", "leaflet", "quality", "teams", "design", "develop", "communication", "banners", "promotional materials", "design management", "multiple projects", "online advertising", "ui"], "requirements": {"degrees": ["diploma", "degree"], "majors": ["multimedia design", "related disciplines"], "languages": [], "language_level": [], "hard_skills": ["web", "indesign", "illustrator", "multimedia", "after effect", "photoshop"], "soft_skills": ["flexible", "communication skills", "work independently", "cheerful", "open-minded", "presentation", "quick learner", "team player", "creative", "interpersonal"], "languages_combined": []}, "experience_required": {"duration": ["1-3 years"], "field": ["design house", "graphic design", "advertising"]}}, {"job_id": "100003009032237", "location_code": "hk", "company": "Dorsett Hospitality International Services Limited", "job_title": "Senior Interior Designer / Interior Designer", "description": "Job Responsibilities:\n\nHandle interior design presentation and full set of construction drawings\nDesign Material and Accessories sourcing\nGenerate and execute solutions to any ad-hoc design and project problems\nCo-ordinate with in-house project, procurement team and external consultants to meet project deadline\nSupervise and coach junior staff members in daily works, develop team capabilities, and contribute to team cohesiveness\nFactory inspection for FF&E occasionally\nWilling to travel occasionally\n\n\nJob\u00a0Requirements:\n\nDiploma in Interior Design preferable, or equivalent\nAt least 3-5 years or above relevant experience preferably with hotel design project\nAble to handle project independently and deliver project from design concept to completion\nStrong presentation, communication and interpersonal skills\nCapable to handle design details, drawing & on site-coordination\nProficient in AutoCAD, Photoshop and free-hand sketches.\nInitiative, creative, self-motivating and good team player\nAbility to work independently and work under tight schedule\u00a0\nStrong adaptability and flexibility to change\n\n\nWe offer attractive compensation package to the right candidate. Interested parties please apply with full resume, present and expected salary to Human Resources Department.\n\n\u00a0For more information, please visit our career portal\u00a0http://career.dorsett.com\n\n\u00a0We are an equal opportunity employer and welcome applications from all qualified candidates. All personal data collected is for recruitment purpose only. Applicants not hearing from us within six weeks from the date of advertisement may consider their applications unsuccessful.\u00a0", "employment_types": ["Full Time", "Permanent"], "selling_points": [], "locations": ["Central"], "categories": ["Design", "Interior", "Others", "Hospitality / F & B", "Hospitality / Hotel Services"], "post_time": "2022-01-07T10:32:06Z", "salary": {"currency": null, "max": null, "min": null, "period": "monthly", "term": null}, "salary_visible": false, "title_keywords": ["interior designer", "senior interior designer"], "responsibilities": ["ad-hoc", "design presentation", "co-ordinate with", "design", "drawings", "develop", "inspection"], "requirements": {"degrees": ["diploma"], "majors": ["design"], "languages": [], "language_level": [], "hard_skills": ["photoshop", "autocad"], "soft_skills": ["good team player", "independently", "work independently", "capable", "creative", "communication and interpersonal skills", "adaptability", "coordination", "initiative", "presentation"], "languages_combined": []}, "experience_required": {"duration": ["at least 3-5 years"], "field": ["relevant experience", "design"]}}, {"job_id": "100003009022416", "location_code": "hk", "company": "Just Med Limited", "job_title": "Graphic Designer", "description": "Major Responsibilities:\nResponsible for\u00a0graphic design, shop display\u00a0and other ad hoc design projects\nWork closely with Sales and Marketing Dept.\n\nBasic Requirements:\n\nDiploma or above in Graphic Design or related disciplines\nMinimum 1 year of relevant working experience\nProficiency in\u00a0Adobe, Photoshop, etc\nIndependent, creative, efficient,\u00a0 responsible, and well organized", "employment_types": ["Full Time", "Permanent"], "selling_points": [], "locations": ["Kwai Hing"], "categories": ["Design", "Graphics", "Others"], "post_time": "2022-01-05T05:34:39Z", "salary": {"currency": null, "max": null, "min": null, "period": "monthly", "term": null}, "salary_visible": false, "title_keywords": ["graphic designer"], "responsibilities": ["graphic design", "ad hoc", "design"], "requirements": {"degrees": ["diploma or above"], "majors": ["related disciplines", "graphic design"], "languages": [], "language_level": [], "hard_skills": ["adobe", "basic", "photoshop"], "soft_skills": ["efficient", "independent", "responsible", "well organized", "creative"], "languages_combined": []}, "experience_required": {"duration": ["minimum 1 year"], "field": ["relevant working experience"]}}, {"job_id": "100003009027792", "location_code": "hk", "company": "Hong Kong Sheng Kung Hui Welfare Council Limited", "job_title": "Graphic and Multimedia Designer (Ref: MOSTE(KC)/GMD/20211008-4)", "description": "Responsibilities:\n\nProvide quality design for printed artworks and digital marketing artworks (including DM, banner ads, website, Facebook and Instagram)\uff1b\nManage design projects from concepts to production independently\uff1b\nPerform photo and video shooting, including editing and retouching;\nWork closely with different parties to ensure on time and on budget execution\uff1b\nPerform ad hoc projects when required.\n\nRequirements:\n\nHigher Diploma or above in Design / Web Design / Multimedia Design or related disciplines;\n1-3 years working experience in graphic and multimedia design;\nProficient in AI, Photoshop, Infographic, Illustrator, InDesign, Flash, Dreamweaver, Adobe Premiere/After Effect or other relevant software\uff1b\nKnowledge in Social Media Marketing and Mobile Application / Web design\uff1b\nExperience in video production or photography is an advantage\uff1b\nInnovative, proactive with an excellent sense of graphic design, web design and digital design\uff1b\nGood communication and presentation skills.\n\nBenefits for Full-time Staff:\n\n14 days annual leave entitlement, 17 days public holiday, Marriage Leave, Maternity Leave, Paternity Leave, Compensation Leave, Free Medical Check, Medical\u00a0Insurance, Life Insurance, Medical Consultation Discount, Employer MPF contribution up to 15% according to seniority, On-the-job training, Good promotion ladder.\n\nThis position is project-based.\n\nRemuneration packages will commensurate with qualifications and experience.\u00a0 Interested parties please apply with full curriculum vitae with Expected Salary and Available Date by\u00a0clicking\u00a0\"Apply Now\".\u00a0 Please indicate the reference number on the envelope.\n\nAll applications will be treated in strict confidence for the recruitment purpose only.\u00a0 Candidates not invited for interview within 8 weeks may consider their applications unsuccessful, and the application papers will be retained for a maximum period of 6 months.", "employment_types": ["Full Time", "Contract"], "selling_points": [], "locations": ["Hung Hom"], "categories": ["Design", "Multi-media", "Others", "Public / Civil", "Social Services - Community / Non-profit Organization"], "post_time": "2022-01-06T16:08:26Z", "salary": {"currency": null, "max": null, "min": null, "period": "monthly", "term": null}, "salary_visible": false, "title_keywords": ["multimedia designer"], "responsibilities": ["retouching", "budget", "quality", "website", "design", "video shooting", "digital marketing", "ad hoc projects", "facebook", "editing"], "requirements": {"degrees": ["higher diploma or above"], "majors": ["multimedia design", "web design", "related disciplines", "design"], "languages": [], "language_level": [], "hard_skills": ["web design", "ai", "indesign", "illustrator", "mobile", "adobe premiere", "multimedia", "flash", "dreamweaver", "after effect", "photoshop"], "soft_skills": ["communication", "presentation skills", "innovative", "proactive"], "languages_combined": []}, "experience_required": {"duration": ["1-3 years"], "field": ["video production", "graphic", "design"]}}, {"job_id": "100003009027503", "location_code": "hk", "company": "E & Q Limited", "job_title": "Event and Exhibition Designer", "description": "Role & Responsibilities\n\n\u00a0 \u00a0 \u00a0 \u00a0Handle full set of creative design drawings including 3D rendering, elevation and related marketing campaigns for Event, Roadshow, Exhibition and retails, etc.\n\u00a0 \u00a0 \u00a0 \u00a0Develop and execute concepts across a range of designs including branding, advertising, promotion materials and PR gift.\n\u00a0 \u00a0 \u00a0 \u00a0Work closely with production team for concept development and execution\n\nCapabilities Required\n\nAt least 3-5 years relevant experience in Luxury, cosmetics and retail event\u00a0\nTechnical knowledge on production, QC and on-site supervision are required\nExcellent skills on design software such as Photoshop, Illustrator, SketchUp, 3D-Max software for MAC\nKnowledge on video editing and motion graphic is a plus\nCreative, detail-minded, self-motivated, responsible and able to work under pressure and tight schedule\nA positive character and a good team player\nWilling to work under pressure and overtime\n\nWe offer 5-day work, attractive salary, annual bonus and MPF to the right candidate.\n\nFor interested candidates, please click apply now button your full resume, current & expected salary, project portfolioIf applicable) and earliest availability for job inquiries. Candidates who applied without the requested materials will not be considered.\n\nPersonal data collected will be used for recruitment purposes only.", "employment_types": ["Full Time", "Permanent"], "selling_points": [], "locations": ["Yau Tsim Mong Area"], "categories": ["Design", "Graphics", "Visual Merchandising", "Others"], "post_time": "2022-01-06T10:14:00Z", "salary": {"currency": null, "max": null, "min": null, "period": "monthly", "term": null}, "salary_visible": false, "title_keywords": ["event and exhibition designer"], "responsibilities": ["advertising", "software", "design drawings", "3d rendering", "design", "develop", "video editing", "on-site supervision", "schedule", "marketing campaigns", "motion graphic", "work under pressure"], "requirements": {"degrees": [], "majors": [], "languages": [], "language_level": [], "hard_skills": ["creative design", "plus", "illustrator", "video editing", "photoshop", "max", "sketchup"], "soft_skills": ["detail-minded", "self-motivated", "good team player", "responsible", "creative", "positive", "work under pressure"], "languages_combined": []}, "experience_required": {"duration": ["at least 3-5 years"], "field": ["retail", "relevant experience"]}}, {"job_id": "100003009030386", "location_code": "hk", "company": "Aedas Interiors Limited", "job_title": "Senior CAD Draughtsman", "description": "Requirements:\n\nMinimum 8 years of experience in CAD in interiors;\nPossess full knowledge of AutoCAD software;\nKnowledge of Revit / BIM is an advantage;\nExperience of producing large scale documentation packages;\nConfident in producing fully co-ordinated and accurate sets of drawings;\nBeneficial if candidates are multilingual and able to converse well in English, Cantonese and Mandarin.\n\nAedas Interiors provides opportunities for long term career development with an expanding international practice. We offer attractive compensation and benefit package including 5-day work. Interested parties please send detailed CV, current & expected salary, availability, and specify clearly the position and reference no. by clicking Apply Now.\n\u00a0\nAedas Interiors is an Equal Opportunity Employer\n(Data collected will be used for recruitment purpose only)", "employment_types": ["Full Time", "Permanent"], "selling_points": ["Familiar in CAD with min. 8 years experience", "Full knowledge of AutoCAD / Revit / BIM", "Exp. producing large scale documentation packages"], "locations": ["Quarry Bay"], "categories": ["Design", "Interior", "Others"], "post_time": "2022-01-07T07:22:55Z", "salary": {"currency": null, "max": null, "min": null, "period": "monthly", "term": null}, "salary_visible": false, "title_keywords": [], "responsibilities": ["documentation", "software", "career development", "drawings"], "requirements": {"degrees": [], "majors": [], "languages": ["cantonese", "english", "mandarin"], "language_level": [], "hard_skills": ["cad", "bim", "autocad", "documentation", "revit"], "soft_skills": ["confident", "accurate"], "languages_combined": [{"language": "cantonese", "language_level": []}, {"language": "english", "language_level": []}, {"language": "mandarin", "language_level": []}]}, "experience_required": {"duration": ["minimum 8 years"], "field": []}}, {"job_id": "100003009025154", "location_code": "hk", "company": "Cathay Pacific Airways Ltd", "job_title": "Assistant Manager Strategy & Service Design", "description": "Reports to: Customer Experience Manager \u2013 Strategy & Service Design\nDepartment:\u00a0Customer Experience & Design (CED)\n\nRole Introduction\n\nWe are looking for an experienced service designer to drive and improve customer experiences for Cathay Pacific. This role will work closely with insights, designers and business units to develop a holistic view of end-to-end customer journey for our passengers in their air travel experience. Within the Customer Experience and Design (CED) department, you will design engaging, thoughtful and progressive services across multiple touchpoints (including airport/ground, inflight, food & beverage and digital). You will support the implementation of our design principles and act as a key design thinking champion within the broader organisation to promote human-centred design practices.\u00a0\n\nKey Responsibilities\n\nSupport service design stages of a project, translating research insights into memorable customer experiences\u00a0\nTriangulate and analyse customer data, feedback and internal business pain points to support development of customer experience strategy\nMap end-to-end customer journeys, providing a holistic view to enable new service experiences that are best-in-class \u00a0\nWork closely with stakeholder groups to manage projects on day-to-day basis, managing priorities, resources and timing \u00a0 Prepare and participate in design research such as customer interviews, concept and prototype testing\nUnderstand service design techniques including value proposition, journey mapping, service blueprinting, customer testing and user research\nKnowledgeable in design best practices, trends, and techniques in human-centred design\nEmbody a \u2018growth mindset\u2019 to see business and internal challenges as opportunities and help to drive a positive culture of change\nRequirements\n\nDegree holder with 3+ years\u2019 experience in customer experience, preferably with a background in service design, user experience\nability in user research and customer journey mapping to uncover pain points, customer needs and future opportunities\nExcellent visualisation and storytelling skills to communicate customer insights, strategy and vision in empathetic and impactful way\nAbility to facilitate design thinking and discovery workshops with stakeholders to uncover design requirements and drive alignment\nExcellent planning and organisational skills, ability to work with high attention to detail, but understand and see the bigger picture\nProven ability to build relationships across stakeholder groups to effectively communicate\nPast experience with design thinking methodology to deliver customer experience design\n\nApplication Deadline:\u00a0 26 January 2022\n\nPersonal & Application Information\n\n\nCathay Pacific is an Equal Opportunities Employer. Personal data provided by job applicants will be used strictly in accordance with our personal data policy and for recruitment purposes only. Candidates not notified within eight weeks may consider their application unsuccessful. All related information will be kept in our file for up to 24 months. A copy of our Personal Information Collection Statement will be provided upon request by contacting our Data Protection Officer.\n\nPlease note that with effect from 1 December 2021, all employees must be vaccinated in order to access Cathay City and all other Cathay Group Company premises in Hong Kong. Consideration will be given to those who are unable to get vaccinated for valid medical reasons.\n\n\n\n\n", "employment_types": ["Full Time", "Permanent"], "selling_points": ["Degree holder with 3+ years\u2019 experience", "Design engaging, thoughtful & progressive services", "5-day work, Travel Benefits, Medical Benefits"], "locations": ["Lantau Island"], "categories": ["Transportation & Logistics", "Aviation Services", "Design", "Others"], "post_time": "2022-01-06T03:37:57Z", "salary": {"currency": null, "max": null, "min": null, "period": "monthly", "term": null}, "salary_visible": false, "title_keywords": ["assistant manager"], "responsibilities": ["design", "testing", "manage projects", "customer data", "analyse"], "requirements": {"degrees": ["degree holder"], "majors": ["design"], "languages": [], "language_level": [], "hard_skills": ["workshops"], "soft_skills": ["organisational skills", "attention to detail"], "languages_combined": []}, "experience_required": {"duration": ["3+ years"], "field": ["design"]}}]