[{"job_id": "100003009052690", "location_code": "hk", "company": "Descente China Investment Limited", "job_title": "In-store Visual Merchandiser", "description": "Responsibilities:\n\n\u2022 Support the team in daily operation of visual merchandising for stores\n\n\u2022 Responsible for window & in-store visual merchandising settings\n\n\u2022 Ensure all in-store visual presentation according to the direction and guidelines\n\n\u2022 Design POP & graphics and follow up with seasonal production materials\n\n\u2022 Assist in setting up new store and other ad hoc projects\n\n\nRequirements:\n\n\u2022 Min. 1 year relevant experience in retail industry\n\n\u2022 Self-motivated, responsible and be a good team player\n\n\u2022 Creative, independent and passion in fashion\n\n\u2022 Excellent in design software (e.g. Photoshop, Illustrator and etc.)\n\n\u2022 Creative thinking while multi-tasking on several assignment and tight overlapping deadlines\n\n\u2022 Immediately available is preferable.", "employment_types": ["Full Time"], "selling_points": ["Min. 1 year relevant experience", "Window & in-store visual merchandising settings", "Immediately available"], "locations": ["Not Specified"], "categories": ["Design", "Visual Merchandising"], "post_time": "2022-01-17T03:42:28Z", "salary": {"currency": null, "max": null, "min": null, "period": "monthly", "term": null}, "salary_visible": false, "title_keywords": ["visual merchandiser"], "responsibilities": ["graphics", "guidelines", "merchandising", "daily operation", "design", "ad hoc projects", "visual", "visual presentation", "support the team"], "requirements": {"degrees": [], "majors": [], "languages": [], "language_level": [], "hard_skills": ["illustrator", "photoshop"], "soft_skills": ["good team player", "self-motivated", "independent", "responsible", "passion in", "multi-tasking", "creative"], "languages_combined": []}, "experience_required": {"duration": ["1 year"], "field": ["retail industry", "relevant experience"]}}, {"job_id": "100003009044025", "location_code": "hk", "company": "I.T Apparels Limited", "job_title": "Assistant Visual Merchandiser (REF: JDB-IT-AVM)", "description": "Job Description\n\nMy client is an interior design firm based in Hong Kong. They are specializing an international brand including retail and commercial design projects. The boutique locate for K11 MUSEA, 1881 Heritage, Ocean Terminal, Element Shop, Macau and China.\n\nWelcome to join our team to cope with our rapid expansion in both mainland China and Hong Kong.\n\nRequirements\n\nDiploma holder or above in Interior Design\nBasic\u00a0computer knowledge in AutoCAD\u00a0and\u00a0Photoshop are\u00a0preferable\nCapable in handling project independently for interior designer\n\nResponsible of site management, site survey,\u00a0 site staff supervision, etc.\u00a0for interior designer\n\nBasic Cantonese, English & Putonghua\nTraveling to overseas/ PRC is required\nMin 2 years site experience for interior designer\u00a0\n\nResponsibilities:\u00a0\n\nAssist the Senior Interior Designer\nDealing with clients, contractors, architectures, vendors and project team members\nResponsible for design drawings and documentation including concept design and development, construction drawing, materials sourcing and selection\nIdentify and understand clients\u2019 needs and provide customer services\n\nWe offer\u00a0double pay,\u00a0bank holidays, 5 1/2day work,\u00a0annual leave and MPF. Interested candidates please send your application letter with CV, portfolio and salary expectations by clicking 'Apply Now'", "employment_types": ["Full Time"], "selling_points": ["Visual Merchandising", "Promotional Displays", "1-2 years of Visual Merchandising experience"], "locations": ["Not Specified"], "categories": ["Design", "Fashion", "Graphics", "Visual Merchandising"], "post_time": "2022-01-13T02:49:39Z", "salary": {"currency": null, "max": null, "min": null, "period": "monthly", "term": null}, "salary_visible": false, "title_keywords": ["assistant visual merchandiser"], "responsibilities": ["design"], "requirements": {"degrees": ["diploma holder"], "majors": ["design"], "languages": ["cantonese", "putonghua", "english"], "language_level": ["basic"], "hard_skills": ["documentation", "basic", "photoshop", "autocad"], "soft_skills": ["independently", "capable", "responsible"], "languages_combined": [{"language": "cantonese", "language_level": ["basic"]}, {"language": "putonghua", "language_level": []}, {"language": "english", "language_level": []}]}, "experience_required": {"duration": ["min 2 years"], "field": ["designer"]}}, {"job_id": "100003009052316", "location_code": "hk", "company": "Charlotte Tilbury Beauty Asia Pacific Limited", "job_title": "Store Designer APAC", "description": "Accountabilities \u2013 Key Result Areas\n\nDesign, develop and execute all visual merchandising and promotional displays for promotional program, seasonal change and ad-hoc events\nMaintain and upkeep all visual merchandising materials at stores regularly\nAssist in sourcing, negotiation\u00a0and liaison with suppliers for the ordering, delivering and producing of materials,\u00a0and set up\u00a0relating to all visual merchandising\nAssist in setting up and coordinates new store opening and store upgrading\nWork closely in team for concept development, execution and all creative deliberationSupport graphic design\u00a0and development of artwork for various marketing materials such as print ad, brochure, packaging, POP, flyer, poster and etc.\nLiaise and coordinate with external agencies and vendors for print/production and quality control.\nProject management of all VM initiatives including windows, seasonal brand imagery, LED screens, POS and merchandise presentations all to be delivered in store, on time and on budget\nEnhance aesthetic appeal of shop front windows and in-store displays to promote new product launches, festive and seasonal themes including deliver regular floor moves, window installations, and mannequins styling, etc.\nExperience / Qualification Requirements\nDegree holder in visual merchandising and design related discipline\nAt least 1 - 2 years experience in fashion industry, with solid experience in visual design, window set up, interior displays and space utilization\nProficient design software skills such as Illustrator, Photoshop, AutoCAD, etc.\nCreative and possess good knowledge and sense of fashion, accessories, color trends and styling\nBe passionate about the brand\u2019s identity, with personal charisma and good understanding of the dynamics of the fashion industry\nCommunicative and be able to collaborate with business teams to achieve brand objectives\nCandidates with less experience will be considered as Visual Merchandising Coordinator.\n\nCompetitive remuneration and benefit package will be offered to the right candidate. Please submit your application by clicking \"Apply Now\" below.\n\nAll data collected is for recruitment purpose only.\n\nSure you want to know more about our company and brands, simply follow our\n\nWEBSITE at\u00a0http://www.ithk.com\u00a0 \u00a0 \u00a0 \u00a0 \u00a0 \u00a0 \u00a0 \u00a0 \u00a0 \u00a0 \u00a0 \u00a0 \u00a0 \u00a0 \u00a0 \u00a0 \u00a0 \u00a0 \u00a0 \u00a0 \u00a0 \u00a0 \u00a0 \u00a0 \u00a0 \u00a0 \u00a0 \u00a0 \u00a0 \u00a0 \u00a0 \u00a0 \u00a0 \u00a0\n\nFACEBOOK at\u00a0http://www.facebook.com/I.Ttheofficialpage\u00a0 \u00a0 \u00a0 \u00a0 \u00a0 \u00a0 \u00a0 \u00a0 \u00a0 \u00a0 \u00a0 \u00a0 \u00a0 \u00a0\u00a0\n\nINSTAGRAM at\u00a0http://instagram.com/ithk\u00a0 \u00a0 \u00a0 \u00a0 \u00a0 \u00a0 \u00a0 \u00a0 \u00a0 \u00a0 \u00a0 \u00a0 \u00a0 \u00a0 \u00a0 \u00a0 \u00a0 \u00a0 \u00a0 \u00a0 \u00a0 \u00a0 \u00a0 \u00a0 \u00a0 \u00a0 \u00a0 \u00a0\n\nWEIBO at\u00a0http://e.weibo.com/ithongkong", "employment_types": ["Full Time", "Permanent"], "selling_points": [], "locations": ["Central"], "categories": ["Design", "Interior", "Visual Merchandising"], "post_time": "2022-01-17T02:44:04Z", "salary": {"currency": null, "max": null, "min": null, "period": "monthly", "term": null}, "salary_visible": false, "title_keywords": ["designer"], "responsibilities": ["liaise", "collaborate with", "software", "data", "budget", "merchandising", "website", "design", "maintain", "facebook", "ad-hoc events", "teams", "presentations", "develop", "visual", "promotional program", "coordinate with", "graphic design", "project management", "recruitment", "quality control", "marketing materials"], "requirements": {"degrees": ["degree holder"], "majors": ["design"], "languages": [], "language_level": [], "hard_skills": ["pos", "visual merchandising", "illustrator", "presentations", "project management", "visual design", "autocad", "facebook", "photoshop"], "soft_skills": ["project management", "creative", "negotiation", "passionate about"], "languages_combined": []}, "experience_required": {"duration": ["at least 1 - 2 years"], "field": ["merchandising", "design"]}}, {"job_id": "100003009054656", "location_code": "hk", "company": "SEN Construction Company Limited", "job_title": "Interior Designer / Assistant Interior Designer", "description": "Degree holder or Diploma in interior design\u00a0\nProficient in CAD (Photoshop, Sketch Up, 3D Max are bonus)\nGood team-player who is initiative, creative, self-motivated, willing to work in a fast paced and demanding environment\nGood in presentation skills\nGood Leadership Skills\nAt least 3 year working experience\u00a0 **Less experience consider as Assistant Interior Designer**\nStrong sense of design and be able to handle full set of drawing with detailing design\nWork independent", "employment_types": ["Full Time"], "selling_points": ["\u505a\u5927\u54c1\u724c\u5e97\u8216\u88dd\u4fee\u8a2d\u8a08, \u589e\u52a0\u500b\u4eba\u7d93\u9a57\u503c", "Double pay", "\u7531\u4e2d\u74b0\u6e2f\u9435\u5230\u516c\u53f8, \u53ea\u8981\u6b65\u884c5\u5206\u9418"], "locations": ["Central"], "categories": ["Design", "Interior", "Visual Merchandising", "Others"], "post_time": "2022-01-17T10:25:13Z", "salary": {"currency": "HKD", "max": 34999, "min": 14000, "period": "monthly", "term": null}, "salary_visible": true, "title_keywords": ["interior designer", "assistant interior designer"], "responsibilities": ["design"], "requirements": {"degrees": ["diploma", "degree holder"], "majors": ["design"], "languages": [], "language_level": [], "hard_skills": ["sketch up", "cad", "max", "photoshop"], "soft_skills": ["self-motivated", "independent", "team-player", "leadership skills", "presentation skills", "creative", "initiative"], "languages_combined": []}, "experience_required": {"duration": ["at least 3 year"], "field": ["designer"]}}, {"job_id": "100003009053424", "location_code": "hk", "company": "Wams Design Limited", "job_title": "Senior Designer/Interior Designer/Assistant Designer", "description": "We are looking for a driven, passionate superstar to join Team Tilbury as our Store Designer.\u00a0 You will be involved in all aspects of creative store design and project manage \u2013 from design to approvals to suppliers recruitment to technical drawings development to production and installation. You will be part of a growing Store Design and VM team responsible for all APAC countries excluding China. You will thrive on the challenge of a fast-paced environment, and you will be able to use your previous experience as a Store Designer and Project Manager either in house or at an advertising agency to make great effect in our team. In your role, you will report to our Senior Store Design Manager and work cross functionally with the APAC & Global teams.\n\nKey Responsibility\n\nTo design new stores & renovations of existing stores following global design guidelines and standards.\nTo design in-store shopping experiences that fits local customers\u2019 needs & keep up with fast-changing retail market trend\nTo manage the design requirements from Landlord and other functions\nTo follow up approvals internally and externally\nTo update design drawings and work with suppliers on technical drawings.\nTo anticipate design issues and provide solutions to ensure stores are open as per timeline and budget\nTo work closely with internal teams on special projects such as Pop up stores, temporary stores in accordance with overall commercial strategy.\nTo control strictly and keep in line with budget planning.\nTo summarize & establish APAC store design guideline and keep update accordingly.\nTo carry out market trend studies\nTo develop & propose local store innovations to create increased customer relevance and optimize in-store experience\n\nSome attributes we are looking for:\n\nCreative thinking and agile to new ideas and ways of working\nBroad knowledge of M & E, technical details in production\nExperience of managing workflow between Global and Regional teams\nStrong teamwork and communication skills to feedback to stalk holders\nExperience of handling multiple projects and requests simultaneously.\nExperience of project management from design to supplier recruitment to TD to production and installation\nExperience of on-site supervision & snagging solutions\nStrong sense of time management and cost control\n\nJob Qualification\n\nRequirements\n\n\nArchitecture or interior design major\nProficient in using Auto CAD/ 3D Max/ Sketch up/Illustration/ Photo shop and Microsoft office\nFrequently in English and Chinese.\nMore than 5 years working experience in beauty brand company.", "employment_types": ["Full Time", "Permanent"], "selling_points": [], "locations": ["Wan Chai"], "categories": ["Design", "Graphics", "Interior", "Visual Merchandising"], "post_time": "2022-01-17T06:58:05Z", "salary": {"currency": null, "max": null, "min": null, "period": "monthly", "term": null}, "salary_visible": false, "title_keywords": ["senior designer", "interior designer", "assistant designer"], "responsibilities": ["ideas", "budget", "design", "communication", "technical drawings", "control", "budget planning", "teams", "develop", "installation", "management", "design drawings", "provide solutions", "on-site supervision", "guidelines", "project management", "recruitment", "cost control", "multiple projects"], "requirements": {"degrees": [], "majors": [], "languages": ["english", "chinese"], "language_level": [], "hard_skills": ["microsoft office", "auto cad", "sketch up", "max", "illustration"], "soft_skills": [], "languages_combined": [{"language": "english", "language_level": []}, {"language": "chinese", "language_level": []}]}, "experience_required": {"duration": ["5 years"], "field": ["brand", "beauty"]}}, {"job_id": "100003009051059", "location_code": "hk", "company": "Talent Blue Search Limited", "job_title": "Assistant Retail Marketing Manager \u2013 European Home Appliances Brand", "description": "Our client, a European Home Appliances Brand, is seeking an Assistant Retail Marketing Manager.\n\nThis is a new position created to develop and implement comprehensive marketing and merchandising programs for strategic retailers\n\nResponsibilities:\n\nAuthor, strategize and execute the channel strategy for retailers\nDevelop retail marketing strategy based on category analysis, retailer insights and sales objectives to formulate retail marketing, merchandising and instore activation plans\nFormulate budget and monitor spending monthly\nWith the support from design and VM team to create clear and compelling instore brand presentations.\nPartner/Negotiate with retailers to execute instore activation plan to achieve brand and sales objectives\nRequirements:\n\nDegree holder in Business Administration, Design or other discipline.\n5+ years of marketing experience, particularly involving trade marketing, Visual Merchandising, display, design, etc.\nStrong commercial acumen, with in ROI and formulating budgets.\nThis is a new position, particularly welcomes Trade Marketing Professionals , with experience with VM / Display in Retail Stores from beauty, FMCG and home appliances.\n580K - 660K per annual", "employment_types": ["Full Time", "Permanent"], "selling_points": ["Retail Marketing Strategy Visual & Display Plan", "In-store program event Retailer Partnership", "580K - 660K per annual"], "locations": ["Not Specified"], "categories": ["Design", "Visual Merchandising", "Marketing / Public Relations", "Management", "Marketing - General / Support"], "post_time": "2022-01-15T01:36:02Z", "salary": {"currency": null, "max": null, "min": null, "period": "monthly", "term": null}, "salary_visible": false, "title_keywords": ["marketing manager", "assistant"], "responsibilities": ["vm team", "analysis", "budget", "merchandising", "monitor", "design", "develop", "presentations", "plan", "plans"], "requirements": {"degrees": ["degree holder"], "majors": ["business administration", "design"], "languages": [], "language_level": [], "hard_skills": ["visual merchandising", "acumen"], "soft_skills": [], "languages_combined": []}, "experience_required": {"duration": ["5+ years"], "field": ["fmcg", "merchandising", "design", "marketing", "beauty", "retail"]}}, {"job_id": "100003009051452", "location_code": "hk", "company": "City Chain Company Limited", "job_title": "Senior Project Officer", "description": "Let\u2019s work together\n\n\nExperience in-store visual merchandising, store project management, furniture design and fitting out works\nPrioritize manage and track multiple, simultaneous projects in terms of timing and budget\nGather market intelligence regarding interior and store design trends\nOrganize the standard design of furniture and fixture\nManage Hong Kong and Macau store projects\nMake site visits\nManage external contractors\n\n\u00a0We are looking for\n\n\nUniversity graduate in\u00a0Interior Design, Architecture, Project management, Project Construction preferred\nMinimum 3 years experience in retail projects preferably\nCandidates with retail industry experience will be at an advantage\nExperienced in international and local firms\nStrong grasp of VM, interior and store design as well as store project management capabilities\nStrong business sense, analytical and problem-solving skills\nExcellent leadership and communication skills\nProficient in AutoCAD, Photoshop, AI and other design skills, MS Word and Excel\nGood command of written and spoken English, Mandarin and Cantonese\nImmediate availability will be an advantage\n\n\u00a0\u00a0Join us now:\n\nPlease send\u00a0full resume stating your academic qualifications, career history, availability with current and expected salary\u00a0to: The\u00a0Human Resources Manager\n\n\u00a0On offer is a competitive package\n\nAttractive\u00a0Remuneration\n5 Days Work\nAnnual Leave\nFamily Leave\nMonthly Early Release\u00a0\n\n\n\nBirthday Leave with gifts\nMarriage Leave with red packets\nExamination Leave\nMedical Scheme\nStaff Discount\n\n\n\nWebsite:\u00a0www.citychain.com\n", "employment_types": ["Full Time"], "selling_points": ["Responsible for store project", "Prioritize manage and track multiple", "3 years solid experience"], "locations": ["Wong Tai Sin Area"], "categories": ["Design", "Interior", "Visual Merchandising"], "post_time": "2022-01-16T00:29:46Z", "salary": {"currency": null, "max": null, "min": null, "period": null, "term": null}, "salary_visible": false, "title_keywords": ["senior project officer"], "responsibilities": ["budget", "merchandising", "website", "design", "communication", "project management", "visual", "design trends", "architecture"], "requirements": {"degrees": ["university graduate"], "majors": ["project management", "architecture", "design"], "languages": ["cantonese", "english", "mandarin"], "language_level": ["good command"], "hard_skills": ["excel", "ai", "ms word", "visual merchandising", "scheme", "project management", "make", "photoshop", "problem-solving skills", "red", "autocad"], "soft_skills": ["communication skills", "business sense", "prioritize", "project management", "problem-solving skills", "leadership"], "languages_combined": [{"language": "cantonese", "language_level": ["good command"]}, {"language": "english", "language_level": ["good command"]}, {"language": "mandarin", "language_level": ["good command"]}]}, "experience_required": {"duration": ["minimum 3 years"], "field": ["retail industry", "design", "store visual merchandising", "project management", "retail"]}}, {"job_id": "100003009053480", "location_code": "hk", "company": "Untitled Limited", "job_title": "Senior 3D Designer (5 days work)", "description": "Requirements:\n\n\n2 years minimum experience in event production / exhibition field / shopping mall decorations\nCompetency in adobe illustrator / Photoshop / 3D studio max, Auto CAD\nPreparing studies, layouts, and construction drawing.\nSeasonal-Decoration, Event Design experience will be an absolute advantage\nExhibition, or environmental design qualification in degree or diploma level\nFresh Graduate will be considered\nAble to handle projects from concept design through to completion\nMust be a team player and willing to work overtime, self initiative & motivated, strong sense of responsibitity and able to work under pressure\n\n\nWe offer attractive package to the right candidate.\n\nInterested parties please send full resume with salary expected, to Fax No. 3426 9709\n\nhttp://www.facebook.com/pages/untitled-limited/336303970488", "employment_types": ["Full Time"], "selling_points": ["Five-day work week", "Double pay", "Performance bonus"], "locations": ["Quarry Bay"], "categories": ["Media & Advertising", "Creative / Design", "Design", "Graphics", "Visual Merchandising"], "post_time": "2022-01-17T07:02:15Z", "salary": {"currency": null, "max": null, "min": null, "period": "monthly", "term": null}, "salary_visible": false, "title_keywords": ["senior 3d designer"], "responsibilities": ["design", "work under pressure"], "requirements": {"degrees": ["diploma", "degree", "fresh graduate"], "majors": ["design"], "languages": [], "language_level": [], "hard_skills": ["max", "auto cad", "photoshop", "adobe illustrator"], "soft_skills": ["work overtime", "motivated", "team player", "initiative", "work under pressure"], "languages_combined": []}, "experience_required": {"duration": ["2 years"], "field": ["design"]}}, {"job_id": "100003009038582", "location_code": "hk", "company": "Rue Madame Limited", "job_title": "Senior Visual Merchandiser", "description": "Job Responsibilities:\n\nTo plan, design and execute in-store and window display of our concept stores;\nTo assist in new store opening visual set up;\nTo ensure VM concept for our mono-brand store match the brands\u2019 requirements;\nTo well organize the VM schedule;\nTo train our retail team to maintain a good VM in the shops at all time;\nTo coordinate\u00a0 with Image & Design team to implement promotional/seasonal in-store display;\nTo liaise with overseas mono-brand headquarter and suppliers via email;\nTo source VM materials (including sourcing, organizing and distributing);\nTo assist in ad hoc projects as assigned.\n\nRequirements:\n\nOrganized and creative\nAt least 5 years relevant experience in fashion / luxury industry;\nCreative\u00a0with strong fashion sense, with interests and\u00a0knowledge in fashion styling and color trends;\nProficient in Photoshop and illustrator;\nFluent in Cantonese and English;\nGood communication and\u00a0presentation skills;\nGood team player.\n\nBenefits:\n\n5-day work week\nFlex working hours\nMedical insurance & dental care\nPublic Holiday\n12-17 days paid Annual Leave\n5 days Marriage Leave\nBirthday Leave\nStaff purchase discount\n\nAttractive remuneration package will be offered to the right candidate.\u00a0 Please apply with full resume stating present & expected salary and contact phone number\u00a0by clicking below \"Apply Now\".\u00a0\n\nPersonal data collected will be used for recruitment purpose only.\u00a0 For more information, please visit our website:\u00a0www.rm-fg.com", "employment_types": ["Full Time", "Permanent"], "selling_points": ["Young & energetic team", "Excellent career development opportunity", "Creative job"], "locations": ["Sheung Wan"], "categories": ["Design", "Graphics", "Interior", "Visual Merchandising"], "post_time": "2022-01-11T07:26:20Z", "salary": {"currency": null, "max": null, "min": null, "period": "monthly", "term": null}, "salary_visible": false, "title_keywords": ["visual merchandiser"], "responsibilities": ["design", "coordinate", "maintain", "ad hoc projects", "schedule", "plan", "visual", "liaise with"], "requirements": {"degrees": [], "majors": [], "languages": ["cantonese", "english"], "language_level": ["fluent"], "hard_skills": ["luxury industry", "illustrator", "photoshop"], "soft_skills": ["organized", "good team player", "communication", "presentation skills", "creative"], "languages_combined": [{"language": "cantonese", "language_level": ["fluent"]}, {"language": "english", "language_level": ["fluent"]}]}, "experience_required": {"duration": ["at least 5 years"], "field": ["relevant experience"]}}, {"job_id": "100003009046956", "location_code": "hk", "company": "Fossil (East) Ltd", "job_title": "Senior Graphic Designer", "description": "\uff1cSCOPE OF POSITION\uff1e\nThe position aims to support the development and execution for press and communication strategies around brand initiatives, special projects, and trade marketing activities.\n\n\uff1cReport to\uff1e\nHead of Onitsuka Tiger Hong Kong\n\n\uff1cDUTIES AND RESPONSIBILITIES\uff1e\n\nCo-ordinate and prepare in-store/marketing materials to maximize retail presence e.g. POP, leaflets etc.\nResponsible for compiling reports of retail marketing programs to keep track on results and evaluate the effectiveness\nSupport the development and execution of all in-store promotions and marketing activities/events at retail level to enhance brand image, product awareness and drive sales/traffic\nManage VIP data for easy analysis. CRM implementation and maintenance of CRM system and activation\nWork closely with different departments and external parties for all trade marketing issues\nManage budget and targets for retention activities and report against ROI\nTranslation and blasting of press release. Arrange delivery of seeding products\nHandle customer complaints\nPrepare visual merchandising guideline and presentation to front line staff. Assist in coordinating and implementing new shop opening and retail promotions.\nDevelop and implement all visual merchandising and promotional displays for seasonal changeover, promotional programs and ad-hoc events under the direction of Onitsuka Tiger Headquarter Japan.\nSource and liaison with suppliers for the ordering, delivering and producing of materials relating to all visual merchandising.\nFollow up VM fixtures and replenishment works such as quotation, delivery schedule, quality control, etc.\nResponsible for the graphic design for various marketing campaigns and functions.\nPerform quality checks and shop visits to ensure complete implementation of visual merchandising materials according to the guideline and standard.\nOther ad hoc duties as assigned\n\uff1cDESIRED SKILLS & EXPERIENCE\uff1e\n\nUniversity graduate in Marketing, Digital Marketing or related disciplines\n3-5 years related hands-on experience of Marketing, preferable in fashion retail industry\nGood command of written and spoken English and Chinese is essential\nGood interpersonal skills, hardworking, creative, self-motivated and willing to learn\nAbility to work in fast-paced environment\nWord, Excel, Power Point skill is a must\nKnowledge in AI and Photoshop is preferable\n\nWe offer attractive remuneration package to the right candidate. If you are interested in this exciting opportunity, please click \u201cApply Now\u201d to submit applications with detailed resume stating career history, present & expected salary and date available.\n\nPersonal data collected will be used for recruitment purpose only. Applicants not hearing from us within 6 weeks may consider their applications unsuccessful and all related information will be destroyed after 6 months.", "employment_types": ["Full Time", "Permanent"], "selling_points": ["4+ years experience in Graphic Design", "Fashion Accessories Industry", "Proficient in AI / InDesign / Photoshop"], "locations": ["Tsim Sha Tsui"], "categories": ["Design", "Graphics", "Visual Merchandising"], "post_time": "2022-01-14T02:41:31Z", "salary": {"currency": null, "max": null, "min": null, "period": "monthly", "term": null}, "salary_visible": false, "title_keywords": ["senior graphic designer"], "responsibilities": ["data", "external parties", "budget", "merchandising", "quotation", "quality", "communication", "ad-hoc events", "ad hoc duties", "implementation", "develop", "reports", "marketing campaigns", "visual", "report", "customer complaints", "leaflets", "delivery schedule", "digital marketing", "drive sales", "trade marketing", "maintenance", "graphic design", "analysis", "replenishment", "evaluate", "quality control", "marketing materials"], "requirements": {"degrees": ["university graduate"], "majors": ["related disciplines", "marketing", "digital marketing"], "languages": ["english", "chinese"], "language_level": ["good command"], "hard_skills": ["excel", "maintenance", "ai", "analysis", "visual merchandising", "word", "power point", "translation", "photoshop"], "soft_skills": ["self-motivated", "responsible", "willing to learn", "communication", "hands-on", "interpersonal skills", "work in fast-paced environment", "creative", "presentation", "hardworking"], "languages_combined": [{"language": "english", "language_level": ["good command"]}, {"language": "chinese", "language_level": ["good command"]}]}, "experience_required": {"duration": ["3-5 years"], "field": ["related", "marketing", "retail industry"]}}, {"job_id": "100003009047466", "location_code": "hk", "company": "ASICS HongKong Limited", "job_title": "Sr. Marketing Executive, Onitsuka Tiger Hong Kong", "description": "The Role\nWe are looking for a creative and passionate Graphic Designer to join our team.\u00a0\u00a0You will have a chance to work at a fast-paced mission driven company that brings material science to life and benefit the mass.\u00a0 We are bringing business disruption and new hygiene standard to the world with the introduction of new photocatalyst products and services. With the continuous R&D and business innovation, we are thrilled to develop the next generation technology that safeguards everyday life.\u00a0 Raze Technology is the world's leading photocatalyst solution company, developing a long-lasting disinfectant coating.\n\nResponsibilities\nResponsible for creative concept development and handle all stages of design include but not limited to the following:\u00a0\n\n\nSocial media visual and feed designs (Facebook, Instagram, eDM, Google ad, etc.);\u00a0\nOnline store visual (Web banner, product page, etc);\u00a0\nSales kit and POP materials;\nProduct retouching and mock-ups;\u00a0\nPerform ad-hoc projects as assigned.\n\nRequirements\n\n\nDiploma or above in Graphic Design/ Multimedia/ Creative Media or other related disciplines;\nAt least 3 years relevant working experience in graphic design, FMCG or digital marketing agency experience is preferred;\nProficient in using Adobe Illustrator, Photoshop in Mac environment;\u00a0\nProficient in animation and video editing is a plus;\nGood team player, multi-tasking and responsible;\nVisual merchandising experience is an advantage;\u00a0\nImmediate availability is highly preferable.\n\nWe offer the right candidate attractive remuneration package and outstanding prospects for career advancement and development.\u00a0 The right candidate will progress career in a forward thinking and dynamic business with exciting growth plans.\u00a0 If you are qualified and interested, please send your full resume with current & expected salary and availability by clicking \"APPLY\".\n\nAll information collected will be treated as strictly confidential and used for recruitment purposes only. (Only shortlisted candidates will be notified)", "employment_types": ["Full Time", "Permanent"], "selling_points": ["Marketing, Visual Merchandising, VM", "Trade Marketing, Design, e-commerce", "Fashion, Retail, Wholesales"], "locations": ["Kwun Tong"], "categories": ["Design", "Visual Merchandising", "Marketing / Public Relations", "Others", "E-commerce", "Marketing - Brand / Product Management"], "post_time": "2022-01-14T03:12:27Z", "salary": {"currency": null, "max": null, "min": null, "period": "monthly", "term": null}, "salary_visible": false, "title_keywords": ["marketing executive"], "responsibilities": ["pop materials", "edm", "product retouching", "mock-ups", "social media visual and feed designs", "design", "visual", "facebook", "ad-hoc projects", "sales kit"], "requirements": {"degrees": ["diploma or above"], "majors": ["related disciplines", "graphic design", "creative media"], "languages": [], "language_level": [], "hard_skills": ["plus", "mac environment", "visual merchandising", "adobe illustrator", "multimedia", "animation and video editing", "photoshop"], "soft_skills": ["good team player", "creative", "multi-tasking", "responsible"], "languages_combined": []}, "experience_required": {"duration": ["at least 3 years"], "field": ["fmcg", "agency", "graphic design", "merchandising", "relevant working experience", "digital marketing"]}}, {"job_id": "100003009047149", "location_code": "hk", "company": "SEN Construction Company Limited", "job_title": "Interior Designer / Assistant Interior Designer", "description": "We are currently seeking a specialist to join our creative team in HK.\u00a0 This opening offer an opportunity to work with well-known international brands and their professional team.\u00a0\n\nJob Duties:\n\nStrengthen the current creative offering in the areas of high-end/fine retail experiential\u00a0related industries.\u00a0\nTake creative lead on projects being involved at pitch stage and generally offering original, creative and effective design solutions.\nWork on projects from concept right the way through to finished product.\nYou will be comfortable driving creative pitch work, individually or by working with. \u00a0You will also have a chance to mentoring and reviewing other team members work.\u00a0\n\nRequirements:\n\nMinimum 4 years\u00a0Retail Experiential Design experience, solid experience in Cosmetics industry with Pop Up Event / Store Design / VM Design is more appreciated.\u00a0\nSoftware Requirement: 3DMAX (V-Ray), AutoCAD and Photoshop is a must.\nDegree in Interior Design or any other equivalent.\nGood understanding of consumer behaviour and latest market trend.\nAble to develop strategic and conceptual ideas for innovative retail solutions.\nHave a strong creative background and a good eye for detail.\u00a0\nStrong problem solving and analytical ability, with teamwork spirit.\nGood time management skill, able to catch-up deadline.\u00a0\nGood overall project process knowledge, as factory visit is required.\nGood hand sketch ability is appreciated.\u00a0 \u00a0\nKey elements to join our TEAM:\n\nBe responsible\nBe positive\nBe open-minded\nGood Language skills (English, Mandarin)\nGood Team Player\nWilling to work overtime\n\nWe OFFER:\n\nFive Day Work Week\nYear End Performance Bonus\nMedical Insurance\nEducational Allowance\nSeniority Allowance\nCoaching and Training\nBirthday Allowance\nQuarterly Team Building\nActivity Overtime Allowance\n\nAction NOW:\n\nThis is an exciting opportunity for you to join our creative team that are passionate and committed to everything in retail design and brand experience!\u00a0 DON\u2019T HESITATE!!\u00a0\u00a0If you are passion to develop your career, please send your PORTFOLIO and CV to us.\u00a0 A step further to your success. Make sure you mark the current / expected salary and date of available in your CV.\n\nPersonal data collected is for recruitment purpose only", "employment_types": ["Full Time"], "selling_points": ["\u505a\u5927\u54c1\u724c\u5e97\u8216\u88dd\u4fee\u8a2d\u8a08, \u589e\u52a0\u500b\u4eba\u7d93\u9a57\u503c", "Double pay", "\u7531\u4e2d\u74b0\u6e2f\u9435\u5230\u516c\u53f8, \u53ea\u8981\u6b65\u884c5\u5206\u9418"], "locations": ["Central"], "categories": ["Design", "Interior", "Visual Merchandising", "Others"], "post_time": "2022-01-14T02:28:08Z", "salary": {"currency": "HKD", "max": 34999, "min": 14000, "period": "monthly", "term": null}, "salary_visible": true, "title_keywords": ["interior designer", "assistant interior designer"], "responsibilities": ["design solutions"], "requirements": {"degrees": ["degree"], "majors": ["design"], "languages": ["english", "mandarin"], "language_level": ["good"], "hard_skills": ["problem solving", "3dmax", "photoshop", "autocad"], "soft_skills": ["good team player", "work overtime", "creative", "responsible", "open-minded", "problem solving", "teamwork spirit", "time management skill", "eye for detail", "innovative", "positive"], "languages_combined": [{"language": "english", "language_level": ["good"]}, {"language": "mandarin", "language_level": ["good"]}]}, "experience_required": {"duration": ["minimum 4 years"], "field": ["retail", "design"]}}, {"job_id": "100003009044035", "location_code": "hk", "company": "Spring Professional (Hong Kong) Limited", "job_title": "Art Consultant / Art Specialist / Art advisor (Interior Design Firm)", "description": "We are currently seeking a specialist to join our creative team in HK.\u00a0 This opening offer an opportunity to work with well-known international brands and their professional team.\u00a0\n\nJob Duties:\n\nStrengthen the current creative offering in the areas of high-end/fine retail experiential\u00a0related industries.\u00a0\nTake creative lead on projects being involved at pitch stage and generally offering original, creative and effective design solutions.\nWork on projects from concept right the way through to finished product.\nYou will be comfortable driving creative pitch work, individually or by working with.\u00a0\u00a0\n\nRequirements:\n\nMinimum 2 years\u00a0Retail Experiential Design experience, solid experience in Cosmetics industry with Pop Up Event / Store Design / VM Design is more appreciated.\u00a0\nDiploma or Degree in Interior Design or any other equivalent.\nGood understanding of consumer behaviour and latest market trend.\nAble to develop strategic and conceptual ideas for innovative retail solutions.\nHave a strong creative background and a good eye for detail.\u00a0\nStrong problem solving and analytical ability, with teamwork spirit.\nGood time management skill, able to catch-up deadline.\u00a0\nGood overall project process knowledge, as factory visit is required.\nSoftware Requirement: 3DMAX (V-Ray), AutoCAD and Photoshop is a must.\nGood hand sketch ability is appreciated.\u00a0 \u00a0\nKey elements to join our TEAM:\n\nBe responsible\nBe positive\nBe open-minded\nGood Language skills (English, Mandarin)\nGood Team Player\nWilling to work overtime\n\nWe OFFER:\n\nFive Day Work Week\nYear End Performance Bonus\nMedical Insurance\nEducational Allowance\nSeniority Allowance\nCoaching and Training\nBirthday Allowance\nQuarterly Team Building\nActivity Overtime Allowance\n\nAction NOW:\n\nThis is an exciting opportunity for you to join our creative team that are passionate and committed to everything in retail design and brand experience!\u00a0 DON\u2019T HESITATE!!\u00a0\u00a0If you are passion to develop your career, please send your PORTFOLIO and CV to us.\u00a0 A step further to your success. Make sure you mark the current / expected salary and date of available in your CV.\n\nPersonal data collected is for recruitment purpose only", "employment_types": ["Full Time"], "selling_points": ["Luxury residential and hospitality projects", "Artwork selection experience", "Aesthetic, taste, have an eye for artwork"], "locations": ["Central & Western Area"], "categories": ["Design", "Graphics", "Interior", "Visual Merchandising"], "post_time": "2022-01-13T02:52:17Z", "salary": {"currency": null, "max": null, "min": null, "period": "monthly", "term": null}, "salary_visible": false, "title_keywords": ["specialist", "advisor", "consultant"], "responsibilities": ["design solutions"], "requirements": {"degrees": ["diploma", "degree"], "majors": ["design"], "languages": ["english", "mandarin"], "language_level": ["good"], "hard_skills": ["problem solving", "3dmax", "photoshop", "autocad"], "soft_skills": ["good team player", "work overtime", "creative", "responsible", "open-minded", "problem solving", "teamwork spirit", "time management skill", "eye for detail", "innovative", "positive"], "languages_combined": [{"language": "english", "language_level": ["good"]}, {"language": "mandarin", "language_level": ["good"]}]}, "experience_required": {"duration": ["minimum 2 years"], "field": ["retail", "design"]}}, {"job_id": "100003009049007", "location_code": "hk", "company": "M plus design & architecture consultancy (HongKong) limited", "job_title": "Senior 3D Designer", "description": "Job Description\n\nMy client is an interior design firm based in Hong Kong. They are specializing an international brand including retail and commercial design projects. The boutique locate for K11 MUSEA, 1881 Heritage, Ocean Terminal, Element Shop, Macau and China.\n\nWelcome to join our team to cope with our rapid expansion in both mainland China and Hong Kong.\n\nRequirements\n\nDiploma holder or above in Interior Design\nBasic\u00a0computer knowledge in AutoCAD\u00a0and\u00a0Photoshop are\u00a0preferable\nCapable in handling project independently for interior designer\n\nResponsible of site management, site survey,\u00a0 site staff supervision, etc.\u00a0for interior designer\n\nBasic Cantonese, English & Putonghua\nTraveling to overseas/ PRC is required\nMin 2 years site experience for interior designer\u00a0\n\nResponsibilities:\u00a0\n\nAssist the Senior Interior Designer\nDealing with clients, contractors, architectures, vendors and project team members\nResponsible for design drawings and documentation including concept design and development, construction drawing, materials sourcing and selection\nIdentify and understand clients\u2019 needs and provide customer services\n\nWe offer\u00a0double pay,\u00a0bank holidays, 5 1/2day work,\u00a0annual leave and MPF. Interested candidates please send your application letter with CV, portfolio and salary expectations by clicking 'Apply Now'", "employment_types": ["Full Time", "Permanent", "Contract"], "selling_points": ["Retail Experiential Design (VM, Pop Up etc) Exp", "Strong in 3D Max-V-Ray, AutoCAD, PS", "Creative Thinking and Design Sense"], "locations": ["Central"], "categories": ["Media & Advertising", "Creative / Design", "Design", "Interior", "Visual Merchandising"], "post_time": "2022-01-14T07:54:20Z", "salary": {"currency": "HKD", "max": 34999, "min": 30000, "period": "monthly", "term": null}, "salary_visible": true, "title_keywords": ["senior 3d designer"], "responsibilities": ["design"], "requirements": {"degrees": ["diploma holder"], "majors": ["design"], "languages": ["cantonese", "putonghua", "english"], "language_level": ["basic"], "hard_skills": ["documentation", "basic", "photoshop", "autocad"], "soft_skills": ["independently", "capable", "responsible"], "languages_combined": [{"language": "cantonese", "language_level": ["basic"]}, {"language": "putonghua", "language_level": []}, {"language": "english", "language_level": []}]}, "experience_required": {"duration": ["min 2 years"], "field": ["designer"]}}, {"job_id": "100003009048955", "location_code": "hk", "company": "M plus design & architecture consultancy (HongKong) limited", "job_title": "Advanced 3D Designer", "description": "Job Highlights:\n\n-\u00a0At least 4 years working experience in packaging & print design\n\n-\u00a0Design highly creative graphic and construction design for gift box, display box packaging, etc\n\n-\u00a0Proficient in Photoshop, Illustrator and InDesign\n\nResponsibilities:\n\n-\u00a0Manage multiple packaging \u3001 graphic design & window display graphic design projects\n\n-\u00a0Design highly creative graphic and construction design for gift box, display box packaging, etc\n\n-\u00a0Create and follow up on packaging structure design and mechanical artwork files such as die-cut drawings\n\n-\u00a0Design collateral materials for marketing or promotional needs\n\n-\u00a0Handle projects independently and communicate closely with other parties including internal departments, retail shops, external printing companies and related vendors\n\n-\u00a0Manage artwork and create display guidelines to retail shop is a must\n\nRequirements:\n\n-\u00a0Diploma or above in graphic/ packaging design\n\n-\u00a0At least 4 years working experience in packaging & print design\n\n-\u00a0Familiar with printing procedure and packaging with strong marketing sense\n\n-\u00a0Good knowledge of paper materials and print finishing effects\n\n-\u00a0Proficient in Photoshop, Illustrator and InDesign\n\n-\u00a0Able to work under pressure and meet deadlines under tight schedule\n\n-\u00a0Occasional travel overseas is required\n\nInterested parties please send resume and \u300adesign portfolio\u300b with current & expected salary to us by email.", "employment_types": ["Full Time", "Permanent", "Contract"], "selling_points": ["Retail Experiential Design (VM, Pop Up etc) Exp", "Strong in 3D Max-V-Ray, AutoCAD, PS", "Creative Thinking and Design Sense"], "locations": ["Central"], "categories": ["Media & Advertising", "Creative / Design", "Design", "Interior", "Visual Merchandising"], "post_time": "2022-01-14T07:47:32Z", "salary": {"currency": "HKD", "max": 24999, "min": 20000, "period": "monthly", "term": null}, "salary_visible": true, "title_keywords": ["designer"], "responsibilities": ["guidelines", "graphic design", "design", "drawings"], "requirements": {"degrees": ["diploma or above"], "majors": ["packaging design"], "languages": [], "language_level": [], "hard_skills": ["indesign", "illustrator", "photoshop"], "soft_skills": ["meet deadlines", "marketing sense", "work under pressure"], "languages_combined": []}, "experience_required": {"duration": ["at least 4 years"], "field": ["packaging & print design"]}}, {"job_id": "100003009036288", "location_code": "hk", "company": "Luk Fook Holdings Company Limited", "job_title": "Senior Packaging Designer in Visual Merchandising Department", "description": "Our client is looking for an Art Consultant to join their business. Ideal candidates should have an eye for design and artworks for high-end residential and hospitality projects.\n\nResponsibilities:\n\nAssist luxury hospitality and residential project from design to installation\nLiaise with the design team and clients\u00a0\nOversee and art and accessory programme\u00a0\nCreate bespoke artworks using design tools\nLiaise with studios & artists to choose and install artworks\u00a0\nKeep updated styling and accessory trends\u00a0\n\nQualifications:\n\nDegree or Diploma in Fine Arts, Applied Media or Graphic Design\n5 years of experience\nKnowledge in Microsoft Office, Photo shop, Autocad and Sketchup\nExperience in project management\u00a0\nGood presentation skills\nProficiency in English, Cantonese and Mandarin\u00a0", "employment_types": ["Full Time"], "selling_points": ["design for gift box, display box packaging, etc", "Proficient in Photoshop, Illustrator and InDesign", "4yrs working experience in packaging& print design"], "locations": ["Shatin Area"], "categories": ["Design", "Visual Merchandising"], "post_time": "2022-01-10T09:54:40Z", "salary": {"currency": null, "max": null, "min": null, "period": "monthly", "term": null}, "salary_visible": false, "title_keywords": ["merchandising", "designer"], "responsibilities": ["installation", "graphic design", "design", "project management", "liaise with"], "requirements": {"degrees": ["diploma", "degree"], "majors": ["graphic design", "fine arts"], "languages": ["cantonese", "english", "mandarin"], "language_level": ["proficiency"], "hard_skills": ["project management", "autocad", "sketchup", "microsoft office"], "soft_skills": ["project management", "presentation skills", "ideal"], "languages_combined": [{"language": "cantonese", "language_level": ["proficiency"]}, {"language": "english", "language_level": ["proficiency"]}, {"language": "mandarin", "language_level": ["proficiency"]}]}, "experience_required": {"duration": ["5 years"], "field": ["project management"]}}, {"job_id": "100003009033006", "location_code": "hk", "company": "L'Occitane (Far East) Limited", "job_title": "Graphic Designer, Visual Merchandising  (12-month Contract)", "description": "Roles & Responsibilities\n\n\n\nSupport & responsible for the graphic design and artwork development of seasonal visuals changeover, promotional displays, visual merchandising & ad-hoc event\nLiaise and coordinate with external vendors for print production and delivery\nProject support for VM initiatives including roadshow, windows & in-store display, POSM, etc.\u00a0\nAssist and support for the fixture & props delivery\nAssist and support for props sourcing & showroom setup\nRequirements\n\n\nHigher Diploma or above in graphic design or visual merchandising related discipline\nProficient in Adobe Creative Suite & design software on both Mac and PC platform\n2 years solid experience in graphic design & print production\nKnowledge of VM techniques, window set-up & in-store display is an advantage\nSelf-motivated, organized and able to manage a diversity of projects with tight schedule\nA good team player and attention to detail\nGood command of both written and spoken English and Chinese\nOccasionally work at non-office hour\nImmediately available preferred\n\n\n\nWe offer an attractive package to the right candidates. Interested parties please send detailed resume, salary history, expected salary and date available to L\u2019Occitane (Far East) Ltd.,20th Floor, K11 ATELIER King\u2019s Road, 728 King\u2019s Road, Quarry Bay, Hong Kong, or e-mail to HR Department (email address shown in our company profile).\n\n(All personal data collected will be used for recruitment purpose only.)\n\n\n\nL\u2019OCCITANE is an Equal Opportunities Employer and is committed to ensuring that factors relating to its employees\u2019 ability to perform workplace responsibilities, and to develop in their employment, are the only ones considered in the decisions about their career with L\u2019OCCITANE.\n\nBuilding a more diverse and inclusive organisational culture is one of the ways we cultivate change.\n\nThis involves building an inclusive workplace that makes our people feel:\n\nsafe from any sort of discrimination or harassment\nrespected and valued for who they are as individuals.\n\nWe recruit competent and positive minded people who share our core values entrepreneurship, team spirit, leading by example and authenticity and our commitment to sustainability.\n", "employment_types": ["Contract"], "selling_points": ["Higher Diploma in graphic design/VM", "2 yr experience in graphic design", "Proficient in Adobe Creative Suite"], "locations": ["Quarry Bay"], "categories": ["Design", "Graphics", "Visual Merchandising"], "post_time": "2022-01-08T05:48:11Z", "salary": {"currency": null, "max": null, "min": null, "period": "monthly", "term": null}, "salary_visible": false, "title_keywords": ["merchandising", "graphic designer"], "responsibilities": ["ad-hoc", "liaise", "artwork development", "graphic design", "merchandising", "coordinate with", "visual", "setup"], "requirements": {"degrees": ["higher diploma or above"], "majors": ["graphic design"], "languages": ["english", "chinese"], "language_level": ["good command"], "hard_skills": ["pc platform", "visual merchandising", "adobe creative suite"], "soft_skills": ["organized", "self-motivated", "good team player", "attention to detail", "creative"], "languages_combined": [{"language": "english", "language_level": ["good command"]}, {"language": "chinese", "language_level": ["good command"]}]}, "experience_required": {"duration": ["2 years"], "field": ["graphic design", "print"]}}, {"job_id": "100003009035096", "location_code": "hk", "company": "Kenal Group Limited", "job_title": "Assistant Project Manager / Project Manager (Event, In-store Display & Set-up)", "description": "Job Highlights\n\u00a0\u00a0\u00a0\u00a0\u00a0\u00a0\u00a0\u00a0Provide professional event management service.\n\u00a0\u00a0\u00a0\u00a0\u00a0\u00a0\u00a0\u00a0Provide professional client service and develop new account\nJob Description\n\nResponsibilities\n\n\u00a0\u00a0\u00a0\u00a0\u00a0\u00a0\u00a0\u00a0Communicate with client on event enquiry and build good relationship.\n\u00a0\u00a0\u00a0\u00a0\u00a0\u00a0\u00a0\u00a0Manage production and technical aspects of events, meetings, and exhibitions.\n\u00a0\u00a0\u00a0\u00a0\u00a0\u00a0\u00a0\u00a0Work closely with teammate and management to plan assigned projects.\n\u00a0\u00a0\u00a0\u00a0\u00a0\u00a0\u00a0\u00a0Develop and manage design, construction, and technical drawings of assigned projects with in-house designer.\n\u00a0\u00a0\u00a0\u00a0\u00a0\u00a0\u00a0\u00a0Develop production schedules for assigned projects and work accordingly with clients.\n\u00a0\u00a0\u00a0\u00a0\u00a0\u00a0\u00a0\u00a0Implement, supervise, and manage the execution for event and production on site.\n\u00a0\u00a0\u00a0\u00a0\u00a0\u00a0\u00a0\u00a0Provide cost management on event and work closely with client & management to monitor budget.\n\u00a0\u00a0\u00a0\u00a0\u00a0\u00a0\u00a0\u00a0Manage, negotiate, and coordinate with vendor.\n\u00a0\u00a0\u00a0\u00a0\u00a0\u00a0\u00a0\u00a0Evaluate vendors and partners' performance upon service delivery.\n\u00a0\u00a0\u00a0\u00a0\u00a0\u00a0\u00a0\u00a0Business development on new client accounts.\n\nRequirements\n\n\u00a0\u00a0\u00a0\u00a0\u00a0\u00a0\u00a0\u00a04+ years of event experience and specialize in production aspect.\n\u00a0\u00a0\u00a0\u00a0\u00a0\u00a0\u00a0\u00a0Skilled at technical drawing with AutoCAD would be highly preferable.\n\u00a0\u00a0\u00a0\u00a0\u00a0\u00a0\u00a0\u00a0Excellent communication and coordination skills as well as problem-solving abilities.\n\u00a0\u00a0\u00a0\u00a0\u00a0\u00a0\u00a0\u00a0Strong responsibility, self-motivated and can work under high pressure.\n\u00a0\u00a0\u00a0\u00a0\u00a0\u00a0\u00a0\u00a0Strong attention to detail coupled with the ability on multi-tasking.\n\u00a0\u00a0\u00a0\u00a0\u00a0\u00a0\u00a0\u00a0Familiar with event setup, staging, AVL equipment.\n\u00a0\u00a0\u00a0\u00a0\u00a0\u00a0\u00a0\u00a0Passionate about the job and willing to work flexible hours", "employment_types": ["Full Time", "Temporary"], "selling_points": ["project management", "supervise overall projects", "event / exhibition / in-store display"], "locations": ["Kowloon Bay"], "categories": ["Media & Advertising", "Production", "Design", "Visual Merchandising"], "post_time": "2022-01-10T05:57:12Z", "salary": {"currency": null, "max": null, "min": null, "period": "monthly", "term": null}, "salary_visible": false, "title_keywords": ["assistant project manager", "project manager"], "responsibilities": ["service delivery", "communicate with client", "management", "cost", "schedules", "budget", "monitor", "coordinate with", "design", "develop", "good relationship", "evaluate", "technical drawings", "plan"], "requirements": {"degrees": [], "majors": [], "languages": [], "language_level": [], "hard_skills": ["problem-solving", "autocad"], "soft_skills": ["flexible", "self-motivated", "coordination skills", "problem-solving", "communication", "multi-tasking", "work under high pressure", "attention to detail", "passionate about"], "languages_combined": []}, "experience_required": {"duration": ["4+ years"], "field": []}}, {"job_id": "100003009040722", "location_code": "hk", "company": "Pricerite Home Ltd", "job_title": "Assistant Interior Designer", "description": "Job Responsibilities:\n\nConceptualize design and implement home furnishing solutions, sales support areas and point of sales materials at stores\nContribute to the creation of a Showroom matrix that reflects a wide variety of styles, living situations and price levels to create a good tempo with distinct visual impressions\nStay up to date and knowledgeable about home furnishing, retailing and trends in order to generate creative ideas\nTo work on continuous improvement of store visual presentation\nCommunicate with internal parties on the design requirements for projects\nHandle ad hoc projects assigned by management\n\nJob Requirements:\n\n\n\nHigher Diploma or above in Interior Design\u00a0or related discipline\n1 - 2 years' experience in interior design or home furnishing\u00a0\nProficiency in AutoCAD, Sketchup, Photoshop, Illustrator and MS office\nGood command of both written & spoken English and Chinese\nGood communication and presentation skill\nInnovative and able to work under pressure\nPassion for about home furnishing, design and how people live at home\nAble to work in a fast retail environment, generate new ideas and concepts\nFresh graduates are welcome\n\nWe offer an attractive package commensurate with your qualifications and experience.\u00a0 Please apply with\u00a0full resume, portfolio, present and expected salary, quoting the ref. no. to the Human Resources Department, Pricerite Home Limited, 28/F Manhattan Place, 23 Wang Tai Road, Kowloon Bay, Kowloon, HK; or fax to 2820 0651 or press \"APPLY NOW\"\u00a0\n\nAll information provided by applicants will be treated in strict confidentiality and used for recruitment purpose only.\u00a0 We will retain your application for a maximum period of 6 months and may refer it to other vacancies within the Group.", "employment_types": ["Full Time", "Permanent"], "selling_points": ["AutoCAD, Sketchup, Photoshop", "Store visual presentation", "Furniture / household related industry"], "locations": ["Kowloon Bay"], "categories": ["Design", "Interior", "Visual Merchandising", "Others"], "post_time": "2022-01-12T02:59:04Z", "salary": {"currency": null, "max": null, "min": null, "period": "monthly", "term": null}, "salary_visible": false, "title_keywords": ["assistant interior designer"], "responsibilities": ["creative ideas", "management", "design", "ad hoc projects", "visual", "communicate with internal parties", "visual presentation"], "requirements": {"degrees": ["higher diploma or above"], "majors": ["design"], "languages": ["english", "chinese"], "language_level": ["good command"], "hard_skills": ["presentation skill", "sketchup", "illustrator", "autocad", "photoshop", "ms office"], "soft_skills": ["presentation skill", "passion for", "communication", "innovative", "work under pressure"], "languages_combined": [{"language": "english", "language_level": ["good command"]}, {"language": "chinese", "language_level": ["good command"]}]}, "experience_required": {"duration": ["1 - 2 years"], "field": ["design"]}}, {"job_id": "100003009041974", "location_code": "hk", "company": "Steve Leung Designers Ltd", "job_title": "FF&E Designer / Assistant FF&E Designer", "description": "Diploma or above in Interior Design/Visual Merchandising/Product Design\nRelevant working experience in show-flat, club house, retail shop design; experience in hospitality is an advantage\nFamiliar with creative styling, furniture, lighting, artwork and artifact selection\nProficient in Microsoft applications, Photoshop & AutoCAD.\nWell Organized, attention to details and good interpersonal skills\nProactive, self-motivated and work independently\nGood command of written and presentation skills in English and Mandarin\nWilling to travel\nHigh-End hospitality specification experience as a plus\nCandidate with more experience to be considered as Senior FF&E Designer\n\nJob Description\n\nCoordinate with clients,\u00a0suppliers\u00a0and contractors.\nParticipate in the whole design process, from conceptual generation to FF&E selection to installation.\nAssist in the preparation of proposals and presentation\n\nWe work on a 5-day week and offer attractive salaries, with year-end bonus and other fringe benefits including group medical insurance and MPF contribution.\n\nInterested parties please click\u00a0\u201cApply Now\u201d\u00a0to apply job with your full resume, current and expected salary.\n\nYou are welcome to visit our website:\u00a0www.steveleung.com\u00a0to have more understanding of our company.\n\nAll personal data collected will be used for recruitment purpose only.\u00a0", "employment_types": ["Full Time", "Permanent"], "selling_points": [], "locations": ["Kowloon Bay"], "categories": ["Design", "Industrial / Product", "Interior", "Visual Merchandising"], "post_time": "2022-01-12T04:57:17Z", "salary": {"currency": null, "max": null, "min": null, "period": "monthly", "term": null}, "salary_visible": false, "title_keywords": ["designer", "assistant"], "responsibilities": ["installation", "year-end", "mpf", "merchandising", "design", "coordinate with clients", "product design", "visual", "insurance"], "requirements": {"degrees": ["diploma or above"], "majors": ["design"], "languages": ["english", "mandarin"], "language_level": ["good command"], "hard_skills": ["plus", "microsoft applications", "visual merchandising", "photoshop", "autocad"], "soft_skills": ["self-motivated", "proactive", "work independently", "well organized", "presentation skills", "interpersonal skills", "attention to details", "creative", "presentation"], "languages_combined": [{"language": "english", "language_level": ["good command"]}, {"language": "mandarin", "language_level": ["good command"]}]}, "experience_required": {"duration": [], "field": ["retail", "designer", "relevant working experience", "design"]}}, {"job_id": "100003009030524", "location_code": "hk", "company": "Simplylife Limited", "job_title": "Visual Merchandiser", "description": "Job Description\n\nThe incumbent will be responsible for the design, sourcing and production of marketing promotion materials, in-store visual presentation, mix & match and ad hoc projects.\n\nResponsibilities\n\n\u00a0\u00a0\u00a0\u00a0\u00a0\u00a0\u00a0\u00a0 Work closely with marketing team and retail operation team for production and implementation of retail shops visual merchandise display, POP and mannequin styling\n\u00a0\u00a0\u00a0\u00a0\u00a0\u00a0\u00a0\u00a0 Responsible for the graphic design for various marketing campaigns and functions\n\u00a0\u00a0\u00a0\u00a0\u00a0\u00a0\u00a0\u00a0 Assist in the set-up of new shop and events\n\u00a0\u00a0\u00a0\u00a0\u00a0\u00a0\u00a0\u00a0 Regular stores visit to maintain good standard of visual merchandising presentation\n\u00a0\u00a0\u00a0\u00a0\u00a0\u00a0\u00a0\u00a0 Command VM & display training to retail staff\n\nRequirements\n\n\u00a0\u00a0\u00a0\u00a0\u00a0\u00a0\u00a0\u00a0 Diploma / Degree holder of Art or design related discipline\n\u00a0\u00a0\u00a0\u00a0\u00a0\u00a0\u00a0\u00a0 2-3 years' visual merchandising experience in retail, especially from Furniture retail is highly preferred\n\u00a0\u00a0\u00a0\u00a0\u00a0\u00a0\u00a0\u00a0 Motivated in digital & graphic\n\u00a0 \u00a0 \u00a0 \u00a0\u00a0\u00a0\ns designProficiency in Photoshop, Illustrator or other visual design tools\n\u00a0\u00a0\u00a0\u00a0\u00a0\u00a0\u00a0\u00a0 Knowledge in 3D graphic/window design\n\u00a0\u00a0\u00a0\u00a0\u00a0\u00a0\u00a0\u00a0 Demonstrates creative skills\n\u00a0\u00a0\u00a0\u00a0\u00a0\u00a0\u00a0\u00a0 Creative and independent\n\u00a0\u00a0\u00a0\u00a0\u00a0\u00a0\u00a0\u00a0 Good communication and interpersonal skills", "employment_types": ["Full Time", "Permanent"], "selling_points": [], "locations": ["Kwai Tsing Area"], "categories": ["Design", "Interior", "Multi-media", "Visual Merchandising"], "post_time": "2022-01-07T07:39:22Z", "salary": {"currency": null, "max": null, "min": null, "period": "monthly", "term": null}, "salary_visible": false, "title_keywords": ["visual merchandiser"], "responsibilities": ["graphic design", "merchandising", "implementation", "design", "maintain", "ad hoc projects", "marketing campaigns", "visual", "visual presentation"], "requirements": {"degrees": ["diploma", "degree holder"], "majors": ["art", "design"], "languages": [], "language_level": [], "hard_skills": ["visual design", "visual merchandising", "illustrator", "photoshop"], "soft_skills": ["motivated", "independent", "creative", "communication and interpersonal skills"], "languages_combined": []}, "experience_required": {"duration": ["2-3 years"], "field": ["retail", "merchandising"]}}, {"job_id": "100003009029761", "location_code": "hk", "company": "CDF Hong Kong Downtown Duty Free Shop Limited", "job_title": "Visual Merchandising Manager", "description": "Responsibilities:\n\nReport directly to the General Manager\nSupervise Visual Merchandising Team for beauty & liquor entities\nDevelop and implement visual merchandising strategies, policies, and processes to support and expand both beauty & liquor retail presence in both online/offline\nCreate, design, develop, and implement all types of VM plans and materials for in-store and digital displays (e.g., signages, props, etc.)\nDesign and execution of small-scale pop-up store, in-store set up, special events, and campaign launch\nLead and maintain the team's work efficiency and quality\nCollaborate closely with brands and internal departments (Merchandising, Marketing, Retail operations) to complete display projects from concept to completion, ensuring that all deadlines, budgets, and quality standards are met\n\nRequirements:\n\nDegree in Visual Merchandising or Design related disciplines\nMinimum 7 years solid experience in visual merchandising with at least 3 years at supervisory level, preferably from the retail or mall industry\nStrong conceptual thinking in both visual and interactive visual; good sense of photography\nSelf-motivated, detail-minded, strong sense of responsibility, good communication skills and supervisory skills\nAble to handle multiple tasks with tight deadlines in a fast-paced environment and work under pressure\nFamiliar with Photoshop, Illustrator, InDesign is a must\nGood command of English and Chinese\n\nTo learn more about our company, please visit our website\u00a0and\u00a0http://www.cdfg.com.cn/\n\nWe offer 5-day work week, competitive salary and fringe benefits to the right candidate. Interested parties please apply with full resume with current and expected salary\u00a0by clicking \"Apply Now\".\n\nAll information provided by applicants will be treated in strict confidence and used for recruitment purpose only. All personal data of unsuccessful applicants will be retained for 6 months for future recruitment purpose and will then be destroyed.", "employment_types": ["Full Time", "Permanent"], "selling_points": ["Annual Performance Bonus, Transport Allowance", "Support Beauty & Liquor entities", "Develop and implement VM strategies"], "locations": ["Airport Area"], "categories": ["Design", "Graphics", "Visual Merchandising", "Others"], "post_time": "2022-01-07T06:07:46Z", "salary": {"currency": null, "max": null, "min": null, "period": "monthly", "term": null}, "salary_visible": false, "title_keywords": ["visual merchandising manager"], "responsibilities": ["collaborate", "budgets", "policies", "operations", "merchandising", "quality", "design", "develop", "maintain", "visual", "plans", "report"], "requirements": {"degrees": ["degree"], "majors": ["related disciplines", "design"], "languages": ["english", "chinese"], "language_level": ["good command"], "hard_skills": ["visual merchandising", "indesign", "illustrator", "photoshop"], "soft_skills": ["detail-minded", "communication skills", "self-motivated", "sense of responsibility", "fast-paced environment", "handle multiple tasks", "work under pressure"], "languages_combined": [{"language": "english", "language_level": ["good command"]}, {"language": "chinese", "language_level": ["good command"]}]}, "experience_required": {"duration": ["at least 3 years", "minimum 7 years"], "field": ["supervisory level", "retail", "merchandising"]}}, {"job_id": "100003009038206", "location_code": "hk", "company": "Talentus Group HK Limited", "job_title": "Senior Store Creative & Architectural Manager, APAC - Fashion Retail", "description": "About the Company\u00a0\n\nOur client is\u00a0a listed international fast fashion retailer that is continuing to expand across Asia.\u00a0To cope with\u00a0business needs,\u00a0management is looking for a Senior Store Creative &\u00a0Architectural Manager\u00a0to\u00a0lead the Asia Pacific store visual localisation project.\n\n\nAbout the Role\n\nReporting to the Senior Retail Director of APAC,\u00a0your mission will be to uplift the customer journey through adapting and enhancing the creative visual concept of existing doors in accordance to the geographical location it is based in. You will be in charge of the creative & decorative aspect of stores (interior store display) while working coherently with Visual Merchandising team (Product Display), and Store Project teams to ensure the overall visual results are enhanced while retaining the brand\u2019s original DNA.\n\nOur\u00a0client will be expecting the Senior Store Development Manager\u00a0to bring in a new visually impactful shopping experience for its shoppers in Asia. You will be responsible for the store visual concept, store layout design, fixture design, production, delivery and installation.\n\nRequirements:\u00a0\n\nArchitecture / Interior Design / Engineering degree holder with a proven track record of success with any sizeable retail\u00a0MNCs\nMinimal of\u00a07\u00a0years relevant working experience with at least\u00a02\u00a0years\u00a0at a\u00a0managerial\u00a0level\nExcellent sense of visual, design, style and aesthetic\nGood business acumen and understanding towards\u00a0the Asia retail\u00a0markets and its unique geographical culture\u00a0\nAbility to communicate and collaborate\u00a0with\u00a0multiple stakeholders\nProficient in design softwares such as\u00a0Illustrator, Photoshop, AutoCAD, 3Ds Max, etc.\nExcellent verbal and written English, Mandarin and Cantonese (any other spoken language will be an advantage)\n\nInterested parties, please apply directly with your most updated resume, latest and expected salary package.\u00a0Referral programs are available.\u00a0\n\n\nNote: All information collected will be kept in strict confidence and will be used for recruitment purpose only.", "employment_types": ["Full Time"], "selling_points": ["International MNC regional role", "Develop and lead ongoing store visuals", "Drive a new shopping journey for Asia"], "locations": ["Not Specified"], "categories": ["Sales, CS & Business Devpt", "Business Development", "Design", "Interior", "Visual Merchandising"], "post_time": "2022-01-11T06:37:04Z", "salary": {"currency": "HKD", "max": 89999, "min": 70000, "period": "monthly", "term": null}, "salary_visible": true, "title_keywords": ["creative", "manager"], "responsibilities": ["collaborate with", "reporting", "management", "installation", "layout design", "merchandising", "teams", "design", "visual", "architecture"], "requirements": {"degrees": ["degree holder"], "majors": ["architecture", "engineering", "design"], "languages": ["cantonese", "english", "mandarin"], "language_level": ["advantage", "excellent"], "hard_skills": ["3ds max", "design softwares", "visual merchandising", "illustrator", "acumen", "autocad", "photoshop"], "soft_skills": ["business acumen", "unique", "creative", "responsible"], "languages_combined": [{"language": "cantonese", "language_level": ["excellent"]}, {"language": "english", "language_level": ["advantage", "excellent"]}, {"language": "mandarin", "language_level": ["advantage", "excellent"]}]}, "experience_required": {"duration": ["at least 2 years", "of 7 years"], "field": ["development", "relevant working experience", "managerial"]}}, {"job_id": "100003009035028", "location_code": "hk", "company": "\u5167\u598d\u7f8e\u6709\u9650\u516c\u53f8", "job_title": "\u5e73\u9762\u53ca\u591a\u5a92\u9ad4\u8a2d\u8a08\u5e2b", "description": "\u81ea2015\u5e74\u6210\u7acb\uff0cyanis beauty\u6fc0\u5149\u812b\u6bdb\u7642\u7a0b\uff0c\u7372\u7f8e\u570bFDA\u53ca\u6b50\u76dfCE\u8a8d\u8b49\u80fd\u5fb9\u5e95\u6839\u9664\u6bdb\u9aee\uff0c\u4e26\u4e0d\u65b7\u5f15\u5165\u5148\u9032\u6280\u8853\u3002\nYanis beauty \u5229\u7528Gentlelase pro 755\u6fc0\u5149\u6ce2\u9577\u812b\u6bdb\u6280\u8853\uff0c\u4f7f\u7528\u539f\u5ee0\u51b7\u51cd\u6280\u8853\u3002\n\n\u5e73\u9762\u53ca\u591a\u5a92\u9ad4\u8a2d\u8a08\u5e2b\n\n\u8077\u8cac:\n\u8ca0\u8cac\u5e73\u9762\u8a2d\u8a08\u3001\u591a\u5a92\u9ad4\u8a2d\u8a08\u3001FACEBOOK\u5ee3\u544a\u904b\u4f5c\u53ca\u526a\u7247\u7b49\u5de5\u4f5c\n\u5305\u62ec\u793e\u4ea4\u5a92\u9ad4\u3001\u5ee3\u544a\u3001\u7522\u54c1\u6587\u5b57\u8a2d\u8a08\u53ca\u63d2\u756b\u8a2d\u8a08\n\u8ca0\u8cac\u652f\u63f4\u5e02\u5834\u63a8\u5ee3\u90e8\u5de5\u4f5c\n\n\u8981\u6c42:\n\u9700\u8981\u4e00\u5e74\u6216\u4ee5\u4e0a\u76f8\u95dc\u5de5\u4f5c\u7d93\u9a57;\n\u826f\u597d\u7cb5\u8a9e\uff0c\u4e00\u822c\u82f1\u8a9e\n\u826f\u597d\u8b80\u5beb\u4e2d\u6587\uff0c\u61c2\u8b80\u5beb\u82f1\u6587\n\u719f\u6089PhotoShop , AfterEffect , Premiere Pro, AI , InDesign ,\n\u5c0d\u5de5\u4f5c\u8a8d\u771f\u8ca0\u8cac\uff0c\u5de5\u4f5c\u6548\u7387\u9ad8\n\u61c2\u82f1\u6587\u6253\u5b57 , \u4e2d\u82f1\u6587\u96fb\u8166\u64cd\u4f5c , \u4e2d\u6587\u6253\u5b57 , \u61c2\u651d\u5f71 , \u61c2\u62cd\u7247\u53ca\u61c2\u526a\u7247.\n\u91cd\u8996\u5718\u9ad4\u5408\u4f5c\u7cbe\u795e\uff0c\u7a4d\u6975\u6709\u79ae\u3001\u5bcc\u8cac\u4efb\u5fc3\u53ca\u5b88\u6642\n\n\u6709\u85aa\u5e74\u5047 7\u5929\u8d77\n\u751f\u65e5\u5047\u671f\n\u6bcf\u5929\u5de5\u4f5c9\u5c0f\u6642\n\u6709\u85aa\u5728\u8077\u57f9\u8a13\u53ca\u826f\u597d\u6649\u5347\u6a5f\u6703\n\u9ad8\u9054\u6a19\u734e\u91d1\n\u8d85\u6642\u88dc\u9418\n\u54e1\u5de5\u8cfc\u7269\u548c\u7642\u7a0b\u512a\u60e0\n\u54e1\u5de5\u65c5\u884c\n\n\u6709\u610f\u61c9\u5fb5\u8005\uff0c\u8acb\u5c07\u500b\u4eba\u5b8c\u6574\u7c21\u6b77\uff0c\u5305\u62ec\u60a8\u9810\u671f\u7684\u85aa\u916c Whatsapp 56026466 Ms Li\uff08\u6c42\u8077\u8005\u905e\u4ea4\u500b\u4eba\u8cc7\u6599\u53ea\u4f5c\u62db\u8058\u7528\u9014\uff0c\u6240\u6709\u8cc7\u6599\u7d55\u5c0d\u4fdd\u5bc6)", "employment_types": ["Full Time"], "selling_points": ["\u751f\u65e5\u5047\u671f", "\u8d85\u6642\u88dc\u9418", "PhotoShop , AfterEffect , Premiere Pro, AI , InDes"], "locations": ["Mong Kok"], "categories": ["Design", "Multi-media", "Visual Merchandising", "Beauty Care / Health", "Others"], "post_time": "2022-01-10T05:25:44Z", "salary": {"currency": null, "max": null, "min": null, "period": "monthly", "term": null}, "salary_visible": false, "title_keywords": [], "responsibilities": [], "requirements": {"degrees": [], "majors": [], "languages": [], "language_level": [], "hard_skills": ["whatsapp", "indesign", "premiere pro", "ai"], "soft_skills": [], "languages_combined": []}, "experience_required": {"duration": [], "field": []}}, {"job_id": "100003009018522", "location_code": "hk", "company": "Pandora Jewelry Asia-Pacific Limited", "job_title": "Visual Merchandiser", "description": "About the position:\n\nThe aim of this role is to ensure PANDORA window and in store displays are consistent with global PANDORA visual merchandising guidelines in order to maximize sales and PANDORA branding\n\nJob Responsibilities:\n\n\nOversee all visual merchandising activities for all the stores in Hong Kong and Macau\nWork cross functionally and develop structure VM guideline to ensure VM plan ties with brand strategies\nCreate visually inspiring in-store and window displays which reflect and maintain PANDORA brand identity, by displaying merchandise according to global visual merchandising guidelines, ensure all products and displays are executed to high standards\nCoordination with suppliers on campaign materials and props production, and liaise with production house and landlord for seasonal window installation\nPlan schedule to meet the needs of the business, arrange store visits to ensure proper execution for windows change and product launch\u00a0\nDevelop and conduct VM training to Pandora staffs and wholesales partners, in order to achieve execution excellence and store image consistency base on Pandora guidelines and store profile\nWork closely with stores operation team and stores team to update display bases on individual store profile such as bestsellers, price points, base activation etc.\u00a0\nPrepare budget for visual merchandising activities and process related payment and control expenses for cost effectiveness\nConsolidate individual stores VM reports and market orders for wholesalers\nDevelop and implement displays for special events as directed by management\nQualifications & Experience:\u00a0\n\n\nDegree in Design, Marketing or Visual Merchandising or related experience\nMinimum 2-3 years of experience in visual merchandising with regional exposure, preferably within jewellery, accessories brand\nProficient in MS Office, Adobe Creative Suite, Photoshop is an advantage\nExcellent command of both spoken and written English\nSelf-driven and able to work independently with minimum supervision\nProactive, organized and detail-minded\nA good team player with excellent interpersonal and communication skills\nThrives in a fast-pace work environment and can work with tight deadlines and under pressure\nA creative flair with an eye for style\n\nSHINE WITH US.\n\nWe want to become the world\u2019s most loved jewelry brand. Come join us.\nDue to the high volume of applications, only shortlisted candidates will be notified. If you are not contacted by us within 6 weeks, please consider your application unsuccessful. All data collected would be used for recruitment purpose only.\u00a0", "employment_types": ["Full Time", "Permanent"], "selling_points": ["Oversee all VM activities", "2-3 yrs of experience in VM with regional exposure", "Permanent role, 5 days work per week"], "locations": ["Tsim Sha Tsui"], "categories": ["Design", "Visual Merchandising", "Others", "Sales, CS & Business Devpt", "Retail Sales"], "post_time": "2022-01-04T03:49:37Z", "salary": {"currency": null, "max": null, "min": null, "period": "monthly", "term": null}, "salary_visible": false, "title_keywords": ["visual merchandiser"], "responsibilities": ["brand strategies", "merchandising", "coordination with", "budget", "design", "communication", "payment", "maintain", "plan", "liaise with", "control", "expenses", "develop", "reports", "schedule", "visual", "installation", "merchandising guidelines", "cost", "management", "guidelines"], "requirements": {"degrees": ["degree"], "majors": ["marketing", "design"], "languages": ["english"], "language_level": ["excellent"], "hard_skills": ["photoshop", "visual merchandising", "adobe creative suite", "ms office"], "soft_skills": ["detail-minded", "organized", "work independently", "proactive", "good team player", "communication skills", "under pressure", "interpersonal", "inspiring", "coordination", "creative", "driven"], "languages_combined": [{"language": "english", "language_level": ["excellent"]}]}, "experience_required": {"duration": ["minimum 2-3 years"], "field": ["brand", "related", "merchandising", "design", "marketing"]}}, {"job_id": "100003009034864", "location_code": "hk", "company": "The Brand Agency Limited", "job_title": "Senior Graphic Designer / Graphic Designer", "description": "To cope with our business expansion, we are now inviting candidates of high caliber for the following position:\n\n\u00a0\u00a0Senior Graphic Designer / Graphic Designer\u00a0\n\nJob Responsibilities:\n\n\nResponsible from concept development, artwork output and production for brands and corporate projects\nDevelop and execute graphic, digital and VM design to support marketing campaigns, online and offline stores\nMonitor design and VM budget\nWork closely with Principal, internal, and external parties to ensure design and production are properly delivered as per guidelines and timelines\nSupport ad-hoc projects when required\n\nJob Requirements:\n\n\nHigher Diploma or above in Design or other related disciplines\nMin 3 years related experience\nExposure in retail brand and eCommerce will be definite advantage\nProficient in MAC software including InDesign, Illustrator, Photoshop etc\nIndependent, Detail-oriented, Great communication skills and can work under pressure\nGood command of English and Chinese\u00a0\nCandidate with less experience will be considered as Graphic Designer\nWe offer a 5-day work week, health Insurance and an attractive remuneration package with career development opportunities.\n\n\nInterested parties please send your CV and portfolio with salary history and expected salary through APPLY NOW. Any applications without a portfolio will not be considered.\n\n(All personal data collected will be used for recruitment purpose only)", "employment_types": ["Full Time"], "selling_points": ["Develop and execute creative concept", "Design to support online and offline stores", "Higher Diploma or above in Design"], "locations": ["North Point"], "categories": ["Design", "Fashion", "Graphics", "Visual Merchandising"], "post_time": "2022-01-10T04:26:40Z", "salary": {"currency": null, "max": null, "min": null, "period": "monthly", "term": null}, "salary_visible": false, "title_keywords": ["senior graphic designer", "graphic designer"], "responsibilities": ["guidelines", "budget", "monitor", "external parties", "design", "develop", "marketing campaigns", "ad-hoc projects", "artwork output"], "requirements": {"degrees": ["higher diploma or above"], "majors": ["related disciplines", "design"], "languages": ["english", "chinese"], "language_level": ["good command"], "hard_skills": ["indesign", "illustrator", "photoshop"], "soft_skills": ["work under pressure", "communication skills", "independent", "detail-oriented"], "languages_combined": [{"language": "english", "language_level": ["good command"]}, {"language": "chinese", "language_level": ["good command"]}]}, "experience_required": {"duration": ["min 3 years"], "field": ["related", "graphic", "designer"]}}, {"job_id": "100003009019976", "location_code": "hk", "company": "Xiaomi H.K. Limited", "job_title": "\u9673\u5217\u4e3b\u7ba1/\u7d93\u7406 (Visual Merchandiser Supervisor/Manager)", "description": "\u8077\u8cac\n\n- \u7ba1\u7406\u9999\u6e2f\u5404\u92b7\u552e\u6e20\u9053\u3001\u7c73\u5bb6\u53ca\u7c73\u5e97\u7684\u9673\u5217\u6548\u679c\n- \u5b9a\u671f\u5de1\u67e5\u5404\u92b7\u552e\u6e20\u9053\u3001\u7c73\u5bb6\u53ca\u7c73\u5e97\uff0c\u8a55\u6838\u9673\u5217\u6210\u6548\n- \u5354\u52a9\u5718\u968a\u7dad\u6301\u826f\u597d\u5de5\u4f5c\u6548\u7387\uff0c\u78ba\u4fdd\u9673\u5217\u7b26\u5408\u4f01\u696d\u6e96\u5247\uff0c\u512a\u5316\u54c1\u724c\u5f62\u8c61\n- \u6839\u64da\u516c\u53f8\u7684\u6e96\u5247\uff0c\u70ba\u5404\u6a23\u7522\u54c1\u53ca\u670d\u52d9\u5236\u5b9a\u9673\u5217\u65b9\u6848\uff0c\u78ba\u4fdd\u9673\u5217\u7b56\u7565\u8207\u5e02\u5834\u71df\u92b7\u8a08\u5283\u4e00\u81f4\n- \u7d71\u7c4c\u9673\u5217\u7269\u8cc7\u53ca\u5ba3\u50b3\u7269\u6599\uff0c\u5354\u52a9\u57f7\u884c\u843d\u5be6\u9673\u5217\u8a08\u5283\uff0c\u4e26\u8a08\u5283\u9805\u76ee\u6210\u672c\u53ca\u5354\u52a9\u9673\u5217\u9810\u7b97\n- \u958b\u62d3\u53ca\u6301\u7e8c\u512a\u5316\u9673\u5217\u7269\u6599\u548c\u9053\u5177\uff0c\u4e26\u63a7\u5236\u6210\u672c\u65bc\u9810\u7b97\u7bc4\u570d\u5167\n- \u5e36\u9818\u5404\u9580\u5e97\u7684\u9673\u5217\u54e1\u5de5\u57f7\u884c\u9673\u5217\u8a08\u5283\u548c\u5de5\u4f5c\uff0c\u63d0\u5347\u5718\u968a\u6210\u54e1\u7684\u9673\u5217\u6280\u5de7\u53ca\u77e5\u8b58\n\n\n\n\n\u8981\u6c42\n\n- \u5927\u5b78\u5b78\u4f4d\u6301\u6709\u8005\uff0c\u53ca\u51775\u5e74\u6216\u4ee5\u4e0a\u76f8\u95dc\u7d93\u9a57\uff0c\u6709\u96f6\u552e\u696d\u524d\u7dda\u7d93\u9a57\u8005\u512a\u5148\u8003\u616e\n- \u80fd\u64cd\u4f5cAdobe Photoshop\u3001Illustrator\u3001MS Office\u53ca\u5176\u4ed6\u76f8\u95dc\u8edf\u4ef6\uff0c\u4e26\u61c2\u4e2d\u6587\u8f38\u5165\u6cd5\n- \u64c1\u6709\u826f\u597d\u7684\u8868\u9054\u80fd\u529b\uff0c\u6d41\u5229\u5ee3\u6771\u8a71\uff0c\u826f\u597d\u82f1\u8a9e\u3001\u666e\u901a\u8a71\n- \u5c0a\u91cd\u5718\u968a\u7cbe\u795e\u3001\u61c2\u5f97\u63a5\u7d0d\u610f\u898b\u3001\u6709\u5275\u696d\u7cbe\u795e\u3001\u6709\u4e0a\u9032\u5fc3\u3001\u9858\u610f\u4e0d\u65b7\u5b78\u7fd2", "employment_types": ["Full Time", "Permanent"], "selling_points": ["Bachelor Degree", "5 years experience", "passionate in retail industry"], "locations": ["Tsim Sha Tsui"], "categories": ["Design", "Visual Merchandising"], "post_time": "2022-01-04T09:37:06Z", "salary": {"currency": null, "max": null, "min": null, "period": "monthly", "term": null}, "salary_visible": false, "title_keywords": ["\u7d93\u7406", "visual merchandiser", "supervisor", "manager"], "responsibilities": [], "requirements": {"degrees": [], "majors": [], "languages": [], "language_level": [], "hard_skills": [], "soft_skills": [], "languages_combined": []}, "experience_required": {"duration": [], "field": []}}, {"job_id": "100003009051397", "location_code": "hk", "company": "Raze Technology Limited", "job_title": "Graphic Designer", "description": "The Role\nWe are looking for a creative and passionate Graphic Designer to join our team.\u00a0\u00a0You will have a chance to work at a fast-paced mission driven company that brings material science to life and benefit the mass.\u00a0 We are bringing business disruption and new hygiene standard to the world with the introduction of new photocatalyst products and services. With the continuous R&D and business innovation, we are thrilled to develop the next generation technology that safeguards everyday life.\u00a0 Raze Technology is the world's leading photocatalyst solution company, developing a long-lasting disinfectant coating.\n\nResponsibilities\nResponsible for creative concept development and handle all stages of design include but not limited to the following:\u00a0\n\n\nSocial media visual and feed designs (Facebook, Instagram, eDM, Google ad, etc.);\u00a0\nOnline store visual (Web banner, product page, etc);\u00a0\nSales kit and POP materials;\nProduct retouching and mock-ups;\u00a0\nPerform ad-hoc projects as assigned.\n\nRequirements\n\n\nDiploma or above in Graphic Design/ Multimedia/ Creative Media or other related disciplines;\nAt least 3 years relevant working experience in graphic design, FMCG or digital marketing agency experience is preferred;\nProficient in using Adobe Illustrator, Photoshop in Mac environment;\u00a0\nProficient in animation and video editing is a plus;\nGood team player, multi-tasking and responsible;\nVisual merchandising experience is an advantage;\u00a0\nImmediate availability is highly preferable.\n\nWe offer the right candidate attractive remuneration package and outstanding prospects for career advancement and development.\u00a0 The right candidate will progress career in a forward thinking and dynamic business with exciting growth plans.\u00a0 If you are qualified and interested, please send your full resume with current & expected salary and availability by clicking \"APPLY\".\n\nAll information collected will be treated as strictly confidential and used for recruitment purposes only. (Only shortlisted candidates will be notified)", "employment_types": ["Full Time", "Part Time", "Permanent", "Temporary", "Contract", "Freelance"], "selling_points": [], "locations": ["Southern Area"], "categories": ["Design", "Graphics", "Multi-media", "Visual Merchandising"], "post_time": "2022-01-15T14:27:50Z", "salary": {"currency": null, "max": null, "min": null, "period": "monthly", "term": null}, "salary_visible": false, "title_keywords": ["graphic designer"], "responsibilities": ["pop materials", "edm", "product retouching", "mock-ups", "social media visual and feed designs", "design", "visual", "facebook", "ad-hoc projects", "sales kit"], "requirements": {"degrees": ["diploma or above"], "majors": ["related disciplines", "graphic design", "creative media"], "languages": [], "language_level": [], "hard_skills": ["plus", "mac environment", "visual merchandising", "adobe illustrator", "multimedia", "animation and video editing", "photoshop"], "soft_skills": ["good team player", "creative", "multi-tasking", "responsible"], "languages_combined": []}, "experience_required": {"duration": ["at least 3 years"], "field": ["fmcg", "agency", "graphic design", "merchandising", "relevant working experience", "digital marketing"]}}, {"job_id": "100003009047471", "location_code": "hk", "company": "Lush Asia Limited", "job_title": "Design Specialist", "description": "LUSH\u00a0Fresh Handmade Cosmetics\u00a0Needs\u00a0YOU!\u00a0\u00a0LUSH is an international retailer of fresh handmade cosmetics that is known worldwide for changing the face, body and soul of the cosmetics industry. Our unique bath and beauty products, amazing skin and hair care, personalized customer service, environmental activism and fun and unique atmosphere make LUSH a truly unique and inspirational place to work.\n\nDRIVE SALES, TAKE OPPORTUNITIES, DEVELOP TEAMS\n\nWe are looking for a\u00a0Design Specialist, based in Hong Kong, to join the company and work with our brand communications team. If you\u2019re ambitious with a desire to succeed in a fast-paced, exciting environment then that\u2019ll help too!\u00a0\n\n\nKey responsibilities and duties\n\n\nCreative\n\nActively contributes creative ideas and briefs for all branded platforms.\nLead and drive a range of creative and branding projects together with the brand team, including PR and event, content, ethical campaigns, and marketing activities. Develop and execute creative concepts across print and video etc.\nWork closely with retail, digital, and brand teams to define the best way to communicate brand messages and content.\nLead the monthly retail shop window projects, creating impactful artwork that can attract attention, drive footfall into our stores and help develop a meaningful customer journey inside the store.\nPitch the creative brief for each design project effectively and take on feedback to refine the project scope.\u00a0\u00a0\nContribute to the review and evaluation of each design project and bring insight and learnings to the team.\u00a0\nBasic understanding of Lush Visual Merchandising Guidelines and the ability to contribute to store and pop-up displays.\nMarketing\n\nManage the Lush Times and any branded publication projects.\nDevelop and execute creative directions for marketing communications projects. Lead development of designs.\u00a0\nContribute ideas for retail marketing design and review the impact of these design works.\nTo work closely with the multimedia designer on any crossover projects for the brand.\nBrand Support\n\nWork closely with the global and regional designer to develop, update and manage visual/style guidelines for brand consistency.\nManage the budget of design discipline and contribute to the whole brand communications budget\u00a0\u00a0\nTo support the company on all design elements, including quotation, negotiation with vendors, budget, production for the internal and external company events, activities and projects.\u00a0\nTo work on any ad-hoc projects required by the senior management.\n\nTo be successful in this role, you will be expected to have the following attributes\n\nRequirement\u00a0\n\nDegree/Higher Diploma holder in Graphic/ Web Design/ Multimedia Design or related discipline\nFamiliar with Photoshop, Adobe Acrobat, Illustrator and Premiere Pro\nWell organized, mature, highly responsible and independent\nGood communication skills\nCreative mind with the ability to reflect on projects from both a practical and financial viewpoint.\nExcellent writing skills in both English & Chinese.\nMinimum 5 years of design work experience preferred.\nPortfolio link should be provided in the resume.\u00a0\u00a0\nSkills\nStrong communication and interpersonal skills\nBeing resilient at work\nSolutions focused mindset\nEffective time management\nQuick to adapt to new situations and directions\nBeing responsible and detail-minded\nExcellent feedback and coaching skills.\u00a0Able to take on and use developmental feedback\nConfidence in handling difficult conversations\nTreat all colleagues as equals and value all opinions\nProfessional performance management\nExcellent self discipline\nWhat we offer\n\n5-day per week\nA fun and dynamic place to work\nOpportunities to develop\nComprehensive training\nCompetitive salary\nMedical insurance coverage\n\nDoes this sound like you? Please apply by submitting a CV and covering letter to us.\n", "employment_types": ["Full Time"], "selling_points": ["Creative", "Marketing", "Brand Support"], "locations": ["Lai Chi Kok"], "categories": ["Design", "Graphics", "Multi-media", "Visual Merchandising"], "post_time": "2022-01-14T04:01:19Z", "salary": {"currency": null, "max": null, "min": null, "period": "monthly", "term": null}, "salary_visible": false, "title_keywords": ["design specialist"], "responsibilities": ["creative ideas", "merchandising guidelines", "ideas", "guidelines", "review", "teams", "budget", "design", "develop", "quotation", "visual", "evaluation", "brand consistency", "ad-hoc projects", "publication", "senior management"], "requirements": {"degrees": ["degree", "higher diploma holder"], "majors": ["multimedia design", "web design"], "languages": ["english", "chinese"], "language_level": ["excellent"], "hard_skills": ["web design", "illustrator", "writing skills", "multimedia", "premiere pro", "adobe acrobat", "photoshop"], "soft_skills": ["detail-minded", "communication skills", "confidence", "independent", "responsible", "focused", "well organized", "mature", "writing skills", "time management", "communication and interpersonal skills", "creative"], "languages_combined": [{"language": "english", "language_level": ["excellent"]}, {"language": "chinese", "language_level": ["excellent"]}]}, "experience_required": {"duration": ["minimum 5 years"], "field": ["design"]}}, {"job_id": "100003009044996", "location_code": "hk", "company": "Framis Italia HK Limited", "job_title": "JUNIOR GRAPHIC DESIGNER", "description": "Framis Italia is the leading provider of innovative, high quality and fully integrated solutions in thermo adhesive polyurethane applications with a 360\u00b0 approach to the technology by supplying films, tapes and machines to international top brands and their partner manufacturers.\n\nThe Company is growing and needs a Graphic designer who is passionate about the fashion world and up to date regarding current design trends and best practices for both print and digital.\n\nThe candidate will report to the Product Manager, and the mainly responsibilities will include executing on creative briefs for printed and digital collateral; create brand guidelines, collaborating on product campaigns.\n\nJob Descriptions:\n\nWork together with Product Manager on new projects from concept to graphic design and artwork adaptation\nConcept and execute design and branding elements including but not limited to look books, logo/branding design, patterns, application examples.\nResearch on trends and tendencies in the fashion context to develop potential new ideas.\nDesign and develop printed invitations to events and tradeshows, postcards, press releases\nSupport production team in reviewing customer\u2019s artwork layouts\nStrong knowledge of all relevant artwork software: Illustrator, AI, Photoshop\n\nInterested parties please send email with CV via \" Apply Now\".", "employment_types": ["Full Time"], "selling_points": ["Strong knowledge of all relevant artwork software", "Illustrator, AI, Photoshop", "Look books, logo/branding design, patterns"], "locations": ["Kwai Fong"], "categories": ["Design", "Graphics", "Industrial / Product", "Visual Merchandising"], "post_time": "2022-01-13T07:16:49Z", "salary": {"currency": null, "max": null, "min": null, "period": "monthly", "term": null}, "salary_visible": false, "title_keywords": ["junior graphic designer"], "responsibilities": ["ideas", "software", "graphic design", "quality", "design and develop", "design", "develop", "executing", "brand guidelines", "design trends", "report"], "requirements": {"degrees": [], "majors": [], "languages": [], "language_level": [], "hard_skills": ["photoshop", "logo", "illustrator", "ai"], "soft_skills": ["innovative", "creative", "passionate about"], "languages_combined": []}, "experience_required": {"duration": [], "field": []}}, {"job_id": "100003009033781", "location_code": "hk", "company": "SEN Construction Company Limited", "job_title": "Interior Designer / Assistant Interior Designer", "description": "Responsibilities:\n\nPropose and execute VM display on a weekly basis\nDeliver a high standard of visual display and align with the brand's guideline\nDesign and execute all graphic designs: eDMs, in-store signage, web banner, and social media graphics\nDesign and execution of Pop-Up Store, in-store set up, special events, and campaign launch\nNegotiate with vendors for cost efficiency\nSourcing of props & VM equipment for in-store display\nWork closely with headquarter for visual development and execution\n\nRequirement:\n\nDegree or diploma holder in Visual Merchandising, Art & Design or other design related discipline\nProficient in Photoshop, Illustrator, InDesign and Multimedia software\nMinimum 3-4 years\u2019 experience in visual merchandising and graphic design in shopping mall, department store and F&B will be an advantage\nPhotography, photo retouching and video editing skills will be an advantage\nStrong interpersonal and communication skills\nSelf-motivated, organized and able to work with tight schedule\nGood command of both written and spoken English and Chinese\nImmediate available is highly preferred\n\n\n\n\nWe offer attractive remuneration package to the right candidate. Please apply with full resume stating present and expected salaries to Group Human Resources Department, 11/F., 68 Yee Wo Street, Causeway Bay, Hong Kong or by fax to 2895 5766.\n\nAll personal data/information provided by applicants to 8D International Limited is used for recruitment and related purpose(s) only.\n\nWe are an equal Opportunities Employer.", "employment_types": ["Full Time"], "selling_points": ["\u505a\u5927\u54c1\u724c\u5e97\u8216\u88dd\u4fee\u8a2d\u8a08, \u589e\u52a0\u500b\u4eba\u7d93\u9a57\u503c", "Double pay", "\u7531\u4e2d\u74b0\u6e2f\u9435\u5230\u516c\u53f8, \u53ea\u8981\u6b65\u884c5\u5206\u9418"], "locations": ["Central"], "categories": ["Design", "Interior", "Visual Merchandising", "Others"], "post_time": "2022-01-10T01:47:33Z", "salary": {"currency": "HKD", "max": 34999, "min": 14000, "period": "monthly", "term": null}, "salary_visible": true, "title_keywords": ["interior designer", "assistant interior designer"], "responsibilities": ["graphics", "social media", "cost", "edms", "graphic designs", "design", "visual"], "requirements": {"degrees": ["diploma holder", "degree"], "majors": ["art", "design"], "languages": ["english", "chinese"], "language_level": ["good command"], "hard_skills": ["visual merchandising", "indesign", "illustrator", "video editing", "multimedia", "photoshop"], "soft_skills": ["organized", "communication skills", "self-motivated", "interpersonal"], "languages_combined": [{"language": "english", "language_level": ["good command"]}, {"language": "chinese", "language_level": ["good command"]}]}, "experience_required": {"duration": ["minimum 3-4 years"], "field": ["graphic design", "f&b", "merchandising"]}}, {"job_id": "100003009036952", "location_code": "hk", "company": "Eventist Hong Kong Limited", "job_title": "3D Designer / Senior 3D Designer", "description": "Associate Creative Director / Senior Designer WANTED: Creative souls only!\nYou must have answered all yes and curious enough to scroll and explore. The long wait is over, you creative and non-conforming soul!\n\nNoiseless Design\u00a0is a multi-disciplinary design office and has won some awards in Hong Kong, Korea and Germany. Team members are diverse from dog-lovers to sorbet-maker, but we share the same passion for delivering excellent design and innovation with professional experience.\n\nThat\u2019s why we are looking for an\u00a0Associate Creative Director / Senior Designer to lead our team to the next level.\u00a0Because you\u2019ll be moving fluidly between leading design projects and creative tasks. You are also going to manage our talented teammates.\n\nWhat You\u2019ll Be:\u00a0\n\nTHE\u00a0MASTERMIND:\u00a0You\u2019ll be in charge of design project\u2019s concept and direction. You should get excited about working on projects across a roster of disciplines such as experience design, brand development, retail design and many more. Always have your idea pocket and tool kit ready to conceptualise and deliver story rich multimedia experiences and etc\nTHE MENTOR:\u00a0You\u2019ll guide and inspire the team, especially when we\u2019re feeling stuck or under a tight schedule, through\u00a0concept development, design quality refining and presentation deck building, from start to finish\nTHE TEAM PLAYER:\u00a0Brace yourself to collaborate with a slew of creative minds internally, the design/PM team, and externally, our clients to bring campaigns to life. Being an aficionado of culture, art and design like us would be desirable because we\u2019re going to work (really) closely as a team\nWhat You\u2019ll bring:\n\n9+ years of experience in the field (Candidates with less experience will be considered as Senior Designer)\nDegree or above in Graphic Design, Advertising or related discipline\nExperience in managing teams \u2013 We need you to host brainstorming sessions and coach designers\nExperience in either or all of:\u00a0retail\u00a0design, UX/UI, 3D, animation, advertising is an advantage\nExcellent command of Cantonese, English and Putonghua\nDisciplined and organised to work under pressure and tight deadlines. Yes expect last-minute client requests to be fulfilled\u2026\nFantastic knowledge of Photoshop, Illustrator and InDesign\nStrong typographic sense\nSense of humour, no joke!\nWhat You\u2019ll Get\n\nWork with our award winning team - we have won some Red Dots, International Design Awards and Golden Pin Design Award etc\nMulti-disciplinary projects opportunities\nFlat organisation structure- share and exchange freely alongside unlimited jokes\nStaff-led design initiatives every Friday\nCompetitive remuneration package\nCheck out noiseless-design.com for our projects and vision\n\u00a0If you think you\u2019re who we look for, show us what you\u2019ve got by sending your full resume, portfolio of works, current salary and expected salary to future @noiseless-design.com", "employment_types": ["Full Time"], "selling_points": ["Minimum 1 year experience", "Good career and attractive remuneration package", "San Po Kong, 5-day work"], "locations": ["Wong Tai Sin Area"], "categories": ["Design", "Graphics", "Visual Merchandising", "Others"], "post_time": "2022-01-11T00:58:45Z", "salary": {"currency": null, "max": null, "min": null, "period": "monthly", "term": null}, "salary_visible": false, "title_keywords": ["designer", "senior 3d designer"], "responsibilities": ["collaborate with", "advertising", "graphic design", "quality", "teams", "design", "schedule", "ui", "animation", "work under pressure"], "requirements": {"degrees": ["degree or above"], "majors": ["graphic design"], "languages": ["cantonese", "putonghua", "english"], "language_level": ["excellent"], "hard_skills": ["no", "indesign", "illustrator", "multimedia", "dog", "exchange", "red", "photoshop"], "soft_skills": ["passion for", "diverse", "organisation", "organised", "team player", "creative", "presentation", "work under pressure"], "languages_combined": [{"language": "cantonese", "language_level": ["excellent"]}, {"language": "putonghua", "language_level": ["excellent"]}, {"language": "english", "language_level": ["excellent"]}]}, "experience_required": {"duration": ["9+ years"], "field": ["designer", "brand", "advertising", "development", "design", "retail", "team"]}}, {"job_id": "100003009036511", "location_code": "hk", "company": "Noiseless Design", "job_title": "Associate Creative Director / Senior Designer", "description": "Job Description\n\nMy client is an interior design firm based in Hong Kong. They are specializing an international brand including retail and commercial design projects. The boutique locate for K11 MUSEA, 1881 Heritage, Ocean Terminal, Element Shop, Macau and China.\n\nWelcome to join our team to cope with our rapid expansion in both mainland China and Hong Kong.\n\nRequirements\n\nDiploma holder or above in Interior Design\nBasic\u00a0computer knowledge in AutoCAD\u00a0and\u00a0Photoshop are\u00a0preferable\nCapable in handling project independently for interior designer\n\nResponsible of site management, site survey,\u00a0 site staff supervision, etc.\u00a0for interior designer\n\nBasic Cantonese, English & Putonghua\nTraveling to overseas/ PRC is required\nMin 2 years site experience for interior designer\u00a0\n\nResponsibilities:\u00a0\n\nAssist the Senior Interior Designer\nDealing with clients, contractors, architectures, vendors and project team members\nResponsible for design drawings and documentation including concept design and development, construction drawing, materials sourcing and selection\nIdentify and understand clients\u2019 needs and provide customer services\n\nWe offer\u00a0double pay,\u00a0bank holidays, 5 1/2day work,\u00a0annual leave and MPF. Interested candidates please send your application letter with CV, portfolio and salary expectations by clicking 'Apply Now'", "employment_types": ["Full Time"], "selling_points": ["Always be passionate in creativity?", "Stopped believing that inspiring jobs exist?", "Ready to lead an award winning team?"], "locations": ["Kwun Tong"], "categories": ["Design", "Graphics", "Multi-media", "Visual Merchandising"], "post_time": "2022-01-10T10:55:13Z", "salary": {"currency": null, "max": null, "min": null, "period": "monthly", "term": null}, "salary_visible": false, "title_keywords": ["creative director", "associate", "senior designer"], "responsibilities": ["design"], "requirements": {"degrees": ["diploma holder"], "majors": ["design"], "languages": ["cantonese", "putonghua", "english"], "language_level": ["basic"], "hard_skills": ["documentation", "basic", "photoshop", "autocad"], "soft_skills": ["independently", "capable", "responsible"], "languages_combined": [{"language": "cantonese", "language_level": ["basic"]}, {"language": "putonghua", "language_level": []}, {"language": "english", "language_level": []}]}, "experience_required": {"duration": ["min 2 years"], "field": ["designer"]}}, {"job_id": "100003009022902", "location_code": "hk", "company": "ALF Retail Hong Kong Limited", "job_title": "Visual Merchandising Advisor (Marks and Spencer)", "description": "Marks & Spencer \u99ac\u838e \u73fe\u6b63\u62db\u8058\u5927\u91cf\u517c\u8077\uff01\n\u517c\u8077\u6642\u85aa\u53ef\u9054$64\n\u6b61\u8fce\u9031\u672b\u53ca\u5047\u65e5\u517c\u8077\n\n\u5de5\u4f5c\u5730\u9ede:\u00a0\u4e2d\u74b0\u4e2d\u532f\u5927\u5ec8 / \u4e2d\u74b0\u5efa\u696d\u69ae\u57fa\u4e2d\u5fc3\n\n\u5de5\u4f5c\u8077\u8cac\n\n\u4fdd\u6301\u8ca8\u5834\u9673\u5217\u6574\u9f4a, \u5b58\u8ca8\u5145\u8db3\n\u63d0\u4f9b\u6536\u9280\u670d\u52d9\n\u8655\u7406\u5916\u9001\u5e73\u53f0\u8a02\u55ae\n\n\u5de5\u4f5c\u8981\u6c42\n\n\u4e2d\u4e94\u7a0b\u5ea6\uff0c\u6c92\u6709\u96f6\u552e\u7d93\u9a57\u4ea6\u6b61\u8fce\n\u500b\u6027\u7a4d\u6975\u4e3b\u52d5\n\n\u5de5\u4f5c\u6642\u9593\n\n\u517c\u8077\u6bcf\u661f\u671f\u7d042\u00a0- 7\u5929\u5de5\u4f5c, \u6bcf\u661f\u671f\u5fc5\u9808\u5de5\u4f5c\u6700\u5c1114\u5c0f\u6642\n\n\u54e1\u5de5\u85aa\u916c\u53ca\u798f\u5229\n\n\u517c\u8077\u6642\u85aa\u53ef\u9054$64\n\u54e1\u5de5\u8cfc\u7269\u6298\u6263\u512a\u60e0(\u4e03\u6298)\n\n\u6709\u610f\u8005\u8acb\u5c07\u500b\u4eba\u5c65\u6b77\u8868\u4ee5\u4ee5\u4e0b\u65b9\u5f0f\u905e\u4ea4:\n\n\u7533\u8acb\u65b9\u6cd5\n\u96fb\u90f5: Apply Now\nWhatsApp:\u00a09306 2530\n\u50b3\u771f:3656 2180\n\n\u6240\u6709\u6c42\u8077\u8005\u4e4b\u500b\u4eba\u8cc7\u6599\u7d55\u5c0d\u4fdd\u5bc6\u53ca\u53ea\u4f5c\u62db\u8058\u4e4b\u7528\u3002\u5982\u516d\u661f\u671f\u5167\u672a\u7372\u63a5\u898b,\u5247\u4f5c\u843d\u9078\u8ad6,\u6055\u4e0d\u4f5c\u53e6\u51fd\u901a\u77e5\u3002\n\nPersonal information received from application will be kept confidential and used for employment-related purpose only. Applicants who have not been arranged interview in six weeks may assume their application unsuccessful.", "employment_types": ["Full Time", "Permanent"], "selling_points": ["Delivering company standard", "In store window display, images and in-store decor", "Passionate in Visual Merchandising"], "locations": ["Not Specified"], "categories": ["Design", "Fashion", "Visual Merchandising", "Sales, CS & Business Devpt", "Retail Sales"], "post_time": "2022-01-05T06:49:53Z", "salary": {"currency": null, "max": null, "min": null, "period": "monthly", "term": null}, "salary_visible": false, "title_keywords": ["visual merchandising advisor"], "responsibilities": [], "requirements": {"degrees": [], "majors": [], "languages": [], "language_level": [], "hard_skills": ["whatsapp"], "soft_skills": [], "languages_combined": []}, "experience_required": {"duration": [], "field": []}}, {"job_id": "100003008997916", "location_code": "hk", "company": "PLUG Design Limited", "job_title": "Art Director /  Senior Designer", "description": "\u00a0Job Responsibilities\n\nCoordinate merchandise in shops and windows to meet brand image.\nResponsible for conceptualizing, designing, and implementing window and in-store displays.\nSourcing of materials / equipment for window displays.\u00a0\nSupport layout move, product handling for renovation/store opening project.\nChange the display/mannequins in windows, in-store and focal areas regularly.\nWork closely with store manager and provide training to retail store team.\n\n\u00a0Job Requirements\n\nAt least 2\u2019 relevant years experience in visual merchandising\u00a0\nAble to handle in-store display and styling independently\nKnowledge of VM techniques, visual arrangement, window set-up and in-store display\u00a0\nKnowledge in sketch-up, AI, Auto-CAD is preferrable\nCreative, energetic and with strong fashion sense\n\n\n\nBenefits\n\nLimitless opportunity for growth\nOpen-minded team member and leader\nPerformance Bonus\u00a0\nThe opportunity to join a growing business\nBirthday off /\u00a0Marriage leave /\u00a0Bank holiday\nStaff purchase discount\nWorking in a friendly working environment\u00a0\n\nHEAVEN PLEASE\nWebsite :\u00a0heavenplease.com\nOnline Store : \u00a0heavenpleasestores.com\u00a0\nFacebook / IG :\u00a0Heaven Please\n\nInterested parties please send full resume with availability, current and expected salary to us by clicking \"Apply Now\" .\n\n*All information provided will be treated in strict confidence and used for recruitment purposes only", "employment_types": ["Full Time"], "selling_points": [], "locations": ["Chai Wan"], "categories": ["Design", "Visual Merchandising"], "post_time": "2021-12-26T16:20:53Z", "salary": {"currency": null, "max": null, "min": null, "period": "monthly", "term": null}, "salary_visible": false, "title_keywords": ["art director", "senior designer"], "responsibilities": ["provide training", "renovation", "coordinate", "designing", "conceptualizing"], "requirements": {"degrees": [], "majors": [], "languages": [], "language_level": [], "hard_skills": ["cad", "visual merchandising", "ai"], "soft_skills": ["energetic", "independently", "creative"], "languages_combined": []}, "experience_required": {"duration": [], "field": ["merchandising"]}}, {"job_id": "100003008998692", "location_code": "hk", "company": "Magic Search Limited", "job_title": "Project Designer (Fashion Brands)", "description": "Our client is a Fashion brand. To cope with their business expansion, they are looking for a Project Designer\u00a0to join the team.\n\nThe Job:\n\nResponsible for in-store & other project settings and implementation.\n3D\u00a0Rendering &\u00a0Simulation for Store project\nDraft store planning outline according to HQ guideline.\nCo-ordinate with other internal departments on merchandising support, regular shop visits to ensure corporate standards are maintained, and working closely with VM team.\u00a0\u00a0\nResponsible on Store, events, shows & Pop up store design\nCommunicate the corporate philosophy to sales staff and to implement the comprehensive training program.\n\nThe Candidate:\n\nDiploma or above in Visual Design, Project Planning or related disciplines\nProficiency in design software (AutoCAD, Photoshop), for computer-aided design work\n5 years relevant experiences and preferably in international fashion brands\nGood command of both written and spoken English and Chinese. Mandarin is a must\n\nAll information provided will be treated in strict confidence and used solely for recruitment purposes. To apply, please quote current and expected salary and Click \"Apply Now\"", "employment_types": ["Full Time", "Permanent"], "selling_points": ["Project Designer", "Proficiency in design softwares", "6 years relevant experiences"], "locations": ["Not Specified"], "categories": ["Building & Construction", "Architectural Services", "Design", "Interior", "Visual Merchandising"], "post_time": "2021-12-24T04:05:18Z", "salary": {"currency": null, "max": null, "min": null, "period": "monthly", "term": null}, "salary_visible": false, "title_keywords": ["project designer"], "responsibilities": ["design work", "project planning", "vm team", "software", "3d rendering", "co-ordinate with", "merchandising", "implementation", "design", "recruitment", "visual", "store planning"], "requirements": {"degrees": ["diploma or above"], "majors": ["related disciplines", "design"], "languages": ["english", "chinese", "mandarin"], "language_level": ["good command"], "hard_skills": ["visual design", "photoshop", "autocad"], "soft_skills": ["comprehensive", "confidence", "responsible"], "languages_combined": [{"language": "english", "language_level": ["good command"]}, {"language": "chinese", "language_level": ["good command"]}, {"language": "mandarin", "language_level": []}]}, "experience_required": {"duration": ["5 years"], "field": []}}, {"job_id": "100003008998025", "location_code": "hk", "company": "Dah Chong Hong, Limited", "job_title": "Assistant Officer / Clerk / \u6587\u54e1", "description": "Responsibilities:\n\nPropose and execute VM display on a weekly basis\nDeliver a high standard of visual display and align with the brand's guideline\nDesign and execute all graphic designs: eDMs, in-store signage, web banner, and social media graphics\nDesign and execution of Pop-Up Store, in-store set up, special events, and campaign launch\nNegotiate with vendors for cost efficiency\nSourcing of props & VM equipment for in-store display\nWork closely with headquarter for visual development and execution\n\nRequirement:\n\nDegree or diploma holder in Visual Merchandising, Art & Design or other design related discipline\nProficient in Photoshop, Illustrator, InDesign and Multimedia software\nMinimum 3-4 years\u2019 experience in visual merchandising and graphic design in shopping mall, department store and F&B will be an advantage\nPhotography, photo retouching and video editing skills will be an advantage\nStrong interpersonal and communication skills\nSelf-motivated, organized and able to work with tight schedule\nGood command of both written and spoken English and Chinese\nImmediate available is highly preferred\n\n\u00a0\nWe offer attractive remuneration package to the right candidate. Please apply with full resume stating present and expected salaries to Group Human Resources Department, 11/F., 68 Yee Wo Street, Causeway Bay, Hong Kong or by fax to 2895 5766.\n\nAll personal data/information provided by applicants to Regal Estate Management Limited is used for recruitment and related purpose(s) only.\n\nWe are an equal Opportunities Employer.", "employment_types": ["Full Time"], "selling_points": [], "locations": ["Kowloon Bay"], "categories": ["Design", "Visual Merchandising", "Merchandising & Purchasing", "Others", "Sales, CS & Business Devpt", "Retail Sales"], "post_time": "2021-12-24T02:22:23Z", "salary": {"currency": null, "max": null, "min": null, "period": "monthly", "term": null}, "salary_visible": false, "title_keywords": ["assistant officer", "clerk", "\u6587\u54e1"], "responsibilities": ["graphics", "social media", "cost", "edms", "graphic designs", "design", "visual"], "requirements": {"degrees": ["diploma holder", "degree"], "majors": ["art", "design"], "languages": ["english", "chinese"], "language_level": ["good command"], "hard_skills": ["visual merchandising", "indesign", "illustrator", "video editing", "multimedia", "photoshop"], "soft_skills": ["organized", "communication skills", "self-motivated", "interpersonal"], "languages_combined": [{"language": "english", "language_level": ["good command"]}, {"language": "chinese", "language_level": ["good command"]}]}, "experience_required": {"duration": ["minimum 3-4 years"], "field": ["graphic design", "f&b", "merchandising"]}}, {"job_id": "100003008996803", "location_code": "hk", "company": "Contempo Limited", "job_title": "Technical Designer (Part-time, 2-3 days/week)", "description": "Responsibilities:\n\nHandle 3D projects in creating meticulous 3D product visuals using CLO software.\nCreate and maintain a range of 3D libraries of graphics, prints, and artworks.\u00a0\nManipulate 2D digital patterns to create accurate 3D visuals.\nWork with Product development and Merchandising teams to ensure product visuals align with customer expectations.\nApply details, prints, and color to final 3D assets ready for Merchandising presentations.\nProvide assistance to solve the 3D visual & production issues.\nHandle any other ad-hoc duties as required.\n\nRequirements:\n\n\nDiploma holder in Fashion/Product Design or related discipline.\nMin 1 year solid experience in apparel, home textile, or fashion accessories-related industry.\nExperience in designing and building projects with a proven portfolio of previous work.\nPractical experience of using CLO software is a MUST.\nPattern construction knowledge is preferable.\nProficiency in MS Office and Adobe programs (Photoshop/Illustrator).\nExperience in Shima-Seiki,\u00a0Lectra, Gerber, Optitex, Browzwear is an advantage.\nProactive, able to meet project schedule, and good communication skills.\nGood command of written and spoken English, Chinese as well as knowledge in Mandarin.\nWe offer an attractive remuneration package.\n\n\nInterested candidates are invited to apply by sending your full resume, design portfolio, present & expected salary, and earliest available date to the Human Resources Department by clicking \"Apply Now\".\n\nClick here to visit our website\n\nOnly short-listed candidates will be notified.\u00a0 Personal Data collected will be kept in the strictest confidence and for recruitment purposes only.\u00a0", "employment_types": ["Part Time", "Permanent"], "selling_points": ["Create 3D visuals by CLO & Shima Seiki software", "Manipulate 2D digital pattern to create 3D visuals", "Create & maintain a range of CLO Libraries"], "locations": ["Kwun Tong"], "categories": ["Design", "Graphics", "Industrial / Product", "Visual Merchandising"], "post_time": "2021-12-23T08:44:03Z", "salary": {"currency": null, "max": null, "min": null, "period": "monthly", "term": null}, "salary_visible": false, "title_keywords": ["designer"], "responsibilities": ["graphics", "software", "ad-hoc duties", "teams", "merchandising", "presentations", "maintain", "visual", "provide assistance"], "requirements": {"degrees": ["diploma holder"], "majors": ["design"], "languages": ["english", "chinese", "mandarin"], "language_level": ["good command"], "hard_skills": ["illustrator", "adobe", "photoshop", "ms office"], "soft_skills": ["communication skills", "proactive"], "languages_combined": [{"language": "english", "language_level": ["good command"]}, {"language": "chinese", "language_level": ["good command"]}, {"language": "mandarin", "language_level": ["good command"]}]}, "experience_required": {"duration": ["min 1 year"], "field": ["textile", "related"]}}, {"job_id": "100003008987492", "location_code": "hk", "company": "Dah Chong Hong, Limited", "job_title": "Merchandise Planning Assistant", "description": "A leading branding and marketing solutions provider with over 18 years of history in HK serving top-tier clients with 2 regional offices in China is hiring to cope with the growing business.\n\nCreative solutions from design, event, fabrication and production\nPermanent Role in a well established company\nDynamic and fun workplace\nMarketing Exposure to Top-Tier Branding\nPopup Store, Shop Design, Promotion Events\n\nResponsibilities\n\nInitiate design concept, layouts and material selection\nHandle presentation with concept diagrams, perspective drawings and other means to demonstrate the design\nPrepare working drawings and detail drawings for projects\nCoordinate with clients, consultants and contractors\n\nRequirements\n\nDesign background and with 3 years\u2019 experience in interior design or related field\nExperience in technical drawing and rendering of Interior/Shop/Pop Up Stores\nKnowledge and experience in working with sub-contractors and factory\nProficient in AutoCAD, Sketchup / 3D max\n\nFeel free to explore with Ms. So at 35529113 / 98651077 for confidential discussion.", "employment_types": ["Full Time"], "selling_points": [], "locations": ["Kowloon Bay"], "categories": ["Design", "Visual Merchandising", "Merchandising & Purchasing", "Others", "Sales, CS & Business Devpt", "Retail Sales"], "post_time": "2021-12-20T06:43:37Z", "salary": {"currency": null, "max": null, "min": null, "period": "monthly", "term": null}, "salary_visible": false, "title_keywords": ["assistant"], "responsibilities": ["detail drawings", "design concept", "design", "drawings", "coordinate with clients"], "requirements": {"degrees": [], "majors": [], "languages": [], "language_level": [], "hard_skills": ["max", "sketchup", "autocad"], "soft_skills": [], "languages_combined": []}, "experience_required": {"duration": ["3 years"], "field": ["related", "design"]}}]