[{"job_id": "100003009052930", "location_code": "hk", "company": "DigiSalad Solutions Limited", "job_title": "UX Lead / (Senior) UX & UI Designer", "description": "Got tired of your boring work?\n\nWe have cool people. We deliver cool design. We are not a machine to work under long hours everyday with strict rules. We are not someone\u2019s pair of hands. We work in a creative, fun and flexible environment with no pressure.\n\nIf you think you are cool enough and ready to overcome challenges with supportive teammates to break your boundaries. Join us now!\n\nCheck out our new promotional video to find out who we are & why Digi is with Salad!\n\nResponsibilities:\n\nUtilize industry design standards and best practices to define and implement design criteria by a variety of methods to convey ideas and concepts (e.g. personas, user flow diagrams, wireframes, design prototypes, etc)\nDesign and specify UX and UI design for Responsive Web and Mobile application (iOS & Android)\nDeliver inventive, durable and thoughtful, solutions from concept to launch\nApply conceptual thinking to create desirable and feasible digital solutions across multiple platforms\nWork closely with a blended cross-functional team and tackle all aspects of the design process\nMaintain knowledge of design trends and assist with implementation of design innovations\u00a0\nLess Experience will be considered as Senior UX & UI Designer or UX & UI Designer\n\nRequirements:\n\nDegree or Diploma holder in visual design, interactive design, creative media or relevant discipline\nMinimum 3 years of experience in App and Responsive Web design\nStrong portfolio demonstrating proven UX workflow and strong design techniques\nProven ability in a variety of design tools such as Figma, Sketch, Invision, Photoshop, Illustrator and a bonus if you have experience with Adobe After Effects/ Flinto/ Principle\nBasic Knowledge in HTML production, HTML5, CSS3, JavaScript\nEffectively communicate research findings, conceptual ideas, detailed design, and design rationale both verbally and visually\nWilling to learn new trends and technology\nPositive attitude and motivation to deliver highest quality work\nDigital Agency Background is preferable but not a must\u00a0\n\nBenefit We Offer:\n\n5 days\u2019 work\nPerformance Bonus\nMedical Coverage\nFlexible Working Hours\nBirthday, Wedding, Maternity and Paternity leaves\nFun, young and joyful environment\u00a0\n\nWe're looking for talented individuals that want to do great work in a fun, creative, young and smart place. Attractive long term career prospect, along with competitive remuneration package and fringe benefits will be offered to the right candidate.\n\nJoin Us and Be a Cool People Now!\n\nInterested parties please click \"Apply Now\" to send a cover letter stating your expected salary, resume and a full set of your portfolio to us.\n\n*All information will be treated as confidential and used solely for recruitment purposes.\n", "employment_types": ["Full Time", "Permanent"], "selling_points": ["UX-Driven Digital Agency", "Fun and Young Working Environment", "Birthday Leave and Medical Coverage"], "locations": ["Tsuen Wan Area"], "categories": ["Design", "Multi-media", "Web Designer", "Information Technology (IT)", "UI/UX Designer"], "post_time": "2022-01-17T04:34:39Z", "salary": {"currency": null, "max": null, "min": null, "period": "monthly", "term": null}, "salary_visible": false, "title_keywords": ["ui designer", "lead"], "responsibilities": ["ideas", "implementation", "design", "maintain", "design trends", "ui"], "requirements": {"degrees": ["diploma holder", "degree"], "majors": ["creative media", "design"], "languages": [], "language_level": [], "hard_skills": ["web design", "basic", "illustrator", "html", "adobe after effects", "visual design", "javascript", "photoshop"], "soft_skills": ["willing to learn", "positive attitude", "creative", "responsive", "detailed"], "languages_combined": []}, "experience_required": {"duration": ["minimum 3 years"], "field": ["design"]}}, {"job_id": "100003009052672", "location_code": "hk", "company": "Refuel Digital Marketing Limited", "job_title": "Web & Graphic Designer [Salary range: 20K -25K (depends on exp.) ]", "description": "Responsibilities:\n\nProvide support to the Design and Marketing teams in designing, developing and executing promotional materials\nProduce a range of communication and collateral materials under group branding guidelines, such as print and online advertising, posters, leaflets, tent cards, menus and websites etc.\nAd-hoc projects as assigned\n\n\u00a0Requirements:\n\nDiploma holder or above in Graphic / Multimedia Design or related disciplines\nMinimum 1 year relevant experience\u00a0\nProficiency in Mac, knowledge in Adobe Creative Suite\nExperience in F&B and branding design\nKnowledge of food & product shooting is an advantage\nGood art sense & graphic skills, passionate, creative and energetic\nGood communication skills in English and Cantonese\nAble to multi task under tight deadlines\nImmediately available is preferred\n\nPlease send full resume and expected salary email by click \u201cApply Now\u201d.\n\nAll information obtained will be kept in strict confidence and will be used for recruitment purpose only.", "employment_types": ["Full Time"], "selling_points": [], "locations": ["Shatin Area"], "categories": ["Design", "Graphics", "Multi-media", "Web Designer"], "post_time": "2022-01-17T03:41:00Z", "salary": {"currency": null, "max": null, "min": null, "period": "monthly", "term": null}, "salary_visible": false, "title_keywords": ["graphic designer"], "responsibilities": ["provide support", "guidelines", "leaflets", "teams", "developing", "design", "communication", "promotional materials", "executing", "designing", "ad-hoc projects", "online advertising"], "requirements": {"degrees": ["diploma holder"], "majors": ["multimedia design", "related disciplines"], "languages": ["cantonese", "english"], "language_level": ["good"], "hard_skills": ["multimedia", "adobe creative suite"], "soft_skills": ["passionate", "communication skills", "confidence", "creative", "energetic"], "languages_combined": [{"language": "cantonese", "language_level": ["good"]}, {"language": "english", "language_level": ["good"]}]}, "experience_required": {"duration": ["minimum 1 year"], "field": ["f&b", "relevant experience", "design"]}}, {"job_id": "100003009051527", "location_code": "hk", "company": "Ma Belle Jewellery Co Ltd", "job_title": "Designer/ Web Designer/ Digital Designer", "description": "Job Description\nResponsible for the creation, design, development, and maintenance of the corporate websites of individual businesses.\nCreate graphic and animated design for our website, social media, and branding assets for marketing campaigns\nApply best practices to increase page speed & ratings, and SEO ranking\nRequirement\n\nDiploma holder or above in web, graphic design, or related field\nAt least 2 years of relevant working experience\nKnowledge in\u00a0SEO, CSS, HTML5, Java\u00a0and WordPress\nKnowledge in Adobe Photoshop, Fireworks, Illustrator, Flash, Dreamweaver\nExperience in video shooting and production is an advantage\nStrong sense of responsibility, a good team player while being able to work independently to meet project deadlines\nGood communication skills\nGood command of written and spoken Chinese, Mandarin & English\nPortfolio attachment is a MUST\nImmediate availability is highly preferred\nCandidate with more experiences would also be considered as Senior Web & Graphic Designer\n\nBenefit\n\nMedical insurance\nDental\u00a0insurance\nDiscretionary bonus\nAttractive performance bonus\nFriendly and collaborative work environment\n\nWe offer competitive remuneration package and good prospects to the right candidates.\n\n*For more details, please visit our official website:\u00a0https://refueldigital.com.hk/\n\n*Interested parties please send your full resume with expected salary by clicking \u201cApply now\u201d\n\n*The information provided by applicants will be kept confidential and will be\u00a0used solely for recruitment purpose only.\u00a0All the applications will be destroyed after 6-month.", "employment_types": ["Full Time", "Permanent"], "selling_points": ["multimedia/online advertising/video editing", "Adobe Photoshop ,Illustrator, After Effects", "Knowledge in HTML, CSS, UI/UX design"], "locations": ["Tin Hau"], "categories": ["Design", "Graphics", "Multi-media", "Web Designer"], "post_time": "2022-01-16T08:05:51Z", "salary": {"currency": null, "max": null, "min": null, "period": null, "term": null}, "salary_visible": false, "title_keywords": ["digital designer", "designer"], "responsibilities": ["social media", "seo", "maintenance", "website", "design", "marketing campaigns"], "requirements": {"degrees": ["diploma holder"], "majors": ["graphic design"], "languages": ["english", "chinese", "mandarin"], "language_level": ["good command"], "hard_skills": ["java", "seo", "web", "adobe photoshop", "illustrator", "wordpress", "flash", "dreamweaver", "css"], "soft_skills": ["communication skills", "good team player", "work independently", "sense of responsibility"], "languages_combined": [{"language": "english", "language_level": ["good command"]}, {"language": "chinese", "language_level": ["good command"]}, {"language": "mandarin", "language_level": ["good command"]}]}, "experience_required": {"duration": ["at least 2 years"], "field": ["graphic", "video shooting", "designer", "relevant working experience"]}}, {"job_id": "100003009054877", "location_code": "hk", "company": "Dragon Creative Media Limited", "job_title": "Multimedia Graphic Designer / Graphic Designer", "description": "Designer/ Web Designer/ Digital Designer\n\nThe Job\n\nprepare various online and offline marketing materials including but not limited to graphic/ video promotion materials, social media post, web design, photo retouching etc.\nwork closely with different teams and external parties to develop and execute cross-platform marketing\u00a0 campaign visuals and concepts\n\n\u00a0The Person\n\nDiploma or above in in Graphic/ Multimedia/ Animation/ Web Design or related discipline\nAt least 3 years of experience in e-Commerce, Graphic, Multimedia and Web Design\nexperienced in graphic/ multimedia/ online advertising/ web design/ video editing/ production skills is preferred\nproficient in Adobe Photoshop, Illustrator, After Effects and Premiere, Dreamweaver, XD and related software.\nhighly technical skills in motion graphic design and animation\nstrong sense on graphic, layout. colouring and usability on graphics\nknowledge in HTML, CSS, UI/UX design\nexperience in jQuery, Javascript and 3D rendering will be a plus\ncreative, detail-minded and well-organized working behavior\nwork independently and under pressure with tight schedule\ngood player with excellent communications skills\nWe offer 5-day week, attractive remuneration, career advancement opportunity, medical benefit, discretionary bonus, staff purchase privileges to the right candidate. Interested parties, please\u00a0send us your full resume with current and expected salary.\n\n\nPersonal data collected will be used for recruitment purposes only and will be treated in strict confidence.\u00a0 Applicants not invited for interview within\u00a04 months\u00a0may consider their applications unsuccessful.", "employment_types": ["Full Time"], "selling_points": ["5 days work", "At least 1 year multimedia experience", "Strong creative sense"], "locations": ["Southern Area"], "categories": ["Design", "Graphics", "Multi-media", "Web Designer"], "post_time": "2022-01-17T12:18:24Z", "salary": {"currency": null, "max": null, "min": null, "period": "monthly", "term": null}, "salary_visible": false, "title_keywords": ["graphic designer"], "responsibilities": ["social media", "photo retouching", "external parties", "teams", "design", "develop", "marketing materials"], "requirements": {"degrees": ["diploma or above"], "majors": ["web design", "animation"], "languages": [], "language_level": [], "hard_skills": ["graphics", "web design", "plus", "e-commerce", "jquery", "adobe photoshop", "illustrator", "premiere", "html", "video editing", "after effects", "javascript", "multimedia", "dreamweaver", "css"], "soft_skills": ["detail-minded", "work independently", "under pressure", "well-organized", "technical skills", "creative"], "languages_combined": []}, "experience_required": {"duration": ["at least 3 years"], "field": ["graphic", "design", "e-commerce"]}}, {"job_id": "100003009051843", "location_code": "hk", "company": "Stylevana", "job_title": "Part-time Digital and Graphic Designer", "description": "Job Description\n\n- Certificate / Diploma in Multimedia Design with 1-2 year multimedia experience\n\n- Proficiency in Photoshop, Illustrator, After Effects, MAYA, 3DMax & AutoCAD\n\n- To handle multimedia projects [text, sound, images, 3D-modelling, animation & rendering]\n\n- Creative, strong sense in multimedia design, self-motivated and self-disciplined", "employment_types": ["Part Time"], "selling_points": ["Design & create online content for eCom", "knowledge of Photoshop, Illustrator & Premiere", "Work in office for 2-3 days per week"], "locations": ["Kwai Hing"], "categories": ["Design", "Graphics", "Web Designer", "E-commerce", "Others"], "post_time": "2022-01-17T01:20:54Z", "salary": {"currency": null, "max": null, "min": null, "period": "hourly", "term": null}, "salary_visible": false, "title_keywords": ["digital and graphic designer"], "responsibilities": ["multimedia design", "animation"], "requirements": {"degrees": ["certificate", "diploma"], "majors": ["multimedia design"], "languages": [], "language_level": [], "hard_skills": ["maya", "illustrator", "after effects", "autocad", "3dmax", "multimedia", "photoshop"], "soft_skills": ["self-motivated", "creative"], "languages_combined": []}, "experience_required": {"duration": ["1-2 year"], "field": ["design"]}}, {"job_id": "100003009054870", "location_code": "hk", "company": "Nu Skin Enterprises Hong Kong, LLC", "job_title": "Designer (Web and Graphic Design)", "description": "Responsibility:\n\nEffectively help on the design tasks and projects to meet deadlines\nMaintain and update web content by using Adobe Experience Manager\nProducing rich and creative media online campaigns include eDM, web banners, etc.\n\nRequirement:\n\n2-year experience in graphic design, with passion in graphic design and creating user-friendly web interfaces\nKnowledge in Adobe Creative Suite. E.g. Adobe Creative Suite, e.g. Photoshop, illustrator, Dreamweaver, etc\nKnowledge in HTML and CSS is a must.\nExcellent communication skills and attention to detail\n\n\nWe offer 5 days work, excellent career development with on/off-the-job trainings, competitive compensation including incentive bonus & annual performance bonus, medical benefits, life & accidental insurance, annual leave & product benefits.\n\nIf you are ready for a new challenge in your career, please send your detailed resume with\u00a0Current and Expected Salary and Your Availability\u00a0by clicking Apply Now.\n\n\n\nALL PERSONAL INFORMATION WE COLLECTED IS FOR THE PURPOSE OF RECRUITMENT ONLY\n\n\n\nPlease visit\u00a0www.nuskin.com\u00a0to find out more about us!", "employment_types": ["Full Time", "Permanent"], "selling_points": ["Support design tasks and projects", "Produce creative media online campaigns", "Knowledge in Adobe Creative Suite"], "locations": ["Causeway Bay"], "categories": ["Design", "Graphics", "Multi-media", "Web Designer"], "post_time": "2022-01-17T12:14:08Z", "salary": {"currency": null, "max": null, "min": null, "period": "monthly", "term": null}, "salary_visible": false, "title_keywords": ["designer"], "responsibilities": ["banners", "maintain", "design", "edm"], "requirements": {"degrees": [], "majors": [], "languages": [], "language_level": [], "hard_skills": ["web", "illustrator", "html", "dreamweaver", "css", "adobe creative suite", "photoshop"], "soft_skills": ["communication skills", "passion in", "friendly", "attention to detail", "creative", "detailed"], "languages_combined": []}, "experience_required": {"duration": ["2-year"], "field": ["graphic design"]}}, {"job_id": "100003008993855", "location_code": "hk", "company": "Tranthink Technology Service Limited", "job_title": "Graphic Designer", "description": "Job responsibilities:\nDesign web pages for corporate branding and work on interface solutions\nSupport senior designers to create and convey design solutions\nAnalysis and improvement for the design projects (wireframe, mockup and prototype)\nDesign for the advertising material and relevant graphics when needed\nHandle ad-hoc tasks or projects as assigned\nRequirements:\nHigher Diploma or Degree in Web Design/ Graphic Design or related discipline;\nAt least 2 years working experience in Website/ Graphic Design/ UI/UX work, with experience of a full cycle project in mobile/web;\nCurrent experience in web design, digital promotion, graphic design with promotion material etc;\nSolid experience in designing Corporate Branding / commercial website/marketing material etc;\nProficient in Adobe Creative, Photoshop, Illustrator, XD etc;\nA portfolio to demonstrate design work;\nWork independently and good team player;\nGood in spoken and writing in English and Chinese\nPlease click \"Apply Now\" to submit your application.\n\n\nPersonal data collected will be used for recruitment purpose only.\n", "employment_types": ["Full Time", "Permanent"], "selling_points": ["5 Days Work, Double Pay, Medical Insurance", "Flexible working hours, Free snack", "Designing promotional materials"], "locations": ["Not Specified"], "categories": ["Design", "Graphics", "Web Designer", "Information Technology (IT)", "Others"], "post_time": "2022-01-16T21:50:01Z", "salary": {"currency": null, "max": null, "min": null, "period": "monthly", "term": null}, "salary_visible": false, "title_keywords": ["graphic designer"], "responsibilities": ["graphics", "advertising", "design solutions", "analysis", "ad-hoc tasks", "design"], "requirements": {"degrees": ["diploma", "degree"], "majors": ["web design", "graphic design"], "languages": ["english", "chinese"], "language_level": ["good"], "hard_skills": ["web design", "web", "illustrator", "mobile", "adobe", "photoshop"], "soft_skills": ["good team player", "work independently", "creative"], "languages_combined": [{"language": "english", "language_level": ["good"]}, {"language": "chinese", "language_level": ["good"]}]}, "experience_required": {"duration": ["at least 2 years"], "field": ["graphic design", "design", "commercial", "marketing", "digital"]}}, {"job_id": "100003009053342", "location_code": "hk", "company": "Endeavour Search Limited", "job_title": "Full Stack Developer \u2013 Corporate Communication Projects / Interactive app/web design / MNC", "description": "Executive Summary:\nGlobal firm with footprint across North America and Europe with Headquarter in HK\nPublicly Listed company - Annual global sales turnover at 6 Billion USD\nEstablished for 30 years with solid stable work culture and puts people first\nAround 600 staffs in Hong Kong office and IT team around 50 staffs.\nStable work culture for longer term career development\nGrade A office \u2013 5 mins from MTR\nMajor Responsibilities:\nDevelop interactive and modern user interfaces using the frontend technologies such as React, Angular, Vue.JS with the digital communication team\nIntegrate internal and third-party APIs using provided documentation\nWrite solid, tested, and well-documented code that is easy to read, scalable and easy to share with other developers\nUse component-based approach to analyze design handover files and follow that structure when building the web applications\nBuild restful API\u2019s using Drupal 9+ and maintain an information-rich API documentation\nUse version control (git) to push and track code changes in a timely manner and use branch strategies to collaborate with other developers\nProactively monitor infrastructure to ensure web applications are in good performance\nKey Requirements\nHigher Diploma holder in Computer Science, Information Systems or related disciplines\nAt least 2-5 years\u2019 experience in HTML, CSS, Javascript working on production level projects\nExperience with PHP frameworks and Drupal is desirable\nFamiliar with oAuth2 authentication method, implementation in the backend and exploitation on the frontend\nFamiliar with React.js, hooks, Restful APIs and handling JSON format data\nExcellent understanding of modern Javascript\nKnowledge on mobile app development (native or hybrid), Wordpress would be a plus\nStrong project management, analytical, technical, and problem-solving skills with critical thinking\nGood command of written and spoken English\nTo apply, please send your CV in word document to Gloria(a)endeavourasia.com or call 3956-1829 for a confidential discussion.", "employment_types": ["Full Time", "Permanent"], "selling_points": ["In-House Perm Role; MNC", "Interactive web/app design for the group image", "Long term career development & training provided"], "locations": ["Kwai Tsing Area"], "categories": ["Design", "Web Designer", "Information Technology (IT)", "Software Development", "UI/UX Designer"], "post_time": "2022-01-17T06:48:41Z", "salary": {"currency": null, "max": null, "min": null, "period": "monthly", "term": null}, "salary_visible": false, "title_keywords": ["developer"], "responsibilities": ["collaborate with", "control", "infrastructure", "a timely manner", "monitor", "design", "develop", "communication", "maintain", "documentation"], "requirements": {"degrees": ["higher diploma holder"], "majors": ["related disciplines", "computer science"], "languages": ["english"], "language_level": ["good command"], "hard_skills": ["plus", "react", "php", "problem-solving skills", "word", "html", "mobile", "wordpress", "javascript", "project management", "css"], "soft_skills": ["problem-solving skills", "project management"], "languages_combined": [{"language": "english", "language_level": ["good command"]}]}, "experience_required": {"duration": ["at least 2-5 years"], "field": []}}, {"job_id": "100003009049406", "location_code": "hk", "company": "Midland Holdings Limited", "job_title": "Web Designer", "description": "Responsibilities:\n\nWeb UI/UX and Banner Design\n\nOnline campaigns development and maintenance\nWork closely with Web Developer/ Programmer on web development\n\nRequirements:\n\nDegree or Diploma in Web Design, Creative/ Interactive Media or related disciplines\n\nFamiliar in HTML5, JAVASCRIPT, CSS, bootstrap\nAdobe Creative Cloud, MS Powerpoint, Apple Keynote\n1-3 years of experience in web design\n\nCompetitive Salary will be offered to the right candidate. \u00a0For application, please update your resume by clicking \"APPLY NOW\" or complete the online application form which is available at\u00a0https://www.midland.com.hk/joinus/\u00a0and sent to the corresponding email address together with your full resume, present & expected salary.\u00a0\n\nAll personal data collected will be used for recruitment purpose only. Applicants not hearing from us within 2 months may consider their applications unsuccessful. \u00a0All personal data supplied will be kept for a reasonable period in accordance with the legal requirements.\n\nAs an Equal Opportunities Employer, we are committed to eliminating discrimination in employment. Our vacancy is open to all applicants meeting the basic entry requirement irrespective of their disability, sex, marital status, pregnancy, age, family status, sexual orientation and race.", "employment_types": ["Temporary", "Contract"], "selling_points": ["5 days work with discretionary bonus", "Web UI/UX and Banner Design", "Familiar in HTML5, JAVASCRIPT, CSS, bootstrap"], "locations": ["Admiralty"], "categories": ["Design", "Web Designer", "Information Technology (IT)", "Others", "UI/UX Designer"], "post_time": "2022-01-15T19:11:38Z", "salary": {"currency": null, "max": null, "min": null, "period": "monthly", "term": null}, "salary_visible": false, "title_keywords": ["designer"], "responsibilities": ["maintenance", "ui", "design"], "requirements": {"degrees": ["diploma", "degree"], "majors": ["related disciplines", "web design"], "languages": [], "language_level": [], "hard_skills": ["web design", "basic", "javascript", "adobe", "css", "ms powerpoint"], "soft_skills": ["committed", "creative"], "languages_combined": []}, "experience_required": {"duration": ["1-3 years"], "field": ["design"]}}, {"job_id": "100003009054201", "location_code": "hk", "company": "Endeavour Search Limited", "job_title": "Senior Digital Designer (AM Grade) - Corporate Communication / MNC / Global Leading Brands", "description": "Job Description\n\nResponsible for the creation, design, development of graphic design\nResponsible for design tasks including but not limited to leaflet, poster, banner, etc.\nPerform any other tasks assigned by supervisor\n\nRequirement:\n\nDiploma holder or above in web, graphic design, or related field\nKnowledge in Adobe Software, website design, video shooting & editing\nExperience in Solidworks, 3Dmax, Keyshot, Autocad would be an advantage\nExperience in IT support and help desk on PC and Mac\nStrong sense of responsibility, a good team player while being able to work independently to meet project deadlines\nGood communication skills\nGood command of written and spoken Chinese\nPortfolio attachment is a MUST\nImmediate availability is highly preferred\nFresh graduates would also be considered\n\nBenefit:\n\nDiscretionary bonus\nAttractive performance bonus\nFriendly and collaborative work environment\n\nWe offer competitive remuneration package and good prospects to the right candidates. Interested parties please send your full resume with expected salary by clicking \u201cApply now\u201d\n\n*Data collected will be kept confidential and used for recruitment purposes only. All the applications will be destroyed after 6-month.", "employment_types": ["Full Time", "Permanent"], "selling_points": ["Lead & present digital design", "Familiar with UI / Web/ App design", "MNC, young and dynamic culture; Fluent Eng"], "locations": ["Not Specified"], "categories": ["Design", "Industrial / Product", "Multi-media", "Web Designer"], "post_time": "2022-01-17T08:47:25Z", "salary": {"currency": null, "max": null, "min": null, "period": "monthly", "term": null}, "salary_visible": false, "title_keywords": ["digital designer"], "responsibilities": ["graphic design", "other tasks", "leaflet", "design"], "requirements": {"degrees": ["diploma holder"], "majors": ["graphic design"], "languages": ["chinese"], "language_level": ["good command"], "hard_skills": ["web", "3dmax", "adobe software", "pc", "solidworks", "autocad"], "soft_skills": ["communication skills", "good team player", "work independently", "sense of responsibility"], "languages_combined": [{"language": "chinese", "language_level": ["good command"]}]}, "experience_required": {"duration": [], "field": ["it support"]}}, {"job_id": "100003009052667", "location_code": "hk", "company": "Love Design Production Limited", "job_title": "Graphic Designer (16K-18K depends on experience)", "description": "Job Duties:\u00a0\n\nDesign and create digital creatives for eCommerce websites\nAssist in adapting existing graphic to different languages and for different target markets\u00a0\n\n\u00a0Job Requirements:\u00a0\n\nFormal training in design (Diploma holder in graphic design) with solid understanding on website marketing and Ecommerce websites\nExpert knowledge of Photoshop, Illustrator\nKnowledge in Premiere is preferred\nEffective time management\nWork well with the team\nStrong written English and communication skills\nImmediately availability preferred\nWork in office for 2-3 days per week\u00a0\n\nWe offered a fun and friendly team environment.\u00a0The right candidates or interested parties should\u00a0apply with samples of your past work (online portfolio or in PDF no more than 5MB), a CV, your current and expected salary and availability\u00a0by clicking \u201cApply Now\u201d for an interview.", "employment_types": ["Full Time"], "selling_points": [], "locations": ["Shatin Area"], "categories": ["Design", "Graphics", "Multi-media", "Web Designer"], "post_time": "2022-01-17T03:40:45Z", "salary": {"currency": null, "max": null, "min": null, "period": "monthly", "term": null}, "salary_visible": false, "title_keywords": ["graphic designer"], "responsibilities": ["design"], "requirements": {"degrees": ["diploma holder"], "majors": ["ecommerce", "graphic design", "marketing", "design"], "languages": ["english"], "language_level": [], "hard_skills": ["illustrator", "premiere", "photoshop"], "soft_skills": ["communication skills", "time management"], "languages_combined": [{"language": "english", "language_level": []}]}, "experience_required": {"duration": [], "field": []}}, {"job_id": "100003009054212", "location_code": "hk", "company": "Sedgwick Richardson (Hong Kong) Ltd", "job_title": "Designer (Publishing)", "description": "As our User Researcher of our Design Hub team in Hong Kong, your primary mission will be to understand the needs and product requirements and transform that understanding into user-focused and intuitive products and services.\n\nYou will:\n\nmanage and run all forms of requirement gathering, user research, UX workshop, customer interview, usability testing, focus group etc.\nfacilitate the product vision by researching, sketching, prototyping and user-testing experiences for digital products\ndesign experiences through human-centred-design\nensure that research findings and insights are translated into actionable product goals and direction and sharing insights with stakeholders\ncreate wireframes (from sketches to high-fidelity ones)\ntranslate concepts into user flows & wireframes\ncreate rapid prototypes to validate design concepts with stakeholders and customers\nrun workshops and other group activities\nContributing to on-going enhancement of customer experience and user experience methodologies\nstay abreast of UX and technology trends and look for inspiration\n\nRequirements:\n\nMinimum of 5 years relevant experience as a User Researcher, interaction designer or similar roles\nnative Cantonese speaker with strong local cultural understanding. Fluent and comfortable in English\nexperienced in user research, prototyping and user testing methodologies\nunderstand Agile / iterative project management methodologies\nable to handle a Mac and the usual tools (Adobe, Sketch)\nbe a self-motivated and resilient team player driving collaboration\nwith strong sense of personal accountability", "employment_types": ["Full Time"], "selling_points": [], "locations": ["Central"], "categories": ["Design", "Graphics", "Multi-media", "Web Designer"], "post_time": "2022-01-17T08:49:51Z", "salary": {"currency": null, "max": null, "min": null, "period": "monthly", "term": null}, "salary_visible": false, "title_keywords": ["designer"], "responsibilities": ["design concepts", "workshop", "user experience", "sketches", "design", "testing", "project management"], "requirements": {"degrees": [], "majors": [], "languages": ["cantonese", "english"], "language_level": ["native", "fluent"], "hard_skills": ["agile", "project management", "adobe", "rapid", "workshops", "focus"], "soft_skills": ["self-motivated", "agile", "focused", "accountability", "project management", "team player", "focus"], "languages_combined": [{"language": "cantonese", "language_level": ["native"]}, {"language": "english", "language_level": ["fluent"]}]}, "experience_required": {"duration": ["minimum of 5 years"], "field": ["designer", "design", "testing", "relevant experience", "digital"]}}, {"job_id": "100003009054790", "location_code": "hk", "company": "EY Mtel Solutions Limited", "job_title": "UI / UX Designer", "description": "ABOUT SEDGWICK RICHARDSON\n\nWe\u2019re a regional team of strategists, designers and sustainability specialists who are passionate about building brands that have a positive impact on our world. We are a new kind of company that is changing how brands are created. We fuse sustainability principles into brand building to create relevant brands that thrive.\n\nTogether, we Build Belief in the Future.\n\nAbout You\n\nYou work in a \u2018concept first\u2019 mode and think holistically about brands and publications. You understand that today they need to be designed to live across multiple channels and formats, and that this often means taking a digital first approach.\n\nYou want to work with a team truly committed to improving the world we live in. You want to learn about how sustainability thinking applies to brand design.\n\n\n\nYour responsibilities\n\nGenerate brilliant creative concepts and fresh ideas\nExtraordinary aesthetic sense and taste\nHighly sensitive to typography, imagery, layout hierarchy\nPay attention to the quality and every detail of design execution\nConsult internally with Creative Director and the Account Management team to agree on the theme, creative direction, other design parameters\nSupport in the creation of presentations and marketing content & materials\nDeliver design solutions within specified, approved schedules and resources\nSee designs through to final artwork and delivery\nManage the printing process for publications\n\nYour skills\n\nYou\u2019re able to articulate and visualise your ideas and concepts clearly\nFluency in spoken and written English required, Cantonese and Mandarin a big plus.\nYou\u2019ll have 3+ years of experience in publication design\nYou have intimate working knowledge of Adobe Photoshop, Illustrator, InDesign.\nYou\u2019re self-motivated, organised, accountable and thrive in a multi-cultural environment\nYour attitude is respectful, collaborative and positive\nYou are passionate about typography and understand typographic hierarchy\nYou have experience in data visualisation and information design\nYou can demonstrate an understanding of pagination planning\nYou have rigorous file management skills\n\nPlease send us a short email with your r\u00e9sum\u00e9 (and a link to your online portfolio) explaining why you are interested to join our team. This must include previous and expected salary.", "employment_types": ["Full Time", "Permanent"], "selling_points": ["Diploma/Degree in Design or a related field", "Photoshop, Illustrator, Sketch, Figma", "Knowledge of prototyping, HTML/CSS, JavaScript"], "locations": ["Kwun Tong"], "categories": ["Design", "Graphics", "Web Designer", "Information Technology (IT)", "UI/UX Designer"], "post_time": "2022-01-17T11:05:27Z", "salary": {"currency": null, "max": null, "min": null, "period": "monthly", "term": null}, "salary_visible": false, "title_keywords": ["ux designer"], "responsibilities": ["management team", "ideas", "design solutions", "schedules", "data", "quality", "presentations", "design", "file management", "publication", "planning"], "requirements": {"degrees": [], "majors": [], "languages": ["cantonese", "english", "mandarin"], "language_level": ["fluency"], "hard_skills": ["plus", "indesign", "adobe photoshop", "illustrator", "presentations"], "soft_skills": ["self-motivated", "passionate about", "accountable", "collaborative", "committed", "sensitive to", "organised", "articulate", "creative", "positive", "respectful"], "languages_combined": [{"language": "cantonese", "language_level": ["fluency"]}, {"language": "english", "language_level": ["fluency"]}, {"language": "mandarin", "language_level": ["fluency"]}]}, "experience_required": {"duration": ["3+ years"], "field": ["design"]}}, {"job_id": "100003009052049", "location_code": "hk", "company": "China Mobile International Limited", "job_title": "Assistant UI/UX Design Manager (Ref: CMIJD-1213-AUIUXMPMHK)", "description": "IMPORTANT PLEASE NOTE: We want to see your best work. For fast attention please link prominently to an online portfolio of no more than ten examples of your best work. Thanks :)\n\nWant a challenge creating outstanding brands and websites?\u00a0\n\nStepworks is a wholehearted independent branding firm, based in Hong Kong. Superb design underpins our work, which is enhanced by next level digital.\n\nWe have a strong track record helping organisations create positive change with our brand building skills, in HK and worldwide.\n\nOn our multicultural team you\u2019ll meet caring people who are really good at building brands that deliver valuable competitive advantages for our clients.\n\nMore on our wholehearted approach to brand building at www.stepworks.co\n\nResponsibilities\n\n\nWork on a range of creative brand building projects for respected organisations\nDesign websites underpinned by a good UX and UI foundation\u00a0\nExpress brand-led ideas using graphic and motion graphics\nProactively take responsibility of the quality of work under your care\nProduce deliverables on brief to a world-class standard with high degree of client satisfaction\nMaintain healthy working relationships\nUnderstand evolving industry best practices in digital, web and brand building\nCapabilities\u00a0\n\nOver 5 years relevant experience\nA strong sense of design aesthetics, artistic talent and creativity\nBe fluent and confident in English and Cantonese\nExpertise across the Adobe Creative SuiteExpertise across the Adobe Creative Suite, Figma or other web prototyping tools, and motion graphic software for web\nGood communication skills and superb organisation and time management skills\nBe experienced in production processes for digital and print\nOther creative skills like illustration, music/audio etc, will be considered a bonus\nEnjoy working in a team environment and be wholehearted\nRewards\n\nFlexible working arrangements\nCompetitive salary, profit sharing and opportunity for growth\nGreat culture working on projects that create positive change\nCaring team who look after each other\nTraining and support for your ambitions\u00a0\nA high credibility gig in your resume\nSounds good?\n\n\nEmail your portfolio, r\u00e9sum\u00e9 and expected salary. We\u2019ll treat it all in confidence.\n\nDon\u2019t forget to link to your portfolio!", "employment_types": ["Full Time", "Permanent"], "selling_points": ["Bachelor's degree or above", "UI/UX Design of mCloud Platform", "Proficient in design software"], "locations": ["Kwai Hing"], "categories": ["Design", "Graphics", "Industrial / Product", "Web Designer"], "post_time": "2022-01-17T01:57:11Z", "salary": {"currency": null, "max": null, "min": null, "period": "monthly", "term": null}, "salary_visible": false, "title_keywords": ["design manager", "assistant"], "responsibilities": ["management", "ideas", "software", "quality", "motion graphic", "design", "communication", "motion graphics", "maintain", "working relationships", "audio", "ui"], "requirements": {"degrees": ["degree"], "majors": [], "languages": ["cantonese", "english"], "language_level": ["fluent"], "hard_skills": ["graphics", "no", "web", "adobe", "illustration", "adobe creative suite"], "soft_skills": ["confident", "communication skills", "flexible", "confidence", "independent", "time management skills", "enjoy working", "organisation", "creative", "positive", "world-class"], "languages_combined": [{"language": "cantonese", "language_level": ["fluent"]}, {"language": "english", "language_level": ["fluent"]}]}, "experience_required": {"duration": ["5 years"], "field": ["relevant experience"]}}, {"job_id": "100003009049783", "location_code": "hk", "company": "Equity Financial Press Limited", "job_title": "Senior Designer / Assistant Art Director", "description": "Big Leap Global - Your Trusted Partner in Blockchain APP Development\n\nIf the internet revolutionized the world in the 2000s, social media changed the game in 2010s, then in 2020s, blockchain and internet will be the winning factor for those adopt it to eliminate those do not.\u00a0\n\nWe are a blockchain and game mobile application firm with user-oriented mindsets.\n\nWith our expertise in UI/UX design, blockchain software development and marketing & user penetration, we provide solutions to CEO, CTO or product managers who are looking to outsource their blockchain development. We help companies not just to design and build great social media and blockchain apps but we help them to take it to the world!\n\nIf you see the future of technology like we do, and you are determined to fast track your career by entering one of the most rapidly growing industries in the 2020s, come join us.\u00a0\n\nWe are sure you can design something even nicer than a Shiba Inu on a coin. How about Corgi?\n\n\n\n\n\nHow you can create the next big thing:\n\nYou will be reporting to the senior designer and will be contributing your highly usable and intuitive interface creation for our mobile app and mobile game projects. Your design shall be easy for users to digest and trigger users to share the product with their friends.\u00a0\n\n\n\nDevelop intuitive, usable, and engaging interactions and visual designs for mobile.\nCreate wireframes, page flows, mockup / interactive prototypes across mobile and desktop to communicate interaction and design ideas\nCollaborate with cross-functional teams (executive suite, marketing, engineering, operation) throughout the design process\nParticipate in the full-cycle development process from definition, through design, build, test, release, and maintenance.\nResearch and track advancements in latest mobile application design patterns in the blockchain field and the several key competitors of each project.\u00a0\n\nWhat makes you a game changer:\n\n\n\n2-years or above solid experience in designing UI of mobile applications and mobile web pages.\u00a0\nDiploma or above in Web Design / Graphic / Multimedia design or related discipline\nExperience working with blockchain startup will be an advantage\nExperience in unity\u00a0\nIntermediate to knowledge of relevant technologies and tools (e.g., HTML/CSS,Photoshop, Illustrator)\nAble to work under pressure with tight deadlines with a strong sense of responsibility\nWhat\u2019s next?\n\n\nTo facilitate the recruitment process, remember to insert the followings in your resume,\u00a0\n\n\nLinks to your design portfolio\nYour current salary and expected salary\nYour availability for reporting duties\nThis will help us to choose your profile easier among the numerous applications.\u00a0\n", "employment_types": ["Full Time", "Permanent"], "selling_points": ["Design institute graduate or above", "5 to 7 yrs experience in graphic design field", "Website design experience is an advantage"], "locations": ["Central & Western Area"], "categories": ["Design", "Graphics", "Web Designer", "Media & Advertising", "Print Media"], "post_time": "2022-01-14T09:13:57Z", "salary": {"currency": null, "max": null, "min": null, "period": "monthly", "term": null}, "salary_visible": false, "title_keywords": ["senior designer", "art director", "assistant"], "responsibilities": ["collaborate with", "social media", "reporting", "multimedia design", "mobile app", "software", "ideas", "maintenance", "designing", "provide solutions", "design", "develop", "visual", "recruitment process", "ui", "cross-functional teams", "work under pressure"], "requirements": {"degrees": ["diploma or above"], "majors": ["multimedia design", "web design"], "languages": [], "language_level": [], "hard_skills": ["blockchain", "web design", "maintenance", "illustrator", "web pages", "html", "mobile", "factor", "multimedia", "css", "unity", "photoshop"], "soft_skills": ["sense of responsibility", "determined", "work under pressure"], "languages_combined": []}, "experience_required": {"duration": [], "field": []}}, {"job_id": "100003009048878", "location_code": "hk", "company": "Prenetics Limited", "job_title": "Graphic Designer", "description": "Founded in 2014, Prenetics is a major global diagnostics and genetic testing company with the mission to bring health closer to millions of people globally and decentralize healthcare by making the three pillars \u2014 Prevention, Diagnostics and Personalized Care \u2014 comprehensive and accessible to anyone, at anytime and anywhere. Prenetics is led by visionary entrepreneur, Danny Yeung, with a team of over 800 employees and operations across 9 locations, including United Kingdom, Hong Kong, India, South Africa, and Southeast Asia. Prenetics develops consumer genetic testing and early colorectal cancer screening; provides COVID-19 testing, rapid point of care and at-home diagnostic testing and medical genetic testing.\n\nMost recently, Prenetics made international headlines to become the first Unicorn in Hong Kong to publicly list on the Nasdaq via merger with 2021 Adrian Cheng's Artisan Acquisition Corp, valuing Prenetics at approximately US $1.7b.\n\nThe ideal candidate will be the lifeblood of our creative thrust for our mobile and web applications geared towards health and wellness. You will consider underlying cognitive and emotional needs and craft experiences that connect our products with those needs. You are an inspiring though leader which possess:\n\nCreative mind. Your work is imaginative, unique, and inspired. You have an innate ability to expand boundaries and imagine new possibilities.\nPictorial talent. You communicate with images. Your artistic vein shows in everything you do. Your designs are elegant, aesthetic, and balanced.\nInquisitive attitude. You follow a trail of questions, formulate sound hypotheses, and design insightful tests in pursuit of people's intrinsic motivations.\nIterative bias. Your path to discovery is continuous and progressive. Each iteration shows a coherent narrowing in focus and increase in precision.\nOutward drive. You know discovery takes place outside the office, when inspired ideas are reaffirmed, perfected, or redefined by real customers.\n\nResponsibilities\n\nSupport in brainstorming sessions with the Marketing and Product Team.\nSupport in creating images, graphics, advertising, and websites for the brand\nPresent designs to internal clients or team manager\nReview designs for errors before printing or publishing them\nConduct layout adjustment based on user feedback\nRefine, maintain and enforce our design guidelines and strategies\nPerform content updates on our web properties and marketing assets as needed\n\nQualifications\n\nBachelor's degree in Graphic Design, Fine Arts, Industrial Design, or related field\nExperience with main Adobe Creative Cloud apps (Photoshop, Illustrator, InDesign, etc.), Figma, or other visual design tools\nStrong communication, conceptual thinking, typography skills and design skills\nExperience in digital illustration and motion graphics (Adobe AfterEffects) would be a plus\n\nReminder: please provide a Portfolio Link of your work when you apply\n\nOur DNA is\u00a0P-R-E-N-E-T-I-C-S. See what each word of our company name means:\n\nPassion\n\nYou love what you do and accomplish amazing result\nYou spread positivity, bring enthusiasm to work and inspire team members\nYou drive team toward specific goals, even when they seem unlikely or difficult\n\nResilience\n\nYou embrace changes and be able to drive through uncertainty, ambiguity and uncomfortable situations\nYou bounce back quickly from setbacks and challenges\nYou are persistent and determined to achieve the desired outcome\n\nEmpowerment\n\nYou trust others to play their positions well like an elite sports team\nYou foster a strong team spirit while encouraging others to take initiatives and risks\nYou create a space to allow team to grow and hold each other accountable\n\niNtegrity\n\nYou are trustworthy and lead by example\nYou are consistent in your message and action all the times\nYou deliver what you have promised\n\nEpic\n\nYou challenge your own comfort zone and always outperform yourself\nYou make meaningful and amazing impact to the world\nYou dare to take risks and you move fast\n\nTransparency\n\nYou are completely honest and committed to giving candid feedbacks, no matter how challenging it might be\nYou share ideas, knowledge and skills that empower others and create access to information with the wider team\nYou share wins and failures openly\n\nIngenuity\n\nYou make sound judgement and come up with solutions that are creative and smart. Copy when feasible\nYou challenge the status quo and question things that could be done differently for better. Modify the wheel if you can\u2019t change it\nYou think outside of the box and make value-based innovation\n\nCommunications\n\nYou articulate your thoughts and ideas effectively and respectfully\nYou know your audience and talk in a way they want to be told\nYou make sure communications happens, no matter where you are\n\nSelflessness\n\nYou put the needs of others before one's own and find ways in helping other to succeed\nYou focus on team wins than personal wins and share credits\nYou act in the company's best interest\n\nWe are Prenetics, our people make us who we are.", "employment_types": ["Full Time", "Permanent"], "selling_points": ["Help create mobile and web applications", "Present and review designs", "Conduct layout adjustment"], "locations": ["Quarry Bay"], "categories": ["Design", "Graphics", "Industrial / Product", "Web Designer"], "post_time": "2022-01-14T07:33:42Z", "salary": {"currency": null, "max": null, "min": null, "period": "monthly", "term": null}, "salary_visible": false, "title_keywords": ["graphic designer"], "responsibilities": ["communicate with", "graphics", "ideas", "advertising", "guidelines", "operations", "graphic design", "design", "testing", "review designs", "communication", "motion graphics", "maintain", "visual"], "requirements": {"degrees": ["degree", "bachelor"], "majors": ["graphic design", "fine arts", "design"], "languages": [], "language_level": [], "hard_skills": ["graphics", "plus", "no", "web applications", "web", "indesign", "illustration", "illustrator", "word", "mobile", "visual design", "adobe", "c", "make", "rapid", "r", "focus", "photoshop"], "soft_skills": ["team spirit", "trustworthy", "persistent", "communication", "comprehensive", "visionary", "articulate", "focus", "determined", "integrity", "coherent", "committed", "honest", "creative", "ideal", "unique", "progressive", "accountable", "inspiring", "imaginative"], "languages_combined": []}, "experience_required": {"duration": [], "field": ["digital"]}}, {"job_id": "100003009049609", "location_code": "hk", "company": "Chow Sang Sang Holdings International Limited", "job_title": "Executive - Web Development", "description": "Job Responsibilities:\n\nTake work from concept to final execution within deadline;\nUnderstand marketing initiatives, strategic positioning and target audience;\u00a0\nCommunicate with clients & sales team in order to ensure the design meet customers' requirements;\nCarry out graphic design and artwork production for printing Annual Report purposes as assigned; and\nPerform digital design works including but not limited to design website\u2019s visual imagery, graphics, animations and production of relevant digital photographs.\n\nJob Requirements:\n\nDesign institute graduate or above;\n5 years or above solid experience in graphic/ digital design field;\u00a0\nExperience in the implementation of mobile/ responsive web layouts design would be advantageous;\nProficient in Adobe InDesign, Illustrator and Photoshop, MS Office;\nGood command of both spoken Mandarin & Cantonese;\nSelf-motivated, responsible and detail-oriented;\nA good teamwork player; and\nCandidate with more experience will be considered for the position of\u00a0 Assistant Art Director.\n\nWe offer competitive remuneration package. Interested parties please send full resume including date of availability, current and expected salary\u00a0to HR Department, 2/F, 100QRC, 100 Queen\u2019s Road Central, Hong Kong or by fax to 2523 7232 or by clicking apply now.\n\nTo understand more about EQUITY GROUP, please visit our website at http://www.equitygroup.com.hk\n\nData collected is for recruitment purpose only.", "employment_types": ["Full Time", "Permanent"], "selling_points": ["Web UI implementation for E-learning platform", "Update dynamic client content via AJAX query", "2 yrs or above web development related experience"], "locations": ["Cheung Sha Wan"], "categories": ["Design", "Web Designer", "Information Technology (IT)", "Application Specialist - Software", "UI/UX Designer"], "post_time": "2022-01-14T08:57:43Z", "salary": {"currency": null, "max": null, "min": null, "period": "monthly", "term": null}, "salary_visible": false, "title_keywords": ["executive"], "responsibilities": ["communicate with", "graphics", "graphic design", "artwork production", "website", "design", "sales team", "animations", "visual", "report"], "requirements": {"degrees": [], "majors": [], "languages": ["cantonese", "mandarin"], "language_level": ["good command"], "hard_skills": ["web", "adobe indesign", "illustrator", "mobile", "ms office", "photoshop"], "soft_skills": ["self-motivated", "responsible", "teamwork", "detail-oriented", "responsive"], "languages_combined": [{"language": "cantonese", "language_level": ["good command"]}, {"language": "mandarin", "language_level": ["good command"]}]}, "experience_required": {"duration": ["5 years"], "field": ["art director", "digital", "graphic", "design"]}}, {"job_id": "100003009046902", "location_code": "hk", "company": "Dragon Creative Media Limited", "job_title": "Multimedia Graphic Designer / Graphic Designer", "description": "Responsibilities:\n\nResponsive Web UI implementation for E-learning platform (mainly in JavaScript)\nUpdate dynamic client content via AJAX query and JSON respond\nDesign and build JS reusable Classes object with decent interface\nClearly state inline comments and overall documentation\nPerform other ad-hoc projects and tasks as assigned\nRequirements:\n\nDegree in Computer Science, Information System or other related disciplines, qualification in\u00a0Artificial intelligence will be an advantage\n2 years or above web development related experience\nProficiency in HTML5, CSS, JavaScript (DOM, Classes, and Regular Expression)\nExperience in responsive and mobile-first web design development\nHigh diploma level in Computer Science, or other related disciplines\nFamiliar Photoshop, Illustrator, Dreamweaver with good sense in graphic design will be an advantage\nGood command in written English and/or Chinese\nWe offer 5-day-work week with competitive remuneration packages to the right candidate.\u00a0 Interested parties please send your CV with EXPECTED SALARY through the below application procedure.\n\n(Personal data will be used by Chow Sang Sang (CSS) for recruitment only.\u00a0 CSS may refer suitable applications to other vacancies within CSS and its associated companies.\u00a0 We will retain unsuccessful applications for a maximum period of 24 months)", "employment_types": ["Full Time"], "selling_points": ["5 days work", "At least 1 year multimedia experience", "Strong creative sense"], "locations": ["Southern Area"], "categories": ["Design", "Graphics", "Multi-media", "Web Designer"], "post_time": "2022-01-14T01:40:36Z", "salary": {"currency": null, "max": null, "min": null, "period": "monthly", "term": null}, "salary_visible": false, "title_keywords": ["graphic designer"], "responsibilities": ["comments", "implementation", "design", "documentation", "ad-hoc projects", "ui"], "requirements": {"degrees": ["high diploma", "degree"], "majors": ["related disciplines", "computer science"], "languages": ["english", "chinese"], "language_level": ["good command"], "hard_skills": ["web design", "web development", "information system", "illustrator", "mobile", "javascript", "dreamweaver", "css", "photoshop"], "soft_skills": ["responsive"], "languages_combined": [{"language": "english", "language_level": ["good command"]}, {"language": "chinese", "language_level": ["good command"]}]}, "experience_required": {"duration": ["2 years"], "field": ["related", "development", "design"]}}, {"job_id": "100003009048718", "location_code": "hk", "company": "PERSOLKELLY Hong Kong Limited", "job_title": "UI Designer (E-commerce)(Mobile App)", "description": "Our\u00a0Client, a\u00a0Chinese\u00a0multinational\u00a0e-commerce, retail, Internet, AI and technology conglomerate, is seeking a\u00a0Mobile App UI Designer to support their team.\n\nJob Responsibilities:\n\nSpecialized in graphic, visual communication with knowledge of marketing\nLiaise with internal parties and initiate brainstorming/creative sessions to translate marketing objectives into compelling creative strategies and solutions\nWork closely and support UED team for ongoing and ad hoc promotion or activities\nResponsible for Mobile Application's Design.\nDevelop and standardized the design template for all creative promotion materials for both online and offline channels including POSM, mobile ad banner, etc.\nResponsible for the maintenance of design materials and inventory\n\nJob Requirements:\n\nNeed to be Hong Kong Resident\nGraphic or Digital Design or other related field\nMore 3 years of working experience in design related field, preferable with\u00a0exposure in mobile/ web product/ advertising industry and design studio company\nStrong creative view and ability to communicate and present ideas in a clear\nHigh level of initiative and ability to work under tight deadlines in a fast-paced, team-oriented environment\nGood command of both English and Chinese and proficiency in Putonghua\nApplicants are required to submit the creative design portfolio\n\nGood to have:\n\nExperience in financial or banking products will be advantages\nExperience in animation / UI will be advantages\nTo apply for this position, please click on \u201cApply Now\u201d bottom.\u00a0 All applications will be treated in strict confidence, and used for recruitment purposes only in accordance with PERSOLKELLY Hong Kong Limited\u2019s Privacy Notice.\u00a0", "employment_types": ["Full Time", "Contract"], "selling_points": ["5 day working", "Competitive salary", "Multinational Corporation"], "locations": ["Causeway Bay"], "categories": ["Design", "Graphics", "Multi-media", "Web Designer"], "post_time": "2022-01-14T07:08:04Z", "salary": {"currency": null, "max": null, "min": null, "period": "monthly", "term": null}, "salary_visible": false, "title_keywords": ["ui designer"], "responsibilities": ["ad hoc", "maintenance", "creative promotion materials", "inventory", "design", "develop", "communication", "visual", "liaise with", "internal parties"], "requirements": {"degrees": [], "majors": [], "languages": ["putonghua", "english", "chinese"], "language_level": ["proficiency", "good command"], "hard_skills": ["creative design", "mobile", "web"], "soft_skills": ["clear", "confidence", "creative", "initiative"], "languages_combined": [{"language": "putonghua", "language_level": ["good command"]}, {"language": "english", "language_level": ["proficiency", "good command"]}, {"language": "chinese", "language_level": ["proficiency", "good command"]}]}, "experience_required": {"duration": ["3 years"], "field": ["related", "design", "banking", "advertising industry", "financial"]}}, {"job_id": "100003009050075", "location_code": "hk", "company": "\u8a66\u5413\u5566\u5e02\u5834\u63a8\u5ee3\u6709\u9650\u516c\u53f8", "job_title": "Graphic Designer (5 Days Work)", "description": "Responsibilities:\n\nDesign and Optimization the user experience and for mCloud platform, provide high quality GUI design timely\nEvaluate and balance business needs with user goals, improve the business interactive process.\nWork closely with RD team, able to conduct risk control and resource management, meet project timeline and ensure the design delivery.\nCarry out routinely user experience analysis and improvements for the platform to meet internal and customer needs.\nWork with overseas customers/co-workers during non-office hour if necessary.\nCoordinate with internal /external parties to enhance the design level if necessary.\nParticipate in the ad-hoc assignment if needed\n\nRequirements:\n\nBachelor's degree or above\nHCI, industrial design, information design, computer and other related majors\nMinimum 3 years of experience, preferable in relevant industry, Carriers or other ICT service providers;\nIndependent design experience in medium and large-scale projects and successful cases is preferred;\nSolid design skills, able to explore cutting-edge design trends.\nProficient in using office toolkit and design software, e.g. Photoshop, Sketch, Adobe illustrator, Axure and other design software.\nBasic understanding of various front-end technologies (including HTML / CSS / JavaScript, etc.)\nExcellent teamwork skills, self-motived and able to work under pressure\nOpen-minded, ownership, be creative and think out of the box;\nCurious about cutting-edge user research theories and design tr'ends;\nGood communication and coordination skills, certain management experience;\nExcellent written and verbal communication skills in both English and Mandarin;\nStrong logical thinking, be able to produce excellent design schemes in complex business scenarios; Technical foundation is preferred\n\n** Candidate with less experience will also be considered.\n\nInterested parties please send your full resume with current & expected salary to\u00a0hr@ cmi.chinamobile.com. Please indicate the reference number in the subject line.\n\nAll personal data collected will be used for recruitment and employment related purpose only", "employment_types": ["Full Time", "Permanent"], "selling_points": ["Higher Diploma in Web/ Graphic/ Multimedia Design", "2+ yrs exp. in graphic design", "Good design theory & insight on GUI design trends"], "locations": ["Lai Chi Kok"], "categories": ["Design", "Graphics", "Multi-media", "Web Designer"], "post_time": "2022-01-14T09:58:07Z", "salary": {"currency": null, "max": null, "min": null, "period": "monthly", "term": null}, "salary_visible": false, "title_keywords": ["graphic designer"], "responsibilities": ["ad-hoc", "control", "management", "analysis", "external parties", "quality", "user experience", "design", "coordinate with", "evaluate"], "requirements": {"degrees": ["degree or above", "bachelor"], "majors": [], "languages": ["english", "mandarin"], "language_level": ["excellent"], "hard_skills": ["basic", "html", "adobe illustrator", "javascript", "css", "photoshop"], "soft_skills": ["communication skills", "independent", "coordination skills", "cutting-edge", "open-minded", "teamwork", "communication", "creative", "work under pressure"], "languages_combined": [{"language": "english", "language_level": ["excellent"]}, {"language": "mandarin", "language_level": ["excellent"]}]}, "experience_required": {"duration": ["minimum 3 years"], "field": ["management", "design"]}}, {"job_id": "100003009042084", "location_code": "hk", "company": "Sekgamdong Limited", "job_title": "Web designer", "description": "Responsibilities :\n\n\nVisual design of printed materials\u00a0including product brochures, sales and marketing collateral, promotion materials, \u00a0photo retouching and editing\nProduction of animations, motion graphics, graphic designs and basic videos for Webpage, EDM, Facebook, Instagram and Google Ads\nBrainstorm and collaborate innovative ideas with our sales & marketing team\nHandle ad-hoc tasks or projects as assigned\n\nRequirements:\n\n\nHigher Diploma or above in Web / Graphic / Multimedia Design or related disciplines\n2+ years experience in graphic design\nGood knowledge of design theory and insight on GUI design trends\nBasic Knowledge of Adobe Premiere & After Effect\nExperience in designing user interface for mobile-friendly webpages is an advantage\nCreative, independent, well organized, self-motivated and able to handle multiple projects under tight deadline\nGood interpersonal and communications skills\n\nWe offer 5 days work, 12 days annual leave, medical scheme, health incentive program, attractive remuneration package and bonus scheme. Interested parties please quote Employer Ref. No. and send detailed resume with\u00a0CURRENT & EXPECTED SALARIES\u00a0and available date\u00a0by\u00a0clicking the \"Apply Now\" button.\n\n\nFor company information, please visit our website :\u00a0https://tryhala.com/info/tryhala-about-us/\n\n\nAll information is collected for recruitment purpose only.", "employment_types": ["Full Time", "Permanent"], "selling_points": ["Creative", "Passionate", "Interactive"], "locations": ["Hung Hom"], "categories": ["Media & Advertising", "Creative / Design", "Production", "Design", "Web Designer"], "post_time": "2022-01-12T05:59:43Z", "salary": {"currency": null, "max": null, "min": null, "period": "monthly", "term": null}, "salary_visible": false, "title_keywords": ["designer"], "responsibilities": ["collaborate", "photo retouching", "ideas", "edm", "ad-hoc tasks", "graphic designs", "design", "motion graphics", "animations", "visual", "facebook", "editing"], "requirements": {"degrees": ["higher diploma or above"], "majors": ["multimedia design", "related disciplines"], "languages": [], "language_level": [], "hard_skills": ["basic", "web", "mobile", "adobe premiere", "multimedia", "after effect"], "soft_skills": ["self-motivated", "independent", "well organized", "friendly", "creative", "interpersonal"], "languages_combined": []}, "experience_required": {"duration": ["2+ years"], "field": ["graphic design"]}}, {"job_id": "100003009049628", "location_code": "hk", "company": "TecPal Limited", "job_title": "UX / UI Designer", "description": "Responsibilities :\n\nResponsible for web application and mobile apps UI & UX design\n\nWork closely with Users to provide UX wireframe, flowcharts and UI layouts\nWork closely with developers to ensure the UI & UX are well implemented and met with quality\nExperience in designing responsive UI, wireframe and prototypes is required\nExperience in HTML, CSS and JavaScript is a big advantage\n\nRequirements :\n\nDiploma or above in Web / Graphic / Multimedia Design or related disciplines\nAt least 1 year experience in Web and Graphic Design\nExperience in Figma, Photoshop and Illustrator, knowledge of HTML, CSS and JavaScript will be an advantage\nExperience in UI design\nGood communication skills and a good team player\nAble to work independently, under pressure and meet tight schedule\nPortfolio links should be provided in the resume\n\n\nSalary and benefit will commensurate with qualifications and experience.\u00a0\nWe offer 5-day work, competitive remuneration package & good career opportunities to the qualified candidate.\n\nInterested parties, please\u00a0send your full resume with current and expected\u00a0salary to us via Email.", "employment_types": ["Full Time"], "selling_points": ["Multicultural Workplace", "15-day Annual Leave", "Excellent Career Development"], "locations": ["Hung Hom"], "categories": ["Media & Advertising", "Creative / Design", "Design", "Web Designer", "Information Technology (IT)", "UI/UX Designer"], "post_time": "2022-01-14T08:59:43Z", "salary": {"currency": null, "max": null, "min": null, "period": "monthly", "term": null}, "salary_visible": false, "title_keywords": ["ui designer"], "responsibilities": ["quality", "ui", "design", "designing"], "requirements": {"degrees": ["diploma or above"], "majors": ["multimedia design", "related disciplines"], "languages": [], "language_level": [], "hard_skills": ["web", "illustrator", "html", "javascript", "multimedia", "css", "photoshop"], "soft_skills": ["communication skills", "good team player", "under pressure", "work independently"], "languages_combined": []}, "experience_required": {"duration": ["at least 1 year"], "field": ["graphic design", "design"]}}, {"job_id": "100003009045115", "location_code": "hk", "company": "Xenyo Limited", "job_title": "Web Designer / Senior Web Designer / UI UX Designer", "description": "Responsibilities:\n\n\nCreate innovative user experiences and user interfaces for mobile apps and smart home devices\nIntegrate design features, wireframes, sketches, flow diagrams, style guides and user research into the product development process\nCollaborate with product development and engineering team\nStay up-to-date with the latest UX/UI design trends, tools, best practices\nRequirements:\n\nDiploma or above in Visual Design, interactive Design or similar disciplines\nMore than 3 years of related work experience\nGood knowledge of UX design techniques\nProficiency in Sketch and/or Adobe CS\nGood command in written and spoken English\nSelf-starter, independent and well-organized\nCome and join us in a multi-cultural, dynamic and stable work environment, experience the opportunity to develop your career and to work in different exciting projects in an nicely decorated office.\n\nWe are an Equal Opportunity Employer. Interested parties, please send us your job application, the position you apply, together with Current and Expected Salary. We look forward to your application.", "employment_types": ["Full Time"], "selling_points": ["Strong Portfolio", "Passion to create great user experiences", "Chance to work on large projects"], "locations": ["Kwun Tong"], "categories": ["Media & Advertising", "Creative / Design", "Design", "Graphics", "Web Designer"], "post_time": "2022-01-13T07:12:05Z", "salary": {"currency": null, "max": null, "min": null, "period": "monthly", "term": null}, "salary_visible": false, "title_keywords": ["ux designer", "designer"], "responsibilities": ["collaborate with", "sketches", "design", "design trends", "ui"], "requirements": {"degrees": ["diploma or above"], "majors": ["design"], "languages": ["english"], "language_level": ["good command"], "hard_skills": ["visual design", "adobe cs"], "soft_skills": ["independent", "well-organized"], "languages_combined": [{"language": "english", "language_level": ["good command"]}]}, "experience_required": {"duration": ["3 years"], "field": ["related"]}}, {"job_id": "100003009046052", "location_code": "hk", "company": "Adhoc Fun Limited", "job_title": "Graphic Designer (Internship)", "description": "Xenyo is looking for a UI/ UX designer for our own projects, as well as projects for some of the largest organizations in Asia.. The candidate will have chance to work in an creative environment and amazing team.\n\nDuties\n\nHandle projects from scratch - creative concepts to project delivery on major Hong Kong websites\nSenior candidates to provide leadership role.\nIdentify design problems and devise elegant solutions\nTranslate business requirements to great digital experiences\nBe creative\n\nRequirements\n\nPassion to create great user experiences\nStrong Design Sense & Understanding of UI, UX, Typography and Color\nAttention to Detail and Organised\nGood Creative Portfolio\nAlways eager to improve\nProficiency in Photoshop or Sketch, Illustrator\nAt least 2 years working experience in UI/UX, web and app design\nDiploma or above in Web/Graphic/Multimedia Design, Communication or related disciplines preferred\n\nInterested parties, please send your full resume and portfolio with current & expected salary via JobsDB .\u00a0", "employment_types": ["Part Time", "Internship", "Freelance"], "selling_points": ["Interesting illustration work for the characters", "Currently enrolled in a bachelor\u2019s degree", "Student Internship, Freelance, work form home"], "locations": ["Kwun Tong"], "categories": ["Design", "Graphics", "Multi-media", "Web Designer"], "post_time": "2022-01-13T09:30:18Z", "salary": {"currency": null, "max": null, "min": null, "period": "hourly", "term": null}, "salary_visible": false, "title_keywords": ["graphic designer", "internship"], "responsibilities": ["design"], "requirements": {"degrees": ["diploma or above"], "majors": ["multimedia design", "related disciplines"], "languages": [], "language_level": [], "hard_skills": ["multimedia", "illustrator", "web", "photoshop"], "soft_skills": ["communication", "creative", "attention to detail", "organised"], "languages_combined": []}, "experience_required": {"duration": ["at least 2 years"], "field": ["design"]}}, {"job_id": "100003009042608", "location_code": "hk", "company": "ESD Services Limited (ESDlife)", "job_title": "Web Designer", "description": "Job Responsibilities\n\nl\u00a0\u00a0 Responsible for creating, develop creative concepts to design, artwork and the final output to meet business objectives\n\nl\u00a0\u00a0 Create awesome and interesting illustration work for the characters\n\nl\u00a0\u00a0 Handle content creation, design and production assets for the character brand, including brand style guides and other design materials across Omni channels\n\nl\u00a0\u00a0 Support the team in other ad-hoc activities as required and necessary\n\nRequirements:\n\nl\u00a0\u00a0 Currently enrolled in a bachelor\u2019s degree, Higher Diploma or equivalent in Visual Arts / Design / Creative or other related disciplines, must be enrolled in an accredited university/college program to receive credit\n\nl\u00a0\u00a0 Creative and enthusiastic, strong in storytelling, visual communication and creating engaging experiences\n\nl\u00a0\u00a0 Strong sense on Graphic, Layout, Coloring and usability on graphics and images with inputting creative concepts and designs\n\nl\u00a0\u00a0 Proficient in design software such as Photoshop / Illustrator / Procreate\n\nl\u00a0\u00a0 Good command of English and Chinese\n\nl\u00a0\u00a0 Shows initiative, drive and a commitment to innovation\n\nl\u00a0\u00a0 Strong sense of responsibility, self-motivated and able to work independently as well as a good team player\n\nWe offer attractive remuneration and fringe benefits to the right candidates. Please send us the application by clicking the \"Apply Now\" button, together with a detailed resume,\u00a0current and expected salary.\n\n\u00a0We will only notify suitable candidates for an interview. Thank you!\n\nWe are an equal opportunity employer and welcome applications from all qualified candidates. Personal data provided by job applicants will be used only for recruitment purpose and will be kept strictly confidential. Information of unsuccessful candidates will be properly disposed within 6 months.", "employment_types": ["Full Time", "Permanent"], "selling_points": [], "locations": ["Hung Hom"], "categories": ["Design", "Web Designer", "Information Technology (IT)", "UI/UX Designer"], "post_time": "2022-01-12T08:09:09Z", "salary": {"currency": null, "max": null, "min": null, "period": "monthly", "term": null}, "salary_visible": false, "title_keywords": ["designer"], "responsibilities": ["ad-hoc", "develop creative concepts", "support the team", "design"], "requirements": {"degrees": ["diploma", "degree", "bachelor"], "majors": ["related disciplines", "design"], "languages": ["english", "chinese"], "language_level": ["good command"], "hard_skills": ["graphics", "visual communication", "illustrator", "photoshop"], "soft_skills": ["self-motivated", "work independently", "good team player", "sense of responsibility", "communication", "enthusiastic", "creative", "initiative"], "languages_combined": [{"language": "english", "language_level": ["good command"]}, {"language": "chinese", "language_level": ["good command"]}]}, "experience_required": {"duration": [], "field": []}}, {"job_id": "100003009042636", "location_code": "hk", "company": "Openrice Limited", "job_title": "Junior Web Designer", "description": "Passionate in graphic design and eager to take part in innovative projects for various industries?\nWe are looking for a graphic designer to join our small yet dynamic team. We welcome anyone with a passion for visual communication, digital design and the marketing field. You will be able to work in a flexible, fast-paced and creative environment.\n\nWHAT WE ARE LOOKING FOR:\n\n1. CHARACTER:\n\nHungry for challenges and achievements\nCreative with advanced problem-solving skills\nEager to explore new things\nProactive and able to work as a team player\n\n2. EDUCATION AND SKILLS:\n\nUniversity graduates with 1-2 years of relevant experience\u00a0in Design (fresh graduate with outstanding potential will also be considered)\nStrong sense in layout, typographic and graphic design\nExperience in \u00a0UX/UI design for web portal, e-commerce or mobile application will be an advantage\nHighly proficient in Adobe Creative Suite, including Photoshop, Illustrator, InDesign, XD, etc.\n\u00a0Language\nProficiency in Chinese and English writing and reading; Mandarin will be an advantage\nOrganization and multitasking\nAbility to organize and manage multiple projects simultaneously in a fast-paced environment\n\nWHAT WE OFFER:\n\nOpportunities to be involved in product branding and marketing designs\nExciting challenges and engaging projects including graphics for social media, logo design, UI/UX design, and etc.\nCreative work environment with little office hierarchy\nMarket-competitive rate\nA chance to work with a team of top notch web experts\n\nWHAT WHAT YOU WILL DO:\n\n30%:\u00a0Collaborate with the Development and Marketing Team to execute design solutions (web/print/social media) that comply with project specifications, brand identity and strategic marketing goals\n25%:\u00a0Visualize concepts into rough drafts as the foundation for future execution, establish standards for style, aesthetics and typeface; design preliminary layout.\n25%:\u00a0Contribute to brainstorming workshops in projects and product innovation\n20%:\u00a0Participate in other innovative projects and learning opportunities under the group\u2019s investments", "employment_types": ["Full Time", "Permanent"], "selling_points": ["Stable and fast growing business", "Flexible working hours", "Immediate availability is preferred"], "locations": ["Quarry Bay"], "categories": ["Media & Advertising", "Production", "Design", "Graphics", "Web Designer"], "post_time": "2022-01-12T08:14:59Z", "salary": {"currency": null, "max": null, "min": null, "period": "monthly", "term": null}, "salary_visible": false, "title_keywords": ["designer", "junior"], "responsibilities": ["graphic design", "manage multiple projects", "design", "communication", "visual", "ui"], "requirements": {"degrees": ["fresh graduate"], "majors": ["design"], "languages": ["english", "chinese", "mandarin"], "language_level": ["advantage", "proficiency"], "hard_skills": ["small", "web", "e-commerce", "indesign", "illustrator", "mobile", "visual communication", "dynamic", "problem-solving skills", "adobe creative suite", "photoshop"], "soft_skills": ["passionate", "flexible", "proactive", "manage multiple projects simultaneously", "creative", "advanced", "passion for", "work as a team", "fast-paced environment", "communication", "dynamic", "problem-solving skills", "innovative"], "languages_combined": [{"language": "english", "language_level": ["proficiency"]}, {"language": "chinese", "language_level": ["proficiency"]}, {"language": "mandarin", "language_level": ["advantage"]}]}, "experience_required": {"duration": ["1-2 years"], "field": ["relevant experience", "design", "e-commerce"]}}, {"job_id": "100003009055732", "location_code": "hk", "company": "Lorence & Company Limited", "job_title": "Web and Graphic Designer", "description": "Responsibilities:\n\nProvide support to the Design and Marketing teams in designing, developing and executing promotional materials\nProduce a range of communication and collateral materials under group branding guidelines, such as print and online advertising, posters, leaflets, tent cards, menus and websites etc.\nAd-hoc projects as assigned\n\n\u00a0Requirements:\n\nDiploma holder or above in Graphic / Multimedia Design or related disciplines\nMinimum 1 year relevant experience\u00a0\nProficiency in Mac, knowledge in Adobe Creative Suite\nExperience in F&B and branding design\nKnowledge of food & product shooting is an advantage\nGood art sense & graphic skills, passionate, creative and energetic\nGood communication skills in English and Cantonese\nAble to multi task under tight deadlines\nImmediately available is preferred\n\nPlease send full resume and expected salary email by click \u201cApply Now\u201d.\n\nAll information obtained will be kept in strict confidence and will be used for recruitment purpose only.", "employment_types": ["Full Time", "Permanent"], "selling_points": [], "locations": ["Kwun Tong"], "categories": ["Design", "Graphics", "Web Designer"], "post_time": "2022-01-18T02:53:55Z", "salary": {"currency": null, "max": null, "min": null, "period": "monthly", "term": null}, "salary_visible": false, "title_keywords": ["graphic designer"], "responsibilities": ["provide support", "guidelines", "leaflets", "teams", "developing", "design", "communication", "promotional materials", "executing", "designing", "ad-hoc projects", "online advertising"], "requirements": {"degrees": ["diploma holder"], "majors": ["multimedia design", "related disciplines"], "languages": ["cantonese", "english"], "language_level": ["good"], "hard_skills": ["multimedia", "adobe creative suite"], "soft_skills": ["passionate", "communication skills", "confidence", "creative", "energetic"], "languages_combined": [{"language": "cantonese", "language_level": ["good"]}, {"language": "english", "language_level": ["good"]}]}, "experience_required": {"duration": ["minimum 1 year"], "field": ["f&b", "relevant experience", "design"]}}, {"job_id": "100003009055716", "location_code": "hk", "company": "AXA Hong Kong", "job_title": "User Experience Researcher", "description": "As our User Researcher of our Design Hub team in Hong Kong, your primary mission will be to understand the needs and product requirements and transform that understanding into user-focused and intuitive products and services.\n\nYou will:\n\nmanage and run all forms of requirement gathering, user research, UX workshop, customer interview, usability testing, focus group etc.\nfacilitate the product vision by researching, sketching, prototyping and user-testing experiences for digital products\ndesign experiences through human-centred-design\nensure that research findings and insights are translated into actionable product goals and direction and sharing insights with stakeholders\ncreate wireframes (from sketches to high-fidelity ones)\ntranslate concepts into user flows & wireframes\ncreate rapid prototypes to validate design concepts with stakeholders and customers\nrun workshops and other group activities\nContributing to on-going enhancement of customer experience and user experience methodologies\nstay abreast of UX and technology trends and look for inspiration\n\nRequirements:\n\nMinimum of 5 years relevant experience as a User Researcher, interaction designer or similar roles\nnative Cantonese speaker with strong local cultural understanding. Fluent and comfortable in English\nexperienced in user research, prototyping and user testing methodologies\nunderstand Agile / iterative project management methodologies\nable to handle a Mac and the usual tools (Adobe, Sketch)\nbe a self-motivated and resilient team player driving collaboration\nwith strong sense of personal accountability", "employment_types": ["Full Time", "Permanent"], "selling_points": ["user research", "UX workshop", "customer interview"], "locations": ["Not Specified"], "categories": ["Design", "Multi-media", "Web Designer", "Information Technology (IT)", "UI/UX Designer"], "post_time": "2022-01-18T02:52:52Z", "salary": {"currency": null, "max": null, "min": null, "period": "monthly", "term": null}, "salary_visible": false, "title_keywords": ["researcher"], "responsibilities": ["design concepts", "workshop", "user experience", "sketches", "design", "testing", "project management"], "requirements": {"degrees": [], "majors": [], "languages": ["cantonese", "english"], "language_level": ["native", "fluent"], "hard_skills": ["agile", "project management", "adobe", "rapid", "workshops", "focus"], "soft_skills": ["self-motivated", "agile", "focused", "accountability", "project management", "team player", "focus"], "languages_combined": [{"language": "cantonese", "language_level": ["native"]}, {"language": "english", "language_level": ["fluent"]}]}, "experience_required": {"duration": ["minimum of 5 years"], "field": ["designer", "design", "testing", "relevant experience", "digital"]}}, {"job_id": "100003009047350", "location_code": "hk", "company": "YOOV Internet Technology (HK) Limited", "job_title": "UI/UX Designer (5-day work)", "description": "To cope with our business growth, we are currently looking for a high calibre candidate to join us as an UI/UX Designer, mainly focus on the product design of our cloud-based low code system.\n\n\n\nResponsibilities\n\n\nIllustrate and present design ideas using storyboards, flow maps, and wireframes\nDesign delightful interactions and intuitive user interface that help our users accomplish their tasks efficiently and effectively\nCreate high-quality user interface designs for different devices that elevate the user experience and achieve business requirements\nBuild high fidelity prototypes for review and usability testing\nHelp the team develop and maintain the design system\nAssist the product team prepare and conduct usability testing and user research\n\nRequirements\n\nDegree or diploma holder in Interaction Design, Communication Design, HCI, or related disciplines\n1-2 years experience working as a UI/UX Designer or related fields\nProficient with design tools such as Figma and Sketch\nExcellent communication, presentation, and interpersonal skills\nFundamental understanding of web design standards and best practices\nExperience in HTML/CSS, app development, and B2B products is an advantage\nMust submit a soft copy or a link of your portfolio (Candidates with no portfolio will not be considered)\nInterested candidates please send your job application to our HR Department by \u201cAPPLY NOW\u201d. Please indicate the details of your working experience, current and expected salary, and your date of availability in your CV.\n\n(Only shortlisted candidates will be contacted)\n\nPersonal Information Collection Statement (PICS)\n\nThe personal data collected will be used by our member(s) of the recruitment team for recruitment purpose only. It is our policy to retain the personal data of unsuccessful applicants for future recruitment purposes for a period of 3 months. When there are vacancies in our subsidiary or associate companies during that period, we may transfer the candidate\u2019s application to them for consideration of employment. And, all information will be kept confidential during that period and be destroyed after use.\n", "employment_types": ["Full Time", "Permanent"], "selling_points": ["User experience and interface design", "Excellent Career Development Opportunity", "Work-Life Balance Fast Growing IT Company"], "locations": ["Kwun Tong"], "categories": ["Design", "Web Designer", "Information Technology (IT)", "Software Development", "UI/UX Designer"], "post_time": "2022-01-14T02:52:55Z", "salary": {"currency": null, "max": null, "min": null, "period": "monthly", "term": null}, "salary_visible": false, "title_keywords": ["ux designer"], "responsibilities": ["ideas", "review", "quality", "user experience", "design", "testing", "develop", "user interface", "maintain", "storyboards"], "requirements": {"degrees": ["diploma holder", "degree"], "majors": ["related disciplines", "design"], "languages": [], "language_level": [], "hard_skills": ["css", "web design", "no", "html"], "soft_skills": ["communication", "interpersonal skills", "presentation"], "languages_combined": []}, "experience_required": {"duration": ["1-2 years"], "field": ["related", "development", "designer"]}}, {"job_id": "100003009051331", "location_code": "hk", "company": "Big Leap Global Limited", "job_title": "APP UI/UX Designer", "description": "Big Leap Global - Your Trusted Partner in Blockchain APP Development\n\nIf the internet revolutionized the world in the 2000s, social media changed the game in 2010s, then in 2020s, blockchain and internet will be the winning factor for those adopt it to eliminate those do not.\u00a0\n\nWe are a blockchain and game mobile application firm with user-oriented mindsets.\n\nWith our expertise in UI/UX design, blockchain software development and marketing & user penetration, we provide solutions to CEO, CTO or product managers who are looking to outsource their blockchain development. We help companies not just to design and build great social media and blockchain apps but we help them to take it to the world!\n\nIf you see the future of technology like we do, and you are determined to fast track your career by entering one of the most rapidly growing industries in the 2020s, come join us.\u00a0\n\nWe are sure you can design something even nicer than a Shiba Inu on a coin. How about Corgi?\n\n\n\n\n\nHow you can create the next big thing:\n\nYou will be reporting to the senior designer and will be contributing your highly usable and intuitive interface creation for our mobile app and mobile game projects. Your design shall be easy for users to digest and trigger users to share the product with their friends.\u00a0\n\n\n\nDevelop intuitive, usable, and engaging interactions and visual designs for mobile.\nCreate wireframes, page flows, mockup / interactive prototypes across mobile and desktop to communicate interaction and design ideas\nCollaborate with cross-functional teams (executive suite, marketing, engineering, operation) throughout the design process\nParticipate in the full-cycle development process from definition, through design, build, test, release, and maintenance.\nResearch and track advancements in latest mobile application design patterns in the blockchain field and the several key competitors of each project.\u00a0\n\nWhat makes you a game changer:\n\n\n\n2-years or above solid experience in designing UI of mobile applications and mobile web pages.\u00a0\nDiploma or above in Web Design / Graphic / Multimedia design or related discipline\nExperience working with blockchain startup will be an advantage\nExperience in unity\u00a0\nIntermediate to knowledge of relevant technologies and tools (e.g., HTML/CSS,Photoshop, Illustrator)\nAble to work under pressure with tight deadlines with a strong sense of responsibility\nWhat\u2019s next?\n\n\nTo facilitate the recruitment process, remember to insert the followings in your resume,\u00a0\n\n\nLinks to your design portfolio\nYour current salary and expected salary\nYour availability for reporting duties\nThis will help us to choose your profile easier among the numerous applications.\u00a0\n", "employment_types": ["Full Time", "Permanent"], "selling_points": ["Acquire valuable blockchain exposure", "Global projects", "Work closely within small teams"], "locations": ["Central & Western Area"], "categories": ["Design", "Multi-media", "Web Designer", "Information Technology (IT)", "UI/UX Designer"], "post_time": "2022-01-15T09:22:20Z", "salary": {"currency": null, "max": null, "min": null, "period": "monthly", "term": null}, "salary_visible": false, "title_keywords": ["ux designer"], "responsibilities": ["collaborate with", "social media", "reporting", "multimedia design", "mobile app", "software", "ideas", "maintenance", "designing", "provide solutions", "design", "develop", "visual", "recruitment process", "ui", "cross-functional teams", "work under pressure"], "requirements": {"degrees": ["diploma or above"], "majors": ["multimedia design", "web design"], "languages": [], "language_level": [], "hard_skills": ["blockchain", "web design", "maintenance", "illustrator", "web pages", "html", "mobile", "factor", "multimedia", "css", "unity", "photoshop"], "soft_skills": ["sense of responsibility", "determined", "work under pressure"], "languages_combined": []}, "experience_required": {"duration": [], "field": []}}, {"job_id": "100003009046604", "location_code": "hk", "company": "RollAngle", "job_title": "Graphic Designer", "description": "Passionate in graphic design and eager to take part in innovative projects for various industries?\nWe are looking for a graphic designer to join our small yet dynamic team. We welcome anyone with a passion for visual communication, digital design and the marketing field. You will be able to work in a flexible, fast-paced and creative environment.\n\nWHAT WE ARE LOOKING FOR:\n\n1. CHARACTER:\n\nHungry for challenges and achievements\nCreative with advanced problem-solving skills\nEager to explore new things\nProactive and able to work as a team player\n\n2. EDUCATION AND SKILLS:\n\nUniversity graduates with 1-2 years of relevant experience\u00a0in Design (fresh graduate with outstanding potential will also be considered)\nStrong sense in layout, typographic and graphic design\nExperience in \u00a0UX/UI design for web portal, e-commerce or mobile application will be an advantage\nHighly proficient in Adobe Creative Suite, including Photoshop, Illustrator, InDesign, XD, etc.\n\u00a0Language\nProficiency in Chinese and English writing and reading; Mandarin will be an advantage\nOrganization and multitasking\nAbility to organize and manage multiple projects simultaneously in a fast-paced environment\n\nWHAT WE OFFER:\n\nOpportunities to be involved in product branding and marketing designs\nExciting challenges and engaging projects including graphics for social media, logo design, UI/UX design, and etc.\nCreative work environment with little office hierarchy\nMarket-competitive rate\nA chance to work with a team of top notch web experts\n\nWHAT WHAT YOU WILL DO:\n\n30%:\u00a0Collaborate with the Development and Marketing Team to execute design solutions (web/print/social media) that comply with project specifications, brand identity and strategic marketing goals\n25%:\u00a0Visualize concepts into rough drafts as the foundation for future execution, establish standards for style, aesthetics and typeface; design preliminary layout.\n25%:\u00a0Contribute to brainstorming workshops in projects and product innovation\n20%:\u00a0Participate in other innovative projects and learning opportunities under the group\u2019s investments", "employment_types": ["Full Time", "Permanent"], "selling_points": ["Design > Graphics", "Design > Multi-media", "Design > Web Designer"], "locations": ["Kwun Tong"], "categories": ["Design", "Graphics", "Multi-media", "Web Designer"], "post_time": "2022-01-13T16:19:15Z", "salary": {"currency": null, "max": null, "min": null, "period": "monthly", "term": null}, "salary_visible": false, "title_keywords": ["graphic designer"], "responsibilities": ["graphic design", "manage multiple projects", "design", "communication", "visual", "ui"], "requirements": {"degrees": ["fresh graduate"], "majors": ["design"], "languages": ["english", "chinese", "mandarin"], "language_level": ["advantage", "proficiency"], "hard_skills": ["small", "web", "e-commerce", "indesign", "illustrator", "mobile", "visual communication", "dynamic", "problem-solving skills", "adobe creative suite", "photoshop"], "soft_skills": ["passionate", "flexible", "proactive", "manage multiple projects simultaneously", "creative", "advanced", "passion for", "work as a team", "fast-paced environment", "communication", "dynamic", "problem-solving skills", "innovative"], "languages_combined": [{"language": "english", "language_level": ["proficiency"]}, {"language": "chinese", "language_level": ["proficiency"]}, {"language": "mandarin", "language_level": ["advantage"]}]}, "experience_required": {"duration": ["1-2 years"], "field": ["relevant experience", "design", "e-commerce"]}}, {"job_id": "100003009044129", "location_code": "hk", "company": "Goodbye Dear Company Limited", "job_title": "UI UX designer", "description": "You will:\u00a0\n\nDevelop creative concepts, artworks, design layout, animation for promotional & marketing materials on websites, social media, EDM, etc.\nFrontend related design/development works on other digital platforms such as eDM, webpage\nWork closely with Marketing Team to ensure all outputs are on brand and in line with commercial objectives\n\nYou should have / be:\u00a0\n\n\nCREATIVE MIND with STRONG AESTHETIC SENSE\nDegree holder in Advertising, Creative Media, Graphic Design or related disciplines\n2-3 years\u2019 experience in related area with eCommerce knowledge\nCreative mind with strong aesthetic sense\nProficiency in Adobe Photoshop & Illustrator\nGood knowledge in HTML5, CSS & UI/UX design. Knowledge of related frameworks like bootstrap would be an advantage\nPassionate, self-motivated, responsible, able to work independently but also a great team player\nGood at communicating in English and Cantonese\nCandidate with more experience will be considered as 'Senior Web Designer'\nPortfolio links should be provided in the resume\n\n\u00a0In addition, you will be able to:\u00a0\u00a0\u00a0\n\nEnjoy an attractive and competitive remuneration package\nReceive training and development opportunities\n\nPlease send in your\u00a0full resume, portfolio links and expected salary by \u201cApply Now\u201d.\n\nTo know more about us, please visit our website at\u00a0https://corporate.esdlife.com/\u00a0and\u00a0https://health.esdlife.com/shop/hk/\n\n\nWe are an equal opportunity employer and welcome applications from all qualified candidates. The information provided will be treated in strict confidence and used only for consideration of application for relevant/similar post(s) within the Hutchison Group of Companies.\n\nApplicants not having heard from us within four weeks from the date of this advertisement may consider their application unsuccessful. All personal data of unsuccessful applicants will be destroyed after the recruitment exercise when no longer required.", "employment_types": ["Full Time", "Contract"], "selling_points": [], "locations": ["Kwun Tong"], "categories": ["Design", "Multi-media", "Web Designer", "Information Technology (IT)", "UI/UX Designer"], "post_time": "2022-01-13T03:09:46Z", "salary": {"currency": null, "max": null, "min": null, "period": "monthly", "term": null}, "salary_visible": false, "title_keywords": ["ux designer"], "responsibilities": ["social media", "advertising", "edm", "graphic design", "website", "design", "recruitment", "marketing materials", "personal data", "develop creative concepts", "ui", "animation"], "requirements": {"degrees": ["degree holder"], "majors": ["related disciplines", "creative media", "graphic design"], "languages": ["cantonese", "english"], "language_level": ["good"], "hard_skills": ["no", "web", "adobe photoshop", "illustrator", "css"], "soft_skills": ["passionate", "self-motivated", "work independently", "confidence", "responsible", "team player", "creative"], "languages_combined": [{"language": "cantonese", "language_level": ["good"]}, {"language": "english", "language_level": ["good"]}]}, "experience_required": {"duration": ["2-3 years"], "field": ["related", "ecommerce", "designer"]}}, {"job_id": "100003009042115", "location_code": "hk", "company": "\u91ab\u7d50\u6709\u9650\u516c\u53f8", "job_title": "UI/UX Designer (App & Web)", "description": "JOIN OpenRice\u2026\u2026if you want to service our\n\n\u00a05 million App users with\n\n\u00a09 million pageviews per day in Hong Kong!\u00a0\n\n\nOpenRice\u00a0is seeking an energetic and passionate individual to join a dynamic and collaborative environment as part of marketing\u00a0team.\n\nYou will be responsible for:\n\nResponsible for the creation, design, development of internal campaign / client projects\nDevelop creative concept and art direction for marketing campaign\u00a0\nHandle advertising, creative development and design projects\nCo-work with different departments on advertising campaigns\n\nYou should possess:\n\nExpress your idea using graphic and motion graphics\nProactively take responsibility of the quality of work under your care\n1-2 years relevant experience\nA strong sense of design aesthetics, artistic talent and creativity\nGood knowledge across the Adobe Creative Suite and motion graphic software for web\nOther creative skills like illustration, 3D rendering / Programming will be considered as a bonus\nEnjoy working in a team environment and be wholehearted\nIMPORTANT PLEASE NOTE: We want to see your best work. For fast attention, please link prominently to an online portfolio of no more than ten examples of your best work. Thanks :)\n\n\nWe offer a competitive remuneration package including excellent career prospects to the right candidate. Interested parties please submit your detailed resume with expected salary and available date by clicking the Quick Apply button.\n\nAll personal information submitted by job applicants will be used for recruitment purposes and we reserve the rights to consider the applications for other positions in our Group.", "employment_types": ["Full Time", "Permanent"], "selling_points": ["Leading Insurtech Company", "Energetic company", "Young and Passionate Team"], "locations": ["Kwun Tong"], "categories": ["Design", "Web Designer", "Information Technology (IT)", "UI/UX Designer"], "post_time": "2022-01-12T06:16:19Z", "salary": {"currency": null, "max": null, "min": null, "period": "monthly", "term": null}, "salary_visible": false, "title_keywords": ["ux designer"], "responsibilities": ["advertising", "software", "3d rendering", "quality", "design", "develop", "motion graphics", "advertising campaigns", "motion graphic"], "requirements": {"degrees": [], "majors": [], "languages": [], "language_level": [], "hard_skills": ["graphics", "no", "web", "dynamic", "programming", "illustration", "adobe creative suite"], "soft_skills": ["passionate", "creative", "responsible", "enjoy working", "collaborative", "dynamic", "energetic"], "languages_combined": []}, "experience_required": {"duration": ["1-2 years"], "field": ["relevant experience"]}}, {"job_id": "100003009042863", "location_code": "hk", "company": "Casetagram Limited", "job_title": "Senior UXUI Designer", "description": "Job Highlights\n\nWebsite and mobile app user interface designs\nGraphic and digital design for banner\nWork with project and development team\n\nJob Responsibilities\n\nWebsite and mobile app user interface designs;\nProduce all kind of graphic and digital design for banner and other presentation materials;\nWork with project and development team; and\nManage any ad-hoc tasks or projects as assigned.\n\nJob Requirements:\n\nHigher Diploma or above in digital design, multimedia design, graphic communications or related field;\nMinimum 1 years' of working experience in design related field\nHands on skills in Adobe Photoshop, Illustrator, Sketch;\nKnowledge of UI design principles and techniques;\nDetail minded with can-do attitude and ability to multitask;\nProvide online portfolio link in addition to resume. *Immediate availability is preferred\n\nWorking location & hours\n\n5-days work\nWork in Kwun Tong", "employment_types": ["Full Time", "Permanent"], "selling_points": ["Websites/ Mobile/ Apps - Senior UXUI Designer", "E-commerce & Transactional Site Design", "Shopify Site Designs / SDK are advantageous"], "locations": ["Kwun Tong"], "categories": ["Design", "Multi-media", "Web Designer", "E-commerce", "Software Development"], "post_time": "2022-01-12T09:02:48Z", "salary": {"currency": null, "max": null, "min": null, "period": "monthly", "term": null}, "salary_visible": false, "title_keywords": ["designer"], "responsibilities": ["mobile app", "ad-hoc tasks", "website", "design", "user interface"], "requirements": {"degrees": ["higher diploma or above"], "majors": ["multimedia design", "communications", "design"], "languages": [], "language_level": [], "hard_skills": ["illustrator", "adobe photoshop", "multimedia"], "soft_skills": ["ability to multitask", "hands on", "can-do attitude"], "languages_combined": []}, "experience_required": {"duration": ["minimum 1 years"], "field": ["related", "design"]}}, {"job_id": "100003009042072", "location_code": "hk", "company": "Osmium Consulting Group Limited", "job_title": "UI / UX Designer | 38k-48k", "description": "Conduct researches, prototyping, interaction design and implementation for a large-scale digital transformation project.\nCreate user interface and user experience sketches, prototype, concept models and detail schematics and wireframe for desktop and mobile applications and other promotion materials of the company.\nWork\u00a0independent with the Project team and stakeholders to ensure project are executed on-time.\nRequirements\u00a0\n\n3 years or above relevant experience would be preferred.\nProficiency in\u00a0Figma/Sketch and Adobe Creative Suite.\nExperience in\u00a0inVision and Powtoon\u00a0would be an advantage.\nHigher Diploma or above in Graphic Design, Multimedia Design or related discipline.\nSelf-motivated, with high energy and an engaging level of enthusiasm.\nGood written communication skills in Chinese and English.\nCandidate\u00a0with more\u00a0experience will be considered\u00a0as Senior\u00a0UI/UX Designer\nWe offer:\n5 days work week\nOn-Job and Online Training\nMedical Insurance\nDouble Pay and Bonus\nTeam Building Activity\nWork Life Balance\nDynamic Environment\nYour application will go directly to MediConCen Limited.\n\n\nPersonal data will be used for recruitment purposes only.", "employment_types": ["Full Time"], "selling_points": ["UX UI Designer | In House | Rare Opportunity", "5 Days Work | Bouns | Med", "Work From Home"], "locations": ["Not Specified"], "categories": ["Media & Advertising", "Creative / Design", "Design", "Web Designer", "Information Technology (IT)", "UI/UX Designer"], "post_time": "2022-01-12T05:54:06Z", "salary": {"currency": null, "max": null, "min": null, "period": "monthly", "term": null}, "salary_visible": false, "title_keywords": ["ux designer"], "responsibilities": ["multimedia design", "graphic design", "implementation", "sketches", "design", "user experience", "user interface", "communication", "ui"], "requirements": {"degrees": ["higher diploma or above"], "majors": ["multimedia design", "graphic design"], "languages": ["english", "chinese"], "language_level": ["good"], "hard_skills": ["mobile", "multimedia", "adobe creative suite"], "soft_skills": ["communication skills", "self-motivated", "creative", "independent"], "languages_combined": [{"language": "english", "language_level": ["good"]}, {"language": "chinese", "language_level": ["good"]}]}, "experience_required": {"duration": ["3 years"], "field": ["relevant experience", "designer"]}}, {"job_id": "100003009040331", "location_code": "hk", "company": "I-Skincare Company Limited", "job_title": "Graphic Designer (Tsim Sha Tsui / 5 Days work)", "description": "Casetify is looking for a Senior UXUI designer experienced in information architecture, interaction, and user testing to join our team. You will collaborate with the E-commerce team to design and build next generation Web/mobile applications. The right candidates will be excellent communicators, comfortable in a high-velocity startup, and passionate about creating products that transform people\u2019s lifestyle.\nResponsibilities:\nPrepare UX/UI design and materials including wire framing, mockup and rapid prototyping for various interfaces, including websites, mobile devices and apps for ecommerce site;\nAnalyze current user journey to understand motivation, expose pain points, issues and improvement opportunities;\nConduct user research, A/B testing, and propose solutions to optimize customer experience;\nCommunicate concepts and work collaboratively with project team / Tech team in order to develop the most efficient design schemas;\nSit with developers to do pixel-perfect reviews of frontend products before they are pushed in production;\nConsume our Design System library and contribute to its evolution.\nRequirements:\n\n\nBachelor Degree in Creative Media / Interactive Design / Web Design / Web Development;\n5+ years of experience building transactional website;\nSpecific experience in a fast growing ecommerce company;\nAbility to solve problems of complexity through smart design;\nBeing data-driven, and be able to back up your assertions with data, with proficiency in analytic tools - Hotjar, Google Analytics, Optimizely etc;\nA user-first attitude and ensure we consistently deliver a user-centric culture;\nStrong understanding of web grids and browser limitations;\nFamiliarity with usability testing, A/B testing methods;\nProficiency with Photoshop, Adobe XD, Webflow, HTML, CSS, PHP;\nBouns: Experience with Shopify site designs / SDK.\nPlease include 2 URLs of your Open Source, personal projects into your resume.\n\n", "employment_types": ["Full Time", "Permanent", "Contract"], "selling_points": ["Visual creation and video editing", "Min. 3 years of design experience", "Proficient in Illustratior and Photoshop"], "locations": ["Tsim Sha Tsui"], "categories": ["Design", "Graphics", "Multi-media", "Web Designer"], "post_time": "2022-01-12T02:18:27Z", "salary": {"currency": null, "max": null, "min": null, "period": "monthly", "term": null}, "salary_visible": false, "title_keywords": ["graphic designer"], "responsibilities": ["design", "develop", "testing", "mobile devices", "ui"], "requirements": {"degrees": ["degree", "bachelor"], "majors": ["creative media", "web design", "design"], "languages": [], "language_level": [], "hard_skills": ["web design", "web development", "google analytics", "web", "php", "adobe xd", "shopify", "html", "css", "photoshop"], "soft_skills": ["solve problems", "creative", "driven"], "languages_combined": []}, "experience_required": {"duration": ["5+ years"], "field": ["ecommerce"]}}, {"job_id": "100003009046440", "location_code": "hk", "company": "PressLogic Limited", "job_title": "Graphic Designer", "description": "\u00a0Responsibilities :\nDesign product flows and journeys that optimize user experience based on the acquired insights as well as business and technical requirements.\u00a0\nFollow through product from concept development, artwork design\u00a0and production\nExecute creative solutions to meet the client needs\nDevelop pixel-perfect UI components that are ready for production and ensure design consistency across different app and web platforms.\nDevelop pixel-perfect UI components that are ready for production and ensure design consistency across different app and web platforms.\nCreate compelling user interface designs for Mobile apps and\nwebsites\n\n\u00a0Requirements :\n\nDiploma or above in Graphic / Multimedia Design or related\u00a0disciplines\n3+ years of UX and UI design experience and have experience designing for large customer-facing platforms.\nUnderstanding of UI/UX design methodologies on mobile and desktop platform\nStrong skilled in Figma, Adobe, Sketch, etc.\n\nStrong self-motivation to start and run the work individually and with the teams.\n\nGood understanding of interaction, journeys and prototyping is an advantage\nSelf-motivated, willing to learn, and a strong sense of responsibility and commitment\nExperienced in the Website interface will be an advantag\nMore experience shall be considered as a Senior\u00a0UI / UX Designer", "employment_types": ["Full Time", "Permanent"], "selling_points": ["Birthday Leave & Work Anniversary Leave", "Fun, young and joyful office environment", "Social Media Graphic Design - Branding Development"], "locations": ["Lai Chi Kok"], "categories": ["Media & Advertising", "Creative / Design", "Design", "Graphics", "Web Designer"], "post_time": "2022-01-13T11:11:32Z", "salary": {"currency": null, "max": null, "min": null, "period": "monthly", "term": null}, "salary_visible": false, "title_keywords": ["graphic designer"], "responsibilities": ["user experience", "design", "develop", "user interface", "ui"], "requirements": {"degrees": ["diploma or above"], "majors": ["multimedia design", "related disciplines"], "languages": [], "language_level": [], "hard_skills": ["mobile", "adobe", "multimedia"], "soft_skills": ["self-motivated", "self-motivation", "willing to learn", "sense of responsibility"], "languages_combined": []}, "experience_required": {"duration": ["3+ years"], "field": ["designer", "design"]}}, {"job_id": "100003009037154", "location_code": "hk", "company": "Wondersky Online Limited", "job_title": "Graphic Designer (Full Time or Part Time)", "description": "Responsibilities:\n\nCreate optimized social media graphic design for branding development and daily content in different topic\nResponsible for concept development, visualization and hands on design for key visual, social media posts and promotion collateral, etc\nWork closely with editorial team to ensure concept's achievability and present accurately\u00a0\nAdjust and revise on project goals and design style accordingly as required from time to time\nFollow through project from concept development, executing layouts, artwork design independently\nStaying abreast of current marketing trends among digital, social media platform to develop a cutting edge among the advertisement industry\nSupport any ad-hoc job tasks assigned, including but not limited to client ad related tasks\n\nRequirements:\n\nDegree in multimedia design / graphic design or other relative disciplines\nAt least 3 years of experience in marketing design\nExperience in create optimized social media design is preferred\nFamiliar with social media operations is preferred\nGood verbal and written communications in English and Chinese\nCapable of drawing storyboards\u00a0\nWith website design experience is a plus\nAdvance users of Photoshop, illustrator, and video editing tools\nStrong sense in aesthetics design\n\nWe Offer:\n\n5 Days work\nFlexible Working Hour\nBirthday Leave & Work Anniversary Leave\u00a0\nMedical Coverage\nFun, young and joyful office environment\u00a0\n\nInterested candidates, please email full resume with 1.) EXPECTED SALARY 2.) AVAILABILITY 3.)\u00a0WORK REFERENCE\u00a0 to the HR department by clicking 'Apply Now'.\n\nFor company information, please refer to the website http://www.presslogic.com/.\n\nAll information received will be kept in strict confidence and only for employment-related purposes.", "employment_types": ["Full Time", "Permanent"], "selling_points": [], "locations": ["Sheung Wan"], "categories": ["Design", "Graphics", "Multi-media", "Web Designer"], "post_time": "2022-01-11T01:56:48Z", "salary": {"currency": null, "max": null, "min": null, "period": "monthly", "term": null}, "salary_visible": false, "title_keywords": ["graphic designer"], "responsibilities": ["ad-hoc", "social media", "visualization", "graphic design", "design", "develop", "executing", "visual"], "requirements": {"degrees": ["degree"], "majors": ["multimedia design", "graphic design"], "languages": ["english", "chinese"], "language_level": ["good"], "hard_skills": ["plus", "illustrator", "video editing", "multimedia", "photoshop"], "soft_skills": ["capable"], "languages_combined": [{"language": "english", "language_level": ["good"]}, {"language": "chinese", "language_level": ["good"]}]}, "experience_required": {"duration": ["at least 3 years"], "field": ["social media", "marketing", "design"]}}, {"job_id": "100003009043403", "location_code": "hk", "company": "Wemine Limited", "job_title": "GRAPHIC & UX DESIGNER (Full Time)", "description": "We are looking for a graphic designer to join our dynamic team.\n\nPassionate in graphic design, and eager to take part in innovative projects for a startup company.\n\nWHAT WE ARE LOOKING FOR:\n\nHungry for challenges and achievements\nCreative and with the advancement of your problem-solving skills\nDegree holder\u00a0with graphic design experience, with the UX/UI design for Web portal, eCommerce platform or Mobile Application will be an advantage\nResponsible for the branding and marketing visuals for digital and offline channels\nSupport and work closely with developers, marketers\nConduct branding, design research and analysis\nStrong sense at layout/typographic and Graphic Design\nHighly proficient in Adobe Creative Suite e.g. Photoshop, illustrator, InDesign, XD, etc.\nStrong knowledge of HTML5, CSS3, will be an advantage\nProficiency in Chinese or English\nPortfolio links should be provided in the resume.\n\nWHAT WE OFFER:\n\nOpportunities to involve in product branding and marketing designs\nCreative working environment with little office hierarchy\nMarket-competitive rate\nA team of top notch web experts\u00a0\n\nWHAT WHAT YOU WILL DO:\n\n30%:\u00a0Collaborate with the Development and Marketing Team to execute design solutions (web/social media/UI & UX for APP) that comply with project specifications, brand identity and strategic marketing goals\n\n25%:\u00a0Visualize concepts into rough drafts as the foundation for future execution, establish standards for style, aesthetics and typeface; design preliminary layout.\n\n25%:\u00a0Contribute to brainstorming workshops in projects and product innovation\n\n20%:\u00a0Participate in other innovative projects and learning opportunities under the group\u2019s investments\u00a0\u00a0\u00a0\n\nResponsible for the branding and marketing visuals for social media channels; take part in APP development projects;\nConduct branding, design research and analysis\nSupport and work closely with developers and marketers\n\nAbout\u00a0WeMine Limited\n\nWeMine is a marketing technology (Mar-Tech) firm that specializes in developing an intelligent marketing suite* on WeChat (and other social media platforms soon). Being exploited to such a sophisticated multi-purpose open platform, we challenge ourselves to unearth the gem within every day.\n\nAs a rapidly growing startup, we are constantly looking for fresh and passionate talents who are never tired of being challenged, questioned, and indeed, inspired to build a universally friendly infrastructure for marketers and business operators.\n\nUp for it? Send us your CV.\n\n*Wanna know what's inside our intelligent suite? Watch the video here -\u00a0https://goo.gl/gY0AFf- as an example.", "employment_types": ["Full Time", "Permanent"], "selling_points": ["Create banging visuals for social media channels", "Bring innovation to UI/UX design", "Join a team of top-notch digital experts"], "locations": ["Kwun Tong"], "categories": ["Design", "Graphics", "Multi-media", "Web Designer"], "post_time": "2022-01-12T11:32:37Z", "salary": {"currency": null, "max": null, "min": null, "period": "monthly", "term": null}, "salary_visible": false, "title_keywords": ["ux designer"], "responsibilities": ["graphic design", "analysis", "ui", "design"], "requirements": {"degrees": ["degree holder"], "majors": ["ecommerce", "graphic design", "design"], "languages": ["english", "chinese"], "language_level": ["proficiency"], "hard_skills": ["web", "analysis", "indesign", "illustrator", "mobile", "dynamic", "problem-solving skills", "adobe creative suite", "photoshop"], "soft_skills": ["passionate", "responsible", "innovative", "dynamic", "problem-solving skills", "creative"], "languages_combined": [{"language": "english", "language_level": ["proficiency"]}, {"language": "chinese", "language_level": ["proficiency"]}]}, "experience_required": {"duration": [], "field": ["ecommerce", "graphic design", "design"]}}, {"job_id": "100003009043055", "location_code": "hk", "company": "MoneyHero Global Limited", "job_title": "Designer (Visual Communications, Graphic, or Multimedia)", "description": "THE ROLE\u00a0\nWe are looking for a passionately user and outcome-oriented designer to join the MoneyHero Marketing team. If you are the person who is observant to the big picture and has good attention to details, obsessed with aesthetics and uncomfortable with bad typography or bad alignments, believe in having fun while achieving results, then you are exactly the candidate who we want to welcome to our team!\n\nYOUR TASK\nAssist design research and material preparation\nProduce digital designs\u00a0 as assigned such as banner ads, social posts, infographics\nUse various techniques to create drafts, models and prototypes\nPitch creative ideas\nCollaborate with team members to launch projects\nTake on special design tasks (e.g. color correction)\nUse feedback from other designers to improve\nSKILLS & REQUIREMENTS\n1-2 years of experiences\u00a0\nStrong graphic sense including typography, colors, graphics and layout\nPassionate in creative and design with an eye for detail\u00a0\nA team player with good track record of time management and communication skills\u00a0\u00a0\nPreferably majoring in Design, Creative Media, Digital Media, Visual Comm or related disciplines\nProficient in the use of Mac & Adobe Creative Suite\nFluent in written and spoken English and Chinese", "employment_types": ["Full Time", "Permanent"], "selling_points": ["1-2 years of experiences", "Passionate in creative", "Proficient in the use of Mac &Adobe Creative Suite"], "locations": ["Tin Hau"], "categories": ["Design", "Graphics", "Multi-media", "Web Designer"], "post_time": "2022-01-12T09:40:45Z", "salary": {"currency": null, "max": null, "min": null, "period": "monthly", "term": null}, "salary_visible": false, "title_keywords": ["designer"], "responsibilities": ["collaborate with", "graphics", "creative ideas", "management", "design", "communication", "visual"], "requirements": {"degrees": [], "majors": [], "languages": ["english", "chinese"], "language_level": ["fluent"], "hard_skills": ["graphics", "adobe creative suite", "fun"], "soft_skills": ["passionate", "communication skills", "time management", "eye for detail", "attention to details", "team player", "creative"], "languages_combined": [{"language": "english", "language_level": ["fluent"]}, {"language": "chinese", "language_level": ["fluent"]}]}, "experience_required": {"duration": ["1-2 years"], "field": []}}, {"job_id": "100003009043305", "location_code": "hk", "company": "Mad Head App Limited", "job_title": "Senior Graphic Designer", "description": "We are hiring!\nCome to join our team of professionals passionate to games!\n\nWhat you will be doing:\n\nAssist on creative development and layout adaptation\nHandle day to day graphics design and production for advertising, social media content, and website\nResearch and consolidate insight of new games/ apps, best practices of design and advertising across the market\nGenerate ideas and create content for feeds on social media\nPerform ad hoc assignments by management\u00a0\n\nWhat you need for this position:\n\nHigher diploma in Graphic Design or related discipline\nAt least 2 years of relevant experience in graphic design\nExperienced user of Adobe Photoshop and Adobe Illustrator\nKnowledge in social media management is an advantage\nProficient in spoken and written Chinese (both Cantonese and Mandarin) and English Independent, highly self-motivated, enjoy new challenges, and able to think out of the box\nA good team player and attention to detail\nCandidate with less experience would also be considered as Graphic Designer\u00a0\n\nWorking Location & Hours:\u00a0\nHong Kong Science Park\n5-day work, 10:00 \u2013 19:00 (Lunch hour 13:45 \u2013 15:00)\n\nWe Offer:\n\n\nAttractive Performance Bonus\nIn-game staff reward\nGood Career Prospects\nGroup Medical Insurance & Body-Check\nBirthday Leave, Marriage Leave, Compassionate Leave\nApplication method:\n\n\nInterested candidates please click the \"Apply Now\" button to apply and provide your portfolio for our review.\n\nWe are an equal opportunity employer and welcome applications from all qualified candidates. All information provided will be treated in strict confidence and used for recruitment purposes only.", "employment_types": ["Full Time", "Permanent", "Contract"], "selling_points": ["Graphic Design in Game Industry", "Self-motivated with a strong aesthetic sense", "Young, Creative & Energetic Team"], "locations": ["Shatin Area"], "categories": ["Design", "Graphics", "Multi-media", "Web Designer"], "post_time": "2022-01-12T10:36:16Z", "salary": {"currency": null, "max": null, "min": null, "period": "monthly", "term": null}, "salary_visible": false, "title_keywords": ["senior graphic designer"], "responsibilities": ["graphics", "social media", "management", "advertising", "ideas", "graphic design", "website", "design", "social media content", "ad hoc assignments"], "requirements": {"degrees": ["diploma"], "majors": ["graphic design"], "languages": ["cantonese", "english", "chinese", "mandarin"], "language_level": ["proficient"], "hard_skills": ["graphics", "adobe photoshop", "adobe illustrator"], "soft_skills": ["passionate", "good team player", "self-motivated", "independent", "attention to detail", "creative"], "languages_combined": [{"language": "cantonese", "language_level": ["proficient"]}, {"language": "english", "language_level": ["proficient"]}, {"language": "chinese", "language_level": ["proficient"]}, {"language": "mandarin", "language_level": ["proficient"]}]}, "experience_required": {"duration": ["at least 2 years"], "field": ["graphic design", "graphic", "relevant experience", "designer"]}}, {"job_id": "100003009037351", "location_code": "hk", "company": "Olens", "job_title": "Graphic Designer / Digital Designer - 5 days work", "description": "UI/UX Graphic Designer\n\nZhenHub is a fast growing logistics platform that supports global ecommerce retailers like Walmart, Supercell and Daimler. Our clients are a number of Fortune 500 companies. We are looking for smart, aspiring digital marketers to join our team.\u00a0\n\nThis position will be challenging, you will have to learn quickly or you will be left behind. We are looking for the best and brightest. If you think you have what it takes then apply for this position. The successful candidate will have an opportunity with work with global tech companies, lead marketing projects and learn about the latest digital marketing techniques.\n\nRESPONSIBILITIES\n\nYou will:\n\nDesign graphics/interactions for UI/UX on Web/Mobile applications\nGathering and evaluating user requirements, in collaboration with developer\nTake charge of the development and creation for different Digital/Print marketing materials and brand collaterals, from creative concept development to final production\nEnhance and maintain the user interface and usability of the responsive website.\nLiaise with Vendors in production of print materials\nMaintain and Update visual elements on Website and Social Media Platforms\nDesign creative materials including webpages, banners, eDM.\nPerform user testing and other activities to gain knowledge from end users.\nWork closely with web/app developers to understand technical requirements\nPhoto shooting and editing\n\n\nREQUIREMENTS:\n\n\nDiploma or above in Graphic Design, Fine Art or other related disciplines\n2 years solid experience in graphic design\nHands-on experience in design software such as Photoshop, Illustrator, Dreamweaver/WordPress/HTML, Flash and Premiere\nCreative and passionate, with strong aesthetic sense, ability to think out-of-the-box and great eye for detail\nStrong abilities in HTML/CSS skills in web design.\nKnowledge and experience in JavaScript, ReactJS, Invision is an advantage\nProficient in Adobe Creative Suite (PS, FW & IL)\nAble to work under pressure and deliver on tight deadlines\nGood communication skills and good command in both spoken and written English and Chinese\n\nWe\u00a0offer\u00a0an attractive remuneration package to the right candidate. Interested parties please click the \"APPLY NOW\" button above and send your application together with a detailed resume including current & expected salary and availability to Human Resources Department.\n\nCompany website:\u00a0https://www.zhenhub.com\n\nor\n\nPlease submit your applications to careers(a)zhenhub.com.", "employment_types": ["Full Time", "Permanent"], "selling_points": [], "locations": ["Kwai Hing"], "categories": ["Design", "Graphics", "Multi-media", "Web Designer"], "post_time": "2022-01-11T02:35:20Z", "salary": {"currency": null, "max": null, "min": null, "period": "monthly", "term": null}, "salary_visible": false, "title_keywords": ["digital designer", "graphic designer"], "responsibilities": ["edm", "social media platforms", "website", "design", "testing", "user interface", "liaise with", "maintain", "banners", "design graphics", "visual", "marketing materials", "editing", "ui"], "requirements": {"degrees": ["diploma or above"], "majors": ["related disciplines", "graphic design", "fine art"], "languages": ["english", "chinese"], "language_level": ["good command", "good"], "hard_skills": ["web design", "illustrator", "html", "premiere", "wordpress", "javascript", "flash", "dreamweaver", "css", "adobe creative suite", "photoshop"], "soft_skills": ["passionate", "communication skills", "hands-on", "eye for detail", "creative", "work under pressure"], "languages_combined": [{"language": "english", "language_level": ["good command", "good"]}, {"language": "chinese", "language_level": ["good command", "good"]}]}, "experience_required": {"duration": ["2 years"], "field": ["graphic design", "design"]}}, {"job_id": "100003009038129", "location_code": "hk", "company": "ZhenHub Technologies Limited", "job_title": "UI/UX Graphic Designer", "description": "To cope with the rapid growth of our retail and salon business, we are looking for talent\u00a0with the following background to join our vibrant and inspiring marketing team.\n\nJob Duties:\n\nWork closely with marketing team to help translate the creative concept to visuals\nPhotos retouch, create motion video editing\nCreate graphic designs and animation for all artworks including but not limited to POSM, company website, social media platforms, EDMs, Google banner ads, eDM etc.\nIn charge of the production and ensure end products completed on schedule and high standard.\nAssist in planning and implementing marketing strategies for HK market including ATL, BTL, online & social media, CRM & PR\nAd-hoc project as assigned.\n\nRequirements:\n\nHigher diploma or university degree in Design or related disciplines.\nMinimum of 3 years\u2019 experience in graphic and / or multimedia design, experience in beauty industry is a plus.\nExperience with design software and graphics editing software, such as Illustrator and Photoshop\nKnowledge of design techniques\nMulti-tasking and good time management\nCreative, keen eyes for details, and open-minded\nInterested parties please use \"quick apply\" to submit your CV with a work portfolio link, expected salary and availability.\u00a0Only shortlisted candidates will be contacted, and all applications will be treated in strict confidentiality.", "employment_types": ["Full Time"], "selling_points": ["Fast Global Startup Environment", "Solid experience in Web Application UI/UX design", "Adobe Creative Suite"], "locations": ["Tsuen Wan Area"], "categories": ["Design", "Graphics", "Multi-media", "Web Designer"], "post_time": "2022-01-11T05:23:21Z", "salary": {"currency": null, "max": null, "min": null, "period": "monthly", "term": null}, "salary_visible": false, "title_keywords": ["graphic designer"], "responsibilities": ["ad-hoc", "social media", "edms", "marketing strategies", "edm", "social media platforms", "graphic designs", "video editing", "schedule", "company website", "animation", "planning"], "requirements": {"degrees": ["diploma", "university degree"], "majors": ["related disciplines", "design"], "languages": [], "language_level": [], "hard_skills": ["graphics", "plus", "illustrator", "multimedia", "photoshop"], "soft_skills": ["creative", "open-minded", "keen", "multi-tasking", "time management"], "languages_combined": []}, "experience_required": {"duration": ["minimum of 3 years"], "field": ["beauty industry", "graphic", "design", "editing"]}}, {"job_id": "100003009041978", "location_code": "hk", "company": "Belle Worldwide (Talent Management) Limited", "job_title": "Graphic Design (Multimedia Design)", "description": "Job Highlights\n\nGraphic design for our magazine and Website\nLayout design of our magazine and our advertising\nArt direction for our photo shooting\n\nResponsibilities:\n\nDesign online/print material for marketing purpose\nWebsite Design\nSimple video shooting and editing\n\nRequirements:\n\n1-2 years related work experience\nBasic knowledge in beauty industry\nBasic html, css knowledge\nBasic video shooting & editing skills\nVideo Editing\n***Please send CV and Portfolio by email to Miss Ng.\n\n", "employment_types": ["Full Time", "Permanent"], "selling_points": ["develop creative concepts, graphic and artworks", "multimedia design (video, motion graphic)", "2 years\u2019 relevant working experience"], "locations": ["Kwai Hing"], "categories": ["Design", "Graphics", "Multi-media", "Web Designer"], "post_time": "2022-01-12T04:58:56Z", "salary": {"currency": null, "max": null, "min": null, "period": "monthly", "term": null}, "salary_visible": false, "title_keywords": [], "responsibilities": ["editing", "video shooting", "website", "design"], "requirements": {"degrees": [], "majors": [], "languages": [], "language_level": [], "hard_skills": ["video editing", "css", "basic", "html"], "soft_skills": [], "languages_combined": []}, "experience_required": {"duration": ["1-2 years"], "field": ["related"]}}, {"job_id": "100003009044589", "location_code": "hk", "company": "Match Talent Limited", "job_title": "Head of Creative", "description": "Role & Responsibilities:\n\nResponsible for developing creative concepts, graphic and artworks adaptation for all marketing materials related to brand communication and retail marketing, including advertisements, leaflets, posters, banner, eDMs, etc\nExecute full spectrum of multimedia design and production including video and photo shooting and editing motion graphic design interactive online activities, etc\nHandle projects independently from concept to final production\nManage social media platforms and websites updating\nAssist in regular promotion projects and ad hoc graphic / multimedia design projects\n\nRequirements:\n\nDiploma holder or above in Multimedia Design / Graphic Design / related discipline\nAt least 2 years\u2019 relevant working experience, preferably in retail industry\nStrong fashion sense and creative, Self-motivated, good team player\nGood time management and work efficiency with quality\nAble to work under tight schedule\nProficient in Adobe Illustrator, Photoshop, InDesign, Premier, After effects and MS Office\nGood command of spoken and written English, Cantonese and Mandarin\n\nInterested parties, please \"APPLY NOW\" or send your full resume with current and expected salary to Head of Human Resources Department, 6/F, The Edge, 30-34 Kwai Wing Road, Kwai Chung, N.T., Hong Kong\n\nFor more information, please contact Ms. Wan at 39290621.\n\nAll information received will be kept strictly confidential and only for employment-related purposes.", "employment_types": ["Full Time", "Permanent"], "selling_points": ["Creating innovative and compelling brand voice", "5-days working hours with WFH", "Strong creativity and managing design team"], "locations": ["Causeway Bay"], "categories": ["Design", "Graphics", "Web Designer", "E-commerce", "Marketing - Brand / Product Management"], "post_time": "2022-01-13T04:42:12Z", "salary": {"currency": null, "max": null, "min": null, "period": "monthly", "term": null}, "salary_visible": false, "title_keywords": ["creative"], "responsibilities": ["multimedia design", "edms", "ad hoc", "advertisements", "leaflets", "social media platforms", "developing", "communication", "marketing materials", "editing", "motion graphic design"], "requirements": {"degrees": ["diploma holder"], "majors": ["multimedia design", "graphic design"], "languages": ["cantonese", "english", "mandarin"], "language_level": ["good command"], "hard_skills": ["indesign", "adobe illustrator", "after effects", "multimedia", "ms office", "photoshop"], "soft_skills": ["time management", "good team player", "self-motivated", "creative"], "languages_combined": [{"language": "cantonese", "language_level": ["good command"]}, {"language": "english", "language_level": ["good command"]}, {"language": "mandarin", "language_level": ["good command"]}]}, "experience_required": {"duration": ["at least 2 years"], "field": ["retail industry", "relevant working experience"]}}, {"job_id": "100003009033740", "location_code": "hk", "company": "Educational Publishing House, Limited", "job_title": "Web Designer", "description": "Our client is an International Crypto Exchange looking for a creative director to develop the best\u00a0campaign strategies to boost its image in the market.\n\nResponsibilities:\n\nDevelop an innovative and compelling brand voice and image strategy for new products\nWork cross-functionally in developing the best campaign strategy with peers\nContinuously improve the quality, craft, and standards of graphic design\nCommunicate and collaborate with cross-departmental staff on strategy direction\nSupervise the overall design process and provide guidance to designers when necessary\n\nRequirements:\n\nMinimum of 7 years of relevant experience in the Financial Technology Industry\nCandidates with less than 7 years of experience are considered as Senior Brand Designer\nBachelor\u2019s degree in Graphic Design, or any related disciplines\nExtensive portfolio with a track of previous work\u00a0(Compulsory upon application)\nStrong understanding of digital design, design software, motion graphics, and animation\nExperiences in leading and working with design, product, and creative departments\nExcellent command of English, Cantonese, and Mandarin\n_________________________________________________________________\nAll job openings are available on our website website:\u00a0www.matchtalent.com.hk", "employment_types": ["Full Time", "Permanent"], "selling_points": ["5-day work week, Medical & dental insurance", "Team player", "Fresh graduates are also welcomed"], "locations": ["Tsuen Wan Area"], "categories": ["Design", "Web Designer"], "post_time": "2022-01-10T01:43:56Z", "salary": {"currency": null, "max": null, "min": null, "period": "monthly", "term": null}, "salary_visible": false, "title_keywords": ["designer"], "responsibilities": ["collaborate with", "graphic design", "quality", "developing", "design", "develop", "provide guidance"], "requirements": {"degrees": ["degree", "bachelor"], "majors": ["related disciplines", "graphic design"], "languages": ["cantonese", "english", "mandarin"], "language_level": ["excellent"], "hard_skills": ["graphics"], "soft_skills": ["creative", "extensive"], "languages_combined": [{"language": "cantonese", "language_level": ["excellent"]}, {"language": "english", "language_level": ["excellent"]}, {"language": "mandarin", "language_level": ["excellent"]}]}, "experience_required": {"duration": ["7 years", "minimum of 7 years"], "field": ["designer", "brand", "design", "relevant experience", "financial"]}}, {"job_id": "100003009037817", "location_code": "hk", "company": "HKT Consumer Group", "job_title": "Senior Digital Designer", "description": "Graphic\u00a0Designer/Digital\u00a0Designer\n\nJob\u00a0Description\n\n\nResponsible\u00a0for\u00a0developing\u00a0concept\u00a0development,\u00a0graphic\u00a0design\u00a0&\u00a0artwork\u00a0adaptation for\u00a0online\u00a0&\u00a0offline\u00a0platforms\u00a0including\u00a0marketing\u00a0&\u00a0promotional\u00a0materials\u00a0includes\u00a0advertisements,\u00a0brochures,\u00a0leaflets,\u00a0banners,\u00a0posters,\u00a0newsletters,\u00a0website\u00a0banners,\u00a0FB,\u00a0IG\u00a0etc.\u00a0\nBrainstorm\u00a0and\u00a0collaborate\u00a0innovative\u00a0ideas\u00a0with\u00a0our\u00a0marketing\u00a0team\nDevelop\u00a0creative\u00a0concept\u00a0to\u00a0design,\u00a0structural\u00a0drawing,\u00a0artwork\u00a0and\u00a0the\u00a0final\u00a0output\u00a0to\u00a0meet\u00a0business\u00a0objectives\nHandle\u00a0regular\u00a0promotion\u00a0projects\u00a0and\u00a0ad\u00a0hoc\u00a0graphic\u00a0design\u00a0projects\n\u00a0\n\nRequirements\n\n\nDiploma\u00a0holder\u00a0in\u00a0graphics/\u00a0product\u00a0designs\nAt\u00a0least\u00a02-3\u00a0years\u00a0of\u00a0relevant\u00a0experience\nCreative\u00a0and\u00a0innovative\u00a0with\u00a0aesthetic\u00a0sense\nAttention\u00a0to\u00a0details\u00a0and\u00a0able\u00a0to\u00a0multi-tasking\u00a0and\u00a0meet\u00a0tight\u00a0deadlines\nProficient\u00a0in\u00a0using\u00a0Adobe\u00a0Illustrator,\u00a0Photoshop\u00a0in\u00a0Mac\u00a0environment\u00a0and\u00a0strong\u00a0knowledge\u00a0in\u00a0HTML\u00a0and\u00a0CSS\nExperience\u00a0in\u00a0graphic\u00a0design\u00a0in\u00a0fashion\u00a0&\u00a0beauty\u00a0&\u00a0digital\u00a0marketing\u00a0is\u00a0a\u00a0definite\u00a0advantage\nCan\u00a0work\u00a0independently,\u00a0well-organized,\u00a0responsible\u00a0and\u00a0a\u00a0good\u00a0team\u00a0player\nGood\u00a0command\u00a0in\u00a0Chinese\u00a0and\u00a0English\nLess\u00a0experienced\u00a0will\u00a0be\u00a0considered\u00a0as\u00a0Junior\u00a0Designer\n5-Day\u00a0work;\u00a0Bank\u00a0holiday;\u00a0Discretionary\u00a0bonus\n\nWorking\u00a0location\u00a0in\u00a0Kwai\u00a0Hing\u00a0(near\u00a0MTR\u00a0station).\n\nInterested\u00a0parties,\u00a0please\u00a0send\u00a0full\u00a0resume\u00a0with\u00a0expected\u00a0salary\u00a0to\u00a0us.\nImmediate\u00a0available\u00a0is\u00a0preferred", "employment_types": ["Full Time"], "selling_points": [], "locations": ["Quarry Bay"], "categories": ["Design", "Graphics", "Web Designer"], "post_time": "2022-01-11T03:56:37Z", "salary": {"currency": null, "max": null, "min": null, "period": "monthly", "term": null}, "salary_visible": false, "title_keywords": ["digital designer"], "responsibilities": ["collaborate", "ideas", "ad hoc", "advertisements", "leaflets", "graphic design", "developing", "website", "develop", "design", "banners", "promotional materials"], "requirements": {"degrees": ["diploma holder"], "majors": [], "languages": ["english", "chinese"], "language_level": ["good command"], "hard_skills": ["graphics", "mac environment", "html", "adobe illustrator", "css", "photoshop"], "soft_skills": ["meet tight deadlines", "work independently", "good team player", "responsible", "well-organized", "innovative", "multi-tasking", "attention to details", "creative"], "languages_combined": [{"language": "english", "language_level": ["good command"]}, {"language": "chinese", "language_level": ["good command"]}]}, "experience_required": {"duration": ["at least 2-3 years"], "field": ["graphic design", "relevant experience", "beauty", "digital marketing"]}}, {"job_id": "100003009039585", "location_code": "hk", "company": "Mad Head App Limited", "job_title": "UI / UX Designer (Mobile Game)", "description": "Your role:\n\nResponsible for the UI and UX design of various digital media platforms (mobile application, website, online platform)\u00a0\nCreate artworks, design layout, video clips and animation for promotional & marketing materials in website, social media, EDMs, etc.\u00a0\nWork closely with marketing team and design team to facilitate the creative process\n\nTo succeed in this role:\n\nHigher Diploma or above in Multimedia/Interaction Design or other related discipline\u00a0\n3 - 5 years of working experience in creative design\u00a0\nCreative, well-organized, detail-minded, independent, self-initiate, hardworking, aggressive and good personality\u00a0\nKnowledge in HTML5, CSS, Action script will be an advantage\nLess experience will be considered as Digital Designer", "employment_types": ["Full Time"], "selling_points": ["Design/develop In-game and Website UI", "Handle multiple projects", "Minimum of 2 years working experience"], "locations": ["Shatin Area"], "categories": ["Design", "Graphics", "Multi-media", "Web Designer"], "post_time": "2022-01-11T10:09:44Z", "salary": {"currency": null, "max": null, "min": null, "period": "monthly", "term": null}, "salary_visible": false, "title_keywords": ["ux designer"], "responsibilities": ["social media", "edms", "website", "design", "facilitate the creative process", "marketing materials", "ui", "animation"], "requirements": {"degrees": ["higher diploma or above"], "majors": ["design"], "languages": [], "language_level": [], "hard_skills": ["clips", "creative design", "mobile", "multimedia", "css"], "soft_skills": ["detail-minded", "independent", "responsible", "well-organized", "creative", "hardworking"], "languages_combined": []}, "experience_required": {"duration": ["3 - 5 years"], "field": ["digital", "designer", "design"]}}, {"job_id": "100003009022820", "location_code": "hk", "company": "Hong Kong Adventist College", "job_title": "GRAPHIC DESIGNER", "description": "About Madhead\nMadhead, one of the leading HK-based mobile game developers, serving in Hong Kong and Taiwan, expanded its business scope from Facebook apps to mobile game development and launched the smash hit mobile game \"Tower of Saviors\" in early 2013. The game has ranked among the top mobile games in Taiwan, Hong Kong, Malaysia, and other South-East Asia regions with global downloads hitting over 23 million to date.\n\n\nFor more details, please visit:\nhttps://www.linkedin.com/company/madhead\nhttps://www.madhead.com/\nhttps://www.facebook.com/tos.zh\n\nJob Highlights\nDesign/develop In-game and Website UI\nHandle multiple projects\nMinimum of 2 years working experience\n\nJob Description\n\n\nUnderstand users\u2019 thinking and design user-friendly UX/UI flows\nDesign from concept to completion all facets of the UI including wireframes, mock-ups, and prototypes\nFlexible, multi-task, handle ad hoc tasks and projects when required\nDesign/develop In-game and Website with a good sense of user experience and creativity\nCollaborate closely with the product team, project management team, and developers to iterate on the design artwork to deliver the best user experience\n\nRequirements\n\n\nDegree/Higher Diploma holder in Web, Multimedia and Graphic Design or related disciplines\nMinimum 1-year relevant working experience in UI/UX design\nUp-to-date with the latest UI trends, techniques, and technologies\nProficiency in relevant design software (such as Figma, Adobe CC, etc.)\nProficient in animation software like Adobe After Effects.\nProficient in creating game VFX (\u904a\u6232\u7279\u6548).\nKnowledge of 3D production and digital drawing is a plus.\nKnowledge of UI/UX design work and skills in HTML/CSS/JavaScript is a plus\nProactive, creative, independent, strong sense of integrity and able to work under pressure to meet deadlines;\nStrong presentation skills with good verbal skills in Cantonese and Mandarin\nExperience in developing user-friendly UI for the game industry would be an advantage\n\nBenefits\n\n\nAttractive Performance Bonus\nIn-game staff reward\nGood Career Prospects\nDental, Group Medical Insurance & Body-Check\nBirthday Leave, Marriage Leave, Compassionate Leave\n\nWorking Location & Hours\n\n\nHong Kong Science Park, Shatin\n5-day work, 10:00 \u2013 19:00 (Lunch hour 13:45 \u2013 15:00)\n\nApplication method:\nInterested candidates please click the \"Apply Now\" button to apply and provide your portfolio for our review.", "employment_types": ["Full Time", "Permanent"], "selling_points": ["To create superior and original designs", "To liaise with external agencies", "Diploma/University degree in advertising"], "locations": ["Not Specified"], "categories": ["Design", "Graphics", "Interior", "Web Designer"], "post_time": "2022-01-10T03:40:54Z", "salary": {"currency": null, "max": null, "min": null, "period": "monthly", "term": null}, "salary_visible": false, "title_keywords": ["graphic designer"], "responsibilities": ["collaborate", "mock-ups", "ad hoc tasks", "website", "design", "develop", "user experience", "project management", "ui"], "requirements": {"degrees": ["degree", "higher diploma holder"], "majors": ["related disciplines", "graphic design"], "languages": ["cantonese", "mandarin"], "language_level": ["good"], "hard_skills": ["plus", "web", "html", "adobe after effects", "javascript", "multimedia", "adobe cc", "css", "animation software"], "soft_skills": ["independent", "creative", "integrity", "presentation skills", "friendly", "meet deadlines", "proactive", "work under pressure"], "languages_combined": [{"language": "cantonese", "language_level": ["good"]}, {"language": "mandarin", "language_level": ["good"]}]}, "experience_required": {"duration": ["minimum 1-year"], "field": ["relevant working experience", "design", "developing"]}}, {"job_id": "100003008993854", "location_code": "hk", "company": "Tranthink Technology Service Limited", "job_title": "Graphic Designer", "description": "Job Requirements:\nDiploma/University degree in advertising, graphic design or a relevant discipline;\nSolid working experience in graphic design and advertising with knowledge in web building, CSS, CMS and HTML 5 preferred;\nFamiliar with current graphic design practice, such as Adobe Photoshop, Adobe Illustrator, Adobe In Design and Flash;\nExcellent communication skills with good command in written & spoken English, Cantonese and Mandarin;\nAble to handle multiple tasks of varying complexities within deadlines;\nAble to work well under pressure\nFresh graduates are welcome to apply\nKey Job Responsibilities:\nTo create superior and original designs for the school website and promotional materials include posters, flyers, logos, banners, signage, etc.\nTo liaise with external agencies such as printing houses, web developers and AD agencies\nTo work with marketing team on promotional projects and to help in executing marketing activities such as delivery of presentations and promotions at education exhibitions in Hong Kong, Macau or Mainland China\nTo communicate with parents, students and prospective parties about our school programs\nWe offer 5-day work to the right candidates. Interested parties please send your full resume with date available and expected salary to Human Resources Office via email by clicking \"Apply Now\".\nClosing Date:\u00a0 January 20, 2022\n(Personal data collected will be used for recruitment purpose only.)", "employment_types": ["Full Time", "Permanent"], "selling_points": ["5 Days Work, Double Pay, Medical Insurance", "Flexible working hours, Free snack", "Designing promotional materials"], "locations": ["Not Specified"], "categories": ["Design", "Graphics", "Web Designer", "Information Technology (IT)", "Others"], "post_time": "2022-01-09T16:25:32Z", "salary": {"currency": null, "max": null, "min": null, "period": "monthly", "term": null}, "salary_visible": false, "title_keywords": ["graphic designer"], "responsibilities": ["website", "presentations", "banners", "promotional materials", "executing", "liaise with", "communicate with parents"], "requirements": {"degrees": ["diploma", "university degree"], "majors": ["graphic design"], "languages": ["cantonese", "english", "mandarin"], "language_level": ["excellent", "good command"], "hard_skills": ["web", "adobe photoshop", "html", "adobe illustrator", "adobe", "flash", "css"], "soft_skills": ["handle multiple tasks", "communication skills", "under pressure"], "languages_combined": [{"language": "cantonese", "language_level": ["excellent", "good command"]}, {"language": "english", "language_level": ["excellent", "good command"]}, {"language": "mandarin", "language_level": ["excellent", "good command"]}]}, "experience_required": {"duration": [], "field": ["graphic design", "advertising"]}}, {"job_id": "100003009035508", "location_code": "hk", "company": "Zodiac Lighting Ltd", "job_title": "Graphic Designer (5 days work)", "description": "Good Command on graphic design\nPhoto Editing software included Illustrator, Photoshop, IN Design\nPhoto shooting skill\n1-2 years working experience\nExperience in Catalogue Production is preferred", "employment_types": ["Full Time", "Permanent"], "selling_points": [], "locations": ["Chai Wan"], "categories": ["Design", "Graphics", "Multi-media", "Web Designer"], "post_time": "2022-01-10T07:30:01Z", "salary": {"currency": null, "max": null, "min": null, "period": "monthly", "term": null}, "salary_visible": false, "title_keywords": ["graphic designer"], "responsibilities": ["software", "graphic design", "design", "editing", "catalogue"], "requirements": {"degrees": [], "majors": [], "languages": [], "language_level": [], "hard_skills": ["illustrator", "photoshop"], "soft_skills": [], "languages_combined": []}, "experience_required": {"duration": ["1-2 years"], "field": []}}, {"job_id": "100003009036158", "location_code": "hk", "company": "Landcrowd Limited", "job_title": "UI designer - Recent Grads Welcome", "description": "WHO WE ARE AND WHAT WE DO:\n\nSpacious, Hong Kong's #1 internet property platform, is looking for a UI Designer, with a good sense of UX, to join our best-in-class Hong Kong based product team. You will work with a high-quality technology team of veterans and seasoned developers\u00a0to create amazing user experiences.\u00a0\n\nSpacious helps\u00a0to\u00a0make finding a property online\u00a0to\u00a0buy or rent easier and more efficient. Spacious has been providing the best-in-class search experience for property hunters in Greater China with its premium user interface, offering the highest quality listings and data comparisons for more than half a decade. This focus enables Spacious\u00a0to\u00a0generate the highest quality enquiries for property agents, developers, etc., who\u00a0pay\u00a0to\u00a0list.\n\nSpacious is a profitable, self-sustaining and proven business that is growing very quickly. We have over 1,000,000+ monthly high-value property searchers visiting our website/mobile app.\u00a0\n\nWe are a design-focused startup with a highly technical team with a technical founder who has coded various technologies for more than a decade.\u00a0UI/UX and technology are at the core of what we do and how we differentiate ourselves from our competition.\n\nFinding a home is one of life's most important (and stressful) events; by making the process easier, we positively impact people's lives every day with our work. Friends, family and strangers who have used Spacious to find a home often tell us how grateful they are for Spacious.\n\nWe are an international team with team members from the UK, USA, India and of course, Hong Kong.\nRoughly half our team are women.\nWe operate a friendly, collaborative company with diverse opinions in an environment that respects diversity and inclusion, from a top-quality office in the heart of Hong Kong.\nWe operate a flat organization with no strict reporting lines, open communication, and we trust our employees to manage their own time, offering a high degree of autonomy.\n\nThis is our website:\u00a0www.spacious.hk\nSpacious mobile apps are award winning on both Android and iOS apps.\n\nWHO WE ARE LOOKING FOR:\n\nDuties:\n(a)\u00a0Execute all visual design stages from concept to final hand-off to software engineering (50%)\n(b)\u00a0Collaborate with product management and engineering to define and implement innovative solutions for the product direction, visuals and experience (10%)\n(c)\u00a0Conceptualize original ideas that bring simplicity and user-friendliness to complex design roadblocks\u00a0(10%)\n(d)\u00a0Create wireframes, storyboards, user flows, process flows, and site maps to communicate interaction and design ideas effectively\u00a0(10%)\n(e)\u00a0Conduct user research and evaluate user feedback\u00a0(10%)\n(f)\u00a0Establish and promote design guidelines, best practices and standards (5%)\n(g) Help to create creative materials for paid ads, blog posts, social media,\u00a0clients content, offline banners when required (5%)\n\nRecent Grads welcome. This role is a fantastic opportunity to learn from one of Hong Kong's most experienced and highly skilled startup teams.\n\nThe ideal candidate should have an eye for clean and artful design, possess superior UI skills, translate high-level requirements into interaction flows and artefacts and transform them into beautiful, intuitive, and functional user interfaces.\n\nIf the challenge of working in an exciting, fast-paced startup that is growing quickly appeals to you, then get in touch.\n\nQualifications:\n\nDegree in design related subject.\nPrevious experience of UI Design for web and mobile App design or wireframing\nA portfolio of relevant design work (please attach samples as a cover letter or provide a link to your portfolio)\nPassionate about details and have a pixel-perfect obsession\nCareer Path\nSenior UI/UX Designer\nAs you gain experience and knowledge from the rest of the team - you will naturally move to more senior UX/UI roles with greater ownership levels. We have annual salary reviews and have quarterly catchups to offer feedback on how you are doing.\nUltimately this leads to a career path with people management leadership responsibilities.\n\nExperience\nRecent Grads Welcome\n\nWHY YOU SHOULD JOIN US:\n\nWe work in a fun, collaborative open space where we encourage creativity and ideas to flow freely.\u00a0\nYou'll be able to steer the future roadmap to improve our products, big or small, and see the results of your products reach our customers.\nGet to work with flexible working hours. Our priority is on getting the job done.\nFlat structure environment, you will be able to work independently and make your own choices.\nWe provide guidance and mentorship to polish your technical skills, business skills and entrepreneurship mindset.\nWe are one of the standout tech startups in Hong Kong, targeting a huge opportunity in Asia.\nBenefits\nExcellent monthly salary\nMPF\nMedical Insurance\n18 days annual leave\nA budget for continual learning", "employment_types": ["Full Time"], "selling_points": ["Fast-growing, profitable, exciting tech startup", "Friendly design-focused startup team/mentorship", "Strong career development, continuous learning"], "locations": ["Sheung Wan"], "categories": ["Media & Advertising", "Creative / Design", "Design", "Web Designer", "Information Technology (IT)", "UI/UX Designer"], "post_time": "2022-01-10T09:31:12Z", "salary": {"currency": "HKD", "max": 24999, "min": 17000, "period": "monthly", "term": null}, "salary_visible": true, "title_keywords": ["ui designer"], "responsibilities": ["collaborate with", "ideas", "software", "data", "quality", "website", "design", "communication", "user interface", "banners", "storyboards", "mobile app", "teams", "visual", "ui", "reporting", "management", "social media", "design work", "guidelines", "evaluate"], "requirements": {"degrees": ["degree", "recent grads"], "majors": ["design"], "languages": [], "language_level": [], "hard_skills": ["clean", "small", "no", "web", "fun", "make", "mobile", "visual design", "c", "focus", "android"], "soft_skills": ["efficient", "flexible", "work independently", "creative", "focused", "collaborative", "communication", "diverse", "friendly", "leadership", "focus", "innovative", "superior", "passionate about", "ideal"], "languages_combined": []}, "experience_required": {"duration": [], "field": ["product management", "engineering", "design", "team"]}}, {"job_id": "100003009035913", "location_code": "hk", "company": "Hong Kong Digital Asset Ex Limited", "job_title": "UI/UX Designer", "description": "About MADworld:\nMADworld (Multiverse Art Defender) is an upcoming NFT platform for both real world and digital collectibles founded by some of the biggest players in the industry including Animoca Brands. Along with its soon-to-be listed utility token ready to disrupt the industry, the company is rapidly expanding to meet its product launch demands. Visit us at: Madworld.io\n\n\u00a0MADWorld.io (which partnered closely with Ucollex.io), is reinventing the way creators develop, digitize, and distribute all forms of creative expression. MADworld supports artists and creators who wish to use non-fungible tokens (NFTs) to effectively promote and monetize their work. It allows artists and creators to generate NFTs that fuse physical and digital elements, generate NFTs from live or original visual and audio content, and distribute the NFTs through the MADworld platform under the artists' own terms.\n\n\u00a0The company already supports renowned artists such as Marvel and DC veteran comic illustrators\u00a0Pat Lee\u00a0and\u00a0Dan Fraga\u00a0to provide exposure to blockchain and crypto industry investors\n\n\u00a0Core features includes digital art battle (live competition); toy art marketplace, asset management metaverse for Chargespot, Augmented reality (AR) and Virtual reality (VR) as well as creating tokenized NFT community with tons of goodies for the collectors and the creators!\n\n\u00a0\nAbout the role:\nWe are now seeking for a cool Graphic Designer / Social Media Coordinator,\u00a0who has a passion for NFT products and services, and enjoys working in a dynamic, best-in-class fintech, global start-up environment. You will a diverse range of tasks that will cover graphic design and digital marketing. Collaboratively plan and design the social media content calendar in line with the marketing plan. As well as Create and curate engaging Social media content in line with brand guidelines\n\nIf you are someone who thrives in an exciting and new industry where being self-directed, determined, and resilient are a requirement and where creativity flourishes, we would love for you to join us.\n\nWhat\u2019s Involved:\n\nGraphic Design\n\nDevelopment and design of marketing material for digital assets (Website, organic and paid social creatives).\nDesign and execution of email marketing campaigns.\nExplore new ways of thinking, industry trends and new ideas by contributing to the wider design team\nCreate new and update existing product designs to enhance UX/UI from end to end\n\nSocial Media\n\nAssist in managing social media accounts with the aim to increase engagement, social media following and traffic to website\n\n\u00a0We are excited about you because you have:\n\nExperience with Adobe Creative Suite: Photoshop & illustrator etc.\nInterest and experience in social media marketing with a solid understanding of how to actively engage using social media platforms (i.e. Instagram, Facebook etc.)\nDemonstrated knowledge of preparing artwork for digital platforms\nExceptional communication and interpersonal skills with a flexible approach, positive friendly attitude and ability to work well within a team\nExcellent eye for typography and creative layouts\nKnowledge of 3D software eg Maya, Blender, 3DS Max a plus.\nEnthusiastic and interested in blockchain/NFT design UI/UX\nEnclosed with your portfolio or links to your design work\n\n\u00a0What\u2019s in it for you?\n(Don\u2019t forget to checkout our perks in the employer profile page)\nCompetitive salary & equity grants / Medical, dental & vision insurance / Annual bonus program / Paid time off & work from home flexibility / Free Glam Bag Plus subscription / Learning & development programs\n\nSo go ahead and make the important choice to be part of an organisation working together for a better future please submit your application, including a cover letter and current resume to\u00a0careers@ MADworld.io (no spacing)\u00a0\n\nThe perks of choosing us:\nUnder our rapidly expanding global startup, you will be rewarded with flexible Hours start of the working day, attractive package to include base equity and/or tokens, equity as well as health benefits, flat organization structure, as much responsibility as you\u2019re able to handle (just put your hand up), challenging work with exposure to cutting edge technologies dedicated to NFT and crypto world, growth in line with rapid scaling of the company, and most importantly, being surrounded with cool-positive and like-minded individuals\n\nWe guarantee that you\u2019ll be supported by a great team of agile experts in a can-do and supportive environment, where change and innovative thinking is encouraged!\n\n\u00a0So go ahead and make the important choice to be part of an organisation working together for a better future please click \u2018Apply\u2019 and submit your application, including a current resume.\n\nWhat is our home look like?\n\nWe are a band of brothers and sisters of bright, talented, collaborative members who love to evolve and jump on new opportunities.\nPeople who care about your growth and career development.\nCross-functional teams who value teamwork - from Hackathon to team off-sites, to Product roadshows, you get to experience it all.\n\n\u00a0If you are highly passionate about the digital environment and love the challenge of building a revolutionized collectibles platform, apply and let us know more about you!", "employment_types": ["Full Time", "Permanent"], "selling_points": ["UI/UX Design", "Crypto", "Fintech"], "locations": ["Central"], "categories": ["Banking / Finance", "Financial Services", "Design", "Web Designer", "Information Technology (IT)", "UI/UX Designer"], "post_time": "2022-01-10T08:45:43Z", "salary": {"currency": null, "max": null, "min": null, "period": "monthly", "term": null}, "salary_visible": false, "title_keywords": ["ux designer"], "responsibilities": ["ideas", "software", "social media platforms", "website", "design", "communication", "social media content", "brand guidelines", "plan", "facebook", "develop", "marketing plan", "marketing campaigns", "visual", "audio", "marketing material", "ui", "social media", "ar", "digital marketing", "career development", "cross-functional teams", "design work", "development programs", "graphic design", "insurance", "asset management"], "requirements": {"degrees": [], "majors": [], "languages": [], "language_level": [], "hard_skills": ["3d software", "plus", "crypto", "agile", "illustrator", "facebook", "adobe creative suite", "blockchain", "maya", "3ds max", "no", "io", "make", "photoshop", "ar", "cool", "dynamic", "go", "rapid", "dc"], "soft_skills": ["agile", "interested in", "collaborative", "passionate about", "determined", "diverse", "creative", "supportive", "dynamic", "communication and interpersonal skills", "friendly", "can-do", "enthusiastic", "positive", "flexible", "passion for", "teamwork", "learning", "organisation", "innovative"], "languages_combined": []}, "experience_required": {"duration": [], "field": ["social media", "marketing", "it", "team"]}}, {"job_id": "100003009035077", "location_code": "hk", "company": "Ucollex International Limited", "job_title": "Graduate Graphic Designer / Social Media Coordinator", "description": "Responsibilities:\n\nResponsible for the creation, design of internal web / client projects.\nHandle web banner and poster creative and design.\nCo-work with different departments on advertising campaigns.\nA strong sense of design aesthetics and creativity.\nRequirements:\n\nDiploma or above in Visual Design, Multimedia Design, Visual Communication, or related disciplines.\n1-2 years relevant experience\u00a0is preferred\nGood knowledge across the Adobe Creative Suite and motion graphic software for web\nEnjoy working in a team environment.\nFresh graduates are also welcomed", "employment_types": ["Full Time", "Permanent"], "selling_points": ["Most disruptive Fintech in the digital world", "Forward thinking and outgoing team culture", "Collaborative and Open-space environment"], "locations": ["Wan Chai"], "categories": ["Design", "Graphics", "Web Designer"], "post_time": "2022-01-10T05:54:10Z", "salary": {"currency": null, "max": null, "min": null, "period": "monthly", "term": null}, "salary_visible": false, "title_keywords": ["coordinator", "graphic designer"], "responsibilities": ["advertising campaigns", "design"], "requirements": {"degrees": ["diploma or above"], "majors": ["multimedia design", "related disciplines", "design"], "languages": [], "language_level": [], "hard_skills": ["web", "visual communication", "visual design", "multimedia", "adobe creative suite"], "soft_skills": ["communication", "enjoy working", "creative"], "languages_combined": []}, "experience_required": {"duration": ["1-2 years"], "field": ["relevant experience"]}}, {"job_id": "100003009036186", "location_code": "hk", "company": "Computer And Technologies Resources Limited", "job_title": "UI/ UX Designer (Ref: JDB/PRD/UIUXD)", "description": "Responsibilities:\n\nResponsible for UI and UX design of applications including mobile apps and responsive website\nNeed to participate\u00a0in product design and creating the design guidelines\nWork closely with internal stakeholder to gather requirement and present the design concept\nCreate UI mock-ups, components and prototypes\nIdentify and troubleshoot UI/UX problems\n\nRequirements:\n\nDiploma or above in Graphic Design, Multimedia or related disciplines\n\nExperience in designing web/mobile products or commercial products\nProficient in UI/UX design software (e.g. Figma, Adobe XD)\nBasic knowledge in HTML, CSS, JavaScript is a must\nBasic knowledge in Vue is a plus\nUpdate-to-date with latest trends and technique in design UI & UX\n\nCreativity and Flexibility\nSelf-motivated, a team player, hardworking and able to work independently\n\nBenefits:\u00a0 \u00a0\u00a0\n\nAnnual Leave 12-18 days\nBirthday Leave\nMarriage Leave\nCompassionate Leave\nFull Paid Paternity Leave\u00a0\nMaternity Leave\u00a0\nNotebook Subsidy\nEducation\u00a0Subsidy\nExamination Time-off\u00a0\nGraduation\u00a0Time-off\nAs a caring company, staff development is one of our top priorities.\u00a0We offer attractive\u00a0remuneration packages with a wide range of fringe benefits include medical & dental insurance, education allowance, performance bonus and excellent career prospect to the right candidate.\u00a0We also offer on-the-job training and specialized training programme to uplift the potential of our staff.\u00a0\n\nInterested parties please send your detailed resume\u00a0with\u00a0current and expected salary\u00a0by email\u00a0to:\u00a0hr_manager @ctil.com\u00a0or by mail to \"Human Resources Department, Computer And Technologies\u00a0Resources Limited, Level 10, Cyberport 2, 100 Cyberport Road, Hong Kong\".\u00a0Please quote the employer reference number in the application.\u00a0\nIn order to explore more about our growth initiatives and other job opportunities, please visit our website\u00a0https://www.ctil.com/.\u00a0\nMore job openings in our C&T group can be viewed in our website\u00a0https://careers.ctil.com/index.php?page=en_Job+Openings.\u00a0\nAll personal data collected will be kept in strict confidence and would only be used for recruitment purpose.", "employment_types": ["Full Time", "Permanent"], "selling_points": ["Responsible for UI and UX design of applications", "Participate in product design & creating guideline", "Birthday Leave & Transportation Subsidy & Time-off"], "locations": ["Pok Fu Lam"], "categories": ["Design", "Web Designer", "Information Technology (IT)", "Software Development", "UI/UX Designer"], "post_time": "2022-01-10T09:36:02Z", "salary": {"currency": null, "max": null, "min": null, "period": "monthly", "term": null}, "salary_visible": false, "title_keywords": ["ux designer"], "responsibilities": ["guidelines", "design concept", "mock-ups", "website", "design", "product design", "troubleshoot", "ui"], "requirements": {"degrees": ["diploma or above"], "majors": ["related disciplines", "graphic design"], "languages": [], "language_level": [], "hard_skills": ["plus", "basic", "web", "adobe xd", "html", "mobile", "javascript", "multimedia", "css"], "soft_skills": ["self-motivated", "team player", "work independently", "hardworking"], "languages_combined": []}, "experience_required": {"duration": [], "field": ["commercial"]}}, {"job_id": "100003009035522", "location_code": "hk", "company": "The French Chamber of Commerce and Industry in HK", "job_title": "Designer UX / UI", "description": "Since its creation in 2009, Our Client - has grown into Asian leading player in Blended Learning solution and one of the European top providers of training for front line staff of Luxury, Watch, Beverage & Cosmetic Brands.\nThey design memorable customer experiences on assessing the 4 dimensions of customer experience recommending, designing, and implementing turnkey solutions to align brand strategy with customer perception. They have a comprehensive product range that extends from product training to bespoke soft skills contents. Its multimodal approach draws on several learning formats. Since 2009 The Group has delivered over 4,000 training programmes and over 400 E-learning modules for leading international brands.\nWe are looking for a Designer (UX/UI)\nYou will be based in their Hong Kong regional office and will be a key position within the Learning & Development team and the marketing team.\nThe role works cross functionally with the internal teams.\nYour role:\n\n\u2022 Act as the main point-of-contact with the Technical, Training teams and designated learning technology provider.\n\n\u2022 Product design which included all kind of graphic and digital design, and presentation materials\u00a0\n\n\u2022 Create compelling website and mobile app user interface designs\u00a0\n\n\u2022 Translate user flow into wireframes, mockups, components, and clickable prototypes for website and\u202fmobile application\u00a0\n\n\u2022 Create a visual identity as reference of all design initiatives\u00a0\n\nWho are we looking for:\u00a0\n\n\u2022 Energetic and engaging with a \u2018can do\u2019 attitude, with excellent interpersonal skills\n\n\u2022 High level of communication skills both verbal and written\n\n\u2022 Collaborative spirit and influence in a \u201cwin as a team\u201d environment.\n\nWhat you will develop\n\n\u2022 Elearning technologies\n\n\u2022 UI: graphic design in a digital environment\n\n\u2022 Software for Data tracking to integrate the customer at the core of your design\u00a0\n\nRequirements\n\u2022 Degree holder in Graphic Design, Multimedia, Information or related disciplines\u00a0\n\n\u2022 At least 5years digital experience of\u202fWeb and Mobile Apps UI/UX design\n\n\u2022 3-5 years of work experience\n\n\u2022 Possess a strong portfolio of UI/UX-focused work for both web and mobile applications\u00a0\n\n\u2022 Experience in EdTech would be an advantage\u00a0\n\n\u2022 High competence in web design and wireframe tools,\u00a0\n\n\u2022 Sketch, Adobe Creative Cloud, and Microsoft environment are a must\n\n\u2022 Principle, Invision, Final Cut Pro, HTML, CSS, Javascript are a plus\n\n\u2022 Great command of English\n\nBenefits\n\u2022 Fast career development within the company\n\n\u2022 Corporate, international and B2B exposure\n\n\u2022 Attractive remuneration package with annual discretionary bonus\n\n\u2022 Medical coverage\n\n\u2022 Training budget of 10000$ end year 2 for personal development\n\n\u2022 Unlimited access to all trainings we develop\n\n\u2022 WFH 1 day a week after probation period (subject to employee\u2019s performance)\n\n\u2022 Sport budget 2500$ after a year seniority\n\n\u2022 3 years and 5 years anniversary gift\n\n\u2022 5 day off per year for CSR initiative after a year seniority", "employment_types": ["Full Time"], "selling_points": ["5 years experience", "Website and Mobile App experience", "Graphic and Digital Design"], "locations": ["Sheung Wan"], "categories": ["Design", "Graphics", "Web Designer"], "post_time": "2022-01-10T07:32:26Z", "salary": {"currency": null, "max": null, "min": null, "period": "monthly", "term": null}, "salary_visible": false, "title_keywords": ["designer"], "responsibilities": ["software", "data", "graphic design", "design", "develop", "ui", "tracking"], "requirements": {"degrees": ["degree holder"], "majors": ["related disciplines", "graphic design"], "languages": ["english"], "language_level": [], "hard_skills": ["final cut pro", "web design", "plus", "web", "html", "mobile", "adobe", "javascript", "multimedia", "css"], "soft_skills": ["creative", "focused"], "languages_combined": [{"language": "english", "language_level": []}]}, "experience_required": {"duration": ["3-5 years"], "field": ["digital", "design"]}}, {"job_id": "100003009034067", "location_code": "hk", "company": "Webs s'up Production Company Limited", "job_title": "Digital Designer", "description": "We\u2019re Webs S\u2019 up, a digital consultancy with a singular mission \u2013 We Enhance Engagement.\n\n\nJoin us to become a Webs S\u2019 up family member!\nYou will be entitled to a competitive salary and attractive staff benefits including:\nAnnual leave, paid sick leave, compensation leave, marriage leave, maternity leave, paternity leave and compassionate leave\nFive-day work week in Kowloon Bay Office\nComprehensive medical and dental coverage\nProfessional training and career advancement opportunities\nFriendly working environment\u00a0and work-life balance culture\nWhat do you need to do?\nCreate and present a variety of UX & UI assets (sketches, user flows, wireframes & prototypes for Company's web, responsive and mobile projects) iteratively while confidently articulating the rationale for your designs\nDeliver specifications that comply with existing design language including: color palette usage, branding, imagery, layout, and typography\nDemonstrate proficiency in balancing user goals, technology needs, and business objectives\nExperience with banking, financial services, insurance, and property companies/projects is preferable\nWhat do you need to have?\nMinimum 3 years\u2019 solid experience on UX & UI design of web application and mobile app\nBeing involved from research and concept design, to detailed design in an Agile process\nExtensive knowledge of wireframing and prototyping tools such as Sketch, InVision, Figma, and Adobe Xd\nAwareness of the latest front-end technologies: HTML, CSS, JavaScript, JQuery etc.\nExperience in user testing and usability analysis\nExcellent verbal and written communication skills\nReady to join us? Apply now to submit your resume & expected salary to us!\n(Personal data will be used for Webs s\u2019 up Production Limited recruitment purposes only. We will retain the applications of candidates for no more than 12 months.)", "employment_types": ["Full Time", "Permanent"], "selling_points": ["Competitive salary with attractive Talent Benefits", "Open-minded and young working environment", "Knowledge in HTML5 and CSS for rapid prototyping"], "locations": ["Kowloon Bay"], "categories": ["Media & Advertising", "Creative / Design", "Design", "Web Designer"], "post_time": "2022-01-10T02:34:35Z", "salary": {"currency": null, "max": null, "min": null, "period": "monthly", "term": null}, "salary_visible": false, "title_keywords": ["digital designer"], "responsibilities": [], "requirements": {"degrees": [], "majors": [], "languages": [], "language_level": [], "hard_skills": [], "soft_skills": [], "languages_combined": []}, "experience_required": {"duration": [], "field": []}}, {"job_id": "100003009032052", "location_code": "hk", "company": "Khan Industries Limited", "job_title": "Web & Graphic Designer", "description": "Our client is a mobile trading platform focus in securities trading who is looking for a graphic and multimedia designer.\n\nResponsibilities\n\nProvide quality design for printed artworks and digital marketing artworks for mobile investment app (including DM, banner ads, website, Facebook, LinkedIn and Instagram)\uff1b\nManage design projects from concepts to production independently\uff1b\nWork closely with different parties to ensure on time execution\uff1b\nPerform ad hoc design projects when required.\nRequirements\n\nHigher Diploma or above in Design / Web Design / Multimedia Design or related disciplines;\n1-3 years working experience in graphic and multimedia design; Experience in FinTech working environment is a plus\nProficient in AI, Photoshop, Infographic, Illustrator, InDesign, Flash, Dreamweaver, Adobe Premiere/After Effect or other relevant software\uff1b\nKnowledge in Social Media Marketing and Mobile Application / Web design\uff1b\nInnovative, proactive with an excellent sense of graphic design, web design and digital design\uff1b\nGood command in English, Cantonese, Mandarin (is a plus)", "employment_types": ["Full Time", "Permanent"], "selling_points": ["HKD16,000 - 18,000 /month", "5 days work, Overtime Pay", "Small team, Friendly work environment"], "locations": ["Ngau Tau Kok"], "categories": ["Design", "Graphics", "Web Designer", "E-commerce", "Others"], "post_time": "2022-01-07T10:09:33Z", "salary": {"currency": null, "max": null, "min": null, "period": "monthly", "term": null}, "salary_visible": false, "title_keywords": ["graphic designer"], "responsibilities": ["ad hoc", "quality", "website", "design", "digital marketing", "facebook"], "requirements": {"degrees": ["higher diploma or above"], "majors": ["multimedia design", "web design", "related disciplines", "design"], "languages": ["cantonese", "english", "mandarin"], "language_level": ["good command"], "hard_skills": ["web design", "plus", "ai", "indesign", "illustrator", "mobile", "adobe premiere", "multimedia", "flash", "dreamweaver", "after effect", "photoshop"], "soft_skills": ["innovative", "proactive"], "languages_combined": [{"language": "cantonese", "language_level": ["good command"]}, {"language": "english", "language_level": ["good command"]}, {"language": "mandarin", "language_level": ["good command"]}]}, "experience_required": {"duration": ["1-3 years"], "field": ["graphic", "design"]}}, {"job_id": "100003009031316", "location_code": "hk", "company": "ACG (Able Communications Group)", "job_title": "Web and Graphic Designer - 5 days' work", "description": "Job Duties\n\nResponsible for new development & maintenance to the websites and eCommerce sites\nCreate graphic design for corporate websites, social media and any online advertising materials\nApply best practices to increase page speed & ratings, and SEO ranking\nProvide documentation and administrative support as assigned\n\nRequirements\n\nAt least 1 year experience in related field\nDiploma or above in design or related disciplines\nKnowledge in HTML and CSS\nProficient in Adobe Photoshop, Illustrator, SEO and Wordpress\nGood art sense, detail-oriented, good communication skills\nGood command of Chinese & English\nPortfolio attachment is a MUST\n\nWe will offer\n\n5 days work\n12 days annual leave\nWedding leave\nOvertime pay\nSmall team, Friendly work environment\nInterested parties, please send your resume stating expected salary, portfolio and click \"Apply Now' to submit your application.\n\nAll personal data provided by job applicants will be used for recruitment purpose only. Applicants who are not invited for interview within six weeks might consider their applications unsuccessful.", "employment_types": ["Full Time", "Permanent"], "selling_points": ["UI/UX design work experience", "Over 10,000 square feet office in Causeway Bay", "Birthday and Marriage Leave"], "locations": ["Causeway Bay"], "categories": ["Design", "Graphics", "Web Designer"], "post_time": "2022-01-07T09:11:18Z", "salary": {"currency": null, "max": null, "min": null, "period": "monthly", "term": null}, "salary_visible": false, "title_keywords": ["graphic designer"], "responsibilities": ["social media", "seo", "maintenance", "administrative support", "graphic design", "documentation", "online advertising"], "requirements": {"degrees": ["diploma or above"], "majors": ["related disciplines", "design"], "languages": ["english", "chinese"], "language_level": ["good command"], "hard_skills": ["small", "seo", "adobe photoshop", "illustrator", "html", "wordpress", "css"], "soft_skills": ["communication skills", "friendly", "detail-oriented"], "languages_combined": [{"language": "english", "language_level": ["good command"]}, {"language": "chinese", "language_level": ["good command"]}]}, "experience_required": {"duration": ["at least 1 year"], "field": ["related"]}}, {"job_id": "100003009020253", "location_code": "hk", "company": "Cornerstone Global Partners", "job_title": "UX/UI Designer (Leading Insurance firm)", "description": "Responsibilities:\n\nPrepare eShop promotion landing page, CMS management and maintain website content\nPrepare artworks for web interface including web design, page layout, banner, animation etc.\nSupport the production of online campaign including online/mobile shopping\nDesign promotional materials including web banner, eDM, catalogues, brochure, and poster advertisement.\n\nRequirements:\n\nDiploma or above in Graphic, Multimedia Design, or related disciplines\nKnowledge of design applications (DreamWeaver, Photoshop, Illustrator)\nFamiliar with HTML5, UX & UI, CSS, JS\nGood communication skills in both Chinese & English\nA good team player with good time management skill\n\nAn attractive salary and benefit package will be offered. Interested parties please forward detailed resume stating expected salary to: People\u00a0Department, PARKnSHOP (HK) Limited, Watson House, 1-5 Wo Liu Hang Road, Fo Tan, N.T. or email to us.\n\nWe are an equal opportunity employer and welcome applications from all qualified candidates. The information provided will be treated in strict confidence and be used only for consideration of your application for relevant / similar posts within the A.S. Watson Group. All personal data of unsuccessful applicants will be destroyed within 12 months from the date of application.", "employment_types": ["Full Time"], "selling_points": ["Design/develop Mobile and Website UI", "UX/UI Development | Mobile Apps focus", "At least 5 years of relevant experience"], "locations": ["Central & Western Area"], "categories": ["Design", "Industrial / Product", "Web Designer", "Information Technology (IT)", "UI/UX Designer"], "post_time": "2022-01-04T10:17:11Z", "salary": {"currency": null, "max": null, "min": null, "period": "monthly", "term": null}, "salary_visible": false, "title_keywords": ["ui designer"], "responsibilities": ["management", "edm", "website", "design", "maintain", "promotional materials", "animation"], "requirements": {"degrees": ["diploma or above"], "majors": ["multimedia design", "related disciplines"], "languages": ["english", "chinese"], "language_level": ["good"], "hard_skills": ["illustrator", "multimedia", "dreamweaver", "css", "photoshop"], "soft_skills": ["communication skills", "good team player", "time management skill"], "languages_combined": [{"language": "english", "language_level": ["good"]}, {"language": "chinese", "language_level": ["good"]}]}, "experience_required": {"duration": [], "field": []}}, {"job_id": "100003009013952", "location_code": "hk", "company": "Stepworks Co Ltd", "job_title": "Web and graphic designer", "description": "Diploma in graphics design or related discipline\n3 years of relevant experience, preferably in books design\nProficient in Indesign, Illustrator, Photoshop\nCreative, independent & self-motivated\nGood communication skills\n\nWe offer a competitive package including medical and dental benefits, double pay and 5-day work etc. to the right candidate. Interested parties please send your application letter with detail resume and expected salary to: Human Resources Manager, Hong Kong Educational Publishing Co., Ltd, 9/F, Eastern Central Plaza, 3 Yiu Hing Road, Shau Kei Wan, Hong Kong or by clicking \"Apply Now\" for application. (Pls quote \"Our Ref:EPD104JOBS\")\n\nAll information of applicants will be kept confidential and would be use for recruitment purposes only.", "employment_types": ["Full Time", "Permanent"], "selling_points": ["Over 5 years relevant experience", "Enjoy working in a team environment", "5-day work week"], "locations": ["Central"], "categories": ["Media & Advertising", "Creative / Design", "Design", "Graphics", "Web Designer"], "post_time": "2022-01-03T02:53:31Z", "salary": {"currency": null, "max": null, "min": null, "period": "monthly", "term": null}, "salary_visible": false, "title_keywords": ["graphic designer"], "responsibilities": ["graphics", "communication", "design"], "requirements": {"degrees": ["diploma"], "majors": ["design"], "languages": [], "language_level": [], "hard_skills": ["graphics", "indesign", "illustrator", "photoshop"], "soft_skills": ["communication skills", "self-motivated", "creative", "independent"], "languages_combined": []}, "experience_required": {"duration": ["3 years"], "field": ["relevant experience", "design"]}}, {"job_id": "100003009019783", "location_code": "hk", "company": "Hong Kong Educational Publishing Company Ltd.", "job_title": "Graphic Designer", "description": "Job Description\nResponsible for the creation, design, development, and maintenance of the corporate websites of individual businesses.\nCreate graphic and animated design for our website, social media, and branding assets for marketing campaigns\nApply best practices to increase page speed & ratings, and SEO ranking\nRequirement\n\nDiploma holder or above in web, graphic design, or related field\nAt least 2 years of relevant working experience\nKnowledge in SEO, CSS, HTML5, Java and WordPress\nKnowledge in Adobe Photoshop, Fireworks, Illustrator, Flash, Dreamweaver\nExperience in video shooting and production is an advantage\nStrong sense of responsibility, a good team player while being able to work independently to meet project deadlines\nGood communication skills\nGood command of written and spoken Chinese, Mandarin & English\nPortfolio attachment is a MUST\nImmediate availability is highly preferred\nCandidate with more experiences would also be considered as Senior Web & Graphic Designer\n\nBenefit\n\nMedical insurance\nDental insurance\nDiscretionary bonus\nAttractive performance bonus\nFriendly and collaborative work environment\n\nWe offer competitive remuneration package and good prospects to the right candidates.\n*For more details, please visit our official website: https://hkfamily.com.hk/\u00a0\n*Interested parties please send your full resume with expected salary by clicking \u201cApply now\u201d\n\n*The information provided by applicants will be kept confidential and will be\u00a0used solely for recruitment purpose only.\u00a0All the applications will be destroyed after 6-month.", "employment_types": ["Full Time", "Permanent"], "selling_points": [], "locations": ["Eastern Area"], "categories": ["Design", "Graphics", "Multi-media", "Web Designer"], "post_time": "2022-01-04T10:42:17Z", "salary": {"currency": null, "max": null, "min": null, "period": "monthly", "term": null}, "salary_visible": false, "title_keywords": ["graphic designer"], "responsibilities": ["social media", "seo", "maintenance", "website", "design", "marketing campaigns"], "requirements": {"degrees": ["diploma holder"], "majors": ["graphic design"], "languages": ["english", "chinese", "mandarin"], "language_level": ["good command"], "hard_skills": ["java", "seo", "web", "adobe photoshop", "illustrator", "wordpress", "flash", "dreamweaver", "css"], "soft_skills": ["communication skills", "good team player", "work independently", "sense of responsibility"], "languages_combined": [{"language": "english", "language_level": ["good command"]}, {"language": "chinese", "language_level": ["good command"]}, {"language": "mandarin", "language_level": ["good command"]}]}, "experience_required": {"duration": ["at least 2 years"], "field": ["graphic", "video shooting", "designer", "relevant working experience"]}}, {"job_id": "100003009014607", "location_code": "hk", "company": "Hong Kong Loving Family Limited", "job_title": "Web & Graphic Designer [Salary range: 20K -25K (depends on exp.) ]", "description": "Responsibilities\n\nResponsible for managing company's online marketing platform, including releasing new products, optimizing the user flows and interface in order to improve customer experience\nResponsible for building mobile\u2019s page of online marketing platform by designing the user interface\nResponsible for designing online marketing activities with Digital Marketing team for different scenarios, users and products, in order to enhance the attractiveness of the activities and customer engagement to generate leads and purchase\nResponsible for website user research, evaluation of user feedback, and website optimization based on the feedback\nCollaborate with the IT development and UI design teams to develop and maintain the online marketing platform, including proposing business requirements, reviewing design drafts, and conducting UAT testing\nResponsible for SEO optimization and suggest SEO keywords to improve website organic search ranking in various search engines\nAccomplish any other duties as assigned\n\nRequirements\n\nBachelor degree or above in Interaction Design, HCI, Web, Finance, Economics, Mathematics, Statistics, Computer and other related disciplines\n4-5 years relevant working experiences in marketing and UX/UI design on both mobile and desktop platform is an advantage, and experience in developing UI prototypes are preferred\nExcellent interpersonal, problem-solving skills and data analytical skill\nProficiency in Excel and Google Analytics\nGood command of written and spoken English and Chinese (including Mandarin)\nApplication\n\n\nInterested parties please send a detailed resume, stating current and expected salary to Human Resources Department.\n\nInformation supplied will be treated in strict confidence and used in accordance with the Personal Data (Privacy) Ordinance. Applicants not invited for interview within 6 weeks may consider their applications unsuccessful.\n", "employment_types": ["Full Time"], "selling_points": [], "locations": ["Shatin Area"], "categories": ["Design", "Graphics", "Multi-media", "Web Designer"], "post_time": "2022-01-03T03:47:22Z", "salary": {"currency": null, "max": null, "min": null, "period": "monthly", "term": null}, "salary_visible": false, "title_keywords": ["graphic designer"], "responsibilities": ["collaborate with", "any other duties", "evaluation", "seo", "teams", "website", "design", "develop", "uat testing", "user interface", "purchase", "maintain", "digital marketing", "designing", "ui"], "requirements": {"degrees": ["degree or above", "bachelor"], "majors": ["mathematics", "finance", "economics", "statistics", "design", "related disciplines"], "languages": ["english", "chinese", "mandarin"], "language_level": ["good command"], "hard_skills": ["excel", "analytical skill", "google analytics", "web", "mobile", "problem-solving skills"], "soft_skills": ["problem-solving skills", "analytical skill", "interpersonal"], "languages_combined": [{"language": "english", "language_level": ["good command"]}, {"language": "chinese", "language_level": ["good command"]}, {"language": "mandarin", "language_level": ["good command"]}]}, "experience_required": {"duration": ["4-5 years"], "field": ["marketing", "developing", "design"]}}, {"job_id": "100003009022755", "location_code": "hk", "company": "Randstad Hong Kong Limited", "job_title": "User Experience (UX) Researcher - Banking / Financial", "description": "Our Customer Relationship Management and e-Marketing Team widely and creatively drives and implements strategies for managing communications and interactions with our customers. We frequently adopt new technology to organize, automate, and synchronize business processes and sales activities for direct marketing and achieving high quality customer service. In order to attract, retain and enhance the loyalty of FANCL customers to support business growth, not only we would establish innovative online and mobile communication platforms, but also highly emphasize the importance of being customer centric to understand the ultimate need of our customers.\n\nResponsibilities:\n\nInitiate the development of innovative customer loyalty programs for business growth\nConduct various customer analyses to unveil the hidden untapped business opportunities\nEnhance the critical analytics infrastructure to support customer centric strategy for online and mobile marketing campaigns, direct marketing and iFANCL Apps\nLead and coordinate CRM and direct marketing campaigns for several Asia Pacific regions, including Hong Kong, China, Taiwan and Singapore\nCoordinate and support iFANCL online store items launch and promotions strategies\nRequirements:\n\nBachelor Degree in Marketing, e-Commerce, Engineering, Computer Science or a related discipline\nAt least 3 years\u2019 relevant experience in direct marketing, online marketing, mobile App system development, customer and content traffic data analysis, online/ membership system development or e-marketing activities coordination, preferably in cosmetics or FMCG marketing field\nKnowledgeable in CRM system design, Apps development and on-line system management\nStrong numerical sense and analytical skills\nCreative with strong marketing sense and business acumen\nIndependent, self-motivated, able to work under pressure and embrace fast-pace working culture\nProficiency in MS Access, Excel, Word and Chinese Word Processing\nGood command of both written and spoken English and Chinese (Cantonese & Mandarin)\nWhat We Offer\nA 5-day work week\nCompetitive Salary Package\nGuaranteed 13 Months\u2019 Pay & Year End Discretionary Bonus\nOn the Job Training & Training Sponsorship\nFull Paid Sick Leave, Annual Leave, Maternity Leave, Paternity Leave\nStaff Benefits e.g. Staff Purchase Discounts, Free Product, Sponsor of Gym Membership, Comprehensive Medical Benefits Coverage, etc.\nStaff Activities & Events e.g. Mid-Autumn Festival Gathering, New Joiner Gathering, Annual Dinner, Christmas Parties, Health Talks, Sports Activities, Interests Classes etc.\u00a0\u00a0\nInterested applicants please click 'Apply Now'\u00a0and send your r\u00e9sum\u00e9 with expected salary to us.\u00a0For internal reference purpose, please also state your public examination results on your attached r\u00e9sum\u00e9.\nPersonal data collected will be used for recruitment purposes only.", "employment_types": ["Full Time", "Permanent"], "selling_points": [], "locations": ["Causeway Bay"], "categories": ["Design", "Web Designer", "Marketing / Public Relations", "Marketing - Market Research", "Information Technology (IT)", "UI/UX Designer"], "post_time": "2022-01-05T06:27:26Z", "salary": {"currency": "HKD", "max": 44999, "min": 30000, "period": "monthly", "term": null}, "salary_visible": true, "title_keywords": ["researcher"], "responsibilities": ["coordinate", "business opportunities", "infrastructure", "marketing campaigns"], "requirements": {"degrees": ["degree", "bachelor"], "majors": ["marketing", "engineering", "computer science", "e-commerce"], "languages": ["cantonese", "english", "chinese", "mandarin"], "language_level": ["proficiency", "good command"], "hard_skills": ["excel", "chinese word processing", "e-commerce", "analysis", "word", "analytical skills", "mobile", "system design", "acumen"], "soft_skills": ["self-motivated", "marketing sense", "independent", "analytical skills", "coordination", "business acumen", "creative", "work under pressure"], "languages_combined": [{"language": "cantonese", "language_level": ["good command"]}, {"language": "english", "language_level": ["good command"]}, {"language": "chinese", "language_level": ["proficiency", "good command"]}, {"language": "mandarin", "language_level": ["good command"]}]}, "experience_required": {"duration": ["at least 3 years"], "field": ["fmcg", "system development", "data analysis", "marketing", "relevant experience"]}}, {"job_id": "100003009023696", "location_code": "hk", "company": "FANCL (Fantastic Natural Cosmetics Limited)", "job_title": "Senior Marketing Executive (CRM & e-Marketing)", "description": "\u8077\u8cac\uff1a\n\u53c3\u8207\u300a\u5c31\u4fc2\u9999\u6e2f\u300bBeing Hong Kong\u7f8e\u8853\u6392\u7248\uff0c\u5305\u62ec\u96dc\u8a8c\u53ca\u5404\u985e\u7dda\u4e0a\u548c\u7dda\u4e0b\u5e02\u5834\u63a8\u5ee3\u5275\u610f\u8a2d\u8a08\n\u8981\u6c42\uff1a\n- \u559c\u6b61\u300a\u5c31\u4fc2\u9999\u6e2f\u300b\uff0c\u4e26\u5e0c\u671b\u548c\u6211\u5011\u4e00\u8d77\u53bb\u5448\u73fe\u9999\u6e2f\u672a\u5b8c\u7684\u6545\u4e8b\n- \u71b1\u611b\u601d\u8003\u548c\u95b1\u8b80\uff0c\u5c0d\u4eba\u3001\u5c0d\u4e16\u754c\u4ecd\u7136\u5145\u6eff\u597d\u5947\u5fc3\n- \u5c0d\u66f8\u520a\u8a2d\u8a08\u6709\u6fc3\u539a\u8208\u8da3\uff0c\u9858\u610f\u4e0d\u65b7\u5b78\u7fd2\u53ca\u4f5c\u591a\u65b9\u9762\u5617\u8a66\n- \u500b\u6027\u4e3b\u52d5\u7a4d\u6975\uff0c\u6709\u8cac\u4efb\u5fc3\uff0c\u559c\u6b61\u878d\u5165\u5718\u968a\u5de5\u4f5c\n\u689d\u4ef6\uff1a\n-\u64c1\u6709\u5c08\u4e0a\u6559\u80b2\uff0c\u61c2\u8b80\u5beb\u4e2d\u82f1\u6587\uff0c\u4e3b\u4fee\u8a2d\u8a08\u3001\u5275\u610f\u6216\u85dd\u8853\u985e\u79d1\u76ee\n-\u719f\u6089InDesign\u3001Illustrator\u3001\u4e86\u89e3Adobe\u7cfb\u5217\u8edf\u4ef6\uff0cPremiere Pro\u3001PhotoShop\u3001MS Word\u53caMS Excel\u7b49\u64cd\u4f5c\n-\u51772\u5e74\u7d93\u9a57\u66f8\u520a\u5e73\u9762\u8a2d\u8a08\u7d93\u9a57\uff1b\u719f\u6089\u651d\u5f71\u3001\u62cd\u651d\u53ca\u77ed\u7247\u526a\u63a5\u7b49\u512a\u5148\u8003\u616e\n-\u4f86\u51fd\u8acb\u9644\u4e0a\u4f60\u7684\u5c65\u6b77\u53ca\u4f5c\u54c1\uff0c\u4ee5\u53ca\u4e00\u6bb5\u7d04100\u5b57\u7684\u6587\u7ae0\uff0c\u5206\u4eab\u4f60\u7684\u95b1\u8b80\u7d93\u9a57\n\n(\u7533\u8acb\u4eba\u63d0\u4f9b\u4e4b\u5168\u90e8\u8cc7\u6599\u7d55\u5c0d\u4fdd\u5bc6\u53ca\u53ea\u7528\u4f5c\u62db\u8058\u7528\u9014\uff09\n\n", "employment_types": ["Full Time", "Permanent"], "selling_points": ["Lead and coordinate CRM & direct marketing", "Conduct customer analysis and enhance CRM programs", "5-day work,13 mth pay and year end bonus"], "locations": ["Tsim Sha Tsui"], "categories": ["Design", "Graphics", "Multi-media", "Web Designer"], "post_time": "2022-01-05T09:31:16Z", "salary": {"currency": null, "max": null, "min": null, "period": "monthly", "term": null}, "salary_visible": false, "title_keywords": ["senior marketing executive"], "responsibilities": [], "requirements": {"degrees": [], "majors": [], "languages": [], "language_level": [], "hard_skills": [], "soft_skills": [], "languages_combined": []}, "experience_required": {"duration": [], "field": []}}, {"job_id": "100003009013197", "location_code": "hk", "company": "ZhenHub Technologies Limited", "job_title": "UI/UX Graphic Designer", "description": "Job Responsibilities:\n\n- To assist in creative ideas generation\n- To work with our programmers throughout the process\n- To support the company in all graphic matters.\n- To design online advertising materials, including Social media materials, Web pages, EDM and animation banners, etc.\n\nJob Requirements:\n\n- Diploma or above in Web Design / Multimedia design / Graphic Design or related discipline\n- Proven Portfolio\n- Experience and passionate in web design or graphic design field\n- Strong art sense, good layout and attention to details\n- Proficient in Photoshop, Illustrator, Flash and Dreamweaver\n- Good hand/computer drawing skill is an advantage\n- Good animation skill is a merit\n- Knowledge in CSS and HTML is a plus;\n- Independent, self-disciplined, responsible, good problem solving skill and a good team player;\n- Willing to work overtime and meet demanding timelines;\n\nGraphic design / Web design / UI design samples enclosed together with the application will be highly recommended.\nLess experience will be consider as a Junior Digital Designer\n\nInterested parties please email detail resume with recent portfolio, current and expected salary to recruit[@]digitpepper.com\nPersonal data collected will be used for recruitment purpose only", "employment_types": ["Full Time"], "selling_points": ["Fast Global Startup Environment", "Solid experience in Web Application UI/UX design", "Adobe Creative Suite"], "locations": ["Tsuen Wan Area"], "categories": ["Design", "Graphics", "Multi-media", "Web Designer"], "post_time": "2022-01-03T01:43:51Z", "salary": {"currency": null, "max": null, "min": null, "period": "monthly", "term": null}, "salary_visible": false, "title_keywords": ["graphic designer"], "responsibilities": ["social media", "creative ideas", "edm", "design", "banners", "online advertising", "animation"], "requirements": {"degrees": ["diploma or above"], "majors": ["multimedia design", "web design", "graphic design"], "languages": [], "language_level": [], "hard_skills": ["web design", "plus", "illustrator", "html", "problem solving", "flash", "multimedia", "dreamweaver", "css", "photoshop"], "soft_skills": ["passionate", "good team player", "work overtime", "independent", "responsible", "attention to details", "problem solving skill"], "languages_combined": []}, "experience_required": {"duration": [], "field": ["graphic design", "designer", "design", "digital"]}}, {"job_id": "100003009014935", "location_code": "hk", "company": "Digit Pepper Limited", "job_title": "Digital Designer / Junior Web Designer", "description": "To cope with our business growth, we are currently looking for a high calibre candidate to join us as a Graphic Designer, mainly focus on preparing marketing materials for company\u2019s products & services.\n\nResponsibilities\n\nResponsible for graphic designs for B2B online marketing materials (website, social media, newsletter, etc.) and print materials (leaflet, brochure, poster, etc.)\nKnowledge on video editing\nWork closely with internal teams to deliver high quality design artworks\nAd-hoc assignments\n\n\u00a0Requirements\n\nDegree holder in Graphic Design, Multimedia Design, or other related disciplines\nMinimum 5 years or above working experiences in design/advertising agency\nStrong sense on art/design & digital marketing trend\nExperience in B2B/Technology/Software field is highly preferred\nHigh proficiency in Adobe Photoshop and Adobe Illustrator is a must\nHigh proficiency in Adobe Premiere and Adobe After Effects is an advantage\nUnderstanding of UI/UX design preferred\nExcellent communication skills in both written and spoken English, Cantonese and Mandarin\nA good team-player, self-motivated, detail-oriented, and responsible\nAble to work independently and under pressure for tight schedule\nDesign portfolio is required for submission\nImmediately available is highly preferred\n\nInterested candidates please send your job application to our HR Department by \u201cAPPLY NOW\u201d. Please indicate the details of your working experience, current and expected salary, and your date of availability in your CV.\n\n(Only shortlisted candidates will be contacted)\n\nPersonal Information Collection Statement (PICS)\n\nThe personal data collected will be used by our member(s) of the recruitment team for recruitment purpose only. It is our policy to retain the personal data of unsuccessful applicants for future recruitment purposes for a period of 3 months.\u00a0 When there are vacancies in our subsidiary or associate companies during that period, we may transfer the candidate\u2019s application to them for consideration of employment.\u00a0 And, all information will be kept confidential during that period and be destroyed after use.", "employment_types": ["Full Time"], "selling_points": [], "locations": ["Chai Wan"], "categories": ["Design", "Graphics", "Multi-media", "Web Designer"], "post_time": "2022-01-03T04:33:35Z", "salary": {"currency": null, "max": null, "min": null, "period": "monthly", "term": null}, "salary_visible": false, "title_keywords": ["digital designer", "designer", "junior"], "responsibilities": ["social media", "ad-hoc assignments", "leaflet", "graphic designs", "website", "teams", "quality", "video editing", "design", "marketing materials"], "requirements": {"degrees": ["degree holder"], "majors": ["multimedia design", "graphic design", "related disciplines"], "languages": ["cantonese", "english", "mandarin"], "language_level": ["excellent"], "hard_skills": ["adobe photoshop", "adobe after effects", "adobe illustrator", "adobe premiere", "multimedia"], "soft_skills": ["communication skills", "self-motivated", "work independently", "under pressure", "responsible", "team-player", "detail-oriented"], "languages_combined": [{"language": "cantonese", "language_level": ["excellent"]}, {"language": "english", "language_level": ["excellent"]}, {"language": "mandarin", "language_level": ["excellent"]}]}, "experience_required": {"duration": ["minimum 5 years"], "field": ["advertising agency", "design"]}}, {"job_id": "100003009013395", "location_code": "hk", "company": "New Yaohan", "job_title": "Senior UI / Web Designer (Station in Macau)", "description": "IMPORTANT PLEASE NOTE: We want to see your best work. For fast attention please link prominently to an online portfolio of no more than ten examples of your best work. Thanks :)\n\nWant a challenge creating outstanding brands and websites?\u00a0\n\nStepworks is a wholehearted independent branding firm, based in Hong Kong. Superb design underpins our work, which is enhanced by next level digital.\n\nWe have a strong track record helping organisations create positive change with our brand building skills, in HK and worldwide.\n\nOn our multicultural team you\u2019ll meet caring people who are really good at building brands that deliver valuable competitive advantages for our clients.\n\nMore on our wholehearted approach to brand building at www.stepworks.co\n\nResponsibilities\n\n\nWork on a range of creative brand building projects for respected organisations\nDesign websites underpinned by a good UX and UI foundation\u00a0\nExpress brand-led ideas using graphic and motion graphics\nProactively take responsibility of the quality of work under your care\nProduce deliverables on brief to a world-class standard with high degree of client satisfaction\nMaintain healthy working relationships\nUnderstand evolving industry best practices in digital, web and brand building\nCapabilities\u00a0\n\nOver 5 years relevant experience\nA strong sense of design aesthetics, artistic talent and creativity\nBe fluent and confident in English and Cantonese\nExpertise across the Adobe Creative SuiteExpertise across the Adobe Creative Suite, Figma or other web prototyping tools, and motion graphic software for web\nGood communication skills and superb organisation and time management skills\nBe experienced in production processes for digital and print\nOther creative skills like illustration, music/audio etc, will be considered a bonus\nEnjoy working in a team environment and be wholehearted\nRewards\n\nFlexible working arrangements\nCompetitive salary, profit sharing and opportunity for growth\nGreat culture working on projects that create positive change\nCaring team who look after each other\nTraining and support for your ambitions\u00a0\nA high credibility gig in your resume\nSounds good?\n\n\nEmail your portfolio, r\u00e9sum\u00e9 and expected salary. We\u2019ll treat it all in confidence.\n\nDon\u2019t forget to link to your portfolio!", "employment_types": ["Full Time"], "selling_points": [], "locations": ["Others - Macau"], "categories": ["Design", "Web Designer"], "post_time": "2022-01-03T02:12:04Z", "salary": {"currency": null, "max": null, "min": null, "period": "monthly", "term": null}, "salary_visible": false, "title_keywords": ["designer"], "responsibilities": ["management", "ideas", "software", "quality", "motion graphic", "design", "communication", "motion graphics", "maintain", "working relationships", "audio", "ui"], "requirements": {"degrees": ["degree"], "majors": [], "languages": ["cantonese", "english"], "language_level": ["fluent"], "hard_skills": ["graphics", "no", "web", "adobe", "illustration", "adobe creative suite"], "soft_skills": ["confident", "communication skills", "flexible", "confidence", "independent", "time management skills", "enjoy working", "organisation", "creative", "positive", "world-class"], "languages_combined": [{"language": "cantonese", "language_level": ["fluent"]}, {"language": "english", "language_level": ["fluent"]}]}, "experience_required": {"duration": ["5 years"], "field": ["relevant experience"]}}, {"job_id": "100003009017025", "location_code": "hk", "company": "Commercial Radio Productions Ltd", "job_title": "Senior Multimedia Designer/ Multimedia Designer", "description": "Commercial Radio Interactive, a division of Commercial Radio Productions Limited and the digital arm of Commercial Radio,\u00a0are looking for a passionate and energetic Multimedia Designer to join our team and develop his/her career under the guidance of our experienced senior designer.\n\nJob Responsibilities\n\n\u2022\u00a0Work closely with Project and Marketing teams to design all digital marketing materials, including website layout, digital web banners, and eDM\n\u2022\u00a0Create visual, video, animation and other graphic design content for social media\n\u2022\u00a0Assist in ad-hoc online advertising and digital projects as assigned\n\nJob Requirements\n\n\u2022\u00a0Minimum 2 years working experience in Graphic Design, Digital Multimedia Design, Creative Media, Advertising or related disciplines\n\u2022\u00a0Proficiency in Photoshop, Illustrator, Dreamweaver and After Effect is an advantage\n\u2022\u00a0Understanding of UI/UX principles and proficient on using web design comp tools such as Adobe Sketch, XD.\n\u2022\u00a0Knowledge of front-end wireframe, responsive web design & prototyping development using HTML5 & CSS.\n\u2022\u00a0Creative, passionate about design / advertising and have a good sense of art direction\n\u2022\u00a0Responsible, self-motivated, willing to learn new skills, able to work under pressure and tight deadlines\n\u2022\u00a0Knowledge of social media, photo shooting, video editing is an advantage\n\u2022 Portfolio in pdf is required for application\n\nLocation: 3 Broadcast Drive, Kowloon, Hong Kong\n\nApplication Procedure:\n\nWe offer attractive remuneration package, competitive salary, medical scheme and life insurance to the right candidate. Interested candidates, please submit application letter with full resume, present and expected salary by clicking \u201cApply Now\u201d (Please quote the job reference number on the e-mail subject line).\n\nAll information received will be kept in strict confidence and only for employment-related purpose. Only short listed candidates will be invited for interview.", "employment_types": ["Full Time"], "selling_points": ["Minimum 2 yrs working experience in Digital Design", "Proficiency in Photoshop, Illustrator, Dreamweaver", "Understanding of UI/UX principles, web design"], "locations": ["Not Specified"], "categories": ["Design", "Multi-media", "Web Designer", "Media & Advertising", "Broadcasting - TV / Radio"], "post_time": "2022-01-03T10:22:34Z", "salary": {"currency": null, "max": null, "min": null, "period": "monthly", "term": null}, "salary_visible": false, "title_keywords": ["multimedia designer"], "responsibilities": ["ad-hoc", "social media", "edm", "graphic design", "teams", "website", "design", "banners", "digital marketing", "visual", "online advertising", "animation"], "requirements": {"degrees": [], "majors": [], "languages": [], "language_level": [], "hard_skills": ["web design", "illustrator", "video editing", "adobe", "multimedia", "dreamweaver", "css", "after effect", "photoshop"], "soft_skills": ["self-motivated", "responsible", "willing to learn", "creative", "responsive", "passionate about", "work under pressure"], "languages_combined": []}, "experience_required": {"duration": ["minimum 2 years"], "field": ["advertising", "related", "graphic design", "design", "digital", "media"]}}, {"job_id": "100003009016972", "location_code": "hk", "company": "iDentity Workshop Limited", "job_title": "Graphic Designer / Assistant Designer (5 DAYS WORK)", "description": "Create layout and artwork design\nAssist in output and production progress\nCarry out ad hoc project / duties assigned by management\nThink creatively with freedom\n\nJob Requirements\n\nKnowledge in design layout and artwork is a MUST.\nMinimum 1 years experience in Advertising Agency / Design industry.\nProficiency in Mac design software such as, Illustrator, Photoshop, In-Design, After Effect, etc\nImmediate available or short notice will be an advantage\nFreelance and Part-time are also welcome.\n\n\nBenefits\n\n5 days work\nMonday to Friday, work on 9:30am, not much OT\nAttendance bonus\nBank Holiday\nAnnual Leave\nFree snack and drinks\nNice and clean working environment\n\n\nWe are looking for a fun, positive, mature and strong design sense person to join our growing team.\n\nInterested parties please send your full resume with portfolio and expected salary by click \"Apply Now\".\n\nPlease visit our website http://www.identity.com.hk/ or Facebook https://www.facebook.com/iDentityWorkshopLtd/ to know more about us.\n\n*Data collected will be used for recruitment purpose only", "employment_types": ["Full Time", "Part Time", "Permanent", "Freelance"], "selling_points": ["5 days work, work on 9:30am, not much OT", "Clean and stable working environment", "Create layout and artwork"], "locations": ["Kwai Hing"], "categories": ["Design", "Graphics", "Industrial / Product", "Web Designer"], "post_time": "2022-01-03T10:14:00Z", "salary": {"currency": null, "max": null, "min": null, "period": null, "term": null}, "salary_visible": false, "title_keywords": ["graphic designer", "assistant designer"], "responsibilities": ["management", "ad hoc", "software", "advertising", "design"], "requirements": {"degrees": [], "majors": [], "languages": [], "language_level": [], "hard_skills": ["in-design", "after effect", "illustrator", "photoshop"], "soft_skills": [], "languages_combined": []}, "experience_required": {"duration": ["minimum 1 years"], "field": ["advertising agency", "design"]}}, {"job_id": "100003009017481", "location_code": "hk", "company": "VTECH Corporate Services Ltd", "job_title": "Multimedia Developer (VCO208/J02)", "description": "To Put A smile on our Customers\u2019 Faces\n\n\"Don\u2019t box me in! We wanted to live the\u00a0life, a DIFFERENT LIFE.\nOur ability to\u00a0helps UNCOVER EXCITING POTENTIALS.\u00a0We wanted interesting challenges.\"\n\n\n\nOur eLab Technology Team's Mission & Value\n\n\nJoin a team of 300 Spartans & battle side by side in squad formation\nUnleash the power of programming - Java, React. Native, \u2026\nDefend the system and eliminate any threat to uphold the stability\nBuild digital products that serve millions\nThe battleground is on the cloud\nEmbrace new technologies to be faster, easier and to inspire an\ninventive culture\nAlways respect the man and woman you are working with, and leave\nno man behind, as we work as one team\nContinuous professional training is provided for your survival\nThere is always time to retreat from the frontline and enjoy freshly\nbrewed coffee and countless refreshments\nWe take care of you and your family, healthcare coverage and health\ninsurance is provided\nEnjoy amazing discount from all company's brands\n\nInterested parties please e-mail your full resume in WORD FORMAT with expected salary to our company email (shown in our Company Profile).\u00a0\nWe are an equal opportunity employer and welcome applications from all qualified candidates. The information provided will be treated in strict confidence and be used only for consideration of your application for relevant / similar posts within the A.S. Watson Group.\u00a0\nApplicants not hearing from us within 6 weeks from the date of advertisement may consider their applications unsuccessful. All personal data of unsuccessful applicants will be destroyed within 12 months from the date of application.", "employment_types": ["Full Time", "Permanent"], "selling_points": ["Motion graphic design, video and photo shooting", "Web banner, eDM, posters artwork design", "5 days work, flexible hours, double pay, bonus"], "locations": ["Tai Po Area"], "categories": ["Design", "Graphics", "Multi-media", "Web Designer"], "post_time": "2022-01-04T00:42:33Z", "salary": {"currency": null, "max": null, "min": null, "period": "monthly", "term": null}, "salary_visible": false, "title_keywords": ["developer"], "responsibilities": ["insurance"], "requirements": {"degrees": [], "majors": [], "languages": [], "language_level": [], "hard_skills": ["no", "java", "programming", "react"], "soft_skills": [], "languages_combined": []}, "experience_required": {"duration": [], "field": []}}, {"job_id": "100003009017150", "location_code": "hk", "company": "A.S. Watson Retail (HK) Limited", "job_title": "[Adventurer] UX Specialist", "description": "OneDegree is a new generation of InsurTech that reimagining the industry with design and digital innovation. Our mission is to set new standards for insurance that puts customers first.\n\nWe are among the first batch of virtual insurers authorized by the Hong Kong Insurance Authority to provide insurance products purely through online channels. We pride ourselves on providing breakthrough innovations in products and services via our digital platform. We are currently offering Pet, Fire and Critical Illness Insurance and expected to provide wider coverage to the general public in the coming year.\n\nWant to join us and make a change? We are looking for a Senior UX/UI Designer to create designs that will set us apart from the crowd.\n\nIf you are passionate about design, come and join our team!\n\nWhat you\u2019ll be doing:\n\nTranslating concepts into wireframes and mockups that lead to intuitive user experiences.\nFacilitating client\u2019s product visions by researching, conceiving, wireframing, sketching, prototyping, and mocking up user experiences for digital products.\nDesigning and delivering wireframes, user stories, user journeys, and mockups optimized for a wide range of devices and interfaces.\nIdentifying design problems and devise elegant solutions.\nMaking strategic design and user-experience decisions related to core, and new functions and features.\nTaking a user-centered design approach and rapidly testing and iterating your designs.\nTaking smart risks and championing new ideas.\n\nWe\u2019re looking for:\u00a0\n\n5+ years of UX/UI design experience. Preference will be given to candidates who have experience designing complex solutions for complete digital environments.\nExpertise in UX software such as InVision, UXPin, Balsamiq, Framer.js, Quartz Composer, and the like is a must. Basic HTML5, CSS3, and JavaScript skills are a plus.\nAbility to work with customers to understand detailed requirements and design complete user experiences that meet client needs and vision\nA solid grasp of user-centered design and testing methodologies, subsystems, and usability and accessibility concerns.\nAbility to iterate your designs and solutions efficiently and intelligently.\nAbility to clearly and effectively communicate design processes, ideas, and solutions to teams and clients\nBe willing to help teammates, share knowledge and experience with them, and learn from them.\n\n**Please attached your portfolio for reference\n\n\n\n\nMore about us:\n\nFast-growing insurtech startup in Hong Kong\nYoung and energetic team\nFlat organization structure\nOpportunities to grow and shine!\n\nWe value our employee - let\u2019s check out what we offer\n\n15 days annual leave\nMedical benefits\nWork-life balance environment\n\nTo us, people are our greatest asset and we are more than happy to invest in employees! We create a healthy\u00a0work atmosphere and provide you with the tools and support for doing your job successfully.\u00a0With a culture of flexibility and transparency,\u00a0we believe there should be no barriers, and everyone\u2019s contributions matter.\u00a0\n\nWe would like to be an \u2018EMPLOYER OF CHOICE\u2019!\n\n\n", "employment_types": ["Permanent"], "selling_points": ["/*EXPERIENCE: 2 YEARS", "/*UNIVERSITY GRADUATE IN UX,or PSYCHOLOGY", "/*KNOWLEDGE OF QUALITATIVE AND QUANTITATIVE IS +"], "locations": ["Shatin Area"], "categories": ["Design", "Web Designer", "E-commerce", "Marketing - Brand / Product Management", "Information Technology (IT)", "UI/UX Designer"], "post_time": "2022-01-03T10:50:41Z", "salary": {"currency": null, "max": null, "min": null, "period": null, "term": null}, "salary_visible": false, "title_keywords": ["specialist"], "responsibilities": ["online channels", "ideas", "software", "teams", "digital platform", "design", "testing", "designing", "insurance", "ui"], "requirements": {"degrees": [], "majors": [], "languages": [], "language_level": [], "hard_skills": ["plus", "basic", "make", "batch", "javascript"], "soft_skills": ["energetic", "passionate about", "detailed"], "languages_combined": []}, "experience_required": {"duration": ["5+ years"], "field": ["related", "digital", "design"]}}, {"job_id": "100003009015503", "location_code": "hk", "company": "ONEDEGREE HONG KONG LIMITED", "job_title": "Senior UX/UI Designer - Insurtech Startup", "description": "UI/UX Graphic Designer\n\nZhenHub is a fast growing logistics platform that supports global ecommerce retailers like Walmart, Supercell and Daimler. Our clients are a number of Fortune 500 companies. We are looking for smart, aspiring digital marketers to join our team.\u00a0\n\nThis position will be challenging, you will have to learn quickly or you will be left behind. We are looking for the best and brightest. If you think you have what it takes then apply for this position. The successful candidate will have an opportunity with work with global tech companies, lead marketing projects and learn about the latest digital marketing techniques.\n\nRESPONSIBILITIES\n\nYou will:\n\nDesign graphics/interactions for UI/UX on Web/Mobile applications\nGathering and evaluating user requirements, in collaboration with developer\nTake charge of the development and creation for different Digital/Print marketing materials and brand collaterals, from creative concept development to final production\nEnhance and maintain the user interface and usability of the responsive website.\nLiaise with Vendors in production of print materials\nMaintain and Update visual elements on Website and Social Media Platforms\nDesign creative materials including webpages, banners, eDM.\nPerform user testing and other activities to gain knowledge from end users.\nWork closely with web/app developers to understand technical requirements\nPhoto shooting and editing\n\n\nREQUIREMENTS:\n\n\nDiploma or above in Graphic Design, Fine Art or other related disciplines\n2 years solid experience in graphic design\nHands-on experience in design software such as Photoshop, Illustrator, Dreamweaver/WordPress/HTML, Flash and Premiere\nCreative and passionate, with strong aesthetic sense, ability to think out-of-the-box and great eye for detail\nStrong abilities in HTML/CSS skills in web design.\nKnowledge and experience in JavaScript, ReactJS, Invision is an advantage\nProficient in Adobe Creative Suite (PS, FW & IL)\nAble to work under pressure and deliver on tight deadlines\nGood communication skills and good command in both spoken and written English and Chinese\n\nWe\u00a0offer\u00a0an attractive remuneration package to the right candidate. Interested parties please click the \"APPLY NOW\" button above and send your application together with a detailed resume including current & expected salary and availability to Human Resources Department.\n\nCompany website:\u00a0https://www.zhenhub.com\n\nor\n\nPlease submit your applications to careers(a)zhenhub.com.", "employment_types": ["Full Time"], "selling_points": ["Flat structure, job flexibility and empowerment", "Fast-growing insurtech startup", "Work-life balance, medical benefits"], "locations": ["Ngau Tau Kok"], "categories": ["Design", "Web Designer"], "post_time": "2022-01-03T06:51:16Z", "salary": {"currency": null, "max": null, "min": null, "period": "monthly", "term": null}, "salary_visible": false, "title_keywords": ["ui designer"], "responsibilities": ["edm", "social media platforms", "website", "design", "testing", "user interface", "liaise with", "maintain", "banners", "design graphics", "visual", "marketing materials", "editing", "ui"], "requirements": {"degrees": ["diploma or above"], "majors": ["related disciplines", "graphic design", "fine art"], "languages": ["english", "chinese"], "language_level": ["good command", "good"], "hard_skills": ["web design", "illustrator", "html", "premiere", "wordpress", "javascript", "flash", "dreamweaver", "css", "adobe creative suite", "photoshop"], "soft_skills": ["passionate", "communication skills", "hands-on", "eye for detail", "creative", "work under pressure"], "languages_combined": [{"language": "english", "language_level": ["good command", "good"]}, {"language": "chinese", "language_level": ["good command", "good"]}]}, "experience_required": {"duration": ["2 years"], "field": ["graphic design", "design"]}}, {"job_id": "100003009016367", "location_code": "hk", "company": "C-Mer Dennis Lam & Partners Eye Center", "job_title": "Graphic Designer", "description": "Create compelling mobile responsive and engaging retail related promotion landing pages for App/website\nEnsure quality, timeliness, relevance and accuracy of content\nMaintain high-quality user interface and experience\nConduct Web/App user acceptance test\nPresent new solutions for future UI/UX product development\nTrouble shoot coding related issues\nCreate traditional print, still or animated design for our website, social media, and branding assets for marketing campaigns\nAssist with in-store promotional event\nRequirement:\nBachelor degree in web, graphic design or related field\n3+ years of working experience with digital publishing experience\nAdobe Creative Suite proficiency\nDetail oriented and able to work independently or as a team\nAble to organize and meet tight project deadline\nGood knowledge of CSS, HTML5, Java, and SEO\nGood product photography skills\nGood graphic design skills\nGood written and communication skills in both Chinese and English\nWe offer competitive remuneration package including meal allowance, medical scheme, discretionary bonus, double pay\u00a0and\u00a0pension fund with excellent career exposure opportunities to the right candidates.\nInterested parties, please apply with full resume\u00a0in MS Word format with present and expected salary\u00a0together with your portfolio\u00a0via the \u201cAPPLY NOW\u201d button below.\nCompany website:\u00a0www.newyaohan.com\n(Personal data collected will be used for recruitment purpose only)\n\u65b0\u516b\u4f70\u4f34\u6295\u8cc7\u7ba1\u7406\u6709\u9650\u516c\u53f8-\u6fb3\u9580\u65c5\u904a\u5a1b\u6a02\u80a1\u4efd\u6709\u9650\u516c\u53f8\u9644\u5c6c\u516c\u53f8\nPanda Sociedade de Gestao de Investimentos Limitada - A Subsidiary of STDM", "employment_types": ["Full Time"], "selling_points": ["Young and dynamic marketing team", "Work location: Central", "5 days work week"], "locations": ["Central"], "categories": ["Media & Advertising", "Creative / Design", "Design", "Graphics", "Web Designer"], "post_time": "2022-01-03T08:57:08Z", "salary": {"currency": null, "max": null, "min": null, "period": "monthly", "term": null}, "salary_visible": false, "title_keywords": ["graphic designer"], "responsibilities": ["social media", "seo", "graphic design", "quality", "website", "coding", "design", "communication", "user interface", "maintain", "marketing campaigns", "ui"], "requirements": {"degrees": ["degree", "bachelor"], "majors": ["graphic design"], "languages": ["english", "chinese"], "language_level": ["good"], "hard_skills": ["java", "seo", "web", "scheme", "mobile", "css", "adobe creative suite"], "soft_skills": ["communication skills", "work independently", "detail oriented", "creative", "responsive"], "languages_combined": [{"language": "english", "language_level": ["good"]}, {"language": "chinese", "language_level": ["good"]}]}, "experience_required": {"duration": ["3+ years"], "field": ["digital", "publishing"]}}, {"job_id": "100003009007874", "location_code": "hk", "company": "EC Healthcare", "job_title": "Multi-media Designer", "description": "Job Duties\nResponsible for coming up/executing graphic ideas related to eye care information\nCollaborate with marketing, event and content team members on crafting the\u00a0overall visual strategy\nDesign both offline and online communications and marketing content\nDesign campaign and events material\nAd-hoc duties as assigned from time to time\nRequirements\n\nCertificate / Diploma / Degree holder in Design / Graphic Design / Creative Media / Multimedia Design or related field\nMinimum 1- 2 years of solid experience in commercial design and production\nGood illustration skill is a huge advantage\nFamiliar with websites and social media platforms such as Facebook, Instagram and YouTube\nGood communication & interpersonal skills\nCandidate familiar with medical industry, especially ophthalmology, is highly preferred\nImmediate availability is highly preferred\nBenefits\n\nYoung and dynamic marketing team\n5-day work per week\nMedical insurance\nAnnual leave\nAnnual discretionary bonus\nSpecial offer of eye treatment for staff and family\nSkills\n\nAdobe Photoshop/Illustrator/In-design/After Effect/Premiere/retouching\nSocial media operations (Facebook/Instagram)\nCompany website:\nhttps://smile.hkcmereye.com\nhttps://www.hkcmereye.com\n\n*Candidates without portfolio will not be considered*", "employment_types": ["Full Time"], "selling_points": ["evelop creative concepts, layouts and artworks", "Photoshop, Illustrator", "1-2 years of work experience in design field"], "locations": ["Mong Kok"], "categories": ["Design", "Graphics", "Multi-media", "Web Designer"], "post_time": "2021-12-30T04:56:49Z", "salary": {"currency": null, "max": null, "min": null, "period": "monthly", "term": null}, "salary_visible": false, "title_keywords": ["designer"], "responsibilities": ["collaborate with", "ideas", "ad-hoc duties", "design", "executing", "visual"], "requirements": {"degrees": ["certificate", "diploma", "degree holder"], "majors": ["multimedia design", "graphic design", "creative media", "design"], "languages": [], "language_level": [], "hard_skills": ["facebook", "illustration", "multimedia"], "soft_skills": ["communication", "creative", "interpersonal skills"], "languages_combined": []}, "experience_required": {"duration": ["minimum 1- 2 years"], "field": ["commercial", "design"]}}, {"job_id": "100003009014473", "location_code": "hk", "company": "E-buy Global Limited", "job_title": "Assistant Design and Marketing Officer (Content Marketing)", "description": "To cope with the departmental growth, we are looking for a creative graphic designer to join our Hong Kong office. The ideal candidate should have graphics and multimedia design background, a good sense of aesthetics, good communication skills, willingness to undertake a wide range of tasks and will work in a team as well as individually.\n\nResponsibilities:\n\nProvide innovative ideas for web development and motion graphic design;\nAssist in video shooting and editing;\nResponsible for photo shooting and retouch of event/product shot;\nProduce multimedia materials, such as web banner, eDM, posters and other electronic promotion materials;\nDevelop artwork design and website visual content.\n\nRequirements:\n\nHigher diploma or above in Multimedia/Graphic Design or other related disciplines;\nMinimum 1 year experience in video editing, shooting & multimedia;\nKnowledge in sound editing and graphic design tools, such as After Effects, Premiere, GarageBand, Illustrator, Photoshop, Adobe CS5 Suite, etc.;\nKnowledge of 3D software, such as Maya, 3Ds Max, etc.;\nFamiliar with Search Engine Optimization, eDM design and eCommerce technologies will be an advantage;\nSelf-motivated, able to work under pressure and quality oriented;\nGood command of written and spoken English;\nFresh graduates with potential will also be considered\n\n\n\nWe offer an attractive remuneration package including 5-day work, flexible work hours and other benefits to the right candidates. Interested parties please forward full resume with expected salary and quote job reference number by \"Apply Now\" or to\n\nVTech Group of Companies,\nThe Human Resources and Administration Department,\n23/F, Block 1, Tai Ping Industrial Centre,\n57 Ting Kok Road, Tai\u00a0Po,\u00a0Hong Kong\n\nFor more information about us, please visit our website at:\u00a0www.vtech.com\u00a0\u00a0\u00a0\n\nAll applications will be used for the purpose of recruitment only. Applicants not invited for an interview within 4 weeks may consider their applications unsuccessful. We will retain the applications for a maximum period of six months and may refer them to suitable openings within our Group.\u00a0", "employment_types": ["Full Time"], "selling_points": ["Bachelor\u2019s degree in graphic design", "Graphic design skills with a great portfolio", "Fresh graduates are welcome to apply"], "locations": ["Kwai Hing"], "categories": ["Design", "Graphics", "Multi-media", "Web Designer"], "post_time": "2022-01-03T03:28:57Z", "salary": {"currency": null, "max": null, "min": null, "period": "monthly", "term": null}, "salary_visible": false, "title_keywords": ["assistant", "marketing officer"], "responsibilities": ["ideas", "edm", "website", "design", "video shooting", "visual", "editing", "develop artwork", "motion graphic design"], "requirements": {"degrees": ["higher diploma or above"], "majors": ["related disciplines", "graphic design"], "languages": ["english"], "language_level": ["good command"], "hard_skills": ["3d software", "maya", "3ds max", "illustrator", "premiere", "video editing", "after effects", "adobe", "multimedia", "photoshop"], "soft_skills": ["self-motivated", "work under pressure"], "languages_combined": [{"language": "english", "language_level": ["good command"]}]}, "experience_required": {"duration": ["minimum 1 year"], "field": ["editing", "video"]}}, {"job_id": "100003009015568", "location_code": "hk", "company": "\u806f\u8a0a\u79d1\u6280(\u570b\u969b)\u6709\u9650\u516c\u53f8", "job_title": "Digital Marketing Executive", "description": "Job Responsibilities:\u00a0\n\nDevelop creative concept, art direction and mechanic for social media campaigns and digital projects\nResearch and consolidate insight of design works, social games, new mobile experience\nDevelop artwork design / illustration across digital platforms (Facebook, Instagram, WeChat, e-shop)\u00a0\nSupports the creation and post-production of videos from raw footages\nFormatting of presentation decks\nWebpage management and assists with uploading and keeping materials updated using tools\nCo-work with different departments on mall marketing events and campaigns\nWorks with relevant vendors, ensures quotations are within budget and supervises the production of materials such as translations, printing of posters, and photography\nStay up to date on latest creative trends, transmedia applications and competitive business environment\n\nJob Requirements:\n\nMinimum 1-2 years of experience, preferably knowledgeable in UX, UI, design thinking\nRelevant work portfolio is a must\nGraphic design, video filming & editing\nStrong layout and typography skill\nAdobe illustrator, InDesign, Photoshop, Premier Pro (After Effect is preferred but optional)\nHTML is required, CSS would be an added value\nSocial media management experience: LinkedIn, Facebook, Instagram, WeChat \u2026\nDigital analytics (Adobe Analytics)\nAbility to pay attention to detail and grasp project needs and consider practical solutions\nAbility to imbibe good time management and balance work on multiple projects simultaneously\nExperience in digital media / advertising agency / consumer goods is definitely welcome\nImmediately Available would be an advantage\n\nThe information provided will be used for selection purpose only. All information of unsuccessful applicants will be destroyed within six months.", "employment_types": ["Full Time", "Permanent"], "selling_points": ["5-day work, Education, Housing", "Medical Insurance, Performance Bonus, Gratuity", "14+ days Annual+Birthday Leaves, Flexible WorkHour"], "locations": ["Quarry Bay"], "categories": ["Design", "Graphics", "Multi-media", "Web Designer"], "post_time": "2022-01-03T08:51:35Z", "salary": {"currency": null, "max": null, "min": null, "period": "monthly", "term": null}, "salary_visible": false, "title_keywords": ["digital marketing executive"], "responsibilities": ["marketing events", "management", "e-shop", "social media campaigns", "budget", "design", "develop", "formatting", "facebook", "develop artwork"], "requirements": {"degrees": [], "majors": [], "languages": [], "language_level": [], "hard_skills": ["indesign", "html", "adobe illustrator", "wechat", "adobe", "css", "facebook", "after effect", "photoshop"], "soft_skills": ["time management", "attention to detail"], "languages_combined": []}, "experience_required": {"duration": ["minimum 1-2 years"], "field": ["social media", "management", "design", "digital media", "advertising agency"]}}, {"job_id": "100003009021268", "location_code": "hk", "company": "Manulife (International) Limited", "job_title": "Trainee / Business Development Manager", "description": "Responsibilities:\n\nCurate, edit, and schedule outgoing email communications which align with business goals\nUse existing tools to improve email visibility and performance\nPrepare finished art on website and social media platform\nCreate a wide range of graphics and layouts for product illustrations, company logos, and websites with software\nReview final layouts and suggest improvements when necessary\nPerform ad-hoc tasks and projects as assigned\u00a0\u00a0\n\nRequirements:\n\nUniversity degree holder with minimum 2 years of experience in digital marketing\u00a0\nExperience in service/e-commerce industry with a B2C focus is preferable\nFamiliar with online culture and good understanding on engaging with audiences through an integrated approach\nPrevious experience with email templating and scheduling is a MUST\nSensitive to numbers, strong analytical skills & artistic sense\nWell-organized, self-motivated, detail-minded, able to multi-task\nGood command of both spoken and written English and Chinese\nProficiency with required desktop publishing tools, including Photoshop, InDesign Quark, and Illustrator\nFresh graduates are welcome to apply", "employment_types": ["Full Time"], "selling_points": [], "locations": ["Kwun Tong"], "categories": ["Design", "Web Designer", "Hospitality / F & B", "Hospitality / Hotel Services", "Sales, CS & Business Devpt", "Wholesale"], "post_time": "2022-01-05T03:29:14Z", "salary": {"currency": null, "max": null, "min": null, "period": "monthly", "term": null}, "salary_visible": false, "title_keywords": ["business development manager", "trainee"], "responsibilities": ["graphics", "social media", "business goals", "review final layouts", "software", "ad-hoc tasks", "website", "schedule", "suggest improvements"], "requirements": {"degrees": ["university degree"], "majors": ["digital marketing"], "languages": ["english", "chinese"], "language_level": ["good command"], "hard_skills": ["e-commerce", "indesign", "illustrator", "analytical skills", "focus", "photoshop"], "soft_skills": ["detail-minded", "self-motivated", "multi-task", "sensitive to numbers", "well-organized", "analytical skills", "focus"], "languages_combined": [{"language": "english", "language_level": ["good command"]}, {"language": "chinese", "language_level": ["good command"]}]}, "experience_required": {"duration": ["minimum 2 years"], "field": ["digital marketing", "e-commerce"]}}, {"job_id": "100003009006595", "location_code": "hk", "company": "Kiwi Media Limited", "job_title": "Web designer", "description": "Duties and Requirements:\n1.\u00a0\u00a0 \u00a0To maintain and enhance company\u2019s web marketing operations on WORDPRESS platform with ADOBE Photoshop and Illustrator tools.\n2.\u00a0\u00a0 \u00a0To promote company\u2019s updated cloud services and solution (including abss-integrated web services and Microsoft cloud services) offerings to existing and potential customers, including e-channels marketing. i.e. Facebook, eDM, SEO, Google Analytics\u2026.\n3.\u00a0\u00a0 \u00a0To identify potential customers with all necessary business development effort for in-house developed business applications - Point of Sales (POS) and Customer Relationship Management (CRM) solution, on Microsoft Power Platform including Power BI, Power Automate, and Robotic Process Automation (RPA) tools with solution demonstration and presentation.\n4.\u00a0\u00a0 \u00a0To do all pre-sales and marketing tasks including on-site presentation, demo, quotation on integration, migration services and subscriptions, seminar-exhibition events preparation and staffing, etc..\n5.\u00a0\u00a0 \u00a0To work with our technical team for support, testing, and enablement of new cloud features on Microsoft PowerPlatform, SharePoint, Forms, 365 Dynamics Business Central, Teams and Azure cloud platforms.\n6.\u00a0\u00a0 \u00a0Requires candidates to have good I.T. sense, with good proficiency in both English and Chinese communications. At least one full year of related commercial working experience.\n7.\u00a0\u00a0 \u00a0Company provides on-the-job training and promotion opportunities with more job responsibilities. College (including IVE) fresh graduates welcomed.\n8.\u00a0\u00a0 \u00a0Welfare entitlement as caring company (including birthday leave)\nInterested party please send full resume by clicking \"Apply now\"\n", "employment_types": ["Full Time", "Part Time", "Permanent", "Freelance"], "selling_points": ["Web/UX design, online material design", "5-day work, Annual bonus, 14-day AL", "Birthday leave, Medical allowance"], "locations": ["Tsuen Wan Area"], "categories": ["Design", "Graphics", "Multi-media", "Web Designer"], "post_time": "2021-12-29T09:32:57Z", "salary": {"currency": null, "max": null, "min": null, "period": "monthly", "term": null}, "salary_visible": false, "title_keywords": ["designer"], "responsibilities": ["management", "seo", "power bi", "edm", "operations", "quotation", "teams", "testing", "maintain", "facebook", "migration"], "requirements": {"degrees": [], "majors": [], "languages": ["english", "chinese"], "language_level": ["proficiency", "good"], "hard_skills": ["google analytics", "bi", "seo", "azure", "web", "pos", "adobe photoshop", "illustrator", "rpa", "wordpress", "integration", "facebook", "web services"], "soft_skills": ["presentation"], "languages_combined": [{"language": "english", "language_level": ["proficiency", "good"]}, {"language": "chinese", "language_level": ["proficiency", "good"]}]}, "experience_required": {"duration": [], "field": ["related", "commercial"]}}, {"job_id": "100003009006642", "location_code": "hk", "company": "Bond West Consultants", "job_title": "UI / UX Designer (5 days work, in-house) 25K", "description": "Trainee / Business Development Manager (Income $30,000Up + High Bonus & Incentives)\nWe are now recruiting a\u00a0Trainee / Business Development Manager with high calibre and intelligence to join this fast-growing industry. \u00a0\nSuccessful candidate will be offered a 6 months fast track promotion which including attractive packages, comprehensive on-the-job training and all professional financial knowledge and skills.\nThis is an entry point that leads you to a management position as soon as 6 months!\u00a0\u00a0\nWe Offer :\u00a0\n\u2022 Fast-track promotion program to management level within 6 months\u00a0\n\u2022 5 days work, 20 days annual leave and bank holidays\u00a0\n\u2022 Medical & life insurance, provident fund and low interest mortgage Insurance benefit\u00a0\n\u2022 Professional training program (Pre-job and on-job training for promotion to management level) excellent career path to management with the market leader\u00a0\n\u2022 Monthly income $30,000 up + high monthly and annual performance bonus\u00a0\u00a0\u00a0\n\u2022 Management overrides, overseas trips and incentives\u00a0\u00a0\n\u2022 Client Base Provided\nRequirements :\n\u2022 Degree holder preferred / F.5 or above with management experience\u00a0\n\u2022 3 Years or more working experience, fresh graduate or new in industry will also be considered\n\u2022 Sales driven, self-motivated and customer oriented\n\u2022 Finance related experience is not necessary, but solid management skill is an absolute advantage\u00a0\n\u2022 Fluent in Cantonese\u00a0\u00a0\n\u2022 Strong desire for a successful career\u00a0\n\u2022 Valid HKID holder for working in Hong Kong\nJob Descriptions\u00a0:\u00a0\n\u2022 Deliver professional financial planning to individual clients on life and medical protection, risk management, savings planning, investment planning, retirement planning and MPF etc.\u00a0\n\u2022 Provide professional service to corporate clients on MPF, group medical plan and business insurance\u00a0\n\u2022 Maintain ongoing client relationship and develop an affluent client base\u00a0\n\u2022 Provide team management and attempt planning strategies for building team\n\u2022 Welcome candidates changing from Telecom sales, Aviation (airline industry), food & beverages industry to join\nInterested Candidate please send your detailed CV to us or contact Ms Chiu at mobile: 9735-6840.\n\n\n*Only shortlisted candidates will be notified.\u00a0 All data collected will be used for recruitment purposes only and will be used strictly confidential.", "employment_types": ["Full Time", "Permanent"], "selling_points": ["Attractive Package", "Inhouse", "work life balance"], "locations": ["Yau Tsim Mong Area"], "categories": ["Media & Advertising", "Creative / Design", "Design", "Web Designer", "Others"], "post_time": "2021-12-29T09:41:21Z", "salary": {"currency": null, "max": null, "min": null, "period": "monthly", "term": null}, "salary_visible": false, "title_keywords": ["ux designer"], "responsibilities": [], "requirements": {"degrees": [], "majors": [], "languages": [], "language_level": [], "hard_skills": [], "soft_skills": [], "languages_combined": []}, "experience_required": {"duration": [], "field": []}}, {"job_id": "100003009011319", "location_code": "hk", "company": "PCCW Solutions", "job_title": "UI/Web Designer", "description": "Responsibilities:\n\nDesign website layout\nCreate, implement & optimise media materials for website\nFront-end program coding (HTML/CSS/JS)\nPhoto/Video shooting and editing\nDemonstrate excellent creativity across all media design\n\nRequirements:\n\nDiploma holder or above in either Graphic design or Front-end programming related disciplines\nWebsite or UX design\u00a0experience\nHTML,\u00a0CSS, Javascript\u00a0knowledge\nFamiliar with AI, PS, AE, ID and Premiere\n1 year relevant working experience with strong sense of trends and creativity\nSelf-motivated, independent & able to work under pressure and meeting deadline\nPlease provide your portfolio with CV\n\nBenefits:\n\n5-day working\n14 days Annual leave, Birthday/Special leave\nAnnual bonus\nMedical, dental and hospitalization coverage\nFully stocked pantry and regular social activities\u00a0", "employment_types": ["Full Time"], "selling_points": ["UI/Web Designer", "3 years&#x2019; experience as a UI/UX designer", "Candidate with less experience will be considered as Junior UI/Web designer"], "locations": ["Wan Chai"], "categories": ["Design", "Industrial / Product", "Web Designer", "Information Technology (IT)", "Others"], "post_time": "2021-12-31T06:56:30Z", "salary": {"currency": null, "max": null, "min": null, "period": "monthly", "term": null}, "salary_visible": false, "title_keywords": ["designer"], "responsibilities": ["website", "coding", "design", "video shooting", "editing"], "requirements": {"degrees": ["diploma holder"], "majors": ["related disciplines", "graphic design"], "languages": [], "language_level": [], "hard_skills": ["ai", "id", "premiere", "html", "javascript", "programming", "css"], "soft_skills": ["self-motivated", "independent", "work under pressure"], "languages_combined": []}, "experience_required": {"duration": ["1 year"], "field": ["relevant working experience", "design"]}}, {"job_id": "100003009017479", "location_code": "hk", "company": "VTech Corporate Services Limited", "job_title": "Web Marketing Analyst (VCO210/J02)", "description": "(Ref Number: jobs@1229a_nc)\n\nOur client, a conglomerate is now looking for a high caliber for the following position:\n\nUI / UX Designer\n\nResponsibilities:\n\n\nResponsible for user interface design of system, mobile apps and websites\nBanner, image retouch and other graphics design\n\u00a0Requirements:\n\nDiploma holder in Web / App / Multimedia / Graphics design or related discipline\nProficiency in graphics & web design tools such as Adobe Photoshop, Illustrator, XD or Sketch\nKnowledge of design, prototyping tools and usability best practices in wire frames and prototypes\nStrong sense on responsive design, UI/UX and technology trends\nKnowledge of iOS & Android app official UI guideline\nAt least 3 years\u2019 solid experience in Web/App/Multimedia design\nKnowledge of JavaScript, HTML5, CSS3 is a plus\nResponsible, detail-minded, have good interpersonal and communication skills\nCandidates with less experience will be considered as UI/UX Designer\n\nPlease send in your full resume with last drawn, expected salary and availability\u00a0to Bond West Application Email Address\u00a0\"Click Here\"\u00a0or via\u00a0\"APPLY\" button.\n\nFor any inquiry, please feel free to contact Ms. Natalie Chan\u00a0at 2957 8166.\n(Data collected is only for recruitment purpose)", "employment_types": ["Full Time", "Permanent"], "selling_points": ["Degree in Marketing or related disciplines", "Passionate in digital communication technologies", "5 day work, flexible working hour, double pay"], "locations": ["Tai Po Area"], "categories": ["Design", "Web Designer", "Information Technology (IT)", "IT - Webmaster / SEO", "Marketing / Public Relations", "Digital Marketing"], "post_time": "2022-01-04T00:41:21Z", "salary": {"currency": null, "max": null, "min": null, "period": "monthly", "term": null}, "salary_visible": false, "title_keywords": ["analyst"], "responsibilities": ["graphics", "user interface", "design"], "requirements": {"degrees": ["diploma holder"], "majors": ["design"], "languages": [], "language_level": [], "hard_skills": ["graphics", "web design", "plus", "web", "adobe photoshop", "illustrator", "javascript", "multimedia", "android"], "soft_skills": ["detail-minded", "communication skills", "responsible", "responsive", "interpersonal"], "languages_combined": []}, "experience_required": {"duration": ["at least 3 years"], "field": ["designer", "design"]}}, {"job_id": "100003009002611", "location_code": "hk", "company": "Lorence & Company Limited", "job_title": "Web and Graphic Designer", "description": "Summary\n\nThe successful candidate will be part of the UI/UX team and participate in a Digital Transformation Project in Hong Kong \u2013 Responsible for collecting, researching and evaluating user requirements, designing graphic elements, and to deliver an outstanding user experience.\n\nJob Duties\n\nHe / She will be responsible for creating the UI and optimal experience for users in different media and platforms performing detailed requirements analysis and documenting processes with the following scope of duties:\n\nCollaborate with product management and development team to define and implement innovative solutions for the product direction, visuals and experience\nCreate personas through user research and data\nUnderstand product specifications and user psychology\nDefine the right interaction model and evaluate its success\nFind creative ways to solve UX problems (e.g. usability, findability)\nCommunicate design ideas and prototypes to the team and developers\nDevelop wireframes and prototypes around customer needs\nConduct concept and usability testing and gather feedback\nAble to manage project(s) from beginning to end and meet deadlines\n\nThe Person\n\nA minimum of 3 years\u2019 experience as a UI/UX designer with strong digital platform knowledge\nAbility to work independently but also a great team player\nEffective verbal and written communication in English and Chinese\nProven experience as a UX Designer, UI Designer or similar role\nKnowledge on coding and grid system, e.g. html, CSS, react-native, bootstrap\nStrong portfolio of design projects\nProficient in UI/UX design software (e.g. Figma, Invision, Marvel, Adobe XD ,Photoshop, Illustrator, MS office)\nUp-to-date with the latest UI trends, techniques, and technologies\nAbility to present your designs and sell your solutions to various stakeholders\nAbility to solve problems creatively and effectively\nExperienced with Agile / iterative project management methodologies- Analytical mind with a business acumen\nCandidate with less experience will be considered as Junior UI/Web designer", "employment_types": ["Full Time", "Permanent"], "selling_points": ["Minimum 1 year relevant experience", "Five work day week", "Immediately available is preferred"], "locations": ["Kwun Tong"], "categories": ["Design", "Graphics", "Web Designer"], "post_time": "2021-12-28T06:32:45Z", "salary": {"currency": null, "max": null, "min": null, "period": "monthly", "term": null}, "salary_visible": false, "title_keywords": ["graphic designer"], "responsibilities": ["collaborate with", "management", "ideas", "data", "analysis", "design", "develop", "evaluate", "testing", "specifications", "ui"], "requirements": {"degrees": [], "majors": [], "languages": ["english", "chinese"], "language_level": [], "hard_skills": ["agile", "web", "react", "adobe xd", "illustrator", "html", "acumen", "project management", "css", "ms office", "photoshop"], "soft_skills": ["work independently", "agile", "communication", "solve problems", "project management", "analytical mind", "business acumen", "team player"], "languages_combined": [{"language": "english", "language_level": []}, {"language": "chinese", "language_level": []}]}, "experience_required": {"duration": ["minimum of 3 years"], "field": ["digital", "designer"]}}, {"job_id": "100003009006656", "location_code": "hk", "company": "Pricerite Home Ltd", "job_title": "Part Time Graphic Designer", "description": "Responsibilities:\n\nDesign shop front display items, including but not limited to poster, banner, POP, and print adv.\nDesign and collateral in accordance with brand guidelines\nContribute to concept development, design and production of online media marketing, e.g. GDN, eDM, banner advertisement, and video graphics\nDesign website and web page layout/user interface for online sales platforms to meet commercial or promotion if required\nAssist in ad hoc duties as assigned\nGood team player, responsible, work closely with team member from concept to final production\nAble to meet tight deadline and multi-tasking\n\nRequirements:\n\nHigher Diploma or above in Graphic / Web/ Multimedia Design or related discipline\n1 year or above relevant experience and passion in graphic design fields\nStrong art sense, good typography, branding and layout\nCreative, proactive, positive attitude and strong attention to detail\nProficiency in Illustrator, Photoshop, Indesign, Ms Powerpoint, Ms Excel and MS office\nKnowledge in video editing, motion graphics and HTML 5 will be an advantage\nGood command of both written & spoken English and Chinese\nFresh graduates are also welcome\nAble to work at least 2-3 days per week\n\n\nWe offer attractive remuneration package including\u00a0comprehensive medical insurance scheme, birthday leave, full pay paternity leave, discretionary bonus, education subsidies & leave and job-related training etc.\nPlease apply in confidence with cover letter and full resume, quoting reference to the\u00a0Manager, Human Resources, Pricerite Home Limited,\u00a028/F, Manhattan Place, 23 Wang Tai Road, Kowloon Bay, Hong Kong\u00a0or\u00a0press below \"Apply Now\".\nThe information provided will be used for selection purpose only. All information of unsuccessful applicants will be destroyed within six months.", "employment_types": ["Part Time"], "selling_points": ["Graphic Designer", "Part-time", "Hourly Rate"], "locations": ["Kowloon Bay"], "categories": ["Design", "Graphics", "Multi-media", "Web Designer"], "post_time": "2021-12-29T09:47:24Z", "salary": {"currency": null, "max": null, "min": null, "period": "hourly", "term": null}, "salary_visible": false, "title_keywords": ["graphic designer"], "responsibilities": ["graphics", "ad hoc duties", "edm", "website", "design", "user interface", "brand guidelines"], "requirements": {"degrees": ["higher diploma or above"], "majors": ["multimedia design"], "languages": ["english", "chinese"], "language_level": ["good command"], "hard_skills": ["graphics", "web", "indesign", "illustrator", "html", "scheme", "video editing", "ms excel", "multimedia", "ms powerpoint", "ms office", "photoshop"], "soft_skills": ["proactive", "confidence", "passion in", "positive attitude", "comprehensive", "attention to detail", "creative"], "languages_combined": [{"language": "english", "language_level": ["good command"]}, {"language": "chinese", "language_level": ["good command"]}]}, "experience_required": {"duration": ["1 year"], "field": ["graphic design", "relevant experience"]}}, {"job_id": "100003009004587", "location_code": "hk", "company": "Yakoo Technology Limited", "job_title": "Digital Designer", "description": "Responsibilities:\n\nPrepare marketing materials, and maintain website content, electronic direct mailers, social media platforms and e-commerce\nIdentify improvement opportunities in SEM & SEO growth and efficiency\nWork closely with IT and global marketing teams to optimize website content, architecture and layouts\nLead or assist in any ad hoc projects as assigned\n\nRequirements:\n\nDegree or above in Marketing or related disciplines\nMinimum 4 years of experience in SEM, SEO and website project\nExperience in digital marketing and emerging digital technology, social trends and insights\nPassion for digital communication techniques and technologies\nStrong knowledge in Google AdWords and Google Analytics\nKnowledge in graphic design and website development would be an asset\nExcellent command of written & spoken English & Chinese with strong interpersonal skill\nCandidates with less experiences will be considered as Web Marketing Developer\n\nWe offer attractive remuneration package including 5-day work, flexible work hours and other benefits to the right candidate. Interested parties please forward full resume with expected salary and quote job reference number to\n\n\nVTech Group of Companies,\nThe Human Resources and Administration Department,\n23/F, Tai Ping Industrial Centre, Block 1,\n57 Ting Kok Road, Tai Po, Hong Kong\n\nOR\u00a0apply on-line directly through our corporate website at www.vtech.com/en/careers/.\n\nFor more information about\u00a0us, please visit our website at\u00a0www.vtech.com.\n\nAll applications will be used for the purpose of recruitment only. Applicants not invited for interview within 4 weeks may consider their applications unsuccessful. We will retain the applications for a maximum period of six months and may refer them to suitable openings within our Group.", "employment_types": ["Full Time"], "selling_points": [], "locations": ["Shatin Area"], "categories": ["Design", "Graphics", "Multi-media", "Web Designer"], "post_time": "2021-12-29T02:43:56Z", "salary": {"currency": null, "max": null, "min": null, "period": "monthly", "term": null}, "salary_visible": false, "title_keywords": ["digital designer"], "responsibilities": ["seo", "social media platforms", "teams", "website", "maintain", "ad hoc projects", "sem", "architecture", "prepare marketing materials"], "requirements": {"degrees": ["degree or above"], "majors": ["related disciplines", "marketing"], "languages": ["english", "chinese"], "language_level": ["excellent"], "hard_skills": ["google analytics", "seo", "web", "adwords", "sem"], "soft_skills": ["communication", "interpersonal skill", "passion for"], "languages_combined": [{"language": "english", "language_level": ["excellent"]}, {"language": "chinese", "language_level": ["excellent"]}]}, "experience_required": {"duration": ["minimum 4 years"], "field": ["developer", "digital", "marketing", "digital marketing"]}}, {"job_id": "100003009004483", "location_code": "hk", "company": "Don Nelson Recruitment Limited", "job_title": "Experienced UI/UX Designer (MNC Professional Brand)", "description": "The role of the Digital Design Manager is to create engaging & experiential content & designs throughout the digital customer journey that reflects our DFS brand positioning as \u201cThe World Traveler\u2019s Luxury Retailer. Since 1960.\u201d\n\nResponsibilities\u00a0\u00a0\n\nLead creative strategies, concepts, and content that meet our business objectives.\nAct as the centralized subject-matter-expert on all digital content requests within the organization.\nMaintain an elevated and consistent visual vocabulary that reflects our brand\u2019s luxury positioning and luxurious tone-of-voice throughout an omni-channel customer journey.\nIncorporate & infuse market trends & insight into our concepts \u2014 integrating technology with art & commerce to ensure a balance of creativity & functionality with editorial & commercial value.\nCreate global & local customer-facing content (both static & dynamic) across our channels including personalization & segmentation opportunities, while ensuring O2O connectivity for offline touchpoints:\nOnline Channels & Touchpoints \u2014\u00a0Website, EDM, E-Commerce, Social Media (Facebook, Instagram), Media Buys, Online Catalogs & Gift Guides, etc.\nOffline Channels & Touchpoints \u2014 In-Store Digital LED Screens, Interactive Applications, OOH Media, etc.\nContent Types \u2014 DFS Masterbrand Content, Seasonal Campaigns, Branded Content, Product & Category Stories, Editorial Content (Brand Ambassador Editorial & Interviews, Travel Guides), Retail Experiences, Events & Promotions, Loyalty Programs & Services, Artful & Experiential Content, etc.\nContent planning for our DFS calendar \u2014 while collaborating closely with key stakeholders and cross-functional teams across marketing, merchandising, and operations from corporate to division, to ensure our content is envisioned & implemented successfully, balancing their priorities.\nManage end-to-end production lifecycle of creative content and assets from concept to execution (ideation, pre-production, photo & video shoots, post-production, design & adaptations, etc.)\nSource, review, evaluate, and manage external agency partners and talent, while continuing to build relationships with vendors & contributors, including managing budgets.\nAbility to lead internal and external stakeholders & partners to achieve company objectives & goals.\nAbility to mentor our designers to help them gain further expertise within digital design.\nConstant refining of technical skills per industry best practices & standards.\n\nRequirements\u00a0\u00a0\n\nBachelor\u2019s university degree or equivalent\nAt least 5-7 years of experience\nExpertise in Adobe XD, Adobe Creative Suite, After Effects, Final Cut Pro, PowerPoint\nExperience in managing designers & external vendors\nProven track-record with experience in an advertising agency or luxury retail environment\nExcellent written & spoken English communication skills\nFluency in Simplified & Traditional Chinese (preferred)\nEnthusiastic, entrepreneurial, highly creative & curious\nConceptual thinker with ability to evaluate & judge creative copy writing for luxury retail\nElevated visual aesthetic with a strong customer-centric point-of-view\nAbility to conceptualize & create content holistically across online & offline channels\nKnowledge of UI/UX design, wire framing, GUI (screen layout & composition) style guide implementation \u2014\u00a0with the ability to create beautiful, dynamic & intuitive user interfaces\nSolid understanding of current web platform, interaction design, and usability principles\nStrong portfolio demonstrating ability in concepting & designing elevated experiences for luxury retail\nProficiency in Western & China digital & social media trends (WeChat, XHS, etc.)\nAbility to prioritize & manage multiple projects within a fast-paced, deadline-driven environment\nAbility to collaborate well within a global & multi-cultural team", "employment_types": ["Full Time", "Permanent"], "selling_points": ["Permanent role with attractive package", "Your design will be seen in the regional level", "Good teamwork atmosphere and environment"], "locations": ["Kwun Tong Area"], "categories": ["Design", "Multi-media", "Web Designer", "Information Technology (IT)", "UI/UX Designer"], "post_time": "2021-12-29T02:34:21Z", "salary": {"currency": null, "max": null, "min": null, "period": "monthly", "term": null}, "salary_visible": false, "title_keywords": ["ux designer"], "responsibilities": ["social media", "online channels", "pre-production", "budgets", "creative content", "edm", "operations", "review", "merchandising", "website", "design", "evaluate", "maintain", "visual", "facebook", "cross-functional teams", "planning"], "requirements": {"degrees": ["university degree", "bachelor"], "majors": [], "languages": ["english", "chinese"], "language_level": ["fluency", "excellent"], "hard_skills": ["final cut pro", "web", "adobe xd", "powerpoint", "wechat", "after effects", "dynamic", "adobe creative suite"], "soft_skills": ["communication skills", "prioritize", "dynamic", "enthusiastic", "creative", "driven"], "languages_combined": [{"language": "english", "language_level": ["excellent"]}, {"language": "chinese", "language_level": ["fluency"]}]}, "experience_required": {"duration": ["at least 5-7 years"], "field": ["luxury retail", "advertising agency"]}}, {"job_id": "100003009008956", "location_code": "hk", "company": "DFS Hong Kong Limited", "job_title": "Digital Design Manager , Contract - DFS91121288", "description": "Responsibilities:\n\nPerform graphic design for marketing campaigns and promotions\nResponsible for branding and marketing collaterals, such as leaflet, poster, catalog and etc.\nDevelop product display materials and exhibition booth design\nMaintain and update company web page\nHandle adhoc design projects assigned by supervisor\u00a0\n\nRequirements:\n\nDiploma or Certificate in Graphic Design or related discipline\nMinimum 2 years solid experience in graphic design\nProficiency in Photoshop, Illustrator\nKnowledge in web design and photography will be advantage\nExperience in Food Industry will be advantage\nAble to meet tight deadlines and multi-task\nSelf-motivated, creative and able to work independently\nImmediate availability is highly preferred\u00a0\n\nWe offer 5 day work with attractive remuneration packages including double pay and medical group insurance to the right candidate", "employment_types": ["Full Time", "Contract"], "selling_points": ["Work Life Balance, Five-day Work Week", "World's Leading Luxury Travel Retailer", "International & Dynamic Working Environment"], "locations": ["Quarry Bay"], "categories": ["Design", "Graphics", "Multi-media", "Web Designer"], "post_time": "2021-12-30T09:42:08Z", "salary": {"currency": null, "max": null, "min": null, "period": "monthly", "term": null}, "salary_visible": false, "title_keywords": ["design manager"], "responsibilities": ["graphic design", "marketing collaterals", "leaflet", "exhibition booth", "design", "develop", "maintain", "marketing campaigns"], "requirements": {"degrees": ["certificate", "diploma"], "majors": ["graphic design"], "languages": [], "language_level": [], "hard_skills": ["web design", "illustrator", "photoshop"], "soft_skills": ["meet tight deadlines", "work independently", "multi-task", "self-motivated", "creative"], "languages_combined": []}, "experience_required": {"duration": ["minimum 2 years"], "field": ["graphic design", "food industry"]}}, {"job_id": "100003009006335", "location_code": "hk", "company": "Ping Shan Foods Company Limited", "job_title": "Graphic Designer", "description": "Casetify is looking for a Senior UXUI designer experienced in information architecture, interaction, and user testing to join our team. You will collaborate with the E-commerce team to design and build next generation Web/mobile applications. The right candidates will be excellent communicators, comfortable in a high-velocity startup, and passionate about creating products that transform people\u2019s lifestyle.\nResponsibilities:\nPrepare UX/UI design and materials including wire framing, mockup and rapid prototyping for various interfaces, including websites, mobile devices and apps for ecommerce site;\nAnalyze current user journey to understand motivation, expose pain points, issues and improvement opportunities;\nConduct user research, A/B testing, and propose solutions to optimize customer experience;\nCommunicate concepts and work collaboratively with project team / Tech team in order to develop the most efficient design schemas;\nSit with developers to do pixel-perfect reviews of frontend products before they are pushed in production;\nConsume our Design System library and contribute to its evolution.\nRequirements:\n\n\nBachelor Degree in Creative Media / Interactive Design / Web Design / Web Development;\n5+ years of experience building transactional website;\nSpecific experience in a fast growing ecommerce company;\nAbility to solve problems of complexity through smart design;\nBeing data-driven, and be able to back up your assertions with data, with proficiency in analytic tools - Hotjar, Google Analytics, Optimizely etc;\nA user-first attitude and ensure we consistently deliver a user-centric culture;\nStrong understanding of web grids and browser limitations;\nFamiliarity with usability testing, A/B testing methods;\nProficiency with Photoshop, Adobe XD, Webflow, HTML, CSS, PHP;\nBouns: Experience with Shopify site designs / SDK.\nPlease include 2 URLs of your Open Source, personal projects into your resume.\n\n", "employment_types": ["Full Time", "Permanent"], "selling_points": ["Degree in Graphic Design / Communication Design", "Experience in Food Industry will be advantage", "Dedicated, Good work ethics, team work"], "locations": ["Sheung Wan"], "categories": ["Design", "Graphics", "Web Designer", "Marketing / Public Relations", "Marketing - General / Support"], "post_time": "2021-12-29T08:12:31Z", "salary": {"currency": null, "max": null, "min": null, "period": "monthly", "term": null}, "salary_visible": false, "title_keywords": ["graphic designer"], "responsibilities": ["design", "develop", "testing", "mobile devices", "ui"], "requirements": {"degrees": ["degree", "bachelor"], "majors": ["creative media", "web design", "design"], "languages": [], "language_level": [], "hard_skills": ["web design", "web development", "google analytics", "web", "php", "adobe xd", "shopify", "html", "css", "photoshop"], "soft_skills": ["solve problems", "creative", "driven"], "languages_combined": []}, "experience_required": {"duration": ["5+ years"], "field": ["ecommerce"]}}, {"job_id": "100003009004334", "location_code": "hk", "company": "New Beauty Group Limited", "job_title": "Graphic Designer", "description": "Responsibilities:\n- Graphic design for digital projects (website, mobile app, social media)\n- Create wireframe, user flow, HiFi design\n- Work closely with programmers and project team\n- Any other ad hoc duties as assigned\n\nRequirements:\n- Diploma or above in Graphic/Multimedia design or related disciplines\n- Experience in\u00a0UX design of digital products/services\n- Knowledge in website or mobile application development is a plus\n- Proficiency in Sketch, Adobe XD, InVision, etc.\n- Innovative, self-motivated, well organised, responsible, able to handle projects with tight deadline and good communication skill\n- Fresh graduates will be considered\n- Fluent in Cantonese\n\nBenefits:\n- Able to participate in the whole project development process\n- Gain experience from a variety of project types from different industries (NGO, FMCG)\n- 5 day work week\n- Performance bonus\n- Working location: Tsuen Wan West", "employment_types": ["Full Time"], "selling_points": ["Convenient working location: MongKok", "Adobe Photoshop, Illustrator, Indesign", "5-day work week"], "locations": ["Mong Kok"], "categories": ["Design", "Graphics", "Multi-media", "Web Designer"], "post_time": "2021-12-29T02:01:48Z", "salary": {"currency": null, "max": null, "min": null, "period": "monthly", "term": null}, "salary_visible": false, "title_keywords": ["graphic designer"], "responsibilities": ["ad hoc duties", "social media", "mobile app", "graphic design", "website", "design"], "requirements": {"degrees": ["diploma or above"], "majors": ["multimedia design", "related disciplines"], "languages": ["cantonese"], "language_level": ["fluent"], "hard_skills": ["adobe xd", "mobile", "plus", "multimedia"], "soft_skills": ["self-motivated", "responsible", "communication skill", "organised", "innovative"], "languages_combined": [{"language": "cantonese", "language_level": ["fluent"]}]}, "experience_required": {"duration": [], "field": ["digital", "design"]}}, {"job_id": "100003009001846", "location_code": "hk", "company": "Share Innovation Limited", "job_title": "UI/UX designer", "description": "Our client is an Europe client with solid global brand name. As the new product is planning to launch, they are looking for few experienced UI/UX Designers to join the team.\n\nResponsibilities\n\nResponsible for the UX/UI design output\nUnderstand the global branding philosophy and user experience and behavior\nResearch and evaluate the new and innovative technologies\nCreate the UX/UI for digital application with Adobe xD\nWork closely with the project team and our clients to optimize the workflow\nCreaton of UI concepts, prototypes, user interfaces and documentation of UI guidelines\nCollaborate with the local teams and HQ if required\nRequirements\u00a0\n\nBachelor degree in digital design or any relevant discipline\u00a0\nMinimum 3 years of hands on UX/UI design experience and work with Agile development team\nHave proven record on driving the product through concept, wire framing and visual phases\nHave practical experience in working on responsive web design projects and passionate about digital trends\u00a0 and website technologies with cross-device applications knowledge\u00a0\nExperience in using the design tools like Sketch, InVision, Zepplin, Adobe Photoshop, Adobe xD etc.\u00a0\nHave programming experience in C/C#,Java, JavaScript, HTML and CSS is an advantage\nDetail-minded to handle the design process and UX/UI design including usability evaluation, user cases, user scenarios, user journeys etc.\nStrong presentation skills is needed to present the ideas with clear concepts\nCreative, innovative, logical thinking, problem solving skills, team player with good communication skills\nExcellent language communication in both English and Cantonese\nPersonal data provided by job applicants will be used strictly in accordance with the employer's personal data policies and for recruitment purposes only.", "employment_types": ["Full Time", "Permanent"], "selling_points": ["designer, ui designer, ux designer", "uiux, app design", "app developer, website developer"], "locations": ["Tsuen Wan Area"], "categories": ["Design", "Web Designer", "Information Technology (IT)", "UI/UX Designer"], "post_time": "2021-12-28T03:09:00Z", "salary": {"currency": null, "max": null, "min": null, "period": "monthly", "term": null}, "salary_visible": false, "title_keywords": ["ux designer"], "responsibilities": ["collaborate with", "guidelines", "teams", "user experience", "design", "evaluate", "documentation", "ui"], "requirements": {"degrees": ["degree", "bachelor"], "majors": ["design"], "languages": ["cantonese", "english"], "language_level": ["excellent"], "hard_skills": ["web design", "agile", "adobe xd", "adobe photoshop", "html", "c", "javascript", "programming", "css", "problem solving skills"], "soft_skills": ["detail-minded", "communication skills", "agile", "innovative", "clear", "communication", "presentation skills", "hands on", "team player", "problem solving skills", "creative", "responsive", "passionate about"], "languages_combined": [{"language": "cantonese", "language_level": ["excellent"]}, {"language": "english", "language_level": ["excellent"]}]}, "experience_required": {"duration": ["minimum 3 years"], "field": ["development", "design", "programming", "digital", "team"]}}, {"job_id": "100003009001357", "location_code": "hk", "company": "Adhoc Fun Limited", "job_title": "Graphic Designer (Internship)", "description": "Perfect Health is a leading Medical group with over 50 treatment centers around the world. We strive for perfection with passion. Our team are filled with young, ambitious and driven professionals. We are now seeking for a Graphic Designer to join our Marketing Team.\n\nResponsibilities:\n\nProvide insightful ideas and produce creative work\nDevelop creative graphics for products, photos and other necessary materials for social media advertising\nCreate high-impact presentations with compelling visual\u00a0to grow brand awareness\nDevelop the creative rationales for each visual idea and its intended messages\n\nRequirements:\n\nDiploma or above in Design or related discipline\nProficient in Adobe Photoshop ,Illustrator\u00a0\nMin 2 years hands-on experience in commercial design field, experience in Beauty industry will be an advantage\nAble to handle multiple projects independently and willing to contribute beyond basic responsibilities\nAn outstanding portfolio demonstrating strong conceptual work with excellent execution of ideas; portfolio with feminine as major customer group will be an advantage\u00a0", "employment_types": ["Part Time", "Internship", "Freelance"], "selling_points": ["Interesting illustration work for the characters", "Currently enrolled in a bachelor\u2019s degree", "Student Internship, Freelance, work form home"], "locations": ["Kwun Tong"], "categories": ["Design", "Graphics", "Multi-media", "Web Designer"], "post_time": "2021-12-28T02:20:32Z", "salary": {"currency": null, "max": null, "min": null, "period": "hourly", "term": null}, "salary_visible": false, "title_keywords": ["graphic designer", "internship"], "responsibilities": ["graphics", "social media", "advertising", "ideas", "presentations", "develop", "visual"], "requirements": {"degrees": ["diploma or above"], "majors": ["design"], "languages": [], "language_level": [], "hard_skills": ["adobe photoshop", "basic", "illustrator"], "soft_skills": ["hands-on", "independently"], "languages_combined": []}, "experience_required": {"duration": ["min 2 years"], "field": ["commercial", "beauty industry", "design"]}}, {"job_id": "100003009004193", "location_code": "hk", "company": "C-Mer Dennis Lam & Partners Eye Center", "job_title": "Graphic Designer", "description": "About the Role\n\nThe UX & UI Designer \u2013 Digital Product will be passionate about digital design with an educated design sense, knowledge in responsive web design and mobile apps, creative flair, keen interest and ability to deliver effective digital design solutions that are aligned with the company and brand creative vision. As an UX & UI Designer, you are expected to have passion for conceptualising to create wireframes, mockups, prototyping, visual design and an in-depth understanding of UI/UX tools, trends, touch-points & platforms.\nYou will also execute creative projects and ensure all web content is accurately published and up-to-date according to the digital brand guideline.\nThis role requires you to be a creative solutions provider focused on the overall design systems and brand guidelines creation, and apply them across all digital touch points on all the projects and initiatives.\n\nKey responsibilities:\nCreate wireframes, user interface from design ideas\nParticipate in the whole design process (especially the prototype stage), from concept to launch\nPerform UAT occasionally to ensure website content is published accurately, and web applications are working as expected.\nProvide support for the development and maintenance of web content, experience on using ecommerce platform like Shopify will be an advantage.\nCollaborate with digital team to get full technical support\nAssist Senior Designers to help build company digital branding style guides\nCompleting tasks assigned by the Project Manager in an efficient and timely manner\nCare about the little things and have great attention to detail\nBe comfortable experimenting, accepting feedback and iterating on ideas\nEducation & Experience\nHigher diploma or Bachelor\u2019s degree above\n2 years\u2019 experience in digital design\nEnjoy working in a dynamic, fast-paced environment\nDetail-oriented, with a passion about digital design\nExcellent visual design skills with sensitivity to user-system interaction\nExperience in working on the whole design process\nExperiences in using Adobe Creative Suite, Figma or Sketch \u00a0(or other prototype tools) will be highly preferable\nPrevious Experience in ecommerce platform (ie: Shopify & Magento) will be highly preferable\nHighly organised with experience in project management tools is a bonus\nExcellent interpersonal, communication and presentation skills\nFluent in English and Cantonese/Mandarin\nWe offer 5-day work, double pay, medical benefit, free company coaches and bright career prospect to the right candidate. Interested parties please send your application letter with detailed resume stating current salary, expected salary and date of available to hr @ kef.com .\nWe are an equal opportunities employer. Personal data collected will be treated as strictly confidential and used for recruitment purpose only.", "employment_types": ["Full Time"], "selling_points": ["Young and dynamic marketing team", "Work location: Central", "5 days work week"], "locations": ["Central"], "categories": ["Media & Advertising", "Creative / Design", "Design", "Graphics", "Web Designer"], "post_time": "2021-12-29T01:40:15Z", "salary": {"currency": null, "max": null, "min": null, "period": "monthly", "term": null}, "salary_visible": false, "title_keywords": ["graphic designer"], "responsibilities": ["collaborate with", "provide support", "ideas", "uat", "maintenance", "design solutions", "technical support", "systems", "website", "design", "communication", "user interface", "project management", "brand guidelines", "visual", "ui"], "requirements": {"degrees": ["diploma", "degree", "bachelor"], "majors": [], "languages": ["cantonese", "english", "mandarin"], "language_level": ["fluent"], "hard_skills": ["web design", "web applications", "web", "maintenance", "shopify", "mobile", "visual design", "dynamic", "project management", "adobe creative suite"], "soft_skills": ["focused", "fast-paced environment", "enjoy working", "sensitivity", "detail-oriented", "communication", "passionate about", "efficient", "keen", "creative", "interpersonal", "dynamic", "attention to detail", "responsive", "passion for", "timely", "project management", "presentation skills", "organised"], "languages_combined": [{"language": "cantonese", "language_level": ["fluent"]}, {"language": "english", "language_level": ["fluent"]}, {"language": "mandarin", "language_level": ["fluent"]}]}, "experience_required": {"duration": ["2 years"], "field": ["ecommerce", "maintenance", "development", "design", "education", "project management", "digital"]}}, {"job_id": "100003009003034", "location_code": "hk", "company": "GP Acoustics Group", "job_title": "UX & UI Designer", "description": "Responsibilities:\n\nDesign user interface for Portal, POS, Customer Frontends (Mobile Apps, Tablet, PC);\nDesign for UI and UX;\nCollaborate with our development team to bring your designs to live;\nCommunicate with clients to gather requirements and present design concept.\n\nRequirements:\n\nDegree Holder in digital design or related disciplines;\nMinimum 1 year of UI /UX design experience (especially on web and Mobile App), or equivalent experience;\nExperience designing intuitive user experiences based on requirements;\nProficiency in graphic design - familiar with Photoshop or AI;\nProficiency in prototyping tools like Sketch, Figma;\nPassionate to provide innovative, creative and reliable digital business solutions (web, app, system) to our clients;\nGood team player with strong growth mindset, excellent communication, work with strict deadlines and under high-pressure situations;\nGood command of spoken and written English, Chinese and Mandarin;\nCandidate with more experience will be considered as SeniorUX/UI Designer;\nImmediate availability or short notice is highly preferred.\n\nWe offer attractive salary and fringe benefits to the right candidate.\u00a0 Interested candidates should send FULL RESUME with Current & Expected salary.\n\nData collected will be used for recruitment purpose only.\n\n\n\n", "employment_types": ["Full Time"], "selling_points": ["Digital Design", "2 years\u2019 experience in digital design", "Experience in ecommerce platform"], "locations": ["Shatin Area"], "categories": ["Design", "Web Designer", "Marketing / Public Relations", "Digital Marketing", "Information Technology (IT)", "UI/UX Designer"], "post_time": "2021-12-28T08:02:25Z", "salary": {"currency": null, "max": null, "min": null, "period": "monthly", "term": null}, "salary_visible": false, "title_keywords": ["ui designer"], "responsibilities": ["collaborate with", "communicate with", "design concept", "design", "user interface", "ui"], "requirements": {"degrees": ["degree holder"], "majors": ["related disciplines", "design"], "languages": ["english", "chinese", "mandarin"], "language_level": ["good command"], "hard_skills": ["ai", "mobile", "web", "photoshop"], "soft_skills": ["passionate", "good team player", "creative", "innovative", "communication", "reliable"], "languages_combined": [{"language": "english", "language_level": ["good command"]}, {"language": "chinese", "language_level": ["good command"]}, {"language": "mandarin", "language_level": ["good command"]}]}, "experience_required": {"duration": ["minimum 1 year"], "field": ["designer", "design"]}}, {"job_id": "100003009003833", "location_code": "hk", "company": "Infinity Technology Corporation Limited", "job_title": "UX/UI Designer", "description": "Job Responsibilities\n\nl\u00a0\u00a0 Responsible for creating, develop creative concepts to design, artwork and the final output to meet business objectives\n\nl\u00a0\u00a0 Create awesome and interesting illustration work for the characters\n\nl\u00a0\u00a0 Handle content creation, design and production assets for the character brand, including brand style guides and other design materials across Omni channels\n\nl\u00a0\u00a0 Support the team in other ad-hoc activities as required and necessary\n\nRequirements:\n\nl\u00a0\u00a0 Currently enrolled in a bachelor\u2019s degree, Higher Diploma or equivalent in Visual Arts / Design / Creative or other related disciplines, must be enrolled in an accredited university/college program to receive credit\n\nl\u00a0\u00a0 Creative and enthusiastic, strong in storytelling, visual communication and creating engaging experiences\n\nl\u00a0\u00a0 Strong sense on Graphic, Layout, Coloring and usability on graphics and images with inputting creative concepts and designs\n\nl\u00a0\u00a0 Proficient in design software such as Photoshop / Illustrator / Procreate\n\nl\u00a0\u00a0 Good command of English and Chinese\n\nl\u00a0\u00a0 Shows initiative, drive and a commitment to innovation\n\nl\u00a0\u00a0 Strong sense of responsibility, self-motivated and able to work independently as well as a good team player\n\nWe offer attractive remuneration and fringe benefits to the right candidates. Please send us the application by clicking the \"Apply Now\" button, together with a detailed resume,\u00a0current and expected salary.\n\n\u00a0We will only notify suitable candidates for an interview. Thank you!\n\nWe are an equal opportunity employer and welcome applications from all qualified candidates. Personal data provided by job applicants will be used only for recruitment purpose and will be kept strictly confidential. Information of unsuccessful candidates will be properly disposed within 6 months.", "employment_types": ["Full Time"], "selling_points": ["UX/UI Design; Digital Design", "Dynamic and Fast-paced Environment", "Website, Mobile App, System, POS and Digital"], "locations": ["Lai Chi Kok"], "categories": ["Design", "Web Designer", "E-commerce", "Software Development", "Information Technology (IT)", "UI/UX Designer"], "post_time": "2021-12-28T10:58:59Z", "salary": {"currency": null, "max": null, "min": null, "period": "monthly", "term": null}, "salary_visible": false, "title_keywords": ["ui designer"], "responsibilities": ["ad-hoc", "develop creative concepts", "support the team", "design"], "requirements": {"degrees": ["diploma", "degree", "bachelor"], "majors": ["related disciplines", "design"], "languages": ["english", "chinese"], "language_level": ["good command"], "hard_skills": ["graphics", "visual communication", "illustrator", "photoshop"], "soft_skills": ["self-motivated", "work independently", "good team player", "sense of responsibility", "communication", "enthusiastic", "creative", "initiative"], "languages_combined": [{"language": "english", "language_level": ["good command"]}, {"language": "chinese", "language_level": ["good command"]}]}, "experience_required": {"duration": [], "field": []}}, {"job_id": "100003009002163", "location_code": "hk", "company": "Centurysoft International Limited", "job_title": "Web / App Programmer (for Commercial project)", "description": "Job Duties\nResponsible for coming up/executing graphic ideas related to eye care information\nCollaborate with marketing, event and content team members on crafting the\u00a0overall visual strategy\nDesign both offline and online communications and marketing content\nDesign campaign and events material\nAd-hoc duties as assigned from time to time\nRequirements\n\nCertificate / Diploma / Degree holder in Design / Graphic Design / Creative Media / Multimedia Design or related field\nMinimum 1- 2 years of solid experience in commercial design and production\nGood illustration skill is a huge advantage\nFamiliar with websites and social media platforms such as Facebook, Instagram and YouTube\nGood communication & interpersonal skills\nCandidate familiar with medical industry, especially ophthalmology, is highly preferred\nImmediate availability is highly preferred\nBenefits\n\nYoung and dynamic marketing team\n5-day work per week\nMedical insurance\nAnnual leave\nAnnual discretionary bonus\nSpecial offer of eye treatment for staff and family\nSkills\n\nAdobe Photoshop/Illustrator/In-design/After Effect/Premiere/retouching\nSocial media operations (Facebook/Instagram)\nCompany website:\nhttps://smile.hkcmereye.com\nhttps://www.hkcmereye.com\n\n*Candidates without portfolio will not be considered*", "employment_types": ["Full Time"], "selling_points": ["Degree/Diploma in Computing Science or equivalent", "Minimum 2 years experience in software development", "5 days work & Year-end Double Pay"], "locations": ["Kwai Hing"], "categories": ["Design", "Web Designer", "Information Technology (IT)", "Application Specialist - Software", "Software Development"], "post_time": "2021-12-28T03:59:17Z", "salary": {"currency": null, "max": null, "min": null, "period": "monthly", "term": null}, "salary_visible": false, "title_keywords": ["programmer"], "responsibilities": ["collaborate with", "ideas", "ad-hoc duties", "design", "executing", "visual"], "requirements": {"degrees": ["certificate", "diploma", "degree holder"], "majors": ["multimedia design", "graphic design", "creative media", "design"], "languages": [], "language_level": [], "hard_skills": ["facebook", "illustration", "multimedia"], "soft_skills": ["communication", "creative", "interpersonal skills"], "languages_combined": []}, "experience_required": {"duration": ["minimum 1- 2 years"], "field": ["commercial", "design"]}}, {"job_id": "100003009005821", "location_code": "hk", "company": "Intepay Company Limited", "job_title": "Full-time/Part-time/Internship-Backend Developer/Web Developer/CMS System Developer", "description": "Job Description:\n\u25cf\u00a0 Analysis, design and implementation of Web application / Mobile app systems;\n\u25cf\u00a0 Ensuring conformance of software packages against user requirement ;\n\u25cf\u00a0 Design and complete requirement specifications for different components for application systems\n\u25cf\u00a0 Prepare system specifications and cases of testing; maintain systems documentations and monitor service provision of IT solutions\n\nJob Duties:\n\u25cf\u00a0 Participating in mobile app implementation and system enhancements.\n\u25cf\u00a0 Development of web platform and apps.\n\u25cf\u00a0 Daily system maintenance, troubleshooting and periodically software deployment.\n\nResponsibilities:\n\u25cf\u00a0 Design, build, test and maintain web and mobile business applications for clients in various industries.\n\u25cf\u00a0 Participate in system design, programming, testing and system delivery\n\u25cf\u00a0 Maintain and support the application services\n\u25cf\u00a0 Analyze and optimize program for efficiency and performance\n\nRequirements:\n\u25cf Degree/Diploma in Computing Science or equivalent.\n\u25cf Minimum 2 years of solid and relevant experience in software development.\n\u25cf Application with less experience or fresh graduate may be considered as Junior Programmer.\u2022 \u25cf Experience or Good Knowledge either of Swift (iOS) or Kotlin & Java (Android), ReactJS, Flutter and PHP.\n\u25cf Experience with node.js or Python on Linux Environment will be a definite advantage\n\u25cf Ability to quickly grasp any new technologies\n\u25cf Good communication skill in both Chinese & English\n\u25cf Willing to learn, self-initiative, sense of responsibility and interpersonal skill.\n\u25cf Salary range depends on the capability of the candidates.\n", "employment_types": ["Full Time", "Part Time", "Internship"], "selling_points": ["Monthly Salary up to HKD30K \u6708\u85aa\u9ad8\u90543\u842c", "Working five days a week/public holidays 5\u5929\u5de5\u4f5c \u7d05\u65e5\u653e\u5047", "Flexible Working in Hong Kong Science Park \u9999\u6e2f\u79d1\u6280\u5712\u5de5\u4f5c"], "locations": ["Shatin Area"], "categories": ["Design", "Web Designer", "Information Technology (IT)", "Network & System", "E-commerce", "Software Development"], "post_time": "2021-12-29T05:00:52Z", "salary": {"currency": null, "max": null, "min": null, "period": "monthly", "term": null}, "salary_visible": false, "title_keywords": ["developer", "system developer", "internship"], "responsibilities": ["user requirement", "mobile app", "software", "maintenance", "analysis", "systems", "monitor", "implementation", "design", "testing", "troubleshooting", "system delivery", "specifications", "maintain", "system design", "application systems"], "requirements": {"degrees": ["diploma", "degree", "fresh graduate"], "majors": ["science"], "languages": ["english", "chinese"], "language_level": ["good"], "hard_skills": ["linux", "java", "php", "python", "swift", "kotlin", "android"], "soft_skills": ["sense of responsibility", "communication skill", "willing to learn", "interpersonal skill", "self-initiative"], "languages_combined": [{"language": "english", "language_level": ["good"]}, {"language": "chinese", "language_level": ["good"]}]}, "experience_required": {"duration": ["minimum 2 years"], "field": ["relevant experience", "software development"]}}, {"job_id": "100003009005044", "location_code": "hk", "company": "Aesop", "job_title": "Regional Digital Content Producer", "description": "Job Highlights\n\nFast-growing new FinTech startup company\nFriendly Working Environment in Hong Kong Science Park\uff08Sha Tin\uff09\nFull-Time: HKD18000-HKD30000 per month\nPart-Time: HKD 70-100 per hour (at least 2 days per week)\nWinter Break/Sem B Internship: HKD 10500 per month\nWorking Days: Mon-Fri 10:00-19:00\nJob Descriptions\n\n\nResponsible for\u00a0\u00a0the design, building, and development of our backend & CMS system to improve business process and business operations.\nFamiliar with Google Firebase, Web design, APIs and GitHub.\nCoordinate with the project team to perform system integration and implementation\nKnowledge of algorithm, data structure and design patterns.\nMaintain and administrator company intranet website and improve function according to company needs\nDevelop IT solutions for management to visualize the business and performance trends\nParticipation in entrepreneurial activities (if required)\n\nJob Requirements\n\nDiploma and degree holder in computer science, information technology or related disciplines\nSolid experience in backend development is a must\nIndependent, logical mind with problem-solving skills\nFamiliar with Google Firebase,\u00a0Web design and GitHub.\nIn-depth knowledge of Java, Typescript, PHP, Python,\u00a0Node.js, NativeScript\nSelf-motivated, energetic and passionate on exploring new technology\nFluent in written and oral Chinese and English", "employment_types": ["Full Time", "Permanent"], "selling_points": ["Site Merchandising and Content Management", "Global and growing retail organisation", "Attractive Benefits"], "locations": ["Central & Western Area"], "categories": ["Design", "Multi-media", "Web Designer", "E-commerce", "Others"], "post_time": "2021-12-29T03:22:37Z", "salary": {"currency": null, "max": null, "min": null, "period": "monthly", "term": null}, "salary_visible": false, "title_keywords": ["producer"], "responsibilities": ["management", "data", "operations", "coordinate with", "implementation", "design", "website", "develop", "business process", "maintain"], "requirements": {"degrees": ["diploma", "degree holder"], "majors": ["related disciplines", "computer science", "information technology"], "languages": ["english", "chinese"], "language_level": ["fluent"], "hard_skills": ["web design", "java", "php", "typescript", "python", "problem-solving skills"], "soft_skills": ["passionate", "self-motivated", "oral", "independent", "problem-solving skills", "energetic"], "languages_combined": [{"language": "english", "language_level": ["fluent"]}, {"language": "chinese", "language_level": ["fluent"]}]}, "experience_required": {"duration": [], "field": ["development"]}}, {"job_id": "100003009004397", "location_code": "hk", "company": "Alipay Payment Services (HK) Limited", "job_title": "Brand Marketing Manager", "description": "POSITION PURPOSE\n\nThe Regional Digital Content Producer role will be accountable and responsible for contributing to and delivering on a range of projects and BAU within the global and regional digital program of work, with specific relation to content, merchandising and campaigns\n\nThe successful applicant will be central to the planning and coordination of content and commercial activities for .com tied to campaigns and optimisation. They will embed digital thinking, delivery and support across Aesop\u2019s functions and provide the culture, capacity and capabilities needed to make this happen.\u202f\n\nThe role will require excellent communication skills, exceptional organisation skills, problem solving & risk mitigation sensibilities, as well as\u202fa level of comfort working with various business functions,\u202fin particular Marketing, Creative and Digital. They will have awareness and consideration for the complexities within the digital program and Aesop\u2019s online retail environment. Previous experience in digital production in a multi-lingual, global retail context would be valuable.\u202f\u202f\n\nThe role will act as a key source of digital knowledge surrounding our digital platforms and processes to our local region, along with supporting the digital production team ensuring successful project/content delivery for the region, in line with Global initiatives.\u00a0\n\nMAIN RESPONSIBILITIES\n\nSite Merchandising and Content Management\n\n\u00a0\u00a0\u00a0\u00a0\u00a0\u00a0\u00a0 Responsible for campaign reviews for Asia and execution to ensure product information and content is consistent and accurate\n\u00a0\u00a0\u00a0\u00a0\u00a0\u00a0\u00a0 Ensure accuracy and consistency across the site, with an understanding of its impact on the customer experience.\n\u00a0\u00a0\u00a0\u00a0\u00a0\u00a0\u00a0 Develop and execute regional merchandising and content collection strategy that responds to campaign, seasonality and performance objectives\n\u00a0\u00a0\u00a0\u00a0\u00a0\u00a0\u00a0 Brief landing pages and creative assets that support commercial initiatives\u00a0\n\u00a0\u00a0\u00a0\u00a0\u00a0\u00a0\u00a0 Monitor the live site daily to check for category navigation issues and opportunities and product accuracy\n\u00a0\u00a0\u00a0\u00a0\u00a0\u00a0\u00a0 Work with Global Digital to optimize site content indexed within to ensure customers can find content within the search function\n\u00a0\u00a0\u00a0\u00a0\u00a0\u00a0\u00a0 Collaborate with Customer Service team to troubleshoot and escalate website issues\n\u00a0\u00a0\u00a0\u00a0\u00a0\u00a0\u00a0 Build and deploy site assets on for local and regional omnichannel programs\n\u00a0\u00a0\u00a0\u00a0\u00a0\u00a0\u00a0 Work with the Global SEO lead to implement local SEO strategies at a content management level.\n\nPerformance Driving Initiatives\n\n\u00a0\u00a0\u00a0\u00a0\u00a0\u00a0\u00a0 Support Regional Online Operations Manager to drive conversion and revenue during key promotional periods by submitting creative briefs for regional campaigns\u00a0\n\u00a0\u00a0\u00a0\u00a0\u00a0\u00a0\u00a0 Partner with Marketing and Insights to implement performance improvement programs on an ongoing basis\n\nReporting\u00a0\n\n\u00a0\u00a0\u00a0\u00a0\u00a0\u00a0\u00a0 Own KPIs and analyze data to assess performance and implement improvements\u00a0\n\u00a0\u00a0\u00a0\u00a0\u00a0\u00a0\u00a0 Create weekly, monthly and quarterly reports\u00a0\u00a0\n\nSKILLS / QUALIFICATIONS\n\n\u00a0\u00a0\u00a0\u00a0\u00a0\u00a0\u00a0 BA/BS degree or equivalent experience in relevant fields\n\u00a0\u00a0\u00a0\u00a0\u00a0\u00a0\u00a0 Experience in site merchandising and content management or other related digital activities\n\u00a0\u00a0\u00a0\u00a0\u00a0\u00a0\u00a0 Rigorous and able to understand analysis related to customer behavior\n\u00a0\u00a0\u00a0\u00a0\u00a0\u00a0\u00a0 Experience working with data\n\u00a0\u00a0\u00a0\u00a0\u00a0\u00a0\u00a0 An advocate for change and creative improvement who leads and encourages action to improve processes or products and helps others to adapt to new approaches\n\u00a0\u00a0\u00a0\u00a0\u00a0\u00a0\u00a0 Process and detail-oriented mindset, and demonstrated ability to maintain a clear history of changes and optimization results\n\u00a0\u00a0\u00a0\u00a0\u00a0\u00a0\u00a0 Proven experience identifying opportunities to find efficiencies throughout the customer journey that impact the user experience\n\u00a0\u00a0\u00a0\u00a0\u00a0\u00a0\u00a0 Strong communication skills and ability to work cross-functionally with other teams\u00a0\n\u00a0\u00a0\u00a0\u00a0\u00a0\u00a0\u00a0 A team leader who develops respectful influencing strategies to leverage support from cross-functional stakeholders\n\u00a0\u00a0\u00a0\u00a0\u00a0\u00a0\u00a0 Self-motivated and able to apply their energy and enthusiasm to engage a range of time-poor stakeholders\n\u00a0\u00a0\u00a0\u00a0\u00a0\u00a0\u00a0 Previous experience working in e-commerce D2C a plus\n\u00a0\u00a0\u00a0\u00a0\u00a0\u00a0\u00a0 Sound understanding of what a CMS is and how they work or experience in working with one\n\u00a0\u00a0\u00a0\u00a0\u00a0\u00a0\u00a0 Experience in working with Contentful and Hybris platforms is a bonus but not a necessity", "employment_types": ["Full Time", "Permanent"], "selling_points": ["Digital Marketing", "Digital Wallet", "Young and Energetic Working Environment"], "locations": ["Causeway Bay"], "categories": ["Design", "Web Designer", "Marketing / Public Relations", "Marketing - Brand / Product Management", "Digital Marketing"], "post_time": "2021-12-29T02:17:49Z", "salary": {"currency": null, "max": null, "min": null, "period": "monthly", "term": null}, "salary_visible": false, "title_keywords": ["marketing manager"], "responsibilities": ["collaborate with", "data", "operations", "merchandising", "website", "communication", "customer service", "maintain", "troubleshoot", "deploy", "monitor", "user experience", "teams", "develop", "bs", "reports", "analyze data", "kpis", "reporting", "management", "seo", "analysis", "coordination", "planning"], "requirements": {"degrees": ["degree"], "majors": [], "languages": [], "language_level": [], "hard_skills": ["plus", "seo", "e-commerce", "analysis", "problem solving", "make"], "soft_skills": ["communication skills", "self-motivated", "responsible", "accurate", "accountable", "detail-oriented", "problem solving", "clear", "customer service", "troubleshoot", "coordination", "organisation", "creative", "respectful"], "languages_combined": []}, "experience_required": {"duration": [], "field": ["management", "e-commerce", "related", "merchandising", "digital", "retail"]}}, {"job_id": "100003009005226", "location_code": "hk", "company": "Pacific Foundation Securities Limited", "job_title": "\u7db2\u8def\u8a2d\u8a08\u53ca\u63a8\u5ee3\u4e3b\u4efb E-Commerce and Digital Marketing Officer", "description": "\u8077\u8cac\uff1a\n\n\u8ca0\u8cac\u7ba1\u7406\u516c\u53f8\u7db2\u7ad9\u53caApp\uff1b\n\u8ca0\u8cac\u516c\u53f8\u73fe\u6709\u5a92\u4ecb\u5e73\u53f0\u71df\u904b\u7ba1\u7406\uff0c\u63d0\u9ad8\u7db2\u7ad9\u7684\u9ede\u64ca\u7387\u3001\u8f49\u5316\u7387\u3001\u700f\u89bd\u91cf\uff1b\n\u5354\u52a9\u5176\u4ed6\u81e8\u6642\u88ab\u59d4\u6d3e\u7684\u5de5\u4f5c\u6216\u5c08\u6848\u9805\u76ee\n\u8a2d\u8a08\u7c21\u55ae\u5e73\u9762\u5ba3\u50b3\u6d77\u5831\uff0c\u61c2Photoshop, AI\u512a\u5148\n\n\u8981\u6c42\uff1a\n\n\u4e2d\u5b78\u6216\u4ee5\u4e0a\u5b78\u6b77\uff0c\u5177\u67091\u5e74\u6216\u4ee5\u4e0a\u96fb\u5546\u5e73\u53f0\u7684\u904b\u71df\u5de5\u4f5c\u7d93\u9a57\uff0c\u64c1\u6709\u91d1\u878d\u985e\u76ee\u7d93\u9a57\u5c07\u7372\u512a\u5148\u8003\u616e\n\u7cbe\u901a\u7db2\u4e0a\u4ea4\u6613\u63a8\u5ee3\u6d41\u7a0b\u53ca\u5404\u7a2e\u71df\u92b7\u5de5\u5177\n\u719f\u6089\u96fb\u5546\u5e73\u53f0\u653f\u7b56\u548c\u898f\u5b9a\n\u719f\u7df4\u904b\u7528\u96fb\u5546\u5e73\u53f0\u7684\u64cd\u4f5c\u5f8c\u53f0\u548c\u5e73\u53f0\u898f\u5247\n\u826f\u597d\u7cb5\u8a9e\u3001\u666e\u901a\u8a71\u548c\u4e2d\u82f1\u6587\u8b80\u5beb\u80fd\u529b", "employment_types": ["Full Time"], "selling_points": ["\u8ca0\u8cac\u7ba1\u7406\u516c\u53f8\u7db2\u7ad9\u53caApp", "\u8a2d\u8a08\u7c21\u55ae\u5e73\u9762\u5ba3\u50b3\u6d77\u5831\uff0c\u61c2Photoshop, AI\u512a\u5148", "\u719f\u7df4\u904b\u7528\u96fb\u5546\u5e73\u53f0\u7684\u64cd\u4f5c\u5f8c\u53f0\u548c\u5e73\u53f0\u898f\u5247"], "locations": ["Sheung Wan"], "categories": ["Design", "Web Designer", "Information Technology (IT)", "Network & System", "E-commerce", "Marketing - Brand / Product Management"], "post_time": "2021-12-29T03:37:58Z", "salary": {"currency": null, "max": null, "min": null, "period": "monthly", "term": null}, "salary_visible": false, "title_keywords": ["digital marketing officer"], "responsibilities": [], "requirements": {"degrees": [], "majors": [], "languages": [], "language_level": [], "hard_skills": [], "soft_skills": [], "languages_combined": []}, "experience_required": {"duration": [], "field": []}}, {"job_id": "100003009000309", "location_code": "hk", "company": "A.S. Watson Retail (HK) Limited", "job_title": "(Senior) UX & Design Specialist", "description": "Responsibilities:\n\nDevelop brand\u00a0strategy, including brand positioning, segmentation, definition and articulation\nOwn brand guideline to consult and define different business units to interact or represent the brand\nConduct or apply market research, analyze customer and marketing insights for future branding and marketing development and strategies\nResponsible for design and production of marketing material\nManage and develop relevant and engaging content for the brand character\nDesign, develop and package the\u00a0branded merchandise\nRequirements:\n\nDegree holder in Brand Marketing, Communication or related disciplines\n6+ years of experience in branding, brand identity, customer experience design\nProficiency in Adobe creative suite\nGood presentation and communication skills in Chinese and English\nPositive attitude, pro-active, can work independently and in a team environment", "employment_types": ["Permanent"], "selling_points": ["3 years in relevant experience", "Hands-on and proven experiences in UX & UI design", "Have O2O commerce experience"], "locations": ["Shatin Area"], "categories": ["Design", "Web Designer", "E-commerce", "Marketing - Brand / Product Management", "Information Technology (IT)", "UI/UX Designer"], "post_time": "2021-12-25T00:05:29Z", "salary": {"currency": null, "max": null, "min": null, "period": null, "term": null}, "salary_visible": false, "title_keywords": ["ux & design specialist"], "responsibilities": ["marketing material", "market research", "design", "develop"], "requirements": {"degrees": ["degree holder"], "majors": ["related disciplines", "marketing"], "languages": ["english", "chinese"], "language_level": ["good"], "hard_skills": ["adobe creative suite"], "soft_skills": ["communication skills", "work independently", "communication", "positive attitude", "pro-active", "creative", "presentation"], "languages_combined": [{"language": "english", "language_level": ["good"]}, {"language": "chinese", "language_level": ["good"]}]}, "experience_required": {"duration": ["6+ years"], "field": ["brand", "design"]}}]