[{"job_id": "100003009054406", "location_code": "hk", "company": "Prowess Recruitment Consulting Limited", "job_title": "Logistics Operation Manager / Officer - Airport", "description": "The successful candidate will be responsible for in charge\u00a0a team to provide 7 x 24 functional direction and leadership roles to the Airport Logistics Centre and acts as the primary interface on line haul performance with the line haul providers and with the Aviation commercial group management team.\u00a0\u00a0You also monitor the line haul performance to and from other regions, where the company owned or controlled aircraft are used.\n\nThe job holder\u2019s major responsibilities are to:\nReporting to the\u00a0Department Director, you will manage teams of supervisors and\u00a0operators to ensure effective management of transportation in the network service including daily space planning and optimize space allocation on network flights while meeting customers\u2019 requirements.\n\nYou will have to ensure timely provision of reports / information in terms of flight performance/incidents, capacity allocation, utilization, and line-haul reports, etc. to optimize capacity on network flights and improve the performance on commercials flights.\n\nYou will represent\u00a0Operation\u00a0Department\u00a0in building and maintaining good business relationship with\u00a0airlines, line-haul service providers / suppliers and negotiating for service performance improvement, flight information updating process and space booking issues.\u00a0\nYou will also be required to lead the team in proactively monitoring the inbound / outbound flight movements, providing real-time visibility of movement through systems, promptly responding to network requests and timely updates of service incidents.\n\nIn the event of potential service incidents with transit time impact, you are required to support contingency actions as planned by the regional team in order to keep the impact to its minimal.\u00a0\n\nRequirements:\n\nDegree holder, preferably in Transportation or Logistics related discipline\nLeast 10 years working experience in\u00a0flight dispatch/operation,\u00a0airline, transportation or logistics industry with supervisory level experience\nFamiliar with air transport practices and Hong Kong Customs rules and regulations is an advantage\nGood command of both spoken and written Business English and Cantonese\nStrong planning and data analysis skills\nStrong interpersonal and stakeholder management skills\nHigh level of energy, motivation and drive skills\nComfortable working in a relatively unstructured and multi-cultural environment\nLess experience will consideration as\u00a0Logistics Operation Officer\n\nOffer and Benefit :\n\n\u00a0Stable shift duty 5 Days' work in a week\u00a0\n\u00a0Medical scheme and transportation allowance\u00a0\n\u00a015 Days annul leave with annual performance bonus\n\u00a0Entitled the banking holidays with clear career promotion\u00a0\n\nMORE POSITIONS PLEASE VISIT OUR WEBSITE AT: http://www.prowess.hk\n\nWhatsApp to our consultant\u00a0:\u00a0https://wa.me/85291493008\u00a0or contact us at\u00a0+852\u00a0 2838 9621 for more information of the position.\nFor interested candidates, please submit your full resume with expected salary in MS Word format to us through the above email.\n\n", "employment_types": ["Full Time", "Permanent", "Contract"], "selling_points": ["University degree least 10 years' experience", "Ability to work in fast-paced airport environment", "Excellent planning & good operation management"], "locations": ["Airport Area"], "categories": ["Transportation & Logistics", "Aviation Services", "Management", "General Management", "Freight Forwarding"], "post_time": "2022-01-17T09:24:09Z", "salary": {"currency": null, "max": null, "min": null, "period": "monthly", "term": null}, "salary_visible": false, "title_keywords": ["officer", "logistics", "operation manager"], "responsibilities": ["reporting", "management", "maintaining", "monitoring", "teams", "systems", "reports", "booking", "planning"], "requirements": {"degrees": ["degree holder"], "majors": [], "languages": ["cantonese", "english"], "language_level": ["good command"], "hard_skills": ["whatsapp", "analysis", "airline", "scheme"], "soft_skills": ["clear", "stable", "interpersonal"], "languages_combined": [{"language": "cantonese", "language_level": ["good command"]}, {"language": "english", "language_level": ["good command"]}]}, "experience_required": {"duration": ["least 10 years"], "field": ["logistics industry", "supervisory level", "operation", "logistics"]}}, {"job_id": "100003009051896", "location_code": "hk", "company": "Plastech (China) Company Limited", "job_title": "Assistant General Manager", "description": "Responsibilities:\nAssist President for all kinds of Regional management;\nAssist President to execute sales strategies and sales planning;\nAssist President to establish ERP system;\nManage the company website;\nCoordinate all business related affairs both Hong Kong headquarter and regional offices;\nConsolidate and analyze reports and format presentations;\nAd-hoc projects as required;\nRequirements:\nBachelor Degree in Business or above with minimum 5 years relevant experience;\nMature, responsible, trustworthy, self-motivated and detail-oriented;\nStrong communication and interpersonal skills with strong sense of responsibilities;\nExcellent command in spoken and written English, Mandarin and Cantonese;\nProficiency in PC software, e.g. MS PowerPoint, Word, and Excel;\nWilling to travel when required.\nInterested parties, please click \"Apply Now\" to submit your application.\n\n\nPersonal data collected will be used for recruitment purpose only.", "employment_types": ["Full Time", "Permanent"], "selling_points": ["Assist President for all kinds of Regional mngmt.", "Assist President to execute sales strategies", "Minimum 5 years relevant experience"], "locations": ["Wan Chai"], "categories": ["Sales, CS & Business Devpt", "Business Development", "Management", "General Management", "Sales - Sales Management"], "post_time": "2022-01-17T01:28:02Z", "salary": {"currency": null, "max": null, "min": null, "period": "monthly", "term": null}, "salary_visible": false, "title_keywords": ["assistant general manager"], "responsibilities": ["management", "presentations", "coordinate", "reports", "ad-hoc projects", "company website", "planning"], "requirements": {"degrees": ["degree", "bachelor"], "majors": ["business"], "languages": ["cantonese", "english", "mandarin"], "language_level": ["excellent"], "hard_skills": ["pc", "ms powerpoint", "word", "excel"], "soft_skills": ["self-motivated", "trustworthy", "responsible", "mature", "detail-oriented", "communication and interpersonal skills", "sense of responsibilities"], "languages_combined": [{"language": "cantonese", "language_level": ["excellent"]}, {"language": "english", "language_level": ["excellent"]}, {"language": "mandarin", "language_level": ["excellent"]}]}, "experience_required": {"duration": ["minimum 5 years"], "field": ["business", "relevant experience"]}}, {"job_id": "100003009054764", "location_code": "hk", "company": "Fillture Group Limited", "job_title": "General Manager - FinTech", "description": "A FinTech group is looking for General Manager to join their team. This role will be\u00a0develop action plan for consumer business to improve productivity, make recommendations on modification of procedures and application of technology to enhance operational efficiency and minimize operational risk.\n\nResponsibilities:\n\nFormulate the business plan, corporate strategies and policies according to the group annual objectives, monitoring their implementation and timely report to CEO.\nMonitor the achievement status of KPI\u2019s closely, analyze and make suggestions to different departments and subordinates to improve performance.\nReport the business performance to CEO regularly, adjust business strategies in a timely manner according to the actual operating situation.\nParticipate in thematic meetings in order to discuss the operation matters and development of various projects.\nReview and approve for the staffing plan, performance evaluation and make recommendations based on the result of appraisal.\nEssential to promote and establish a good communication and working atmosphere.\nKeep updated in industry news and local policies, organize various departments to conduct market research and new product development.\nRequirements:\n\nBachelor degree or above, majoring in Business Administration, Finance, Economics, or the relevant\n10 years or above working experience in Finance companies or banks; preferably the relevant experience in running mortgage and unsecured personal loan business\n\u00a0At least 5 years role as senior executive position of Finance companies or banks\nFamiliar with the financial market crossing Mainland and Hong Kong, good connections with target clients, strong financial business development capability\nCompetence in FinTech is necessary; Sales-oriented with strong marketing skills\nExcellent team management capability and cross-cultural communication and coordination capability\nGood computer skills and experienced in MS Office applications\nFluent in written and spoken English & Mandarin\nActive and Open-minded; Process work in a timely, punctual manner\n\nApply for this job:\n\nInterested candidate please CLICK apply button to apply online or send your resume in MS word format to Fillture Group Limited\n\nFor more information, please contact\u00a0Danvis Lau\u00a0+852 2814 9388.\n\nPlease note that only shortlisted candidate will be notified. All information will be treated in strict confidence and solely used for recruitment purposes.", "employment_types": ["Full Time", "Permanent"], "selling_points": ["FinTech Company", "Experienced in consumer loans", "Attractive Salary Package and Benefits"], "locations": ["Central & Western Area"], "categories": ["Banking / Finance", "Loan", "Financial Services", "Management", "General Management"], "post_time": "2022-01-17T10:58:45Z", "salary": {"currency": null, "max": null, "min": null, "period": "monthly", "term": null}, "salary_visible": false, "title_keywords": ["general manager"], "responsibilities": ["make recommendations", "policies", "conduct market research", "monitoring", "monitor", "implementation", "a timely manner", "review", "communication", "plan", "evaluation", "business plan", "report"], "requirements": {"degrees": ["degree or above", "bachelor"], "majors": ["finance", "economics", "business administration"], "languages": ["english", "mandarin"], "language_level": ["fluent"], "hard_skills": ["ms word", "marketing skills", "computer skills", "ms office"], "soft_skills": ["confidence", "open-minded", "timely", "communication", "coordination", "active"], "languages_combined": [{"language": "english", "language_level": ["fluent"]}, {"language": "mandarin", "language_level": ["fluent"]}]}, "experience_required": {"duration": ["10 years"], "field": ["loan business", "finance", "relevant experience"]}}, {"job_id": "100003009044744", "location_code": "hk", "company": "Full Africa International Limited", "job_title": "General Manager", "description": "Our\u00a0\"Agency Management\"\u00a0program offers excellent opportunity to high potential talents to further develop themselves to become future leaders of our organization. Successful candidates will be engaged in a fast-track program within our operating business units. We are now extending invitations to high caliber candidates with passion and commitment to join us.\u00a0\n\nWe are looking for an individual who:\n\nMin. 5 years' work experience in\u00a0supervisor position\nStrong leadership skill and able to coach and inspire team members\nIs determined and outgoing\nMature personality with excellent inter-personal and communication skills\nAn energetic person, who likes sport activities\nGood command in Chinese and HK ID card holder\n\nIf this fits your profile, we would very much like to hear from you.\u00a0\n\nWe offer 5-day work, bank holiday, medical benefits, attractive remuneration package with attractive bonus structure, luxury conventions and\u00a0generous fringe benefits to the right candidate.\u00a0\n\nInterested parties, please\u00a0apply\u00a0by click \"APPLY\u00a0NOW\".\n\n\n\nOnly short-listed candidates will be contacted. All applicant information is treated confidentially, personal data collection is only for recruitment selection purposes. The recruitment offer is subject to the terms & conditions as stipulated in the agreement.", "employment_types": ["Full Time", "Permanent"], "selling_points": [], "locations": ["Wan Chai"], "categories": ["Management", "General Management"], "post_time": "2022-01-15T03:49:20Z", "salary": {"currency": null, "max": null, "min": null, "period": "monthly", "term": null}, "salary_visible": false, "title_keywords": ["general manager"], "responsibilities": ["communication", "management", "develop"], "requirements": {"degrees": [], "majors": [], "languages": ["chinese"], "language_level": ["good command"], "hard_skills": ["id"], "soft_skills": ["outgoing", "communication skills", "determined", "inter-personal", "mature", "leadership skill", "energetic"], "languages_combined": [{"language": "chinese", "language_level": ["good command"]}]}, "experience_required": {"duration": ["5 years"], "field": ["supervisor position"]}}, {"job_id": "100003009052757", "location_code": "hk", "company": "Yicon Consultants Limited", "job_title": "Deputy General Manager - Property Development (\u526f\u7e3d\u7d93\u7406 - \u7269\u696d\u62d3\u5c55)", "description": "Purpose& Overall Relevance for the Organization:\nDrive and coordinate production allocation and availability management for finished products and components across all Footwear LOs/functions\nDrive conceptual evolution, implementation and ramp-up of Speed programs; and coordinate all operations of Speed programs across the Footwear organization, incl. feasibility checks, material staging, capacity and availability management\nSupport the Director Allocation & Capacity in the operational and strategic planning process; and in identifying/implementing initiatives that enhance the capabilities, efficiency, effectiveness and collaboration within Footwear Sourcing\n\n\nKey Responsibilities:\nOptimize seasonal production allocation along various dimensions incl. availability, landed costs (FOB, duty, VA), key technologies, model mix and factory capabilities; drive allocation strategy implementation through production allocation on BU and franchises level; actively influence and shape development allocation through production allocation decisions\nDrive monthly performance of Footwear Sourcing operations along relevant dimensions (e.g. order fulfilment KPIs, capacity utilization, process compliance and efficiency, etc.)\nDrive component business and feasibility checks and develop alternative sourcing options to optimize trade benefits\nProactively identify potential issues for fulfilment and capacity utilization and work closely with the LOs and/or functional teams to develop mitigation measures\nManage end to end planning process of special Statement projects (e.g Yeezy..)\nManage the current Footwear Speed programs Continuous Replenishment / Planned Responsiveness / In-Season Creation: monitor execution of all on/off-system processes to ensure high degree of speed feasibility, order fulfilment, and to identify improvement opportunities; specifically, own and drive the seasonal speed feasibility checks and support SMU requests\nSupport the department in ad-hoc data analyses\nSupport selected projects as defined by Director Allocation & Capacity\n\n\nKey Relationships:\nLO teams and esp. LO Planning Managers, DPCs and SDOMs\nSupplier teams and esp. Business Planning Managers\nGlobal Supply Planning and BU planning\nGOPS Speed team\nProduct Operations\nother COPS functions\n\n\nKnowledge Skills and Abilities:\nStrong analytical and quantitative skills\nGood interpersonal and communication skills\nUnderstanding of trade topics (import duties, FTA, trade barriers) affecting imports from the Footwear source countries into major markets\nGood knowledge of Footwear industry and manufacturing methods a plus\nGood knowledge of standard Software applications (Excel, PowerPoint)\nProject management skills a plus\n\n\nRequisite Education and Experience / Minimum Qualifications:\nUndergraduate university degree\nMinimum of 5 years working experience in a Sourcing role or operations\nFluency in English, knowledge of another language (ideally Mandarin, Vietnamese, Bahasa, or German) an advantage.\n\nAT ADIDAS WE HAVE A WINNING CULTURE. BUT TO WIN, PHYSICAL POWER IS NOT ENOUGH. JUST LIKE ATHLETES OUR EMPLOYEES NEED MENTAL STRENGTH IN THEIR GAME. WE FOSTER THE ATHLETE\u2018S MINDSET THROUGH A SET OF BEHAVIORS THAT WE WANT TO ENABLE AND DEVELOP IN OUR PEOPLE AND THAT ARE AT THE CORE OF OUR UNIQUE COMPANY CULTURE \u2013 THE 3CS: CONFIDENCE, COLLABORATION AND CREATIVITY.\n\nCONFIDENCE allows athletes to make quick decisions on the field, to reach higher. For us at adidas confidence means acknowledging that we don\u2019t have all the answers. But we are willing to take risks, we try new things. And if we fail, then this is part of our learning \u2013 it helps us improve.\n\nCOLLABORATION. Every elite athlete relies on partners: coaches, teammates, and nutritionists. We, too, know that we are stronger together. Winning as one team takes open and candid dialogue, inclusiveness and trust in each other\u2019s abilities and talents.\n\nBeing the best sports company in the world takes CREATIVITY. No great athlete succeeds by copying their predecessors\u2019 training plans and strategies. We have to be open to new ideas, explore, gain an edge and stand out. Only then can we succeed.\n\nADIDAS CELEBRATES DIVERSITY, SUPPORTS INCLUSIVENESS AND ENCOURAGES INDIVIDUAL EXPRESSION IN OUR WORKPLACE. WE DO NOT TOLERATE THE HARASSMENT OR DISCRIMINATION TOWARD ANY OF OUR APPLICANTS OR EMPLOYEES. WE ARE AN EQUAL OPPORTUNITY EMPLOYER.\nJOB TITLE:\nSenior Manager Delivery Management FW\nBRAND:\nadidas\nLOCATION:\nHong Kong\nTEAM:\nSourcing\nSTATE:\nHK\nCOUNTRY/REGION:\nCN\nCONTRACT TYPE:\nFull time\nNUMBER:\n412369\nDATE:\nJan 7, 2022", "employment_types": ["Full Time", "Permanent", "Contract", "Freelance"], "selling_points": [], "locations": ["Not Specified"], "categories": ["Professional Services", "Business Consultancy", "Management", "General Management", "Property / Real Estate", "Property Management"], "post_time": "2022-01-17T03:56:17Z", "salary": {"currency": null, "max": null, "min": null, "period": "monthly", "term": null}, "salary_visible": false, "title_keywords": ["general manager"], "responsibilities": ["management", "strategic planning", "operations", "compliance", "implementation", "coordinate", "kpis", "costs"], "requirements": {"degrees": [], "majors": [], "languages": [], "language_level": [], "hard_skills": [], "soft_skills": [], "languages_combined": []}, "experience_required": {"duration": [], "field": []}}, {"job_id": "100003009051499", "location_code": "hk", "company": "", "job_title": "Manager / Asst. Manager  (5 days work)", "description": "Responsibilities:\n\nExecute and implement strategic business plan to achieve objectives (short, medium and long term);\nOversee the daily operational activities;\nCoordinate the human and materials resources of the Chinese medicine clinics;\nFormulate polices and coordinate methods to ensure patient satisfaction;\nPerform ad hoc projects and assignment as required.\n\nRequirements:\n\nBachelor\u2019s degree in Pharmacy, Chinese medicine or equivalent;\n5 years or above experience in pharmacy or Chinese medicines industry of which at least 2 years management experience;\nStrong industry network with a solid track record of proven ability to operate clinic;\nGood command of spoken and written English & Chinese (Cantonese & Putonghua);\nHave a startup mindset, well-organized, open-minded, decisive and flexible.\n\nWe offer 5-day work week and competitive remuneration package to qualified candidates. Interested parties please send your resume with current and expected salary for application. Please visit our company\u2019s website www.tianda.com to know more about us.\n\nData collected will be used for recruitment purpose only.\u00a0 Applicants not heard from us within 6 weeks may consider their applications filed for future openings.", "employment_types": ["Full Time", "Permanent"], "selling_points": ["Coaching & team building, develop new market", "International & friendly working environment", "very attractive remuneration  package"], "locations": ["Not Specified"], "categories": ["Professional Services", "Business Consultancy", "Management", "General Management", "Sales, CS & Business Devpt", "Sales - Sales Management"], "post_time": "2022-01-16T05:28:25Z", "salary": {"currency": "HKD", "max": 69999, "min": 25000, "period": "monthly", "term": null}, "salary_visible": true, "title_keywords": ["asst. manager", "manager"], "responsibilities": ["business plan", "ad hoc projects", "coordinate"], "requirements": {"degrees": ["degree", "bachelor"], "majors": [], "languages": ["cantonese", "putonghua", "english", "chinese"], "language_level": ["good command"], "hard_skills": [], "soft_skills": ["flexible", "open-minded", "decisive", "well-organized"], "languages_combined": [{"language": "cantonese", "language_level": ["good command"]}, {"language": "putonghua", "language_level": ["good command"]}, {"language": "english", "language_level": ["good command"]}, {"language": "chinese", "language_level": ["good command"]}]}, "experience_required": {"duration": ["5 years", "at least 2 years"], "field": ["management"]}}, {"job_id": "100003009052607", "location_code": "hk", "company": "STA Pacific Limited", "job_title": "General Manager, Clinical operations", "description": "Responsibilities:\n\nAssist in managing the daily operations of a portfolio of cleaning service contracts\nAct as a business partner to develop and maintain relationships with clients\nLead the team for cleaning operations and management of operational workflows in order to maximize the operation efficiency and effectiveness\n\nRequirements:\n\nForm 5 or above\nMinimum 2 years' supervisory experience in cleaning industry\nStrong leadership and interpersonal skills\nSelf-motivated, customer oriented, proactive and independent\nGood team player with strong sense of responsibility and commitment\nProficiency in MS Office applications\n\n\n\nWe treasure human resources as our most valuable asset. We offer attractive remuneration package and career advancement opportunities to the right candidate. Interested parties please send full resume with your present and expected salary by one of the following means:\n\nMail\u00a0 : Unit 813, 8/F, Chevalier Commercial Centre, 8 Wang Hoi Road, Kowloon Bay, Kowloon\n\nEmail : Click 'Apply Now' or whhr @waihong.com.hk\u00a0\n\nPlease quote our reference no. on envelop or subject line of the email.\u00a0\n\nWaihong is an equal opportunity employer and welcomes applications from all qualified candidates. Personal data provided by job applicants will be used strictly in accordance with the employer's personal data policies, a copy of which will be provided immediately upon request.\n\n\u8077\u8cac\u00a0:\u00a0\n\n\u5354\u52a9\u7ba1\u7406\u53ca\u76e3\u5bdf\u5408\u7d04\u5de5\u5730\u7684\u65e5\u5e38\u6e05\u6f54\u904b\u4f5c\n\u8207\u5ba2\u6236\u5efa\u7acb\u4e26\u4fdd\u6301\u7dca\u5bc6\u7684\u5408\u4f5c\u95dc\u4fc2\uff0c\u63d0\u6607\u5ba2\u6236\u670d\u52d9\u8cea\u7d20\n\u63d0\u51fa\u5efa\u8b70\u512a\u5316\u65e5\u5e38\u904b\u4f5c\u7a0b\u5e8f\u4ee5\u63d0\u9ad8\u71df\u904b\u6548\u7387\n\n\u00a0\u5b78\u6b77\u8981\u6c42\u00a0:\u00a0\n\n\u4e2d\u4e94\u7562\u696d\u6216\u4ee5\u4e0a\u7a0b\u5ea6\n\u5169\u5e74\u6216\u4ee5\u4e0a\u6e05\u6f54\u670d\u52d9\u6027\u884c\u696d\u7d93\u9a57\n\u64c1\u6709\u826f\u597d\u7684\u5ba2\u6236\u670d\u52d9\u53ca\u6e9d\u901a\u6280\u5de7\u3001\u5177\u9818\u5c0e\u624d\u80fd\u4e26\u80fd\u7368\u7acb\u8655\u7406\u65e5\u5e38\u71df\u904b\u4e8b\u5b9c\n\u826f\u597d\u5718\u968a\u7cbe\u795e\u3001\u4e3b\u52d5\u53ca\u5177\u8cac\u4efb\u611f\n\u61c2\u5f97\u904b\u7528\u4e00\u822c\u96fb\u8166\u61c9\u7528\u8edf\u4ef6\uff0c\u5982Word, Excel\u7b49\n\n\u00a0\u6211\u5011\u91cd\u8996\u4eba\u624d\uff0c\u8996\u54e1\u5de5\u70ba\u6700\u73cd\u8cb4\u7684\u4eba\u529b\u8cc7\u7522\u3002\u6211\u5011\u63d0\u4f9b\u512a\u539a\u5f85\u9047\u53ca\u826f\u597d\u7684\u6649\u5347\u548c\u767c\u5c55\u6a5f\u6703\u4e88\u5408\u9069\u7684\u61c9\u5fb5\u8005\u3002\u6709\u610f\u61c9\u5fb5\u4e0a\u8ff0\u8077\u4f4d\u8005\uff0c\u6b61\u8fce\u7d93\u7531\u4e0b\u5217\u4efb\u4f55\u9014\u5f91\u905e\u4ea4\u500b\u4eba\u5c65\u6b77\u3001\u73fe\u6642\u53ca\u8981\u6c42\u4e4b\u5f85\u9047\u81f3\u672c\u516c\u53f8\u4eba\u529b\u8cc7\u672c\u53ca\u57f9\u8a13\u90e8\uff1a\u00a0\n\n\u90f5\u5bc4\uff1a\u4e5d\u9f8d\u4e5d\u9f8d\u7063\u5b8f\u958b\u90538\u865f\u5176\u58eb\u5546\u696d\u4e2d\u5fc38\u6a13813\u5ba4\n\n\u96fb\u90f5\uff1a\u6309\"Apply Now\" \u6216 whhr @waihong.com.hk\n\n\u00a0\u8acb\u65bc\u96fb\u90f5\u4e3b\u984c\u6216\u4fe1\u5c01\u5c01\u9762\u4e00\u6b04\u8a3b\u660e\u8077\u4f4d\u7684\u53c3\u8003\u7de8\u865f\u3002\n\n\u60e0\u5eb7\u74b0\u5883\u670d\u52d9\u6709\u9650\u516c\u53f8\u662f\u4e00\u500b\u5e73\u7b49\u6a5f\u6703\u50f1\u4e3b\uff0c\u6b61\u8fce\u4efb\u4f55\u7b26\u5408\u8981\u6c42\u7684\u4eba\u58eb\u7533\u8acb\u672c\u516c\u53f8\u4e4b\u8077\u4f4d\u3002\u00a0\u672c\u516c\u53f8\u540c\u6642\u56b4\u683c\u9075\u5b88\u500b\u4eba\u8cc7\u6599\uff08\u79c1\u96b1\uff09\u689d\u4f8b\u4e4b\u898f\u5b9a\uff0c\u6240\u6709\u61c9\u5fb5\u8005\u63d0\u4f9b\u7684\u500b\u4eba\u8cc7\u6599\u7d55\u5c0d\u4fdd\u5bc6\uff0c\u4e26\u53ea\u4f5c\u8207\u62db\u8058\u6709\u95dc\u4e4b\u7528\u9014\u3002\u5018\u6709\u9700\u8981\uff0c\u61c9\u5fb5\u8005\u53ef\u5411\u672c\u516c\u53f8\u7d22\u53d6\u6709\u95dc\u653f\u7b56\u4e4b\u8907\u672c\u3002\u00a0", "employment_types": ["Full Time", "Permanent"], "selling_points": ["Leadership management to clinical services", "Oversee clinical operations ansd", "Registerd Nurse with strong business acumen"], "locations": ["Not Specified"], "categories": ["Management", "General Management", "Medical Services", "Nursing"], "post_time": "2022-01-17T03:31:29Z", "salary": {"currency": null, "max": null, "min": null, "period": "monthly", "term": null}, "salary_visible": false, "title_keywords": ["operations", "general manager"], "responsibilities": ["maintain relationships", "management", "service contracts", "operations", "develop", "daily operations", "cleaning"], "requirements": {"degrees": ["form 5 or above"], "majors": [], "languages": [], "language_level": [], "hard_skills": ["ms office"], "soft_skills": ["self-motivated", "good team player", "independent", "sense of responsibility", "interpersonal skills", "proactive", "leadership"], "languages_combined": []}, "experience_required": {"duration": ["minimum 2 years"], "field": ["supervisory experience"]}}, {"job_id": "100003009052013", "location_code": "hk", "company": "TDMALL (Hong Kong) Limited", "job_title": "Operation Manager (Chinese Medicine Clinic)", "description": "\u5de5\u4f5c\u5167\u5bb9\uff1a1.\u8ca0\u8cac\u57f9\u8a13\u9805\u76ee\u7522\u54c1\u8a2d\u8a08\u548c\u958b\u5c55\u3002\u5305\u62ec\u8207\u5408\u4f5c\u5925\u4f34\u7684\u6e9d\u901a\u3001\u8a2d\u8a08\u548c\u7c3d\u8a02\u9805\u76ee\u5408\u4f5c\u5354\u8b70\u53ca\u57f7\u884c\uff1b\n2.\u5c0d\u9805\u76ee\u7684\u610f\u7fa9\u548c\u958b\u5c55\u65b9\u5f0f\u9032\u884c\u8ad6\u8b49\u548c\u982d\u8166\u98a8\u66b4\uff0c\u548c\u4f86\u81ea\u4e16\u754c\u5404\u5730\u7684\u5408\u4f5c\u5925\u4f34\u9032\u884c\u7d93\u5e38\u6027\u7684\u6e9d\u901a\uff1b\n3.\u8ca0\u8cac\u8ab2\u7a0b\u7684\u8abf\u7814\u53ca\u8a55\u4f30\uff0c\u5354\u52a9\u9032\u884c\u65b9\u6848\u7684\u8a2d\u8a08\u548c\u5ba3\u50b3\u5de5\u4f5c\u3002\n4.\u8ca0\u8cac\u5c0d\u5916\u6e9d\u901a\u7684\u884c\u653f\u6027\u4e8b\u52d9\u3002\n\u5de5\u4f5c\u8981\u6c42\uff1a1. \u5728\u7522\u54c1\u8a2d\u8a08\u53ca\u9805\u76ee\u7ba1\u7406\u9818\u57df\u6709\u4e00\u5b9a\u7684\u7d93\u9a57\uff1b\uff08\u689d\u4ef6\u512a\u79c0\u8005\u53ef\u9069\u7576\u653e\u5bec\uff09\n2. \u6709\u8f03\u5f37\u7684\u6297\u58d3\u80fd\u529b\uff0c\u80fd\u7368\u7acb\u5b8c\u6210\u4efb\u52d9\uff0c\u6709\u5f37\u70c8\u7684\u8cac\u4efb\u5fc3\uff0c\u559c\u6b61\u6709\u6fc0\u60c5\u548c\u6709\u6311\u6230\u6027\u7684\u5de5\u4f5c\uff1b\n3. \u6709\u7522\u54c1\u7684\u908f\u8f2f\u548c\u601d\u8def\uff0c\u5c0d\u6642\u9593\u7bc0\u9ede\u6709\u826f\u597d\u7684\u628a\u63e1\uff1b\n4. \u6211\u5011\u7279\u5225\u6b23\u8cde\u548c\u6b61\u8fce\u5bcc\u6709\u539f\u5247\u548c\u4e3b\u898b\u3001\u5805\u6301\u4e0d\u61c8\u3001\u4e0d\u70ba\u7d30\u7bc0\u59a5\u5354\u3001\u5bcc\u6709\u5145\u6c9b\u7684\u5275\u9020\u529b\u548c\u60f3\u8c61\u529b\u7684\u540c\u4e8b\u8207\u6211\u5011\u4e00\u9053\u524d\u884c\uff1b\n5. \u672c\u79d1\u53ca\u4ee5\u4e0a\u5b78\u6b77\uff08\u5c0d\u5c08\u696d\u4e0d\u8981\u6c42\uff09\uff1b\n6. \u82f1\u6587\u6d41\u5229\u3002", "employment_types": ["Full Time", "Permanent"], "selling_points": [], "locations": ["Central & Western Area"], "categories": ["Sales, CS & Business Devpt", "Business Development", "Management", "General Management"], "post_time": "2022-01-17T01:50:32Z", "salary": {"currency": null, "max": null, "min": null, "period": "monthly", "term": null}, "salary_visible": false, "title_keywords": ["operation manager"], "responsibilities": [], "requirements": {"degrees": [], "majors": [], "languages": [], "language_level": [], "hard_skills": [], "soft_skills": [], "languages_combined": []}, "experience_required": {"duration": [], "field": []}}, {"job_id": "100003009055946", "location_code": "hk", "company": "Waihong Environmental Services Limited", "job_title": "Assistant Operations Manager (Ref: OPS0101)", "description": "Full Africa\u00a0International Ltd, is\u00a0a gold trading and investment holding company\u00a0located\u00a0at Wanchai, is now inviting high caliber candidate to join us.\n\nMain Responsibilities\n\nReport to Director\n-To oversee all-around activities related to gold trading business including HK, PRC & Africa.\n-To contribute business planning, develop business strategies and make consistent with company\u2019s overall mission and long-term objectives.\n-To lead the sales & operations teams to develop company\u2019s sales force and achieve sales & profit goals.\n-To keep abreast of market development and competitors movement.\n\nJob Requirements & Qualification:\n\n-Bachelor degree in business management field or equivalent.\n-Minimum 10years\u2019 working experience in related position.\n-Strong management skill, self-motivated & excellent communication and interpersonal skills.\n-Proficient in Putonghua and English.", "employment_types": ["Full Time", "Permanent"], "selling_points": [], "locations": ["Not Specified"], "categories": ["Management", "General Management", "Property / Real Estate", "Property Management", "Others", "Others"], "post_time": "2022-01-18T03:07:17Z", "salary": {"currency": null, "max": null, "min": null, "period": "monthly", "term": null}, "salary_visible": false, "title_keywords": ["assistant operations manager"], "responsibilities": ["operations", "teams", "develop", "report", "planning"], "requirements": {"degrees": ["degree"], "majors": ["business"], "languages": ["putonghua", "english"], "language_level": [], "hard_skills": ["business management"], "soft_skills": ["self-motivated", "communication and interpersonal skills"], "languages_combined": [{"language": "putonghua", "language_level": []}, {"language": "english", "language_level": []}]}, "experience_required": {"duration": [], "field": ["related"]}}, {"job_id": "100003009053483", "location_code": "hk", "company": "\u6df1\u5733\u5e02\u745e\u4e2d\u5353\u8d8a\u570b\u969b\u767c\u5c55\u6709\u9650\u516c\u53f8", "job_title": "NDC\u570b\u969b\u9805\u76ee\u7522\u54c1\u7d93\u7406", "description": "Reporting to Senior Management, the incumbent will be responsible for the\u00a0Business Development functions include identifying customer markets, monitoring industry trends, conducting competitor analyses and crafting business plans with the aim to determine ideal market opportunities to pursue and introduce new lifestyle and sports brands to Asia under distribution/ joint-venture / franchising / other suitable models.\u00a0\n\nResponsibilities\n\nConduct market research and analysis to identify customer markets, monitor industry trends, conduct competitor analyses to drive business opportunities\nAssist in developing business proposals and participate in new business pitches for targeted brands and future business collaboration\nAssist in Company\u2019s branding and media communication activities e,g, press releases, corporate marketing collaterals and website, etc.\nSupport senior management on preparing business presentation materials and internal / external communications materials such as press materials related to corporate-level etc.\nParticipate in operational analysis and special corporate projects\n\nRequirements\n\nUniversity graduate with 3 years\u2019\u00a0 working experience in business analysis, business development or consultancy\nStrong numeric and business acumen\nGood interpersonal & presentation skills\nProactive, energetic, dynamic and with genuine passion in retail industry\nAttentive to details and with multi-tasking capability\nStrong oral and written communication in English, Mandarin and Cantonese\nExcellent command of\u00a0 Microsoft office application including PowerPoint, Excel and Word\n\nWe offer competitive remuneration package with\u00a0a wide range of fringe benefits including\n\n5-day work week\nDiscretionary Bonus\nComprehensive Medical Coverage\nStaff Shopping Discount\nNon-contributory Retirement Benefits Scheme\nBirthday Leave\n\nInterested parties please send resume with present and expected salary to Human Resources Department, Swire Resources Limited,\u00a012/F Kingston International Centre, 19 Wang Chiu Road Kowloon Bay, Hong Kong or by\u00a0clicking the below \"Apply Now\" button.\n\nSwire Resources Limited is Equal Opportunity Employer\n", "employment_types": ["Full Time"], "selling_points": ["\u826f\u597d\u6649\u5347\u6e20\u9053", "\u4e94\u96aa\u4e00\u91d1", "\u6e2f\u6fb3\u4eba\u624d\u5c08\u9805\u670d\u52d9"], "locations": ["Others - China"], "categories": ["Management", "General Management"], "post_time": "2022-01-17T07:02:25Z", "salary": {"currency": null, "max": null, "min": null, "period": "monthly", "term": null}, "salary_visible": false, "title_keywords": [], "responsibilities": ["conduct market research", "analysis", "monitor", "business opportunities", "developing", "marketing collaterals", "communication", "website", "senior management"], "requirements": {"degrees": ["university graduate"], "majors": ["business"], "languages": ["cantonese", "english", "mandarin"], "language_level": [], "hard_skills": ["excel", "microsoft office", "analysis", "word", "powerpoint", "dynamic", "acumen"], "soft_skills": ["oral", "attentive to details", "passion in", "genuine", "communication", "presentation skills", "energetic", "dynamic", "multi-tasking", "business acumen", "proactive", "interpersonal"], "languages_combined": [{"language": "cantonese", "language_level": []}, {"language": "english", "language_level": []}, {"language": "mandarin", "language_level": []}]}, "experience_required": {"duration": ["3 years"], "field": ["business analysis", "business development"]}}, {"job_id": "100003009053121", "location_code": "hk", "company": "Konew Financial Express Ltd", "job_title": "Manager, Branch Development", "description": "Our client is a renowned medical group. They are looking for a passionate professional to join their senior team.\n\nKey Responsibilities:\u00a0\n\nBe able to demonstrate extensive leadership & accountability in driving quality patient service delivery in accordance with professional nursing / clinical standards & compliance\u00a0\nProvide guidance and support to clinical functional heads in relation to clinical governance & practices, quality standards, resource prioritization & continuous improvement to achieve outcomes & targets in line with the Hospital strategic plans\u00a0\nAnalyze & evaluate overall clinical operations, formulate policies & procedures, initiate clinical service enhancement, identify needs of policy change, areas of potential cost savings, provide recommendation & expertise support to senior management.\u00a0\nOversee staff development in clinical operations\u00a0\n\nRequirement:\n\nRegistered Nurse with a current practicing certificate\u00a0\nMin 8 years of solid experience in relevant managerial positions and with extensive knowledge in front line clinical service delivery\u00a0\nPositive attitude & self-motivation to develop & integrate new initiatives for effective and efficient cross-functional collaboration on patient service processes\u00a0\nStrong business acumen with demonstrated skills in identifying opportunities for improvement and innovation in clinical services\u00a0\nTraining / experience in audit / accreditation processes is an advantage\u00a0\nBilingual in English & Cantonese communication\u00a0\n\nInterested parties please send your CV by clicking \"Apply Now\". All personal information will be used strictly for recruitment purpose.\u00a0 Please assume your application has not been successful if you have not heard from us in two weeks' time", "employment_types": ["Full Time", "Permanent"], "selling_points": ["Branch strategic development", "Supervise and coach a team", "Oversee and support all branches\u2019 daily operations"], "locations": ["Central"], "categories": ["Sales, CS & Business Devpt", "Business Development", "Management", "General Management", "Sales - Sales Management"], "post_time": "2022-01-17T05:56:30Z", "salary": {"currency": null, "max": null, "min": null, "period": "monthly", "term": null}, "salary_visible": false, "title_keywords": ["manager"], "responsibilities": ["service delivery", "cost", "strategic plans", "operations", "policies", "compliance", "quality", "procedures", "evaluate", "provide recommendation", "senior management", "provide guidance"], "requirements": {"degrees": ["certificate"], "majors": [], "languages": ["cantonese", "english"], "language_level": [], "hard_skills": ["acumen"], "soft_skills": ["efficient", "positive attitude", "communication", "self-motivation", "business acumen", "patient", "extensive"], "languages_combined": [{"language": "cantonese", "language_level": []}, {"language": "english", "language_level": []}]}, "experience_required": {"duration": ["min 8 years"], "field": ["managerial", "training", "audit", "clinical"]}}, {"job_id": "100003009054956", "location_code": "hk", "company": "Pearl Lam Galleries Limited", "job_title": "Assistant Gallery Manager", "description": "Main Duties & Responsibilities:\n\n\nFormulate branch strategic plan in line with our business development needs\nDevice effective branch network capacity planning strategy and mechanism to deliver the company\u2019s business and customer segmentation strategy\nOversee and support all branches\u2019 daily operations, including but not limited to handle loan applications and handle customer enquiries when necessary\nSupervise and coach the branch team to perform their tasks in a professional way in order to enhance the sales achievement and productivity of branch staff\nHandle ad hoc tasks as assigned from time to time\n\nRequirements:\n\nBachelor degree or above in business related disciplines, or equivalent\nMinimum 8 years' relevant working experience in financial service industry, including 3 years' experience in a managerial capacity overseeing branch operations is a must\u00a0\nExperience in leading strategic projects for branch development is an advantage\nProven sales record in mortgage or personal loan achievement\nSound knowledge of financial market, mortgage or personal loan products\nAble to handle multi-tasks and meet tight deadlines\nStrong leadership, coaching, communications and interpersonal skills\nIndependent, proactive and attentive to details\nMature, able to work under pressure with strong sense of confidentially\nCandidates with more experience will be considered as Senior Manager\n\nWe offer:\n\nDiscretionary bonus\nMedical insurance\nDental insurance\nHardship allowance\nCompetitive annual leave days\nBirthday leave\nAnniversary leave\nPerformance reward days\nStudy leave\nMarriage leave\nCompassionate leave\n\nHow to apply:\n\nInterested parties, please send your resume stating your expected salary to Human Capital Department\u00a0by clicking \"APPLY NOW\".\n\n(We are an equal opportunity employer.\u00a0 Personal data collected will be used for recruitment purpose only.\u00a0 The unsuccessful applications will be destroyed after 6 months.)", "employment_types": ["Full Time", "Permanent"], "selling_points": ["Assistant Art Gallery Manager", "Personal Assistant", "Executive Secretary"], "locations": ["Central"], "categories": ["Management", "General Management"], "post_time": "2022-01-17T15:02:17Z", "salary": {"currency": "HKD", "max": 19999, "min": 14000, "period": "monthly", "term": null}, "salary_visible": true, "title_keywords": ["manager", "assistant"], "responsibilities": ["handle customer enquiries", "ad hoc tasks", "daily operations", "plan", "planning"], "requirements": {"degrees": ["degree or above", "bachelor"], "majors": ["related disciplines", "business"], "languages": [], "language_level": [], "hard_skills": ["loan products"], "soft_skills": ["meet tight deadlines", "independent", "multi-tasks", "attentive to details", "mature", "interpersonal skills", "proactive", "leadership", "work under pressure"], "languages_combined": []}, "experience_required": {"duration": ["3 years", "minimum 8 years"], "field": ["managerial", "development", "relevant working experience", "service industry", "financial"]}}, {"job_id": "100003009055477", "location_code": "hk", "company": "Manpower Services (Hong Kong) Limited", "job_title": "Data Preparation Supervisor", "description": "Position overview:\n\nPearl Lam Galleries are looking for staff who with a focus in assisting the Senior Gallery Manager / Gallery Director.\u00a0 The position will demand someone who is keen to learn and can assist the Senior Gallery Manager / Gallery Director in all administrative duties including co-ordinations, shipping, logistics, registrar, HR, accounts, etc.\n\nFollowing a rigorous programme, Pearl Lam Galleries presents museum-quality exhibitions that re-evaluate and challenge perceptions of cultural practice in Asia.\u00a0 With a thoughtfully balanced roster of Chinese and international artists, the Gallery is strategic in it's curation, positioning itself as an educator.\u00a0 The Gallery's flagship space is located in the historic Pedder Building in Hong Kong whilst the Shanghai space lies in the heart of the Bund District.\u00a0 With a team of international staff, Pearl Lam Galleries' reach is global, having presentations at major international art fairs.\n\nWorking Days:\u00a0 Mon - Sat\nWorking Hours:\u00a0 10:00 - 19:00 (with one hour lunch time)\n\nAbout you:\nMinimum 4 years as Personal Assistant / Executive Secretary or related field\nSelf-motivated and takes immediate responsibility for the role and tasks\nCan work under pressure and multi-tasks with good temper and detailed minded\nExcellent in spoken and written English & Chinese (Traditional & Simplified Chinese)\nHighly organised and efficient team player who can work seamlessly with all departments\nProficiency in Apple Mac, Word, Adobe Photoshop, Illustrator, Premier.\nDress Code - BLACK", "employment_types": ["Contract"], "selling_points": ["1-2 years data preparation aggregate experience", "Bachelor\u2019s degree holder from a university in Hong", "Good command of written and spoken English, Chines"], "locations": ["Aberdeen"], "categories": ["Management", "General Management"], "post_time": "2022-01-18T02:38:16Z", "salary": {"currency": null, "max": null, "min": null, "period": "monthly", "term": null}, "salary_visible": false, "title_keywords": ["supervisor"], "responsibilities": ["sat", "shipping", "hr", "quality", "presentations", "evaluate", "logistics", "administrative duties", "work under pressure"], "requirements": {"degrees": [], "majors": [], "languages": ["english", "chinese"], "language_level": ["excellent"], "hard_skills": ["pearl", "adobe photoshop", "word", "presentations", "illustrator", "code", "focus"], "soft_skills": ["efficient", "self-motivated", "multi-tasks", "keen", "detailed", "team player", "organised", "focus", "work under pressure"], "languages_combined": [{"language": "english", "language_level": ["excellent"]}, {"language": "chinese", "language_level": ["excellent"]}]}, "experience_required": {"duration": [], "field": []}}, {"job_id": "100003009052929", "location_code": "hk", "company": "Flora Floriculture Limited", "job_title": "Flower Shop Manager", "description": "Date: Late March\n\nTime: 0730-2300 (8 hours per shift)\nSalary: Negotiable\n\n\nDuties:\n\n-Lead and manage the work of Support Staff; Produce list of confines regularly;\n\n-Liaise with and handle request and enquiries from different parties,etc.\nRequirement:\n-Bachelor\u2019s degree holder from a university in Hong Kong or equivalent;\n-Have 1-2 years data preparation aggregate experience\n-Good command of written and spoken English, Chinese & Mandarin\n\n\n**Apply with your Resume, all Job & Education certificates", "employment_types": ["Full Time"], "selling_points": [], "locations": ["Sheung Wan"], "categories": ["Management", "General Management"], "post_time": "2022-01-17T04:34:29Z", "salary": {"currency": "HKD", "max": 29999, "min": 20000, "period": "monthly", "term": null}, "salary_visible": true, "title_keywords": ["shop manager"], "responsibilities": [], "requirements": {"degrees": ["degree holder"], "majors": [], "languages": ["english", "chinese", "mandarin"], "language_level": [], "hard_skills": [], "soft_skills": [], "languages_combined": [{"language": "english", "language_level": []}, {"language": "chinese", "language_level": []}, {"language": "mandarin", "language_level": []}]}, "experience_required": {"duration": ["1-2 years"], "field": []}}, {"job_id": "100003009054079", "location_code": "hk", "company": "The Translation Business", "job_title": "Assistant Manager \u2013 Client Support", "description": "Job Highlights\nManaging a flower shop\nSecondary education or above\nExperience in hospitality / flower shop management\nJob Description\n\nJob Duties\n\n* To manage and supervise the operation of the shop, including:\n\n* To purchase goods from different suppliers to support sales operation\n\n* Inventory and cost control\n\n* To maintain and improve profitability\n\n* To organize workflow to staff\n\n* To arrange manpower for daily operation\n\n* To design attractive appearance for both the interior and exterior\u00a0\n\nWork location: Sheung Wan\n\nFull-time working hours: 5.5 days/week\n09:00-19:00 (Mon \u2013 Fri)\n09:00-13:00 (Sat)\nOvertime work may be needed\n\nJob Requirements\n\n*\u00a0Secondary education or above, with a pass in both Chines and English\n\n* Good communication and interpersonal skills\n\n* Smart, able to work independently and proactively\n\n* With excellent sense of responsibility\n\n* Hardworking and passionate\n\n* Willing to learn\n\n* Experience in flower shop or hospitality management is preferred\n\nSalary: 20k-30k (depends on experience)\nLocation: Sheung Wan (1 minute walk from MTR)\n\nAll personal data collected will be used for recruitment purpose only will be treated in accordance with our Personal Data Policy, which is available immediately upon request.", "employment_types": ["Full Time", "Permanent"], "selling_points": [], "locations": ["Ngau Tau Kok"], "categories": ["Management", "General Management"], "post_time": "2022-01-17T16:21:02Z", "salary": {"currency": null, "max": null, "min": null, "period": "monthly", "term": null}, "salary_visible": false, "title_keywords": ["assistant manager"], "responsibilities": ["inventory", "daily operation", "design", "purchase", "maintain", "cost control"], "requirements": {"degrees": [], "majors": [], "languages": [], "language_level": [], "hard_skills": [], "soft_skills": [], "languages_combined": []}, "experience_required": {"duration": [], "field": []}}, {"job_id": "100003009055431", "location_code": "hk", "company": "Network Direct Promotion Limited", "job_title": "Key account officer (Managed Print Service)", "description": "Key Responsibilities include:\n\nTo liaise\u00a0and\u00a0coordinate\u00a0both internal and external parties on project management\nTo provide support to clients\u00a0by responding to their enquiries and ensure efficient service delivery\u00a0\nTo provide technical support to\u00a0linguists\u00a0to facilitate the production process\u00a0\nTo provide IT help desk support\u00a0\nTo handle accounts entries and bank reconciliation\u00a0\u00a0\nTo provide\u00a0a\u00a0full\u00a0range of\u00a0administrative\u00a0support\u00a0to\u00a0the\u00a0Operations\u00a0Manager to facilitate smooth operation of the business process\u00a0\n\nWhat we look for in the candidates:\n\nDiploma / Associate degree or above\u00a0\nAt least 2 years relevant working experience\u00a0\nStrong in Microsoft Office, Adobe Acrobat Pro DC\u00a0and\u00a0English/Chinese Word Processing\u00a0\nExperience in MS Windows\u00a010\u00a0and\u00a0PC hardware/software\u00a0\nKnowledgeable in computerized accounting system\u00a0\nGood command of spoken/written English and Chinese\u00a0\nGood\u00a0communication\u00a0and\u00a0time management skills with the ability to multi-task under tight deadlines\u00a0\nSelf-motivated,\u00a0independent,\u00a0well-organized\u00a0and willing to learn\u00a0\n\nCandidate(s) with less experience will be considered.\n\nInterested parties please send applications with expected salary by email. We offer candidates intensive training opportunities and an attractive remuneration package.\u00a0\n\nAll information collected is for recruitment purpose only.", "employment_types": ["Full Time"], "selling_points": ["Client Manager", "Client Service Officer", "(Managed Print Services)"], "locations": ["Not Specified"], "categories": ["Sales, CS & Business Devpt", "Customer Service - Supervisor / Officer", "Management", "General Management", "Marketing / Public Relations", "Others"], "post_time": "2022-01-18T02:34:07Z", "salary": {"currency": null, "max": null, "min": null, "period": "monthly", "term": null}, "salary_visible": false, "title_keywords": ["officer"], "responsibilities": ["liaise", "service delivery", "provide support", "management", "production process", "software", "administrative support", "technical support", "operations", "internal and external parties", "bank reconciliation", "coordinate", "project management", "hardware", "business process", "communication"], "requirements": {"degrees": ["diploma", "degree or above"], "majors": [], "languages": ["english", "chinese"], "language_level": ["good command"], "hard_skills": ["chinese word processing", "help desk support", "microsoft office", "ms windows", "project management", "hardware", "accounting system", "dc", "pc", "adobe acrobat"], "soft_skills": ["efficient", "self-motivated", "multi-task", "independent", "time management skills", "well-organized", "willing to learn", "communication", "project management", "smooth"], "languages_combined": [{"language": "english", "language_level": ["good command"]}, {"language": "chinese", "language_level": ["good command"]}]}, "experience_required": {"duration": ["at least 2 years"], "field": ["relevant working experience"]}}, {"job_id": "100003009055905", "location_code": "hk", "company": "Baguio Green Group Limited", "job_title": "Plastic Recycling Site Manager", "description": "Job Highlights:\n\n\u2022 Top multinational IT Company\n\n\u2022 Cabin Crew candidates are welcomed\n\n\u2022 Immediately available preferred\n\n\u2022 5 days of work per week\n\nJob Description:\n\nOur Client is an American multinational information technology company listed in U.S. who is seeking a Client Manager / Client Service Officer for their Managed Print Services.\n\nResponsibilities:\n\n\u2022 Manage account operation activities and escalations to maintain and build excellent relationship with client\n\n\u2022 As a contact and escalation point between customers and other support teams\n\n\u2022 This is not a quota baring sales role, but you have to build understanding and knowledge of client business and needs to identify up-sell & cross-sell opportunities and drive contract renewal with sales team\n\n\u2022 Prepare PO, report, contract and invoicing related document\n\n\u2022 Closely engage and liaise with other delivery team to ensure the timely and cost-effective delivery whilst managing delivery scope and resources\n\n\u00a0Requirement:\n\n\u2022 Cabin Crew candidates are welcomed to apply\n\n\u2022 Tertiary education in Business Management / Computer Science / or related disciplines\n\n\u2022 2 year or above of account management or customer services experience\n\n\u2022 Good communication skill and a trusted advisor to the customer\n\n\u2022 Fluent in Cantonese and English, Verbal and written\n\n\u2022 Positive thinking, customer-oriented with good interpersonal skills \u2022 PC literacy: MS Office - Excel & PowerPoint\n\n\u00a0\n\u2022 Applicants with more experiences will be considered for senior position\n\n\u2022Immediately available preferred\n\n\u2022 We offer career prospect, attractive remuneration and fringe benefits including but not limited to the followings:\n\n\u2013 15 days' annual leave\n\n\u2013\u00a05 days\u2019 work week & bank holiday\n\n\u2013 Clinical, hospitalization and dental insurance\n\n\n\n\u6709\u610f\u61c9\u5fb5\u8005\uff0c\u8acb\u5c07\u500b\u4eba\u5c65\u6b77\u4e26\u8a3b\u660e\u73fe\u6642\u85aa\u91d1\u3001\u8981\u6c42\u5f85\u9047\u53ca\u53ef\u5230\u8077\u65e5\u671f\uff0c\u81f4\u96fb \u6216\u00a0Whatsapp\u00a0\u5f6d\u5c0f\u59d0\u00a05174 7979\u4eba\u529b\u8cc7\u6e90\u90e8\u9810\u7d04\u9762\u8a66\u3002\n\n\n\n(\u7533\u8acb\u4eba\u6240\u63d0\u4f9b\u7684\u8cc7\u6599\u7d55\u5c0d\u4fdd\u5bc6\uff0c\u4e26\u53ea\u4f5c\u62db\u8058\u6709\u95dc\u7684\u7528\u9014\u3002", "employment_types": ["Full Time", "Permanent"], "selling_points": ["Minimum 5-8 years' relevant experience", "Friendly working environment, Work life balance", "16+AL, 5-day work, Birthday Leave etc."], "locations": ["Lai Chi Kok"], "categories": ["Sales, CS & Business Devpt", "Business Development", "Management", "General Management", "Marketing / Public Relations", "Marketing - Brand / Product Management"], "post_time": "2022-01-18T03:04:28Z", "salary": {"currency": null, "max": null, "min": null, "period": "monthly", "term": null}, "salary_visible": false, "title_keywords": ["manager"], "responsibilities": ["cost", "teams", "invoicing", "maintain", "sales team", "contact", "liaise with", "report"], "requirements": {"degrees": [], "majors": [], "languages": ["cantonese", "english"], "language_level": ["fluent"], "hard_skills": ["business management", "excel", "powerpoint", "pc", "ms office"], "soft_skills": ["customer-oriented", "communication skill", "interpersonal skills", "positive thinking"], "languages_combined": [{"language": "cantonese", "language_level": ["fluent"]}, {"language": "english", "language_level": ["fluent"]}]}, "experience_required": {"duration": ["2 year"], "field": ["account management", "customer services"]}}, {"job_id": "100003009053836", "location_code": "hk", "company": "Konew Financial Express Ltd", "job_title": "Sales Manager, SME", "description": "SCOPE\n\nTo manage and direct the waste and recycling production line, maintenance, repair and improvement of all systems and plants relative to the physical well being and performance of the recycling and sorting factory, under the direction of General Manager and within the guideline of the Group.\n\nPRIMARY RESPONSIBILITIES\n\nTo ensure that all Group policies & procedures are followed and implemented accordingly.\nTo ensure that all local and national statutory regulations pertaining to recycling and sorting practices are adhered and compliance.\nExplore the use of smart technologies / AI to drive continuous improvement of each waste and plastic recycling site.\nTo ensure that all recycling machine are well adjusted, perform and to maximum the productivity.\nTo ensure effective communication between the management and the department and provide a professional, advisory, and executive support service to the General Manager to formulate strategic goals and plan for the production line.\nTo establish contact and good rapport with local authorities; fire bureau, health & hygiene, environment protection, Power plant, water supply, etc.\nTo establish and maintain good working relationships with local contractors who will provide repair and maintenance service, especially during the emergency breakdown of the system.\nTo determine and maintain organizational structure, job descriptions and standards & procedures for the department, and update and review annually. To plan and conduct on the job training, planning for the engineering long term training program.\nTo recruit, institute and develop training programs for all colleagues.\nTo facilitate and promote multitasking among colleagues.\nTo supervise, evaluate colleague\u2019s performance.\nTo prepare and manage a cost-effective operating budget to cover the cost of all maintenance, utilities within the financial parameters set down by the Group budget.\nMade a special capital budget recommendation to include all changes, replacement, and upgrade of equipment required\u3002\nTo develop, implement and maintain a work order system to address routine repairs. Work order procedures developed must address requesting work, reporting work, recording, assignment planning, scheduling, execution, follow up, communication/feedback of work done and historical record keeping.\nTo develop, implement and maintain a preventive maintenance program on all systems, plants, and various architectural features. Program to ensure operation of property is safe, effective and efficient.\nTo develop, implement and maintain energy conservation, tracking program to minimize utility expenses.\nTo regularly reviews and renegotiate as necessary all outside service contracts in areas of responsibility.\nTo maintains and updates all property records, technical drawings, manuals, administrative files, etc.\nTo perform other tasks and duties as assigned by management.\nconduct on-site orientation to new associate and responsible for staff training\n\nQUALIFICATIONS\n\n\nEducation:\n\n\nFormal education from technical institute, preferably with diploma or degree qualification in engineering/computerizing\n\n\n\u00a0Certification:\n\nHigher Diploma or Certificate holder in Building Services, Mechanical Engineering or Electrical Engineering or computerizing or equivalent.\n\nExperience:\n\nMin 8 years working experience in similar capacity, experience in PET recycling production line set up\n\nExperience in Recycling Plant/Factory set up\n\nExperience in plastic recycling\n\n\nExperience in Environment facilities industry\n\nOther:\n\n\nProficient in Microsoft Office Good command of written and spoken English and Chinese.\n\nProblem solving skills.\n\nManagement skills\n\nFor interested parties, please send your full resume with availability, current and expected salary to us. Data collected will be used for recruitment purpose only.", "employment_types": ["Full Time", "Permanent"], "selling_points": ["SME strategic development", "Supervise and coach a team", "Minimum 8 years relevant experience"], "locations": ["Central"], "categories": ["Sales, CS & Business Devpt", "Business Development", "Management", "General Management", "Sales - Sales Management"], "post_time": "2022-01-17T07:36:08Z", "salary": {"currency": null, "max": null, "min": null, "period": "monthly", "term": null}, "salary_visible": false, "title_keywords": ["sales manager"], "responsibilities": ["regulations", "budget", "executive support", "communication", "maintain", "technical drawings", "plan", "compliance", "expenses", "develop", "other tasks", "reporting", "management", "cost", "service contracts", "review", "procedures", "hygiene", "scheduling", "contact", "tracking", "maintenance", "policies", "systems", "evaluate", "repair", "working relationships", "planning"], "requirements": {"degrees": ["certificate", "diploma", "degree"], "majors": ["electrical engineering", "building services", "engineering", "mechanical engineering"], "languages": ["english", "chinese"], "language_level": ["good command", "proficient"], "hard_skills": ["maintenance", "microsoft office", "ai", "safe", "problem solving skills"], "soft_skills": ["efficient", "responsible", "organizational", "communication", "problem solving skills"], "languages_combined": [{"language": "english", "language_level": ["good command", "proficient"]}, {"language": "chinese", "language_level": ["good command", "proficient"]}]}, "experience_required": {"duration": ["min 8 years"], "field": []}}, {"job_id": "100003009044899", "location_code": "hk", "company": "Pet-Link Company Limited", "job_title": "Assistant General Manager", "description": "Main Duties & Responsibilities:\n\nSupervise and coach the SME team to perform their tasks in a professional way in order to enhance the sales achievement and productivity\nOversee all daily operations, including but not limited to loan application, handle customer enquiries, resolve issues, and prepare documents accurately\nDevice effective SME network capacity planning strategy and mechanism to deliver the company\u2019s business and customer segmentation strategy\nResponsible for the corporate loan business development and maintain good relationships with existing clients to grow revenue\nFormulate SME strategic plan in line with our business development needs\nProvide updated financial market information, professional advice, and high-quality services for SME clients to strengthen customer loyalty\nMaintain awareness of operational risks and adhere to relevant policies and compliance standards\nExecute any ad hoc duties as assigned\n\nRequirements:\n\n\nBachelor degree or above in Finance, Sales & Marketing or related disciplines\nMinimum 8-year relevant working experience in financial industry, including at least\u00a03 years' experience in a managerial / project management capacity; experience in branch operations would be an advantage\nProven sales record in SME loan achievement\nSound knowledge of financial market, mortgage or personal loan products\nAble to handle multi-tasks and meet tight deadlines\nStrong leadership, coaching, communications and interpersonal skills\nIndependent, proactive and attentive to details\nMature, able to work under pressure with strong sense of confidentially\n\nWe offer:\n\nDiscretionary bonus\nMedical insurance\nDental insurance\nHardship allowance\nCompetitive annual leave days\nBirthday leave\nAnniversary leave\nPerformance reward days\nStudy leave\nMarriage leave\nCompassionate leave\n\nHow to apply:\n\nInterested parties, please send your resume stating your expected salary to Human Capital Department\u00a0by clicking \"APPLY NOW\".\n\n(We are an equal opportunity employer.\u00a0 Personal data collected will be used for recruitment purpose only.\u00a0 The unsuccessful applications will be destroyed after 6 months.)", "employment_types": ["Full Time", "Permanent"], "selling_points": [], "locations": ["Tai Po Area"], "categories": ["Management", "General Management", "Top Executives (CEO, CFO, CTO, GM, MD etc.)"], "post_time": "2022-01-13T06:35:06Z", "salary": {"currency": null, "max": null, "min": null, "period": "monthly", "term": null}, "salary_visible": false, "title_keywords": ["assistant general manager"], "responsibilities": ["ad hoc duties", "market information", "handle customer enquiries", "policies", "compliance", "quality", "daily operations", "maintain", "plan", "sme", "prepare documents", "planning"], "requirements": {"degrees": ["degree or above", "bachelor"], "majors": ["related disciplines", "finance", "marketing"], "languages": [], "language_level": [], "hard_skills": ["project management", "loan products"], "soft_skills": ["meet tight deadlines", "independent", "multi-tasks", "attentive to details", "mature", "project management", "interpersonal skills", "proactive", "leadership", "work under pressure"], "languages_combined": []}, "experience_required": {"duration": ["at least 3 years", "minimum 8-year"], "field": ["managerial", "project management", "financial industry", "relevant working experience"]}}, {"job_id": "100003009052646", "location_code": "hk", "company": "Headsearch21 Consultancy Ltd", "job_title": "EHS Manager (5 days / Manufacturing / 30-40K)", "description": "Responsibilities:\n\nSupport Managing Director/General Manager to monitor and execute the new business development and existing operations including new product development, RND, Merchant, Design, Sales & Marketing, Retail, Warehouse, Factory, Overseas trading and e-commerce.\nFormulate and implement annual business operating plans and budget to achieve annual\u00a0KPI target.\nProvide solid guidance and form a highly motivated and energetic team to achieve targets and company goals.\nManage overall P&L, cost & expenditure, policy & procedures of the Company.\nAny other ad-hoc assignments as assigned.\n\nRequirements:\n\nUniversity graduate in Business Management, Marketing or related discipline\nAt least 15 years of experience in the fields of FMCG industries, with minimum 5 years in senior management level, solid PRC experiences preferred.\nFlexibility and adaptability to face challenges in a growing organization\nExcellent business acumen, ability to convert the business strategy to operational implementation.\nAble to inspire, lead and manage the team to implement business strategies effectively.\nGood spoken and written in English and Mandarin.\nWilling to travel Overseas and PRC subject to the development of Covid-19.\n\nCompany website: https://www.pet-link.com\u00a0\u00a0https://eshop.iloverabbit.com/\n\nWe offer competitive salary remuneration package which included year-end KPI bonus, hardworking allowance, medical insurance, dental allowance, 14 days annual leave and staff purchase discount to the successful candidate.\n\nInterested applicants please email your detailed resume indicating your current, expected salary and also date of availability along with your relevant portfolio. Applicants without portfolio will not be considered.\n\n*All information provided will be treated in strict confidential and used only for recruitment purposes.\u00a0", "employment_types": ["Full Time", "Permanent"], "selling_points": ["Deg+4 yrs EHS exp (Environmental, Health & Safety)", "ISO14001 / Safety Management System", "Less experience --> Senior EHS Officer"], "locations": ["Not Specified"], "categories": ["Sciences, Lab, R&D", "Environmental Science / Waste Management", "Management", "General Management", "Manufacturing", "Quality Assurance, Control & Testing / ISO"], "post_time": "2022-01-17T03:43:11Z", "salary": {"currency": "HKD", "max": 44999, "min": 30000, "period": "monthly", "term": null}, "salary_visible": true, "title_keywords": ["manager"], "responsibilities": ["achieve targets", "guidance", "cost", "operations", "ad-hoc assignments", "budget", "monitor", "procedures", "design", "p&l", "plans"], "requirements": {"degrees": ["university graduate"], "majors": ["business", "marketing"], "languages": ["english", "mandarin"], "language_level": ["good"], "hard_skills": ["business management", "acumen"], "soft_skills": ["business acumen", "adaptability", "hardworking", "detailed"], "languages_combined": [{"language": "english", "language_level": ["good"]}, {"language": "mandarin", "language_level": ["good"]}]}, "experience_required": {"duration": ["minimum 5 years", "at least 15 years"], "field": ["management", "fmcg"]}}, {"job_id": "100003009053173", "location_code": "hk", "company": "China Mobile Hong Kong \u4e2d\u570b\u79fb\u52d5\u9999\u6e2f", "job_title": "Strategy Manager", "description": "CHINA MOBILE HONG KONG COMPANY LIMITED (\"CMHK\") is the wholly-owned subsidiary of China Mobile Limited (HKEx: 941) (NYSE: CHL), which ranks 65th on the Fortune Global 500.\n\nOur company strives to offer superior service experience and to become the preferable digital partner for customers. We are preserving an environment with trust, responsibility and caring. At CMHK, we commit to maximizing people\u2019s potential and paving the way toward success for every striver. We are now inviting high caliber professional to join us.\n\nDepartment: Entreprise Management\n\nIn this position, you will:\n\n\n\nAnalyze strategy information to drive long-term corporate strategic planning and execution\nConduct research on market competitive landscapes, benchmark digital performance and processes against industry best practice and identify digital opportunities to grow business\nCooperate with the company's business process development, improve the organizational structure and operational efficiency\nPerform gap analysis of digital asset capabilities to identify opportunities and improvements\nLead co-lead cross functional workstreams to create, implement and monitor process improvement, provide digital solution to help solve the business needs\n\nTo be successful in this position, you should meet the following requirements:\n\n\nGood technical background, Degree holder in Information Technology, Business Management or related disciplines\u00a0\nAt least 6 years' of working experience in strategy research and analytics, or digital project management field\nExpertise in digital management knowledge and strategy tactics, solution focused and service oriented Sound knowledge of innovative technologies, design patterns and keep abreast of latest technology trends\nGood command of written and spoken Chinese (must) and English (plus), strong skills in reporting, writing and communication\u00a0\nAble to work in challenging environment and under pressure to meet target lines\u00a0\nProactive, confident, innovative, organized and interactive, able to work independently\nBe able to communicate effectively with excellent presentation skills, strong written and oral skills, customer relationship skills including the ability to quickly create productive collaborations among key stakeholders\n\nWhen you work:\n\n5 days work\n8 hours/day\n\nWhat you enjoy:\n\nDouble pay\nDiscretionary Performance bonus\nLife insurance\nMedical insurance\nEducation subsidies\nBirthday gift\nMarriage leave\nBirthday leave\nStaff discount\n\n\nInterested\u00a0parties please send full resume with your availability, present and expected salary,\u00a0by clicking\u00a0Apply Now\u00a0button.\n\u00a0\u00a0\n\n\nCMHK is committed to be an equal opportunity employer. We offer exceptional benefits package and the opportunity to work in a challenging environment. Personal data provided by applicants will be treated strictly in accordance with our personal data policy and for recruitment purposes only.", "employment_types": ["Full Time", "Permanent"], "selling_points": ["14 or above AL, 5 days work week", "Staff Offer, Staff SIM", "13th mth salary, dis. performnace bonus"], "locations": ["Kwai Hing"], "categories": ["Professional Services", "Business Analysis / Data Analysis", "Management", "General Management", "Marketing / Public Relations", "Management"], "post_time": "2022-01-17T06:16:04Z", "salary": {"currency": null, "max": null, "min": null, "period": null, "term": null}, "salary_visible": false, "title_keywords": ["manager"], "responsibilities": ["reporting", "management", "strategic planning", "analysis", "monitor", "design", "communication", "project management", "business process", "insurance", "conduct research", "cooperate with"], "requirements": {"degrees": ["degree holder"], "majors": ["related disciplines", "business", "information technology"], "languages": ["english", "chinese"], "language_level": ["good command"], "hard_skills": ["business management", "plus", "analysis", "gap", "mobile", "project management"], "soft_skills": ["confident", "organized", "work independently", "proactive", "under pressure", "oral", "focused", "productive", "organizational", "communication", "project management", "presentation skills", "innovative", "superior"], "languages_combined": [{"language": "english", "language_level": ["good command"]}, {"language": "chinese", "language_level": ["good command"]}]}, "experience_required": {"duration": ["at least 6 years"], "field": ["digital", "project management", "research"]}}, {"job_id": "100003009052089", "location_code": "hk", "company": "DKSH Hong Kong Limited", "job_title": "Senior Manager, Sales & Operations Planning, FMCG", "description": "RESPONSIBILITIES\n\n\n\n\nDirect the development and growth of HJ Business\n\nProvide direction and high level strategies for Asia to achieve Regional HJ target\nStrategize with markets to ensure good performance and assist with achieving set business objectives, budgets and estimates\nDesign and develop regional seminars for HJ coordinators to formulate an agile platform to share synergies and expertise (including competition intelligence)\nStrategize with market HJ and retail departments in reaching HJ sales target through recurring sales and event activations with strategic direction\n\n\n\nClient Database Management\n\nLeverage regional client database with efficiency to enhance HJ business\nDirect client segmentation strategies with local market with regional focus\n\n\n\nBuilding Client relations\n\nStrategize action plan (together with market heads) to achieve business objectives\nInitiate, manage and maintain contact with regional third parties to further develop and grow HJ business in the region\n\n\n\nBuilding Business relations \u2013 Sales Expert community development\n\nProvide direction on HJ community development working together with market heads with concrete action plan\nImplement annual think tank / boot camp with market management to strategize new plans to build business\nGive direction for an encompassing and targeted booster program to raise level of competence in areas of jewelry and technical skills, client relationship building, lifestyle experiences (to include trainings on art, auction, GIA)\n\n\n\nInformation and Intelligence sharing\n\nShare and follow-up of the international HJ strategy within countries\nShare competitive intelligence (on a regional level)\n\n\n\nREQUIRED COMPETENCIES\n\nBachelor degree in Business Administration \u2013 Marketing or equivalent is preferred\n10+ years working experience in marketing and business development, either luxury field or other high-end industry\nStrong analytical skills, details oriented and positive work attitude\nStrong negotiation skills with excellent communication and interpersonal skills\nComputer skills: proficient in Microsoft office, AS400 would be a plus\nEnglish (mandatory), Cantonese (required), Mandarin (required). French (if possible)\nProactive in attaining market, customer and competitor knowledge\nAble to multi-task, reliable, positive attitude and able to work under pressure\nAbility to work well with different cultures and enjoy work/travelling", "employment_types": ["Full Time", "Permanent"], "selling_points": ["Develop & Lead the S&OP in FMCG HK", "Improvement to operational efficiencies", "Drive key objectives including forecast accuracy"], "locations": ["Aberdeen"], "categories": ["Management", "General Management", "Transportation & Logistics", "Inventory / Warehousing", "Supply Chain"], "post_time": "2022-01-17T02:04:45Z", "salary": {"currency": null, "max": null, "min": null, "period": "monthly", "term": null}, "salary_visible": false, "title_keywords": ["senior manager", "operations", "sales"], "responsibilities": ["budgets", "management", "provide direction", "work under pressure", "sales target", "design and develop", "develop", "communication", "maintain", "contact", "database", "plan", "plans", "administration"], "requirements": {"degrees": ["degree", "bachelor"], "majors": ["marketing", "business administration"], "languages": ["cantonese", "english", "french", "mandarin"], "language_level": [], "hard_skills": ["plus", "agile", "microsoft office", "analytical skills", "computer skills", "focus"], "soft_skills": ["multi-task", "agile", "analytical skills", "positive attitude", "negotiation skills", "communication and interpersonal skills", "reliable", "technical skills", "focus", "proactive", "positive work attitude", "work under pressure"], "languages_combined": [{"language": "cantonese", "language_level": []}, {"language": "english", "language_level": []}, {"language": "french", "language_level": []}, {"language": "mandarin", "language_level": []}]}, "experience_required": {"duration": ["10+ years"], "field": ["marketing", "business development"]}}, {"job_id": "100003009051345", "location_code": "hk", "company": "C2 Recruitment Limited", "job_title": "Assistant Business Manager", "description": "Job Responsibilities:\n\nResponsible for the implementation of S&OP in the market and execution as per Group CG S&OP design framework\nEstablish the step meetings in the market (Market Demand Review, Supply Demand Review, Market Pre-S&OP and Clients & Products Portfolio Review)\nAccountable for the market submission to CG Executive S&OP meeting (include but not limited to coordination with stakeholder and alignment with Market VP)\nPut together step meetings calendar in a rolling 12 to 18 months and make sure all reviews are conducted on a monthly basis\nDocument and communicate key actions and decisions to drive organizational alignment of the plans (Net Sales, EBIT and Inventory)\nLead and develop the monthly demand plan collaborating across the market organization\nEstablish demand planning measures and controls with root cause and corrective action to improve forecast accuracy and bias\nCollaborate closely cross functionally to develop accurate demand plans while supporting the optimization of supply and inventory plans.\u00a0 Establish one set of number in the market\nidentify gaps to supply and demand alignment leading teams to identify scenariosto mitigate and prepare recommendation\nAlign market processes and standard template to those defined by Group CG S&OP and sharing best practices and learnings in the S&OP community\nMeasure S&OP key performance indicators (KPIs) to determine the success of S&OP process\nEstablish the mechanism to track overall S&OP process maturity and lead key process improvement initiatives\nConduct the self-assessment and audit to measure compliance, adherence to the process and continuous improvement\nSupport overall roadmap to achieve objectives, including process, application support tools, policies and control mechanism\nChampion CG S&OP in market with the support of Group CG S&OP and Market VP\nEnsure S&OP meeting principle, objective and expected outcome are accomplished\nJob Requirements:\n\nBachelor's degree in supply chain management or business or equivalent\n5 to 10 years of sales and operations planning with experience leading a demand planning team\nSubject matter expert of Demand, Supply and Inventory Management.\u00a0 Proven ability to effectively drive the requirement of these three areas\nBackground in Finance would be an added advantage to navigate the financial elements of S&OP\nExperience in implementing S&OP or handling change management process/project will be a benefit\nDemand planning experience is essential and success in setting up and managing Demand Planning team is needed\nA proven leader with excellent people management skills.\u00a0 Someone who is a collaborator as this role requires close relentless engagement with many stakeholders\nContinuous improvement seeker who seek perpetual enhancement to the process and progress evolution\nA strong sense of urgency in identifying, analyzing and acting on situations and opportunities\nExperience in FMCG multinational industry is an added advantage\nStrong communication (verbal and written), interpersonal and leadership skill\nTrack record for achieving results in matrix organization\nResults oriented focused individual with passion for continuous improvement\nHave the intellectual curiously and tenacity to dwell deeper until root cause is exposed\nAbility to mediate when necessary\nAble to manage strategically and tactically as well\nChange management embracer who are comfortable in having organizational tension to revolutionize ways of working\n\nWe offer performance bonus and attractive benefits including medical insurance and company shuttle bus services to the right candidate.\u00a0 Interested parties please apply in full resume with current and expected salaries to Human Resources Department, DKSH Hong Kong Limited, 23rd Floor, Tower A, Southmark, 11 Yip Hing Street, Wong Chuk Hang, Hong Kong or by clicking \"Apply Now\"\n\nAll personal data collected will be used for recruitment purpose only.\u00a0 Candidates will be contacted within 2 weeks if the background and experience are closely relevant to the job requirement.\n\nDrive Growth. Be the Difference. Join DKSH.\n\n\nDKSH\u2019s strength lies in our great diversity of services, industries, clients, products, regions and employees from various nationalities. We are proud of our people: they are the reason we are successful. Our people are the best in the industry. They are passionate about their career growth and about business success. They work as part of an energetic and committed team, positively impacting millions of lives through the products and services we provide.\n\nJoin us today if you are ready to \"Drive growth.\u00a0 Be the Difference.\"\u00a0 With DKSH, you will experience a world of learning and development, own your career and take business responsibility and have a positive impact that touches people's lives.", "employment_types": ["Full Time", "Permanent"], "selling_points": ["Regional business planning and operations role", "Implementation of business development plans", "Highly organized and logical in thought"], "locations": ["Central & Western Area"], "categories": ["Admin & HR", "Administration / Operation Manager", "Professional Services", "Business Consultancy", "Management", "General Management"], "post_time": "2022-01-16T21:50:27Z", "salary": {"currency": null, "max": null, "min": null, "period": "monthly", "term": null}, "salary_visible": false, "title_keywords": ["manager", "assistant"], "responsibilities": ["inventory", "demand planning", "audit", "design", "plan", "plans", "market demand review", "collaborate", "control", "market pre-s&op", "compliance", "teams", "implementation", "develop", "forecast", "kpis", "clients & products portfolio review", "coordination with stakeholder", "market submission", "policies", "supply demand review"], "requirements": {"degrees": ["degree", "bachelor"], "majors": ["business"], "languages": [], "language_level": [], "hard_skills": ["demand planning"], "soft_skills": ["focused", "passion for", "urgency", "organizational", "relentless", "communication", "leadership skill", "interpersonal"], "languages_combined": []}, "experience_required": {"duration": ["5 to 10 years"], "field": ["management", "fmcg", "team", "planning"]}}, {"job_id": "100003009052469", "location_code": "hk", "company": "Sushi Express (Hong Kong) Co., Limited", "job_title": "Project Manager", "description": "Our client is a reputable Consulting firm in Hong Kong, they are looking for high calibre candidates to join their team:\n\n\n\nResponsibilities:\n\nAdvise and support management on strategic, business and operational related topics\nDevelop and maintain strong relationship with clients and business partners\nDevelop, update and monitor regional business plan and manage budget proactively\nPlan and execute company development and growth strategies\nSupport the implementation of business development plans\nCoordinate internal engagement activities and meetings fostering positive and open communication\n\nRequirements:\n\nDegree in Business Administration, Management or related disciplines\nProven record of project management and delivery, business analysis, change management within a business change environment\nStrong passion in people-oriented industry\nHighly organized and logical in thought and action\nStrong communication and negotiation skills is required\nSelf-motivated, able to work individually and as a team\nExcellent command of English and Chinese\nMore experienced will be considered as Business Manager\n\nPersonal data provided by job applicants will be used strictly in accordance with the employer's personal data policies and for recruitment purposes only.", "employment_types": ["Full Time", "Permanent"], "selling_points": [], "locations": ["Not Specified"], "categories": ["Management", "General Management"], "post_time": "2022-01-17T03:06:40Z", "salary": {"currency": null, "max": null, "min": null, "period": "monthly", "term": null}, "salary_visible": false, "title_keywords": ["project manager"], "responsibilities": ["management", "budget", "monitor", "implementation", "develop", "coordinate", "communication", "maintain", "plan", "business plan", "plans"], "requirements": {"degrees": ["degree"], "majors": ["related disciplines", "business administration"], "languages": ["english", "chinese"], "language_level": ["excellent"], "hard_skills": ["project management", "analysis"], "soft_skills": ["organized", "self-motivated", "passion in", "communication", "project management", "negotiation skills", "people-oriented"], "languages_combined": [{"language": "english", "language_level": ["excellent"]}, {"language": "chinese", "language_level": ["excellent"]}]}, "experience_required": {"duration": [], "field": []}}, {"job_id": "100003009051187", "location_code": "hk", "company": "Mindset Asia Limited", "job_title": "General Manager - Learning Center", "description": "What you will do\n\nThe candidate will be managing the Service Business (including HVAC, BMS and Fire & Security services) of the company in HK and Macau. This role is expected to deliver superb maintenance and service solutions to a wide customer base across all industry segments.\n\n\u00a0How you will do it\n\nSet and execute strategies to grow HVAC, BMS and Fire & Security services businesses\nAchieve annual secured order, revenue and margin target in accordance with Company\u2019s objectives and direction\nManage service teams to provide preventive maintenance services and repair work for systems at customer sites; and testing and commissioning of systems installed by others\nCoordinate with Sales team to prepare maintenance and repair proposals and tenders\nDevelop and maintain key customer relationships with professional knowledge and excellent service quality\nHandle customer complaints and direct service managers to resolve issues\nManage subcontractors to achieve healthy partnership\nEnsure quality of work to the satisfaction of customer\nStrengthen relationships with customers to secure more orders\nEnsure teams adhering to the compliance of EHS, Ethics Code and Company policies in all work sites\n\nWhat we look for\n\nRequired\n\nDegree holder in Building Services or engineering-related disciplines\nMinimum 20 years\u2019 HVAC, BMS and Fire & Security services experience, of which at least 10 years at managerial level\nStrong technical knowledge and experience in HVAC, BMS and Fire & Security Systems\nExperience in tracking performance of service teams\nCompetency in project planning and have strong leadership skills\u00a0\n\nPreferred\n\nGood communication and interpersonal skills\nProficient in English and Chinese\nAbility to travel, learn and train up others\nGood problem-solving techniques, organizing and planning ability\nIndependent and able to work under pressure and tight deadline\nPrior experience with government maintenance contracts is a plus\n\n", "employment_types": ["Full Time", "Permanent"], "selling_points": [], "locations": ["Not Specified"], "categories": ["Education", "Others", "Management", "General Management", "Admin & HR", "Training & Development"], "post_time": "2022-01-15T04:21:46Z", "salary": {"currency": null, "max": null, "min": null, "period": "monthly", "term": null}, "salary_visible": false, "title_keywords": ["general manager"], "responsibilities": ["quality", "communication", "maintain", "work under pressure", "contracts", "compliance", "teams", "testing", "develop", "commissioning", "customer complaints", "coordinate with", "tracking", "project planning", "maintenance", "policies", "systems", "repair", "sales team", "maintenance services", "planning"], "requirements": {"degrees": ["degree holder"], "majors": ["related disciplines", "building services", "engineering"], "languages": ["english", "chinese"], "language_level": ["proficient"], "hard_skills": ["plus", "maintenance", "hvac", "problem-solving", "bms", "code"], "soft_skills": ["independent", "problem-solving", "leadership skills", "communication and interpersonal skills", "work under pressure"], "languages_combined": [{"language": "english", "language_level": ["proficient"]}, {"language": "chinese", "language_level": ["proficient"]}]}, "experience_required": {"duration": ["at least 10 years", "minimum 20 years"], "field": ["managerial", "security", "maintenance"]}}, {"job_id": "100003009052374", "location_code": "hk", "company": "Trenda Group Holdings Limited", "job_title": "\u8463\u529e\u52a9\u7406 Management Officer", "description": "Our client is an established Learning center, with an objective to provide continuing education for the professional preparatory programs, including ACCA, LCCI, MYOB, Secretarial and etc..\n\nResponsibilities\n\nLead the continuous development and provide strategic direction for the long term growth plan of the Learning Center for 3 to 5 years\nAssist in program development and promote the quality and standard of the programs\nFully responsible for the management of day-to-day operation, financial matters, forecasts, audit and maintain a strong culture of risk management\nEnsure that the effective operation and have the right governance structure to deliver program growth with full compliance\nEstablish and maintain regular communication with various government authorities for a better understanding of legal and regulatory requirements\nMaintain good partnership with internal management (including the Board members, management team and tutors) and external organisations, such as the Education department, HKSAR Re-training Board, Continuing Education Fund and other co-operative partners\nExplore and expand the partnership with different organisations to look for collabrative partnership\nRequirements\nProfessionally qualified with ACCA/HKICPA or Master degree in Education or related disciplines\nOver 15 years experience in the education/learning centre\nDemonstrate effective leadership and passionate in education development\nSolid experience in leading, coaching, driving and inspiring team members\nProven organisation skill and ability to priortise\nExcellent in communication and presentation skill\nGood in English and Chinese, verbal and written\nInterested parties can apply online by forwarding your resume and quoting the job reference. All applications will be strictly confidential and used for recruitment purposes only.\n", "employment_types": ["Full Time", "Permanent", "Contract"], "selling_points": ["\u6574\u7406\u4f1a\u8bae\u7eaa\u8981", "\u89c4\u6574\u5404\u90e8\u95e8\u63d0\u4ea4\u8463\u4e8b\u957f\u7684\u6863\u6848", "\u534f\u8c03\u5404\u90e8\u95e8\u5de5\u4f5c"], "locations": ["Pok Fu Lam"], "categories": ["Management", "General Management"], "post_time": "2022-01-17T02:53:15Z", "salary": {"currency": null, "max": null, "min": null, "period": "monthly", "term": null}, "salary_visible": false, "title_keywords": ["officer"], "responsibilities": ["management team", "management", "regulatory requirements", "compliance", "quality", "audit", "communication", "maintain", "plan", "day-to-day operation"], "requirements": {"degrees": ["master degree"], "majors": ["related disciplines"], "languages": ["english", "chinese"], "language_level": ["good"], "hard_skills": ["presentation skill", "acca", "hkicpa"], "soft_skills": ["passionate", "presentation skill", "organisation skill", "communication", "learning", "inspiring", "leadership"], "languages_combined": [{"language": "english", "language_level": ["good"]}, {"language": "chinese", "language_level": ["good"]}]}, "experience_required": {"duration": ["15 years"], "field": ["team", "education"]}}, {"job_id": "100003009056216", "location_code": "hk", "company": "adidas Hong Kong Ltd", "job_title": "Senior Manager Delivery Management FW", "description": "Purpose& Overall Relevance for the Organization:\nDrive and coordinate production allocation and availability management for finished products and components across all Footwear LOs/functions\nDrive conceptual evolution, implementation and ramp-up of Speed programs; and coordinate all operations of Speed programs across the Footwear organization, incl. feasibility checks, material staging, capacity and availability management\nSupport the Director Allocation & Capacity in the operational and strategic planning process; and in identifying/implementing initiatives that enhance the capabilities, efficiency, effectiveness and collaboration within Footwear Sourcing\n\n\nKey Responsibilities:\nOptimize seasonal production allocation along various dimensions incl. availability, landed costs (FOB, duty, VA), key technologies, model mix and factory capabilities; drive allocation strategy implementation through production allocation on BU and franchises level; actively influence and shape development allocation through production allocation decisions\nDrive monthly performance of Footwear Sourcing operations along relevant dimensions (e.g. order fulfilment KPIs, capacity utilization, process compliance and efficiency, etc.)\nDrive component business and feasibility checks and develop alternative sourcing options to optimize trade benefits\nProactively identify potential issues for fulfilment and capacity utilization and work closely with the LOs and/or functional teams to develop mitigation measures\nManage end to end planning process of special Statement projects (e.g Yeezy..)\nManage the current Footwear Speed programs Continuous Replenishment / Planned Responsiveness / In-Season Creation: monitor execution of all on/off-system processes to ensure high degree of speed feasibility, order fulfilment, and to identify improvement opportunities; specifically, own and drive the seasonal speed feasibility checks and support SMU requests\nSupport the department in ad-hoc data analyses\nSupport selected projects as defined by Director Allocation & Capacity\n\n\nKey Relationships:\nLO teams and esp. LO Planning Managers, DPCs and SDOMs\nSupplier teams and esp. Business Planning Managers\nGlobal Supply Planning and BU planning\nGOPS Speed team\nProduct Operations\nother COPS functions\n\n\nKnowledge Skills and Abilities:\nStrong analytical and quantitative skills\nGood interpersonal and communication skills\nUnderstanding of trade topics (import duties, FTA, trade barriers) affecting imports from the Footwear source countries into major markets\nGood knowledge of Footwear industry and manufacturing methods a plus\nGood knowledge of standard Software applications (Excel, PowerPoint)\nProject management skills a plus\n\n\nRequisite Education and Experience / Minimum Qualifications:\nUndergraduate university degree\nMinimum of 5 years working experience in a Sourcing role or operations\nFluency in English, knowledge of another language (ideally Mandarin, Vietnamese, Bahasa, or German) an advantage.\n\nAT ADIDAS WE HAVE A WINNING CULTURE. BUT TO WIN, PHYSICAL POWER IS NOT ENOUGH. JUST LIKE ATHLETES OUR EMPLOYEES NEED MENTAL STRENGTH IN THEIR GAME. WE FOSTER THE ATHLETE\u2018S MINDSET THROUGH A SET OF BEHAVIORS THAT WE WANT TO ENABLE AND DEVELOP IN OUR PEOPLE AND THAT ARE AT THE CORE OF OUR UNIQUE COMPANY CULTURE \u2013 THE 3CS: CONFIDENCE, COLLABORATION AND CREATIVITY.\n\nCONFIDENCE allows athletes to make quick decisions on the field, to reach higher. For us at adidas confidence means acknowledging that we don\u2019t have all the answers. But we are willing to take risks, we try new things. And if we fail, then this is part of our learning \u2013 it helps us improve.\n\nCOLLABORATION. Every elite athlete relies on partners: coaches, teammates, and nutritionists. We, too, know that we are stronger together. Winning as one team takes open and candid dialogue, inclusiveness and trust in each other\u2019s abilities and talents.\n\nBeing the best sports company in the world takes CREATIVITY. No great athlete succeeds by copying their predecessors\u2019 training plans and strategies. We have to be open to new ideas, explore, gain an edge and stand out. Only then can we succeed.\n\nADIDAS CELEBRATES DIVERSITY, SUPPORTS INCLUSIVENESS AND ENCOURAGES INDIVIDUAL EXPRESSION IN OUR WORKPLACE. WE DO NOT TOLERATE THE HARASSMENT OR DISCRIMINATION TOWARD ANY OF OUR APPLICANTS OR EMPLOYEES. WE ARE AN EQUAL OPPORTUNITY EMPLOYER.\nJOB TITLE:\nSenior Manager Delivery Management FW\nBRAND:\nadidas\nLOCATION:\nHong Kong\nTEAM:\nSourcing\nSTATE:\nHK\nCOUNTRY/REGION:\nCN\nCONTRACT TYPE:\nFull time\nNUMBER:\n412369\nDATE:\nJan 7, 2022", "employment_types": ["Full Time"], "selling_points": [], "locations": ["Not Specified"], "categories": ["Admin & HR", "Clerical / Admin Staff", "Management", "General Management"], "post_time": "2022-01-18T03:34:32Z", "salary": {"currency": null, "max": null, "min": null, "period": "monthly", "term": null}, "salary_visible": false, "title_keywords": ["senior manager"], "responsibilities": ["management", "strategic planning", "operations", "compliance", "implementation", "coordinate", "kpis", "costs"], "requirements": {"degrees": [], "majors": [], "languages": [], "language_level": [], "hard_skills": [], "soft_skills": [], "languages_combined": []}, "experience_required": {"duration": [], "field": []}}, {"job_id": "100003009056220", "location_code": "hk", "company": "Swire Resources Ltd", "job_title": "Business Development Executive", "description": "Reporting to Senior Management, the incumbent will be responsible for the\u00a0Business Development functions include identifying customer markets, monitoring industry trends, conducting competitor analyses and crafting business plans with the aim to determine ideal market opportunities to pursue and introduce new lifestyle and sports brands to Asia under distribution/ joint-venture / franchising / other suitable models.\u00a0\n\nResponsibilities\n\nConduct market research and analysis to identify customer markets, monitor industry trends, conduct competitor analyses to drive business opportunities\nAssist in developing business proposals and participate in new business pitches for targeted brands and future business collaboration\nAssist in Company\u2019s branding and media communication activities e,g, press releases, corporate marketing collaterals and website, etc.\nSupport senior management on preparing business presentation materials and internal / external communications materials such as press materials related to corporate-level etc.\nParticipate in operational analysis and special corporate projects\n\nRequirements\n\nUniversity graduate with 3 years\u2019\u00a0 working experience in business analysis, business development or consultancy\nStrong numeric and business acumen\nGood interpersonal & presentation skills\nProactive, energetic, dynamic and with genuine passion in retail industry\nAttentive to details and with multi-tasking capability\nStrong oral and written communication in English, Mandarin and Cantonese\nExcellent command of\u00a0 Microsoft office application including PowerPoint, Excel and Word\n\nWe offer competitive remuneration package with\u00a0a wide range of fringe benefits including\n\n5-day work week\nDiscretionary Bonus\nComprehensive Medical Coverage\nStaff Shopping Discount\nNon-contributory Retirement Benefits Scheme\nBirthday Leave\n\nInterested parties please send resume with present and expected salary to Human Resources Department, Swire Resources Limited,\u00a012/F Kingston International Centre, 19 Wang Chiu Road Kowloon Bay, Hong Kong or by\u00a0clicking the below \"Apply Now\" button.\n\nSwire Resources Limited is Equal Opportunity Employer\n", "employment_types": ["Full Time", "Permanent"], "selling_points": ["Conduct market research and analysis", "developing business proposals & pitches", "Support senior management in business presentation"], "locations": ["Kowloon Bay"], "categories": ["Professional Services", "Business Consultancy", "Sales, CS & Business Devpt", "Business Development", "Management", "General Management"], "post_time": "2022-01-18T03:37:09Z", "salary": {"currency": null, "max": null, "min": null, "period": null, "term": null}, "salary_visible": false, "title_keywords": ["business development executive"], "responsibilities": ["conduct market research", "analysis", "monitor", "business opportunities", "developing", "marketing collaterals", "communication", "website", "senior management"], "requirements": {"degrees": ["university graduate"], "majors": ["business"], "languages": ["cantonese", "english", "mandarin"], "language_level": [], "hard_skills": ["excel", "microsoft office", "analysis", "word", "powerpoint", "dynamic", "acumen"], "soft_skills": ["oral", "attentive to details", "passion in", "genuine", "communication", "presentation skills", "energetic", "dynamic", "multi-tasking", "business acumen", "proactive", "interpersonal"], "languages_combined": [{"language": "cantonese", "language_level": []}, {"language": "english", "language_level": []}, {"language": "mandarin", "language_level": []}]}, "experience_required": {"duration": ["3 years"], "field": ["business analysis", "business development"]}}, {"job_id": "100003009051602", "location_code": "hk", "company": "Success Meteor", "job_title": "Recruitment Manager", "description": "Job Descriptions\n\nManage full spectrum of recruitment services, including but not limited to interviewing candidates, understanding their' needs, assessing and identifying the right candidates;\nTranslate business requirements into recruitment practices and deliver solutions aligned with business objectives;\nSource and evaluate the effectiveness of advertising and recruitment channel;\nResponsible for sales management of the team including hiring, training and performance evaluation.\n\n\u00a0Job Requirements\n\nBachelor\u2019s degree holder, with major in relevant sector preferable;\nPossess excellent presentation and influencing skills to advise candidate at all levels in a professional manner;\nExcellent command in English, Mandarin and Cantonese.\n\n\u00a0Benefits\n\nBasic salary up to 25,000 + competitive commission;\nComprehensive training programs;\nExcellent career path;\nRemuneration negotiable.\n\nCandidates without recruitment or sales experience but have the right motivation and attitude are welcomed. Training will be provided.", "employment_types": ["Full Time"], "selling_points": ["Excellent working environment", "Competitive basic salary and commission structure", "Candidates with relevant experience are preferable"], "locations": ["Tsim Sha Tsui"], "categories": ["Management", "General Management", "Admin & HR", "HR Director / Manager", "Insurance", "Others"], "post_time": "2022-01-16T13:59:47Z", "salary": {"currency": "HKD", "max": 54999, "min": 25000, "period": "monthly", "term": null}, "salary_visible": true, "title_keywords": ["manager"], "responsibilities": ["advertising", "evaluate", "recruitment", "evaluation", "sales management"], "requirements": {"degrees": ["bachelor", "degree holder"], "majors": [], "languages": ["cantonese", "english", "mandarin"], "language_level": ["excellent"], "hard_skills": [], "soft_skills": ["presentation"], "languages_combined": [{"language": "cantonese", "language_level": ["excellent"]}, {"language": "english", "language_level": ["excellent"]}, {"language": "mandarin", "language_level": ["excellent"]}]}, "experience_required": {"duration": [], "field": []}}, {"job_id": "100003009052728", "location_code": "hk", "company": "Richemont Asia Pacific Limited - Cartier", "job_title": "Regional HJ Business & Talent Development Director", "description": "RESPONSIBILITIES\n\n\n\n\nDirect the development and growth of HJ Business\n\nProvide direction and high level strategies for Asia to achieve Regional HJ target\nStrategize with markets to ensure good performance and assist with achieving set business objectives, budgets and estimates\nDesign and develop regional seminars for HJ coordinators to formulate an agile platform to share synergies and expertise (including competition intelligence)\nStrategize with market HJ and retail departments in reaching HJ sales target through recurring sales and event activations with strategic direction\n\n\n\nClient Database Management\n\nLeverage regional client database with efficiency to enhance HJ business\nDirect client segmentation strategies with local market with regional focus\n\n\n\nBuilding Client relations\n\nStrategize action plan (together with market heads) to achieve business objectives\nInitiate, manage and maintain contact with regional third parties to further develop and grow HJ business in the region\n\n\n\nBuilding Business relations \u2013 Sales Expert community development\n\nProvide direction on HJ community development working together with market heads with concrete action plan\nImplement annual think tank / boot camp with market management to strategize new plans to build business\nGive direction for an encompassing and targeted booster program to raise level of competence in areas of jewelry and technical skills, client relationship building, lifestyle experiences (to include trainings on art, auction, GIA)\n\n\n\nInformation and Intelligence sharing\n\nShare and follow-up of the international HJ strategy within countries\nShare competitive intelligence (on a regional level)\n\n\n\nREQUIRED COMPETENCIES\n\nBachelor degree in Business Administration \u2013 Marketing or equivalent is preferred\n10+ years working experience in marketing and business development, either luxury field or other high-end industry\nStrong analytical skills, details oriented and positive work attitude\nStrong negotiation skills with excellent communication and interpersonal skills\nComputer skills: proficient in Microsoft office, AS400 would be a plus\nEnglish (mandatory), Cantonese (required), Mandarin (required). French (if possible)\nProactive in attaining market, customer and competitor knowledge\nAble to multi-task, reliable, positive attitude and able to work under pressure\nAbility to work well with different cultures and enjoy work/travelling", "employment_types": ["Full Time"], "selling_points": [], "locations": ["Not Specified"], "categories": ["Sales, CS & Business Devpt", "Business Development", "Management", "General Management", "Marketing / Public Relations", "Management"], "post_time": "2022-01-17T03:49:43Z", "salary": {"currency": null, "max": null, "min": null, "period": "monthly", "term": null}, "salary_visible": false, "title_keywords": ["director"], "responsibilities": ["budgets", "management", "provide direction", "work under pressure", "sales target", "design and develop", "develop", "communication", "maintain", "contact", "database", "plan", "plans", "administration"], "requirements": {"degrees": ["degree", "bachelor"], "majors": ["marketing", "business administration"], "languages": ["cantonese", "english", "french", "mandarin"], "language_level": [], "hard_skills": ["plus", "agile", "microsoft office", "analytical skills", "computer skills", "focus"], "soft_skills": ["multi-task", "agile", "analytical skills", "positive attitude", "negotiation skills", "communication and interpersonal skills", "reliable", "technical skills", "focus", "proactive", "positive work attitude", "work under pressure"], "languages_combined": [{"language": "cantonese", "language_level": []}, {"language": "english", "language_level": []}, {"language": "french", "language_level": []}, {"language": "mandarin", "language_level": []}]}, "experience_required": {"duration": ["10+ years"], "field": ["marketing", "business development"]}}, {"job_id": "100003009046814", "location_code": "hk", "company": "Johnson Controls Hong Kong Limited", "job_title": "General Manager, Service & Maintenance (Building Services)", "description": "What you will do\n\nThe candidate will be managing the Service Business (including HVAC, BMS and Fire & Security services) of the company in HK and Macau. This role is expected to deliver superb maintenance and service solutions to a wide customer base across all industry segments.\n\n\u00a0How you will do it\n\nSet and execute strategies to grow HVAC, BMS and Fire & Security services businesses\nAchieve annual secured order, revenue and margin target in accordance with Company\u2019s objectives and direction\nManage service teams to provide preventive maintenance services and repair work for systems at customer sites; and testing and commissioning of systems installed by others\nCoordinate with Sales team to prepare maintenance and repair proposals and tenders\nDevelop and maintain key customer relationships with professional knowledge and excellent service quality\nHandle customer complaints and direct service managers to resolve issues\nManage subcontractors to achieve healthy partnership\nEnsure quality of work to the satisfaction of customer\nStrengthen relationships with customers to secure more orders\nEnsure teams adhering to the compliance of EHS, Ethics Code and Company policies in all work sites\n\nWhat we look for\n\nRequired\n\nDegree holder in Building Services or engineering-related disciplines\nMinimum 20 years\u2019 HVAC, BMS and Fire & Security services experience, of which at least 10 years at managerial level\nStrong technical knowledge and experience in HVAC, BMS and Fire & Security Systems\nExperience in tracking performance of service teams\nCompetency in project planning and have strong leadership skills\u00a0\n\nPreferred\n\nGood communication and interpersonal skills\nProficient in English and Chinese\nAbility to travel, learn and train up others\nGood problem-solving techniques, organizing and planning ability\nIndependent and able to work under pressure and tight deadline\nPrior experience with government maintenance contracts is a plus\n\n", "employment_types": ["Full Time", "Permanent"], "selling_points": ["GM Experience in HVAC, BMS and Fire & Security", "With strong project planning and leadership skills", "Cover scope in Hong Kong and Macau"], "locations": ["Kwun Tong"], "categories": ["Engineering", "Engineering Project Management", "Management", "General Management", "Building & Construction", "Others"], "post_time": "2022-01-16T21:50:16Z", "salary": {"currency": null, "max": null, "min": null, "period": "monthly", "term": null}, "salary_visible": false, "title_keywords": ["general manager"], "responsibilities": ["quality", "communication", "maintain", "work under pressure", "contracts", "compliance", "teams", "testing", "develop", "commissioning", "customer complaints", "coordinate with", "tracking", "project planning", "maintenance", "policies", "systems", "repair", "sales team", "maintenance services", "planning"], "requirements": {"degrees": ["degree holder"], "majors": ["related disciplines", "building services", "engineering"], "languages": ["english", "chinese"], "language_level": ["proficient"], "hard_skills": ["plus", "maintenance", "hvac", "problem-solving", "bms", "code"], "soft_skills": ["independent", "problem-solving", "leadership skills", "communication and interpersonal skills", "work under pressure"], "languages_combined": [{"language": "english", "language_level": ["proficient"]}, {"language": "chinese", "language_level": ["proficient"]}]}, "experience_required": {"duration": ["at least 10 years", "minimum 20 years"], "field": ["managerial", "security", "maintenance"]}}, {"job_id": "100003009053997", "location_code": "hk", "company": "Aeon Stores (Hong Kong) Co Ltd", "job_title": "Security Officer \u4fdd\u5b89\u4e3b\u4efb", "description": "\u5de5\u4f5c\u5730\u9ede: AEON\u8354\u679d\u89d2\u5e97\n\n\u5de5\u4f5c\u6642\u9593: \u6bcf\u5929\u8f2a\u73ed\u5de5\u4f5c9\u5c0f\u6642(\u53e6\u52a0\u4f11\u606f1\u5c0f\u6642);\u6bcf\u6708\u5047\u671f\u7d046\u5929\n\n\u8077\u8cac: \u7ba1\u7406\u8ca8\u5834\u79e9\u5e8f\u53ca\u57f7\u884c\u5de1\u908f\u9632\u6b62\u5e97\u8216\u76dc\u7aca;\u7ba1\u7406\u53ca\u8ddf\u9032\u5e97\u8216\u6e05\u6f54\u3001\u6d88\u9632\u7b49\u4e8b\u9805;\u5354\u8abf\u4e0b\u5c6c\u6bcf\u6708\u503c\u52e4\u66f4\u8868\u53ca\u5206\u914d\u5de5\u4f5c;\u70ba\u4e0b\u5c6c\u63d0\u4f9b\u57f9\u8a13\u3001\u8655\u7406\u610f\u5916\u8abf\u67e5\u53ca\u6848\u4ef6\u8a18\u9304\u5de5\u4f5c\u7b49\n\n\u5b78\u6b77: \u4e09\u5e74\u6216\u4ee5\u4e0a\u4fdd\u5b89\u5de5\u4f5c\u7d93\u9a57,\u4e00\u5e74\u6216\u4ee5\u4e0a\u7763\u5c0e\u5c64\u7d93\u9a57\u3001\u9808\u6301\u6709\u6548\u4fdd\u5b89\u4eba\u54e1\u8a31\u53ef\u8b49\u3001\u719f\u6089\u4fdd\u5b89\u689d\u4f8b\n\n\u85aa\u916c: \u6bcf\u6708$16,000\u6216\u4ee5\u4e0a(\u5168\u8077\u53e6\u4eab\u6709\u96d9\u7ce7, \u82b1\u7d05, \u8868\u73fe\u82b1\u7d05\u7b49)\n\n\u5176\u4ed6\u8981\u6c42: \u61c2\u57fa\u672c\u96fb\u8166;\u5177\u9818\u5c0e\u624d\u80fd \u3001\u61c9\u8b8a\u89e3\u96e3\u80fd\u529b;\u4e3b\u52d5\u7a4d\u6975;\u5b88\u6642\u8aa0\u61c7;\u6ce8\u91cd\u9867\u5ba2\u670d\u52d9\n\n\u798f\u5229: \u672c\u516c\u53f8\u5c07\u63d0\u4f9b\u512a\u8cea\u57f9\u8a13\u3001\u826f\u597d\u6649\u5347\u6a5f\u6703\u3001\u5e74\u7d42\u96d9\u7ce7\u3001\u8868\u73fe\u82b1\u7d05\u3001\u54e1\u5de5\u8cfc\u7269\u512a\u60e0\u3001\u826f\u597d\u91ab\u7642\u53ca\u7259\u79d1\u798f\u5229\u3001\u751f\u65e5\u79ae\u5238\u7b49\n\n**\u5982\u6709\u8208\u8da3\u8005\u8acb\u5c07\u5c65\u6b77\u50b3\u9001\u81f3\u672c\u516c\u53f8\u96fb\u90f5\u6216\u806f\u7d616931 9196(\u53ea\u9650WhatsApp)\u9810\u7d04\u9762\u8a66\n\n\u5de5\u4f5c\u985e\u578b: \u5168\u8077, \u9577\u5de5\n\n\u85aa\u916c: $16,500.00\u81f3$20,000.00(\u6bcf\u6708)\n\n\u6642\u9593:\n\n\u65e5\u73ed\n\u65e9\u73ed\n\u665a\u73ed\n\n\u798f\u5229:\n\n\u7259\u79d1\u4fdd\u96aa\n\u5728\u8077\u5c08\u696d\u57f9\u8a13\n\u54e1\u5de5\u8cfc\u7269\u512a\u60e0\n\u6649\u5347\u6a5f\u6703\n\u91ab\u7642\u4fdd\u96aa\n\u984d\u5916\u4f11\u606f\u65e5\n\n\u88dc\u5145\u85aa\u916c:\n\n13\u500b\u6708\n\u5e74\u7d42\u734e\u91d1\n\u52e4\u5de5\u734e\u91d1\n\n\u5de5\u4f5c\u7d93\u9a57:\n\n\u4fdd\u5b89: 1 \u5e74 (\u512a\u5148\u8003\u616e)\n\n\u57f7\u7167/\u8a8d\u8b49:\n\nQAS\u8b49\u66f8 (\u512a\u5148\u8003\u616e)\n\u4fdd\u5b89\u4eba\u54e1\u8a31\u53ef\u8b49 (\u512a\u5148\u8003\u616e)\n\n\u9060\u7a0b\u5de5\u4f5c:\n\n\u5426", "employment_types": ["Full Time"], "selling_points": [], "locations": ["Lai Chi Kok"], "categories": ["Management", "General Management", "Others", "Security / Safety Control"], "post_time": "2022-01-17T07:59:45Z", "salary": {"currency": null, "max": null, "min": null, "period": "monthly", "term": null}, "salary_visible": false, "title_keywords": ["officer"], "responsibilities": [], "requirements": {"degrees": [], "majors": [], "languages": [], "language_level": [], "hard_skills": [], "soft_skills": [], "languages_combined": []}, "experience_required": {"duration": [], "field": []}}, {"job_id": "100003009052500", "location_code": "hk", "company": "Conrad Hong Kong", "job_title": "Senior Manager, Carrier Sales", "description": "The Challenge We Pose To You\n\nSales of the full suite of products and services to new and existing carrier partners for achieving sales targets\nImplement sales strategy and customer acquisition plan on new and existing accounts\nPrepare sales proposal and presentation, aiming to close new projects by offering competitive solutions and flexible supports\nGenerate periodic sales funnel, project pipelines and sales reports\nCollaborate with internal departments aligning business objectives with customer needs\nHandle ad hoc projects as assigned\nWhat You Bring To Us\n\nUniversity graduate in Computing, Electronics Engineering or related discipline\nMinimum 8 years relevant experience in the telecommunications industry, preferably in the international market\nRelevant experience in managing global accounts or selling to carriers/Telcos\nStrong business networking in the Telecommunication industry is an asset\nStrong business acumen, analytical and strategic mind\nGood selling, communications, and interpersonal skills\nGood command of spoken and written English, Cantonese and Putonghua\nOur Offer\n\n5-day work, 14 days annual leave, a competitive remuneration package, comprehensive medical and dental plan, local and regional training and rewarding career opportunities.\n\nPlease send your complete resume (in MS word format), inclusive of your available date, current and expected salary by clicking Apply Now or by mail to:\u00a0Human Resources and Administration Department, CITIC Telecom International CPC Limited, 20/F, Lincoln House, Taikoo Place, 979 King's Road, Quarry Bay, Hong Kong.\n\nWebsite: http://www.citictel-cpc.com/\n\nAll information received will be kept strictly confidential and for employment-related purpose only.", "employment_types": ["Full Time"], "selling_points": ["Implement sales strategy", "Prepare sales proposal and presentation", "Minimum 8 years relevant experience"], "locations": ["Not Specified"], "categories": ["Admin & HR", "Administration / Operation Manager", "Management", "General Management", "Information Technology (IT)", "IT Management"], "post_time": "2022-01-17T03:14:55Z", "salary": {"currency": null, "max": null, "min": null, "period": "monthly", "term": null}, "salary_visible": false, "title_keywords": ["senior manager", "sales"], "responsibilities": ["collaborate with", "sales reports", "prepare sales", "website", "ad hoc projects", "plan", "administration"], "requirements": {"degrees": ["university graduate"], "majors": ["engineering"], "languages": ["cantonese", "putonghua", "english"], "language_level": ["good command"], "hard_skills": ["pipelines", "ms word", "acumen"], "soft_skills": ["flexible", "comprehensive", "interpersonal skills", "business acumen", "presentation"], "languages_combined": [{"language": "cantonese", "language_level": ["good command"]}, {"language": "putonghua", "language_level": ["good command"]}, {"language": "english", "language_level": ["good command"]}]}, "experience_required": {"duration": ["minimum 8 years"], "field": ["telecommunications", "relevant experience"]}}, {"job_id": "100003009053154", "location_code": "hk", "company": "Hang Yick Properties Management Limited", "job_title": "Senior Property Officer", "description": "Job Description:\nResponsible for all rounded supervision on property management, facility management, manpower development and communication with members of IO/OC.\nTo handle\u00a0emergency incidents, customer enquiries and complaints\nJob Requirement:\n\n\n\nDegree or Diploma holder of Property Management or qualification equivalent to Qualifications Framework;\nMinimum\u00a05 years of experience in property management of which at least\u00a02 years in supervisory capacity;\nWell versed in Building Management Ordinance, especially in relating to the structure of the organization of Owners Incorporation;\nCustomer-oriented and good communication skills;\nGood command of spoken and written English and Chinese;\nAble to work independently and under pressure;\nImmediate available is highly preferred;\nRemuneration will be in commensurate with qualifications and experience. Fringe benefits include birthday leave, marriage leave, paternity leave / 14 weeks\u2019 of maternity leave, full attendance leave, training allowance, newborn baby allowance, medical allowance and other special leave. Please promptly send full resume with expected salary to Human Resources Department at 21/F Well Tech Centre,9 Pat Tat Street, San Po Kong, Kowloon OR by fax 2321-9512.\n\nAll information received will be kept in the strictest confidentiality and only for employment-related purposes within our affiliates.\n\nYou are most welcomed to visit our website www.hy.com.hk.", "employment_types": ["Full Time", "Permanent"], "selling_points": ["Member of Henderson Land Group", "Work from Monday to Friday", "Brilliant Promotion Path"], "locations": ["Shatin Area"], "categories": ["Management", "General Management", "Property / Real Estate", "Property Management", "Others"], "post_time": "2022-01-17T06:18:49Z", "salary": {"currency": null, "max": null, "min": null, "period": "monthly", "term": null}, "salary_visible": false, "title_keywords": ["senior property officer"], "responsibilities": ["communication", "management", "customer enquiries and complaints"], "requirements": {"degrees": ["diploma holder", "degree"], "majors": [], "languages": ["english", "chinese"], "language_level": ["good command"], "hard_skills": ["hy"], "soft_skills": ["communication skills", "customer-oriented", "under pressure", "work independently"], "languages_combined": [{"language": "english", "language_level": ["good command"]}, {"language": "chinese", "language_level": ["good command"]}]}, "experience_required": {"duration": ["at least 2 years", "minimum 5 years"], "field": ["management", "supervisory"]}}, {"job_id": "100003009052205", "location_code": "hk", "company": "Equinix Hong Kong Ltd", "job_title": "Senior Sales Manager, FSI", "description": "Responsibilities\n\nSuggest, assist in identify, setting up sales strategy\nSet up sales plan in order to archive sales target required by the company.\nDetailing sales action plan to ensure that the target will be achieved on a monthly, quarterly and annual basis.\nSupport, motivate staff member to achieve individual and team target\nSupervise daily work of sales staff\nLiaise closely with HR department in solving daily HR issues including discipline compliance, work attitude, etc.\nBuild up good relationship with service provider in Telco and IT industries.\nProspect for new customers, sell the Equinix value proposition and manage customer acquisition process throughout sales cycle\nManage the assigned existing customers to increase their spending, reduce churn, and ensure maximum profitability of customers\nDeliver business value with handling quotation, site tours and contracts to potential customers\nUnderstand customer's IT requirements, Organization structures and Decision Making Process to identify opportunities and provide Equinix solutions.\nWork closely with other job functions in the company to improve the overall customer satisfaction level.\nTimely, comprehensively and accurately update Sales Force Dot Com (SFDC) to ensure the management team has the detailed records on every customer activities.\nCollect and report market intelligence, such as competitor activity, market pricing and demand trends.\nOther duties reasonably relating to this position\n\nRequirements\n\nDegree holder or equivalent\nMinimum 15 years in sales with a minimum of 8 years in supervising position, preferably in telecommunications and IT industry\nProven track record in driving team for hunting new business in Hong Kong, Taiwan and Southern China\nBe able to articulate the company\u2019s value proposition and formulate strategy for differentiation over competition\nKnowledge of selling through Telco and IT industries to their end-users and various channel models\nPrior working experience in MNC sales and matrix organization\nSolid experiences and senior contacts with Banking, Finance, Security and Insurance (BFSI) industry\nGood written and verbal communication skill in English, Cantonese and Mandarin is a must\nGood presentation skill\nExcellent communication and customer interaction skills\nAble to work well under pressure, and with team members in other parts of the organization\nComputer knowledge, familiar with Microsoft Office, SFDC", "employment_types": ["Full Time"], "selling_points": ["Supervise daily work of sales staff", "Set up sales plan", "15 years in sales"], "locations": ["Not Specified"], "categories": ["Management", "General Management", "Marketing / Public Relations", "Marketing - Marketing Communication"], "post_time": "2022-01-17T02:27:45Z", "salary": {"currency": null, "max": null, "min": null, "period": "monthly", "term": null}, "salary_visible": false, "title_keywords": ["senior sales manager"], "responsibilities": ["liaise", "management team", "other duties", "contracts", "sales target", "compliance", "hr", "quotation", "good relationship", "plan", "report"], "requirements": {"degrees": ["degree holder"], "majors": [], "languages": ["cantonese", "english", "mandarin"], "language_level": ["good"], "hard_skills": ["presentation skill", "microsoft office"], "soft_skills": ["presentation skill", "under pressure", "communication skill", "communication", "articulate"], "languages_combined": [{"language": "cantonese", "language_level": ["good"]}, {"language": "english", "language_level": ["good"]}, {"language": "mandarin", "language_level": ["good"]}]}, "experience_required": {"duration": [], "field": ["finance", "insurance", "security", "banking"]}}, {"job_id": "100003009046186", "location_code": "hk", "company": "Hong Kong Arts Development Council", "job_title": "Business Development & International Programmes Senior Manager (Job ref: BDIPSM-2205-JDB)", "description": "We are now looking for a Senior Manager who will be responsible for business development and international programmes of the Hong Kong Arts Development Council. He/she reports directly to the Chief Executive and assists in devising, implementing and evaluation of large-scale activities. He/she will be a leader of several teams in carrying out proactive projects and schemes under his/her charge.\n\nRequirements:\n\nUniversity degree with at least 8 years of relevant full-time working experience in arts and culture, including project management experience;\nStrong administrative, analytical and strategy development capacity and skills;\nExcellent communication skills in both written and spoken English and Chinese;\nStrong sense of responsibility, self-motivation and an aptitude for innovation and change;\nProven achievements that demonstrate professional capabilities in organization, arts administration, proactiveness and people management;\nReadiness to work under pressure and deliver work of the highest quality;\nProficiency in PC operations (MS Office applications and Chinese Word Processing);\nPrevious experience with NGOs and public organisations will be an added value\n\nSalary offered will be commensurate with qualifications and experience. Interested persons please send CV with details on education and work experience, stating salary history and expected salary, and indicating your earliest availability to the Human Resources Department, 10/F, 1063 King\u2019s Road, Quarry Bay, Hong Kong no later than 4 February 2022. Please quote the job reference on the envelope.\n\nApplicants not invited for interview within 16 weeks from the closing date for application may assume that their applications are unsuccessful. Personal data collected will be treated in strictest confidence and will only be used for recruitment purposes. HKADC reserves the right to consider late applications and not to make appointment for the post advertised. We do not accept applications through e-mail or fax.\n\nHKADC is an Equal Opportunities Employer", "employment_types": ["Full Time", "Permanent"], "selling_points": [], "locations": ["Quarry Bay"], "categories": ["Sales, CS & Business Devpt", "Business Development", "Others", "Entertainment - Artists / Singers / Musicians", "Management", "General Management"], "post_time": "2022-01-14T06:46:35Z", "salary": {"currency": null, "max": null, "min": null, "period": "monthly", "term": null}, "salary_visible": false, "title_keywords": ["senior manager"], "responsibilities": ["management", "work under pressure", "operations", "teams", "quality", "communication", "project management", "reports", "recruitment", "evaluation", "personal data", "administration"], "requirements": {"degrees": ["university degree"], "majors": ["project management"], "languages": ["english", "chinese"], "language_level": ["excellent", "proficiency"], "hard_skills": ["no", "chinese word processing", "pc operations", "project management", "make", "ms office"], "soft_skills": ["communication skills", "confidence", "responsible", "sense of responsibility", "project management", "self-motivation", "proactive", "work under pressure"], "languages_combined": [{"language": "english", "language_level": ["excellent"]}, {"language": "chinese", "language_level": ["excellent", "proficiency"]}]}, "experience_required": {"duration": ["at least 8 years"], "field": ["project management", "human resources", "education"]}}, {"job_id": "100003009052619", "location_code": "hk", "company": "Panda Hotel", "job_title": "Front Desk Team Leader", "description": "Responsibilities:\n\nTo check-in and check-out room guests\nTo be familiar with the hotel\u2019s services and facilities and have accurate city information\nTo supervise Front Desk Service Associates to perform duties\n\nRequirements:\n\nF.5 or Certificate / Diploma holder in Hospitality Management or related disciplines\nMinimum 3 years Front Desk experience in Hotel industry\nFamiliar with reception and cashier function, able to supervise Front Desk Service Associates to perform duties\nGood interpersonal skill and customer-oriented\nFluent in spoken and written English and Chinese (both Cantonese and Putonghua)\n\nFringe Benefit:\n\nFree Duty Meal\n12 days Annual Leave\nBirthday Leave\nMarriage Leave\nFull Paid Paternity Leave\nMedical Benefits (Outpatient and Hospitalization)\nStaff Dining Privileges\nStaff Rates on Hotel Guest Room\nExternal Training Subsidy\nDiscretionary Bonus\n\nAs a family-friendly employer, we offer attractive remuneration package and fringe benefits to the right candidates. Interested parties can apply\u00a0with full resume and expected salary\u00a0to Human Resources & Training Department at email [via APPLY NOW] \u00a0", "employment_types": ["Full Time"], "selling_points": [], "locations": ["Tsuen Wan Area"], "categories": ["Management", "General Management", "Hospitality / F & B", "Hospitality / Hotel Services", "Others"], "post_time": "2022-01-17T03:34:25Z", "salary": {"currency": null, "max": null, "min": null, "period": "monthly", "term": null}, "salary_visible": false, "title_keywords": ["team leader"], "responsibilities": [], "requirements": {"degrees": ["diploma holder", "certificate"], "majors": ["hospitality management", "related disciplines"], "languages": ["cantonese", "putonghua", "english", "chinese"], "language_level": ["fluent"], "hard_skills": [], "soft_skills": ["perform duties", "customer-oriented", "interpersonal skill"], "languages_combined": [{"language": "cantonese", "language_level": ["fluent"]}, {"language": "putonghua", "language_level": ["fluent"]}, {"language": "english", "language_level": ["fluent"]}, {"language": "chinese", "language_level": ["fluent"]}]}, "experience_required": {"duration": ["minimum 3 years"], "field": ["front desk", "hotel industry"]}}, {"job_id": "100003009045823", "location_code": "hk", "company": "China CITIC Bank International Limited", "job_title": "Assistant General Manager, IT Applications", "description": "Job Purpose\n\n\nManage assigned application development teams to implement and support application systems for various BU/SU.\n\n\nResponsibilities\n\n\nSupport the team head to determine the automation strategy, prepare long term IT development plan, defines IT standards, procedures and guidelines, and ensures they are all strictly followed.\nManage the enhancement of the all TMG systems in order to boost the business growth.\nClosely communicate with the users side to understand the series of new treasury products\nProvide sound technical advice and guide Application Team to support overall business planning of the Bank. Work closely with business and support units to expand various business and improve operational accuracy and efficiency.\nProvide technical insights for management to define IT strategy and direct teams to follow the established strategies.\nPlan, select, acquire, allocate, and control resources to produce the best price performance application system.\nBuild a highly motivated, competent and professional team to support business needs.\nEnsure system stability and reliability without interruption to customers, business and operation.\nEnsure procedures, guidelines and compliance rules are strictly followed.\nReview peer ideas and contributes solution in line with the IT Architecture Solution.\nParticipate in regular change review board and comprehensively review important production implementation process in order to achieve least service impact.\nDevelop the high-level project plan, sets objectives, identifies resources, resolve constraint and delivers good quality application systems.\nManage application software development projects covering a wide spectrum of banking services.\nApprove, review, supervise all application development work to ensure good quality results are delivered that meet the business expectation.\nEvaluate, identify potential challenges and develops contingency plan to minimize business risks.\nConduct survey/study of emerging technology and makes recommendation on how the new technology may be applied to benefit the Bank business.\nEvaluate user requests and recommends solution to the end-user (business). Review technical solution proposal for an optimal cost effective investment.\nDevelop appropriate methodology to improve efficiency in the whole system development life cycle.\nNegotiate with vendors and users to ensure the developed/acquired application software is cost effective.\nDevelop appropriate methodology to improve efficiency in the whole system development life cycle.\nProvide technical support to ensure smooth 24 hours round-the-clock operation (including Disaster Recovery Site support) within the Bank.\nDevelop, coach and mobilize resources and re-prioritize activities across sub-teams to deal with the fluctuating demand from rapid business changes.\nTrain/equip application development staff and ensures they have the ability to perform the required development work and can face the ever-changing technology.\nWorks out development plan for and provides coaching to team members as appropriate.\nIdentify and retain talents with career progression plan. Plan back-up and contingency to minimize impact to existing servicing level.\nEnsure audit comments are responded and tackled promptly.\nProvide overseas branches on IT matters in respect of both HO or local compliance related.\n\n\nRequirements\n\n\nDegree holder in Information Technology\nAt least 20 years' experience in application software development with at least 12 years in project management and people management.\nAt least 10 years\u2019 experience to manage vendor in project delivery and package maintenance and support.\nRich exposure in various banking applications.\nPreferable with experience to manage multiple sub-teams serving different business domain area.\nCertified PMP is preferable\nExposure to multiple computer platforms, including mainframe and open platform etc.\nIn-depth knowledge of the Banking industry and various banking products\nManage major and sizable projects experience\nManage multiple vendors experience\n\nFor more details about career opportunities with the Bank, please visit our website http://www.cncbinternational.com/careers/en/index.jsp. Please apply with full resume stating current and expected salaries.\n\nPersonal data collected will be used for recruitment related purposes only. Applicants not invited for interview within 6 weeks may consider their applications unsuccessful. However, applicants may be considered for other suitable positions within the Group for a period of not more than 2 years. Personal data will be destroyed at any time after 3 months.\n\nChina CITIC Bank International is committed to being an equal opportunities employer and intends to provide a work environment free of unlawful discrimination or harassment. All employment decisions will be made in a non-discriminatory manner.", "employment_types": ["Full Time"], "selling_points": [], "locations": ["Not Specified"], "categories": ["Management", "General Management", "Information Technology (IT)", "Support", "Software Development"], "post_time": "2022-01-13T08:49:00Z", "salary": {"currency": null, "max": null, "min": null, "period": "monthly", "term": null}, "salary_visible": false, "title_keywords": ["assistant general manager"], "responsibilities": ["ideas", "software", "technical advice", "system stability", "quality", "audit", "plan", "application systems", "application development", "control", "compliance", "teams", "application system", "develop", "banking", "architecture", "support business needs", "management", "cost", "solution proposal", "review", "procedures", "support the team", "communicate with", "production implementation", "guidelines", "technical support", "systems", "comments", "project plan", "evaluate", "planning"], "requirements": {"degrees": ["degree holder"], "majors": ["information technology"], "languages": [], "language_level": [], "hard_skills": ["project management", "pmp", "vendor", "maintenance"], "soft_skills": ["project management", "committed"], "languages_combined": []}, "experience_required": {"duration": ["at least 10 years", "at least 12 years", "at least 20 years"], "field": ["maintenance", "project management", "people management", "business", "software development"]}}, {"job_id": "100003009047939", "location_code": "hk", "company": "The University of Hong Kong", "job_title": "Senior Technical Manager/Technical Manager I (Ref.: 511345)", "description": "Work type:\u00a0Full-time\nDepartment:\u00a0Project Division of the Estates Office (66062)\nCategories:\u00a0Professional & Management, Executive / Technical / Support\n\nApplications are invited for appointment as\u00a0Senior Technical Manager/Technical Manager I\u00a0(3 posts) in the Project Division of the Estates Office\u00a0(Ref.: 511345), to commence as soon as possible, on a two- or three-year fixed-term basis, with the possibility of renewal subject to satisfactory performance.\n\nTo cope with the increasing workload on different projects, we are looking for high calibre professional to fill the posts. \u00a0Reporting to the Director of Estates and working under the Assistant Director of Estates, the appointees will work in conjunction with the project management team to oversee the design, contractual and financial aspects of the projects.\n\nApplicants should:\u00a0(a) have a good university degree in Architecture, Building Services or a related discipline, and relevant professional qualifications;\u00a0(b) have demonstrated record in leadership with at least 10 years\u2019 post-professional qualification experience in managing large-scale building projects, of which at least 5 years must be at a managerial position;\u00a0(c) be conversant with the local statutory regulations and dealing with Government subvention procedures;\u00a0(d) have excellent communication, analytical and leadership skills as well as the ability to work independently and to develop solid relationship with internal and external stakeholders; and\u00a0(e) possess a valid Construction Industry Safety Training Certificate (Green Card) issued in accordance with Chapter 59 of the Factories and Industrial Undertakings Ordinance (i.e. by attending the relevant safety training courses which are recognized by the Commissioner for Labour), or equivalent.\u00a0\u00a0Those with relevant experience in higher education facilities and campus development would have an advantage.\u00a0\n\nApplicants with less experience or lower qualifications may be considered for appointment as Technical Manager I.\n\nA highly competitive salary commensurate with qualifications and experience will be offered, in addition to annual leave and medical benefits.\u00a0 At current rates, salaries tax does not exceed 15% of gross income.\u00a0 The appointment will attract a contract-end gratuity and University contribution to a retirement benefits scheme, totalling up to 15% of basic salary.\u00a0\n\nThe University only accepts online application for the above posts.\u00a0 Applicants should apply online and upload an up-to-date C.V[via APPLY NOW].\u00a0\u00a0Closes\u00a0January 20, 2022.\n\nAdvertised:Dec 30, 2021 (HK Time)\nApplications close:Jan 20, 2022 (HK Time)", "employment_types": ["Full Time"], "selling_points": ["have a good university degree", "relevant professional qualifications", "oversee the projects"], "locations": ["Not Specified"], "categories": ["Building & Construction", "Architectural Services", "Building / Construction / QS", "Management", "General Management"], "post_time": "2022-01-14T04:19:38Z", "salary": {"currency": null, "max": null, "min": null, "period": "monthly", "term": null}, "salary_visible": false, "title_keywords": ["technical manager"], "responsibilities": ["regulations", "reporting", "management", "procedures", "design", "develop", "communication", "project management", "architecture"], "requirements": {"degrees": ["certificate", "university degree"], "majors": ["building services", "architecture"], "languages": [], "language_level": [], "hard_skills": ["project management", "c", "green card", "professional qualifications"], "soft_skills": ["work independently", "leadership skills", "communication", "project management", "leadership"], "languages_combined": []}, "experience_required": {"duration": ["at least 10 years", "at least 5 years"], "field": ["managerial", "development", "relevant experience", "education"]}}, {"job_id": "100003009051188", "location_code": "hk", "company": "Mindset Asia Limited", "job_title": "Sales Expert - Industrial/Manufacturing sector", "description": "Our Client, an international Private Equity, is looking for a high caliber\u00a0sales management expert to lead the sales team and maximise the sales effectiveness in their portfolio companies, to join their management team in Hong Kong.\n\nStrategic Business development\nIndustrial/Manufacturing Sector\nHK/China/Asia markets\nKey Responsibilities\nProvide hands-on sales consulting and monitor the sales prospect development at their portfolio companies\nAble to deep-dive into sales function for project management, due diligence and sales process improvement\nAble to build and lead the sales teams through originating, shaping and driving sales strategy from inception through to budgeting and implementation by working alongside with the portfolio companies\nProvide advice, directions and guidelines to achieve the sales penetration and development to optimize their market share\nMaximize the sales growth opportunities with the portfolio companies\nHigh awareness and sensitive to the changes in market share, perception and competitiveness\nPassionate about customer centricity and highly efficient and effective in working on customer experience and journey\nUnderstand customer supporting filter and the use of the required sales tools such as SalesForce\nExperience/Qualifications\nMinimum 15 years in a strategic business development related role with industrial/manufacturing industry\nUniversity degree holder in Marketing/Business or related discipline\nSolid and extensive experience in business development in launching sales events and programs to grow the market share\nStrong in pricing and negotiation and ability to influence and possess value-driven to direct the sales team to achieve sale targets\nA progressive and growth mindset to explore new opportunities, approach, ideas and perspectives\nEntrepreneurial and self-driven, energetic, problem solver and results oriented\nFlexible and adaptive to meet with the evolving needs of high-growth and fast paced environment\nExcellent in communication and interpersonal skills\nFluent in English, Cantonese and Mandarin are required\n\nInterested parties can apply online by forwarding your resume and quoting the job reference.\u00a0 All applications will be strictly confidential and used for recruitment purposes only", "employment_types": ["Full Time"], "selling_points": [], "locations": ["Not Specified"], "categories": ["Management", "General Management", "Sales, CS & Business Devpt", "Sales - Sales Management"], "post_time": "2022-01-15T04:26:16Z", "salary": {"currency": null, "max": null, "min": null, "period": "monthly", "term": null}, "salary_visible": false, "title_keywords": ["sales"], "responsibilities": ["management team", "due diligence", "ideas", "consulting", "guidelines", "budgeting", "monitor", "teams", "implementation", "communication", "project management", "provide advice", "sales team", "sales management"], "requirements": {"degrees": ["university degree"], "majors": ["business", "marketing"], "languages": ["cantonese", "english", "mandarin"], "language_level": ["fluent"], "hard_skills": ["project management", "salesforce", "private equity"], "soft_skills": ["efficient", "flexible", "negotiation", "problem solver", "deep", "project management", "hands-on", "sensitive to", "communication and interpersonal skills", "progressive", "energetic", "extensive", "driven", "passionate about"], "languages_combined": [{"language": "cantonese", "language_level": ["fluent"]}, {"language": "english", "language_level": ["fluent"]}, {"language": "mandarin", "language_level": ["fluent"]}]}, "experience_required": {"duration": [], "field": ["business development"]}}, {"job_id": "100003009048048", "location_code": "hk", "company": "Manpower Services (Hong Kong) Limited", "job_title": "HR,& Admin Officer/AM_ Professional Association", "description": "Jot Duties:\n\nSupervise the Office Assistants daily\nPerform the duties of the office, warehouse facilities, and security\nArrange the renovation and relocation work\nPerform the duties of recruitment, logistical arrangements for incoming and outgoing staff\nAdminister the personnel record, e.g., attendance, leave records, emergency contact, organization chart, etc.\nAssist in Compensation & Benefits administration\nAssist in preparing and monitoring the Administration and Human Resources Annual Budget and Expenses\nReview and update various AHR policies, procedures, and regulations to ensure compliance with legal requirements\nAssist in the organization of staff events including Staff Dinner, Annual Christmas Dinner, and Spring Dinner, training, and seminar, etc.\nReport to the Assistant Director, Administration, and Human Resources regularly (as the case may be) to the above matters\nUndertake any other duties as may be assigned by the Assistant Director, Administration, and Human Resources and/or the Secretary-General or their duly authorized representatives.\nResponsible to prepare a simple staff newsletter (e.g., Put short description + photos)\u00a0\n\nRequirements:\n\nA degree holder with at least 7 years or above relevant experiences in NGO, Professional Association, Government\nGood command of written and spoken English and Chinese, including proficiency in Mandarin\nIndependent, strong communication skills, and able to multi-task and work under pressure\n\nInterested parties, please send your resume in MS WORD format with current and expected salary and notice period to\u00a0charlton.chan@manpowergrc.hk", "employment_types": ["Permanent"], "selling_points": ["NGO/Professional Asso/HKGovt/Newspaper Experiences", "Experiences in Administration and Human Resources", "Excellent in English and Chinese"], "locations": ["Central & Western Area"], "categories": ["Admin & HR", "Secretary", "Management", "General Management", "HR Supporting Staff"], "post_time": "2022-01-14T04:36:25Z", "salary": {"currency": null, "max": null, "min": null, "period": "monthly", "term": null}, "salary_visible": false, "title_keywords": ["officer", "hr", "admin"], "responsibilities": ["logistical arrangements", "renovation", "recruitment"], "requirements": {"degrees": [], "majors": [], "languages": [], "language_level": [], "hard_skills": [], "soft_skills": [], "languages_combined": []}, "experience_required": {"duration": [], "field": []}}, {"job_id": "100003009049216", "location_code": "hk", "company": "Arrow Asia Pac Ltd", "job_title": "Senior Business Process Manager", "description": "What You'll Be Doing\n\nAct as the right-hand person to senior executive to provide solid analytical support to help understand business performance and formulate strategic initiatives\nFormulating strategic planning process, rolling out business process excellence and setting ambitious & achievable goal for the business\nWork closely with senior executives in business management and supplier management, provide timely and thoughtful handling,\nInvolve in formulating budget setting, implement ad-hoc projects, meeting coordination, presentation preparation, and agenda planning\nOversee an end-to-end project management cycle and be accountable for project deliverables and timeline, able to identify potential risks and proactively recommend solutions\nKeep abreast of business situations and market trends, provide most updated market information to identify business opportunities to drive growth strategies\nOptimize organizational productivity and performance by leveraging resources\nInvolve and facilitate business meetings/conferences and business development activities, including the creation of agendas and preparation of materials\n\nWhat We Are Looking For\n\nBachelor\u2019s degree or above in any related discipline\n10 years or above experience in business planning and business process improvement projects excellent\nGood communication and presentation skills in both English and Chinese\nPossess acute business acumen, strong analytical and problem-solving skills\nStrong organizational and interpersonal skills that able to perform and prioritize multiple tasks and build relationships with stakeholders\nDemonstrate proactiveness in problem-solving and decision-making\nExcellent attention to detail\nAble to achieve high performance goals and meet deadlines in a fast-paced environment\nCandidate with less experience would be considered as Business Manager.\n\n\n\nWhat\u2019s In It For You\n\nAt Arrow, we recognize that financial rewards and great benefits are important aspects of an ideal job. That\u2019s why we offer competitive financial compensation, including various compensation plans, and a solid benefits package.\n\nDouble Pay\nPerformance Bonus\nMedical & Dental\nLife Insurance\nMPF with additional employer contributions\nPaid Time Off\nFree Shuttle to HKSTP Office\n5-Day Work Week\nGrowth Opportunities\nAnd More!", "employment_types": ["Full Time", "Permanent"], "selling_points": ["Fortune 102 US Company", "Competitive package and benefit", "Right-hand person to senior executive"], "locations": ["Shatin Area"], "categories": ["Admin & HR", "Administration / Operation Manager", "Management", "General Management"], "post_time": "2022-01-14T08:16:51Z", "salary": {"currency": null, "max": null, "min": null, "period": "monthly", "term": null}, "salary_visible": false, "title_keywords": ["manager"], "responsibilities": ["management", "market information", "strategic planning", "identify business opportunities", "project deliverables", "budget", "identify potential risks", "project management", "conferences", "business process", "communication", "coordination", "ad-hoc projects", "planning"], "requirements": {"degrees": ["degree or above", "bachelor"], "majors": [], "languages": ["english", "chinese"], "language_level": ["good"], "hard_skills": ["business management", "problem-solving", "goal", "project management", "problem-solving skills", "acumen"], "soft_skills": ["multiple tasks", "fast-paced environment", "organizational", "timely", "problem-solving", "accountable", "prioritize", "communication", "project management", "presentation skills", "interpersonal skills", "coordination", "attention to detail", "business acumen", "problem-solving skills", "meet deadlines", "presentation"], "languages_combined": [{"language": "english", "language_level": ["good"]}, {"language": "chinese", "language_level": ["good"]}]}, "experience_required": {"duration": ["10 years"], "field": ["business", "planning"]}}, {"job_id": "100003009050077", "location_code": "hk", "company": "Yew Chung College of Early Childhood Education Limited", "job_title": "Project Manager", "description": "Position Summary\n\nYCCECE is commissioned to drive a large scale funded project.\u00a0 The Project\u2019s vision is to create and implement a nurturing care model comprises a 0-3 years educate framework, capacity building of practitioners and families, and a digital platform that facilitates home-centre communication. The new model aims to enhance professional practice, infrastructure and overall quality of Child Care Centres in Hong Kong. In addition, the project will cultivate a learning community that encourages and empowers knowledge transfer for sustainable development of holistic nurturing care.\n\nTo actualise this vision, it is crucial to support the operation of various events serving different stakeholders. The job holders will perform the following duties:\n\nEnsure that all project outcomes and outputs are delivered on-time, within scope and within budget;\nDevelop and implement a detailed project plan to monitor and track progress of various project components simultaneously ;\nManage changes to the project scope, project schedule and project costs for the rapid changes in the society;\nActively obtain and coordinate internal resources and third parties/vendors for a smooth implementation of the Project;\nCreate synergy among the Project team and stakeholders (e.g. funder, partnership schools);\nCreate and maintain project documentation, including administrative and budget documents requested by the funder; and\nPerform any other duties as required by the College.\n\nRequirements\n\nThe successful candidate should possess a higher degree, and have teaching and programme leadership or management experience in the education industry.\u00a0\n\nA Bachelor's degree in Social Sciences or Education preferred\nAt least 5 years of proven working experience project management\nExcellent written and verbal communication skills in English and Chinese\nOutstanding project management knowledge and skills, Project Management Professional (PMP) or any equivalent qualifications is a plus\nExperience in managing projects in education or non-profit making sectors is a plus\nProficiency in Microsoft Office and other project management tools (e.g. Trello, Microsoft Planner)\nBe comfortable working with a team of self-driven professionals who value competence and efficiency\n\nSalary and Fringe Benefits:\n\nAppointment will be made on contract basis.\u00a0 Remuneration is competitive and will be based on qualifications and relevant experience. The College offers group medical insurance, annual leave and sick leave, and Mandatory Provident Fund to eligible appointee.\n\nApplication Procedure:\n\nApplicants are invited to:\n\nSubmit an application letter with a full Curriculum Vitae, and copies of all graduate transcripts, and the names and contact details of three references.\nSpecify in the application letter current/latest salary and expected salary\nSend applications to the Yew Chung College of Early Childhood Education by clicking below \"Apply Now\" button.\n\nThe College will review applications immediately.\u00a0 Only shortlisted candidates will be contacted.\n\nImportant notes to Applicants:\n\nAppointees will have to undergo a medical examination.\u00a0 Reimbursement of costs subject to a ceiling is applicable.\nLocal applicants will have to undergo a Sexual Conviction Record Check. Overseas applicants will have to present a police report before appointment can be confirmed.\u00a0\nSatisfactory employment reference is required before appointment can be confirmed.\n\nThe College also reserves the right to make an appointment by invitation.\n\nPersonal data collected will be used for recruitment-related purposes only.", "employment_types": ["Full Time", "Contract"], "selling_points": ["Project for 0-3 years education framework", "Project Management", "Experience in managing projects in education"], "locations": ["Aberdeen"], "categories": ["Admin & HR", "Administration / Operation Manager", "Management", "General Management", "Public / Civil", "Social Services - Community / Non-profit Organization"], "post_time": "2022-01-14T09:44:14Z", "salary": {"currency": null, "max": null, "min": null, "period": "monthly", "term": null}, "salary_visible": false, "title_keywords": ["project manager"], "responsibilities": ["any other duties", "management", "infrastructure", "quality", "budget", "digital platform", "develop", "communication", "project plan", "monitor", "coordinate", "implementation", "schedule", "maintain", "project management", "costs", "project documentation"], "requirements": {"degrees": ["degree", "bachelor"], "majors": ["social sciences"], "languages": ["english", "chinese"], "language_level": ["excellent"], "hard_skills": ["planner", "plus", "project management professional", "microsoft office", "project management", "rapid", "documentation", "pmp"], "soft_skills": ["communication skills", "communication", "project management", "learning", "smooth", "leadership", "driven", "detailed"], "languages_combined": [{"language": "english", "language_level": ["excellent"]}, {"language": "chinese", "language_level": ["excellent"]}]}, "experience_required": {"duration": ["at least 5 years"], "field": ["project management", "management", "teaching", "education"]}}, {"job_id": "100003009050784", "location_code": "hk", "company": "EDP Consultants Hong Kong Limited", "job_title": "APAC Security Project Coordinator", "description": "Role Overview\n\nOur client is a truly global business and is one of the world\u2019s most recognisable social media and technology companies. EDP provides the client with embedded corporate security support within the APAC region and we are looking to expand our team by appointing a person specialising in the effective coordination of security projects within the APAC region.\n\nThe Project Coordinator will assist by tracking team projects and tasks using internal tools to ensure timely completion of deliverables and accurate capture of metrics; while also providing project support to new and ongoing initiatives. The Project Coordinator will provide general project coordination in support of the execution and implementation of initiatives for the Client Team.\n\nThe Project Coordinator will support the Global Security Services (GSS) Team as a primary, with added scope for second-line support provided to the wider Global Security Organisation within APAC. GSS\u2019s mission is to protect the people, assets, and reputation of the organization.\n\nPlease note that working at the client site is required Monday to Friday.\n\nThis role will be located in the client\u2019s Hong Kong office.\n\nResponsibilities and Activities Include But Are Not Limited To:\n\nDevelop insightful recommendations to address complex operational and strategic problems.\nParticipate in the evaluation of the impact of proposed changes, with attention to scalability and sustainability over time.\nResponsible for delivering superior support to the Global Security Services leadership team.\nCreate project plans and build consensus among diverse sets of stakeholders.\nCoordinate cross-functional projects from outline to implementation.\nCost management experience and Finance coordination as requested to support the projects\nWorking with SME\u2019s in supporting the projects\nDesign standardized processes and Best Practices from initiation to completion in partnership with SMEs, including project scope, documentation, measurements, communication and implementation to global security leaders and teams.\nProvide key business partners with information and recommendations to assist in the development and implementation of training resources and plans.\nResearch and evaluates industry standards and benchmarks to support project (as needed).\nFoster strong partnerships at all levels\nEffectively prioritize workload demands to meet project deadlines\nDevelop sustainable Best Practices, Process Knowledge Documents and Standards intended for security teams globally\nProof and edit communications, Best Practice documents, resource tools and trainings\nCreative formatting of web-based training templates and knowledge articles, business reviews and presentation documents\nCreate sustainable communication themes in conjunction with systematic routines, processes, and preparedness activities for security teams to execute consistently\n\nQualifications: Experience:\n\nDemonstrated project management skills that drive results.\nHave minimum 3 years project management experience at supervisory level and above.\nDemonstrated leadership skills in a cross-functional capacity.\nKnowledge of processes & procedures development.\nExcellent communication and presentation skills.\nStrong analytical and critical thinking skills.\nHighly motivated and able to work independently as well as in a team environment.\nStrong Written and Verbal Communication Skills.\nAbility to take initiative and achieve results.\nAbility to facilitate progressive change\nAbility to carry out multiple assignments concurrently work under stressful and tight deadlines as well as the ability to manage in a fast-paced environment\nSecurity programs experience an advantage\n\nSystems:\n\nProficient with MS and Google Office Suites Experience\nExperience with Project Management applications (ASANA, Basecamp, Microsoft Project)\nKnowledge of Security systems an advantage (Access Control, CCTV)\n\nEducation:\n\nThird level education and 3+ years of equivalent practical experience.\nPMP / PRINCE2\n\nAdditional Requirements:\n\nAvailability to travel approx. 25 % of the time. Availability to perform other tasks as required\n\nWorking Conditions and Physical/Mental Demands\n\nWith or without reasonable accommodation, a candidate must have the physical and mental capacity to effectively perform all essential functions described. In addition to other demands, the demands of the job include:\n\nMaintaining composure in dealing with executives, clients, staff, and the public, occasionally under conditions of urgency and in pressure situations\nSuccessfully pass background, reference, behavioural selection survey, and controlled substance tests.\nHandling and being exposed to sensitive and confidential information\nMight involve international travel (involving several nights staying away from home) in the performance of duties.\nConducting oral presentations and group meetings\nReading and analysing reports and other data and metrics, including related computer usage\nResponding on an on-call basis to emergencies\n\nSalary\n\nA competitive salary is offered in-line with experience and qualifications. Private medical insurance and a discretionary bonus structure is also included.\n\nApplication Process\n\nIf you are interested in the role, please submit your CV. Please state your existing salary within your application.", "employment_types": ["Full Time"], "selling_points": ["Demonstrated project management skills", "Excellent communication and presentation skills", "Strong analytical and critical thinking skills"], "locations": ["Not Specified"], "categories": ["Management", "General Management"], "post_time": "2022-01-14T11:22:09Z", "salary": {"currency": "HKD", "max": 44999, "min": 35000, "period": "monthly", "term": null}, "salary_visible": true, "title_keywords": ["project coordinator"], "responsibilities": ["cost", "management", "documentation", "systems", "teams", "implementation", "design", "develop", "coordinate", "communication", "project management", "procedures", "formatting", "coordination", "evaluation", "sme", "plans", "access control"], "requirements": {"degrees": [], "majors": [], "languages": [], "language_level": [], "hard_skills": ["presentations"], "soft_skills": ["oral", "urgency", "interested in", "sensitive", "controlled"], "languages_combined": []}, "experience_required": {"duration": [], "field": []}}, {"job_id": "100003009054612", "location_code": "hk", "company": "Sun Life Hong Kong Ltd", "job_title": "Management Trainee Program (Degree Holder in Any Disciplines)", "description": "Job Highlights\n\nBachelor degree holder in all disciplines\nWell-development career ladder\nFive-day work\n\nJob Description\n\nYou will enjoy working at Sun Life if you are with vision, energy and targets, join us and be part of a dynamic team and create values together.\n\nAs the leader in wealth management, offering innovative and intelligent solutions to thousands of individual and businesses in Hong Kong, China, Canada, Malaysia, Indonesia and other high growth cities around the world. We keep our clients\u2019 interests foremost in our minds at all times. This combination of intellectual capital, comprehensive training, staffed with quality leaders and professional managers set us apart as an industrial leader.\n\nWe are currently seeking young and energetic talents\u00a0to join our team as a\u00a0Management Trainee.\n\nJob Responsibilities\n\nProvide professional financial services to our clients, including risk management, health protection, retirement planning and wealth accumulation\nManaging the total wealth of clients by matching our financial and investment solutions to fulfill their financial needs\nClients relationship management, expand clients\u2019 network and review their financial need regularly\nPromoting our Premier Service to potential clients, exploring their needs and making referrals to other business units where appropriate\u00a0\n\nBenefits and Packages\n\nFive-day work\nCompetitive Pay With Quarterly Bonus and Year End Bonus\nInitial Training and On-Job Training Provided\nExcellent Career Path to Management Ladder\nLife and Medical Insurance\nClient Base Provided\u00a0\nFlexible Working Hours\u00a0\nEducation Subsidies\n\nRequirements\n\nBachelor degree or above (Fresh graduates is welcomed)\n1 year working experience or above is preferred\nExperience in\u00a0customer service or sales field\nProactive with positive mindset, excellent interpersonal &\u00a0communication skills\nAble to work independently\nFluent in Cantonese, moderate English\u00a0\n\nWorking Location\n\n\n\nWhampoa\u00a0\n\n**Personal date provided by applicants will be treated in strict confidence and used for recruitment purposes only**\n\nIf you have any further enquiries, please press\u00a0APPLY NOW\u00a0to contact us with your CV. We will get back to you shortly.", "employment_types": ["Full Time"], "selling_points": ["5 day works", "$17,000-$30,000", "Competitive pay"], "locations": ["Hung Hom"], "categories": ["Banking / Finance", "Corporate Finance", "Management", "General Management", "Marketing / Public Relations", "Management"], "post_time": "2022-01-17T10:14:23Z", "salary": {"currency": "HKD", "max": 29999, "min": 17000, "period": "monthly", "term": null}, "salary_visible": true, "title_keywords": ["management trainee"], "responsibilities": ["management", "review", "quality", "planning"], "requirements": {"degrees": [], "majors": [], "languages": [], "language_level": [], "hard_skills": [], "soft_skills": [], "languages_combined": []}, "experience_required": {"duration": [], "field": []}}, {"job_id": "100003009048013", "location_code": "hk", "company": "Hong Kong Sheng Kung Hui Welfare Council Limited", "job_title": "Senior Managers/Managers on Public Relations & Communications (CA/SPRCM/PRCM/20210910-3)", "description": "Reporting to the Director and working closely with senior management, the incumbent will be responsible for leading the Public Relations & Communications Department in the planning and implementation of internal and external communications inclusive event and brand management, brand and engagement programmes and media management.\n\n\nResponsibilities:\n\n\nFormulate and implement comprehensive public relations & communication strategies and plans to position the Welfare Council as an innovative and caring organization in social welfare sector;\nDesign and produce materials to effectively communicate the Welfare Council\u2019s vision, mission, values and programme activities to general public;\nBuild up a brand awareness and enhance the image of the Welfare Council via different social media, events, campaigns and programmes, its services, activities and research, for enhancement of its reputation in the community;\nWork closely with Resources Development Department to formulate fund raising strategies and establish relationship with donors and the community;\nDevelop and maintain professional network, and maintain relationships with external partners, stakeholders and mass media;\nLiaise and communicate with the media, and manage media activitiesincluding press invitation, press releases and conferences, briefings, interviews, etc.;\nServe as media advisor in crisis management.\n\nRequirements :\n\nBachelor degree or above in Public Relations / Marketing / Communications or related disciplines\nMinimum 8 years\u2019 relevant and solid experience in journalism, corporate communications or public relations, preferably with experiences in social services sector or non-governmental organization\nAble to explore complex ideas and turn it to comprehensive and interesting story\nSelf-motivated, out-going, presentable and creative person, with good analytical and organizing skills\nGood command of both spoken and written English, Cantonese and Mandarin\nExperience in digital media communication and staff supervision is preferred\nCandidates with less experience will be considered as Public Relations & Communications Manager\n\nTwo-year contract will be offered as a start. Candidates with satisfactory performance will be reappointed to permanent post after the first contract.\n\n\n\nInterested parties please apply with full curriculum vitae with Expected Salary and Available Date to Human Resources Department, Hong Kong Sheng Kung Hui Welfare Council, 5/F, Marina House, 68 Hing Man Street, Shaukeiwan, Hong Kong or click \"Apply Now\". Please indicate the reference number on the envelope.\n\nApplications will be reviewed upon receiving and continue until 7 February 2022 or until the post is filled.\u00a0All applications will be treated in strict confidence for the recruitment purpose only.\u00a0 Candidates not invited for interview within 8 weeks may consider their applications unsuccessful, and the application papers will be retained for a maximum period of 6 months.", "employment_types": ["Full Time", "Contract"], "selling_points": [], "locations": ["Wan Chai"], "categories": ["Management", "General Management", "Marketing / Public Relations", "Public Relations - General / Support", "Public / Civil", "Social Services - Community / Non-profit Organization"], "post_time": "2022-01-14T04:29:57Z", "salary": {"currency": null, "max": null, "min": null, "period": "monthly", "term": null}, "salary_visible": false, "title_keywords": [], "responsibilities": ["maintain relationships", "social media", "liaise", "communicate with", "design", "develop", "communication", "conferences", "maintain", "plans", "crisis management"], "requirements": {"degrees": ["degree or above", "bachelor"], "majors": ["related disciplines", "marketing", "communications"], "languages": ["cantonese", "english", "mandarin"], "language_level": ["good command"], "hard_skills": [], "soft_skills": ["self-motivated", "presentable", "communication", "comprehensive", "creative"], "languages_combined": [{"language": "cantonese", "language_level": ["good command"]}, {"language": "english", "language_level": ["good command"]}, {"language": "mandarin", "language_level": ["good command"]}]}, "experience_required": {"duration": ["minimum 8 years"], "field": ["digital media", "public relations"]}}, {"job_id": "100003009049302", "location_code": "hk", "company": "State Street Asia Ltd", "job_title": "GM Product Implementation, Vice President", "description": "Who We Are Looking For\n\nGlobal Markets Product Implementation\u2013VP executes a complex portfolio of initiatives, comprehensively delivering product and infrastructure to our State Street Global Markets business teams. The Product Implementation team encompasses all aspects of the business: strategy development and implementation; client facing product development and implementation, trading infrastructure systems design and implementation of operational models; risk oversight and metrics and reporting; The incumbent will work with business leaders to implement strategic and tactical initiatives, will partner with technology, operations and other business partners to deliver product and infrastructure aligned with our strategic goals and regulatory requirements.\n\nWhy this role is important to us\n\nThe team you will be joining is a part of State Street Global Markets (SSGM). When owners and managers of institutional assets need research, trading, securities lending and innovative portfolio strategies, they turn to SSGM business unit. As our investment research and trading arm, SSGM\u2019s number one goal is to enhance and preserve our clients\u2019 portfolio values by applying technology, optimizing trading, and linking asset classes and markets across the world.\n\nJoin us if making your mark in capital markets industry from day one is a challenge you are up for.\n\nWhat You Will Be Responsible For\n\nAs Product Implementation you will\n\nPartner with business leaders to identify product and features necessary for the successful implementation of strategy and initiatives.\nTranslate business strategic vision into functional product plans a\nUsher product through internal governance and regulatory\nDefine product features and develop product overviews, workflows and visual artifacts to crystalize product use, and process owners.\nWork with technology to drive technology solutions and deliverables to meet product requirements\nManage technology and other business partner demand and help resolve competing priorities\nDevelop product roadmap identifying key business milestones and required timelines\nBuild strong relationships with business partners (i.e Legal, Compliance, Operations, IT, Finance, Procurement etc.) and ensure they understand business needs to create robust and sustainable solutions. Manage internal relationships and communications with business partners.\nBe a subject matter expert for the trading businesses across initiatives and projects.\nUnderstand the full trading flow life cycle, be able to anticipate Front Office multi-year requirements and articulate the objectives and priorities of the business\nResolve significant issues or roadblocks working with senior management across the bank as required.\nReview, analyze, and evaluate business and user needs in order to recommend solutions and options.\nDevelop and execute projects and ensure appropriate resource allocations to meet changing needs and requirements.\nIdentify and frame risks and issues as well as ensure their timely resolution or escalation.\nDefine the workflows, processes, policies and procedures utilized to conduct our trading businesses\nEffectively, communicate, collaborate and manage relationships with diverse stakeholders with varied interests.\nResearch and keep abreast of industry trends and upcoming changes brought about by competitive, market and or regulatory influences.\nWhat We Value\n\nThese skills will help you succeed in this role\n\nDemonstrated success executing projects and business portfolios within complex organizational settings.\nDemonstrate capability to interact, negotiate and influence at all levels of management and across the organizations.\nOutstanding organizational, analytical, and consultative abilities.\nEducation & Preferred Qualifications\n\nBachelor\u2019s Degree (MBA pref)\nSubject matter expertise in trading and capital markets.\n5-10 years industry experience\nDemonstrated success executing projects and business portfolios within complex organizational settings.\nDemonstrate capability to interact, negotiate and influence at all levels of management and across the organizations.\nOutstanding organizational, analytical and consultative abilities.\nAbout State Street\n\nWhat we do.\u00a0State Street is one of the largest custodian banks, asset managers and asset intelligence companies in the world. From technology to product innovation we\u2019re making our mark on the financial services industry. For more than two centuries, we\u2019ve been helping our clients safeguard and steward the investments of millions of people. We provide investment servicing, data & analytics, investment research & trading and investment management to institutional clients.\n\nWork, Live and Grow.\u00a0We make all efforts to create a great work environment. Our benefits packages are competitive and comprehensive. Details vary in locations, but you may expect generous medical care, insurance and savings plans among other perks. You\u2019ll have access to flexible Work Program to help you match your needs. And our wealth of development programs and educational support will help you reach your full potential.\n\nInclusion, Diversity and Social Responsibility.\u00a0We truly believe our employees\u2019 diverse backgrounds, experiences and perspective are a powerful contributor to creating an inclusive environment where everyone can thrive and reach their maximum potential while adding value to both our organization and our clients. We warmly welcome the candidates of diverse origin, background, ability, age, sexual orientation, gender identity and personality. Another fundamental value at State Street is active engagement with our communities around the world, both as a partner and a leader. You will have tools to help balance your professional and personal life, paid volunteer days, matching gift program and access to employee networks that help you stay connected to what matters to you.\n\nState Street is an equal opportunity and affirmative action employer.\n\nDiscover more at StateStreet.com/careers\n\nJob ID: R-689069", "employment_types": ["Full Time"], "selling_points": [], "locations": ["Not Specified"], "categories": ["Banking / Finance", "Others", "Management", "General Management", "Marketing / Public Relations", "Marketing - Brand / Product Management"], "post_time": "2022-01-14T08:24:37Z", "salary": {"currency": null, "max": null, "min": null, "period": "monthly", "term": null}, "salary_visible": false, "title_keywords": ["vice president"], "responsibilities": ["operations", "regulatory requirements", "design", "plans", "senior management", "collaborate", "communications with", "infrastructure", "teams", "implementation", "compliance", "develop", "resolution", "visual", "reporting", "management", "review", "procedures", "executing", "policies", "systems", "subject matter expert", "evaluate"], "requirements": {"degrees": ["degree", "bachelor"], "majors": [], "languages": [], "language_level": [], "hard_skills": ["goal"], "soft_skills": ["responsible", "organizational", "timely", "robust", "diverse", "articulate", "innovative"], "languages_combined": []}, "experience_required": {"duration": ["5-10 years"], "field": []}}, {"job_id": "100003009048774", "location_code": "hk", "company": "Hillman Ross", "job_title": "Project Manager - Business Transformation", "description": "Our client is a global sourcing company, an opportunity has arisen for Project Manager - Business Transformation to join their team.\n\n\nWe are now seeking for Project Manager - Business Transformation\n\n\nRESPONSIBILITIES\n\nMaintains confidentiality and professionalism in all situations as a trusted partner.\nConduct researches / fact-based analysis to compile solution proposals\nAnalyze data, formulate solution design plans, and develop functional requirements for solution development and improvement\nEffective calendar management, prior planning, and preparation for internal and external leadership team meetings, including but not limited to town hall meetings, off-sites, vendor webinars, one-on-one meetings, etc.\nEvent management entails planning quarterly meetings, volunteer events, off-sites, webinars, and summits, among other things.\nDocument creation and editing (Word, PowerPoint, Excel, Power BI, Tableau) to support the SVP in all aspects of their work, including global trip plans.\n\nQUALIFICATIONS\n\nMBA/ Master degree holder\nSolid administrative or project management experience; with experience supporting C-level executives preferred\nHigh attention to detail, organization and process.\nHigh level of confidentiality, discernment and judgment.\nAbility to be flexible in response to changing priorities and needs.\nProven ability to manage projects, perform under pressure, and meet deadlines continuously.\nStrong oral and written communication. Ability to communicate with top leaders and external business partners clearly and effectively.\nExcellent communication in English and Chinese\nKeeping up with new technologies and being enthusiastic about new tools and working methods. (e.g., Microsoft Office: Outlook, Word, Excel, PPT. Power BI, Tableau)\n\n\n\nAPPLY FOR THIS JOB\nInterested candidate please CLICK apply button to apply online or send your resume in MS word format to Hillman Ross Recruitment Solution Professional\n\n\n\n\nPlease note that only shortlisted candidate will be notified. All information will be treated in strict confidence and solely used for recruitment purposes.", "employment_types": ["Full Time", "Permanent"], "selling_points": ["Competitive Salary Package", "A multinational Corporation", "Project Management"], "locations": ["Not Specified"], "categories": ["Management", "General Management"], "post_time": "2022-01-14T07:16:04Z", "salary": {"currency": null, "max": null, "min": null, "period": "monthly", "term": null}, "salary_visible": false, "title_keywords": ["project manager"], "responsibilities": ["communicate with", "management", "power bi", "analysis", "design", "develop", "communication", "project management", "recruitment", "manage projects", "analyze data", "plans", "editing", "planning"], "requirements": {"degrees": ["master degree"], "majors": [], "languages": ["english", "chinese"], "language_level": ["excellent"], "hard_skills": ["excel", "bi", "microsoft office", "analysis", "vendor", "powerpoint", "word", "tableau", "project management", "c", "outlook", "ms word"], "soft_skills": ["flexible", "oral", "confidence", "under pressure", "communication", "project management", "attention to detail", "enthusiastic", "meet deadlines", "leadership"], "languages_combined": [{"language": "english", "language_level": ["excellent"]}, {"language": "chinese", "language_level": ["excellent"]}]}, "experience_required": {"duration": [], "field": ["project management", "administrative"]}}, {"job_id": "100003009048510", "location_code": "hk", "company": "Harbour City Estates Ltd", "job_title": "MANAGER \u2013 CENTRE OPERATIONS", "description": "The successful candidate will oversee the center operations of a prestigious shopping mall \u2013 Harbour City to ensure delivery of the highest service standards.\u00a0 He/she will manage a sizable team of building management, customer service and carpark staff and appointed contractors in daily operations including security, crowd control, traffic management, carpark operation, cleaning, landscaping, customer service and statutory compliance. \u00a0\nCandidates should be university graduates in property, facility management or related discipline with at least 10 years\u2019 proven management experience in managing large commercial complex with proven leadership skills in a highly disciplined environment.\u00a0 He/She should be a self-starter who works independently, resourceful in problem-solving, equipped with excellent organization and people management skills and is proficient in spoken and written English and Chinese.\u00a0 Previous training in risk assessment and management, as well as experience in crowd control would be a definite advantage.\nWe offer competitive remuneration package that commensurate with experience and qualifications.\u00a0 Interested parties are invited to send full resume stating contact telephone number, date available, present and expected salary to our recruitment email address.\n(Personal data provided will be used strictly in accordance with the Company\u2019s personal data policy which is available upon request.)", "employment_types": ["Full Time", "Permanent"], "selling_points": ["Should be university graduates in property", "10 years\u2019 proven management experience", "Should be a self-starter who works independently"], "locations": ["Tsim Sha Tsui"], "categories": ["Building & Construction", "Building / Construction / QS", "Management", "General Management", "Property / Real Estate", "Property Management"], "post_time": "2022-01-15T03:50:01Z", "salary": {"currency": null, "max": null, "min": null, "period": "monthly", "term": null}, "salary_visible": false, "title_keywords": ["operations", "manager"], "responsibilities": ["crowd control", "traffic management", "management", "statutory compliance", "operations", "building management", "service standards", "customer service", "daily operations", "landscaping", "cleaning", "carpark operation"], "requirements": {"degrees": [], "majors": [], "languages": ["english", "chinese"], "language_level": ["excellent", "proficient"], "hard_skills": ["problem-solving", "harbour"], "soft_skills": ["independently", "resourceful", "problem-solving", "leadership skills", "customer service"], "languages_combined": [{"language": "english", "language_level": ["excellent", "proficient"]}, {"language": "chinese", "language_level": ["excellent", "proficient"]}]}, "experience_required": {"duration": ["at least 10 years"], "field": ["related", "commercial", "management", "training"]}}, {"job_id": "100003009049688", "location_code": "hk", "company": "Area-17 Limited", "job_title": "Assistant Interior Project Manager / Interior Designer", "description": "AREA-17 Architecture & Interior is an international design consultancy firm. We specialize in retail projects for luxury brands. Our Hong Kong Team is expanding as to accommodate array of upcoming projects, we are now seeking high caliber candidates to grow up together with the firm.\n\nA) Assistant Interior Project Manager\n\nJob Duties:\u00a0\n\nFollow up projects, with clients, suppliers, contractors, designers\nCheck all the drawings in detail and modify defects accurately\nHandle full spectrum of documentations, records, email correspondences among clients and contractors precisely\nReport project status to management and related parties\nCheck quotations, timeline and prepare analysis\nHandle full set of drawings and presentation\nProvide creative and technical solutions to our project\nSite visit and follow up the progress of project\n\nRequirements:\u00a0\n\nA minimum of 4 years solid experience in decoration and fitting-out projects\nProficiency in AutoCAD,\u00a0Photoshop\u00a0and SketchUp is an advantage\nGood command of written and spoken English & Chinese\nA good team player with positive and proactive attitude\nSelf-motivated, well organized and hardworking\nAble to work independently under tight schedule and pressure\u00a0\n\nProspect:\u00a0\n\nTo be able to manage clients and projects independently\n\nB) Interior Designer\n\nJob Duties:\u00a0\n\nHandle full set of drawings and presentation\nProvide creative and technical solutions to our project\nProvide assistance in project management\n\nRequirements:\u00a0\n\nA minimum of 3 years solid experience in decoration and fitting-out projects\nProficiency in AutoCAD,\u00a0Photoshop\u00a0and SketchUp is a must; Proficiency in InDesign and Illustrator is an advantage\nGood command of written and spoken English & Chinese\nA good team player with positive and proactive attitude\nSelf-motivated, well organized and hardworking\nAble to work independently under tight schedule and pressure\u00a0\n\nFor both position (A) and (B), we offer:\n\n15 days of annual leave,\npaid sick leave,\nmedical and dental insurance,\nperformance bonus\n\nCandidates will be selected based on their interest and background.\u00a0If you are interested in joining a fast growing team under a friendly environment, please specify the position you are applying for and send\u00a0your resume,\u00a0expected salary, availability and portfolio in PDF\u00a0by clicking \"Apply Now\". \u00a0We will process your application immediately when your\u00a0portfolio is received.", "employment_types": ["Full Time"], "selling_points": ["Exposure to international projects & luxury retail", "Good career prospect in a growing company", "Minimum 3 to 4 years of experience in the field"], "locations": ["Sheung Wan"], "categories": ["Building & Construction", "Architectural Services", "Design", "Interior", "Management", "General Management"], "post_time": "2022-01-14T09:05:32Z", "salary": {"currency": null, "max": null, "min": null, "period": "monthly", "term": null}, "salary_visible": false, "title_keywords": ["interior project manager", "interior designer", "assistant"], "responsibilities": ["report", "management", "analysis", "drawings"], "requirements": {"degrees": [], "majors": [], "languages": ["english", "chinese"], "language_level": ["good command"], "hard_skills": ["indesign", "illustrator", "project management", "autocad", "photoshop", "sketchup"], "soft_skills": ["good team player", "self-motivated", "hardworking", "work independently", "independently", "creative", "well organized", "project management", "proactive", "presentation", "positive"], "languages_combined": [{"language": "english", "language_level": ["good command", "good command"]}, {"language": "chinese", "language_level": ["good command", "good command"]}]}, "experience_required": {"duration": ["minimum of 4 years", "minimum of 3 years"], "field": []}}, {"job_id": "100003009048586", "location_code": "hk", "company": "Mandarin Oriental Hotel Group Limited", "job_title": "Pastry Chef", "description": "Responsibilities:\n\nFull responsibility for smooth running of the day to day pastry and bakery operations of the culinary departments of 4 restaurants & bars including 2 Michelin starred fine dining restaurant.\nEnsure that all operating equipment, Bakery & Pastry Kitchens are maintained in good working condition.\nInspect incoming products related to pastry & bakery and ensure proper storage and stock rotation.\nPlan & oversee the production of pastry and bakery products.\nImplement & reinforce all hygiene and safety procedures according to hotel guidelines\nMaintain strong communications through one on one updates and daily departmental meetings\nClosely control the food cost, inventory and market lists\nIn charge of creating, revising and costing of all the recipes.\nSupervise and carry out the production standards of all pastry & bakery items in all 4 outlets according to the prescribed recipe and specifications.\nResponsible for recruitment of pastry & bakery staff\nProvide training and coaching related to desserts, pastry & bakery items to kitchen and service staff\nHandle administrative duties related to the department\nResponsible to maintain positive and good team spirit in kitchens and other relevant areas\n\nRequirements:\n\n8 years of experience in the pastry operation preferably in luxury hotel with Michelin-starred or World 50 Best outlets\nAcquire work exposure in Asia is an advantage\nExcellent food & beverage and menu planning knowledge\nCreativity, patience and stamina desired\nAble to maintain composure under busy operation\nStrong interpersonal skills and exemplary leadership skills\nGood command of both spoken and written English\nStrong training Skills\nA team player who is motivational\nAbility to maintain high levels of food quality, consistency and hygiene\nPerform annual budgeting and cost control for his department.\nGood administrative skills\nComputer proficiency in major software\n\n\n\u6709\u610f\u7533\u8acb\u8005\u8acb\u6309 APPLY NOW\u7533\u8acb \u00a0\u00a0\u00a0", "employment_types": ["Full Time"], "selling_points": ["Closely control the food cost, inventory lists", "Responsible for recruitment of pastry staff", "Handle administrative duties"], "locations": ["Admiralty"], "categories": ["Hospitality / F & B", "Food & Beverage", "Management", "General Management", "Hospitality / Hotel Services"], "post_time": "2022-01-14T06:51:27Z", "salary": {"currency": null, "max": null, "min": null, "period": "monthly", "term": null}, "salary_visible": false, "title_keywords": ["pastry chef"], "responsibilities": ["provide training", "control", "cost", "guidelines", "operations", "inventory", "procedures", "hygiene", "maintain", "specifications", "recruitment", "plan", "administrative duties", "departmental meetings"], "requirements": {"degrees": [], "majors": [], "languages": ["english"], "language_level": ["good command"], "hard_skills": [], "soft_skills": ["leadership skills", "team player", "interpersonal skills", "patience"], "languages_combined": [{"language": "english", "language_level": ["good command"]}]}, "experience_required": {"duration": ["8 years"], "field": ["operation"]}}, {"job_id": "100003009049426", "location_code": "hk", "company": "The Society of Rehabilitation and Crime Prevention, Hong Kong", "job_title": "Manager (Employment Development Service) (Lai Chi Kok)", "description": "Reporting to the Senior Management, the appointee will provide leadership and management of the Employment and ERB services of the Agency, which includes but not limited to the overall planning and development of services with different funding modes (government subsidised, non-government funders and self-financing, etc), implementing innovative programmes in response to current and emerging service trend and social needs, promotion of effective stakeholder relationship and networking, as well as mobilising available resources for the service advancement and development.\n\n\u00a0Requirements\n\nPost-secondary education preferably with Bachelor degree in Social Work or Business discipline;\nRegistered Social Worker with minimum 7 years\u2019 work experience preferably in employment / ERB or related services plus over 4 years\u2019 supervisory / management and service development experience;\nProficient in both spoken and written English and Chinese;\nStrong leadership and people management with good presentation, collaboration, networking and organisational skills;\nDynamic and resourceful with proven ability to network and foster relationships, both internally and externally, work efficiently under pressure and multi-tasks oriented;\nExcellent working knowledge on employment marketing, training and enhancement; and\nComputer literate and able to pick up new technologies and innovative concepts quickly.\n\n\u00a0Appointment will be made on contract term with staff benefits including training subsidies, medical benefits. Qualified candidates are invited to submit application letter and full resume with present and expected salary and earliest availability.\n\n(All information provided will be kept as confidential & only be used for recruitment related purposes)", "employment_types": ["Contract"], "selling_points": [], "locations": ["Lai Chi Kok"], "categories": ["Management", "General Management"], "post_time": "2022-01-14T08:36:37Z", "salary": {"currency": null, "max": null, "min": null, "period": "monthly", "term": null}, "salary_visible": false, "title_keywords": ["manager"], "responsibilities": ["reporting", "senior management", "management", "planning"], "requirements": {"degrees": ["degree", "bachelor", "secondary education"], "majors": ["social work", "business"], "languages": ["english", "chinese"], "language_level": ["proficient"], "hard_skills": ["plus", "dynamic"], "soft_skills": ["under pressure", "resourceful", "multi-tasks", "dynamic", "organisational skills", "innovative", "leadership", "presentation"], "languages_combined": [{"language": "english", "language_level": ["proficient"]}, {"language": "chinese", "language_level": ["proficient"]}]}, "experience_required": {"duration": ["4 years", "minimum 7 years"], "field": ["related", "development", "supervisory", "management"]}}, {"job_id": "100003009047020", "location_code": "hk", "company": "Don Nelson Recruitment Limited", "job_title": "Assistant Business Manager - Consulting Industry", "description": "We are an awarded recruitment agency with regional branch office and keep expanding, we are currently seeking for new member to join our Hong Kong office. We provide competitive package, training program and fun working environment. Are you passionate in joining a\u00a0dynamic, creative & energetic team? If you are looking for a challenging, target driven and well rewarded career, please submit your resume to us:\n\nResponsibilities:\n\nAdvise and support management on strategic, business and operational related topics\nDevelop and maintain strong relationship with our clients and business partners\nDevelop, update and monitor business plan and manage budget proactively\nPlan and execute company development and growth strategies\nSupport the implementation of business development plans\nCoordinate internal engagement activities and meetings fostering positive and open communication\n\nRequirements:\n\nDegree in Business Administration, Management or related disciplines\nProven record of project management and delivery, business analysis, change management within a business change environment\nStrong passion in recruitment or people-oriented industry\nHighly organized and logical in thought and action\nStrong communication and negotiation skills is required\nSelf-motivated, able to work individually and as a team\nExcellent command of English and Chinese\nMore experienced will be considered as Business Manager\n\nPersonal data provided by job applicants will be used strictly in accordance with the employer's personal data policies and for recruitment purposes only.", "employment_types": ["Full Time", "Permanent"], "selling_points": ["Awarded and fast growing recruitment agency", "Planning the development and growth strategies", "Challenging work nature with regional exposure"], "locations": ["Sheung Wan"], "categories": ["Professional Services", "Business Consultancy", "Sales, CS & Business Devpt", "Business Development", "Management", "General Management"], "post_time": "2022-01-15T03:49:34Z", "salary": {"currency": null, "max": null, "min": null, "period": "monthly", "term": null}, "salary_visible": false, "title_keywords": ["manager", "assistant"], "responsibilities": [], "requirements": {"degrees": [], "majors": [], "languages": [], "language_level": [], "hard_skills": [], "soft_skills": [], "languages_combined": []}, "experience_required": {"duration": [], "field": []}}, {"job_id": "100003009044900", "location_code": "hk", "company": "Pet-Link Company Limited", "job_title": "Managing Director", "description": "Responsibilities:\n\nWork closely with Directors/CEO, develop strategic annual business plans for Hong Kong, Mainland China and overseas that are aligned to the Company's objectives and directions.\nAct as a strategic partner on daily business, new project development and long-term strategic planning.\nFormulate and execute business operating plans to improve revenues and sustain long term business growth\u00a0\nLead the team at different levels, empower and motivate team members to achieve targets and company goals.\nMonitor and maintain internal control procedures and standards to improve risk management, alert Directors/CEO for any possible crisis in a timely manner.\nResponsible for the overall P&L; cost & expenditure; policy & procedures of the Company\nAny other ad-hoc assignments as assigned.\n\nRequirements:\n\nUniversity graduate in Business Management, Marketing or related discipline\nAt least 20 years of experience in the fields of FMCG industries, with minimum 8 years in senior management level, solid PRC experiences preferred.\nFlexibility and adaptability to face challenges in a growing organization\nExcellent business acumen, ability to convert the business strategy to operational implementation.\nAble to inspire, lead and manage the team to implement business strategies effectively.\nGood spoken and written in English and Mandarin.\nWilling to travel Overseas and PRC subject to the development of Covid-19.\nLess experiences will be considered as Assistant General Manager\n\nCompany website: https://www.pet-link.com\u00a0\u00a0https://eshop.iloverabbit.com/\n\nWe offer competitive salary remuneration package which included year-end KPI bonus, hardworking allowance, medical insurance, dental allowance, 18 days annual leave and staff purchase discount to the successful candidate.\n\nInterested applicants please email your detailed resume indicating your current, expected salary and also date of availability along with your relevant portfolio. Applicants without portfolio will not be considered.\n\n*All information provided will be treated in strict confidential and used only for recruitment purposes.\u00a0", "employment_types": ["Full Time", "Permanent"], "selling_points": [], "locations": ["Tai Po Area"], "categories": ["Management", "General Management", "Top Executives (CEO, CFO, CTO, GM, MD etc.)"], "post_time": "2022-01-13T06:35:06Z", "salary": {"currency": null, "max": null, "min": null, "period": "monthly", "term": null}, "salary_visible": false, "title_keywords": ["director"], "responsibilities": ["achieve targets", "management", "cost", "strategic planning", "ad-hoc assignments", "monitor", "procedures", "business plans", "develop", "a timely manner", "p&l", "maintain", "plans", "internal control"], "requirements": {"degrees": ["university graduate"], "majors": ["business", "marketing"], "languages": ["english", "mandarin"], "language_level": ["good"], "hard_skills": ["business management", "acumen"], "soft_skills": ["business acumen", "adaptability", "hardworking", "detailed"], "languages_combined": [{"language": "english", "language_level": ["good"]}, {"language": "mandarin", "language_level": ["good"]}]}, "experience_required": {"duration": ["minimum 8 years", "at least 20 years"], "field": ["management", "fmcg"]}}, {"job_id": "100003009049353", "location_code": "hk", "company": "Monty Limited", "job_title": "Financial, Planning & Analysis Manager", "description": "The Monty Group is a multinational company investing in a wide range of industries across both operating and investing activities. The company\u2019s interests span a range of sectors including garment, agriculture, real estate, energy, entertainment, capital markets, amongst others. To cope with our long-term and aggressive global expansion plans, we are inviting high calibre candidates to apply for the following position.\n\n\nDuties/Responsibilities:\n\n\n\nLead annual budget process and work with business units to prepare annual budgets and forecasts.\nPrepare management analysis reports and provide commentary on key variances to support business performance review.\nMonitor key performance indicators against budget, highlight trends and analyze the causes of variances.\nAct as a business partner working closely with different stakeholders in operation teams and provide analytics support for performance improvement, cost saving and business development initiatives.\nLead ad hoc analysis as required.\n\n\n\nRequirements:\n\nBachelors degree in Finance, Accounting or related field.\nACCA/HKICPA or equivalent professional qualification.\nMinimum of 10 years relevant finance and analytical experience.\nFluent in English and Chinese, including Mandarin.\nAdvanced Excel and financial modeling skills required.\u00a0 Strong analytical and problem-solving skills with attention to details.\nExcellent interpersonal and communication skills.\n\n\nWe offer attractive remuneration package, 5-days work, work-life balance working environment to the right candidate.\u00a0 Interested parties are welcome to send your full resume with present and expected salary by clicking \"Apply Now\". All personal data will be used for recruitment purpose only.\n\n\n", "employment_types": ["Full Time"], "selling_points": [], "locations": ["Kowloon Bay"], "categories": ["Management", "General Management"], "post_time": "2022-01-14T08:31:07Z", "salary": {"currency": null, "max": null, "min": null, "period": "monthly", "term": null}, "salary_visible": false, "title_keywords": ["manager"], "responsibilities": ["budgets", "management", "cost", "ad hoc", "analysis reports", "analysis", "budget", "review", "monitor", "teams"], "requirements": {"degrees": ["degree"], "majors": ["finance", "accounting"], "languages": ["english", "chinese", "mandarin"], "language_level": ["fluent"], "hard_skills": ["problem-solving skills", "excel", "acca", "hkicpa"], "soft_skills": ["communication skills", "advanced", "attention to details", "problem-solving skills", "interpersonal"], "languages_combined": [{"language": "english", "language_level": ["fluent"]}, {"language": "chinese", "language_level": ["fluent"]}, {"language": "mandarin", "language_level": ["fluent"]}]}, "experience_required": {"duration": ["minimum of 10 years"], "field": ["finance", "analytical"]}}, {"job_id": "100003009029874", "location_code": "hk", "company": "The Hong Kong Medical Association", "job_title": "Assistant Executive Officer - Education (Contract)", "description": "Job responsibilities:\n\nProvides administrative and on-site support to Continuing Medical Education (CME) programmes;\nManages data filing system and reports for course administration;\nAssist in the publishing work for monthly magazine; and\nAssist in ad-hoc duties as assigned\nRequirements:\n\nUniversity graduate in Social Science or other relevant subjects with at least 1 year experience.\u00a0 Fresh graduate will also be considered;\nFamiliar with MS Office and social media platforms; and\nGood written and verbal communication skills;\nKnowledge in social media and meeting software (e.g Facebook and ZOOM)\u00a0 will be an added advantage\nImmediate available is preferred\n\nApplication letters in\u00a0BOTH\u00a0Chinese and English with full resume, present and expected salary and date available should be sent to Human Resources Team of the Hong Kong Medical Association.\n\n\n(Personal data collected for recruitment purpose only)", "employment_types": ["Contract"], "selling_points": [], "locations": ["Wan Chai"], "categories": ["Education", "Others", "Management", "General Management"], "post_time": "2022-01-11T04:39:18Z", "salary": {"currency": null, "max": null, "min": null, "period": "monthly", "term": null}, "salary_visible": false, "title_keywords": ["assistant executive officer"], "responsibilities": ["administration", "reports", "ad-hoc duties", "data"], "requirements": {"degrees": ["university graduate", "fresh graduate"], "majors": ["science"], "languages": ["english", "chinese"], "language_level": [], "hard_skills": ["facebook", "ms office"], "soft_skills": ["communication skills"], "languages_combined": [{"language": "english", "language_level": []}, {"language": "chinese", "language_level": []}]}, "experience_required": {"duration": ["at least 1 year"], "field": []}}, {"job_id": "100003009050133", "location_code": "hk", "company": "Gammon Construction Ltd", "job_title": "Head of Assurance", "description": "Responsibilities:\nProvide overall direction and leadership of the Assurance function to attain the goals of the Board and Shareholders;\nResponsible for risk management and internal control regarding effective operating, designed controls, risk mitigation strategies and overall compliance with Company policies and procedures;\nProfessionally communicate both verbally and in writing, deliver formal presentation to the Board and Shareholders;\nMaintain and develop regular assurance and audit reports to business divisions and Shareholders;\nWork closely with business divisions on internal process reviews;\nProvide professional advice and influence changes to relevant manuals in the Business Management System to correct, strengthen and update whenever necessary;\nRequirements:\u00a0\nDegree in business, construction or related disciplines;\n15 years\u2019 relevant experience in corporate assurance management, preferably with exepreince in cosntruction industry;\nAbility to lead, manage and motivate a team effectively and deliver targets;\nExcellent communication skills, with the ability to present and explain complex information and suggest process improvement to diverse audiences;\nFluency in spoken and written English.\nYou may apply via https://career.gammonconstruction.com/home/index?jobid=ec3a73c2-e260-4f3c-a635-36fc25f13d5f&source=003, providing your full resume, current and expected salary.\nFor more information about Gammon Construction Limited, please visit our company's website at http://www.gammonconstruction.com.\nWe are an equal opportunity employer and welcome applications from all qualified candidates.\u00a0 Information provided will be treated in strict confidence and only be used for consideration of your application for the relevant post within the Company.\u00a0 Applicants who are not invited for an interview within 6 weeks may consider their application unsuccessful.", "employment_types": ["Full Time", "Permanent"], "selling_points": ["Business, construction or related disciplines", "Experience in corporate assurance management", "Fluency in spoken and written English"], "locations": ["Not Specified"], "categories": ["Management", "General Management", "Building & Construction", "Others"], "post_time": "2022-01-14T09:50:35Z", "salary": {"currency": null, "max": null, "min": null, "period": null, "term": null}, "salary_visible": false, "title_keywords": [], "responsibilities": ["management", "policies", "compliance", "procedures", "audit", "develop", "maintain", "reports", "internal control"], "requirements": {"degrees": ["degree"], "majors": ["related disciplines", "business"], "languages": ["english"], "language_level": ["fluency"], "hard_skills": [], "soft_skills": ["communication skills", "confidence", "diverse"], "languages_combined": [{"language": "english", "language_level": ["fluency"]}]}, "experience_required": {"duration": ["15 years"], "field": ["assurance", "relevant experience", "management"]}}, {"job_id": "100003009046398", "location_code": "hk", "company": "Wheelock Properties (Hong Kong) Ltd", "job_title": "Sustainability Manager", "description": "Responsibilities:\n\n\nSupport the implementation, execution and management of the Company\u2019s long term sustainability strategy and action plans to achieve our public sustainability goals and demonstrate our commitment in ESG\nSupport management in developing new sustainability standards and product sustainability\nDevelop and present sustainability training programs for internal teams\nCollaborate across departments to drive the publication of the Company\u2019s annual sustainability report\nProvide expertise in sustainability related issues, ratings, rankings, reporting schemes, initiatives trends and norms.\nPerform the Group's sustainability-related data gathering to ensure accurate and timely collection as well as analyze for ESG / Sustainability reporting and strategic input\nRespond to investor/customer surveys and disclosures as required, and conduct sustainability/ESG-related research\nLead sustainability programs and event campaigns to build collaboration with external parties\nLead internal Office Sustainability Taskforce\nRequirements:\n\nDegree holder in Sustainability, Architecture, Development, Construction or other related disciplines with at least 6 years\u2019 of Sustainability/Corporate Social Responsibility relevant experience\nKnowledge of, and skills in, protocols and standards such as GRI Standards and SDGs; CSR trends and best practices\nExperience in sustainability reporting\nExcellent communication, collaboration and interpersonal skills\nExemplary critical thinking skills, attention to detail, organization and ability to multi-task.\u00a0\nStrong project management skill with ability to collaborate with various stakeholders\u00a0\nAt least one green building accreditation (either BEAM, LEED, WELL, etc.)\nStrong command of sustainability-related data analysis\nImmediate availability is preferred\nWe offer ample opportunities for career development and attractive salary package commensurate with experience and qualifications. \u00a0Interested parties please apply with full resume via\u00a0\u201cAPPLY NOW\u201d.\u00a0\n\n\nFor further information on Wheelock Properties (Hong Kong) Limited, please visit our website: www.wheelockpropertieshk.com\n\nWe are an equal opportunities employer and invite applications from all qualified candidates. Personal data collected will be treated in strict confidence and handled by authorized persons for recruitment-related purposes only within the Wheelock & Wharf Group. Applicants not hearing from us within two months may consider their applications unsuccessful.", "employment_types": ["Full Time", "Permanent"], "selling_points": [], "locations": ["Central"], "categories": ["Sciences, Lab, R&D", "Environmental Science / Waste Management", "Management", "General Management"], "post_time": "2022-01-13T18:55:19Z", "salary": {"currency": null, "max": null, "min": null, "period": null, "term": null}, "salary_visible": false, "title_keywords": ["manager"], "responsibilities": ["collaborate", "reporting", "management", "data", "external parties", "teams", "implementation", "developing", "develop", "plans", "publication", "report"], "requirements": {"degrees": ["degree holder"], "majors": ["related disciplines", "architecture"], "languages": [], "language_level": [], "hard_skills": ["project management", "analysis"], "soft_skills": ["multi-task", "communication", "interpersonal skills", "attention to detail", "project management skill"], "languages_combined": []}, "experience_required": {"duration": ["at least 6 years"], "field": ["corporate social responsibility", "related", "development", "sustainability", "relevant experience", "construction"]}}, {"job_id": "100003009049520", "location_code": "hk", "company": "Jones Lang LaSalle Ltd", "job_title": "Facilities Officer", "description": "About JLL \u2013\u00a0\n\nWe\u2019re JLL. We\u2019re a professional services and investment management firm specializing in real estate. As a Fortune 500 company, we help real estate owners, occupiers and investors achieve their business ambitions.\u00a0\n\nIf you\u2019re looking to step up your career, JLL is the perfect professional home. With us, you\u2019ll have a chance to innovate with the world\u2019s leading businesses, put that expertise into action on landmark projects, and work on game-changing real estate initiatives. You\u2019ll also make long-lasting professional connections and be inspired by the best. We\u2019re focused on opportunity and want to help you make the most of yours. Achieve your ambitions - join us at JLL!\u00a0\n\nAbout the role:\u00a0\n\nWhat this job involves:\u00a0\n\nFacilities Operations\n\nAssist and monitor building procedures and performance measures to ensure simplification and accuracy of work methods and reliability of systems.\nMonitor the Preventive and Planned Maintenance programme to minimise maintenance, repair and replacement costs together with minimising the risk of plant failure. Liaise on any outstanding Work Orders.\nAssist in the implementation a comprehensive energy saving/management program for your site(s)\nEnsure that the team liaises closely with the Regional Operations procedures to ensure service standards are maintained\nRecommend continuous quality improvement practices across your site, ensuring initiatives are shared across all sites\nEnsure consistency of regional policies & procedures with constant updating of as required\nImplement, comply with and audit all internal management systems, for quality assurance\nAssist the Management Team with the coordination of Churn and other relocations\u00a0activities\u00a0\u00a0\u00a0\n\nRisk Management\n\nAssist in the implementation and management of a property risk management program which identifies major property risks including occupational health and safety, fire safety and essential services and environmental.\nAssist in the implementation and monitoring of guidelines and strategies to protect health and safety of staff and others, protect the client and JLL reputation.\nSupport the implementation and monitoring of disaster recovery and business continuity plans\nFollow established escalation procedures and incident reporting procedures\u00a0\n\nProcurement and Vendor Management\n\nAssist in the evaluating the vendor procurement and management practices of your designated site and ensure renegotiation and tendering, including tender documentation; evaluation of tenders and preparation of contracts is in accordance with agreed client procurement guidelines.\nCo-ordinate and monitor the contractor management program ensuring all vendors comply with all aspects of their agreement\nEnsure the Contract Management Database is up to date at all times\nAssist to manage the vendor Risk Management program\n\nProfitability/ Savings Initiatives\n\nAssist the JLL Account Leadership team with generating savings and creating initiatives to improve processes and practices\n\nCustomer Service / Client Relationships\n\nProvide superior customer service\nEnsure feedback from client sessions is recorded and actioned to the satisfaction of the end user.\nPro-actively manage client\u2019s expectations ensuring that the service levels are maintained .\nLead by example\n\nReporting\n\nAssist in the budgeting process as required\nProvide input as required into the Monthly Report to client\nActive involvement in the monitoring and achieving the required Key Performance Indicators\n\nLeadership / Staff Management:\n\nActively support an environment that supports teamwork, co-operation & performance excellence within the team\n\nSound like you? To apply you will have:\n\nTertiary education in Building, Mechanical, Electrical Services, Facilities Management or related disciplines\nMinimum of 2 years\u2019 practical experience in day-to-day operation, repair and maintenance, particularly in commercial office and retail premises\nRelated experience in banking industry is preferable\nKnowledge in Security system, Air-conditioning (CRAC, MVAC) system, Fire Services systems, Electrical Distribution systems and PC systems\nKnowledge in site co-ordination and vendor management\nA good team player with good organizational, communication and client management skills\nGood command of both written and spoken English and Cantonese/Chinese\nGood PC literacy and able to manage daily activities using\u00a0various systems\n\nCritical Competencies for Success\n\nBehave consistently with Jones Lang LaSalle cultural and ethical requirements\nHave a positive and proactive approach to work and able to work on own initiative and as part of a busy team\nAbility to deal with emergency situations in a calm manner\nAble to follow instructions and procedures\nListens effectively and communicates through actions and example\nTakes a flexible approach to work patterns to meet the requirements of Jones Lang LaSalle and clients\nAbility to work within a budget\nDemonstrated initiative\u00a0\nAbility to solve problems\n\nWhat you can expect from us\n\nWe\u2019re an entrepreneurial, inclusive culture. We succeed together - across the desk and around the globe. We believe the best inspire the best, so we invest in supporting each other, learning together and celebrating our success.\n\nOur Total Rewards program reflects our commitment to helping you achieve your ambitions in career, recognition, well-being, benefits and pay. We\u2019ll offer you a competitive salary and benefits package.\n\nWith us, you\u2019ll develop your strengths and enjoy a career full of varied experiences. We can\u2019t wait to see where your ambitions take you at JLL.\n\nApply today!", "employment_types": ["Full Time", "Permanent"], "selling_points": ["Facilities Management", "Central / Banking", "Good Development Opportunity"], "locations": ["Central"], "categories": ["Admin & HR", "Administration / Operation Manager", "Management", "General Management", "Property / Real Estate", "Property Management"], "post_time": "2022-01-14T08:47:54Z", "salary": {"currency": null, "max": null, "min": null, "period": "monthly", "term": null}, "salary_visible": false, "title_keywords": ["officer"], "responsibilities": ["liaise", "business continuity", "operations", "budgeting", "budget", "quality", "audit", "tendering", "communication", "service standards", "customer service", "database", "monthly report", "plans", "costs", "management team", "site co-ordination", "monitor", "implementation", "tender", "banking", "reporting", "management", "monitoring", "procedures", "documentation", "maintenance", "guidelines", "policies", "systems", "contract management", "repair", "preparation of contracts", "coordination", "day-to-day operation", "evaluation of tenders"], "requirements": {"degrees": [], "majors": [], "languages": ["cantonese", "english", "chinese"], "language_level": ["good command"], "hard_skills": ["maintenance", "vendor", "make", "facilities management", "documentation", "pc"], "soft_skills": ["focused", "communication", "comprehensive", "customer service", "leadership", "superior", "calm", "ethical", "initiative", "good team player", "solve problems", "active", "positive", "flexible", "organizational", "teamwork", "learning", "coordination", "proactive"], "languages_combined": [{"language": "cantonese", "language_level": ["good command"]}, {"language": "english", "language_level": ["good command"]}, {"language": "chinese", "language_level": ["good command"]}]}, "experience_required": {"duration": ["minimum of 2 years"], "field": ["banking industry", "maintenance", "related", "commercial", "operation", "retail"]}}, {"job_id": "100003009051835", "location_code": "hk", "company": "PwC", "job_title": "Manager / Senior Manager - Private Client Services - PwC Tax - Hong Kong", "description": "Job Description & Summary\n\nA career in our Tax Wealth Advisory practice, within Tax services, will provide you with the opportunity to help our clients meet and manage their tax obligations across unique but ever changing tax specialties. You\u2019ll advise clients on their local and overseas tax affairs, while acting as a strategic consultant related to business analysis, managing indirect taxes, dispute resolution, and global enterprise tax solutions.\n\nOur team offers clients a scalable solution to address the tax compliance needs of corporations, partnerships, and other business entities by managing compliance services to maximise a tax department\u2019s strengths and minimise the impact on our clients resources. You\u2019ll support clients by providing outsourcing services which includes the preparation and review of income and franchise returns along with responding to inquiries from federal, state and local taxing authorities for our clients.\n\nAssist in preparation of documentation in relation to and support superiors to handle family wealth planning projects\n\nAssist in the set-up of asset holding structure for family wealth planning purposes\n\nAssist in the formation of Hong Kong or offshore companies and the ongoing maintenance including the filing of the necessary returns with the registration authority\n\nAssist in the application and ongoing maintenance of immigration matters\n\nRequirements\n\nA degree holder preferably in Accounting/Law/Corporate Governance but not essential.\n\nStudent member of ICSA / HKICS/HKICPA will be an advantage.\n\nFive years of company secretarial or personal tax experience preferable\n\nProficient in English and Chinese. Putonghua is essential.\n\nChinese writing and reading skill is essential.\n\nA team player with strong initiative and able to work under pressure.\n\n\n\n\u6709\u610f\u7533\u8acb\u8005\u8acb \u6309 APPLY NOW\u7533\u8acb\n\n", "employment_types": ["Full Time"], "selling_points": [], "locations": ["Not Specified"], "categories": ["Accounting", "Finance / Accounting Manager", "Taxation", "Management", "General Management"], "post_time": "2022-01-17T01:19:31Z", "salary": {"currency": null, "max": null, "min": null, "period": "monthly", "term": null}, "salary_visible": false, "title_keywords": ["senior manager", "manager"], "responsibilities": ["tax", "documentation", "maintenance", "compliance", "review", "resolution", "support clients", "business analysis", "planning"], "requirements": {"degrees": ["degree holder"], "majors": ["accounting", "law"], "languages": ["putonghua", "english", "chinese"], "language_level": ["proficient"], "hard_skills": ["hkicpa"], "soft_skills": ["team player", "initiative", "work under pressure"], "languages_combined": [{"language": "putonghua", "language_level": []}, {"language": "english", "language_level": ["proficient"]}, {"language": "chinese", "language_level": ["proficient"]}]}, "experience_required": {"duration": ["five years"], "field": ["secretarial"]}}, {"job_id": "100003009039651", "location_code": "hk", "company": "Ozone Development Limited", "job_title": "Business Development Manager", "description": "Business Development Manager\n\nJob Descriptions:\n\nTo be responsible for leasing of the Group\u2019s co-working space offices, and also all other properties of the Group\nTo actively source and liaise with potential clients and partners to drive new business opportunities\nTo manage the Group\u2019s marketing strategy by overseeing various channels of advertisement and promotions\nTo coordinate with other team members as well as other departments within the Group to ensure efficient and effective leasing activities\nTo process inquiries from both potential and existing clients in a professional manner\nTo build and maintain a clear database of clients\nTo perform various administrative work and assist in the operation of all properties of the Group\nTo carry out ad hoc duties as assigned by supervisor\n\nTo cope with this challenging position, the ideal candidate should meet the following requirements:\n\nDiploma/Associate degree or above (degree holders preferred), major in business administration, marketing or related subjects would be a plus\nMinimum 2 years of working experience, preferably in commercial property leasing, sales and marketing, or business development\nLeasing experience in serviced offices, business centers and/or co-working spaces would be given top priority\nFamiliar with MS Office (Word, Excel, PowerPoint, etc)\nAbility to multitask and manage performance from a macro perspective\nProactive, organised, result-oriented, assertive with good communication skills\nFluent in Cantonese, with business-level language ability in English and Mandarin\n\nPlease send a cover letter together with your resume to Kaman Fung for application.\n\nApplicants not being contacted for an interview within 4 weeks may consider their applications unsuccessful.", "employment_types": ["Full Time", "Permanent"], "selling_points": ["To be responsible for leasing", "Diploma/Associate degree", "To drive new business opportunities"], "locations": ["Kwun Tong"], "categories": ["Building & Construction", "Building / Construction / QS", "Management", "General Management", "Property / Real Estate", "Property Management"], "post_time": "2022-01-11T10:20:32Z", "salary": {"currency": null, "max": null, "min": null, "period": "monthly", "term": null}, "salary_visible": false, "title_keywords": ["business development manager"], "responsibilities": ["ad hoc duties", "administrative work", "business opportunities", "coordinate with", "professional manner", "communication", "maintain", "database", "liaise with", "administration"], "requirements": {"degrees": ["diploma", "degree or above", "degree"], "majors": ["marketing", "business administration"], "languages": ["cantonese", "english", "mandarin"], "language_level": ["fluent"], "hard_skills": ["excel", "plus", "macro", "word", "powerpoint", "ms office"], "soft_skills": ["efficient", "communication skills", "responsible", "assertive", "clear", "organised", "ability to multitask", "proactive", "result-oriented", "ideal"], "languages_combined": [{"language": "cantonese", "language_level": ["fluent"]}, {"language": "english", "language_level": []}, {"language": "mandarin", "language_level": []}]}, "experience_required": {"duration": ["minimum 2 years"], "field": ["business", "commercial", "marketing", "business development"]}}, {"job_id": "100003009039229", "location_code": "hk", "company": "Ampd Energy Limited", "job_title": "Director of Manufacturing", "description": "\u5730\u5340 :\u91d1\u9418,\u4e2d\u74b0,\u5c16\u6c99\u5480\n\u8077\u8cac :\u5354\u52a9\u7ba1\u7406\u5eda\u623f\u7684\u65e5\u5e38\u904b\u4f5c\u3001\u54c1\u8cea\u63a7\u5236\u3001\u74b0\u5883\u885e\u751f, \u5584\u7528\u6e9d\u901a\u6280\u5de7\u53ca\u7522\u54c1\u77e5\u8b58, \u8fce\u5408\u9867\u5ba2\u6240\u9700, \u78ba\u4fdd\u6240\u6709\u54e1\u5de5\u63d0\u4f9b\u826f\u597d\u7684\u670d\u52d9\u614b\u5ea6, \u78ba\u4fdd\u9910\u5ef3\u7bc4\u570d\u6574\u6f54\u885b\u751f\n\u8cc7\u6b77 :\u6c92\u6709\u5b78\u6b77\u8981\u6c42; 2\u5e74\u7d93\u9a57; \u826f\u597d\u7cb5\u8a9e; \u4e00\u822c\u666e\u901a\u8a71; \u826f\u597d\u82f1\u8a9e; \u61c2\u8b80\u5beb\u4e2d\u6587; \u61c2\u8b80\u5beb\u82f1\u6587\n\u5f85\u9047 :\u6bcf\u6708$17,000 - $22,000, \u6709\u5e74\u50479\u5929, \u751f\u65e5\u5047, \u4f9b\u81b3\u98df, \u5c0f\u8cbb \u53ca\u6069\u6064\u5047, \u4e00\u81f3\u516d: \u4e0a\u534811\u6642\u81f3\u4e0b\u534811\u6642/\u4e2d\u534812\u6642\u81f3\u51cc\u66680\u6642, \u65e5: \u4e0a\u534811\u6642\u81f3\u4e0b\u534811\u6642, \u6bcf\u9031\u5de5\u4f5c5\u5929,\u8f2a\u73ed,\u8f2a\u4f11, \u6bcf\u5929\u5de5\u4f5c 11 \u5c0f\u6642\n\u7533\u8acb\u9808\u77e5 :\u6c42\u8077\u8005\u53ef\u96fb\u90f5[via APPLY NOW]\u00a0\u5c65\u6b77\u8868\u7d66DINING CONCEPTS LIMITED\u3002\u5982\u8981\u7d22\u53d6\u6536\u96c6\u500b\u4eba\u8cc7\u6599\u8072\u660e, \u8acb\u8207\u6731\u5c0f\u59d0(Tel:39123914)\u806f\u7d61\u3002", "employment_types": ["Full Time", "Permanent"], "selling_points": ["Rapidly Growing Startup Environment", "Minimum 5 years of Related Experience", "Self-motivated, Detailed Oriented, Organized"], "locations": ["Lai Chi Kok"], "categories": ["Management", "General Management", "Manufacturing", "Manufacturing Management", "Others"], "post_time": "2022-01-11T09:05:45Z", "salary": {"currency": null, "max": null, "min": null, "period": "monthly", "term": null}, "salary_visible": false, "title_keywords": ["director"], "responsibilities": [], "requirements": {"degrees": [], "majors": [], "languages": [], "language_level": [], "hard_skills": [], "soft_skills": [], "languages_combined": []}, "experience_required": {"duration": [], "field": []}}, {"job_id": "100003009034191", "location_code": "hk", "company": "Baker & McKenzie", "job_title": "Business Manager", "description": "Responsibilities:\u00a0\n\nResponsible for all leasing and tenancy matters includes tenancy administration\nHandle\u00a0incoming calls,\u00a0leasing requests and enquiries,\u00a0greeting visitors, mailing, fax and documents distribution & courier service arrangement\nUse Facebook/Instagram to promote events, share news and updates, and increase visibility\nContact supplier for regular maintenance\nMaintain reception desk, co-working space area and conference rooms neat and tidy\nProvide general administrative support and perform other ad-hoc duties\nTo provide quality service and handle tenant enquiry & complaint\nMaintain filing system and related documentation\nReport to manager on a regular basis\n\n\u00a0\u00a0Requirements:\u00a0\n\nF.5 /\u00a0Secondary school diploma or\u00a0above with\u00a0pleasant personality\nWork independently\nAt least 1-2 years relevant experience\nSolid experience as receptionist / customer service would be an advantage\nGood telephone and customer service manner\nGreat sense of responsibility, well-organized and have ability to handle multiple tasks\nGood command of Cantonese,\u00a0English and Putonghua\nProactive, positive work attitude and willing to work under pressure\nProficient in\u00a0MS Office such as Word, Excel and\u00a0Chinese / English word processing\nProficient in\u00a0AI/Photoshop would be an advantage\nFresh graduate will also be considered\n\nWhere You'll be working:\u00a0\n\nworking in Kwun Tong, Kowloon.\u00a0\n\nInterested candidates, please send full resume with your past working experience, salary expectation and availability by clicking \"Apply Now\" with title \u201cRecruitment:\u00a0Receptionist / Admin Assistant for Co-working space\u201d\n\nAll Personal data collected will be used for recruitment purpose only.", "employment_types": ["Full Time", "Permanent"], "selling_points": ["Professional Service", "Business Management", "Real Esate"], "locations": ["Quarry Bay"], "categories": ["Management", "General Management"], "post_time": "2022-01-10T02:55:10Z", "salary": {"currency": null, "max": null, "min": null, "period": "monthly", "term": null}, "salary_visible": false, "title_keywords": ["manager"], "responsibilities": ["administration", "related documentation", "maintenance", "general administrative support", "quality", "maintain", "contact", "ad-hoc duties", "facebook", "report", "greeting visitors"], "requirements": {"degrees": ["fresh graduate", "diploma or above"], "majors": [], "languages": ["cantonese", "putonghua", "english", "chinese"], "language_level": ["good command", "proficient"], "hard_skills": ["excel", "ai", "word processing", "word", "photoshop", "ms office"], "soft_skills": ["work independently", "sense of responsibility", "well-organized", "pleasant", "handle multiple tasks", "customer service", "proactive", "positive work attitude", "work under pressure"], "languages_combined": [{"language": "cantonese", "language_level": ["good command"]}, {"language": "putonghua", "language_level": ["good command"]}, {"language": "english", "language_level": ["good command", "proficient"]}, {"language": "chinese", "language_level": ["proficient"]}]}, "experience_required": {"duration": ["at least 1-2 years"], "field": ["customer service", "relevant experience"]}}, {"job_id": "100003009034004", "location_code": "hk", "company": "Federal Express (Hong Kong) Ltd", "job_title": "Operations Manager", "description": "\nYour tasks\n\nYou will work directly on the global development of the group of companies in interdisciplinary project work with various departments (marketing, sales, operations, etc.) and various divisions / business units / local entities\nYou will take responsibility for important Management projects in the areas of strategy definition & implementation, M&A, sales excellence, digitization, etc.\nYou will support the development of options & recommendations for upcoming management decisions\nYou support and train the business units with relevant tools and methods\nYou help with ad-hoc projects from the CEO Resort\n\n\nWhat you offer\n\nSuccessfully completed studies in business administration, (economic) engineering or (economic) informatics, alternatively a comparable qualification\n3-4 years of professional experience in strategy consulting, corporate strategy, M&A, or project management\nAchiever mentality: you are result oriented and the drive to get something done\nEntrepreneurial mindset: you have a can-do mentality & the ability to motivate colleagues\nEnjoy working independently & on your own responsibility, but still a team player\nEnjoyment of international projects and willingness to travel \u2013 you will be part of a global team with a supervisor and several team colleagues in Germany\nFluent in spoken and written English\n\n\nWhat We Offer:\n\n\nFlat\u00a0hierarchies with short decision-making paths\nVaried\u00a0topics and constantly new challenges\nExciting\u00a0markets & business models with a diverse product portfolio ranging from emotionally charged consumer goods to complex solutions for the automotive sector\nInteresting\u00a0development opportunities on an international basis\nAttractive salary package and personal development / training\n\nWorking Location:\n\nSha Tin\n\nInterested Parties, Please send full resume with contact telephone number, present and expected salary to the Human Resources Department by clicking apply now\u00a0", "employment_types": ["Full Time", "Permanent"], "selling_points": ["To lead and manage effectively and efficiently", "Transportation/Airport Ops management exp. prefer", "Plan, organize, direct& control all aspects of Ops"], "locations": ["Kwun Tong"], "categories": ["Management", "General Management", "Transportation & Logistics", "Freight Forwarding", "Private Transportation"], "post_time": "2022-01-10T02:22:48Z", "salary": {"currency": null, "max": null, "min": null, "period": "monthly", "term": null}, "salary_visible": false, "title_keywords": ["operations manager"], "responsibilities": ["operations", "management", "ad-hoc projects", "implementation"], "requirements": {"degrees": [], "majors": [], "languages": [], "language_level": [], "hard_skills": [], "soft_skills": [], "languages_combined": []}, "experience_required": {"duration": [], "field": []}}, {"job_id": "100003009047263", "location_code": "hk", "company": "JPMorgan Chase Bank, N.A.", "job_title": "Wealth Management, UHNW Single Coverage Advisor, Hong Kong and Philippines, Vice President", "description": "Overall purpose of job:\nResponsible for marketing and sales activities to achieve the business objectives within business policies and guidelines.\nResponsible for managing the achievement of sales objectives of HIV products\nEssential duties and responsibilities:\nManages daily advertising and sales promotion activities.\nDevelop strategic plan to achieve sales objectives and other qualitative objectives\nMake regular visits to identify customers\u2019 needs and provide treatment solution to HCP\nPlan and execute product development and growth strategies\nAccountable for product marketing and strategic planning for assigned products\nP&L management and budget control of the responsible products\nWork with KOL to conclude market insight and to initiate marketing programs\nMaintain intensive working relationship with patient groups\nCommunicates and tracks short and long-range sales and marketing plans.\nComply with integrity and compliance standards\nJob Requirements\nDegree or above\nMinimum 4+ years solid and reputable experience in pharmaceutical industry with strong marketing and sales sense\nProficiency in both spoken and written English and Chinese\nSpecial requirements:\nScience and Marketing education is preferred but not a must\n\nJohnson & Johnson is an Affirmative Action and Equal Opportunity Employer. All qualified applicants will receive consideration for employment without regard to race, color, religion, sex, sexual orientation, gender identity, age, national origin, or protected veteran status and will not be discriminated against on the basis of disability.\n\n\n\nHow to Apply:\nIf you are keen to take up the challenges, please click \"apply now\". You will be redirected to J&J careers website to complete online applicant process and\u00a0online Credo Assessment.\n\nYou would be invited to an online digital interview recording once your applicant is suitable for this position.\u00a0\n\nPersonal data provided by job applicants will be used for recruitment purpose only.Candidates who are not being invited for interviews within four weeks may consider their applications unsuccessful. All applications will be kept for maximum of six months as future reference for similar openings.", "employment_types": ["Full Time"], "selling_points": [], "locations": ["Not Specified"], "categories": ["Banking / Finance", "Others", "Management", "General Management", "Wealth Management"], "post_time": "2022-01-14T02:41:50Z", "salary": {"currency": null, "max": null, "min": null, "period": "monthly", "term": null}, "salary_visible": false, "title_keywords": ["advisor", "wealth management", "vice president"], "responsibilities": ["management", "advertising", "strategic planning", "marketing plans", "compliance", "p&l", "develop", "maintain", "plan", "budget control"], "requirements": {"degrees": ["degree or above"], "majors": [], "languages": ["english", "chinese"], "language_level": ["proficiency"], "hard_skills": [], "soft_skills": ["keen"], "languages_combined": [{"language": "english", "language_level": ["proficiency"]}, {"language": "chinese", "language_level": ["proficiency"]}]}, "experience_required": {"duration": ["minimum 4+ years"], "field": ["pharmaceutical", "marketing"]}}, {"job_id": "100003009045131", "location_code": "hk", "company": "LHG Catering Limited", "job_title": "\u7063\u4ed4 - \u6c38\u83ef\u65e5\u5e38(\u4e2d\u897f\u5f0f\u9910\u98f2) - \u6536\u9280\u54e1", "description": "Summary of the Position\n\nAMPD Energy is seeking a talented and passionate individual to plan, direct, coordinate, and implement a world class assembly, configuration, and test process and to localize this process to multiple global sites. You will be working closely with leaders and teams in R&D, Field Engineering, and Supply Chain to assess the current state and develop plans for standardization and improvement and then implement. The successful candidate will be passionate about continuous improvement and excited about the opportunity to manage a process at multiple sites.\n\nWe are specifically looking for individuals who are organised, detail-oriented, and dependable. Ideally you have extensive experience in Process Management and a strong background in Lean-Six Sigma principles, Quality Tools, and best practices. This is a leadership role and so you must have specific leadership experience and outstanding leadership qualities. You will be expected to work well independently and to communicate clearly and effectively in English and preferably also Chinese.\n\nKnowledge, Qualifications and Skills\n\n\u00a0\u00a0\u00a0\u00a0\u00a0\u00a0\u00a0 Higher diploma or bachelor\u2019s degree preferably in Engineering or related field. Master\u2019s degree preferred.\n\u00a0\u00a0\u00a0\u00a0\u00a0\u00a0\u00a0 Minimum 5 years of Process or Manufacturing Management experience.\n\u00a0\u00a0\u00a0\u00a0\u00a0\u00a0\u00a0 Great planning skills, and excellent project and time management track record.\n\u00a0\u00a0\u00a0\u00a0\u00a0\u00a0\u00a0 Experience with Lean & Six Sigma principles. Experience with Quality Control in a manufacturing environment.\n\u00a0\u00a0\u00a0\u00a0\u00a0\u00a0\u00a0 Knowledge of and practice with the basic Quality Tools, 8D problem solving, SPC, ANOVA, GR&R, PPAP, Cpk analysis, and other common measurement and analytical tools.\n\u00a0\u00a0\u00a0\u00a0\u00a0\u00a0\u00a0 Great documentation, presentation, and report writing skills.\n\u00a0\u00a0\u00a0\u00a0\u00a0\u00a0\u00a0 Background in industrial and/or electrical workplace safety is a huge plus.\n\u00a0\u00a0\u00a0\u00a0\u00a0\u00a0\u00a0 Proficient in MS Office Applications (Word, Excel, Powerpoint).\n\u00a0\u00a0\u00a0\u00a0\u00a0\u00a0\u00a0 Self-motivated, detailed oriented, organized.\n\u00a0\u00a0\u00a0\u00a0\u00a0\u00a0\u00a0 Good command of spoken and written English, and ideally Chinese.\n\nSpecific duties include:\n\n\u00a0\u00a0\u00a0\u00a0\u00a0\u00a0\u00a0 Manage the assembly and configuration process for the company\u2019s products and be responsible for reporting implementation status, creating and maintaining process documentation such as Process Control Plans and Work Instructions.\n\u00a0\u00a0\u00a0\u00a0\u00a0\u00a0\u00a0 Ensure internal and external documentation meets requirements for compliance, suppliers, customers, and other stakeholders.\n\u00a0\u00a0\u00a0\u00a0\u00a0\u00a0\u00a0 Work effectively and constructively within the company\u2019s Quality Management System\n\u00a0\u00a0\u00a0\u00a0\u00a0\u00a0\u00a0 Continue to keep up to date with latest developments in all relevant standards.\n\u00a0\u00a0\u00a0\u00a0\u00a0\u00a0\u00a0 Provide periodic training for the internal team and suppliers on the assembly process and Process Management.\n\u00a0\u00a0\u00a0\u00a0\u00a0\u00a0\u00a0 Participate in new product development to ensure Assembly and manufacturing issues are addressed throughout the development process and all stakeholders understand requirements from the beginning.\n\nBenefits\n\n\u00a0\u00a0\u00a0\u00a0\u00a0\u00a0\u00a0 Competitive cash package\n\u00a0\u00a0\u00a0\u00a0\u00a0\u00a0\u00a0 Full medical, dental & travel insurance coverage\n\u00a0\u00a0\u00a0\u00a0\u00a0\u00a0\u00a0 Uber travel policy (for business travel & travel after 8pm)\n\nHow to apply\n\nPlease submit your application via https://www.linkedin.com/jobs/view/2868244993.\n\nAll information provided will be treated in strict confidence and used solely for recruitment purposes. We regret that we are only able to notify short-listed candidates.\n\nAmpd Energy is an equal opportunity employer. All candidates will be assessed on merit without regard to race, gender, sexual orientation, religion, nationality, marital status, political affiliation or any other factor protected by law.", "employment_types": ["Full Time"], "selling_points": ["\u6536\u9280", "\u4e0a\u53487\u6642\u81f3\u4e0b\u53485\u6642", "\u5168\u8077"], "locations": ["Tsuen Wan Area"], "categories": ["Hospitality / F & B", "Food & Beverage", "Management", "General Management", "Others"], "post_time": "2022-01-13T07:15:41Z", "salary": {"currency": null, "max": null, "min": null, "period": "monthly", "term": null}, "salary_visible": false, "title_keywords": [], "responsibilities": ["quality", "plan", "plans", "control", "maintaining", "configuration", "compliance", "teams", "measurement", "implementation", "develop plans", "report", "reporting", "management", "documentation", "analysis", "coordinate", "quality control", "planning"], "requirements": {"degrees": ["diploma", "degree", "bachelor", "master"], "majors": ["engineering"], "languages": ["english", "chinese"], "language_level": ["good command"], "hard_skills": ["r&d", "excel", "lean", "plus", "basic", "analysis", "word", "writing skills", "powerpoint", "problem solving", "six sigma", "documentation", "ms office"], "soft_skills": ["passionate", "planning skills", "self-motivated", "independently", "detailed oriented", "organized", "responsible", "work effectively", "writing skills", "detail-oriented", "problem solving", "leadership", "organised", "time management", "extensive", "presentation", "passionate about"], "languages_combined": [{"language": "english", "language_level": ["good command"]}, {"language": "chinese", "language_level": ["good command"]}]}, "experience_required": {"duration": ["minimum 5 years"], "field": ["management", "manufacturing", "quality control"]}}, {"job_id": "100003009041934", "location_code": "hk", "company": "\u83ef\u79d1\u8cc7\u672c\u6709\u9650\u516c\u53f8", "job_title": "Assistant Legal Manager", "description": "\u8077\u8cac:\n\n\u8ca0\u8cac\u6536\u9280\u5de5\u4f5c\n\n\u5de5\u4f5c\u6642\u9593\u53ca\u65e5\u6578 (\u8996\u4e4e\u5e97\u8216\u71df\u904b\u9700\u8981\u800c\u5b9a)\n\n\u6bcf\u9031\u5de5\u4f5c5-6\u5929\uff0c\u6bcf\u59299\u5c0f\u6642\u5de5\u4f5c\uff0c\u8f2a\u73ed\u8f2a\u4f11\n\u5de5\u4f5c\u6642\u9593: \u4e0a\u53487\u6642\u81f3\u4e0b\u53485\u6642\n\u00a0\n\n\u798f\u5229:\n\n\u6bcf\u6708\u76ee\u6a19\u734e\u91d1\u3001\u65b0\u6625\u8cde\u91d1\u3001\u798f\u98df\u3001\u5c0f\u8cbb\u3001\u4ea4\u901a\u6d25\u8cbc\u3001\u65b0\u4eba\u734e\u91d1\u3001\u52a0\u73ed\u6d25\u8cbc\u3001\u91ab\u7642\u6d25\u8cbc\n\u6709\u85aa\u5e74\u5047\u3001\u6bcf\u6708\u4f11\u606f\u65e5\u3001\u751f\u65e5\u5047\u53ca\u5229\u662f\u3001\u7fa9\u5de5\u5047\u3001\u7537\u58eb\u4f8d\u7522\u50475\u5929\n\n\u806f\u7d61\u65b9\u6cd5:\n\n\u6b61\u8fce\u6709\u8208\u8da3\u4e4b\u7533\u8acb\u8005\u81f4\u96fb 3962 1190 \u6216 Whatsapp 5195 1706 \u67e5\u8a62", "employment_types": ["Full Time"], "selling_points": [], "locations": ["Central"], "categories": ["Professional Services", "Company Secretary", "Management", "General Management", "Legal & Compliance"], "post_time": "2022-01-12T04:42:41Z", "salary": {"currency": null, "max": null, "min": null, "period": "monthly", "term": null}, "salary_visible": false, "title_keywords": ["manager", "assistant"], "responsibilities": [], "requirements": {"degrees": [], "majors": [], "languages": [], "language_level": [], "hard_skills": ["whatsapp"], "soft_skills": [], "languages_combined": []}, "experience_required": {"duration": [], "field": []}}, {"job_id": "100003009033827", "location_code": "hk", "company": "Konica Minolta Business Solutions (HK) Limited", "job_title": "Assistant Operations Support Manager", "description": "Responsibilities:\n\n\u00fc\u00a0\u00a0 Providing legal support to the company on a wide range of general corporate and commercial matters\n\n\u00fc\u00a0\u00a0 Drafting and reviewing legal documents\n\n\u00fc\u00a0\u00a0 Conducting legal research and advising business units on legal issues and regulatory matters\n\n\u00fc\u00a0\u00a0 Monitoring and reviewing business activities, transactions, documentation and other records in ensuring compliance with regulatory requirements\n\n\u00fc\u00a0\u00a0 Preparing, attending and participating in meetings with senior management, department heads, and/or external stakeholders\n\n\u00fc\u00a0\u00a0 Assisting in the establishment and implementation of internal policies and procedures\n\n\u00fc\u00a0\u00a0 Performing ad hoc projects as required\n\nRequirements:\n\n\u00fc\u00a0\u00a0 Law degree holder\n\n\u00fc\u00a0\u00a0 Minimum 5 years\u2019 legal and compliance experience\n\n\u00fc\u00a0\u00a0 Knowledge of the Hong Kong Listing Rules preferred\n\n\u00fc\u00a0\u00a0 Good command in English and Chinese, fluency in Putonghua an advantage\n\n\u00fc\u00a0\u00a0 Independent, self-initiative, attentive to details and standard, and a team player\n\n\nPlease submit your application to us with your availability\u00a0and expected salary.", "employment_types": ["Full Time", "Permanent"], "selling_points": ["Evaluate the efficiency of manpower", "5 days work", "experience in B2B market is preferable"], "locations": ["Not Specified"], "categories": ["Management", "General Management", "Marketing / Public Relations", "Management", "Marketing - Brand / Product Management"], "post_time": "2022-01-10T01:52:00Z", "salary": {"currency": null, "max": null, "min": null, "period": "monthly", "term": null}, "salary_visible": false, "title_keywords": ["operations", "manager", "assistant"], "responsibilities": ["regulatory requirements", "policies", "compliance", "monitoring", "implementation", "transactions", "procedures", "ad hoc projects", "documentation", "senior management", "business activities"], "requirements": {"degrees": ["degree holder"], "majors": ["law"], "languages": ["putonghua", "english", "chinese"], "language_level": ["fluency", "advantage", "good command"], "hard_skills": [], "soft_skills": ["attentive to details", "team player", "independent", "self-initiative"], "languages_combined": [{"language": "putonghua", "language_level": ["fluency", "good command"]}, {"language": "english", "language_level": ["fluency", "advantage", "good command"]}, {"language": "chinese", "language_level": ["fluency", "advantage", "good command"]}]}, "experience_required": {"duration": ["minimum 5 years"], "field": ["compliance", "legal"]}}, {"job_id": "100003009034070", "location_code": "hk", "company": "Hong Kong China Golden Investment Limited", "job_title": "\u9805\u76ee\u7d93\u7406", "description": "What You'll Do\n\nTo provide quality services to our residents and guests\nTo be responsible for daily operation of the property, including but not limited to office administration, procurement, customer services, complaint handling etc.\nTo supervise the overall performance of contractors to ensure their services\u00a0properly provided\nTo direct and supervise building staff\nTo perform other duties as assigned by supervisor\u00a0\n\nWho You\u2019ll Work With\n\nYou will work with the property services team and external contractors to provide excellent services to all residents and guests.\u00a0\u00a0\n\nWho You Are\n\nCompetencies:\n\nCustomer Oriented\nBuilds Teams\nDevelops Solutions\nPersonally Accountable\u00a0\n\nQualifications and Requirements:\n\nDegree / Diploma holder in Property Management, Facilities Management or related disciplines\nAt least 1 years' of relevant experience in\u00a0luxury residential building\nMember of a professional body recognized by the\u00a0PMSA\u00a0is an advantage\nGood command of both spoken and written English and Chinese\nProficient in MS Office", "employment_types": ["Full Time"], "selling_points": [], "locations": ["Others - China"], "categories": ["Management", "General Management"], "post_time": "2022-01-10T02:35:23Z", "salary": {"currency": null, "max": null, "min": null, "period": "monthly", "term": null}, "salary_visible": false, "title_keywords": [], "responsibilities": ["perform other duties", "management", "office administration", "daily operation", "quality", "teams", "customer services"], "requirements": {"degrees": ["diploma holder", "degree"], "majors": ["related disciplines"], "languages": ["english", "chinese"], "language_level": ["good command"], "hard_skills": ["facilities management", "ms office"], "soft_skills": ["accountable", "responsible"], "languages_combined": [{"language": "english", "language_level": ["good command"]}, {"language": "chinese", "language_level": ["good command"]}]}, "experience_required": {"duration": ["at least 1 years"], "field": ["relevant experience"]}}, {"job_id": "100003009045062", "location_code": "hk", "company": "Antnergy Social Resources", "job_title": "Management Trainee (18-22K, Fresh Grad)", "description": "Provide risk management services that support and facilitate the delivery of business plans, projects and initiatives of the Company.\n\nMain Responsibilities:\n\n\n\nPromote the culture of risk management, educate and train the local managers and employees in risk management principles and methodologies\nMaintain an effective Enterprise Risk Management framework to ensure compliance with regulatory requirements\nManage the implementation of all aspects of the risk function, including implementation of processes, tools and systems to identify, assess, measure, manage, monitor and report risks\nManage the process for developing risk policies and procedures, risk limits and approval authorities\nImplement and maintain the Internal Control Framework\nConduct risk assessments covering strategic, operational areas and project risks, and followed up on improvement actions with related parties\nParticipate in Risk Management and Control committee meeting, Investment\nManagement Committee, Dividend Committee and Management meetings to ensure risks are reported and actions in place to address the risks\nCoordinate and prepare reports to comply with solvency regulatory reporting requirements\nEnsure the Business Continuity Plan is effective and coordinate the drill test\n\nIncumbent Requirements:\n\nAcademic & Professional Qualification\n\nUniversity degree in accounting or actuarial\n\nExperience\n\n\nOver 10 years\u2019 experience in the insurance industry and in management position\nSolid experience risk management, internal audit or control functions\n\n\nKnowledge & Skill Required\n\n\nGood understanding of the insurance business and the risk management framework\nGood communication skills in both English and Chinese", "employment_types": ["Full Time"], "selling_points": ["Fast Track to Management in 2 years", "Professional Training Program", "Work Life balance, harmonious work environment"], "locations": ["Quarry Bay"], "categories": ["Banking / Finance", "Financial Services", "Management", "General Management", "Others", "Student / Fresh Graduate / No Experience"], "post_time": "2022-01-13T07:02:06Z", "salary": {"currency": null, "max": null, "min": null, "period": "monthly", "term": null}, "salary_visible": false, "title_keywords": ["management trainee"], "responsibilities": ["reporting", "management", "control", "business continuity", "regulatory requirements", "policies", "systems", "monitor", "implementation", "developing", "ensure compliance", "procedures", "coordinate", "maintain", "plan", "prepare reports", "internal control", "report"], "requirements": {"degrees": ["university degree"], "majors": ["accounting"], "languages": ["english", "chinese"], "language_level": ["good"], "hard_skills": [], "soft_skills": ["communication skills"], "languages_combined": [{"language": "english", "language_level": ["good"]}, {"language": "chinese", "language_level": ["good"]}]}, "experience_required": {"duration": ["10 years"], "field": ["management position", "risk management", "insurance industry", "audit"]}}, {"job_id": "100003009042917", "location_code": "hk", "company": "Tahoe Life Insurance Company Limited", "job_title": "Head of Risk Management and Control", "description": "\u8077\u8cac:\n\n1) \u76e3\u63a7\u53ca\u4fdd\u6301\u98df\u7269\u8cea\u7d20\u3001\u8ce3\u76f8\u53ca\u63a7\u5236\u98df\u54c1\u8ca8\u5b58;\n2) \u5354\u52a9\u7ba1\u7406\u5eda\u623f\u4eba\u624b\u7ba1\u7406\u3001\u8655\u7406\u57f9\u8a13\u5de5\u4f5c\u53ca\u5f8c\u52e4\u4e8b\u5b9c;\n3) \u76e3\u5bdf\u53ca\u7763\u5c0e\u5404\u54e1\u5de5\u4e4b\u5de5\u4f5c\u65b9\u5f0f\u3001\u614b\u5ea6\u53ca\u5100\u5bb9\u7b49\u798f\u5229:\n\n\u798f\u5229\n\n\u6bcf\u6708\u76ee\u6a19\u734e\u91d1\u3001\u65b0\u6625\u8cde\u91d1\u3001\u81b3\u98df\u6d25\u8cbc / \u798f\u98df\u3001\u5c0f\u8cbb\u3001\u4ea4\u901a\u6d25\u8cbc\u3001\u65b0\u4eba\u734e\u91d1\u3001\u52a0\u73ed\u6d25\u8cbc\u3001\u91ab\u7642\u6d25\u8cbc\n\n\u5047\u671f:\n\n\u6709\u85aa\u5e74\u504712\u5929\u3001\u6bcf\u67086\u5929\u4f11\u606f\u65e5\u3001\u751f\u65e5\u5047\u53ca\u5229\u662f\u3001\u7fa9\u5de5\u5047\u3001\u7537\u58eb\u4f8d\u7522\u50475\u5929\n\n\u5de5\u4f5c\u6642\u9593\u53ca\u65e5\u6578 (\u8996\u4e4e\u5e97\u8216\u71df\u904b\u9700\u8981\u800c\u5b9a)\n\n\u6bcf\u9031\u5de5\u4f5c5-6\u5929\uff0c\u6bcf\u59299\u5c0f\u6642\u5de5\u4f5c\uff0c\u8f2a\u73ed\u8f2a\u4f11\n\u00a0\n\n\u806f\u7d61\u65b9\u6cd5:\n\n\u6b61\u8fce\u6709\u8208\u8da3\u4e4b\u7533\u8acb\u8005\u81f4\u96fb 3962 1190 \u6216 Whatsapp 5195 1706 \u67e5\u8a62", "employment_types": ["Full Time", "Permanent"], "selling_points": ["Report to CEO", "10+ yrs\u2019 exp. in insurance industry", "Risk Management"], "locations": ["Tsim Sha Tsui"], "categories": ["Professional Services", "Business Consultancy", "Management", "General Management", "Insurance", "Others"], "post_time": "2022-01-12T09:14:37Z", "salary": {"currency": null, "max": null, "min": null, "period": "monthly", "term": null}, "salary_visible": false, "title_keywords": [], "responsibilities": [], "requirements": {"degrees": [], "majors": [], "languages": [], "language_level": [], "hard_skills": ["whatsapp"], "soft_skills": [], "languages_combined": []}, "experience_required": {"duration": [], "field": []}}, {"job_id": "100003009045078", "location_code": "hk", "company": "Kabushikigaisha Limited", "job_title": "\u725b\u89d2 - \u5eda\u52d9\u4e3b\u4efb", "description": "Responsibilities:\n-\u00a0 \u00a0 Take responsibility in managing carpark operations in designated district(s)\n-\u00a0 \u00a0 Enforce Company\u2019s operation and administration procedures\n-\u00a0 \u00a0 Handle customer enquiries and complaints\n-\u00a0 \u00a0 Perform on-call duty after office hours\n\nRequirements:\n-\u00a0 \u00a0 Possess tertiary education or professional qualification\n-\u00a0 \u00a0 3-5 years\u2019 managerial experience in customer service industry / retail operations\n-\u00a0 \u00a0 Solid supervisory skill, experience in property management preferable\n-\u00a0 \u00a0 Good command in both written and spoken English and Chinese\n-\u00a0 \u00a0 Holder of valid Hong Kong Driving Licence\u00a0\n\nInterested candidates please forward their applications with detailed resume to:\nHead of Group Human Resources\nWilson Parking (Holdings) Limited\n\u5a01\u4fe1\u505c\u8eca\u5834\u7ba1\u7406(\u63a7\u80a1)\u6709\u9650\u516c\u53f8\nRoom 2901, Tower 1, Metroplaza, 223 Hing Fong Road, Kwai Chung, N.T.\nor email: hr @wilsongrouphk.com\n\nAll personal data collected will be kept in the strictest confidence and\u00a0used for recruitment purpose only.\n\nYou are welcome to visit our website:\nwww.wilsonparking.com.hk", "employment_types": ["Full Time"], "selling_points": ["\u76e3\u63a7\u53ca\u4fdd\u6301\u98df\u7269\u8cea\u7d20\u3001\u8ce3\u76f8\u53ca\u63a7\u5236\u98df\u54c1\u8ca8\u5b58", "\u5354\u52a9\u7ba1\u7406\u5eda\u623f\u4eba\u624b\u7ba1\u7406\u3001\u8655\u7406\u57f9\u8a13\u5de5\u4f5c\u53ca\u5f8c\u52e4\u4e8b\u5b9c", "\u76e3\u5bdf\u53ca\u7763\u5c0e\u5404\u54e1\u5de5\u4e4b\u5de5\u4f5c\u65b9\u5f0f\u3001\u614b\u5ea6\u53ca\u5100\u5bb9\u7b49"], "locations": ["Not Specified"], "categories": ["Hospitality / F & B", "Food & Beverage", "Management", "General Management", "Others"], "post_time": "2022-01-13T07:06:18Z", "salary": {"currency": null, "max": null, "min": null, "period": "monthly", "term": null}, "salary_visible": false, "title_keywords": [], "responsibilities": ["carpark operations", "company\u2019s operation", "customer enquiries and complaints", "administration procedures"], "requirements": {"degrees": [], "majors": [], "languages": ["english", "chinese"], "language_level": ["good command"], "hard_skills": ["hong kong driving licence"], "soft_skills": ["customer service"], "languages_combined": [{"language": "english", "language_level": ["good command"]}, {"language": "chinese", "language_level": ["good command"]}]}, "experience_required": {"duration": ["3-5 years"], "field": ["managerial", "supervisory", "management", "retail operations", "customer service"]}}, {"job_id": "100003009036347", "location_code": "hk", "company": "Wilson Parking (Holdings) Ltd", "job_title": "Deputy Area Manager (Carpark Operations)", "description": "\u8077\u8cac:\n\n\u8ca0\u8cac\u5206\u5e97\u5eda\u623f\u5de5\u4f5c\uff0c\u5305\u62ec\u6d17\u83dc\u3001\u5207\u83dc\u3001\u5207\u8089\u3001\u6e96\u5099\u98df\u6750\u53ca\u5eda\u623f\u57fa\u672c\u6e05\u6f54\u7b49\n\n\u798f\u5229:\n\n\u6bcf\u6708\u76ee\u6a19\u734e\u91d1\u3001\u65b0\u6625\u8cde\u91d1\u3001\u81b3\u98df\u6d25\u8cbc / \u798f\u98df\u3001\u5c0f\u8cbb\u3001\u4ea4\u901a\u6d25\u8cbc\u3001\u65b0\u4eba\u734e\u91d1\u3001\u52a0\u73ed\u6d25\u8cbc\u3001\u91ab\u7642\u6d25\u8cbc\n\n\u5047\u671f:\n\n\u6709\u85aa\u5e74\u504712\u5929\u3001\u6bcf\u67086\u5929\u4f11\u606f\u65e5\u3001\u751f\u65e5\u5047\u53ca\u5229\u662f\u3001\u7fa9\u5de5\u5047\u3001\u7537\u58eb\u4f8d\u7522\u50475\u5929\n\n\u5de5\u4f5c\u6642\u9593\u53ca\u65e5\u6578 (\u8996\u4e4e\u5e97\u8216\u71df\u904b\u9700\u8981\u800c\u5b9a)\n\n\u6bcf\u9031\u5de5\u4f5c5-6\u5929\uff0c\u6bcf\u59299\u5c0f\u6642\u5de5\u4f5c\uff0c\u8f2a\u73ed\u8f2a\u4f11\n\u00a0\n\n\u806f\u7d61\u65b9\u6cd5:\n\n\u6b61\u8fce\u6709\u8208\u8da3\u4e4b\u7533\u8acb\u8005\u81f4\u96fb 3962 1190 \u6216 Whatsapp 5195 1706 \u67e5\u8a62", "employment_types": ["Full Time", "Permanent"], "selling_points": ["Manage carpark operations in designated district", "Enforce company policies & handle customer service", "Tertiary education with 3-5 years' managerial exp"], "locations": ["Not Specified"], "categories": ["Management", "General Management", "Property / Real Estate", "Property Management"], "post_time": "2022-01-10T16:52:49Z", "salary": {"currency": null, "max": null, "min": null, "period": "monthly", "term": null}, "salary_visible": false, "title_keywords": ["area manager", "operations"], "responsibilities": [], "requirements": {"degrees": [], "majors": [], "languages": [], "language_level": [], "hard_skills": ["whatsapp"], "soft_skills": [], "languages_combined": []}, "experience_required": {"duration": [], "field": []}}, {"job_id": "100003009045071", "location_code": "hk", "company": "Kabushikigaisha Limited", "job_title": "\u725b\u89d2 - \u52a9\u7406\u5eda\u52d9\u4e3b\u4efb", "description": "\u5de5\u4f5c\u5167\u5bb9:\n\u652f\u63f4\u524d\u7dda\u5206\u5e97\u7684\u71df\u904b;\n\u5354\u52a9\u7d93\u7406\u8655\u7406\u5206\u5e97\u6295\u8a34\u500b\u6848;\n\u5354\u52a9\u7d93\u7406\u7ba1\u7406\u524d\u7dda\u71df\u904b\u66f4\u8868\u5b89\u6392;\n\u8ca0\u8cac\u7ba1\u7406\u53ca\u5b89\u6392\u8a3a\u6240\u71df\u904b\u53ca\u92b7\u552e\u7269\u8cc7;\n\u5b89\u6392\u71df\u904b\u5718\u968a\u8655\u7406\u6587\u4ef6\u53ca\u5ba2\u6236\u8cc7\u6599;\n\u5176\u4ed6\u76f8\u95dc\u5de5\u4f5c\n\n\u8077\u4f4d\u8981\u6c42:\n\n\n2\u5e74\u4ee5\u4e0a\u524d\u7dda\u71df\u904b\u7d93\u9a57;\n\u5177\u8a3a\u6240/\u7f8e\u5bb9\u884c\u696d\u76f8\u95dc\u7d93\u9a57, \u6709\u8ddf\u75c7/\u91ab\u7f8e\u516c\u53f8\u7d93\u9a57\u512a\u5148;\n\u7a4d\u6975\u4e3b\u52d5,\u6709\u826f\u597d\u7684\u6e9d\u901a\u53ca\u7ba1\u7406\u80fd\u529b;\n\u4e2d\u3001\u82f1\u6587\u66f8\u5beb\u826f\u597d,\u61c2\u82f1\u8a9e,\u7cb5\u8a9e\u53ca\u666e\u901a\u8a71;\n\u5177\u6709\u57fa\u672c\u7684\u96fb\u8166\u77e5\u8b58(Words, Excels).", "employment_types": ["Full Time"], "selling_points": ["\u5206\u5e97\u5eda\u623f\u5de5\u4f5c", "\u5eda\u623f\u57fa\u672c\u6e05\u6f54", "\u6bcf\u59299\u5c0f\u6642\u5de5\u4f5c\uff0c\u8f2a\u73ed\u8f2a\u4f11"], "locations": ["Not Specified"], "categories": ["Hospitality / F & B", "Food & Beverage", "Management", "General Management", "Others"], "post_time": "2022-01-13T07:04:09Z", "salary": {"currency": null, "max": null, "min": null, "period": "monthly", "term": null}, "salary_visible": false, "title_keywords": [], "responsibilities": [], "requirements": {"degrees": [], "majors": [], "languages": [], "language_level": [], "hard_skills": [], "soft_skills": [], "languages_combined": []}, "experience_required": {"duration": [], "field": []}}, {"job_id": "100003009039753", "location_code": "hk", "company": "KOS International Limited", "job_title": "Deputy Head of Loans Operations (Bank)", "description": "\uff08\u4e00\uff09\u8077\u8cac\uff1a\n\n1.\u00a0\u7ba1\u7406\u9805\u76ee\u6295\u8cc7\u5718\u968a\n\n2.\u00a0\u5c0d\u5df2\u6295\u8cc7\u9805\u76ee\u505a\u71df\u904b\u7ba1\u7406\n\n3.\u00a0\u9805\u76ee\u6295\u8cc7\u7ba1\u7406\uff0c\u5305\u62ec\u505a\u9805\u76ee\u53ef\u884c\u6027\u5206\u6790\uff0c\u6295\u8cc7\u6536\u76ca\u5206\u6790\n\n\uff08\u4e8c\uff09\u8981\u6c42\uff1a\n\n1.\u00a0\u6709\u4e00\u5b9a\u4e2d\u570b\u5927\u9678\u5730\u5340\u9805\u76ee\u6295\u8cc7\u7ba1\u7406\u7d93\u9a57\n\n2.\u00a0\u5584\u65bc\u8655\u7406\u8207\u5ba2\u6236\u7684\u95dc\u4fc2\n\n3.\u00a0\u57f7\u884c\u80fd\u529b\u5f37\uff0c\u6709\u5718\u968a\u7ba1\u7406\u7d93\u9a57\n\n4.\u00a0\u666e\u901a\u8a71\u6d41\u5229\n\n5.\u00a0\u672c\u79d1\u4ee5\u4e0a\u5b78\u6b77\n\n\n\n\u5de5\u4f5c\u5730\u70b9\uff1a\u9999\u6e2f\u3001\u5927\u9646", "employment_types": ["Full Time", "Permanent"], "selling_points": ["All-rounded loans operations", "Solid in project management", "Strong people management"], "locations": ["Not Specified"], "categories": ["Banking / Finance", "Loan", "Retail Banking", "Management", "General Management"], "post_time": "2022-01-11T10:56:28Z", "salary": {"currency": null, "max": null, "min": null, "period": "monthly", "term": null}, "salary_visible": false, "title_keywords": ["operations"], "responsibilities": [], "requirements": {"degrees": [], "majors": [], "languages": [], "language_level": [], "hard_skills": [], "soft_skills": [], "languages_combined": []}, "experience_required": {"duration": [], "field": []}}, {"job_id": "100003009037008", "location_code": "hk", "company": "CEO mindPower Ltd", "job_title": "Business Consultant", "description": "Deputy Head of Loans Operations (bank)\n\nIn-charge of loan operations\nRetail and Commercial loans\nStrong people management\n\nAbout the company\n\nOur client is a well-established and fast growing banking group in Hong Kong. To cope with the business expansion, they are now looking for a Head of Loans Operations for their Banking Operations team.\n\nAbout the role\n\nReporting to the Head of Loans Operations, you will lead team members to perform overall loan operations and administrations for both retail and commercial banking lending products. You are required to manage loans booking, drawdown, funds disbursement, fee collection and related data maintenance. You have to review loan operations manuals, policies and procedures to ensure all activities are complied with guidelines and regulations. You will be assigned to conduct projects in streamlining workflow procedures and provide recommendation to improve effectiveness. In addition, you will work with other internal departments to support new product launch and system enhancement projects to optimize operational efficiency.\n\nThe successful applicant\n\nTo qualify, the successful individual must possess:\n\nUniversity Graduate with majoring in Business Administration or other related disciplines.\nMinimum 10 years relevant experience in managing loan operations of retail and /or commercial loans in banks with at least 4 years in managerial level.\nSound knowledge in loans drawdown, system enhancement and operations control in banking is a must.\nStrong people leadership, good project skills and analytical mind.\nGood command in both spoken and written English, Cantonese and Mandarin.\n\nClick \"Apply Now\" to apply for this position or call Emily Leung at +852 3180 4913 for a confidential discussion. All information collected will be kept in strict confidence and will be used for recruitment purpose only.", "employment_types": ["Full Time"], "selling_points": [], "locations": ["Wan Chai"], "categories": ["Professional Services", "Business Consultancy", "Sales, CS & Business Devpt", "Business Development", "Management", "General Management"], "post_time": "2022-01-11T01:17:38Z", "salary": {"currency": null, "max": null, "min": null, "period": "monthly", "term": null}, "salary_visible": false, "title_keywords": ["consultant"], "responsibilities": ["regulations", "reporting", "management", "control", "maintenance", "data", "guidelines", "operations", "policies", "review", "procedures", "improve effectiveness", "provide recommendation", "recruitment", "booking", "banking", "enhancement projects", "administration"], "requirements": {"degrees": ["university graduate"], "majors": ["related disciplines", "business administration"], "languages": ["cantonese", "english", "mandarin"], "language_level": ["good command"], "hard_skills": ["maintenance"], "soft_skills": ["analytical mind", "leadership", "confidence"], "languages_combined": [{"language": "cantonese", "language_level": ["good command"]}, {"language": "english", "language_level": ["good command"]}, {"language": "mandarin", "language_level": ["good command"]}]}, "experience_required": {"duration": ["at least 4 years", "minimum 10 years"], "field": ["commercial", "retail", "relevant experience", "managerial"]}}, {"job_id": "100003009046457", "location_code": "hk", "company": "Sun Life Hong Kong Ltd", "job_title": "Management Trainee Program (Degree Holder in Any Disciplines)", "description": "What you will do\n\nYou will play an active role in further expansion of our business.\n\n\nSupport the Senior Business Development Manager & CEO in achieving company sales and profit targets\nSupport the business development efforts and account servicing of the company\nSupport in preparing proposals, quantitative forecasts, market analysis and other related Business Development activities\nManage and create content for the social media accounts and website of the company and the CEO\nCompile regular reports on performance of website traffic, Google Ads, and social media accounts\nSupport in administration and ad hoc project management tasks as required by the company\n\nWhat is required of you\n\n\nDegree holder or above in Business or related fields\nExcellent communication skills in oral & written English & Chinese (Cantonese & Mandarin)\n2 to 3 years of work experience\nStrong interest in business consultancy and training\nExcellent interpersonal skills and works well under pressure\nExcellent multi-tasker, detail-orientated, and independent worker\nSelf-motivated and strives for excellence\nProficient computer skills with expertise in using MS Word, Excel, PowerPoint\nAdobe Photoshop and/or Adobe Illustrator and video-editing skills preferred\nSEO and Google Ads knowledge preferred\n\nAn attractive remuneration package with career advancement opportunities will be offered with the right candidate.\n\nCome join us now! Send your detailed CV highlighting your career objectives to us.\n\nFind out more about us at www.ceompower.com", "employment_types": ["Full Time"], "selling_points": ["5 day works", "$17,000-$30,000", "Competitive pay"], "locations": ["Hung Hom"], "categories": ["Banking / Finance", "Corporate Finance", "Management", "General Management", "Marketing / Public Relations", "Management"], "post_time": "2022-01-13T11:23:10Z", "salary": {"currency": "HKD", "max": 29999, "min": 17000, "period": "monthly", "term": null}, "salary_visible": true, "title_keywords": ["management trainee"], "responsibilities": ["social media", "ad hoc", "seo", "website", "communication", "project management", "market analysis", "reports", "editing", "administration"], "requirements": {"degrees": ["degree holder"], "majors": ["business"], "languages": ["cantonese", "english", "chinese", "mandarin"], "language_level": ["excellent"], "hard_skills": ["excel", "seo", "analysis", "adobe photoshop", "powerpoint", "adobe illustrator", "project management", "computer skills", "ms word"], "soft_skills": ["communication skills", "oral", "self-motivated", "under pressure", "independent", "project management", "interpersonal skills", "active", "detailed"], "languages_combined": [{"language": "cantonese", "language_level": ["excellent"]}, {"language": "english", "language_level": ["excellent"]}, {"language": "chinese", "language_level": ["excellent"]}, {"language": "mandarin", "language_level": ["excellent"]}]}, "experience_required": {"duration": ["2 to 3 years"], "field": []}}, {"job_id": "100003009037813", "location_code": "hk", "company": "Inspire Brands Capital", "job_title": "Franchise Development Manager - Hong Kong", "description": "Job Highlights\n\nBachelor degree holder in all disciplines\nWell-development career ladder\nFive-day work\n\nJob Description\n\nYou will enjoy working at Sun Life if you are with vision, energy and targets, join us and be part of a dynamic team and create values together.\n\nAs the leader in wealth management, offering innovative and intelligent solutions to thousands of individual and businesses in Hong Kong, China, Canada, Malaysia, Indonesia and other high growth cities around the world. We keep our clients\u2019 interests foremost in our minds at all times. This combination of intellectual capital, comprehensive training, staffed with quality leaders and professional managers set us apart as an industrial leader.\n\nWe are currently seeking young and energetic talents\u00a0to join our team as a\u00a0Management Trainee.\n\nJob Responsibilities\n\nProvide professional financial services to our clients, including risk management, health protection, retirement planning and wealth accumulation\nManaging the total wealth of clients by matching our financial and investment solutions to fulfill their financial needs\nClients relationship management, expand clients\u2019 network and review their financial need regularly\nPromoting our Premier Service to potential clients, exploring their needs and making referrals to other business units where appropriate\u00a0\n\nBenefits and Packages\n\nFive-day work\nCompetitive Pay With Quarterly Bonus and Year End Bonus\nInitial Training and On-Job Training Provided\nExcellent Career Path to Management Ladder\nLife and Medical Insurance\nClient Base Provided\u00a0\nFlexible Working Hours\u00a0\nEducation Subsidies\n\nRequirements\n\nBachelor degree or above (Fresh graduates is welcomed)\n1 year working experience or above is preferred\nExperience in\u00a0customer service or sales field\nProactive with positive mindset, excellent interpersonal &\u00a0communication skills\nAble to work independently\nFluent in Cantonese, moderate English\u00a0\n\nWorking Location\n\n\n\nWhampoa\u00a0\n\n**Personal date provided by applicants will be treated in strict confidence and used for recruitment purposes only**\n\nIf you have any further enquiries, please press\u00a0APPLY NOW\u00a0to contact us with your CV. We will get back to you shortly.", "employment_types": ["Full Time"], "selling_points": ["Generous salary with commissions and bonuses", "Career growth and development opportunity", "Fun, friendly culture with team rewards, events."], "locations": ["Others"], "categories": ["Management", "General Management", "Marketing / Public Relations", "Marketing - Market Research"], "post_time": "2022-01-11T04:11:35Z", "salary": {"currency": "HKD", "max": 54999, "min": 45000, "period": "monthly", "term": null}, "salary_visible": true, "title_keywords": ["manager"], "responsibilities": ["management", "review", "quality", "planning"], "requirements": {"degrees": [], "majors": [], "languages": [], "language_level": [], "hard_skills": [], "soft_skills": [], "languages_combined": []}, "experience_required": {"duration": [], "field": []}}, {"job_id": "100003009038262", "location_code": "hk", "company": "Lululemon HK Limited", "job_title": "Buying Manager, Men's (1 year contract)", "description": "About the Role\n\nBaker McKenzie is currently looking for a Business Manager, to lead and coordinate business operations with the aim of driving and enhancing practice performance in line with the global practice strategy and the overall strategy of the Firm.\n\nMain Responsibilities\n\nAdvise and support Practice Group Leaders on strategic, business and operational related topics\nDevelop, update and monitor the business plan of the practice and help develop and manage budget proactively to ensure effective implementation of the Firm strategy\nDrive improvements of operational and financial performance by monitoring and analysing key performance indicators at practice and service line level, ensuring alignment with planned targets (including cost management, working capital, staffing and margin contribution)\nEnsure cross-practice and cross-functional initiatives implementation at Practice Group level and coordinate resources from other Professional & Business Services (PBS) functions supporting the same Practice Group to ensure proper coverage and effective strategy execution\nFormulate and operationalize strategic initiatives leveraging our geographic, industry and client reach, with a clear view to building market presence and generating revenue\nCapture efficiency and innovation opportunities for the main service lines by leading and participating in initiatives, aligned within the global practice and with other Practice Groups\nEnsure appropriate resourcing model, headcount planning, staffing, and talent pipeline (including training and performance management) leveraging support from, and in coordination with, other PBS functions\nCoordinate interactions with Industry Groups making sure that go-to-market and service delivery is appropriate for clients in those sectors\nMonitor and ensure effective implementation of client and business development plans leveraging support from other PBS functions\nCoordinate internal Practice Group engagement activities and meetings fostering positive and open communication\nLeverage services provided by shared service centres and specialist functions within the PBS organization to drive excellence and efficiency\nLead and participate in projects for the practice\n\nAbout the Team\n\nThe Firm's Services function works closely with our Partners and fee-earners to deliver comprehensive, high quality and high value services to our clients. It is geared towards improving operational and financial performance, and constantly rethinking the services we offer, as well as developing new innovative solutions and platforms.\n\nAbout the Candidate\n\nRelevant undergraduate degree required\nGood professional management experience in a global setting, ideally in a professional services environment\nProficiency in law firm operations, legal accounting and finance\nProficiency in using MS Office applications, including PowerPoint and advanced functions of Excel\nUnderstanding of the elements of law firm profitability at practice group, service line, client, matter and attorney level\nStrong business sense and good judgment in problem-solving\nExcellent oral and written communication skills; effective communicator at all organizational levels\nExperience with business management, including an understanding of the challenges of operating in different markets regionally\nAbility to manage multiple complex operations with continual attention to detail (including accuracy with numbers)\nExperience conducting complex qualitative and quantitative analysis, interpreting results and suggesting action plans\nExperience coordinating people in different locations and cultures\nAbility to work effectively in informal teams and collaborate cross-practice and cross-function in a global organisation", "employment_types": ["Full Time", "Temporary", "Contract"], "selling_points": ["People management and leadership experience", "Passion for buying and product", "Strong sense of fashion trends in sports apparel"], "locations": ["Tin Hau"], "categories": ["Management", "General Management", "Merchandising & Purchasing", "Woven / Knit", "Others"], "post_time": "2022-01-11T06:23:27Z", "salary": {"currency": null, "max": null, "min": null, "period": "monthly", "term": null}, "salary_visible": false, "title_keywords": ["buying manager"], "responsibilities": ["operations", "budget", "coordination with", "quality", "communication", "plans", "service delivery", "collaborate", "monitor", "implementation", "developing", "develop", "teams", "business plan", "cost", "management", "monitoring", "analysis", "coordinate", "planning"], "requirements": {"degrees": ["degree"], "majors": [], "languages": [], "language_level": [], "hard_skills": ["business management", "excel", "problem-solving", "analysis", "powerpoint", "go", "ms office"], "soft_skills": ["work effectively", "communication skills", "oral", "advanced", "business sense", "organizational", "problem-solving", "clear", "communication", "comprehensive", "coordination", "attention to detail", "organisation", "communicator", "innovative", "positive"], "languages_combined": []}, "experience_required": {"duration": [], "field": ["management", "business"]}}, {"job_id": "100003009034396", "location_code": "hk", "company": "PS Group International Ltd", "job_title": "Personal Assistant to Group Founder", "description": "J.P. Morgan is a global leader in financial services, providing strategic advice and products to the world's most prominent corporations, governments, wealthy individuals and institutional investors. Our first-class business in a first-class way approach to serving clients drives everything we do. We strive to build trusted, long-term partnerships to help our clients achieve their business objectives.\n\nJ.P. Morgan Private Bank is a global wealth management leader that delivers the highest quality advice, service, capabilities and products to high-net-worth individuals and families around the world. We deliver highly customized and comprehensive solutions to help clients with the many complexities they face by leveraging the commercial and investment banking capabilities of the firm.\n\nPrivate Banking is involved with every facet of wealth management, including investments, wealth structuring, philanthropy, liquidity and credit management, and tax and estate planning. Our business model focuses on deep client relationships, an integrated team structure and a platform of depth and breadth.\n\nJob Responsibilities & Activities\n\nFocus on ultra-high-net-worth individuals and families, as well as institutions\nManage all aspects of client relationship, develop and maintain long-term relationships through strong personal networks and contacts\nBuild portfolio of clients using resources and expertise of JPMorgan's platforms, products, services, and networks\nActively involve in prospecting and acquiring new clients, cultivate prospect lists and actively convert them into clients and deepen relationships\nUnderstand each client's wealth objectives and investment requirements\nWork in close partnership with Investors in proposing, delivering, and executing solutions for clients; as well as in identifying new business opportunities\nMaintaining client relationships, answering clients' enquiries, day-to-day account operations\nUpdate clients regularly on markets, portfolio performance, investments opportunities, risks\nMay require regular travel into coverage regions to foster relationships\nWork with junior team members in preparing presentations and proposals, and send out various proposal items to clients on request\nKeep track of Clients, AUMs and Revenues using our internal systems; periodic calculation of account performance\nWork together with other teams in meeting all compliance, regulatory, risk management, operational, and due diligence requirements and compliance with internal policies\nOversee private client relationships by providing strategic advice based on each client's wealth objectives. Provide access to specialists and manage clients' investment portfolios\nResponsible for working with other team members on client sponsorship / Know Your Client\nSupervise, coach, and train junior staffs to maximize their individual contribution to the team as required\nQualifications And Essential Experiences\n\nUniversity degree holder and / or with 7+ years of professional experience in a similar capacity\nFluency in English required with Mandarin and / or Cantonese a definite plus\nStrong presentation skills, an excellent communicator with client facing experience a definite advantage\nStrong understanding of the needs and sensitivities of clients (private individuals and families)\nProven track record on investment sales and / or relationship management performance\nAble to work under minimal supervision; adaptable to work in demanding environment\nDetail-oriented and results-focused\nStrong knowledge of local regulatory policies and guidelines\nStrong knowledge of relevant financial markets and instruments\nAppropriate local regulatory qualification and licenses\nWe recognize that our people are our strength and the diverse talents they bring to our global workforce are directly linked to our success. We are an equal opportunity employer and place a high value on diversity and inclusion at our company. We do not discriminate on the basis of any protected attribute, including race, religion, color, national origin, gender, sexual orientation, gender identity, gender expression, age, marital or veteran status, pregnancy or disability, or any other basis protected under applicable law. In accordance with applicable law, we make reasonable accommodations for applicants' and employees' religious practices and beliefs, as well as any mental health or physical disability needs.\n\nInterested parties please click \u201cApply Now\u201d to apply job.\n\nAll applications applied through our system will be delivered directly to the advertiser and privacy of personal data of the applicant will be ensured with security.", "employment_types": ["Full Time"], "selling_points": ["Hair Salon Group", "Personal and business support to Group Founder", "5 Day Week"], "locations": ["North Point"], "categories": ["Management", "General Management"], "post_time": "2022-01-10T03:18:29Z", "salary": {"currency": null, "max": null, "min": null, "period": "monthly", "term": null}, "salary_visible": false, "title_keywords": ["personal assistant"], "responsibilities": ["operations", "quality", "maintain", "sensitivities", "due diligence", "maintaining", "compliance", "teams", "investment portfolios", "presentations", "develop", "banking", "internal systems", "management", "business opportunities", "executing", "tax", "guidelines", "policies", "planning"], "requirements": {"degrees": ["university degree"], "majors": [], "languages": ["cantonese", "english", "mandarin"], "language_level": ["fluency"], "hard_skills": ["make", "focus", "presentations", "plus"], "soft_skills": ["first-class", "responsible", "focused", "adaptable", "deep", "detail-oriented", "diverse", "presentation skills", "comprehensive", "focus", "communicator"], "languages_combined": [{"language": "cantonese", "language_level": []}, {"language": "english", "language_level": ["fluency"]}, {"language": "mandarin", "language_level": []}]}, "experience_required": {"duration": ["7+ years"], "field": []}}, {"job_id": "100003009040518", "location_code": "hk", "company": "Beans Group Limited", "job_title": "\u9910\u5ef3\u4e3b\u4efb Shop Supervisor", "description": "Work Location : Kwun Tong \u00a0/ Chek Lap Kok\n\nWe are looking for a candidate to fill the position of Operations Manager who can ensure operational effectiveness and efficiency (in service and productivity) by executing the FedEx way of operation that is reflective of the organizational culture.\n\nYou will plan, organize, direct and control all aspects of station operations and to provide superior service to our customers and maintain an efficient and cost-effective operation.\n\nRequirements\n\nBachelor\u2019s degree or equivalent\nFive (5) years business experience, preferably in transportation service or air cargo industry\nCustoms clearance, air cargo operations and management experience preferred\nValid driver\u2019s license and excellent driving record\u00a0preferred\nGood numerical reasoning ability\u00a0and solid process or customer experience improvement experience\nFluency in written and spoken English and Chinese is essential\n\nWhat can you expect as a FedEx team member?\n\nCareer Mobility and Development: When you join FedEx, you\u2019re joining a team with possibilities that literally span the world\u2014from opportunities for advancement and location transfer, to training and leadership programs.\n\nTotal Compensation and Benefits Package: We want to keep our employees for a long time, so we offer competitive benefits, opportunities for flexible work arrangements, and programs to support well-being.\n\nApplication\n\nIf you think this is a good fit for your knowledge, skills and aspiration, please send your\u00a0resume\u00a0including the information of\u00a0expected salary range\u00a0and\u00a0date of availability.\u00a0We look forward to having you be part of our Purple Promise, which is to make every FedEx experience outstanding.\n\nTo learn more about FedEx and other opportunities, please visit:\u00a0https://careers.fedex.com/fedex\n\nAll information provided by applicants will be treated in strict confidence and used only for recruitment purpose in accordance with the employer's personal data policies. A copy of Personal Information Collection Statement (PICS) will be provided upon request. Please write to the Human Resources Department. Applicants who are not invited to an interview within four weeks may consider their applications unsuccessful. All personal data of unsuccessful applicants will be destroyed after two years.\n\n\n", "employment_types": ["Full Time"], "selling_points": [], "locations": ["Tsuen Wan Area"], "categories": ["Hospitality / F & B", "Food & Beverage", "Management", "General Management", "Others"], "post_time": "2022-01-12T02:43:22Z", "salary": {"currency": null, "max": null, "min": null, "period": "monthly", "term": null}, "salary_visible": false, "title_keywords": ["\u9910\u5ef3\u4e3b\u4efb", "shop supervisor"], "responsibilities": [], "requirements": {"degrees": [], "majors": [], "languages": [], "language_level": [], "hard_skills": [], "soft_skills": [], "languages_combined": []}, "experience_required": {"duration": [], "field": []}}, {"job_id": "100003009034701", "location_code": "hk", "company": "Opera Hong Kong Limited", "job_title": "Officer (Education and Outreach)", "description": "J.P. Morgan is a global leader in financial services, providing strategic advice and products to the world's most prominent corporations, governments, wealthy individuals and institutional investors. Our first-class business in a first-class way approach to serving clients drives everything we do. We strive to build trusted, long-term partnerships to help our clients achieve their business objectives.\n\nJ.P. Morgan Private Bank is a global wealth management leader that delivers the highest quality advice, service, capabilities and products to individuals and families around the world. We deliver highly customized and comprehensive solutions to help clients with the many complexities they face by leveraging the commercial and investment banking capabilities of the firm.\n\nThe Single Coverage team is a key member of our wealth management front office team and works closely and directly with clients to meet their investment goals and objectives. The role is a hybrid between the current banker and the investment specialist role in the Private Bank in Asia.\n\nResponsibilities\n\nSupport and manage all aspects of client relationships across the team; develop and maintain long-term relationships through professional/personal networks and contacts\nOperate in both banker and investor capacity, and handle/coordinate with various teams on both overall account inquiries/maintenance as well as on investment-related aspects\nArticulate and deliver strategic messages to their portfolio, prepare presentations and proposals, and take both solicited and unsolicited orders in all asset classes\nUpdate clients regularly on markets, portfolio performance, investments opportunities, risks\nPartner with the client including (but not limited to) updating KYC information, client suitability profile, hosting client meetings, monitoring funds/asset transfer and handling client ad-hoc queries.\nCollaborate with the other integrated team members to provide a high quality of client service\nKeeping track of Clients, AUMs and Revenues using our internal systems; periodic calculation of account performance\nWork together with other teams in meeting all compliance, regulatory, risk management, operational, and due diligence requirements and compliance with internal policies\nQualifications\n\n3 years' + experience in the Financial Services and/or Banking industry. Client Service background is a plus.\nIdeally understand and have a working knowledge of the private banking key regulatory and control environments that are relevant to the team and be able to manage the accounts accordingly.\nProven client management skills and effective communication skills (oral and written) who can positively engage and influence clients as well as internal stakeholders.\nStrong organizational and prioritization skills.\nOperate with a high level of integrity and risk awareness.\nMust be a team player and able to work with different business functions across the bank.\nAs the role is an important contributor to the strategy of JPM, comfort and experience working with and reporting to senior management is required.\nAppropriate local regulatory qualification and licenses\nFluency in English mandatory, Cantonese and/or Mandarin strongly preferred\nWe recognize that our people are our strength and the diverse talents they bring to our global workforce are directly linked to our success. We are an equal opportunity employer and place a high value on diversity and inclusion at our company. We do not discriminate on the basis of any protected attribute, including race, religion, color, national origin, gender, sexual orientation, gender identity, gender expression, age, marital or veteran status, pregnancy or disability, or any other basis protected under applicable law. In accordance with applicable law, we make reasonable accommodations for applicants' and employees' religious practices and beliefs, as well as any mental health or physical disability needs.\n\nInterested parties please click \u201cApply Now\u201d to apply job.\n\nAll applications applied through our system will be delivered directly to the advertiser and privacy of personal data of the applicant will be ensured with security.", "employment_types": ["Full Time"], "selling_points": ["Children Chorus, Training, Opera, Concert", "Education, Administration, Music Centre, Singing", "Musical, Class managment"], "locations": ["Sai Ying Pun"], "categories": ["Education", "Others", "Others", "Entertainment - Artists / Singers / Musicians", "Management", "General Management"], "post_time": "2022-01-10T03:59:26Z", "salary": {"currency": null, "max": null, "min": null, "period": "monthly", "term": null}, "salary_visible": false, "title_keywords": ["officer"], "responsibilities": ["ad-hoc", "collaborate with", "quality", "communication", "maintain", "senior management", "due diligence", "control", "compliance", "teams", "presentations", "develop", "kyc", "banking", "internal systems", "reporting", "management", "monitoring", "coordinate with", "maintenance", "policies"], "requirements": {"degrees": [], "majors": [], "languages": ["cantonese", "english", "mandarin"], "language_level": ["fluency"], "hard_skills": ["plus", "maintenance", "presentations", "make", "kyc"], "soft_skills": ["communication skills", "oral", "first-class", "organizational", "integrity", "diverse", "comprehensive", "articulate", "team player"], "languages_combined": [{"language": "cantonese", "language_level": ["fluency"]}, {"language": "english", "language_level": ["fluency"]}, {"language": "mandarin", "language_level": ["fluency"]}]}, "experience_required": {"duration": ["3 years"], "field": ["banking industry", "management", "financial services"]}}, {"job_id": "100003009034019", "location_code": "hk", "company": "Travel Industry Authority", "job_title": "Investigator (Ref.:IV/20220110/JDB049)", "description": "ALL candidates\u00a0MUST\u00a0complete their application\u00a0directly\u00a0through the below link to receive updates on their application status:\nhttps://careers.lululemon.com/en_US/careers/JobDetail/Hong-Kong-Buying-Manager-Men-s-1-year-contract/16144\n\nWho we are\n\nlululemon is an innovative performance apparel company for yoga, running, training, and other athletic pursuits. Setting the bar in technical fabrics and functional design, we create transformational products and experiences that support people in moving, growing, connecting, and being well. We owe our success to our innovative product, emphasis on stores, commitment to our people, and the incredible connections we make in every community we're in. As a company, we focus on creating positive change to build a healthier, thriving future. In particular, that includes creating an equitable, inclusive and growth-focused environment for our people.\n\nA day in the life:\n\nReporting to the Director, Buying APAC, our Buying Manager is responsible for the successful execution of a seasonal assortment, that delivers our design vision in addition to sales, gross margin and inventory productivity goals across all channels. The Buying Manager leads their team in anticipating guest demand and ensuring the delivery of products that exceed expectations and guarantee growth. This person will act as the cross functional leader for all product categories in their department. This person will lead effective partnerships with Planning, In Season Country teams, Visual Merchandising, Digital, Brand and Community, and Retail Operations to ensure the design vision is delivered to our guests. The Buying Manager is responsible for the development of other members of the regional buying team and creating strong relationships with our North American counterparts.\n\nKey responsibilities:\n\nYou contribute to the financial success of the region by meeting and exceeding sales, gross margin and inventory productivity goals through all channels (stores, ecommerce, strategic sales, & showrooms), through the effective partnership with Planning and In Season Country teams\nYou are a \u201cmarket expert\u201d in your product department and region for all channels and can effectively communicate key data points, including merchandising strategies, athletic and fashion trends, pricing and competition that inform the global product strategy\nYou collaborate closely with global merchandising team to ensure that regional needs are incorporated into the line plan\nYou inform the Global Merchandising and Design Teams (at key internal milestones) with strategic insight and identify additional product assortment or business growth opportunities\nYou proactively gather, analyze and drive insight from local market knowledge and competitive landscape across all channels\nYou set seasonal merchandising strategies for the buying team, taking into account strategic initiatives, growth drivers and sales trends\nYou work closely with cross-functional teams to deliver and drive product strategies (short and long term)\nYou formulate and define local pricing strategies\nYou lead the in-season management of your product department, through sales analysis, flow management, product education, chase, cancellations, markdowns and exit\nYou train, support, and develop our Buying Team\n\nQualifications:\n\n10+ years of experience in a merchant/buyer role, with 5 years management experience\nBachelors degree in business, marketing or related field\nVertical retail experience required. Omni channel experience highly desirable\nMastery of retail mathematics and Open to Buy\nStrong analytical skills, including the ability to interpret multiple data points across numerous channels and market segments\nProven ability to work with and lead a cross functional team\nExcellent sense of style and color trends; athletically minded\nProven ability to manage multiple projects simultaneously; Self-starter approach to work, with an eagerness to consistently meet and exceed objectives and take on more responsibility\nExcellent communication skills - interpersonal, written and verbal\nEntrepreneurship \u2013 an ability to make decisions and take calculated risks\nFocus on creating an extraordinary guest experience, organizational and time management skills\nStrong knowledge of MS Office (Word, Excel and Outlook)\nWillingness to travel and work on the retail floor\n\nMust haves:\n\nAcknowledges the presence of choice in every moment and takes personal responsibility for their life.\nPossesses an entrepreneurial spirit and continuously innovates to achieve great results.\nCommunicates with honesty and kindness, and creates the space for others to do the same.\nLeads with courage, knowing the possibility of greatness is bigger than the fear of failure.\nFosters connection by putting people first and building trusting relationships.\nIntegrates fun and joy as a way of being and working, aka doesn\u2019t take themselves too seriously.", "employment_types": ["Full Time"], "selling_points": ["Independently conduct formal investigations", "Compile comprehensive written reports", "High level of professionalism & personal integrity"], "locations": ["Aberdeen"], "categories": ["Management", "General Management"], "post_time": "2022-01-10T02:41:36Z", "salary": {"currency": null, "max": null, "min": null, "period": "monthly", "term": null}, "salary_visible": false, "title_keywords": [], "responsibilities": [], "requirements": {"degrees": [], "majors": [], "languages": [], "language_level": [], "hard_skills": [], "soft_skills": [], "languages_combined": []}, "experience_required": {"duration": [], "field": []}}, {"job_id": "100003009033714", "location_code": "hk", "company": "Institute of ESG and Benchmark", "job_title": "Marketing, Membership & Development Officer", "description": "Job Duties\n\nLead and coach a team to deliver smooth daily operations to internal departments\nTake initiative to assess workflow and process to improve business operations efficiency\nEvaluate the efficiency of manpower to improve overall performance\nConduct data analysis report and provide business insight to Top Management for strategic planning\nPerform any ad-hoc duties as per assigned\nRequirements\u00a0\n\nDegree holder in any discipline\nMinimum 6 years relevant work experience with 2+ years in management role\nWorking experience in B2B market is preferable\nProficient on MS Excel, Word and CRM system operations is a MUST\nDetail minded, strong sense of responsibilities, self-motivated, willing to take up challenges and enjoy working as a team\nStrong leadership, detail-oriented, flexible and able to work independently\nGood command of written and spoken English and Chinese\nCandidate with more experience will be considered as Operations Support Manager", "employment_types": ["Full Time"], "selling_points": ["Bachelors degree, 2-3 years of experience", "Passionate in ESG, green finance, sustainability", "Salary 15-23K"], "locations": ["Causeway Bay"], "categories": ["Sales, CS & Business Devpt", "Business Development", "Management", "General Management", "Marketing / Public Relations", "Marketing - General / Support"], "post_time": "2022-01-10T01:51:38Z", "salary": {"currency": null, "max": null, "min": null, "period": "monthly", "term": null}, "salary_visible": false, "title_keywords": ["officer"], "responsibilities": ["management", "strategic planning", "operations", "evaluate", "data analysis", "daily operations", "ad-hoc duties", "report"], "requirements": {"degrees": ["degree holder"], "majors": [], "languages": ["english", "chinese"], "language_level": ["good command"], "hard_skills": ["ms excel", "word"], "soft_skills": ["flexible", "self-motivated", "work independently", "enjoy working", "detail-oriented", "leadership", "sense of responsibilities"], "languages_combined": [{"language": "english", "language_level": ["good command"]}, {"language": "chinese", "language_level": ["good command"]}]}, "experience_required": {"duration": ["2+ years", "minimum 6 years"], "field": ["management"]}}, {"job_id": "100003009043298", "location_code": "hk", "company": "Sun Life Hong Kong Limited", "job_title": "MPF CONSULTANT (\u5f37\u7a4d\u91d1\u884c\u653f\u4e3b\u4efb)", "description": "\uff08\u4e00\uff09\u8077\u8cac\uff1a\n\n\u00a0\u958b\u62d3\u53ca\u767c\u5c55\u570b\u5167\u5ba2\u6236\u4ee5\u53ca\u9999\u6e2f\u5ba2\u6236\uff0c\u70ba\u516c\u53f8\u5c0b\u627e\u5728\u4e2d\u570b\u5927\u9678\u5730\u5340\u7684\u9805\u76ee\u6295\u8cc7\u6a5f\u6703\n\u00a0\u9805\u76ee\u6295\u8cc7\u7ba1\u7406\uff0c\u5305\u62ec\u505a\u9805\u76ee\u53ef\u884c\u6027\u5206\u6790\uff0c\u6295\u8cc7\u6536\u76ca\u5206\u6790\n\u00a0\u7ba1\u7406\u9805\u76ee\u6295\u8cc7\u5718\u968a\n\u00a0\u5c0d\u5df2\u6295\u8cc7\u9805\u76ee\u505a\u71df\u904b\u7ba1\u7406\n\n\uff08\u4e8c\uff09\u8981\u6c42\uff1a\n\n\u00a0\u6709\u4e00\u5b9a\u4e2d\u570b\u5927\u9678\u5730\u5340\u9805\u76ee\u6295\u8cc7\u7ba1\u7406\u7d93\u9a57\n\u00a0\u5584\u65bc\u8655\u7406\u8207\u5ba2\u6236\u7684\u95dc\u4fc2\n\u00a0\u57f7\u884c\u80fd\u529b\u5f37\uff0c\u6709\u5718\u968a\u7ba1\u7406\u7d93\u9a57\n\u00a0\u666e\u901a\u8a71\u6d41\u5229\n\u00a0\u672c\u79d1\u4ee5\u4e0a\u5b78\u6b77\n\n\u5de5\u4f5c\u5730\u70b9\uff1a\u9999\u6e2f\u3001\u5927\u9646", "employment_types": ["Full Time"], "selling_points": ["$14,000-$25,000", "Flexible working hours", "Fresh Graduate will be considered"], "locations": ["Hung Hom"], "categories": ["Banking / Finance", "Financial Services", "Management", "General Management", "Marketing / Public Relations", "Management"], "post_time": "2022-01-12T10:34:53Z", "salary": {"currency": null, "max": null, "min": null, "period": "monthly", "term": null}, "salary_visible": false, "title_keywords": ["mpf consultant"], "responsibilities": [], "requirements": {"degrees": [], "majors": [], "languages": [], "language_level": [], "hard_skills": [], "soft_skills": [], "languages_combined": []}, "experience_required": {"duration": [], "field": []}}, {"job_id": "100003009039262", "location_code": "hk", "company": "STA Pacific Limited", "job_title": "Store Planning Architect / Interior Architect (UK Jewelry Brand) - 45 - 50K", "description": "We\u00a0are young, energetic and enthusiastic team, which seek breakthrough. Here we aim to enhance personal development and career achievement in balance, provide you with ongoing guidance that you need to be proactive, and take the steps needed to reach you personal goal.\n\nJob Responsibilities\n\nPromote MPF, ORSO and group benefits, like Group Medical and Office Insurance\nMaintain client base Update and Manage client relationship with ongoing service in MPF consolidation\nMaximize client satisfaction through customer service, providing information about products and services\nManage corporate business accounts and ad hoc business programs and activities\n\nJob Requirements\n\nDiploma or above in all discipline\nExperience in\u00a0customer service or sales field\nProactive with positive mindset, excellent interpersonal &\u00a0communication skills\nAble to work independently\nFluent in Cantonese, moderate English\n\nBenefits\n\nSalary: $14,000 to 25,000\nFast track promotion to management level\nIncentive, commission bonus, travel incentives\nMedical benefits and training allowances\nFlexible working hours\n\nWorking Location\n\nWhampoa\n\n**Personal date provided by applicants will be treated in strict confidence and used for recruitment purposes only**\n\nIf you have any further enquiries, please press\u00a0APPLY NOW\u00a0to contact us with your CV. We will get back to you shortly.\u00a0", "employment_types": ["Full Time", "Permanent"], "selling_points": ["7+ years interior design & PM exp.", "Tender Call In & Selection Decision Making", "Manage the contractors for various projects"], "locations": ["Central & Western Area"], "categories": ["Building & Construction", "Architectural Services", "Design", "Interior", "Management", "General Management"], "post_time": "2022-01-11T09:13:41Z", "salary": {"currency": null, "max": null, "min": null, "period": "monthly", "term": null}, "salary_visible": false, "title_keywords": [], "responsibilities": [], "requirements": {"degrees": [], "majors": [], "languages": [], "language_level": [], "hard_skills": [], "soft_skills": [], "languages_combined": []}, "experience_required": {"duration": [], "field": []}}, {"job_id": "100003009037100", "location_code": "hk", "company": "EC Healthcare", "job_title": "Centre Manager/ Assistant Centre Manager (Diagnostic and Imaging Centre)", "description": "Responsibilities\n\nThis key duties of this role included Concept & Technical Drawings, Pre-Construction Organization and construction management\nCoordinate and work with the store planning team and contractors to complete the drawing of the new and renovating stores to cope with the worldwide standard\nResponsible for the full set of the technical drawings & specifications\nParticipated into the whole process of call-in tenders starting from providing accurate tender drawings, sourcing & screening contractors and selection\nProject and contractors' management for the store planning and renovation projects worldwide\nRequirements\n\nBachelor degree in Interior Design / Construction / Related\u00a0\n7+ years in-house / contractors experience for interior design and project management\nWith management experience in retail / luxury retail projects is a MUST\nGood communication in English\nProficient in AutoCAD\nWorking Location: Central\nMon - Fri, 9:30am - 6:30pm\n\nInterested parties, please send your job application with your expected salary and notice period by clicking \"Apply Now\"", "employment_types": ["Full Time"], "selling_points": ["Monitor daily operation of clinic operations", "Review existing policies and procedures", "Participate in clinic business development plans"], "locations": ["Tai Koo"], "categories": ["Sales, CS & Business Devpt", "Business Development", "Management", "General Management", "Medical Services", "Others"], "post_time": "2022-01-11T01:42:08Z", "salary": {"currency": null, "max": null, "min": null, "period": "monthly", "term": null}, "salary_visible": false, "title_keywords": ["assistant centre manager", "centre manager"], "responsibilities": ["management", "construction management", "renovation", "drawings", "coordinate", "specifications", "technical drawings", "tender", "store planning"], "requirements": {"degrees": ["degree", "bachelor"], "majors": ["design"], "languages": ["english"], "language_level": ["good"], "hard_skills": ["project management", "autocad"], "soft_skills": ["communication", "project management"], "languages_combined": [{"language": "english", "language_level": ["good"]}]}, "experience_required": {"duration": ["7+ years"], "field": ["management", "design", "project management", "luxury retail", "retail"]}}, {"job_id": "100003009039509", "location_code": "hk", "company": "Hang Yick Properties Management Limited", "job_title": "Property Manager / Assistant Property Manager", "description": "Job Responsibilities\n\nLead and coach a frontline team to ensure the delivery of standardized workflow with quality customer service and clinical care;\nMaintain a good rapport and professional relationship with Drs and team members\nMonitor daily operation to maintain a high efficiency of clinic operations\nReview existing policies and procedures to to ensure clinic compliance\nHandle feedbacks from customers and external Drs\u00a0\nParticipate in clinic business development plans for execution\nHandle any ad hoc assignments and special projects as assigned by\u00a0management.\n\nRequirements\n\nTraining received from Pharmacy, Nursing or healthcare related disciplines;\nRegistered Nurse will be a definite advantage;\n3+ years relevant experience in clinic operations and centre administration\nWell-organized, customer-oriented and good communication skills\nGood command of written and spoken English and Chinese (Cantonese & Mandarin);\nImmediate available will be considered in priority.", "employment_types": ["Full Time", "Permanent"], "selling_points": ["Member of Henderson Land Group", "Work from Monday to Friday", "Stable subordinates in Management Office"], "locations": ["Not Specified"], "categories": ["Management", "General Management", "Property / Real Estate", "Property Management", "Others"], "post_time": "2022-01-11T09:57:32Z", "salary": {"currency": null, "max": null, "min": null, "period": "monthly", "term": null}, "salary_visible": false, "title_keywords": ["assistant property manager", "property manager"], "responsibilities": ["management", "operations", "policies", "review", "monitor", "quality", "daily operation", "procedures", "compliance", "maintain", "customer service", "ad hoc assignments", "plans"], "requirements": {"degrees": [], "majors": [], "languages": ["cantonese", "english", "chinese", "mandarin"], "language_level": ["good command"], "hard_skills": [], "soft_skills": ["communication skills", "customer-oriented", "well-organized"], "languages_combined": [{"language": "cantonese", "language_level": ["good command"]}, {"language": "english", "language_level": ["good command"]}, {"language": "chinese", "language_level": ["good command"]}, {"language": "mandarin", "language_level": ["good command"]}]}, "experience_required": {"duration": ["3+ years"], "field": ["centre administration", "clinic operations", "relevant experience"]}}, {"job_id": "100003009037091", "location_code": "hk", "company": "", "job_title": "Personal Assistant", "description": "Responsible for all rounded supervision on property management, facility management, manpower development and communication with members of IO/OC.\nJob Requirement:\nDegree or Diploma holder of Property Management or related discipline;\nMust be a RPHM, member of CIH or HKIH;\nHolder of\u00a0PMP (Tier 1) licence;\n7 years of experience in property management;\nPreferably with experience in management portfolio of residential and commercial buildings;\nWell versed in Deed of Mutual Covenant and Building Management Ordinance;\nAn excellent team player with strong leadership and interpersonal\u00a0skills.\n\nRemuneration will be in commensurate with qualifications and experience.\u00a0 Fringe benefits include birthday leave, marriage leave, full attendance leave, training allowance, newborn baby allowance, medical allowance and other special leave.\u00a0 Please promptly send full resume\u00a0with expected salary\u00a0to Human Resources Department at 21/F Well Tech Centre,9 Pat Tat Street, San Po Kong, Kowloon OR by fax 3011-5653.\n\nAll information received will be kept in the strictest confidentiality and only for employment-related purposes within our affiliates.\n\nYou are most welcomed to visit our website\u00a0www.hy.com.hk.", "employment_types": ["Full Time", "Part Time"], "selling_points": [], "locations": ["Ngau Tau Kok"], "categories": ["Admin & HR", "Clerical / Admin Staff", "Personal / Executive Assistant", "Management", "General Management"], "post_time": "2022-01-11T01:40:39Z", "salary": {"currency": null, "max": null, "min": null, "period": "monthly", "term": null}, "salary_visible": false, "title_keywords": ["personal assistant"], "responsibilities": ["attendance", "management", "website", "communication", "building management"], "requirements": {"degrees": ["diploma holder", "degree"], "majors": [], "languages": [], "language_level": [], "hard_skills": ["hy", "pmp", "io"], "soft_skills": ["responsible", "communication", "interpersonal skills", "team player", "leadership"], "languages_combined": []}, "experience_required": {"duration": ["7 years"], "field": ["commercial", "management"]}}, {"job_id": "100003009025329", "location_code": "hk", "company": "West Kowloon Cultural District Authority", "job_title": "Assistant Manager, Park and Public Open Space Operations (Ref: R2877)", "description": "You will be responsible for:\n\n\nassisting with managing and monitoring the OPEX for park operations, including expenses for the park ambassadors team, autonomous vehicle etc;\nproviding input to regular financial reporting;\npreparing documents in support of the team\u2019s procurement and payment needs in compliance with the related guidelines of the Authority;\ndrafting and implementing open space related policies, guidelines, procedures to ensure effective, smooth and efficient performance of public open spaces across the district;\nhandling the day-to-day management of the Park and Public Open Space;\nbuilding good relationship with internal and external key stakeholders including the general public, community groups, NGOs, event organisers and relevant government departments, etc;\nensuring the required performance level of service providers is achieved;\nworking closely with the Facilities Management Team and Landscaping Team to ensure we have the right facilities to enhance the visitor experience in the Park, as well as creating an attractive working environment for our staff;\nassisting in the implementation of branding initiatives;\nassisting in the development and implementation of education and community programmes, including school activities; and\nmonitoring customer feedback and identify areas of improvements with an overall objective to enhance visitors experience.\n\nYou should:\n\n\npossess a recognised university degree in recreation management / facilities management or equivalent;\nhave 5 years of experience in the operation and management park or other form of open space / visitor destinations / event management, preferably in sizeable organisations or public sector;\ndemonstrate good teamwork, interpersonal and communication skills with the ability to effectively interact with all levels of internal and external stakeholders;\nbe pleasant, mature, committed, highly organized, attention to details with good analytical skills, and able to work independently and under pressure;\nability to work under pressure, and a willingness to take on new challenges and to work over the weekend and/or public holiday to support park operations if required;\npossess strong communication and presentation skills and the ability to effectively interact with internal and external personnel at all levels; and\nbe proficient in written and spoken English and Chinese.\nFor interested parties, please submit your application with detailed CV on or before 20 January 2022. Applicants are encouraged to submit their applications as soon as possible. The review of applications will continue until post is filled.\n\n\n\nData collected will only be used for job application processing. Your data may be accessed by our appointed recruitment consultants who have agreed to keep confidence of all personal data in not less than the standards applicable to us. Applicants not being invited for interview within 4 weeks from the submission date may assume their applications unsuccessful.\n\nAll related information will be kept up to 24 months and all personal data will be destroyed afterwards.\n\nFor more information\nhttp://www.westkowloon.hk or contact\nMs. Amanda Tai at 2200 0116", "employment_types": ["Full Time", "Permanent"], "selling_points": ["Manage and monitor the park operation", "Implement branding initiatives", "Have experience in open space operation"], "locations": ["Tsim Sha Tsui"], "categories": ["Management", "General Management", "Marketing / Public Relations", "Public Relations - Event Management", "Property / Real Estate", "Property Management"], "post_time": "2022-01-06T10:03:36Z", "salary": {"currency": null, "max": null, "min": null, "period": null, "term": null}, "salary_visible": false, "title_keywords": ["operations", "assistant manager,"], "responsibilities": ["management team", "management", "guidelines", "operations", "policies", "monitoring", "expenses", "compliance", "procedures", "implementation", "opex", "day-to-day management", "payment", "good relationship", "communication", "financial reporting", "landscaping", "work under pressure"], "requirements": {"degrees": ["university degree"], "majors": [], "languages": ["english", "chinese"], "language_level": ["proficient"], "hard_skills": ["facilities management", "analytical skills"], "soft_skills": ["efficient", "communication skills", "organized", "work independently", "under pressure", "responsible", "teamwork", "mature", "pleasant", "analytical skills", "committed", "autonomous", "communication", "presentation skills", "attention to details", "smooth", "interpersonal", "work under pressure"], "languages_combined": [{"language": "english", "language_level": ["proficient"]}, {"language": "chinese", "language_level": ["proficient"]}]}, "experience_required": {"duration": ["5 years"], "field": ["management", "operation", "team"]}}, {"job_id": "100003009036690", "location_code": "hk", "company": "IT Consulting Solutions Limited", "job_title": "Technical Project Manager / Junior Project Manager (Multiple opening)", "description": "Key Responsibilities\n\nManage small to medium scale technology projects or multiple smaller scale projects through all stages of the life cycle, ensuring on-time, within budget quality delivery\nCoordinates for Data Center and Office power down and electrical/UPS maintenance events across APAC throughout the year from Technology Infrastructure perspective \u2013 coordinates with multiple teams to optimize the run-down plan and manages the execution work mainly on weekends in varied APAC time-zones.\nInitiates and maintains reporting relationships with project stakeholders including team members, peers, managers, customers, vendors, and other affected departments to coordinate efforts across multiple business units and ensure continuous efficient management of projects; gathers input and feedback\nCreates, Manages and regularly project status reports, project schedule / work break down structure, tasks and Milestones delivery list\nHost regular project team meetings to review and execute plans\nIdentifies and documents project risk and issues and creates mitigation plans using comprehensive mitigation assessment and planning techniques\nCollaborates and communicates with other project managers and leaders to coordinate cross-project initiatives and activities\n\nKey Requirements\n\nExcellent organizational and communication skills\nDetail oriented\nExperience managing budgets and forecasting\nTeam building - Ability to build a project team and keep the team focused and on task\nTechnical background in infrastructure project management or project management.\nProficiency in tools such as - Microsoft Project / Project Plan creation and management, Microsoft Word, Excel and PowerPoint\nDemonstrated ability to work as part of a team\nAbility to manage and communicate effectively with stakeholders\nPMP or other Project Management certification (e.g. Prince2)", "employment_types": ["Full Time", "Permanent", "Contract"], "selling_points": ["Investment Bank / Law Firm opening", "Senior / Junior openings", "International working environment"], "locations": ["Central"], "categories": ["Banking / Finance", "Others", "Management", "General Management", "Information Technology (IT)", "IT Project Management / Team Lead"], "post_time": "2022-01-10T12:39:18Z", "salary": {"currency": null, "max": null, "min": null, "period": "monthly", "term": null}, "salary_visible": false, "title_keywords": ["technical project manager", "project manager", "junior"], "responsibilities": ["reporting", "management", "maintenance", "data", "infrastructure", "budget", "quality", "teams", "review", "coordinate", "reports", "schedule", "plan", "plans", "planning"], "requirements": {"degrees": [], "majors": [], "languages": [], "language_level": [], "hard_skills": ["excel", "microsoft project", "microsoft word", "powerpoint", "project management", "pmp"], "soft_skills": ["communication skills", "focused", "organizational", "detail oriented", "project management"], "languages_combined": []}, "experience_required": {"duration": [], "field": []}}, {"job_id": "100003009037074", "location_code": "hk", "company": "Hong Kong Standards & Testing Centre", "job_title": "German Speaking - Business Development Manager (STC\u2019s Germany Frontenhausen Facility)", "description": "Business Development Manager\u00a0(STC\u2019s \u00a0Germany Frontenhausen Facility)\n\nAn international consumer products testing, certification and inspection company, STC (www.stc.group), with headquarters in Asia, is looking for high caliber candidates to fill the position of Business Development Manager.\u00a0 The successful candidate is expected to be posted at STC\u2019s Frontenhausen facility (near Munich).\n\nResponsibilities\n\nDevelop new customers in consumer products testing compliance and regulatory field.\u00a0\nWorking with retailers, buyers which in turn to trigger their assigned factories in China or Asia to do product testing at STC\u2019s laboratories.\nPromote and enhance STC\u2019s image in Germany.\nWork closely with the global sales and key account team to develop new customers.\nPlan, organize and direct business activities to drive and achieve set targets.\nOrganize and take part in local & international trade shows.\n\n\u00a0Qualifications Required\n\n\nAcademic background in Marketing, Science or Engineering related disciplines.\nUnderstanding of operation and business principles.\nNot less than 5 years of relevant working experience.\nExperience and channels in developing new sales.\nHands-on connection with retailers and buyers sourcing in Asia.\nUnderstanding of international consumer products testing regulatory standards and compliance.\nSeasoned supervision skill.\nCandidates with financial target commitment.\nFluent in spoken and written German and English.\nRetired candidates with the right experience are also welcome.\u00a0", "employment_types": ["Full Time", "Permanent"], "selling_points": ["Product Testing & Certification", "Work exp in Sales & Marketing,Business Development", "Work at STC\u2019s Germany Frontenhausen facility"], "locations": ["Overseas"], "categories": ["Sales, CS & Business Devpt", "Customer Service - Manager", "Management", "General Management", "Sciences, Lab, R&D", "Research & Development (R&D)"], "post_time": "2022-01-11T01:38:00Z", "salary": {"currency": null, "max": null, "min": null, "period": "monthly", "term": null}, "salary_visible": false, "title_keywords": ["business development manager"], "responsibilities": ["compliance", "developing", "develop", "inspection", "testing", "plan", "business activities"], "requirements": {"degrees": [], "majors": [], "languages": ["german", "english"], "language_level": ["fluent"], "hard_skills": [], "soft_skills": ["hands-on"], "languages_combined": [{"language": "german", "language_level": ["fluent"]}, {"language": "english", "language_level": ["fluent"]}]}, "experience_required": {"duration": ["5 years"], "field": ["relevant working experience", "developing"]}}, {"job_id": "100003009039671", "location_code": "hk", "company": "Good Wish", "job_title": "Business Development Trainee (15K above) (Part Time/ Full Time)", "description": "This is a Golden opportunity to experience the Asset and Risk Management Industry. We believe in providing a high quality training of financial services that fosters continuous professional development to high new worth individuals and proven to significantly enhance client\u2019s portfolio.\n\n\u00a0Candidates who are looking for an opportunity where provide professional training support to experience the business environment and career development are welcome to join our program:\n\n\u00a0Job Duties:\n\nFollow up with potential clients\nManage and update clients\u00a0database\nIdentifying and developing client business relationships\nDevelop and maintain a strong working relationship with clients\nColdcall to constantly identify and initiate potential key accounts\nOrganize and participate in sales visits with potential and existing clients\nAny other administrative duties as assigned by immediate supervisor \u00a0\n\nRequirements:\n\nPassion to learn and become one of the successful leaders in the industry\nDegree Holder or above in any disciplines, Degree in Finance, Economics, Financial Engineering would be an advantage.\nProficiency in both written and spoken English and Cantonese, proficiency in Mandarin would be an advantage.\nFresh graduates with good interpersonal skills and great eagerness to learn and explore in order to become one of the successful leaders in the industry are welcome.\n\nDO NOT GIVE YOURSELF ANY LIMITATION, PASSION IS ALWAYS YOUR WINNING KEY.\n\nOur offer:\n\nPleasure working environment and warm spirit and atmosphere (incentive trips and oversea conferences)\nProfessional training program with successful leaders in the finance industry\u00a0\n5-day work week with flexible hours\nExcellent opportunities to corporate with different finance firms in the industry\nSFC, CFA, CPA, CFP, CIWM examinations resources and support with individual sponsorship provided, we feel like and we encourage our employees to gain these professional certification.\nPerformance bonus\u00a0\nMedical scheme & study allowance", "employment_types": ["Full Time", "Part Time", "Permanent", "Freelance"], "selling_points": ["5 days work", "Fresh graduates will be considered", "15K or above"], "locations": ["Not Specified"], "categories": ["Banking / Finance", "Financial Services", "Management", "General Management", "Sales, CS & Business Devpt", "Sales - Sales Management"], "post_time": "2022-01-11T10:25:59Z", "salary": {"currency": null, "max": null, "min": null, "period": "monthly", "term": null}, "salary_visible": false, "title_keywords": ["trainee"], "responsibilities": ["developing", "develop", "maintain", "administrative duties", "database"], "requirements": {"degrees": ["degree", "degree holder"], "majors": ["finance", "economics", "any disciplines", "engineering"], "languages": ["cantonese", "english", "mandarin"], "language_level": ["advantage", "proficiency"], "hard_skills": ["cfa", "scheme", "cpa"], "soft_skills": ["flexible", "interpersonal skills"], "languages_combined": [{"language": "cantonese", "language_level": ["advantage"]}, {"language": "english", "language_level": ["advantage"]}, {"language": "mandarin", "language_level": ["proficiency", "advantage"]}]}, "experience_required": {"duration": [], "field": []}}, {"job_id": "100003009043405", "location_code": "hk", "company": "", "job_title": "\u53ef\u6263\u7a05\u5f37\u7a4d\u91d1\u8a08\u5283\u5c08\u54e1 MPF Service Manager", "description": "Manulife is No.\u00a01\u00a0in MPF Market Share as well as the Best Service Provider in Hong Kong.\n\n\u00a0A tailor-made program is offered to high calibers like you to join our profession.\u00a0\n\nOffer:\n\nSpecial package tailor-made for right person according to qualification and experience\nFast Track promotion program to Management Level within 6 months\nProfessional and ongoing training programs to enhance products and marketing knowledge\nHigh Monthly and Annual Performance bonus\nMedical and Life Insurance, low interest mortgage scheme\nFree overseas trip recognition\u00a0\n\nRequirements:\n\nHong Kong Resident\nDegree Holder\nFluency in Cantonese, proficiency in Putonghua is a plus\nMinimum 3 years of working experience\nAggressive person, endeavor to start up own business with strong commitment to succeed\n\n\nOnly short-listed candidates will be contacted.\u00a0 All applicant information is treated confidentially; personal data collection is only for recruitment selection purposes.", "employment_types": ["Full Time", "Permanent"], "selling_points": ["Attractive Compensation & free overseas trip", "Fast Track Promotion to Management Level", "5-day work, bank holidays, 20-day Annual Leave"], "locations": ["Kwun Tong"], "categories": ["Management", "General Management", "Beauty Care / Health", "Beautician", "Hospitality / F & B", "Hospitality / Hotel Services"], "post_time": "2022-01-12T23:26:20Z", "salary": {"currency": "HKD", "max": 29999, "min": 20000, "period": "monthly", "term": null}, "salary_visible": true, "title_keywords": ["manager"], "responsibilities": ["management", "mpf", "recruitment", "personal data", "insurance"], "requirements": {"degrees": ["degree holder"], "majors": [], "languages": ["cantonese", "putonghua"], "language_level": ["fluency", "proficiency"], "hard_skills": ["no", "scheme", "plus"], "soft_skills": [], "languages_combined": [{"language": "cantonese", "language_level": ["fluency", "proficiency"]}, {"language": "putonghua", "language_level": ["proficiency"]}]}, "experience_required": {"duration": ["minimum 3 years"], "field": []}}, {"job_id": "100003009032994", "location_code": "hk", "company": "Goma,Inc", "job_title": "Business Expansion Manager", "description": "Goma Tei ramen is a chain restaurant based in Honolulu, Hawaii. We proud to operate 16 years of business. Our food concept is to bring 21st century technologies to produce traditional style cooking method. We are expanding our business and setting up the platform for franchise in the near future.\n\u00a0H1B Visa petition opportunity available. Franchise opportunities available in the future. Salary $50,000 USD to $60,000 USD annually depend on experience. Business or Food Science degree is required. Experience is required in food business. Medical insurance.\n\nResponsibilities\n\nHire, train, and supervise restaurant employees\nTrack stock levels of food, supplies, and equipment, forecast needs, and oversee ordering as necessary\nTake ownership of budgets and cost control methods to minimize expenses\nAddress customer needs, comments, and complaints\nAdhere to and enforce employee compliance with health, safety, and sanitation standards\nProcess payroll and maintain all relevant records\nEnsure all employees are working within outlined operating standards\nReport on financial performance, inventory, and personnel", "employment_types": ["Full Time"], "selling_points": [], "locations": ["Overseas"], "categories": ["Management", "General Management"], "post_time": "2022-01-09T16:25:50Z", "salary": {"currency": "HKD", "max": 44999, "min": 30000, "period": "monthly", "term": null}, "salary_visible": true, "title_keywords": ["manager"], "responsibilities": ["budgets", "inventory", "expenses", "comments", "compliance", "maintain", "cost control", "forecast", "payroll", "insurance", "report"], "requirements": {"degrees": ["degree"], "majors": ["business", "food science"], "languages": [], "language_level": [], "hard_skills": [], "soft_skills": [], "languages_combined": []}, "experience_required": {"duration": [], "field": ["food", "business"]}}, {"job_id": "100003009025895", "location_code": "hk", "company": "Toll Global Forwarding (Hong Kong) Limited", "job_title": "Business Development Manager", "description": "Achieving sales targets/ priorities \u00a0through promoting Toll products and services to existing and potential customers, and drive quality services throughout the process; keep continuous sales growth;\nCollaborate with manager to ensure alignment with strategies in forecasting, business planning and pipeline development;\nImplement Sales & Marketing Strategy in line with TGF to optimize the company\u2019s capabilities & resources by attracting / identifying new opportunities and retaining current customers;\nUpsell additional services to the existing customer base in order to increase sales volumes and revenues;\nContinually explore qualified new customers, prepare and follow-up quotations and generate sales leads; Work with network to identify import and export opportunities;\nMonitor and respond to concerned parties to ensure accurate, timely and positive customer experience delivery;\nMaintain, monitor and ensure all sales activities are complied with Toll compliances, relevant polices and governances;\nPerform all aspects of the sales process and incorporate daily use in sales management system platform to document sales activity and relevant customer business details;\nSupport to review contracts, and ensure the terms & processes are complied with company compliances & relevant policies;\nSupport to perform market research and analysis on rate trends and understanding rate trends / support to work on pricing strategies internally; maintain right pricing strategies to improve winning ratio;\nCooperate with Credit Department to collect / settle outstanding overdue payments from customers;\nAttend regular sales meeting to understand market intelligences, Toll products & sales programs, and always keep updated readiness for sales developments;\u00a0 \u00a0\nCustomer visits with occasional travel to China (mainly South China);\nSupport to identify & drive safety measures in relationship to clients\u2019 shipments / cargoes packaging\nMinimum 5 years relevant working experience in sales or business development in logistics / freight forwarding industries.\nStrategic thinking and strong networking abilities;\nAnalytical skills and sensible to market trends;\nExperience in using CRM system;\nWith Global freight forwarding experiences;\nProficient in Microsoft Office (Word, Excel, PowerPoint and Outlook).", "employment_types": ["Full Time"], "selling_points": ["Sales Management System;", "Commercially focused & sales orientated;", "Knowledge of global freight forwarding operation"], "locations": ["Kwai Fong"], "categories": ["Sales, CS & Business Devpt", "Business Development", "Management", "General Management"], "post_time": "2022-01-06T06:42:55Z", "salary": {"currency": null, "max": null, "min": null, "period": "monthly", "term": null}, "salary_visible": false, "title_keywords": ["business development manager"], "responsibilities": ["collaborate with", "sales activities", "contracts", "policies", "review", "quality", "monitor", "market research", "analysis", "maintain", "generate sales leads", "payments", "logistics", "sales management", "forecasting", "cooperate with", "planning"], "requirements": {"degrees": [], "majors": [], "languages": [], "language_level": [], "hard_skills": ["excel", "microsoft office", "analysis", "word", "import and export", "analytical skills", "powerpoint", "outlook"], "soft_skills": ["strategic thinking", "timely", "analytical skills", "accurate", "positive"], "languages_combined": []}, "experience_required": {"duration": ["minimum 5 years"], "field": ["business development", "logistics", "relevant working experience"]}}, {"job_id": "100003009027186", "location_code": "hk", "company": "", "job_title": "BUSINESS DEVELOPMENT MANAGER", "description": "YOUR ROLE IS:\n\n\nMonitor team sales growth, identify suitable recruits and provide updated training\ncapture financial needs with prompt follow up on analytically driven leads\nengage end to end customer service including needs identification, solution recommendations, application fulfillment, and follows up\nmanage individual insurance portfolio to ensure the highest rate of customer satisfaction and persistency\nestablish effective working relationships with other teams in order to ensure a consistent approach and application of outstanding service standard\nbuild and maintain a positive team culture, through ensuring quality business referrals and referral skills among team members, and contributing to product knowledge and skills sharing\nmaintain high level of compliance guidelines and procedures\nWe are seeking for:\n\n\nUniversity degree holder and have a minimum of 8 years working experience, preferably in sales and finance, less experienced will be considered as Financial Planning officer\nHKID holder\nBeing ambitious in developing your own career with independence\nYou will get:\n\n\nExcellent and fast track career path\nComprehensive and professional on job training\nAttractive package with month allowance, performance bonus and annual bonus\nLuxurious annual overseas conferences\nGroup life and group medical\nHousing subsidy and preferred mortgage rate\nInterest parties please call Carol Hui at 93777854 for confidential conversation.", "employment_types": ["Full Time"], "selling_points": ["Fast Track to Build Own Team", "Desire to Build Solid Sustainable Career", "Ambitious Talents"], "locations": ["Ngau Tau Kok"], "categories": ["Sales, CS & Business Devpt", "Business Development", "Management", "General Management", "Account Servicing"], "post_time": "2022-01-06T09:15:34Z", "salary": {"currency": null, "max": null, "min": null, "period": "monthly", "term": null}, "salary_visible": false, "title_keywords": ["business development manager"], "responsibilities": ["service standard", "guidelines", "fulfillment", "compliance", "monitor", "teams", "quality", "procedures", "developing", "conferences", "customer service", "maintain", "working relationships", "insurance", "planning"], "requirements": {"degrees": ["university degree"], "majors": ["finance"], "languages": [], "language_level": [], "hard_skills": [], "soft_skills": ["prompt", "comprehensive", "customer service", "driven", "positive"], "languages_combined": []}, "experience_required": {"duration": ["minimum of 8 years"], "field": ["finance", "planning", "financial"]}}, {"job_id": "100003009033205", "location_code": "hk", "company": "Circle Recruitment Limited", "job_title": "Senior Fundraising Manager - Hong Kong", "description": "Our Client, a non-profit making organisation of a school foundation in Hong Kong, \u00a0is currently looking for an agile, well-organized, sociable and well-connected Senior Fundraising Manager with entrepreneurship mindset to join their team in Hong Kong.\n\nResponsibilities:\n\nReports to the Board of Directors/ Senior Management Team to manage a team\u00a0\nOrganise fundraising events on a regular basis to create, promote and implement fundraising initiatives\nReaching potential donors, and writing funding proposals to potential donors/ sponsors\nWork closely with internal parties on communication materials & media releases, etc.\nAble to lead a team for events and to engage effective fundraising communications\nLead and develop traditional (meetings and events)\u00a0and digital campaigns as well as to implement social media strategies (e.g. Facebook, Twitter, LinkedIn, etc.) to enhance brand awareness for the organisation\nRequirements:\u00a0\n\nBachelor\u2019s degree in Marketing, Communications or related disciplines\nMin. 10 years of working experience with strong leadership skills in the relevant field with both local and international explosure is preferred\nFamiliar with fundraising financial model and reporting formats\nStrong communication skills, especially in oral and written skills in English and Chinese (Cantonese and Mandarin)\nSome social media skills on various platforms (e.g. Facebook, Twitter, LinkedIn, etc.)\n\nAble to perform under pressure, possessing exceptional organizational and presentation skills\nComputer proficiency in MS Office\n\nTo apply for this position, please submit your updated CV in Word format to us by email.\n\n\n\nOnly qualified candidates will be considered for the position. \u00a0 \u00a0\n\n\n\nData received by Circle Recruitment Limited relating to job applications will be kept confidential and used only for the purpose of processing applications.", "employment_types": ["Full Time"], "selling_points": [], "locations": ["Aberdeen"], "categories": ["Management", "General Management", "Marketing / Public Relations", "Management"], "post_time": "2022-01-08T14:53:37Z", "salary": {"currency": null, "max": null, "min": null, "period": "monthly", "term": null}, "salary_visible": false, "title_keywords": ["senior fundraising manager"], "responsibilities": ["develop", "communication", "lead a team", "social media strategies", "reports", "digital campaigns", "facebook", "senior management", "internal parties"], "requirements": {"degrees": ["degree", "bachelor"], "majors": ["related disciplines", "marketing", "communications"], "languages": ["cantonese", "english", "chinese", "mandarin"], "language_level": [], "hard_skills": ["facebook", "processing", "word", "ms office"], "soft_skills": ["communication skills", "oral", "under pressure", "organizational", "leadership skills", "presentation skills"], "languages_combined": [{"language": "cantonese", "language_level": []}, {"language": "english", "language_level": []}, {"language": "chinese", "language_level": []}, {"language": "mandarin", "language_level": []}]}, "experience_required": {"duration": ["10 years"], "field": []}}, {"job_id": "100003009031045", "location_code": "hk", "company": "Wright Life Pharmaceutical Limited", "job_title": "\u751f\u7522\u7d93\u7406 Production Manager", "description": "\u8077\u4f4d\u8077\u8cac:\n\n\u7ba1\u7406\u5ee0\u623f\u53ca\u8eca\u9593\u751f\u7522\uff0c\u8ddf\u9032\u751f\u7522\u9032\u5ea6\uff0c\u63d0\u9ad8\u751f\u7522\u6548\u7387\uff0c\u8ca0\u8cac\u7522\u54c1\u751f\u7522\u6d41\u7a0b\u8207\u8cc7\u6e90\u898f\u5283\uff0c\u5305\u62ec\u5b89\u6392\u4eba\u624b\u548c\u7269\u6599\uff0c\u76e3\u7763\u8cea\u91cf\uff0c\u5354\u52a9\u89e3\u6c7a\u751f\u7522\u554f\u984c\u3002\n\n\u8077\u4f4d\u8981\u6c42:\n\n\u4e2d\u4e94\u6216\u4ee5\u4e0a\u7a0b\u5ea6\uff1b5\u5e74\u6216\u4ee5\u4e0a\u85e5\u5ee0\u71df\u904b\u53ca\u7ba1\u7406\u7d93\u9a57\uff1b\u719f\u6089\u9999\u6e2f\u5de5\u5834\u7d93\u71df\u6cd5\u4f8b\uff1b\u826f\u597d\u7684\u7d44\u7e54\u751f\u7522\u548c\u7ba1\u7406\u80fd\u529b\uff1b\u61c2\u96fb\u8166\u57fa\u672c\u64cd\u4f5c\uff0c\u5982Excel\uff0cWord\u53ca\u4e2d\u6587\u8f38\u5165\u6cd5\u3002\n\n\u61c9\u5fb5\u8005\u8acb\u6309Apply Now\u63d0\u4ea4\u500b\u4eba\u4e2d\u6587\u5c65\u6b77\u3001\u73fe\u6642\u85aa\u91d1\u53ca\u8981\u6c42\u85aa\u91d1\u7b49\u3002\n\n\u6240\u6709\u8cc7\u6599\u5c07\u6703\u7d55\u5c0d\u4fdd\u5bc6\uff0c\u4e26\u53ea\u7528\u4f5c\u7533\u8acb\u8077\u4f4d\u4e4b\u7528\u9014\u3002", "employment_types": ["Full Time"], "selling_points": ["5\u5929\u5de5\u4f5c + \u9280\u884c\u5047\u671f", "5\u5e74\u85e5\u5ee0\u7ba1\u7406\u7d93\u9a57", "\u719f\u6089\u9999\u6e2f\u5de5\u5834\u7d93\u71df\u6cd5\u4f8b"], "locations": ["Tsuen Wan Area"], "categories": ["Management", "General Management", "Manufacturing", "Manufacturing Management", "Production Planning / Control"], "post_time": "2022-01-07T09:51:49Z", "salary": {"currency": null, "max": null, "min": null, "period": "monthly", "term": null}, "salary_visible": false, "title_keywords": ["\u751f\u7522\u7d93\u7406", "production manager"], "responsibilities": [], "requirements": {"degrees": [], "majors": [], "languages": [], "language_level": [], "hard_skills": [], "soft_skills": [], "languages_combined": []}, "experience_required": {"duration": [], "field": []}}, {"job_id": "100003009030555", "location_code": "hk", "company": "Delivery Hero Food Hong Kong Limited", "job_title": "Operations Project Senior Manager", "description": "'Hungry to make a difference? Then foodpanda may be the place for you!'\n\nAt foodpanda, we\u2019re on a mission to redefine customers\u2019 food and shopping experience as a multifaceted online platform across the 14 countries we operate in. We\u2019re all about bringing on the smartest and brightest minds as we continue to grow in a fast-moving and agile environment, and hiring those who can thrive in an energetic and hardworking start-up culture. We strive to become everybody\u2019s most loved delivery platform, however, this won't happen without some really awesome people!\n\nWe are looking for a highly-driven and motivated Operations Project Senior Manager to join our fun, professional and dedicated Operations Team based here in Hong Kong. Operations Department aims to bring in passionate individuals with strong entrepreneurial mindsets while managing a diverse workforce to ensure peak-efficient and cost effective day-to-day operations.\u00a0Wait no longer and join us if you want to make a direct and visible impact and contribute to large-scale success!\u00a0\u00a0\n\nRoles and Responsibilities\n\nLead the team in overall growth strategy and execution of initiatives to drive revenue, profitability and growth for the pandago vertical;\nOversee the team\u2019s operations and ensure efficiency, quality, services and cost-effective management of resources;\nBuild and maintain strong network and relationship with local, regional and external stakeholders;\nManage P&L of the vertical, and play a significant role in long-term planning, including setting Objectives and Key Results (OKRs) for the team;\nDevelop and direct the implementation of policies and procedures to ensure that the company complies with all health and safety and other statutory regulations.\n\nQualifications and Requirements\n\nBachelor\u2019 Degree in a related subject. Masters\u2019 Degree / MBA preferred\n5+ years of experience in E-commerce / start up environment\nProven commercial and management experience. Experience in food & delivery, start-up, high tech, retail or ecommerce industry is a huge plus\nProven business process improvement experience\nPerseverance and stamina\nSolid knowledge of performance reporting and financial/budgeting processes\nPeople oriented, self-motivated and with the ability to motivate others\nExcellent interpersonal, communication and presentation skills.\nStart-up mindset \u2013 highly collaborative with an entrepreneurial, roll-up-your-sleeves attitude that\u2019s not afraid to work independently when required.\n\nWhat We Offer\n\nA dynamic, fast paced environment\nA vibrant and international team with diverse background\nSteep learning curve in e-commerce & entrepreneurship\nLearning & development programs and skills trainings\u00a0\nFlexible working hours and agile company with a flat hierarchical structure\nMonthly staff allowance and corporate discounts including at restaurants, gyms and many more\nAgile office environment with a fully-stocked beverage fridge and self-serve beer\u00a0\nUnlimited paid leave policy", "employment_types": ["Full Time"], "selling_points": ["Business Process Improvement", "Project Management", "On-demand Delivery Service Business"], "locations": ["Causeway Bay"], "categories": ["Transportation & Logistics", "Others", "Professional Services", "Business Consultancy", "Management", "General Management"], "post_time": "2022-01-07T07:44:50Z", "salary": {"currency": null, "max": null, "min": null, "period": "monthly", "term": null}, "salary_visible": false, "title_keywords": ["senior manager", "operations"], "responsibilities": ["regulations", "cost", "management", "operations", "policies", "quality", "implementation", "p&l", "develop", "procedures", "maintain", "planning"], "requirements": {"degrees": ["degree", "bachelor"], "majors": [], "languages": [], "language_level": [], "hard_skills": ["plus", "e-commerce"], "soft_skills": ["self-motivated", "work independently", "collaborative", "communication", "presentation skills", "interpersonal"], "languages_combined": []}, "experience_required": {"duration": ["5+ years"], "field": ["ecommerce", "management", "e-commerce", "tech", "commercial", "business", "food", "retail"]}}]