[{"job_id": "100003009052745", "location_code": "hk", "company": "Sun Entertainment Group Limited", "job_title": "CHIEF OPERATING OFFICER", "description": "1. Degree in Manufacturing/ Engineering / Management study\n2. At least 10 years experience in managerial position and electrical appliance industry\n3.\u00a0Monitor all department in the organization including factory, engineering, sales, purchasing and shipping. Especially to assist the Engineering to complete projects in a timely basis.\n4. Develop and implement business plan for profitability\u00a0\n5. Assist in budget preparation and expense management activities.\n6. Evaluate the effectiveness of marketing program and recommend improvements.\n7. Develop strategies to improve overall quality and productivity.\n8. Generate business, cost and employee reports to management.\n9. Schedule regular team meetings to discuss about business updates, issues and suggestions\u00a0\n10. Respond to employee concerns in timely manner.\n11. Provide direction and guidance to employees in their assigned job duties.\n12. Determine staffing requirements and ensure that office positions are filled promptly.\n13. Assist in employee recruitment, training, performance evaluation, promotion and termination.\n14. Manage administrative,logistical, human resources and accounting services to support company operation\n15. Station at China factory mainly and HK office depend on job requirement.\n\n", "employment_types": ["Full Time", "Permanent"], "selling_points": ["10+ years of senior management exp. in Macau/Aus.", "5 yrs entertainment, event & marketing industry", "Qualified accountant of CPA Austra"], "locations": ["Not Specified"], "categories": ["Accounting", "Others", "Management", "Top Executives (CEO, CFO, CTO, GM, MD etc.)", "E-commerce", "Others"], "post_time": "2022-01-17T03:54:02Z", "salary": {"currency": null, "max": null, "min": null, "period": "monthly", "term": null}, "salary_visible": false, "title_keywords": ["operating officer"], "responsibilities": ["guidance", "management", "shipping", "develop strategies", "cost", "provide direction", "budget", "monitor", "quality", "develop", "evaluate", "reports", "schedule", "recruitment", "evaluation", "business plan"], "requirements": {"degrees": ["degree"], "majors": ["manufacturing", "engineering"], "languages": [], "language_level": [], "hard_skills": [], "soft_skills": ["timely"], "languages_combined": []}, "experience_required": {"duration": ["at least 10 years"], "field": ["managerial"]}}, {"job_id": "100003009054078", "location_code": "hk", "company": "Crossings Executive Search", "job_title": "Executive Director / Deputy Executive Director (an NGO) (Ref: EDED/AU)", "description": "Our client is an NGO and a leading animal welfare organisation, with an array of effective services and programmes in HK. On their behalf, we are currently seeking an Executive Director (or Deputy), with the passion and personal calling to apply your skills and leadership towards helping the less fortunate animals in HK get a chance for a better tomorrow. This is an excellent opportunity, for one able to assist with the following:\nResponsibilities:\nReporting to and working closely with the Executive Committee, advocate the organisation\u2019s vision across the community\nStrategize, plan and drive all aspects of development programmes, policies, and plans in pursuit of the mission of the organization.\nDevelop effective and innovative fundraising strategy and implementation plan to achieve the organisation\u2019s goals\nActively manage overall agency-wide operations in a collaborative and inclusive manner, providing leadership to over 150 headcount\nRepresent the organization to build strategic partnerships with external stakeholders including government representatives and community leaders\nRequirements:\nDegree holder in any discipline, ideally with experience working for an NGO\nPersonal calling to help create a better society where animals and human can co-exist harmoniously\nGood understanding of the development issues, trends and growing challenges that impact animal welfare\nProven track record in leading and motivating sizable operations and teams\nInspirational leader in driving change and collaboration.\nProactive attitude with good problem solving skills\nExcellent communicator in English and Chinese with strong engagement and stakeholder management skills\u00a0\nFor all applications, kindly send us your updated CV quoting reference EDED/AU", "employment_types": ["Full Time", "Permanent"], "selling_points": ["An NGO / One of Asia's leading animal welfare org", "Competitive package", "Inspirational leader in driving change"], "locations": ["Not Specified"], "categories": ["Management", "Top Executives (CEO, CFO, CTO, GM, MD etc.)"], "post_time": "2022-01-17T08:48:20Z", "salary": {"currency": null, "max": null, "min": null, "period": "monthly", "term": null}, "salary_visible": false, "title_keywords": ["executive director"], "responsibilities": ["reporting", "policies", "operations", "implementation", "develop", "providing leadership", "plan", "plans"], "requirements": {"degrees": ["degree holder"], "majors": [], "languages": ["english", "chinese"], "language_level": ["excellent"], "hard_skills": ["problem solving skills", "animal welfare"], "soft_skills": ["problem solving skills", "proactive", "communicator"], "languages_combined": [{"language": "english", "language_level": ["excellent"]}, {"language": "chinese", "language_level": ["excellent"]}]}, "experience_required": {"duration": [], "field": []}}, {"job_id": "100003009044899", "location_code": "hk", "company": "Pet-Link Company Limited", "job_title": "Assistant General Manager", "description": "About the job\n\nThe right candidate is responsible for overseeing the development of a media platform business goals and objectives. The typically work is to increase business revenue, identify and develop business opportunities. Other duties and responsibilities may include establishing effective company policies, goals, and sales targets. Business directors are also expected to negotiate contracts with clients and suppliers and propose and develop new partnerships.", "employment_types": ["Full Time", "Permanent"], "selling_points": [], "locations": ["Tai Po Area"], "categories": ["Management", "General Management", "Top Executives (CEO, CFO, CTO, GM, MD etc.)"], "post_time": "2022-01-13T06:35:06Z", "salary": {"currency": null, "max": null, "min": null, "period": "monthly", "term": null}, "salary_visible": false, "title_keywords": ["assistant general manager"], "responsibilities": ["business goals", "other duties", "policies", "business opportunities", "contracts", "develop"], "requirements": {"degrees": [], "majors": [], "languages": [], "language_level": [], "hard_skills": [], "soft_skills": ["responsible"], "languages_combined": []}, "experience_required": {"duration": [], "field": []}}, {"job_id": "100003009051217", "location_code": "hk", "company": "ACT Company", "job_title": "Relationship Manager \u5ba2\u6236\u95dc\u4fc2\u7d93\u7406 - NOVA Prestige Family Office (50k-120k)", "description": "Responsibilities:\n\nSupport Managing Director/General Manager to monitor and execute the new business development and existing operations including new product development, RND, Merchant, Design, Sales & Marketing, Retail, Warehouse, Factory, Overseas trading and e-commerce.\nFormulate and implement annual business operating plans and budget to achieve annual\u00a0KPI target.\nProvide solid guidance and form a highly motivated and energetic team to achieve targets and company goals.\nManage overall P&L, cost & expenditure, policy & procedures of the Company.\nAny other ad-hoc assignments as assigned.\n\nRequirements:\n\nUniversity graduate in Business Management, Marketing or related discipline\nAt least 15 years of experience in the fields of FMCG industries, with minimum 5 years in senior management level, solid PRC experiences preferred.\nFlexibility and adaptability to face challenges in a growing organization\nExcellent business acumen, ability to convert the business strategy to operational implementation.\nAble to inspire, lead and manage the team to implement business strategies effectively.\nGood spoken and written in English and Mandarin.\nWilling to travel Overseas and PRC subject to the development of Covid-19.\n\nCompany website: https://www.pet-link.com\u00a0\u00a0https://eshop.iloverabbit.com/\n\nWe offer competitive salary remuneration package which included year-end KPI bonus, hardworking allowance, medical insurance, dental allowance, 14 days annual leave and staff purchase discount to the successful candidate.\n\nInterested applicants please email your detailed resume indicating your current, expected salary and also date of availability along with your relevant portfolio. Applicants without portfolio will not be considered.\n\n*All information provided will be treated in strict confidential and used only for recruitment purposes.\u00a0", "employment_types": ["Full Time", "Part Time", "Permanent", "Temporary", "Contract", "Internship", "Freelance"], "selling_points": ["Work with The Rich", "NOVA Prestige Family Office", "50-120k"], "locations": ["Kwun Tong"], "categories": ["Admin & HR", "Administration / Operation Manager", "Professional Services", "Business Consultancy", "Management", "Top Executives (CEO, CFO, CTO, GM, MD etc.)"], "post_time": "2022-01-15T05:05:52Z", "salary": {"currency": "HKD", "max": 89999, "min": 70000, "period": "monthly", "term": null}, "salary_visible": true, "title_keywords": ["\u5ba2\u6236\u95dc\u4fc2\u7d93\u7406", "relationship manager"], "responsibilities": ["achieve targets", "guidance", "cost", "operations", "ad-hoc assignments", "budget", "monitor", "procedures", "design", "p&l", "plans"], "requirements": {"degrees": ["university graduate"], "majors": ["business", "marketing"], "languages": ["english", "mandarin"], "language_level": ["good"], "hard_skills": ["business management", "acumen"], "soft_skills": ["business acumen", "adaptability", "hardworking", "detailed"], "languages_combined": [{"language": "english", "language_level": ["good"]}, {"language": "mandarin", "language_level": ["good"]}]}, "experience_required": {"duration": ["minimum 5 years", "at least 15 years"], "field": ["management", "fmcg"]}}, {"job_id": "100003009051906", "location_code": "hk", "company": "PwC", "job_title": "HR Transformation and Change Management Senior Manager", "description": "\u300a\u4e00\u7ad9\u5f0f\u9ad8\u7aef\u5ba2\u6236\u5e73\u53f0\u516c\u53f8\u300b\n\n\u5bcc\u4eba\u8ca1\u6280/\u4fdd\u55ae\u878d\u8cc7/\u5bcc\u4eba\u53d7\u8a17/\u907a\u7522\u7a05/\u5bb6\u65cf\u4fe1\u8a17/\u79c1\u4eba\u9280\u884c\n\n\u5de5\u4f5c\u7bc4\u7587\uff1a\n\n\u516c\u53f8\u505a\u9ad8\u7aef\u5ba2\u6236\u751f\u610f\uff08\u4fdd\u55ae\u878d\u8cc7/\u9ad8\u8cc7\u7522\u589e\u503c/\u907a\u7522\u7a05/\u5bb6\u65cf\u4fe1\u8a17\uff09\n\n\u4e3b\u8981\u5354\u52a9CEO\u65e5\u5e38\u5de5\u4f5c\n\n\u5354\u52a9CEO\u63a5\u898b\u9ad8\u7aef\u5ba2\u6236\n\n\u8ca0\u8cac\u958b\u6236\u53e3/\u5206\u6790\u8cc7\u91d1\u72c0\u6cc1/\u89e3\u91cbproposal\u00a0\u00a0\n\n\u8207\u9ad8\u7aef\u5ba2\u6236\u4fdd\u6301\u806f\u7d61\u00a0\u00a0\n\n\u6587\u4ef6\u8ddf\u9032\n\n\u798f\u5229\uff1a\n\n\u6709\u4f63\u91d1\u5206\uff0c\u82b1\u7d05\n\n\u89c0\u5858\u7532\u7d1a\u5546\u5834\u5beb\u5b57\u6a13\u5de5\u4f5c\n\n\u5730\u65b9\u5bec\u8eba\uff0c\u64c1\u6709\u8212\u9069\u4f11\u606f\u7a7a\u9593\n\nWork with CEO \u6642\u9593\u81ea\u4e3b\n\n\u4e00\u5e74\u53bb\u4e00\u6b21\u4e9e\u6d32\u8207\u6b50\u6d32\uff08\u6a5f\u7968\uff0b\u9152\u5e97)\u00a0\n\n\u8981\u6c42\uff1a\n\n\u80af\u5b78\uff0c\u6709\u8010\u6027\uff01\n\n\u4e2d\u4e94\u7562\u696d\u53ca\u4e94\u79d1\u5408\u683c\n\n\u611b\u6e9d\u901a\uff0c\u4e3b\u52d5\uff0c\u6562\u65bc\u63a5\u53d7\u6311\u6230\n\n\u7d93\u9a57\u4e0d\u62d8\uff0c\u6b61\u8fce\u7562\u696d\u5927\u5b78\u751f\uff0c\u53ea\u8981\u80af\u5b78\n\n*******\u6709\u610f\u8005\u8acb\u7acb\u523b\u9ede\u64caApply Now\u4ee5\u5b89\u6392\u9762\u8a66\u00a0**********", "employment_types": ["Full Time"], "selling_points": [], "locations": ["Not Specified"], "categories": ["Admin & HR", "HR Director / Manager", "Recruitment / Executive Search", "Management", "Top Executives (CEO, CFO, CTO, GM, MD etc.)"], "post_time": "2022-01-17T01:30:03Z", "salary": {"currency": null, "max": null, "min": null, "period": "monthly", "term": null}, "salary_visible": false, "title_keywords": ["senior manager", "hr"], "responsibilities": [], "requirements": {"degrees": [], "majors": [], "languages": [], "language_level": [], "hard_skills": [], "soft_skills": [], "languages_combined": []}, "experience_required": {"duration": [], "field": []}}, {"job_id": "100003009049710", "location_code": "hk", "company": "Playright Children's Play Association", "job_title": "Executive Director", "description": "Job Description & Summary\n\nReporting to the PwC China Human Capital Strategy and Transformation CoE Lead, the HR Transformation and Change Management Lead is responsible for end-to-end implementation of the new target operating model and leading the change management work stream, proactively balancing scope, schedule, budget, risk, project team, outcomes, and benefits.\n\nKey responsibilities include:\n\nTarget Operating Model for the People Organisation\n\n\u2022With the high-level design of the future state Target Operating model confirmed, the HR Tranformation Project Lead will engage key stakeholders to design the detailed team structure, scope, roles and responsibilities of the future state HR teams.\n\n\u2022Leverage past HC transformation experience, leading practices, and connections with other PwC network firms to apply key learnings to develop implementation and workforce transition and change management plan to ensure a successful transformation\n\n\u2022Post implementation, conduct HR activity analysis and other satisfaction surveys to gather input on the impact and effectiveness of the new TOM model, and provide recommendations for further improvements to ensure maximum benefit realisation\n\nChange Management, Culture and Values\n\n\u2022Own and drive the change management strategy and plans for the continuous transformation of the People Organisation\n\n\u2022Work closely with key stakeholders to design change strategy and plan to implement key People Priorities\n\n\u2022Work with a small team to implement change management plans for key people priorities and provide advisory support to other people initiatives\n\n\u2022Design and implement ongoing initiatives to further promote the PwC Culture and Values and continue to drive the right behaviours\n\nWays of working\n\n\u2022Collaborate with key stakeholders (e.g. business and HC leadership) to understand business requirements and objectives\n\n\u2022Support HC Strategy and Transformation CoE Lead to coordinate the delivery of the end to end new target operating model\n\n\u2022Motivate and lead the project team with enthusiasm and drive team effectiveness\n\nRequirements\n\n\u202212+ years of experience in HR Transformation and Change Management, having implemented a new target operating model (operating model, structure, process, ways of working and governance) for one or more organizations\n\n\u2022Previous HR Transformation experience to include but not limited to: HR activity analysis, detailed HR organisation design, capability reviews, change management, and workforce transition planning\n\n\u2022Previous change management experience to include but not limited to: Stakeholder and change impact assessment, change management, communications, training and workforce transition plan design\n\n\u2022Flexible and capable to manage the end to end HR transformation workstreams in a complex global/territory capacity\n\n\u2022Ability to work with different levels of stakeholders to develop relationships, establish credibility and instill confidence\n\n\u2022Ability to identify and solve problems objectively using analysis, leading practices, and experience\n\n\u2022Excellent analytical, articulation, project management, and communication skills\n\n\u2022Prior experience and/or familiarity with agile strategies and some of the relevant HC technologies would be of benefit\n\n\u6709\u610f\u7533\u8acb\u8005\u8acb \u6309 APPLY NOW\u7533\u8acb\n\n", "employment_types": ["Full Time"], "selling_points": [], "locations": ["Chai Wan"], "categories": ["Public / Civil", "Social Services - Community / Non-profit Organization", "Management", "Top Executives (CEO, CFO, CTO, GM, MD etc.)"], "post_time": "2022-01-14T09:08:03Z", "salary": {"currency": null, "max": null, "min": null, "period": "monthly", "term": null}, "salary_visible": false, "title_keywords": ["executive director"], "responsibilities": ["reporting", "change management", "hr", "budget", "teams", "implementation", "design", "develop", "analysis", "coordinate", "provide recommendations", "schedule", "plan", "plans"], "requirements": {"degrees": [], "majors": [], "languages": [], "language_level": [], "hard_skills": ["project management", "analysis", "agile"], "soft_skills": ["communication skills", "confidence", "capable", "agile", "solve problems", "project management", "organisation", "detailed"], "languages_combined": []}, "experience_required": {"duration": [], "field": ["management", "training", "hr", "design", "planning"]}}, {"job_id": "100003009051308", "location_code": "hk", "company": "Manulife (International) Limited", "job_title": "Recruiting Manager \u62db\u52df\u7d93\u7406", "description": "A. JOB SUMMARY\n\nThe Executive Director is accountable for:\n\nDeveloping and implementing Playright's strategic plan that aligns with its positioning as an active play advocate\nAchieving financial goals of the organisation and ensuring proper financial control\nOverseeing operation of the organisation/services and safeguarding compliance with regulatory requirements\nExpanding pool of supporters for the accomplishment of Playright\u2019s mission\nSupporting the Board of Directors for good governance of the organisation\nDeveloping a solid team that is passionate, accountable, and capable to meet Playright\u2019s strategic goals\n\nB. KEY RESPONSIBILITIES\n\nStrategic & Business Development\n\nBring in global perspectives, research, and best practices, and develop insightful local applications\nWork with the Board in the strategic planning process, and review the strategic plan regularly to ensure that services and programmes are tightly linked to Playright\u2019s mission and vision\nTranslate the strategic plan into responsibilities for senior management, in consideration of the unique professions in play environment, hospital play, and playwork, to follow through, monitor, and implement the plans and use the performance results to inform decisions on strategic planning and resources allocation\nLead service strategies, human resources planning, and pilot new service projects for the sustained growth of Playright\nSupport the Board to carry out its governance functions\n\nFinancial Management & Fundraising\n\nPrepare/review multi-year financial plan for the Board\u2019s discussion and approval of resource allocation, funding plans, and investment objectives in the context of strategic goals\nEnsure timely financial statements/audits for the Board\u2019s regular review\nInitiate and materialise fundraising opportunities, support the Board in fundraising activities, and achieve the financial goals of the organization\n\nOrganisation & Service / Consultancy Programme Operations\n\nWork with the Board to set performance targets for the organisation\nOversee the operations of the organisation, services, and consultancy programme in an effective and efficient manner, and in accordance with high standards and expectations\nMonitor and safeguard compliance with all regulatory and funding requirements\nAssess and monitor potential risks, and ensure mitigation plans are in place\n\nStakeholders\u2019 Engagement\n\nAct as an effective representative of Playright, actively engaging with all internal, external, and international stakeholders. Seek stakeholder feedback to inform strategy and resource allocation\nExpand pool of supporters, funders, and partners, gaining the buy-in needed to accomplish the mission and goals of Playright\nEnsure that impacts of Playright are communicated effectively to stakeholders\n\nPeople Management / Competency Enhancement\n\nLead, manage, and develop high performance teams, and be a role model for Playright\u2019s purpose and value\nCommunicate and enhance the competencies of the different professionals in play, and make connections to maximise the impact for play advocacy\nCultivate a culture of professionalism, trust, commitment, and inclusion in all levels of the organisation\n\nC. PERSONAL ATTRIBUTES\n\nLove of PLAY \u2013 exceptional enthusiasm. Inspirational leadership. Bring new and creative ideas to Playright\nExcellent analytical, negotiation, interpersonal, motivational, and change management skills\nStrong ability to establish credibility and relationships with diverse individuals and groups\nStrong COMMUNICATOR \u2013 sensitivity to internal and external environment of Playright. Strong advocate for Playright externally and Inspirational role model internally\nSolid judgement to make decisions that are aligned with the mission and goals, able to make difficult calls when needed, and manage with transparency, empathy, and respect. Willing to work at execution level when needed\nMindfulness in working in NGOs, but with operational experience to drive system and implementation excellence\n\nD. JOB REQUIREMENTS\n\nDegree in Management or Social Welfare or Health Care or Architecture or related discipline, or other similar qualifications\nSignificant proven record of achievement in a management or strategist position, preferably child-related. Experience in running a self-financed service or social enterprise is an advantage\nSignificant proven record of achievement in effective partnership management\nExcellent verbal and written communication skills in Chinese and English\nComputer literate\n\n\nWe offer an attractive remuneration package and friendly working environment to the right candidate.\u00a0Please send detailed resume to Human Resources Department by clicking \u201cApply Now\u201d button by 31 January 2021.\u00a0For more information about our organization, please visit our website:\u00a0https://www.playright.org.hk/\n\nWe are an equal opportunity employer and welcome applications from all qualified candidates.\u00a0All personal data will be used for recruitment purpose only. Only shortlisted candidates will be contacted. If you have not been contacted within 20 business days of your application, please assume your application has not been shortlisted.", "employment_types": ["Full Time"], "selling_points": ["\u64c1\u6709\u62db\u52df / \u5275\u696d\u7d93\u9a57\u512a\u5148", "\u7acb\u5fd7\u6649\u5347\u7ba1\u7406\u968e\u5c64", "\u4ee5\u62db\u52df\u6210\u5c31\u5149\u8f1d\u4e8b\u696d\u3001\u6c38\u7e8c\u7d93\u71df\uff01"], "locations": ["Kwun Tong"], "categories": ["Sales, CS & Business Devpt", "Sales - Sales Management", "Management", "Top Executives (CEO, CFO, CTO, GM, MD etc.)", "Banking / Finance", "Wealth Management"], "post_time": "2022-01-15T07:55:59Z", "salary": {"currency": null, "max": null, "min": null, "period": "monthly", "term": null}, "salary_visible": false, "title_keywords": ["manager"], "responsibilities": ["management", "creative ideas", "change management", "strategic planning", "operations", "review", "monitor", "compliance", "financial statements", "develop", "regular review", "teams", "implementation", "plan", "audits", "plans", "senior management", "planning"], "requirements": {"degrees": ["degree"], "majors": ["architecture"], "languages": ["english", "chinese"], "language_level": ["excellent"], "hard_skills": [], "soft_skills": ["communication skills"], "languages_combined": [{"language": "english", "language_level": ["excellent"]}, {"language": "chinese", "language_level": ["excellent"]}]}, "experience_required": {"duration": [], "field": []}}, {"job_id": "100003009051183", "location_code": "hk", "company": "Early Light International (Holdings) Ltd", "job_title": "Bodyguard and Driver", "description": "Responsibilities:\n\nWork closely with Directors/CEO, develop strategic annual business plans for Hong Kong, Mainland China and overseas that are aligned to the Company's objectives and directions.\nAct as a strategic partner on daily business, new project development and long-term strategic planning.\nFormulate and execute business operating plans to improve revenues and sustain long term business growth\u00a0\nLead the team at different levels, empower and motivate team members to achieve targets and company goals.\nMonitor and maintain internal control procedures and standards to improve risk management, alert Directors/CEO for any possible crisis in a timely manner.\nResponsible for the overall P&L; cost & expenditure; policy & procedures of the Company\nAny other ad-hoc assignments as assigned.\n\nRequirements:\n\nUniversity graduate in Business Management, Marketing or related discipline\nAt least 20 years of experience in the fields of FMCG industries, with minimum 8 years in senior management level, solid PRC experiences preferred.\nFlexibility and adaptability to face challenges in a growing organization\nExcellent business acumen, ability to convert the business strategy to operational implementation.\nAble to inspire, lead and manage the team to implement business strategies effectively.\nGood spoken and written in English and Mandarin.\nWilling to travel Overseas and PRC subject to the development of Covid-19.\nLess experiences will be considered as Assistant General Manager\n\nCompany website: https://www.pet-link.com\u00a0\u00a0https://eshop.iloverabbit.com/\n\nWe offer competitive salary remuneration package which included year-end KPI bonus, hardworking allowance, medical insurance, dental allowance, 18 days annual leave and staff purchase discount to the successful candidate.\n\nInterested applicants please email your detailed resume indicating your current, expected salary and also date of availability along with your relevant portfolio. Applicants without portfolio will not be considered.\n\n*All information provided will be treated in strict confidential and used only for recruitment purposes.\u00a0", "employment_types": ["Full Time", "Permanent"], "selling_points": ["Provide security and driving services", "Holder of valid SPP and Driving License", "Double Pay and Medical Coverage"], "locations": ["Shatin Area"], "categories": ["Others", "Security / Safety Control", "Management", "Top Executives (CEO, CFO, CTO, GM, MD etc.)", "Transportation & Logistics", "Private Transportation"], "post_time": "2022-01-15T04:15:07Z", "salary": {"currency": null, "max": null, "min": null, "period": "monthly", "term": null}, "salary_visible": false, "title_keywords": ["bodyguard", "driver"], "responsibilities": ["achieve targets", "management", "cost", "strategic planning", "ad-hoc assignments", "monitor", "procedures", "business plans", "develop", "a timely manner", "p&l", "maintain", "plans", "internal control"], "requirements": {"degrees": ["university graduate"], "majors": ["business", "marketing"], "languages": ["english", "mandarin"], "language_level": ["good"], "hard_skills": ["business management", "acumen"], "soft_skills": ["business acumen", "adaptability", "hardworking", "detailed"], "languages_combined": [{"language": "english", "language_level": ["good"]}, {"language": "mandarin", "language_level": ["good"]}]}, "experience_required": {"duration": ["minimum 8 years", "at least 20 years"], "field": ["management", "fmcg"]}}, {"job_id": "100003009045995", "location_code": "hk", "company": "Hong Chi Association", "job_title": "Assistant General Secretary (Ref.: AGS/15/01/22/JD)", "description": "The Candidate will:\n\nReport to the General Secretary, assist to formulate / implement the policies of the services projects and initiate new services development. His / her work will include but not limited to: professional leadership, service quality assurance, formulation of professional protocol, staff training and development, liaison with government departments and NGOs, and attending relevant Committees.\n\n\nRequirements:\n\n\nA degree in Social Work / Public Administration or above, preference will be given to candidates with rehabilitation studies\u00a0\nSolid 5 years\u2019 working experiences as senior management (social work officer equivalent or above) in rehabilitation services, experience in working with\u00a0people with intellectual disabilities will be an advantage\nAbility to work in collaboration / as a team with other professions for professional leadership and development\nDedication and commitment to serve the Mission of the Association\nAble to communicate effectively in written / spoken English, Chinese and Putonghua with a wide range of stakeholders including service users, caregivers, board members, government officials, funding bodies as well as the media\n\n\nPlease send the completed Job Application Form (can be downloaded from\u00a0https://www.hongchi.org.hk/uploads/form/App2B_Job_Application_Form(201906).pdf) and mark \u201cConfidential & Ref. No.\u201d to\u00a0Human Resources Office, Pinehill Village, Chung Nga Road, Nam Hang, Tai Po, N.T., Hong Kong\u00a0or by clicking \"Apply Now\".\n\n**Prospective employees are requested to undergo Sexual Conviction Record Check on voluntary basis**\n\u00a0(All data collected will be used for recruitment purposes only.)", "employment_types": ["Full Time", "Contract"], "selling_points": [], "locations": ["Tai Po Area"], "categories": ["Public / Civil", "Social Services - Community / Non-profit Organization", "Management", "Top Executives (CEO, CFO, CTO, GM, MD etc.)"], "post_time": "2022-01-15T01:23:19Z", "salary": {"currency": null, "max": null, "min": null, "period": "monthly", "term": null}, "salary_visible": false, "title_keywords": ["secretary", "assistant"], "responsibilities": ["rehabilitation", "data", "policies", "quality", "recruitment", "report", "senior management", "administration"], "requirements": {"degrees": ["degree"], "majors": ["social work", "public administration"], "languages": ["putonghua", "english", "chinese"], "language_level": [], "hard_skills": ["no"], "soft_skills": ["leadership"], "languages_combined": [{"language": "putonghua", "language_level": []}, {"language": "english", "language_level": []}, {"language": "chinese", "language_level": []}]}, "experience_required": {"duration": ["5 years"], "field": ["management"]}}, {"job_id": "100003009047173", "location_code": "hk", "company": "JPMorgan Chase Bank, N.A.", "job_title": "Commercial Bank - Priority International Coverage Executive (ICE) - Executive Director, Hong Kong", "description": "Employer Description\n\nThe Commercial Banking Division represents a strategically important business to the firm, delivering extensive industry knowledge, local expertise and dedicated service to over 24,000 clients including corporations, municipalities, financial institutions and not-for-profit entities. In Asia Pacific (APAC), Commercial Banking International (CBI) Team serves subsidiaries of US multi-national organizations with annual revenues ranging from US$20 million to US$2 billion across more than 2,000 clients in the region. As well as other multi-national corporations' subsidiaries where their HQ are based in Europe and few Asia markets.\n\nThe team has helped clients take advantage of global opportunities by connecting them with international cash management, trade, liquidity management, financing and foreign exchange solutions. A qualified network of in-country experts and dedicated Parent Bankers leverage local knowledge to customize solutions to help clients expand internationally, navigate the complexities of global payments and understand market nuances.\n\nJob Description\n\nAn opportunity is available to join the Hong Kong team of J.P. Morgan's Commercial Banking International (CBI - HK) in the capacity of an Executive Director/Vice President located in Hong Kong as International Coverage Executive (ICE).\n\nThe ICE is responsible for the overall relationship management as well as transaction services requirements of the APAC subsidiaries of Corporate Client Banking / Specialized Industry (CCBSI) segment. Leveraging the firm's capabilities to meet our clients' domestic and international needs, the team provides local market expertise and industry knowledge, combined with active coordination globally of J.P. Morgan's extensive product and service expertise to deliver comprehensive solutions across multiple product and service disciplines. Traditional Commercial Banking product and service capabilities include but not limited to treasury services, trade finance, bilateral and syndicated commercial lending, foreign exchange and investment banking.\n\nKey Responsibilities\n\nThe CBI Hong Kong Team covering CCBSI clients, the subsidiaries of North America/EMEA/APAC headquartered (HQ) companies operating in HK, with primary focus of Asia Pacific key decision makers and influencers that are based in Hong Kong. We are looking for an experienced Senior Regional Banker/Sales, with strong industry and client knowledge.\n\nBuild and develop both Local and or Regional Treasurer/CFO level coverage of CBI selected clients by active prospecting and serve as a focal point of contact within J.P. Morgan\nResponsible for marketing in-scope banking products (including: Treasury Services (TS), Trade, FX and loan products) and drive TS opportunities.\nDevelopment of forward-looking new business plans for (local or regional) clients and the maintenance of existing business relationships, partnering with HQ parent banking teams and respectiveICE teams to drive and deliver financial goals by conducting comprehensive client analysis: Conversion of client analysis into concrete financial solutions\nWork closely with International Product Specialists (IPS) and Parent Banking team globally to increase treasury services (TS) wallet share of existing clients as well as cross-sell products, annual reviews and portfolio statistical reporting\nMaintain the existing portfolio of CCBSI clients, including client due diligence, KYC, AML and other requirements\nManage the sales pipelines, book timely client call memos, be responsible to coordinate with Associates & product partners for preparing proposals/presentations for clients\nQualifications\n\nMore than 10 years industry experience as Client Relationship manager or Sales coverage with proven ability to build and develop client relationships with specific focus on multi-national clients for transaction banking and other services, win new business, close transactions and develop networks, both internally and externally\nThis role is also open to VP level candidates\nDemonstrable credit knowledge\nStrong knowledge of Treasury Services products including cash management, liquidity and cross-border products would be a key requirement\nExcellence in oral and written communication with proven strength for personal engagement\nFlexibility to co-ordinate, manage multiple transactions and processes while ensuring delivery against deadlines, client expectations and business priorities\nAbility to work consistently across different time zones and geographies dealing with numerous stakeholders\nSelf-starting with clear results orientation and a capacity to operate independently, appropriately balancing short, medium and long-term objectives\nEnthusiastic and team orientated\nStrong influencing skills and proven track record of managing cross cultural environments\nLanguage Requirements\n\nFluent in spoken and written English & Mandarin. Cantonese and Japanese language skills would be an advantage.\nWe recognize that our people are our strength and the diverse talents they bring to our global workforce are directly linked to our success. We are an equal opportunity employer and place a high value on diversity and inclusion at our company. We do not discriminate on the basis of any protected attribute, including race, religion, color, national origin, gender, sexual orientation, gender identity, gender expression, age, marital or veteran status, pregnancy or disability, or any other basis protected under applicable law. In accordance with applicable law, we make reasonable accommodations for applicants' and employees' religious practices and beliefs, as well as any mental health or physical disability needs.\n\nInterested parties please click \u201cApply Now\u201d to apply job.\n\nAll applications applied through our system will be delivered directly to the advertiser and privacy of personal data of the applicant will be ensured with security.", "employment_types": ["Full Time"], "selling_points": [], "locations": ["Not Specified"], "categories": ["Banking / Finance", "Treasury", "Others", "Management", "Top Executives (CEO, CFO, CTO, GM, MD etc.)"], "post_time": "2022-01-14T02:31:03Z", "salary": {"currency": null, "max": null, "min": null, "period": "monthly", "term": null}, "salary_visible": false, "title_keywords": ["executive director", "executive"], "responsibilities": ["reporting", "management", "due diligence", "aml", "maintenance", "kyc", "analysis", "teams", "coordinate with", "business plans", "develop", "presentations", "transactions", "communication", "maintain", "contact", "coordination", "banking"], "requirements": {"degrees": [], "majors": [], "languages": ["cantonese", "japanese", "english", "mandarin"], "language_level": ["advantage", "fluent"], "hard_skills": ["make"], "soft_skills": ["diverse"], "languages_combined": [{"language": "cantonese", "language_level": ["advantage"]}, {"language": "japanese", "language_level": ["advantage"]}, {"language": "english", "language_level": ["fluent"]}, {"language": "mandarin", "language_level": ["fluent"]}]}, "experience_required": {"duration": [], "field": []}}, {"job_id": "100003009047435", "location_code": "hk", "company": "JPMorgan Chase Bank, N.A.", "job_title": "Taiwan Banker Vice President", "description": "\u00a0Deputy General Manager (Station in India)\n\nDegree or above in Manufacturing Engineering or relative area\nMin. 15 years solid experience in toy business(both plastic & electronic toys)\nMin. 7 years experience in management level of sizable toy factories / companies\nMin. 7 years in dealing the manufacturing / engineering & quality issues with\u00a0repute OEM\u00a0toy companies. (no more than 5 years removed from such experience)\nProfessional knowledge in plastic toy\u00a0products manufacturing processes (with good understanding of routine manufacturing management), production planning, store operations and specially in toy products, QA requirement and quality control\u00a0\nFluent English\nStation in India (4-5 breaks back to HK every year, negotiable)\nGood health, able to adapt different environment and culture\nCandidate with much experiences or higher qualification\u00a0may\u00a0be considered as Deputy Managing Director\u00a0\n\u7372\u8058\u5f8c\u66ab\u6642\u5728\u6e2f\u5de5\u4f5c\u76f4\u81f3\u5370\u5ea6\u901a\u95dc\u5f8c\u624d\u555f\u7a0b\u524d\u5f80\u7576\u5730\u99d0\u5ee0", "employment_types": ["Full Time"], "selling_points": [], "locations": ["Not Specified"], "categories": ["Banking / Finance", "Others", "Management", "Top Executives (CEO, CFO, CTO, GM, MD etc.)"], "post_time": "2022-01-14T03:04:59Z", "salary": {"currency": null, "max": null, "min": null, "period": "monthly", "term": null}, "salary_visible": false, "title_keywords": ["vice president"], "responsibilities": ["management", "operations", "quality", "production planning", "quality control"], "requirements": {"degrees": ["degree or above"], "majors": ["manufacturing", "engineering"], "languages": ["english"], "language_level": ["fluent"], "hard_skills": ["no"], "soft_skills": [], "languages_combined": [{"language": "english", "language_level": ["fluent"]}]}, "experience_required": {"duration": ["7 years", "5 years", "15 years"], "field": ["toys", "managing director", "management"]}}, {"job_id": "100003009051000", "location_code": "hk", "company": "Lucky Bell Plastic Factory Ltd", "job_title": "Deputy General Manager (Station in India)\u901a\u95dc\u5f8c\u5373\u8d77\u7a0b\u99d0\u5370\u5ea6", "description": "Job Responsibilities\uff1a\n\nManage full spectrum of C&B functions including\u00a0monthly payroll, MPF, overtime allowances, annual tax returns, leave administration, benefits administration, employee termination, final payment reports and other C&B related matters\nProvide strategic advice and assist department head to drive and implement C&B cycles - \u00a0reviewing and enhancing the incentive/bonus scheme, performing the annual salary review, promotion, salary survey, grading structure review, headcount planning and budgeting, etc\nAssist to formulate, review and implement C&B related policies and strategies from time to time\nCompile HR reports on a regular basis for management review\nWork closely with Mainland Headquarter and involve in relevant projects\nPerform ad-hoc projects as assigned\n\nJob Requirements:\n\nDegree holder in Human Resources, Business Administration, or equivalent disciplines\n8-12 years of C&B experience gained from reputable financial institutions with sound experience on working with Mainland headquarter\nFamiliar with labour ordinances or other relevant ordinance and regulatory requirements\nDetailed minded, with good communication and analytical skills\nEnjoy teamwork, responsible and proactive, with pleasant personality\nAble to complete tasks within required time frame and respond effectively under pressure\nExcellent communication in both written and spoken Chinese (Mandarin a MUST) and English\n\nWe offer attractive remuneration and benefits including 5-day working week to the right candidates. Interested parties, please send your full resume including your\u00a0CURRENT\u00a0and\u00a0EXPECTED\u00a0salary to us by email.\u00a0\n\nPersonal data provided will be used by us for recruitment and related purposes, which is strictly in accordance with the Personal Data (Privacy) Ordinance (Cap. 486 of the Laws of Hong Kong) for Applicants for Employment. Applicants who are not contacted within 6 weeks may consider your applications unsuccessful and the personal data collected will be destroyed after 2 years or such other period as prescribed by the applicable laws.\n\n\u6709\u610f\u7533\u8acb\u8005\u8acb \u6309 APPLY NOW\u7533\u8acb\n\n", "employment_types": ["Full Time"], "selling_points": [], "locations": ["Overseas"], "categories": ["Manufacturing", "Manufacturing Management", "Management", "Top Executives (CEO, CFO, CTO, GM, MD etc.)"], "post_time": "2022-01-14T23:46:35Z", "salary": {"currency": null, "max": null, "min": null, "period": "monthly", "term": null}, "salary_visible": false, "title_keywords": ["general manager"], "responsibilities": ["tax", "mpf", "budgeting", "policies", "review", "hr reports", "payment", "planning", "reports", "ad-hoc projects", "payroll", "management review", "administration"], "requirements": {"degrees": ["degree holder"], "majors": ["business administration"], "languages": ["english", "chinese", "mandarin"], "language_level": ["excellent"], "hard_skills": ["analytical skills"], "soft_skills": ["under pressure", "responsible", "teamwork", "analytical skills", "communication", "pleasant", "proactive", "detailed"], "languages_combined": [{"language": "english", "language_level": ["excellent"]}, {"language": "chinese", "language_level": ["excellent"]}, {"language": "mandarin", "language_level": ["excellent"]}]}, "experience_required": {"duration": ["8-12 years"], "field": ["financial institutions"]}}, {"job_id": "100003009034930", "location_code": "hk", "company": "LW Consulting Limited", "job_title": "Executive Director - Hong Kong Developer", "description": "Responsibilities:\nAssist and develop the bank\u2019s FX and general banking services (including Payment, Payroll & Safe Deposit Box etc.), and optimize the product structure in order to maximize the profitability\n\nImplement the measures for FX and general banking services, monitor business progress and complete business target.\n\nAnalysis on the needs and opportunities of different customers segment, cooperate with the latest market conditions to provide appropriate strategic advice to maximize the profitability\n\nMonitor and ensure the products are operated smoothly. Reflect to management as needed\n\nSupport in the formulation of product marketing plan and staff training etc. Cooperate with other relevant departments to carry out marketing activities\n\nFormulating and review the bank risk related policies, risk management policies and procedure in order to control the potential risks. Report to management timely and formulate measures to follow up.\n\nComplete personal performance management standard\n\nHandle ad hoc projects as assigned by management\n\nRequirements:\nDegree holder with major in Business Administration, Finance, Marketing, Statistics, Financial Management and Administration etc\n\nAt least 4 years\u2019 relevant experience (will be adjusted according to the level of application)\n\nCreative thinking, good project management ability and independent analytical mind\n\nExcellent communication and presentation skills\n\nGood command of spoken & written English and Chinese. Proficient in Word, Excel, PowerPoint and Access of MS office\n\nCandidate with more experience will be considered as Senior Manager\n\nWe offer competitive remuneration package and comprehensive fringe benefits including medical and life insurance, and different types of allowances to the right candidate. Interested parties, please submit your application online. For details, please visit our website http://www.bochk.com\n\n[via APPLY NOW]\u00a0\u00a0\n\nData collected would be used for recruitment purposes only. It might also be disclosed to our subsidiaries or Associated Companies to process the information for appointment. Applicants who do not hear from us within 8 weeks may consider their application unsuccessful and their data will be destroyed within 12 months of receipt.", "employment_types": ["Full Time", "Permanent"], "selling_points": ["Leadership position with a stable management", "Friendly and humble corporate culture", "Very attractive remuneration package"], "locations": ["Central & Western Area"], "categories": ["Property / Real Estate", "Others", "Sales, CS & Business Devpt", "Sales - Real Estate", "Management", "Top Executives (CEO, CFO, CTO, GM, MD etc.)"], "post_time": "2022-01-10T04:44:00Z", "salary": {"currency": "HKD", "max": null, "min": 160000, "period": "monthly", "term": null}, "salary_visible": true, "title_keywords": ["developer", "executive director"], "responsibilities": ["management", "control", "policies", "analysis", "review", "monitor", "develop", "marketing plan", "payment", "ad hoc projects", "banking", "payroll", "cooperate with", "report"], "requirements": {"degrees": ["degree holder"], "majors": ["finance", "statistics", "marketing", "business administration"], "languages": ["english", "chinese"], "language_level": ["good command"], "hard_skills": ["excel", "word", "powerpoint", "project management", "ms office"], "soft_skills": ["independent", "communication", "project management", "presentation skills", "analytical mind", "comprehensive", "creative"], "languages_combined": [{"language": "english", "language_level": ["good command"]}, {"language": "chinese", "language_level": ["good command"]}]}, "experience_required": {"duration": ["at least 4 years"], "field": ["relevant experience"]}}, {"job_id": "100003009051718", "location_code": "hk", "company": "Advance Thermo Control Ltd", "job_title": "General Manager", "description": "1. Degree in Manufacturing/ Engineering / Management study\n2. At least 10 years experience in managerial position and electrical appliance industry\n3.\u00a0Monitor all department in the organization including factory, engineering, sales, purchasing and shipping. Especially to assist the Engineering to complete projects in a timely basis.\n4. Develop and implement business plan for profitability\u00a0\n5. Assist in budget preparation and expense management activities.\n6. Evaluate the effectiveness of marketing program and recommend improvements.\n7. Develop strategies to improve overall quality and productivity.\n8. Generate business, cost and employee reports to management.\n9. Schedule regular team meetings to discuss about business updates, issues and suggestions\u00a0\n10. Respond to employee concerns in timely manner.\n11. Provide direction and guidance to employees in their assigned job duties.\n12. Determine staffing requirements and ensure that office positions are filled promptly.\n13. Assist in employee recruitment, training, performance evaluation, promotion and termination.\n14. Manage administrative,logistical, human resources and accounting services to support company operation\n15. Station at China factory mainly and HK office depend on job requirement.\n\n", "employment_types": ["Full Time"], "selling_points": ["Degree in Manufacturing/Engineering/Management", "Medical insurance", "US base company"], "locations": ["Others - China"], "categories": ["Manufacturing", "Manufacturing Management", "Management", "Top Executives (CEO, CFO, CTO, GM, MD etc.)"], "post_time": "2022-01-16T21:51:06Z", "salary": {"currency": null, "max": null, "min": null, "period": "monthly", "term": null}, "salary_visible": false, "title_keywords": ["general manager"], "responsibilities": ["guidance", "management", "shipping", "develop strategies", "cost", "provide direction", "budget", "monitor", "quality", "develop", "evaluate", "reports", "schedule", "recruitment", "evaluation", "business plan"], "requirements": {"degrees": ["degree"], "majors": ["manufacturing", "engineering"], "languages": [], "language_level": [], "hard_skills": [], "soft_skills": ["timely"], "languages_combined": []}, "experience_required": {"duration": ["at least 10 years"], "field": ["managerial"]}}, {"job_id": "100003009056398", "location_code": "hk", "company": "One Media Group Limited", "job_title": "Business Director, Business Solutions", "description": "About the job\n\nThe right candidate is responsible for overseeing the development of a media platform business goals and objectives. The typically work is to increase business revenue, identify and develop business opportunities. Other duties and responsibilities may include establishing effective company policies, goals, and sales targets. Business directors are also expected to negotiate contracts with clients and suppliers and propose and develop new partnerships.", "employment_types": ["Full Time"], "selling_points": [], "locations": ["Not Specified"], "categories": ["Media & Advertising", "Others", "Management", "Top Executives (CEO, CFO, CTO, GM, MD etc.)"], "post_time": "2022-01-18T04:09:26Z", "salary": {"currency": null, "max": null, "min": null, "period": "monthly", "term": null}, "salary_visible": false, "title_keywords": ["director"], "responsibilities": ["business goals", "other duties", "policies", "business opportunities", "contracts", "develop"], "requirements": {"degrees": [], "majors": [], "languages": [], "language_level": [], "hard_skills": [], "soft_skills": ["responsible"], "languages_combined": []}, "experience_required": {"duration": [], "field": []}}, {"job_id": "100003009044900", "location_code": "hk", "company": "Pet-Link Company Limited", "job_title": "Managing Director", "description": "Responsibilities:\n\nWork closely with Directors/CEO, develop strategic annual business plans for Hong Kong, Mainland China and overseas that are aligned to the Company's objectives and directions.\nAct as a strategic partner on daily business, new project development and long-term strategic planning.\nFormulate and execute business operating plans to improve revenues and sustain long term business growth\u00a0\nLead the team at different levels, empower and motivate team members to achieve targets and company goals.\nMonitor and maintain internal control procedures and standards to improve risk management, alert Directors/CEO for any possible crisis in a timely manner.\nResponsible for the overall P&L; cost & expenditure; policy & procedures of the Company\nAny other ad-hoc assignments as assigned.\n\nRequirements:\n\nUniversity graduate in Business Management, Marketing or related discipline\nAt least 20 years of experience in the fields of FMCG industries, with minimum 8 years in senior management level, solid PRC experiences preferred.\nFlexibility and adaptability to face challenges in a growing organization\nExcellent business acumen, ability to convert the business strategy to operational implementation.\nAble to inspire, lead and manage the team to implement business strategies effectively.\nGood spoken and written in English and Mandarin.\nWilling to travel Overseas and PRC subject to the development of Covid-19.\nLess experiences will be considered as Assistant General Manager\n\nCompany website: https://www.pet-link.com\u00a0\u00a0https://eshop.iloverabbit.com/\n\nWe offer competitive salary remuneration package which included year-end KPI bonus, hardworking allowance, medical insurance, dental allowance, 18 days annual leave and staff purchase discount to the successful candidate.\n\nInterested applicants please email your detailed resume indicating your current, expected salary and also date of availability along with your relevant portfolio. Applicants without portfolio will not be considered.\n\n*All information provided will be treated in strict confidential and used only for recruitment purposes.\u00a0", "employment_types": ["Full Time", "Permanent"], "selling_points": [], "locations": ["Tai Po Area"], "categories": ["Management", "General Management", "Top Executives (CEO, CFO, CTO, GM, MD etc.)"], "post_time": "2022-01-13T06:35:06Z", "salary": {"currency": null, "max": null, "min": null, "period": "monthly", "term": null}, "salary_visible": false, "title_keywords": ["director"], "responsibilities": ["achieve targets", "management", "cost", "strategic planning", "ad-hoc assignments", "monitor", "procedures", "business plans", "develop", "a timely manner", "p&l", "maintain", "plans", "internal control"], "requirements": {"degrees": ["university graduate"], "majors": ["business", "marketing"], "languages": ["english", "mandarin"], "language_level": ["good"], "hard_skills": ["business management", "acumen"], "soft_skills": ["business acumen", "adaptability", "hardworking", "detailed"], "languages_combined": [{"language": "english", "language_level": ["good"]}, {"language": "mandarin", "language_level": ["good"]}]}, "experience_required": {"duration": ["minimum 8 years", "at least 20 years"], "field": ["management", "fmcg"]}}, {"job_id": "100003009049313", "location_code": "hk", "company": "China Merchants Securities International Company Limited", "job_title": "Vice President, Compensation & Benefits", "description": "Job Responsibilities\uff1a\n\nManage full spectrum of C&B functions including\u00a0monthly payroll, MPF, overtime allowances, annual tax returns, leave administration, benefits administration, employee termination, final payment reports and other C&B related matters\nProvide strategic advice and assist department head to drive and implement C&B cycles - \u00a0reviewing and enhancing the incentive/bonus scheme, performing the annual salary review, promotion, salary survey, grading structure review, headcount planning and budgeting, etc\nAssist to formulate, review and implement C&B related policies and strategies from time to time\nCompile HR reports on a regular basis for management review\nWork closely with Mainland Headquarter and involve in relevant projects\nPerform ad-hoc projects as assigned\n\nJob Requirements:\n\nDegree holder in Human Resources, Business Administration, or equivalent disciplines\n8-12 years of C&B experience gained from reputable financial institutions with sound experience on working with Mainland headquarter\nFamiliar with labour ordinances or other relevant ordinance and regulatory requirements\nDetailed minded, with good communication and analytical skills\nEnjoy teamwork, responsible and proactive, with pleasant personality\nAble to complete tasks within required time frame and respond effectively under pressure\nExcellent communication in both written and spoken Chinese (Mandarin a MUST) and English\n\nWe offer attractive remuneration and benefits including 5-day working week to the right candidates. Interested parties, please send your full resume including your\u00a0CURRENT\u00a0and\u00a0EXPECTED\u00a0salary to us by email.\u00a0\n\nPersonal data provided will be used by us for recruitment and related purposes, which is strictly in accordance with the Personal Data (Privacy) Ordinance (Cap. 486 of the Laws of Hong Kong) for Applicants for Employment. Applicants who are not contacted within 6 weeks may consider your applications unsuccessful and the personal data collected will be destroyed after 2 years or such other period as prescribed by the applicable laws.\n\n\u6709\u610f\u7533\u8acb\u8005\u8acb \u6309 APPLY NOW\u7533\u8acb\n\n", "employment_types": ["Full Time"], "selling_points": [], "locations": ["Kwun Tong"], "categories": ["Banking / Finance", "Corporate Banking", "Admin & HR", "Compensation & Benefits", "Management", "Top Executives (CEO, CFO, CTO, GM, MD etc.)"], "post_time": "2022-01-14T08:27:35Z", "salary": {"currency": null, "max": null, "min": null, "period": "monthly", "term": null}, "salary_visible": false, "title_keywords": ["vice president"], "responsibilities": ["tax", "mpf", "budgeting", "policies", "review", "hr reports", "payment", "planning", "reports", "ad-hoc projects", "payroll", "management review", "administration"], "requirements": {"degrees": ["degree holder"], "majors": ["business administration"], "languages": ["english", "chinese", "mandarin"], "language_level": ["excellent"], "hard_skills": ["analytical skills"], "soft_skills": ["under pressure", "responsible", "teamwork", "analytical skills", "communication", "pleasant", "proactive", "detailed"], "languages_combined": [{"language": "english", "language_level": ["excellent"]}, {"language": "chinese", "language_level": ["excellent"]}, {"language": "mandarin", "language_level": ["excellent"]}]}, "experience_required": {"duration": ["8-12 years"], "field": ["financial institutions"]}}, {"job_id": "100003009035334", "location_code": "hk", "company": "ACT Company", "job_title": "Relationship Manager \u5ba2\u6236\u95dc\u4fc2\u7d93\u7406 - NOVA Prestige Family Office (50k-120k)", "description": "My client is a well-established Hong Kong Real Estate Developer with three generations of project experience in Hong Kong. Currently they inviting a veteran with extensive experience from Hong Kong real estate developer side to join their Management which has been expanding rapidly in Hong Kong and overseas.\n\nResponsibilities\n\nManage and lead the operation and business development of the Developer\nEvaluate and make recommendation of new potential investment opportunities\nMake recommendations for new development projects, from market positioning, themes, flat mixes to flat sizes, pricing to sales strategy, etc.\nConnect and develop network with other real estate platforms or potential partners on JV projects or deals in Hong Kong or overseas.\nBuild the corporate culture as a leader and an educator.\n\nCore Requirements\n\nAt least 20+ years of experience in the Hong Kong real estate developer side\nStrong experience in managing business development/land acquisition function and sales and marketing function would be a huge advantage\nExtensive network and experience in the Hong Kong real estate market is a must", "employment_types": ["Full Time", "Part Time", "Permanent", "Temporary", "Contract", "Internship", "Freelance"], "selling_points": ["Work with The Rich", "NOVA Prestige Family Office", "50-120k"], "locations": ["Kwun Tong"], "categories": ["Admin & HR", "Administration / Operation Manager", "Professional Services", "Business Consultancy", "Management", "Top Executives (CEO, CFO, CTO, GM, MD etc.)"], "post_time": "2022-01-10T06:51:20Z", "salary": {"currency": "HKD", "max": 89999, "min": 70000, "period": "monthly", "term": null}, "salary_visible": true, "title_keywords": ["\u5ba2\u6236\u95dc\u4fc2\u7d93\u7406", "relationship manager"], "responsibilities": ["evaluate", "make recommendations", "make recommendation", "develop"], "requirements": {"degrees": [], "majors": [], "languages": [], "language_level": [], "hard_skills": [], "soft_skills": ["extensive"], "languages_combined": []}, "experience_required": {"duration": ["at least 20+ years"], "field": ["developer", "business development", "marketing"]}}, {"job_id": "100003009043399", "location_code": "hk", "company": "Manulife (International) Limited", "job_title": "***  Unit Manager / Senior Unit Manager ***", "description": "\u300a\u4e00\u7ad9\u5f0f\u9ad8\u7aef\u5ba2\u6236\u5e73\u53f0\u516c\u53f8\u300b\n\n\u5bcc\u4eba\u8ca1\u6280/\u4fdd\u55ae\u878d\u8cc7/\u5bcc\u4eba\u53d7\u8a17/\u907a\u7522\u7a05/\u5bb6\u65cf\u4fe1\u8a17/\u79c1\u4eba\u9280\u884c\n\n\u5de5\u4f5c\u7bc4\u7587\uff1a\n\n\u516c\u53f8\u505a\u9ad8\u7aef\u5ba2\u6236\u751f\u610f\uff08\u4fdd\u55ae\u878d\u8cc7/\u9ad8\u8cc7\u7522\u589e\u503c/\u907a\u7522\u7a05/\u5bb6\u65cf\u4fe1\u8a17\uff09\n\n\u4e3b\u8981\u5354\u52a9CEO\u65e5\u5e38\u5de5\u4f5c\n\n\u5354\u52a9CEO\u63a5\u898b\u9ad8\u7aef\u5ba2\u6236\n\n\u8ca0\u8cac\u958b\u6236\u53e3/\u5206\u6790\u8cc7\u91d1\u72c0\u6cc1/\u89e3\u91cbproposal\u00a0\u00a0\n\n\u8207\u9ad8\u7aef\u5ba2\u6236\u4fdd\u6301\u806f\u7d61\u00a0\u00a0\n\n\u6587\u4ef6\u8ddf\u9032\n\n\u798f\u5229\uff1a\n\n\u6709\u4f63\u91d1\u5206\uff0c\u82b1\u7d05\n\n\u89c0\u5858\u7532\u7d1a\u5546\u5834\u5beb\u5b57\u6a13\u5de5\u4f5c\n\n\u5730\u65b9\u5bec\u8eba\uff0c\u64c1\u6709\u8212\u9069\u4f11\u606f\u7a7a\u9593\n\nWork with CEO \u6642\u9593\u81ea\u4e3b\n\n\u4e00\u5e74\u53bb\u4e00\u6b21\u4e9e\u6d32\u8207\u6b50\u6d32\uff08\u6a5f\u7968\uff0b\u9152\u5e97)\u00a0\n\n\u8981\u6c42\uff1a\n\n\u80af\u5b78\uff0c\u6709\u8010\u6027\uff01\n\n\u4e2d\u4e94\u7562\u696d\u53ca\u4e94\u79d1\u5408\u683c\n\n\u611b\u6e9d\u901a\uff0c\u4e3b\u52d5\uff0c\u6562\u65bc\u63a5\u53d7\u6311\u6230\n\n\u7d93\u9a57\u4e0d\u62d8\uff0c\u6b61\u8fce\u7562\u696d\u5927\u5b78\u751f\uff0c\u53ea\u8981\u80af\u5b78\n\n*******\u6709\u610f\u8005\u8acb\u7acb\u523b\u9ede\u64caApply Now\u4ee5\u5b89\u6392\u9762\u8a66\u00a0**********", "employment_types": ["Full Time"], "selling_points": ["Succession Planning for Career Development", "Support Work-Life Balance", "Modernized Office & All Round Support"], "locations": ["Kwun Tong"], "categories": ["Banking / Finance", "Retail Banking", "Insurance", "Insurance Agent / Broker", "Management", "Top Executives (CEO, CFO, CTO, GM, MD etc.)"], "post_time": "2022-01-12T11:30:14Z", "salary": {"currency": null, "max": null, "min": null, "period": "monthly", "term": null}, "salary_visible": false, "title_keywords": ["manager"], "responsibilities": [], "requirements": {"degrees": [], "majors": [], "languages": [], "language_level": [], "hard_skills": [], "soft_skills": [], "languages_combined": []}, "experience_required": {"duration": [], "field": []}}, {"job_id": "100003009035264", "location_code": "hk", "company": "Aurex Group Limited", "job_title": "Regional Business/ Product Director (APAC) HK/China", "description": "\u5b8f\u5229\n\nManulife\n\n\u4e0d\u4e00\u6a23\u5de5\u4f5c\u5e73\u53f0\n\n\u6210\u5c31\u66f4\u7cbe\u5f69\u672a\u4f86\n\n\u6b61\u8fce\u540c\u696d\uff0c\u6df1\u5165\u4e86\u89e3\uff0c\u7d55\u5c0d\u4fdd\u5bc6!", "employment_types": ["Full Time"], "selling_points": ["Global Fortune 500 Company", "Business P&L Management (HVAC BU)", "Based in Hong Kong/ Shanghai"], "locations": ["Central"], "categories": ["Management", "Top Executives (CEO, CFO, CTO, GM, MD etc.)"], "post_time": "2022-01-10T06:33:26Z", "salary": {"currency": null, "max": null, "min": null, "period": "monthly", "term": null}, "salary_visible": false, "title_keywords": ["director"], "responsibilities": [], "requirements": {"degrees": [], "majors": [], "languages": [], "language_level": [], "hard_skills": [], "soft_skills": [], "languages_combined": []}, "experience_required": {"duration": [], "field": []}}, {"job_id": "100003009035168", "location_code": "hk", "company": "Manulife (International) Limited", "job_title": "Recruiting Manager \u62db\u52df\u7d93\u7406", "description": "Global Fortune 500 Company\nBusiness/ Product P&L Management (HVAC)\nBased in HK/ China\nOur Client\nOur client is a prominent global industrial leader in the market, with strong presence across Asia, especially in their HVAC solutions offering. They are currently looking for an experienced leader to lead and drive the portfolio to the next level.\n\u00a0\u00a0\nReporting directly to the Regional VP, Asia, the main role of the incumbent is ultimately to be responsible for the overall business P&L and developing the best product and solutions offering in the market to drive further growth for the region.\nCandidate is required to have experience in the HVAC industry ideally.\n\nCandidate Profile\n\nMinimum Degree in Engineering or related field and MBA.\nAt least 12-15 years of working experience; with 5-8 years managing a successful business unit with direct management of team across Asia.\nHaving technical background (within HVAC/ Compressor field) in the early career is an added advantage.\nThe role can be based in Shanghai/ Hong Kong.\n\nWhat to Expect\nThe successful candidate should be looking at the following:\n\nAttractive remuneration package\nMultinational exposure\nGreat benefits and long term career progression\nIf you believe this opportunity is right for you, please send your CV to Vivien Lee by using the \"Apply Now\" button below.\n\u00a0\u00a0\nTo view similar opportunities or express interest in related positions, please visit our website www.aurexgroup.com and follow us on LinkedIn https://lnkd.in/fgAWEBa", "employment_types": ["Full Time"], "selling_points": ["\u64c1\u6709\u62db\u52df / \u5275\u696d\u7d93\u9a57\u512a\u5148", "\u7acb\u5fd7\u6649\u5347\u7ba1\u7406\u968e\u5c64", "\u4ee5\u62db\u52df\u6210\u5c31\u5149\u8f1d\u4e8b\u696d\u3001\u6c38\u7e8c\u7d93\u71df\uff01"], "locations": ["Kwun Tong"], "categories": ["Sales, CS & Business Devpt", "Customer Service - Manager", "Management", "Top Executives (CEO, CFO, CTO, GM, MD etc.)", "Banking / Finance", "Wealth Management"], "post_time": "2022-01-10T06:17:30Z", "salary": {"currency": null, "max": null, "min": null, "period": "monthly", "term": null}, "salary_visible": false, "title_keywords": ["manager"], "responsibilities": ["reporting", "management", "developing", "p&l", "team across"], "requirements": {"degrees": ["degree"], "majors": ["engineering"], "languages": [], "language_level": [], "hard_skills": ["hvac"], "soft_skills": ["responsible"], "languages_combined": []}, "experience_required": {"duration": ["at least 12-15 years"], "field": []}}, {"job_id": "100003009011414", "location_code": "hk", "company": "Office of the Privacy Commissioner for Personal Data", "job_title": "Assistant Privacy Commissioner (a directorate post)", "description": "Job Highlights\n\n\u00b2\u00a0 \u64c1\u6709\u62db\u52df / \u5275\u696d\u7d93\u9a57\u512a\u5148\n\n\u00b2\u00a0 \u7acb\u5fd7\u6649\u5347\u7ba1\u7406\u968e\u5c64\n\n\u00b2\u00a0 \u4ee5\u62db\u52df\u6210\u5c31\u5149\u8f1d\u4e8b\u696d\u3001\u6c38\u7e8c\u7d93\u71df\uff01\n\nJob\u00a0Description\n\n\u6642\u4ee3\u8f49\u8b8a\uff0c\u8fce\u5408\u5e02\u5834\u9700\u6c42\uff0c\u638c\u63e1\u884c\u696d\u5546\u6a5f !\n\n\u5354\u52a9\u767c\u5c55\u591a\u5143\u500b\u4eba\u53ca\u5546\u696d\u751f\u610f !\n\n\u00fc\u00a0\u00a0 \u8207\u5176\u5e6b\u516c\u53f8\u8001\u95c6\u8acb\u4eba\uff0c\u4e0d\u5982\u5e6b\u81ea\u5df1\u8acb\u4eba\uff1f\n\n\u00fc\u00a0\u00a0 \u6709\u60f3\u904e\u6709\u4e00\u500b\u884c\u696d\u662f\u53ef\u4ee5\u900f\u904e\"\u62db\u52df\"\u53bb\u9577\u4e45\u6301\u7e8c\u767c\u5c55\uff1f\n\n\u00fc\u00a0\u00a0 \u7279\u5225\u6b61\u8fce\u540c\u884c\u62db\u52df\u6216\u6709\u7d93\u9a57\u4eba\u58eb\n\n\u00a0Responsibilities\u00a0\n\n\u8ca0\u8cac\u62db\u8058\u3001\u7ba1\u7406\u53ca\u5728\u8077\u57f9\u8a13\n\u5efa\u7acb\u53ca\u7ba1\u7406\u5c08\u696d\u8ca1\u52d9\u7b56\u5283\u5718\u968a\n\u5171\u4eab\u5718\u968a\u71df\u92b7\u7b56\u7565\n\nRequirements\u00a0\n\n\u6301\u5927\u5b78\u5b78\u4f4d /\u5176\u4ed6\u91d1\u878d\u5c08\u696d\u8cc7\u683c\n\u826f\u597d\u5de5\u4f5c\u614b\u5ea6\u3001\u6709\u8cac\u4efb\u611f\n\u5177\u5099\u826f\u597d\u7684\u6e9d\u901a\u5354\u8abf\u80fd\u529b\n\u8f03\u5f37\u7684\u5206\u6790\u80fd\u529b\n\u5177\u826f\u597d\u7684\u5718\u968a\u5408\u4f5c\u7d93\u6b77\u8005\u512a\u5148\n\nBenefits &Others\u00a0\n\n\u5e95\u85aa\uff1a$20000-$38000\n\u62db\u8058\u734e\u91d1 + \u500b\u4eba\u4f63\u91d1 + \u5168\u884c\u7368\u6709\u7121\u9650\u4ee3\u7ba1\u7406\u4f63\u91d1\n\u5c08\u5c6c\u5168\u65b9\u4f4d\u57f9\u8a13 + \u5b8c\u5584\u6649\u5347\u5236\u5ea6\n\u6d77\u5916\u696d\u52d9\u6703\u8b70\n\u696d\u754c\u7ba1\u7406\u69ae\u8b7d\n\u500b\u4eba\u3001\u5718\u968a\u3001\u62db\u8058\u65c5\u884c\u596c\u8cde\n\n\u672a\u4f86\u7684\u60a8\uff0c\u6703\u611f\u8b1d\u4eca\u5929\u7684\u60a8\uff0c\u4e00\u5207\u7531\u884c\u52d5\u958b\u59cb !\n\n\u5546\u6a5f\u7121\u9650\uff0c\u8acb\u5373\u6309Apply Now\u00a0\u7533\u8acb\u9810\u7d04\u9762\u8a66\uff0c\u671f\u5f85\u4f60\u7684\u52a0\u5165\uff01", "employment_types": ["Full Time", "Contract"], "selling_points": ["Solicitor or barrister admitted to practice in HK", "10 years of post-qualification experience", "Proficiency in advocacy and criminal prosecution"], "locations": ["Wan Chai"], "categories": ["Professional Services", "Legal & Compliance", "Management", "Top Executives (CEO, CFO, CTO, GM, MD etc.)", "Public / Civil", "Others"], "post_time": "2022-01-10T16:52:33Z", "salary": {"currency": "HKD", "max": null, "min": 120000, "period": "monthly", "term": null}, "salary_visible": true, "title_keywords": ["assistant"], "responsibilities": [], "requirements": {"degrees": [], "majors": [], "languages": [], "language_level": [], "hard_skills": [], "soft_skills": [], "languages_combined": []}, "experience_required": {"duration": [], "field": []}}, {"job_id": "100003009031514", "location_code": "hk", "company": "South China Holdings Company Limited", "job_title": "Tax Manager", "description": "A prestigious new opportunity in Hong Kong for anyone who wants to elevate their career path to the next level. Our client, a fast-growing\u00a0 international transportation business,\u00a0is looking to appoint an experienced Chief Corporate Quality Manager for their mainland China and international business. If you\u2019re looking for career move with a highly reputed global employer, head-quartered in Hong Kong,\u00a0this could be the job for you?\u00a0\n\nProject Details\n\nYou\u2019ll be based in one of the client\u2019s head offices in Hong Kong.\u00a0\n\nResponsibilities and Duties\nLead a team of Quality Assurance\u00a0professionals to deliver Second Line of Defence Programme for the management of operational risks outside Hong Kong\nTranslate and implement the Corporate Quality Strategy and Programmes inclusive of communication and coordination with subsidiaries and affiliates worldwide in the management of operational risk\nProvide recommendations for waste removal and continuous improvement using Lean and Quality methodologies\nLead risk-based audits, assurance reviews and investigations, and provide recommendations to senior management\nEnsure effective utilisation of the assurance database in support of quality assurance activity\nDrive and formulate Quality Assurance governance framework according to best practices as well as the Client's requirements\nInitiate and execute programmes to nurture a culture of continuous improvement and promote quality awareness\nEffective resource planning to ensure second line of defence\u00a0Quality Assurance management and support\nOccasional international\u00a0travel will be required\u00a0\nDesired Skills and Experience\nDegree in Engineering / Project Management or a related discipline\nPossession of Corporate Membership / Qualifications of a recognised professional institution in Quality / Auditing\nA minimum of 15 years\u2019 relevant experience, preferably gained in transportation industry or large-scale railway and infrastructure construction projects, of which 8 years should be at managerial level\nExtensive experience in strategic planning and implementation of governance frameworks with solid knowledge of internal controls, risk management, business assurance systems and assurance databases\nProven leadership and project management capabilities with excellent interpersonal, communication and report writing skills.\nExcellent command of both written and spoken English and Putonghua\nQualifications/Educational Requirements\nDegree in a related / technical discipline\nPossession of Corporate Membership of an internationally recognised professional institution in Quality and / or professional auditing qualifications\nEmploying Company Overview and Profile\n\nOur client is a major public transport network in Hong Kong partially privatised in 2000. It is one of the most exciting construction, engineering and operating\u00a0companies in Hong Kong with one of the largest shareholder base in the area and is quickly expanding internationally. Their main goal is to offer innovative and sustainable services to cities all over the world. If you\u2019re looking for a new challenging opportunity in the construction sector and a dynamic fast-growing company with a lot of career options, this could be the right fit for you.\n\nApply for this job", "employment_types": ["Full Time", "Permanent"], "selling_points": ["PRC/HK tax management", "Lead major tax planning projects", "M&A activities including tax structuring"], "locations": ["Central"], "categories": ["Accounting", "Taxation", "Management", "General Management", "Top Executives (CEO, CFO, CTO, GM, MD etc.)"], "post_time": "2022-01-07T09:24:17Z", "salary": {"currency": null, "max": null, "min": null, "period": "monthly", "term": null}, "salary_visible": false, "title_keywords": ["manager"], "responsibilities": ["management", "strategic planning", "coordination with", "quality", "infrastructure", "implementation", "systems", "communication", "lead a team", "project management", "provide recommendations", "database", "databases", "audits", "report", "senior management", "auditing", "planning"], "requirements": {"degrees": ["degree"], "majors": [], "languages": [], "language_level": [], "hard_skills": ["goal", "dynamic"], "soft_skills": ["dynamic", "innovative"], "languages_combined": []}, "experience_required": {"duration": [], "field": []}}, {"job_id": "100003009031944", "location_code": "hk", "company": "C-Mer Eye Care Holdings Limited", "job_title": "COO - Medical Group", "description": "Job Responsibilities:\n\nPRC and HK\u00a0 tax management of the Company and/ or its affiliates (\"the Group\")\nLead major tax planning projects to improve the overall tax efficiency of the Group\nOversee the overall tax compliance profile of the Group including tax return filings, tax payments and tax disputes etc\nProvide\u00a0 tax advice to internal business partners on operational matters in PRC and HK (e.g. new business models, sales and procurement contracts etc.)\nDesign and implement PRC/HK\u00a0 tax policies and strategies, and inter-company transfer pricing arrangements\nProvide tax related support for M&A activities, including tax structuring and tax due diligence etc.\nManage the tax accounting matters for the Group\nWork closely with external tax advisers and overseas colleagues on PRC/HK\u00a0 tax matters\n\nJob Requirements:\n\nQualified Accountant under ACCA/HKICPA or equivalent ,with a Bachelor Degree in Accounting or Business related disciplines\nMinimum 7 years of solid professional experience in corporate taxation at managerial grade in Big 4 Accounting firm\nGood tax accounting knowledge, experience with regional corporate tax and indirect tax.\u00a0\nSound knowledge of China and HK tax law and practice.\nExcellent analytical and problem solving skills, strong tax technical and research skills\nWilling to work under tight timeline and high pressure\nStrong interpersonal skills and able to drive cross-department projects\nProficiency in MS Office application with strong proficiency in MS Excel\nGood command in both spoken Chinese and English. fluency in Mandarin will be an advantage\nOccasional travel to PRC\u00a0\n\n\u00a0We offer attractive package and good career development for right candidate.\u00a0", "employment_types": ["Full Time"], "selling_points": ["Build & execute on the operational Strategy", "Responsible for the clinical operation procedures", "8+ years\u2019 experience in the healthcare industry"], "locations": ["Central"], "categories": ["Professional Services", "Business Consultancy", "Management", "Top Executives (CEO, CFO, CTO, GM, MD etc.)"], "post_time": "2022-01-07T10:00:30Z", "salary": {"currency": null, "max": null, "min": null, "period": "monthly", "term": null}, "salary_visible": false, "title_keywords": [], "responsibilities": ["tax", "due diligence", "management", "contracts", "policies", "compliance", "design", "payments", "tax matters", "operational matters", "planning"], "requirements": {"degrees": ["degree", "bachelor"], "majors": ["business", "related disciplines", "accounting"], "languages": ["english", "chinese", "mandarin"], "language_level": ["fluency", "advantage", "good command"], "hard_skills": ["acca", "hkicpa", "ms excel", "problem solving skills", "ms office"], "soft_skills": ["analytical and problem solving skills", "interpersonal skills", "research skills"], "languages_combined": [{"language": "english", "language_level": ["good command"]}, {"language": "chinese", "language_level": ["good command"]}, {"language": "mandarin", "language_level": ["fluency", "advantage"]}]}, "experience_required": {"duration": ["minimum 7 years"], "field": ["managerial", "accounting", "big 4"]}}, {"job_id": "100003009035476", "location_code": "hk", "company": "Wai Chun Strategic Investment Limited", "job_title": "Financial Manager \u8ca1\u52d9\u7d93\u7406", "description": "Job Duties:\n\n\nReporting directly to the CEO to design and implement business strategies, plans and procedures\nOversee the daily operations of the clinics\nResponsible for formulation, implementation, and review of standard of the clinical operation procedures\nResolve problems related to staffing, utilization of facilities, equipment, and supplies\nEstablish policies that promote company culture and vision\n\nRequirements:\n\nBachelor\u2019s degree or above in relevant disciplines\n8+ years\u2019 experience in\u00a0the\u00a0healthcare industry will be preferable\nExcellent people management with strong interpersonal, coaching and\u00a0problem-solving skills\nAble to work with various people in different capacities and good at\u00a0collaboration\nGood command of spoken and written English, Chinese and Mandarin\n\nBenefits:\n\n5-day work per week\nMedical insurance\nAnnual leave\nAnnual discretionary bonus\nSpecial offer of eye treatment for staff and family", "employment_types": ["Full Time", "Permanent"], "selling_points": ["Finance Manager", "Occasional travel to China is required", "Min 3 years\u2019 serving as Accounting Manager"], "locations": ["Admiralty"], "categories": ["Accounting", "Chief Accountant", "Financial Controller", "Management", "Top Executives (CEO, CFO, CTO, GM, MD etc.)"], "post_time": "2022-01-10T07:20:34Z", "salary": {"currency": null, "max": null, "min": null, "period": "monthly", "term": null}, "salary_visible": false, "title_keywords": ["financial manager"], "responsibilities": ["reporting", "policies", "oversee the daily operations", "review", "procedures", "implementation", "design", "plans"], "requirements": {"degrees": ["degree or above", "bachelor"], "majors": [], "languages": ["english", "chinese", "mandarin"], "language_level": ["good command"], "hard_skills": ["problem-solving skills"], "soft_skills": ["problem-solving skills", "interpersonal"], "languages_combined": [{"language": "english", "language_level": ["good command"]}, {"language": "chinese", "language_level": ["good command"]}, {"language": "mandarin", "language_level": ["good command"]}]}, "experience_required": {"duration": ["8+ years"], "field": ["healthcare industry"]}}, {"job_id": "100003009021212", "location_code": "hk", "company": "Darton Ltd", "job_title": "General Manager (Fine Jewelry)", "description": "Reporting to the Chairman and the Board,\u00a0the appointee will lead the group financial functions covering all lines of business in Hong Kong and PRC, and fulfill compliance and company secretary functions.\u00a0\n\nQualifications:\n\nUniversity degree in Accounting with HKICPA/ACCA or equivalent professional qualifications\nOver 8 years of solid experience in budgetary control, financial planning and business partnering plus not less than 3 years\u2019 experience serving as Accounting Manager or above.\nFinance management experience gained from listed companies and sizable multinational corporation preferred\nStrong in evaluating business processes, driving and implementing strategic changes\nSelf-driven, charismatic, confident and project management skills\nExcellent communication and presentation skills\n\nResponsibilities:\n\nCoverage all the accounting and financial management matters of China and Hong Kong business\nExperience in handling joint ventures\nManage the production of the monthly management accounts and report providing value-added analysis and operational performance;\nCash management and related matters;\nOversee all financial compliance matters and regulators in jurisdictions where the group operates;\nResponsible for financial planning, treasury management, investment evaluations, and strategic business planning\n\nLocation: Admiralty\u00a0\n\nWe offer an attractive remuneration package and excellent career prospects to the right candidate.\u00a0\u00a0Please send full resume (Chinese version is a must), current and expected salary, contact number\u00a0and the availability to our e-mail address by clicking \"Apply Now\" for interview.\n\nPersonal data collected will be used for recruitment purpose only.\n\n\u8077\u8cac:\n\n\u8ca0\u8cac\u6240\u6709\u4e2d\u570b\u5927\u9678\u548c\u9999\u6e2f\u696d\u52d9\u7684\u8ca1\u52d9\u7ba1\u7406\u4e8b\u9805\uff1b\n\u8655\u7406\u5408\u8cc7\u4f01\u696d\u7d93\u9a57\uff1b\n\u7ba1\u7406\u6bcf\u6708\u7d9c\u5408\u7ba1\u7406\u8cec\u76ee\u548c\u5831\u544a\uff0c\u63d0\u4f9b\u589e\u503c\u7684\u5206\u6790\u548c\u71df\u904b\u5831\u544a\n\u73fe\u91d1\u7ba1\u7406\u53ca\u76f8\u95dc\u4e8b\u5b9c\uff1b\n\u76e3\u7763\u6240\u6709\u8ca1\u52d9\u5408\u898f\u4e8b\u5b9c\u548c\u53f8\u6cd5\u7ba1\u8f44\u5340\u4e2d\u7684\u76e3\u7ba1\u6a5f\u69cb\uff1b\n\u8ca0\u8cac\u8ca1\u52d9\u898f\u5283\uff0c\u8cc7\u91d1\u7ba1\u7406\uff0c\u6295\u8cc7\u8a55\u4f30\u548c\u4f01\u696d\u6230\u7565\u898f\u5283\u3002\n\n\u8cc7\u683c:\n\n\u5927\u5b78\u5b78\u4f4d\uff0c\u4e3b\u4fee\u6703\u8a08 , \u9999\u6e2f\u6703\u8a08\u5e2b\u516c\u6703\u6216\u570b\u969b\u5c08\u696d\u6703\u8a08\u7d44\u7e54\u6216\u540c\u7b49\u5c08\u696d\uff1b\n8\u5e74\u6216\u4ee5\u4e0a\u9810\u7b97\u63a7\u5236\uff0c\u8ca1\u52d9\u898f\u5283\u548c\u696d\u52d9\u5408\u4f5c\u7d93\u9a57\uff0c\u4ee5\u53ca\u4e0d\u5c11\u65bc3\u5e74\u6703\u8a08\u7d93\u7406\u7d1a\u6216\u4ee5\u4e0a\u7d93\u9a57\uff1b\n\u64c1\u6709\u4e0a\u5e02\u516c\u53f8\u548c\u5927\u578b\u8de8\u570b\u516c\u53f8\u8ca1\u52d9\u7ba1\u7406\u7d93\u9a57\u8005\u512a\u5148\uff1b\n\u5584\u65bc\u8a55\u4f30\u696d\u52d9\u6d41\u7a0b\uff0c\u63a8\u52d5\u548c\u5be6\u65bd\u6230\u7565\u8b8a\u9769\uff1b\n\u4e3b\u52d5\uff0c\u6709\u9b44\u529b\uff0c\u81ea\u4fe1\u548c\u9805\u76ee\u7ba1\u7406\u6280\u80fd\uff1b\n\u826f\u597d\u7684\u6e9d\u901a\u548c\u8868\u9054\u80fd\u529b\u3002\n\n\u5de5\u4f5c\u5730\u9ede: \u91d1\u9418\n\n\n\u6211\u5011\u63d0\u4f9b\u4e86\u4e00\u500b\u53ef\u89c0\u7684\u85aa\u916c\u798f\u5229\u548c\u826f\u597d\u7684\u8077\u696d\u524d\u666f\u7d66\u5408\u9069\u7684\u4eba\u9078\u3002\u8acb\u5c07\u500b\u4eba\u7c21\u6b77(\u5fc5\u9808\u4e2d\u6587\u7c21\u6b77)\uff0c\u76ee\u524d\u53ca\u671f\u671b\u85aa\u91d1\uff0c\u806f\u7d61\u96fb\u8a71\u548c\u5230\u8077\u65e5\u671f\u96fb\u90f5\u7d66\u6211\u53f8\u3002\n\n\u6536\u96c6\u7684\u500b\u4eba\u8cc7\u8a0a\u5c07\u50c5\u7528\u65bc\u62db\u8058\u7528\u9014\u3002", "employment_types": ["Full Time"], "selling_points": [], "locations": ["Central"], "categories": ["Manufacturing", "Jewelry", "Management", "Top Executives (CEO, CFO, CTO, GM, MD etc.)"], "post_time": "2022-01-05T03:19:22Z", "salary": {"currency": null, "max": null, "min": null, "period": "monthly", "term": null}, "salary_visible": false, "title_keywords": ["general manager"], "responsibilities": ["reporting", "control", "management", "analysis", "compliance", "communication", "project management", "report", "planning"], "requirements": {"degrees": ["university degree"], "majors": ["accounting"], "languages": [], "language_level": [], "hard_skills": ["acca", "plus", "professional qualifications", "analysis", "project management", "hkicpa"], "soft_skills": ["confident", "responsible", "project management skills", "communication", "presentation skills", "driven"], "languages_combined": []}, "experience_required": {"duration": ["3 years", "8 years"], "field": ["management", "financial", "finance", "business", "accounting", "planning"]}}, {"job_id": "100003009031518", "location_code": "hk", "company": "South China Holdings Company Limited", "job_title": "Financial Controller (Frequent Travel to PRC)", "description": "\nSouth China Group is a conglomerate (comprised of 3 listed companies in Hong Kong), having a wide range of businesses, including property development and investment, trading and manufacturing, agriculture and forestry, financial services, information technology and media publishing etc..\n\nJob Description\n\n\u2022 Responsible for financial reporting, planning, forecast, cost control, budgeting of the business units in the PRC.\n\u2022 Provide recommendations to strategically enhance financial performance and business opportunities.\nRequirement\n\u2022 Degree holder in Accounting/Finance, associate or fellow member of ACCA/HKICPA\n\u2022 Minimum 7 years\u2019 solid financial experience in the PRC\n\u2022 Good experience in cost control\n\u2022 Excellent analytical and problem solving skills and ability to exercise sound judgment based on accurate and timely analysis\n\u2022 Strong business sense, able to work under pressure and strong adaptability\n\u2022 Proficiency in both spoken and written English and Chinese, particularly Mandarin\n\u2022 PRC exposure in Leasing/Property Development is preferable\nFrequent travel to PRC ( Nanjing/Tianjin/Shenyang )\n\nAll applications applied through our system will be delivered directly to the advertiser and privacy of personal data of the applicant will be ensured with security.", "employment_types": ["Full Time"], "selling_points": ["Frequent travel to PRC", "Min. 7 years\u2019solid financial experience", "Excellent analytical and problem solving skills"], "locations": ["Central"], "categories": ["Accounting", "Financial Controller", "Management", "General Management", "Top Executives (CEO, CFO, CTO, GM, MD etc.)"], "post_time": "2022-01-07T09:24:28Z", "salary": {"currency": null, "max": null, "min": null, "period": "monthly", "term": null}, "salary_visible": false, "title_keywords": ["financial controller"], "responsibilities": ["budgeting", "business opportunities", "provide recommendations", "financial reporting", "cost control", "forecast", "planning"], "requirements": {"degrees": ["degree holder"], "majors": ["finance", "accounting"], "languages": ["english", "chinese", "mandarin"], "language_level": ["proficiency"], "hard_skills": ["acca", "analysis", "problem solving skills", "hkicpa"], "soft_skills": ["business sense", "timely", "analytical and problem solving skills", "adaptability", "accurate", "work under pressure"], "languages_combined": [{"language": "english", "language_level": ["proficiency"]}, {"language": "chinese", "language_level": ["proficiency"]}, {"language": "mandarin", "language_level": ["proficiency"]}]}, "experience_required": {"duration": ["minimum 7 years"], "field": ["financial"]}}, {"job_id": "100003009024697", "location_code": "hk", "company": "Wharf Hotels Management Limited", "job_title": "Group Director Learning and Development - Corporate Office", "description": "A Fine Jewelry Company is part of the Darton Group that located in Central.\u00a0 We are looking for a General Manager who leads the business team to develop and further expand the business in the international region.\n\nJob Description\n\nResponsible for driving integrated business, sales planning and business development as well as leading a team to develop.\nManage the sourcing plan and execute the purchasing process with suppliers.\nConduct a comprehensive management of procurement, production and marketing operations.\nCoordinate the company's product sales & marketing management, and expand the company's sales channel resources.\nResponsible for the preparation, presentation and subsequent achievement of the annual operating budget, marketing and sales plan and capital budget.\nManager P&L and provide strategies to drive the sales.\nPerform other responsibilities and participate in projects assigned by Senior Management to drive company's vision and strategy.\nRequirements\nDegree holder in Business Administration, Marketing, or related discipline.\nMinimum 10 years' related work experience in brand and Luxury industry with minimum 5 years' work experience in managerial level; experience in Luxury Jewelry is highly preferable.\nAgile, aggressive, result-oriented, data driven with strong interpersonal and communication skills.\nExcellent communication skills and fluency in both spoken and written in English and Chinese.\nExcellent communicator and enjoys a small team environment.\nInterested candidates, please send your most updated CV, latest and expected salary\u00a0 package by clicking \"Apply Now\" button.", "employment_types": ["Full Time"], "selling_points": [], "locations": ["Tsim Sha Tsui"], "categories": ["Management", "General Management", "Admin & HR", "HR Director / Manager", "Top Executives (CEO, CFO, CTO, GM, MD etc.)"], "post_time": "2022-01-06T02:14:38Z", "salary": {"currency": null, "max": null, "min": null, "period": "monthly", "term": null}, "salary_visible": false, "title_keywords": ["director"], "responsibilities": ["management", "operations", "budget", "p&l", "develop", "coordinate", "plan", "senior management", "planning"], "requirements": {"degrees": ["degree holder"], "majors": ["marketing", "business administration"], "languages": ["english", "chinese"], "language_level": ["fluency", "excellent"], "hard_skills": ["small", "luxury industry", "agile"], "soft_skills": ["communication skills", "agile", "driven", "communicator", "interpersonal", "result-oriented"], "languages_combined": [{"language": "english", "language_level": ["fluency", "excellent"]}, {"language": "chinese", "language_level": ["fluency", "excellent"]}]}, "experience_required": {"duration": ["minimum 10 years", "minimum 5 years"], "field": ["related", "managerial", "brand"]}}, {"job_id": "100003009022958", "location_code": "hk", "company": "WilliamSELECT", "job_title": "COO - 3Cs Product", "description": "My client is a start-up company headquartered in the United States. The company specialized in R&D, manufacturing industrial material, supplying to 3Cs and EV companies. To cope with their expansion, they are looking for a Managing Director in Hong Kong/ China to manage their business portfolio globally. The Managing Director will spreadhead business development, sales & marketing and daily operations.\n\nResponsibilities:\n\nManage the P&L and grow the business lines\nBeing one of the board members to develop business strategy and plan, to align with long term and short term objectives with overall strategy and mission\nLead and manage the team to develop a high performing managerial team\nDesign and establish necessary framework and operating principles\nDevelop solutions or improvements based on the analysis results\nMaintain close and trust relationships with global customers in 3Cs and EV sector, stakeholders and partners\nStay informed about the current situation in the markets and industry of the company\n\nRequirement\n\nOver 15 years of experience in material science / industrial application in with at least 8 years in working senior managerial position\nExperienced working with International 3Cs & EV companies would be an advantage\nProfound experience in developing profitable strategies and implementing vision\nGood experience with diverse business functions such as business development, marketing, finance etc.\nExcellent leadership & skills and strong communication skills\nStrong analytical abilities and problem-solving skills with an entrepreneurial mindset\nFluent in English and Chinese is a MUST", "employment_types": ["Full Time"], "selling_points": ["US Start Up Company- R&D, mfg industrial material", "BD, Sales & Marketing, Daily Ops", "15+ yrs in material science/industrial application"], "locations": ["Overseas"], "categories": ["Management", "Top Executives (CEO, CFO, CTO, GM, MD etc.)"], "post_time": "2022-01-05T06:59:01Z", "salary": {"currency": null, "max": null, "min": null, "period": "monthly", "term": null}, "salary_visible": false, "title_keywords": [], "responsibilities": ["analysis", "design", "p&l", "develop", "maintain", "plan"], "requirements": {"degrees": [], "majors": [], "languages": ["english", "chinese"], "language_level": ["fluent"], "hard_skills": ["problem-solving skills"], "soft_skills": ["communication skills", "diverse", "problem-solving skills", "leadership"], "languages_combined": [{"language": "english", "language_level": ["fluent"]}, {"language": "chinese", "language_level": ["fluent"]}]}, "experience_required": {"duration": ["at least 8 years", "15 years"], "field": ["managerial", "finance", "business development", "developing", "business", "marketing"]}}, {"job_id": "100003009024873", "location_code": "hk", "company": "Grandeur International Limited", "job_title": "Project Manager Assistant\u2013 Business Development", "description": "Overview\n\n\u00a0Talent Spot is a one-stop professional staffing and HR solutions provider based in the Asia Pacific region including China, Hong Kong, Taiwan, Singapore, Malaysia, Japan, Korea, Thailand, Vietnam with representative offices in US & Europe.\n\nTalent Spot provides HR solutions such as staffing, direct hire, temp to hire, executive search & selection recruitment process outsourcing, on-site managed recruitment, payroll outsourcing, business process outsourcing, company formation, offshore outsourcing to various industries and companies across Asia Pacific Region.\n\nAwards: Best HR Services Provider in Greater China\n\nBest One-Stop Recruitment Solutions Provider\n\nWe are seeking experienced candidates at different levels to join our teams as specialised recruiters for delivery of recruitment and search services to our clients.\n\nResponsibilities\n\n\nReporting to the Managing Director based in Hong Kong, you will be a core member of our client services team and responsible for managing the end-to-end recruitment process by matching the right talents to the right role for our Clients\n\nEstablishing a robust pipeline of clients & talents in your focus areas and building lasting partnerships with clients\nObtain thorough understanding of clients\u2019 organisation, culture and requirements to ensure that only qualified candidates are presented\nDeliver end to end recruitment process from preparation of long list, candidate interviews and presentation of shortlist, co-ordinate interviews, facilitate the offer discussion and follow up for onboarding\nPerform market research and talent mapping, source candidates through internal database and multiple online platforms. Headhunt and direct approach target candidates.\nSupport business development and marketing activities\nPerform various tasks relating to the above including writing and posting job ads, updating candidate records on database, preparing meeting notes and ensuring compliance with firm standard on client engagements\n\nRequirements\n\nUniversity graduate with at least 5 years of experience in recruitment, ideally gained from recruitment agency\n\n\nRecruitment experience in financial services and technology sector is preferred\nPossess a disciplined and organised work approach\nResults-driven and passionate in building positive and long-term relationship with clients, candidates and colleagues through quality services and deliverables\nExcellent communication and presentation skills. Proficient in both spoken and written English and Chinese (Mandarin and Cantonese).\nThose with less experience can be considered for Consultant roles.\n\n\nWe offer successful candidates the opportunity to work in a dynamic and exciting environment.\u00a0 Our remuneration package is attractive, 5-day work, and other benefits\n\nPersonal data collected will be used for recruitment purposes.\n", "employment_types": ["Full Time"], "selling_points": [], "locations": ["Central"], "categories": ["Management", "Top Executives (CEO, CFO, CTO, GM, MD etc.)"], "post_time": "2022-01-06T02:48:34Z", "salary": {"currency": null, "max": null, "min": null, "period": "monthly", "term": null}, "salary_visible": false, "title_keywords": ["project manager", "assistant"], "responsibilities": ["reporting", "compliance", "market research", "database", "recruitment process"], "requirements": {"degrees": ["university graduate"], "majors": [], "languages": ["cantonese", "english", "chinese", "mandarin"], "language_level": ["proficient"], "hard_skills": [], "soft_skills": ["passionate", "communication", "presentation skills", "organised", "driven", "positive"], "languages_combined": [{"language": "cantonese", "language_level": []}, {"language": "english", "language_level": ["proficient"]}, {"language": "chinese", "language_level": ["proficient"]}, {"language": "mandarin", "language_level": []}]}, "experience_required": {"duration": ["at least 5 years"], "field": ["agency", "financial services", "recruitment"]}}, {"job_id": "100003009018944", "location_code": "hk", "company": "CNB Express Talent-Spot Asia Limited", "job_title": "Senior Regional Consultant/Senior Recruiter", "description": "Wharf Hotels is Hong Kong\u2019s heritage hotel management company, an Asian corporation recognizing diverse cultures that celebrates The Spirit of Discovery. Formerly known as Marco Polo Hotels Management Limited, Wharf Hotels is a wholly owned subsidiary of The Wharf (Holdings) Limited, operating luxury and premium brands Niccolo and Marco Polo Hotels across Asia.\n\nWe are currently seeking a\u00a0Group Director Learning and Development\u00a0at the Corporate Office located in Hong Kong.\n\nActing as the talent advisor for Wharf Hotels, this role is responsible for creating the people development strategies that will ensure that all staff have the skills, knowledge and development opportunities required to help the organisation achieve its vision and mission. The role will lead the L&D function in providing a professional, proactive service, delivering L&D, solutions at all levels across the organisation. The role is responsible for measuring and evaluating the ROI on training for the business ensuring we are compliant and capable. Assisting Vice President Human Resources, the incumbent will leverage our values and brand insights to ensure effective Talent Resources Management.\n\nThe Group Director Learning and Development will be required to manage the talent landscape in Hong Kong, Greater China and the Philippines. The candidate will be responsible including but not limited to:\n\nFormulate the organizational learning infrastructure to drive talent development and succession plan in corporate office and properties\nMonitor, coach and guide the property Learning & Development Leaders to execute the training initiatives effectively\nDesign, curate and facilitate the corporate learning programs to enhance leadership competencies and service gaps\nDrive digital learning platform as part of the overall Digital Transformation Strategy\nInnovate and manage the robust career tracks to build talent profiles for talent pipeline\nForge robust institutional partnerships to maintain the successful reputation that attracts both local and international interns and trainees\nLead the annual performance appraisal exercise in corporate office and properties\nPromote internal mobility by refining the programs of internal transfers and taskforce for cross-properties exposure\nCoordinate all compliance training to ensure employees are familiar with the local legislations and frameworks\nKeep abreast with the latest leadership and change development trends and methodologies with various training organizations, consultants, tertiary institutions, etc.\n\nYour Skills:\n\nA Degree with a major in Training and Human Resources Development or related discipline\nMinimum 10 years of training and development experience in a managerial capacity in hotel or service related industry\nExperience in managing multi-property training initiatives, with Corporate level training & development experience is an advantage\nPassionate in curriculum design and proficient in engaging learning e-tool\nStrong project management and organizational skills to multi-task efficiently\nHighly analytical and strong facilitation, organizational and influencing skills\nFluent in English, Mandarin and Cantonese. Proficient in English business writing\nAbility to work and interact with Associates at all levels\nAbility to drive changes and achieve results in a fast-paced environment\n\nYou are:\n\nPassionate about developing talent for our industry\nPositive, energetic and highly self-motivated\nExcellent interpersonal and communication skills\nWilling to travel regularly\nMeticulous and precise\nWilling to travel (10-15%)\n\nWe offer excellent career development opportunities. If you are interested in the position, please apply with your full resume and expected salary to the link below. Only shortlisted candidates will be contacted.\n\nTo learn more about Wharf Hotels, please visit our website\u00a0[via APPLY NOW]\u00a0\u00a0\n\nEqual opportunities are extended to all candidates and the information provided will be used for the consideration of your application in the hotel group. All personal data collected will be for recruitment purposes only. If you do not hear from us within six weeks of your application, you may consider your application unsuccessful at which time your personal data will be deleted accordingly.\n\n\u6709\u610f\u7533\u8acb\u8005\u8acb \u6309 APPLY NOW\u7533\u8acb\u00a0", "employment_types": ["Full Time"], "selling_points": ["Executive Search & Selection experience", "Strong industry expertise", "Hardworking and proactive"], "locations": ["Central"], "categories": ["Admin & HR", "Recruitment / Executive Search", "Management", "Top Executives (CEO, CFO, CTO, GM, MD etc.)"], "post_time": "2022-01-04T06:41:50Z", "salary": {"currency": null, "max": null, "min": null, "period": "monthly", "term": null}, "salary_visible": false, "title_keywords": ["consultant"], "responsibilities": ["management", "infrastructure", "monitor", "compliance", "design", "developing", "coordinate", "project management", "communication", "maintain", "plan", "legislations"], "requirements": {"degrees": ["degree"], "majors": [], "languages": ["cantonese", "english", "mandarin"], "language_level": ["proficient", "fluent"], "hard_skills": ["project management", "marco"], "soft_skills": ["organizational skills", "capable", "fast-paced environment", "leadership", "mobility", "passionate about", "robust", "diverse", "interpersonal", "passionate", "communication skills", "precise", "energetic", "positive", "meticulous", "self-motivated", "multi-task", "responsible", "organizational", "project management", "learning", "organisation", "proactive"], "languages_combined": [{"language": "cantonese", "language_level": ["fluent"]}, {"language": "english", "language_level": ["proficient", "fluent"]}, {"language": "mandarin", "language_level": ["fluent"]}]}, "experience_required": {"duration": ["minimum 10 years"], "field": ["related", "development", "training", "managerial"]}}, {"job_id": "100003009016514", "location_code": "hk", "company": "Aurex Group Limited", "job_title": "Managing Director, South China Real Estate Services", "description": "Job responsibilities:\n\nlAll-rounded management and coordination of projects across different sectors (e.g. infrastructure, education, financial services & etc.)\n\nlDevelop PPT, research reports, letters, meeting minutes and all paperwork\n\nlTranslation of documents, as well as verbal instant translation when necessary (English & Mandarin)\n\nlConduct industry/ company analysis and research on relevant laws, guidelines and regulations\n\nlCommunicate and maintain excellent relationships with both internal and external parties, including government officials in Hong Kong, China and overseas\n\nlBusiness travel is required\n\nRequirements:\n\nlDegree holder with minimum 5+ years of experience in business development and market research\n\nlHigh proficiency in MS Office, especially PowerPoint and Chinese word processing\n\nlExcellent in both written and spoken English, Cantonese and Mandarin\n\nlFlexible and willing to work outside regular hours when required\n\nlProactive, result-oriented with excellent communication skills\n\nlImmediate available is preferred\n\nlCandidates with less experience will be considered as Project Assistant", "employment_types": ["Full Time"], "selling_points": ["Leading Property Services Firm", "Based in Shenzhen OR Guangzhou", "Must have Property related experience"], "locations": ["Others - China"], "categories": ["Property / Real Estate", "Property Consultancy", "Property Management", "Management", "Top Executives (CEO, CFO, CTO, GM, MD etc.)"], "post_time": "2022-01-03T09:16:00Z", "salary": {"currency": null, "max": null, "min": null, "period": "monthly", "term": null}, "salary_visible": false, "title_keywords": ["director"], "responsibilities": ["regulations", "management", "guidelines", "analysis", "infrastructure", "letters", "internal and external parties", "maintain", "reports", "coordination"], "requirements": {"degrees": [], "majors": [], "languages": ["cantonese", "english", "chinese", "mandarin"], "language_level": ["proficiency"], "hard_skills": ["chinese word processing", "powerpoint", "ms office"], "soft_skills": ["communication skills", "result-oriented"], "languages_combined": [{"language": "cantonese", "language_level": []}, {"language": "english", "language_level": []}, {"language": "chinese", "language_level": ["proficiency"]}, {"language": "mandarin", "language_level": []}]}, "experience_required": {"duration": ["minimum 5+ years"], "field": ["business development", "market research"]}}, {"job_id": "100003009011555", "location_code": "hk", "company": "Clothing Industry Training Authority", "job_title": "Executive Director", "description": "Leading Property Firm\nBased in Shenzhen OR Guangzhou\nMust have property related experience\nAurex Group (formerly Capstone Recruitment) is working with a leading, global real estate services firm delivering integrated solutions within the Property sector. Due to the ongoing growth of the business in China, they are recruiting a leader to assume overall responsibility for the business activities and operational performance of the company in South China.\n\nThe Position\n\nReporting to the CEO, the Managing Director will sit as part of the China Management Board advising on factors within your region that may impact on the China business unit, as well as providing input in relation to strategies for long term development of the business in terms of client requirements and service delivery models.\n\nYou will be directly responsible for the financial profitability, operations, resource management and service delivery in the region. You will ensure that with the growth of the business, there is appropriate infrastructure and intellectual capital put in place to facilitate such growth.\n\nAlong with business management, you will lead client development opportunities for Northern China in alignment with broader initiatives being driven by senior management from the China and Asia business. You will drive ongoing client satisfaction through ensuring consistently high quality service levels are being delivered, keeping abreast of development in the property market, as well as generating creative ideas and solutions.\n\nThe Requirements\n\nThe successful applicant will have a strong management background within a property related business in China and have the ability to drive equally both the financial and non-financial performance of the business. You will nurture a positive environment of success and have a bigger picture view of long term sustainable growth in the region.\n\nInternational experience will be highly regarded. Bilingual capability in English and Mandarin is required.\n\nIf you believe this opportunity is right for you, please send your CV in English to Ben Watt by using the \"Apply Now\" button below.\n\nTo view similar opportunities or express interest in related positions, please visit our website www.aurexgroup.com and follow us on LinkedIn https://lnkd.in/fgAWEBa", "employment_types": ["Full Time", "Contract"], "selling_points": [], "locations": ["Kowloon Bay"], "categories": ["Management", "Top Executives (CEO, CFO, CTO, GM, MD etc.)"], "post_time": "2022-01-03T01:06:21Z", "salary": {"currency": null, "max": null, "min": null, "period": "monthly", "term": null}, "salary_visible": false, "title_keywords": ["executive director"], "responsibilities": ["service delivery", "reporting", "management", "creative ideas", "operations", "infrastructure", "quality", "website", "recruitment", "senior management", "business activities"], "requirements": {"degrees": [], "majors": [], "languages": ["english", "mandarin"], "language_level": [], "hard_skills": ["business management"], "soft_skills": ["creative", "positive", "driven", "responsible"], "languages_combined": [{"language": "english", "language_level": []}, {"language": "mandarin", "language_level": []}]}, "experience_required": {"duration": [], "field": ["related"]}}, {"job_id": "100003009015118", "location_code": "hk", "company": "Lucky Bell Plastic Factory Ltd", "job_title": "Deputy General Manager (Station in India)\u901a\u95dc\u5f8c\u5373\u8d77\u7a0b\u99d0\u5370\u5ea6", "description": "The Authority is looking for an experienced Executive Director with drive, passion and commitment to lead this organisation to a new level.\n\nMajor Responsibilities\nReporting to the board, the role as Executive Director will be to shape the future of CITA\u2019s strategic direction in our ever-changing fashion industry. The key areas of responsibility will be:\n\nProviding vision and inspirational leadership across the organisation\nFormulating and delivering the strategic plan\nDeveloping new initiatives and opportunities\nDemonstrating leadership in vocational and professional training\nEnsuring healthy finance and quality corporate governance\n\nRequirements\nApplicants shall have a relevant university degree and a minimum of 10 years of track record in leading a training institute to deliver an outstanding performance against key metrics. Additionally, applicants must possess the following experiences:\n\nVision, and be able to translate it into a strategy\nLeadership to drive organisational capability and change\nExperience successfully developing relationships with and working with government\nStrong industry connection\nCommercial acumen in managing to a profit and loss\nGood communication and presentation skills, including written and speaking in both English and Mandarin\n\nApplication\u00a0 \u00a0\nIndividuals interested in the position are requested to forward a cover letter articulating your vision and summarising your suitability and your responses to key responsibility, together with a detailed curriculum vitae via email by clicking \"Apply Now\". Please use the subject line \u201cApplication for ED: [Your Name]\u201d.\n\nApplication Deadline: 31 January 2022\n\nAll applications will be treated in the strictest confidence, and the data collected will only be used for the consideration of your application.", "employment_types": ["Full Time"], "selling_points": [], "locations": ["Overseas"], "categories": ["Manufacturing", "Manufacturing Management", "Management", "Top Executives (CEO, CFO, CTO, GM, MD etc.)"], "post_time": "2022-01-03T05:42:20Z", "salary": {"currency": null, "max": null, "min": null, "period": "monthly", "term": null}, "salary_visible": false, "title_keywords": ["general manager"], "responsibilities": ["reporting", "quality", "developing", "plan"], "requirements": {"degrees": ["relevant university degree"], "majors": [], "languages": ["english", "mandarin"], "language_level": ["good"], "hard_skills": ["acumen"], "soft_skills": ["confidence", "interested in", "communication", "presentation skills", "leadership", "detailed"], "languages_combined": [{"language": "english", "language_level": ["good"]}, {"language": "mandarin", "language_level": ["good"]}]}, "experience_required": {"duration": [], "field": ["developing"]}}, {"job_id": "100003009010278", "location_code": "hk", "company": "BIPO Service North Asia Limited", "job_title": "Assistant General Manager/General Manager (Based in TW)", "description": "\u00a0Deputy General Manager (Station in India)\n\nDegree or above in Manufacturing Engineering or relative area\nMin. 15 years solid experience in toy business(both plastic & electronic toys)\nMin. 7 years experience in management level of sizable toy factories / companies\nMin. 7 years in dealing the manufacturing / engineering & quality issues with\u00a0repute OEM\u00a0toy companies. (no more than 5 years removed from such experience)\nProfessional knowledge in plastic toy\u00a0products manufacturing processes (with good understanding of routine manufacturing management), production planning, store operations and specially in toy products, QA requirement and quality control\u00a0\nFluent English\nStation in India (4-5 breaks back to HK every year, negotiable)\nGood health, able to adapt different environment and culture\nCandidate with much experiences or higher qualification\u00a0may\u00a0be considered as Deputy Managing Director\u00a0\n\u7372\u8058\u5f8c\u66ab\u6642\u5728\u6e2f\u5de5\u4f5c\u76f4\u81f3\u5370\u5ea6\u901a\u95dc\u5f8c\u624d\u555f\u7a0b\u524d\u5f80\u7576\u5730\u99d0\u5ee0", "employment_types": ["Full Time"], "selling_points": ["15 years of working exp in HR/Business Technology", "At least 8 years in senior management position", "Based in TW, support visa"], "locations": ["Others"], "categories": ["Sales, CS & Business Devpt", "Business Development", "Admin & HR", "HR Director / Manager", "Management", "Top Executives (CEO, CFO, CTO, GM, MD etc.)"], "post_time": "2021-12-31T03:27:48Z", "salary": {"currency": null, "max": null, "min": null, "period": "monthly", "term": null}, "salary_visible": false, "title_keywords": ["assistant general manager", "general manager"], "responsibilities": ["management", "operations", "quality", "production planning", "quality control"], "requirements": {"degrees": ["degree or above"], "majors": ["manufacturing", "engineering"], "languages": ["english"], "language_level": ["fluent"], "hard_skills": ["no"], "soft_skills": [], "languages_combined": [{"language": "english", "language_level": ["fluent"]}]}, "experience_required": {"duration": ["7 years", "5 years", "15 years"], "field": ["toys", "managing director", "management"]}}, {"job_id": "100003009010512", "location_code": "hk", "company": "Hong Kong Institute of Architects", "job_title": "Deputy Chief Operating Officer", "description": "Job Duties:\n\n\nReporting directly to the CEO to design and implement business strategies, plans and procedures\nOversee the daily operations of the clinics\nResponsible for formulation, implementation, and review of standard of the clinical operation procedures\nResolve problems related to staffing, utilization of facilities, equipment, and supplies\nEstablish policies that promote company culture and vision\n\nRequirements:\n\nBachelor\u2019s degree or above in relevant disciplines\n8+ years\u2019 experience in\u00a0the\u00a0healthcare industry will be preferable\nExcellent people management with strong interpersonal, coaching and\u00a0problem-solving skills\nAble to work with various people in different capacities and good at\u00a0collaboration\nGood command of spoken and written English, Chinese and Mandarin\n\nBenefits:\n\n5-day work per week\nMedical insurance\nAnnual leave\nAnnual discretionary bonus\nSpecial offer of eye treatment for staff and family", "employment_types": ["Full Time", "Contract"], "selling_points": [], "locations": ["Causeway Bay"], "categories": ["Management", "Top Executives (CEO, CFO, CTO, GM, MD etc.)"], "post_time": "2021-12-31T04:09:07Z", "salary": {"currency": null, "max": null, "min": null, "period": "monthly", "term": null}, "salary_visible": false, "title_keywords": ["operating officer"], "responsibilities": ["reporting", "policies", "oversee the daily operations", "review", "procedures", "implementation", "design", "plans"], "requirements": {"degrees": ["degree or above", "bachelor"], "majors": [], "languages": ["english", "chinese", "mandarin"], "language_level": ["good command"], "hard_skills": ["problem-solving skills"], "soft_skills": ["problem-solving skills", "interpersonal"], "languages_combined": [{"language": "english", "language_level": ["good command"]}, {"language": "chinese", "language_level": ["good command"]}, {"language": "mandarin", "language_level": ["good command"]}]}, "experience_required": {"duration": ["8+ years"], "field": ["healthcare industry"]}}, {"job_id": "100003009012224", "location_code": "hk", "company": "C-Mer Eye Care Holdings Limited", "job_title": "COO - Medical Group", "description": "BIPO is a one-stop leading human resources provider in Asia Pacific, focused on providing organisations with innovative ways to manage complex end-to-end HR processes. Through our cloud and mobile-based Human Resources Management system as well as industry-leading solutions such as Payroll Outsourcing, HRMS Solutions, HR value add consultancy services, we help companies transform their HR operations to and beyond their expectations, while achieving business goals related to cost and profitability.\n\nBIPO\u2019s headquarter is located in Singapore and R&D Centre in Indonesia and Malaysia. The company has offices in Australia, India, Japan, Korea, Hong Kong, Taiwan, Malaysia, New Zealand, Philippines, Vietnam, Cambodia, Myanmar, Thailand, UK, Mexico, etc..\n\nThis role will be reporting into Managing Director, North Asia who based in Hong Kong office.\n\n\n1. Overall management of the General Manager in respect to:-\n\nManagement of staff: Plan and steer resources and capacities efficiently for all internal departments including Project, Service Delivery, Business Development, Finance and in line with business pipeline and requirements to ensure hire sufficient team and resources locally\nLegal compliance: Ensure the business/service model execution locally is in line with the law and regulation of Taiwan\nInform staff appropriately and transparently regarding country and company strategy and policy\nProvide guidance to staff with regard to performance expected and establish smart targets and key performance indicators in line with the district and company strategy\nConduct regular performance reviews together with functional leaders in order to evaluate performance and results, recognize strengths and weaknesses among staff members and initiate training measures to support skills development\nCoach and mentor potential/future talent within the country team and plan succession within the district\nPromote cross-functional cooperation and information flow with other department/country\n\n\u00a02.\u00a0Strategic Business Development\n\nActive sales development of top customers within Taiwan country based on our available products including Payroll outsourcing Service, HRMS Solutions and other HR Consultancy Service\nContinuously analyze competitor activities and local industry trends and attend local industry-related functions\nDevelop business plan for the country in conjunction with the team and provide\nprepared information for investment decisions to management\nPositively contribute towards global company initiatives, support implementation and lead required change management initiatives\nTriple up the market shares in short period of time\n\n3.\u00a0HR Consultancy\n\nLiaise with clients to formulate HR strategic and practical plans to address human resource matters including but not limited to\nProvide guidance and ensure client\u2019s HR policies and practices are fully complied with local labour law and other related rules and regulations\nConduct HR related analysis, develop reports and present insights to clients where it is necessary\n\n4.\u00a0Develop and control budget\n\nPlan and forecast annual budget using established indicators and tools appropriately\nReview and monitor budget against country\u2019s P&L, create action plan in case of deviation\nPerform vendor price review on local suppliers, striving to reduce cost year on year\nEnsure timely closing of files and delivery of all accounting relevant information to finance department\nManage profitability of files and look at bottom-line results effects\nSupport local specific reporting requests\n\nYou are expected to have an excellent knowledge of all HR/Technology business processes combined with strategic thinking and good managerial skills. It is also essential that you conduct yourself with high integrity and good interpersonal skills.\n\nA minimum of Bachelor's degree in relevant field from reputable university\n15 years of working experience in HR/Business Technology leadership role, at least 8 years in senior management position in relevant industries\nHands-on management style is a must\nStrong commercial sense, business selling, leadership and maturity\nExcellent interpersonal and functional technical skills\nGood in English and Mandarin, both in verbal and written", "employment_types": ["Full Time"], "selling_points": ["Build & execute on the operational Strategy", "Responsible for the clinical operation procedures", "8+ years\u2019 experience in the healthcare industry"], "locations": ["Central"], "categories": ["Professional Services", "Business Consultancy", "Management", "Top Executives (CEO, CFO, CTO, GM, MD etc.)"], "post_time": "2021-12-31T09:40:10Z", "salary": {"currency": null, "max": null, "min": null, "period": "monthly", "term": null}, "salary_visible": false, "title_keywords": [], "responsibilities": ["regulations", "business goals", "operations", "budget", "plan", "plans", "senior management", "service delivery", "control", "compliance", "monitor", "implementation", "p&l", "develop", "reports", "forecast", "business plan", "liaise with clients", "reporting", "management", "cost", "change management", "review", "provide guidance", "payroll", "policies", "hr", "analysis", "evaluate"], "requirements": {"degrees": ["degree", "bachelor"], "majors": [], "languages": ["english", "mandarin"], "language_level": ["good"], "hard_skills": ["r&d", "inform", "analysis", "vendor", "mobile"], "soft_skills": ["strategic thinking", "focused", "timely", "integrity", "innovative", "hands-on", "interpersonal skills", "technical skills", "active", "leadership", "interpersonal"], "languages_combined": [{"language": "english", "language_level": ["good"]}, {"language": "mandarin", "language_level": ["good"]}]}, "experience_required": {"duration": ["at least 8 years", "15 years"], "field": ["management position", "hr", "business"]}}, {"job_id": "100003009005832", "location_code": "hk", "company": "Bayview Holdings Limited", "job_title": "Chief Executive Officer", "description": "Duties:\n\nDemonstrate a solid achievement in managing fixed income portfolios (e.g., Bonds)\nManage fixed income (global bonds portfolio) and securities\nFormulate a solid view of the market\nEstablish effective and well-organized investment processes\nFormulate and recommend investment policies and strategies to effectively manage portfolios to enhance returns and reduce risk based on thorough research and analysis.\nDevelop and execute investment-related strategies and procedures necessary for optimal investment performance and operations\nDevelop plans for the investment portfolio and the investment division, based on prospective market realities and system growth.\n\nRequirements:\n\nA degree in finance or a relevant field from an accredited institution.\nA strong critical view on the buy side asset management with a proven record in achievements\nPrefer fund/investment managing bonds experience from asset management\nSolid achievement in managing fixed income portfolio (e.g., Bonds)\nA minimum of 8 years of related experience\nStrong experience leading, supervising, and motivating a team of investment professionals.\nStrategic thinker and proficient in decision-making\nAbility to communicate effectively and in a professional manner\nProficient in written and spoken Chinese and English, Cantonese is preferred\n\nInterested parties please send me your resume in MS WORD format with notice period, current and expected salary to jenny.chai@manpowergrc.hk", "employment_types": ["Full Time"], "selling_points": [], "locations": ["Central"], "categories": ["Management", "Top Executives (CEO, CFO, CTO, GM, MD etc.)"], "post_time": "2021-12-29T07:17:38Z", "salary": {"currency": null, "max": null, "min": null, "period": "monthly", "term": null}, "salary_visible": false, "title_keywords": ["officer", "chief executive"], "responsibilities": ["policies", "analysis", "operations", "procedures", "develop", "develop plans"], "requirements": {"degrees": ["degree"], "majors": ["finance"], "languages": ["cantonese", "english", "chinese"], "language_level": ["proficient"], "hard_skills": [], "soft_skills": [], "languages_combined": [{"language": "cantonese", "language_level": ["proficient"]}, {"language": "english", "language_level": ["proficient"]}, {"language": "chinese", "language_level": ["proficient"]}]}, "experience_required": {"duration": ["minimum of 8 years"], "field": ["related", "investment", "team", "asset management"]}}, {"job_id": "100003009000813", "location_code": "hk", "company": "", "job_title": "General Manager", "description": "The incumbent will lead our endeavor in industry-oriented projects for logistics innovations. Through technology R&D projects, LSCM is committed to bring enabling technologies and thus innovations to the logistics and trading industries in HK.\n\nResponsibilities:\n\nLead the research for industry pain points, and direct the R&D for solution innovation\nLiaise with industry partners throughout the project cycle, lead the relationship management\nSurvey on the public policies related to the logistics and trading industry\nManage the industry research with academics and professionals\n\nRequirements:\n\nPh.D. in Engineering or relevant discipline.\nMinimum 15 years of experience in academic or professional teaching and research in areas of trading, supply chain management or logistics\nExperiences of committee roles or close relationship with trade and logistics associations\nPrevious involvement in government advisory services or good experience in public policy consultation will be highly preferred\nPossessing experience with business management or industry operations will certainly have the advantage\nGood command of written and spoken English and Chinese, fluent Putonghua will be desirable\n\nWe offer successful candidates an attractive remuneration package with two years contract and with renewal possibilities.\n\nTo apply, please send your CV and salary expectations to our Human Resources Section. \u00a0LSCM R&D Centre is an equal opportunity employer, personal data collected will be used for recruitment purposes only.\n\nBy mail: Human Resources Section, Logistics and Supply Chain MultiTech R&D Centre Limited, Level 11, Cyberport 2, 100 Cyberport Road, Hong Kong\n\nBy email\u00a0via \"Apply Now\"\n\nApplication closing date: 7 January 2022", "employment_types": ["Full Time", "Permanent"], "selling_points": [], "locations": ["Mong Kok"], "categories": ["Management", "General Management", "Public / Civil", "Social Services - Community / Non-profit Organization", "Top Executives (CEO, CFO, CTO, GM, MD etc.)"], "post_time": "2021-12-27T10:29:49Z", "salary": {"currency": null, "max": null, "min": null, "period": "monthly", "term": null}, "salary_visible": false, "title_keywords": ["general manager"], "responsibilities": ["liaise with", "policies", "management", "logistics"], "requirements": {"degrees": [], "majors": [], "languages": ["putonghua", "english", "chinese"], "language_level": ["good command", "fluent"], "hard_skills": ["business management"], "soft_skills": [], "languages_combined": [{"language": "putonghua", "language_level": ["fluent", "good command"]}, {"language": "english", "language_level": ["good command"]}, {"language": "chinese", "language_level": ["good command"]}]}, "experience_required": {"duration": ["minimum 15 years"], "field": ["management", "research", "supply chain", "business", "logistics", "teaching", "trading"]}}, {"job_id": "100003009012194", "location_code": "hk", "company": "Manpower Services (Hong Kong) Limited", "job_title": "Chief Investment Officer (Fund Mgr) _Family Office", "description": "Job Responsibilities:\n\nResponsible for leading the core functions in the Company with proven track record in leading the teams\nImplement the organization\u2019s vision and lead the execution of company strategy with the goal of increasing shareholders value\nPosition the Consultancy so as to be able to advise its clients how to adapt to the possible systemic changes in the business world\nProvide a strategic vision and direction for the development\nDevelop the Company's business strategies, set up short-term and long-term business objectives, operating plans and monitor its implementation\nDevelop and lead a team of Consultants through Greater China in developing new business for the Consultancy\nLead the team to achieve its business objectives and maintain its operation\nProvide leadership to the Consultancy during a changing and uncertain business period\u00a0\u00a0\n\nJob Requirements:\u00a0\n\nMBA or above in relevant discipline\nMinimum 20 years\u2019 solid experience in property, industrial, and financial industry\nWith strong customer base and business connection in the industry\nCapable leader with strong\u00a0people\u00a0management skills and excellent communication skills\nUnderstands the changing dynamics of global business from one of cooperation to trade-wars and the need to adapt and position the Consultancy to assist its Clients on how to adapt their businesses in an era of global confrontation amidst continuing pandemic concerns and how to benefit from of the scarce areas of cooperation that may remain.\nWill have proven hands on business/industry experience in a senior executive position with an industry leading organization, experience of International business and relationships at sufficiently high level with business leaders in China, Europe and USA.\nFluency in written and spoken English, Putonghua and Cantonese\nTravelling is required.", "employment_types": ["Permanent"], "selling_points": ["Specializes in buy side asset management", "Asset Management in fixed income and securities", "Fund/Investment Manager from Asset Management"], "locations": ["Central & Western Area"], "categories": ["Banking / Finance", "Investment", "Fund Management", "Management", "Top Executives (CEO, CFO, CTO, GM, MD etc.)"], "post_time": "2021-12-31T09:35:23Z", "salary": {"currency": null, "max": null, "min": null, "period": "monthly", "term": null}, "salary_visible": false, "title_keywords": ["officer"], "responsibilities": ["monitor", "teams", "implementation", "develop", "developing", "lead a team", "maintain", "plans"], "requirements": {"degrees": [], "majors": [], "languages": ["cantonese", "putonghua", "english"], "language_level": ["fluency"], "hard_skills": [], "soft_skills": ["communication skills", "hands on", "capable"], "languages_combined": [{"language": "cantonese", "language_level": ["fluency"]}, {"language": "putonghua", "language_level": ["fluency"]}, {"language": "english", "language_level": ["fluency"]}]}, "experience_required": {"duration": ["minimum 20 years"], "field": ["business", "financial industry"]}}, {"job_id": "100003009008209", "location_code": "hk", "company": "Logistics and Supply Chain MultiTech R&D Centre Limited", "job_title": "Special Project Director", "description": "Role and Job Duties:\n\nThe Institute is in the process of recruiting a Chief Operating Officer (COO). In the interim, the post of Deputy COO will serve as the leading administrator of the Secretariat, Registrar of Architect\u2019s Registration Board (ARB) and supporting team of the Institute. The duties include but not limited to:\n\nManage, monitor and responsible for the HKIA Secretariat (currently around 27 staff in Hong Kong and 1 in Beijing) to ensure smooth and efficient daily operation; \u00a0\nImplement effective work plans for the delivery of various events/programmes within time and budget constraints;\nWorks collaboratively to develop and/or improve systems, processes, controls and procedures;\nAssist Council to ensure and maintain good governance and responsive service to the members;\nAssist the Board in determining the long-term strategic direction in close alignment with the Institute\u2019s mission, vision and values;\nMaintain good contact with government, business corporations, NGOs, allied professional bodies, media, all other related stakeholders and the general public of the community;\nAttend functions and events on behalf of the Institute and perform duties designated by Council and Office Bearers;\u00a0\nServe as the Registrar of the Architects Registration Board HKSAR and be responsible for the administrative duties under the Architects Registration Ordinance;\nServe as the Registrar of HKIA and be responsible for the administrative duties under the Operation Manual of the institute;\nProvides timely, accurate and complete reports on the operating condition of the Institute;\nTo act as the legal person (\u6cd5\u4eba) of Office in Beijing;\nPerform any other duties as assigned by Office Bearers and Council from time to time;\nDCOO will report directly to the Council and OB for all matters of HKIA.\u00a0\u00a0\nSkills Required:\n\nPossess basic knowledge of employment law and legal compliance\nExperience in financial and accounting management\nWorking knowledge of IT/Business infrastructure\nOutstanding organizational and leadership abilities\nAptitude in decision-making and problem-solving\nPresentable and with excellent communication and interpersonal skills\nExperience in government funding and tender process will be a plus\nBachelor degree in business administration or relevant field; or more than 15 years\u2019 working experience at Senior Management level of reputable organization; MBA is a plus\u00a0 \u00a0 \u00a0\u00a0\nContract Terms and Eligibility:\n\n\nIt is a temporary post with 9 months contract period. The period may be extended subject to operation needs. Remuneration package will be offered to the right candidate.\n\nInterested applicants, please send full resume with career history, last and expected salary to HKIA Secretariat by clicking \u201cApply Now\u201d.\u00a0 Deadline for application is 10th Jan 2022.\n\nShortlisted candidates will be invited to attend written test and interview. All personal data collected will be strictly kept\u00a0confidential and for recruitment-related purpose only. \u00a0", "employment_types": ["Full Time"], "selling_points": [], "locations": ["Shatin Area"], "categories": ["Engineering", "Electrical / Electronics", "Sciences, Lab, R&D", "Research & Development (R&D)", "Management", "Top Executives (CEO, CFO, CTO, GM, MD etc.)"], "post_time": "2021-12-30T07:14:27Z", "salary": {"currency": null, "max": null, "min": null, "period": "monthly", "term": null}, "salary_visible": false, "title_keywords": ["director"], "responsibilities": ["any other duties", "budget", "daily operation", "monitor", "systems", "develop", "procedures", "maintain", "administrative duties", "contact", "reports", "plans", "report"], "requirements": {"degrees": ["degree", "bachelor"], "majors": ["business administration"], "languages": [], "language_level": [], "hard_skills": ["problem-solving", "basic", "plus"], "soft_skills": ["organizational", "problem-solving", "presentable", "communication and interpersonal skills", "leadership"], "languages_combined": []}, "experience_required": {"duration": ["15 years"], "field": ["management", "accounting", "financial"]}}, {"job_id": "100003009005951", "location_code": "hk", "company": "Baleno Kingdom Ltd", "job_title": "Head of Brand Management", "description": "A Hong Kong based NGO which provides choral and artistic training to children, with frequent performances locally and overseas. Vacancy now arises for a General Manager with the following duties:\n\nTo lead the administrative staff in daily operation and liaison with outside parties;\nTo assist the Honorary Treasurer in preparing the budget;\nTo assist the Music Director in administration of the music and artistic staff, organizes choir practices and performances;\nTo carry out instructions of the Board of Directors, to report to the Board and to coordinate between the Board and the Music Director.\n\n\u00a0Qualifications:\n\nUniversity degree or above, Arts Management or related\u00a0disciplines would be an advantage;\nAt least 8 years\u2019 managerial experience;\nStrong communication skill in Cantonese, Putonghua and English;\nRelevant work experience in management of tutors and members in artistic organization would be an advantage.\nInterested candidates, please contact us at 37059667 for company details before applying.", "employment_types": ["Full Time", "Permanent"], "selling_points": ["Brand Management", "Senior Position", "Station in Guangzhou"], "locations": ["Others - China"], "categories": ["Marketing / Public Relations", "Marketing - Brand / Product Management", "Management", "Top Executives (CEO, CFO, CTO, GM, MD etc.)"], "post_time": "2021-12-29T06:25:00Z", "salary": {"currency": null, "max": null, "min": null, "period": "monthly", "term": null}, "salary_visible": false, "title_keywords": [], "responsibilities": ["administration", "management", "budget", "daily operation", "coordinate", "communication", "report"], "requirements": {"degrees": ["degree or above"], "majors": ["related disciplines"], "languages": ["cantonese", "putonghua", "english"], "language_level": [], "hard_skills": [], "soft_skills": ["communication skill"], "languages_combined": [{"language": "cantonese", "language_level": []}, {"language": "putonghua", "language_level": []}, {"language": "english", "language_level": []}]}, "experience_required": {"duration": ["at least 8 years"], "field": ["managerial", "management"]}}, {"job_id": "100003009013919", "location_code": "hk", "company": "Easy Living Consultant Limited", "job_title": "\u5c4b\u5b87\u7e3d\u76e3\u7763", "description": "\n\nYour new company\nThis leading composite insurer is currently seeking to expand its executive management team and is looking for capable senior insurance professionals to join them. We are currently searching for an experienced individual capable of multi-department management.\n\nYour new role\nAs an experienced insurance professional, you will take part in strategic development across the Life & General Insurance businesses, overseeing all aspects of distribution, products, operations, technology and people development. You will work closely with the board and execute key initiatives on expanding business between Hong Kong & China..\n\nWhat you'll need to succeed\nThe ideal candidate will possess experience within the China Market will be necessary. Experience within Strategy, Distribution, Product, Regulations and Operations will be an asset. At least 15 years across Life & General Insurance in Hong Kong will be required. Communications in Mandarin will be necessary.\n\nWhat you'll get in return\nIn return, my client will provide you an opportunity for growth and development, along with an attractive compensation package.\n\nWhat you need to do now\nIf you fulfil all the qualifications mentioned above and have the drive to succeed or are interested in similar roles within insurance, please contact me with an attached CV at Jason.Kwong@hays.com.hk or please call +852-2230-7939.", "employment_types": ["Full Time"], "selling_points": [], "locations": ["Tsing Yi"], "categories": ["Public / Civil", "Social Services - Community / Non-profit Organization", "Management", "Top Executives (CEO, CFO, CTO, GM, MD etc.)", "Others"], "post_time": "2022-01-03T02:51:56Z", "salary": {"currency": null, "max": null, "min": null, "period": "monthly", "term": null}, "salary_visible": false, "title_keywords": [], "responsibilities": ["regulations", "management team", "management", "operations", "contact", "insurance"], "requirements": {"degrees": [], "majors": [], "languages": ["mandarin"], "language_level": [], "hard_skills": [], "soft_skills": ["interested in", "capable", "ideal"], "languages_combined": [{"language": "mandarin", "language_level": []}]}, "experience_required": {"duration": [], "field": []}}, {"job_id": "100003008444498", "location_code": "hk", "company": "Manulife (International) Limited", "job_title": "***  Unit Manager / Senior Unit Manager ***", "description": "\u5b8f\u5229\n\nManulife\n\n\u4e0d\u4e00\u6a23\u5de5\u4f5c\u5e73\u53f0\n\n\u6210\u5c31\u66f4\u7cbe\u5f69\u672a\u4f86\n\n\u6b61\u8fce\u540c\u696d\uff0c\u6df1\u5165\u4e86\u89e3\uff0c\u7d55\u5c0d\u4fdd\u5bc6!", "employment_types": ["Full Time"], "selling_points": ["Succession Planning for Career Development", "Support Work-Life Balance", "Modernized Office & All Round Support"], "locations": ["Kwun Tong"], "categories": ["Banking / Finance", "Retail Banking", "Insurance", "Insurance Agent / Broker", "Management", "Top Executives (CEO, CFO, CTO, GM, MD etc.)"], "post_time": "2021-12-25T20:27:06Z", "salary": {"currency": null, "max": null, "min": null, "period": "monthly", "term": null}, "salary_visible": false, "title_keywords": ["manager"], "responsibilities": [], "requirements": {"degrees": [], "majors": [], "languages": [], "language_level": [], "hard_skills": [], "soft_skills": [], "languages_combined": []}, "experience_required": {"duration": [], "field": []}}, {"job_id": "100003008994910", "location_code": "hk", "company": "William E Connor & Associates Ltd", "job_title": "CEO Chief of Staff", "description": "Job Accountabilities\n\nServe as a trusted advisor to the CEO and represent the CEO and family when needed.\nSupport the CEO, and Company\u2019s management team, in strategically planning global corporate structure and expansion of the Company\u2019s global office network and services.\nManage and direct the preparation of financial statements, tax returns, regular KPI, periodic portfolio and other reports to the CEO. The CEO and family are Americans.\nDirect and coordinate services received from Legal Counsel, Accountants, Tax Specialists, Wealth Managers, Estate Planners and others effecting CEO directed strategies and initiatives.\nPlan and coordinate a diversified family corporate structure which includes a number of related entities based in multiple jurisdictions including Hong Kong, Japan, the USA, Europe, and the UK.\nManage and direct the affairs and activities of a USA based single-family office responsible for overseeing the affairs, global financial assets, physical assets and real property, trusts and estate planning of the CEO and family.\nOversee charitable and philanthropic strategies and a family foundation.\nHandle special projects and ad hoc requests.\nJob Requirements\n\nIndisputable record of integrity and discretion.\nDegree holder in Finance / Economics/ Accounting or Business Administration with preferably a CPA or CFA designation.\nMinimum of 5 years of experience in Legal, Investment, Consulting or Family office business with demonstrated responsibility for real estate, tax and investment activities.\nExcellent organizational skills and ability to prioritize workflow and manage multiple projects.\nStrong communication skills in both written and spoken English.\nConnor provides excellent career opportunities & attractive fringe benefits to the right candidate. Further information about Connor and our career opportunities can be viewed on our website\u00a0 www.weconnor.com.\u00a0 If you are interested in joining our team, please send your resume with current and expected remuneration packages to us\u00a0by MS Word attachment.\n\n\nConnor is an equal opportunities employer. Personal data provided by applicants will be used strictly for recruitment purposes only. Only short-listed candidates will be notified. Applicants who are not invited for an interview within 8 weeks may consider their applications filed for future reference.", "employment_types": ["Full Time", "Permanent"], "selling_points": ["Chief of Staff to CEO", "Familiar with Finance & Legal, Private Equity", "Excellent Remuneration Package"], "locations": ["Kowloon Bay"], "categories": ["Banking / Finance", "Corporate Finance", "Management", "General Management", "Top Executives (CEO, CFO, CTO, GM, MD etc.)"], "post_time": "2021-12-23T02:39:56Z", "salary": {"currency": null, "max": null, "min": null, "period": "monthly", "term": null}, "salary_visible": false, "title_keywords": ["staff", "ceo"], "responsibilities": ["tax", "management team", "administration", "consulting", "ad hoc requests", "manage multiple projects", "financial statements", "plan and coordinate", "coordinate", "communication", "reports", "planning"], "requirements": {"degrees": ["degree holder"], "majors": ["finance", "economics", "business administration", "accounting"], "languages": ["english"], "language_level": [], "hard_skills": ["cfa", "cpa"], "soft_skills": ["communication skills", "organizational skills", "responsible", "integrity", "prioritize"], "languages_combined": [{"language": "english", "language_level": []}]}, "experience_required": {"duration": ["minimum of 5 years"], "field": ["business", "investment", "legal", "consulting"]}}, {"job_id": "100003008994074", "location_code": "hk", "company": "Mindset Asia Limited", "job_title": "Group Financial Controller - HK Listed Company", "description": "Excellent Career Opportunity for commercial minded Finance Executive for the Hong Kong Listed Group.\n\n\nReporting to the Senior Executive, you will play a key role in the following areas:\n\nProviding accounting and financial insights to improve operational efficiency\nLead financial reporting and process improvement projects\nCarry out financial management, work with business and operational managers to implement financial priorities\nOn-going review of portfolio companies financial planning, reporting, forecast and budgeting activities\nEnsuring portfolio companies' financial governance and audit procedures are in place\nExperience in managing the finance & accounting team, Treasury & Cash Management, Investor relations, banking facilities and etc.\n\nRequirements:\n\nCandidates with advance business or accounting degree preferred, such as CPA or MBA\nMinimum of 20 years of working experience is required\nDirect experience and strong track record in Hong Kong and China region is a must\nTrack record in managing a sizeable team and transformation projects\nAbility to consult and advise operating and corporate leaders on financial, reporting and regulatory issues\u00a0\nStrong leadership skills with high level of self-motivation and initiative\nProven analytical, organisational and problem-solving skills\nStrong interpersonal and communicational skills, both verbal and written in English\nSuperior organisational skills and the ability to prioritize in a dynamic working environment\nGood interpersonal skills with the ability to deal with all levels of internal and external clients\nIf interested, please apply by forwarding your resume online, quoting the job reference.\u00a0 \u00a0All applications will be strictly confidential and used solely for recruitment purposes.", "employment_types": ["Full Time", "Permanent"], "selling_points": [], "locations": ["Not Specified"], "categories": ["Accounting", "Financial Controller", "Property / Real Estate", "Property Management", "Management", "Top Executives (CEO, CFO, CTO, GM, MD etc.)"], "post_time": "2021-12-22T10:40:58Z", "salary": {"currency": null, "max": null, "min": null, "period": "monthly", "term": null}, "salary_visible": false, "title_keywords": ["financial controller"], "responsibilities": ["reporting", "management", "budgeting", "review", "procedures", "audit", "recruitment", "financial reporting", "forecast", "banking", "planning"], "requirements": {"degrees": ["degree"], "majors": ["business", "accounting"], "languages": ["english"], "language_level": [], "hard_skills": ["problem-solving skills", "cpa", "dynamic"], "soft_skills": ["leadership skills", "prioritize", "self-motivation", "organisational skills", "dynamic", "interpersonal skills", "problem-solving skills", "interpersonal", "initiative", "superior"], "languages_combined": [{"language": "english", "language_level": []}]}, "experience_required": {"duration": ["minimum of 20 years"], "field": ["management", "finance", "banking", "accounting", "team"]}}, {"job_id": "100003009008277", "location_code": "hk", "company": "The Hong Kong Jockey Club", "job_title": "Senior Commercial and Contract Manager (China Projects)", "description": "\u5de5\u4f5c\u8077\u8cac\uff1a\u00a0\n\n\u5354\u52a9\u8a2d\u7acb\u53ca\u71df\u904b\u5bb6\u65cf\u8fa6\u516c\u5ba4 (Family Office)\u00a0 (\u5fc5\u9808\u6709\u76f8\u95dc\u7d93\u9a57)\uff1b\n\u8d77\u8349\u53ca\u5236\u5b9a\u9069\u7576\u7684\u76ee\u6a19\u8cc7\u7522\u914d\u7f6e\u65b9\u6848 (\u5fc5\u9808\u6709\u76f8\u95dc\u7d93\u9a57)\uff1b\n\u719f\u6089\u4e2d\u570b\u623f\u5730\u7522\u7a05\u52d9\u7c4c\u5283\uff0c\u5354\u52a9\u7a05\u52d9\u6574\u7406\u7c4c\u5283\u8207\u7ba1\u7406\uff1b\n\u8ca0\u8cac\u6574\u5408\u5b50\u516c\u53f8\uff0c\u91cd\u7d44\u67b6\u69cb\uff1b\n\u6839\u64da\u516c\u53f8\u7d93\u71df\u9700\u6c42\u53ca\u8a08\u756b\uff0c\u7d44\u7e54\u9818\u5c0e\u516c\u53f8\u8ca1\u52d9\u7ba1\u7406\u3001\u6210\u672c\u7ba1\u7406\u3001\u9810\u7b97\u7ba1\u7406\u3001\u6703\u8a08\u6838\u7b97\u3001\u6703\u8a08\u76e3\u7763\u3001\u5be9\u8a08\u3001\u8cc7\u91d1\u7ba1\u7406\u65b9\u9762\u7684\u5de5\u4f5c\uff0c\u63d0\u4f9b\u5c08\u696d\u610f\u898b\u548c\u5efa\u8b70\uff1b\n\u5b8c\u6210\u516c\u53f8\u4e3b\u5e2d\u81e8\u6642\u4ea4\u8fa6\u7684\u5176\u4ed6\u4efb\u52d9\u3002\n\n\u5de5\u4f5c\u8981\u6c42\uff1a\n\n\u5927\u5b78\u7a0b\u5ea6\uff0c\u4e3b\u4fee\u6703\u8a08\u6216\u8ca1\u52d9\n\u66fe\u63a5\u89f8\u53ca\u6253\u7406\u5bb6\u65cf\u57fa\u91d1\u3001\u4e86\u89e3\u5bb6\u65cf\u8fa6\u516c\u5ba4\u7684\u71df\u904b\u7d30\u5247 (\u5fc5\u9808)\n10\u5e74\u6216\u4e0a\u76f8\u95dc\u8ca1\u52d9\u3001\u6703\u8a08\u3001\u5bb6\u65cf\u57fa\u91d1\u884c\u696d\u7d93\u9a57\n\u9999\u6e2f\u6703\u8a08\u5e2b\u516c\u6703\u6216\u570b\u969b\u8a3b\u518a\u6703\u8a08\u5e2b\u6703\u54e1\u00a0(\u6301\u6709\u57f7\u696d\u6703\u8a08\u5e2b\u724c\u7167\u512a\u5148)\n\u719f\u6089\u6703\u8a08\u53ca\u8ca1\u52d9\u6e96\u5247\u3001\u6709\u95dc\u623f\u5730\u7522\u767c\u5c55\u53ca\u7269\u696d\u6295\u8cc7\u53ca\u8ca1\u52d9\u6295\u8cc7\u7b49\u7684\u76f8\u95dc\u9999\u6e2f\u7a05\u52d9\u689d\u4f8b\n\u5177\u7d44\u7e54\u80fd\u529b\uff0c\u7d30\u5fc3\uff0c\u6709\u8cac\u4efb\u611f\uff0c\u80fd\u7368\u7acb\u8655\u7406\u6587\u4ef6\n\u826f\u597d\u4e2d\u82f1\u6587\u53ca\u6d41\u5229\u5ee3\u6771\u8a71\n\u6709\u9700\u8981\u5f80\u8fd4\u4e2d\u6e2f\u5169\u5730\n\n\u516c\u53f8\u798f\u5229\uff1a\n\n\u6709\u85aa\u5e74\u5047\n\u9280\u884c\u5047\u671f\n\u4e94\u5929\u5de5\u4f5c\n\u91ab\u7642\u798f\u5229\n\u5e74\u7d42\u8868\u73fe\u734e\u91d1\n\n*\u6240\u6709\u7533\u8acb\u8005\u8cc7\u6599\u6703\u88ab\u4fdd\u5bc6\u8655\u7406\u4e26\u53ea\u4f5c\u62db\u8058\u7528\u9014*\n\n**\u6709\u610f\u8005\u8acb\u63d0\u4f9b\u500b\u4eba\u4e2d\u6587\u5c65\u6b77\u3001\u8981\u6c42\u5f85\u9047\u53ca\u53ef\u4e0a\u73ed\u65e5\u671f\uff0c\u8a3b\u660e\u81f4\u9673\u5c0f\u59d0**", "employment_types": ["Full Time"], "selling_points": [], "locations": ["Not Specified"], "categories": ["Professional Services", "Business Consultancy", "Building & Construction", "Building / Construction / QS", "Management", "Top Executives (CEO, CFO, CTO, GM, MD etc.)"], "post_time": "2021-12-30T07:23:55Z", "salary": {"currency": null, "max": null, "min": null, "period": "monthly", "term": null}, "salary_visible": false, "title_keywords": ["manager"], "responsibilities": [], "requirements": {"degrees": [], "majors": [], "languages": [], "language_level": [], "hard_skills": [], "soft_skills": [], "languages_combined": []}, "experience_required": {"duration": [], "field": []}}, {"job_id": "100003008998219", "location_code": "hk", "company": "The Royal Garden", "job_title": "Executive Chef", "description": "Job Responsibilities\n\nOversee the operations of all kitchens in The Royal Garden Hotel.\nDevelop standard recipes which allow the restaurant to operate at an acceptable food cost.\nDevelop menus, budgets (where applicable), and \u201cSpecials\" which meet the needs of the target market and are in line with the operating concept for the restaurant.\nTo establish culinary standards specific for the restaurant which meet the needs of the target market.\nMonitor and analyze the menus and products of competitive restaurants.\nPrepare, in conjunction with each Restaurant Manager, annual operating costs and take corrective action when necessary to reduce expenses.\nMaximize employee productivity in order to minimize payroll costs.\nPlan and implement effective skills training programs in conjunction with the Training Manager and Departmental Trainers.\nMaximize employee productivity and morale and consistently maintain discipline following hotel guidelines and local legislation.\n\nJob Requirements\n\nMinimum of 10 years relevant experience in hotel and catering industry\u00a0\nCompetent knowledge of Western & Asian cuisine and Pastry art\nFamiliar with ISO 22000 quality management system\u00a0\nStrong sense in product, market and culinary development trends\u00a0\nStrong presentation skills and customer-oriented\u00a0\nProven managerial abilities in people management and leadership\u00a0\nGood communication, interpersonal, analyzing, organizing and planning skills\u00a0\nGood command of both written and spoken Chinese and English\u00a0\n\nApplying method\n\nInterested parties may email an application letter together with a detailed CV (with current and expected salary) or WhatsApp us at 9729 1612. For more information: Tel: 2733 2930 Fax: 2733 2934. Email address:\u00a0[via APPLY NOW]\u00a0\u00a0\n\n\u6709\u610f\u7533\u8acb\u8005\u8acb\u6309 APPLY NOW\u7533\u8acb\n\n", "employment_types": ["Full Time"], "selling_points": [], "locations": ["Tsim Sha Tsui"], "categories": ["Hospitality / F & B", "Food & Beverage", "Hospitality / Hotel Services", "Management", "Top Executives (CEO, CFO, CTO, GM, MD etc.)"], "post_time": "2021-12-24T02:53:57Z", "salary": {"currency": null, "max": null, "min": null, "period": "monthly", "term": null}, "salary_visible": false, "title_keywords": ["executive"], "responsibilities": ["budgets", "cost", "guidelines", "operations", "expenses", "monitor", "develop", "maintain", "plan", "payroll", "costs"], "requirements": {"degrees": [], "majors": [], "languages": ["english", "chinese"], "language_level": ["good command"], "hard_skills": [], "soft_skills": ["planning skills", "competent", "communication", "presentation skills", "customer-oriented", "leadership", "interpersonal"], "languages_combined": [{"language": "english", "language_level": ["good command"]}, {"language": "chinese", "language_level": ["good command"]}]}, "experience_required": {"duration": ["minimum of 10 years"], "field": ["relevant experience"]}}]