[{"job_id": "100003009054298", "location_code": "hk", "company": "K. Wah International Holdings Ltd", "job_title": "Customer Service Officer (Property Handover)", "description": "Job Responsibilities:\u00a0\u00a0\n\n\nAssist with handover logistics, and work with internal/ external parties to ensure timely and effective service to customers\nProvide after-sales services and follow up proactively\nHandle and respond to customer enquire\nAssist in sales activities and operations\nProvide tours for potential buyers inside property, common area and recreational facilities\nSupport on-site logistics\nCompile operation reports on number of visitors and customer feedback\nMaintain inventory of materials and others upon request\n\nJob Requirements:\u00a0\u00a0\n\n\nDiploma holder or above\n1 to 2 years of relevant experience in particular handover of residential properties or client-facing customer service role\nGood command of spoken & written Cantonese and English, basic skills in Mandarin\nGood interpersonal and communication skills, good telephone manner and responsive to clients\u2019 enquiries\nPositive working attitude, responsible and result-oriented\nGood listener\nProficient in MS Office application (Excel, Word, PowerPoint and Chinese Word Processing)\n\nInterested parties please send resume with salary expectation and availability to\u00a0Human Resources Department, K. Wah International Holdings Limited, 29/F, K. Wah Centre, 191 Java Rd., North Point, H.K.\u00a0or by clicking\u00a0Apply Now.\n\nAll Personal data collected will be used for recruitment purpose only. All applications will be retained for a maximum period of 2 years and may be considered for other suitable positions within the Group.", "employment_types": ["Full Time", "Permanent"], "selling_points": ["Handle all inquiries in a courtesy way", "Identify and deal with customer complaints", "Collect customer feedback on service excellence"], "locations": ["North Point"], "categories": ["Sales, CS & Business Devpt", "Customer Service - Supervisor / Officer", "Property / Real Estate", "Others", "Sales - Real Estate"], "post_time": "2022-01-17T09:05:23Z", "salary": {"currency": null, "max": null, "min": null, "period": "monthly", "term": null}, "salary_visible": false, "title_keywords": ["customer service officer"], "responsibilities": ["sales activities", "operations", "inventory", "external parties", "maintain", "logistics", "reports"], "requirements": {"degrees": ["diploma holder"], "majors": [], "languages": ["cantonese", "english", "chinese", "mandarin"], "language_level": ["good command", "proficient", "basic"], "hard_skills": ["excel", "basic", "chinese word processing", "word", "powerpoint", "ms office"], "soft_skills": ["result-oriented", "communication skills", "responsible", "positive working attitude", "customer service", "interpersonal", "telephone manner", "client-facing", "responsive"], "languages_combined": [{"language": "cantonese", "language_level": ["good command", "basic"]}, {"language": "english", "language_level": ["good command", "basic"]}, {"language": "chinese", "language_level": ["proficient"]}, {"language": "mandarin", "language_level": ["good command", "basic"]}]}, "experience_required": {"duration": ["1 to 2 years"], "field": ["customer service", "relevant experience", "client-facing"]}}, {"job_id": "100003009054297", "location_code": "hk", "company": "K. Wah International Holdings Ltd", "job_title": "Customer Service Ambassador (Full-time / Part-time)", "description": "Job Responsibilities\n\nAssist with handover logistics, and work with internal/ external parties to ensure timely and effective service to customers\nProvide after-sales services and follow up proactively\nHandle and respond to customer enquiry\nAssist in sales activities and operations\nProvide tours for potential buyers inside property, common area, and recreational facilities\nSupport on-site logistics\nCompile operation reports on number of visitors and customer feedback\nMaintain inventory of materials and others upon request\n\nJob Requirements\n\nDiploma holder or above\n1 year of relevant experience in particular handover of residential properties or client-facing customer service role\nGood command of spoken & written Cantonese and English, basic skills in Mandarin\nGood interpersonal and communication skills, good telephone manner, and responsive to clients\u2019 enquiries\nPositive working attitude, responsible and result-oriented\nGood listener\nProficient in MS Office application (Excel, Word, PowerPoint, and Chinese Word Processing)\n6 months renewable contract with satisfaction gratuity\n12 days annual leave\nInterested parties please send resume with salary expectation and availability to\u00a0Human Resources Department, K. Wah International Holdings Limited, 29/F, K. Wah Centre, 191 Java Rd., North Point, H.K.,\u00a0or by clicking\u00a0Apply Now.\n\nAll Personal data collected will be used for recruitment purpose only. All applications will be retained for a maximum period of 2 years and may be considered for other suitable positions within the Group.", "employment_types": ["Part Time", "Temporary", "Contract"], "selling_points": ["12 days annual leave", "Attractive Gratuity provided", "Renewable Contract"], "locations": ["North Point"], "categories": ["Sales, CS & Business Devpt", "Customer Service - Supervisor / Officer", "Property / Real Estate", "Others", "Sales - Real Estate"], "post_time": "2022-01-17T09:05:23Z", "salary": {"currency": null, "max": null, "min": null, "period": "monthly", "term": null}, "salary_visible": false, "title_keywords": ["customer service ambassador"], "responsibilities": ["sales activities", "operations", "inventory", "external parties", "maintain", "logistics", "reports"], "requirements": {"degrees": ["diploma holder"], "majors": [], "languages": ["cantonese", "english", "chinese", "mandarin"], "language_level": ["good command", "proficient", "basic"], "hard_skills": ["excel", "basic", "chinese word processing", "word", "powerpoint", "ms office"], "soft_skills": ["result-oriented", "communication skills", "responsible", "positive working attitude", "customer service", "interpersonal", "telephone manner", "client-facing", "responsive"], "languages_combined": [{"language": "cantonese", "language_level": ["good command", "basic"]}, {"language": "english", "language_level": ["good command", "basic"]}, {"language": "chinese", "language_level": ["proficient"]}, {"language": "mandarin", "language_level": ["good command", "basic"]}]}, "experience_required": {"duration": ["1 year"], "field": ["customer service", "relevant experience", "client-facing"]}}, {"job_id": "100003009053582", "location_code": "hk", "company": "Ztore HK Limited", "job_title": "[Neigbuy.com] Customer Service Officer (Part Time)", "description": "Job Responsibilities:\u00a0\u00a0\n\n\nAssist with handover logistics, and work with internal/ external parties to ensure timely and effective service to customers\nProvide after-sales services and follow up proactively\nHandle and respond to customer enquire\nAssist in sales activities and operations\nProvide tours for potential buyers inside property, common area and recreational facilities\nSupport on-site logistics\nCompile operation reports on number of visitors and customer feedback\nMaintain inventory of materials and others upon request\n\nJob Requirements:\u00a0\u00a0\n\n\nDiploma holder or above\n1 to 2 years of relevant experience in particular handover of residential properties or client-facing customer service role\nGood command of spoken & written Cantonese and English, basic skills in Mandarin\nGood interpersonal and communication skills, good telephone manner and responsive to clients\u2019 enquiries\nPositive working attitude, responsible and result-oriented\nGood listener\nProficient in MS Office application (Excel, Word, PowerPoint and Chinese Word Processing)\n\nInterested parties please send resume with salary expectation and availability to\u00a0Human Resources Department, K. Wah International Holdings Limited, 29/F, K. Wah Centre, 191 Java Rd., North Point, H.K.\u00a0or by clicking\u00a0Apply Now.\n\nAll Personal data collected will be used for recruitment purpose only. All applications will be retained for a maximum period of 2 years and may be considered for other suitable positions within the Group.", "employment_types": ["Part Time"], "selling_points": ["Minimum 1 year working experience in CS", "Handle enquiries and resolve customers\u2019 complaint", "Attractive package for suitable candidate"], "locations": ["Lai Chi Kok"], "categories": ["Sales, CS & Business Devpt", "Customer Service - Supervisor / Officer"], "post_time": "2022-01-17T07:11:55Z", "salary": {"currency": null, "max": null, "min": null, "period": "hourly", "term": null}, "salary_visible": false, "title_keywords": ["customer service officer"], "responsibilities": ["sales activities", "operations", "inventory", "external parties", "maintain", "logistics", "reports"], "requirements": {"degrees": ["diploma holder"], "majors": [], "languages": ["cantonese", "english", "chinese", "mandarin"], "language_level": ["good command", "proficient", "basic"], "hard_skills": ["excel", "basic", "chinese word processing", "word", "powerpoint", "ms office"], "soft_skills": ["result-oriented", "communication skills", "responsible", "positive working attitude", "customer service", "interpersonal", "telephone manner", "client-facing", "responsive"], "languages_combined": [{"language": "cantonese", "language_level": ["good command", "basic"]}, {"language": "english", "language_level": ["good command", "basic"]}, {"language": "chinese", "language_level": ["proficient"]}, {"language": "mandarin", "language_level": ["good command", "basic"]}]}, "experience_required": {"duration": ["1 to 2 years"], "field": ["customer service", "relevant experience", "client-facing"]}}, {"job_id": "100003009054359", "location_code": "hk", "company": "Casetagram Limited", "job_title": "Customer Service Officer (Night Shift - No need to make calls) Fresh grads are welcomed!", "description": "\u8077\u8cac :\n\n\u4e3b\u8981\u8ca0\u8cac\u8336\u6c34\u670d\u52d9\uff1b\u4e00\u822c\u6e05\u6f54\u670d\u52d9 \uff0c\u5305\u62ec\u5438\u5875\u3001\u5012\u5783\u573e\u53ca\u57fa\u672c\u6e05\u6f54\uff1b\u6574\u7406\u6703\u8b70\u5ba4\u3001\u652f\u63f4\u5404\u9805\u6703\u8b70\u53ca\u6d3b\u52d5\u4e4b\u8336\u6c34\u7b49\uff1b\u5982\u6709\u7dca\u6025\u8981\u52d9\uff0c\u9700\u5354\u52a9\u5916\u52e4\u5230\u9644\u8fd1\u9280\u884c\u5165\u7968\u6216\u8cfc\u8cb7\u88dc\u7d66\u7269\u8cc7\u7b49\n\u8cc7\u6b77 :\u6c92\u6709\u5b78\u6b77\u8981\u6c42; 1\u5e74\u7d93\u9a57; \u826f\u597d\u7cb5\u8a9e; \u61c2\u95b1\u8b80\u4e2d\u6587\n\u5f85\u9047 :\u6bcf\u5c0f\u6642$72.00, \u661f\u671f\u4e00,\u4e8c,\u56db,\u4e94: \u4e2d\u534812\u6642\u81f3\u4e0b\u53484\u6642\u53ca\u661f\u671f\u4e09: \u4e0a\u53487\u6642\u81f3\u4e0b\u53484\u6642, \u6bcf\u9031\u5de5\u4f5c5\u5929, \u6bcf\u5929\u5de5\u4f5c 4 - 9 \u5c0f\u6642\n\u7533\u8acb\u9808\u77e5 :\u6c42\u8077\u8005\u53ef\u81f4\u96fb29603323\u8207\u5609\u83ef\u570b\u969b\u96c6\u5718\u6709\u9650\u516c\u53f8\u8521\u5c0f\u59d0\u806f\u7d61\u3002", "employment_types": ["Full Time", "Permanent"], "selling_points": ["5 days work per week", "Fluent in Written / Spoken English", "Passion and Patient in Helping Customers"], "locations": ["Kwun Tong"], "categories": ["Sales, CS & Business Devpt", "Call Centre", "Customer Service - Supervisor / Officer", "Channel / Distribution"], "post_time": "2022-01-17T09:16:20Z", "salary": {"currency": null, "max": null, "min": null, "period": "monthly", "term": null}, "salary_visible": false, "title_keywords": ["customer service officer"], "responsibilities": [], "requirements": {"degrees": [], "majors": [], "languages": [], "language_level": [], "hard_skills": [], "soft_skills": [], "languages_combined": []}, "experience_required": {"duration": [], "field": []}}, {"job_id": "100003009055359", "location_code": "hk", "company": "Veterinary Specialty Hospital", "job_title": "Customer Service Representative", "description": "Job Responsibilities\n\nResponsible for mobile platforms (iOS / Android) and web application software development\nConduct detailed system analysis, problem diagnosis, purpose, develop and implement IT solutions\nPrepare requirement specifications of IT solutions\nMonitor service provision and prepare cases for testing IT solutions\nMaintain system documentation and reports of IT solutions\n\nJob Requirements\n\nDegree / Higher Diploma / Diploma in Computer Science, Computer Engineering or related disciplines\n5 years of working experience, with at least 2 years of hands-on experience in mobile (IOS/Android) and web application programming\nKnowledge of mobile development Java-Android SDK, Objective-C / SwiftUI\nKnowledge of web development WAMP, HTML JavaScript, CSS, JSON and PHP\nKnowledge of mobile cross-platform development VueJS, React or Flutter is in advance\nPassionate about mobile & web application development, cloud platforms (e.g. AWS, GC) and new technologies\nGood analytical and problem-solving skills\nWell organized, disciplined and responsible with a good work ethic\nAble to work independently and be self-driven to meet project schedules\nA self-motivated team player with good interpersonal and communication skills\nA good team player\nInterested parties please send resume with salary expectation and availability to\u00a0Human Resources Department, K. Wah International Holdings Limited, 29/F, K. Wah Centre, 191 Java Rd., North Point, H.K.\u00a0or by clicking\u00a0Apply Now\u00a0.\n\nAll Personal data collected will be used for recruitment purpose only. All applications will be retained for a maximum period of 2 years and may be considered for other suitable positions within the Group.\n\n", "employment_types": ["Full Time"], "selling_points": ["Customer service/ front desk experience", "5 days work with flexible working hours", "Attendance bonus"], "locations": ["Wan Chai"], "categories": ["Sales, CS & Business Devpt", "Call Centre", "Customer Service - Supervisor / Officer", "Hospitality / F & B", "Hospitality / Hotel Services"], "post_time": "2022-01-18T02:18:55Z", "salary": {"currency": null, "max": null, "min": null, "period": "monthly", "term": null}, "salary_visible": false, "title_keywords": ["customer service representative"], "responsibilities": ["software", "system documentation", "analysis", "monitor", "develop", "testing", "specifications", "maintain", "reports"], "requirements": {"degrees": ["diploma", "degree"], "majors": ["related disciplines", "computer engineering", "computer science"], "languages": [], "language_level": [], "hard_skills": ["java", "web development", "web application development", "web", "android sdk", "php", "react", "problem-solving skills", "html", "objective-c", "aws", "mobile", "javascript", "programming", "css", "android"], "soft_skills": ["communication skills", "work independently", "self-motivated", "good team player", "responsible", "well organized", "hands-on", "work ethic", "problem-solving skills", "team player", "interpersonal", "driven", "passionate about"], "languages_combined": []}, "experience_required": {"duration": ["5 years", "at least 2 years"], "field": ["programming"]}}, {"job_id": "100003009055863", "location_code": "hk", "company": "33 Financial Services Limited", "job_title": "Part Time Customer Service Officer - Sales Support Operations", "description": "Responsibilities:\n\n\nTo formulate and implement the workflow and arrangement of pre-management work of new residential development\nTo follow up owners\u2019 request for repair work after new flats handover stage and to coordinate with contractors on the work progress\nResponsible for overseeing the property management of mixed portfolio of residential, commercial and industrial buildings\nProviding quality customer services to our clients, handling complaints and inquiries, liaising with contractors, supervising management agents and monitoring cleaning and general maintenance works\nRequirements:\n\nDegree/ Higher Diploma in Mechanical, Electrical, Building Services or other Engineering disciplines or equivalent\n2-3 years above of solid experience Property Management industry\nExperience in pre-management work of new residential development is an advantage\nWell versed with the Deed of Mutual Covenant and the Building Management Ordinance\nProficient in MS Office\nGood communication skill\nExcellent command of written and spoken English and Chinese and fluent Putonghua is an advantage\nCandidate with less experience will be considered as Assistant Property Officer\n\nInterested parties please send resume with salary expectation and availability to\u00a0Human Resources Department, K. Wah International Holdings Limited, 29/F, K. Wah Centre, 191 Java Rd., North Point, H.K.\u00a0or by clicking\u00a0Apply Now.\n\nAll Personal data collected will be used for recruitment purpose only. All applications will be retained for a maximum period of 2 years and may be considered for other suitable positions within the Group.", "employment_types": ["Part Time"], "selling_points": ["Young and Energetic Team", "Flexible working hours 10 am - 4 pm & 4 pm - 10 pm", "Allowance on nite shift & shifts on Sat Sun & PH"], "locations": ["Tsim Sha Tsui"], "categories": ["Sales, CS & Business Devpt", "Customer Service - Supervisor / Officer", "Others"], "post_time": "2022-01-18T03:08:26Z", "salary": {"currency": "HKD", "max": 74, "min": 40, "period": "hourly", "term": null}, "salary_visible": true, "title_keywords": ["sales", "operations", "customer service officer"], "responsibilities": ["management", "supervising", "maintenance", "monitoring", "quality", "coordinate with", "liaising with", "customer services", "repair", "cleaning"], "requirements": {"degrees": ["diploma", "degree"], "majors": ["building services", "engineering"], "languages": ["putonghua", "english", "chinese"], "language_level": ["advantage", "excellent", "fluent"], "hard_skills": ["ms office"], "soft_skills": ["communication skill"], "languages_combined": [{"language": "putonghua", "language_level": ["advantage", "excellent"]}, {"language": "english", "language_level": ["fluent", "advantage", "excellent"]}, {"language": "chinese", "language_level": ["fluent", "advantage", "excellent"]}]}, "experience_required": {"duration": ["2-3 years"], "field": ["development", "management"]}}, {"job_id": "100003009056603", "location_code": "hk", "company": "miniMinds", "job_title": "Customer Service and Admin Officer - Causeway Bay", "description": "Job Responsibilities\n\nAssist in project launch preparation including preparation of relevant sales documents, organizing sales brochures and sales suites, etc.\nConduct market research and analysis\nCoordinate on show flat design and arrange sales office logistics\nLiaise with property agencies to facilitate sales activities and transactions\nProvide property hand-over and after-sale services to customers\nJob Requirements\n\nBachelor\u2019s degree in surveying, marketing, or related disciplines\n3\u00a0years' experience preferably in marketing & sales of residential properties in property developers\nKnowledge in Residential Properties (First \u2013hand Sales)\nOrdinance Attentive to details, customer-oriented and organized\nGood communication and interpersonal skills Proficient in English and Chinese\n\nInterested parties please send resume with salary expectation and availability to Human Resources Department, K. Wah International Holdings Limited, 29/F, K. Wah Centre, 191 Java Rd., North Point, H.K. or by clicking Apply Now.\n\nAll Personal data collected will be used for recruitment purpose only. All applications will be retained for a maximum period of 2 years and may be considered for other suitable positions within the Group.", "employment_types": ["Full Time"], "selling_points": ["Support frontline customer service & admin work", "Manage centre operations and parents' relationship", "Competitive compensation"], "locations": ["Causeway Bay"], "categories": ["Admin & HR", "Clerical / Admin Staff", "Sales, CS & Business Devpt", "Customer Service - Supervisor / Officer", "Education", "Others"], "post_time": "2022-01-18T05:00:08Z", "salary": {"currency": null, "max": null, "min": null, "period": "monthly", "term": null}, "salary_visible": false, "title_keywords": ["customer service and admin officer"], "responsibilities": ["sales activities", "conduct market research", "analysis", "design", "transactions", "coordinate", "logistics", "liaise with"], "requirements": {"degrees": ["degree", "bachelor"], "majors": ["related disciplines", "marketing", "surveying"], "languages": ["english", "chinese"], "language_level": ["proficient", "good"], "hard_skills": [], "soft_skills": ["organized", "customer-oriented", "communication and interpersonal skills", "attentive to details"], "languages_combined": [{"language": "english", "language_level": ["proficient", "good"]}, {"language": "chinese", "language_level": ["proficient", "good"]}]}, "experience_required": {"duration": ["3 years"], "field": ["property developers", "marketing"]}}, {"job_id": "100003009055466", "location_code": "hk", "company": "Chandler Macleod Group (HK) Limited", "job_title": "Customer Care Team Lead (Up to 25K/mth)", "description": "Responsibilities:\n\nResponsible for creating graphics, digital images, video, and animated contents for marketing the brand\u2019s residential properties in Hong Kong on various platforms such as websites, social media, mobile, television, and advertising displays\nCollaborate with MKT team to develop appropriate visuals, textual and animated elements for the residential projects\nWork with external vendors for production and delivery of multi-media contents for media campaigns\nSupport the execution of brand guidelines while adhering to brand standards and quality, and update internal teams with multi-media best practices\nSupport other ad hoc duties as needed, including photo-shooting, drone-shooting, video-filming and other marketing initiatives\n\nRequirements:\n\nDegree holder in graphic design, digital design, film or related disciplines\n5-8 years\u2019 relevant experience in multi-media design\nIn-depth knowledge of software design such as Adobe Creative Suite and Video-editing software\nArtistic with a keen eye for aesthetics and visually appealing content\nSelf-motived, ability to multi-task and work under pressure\nGood communication and interpersonal skills\nBasic knowledge of web publishing software\n\nInterested parties please send resume with salary expectation and availability to\u00a0Human Resources Department, K. Wah International Holdings Limited, 29/F, K. Wah Centre, 191 Java Rd., North Point, H.K. or by clicking the\u00a0Apply now\u00a0button.\n\nAll personal data collected will be used for recruitment purpose only. All applications will be retained for a maximum period of 2 years and may be considered for other suitable positions within the Group", "employment_types": ["Full Time", "Permanent"], "selling_points": ["A fast-growing fintech firm", "Westernized work environment", "Excellent work environment and culture"], "locations": ["Not Specified"], "categories": ["Sales, CS & Business Devpt", "Customer Service - Supervisor / Officer", "Account Servicing", "Sales Administration"], "post_time": "2022-01-18T02:37:35Z", "salary": {"currency": null, "max": null, "min": null, "period": "monthly", "term": null}, "salary_visible": false, "title_keywords": ["lead"], "responsibilities": ["graphics", "social media", "collaborate with", "ad hoc duties", "advertising", "quality", "teams", "develop", "photo-shooting", "brand guidelines", "contents"], "requirements": {"degrees": ["degree holder"], "majors": ["related disciplines", "graphic design", "design"], "languages": [], "language_level": [], "hard_skills": ["basic", "adobe creative suite", "web"], "soft_skills": ["multi-task", "keen", "communication and interpersonal skills", "creative", "work under pressure"], "languages_combined": []}, "experience_required": {"duration": ["5-8 years"], "field": ["relevant experience", "media", "design"]}}, {"job_id": "100003009056154", "location_code": "hk", "company": "API Lab Testing Limited", "job_title": "Senior Customer Service Executive", "description": "Job Responsibilities:\u00a0\u00a0\nPlan and execute a wide spectrum of brand building and corporate communications programs that in line with the overall corporate image\nFormulate digital communication strategy and annual plan, create and manage the content and promotions on social media platforms\nWork in close collaboration with regional offices in China and provide strategic consultancy on branding and marketing campaign, as well as corporate communications strategy for projects promotion\nPlan and manage corporate events to maintain stakeholders relations and drive positive publicity\nHandle enquiries and manage fraudulent cases and issues\nPrepare and monitor the development of press materials, speeches, key messages and media Q&As for senior executives\nManage the production of a range of cooperate publications and collaterals, advertisements, CI Guide, corporate gifts and corporate video\nSupport ad hoc projects as assigned\nJob Requirements:\u00a0\n\nDegree holder or above in Communication, Marketing, Business Administration, or relevant discipline\nA minimum of 12 years of work experience with 8 years in a managerial role\nHands-on experience in marketing and communication role with proven track record in marketing and branding strategy formulation, digital and social media communication campaigns, advertising, CI guide generation, and event management\nSolid experience to work with regional offices to launch branding and communication campaigns\nExcellent command of written and spoken English and Chinese including Putonghua\nSelf-starter with creativity, strategic mindset and business sense\nIndependent, mature and flexible, with good people skills\nKnowledge of new media and communication channels\nWell versed in computer applications including MS Word, Excel, PowerPoint and Chinese word-processing", "employment_types": ["Full Time"], "selling_points": ["Customer service", "English and Chinese", "Good computer skills"], "locations": ["Tsuen Wan Area"], "categories": ["Sales, CS & Business Devpt", "Customer Service - Supervisor / Officer", "Merchandising & Purchasing", "Furniture", "Toy"], "post_time": "2022-01-18T03:25:49Z", "salary": {"currency": null, "max": null, "min": null, "period": "monthly", "term": null}, "salary_visible": false, "title_keywords": ["senior customer service executive"], "responsibilities": ["advertisements", "social media platforms", "monitor", "communication", "handle enquiries", "maintain", "ad hoc projects", "plan"], "requirements": {"degrees": ["degree holder"], "majors": ["marketing", "business administration"], "languages": ["putonghua", "english", "chinese"], "language_level": ["excellent"], "hard_skills": ["excel", "chinese word-processing", "powerpoint", "ms word"], "soft_skills": ["flexible", "independent", "business sense", "mature", "communication", "hands-on"], "languages_combined": [{"language": "putonghua", "language_level": ["excellent"]}, {"language": "english", "language_level": ["excellent"]}, {"language": "chinese", "language_level": ["excellent"]}]}, "experience_required": {"duration": ["8 years", "minimum of 12 years"], "field": ["managerial", "social media", "management", "advertising", "marketing", "digital"]}}, {"job_id": "100003009055277", "location_code": "hk", "company": "Cos Max Medical Centre Limited", "job_title": "\u5ba2\u6236\u670d\u52d9\u4e3b\u4efb Customer Services Executive", "description": "Job Responsibilities:\n\nAssist in feasibility study in land acquisition\nAssist in overall project development planning related to MEP services, especially at the initial stage\nProvide advice and guidance to the regional office in the preparation of project manpower planning, consultant appointment program, master program, and short term construction programs related to MEP services\nMonitor the project teams and provide advices in improving the construction and MEP works to ensure they are carried out in accordance with the latest government regulations\nResponsible for the contract specifications, drawings and pre-determined quality, budget, development period and sales targets\nEstablish and enhance the Project Management related SOPs and implementation for MEP services\nAssist in solving all ad-hoc project issues\n\nJob Requirements:\n\nDegree holder in Building Services / Electrical / Mechanical or related disciplines with professional qualification\nMinimum of 8 years\u2019 PRC project management\u2019s experience in large scale / prestigious property or municipal development projects\nComprehensive knowledge in project management with experience in residential, commercial and hotel buildings\nWell-versed with PRC statutory standards and regulations\nGood knowledge of MEP Technology and their applications\nGood command of spoken and written English and Chinese. Fluent Putonghua is essential\nOccasional travel to the PRC is required\n\n\n\nInterested parties please click the Apply Now button and submit your resume with salary expectation and availability\n\nAll Personal data collected will be used for recruitment purposes only. All applications will be retained for a maximum period of 2 years and may be considered for other suitable positions within the Group.", "employment_types": ["Full Time", "Permanent"], "selling_points": ["$17,000 - $25,000, \u6bcf\u5e74\u5169\u6b21\u512a\u539a\u82b1\u7d05", "17\u65e5\u516c\u773e\u5047\u671f + 12\u65e5\u5e74\u5047", "\u6b61\u8fce\u61c9\u5c46\u7562\u696d\u751f\u61c9\u5fb5"], "locations": ["Central"], "categories": ["Sales, CS & Business Devpt", "Customer Service - Supervisor / Officer", "Hospitality / F & B", "Hospitality / Hotel Services", "Retail Sales"], "post_time": "2022-01-18T02:00:33Z", "salary": {"currency": "HKD", "max": 24999, "min": 17000, "period": "monthly", "term": null}, "salary_visible": true, "title_keywords": ["\u5ba2\u6236\u670d\u52d9\u4e3b\u4efb", "executive"], "responsibilities": ["regulations", "guidance", "provide advices", "ad-hoc", "budget", "teams", "monitor", "quality", "drawings", "implementation", "project management", "provide advice", "specifications", "sops", "planning"], "requirements": {"degrees": ["degree holder"], "majors": ["related disciplines", "building services"], "languages": ["putonghua", "english", "chinese"], "language_level": ["good command", "fluent"], "hard_skills": ["project management"], "soft_skills": ["project management", "comprehensive"], "languages_combined": [{"language": "putonghua", "language_level": ["fluent"]}, {"language": "english", "language_level": ["good command"]}, {"language": "chinese", "language_level": ["good command"]}]}, "experience_required": {"duration": ["minimum of 8 years"], "field": ["project management", "commercial", "development projects"]}}, {"job_id": "100003009054578", "location_code": "hk", "company": "Manulife (International) Limited", "job_title": "Customer Services Officer", "description": "Job Responsibilities:\n\nProvide assistance in guidance, checking, and advice to the regional offices in the preparation of project manpower planning, consultant appointment program, master program, and short-term construction program.\nCoordinate with regional design and project staff in order to monitor overall project development and project progress.\nAssist in leading the project monitoring teams and provide advices to Regional offices in improving the construction works to ensure they are carried out in accordance with the latest government regulations, contract specifications, drawings, and our predetermined quality, budget, development period, and sales targets.\nConduct regular on-site project review/audit in relation to project SOP, particularly on Quality, HSE compliance, and overall performance.\nAssist in the approval process for all project-related regional submissions.\nAssist in solving all ad-hoc new project issues and regional issues when the regional project team not yet on board.\n\nJob Requirements:\n\nDegree holder in Structural, Construction, or Building Management disciplines with professional qualification\nMinimum of 10 years\u2019 PRC experience in large scale / prestigious property or municipal development projects with a minimum of 5 years solid experience in project management\nComprehensive knowledge in project management with experience in residential / commercial / hotel experience\nWell-versed with PRC statutory standards and regulations\nGood knowledge of program management technology and its applications\nGood command of spoken and written English and Chinese. Fluent Putonghua is essential\n\nInterested parties please send resume with salary expectation and availability to Human Resources Department, K. Wah International Holdings Limited, 29/F, K. Wah Centre, 191 Java Rd., North Point, H.K. or by clicking the Apply now button.\n\nAll Personal data collected will be used for recruitment purpose only. All applications will be retained for a maximum period of 2 years and may be considered for other suitable positions within the Group.", "employment_types": ["Full Time", "Permanent"], "selling_points": ["Guaranteed Basic Income\uff08$15Kto $20K\uff09", "5 days work", "Monthly Bonus + Year-end Bonus"], "locations": ["Not Specified"], "categories": ["Sales, CS & Business Devpt", "Business Development", "Customer Service - Supervisor / Officer", "Marketing / Public Relations", "Marketing - General / Support"], "post_time": "2022-01-17T10:04:48Z", "salary": {"currency": "HKD", "max": 19999, "min": 14000, "period": "monthly", "term": null}, "salary_visible": true, "title_keywords": ["customer services officer"], "responsibilities": ["regulations", "ad-hoc", "budget", "quality", "audit", "design", "drawings", "provide advices", "compliance", "monitor", "project progress", "teams", "provide assistance", "guidance", "monitoring", "coordinate with", "checking", "review", "specifications", "planning"], "requirements": {"degrees": ["degree holder"], "majors": ["building management"], "languages": ["putonghua", "english", "chinese"], "language_level": ["good command", "fluent"], "hard_skills": ["project management"], "soft_skills": ["project management", "comprehensive"], "languages_combined": [{"language": "putonghua", "language_level": ["fluent"]}, {"language": "english", "language_level": ["good command"]}, {"language": "chinese", "language_level": ["good command"]}]}, "experience_required": {"duration": ["minimum of 10 years", "minimum of 5 years"], "field": ["project management", "commercial", "development projects"]}}, {"job_id": "100003009056511", "location_code": "hk", "company": "Gift Something", "job_title": "ECommerce Operations & Customer Service Executive", "description": "Job Responsibilities\n\nAssist in project launch preparation including preparation of relevant sales documents, organizing sales brochures and sales suites, etc.\nConduct market research and analysis\nCoordinate on show flat design and arrange sales office logistics\nLiaise with property agencies to facilitate sales activities and transactions\nProvide property hand-over and after-sale services to customers\nJob Requirements\n\nBachelor\u2019s degree in surveying, marketing, or related disciplines\n3\u00a0years' experience preferably in marketing & sales of residential properties in property developers\nKnowledge in Residential Properties (First \u2013hand Sales)\nOrdinance Attentive to details, customer-oriented and organized\nGood communication and interpersonal skills Proficient in English and Chinese\n\nInterested parties please send resume with salary expectation and availability to Human Resources Department, K. Wah International Holdings Limited, 29/F, K. Wah Centre, 191 Java Rd., North Point, H.K. or by clicking Apply Now.\n\nAll Personal data collected will be used for recruitment purpose only. All applications will be retained for a maximum period of 2 years and may be considered for other suitable positions within the Group.", "employment_types": ["Full Time"], "selling_points": ["Young & Energetic Team", "Fast Growing Company", "Attractive Package"], "locations": ["Tsuen Wan Area"], "categories": ["Sales, CS & Business Devpt", "Customer Service - Supervisor / Officer", "Account Servicing", "Sales Administration"], "post_time": "2022-01-18T04:35:51Z", "salary": {"currency": null, "max": null, "min": null, "period": "monthly", "term": null}, "salary_visible": false, "title_keywords": ["operations", "customer service executive"], "responsibilities": ["sales activities", "conduct market research", "analysis", "design", "transactions", "coordinate", "logistics", "liaise with"], "requirements": {"degrees": ["degree", "bachelor"], "majors": ["related disciplines", "marketing", "surveying"], "languages": ["english", "chinese"], "language_level": ["proficient", "good"], "hard_skills": [], "soft_skills": ["organized", "customer-oriented", "communication and interpersonal skills", "attentive to details"], "languages_combined": [{"language": "english", "language_level": ["proficient", "good"]}, {"language": "chinese", "language_level": ["proficient", "good"]}]}, "experience_required": {"duration": ["3 years"], "field": ["property developers", "marketing"]}}, {"job_id": "100003009053870", "location_code": "hk", "company": "Genesis Block Limited", "job_title": "Customer Services Officer (Cryptocurrency)", "description": "Responsibilities:\n\nResponsible for creating graphics, digital images, video, and animated contents for marketing the brand\u2019s residential properties in Hong Kong on various platforms such as websites, social media, mobile, television, and advertising displays\nCollaborate with MKT team to develop appropriate visuals, textual and animated elements for the residential projects\nWork with external vendors for production and delivery of multi-media contents for media campaigns\nSupport the execution of brand guidelines while adhering to brand standards and quality, and update internal teams with multi-media best practices\nSupport other ad hoc duties as needed, including photo-shooting, drone-shooting, video-filming and other marketing initiatives\n\nRequirements:\n\nDegree holder in graphic design, digital design, film or related disciplines\n5-8 years\u2019 relevant experience in multi-media design\nIn-depth knowledge of software design such as Adobe Creative Suite and Video-editing software\nArtistic with a keen eye for aesthetics and visually appealing content\nSelf-motived, ability to multi-task and work under pressure\nGood communication and interpersonal skills\nBasic knowledge of web publishing software\n\nInterested parties please send resume with salary expectation and availability to\u00a0Human Resources Department, K. Wah International Holdings Limited, 29/F, K. Wah Centre, 191 Java Rd., North Point, H.K. or by clicking the\u00a0Apply now\u00a0button.\n\nAll personal data collected will be used for recruitment purpose only. All applications will be retained for a maximum period of 2 years and may be considered for other suitable positions within the Group", "employment_types": ["Full Time", "Permanent"], "selling_points": ["Growing Digital Assets Brokerage firm", "Great exposure to blockchain and crypto industry", "Fresh graduates and airline staff are welcome"], "locations": ["Tsim Sha Tsui"], "categories": ["Sales, CS & Business Devpt", "Customer Service - Supervisor / Officer", "Account Servicing", "Sales Administration"], "post_time": "2022-01-17T07:39:36Z", "salary": {"currency": null, "max": null, "min": null, "period": "monthly", "term": null}, "salary_visible": false, "title_keywords": ["customer services officer"], "responsibilities": ["graphics", "social media", "collaborate with", "ad hoc duties", "advertising", "quality", "teams", "develop", "photo-shooting", "brand guidelines", "contents"], "requirements": {"degrees": ["degree holder"], "majors": ["related disciplines", "graphic design", "design"], "languages": [], "language_level": [], "hard_skills": ["basic", "adobe creative suite", "web"], "soft_skills": ["multi-task", "keen", "communication and interpersonal skills", "creative", "work under pressure"], "languages_combined": []}, "experience_required": {"duration": ["5-8 years"], "field": ["relevant experience", "media", "design"]}}, {"job_id": "100003009053896", "location_code": "hk", "company": "doTERRA Hong Kong Limited", "job_title": "Customer Service Agent", "description": "Job Responsibilities:\u00a0\u00a0\nPlan and execute a wide spectrum of brand building and corporate communications programs that in line with the overall corporate image\nFormulate digital communication strategy and annual plan, create and manage the content and promotions on social media platforms\nWork in close collaboration with regional offices in China and provide strategic consultancy on branding and marketing campaign, as well as corporate communications strategy for projects promotion\nPlan and manage corporate events to maintain stakeholders relations and drive positive publicity\nHandle enquiries and manage fraudulent cases and issues\nPrepare and monitor the development of press materials, speeches, key messages and media Q&As for senior executives\nManage the production of a range of cooperate publications and collaterals, advertisements, CI Guide, corporate gifts and corporate video\nSupport ad hoc projects as assigned\nJob Requirements:\u00a0\n\nDegree holder or above in Communication, Marketing, Business Administration, or relevant discipline\nA minimum of 12 years of work experience with 8 years in a managerial role\nHands-on experience in marketing and communication role with proven track record in marketing and branding strategy formulation, digital and social media communication campaigns, advertising, CI guide generation, and event management\nSolid experience to work with regional offices to launch branding and communication campaigns\nExcellent command of written and spoken English and Chinese including Putonghua\nSelf-starter with creativity, strategic mindset and business sense\nIndependent, mature and flexible, with good people skills\nKnowledge of new media and communication channels\nWell versed in computer applications including MS Word, Excel, PowerPoint and Chinese word-processing", "employment_types": ["Full Time"], "selling_points": ["Customer Service Experience", "Health & Beauty Industry", "5-day work"], "locations": ["Yau Tsim Mong Area"], "categories": ["Sales, CS & Business Devpt", "Customer Service - Supervisor / Officer", "Retail Sales", "Direct Sales"], "post_time": "2022-01-17T07:42:56Z", "salary": {"currency": null, "max": null, "min": null, "period": "monthly", "term": null}, "salary_visible": false, "title_keywords": ["customer service"], "responsibilities": ["advertisements", "social media platforms", "monitor", "communication", "handle enquiries", "maintain", "ad hoc projects", "plan"], "requirements": {"degrees": ["degree holder"], "majors": ["marketing", "business administration"], "languages": ["putonghua", "english", "chinese"], "language_level": ["excellent"], "hard_skills": ["excel", "chinese word-processing", "powerpoint", "ms word"], "soft_skills": ["flexible", "independent", "business sense", "mature", "communication", "hands-on"], "languages_combined": [{"language": "putonghua", "language_level": ["excellent"]}, {"language": "english", "language_level": ["excellent"]}, {"language": "chinese", "language_level": ["excellent"]}]}, "experience_required": {"duration": ["8 years", "minimum of 12 years"], "field": ["managerial", "social media", "management", "advertising", "marketing", "digital"]}}, {"job_id": "100003009053633", "location_code": "hk", "company": "Vineberg Property Management Limited", "job_title": "\u52a9\u7406\u5ba2\u6236\u670d\u52d9\u76e3\u7763**", "description": "Responsibilities:\n\nCoordinate with external landscape consultants to produce suitable designs\nOrganize and monitor drawings and plans for government submission including tree-felling, transplants, compensation, etc.\nPrepare and monitor tendering process as well as recommendation for award and contract administration\nProduce reports and conduct researches for management\u2019s review\nConduct site, nursery inspections and other assigned tasks\n\nRequirements:\n\nRecognized degree in Landscape Architecture with qualified professional\nObtained professional training in Horticulture is an advantage\nMinimum\u00a05 years\u2019 experience with major developers / consultants\nOn and off site experience in landscape construction, maintenance, tree transplant is a definite advantage\nInnovative, creative and possess strong design skill\nGood at hard landscape detailing\nGood free hand, PSD and CAD presentation skills\nSound knowledge in planting and plant materials\nWritten and verbal proficiency in English and Chinese\nCandidates with less experience will be considered as Assistant Landscape Designer\n\n*Please visit our website www.kwih.comfor more details*\n\nInterested parties please send resume with salary expectation and availability to Human Resources Department, K. Wah International Holdings Limited, 29/F, K. Wah Centre, 191 Java Rd., North Point, H.K. or by clicking the \"Apply Now\" button.\n\nAll Personal data collected will be used for recruitment purpose only. All applications will be retained for a maximum period of\u00a02 years and may be considered for other suitable positions within the Group.", "employment_types": ["Full Time"], "selling_points": [], "locations": ["Tseung Kwan O"], "categories": ["Sales, CS & Business Devpt", "Customer Service - Supervisor / Officer", "Property / Real Estate", "Property Management", "Others", "Security / Safety Control"], "post_time": "2022-01-17T07:16:20Z", "salary": {"currency": null, "max": null, "min": null, "period": "monthly", "term": null}, "salary_visible": false, "title_keywords": [], "responsibilities": ["management", "contract administration", "review", "monitor", "coordinate with", "tendering", "drawings", "reports", "plans"], "requirements": {"degrees": ["degree"], "majors": ["architecture"], "languages": ["english", "chinese"], "language_level": ["proficiency"], "hard_skills": ["cad", "maintenance"], "soft_skills": ["presentation skills", "innovative", "creative"], "languages_combined": [{"language": "english", "language_level": ["proficiency"]}, {"language": "chinese", "language_level": ["proficiency"]}]}, "experience_required": {"duration": ["minimum 5 years"], "field": ["designer", "construction", "maintenance"]}}, {"job_id": "100003009051292", "location_code": "hk", "company": "C2 Recruitment Limited", "job_title": "\u5ba2\u6236\u670d\u52d9\u4e3b\u4efb - \u65b0\u754c\u5340\u63a5\u807d\u71b1\u7dda\u90e8", "description": "[Ref: JMC-CSO(Contract)]\n\n\u00a0The Job:\n\nAdminister tenancy management properly by visiting rental flats regularly to identify abnormalities, handling tenancy movements and changes, explaining tenancy details to tenants and updating tenancy records.\nProvide quality services and enhance relationship with tenants / owners by handling telephone enquiries, referring emergencies to appropriate staff, drafting notices / replies to tenants / owners promptly, taking meeting minutes and organising activities & interest classes etc.\nProvide customer services to tenants / owners when maintenance work is in progress by liaising with and coordinating relevant parties, scheduling works orders and following-up tenants/ owners\u2019 requests, monitoring maintenance works progress to minimise disruption to tenants/ owners.\nAssist in office logistics by preparing work schedules for manual staff, typing documents, maintaining and updating filing system.\n\nThe Person:\n\nMatriculated OR 5 subjects obtained Level 3 or above in HKDSEE, including English and Chinese with min. 1-2 years' experience in customer services in Property Management industry OR Degree/Diploma holders with relevant experience.\nBasic PC knowledge including Word Processing.\nGood communication, and interpersonal skills.\nMature, service-oriented and attentive to details.\n\nAttractive remuneration package will be offered to suitable candidates. To apply, please submit online application: https://careers.hkhs.com/ or send your application with full resume and reference quoted to Human Resources Manager by fax: 2882 4466.\n\nYou are welcome to visit our website www.hkhs.com to learn more about us.\nApplicants not invited for interview within 8 weeks may consider their applications unsuccessful.\n\nPersonal data provided by job applicants will be used strictly in accordance with the Housing Society\u2019s personal data policies which is available in our website and obtainable upon request. Please refer to the Policy Statement on Employment Related Data under Personal Data (Privacy) Ordinance in our website.", "employment_types": ["Full Time", "Permanent"], "selling_points": ["\u7121\u9700\u92b7\u552e\uff0c\u63a5\u807d\u5ba2\u6236\u670d\u52d9\u71b1\u7dda", "\u6708\u85aa\u6708\u5165\u7d04$16,000 - $20,000 \u8996\u4e4e\u7d93\u9a57", "\u8c50\u5bcc\u54e1\u5de5\u6d3b\u52d5\u53ca\u798f\u5229"], "locations": ["Not Specified"], "categories": ["Sales, CS & Business Devpt", "Call Centre", "Customer Service - Supervisor / Officer", "Marketing / Public Relations", "Others"], "post_time": "2022-01-16T21:50:26Z", "salary": {"currency": null, "max": null, "min": null, "period": "monthly", "term": null}, "salary_visible": false, "title_keywords": ["\u5ba2\u6236\u670d\u52d9\u4e3b\u4efb"], "responsibilities": ["management", "maintenance", "maintaining", "schedules", "monitoring", "quality", "liaising with", "customer services", "scheduling", "logistics"], "requirements": {"degrees": ["diploma", "degree"], "majors": [], "languages": ["english", "chinese"], "language_level": [], "hard_skills": ["pc knowledge", "basic", "word processing"], "soft_skills": ["attentive to details", "service-oriented", "mature", "communication", "interpersonal skills"], "languages_combined": [{"language": "english", "language_level": []}, {"language": "chinese", "language_level": []}]}, "experience_required": {"duration": ["1-2 years"], "field": ["management", "relevant experience", "customer services"]}}, {"job_id": "100003009056524", "location_code": "hk", "company": "Sun Life Hong Kong Limited", "job_title": "Customer Service Officer (MPF)", "description": "\u65bc\u5ba2\u6236\u670d\u52d9\u71b1\u7dda\u5167,\u5c31\u5ba2\u6236\u7684\u67e5\u8a62,\u5feb\u901f\u5c0b\u627e\u89e3\u6c7a\u554f\u984c\u7684\u65b9\u6cd5\u4ee5\u53ca\u89e3\u7b54\u6709\u95dc\u90e8\u9580\u7684\u67e5\u8a62\u8207\u53ca\u8f49\u4ecb\u610f\u898b\u6216\u6295\u8a34\n\n\u5168\u76e4\u8ca0\u8cac\u63a5\u807d\u5ba2\u6236\u71b1\u7dda, \u7121\u9700\u92b7\u552e!\n\n\u4e2d\u4e94/\u4e2d\u5b78\u6587\u6191 (DSE)\u6216\u4ee5\u4e0a\u7a0b\u5ea6,\u6b61\u8fce\u6709\u8208\u8da3\u65bc\u5ba2\u6236\u670d\u52d9\u884c\u696d\u767c\u5c55\u53ca \u61c9\u5c46\u7562\u696d\u751f\n\n\u5177\u5099\u57fa\u672c\u5ba2\u6236\u670d\u52d9\u7d93\u9a57, \u7d93\u9a57\u8c50\u5bcc\u8005\u53ef\u53d7\u8058\u70ba\u9ad8\u7d1a\u5ba2\u6236\u670d\u52d9\u4e3b\u4efb\n\n\u6708\u85aa\u6708\u5165\u7d04$16,000 - $20,000 \u8996\u4e4e\u7d93\u9a57\n\n\u826f\u597d\u6649\u5347\u6a5f\u6703 \u53ca \u5b8c\u5584\u5728\u8077\u57f9\u8a13\n\n\u65b0\u754c\u5340\u5de5\u4f5c\n\n\u9700\u8f2a\u73ed\n\n15\u5929\u5e74\u5047\n\n\u91ab\u7642\u6d25\u8cbc\n\n\u8c50\u5bcc\u54e1\u5de5\u6d3b\u52d5\u53ca\u798f\u5229\n\nPersonal data provided by job applicants will be used strictly in accordance with the employer's personal data policies and for recruitment purposes only.", "employment_types": ["Full Time"], "selling_points": ["Answer enquiries & complaints from customers", "Conduct periodic telephone calls", "Clear career path with attractive salary (20k up)"], "locations": ["Hung Hom"], "categories": ["Sales, CS & Business Devpt", "Customer Service - Supervisor / Officer", "Marketing / Public Relations", "Management", "Sales - Sales Management"], "post_time": "2022-01-18T04:39:03Z", "salary": {"currency": "HKD", "max": 29999, "min": 20000, "period": "monthly", "term": null}, "salary_visible": true, "title_keywords": ["customer service officer"], "responsibilities": ["policies", "personal data", "recruitment"], "requirements": {"degrees": [], "majors": [], "languages": [], "language_level": [], "hard_skills": [], "soft_skills": [], "languages_combined": []}, "experience_required": {"duration": [], "field": []}}, {"job_id": "100003009053652", "location_code": "hk", "company": "International Transport Information Systems Limited", "job_title": "Customer Service", "description": "Duties\nHandle service inquiries raised by clients\nMaking outbound calls regarding our services\nProvide sales and administrative support\nEnlarge and extend potential market segments in a proactive approach\nRequirements\n\nDegree holder in Business or related discipline\nMinimum 2 years\u2019 relevant experience in financial industry preferred\nExperience in customer service is an advantage\nSelf-motivated and service-oriented with good communication and interpersonal skills\nFluency in written and spoken Chinese\nBenefits\n\n\nAttractive remuneration package\u00a0will be offered to the right candidates\nHigh commission, monthly performance bonus, year-end performance bonus and pension benefits\nWell-structured training programs and comprehensive training platform\nClear career path and fast-track promotion to management level\nMedical benefits and training allowances", "employment_types": ["Full Time", "Permanent"], "selling_points": [], "locations": ["Kowloon Bay"], "categories": ["Sales, CS & Business Devpt", "Customer Service - Supervisor / Officer", "Information Technology (IT)", "Support"], "post_time": "2022-01-17T07:17:50Z", "salary": {"currency": null, "max": null, "min": null, "period": "monthly", "term": null}, "salary_visible": false, "title_keywords": ["customer service"], "responsibilities": ["administrative support"], "requirements": {"degrees": ["degree holder"], "majors": ["business"], "languages": ["chinese"], "language_level": ["fluency"], "hard_skills": [], "soft_skills": ["self-motivated", "customer service", "communication and interpersonal skills", "service-oriented"], "languages_combined": [{"language": "chinese", "language_level": ["fluency"]}]}, "experience_required": {"duration": ["minimum 2 years"], "field": ["customer service", "financial industry", "relevant experience"]}}, {"job_id": "100003009053184", "location_code": "hk", "company": "Tsit Wing Coffee Co Ltd", "job_title": "Customer Service Representative", "description": "Job Description:\n\nSupport service through hot line and email;\nGather preliminary information and pass to second line support;\nUnderstand customer requirement, provide solution through usage of ITIS software package;\nWrite up of customer requirement;\nConduct system testing;\nProvide user training;\nPrepare and maintain user documentation, such as user manual, training manual, etc.\n\nJob Requirement:\n\nWith 2 year or above relevant experience;\nDiploma or equivalent is a plus;\nKnowledge in logistics, freight forwarding, and transportation is a plus;\nExperience in using ERP systems of any kind is a plus;\nResponsive, good communication/interpersonal skills, and open to new tasks/ exposure;\nAble to listen to customers and understand their key concerns in order to achieve better services and solutions (with analytical mindset);\nPatient, helpful, eager to help customer resolving issues relating to services offered;\nGood command of spoken & written English and/or Chinese.\n\nEmployees with good performance will be promoted.\n\n\n\nWe are equal opportunity employer and welcome applications from all qualified candidates.\n\n", "employment_types": ["Full Time", "Permanent"], "selling_points": [], "locations": ["Kwai Fong"], "categories": ["Admin & HR", "Clerical / Admin Staff", "Sales, CS & Business Devpt", "Customer Service - Supervisor / Officer", "Sales Administration"], "post_time": "2022-01-17T06:20:17Z", "salary": {"currency": null, "max": null, "min": null, "period": "monthly", "term": null}, "salary_visible": false, "title_keywords": ["customer service representative"], "responsibilities": ["software"], "requirements": {"degrees": ["diploma"], "majors": [], "languages": ["english", "chinese"], "language_level": ["good command"], "hard_skills": ["documentation", "erp systems", "plus"], "soft_skills": ["communication", "patient", "responsive", "interpersonal skills"], "languages_combined": [{"language": "english", "language_level": ["good command"]}, {"language": "chinese", "language_level": ["good command"]}]}, "experience_required": {"duration": ["2 year"], "field": ["relevant experience"]}}, {"job_id": "100003009055546", "location_code": "hk", "company": "Hong Kong Housing Society", "job_title": "CES - Officer / Senior Customer Services Representative", "description": "[Ref: CES-O/SCSR]\n\nThe Job\n\nAttend the elderly lounge and arrange activities for the elderly tenants to promote home, health and social care.\nConduct regular home visits and/or telephone assurance to the elderly tenants, and deliver timely health assessments and match with suitable services.\nArrange the logistics with collaborators and organisations and offer onsite coordination with the contingency plan for implementation of activities.\nLiaise, monitor and train volunteers of all ages, and to maintain an up-to-date service records for annual award.\nProvide administrative support, including procurement and contract service payment, statistic and data entry, progress reporting and meeting minutes, inventory control, programme proposal and evaluation, and prepare other documentary work to support the operational needs of AIP scheme.\nHandle daily requests, enquiries and complaints of the elderly tenants and their families, local hospitals and other service units.\n\nThe Person\n\nDegree/Diploma holders in social work / social sciences / health sciences with relevant working experience in elderly services field and knowledge in event organising.\nGood manner, sociable and cheerful character with strong communication, interpersonal, organisation and customer services skills.\nAble to work independently and interested in communicating with elderly people.\nProficiency in MS Windows application, including Excel, Word, PowerPoint and Chinese Word processing.\nFresh Graduate will also be considered.\n\nAttractive remuneration package will be offered to suitable candidates. To apply, please submit online application: https://careers.hkhs.com/ or send your application with full resume and reference quoted to Human Resources Manager by fax: 2882 4466.\n\nYou are welcome to visit our website www.hkhs.com to learn more about us.\nApplicants not invited for interview within 8 weeks may consider their applications unsuccessful.\n\nPersonal data provided by job applicants will be used strictly in accordance with the Housing Society\u2019s personal data policies which is available in our website and obtainable upon request. Please refer to the Policy Statement on Employment Related Data under Personal Data (Privacy) Ordinance in our website.", "employment_types": ["Permanent"], "selling_points": ["Attend the elderly lounge and arrange activities", "Conduct regular home visits or telephone assurance", "Experience in elderly services field"], "locations": ["Others"], "categories": ["Sales, CS & Business Devpt", "Customer Service - Supervisor / Officer"], "post_time": "2022-01-18T02:41:51Z", "salary": {"currency": null, "max": null, "min": null, "period": "monthly", "term": null}, "salary_visible": false, "title_keywords": ["officer", "customer services representative"], "responsibilities": ["liaise", "reporting", "data entry", "coordination with", "monitor", "implementation", "payment", "maintain", "logistics", "inventory control", "plan", "evaluation", "provide administrative support"], "requirements": {"degrees": ["diploma", "degree", "fresh graduate"], "majors": ["social work", "social sciences"], "languages": ["chinese"], "language_level": ["proficiency"], "hard_skills": ["excel", "chinese word processing", "ms windows", "word", "powerpoint"], "soft_skills": ["work independently", "cheerful", "customer services skills", "interested in", "sociable", "communication", "organisation", "interpersonal"], "languages_combined": [{"language": "chinese", "language_level": ["proficiency"]}]}, "experience_required": {"duration": [], "field": ["relevant working experience"]}}, {"job_id": "100003009053946", "location_code": "hk", "company": "Geek Plus International Company Limited", "job_title": "Assistant Manager, Customer Care (Overnight Shift Required)", "description": "About Geek+\nGeek+ leads the technology revolution, by applying advanced robotics and AI technologies to realize high-flexibility and intelligent logistics automation solution. We are always looking for people who can bring new perspectives and life experiences to our company. We understand the value of our people and we strive to constantly satisfy their needs.\n\nWe are looking for a\u00a0Assistant Manager, Customer Care\u00a0to join our team. Are you someone who is driven by curiosity, craves a good challenge? Join us and be part of this exciting adventure!\n\nAbout the role:\n\nProactively liaise with different levels and functional teams to ensure operation runs smoothly\nAct as key escalation point in case of high severity incidents and push for resolution\nInvestigate and resolve customer complaints and queries, divert cases to related functional teams\nContinuously monitor the KPI of the team, speed of response / efficiency in dealing with customer enquiries\nTake ownership of any tasks set and ensure all deadlines are met by being organised\nReview the current operation and working with the manager to set up new processes to streamline and improve the customer experience\nProvide direction to the teammates to ensure that all issues are resolved quickly\nEnsure constant clear communication within the team to uphold complete transparency with new processes, issues, general updates etc\nRequirements:\n\nDegree in any business-related discipline, IT related is preferred\n5 years of working experience in customer service, logistics/IT solutions background would be an absolute advantageMust be fluent in both written and verbal English, Mandarin and Cantonese\nStrong planning and organizational skills as well as attention to detail\nProven experience to manage huge size corporation customers would be a plus\nWilling to learn, detail-oriented and open-minded\u00a0\nSelf-motivated,\u00a0hard-working\u00a0and\u00a0independent\nWhat We Offer:\n\nFive-day work week\nOvernight shift allowance\nYoung and energetic work culture with regional exposure\nCozy office environment with\u00a0light refreshments\nDouble pay & attractive performance bonus\nMedical and dental benefits and insurance\n14 to 21 days Annual Leave\nConvenient work location: KCC\nIf your qualifications, experience, and aspirations match our requirements, please send your resume with your current and expected salary to us.\n\nAll information and materials submitted to Geek+ will remain strictly confidential and be treated for recruitment purposes only. Only short-listed candidates will be notified.", "employment_types": ["Full Time", "Permanent"], "selling_points": ["Exp in technical support and customer services", "Strong communication, independently and flexible", "Overnight shift is required, with allowance"], "locations": ["Kwai Hing"], "categories": ["Sales, CS & Business Devpt", "Customer Service - Supervisor / Officer", "Engineering", "Engineering Project Management", "Information Technology (IT)", "Technical / Functional Consulting"], "post_time": "2022-01-17T07:48:56Z", "salary": {"currency": null, "max": null, "min": null, "period": "monthly", "term": null}, "salary_visible": false, "title_keywords": ["assistant manager,"], "responsibilities": ["robotics", "resolve customer complaints", "provide direction", "customer enquiries", "review", "teams", "monitor", "resolution", "communication", "customer service", "logistics", "liaise with", "planning"], "requirements": {"degrees": ["degree"], "majors": ["business", "it"], "languages": ["cantonese", "english", "mandarin"], "language_level": ["fluent"], "hard_skills": ["plus", "ai"], "soft_skills": ["organizational skills", "self-motivated", "independent", "advanced", "open-minded", "willing to learn", "detail-oriented", "clear", "communication", "customer service", "hard-working", "attention to detail", "organised", "driven"], "languages_combined": [{"language": "cantonese", "language_level": ["fluent"]}, {"language": "english", "language_level": ["fluent"]}, {"language": "mandarin", "language_level": ["fluent"]}]}, "experience_required": {"duration": ["5 years"], "field": ["logistics", "operation", "customer service", "it"]}}, {"job_id": "100003009055111", "location_code": "hk", "company": "Autotoll Limited", "job_title": "Operation and Customer Service Team Leader (Toll)", "description": "To cope with our expansion and continuous growth in the transportation and logistics related service, we are inviting talents to join our professional team.\n\n\n\nAbout the role:\n\nAssist the Operation and Customer Service Team Head in manage the daily operation of the department\nSupervise the team to handle the transaction validation process; and to handle the problematic cases that escalated by team members\nEnsure timely handling of all the cases, including the problematic / dispute cases within the established timeframe\nTo ensure the services provided in transaction handling are according to procedures and make suggestion for any improvement in daily process\nPrepare the monthly report to the Operation and Customer Service Team Head regarding the operation of the department & those required to submit to the Government Department\nShift duty is required\n\nAbout You:\n\nHolder of university degree or equivalent qualification.\nAt least four years post-qualification full time working experience in customer service roles, of which at least two years shall be at supervisory level\n\n\n\nWhat you can get from us:\n\nOn-the-job training, learning and development\u00a0provided\nExecutive workshops, interest class, corporate purchase discount offered by SHKP\nCompetitive salary and annual leaves\nFlexible working opportunities\n\nInterested parties, please send full resume with\u00a0expected salary\u00a0and\u00a0available date\u00a0to Human Resources and Administration Department by e-mail or by fax 2111 9459.\n\n(Data collected will be used for recruitment purpose only.)", "employment_types": ["Full Time", "Permanent"], "selling_points": ["Holder of university degree", "At least four years experience in cs roles", "Shift duty is required"], "locations": ["Kowloon Bay"], "categories": ["Sales, CS & Business Devpt", "Customer Service - Supervisor / Officer"], "post_time": "2022-01-18T01:15:16Z", "salary": {"currency": null, "max": null, "min": null, "period": "monthly", "term": null}, "salary_visible": false, "title_keywords": ["team leader", "customer service"], "responsibilities": ["daily operation", "procedures", "purchase", "customer service", "logistics", "monthly report"], "requirements": {"degrees": ["university degree"], "majors": [], "languages": [], "language_level": [], "hard_skills": ["workshops", "make"], "soft_skills": ["flexible", "timely", "customer service", "learning"], "languages_combined": []}, "experience_required": {"duration": ["at least two years", "at least four years"], "field": ["supervisory level", "customer service", "post-qualification"]}}, {"job_id": "100003009056111", "location_code": "hk", "company": "DHL EXPRESS (HONG KONG) LIMITED", "job_title": "Customer Service Representative (Customer Call Centre)", "description": "Working Location\u00a0:\u00a0\u00a0 Ngau Tau Kok\nWorking Hours\u00a0: Monday \u2013 Sunday,\u00a0including public holidays\u00a07:30 a.m. - 10:30 p.m.\u00a0(5 days, average 42.5 hours per week)\nYou will be responsible for providing quality customer services to both local and overseas clients through 24-hours hotline. You will handle customer enquiries, order booking and shipment tracing, as well as to solve the problems and complaints from customers.\nMore information for you:\u00a0https://youtu.be/Es25e-V-Hvk\nRequirements:\nPost-secondary education (English & Chinese passed in HKCEE / HKDSE or equivalent)\nMore than 1 year customer service experience, preferably in contact centre environment\nGood command of spoken & written English and Chinese, proficiency in Mandarin is an advantage\nCustomer-focus with good telephone manner\nGood interpersonal and communication skills\nGood team-spirit and problem solving skills\nSelf-motivated and able to work under pressure\nBasic PC knowledge and good typing skills\n\nFresh graduates of Degree/ Associate Degree with experiences in direct customer interfaces will also be considered\nApplication:\n\nClick \"Apply Now\" or apply on line via the following link:\u00a0\u00a0\nhttps://dhlexpress.taleo.net/careersection/ex/jobdetail.ftl?job=210083R&iniurl.src=CWS-10001&tz=GMT%2B08%3A00&tzname=Asia%2FShanghai\nand also indicating your current and expected salary, and availability.\u00a0 For more job opportunities, please visit our website at\u00a0https://www.dpdhl.jobs/\nPersonal Information Collection Statement pertaining to Recruitment\nDHL Express (Hong Kong) Limited / DHL Aviation (Hong Kong) Limited (\u201cDHL\u201d) is committed to protecting and respecting your privacy in accordance with the Personal Data (Privacy) Ordinance of Hong Kong (the \u201cOrdinance\u201d) and DHL\u2019s Personal Data Protection Policy (the \u201cPolicy\u201d) at\u00a0https://www.dhl.com/hk-en/home/footer/local-privacy-notice.html\nBy proceeding to respond to this recruitment advertisement, you consent that we may use, retain, process, transfer or otherwise handle the personal data that we collect from you for recruitment,\u00a0 application processing, assessment and communication purposes (including any other purposes directly related thereto) in accordance with the Policy.\nAll personal data of unsuccessful applicants will be retained for future recruitment purposes for a period of not more than two (2) years after which such data will be destroyed.\nYou have the right at any time to make a data access or correction request concerning your personal data held by us. In addition, you may request us to delete your personal data that is no longer required for the relevant purposes which you have given consent. Should you wish to exercise such rights or have any question in relation to your personal data or the Policy, please contact our Human Resources Division in writing.", "employment_types": ["Full Time", "Permanent"], "selling_points": ["1 year customer service experience", "Customer-focus with good telephone manner", "Fresh graduate with Part-Time Customer Service Exp"], "locations": ["Ngau Tau Kok"], "categories": ["Sales, CS & Business Devpt", "Call Centre", "Customer Service - Supervisor / Officer", "Others"], "post_time": "2022-01-18T03:19:58Z", "salary": {"currency": null, "max": null, "min": null, "period": null, "term": null}, "salary_visible": false, "title_keywords": ["customer service representative"], "responsibilities": ["handle customer enquiries", "data", "customer service experience", "quality", "website", "customer services", "communication", "recruitment", "booking", "contact", "personal data", "work under pressure"], "requirements": {"degrees": ["associate degree", "degree", "hkdse", "secondary education"], "majors": [], "languages": ["english", "chinese", "mandarin"], "language_level": ["advantage", "proficiency", "good command"], "hard_skills": ["no", "basic", "typing", "html", "make", "problem solving skills", "pc knowledge", "focus", "processing"], "soft_skills": ["communication skills", "self-motivated", "responsible", "communication", "committed", "problem solving skills", "customer service", "focus", "telephone manner", "interpersonal", "work under pressure"], "languages_combined": [{"language": "english", "language_level": ["proficiency", "advantage", "good command"]}, {"language": "chinese", "language_level": ["proficiency", "advantage", "good command"]}, {"language": "mandarin", "language_level": ["proficiency", "advantage", "good command"]}]}, "experience_required": {"duration": ["1 year"], "field": ["customer service"]}}, {"job_id": "100003009055339", "location_code": "hk", "company": "ServiceOne Limited", "job_title": "Customer Service Coordinator (5-day-work)", "description": "Job Duties:\n\nHandle customer's inquiry\nWork with internal departments to solve problem and follow up issues\nComplaints handling, report review and other ad hoc duties as assigned\n\nRequirements:\n\nWell-manner, pleasant, proactive and good communication skills\nGood English and Mandarin\u00a0\nImmediate available is highly preferred\nInterested candidates please send your resume with date of availability and expected salary by email for application.\n\n\n\nPersonal data collected will be used for recruitment-related purposes only.", "employment_types": ["Full Time", "Permanent"], "selling_points": ["5 mins to MTR station", "Friendly & supportive team members", "IT service"], "locations": ["Chai Wan"], "categories": ["Sales, CS & Business Devpt", "Call Centre", "Customer Service - Supervisor / Officer", "Account Servicing"], "post_time": "2022-01-18T02:13:58Z", "salary": {"currency": null, "max": null, "min": null, "period": "monthly", "term": null}, "salary_visible": false, "title_keywords": ["customer service coordinator"], "responsibilities": ["ad hoc duties", "review", "report"], "requirements": {"degrees": [], "majors": [], "languages": ["english", "mandarin"], "language_level": ["good"], "hard_skills": [], "soft_skills": ["communication skills", "proactive", "pleasant"], "languages_combined": [{"language": "english", "language_level": ["good"]}, {"language": "mandarin", "language_level": ["good"]}]}, "experience_required": {"duration": [], "field": []}}, {"job_id": "100003009055856", "location_code": "hk", "company": "AIA Hong Kong and Macau", "job_title": "Customer Service Ambassador (Hotline - Employee Benefits)", "description": "Bring your career aspirations to life with AIA!\n\nResponsible for running the operations and implementing process improvements of the customer contact centre\n\nRoles and Responsibilities:\n\nHotline Operation\n\nHandles customer enquiries and complaints regarding all activities in Operation process such as Underwriting, Policy Owner Service, and Claims for different line of business\nReports problems, potential crisis and complaint to supervisor for service improvement;\nMakes outbound call to customers for follow-up cases;\nExecutes empowerment guidelines;\n\nAdministrative Works\n\nDocuments call activities in system\nDocuments follow up items in log sheet or send email to AIAHK Business Partners\nWorks closely with AIAHK Business Partners to resolve the complaints and uncertain issues\n\u00a0\n\nOther responsibilities\n\nPerforms other responsibilities and duties periodically assigned by supervisor in order to meet operational and / or other requirements.\n\nMinimum Job Requirements:\n\nSecondary education graduate with 4 years working experience\nCandidates with higher academic qualification or more relevant working experience may be considered as Customer Service Advisor.\nMinimum 2-3 years relevant experience in Insurance / Customer Service / hotline service\nHands-on experience in customer service.\nBasic insurance or MPF knowledge would be definitely an advantage.\nYou are required to obtain relevant license if your job involves in regulated activities.\n\nBuild a career with us as we help our customers and the community live healthier, longer, better lives.\n\nYou must provide all requested information, including Personal Data, to be considered for this career opportunity. Failure to provide such information may influence the processing and outcome of your application. You are responsible for ensuring that the information you submit is accurate and up-to-date.", "employment_types": ["Full Time"], "selling_points": ["Employee benefits", "Min. 2 years of customer service exp.", "Hotline enquiries"], "locations": ["Kowloon City Area"], "categories": ["Sales, CS & Business Devpt", "Customer Service - Supervisor / Officer"], "post_time": "2022-01-18T03:01:03Z", "salary": {"currency": null, "max": null, "min": null, "period": "monthly", "term": null}, "salary_visible": false, "title_keywords": ["customer service ambassador"], "responsibilities": ["guidelines", "customer enquiries and complaints", "reports"], "requirements": {"degrees": ["secondary education"], "majors": [], "languages": [], "language_level": [], "hard_skills": ["processing", "basic"], "soft_skills": ["hands-on", "customer service", "accurate", "responsible"], "languages_combined": []}, "experience_required": {"duration": ["4 years", "minimum 2-3 years"], "field": ["relevant working experience", "education", "customer service", "relevant experience", "insurance"]}}, {"job_id": "100003009053785", "location_code": "hk", "company": "Hysan Development Co. Ltd.", "job_title": "Customer Services Representative (Shopping Mall)", "description": "Job Purpose\nTo provide high standard customer service to the shoppers in Hysan\u2019s shopping mall and create an enjoyable shopping experience for the shoppers.\n\nKey Responsibilities\n\nBe responsible for providing high standard concierge service to our tenants and customers in our shopping mall.\nHandle customers' enquiries & requests, support marketing / promotional activities and the daily operations of our property management services.\nSkills, Qualifications and Experience Requirements\n\nDiploma holder with at least 1 year's customer service experience focusing in frontline customer interaction, hotel or shopping mall concierge experience\nPleasant personality, outgoing and presentable Excellent customer service attitude and communication skills\nGood in spoken and written English and Chinese.\nCompetent in spoken Putonghua. Good in PC skills\nWilling to work on shift (5 days/week).\nEntitled to PH (17 days/year).\nWork location: Causeway Bay\nFresh Graduate will also be considered\n\nCandidate with more\u00a0experience will be considered as Senior Customer Services Representative.\n\nAn attractive remuneration package will be offered to the right candidate. \u00a0Interested parties please press \"Apply now\".\n\nFor enquiries, please call/whatsapp:\u00a09760 3380.\n\nHysan is an equal opportunity employer.\u00a0 All information collected will be kept in strict confidence and used solely for recruitment related purposes within the Hysan Group Companies.\n\nYou may get to know more about us through\u00a0www.hysan.com.hk", "employment_types": ["Full Time", "Permanent"], "selling_points": ["Provide high standard customer service to shoppers", "Diploma holder with at least 1-year CS experience", "5-day work, 11-day AL, Dental, Double Pay + Bonus"], "locations": ["Causeway Bay"], "categories": ["Sales, CS & Business Devpt", "Customer Service - Supervisor / Officer", "Property / Real Estate", "Property Management", "Others"], "post_time": "2022-01-17T07:30:50Z", "salary": {"currency": "HKD", "max": 16999, "min": 14000, "period": "monthly", "term": null}, "salary_visible": true, "title_keywords": ["customer services representative"], "responsibilities": ["management", "customer service experience", "communication", "daily operations", "customer service", "promotional activities"], "requirements": {"degrees": ["diploma holder"], "majors": ["hotel"], "languages": ["putonghua", "english", "chinese"], "language_level": ["good"], "hard_skills": ["pc skills"], "soft_skills": ["outgoing", "communication skills", "responsible", "competent", "presentable", "pleasant", "customer service"], "languages_combined": [{"language": "putonghua", "language_level": []}, {"language": "english", "language_level": ["good"]}, {"language": "chinese", "language_level": ["good"]}]}, "experience_required": {"duration": ["at least 1 year"], "field": ["customer service", "frontline customer interaction"]}}, {"job_id": "100003009054478", "location_code": "hk", "company": "CUHK Medical Centre Limited", "job_title": "Customer Service Officer (Call Centre)", "description": "Key Responsibilities\n\nProvide high-quality customer services with appropriate telephone etiquette\nHandle appointment bookings and general enquiries\nUpdate and maintain Frequently Asked Questions\nAssist in compiling various operation procedures, guidelines, working manuals, reports and other documents required\nProvide administrative support to the hospital administration team\nPerform any other duties (in the capacity as Customer Service Officer) as assigned by supervisor(s) from time to time\nShift duty is required\n\nJob Requirements\n\nHolder of a diploma in Health Management, Hospitality Management or Customer Service related disciplines\nAt least 2 years\u2019 relevant working experience, preferably in hospital\nDemonstrates good communication, customer services, interpersonal and problem-solving skills\nAble to handle multi-task independently\nProficient in MS Office applications\nWilling to rotate to different business unites\nProficiency in both spoken and written English and Chinese, including Mandarin\n\nCompensation and Employment Terms\n\nWe provide a unique employment experience for people seeking careers in hospital and healthcare industry; and offer competitive remuneration packages to the successful candidates. Appointment will be made on a 3-year contract with contract-end gratuity, renewable subject to good performance and mutual agreement.\n\nApplication Deadline\n\n30 January 2022\n\nPersonal Information Collection Statement\n\nData collected will only be used for job application processing. Applicants not contacted by CUHK Medical Centre Limited within eight weeks from the application closing date may assume their applications unsuccessful. All personal data collected will be retained for less than 12 months from the application closing date, and will be destroyed thereafter.", "employment_types": ["Full Time"], "selling_points": ["Handle appointment bookings and general enquiries", "Relevant working experience in hospital", "Stable work environment with competitive benefits"], "locations": ["Shatin Area"], "categories": ["Sales, CS & Business Devpt", "Customer Service - Supervisor / Officer", "Insurance", "Others", "Medical Services", "Others"], "post_time": "2022-01-17T09:43:01Z", "salary": {"currency": null, "max": null, "min": null, "period": "monthly", "term": null}, "salary_visible": false, "title_keywords": ["customer service officer"], "responsibilities": ["any other duties", "guidelines", "quality", "procedures", "customer services", "maintain", "reports", "customer service", "provide administrative support", "administration"], "requirements": {"degrees": ["diploma"], "majors": ["hospitality management", "related disciplines"], "languages": ["english", "chinese", "mandarin"], "language_level": ["proficiency"], "hard_skills": ["problem-solving skills", "ms office"], "soft_skills": ["independently", "multi-task", "communication", "customer service", "problem-solving skills", "interpersonal"], "languages_combined": [{"language": "english", "language_level": ["proficiency"]}, {"language": "chinese", "language_level": ["proficiency"]}, {"language": "mandarin", "language_level": ["proficiency"]}]}, "experience_required": {"duration": ["at least 2 years"], "field": ["relevant working experience"]}}, {"job_id": "100003009053152", "location_code": "hk", "company": "Hong Kong School of Motoring", "job_title": "Assistant Operation Officer / Assistant Duty Officer", "description": "Our purpose is to bring safety, quality and\u00a0sustainability\u00a0to life.\nThe Job\u00a0\nAn excellent career opportunity in a listed multinational corporation to deliver superior B2B services to food traders / food manufacturers / food caterers / overseas food retailer clients\nHandle\u00a0inquiries\u00a0and complaints from clients\nIntroduce and promote our services to clients proactively\nCoordinate between external clients and internal technical colleagues to monitor and follow up the progress of testing projects and all related events\nOn-the-job training will be provided to equip our staff to deliver the best service to clients\nThe Person\nDegree / Higher Diploma holder in Science related subjects, preferably in Food Science or Chemistry\nPossess strong client services mindset\nGood command of written and spoken English and Chinese (Cantonese / Mandarin)\nGood interpersonal and communication skill\nFresh graduates are welcome\nImmediately available would be an advantage\nThe Package\nDouble pay\nPerformance bonus\nMedical benefit\nDental plan with discount\n14 days annual leave\nLife insurance\nGood career prospects\n\u00a0Join us in bringing quality and safety to life.", "employment_types": ["Full Time", "Permanent"], "selling_points": ["Clerical duties (data input, records update, etc)", "At least 1 year of customer services experience", "Attractive performance bonus"], "locations": ["Not Specified"], "categories": ["Admin & HR", "Clerical / Admin Staff", "Sales, CS & Business Devpt", "Customer Service - Supervisor / Officer", "Others", "Student / Fresh Graduate / No Experience"], "post_time": "2022-01-17T06:08:40Z", "salary": {"currency": null, "max": null, "min": null, "period": "monthly", "term": null}, "salary_visible": false, "title_keywords": ["officer", "operation officer", "assistant"], "responsibilities": ["coordinate", "inquiries and complaints", "monitor", "testing"], "requirements": {"degrees": ["degree", "higher diploma holder"], "majors": ["science", "chemistry", "food science"], "languages": ["cantonese", "english", "chinese", "mandarin"], "language_level": ["good command"], "hard_skills": [], "soft_skills": ["communication skill", "interpersonal"], "languages_combined": [{"language": "cantonese", "language_level": ["good command"]}, {"language": "english", "language_level": ["good command"]}, {"language": "chinese", "language_level": ["good command"]}, {"language": "mandarin", "language_level": ["good command"]}]}, "experience_required": {"duration": [], "field": []}}, {"job_id": "100003009054438", "location_code": "hk", "company": "Intertek Testing Services H.K. Ltd.", "job_title": "Customer Services Executive (Food)", "description": "Customer Service / Digital Marketing Assistant - Startup\n\nAbout Us\n\nWe are a growing startup in online education. We run a platform that enables teachers and students to learn anywhere, anytime live in our virtual classroom. Our mission is to make skills learning more accessible, more affordable and more effective to everyone.\n\nWe\u2019re looking for a digital assistant marketing person to join our team. This position will be responsible for developing and executing marketing task to grow the user base of our platform.\n\nJob Highlights\n\n\n\nMulti tasking role\nNew and Existing customer acquisition and relationship management\nWith 1-2 years' experience in customer services\nRecommend appropriate courses to new and existing customers\nNew and existing teachers\u2019 review, recruitment and orientation\nAdministrative tasks\nSupporting various marketing projects\u00a0\nJob Description\n\n\nResponsibilities:\n\nUndertake daily administrative tasks including handling enquiries / complaints (Whatsapp/ Social Media / Phone calls)\nSupporting role in organizing various marketing projects\nAssist in the development of digital marketing, social media strategies, new customer acquisition; including SEO / SEM, planning and overseeing of social media campaigns\nIdentify trends and insights, and optimise spend and performance based on the insights\nMeasure and report performance of all implemented digital marketing campaigns\nKeeping up to date with the latest trends and best practices in online marketing and measurement\nSupport the creation of publication contents, ensure digital media contents is up to date, deliver consistent messages, proper usage of the RMHC trademarks and is measured against clear KPIs\nAd hoc duties per assigned including answering online enquiries; new and Existing customer acquisition and relationship management\nDevelop and understanding and knowledge of existing courses to make appropriate courses recommendations\u00a0 to new and existing customers\nNew and existing teachers\u2019 review, recruitment and orientation\nBrainstorm new and creative growth strategies\nRequirements:\u00a0\n\n\nDiploma / Degree holder\n1-2 years of marketing or e-commerce experience is an advantage\nKnowledge in digital marketing, e-commerce and emerging digital technology, social trends and insights preferable\nExcellent spoken and written skills in English and Chinese (Cantonese and Mandarin)\nOrganized, flexible, be able to deal with multiple projects & meet tight deadlines\nHands on experience in digital analytic tools, managing digital content, email, SMS, CRM and social marketing an advantage\nSomeone with understands the energy and passion needed of any successful startup team\n\nAs a startup in rapid growth stages, we offer excellent career development opportunities to unleash your potential, overseas posting and competitive remuneration package.\n\nInterested parties please apply with your full resume stating present and expected salary by clicking \"Apply Now\".\u00a0 Only short-listed candidates will be contacted.", "employment_types": ["Full Time", "Permanent"], "selling_points": ["Fresh Graduates are welcome", "Double Pay, Discretionary Bonus", "On-the-job training for fast development"], "locations": ["Lai Chi Kok"], "categories": ["Sales, CS & Business Devpt", "Customer Service - Supervisor / Officer", "Sciences, Lab, R&D", "Food Science", "Account Servicing"], "post_time": "2022-01-17T09:33:51Z", "salary": {"currency": null, "max": null, "min": null, "period": "monthly", "term": null}, "salary_visible": false, "title_keywords": ["executive"], "responsibilities": ["phone calls", "ad hoc duties", "social media campaigns", "digital marketing campaigns", "measurement", "develop", "kpis", "publication", "report", "social media", "management", "seo", "review", "marketing projects", "digital marketing", "contents", "administrative tasks", "recruitment", "sem", "social media strategies", "planning"], "requirements": {"degrees": ["diploma", "degree holder"], "majors": [], "languages": ["cantonese", "english", "chinese", "mandarin"], "language_level": ["excellent"], "hard_skills": ["rapid", "e-commerce"], "soft_skills": ["flexible", "organized", "meet tight deadlines", "hands on"], "languages_combined": [{"language": "cantonese", "language_level": ["excellent"]}, {"language": "english", "language_level": ["excellent"]}, {"language": "chinese", "language_level": ["excellent"]}, {"language": "mandarin", "language_level": ["excellent"]}]}, "experience_required": {"duration": ["1-2 years"], "field": ["digital", "marketing", "digital content", "e-commerce"]}}, {"job_id": "100003009054026", "location_code": "hk", "company": "Ponder Deep Limited", "job_title": "Customer Service / Digital Marketing Assistant - Startup", "description": "In the heart of the role:\n\n\n\nHandle feedbacks, complaints and compliments including investigations and liaise with team leaders, supervisors, third parties, to collect information and resolving issues\nResponsible to reply to customer by phone/ in writing\nEscalate case to Legal / Medical Director for advice when necessary\nPrepare meeting agenda and meeting notes\nPrepare report for periodically review by relevant parties, including basic data management and analysis\nMake recommendations based on the feedback themes and trends to improve customer experience, ensuring the improvement actions are tracked through to completion\nOther duties as required by line manager\n\nDesired Qualification & Experience:\n\n\n\nBachelor\u2019s Degree, with relevant customer service experience preferred\nA minimum of 5 years of customer service/ customer experience/complaint handling related experience\nExperience in medical/insurance industry and complaint handling is definitely advantage\nGood problem solving skill with customer centric mindset;\nDemonstrate ability to work independently\nExcellent written and verbal communications in English, Chinese and Mandarin\nProficient in Microsoft Office Suite - Word, Excel, PowerPoint\n\n(All applications will be treated in strict confidence and data collected will be used for recruitment purposes only)", "employment_types": ["Full Time", "Permanent"], "selling_points": ["A startup in rapid growth stages", "Fast growing new industry", "Working together with the founding core team"], "locations": ["Kwun Tong"], "categories": ["Sales, CS & Business Devpt", "Customer Service - Supervisor / Officer", "Marketing / Public Relations", "Marketing - General / Support"], "post_time": "2022-01-17T08:07:54Z", "salary": {"currency": null, "max": null, "min": null, "period": "monthly", "term": null}, "salary_visible": false, "title_keywords": ["customer service", "digital marketing", "assistant"], "responsibilities": ["make recommendations", "prepare report", "management", "other duties", "data", "analysis", "review", "customer service experience", "customer service", "recruitment", "liaise with", "insurance"], "requirements": {"degrees": ["degree", "bachelor"], "majors": [], "languages": ["english", "chinese", "mandarin"], "language_level": ["excellent"], "hard_skills": ["excel", "basic", "data management", "analysis", "word", "powerpoint", "problem solving", "make", "microsoft office suite"], "soft_skills": ["make recommendations", "work independently", "confidence", "responsible", "customer service", "problem solving skill"], "languages_combined": [{"language": "english", "language_level": ["excellent"]}, {"language": "chinese", "language_level": ["excellent"]}, {"language": "mandarin", "language_level": ["excellent"]}]}, "experience_required": {"duration": ["minimum of 5 years"], "field": ["related", "customer service", "insurance industry", "medical"]}}, {"job_id": "100003009055889", "location_code": "hk", "company": "Quality HealthCare Medical Services Ltd", "job_title": "Assistant Manager, Customer Relations", "description": "\u00a0Job duties\nExecute customer service activities in APAC region.\nHandle Order-To-Cash transactions in SAP system\nRespond customer\u2019s enquiries in timely and professional manner\nHandle Export License and all shipping documents in compliance with regulatory requirement\nClose interaction with different internal stakeholders including plant, Regulatory, Quality, Planning to ensure all the orders/shipments to comply with requirement and deliver on-time\nAssist in customer service improvement projects\nOther duties as assigned\n\nEducations & Experiences\n\nUniversity degree in supply chain, logistics or business management\nIntern experience in Supply Chain is preferred\n\nSkills & Qualifications\n\nFluent in English and Korean.\u00a0Cantonese or Mandarin is a plus\nProficient in Excel, Powerpoint, and Database\nStrong motives and fast learner\u00a0with proactive approach\nCreative and dynamic\nCan work within deadlines\nPassionate for challenges\n\nInterested parties please send full resume with your availability, present and expected salary, and date of availability by clicking \"Apply Now\".\n\nAll information received will be kept in strict confidence and will be treated only for employment related purposes.", "employment_types": ["Full Time", "Permanent"], "selling_points": ["Customer Service", "Customer Centric", "Complaints Handling"], "locations": ["Kowloon Bay"], "categories": ["Sales, CS & Business Devpt", "Customer Service - Supervisor / Officer", "Insurance", "Others", "Medical Services", "Others"], "post_time": "2022-01-18T03:03:20Z", "salary": {"currency": null, "max": null, "min": null, "period": "monthly", "term": null}, "salary_visible": false, "title_keywords": ["assistant manager,"], "responsibilities": ["shipping documents", "management", "other duties", "compliance", "professional manner", "quality", "transactions", "customer service", "logistics", "database", "planning"], "requirements": {"degrees": ["university degree"], "majors": ["business"], "languages": ["cantonese", "english", "mandarin", "korean"], "language_level": ["fluent"], "hard_skills": ["business management", "excel", "plus", "sap", "powerpoint", "dynamic"], "soft_skills": ["passionate", "proactive", "timely", "customer service", "dynamic", "creative", "fast learner"], "languages_combined": [{"language": "cantonese", "language_level": []}, {"language": "english", "language_level": ["fluent"]}, {"language": "mandarin", "language_level": []}, {"language": "korean", "language_level": ["fluent"]}]}, "experience_required": {"duration": [], "field": ["supply chain"]}}, {"job_id": "100003009054873", "location_code": "hk", "company": "In N Out International Corporate Limited", "job_title": "Sales / Customer Service Officer", "description": "\u8077\u8cac:\n\n\u8ca0\u8cac\u8a3a\u6240\u63a5\u5f85\u3001\u96fb\u8a71\u9810\u7d04\u53ca\u767b\u8a18\u670d\u52d9\n\u63a5\u807d\u96fb\u8a71\u53ca\u8655\u7406\u4e00\u822c\u67e5\u8a62\n\u8a02\u8cfc\u6587\u5177\n\u4e00\u822c\u6587\u66f8\u5de5\u4f5c\n\u5354\u52a9\u8a3a\u6240\u65e5\u5e38\u904b\u4f5c\n\n\u8981\u6c42:\n\n\u4e2d\u4e94\u7a0b\u5ea6\u53ca2\u5e74\u76f8\u95dc\u5de5\u4f5c\u7d93\u9a57\n\u52e4\u596e\u597d\u5b78\u3001\u5177\u8cac\u4efb\u611f\u3001\u6709\u6548\u7387\u53ca\u5718\u9ad4\u5408\u4f5c\u7cbe\u795e\n\u70ba\u4eba\u7a4d\u6975\u6a02\u89c0\u3001\u71b1\u8aa0\u6709\u79ae\u3001\u5de5\u4f5c\u7a4d\u6975\u4e3b\u52d5\u3001\u5bcc\u8cac\u4efb\u611f\n\u826f\u597d\u4e2d\u82f1\u6587\u8b80\u5beb\u80fd\u529b\uff0c\u80fd\u8aaa\u666e\u901a\u8a71\n\u61c2\u4e00\u822c\u96fb\u8166\u64cd\u4f5c\u00a0(Word / Excel)\n\u5373\u6642\u4e0a\u73ed\u8005\u512a\u5148\n\n\u6709\u610f\u8005\u8acb\u5c07\u500b\u4eba\u5c65\u6b77\u53ca\u8981\u6c42\u5f85\u9047\u96fb\u90f5\u81f3 Chiron Healthcare Group Limited\n\n(\u7533\u8acb\u4eba\u6240\u63d0\u4f9b\u8cc7\u6599\u53ea\u4f5c\u62db\u8058\u4e0a\u8ff0\u8077\u4f4d\u7528\u9014\uff0c\u7d55\u5c0d\u4fdd\u5bc6)", "employment_types": ["Full Time"], "selling_points": [], "locations": ["Aberdeen"], "categories": ["Sales, CS & Business Devpt", "Customer Service - Supervisor / Officer", "Retail Sales", "Direct Sales"], "post_time": "2022-01-17T12:14:16Z", "salary": {"currency": "HKD", "max": 19999, "min": 14000, "period": "monthly", "term": null}, "salary_visible": true, "title_keywords": ["customer service officer", "sales"], "responsibilities": [], "requirements": {"degrees": [], "majors": [], "languages": [], "language_level": [], "hard_skills": ["excel", "word"], "soft_skills": [], "languages_combined": []}, "experience_required": {"duration": [], "field": []}}, {"job_id": "100003009054049", "location_code": "hk", "company": "Guerbet Asia Pacific Limited", "job_title": "Junior Customer Service Representative", "description": "We are a growing company expanding our business and we are inviting passionate and enthusiastic people to join our team!\n\nResponsibilities:\n\nSell the company's service and products to customers\nProvide excellent customer service and handle customer enquiries\nAssist sales/operation team in daily operation\nHandle and follow-up on customer orders, such as prepare quotation and agreement\nCreate reports to management according to internal guidelines to monitor customer and operational performances\nPerform ad-hoc tasks\n* The ideal candidate is a sales-driven, customer-oriented, execution-focused individual.\n\n\nRequirements:\n\nForm 7 or above\n2 years or above of customer service/sales or frontline experience\nFluent in spoken and written Cantonese and English\nComputer skills in Microsoft Office, English and Chinese typing\nCheerful, polite, helpful and responsible personality\nImmediately available would be an advantage", "employment_types": ["Contract", "Internship"], "selling_points": ["Execute customer service activities", "Assist in customer service improvement projects", "Fluent in English and Korean"], "locations": ["Hung Hom"], "categories": ["Sales, CS & Business Devpt", "Customer Service - Supervisor / Officer"], "post_time": "2022-01-17T08:12:23Z", "salary": {"currency": null, "max": null, "min": null, "period": "monthly", "term": null}, "salary_visible": false, "title_keywords": ["customer service representative", "junior"], "responsibilities": ["management", "handle customer enquiries", "guidelines", "ad-hoc tasks", "quotation", "daily operation", "monitor", "customer service", "reports"], "requirements": {"degrees": [], "majors": [], "languages": ["cantonese", "english", "chinese"], "language_level": ["fluent"], "hard_skills": ["computer skills", "typing", "microsoft office"], "soft_skills": ["cheerful", "customer service", "polite", "responsible"], "languages_combined": [{"language": "cantonese", "language_level": ["fluent"]}, {"language": "english", "language_level": ["fluent"]}, {"language": "chinese", "language_level": []}]}, "experience_required": {"duration": ["2 years"], "field": ["customer service"]}}, {"job_id": "100003009055471", "location_code": "hk", "company": "HKT Consumer Group", "job_title": "Digital Customer Service Executive (Email and Live Chat) (5-day work)", "description": "<< Welcome applicants from Aviation / Hospitality industry! >>\n\nYour Role\n\nHandle customer\u2019s enquiries, complaints and technical support via email and web chat in a timely and professional manner\n\nWorking location\n\nShatin (nearby City One Town)\n\nWorking hours\n\n42.5 hours per week, 5-day work\nWilling to take up day or night shift duty (optional to candidates) and work on weekend & public holidays\nPreferably available to take night shift (15:30-00:00 or 17:30-02:00) with shift allowance\n\nTo succeed in this role\n\nF.5 / DSE or above with minimum 1 year of customer service experience\nCustomer-oriented and good caring attitude\nChinese typing using \u901f\u6210 / \u5009\u9821 input method at required speed of 30 wpm is preferred\nGood command of written English and Chinese\nHands-on experience of PC operations and Internet knowledge\n\nWe offer you\n\nAttractive basic salary with commission & sales incentive\nNight shift allowance\nComprehensive training with pay\n14-day annual leave\nMarriage leave\nMaternity leave\nPaternity leave\nCareer development opportunities\nMedical insurance\nMPF/Provident Fund schemes\nStaff offer and staff recreation\nSponsorship of external study\n\nApplication method\u00a0\n\nI want to make an interview appointment:\u00a06029 4292\u00a0\u00a0https://bit.ly/3tidcUa\u00a0\n\nEnquiry hotline:\u00a028887388\u00a0\n\nEmail:\u00a0career-consumer@pccw.com \u00a0", "employment_types": ["Full Time"], "selling_points": [], "locations": ["Shatin Area"], "categories": ["Sales, CS & Business Devpt", "Call Centre", "Customer Service - Supervisor / Officer"], "post_time": "2022-01-18T02:37:56Z", "salary": {"currency": null, "max": null, "min": null, "period": "monthly", "term": null}, "salary_visible": false, "title_keywords": ["customer service executive"], "responsibilities": ["technical support", "professional manner"], "requirements": {"degrees": [], "majors": [], "languages": [], "language_level": [], "hard_skills": ["web chat"], "soft_skills": ["timely"], "languages_combined": []}, "experience_required": {"duration": [], "field": []}}, {"job_id": "100003009056110", "location_code": "hk", "company": "DHL EXPRESS (HONG KONG) LIMITED", "job_title": "Customer Service Representative (Tracing Team)", "description": "CHINA MOBILE HONG KONG COMPANY LIMITED\u00a0(\"CMHK\") is the wholly-owned subsidiary of China Mobile Limited (HKEx: 941) (NYSE: CHL), which ranks 65th on the Fortune Global 500.\u00a0\u00a0\n\nOur company strives to offer superior service experience and to become the preferable digital partner for customers. We are preserving an environment with trust, responsibility and caring. At CMHK, we commit to maximizing people\u2019s potential and paving the way toward success for every striver. We are now inviting high caliber professional to join us.\u00a0\n\nDivision:\u00a0Customer Service Division\n\nIn this position, you will:\n\nHandle customer enquiries in an efficient and accurate manner on various social media platform (Facebook, Whatsapp, live chat);\nEstablish and maintain good customer relationship by providing one-stop customer care services;\nInput and update customer record\u00a0accurately;\n\nTo be successful in this position, you should meet the following requirements:\n\nSecondary education or above;\n1 year relevant experience preferably in customer service;\nCustomer service oriented, willing to work under pressure, self-motivated, pleasant personality;\nGood communication and interpersonal skills;\nProficient in Cantonese, good command of English and Putonghua;\nCandidate with more experience and management skills may be considered as\u00a0Senior Customer Care Specialist.\n\nWhen you work:\u00a0\u00a0\n\n\n8.75 hours per day within 7:30am to 12:00am (including 1 hour\u00a0meal break)\n5-day per week in shift pattern (including Sunday and Public Holiday)\n\nWhat you enjoy:\n\nDouble pay\nDiscretionary Performance bonus\nAnnual Leave\nShift Allowance\nMonthly Performance Bonus\nLife insurance\nMedical insurance\nMeal allowance\nEducation subsidies\nBirthday gift\nMarriage leave\nBirthday leave\nStaff discount\n\nCMHK is committed to be an equal opportunity employer. We offer exceptional benefits package and the opportunity to work in a challenging environment. Personal data provided by applicants will be treated strictly in accordance with our personal data policy and for recruitment purposes only.\n\nPlease submit your application to us by clicking the APPLY NOW button and send your full resume with your availability, current and expected salary to us.", "employment_types": ["Full Time", "Permanent"], "selling_points": ["Responsible for providing quality customer service", "More than 1 year customer service experience", "Post-secondary education"], "locations": ["Ngau Tau Kok"], "categories": ["Sales, CS & Business Devpt", "Customer Service - Supervisor / Officer", "Transportation & Logistics", "Supply Chain"], "post_time": "2022-01-18T03:19:57Z", "salary": {"currency": null, "max": null, "min": null, "period": null, "term": null}, "salary_visible": false, "title_keywords": ["customer service representative"], "responsibilities": ["social media", "management", "handle customer enquiries", "communication", "maintain", "customer service", "facebook", "insurance", "work under pressure"], "requirements": {"degrees": ["secondary education"], "majors": [], "languages": ["cantonese", "putonghua", "english"], "language_level": ["good command", "proficient"], "hard_skills": ["mobile", "facebook", "whatsapp"], "soft_skills": ["efficient", "self-motivated", "customer service oriented", "work under pressure", "pleasant", "committed", "customer service", "communication and interpersonal skills", "accurate", "superior"], "languages_combined": [{"language": "cantonese", "language_level": ["proficient", "good command"]}, {"language": "putonghua", "language_level": ["good command"]}, {"language": "english", "language_level": ["good command"]}]}, "experience_required": {"duration": ["1 year"], "field": ["management", "customer care", "customer service", "relevant experience", "digital"]}}, {"job_id": "100003009056551", "location_code": "hk", "company": "Cre8 (Greater China) Limited", "job_title": "Customer Service Executive/ Customer Service Assistant (Financial Press)", "description": "Working Location: Ngau Tau Kok\nWorking Hours: Monday - Sunday, including public holidays 07:30-22:30 (5 days, average 42.5 hours per week)\nResponsibilities:\nYou will be responsible for providing quality customer services to both local and overseas clients through 24-hours hotline. You are required to handle shipment tracing and customer complaints, as well as to resolve customer enquiries and problems.\nRequirements:\nPost-secondary education (English & Chinese passed in HKCEE / HKDSE or equivalent)\nMore than 1 year customer service experience, preferably in logistic industry (Candidate with more than 3 years customer service experience will be considered as Customer Service Executive)\nGood command of spoken & written English and Chinese, proficiency in Mandarin is an advantage\nGood PC knowledge and typing skill with 40 wpm\nEffective interpersonal, communications, problem solving and telephone handling skills\nCustomer oriented, flexible, initiative and able to work under pressure\nFresh graduates of Degree/ Associate Degree with experiences in direct customer interfaces will also be considered\nApplication:\nClick \"Apply Now\" or apply on line via the following link:https://dhlexpress.taleo.net/careersection/ex/jobdetail.ftl?job=2100ATJ&iniurl.src=CWS-10001&tz=GMT%2B08%3A00&tzname=Asia%2FShanghai\nalso indicating your current and expected salary, and availability.\u00a0 For more job opportunities, please visit our website at https://www.dpdhl.jobs/\nPersonal Information Collection Statement pertaining to Recruitment\nDHL Express (Hong Kong) Limited / DHL Aviation (Hong Kong) Limited (\u201cDHL\u201d) is committed to protecting and respecting your privacy in accordance with the Personal Data (Privacy) Ordinance of Hong Kong (the \u201cOrdinance\u201d) and DHL\u2019s Personal Data Protection Policy (the \u201cPolicy\u201d) at https://www.dhl.com/hk-en/home/footer/local-privacy-notice.html\nBy proceeding to respond to this recruitment advertisement, you consent that we may use, retain, process, transfer or otherwise handle the personal data that we collect from you for recruitment,\u00a0 application processing, assessment and communication purposes (including any other purposes directly related thereto) in accordance with the Policy.\nAll personal data of unsuccessful applicants will be retained for future recruitment purposes for a period of not more than two (2) years after which such data will be destroyed.\nYou have the right at any time to make a data access or correction request concerning your personal data held by us. In addition, you may request us to delete your personal data that is no longer required for the relevant purposes which you have given consent. Should you wish to exercise such rights or have any question in relation to your personal data or the Policy, please contact our Human Resources Division in writing via \"Apply Now\"", "employment_types": ["Full Time", "Permanent", "Temporary", "Contract"], "selling_points": ["5 days work, overtime payment and shift allowance", "career development opportunities", "flexibility working hour"], "locations": ["Central"], "categories": ["Admin & HR", "Clerical / Admin Staff", "Banking / Finance", "Financial Services", "Sales, CS & Business Devpt", "Customer Service - Supervisor / Officer"], "post_time": "2022-01-18T04:46:12Z", "salary": {"currency": null, "max": null, "min": null, "period": "monthly", "term": null}, "salary_visible": false, "title_keywords": ["customer service assistant", "customer service executive"], "responsibilities": ["customer enquiries", "customer complaints", "quality", "customer services"], "requirements": {"degrees": ["associate degree", "degree", "hkdse", "secondary education"], "majors": [], "languages": ["english", "chinese", "mandarin"], "language_level": ["advantage", "proficiency", "good command"], "hard_skills": ["no", "typing", "html", "problem solving", "make", "pc knowledge", "processing"], "soft_skills": ["flexible", "problem solving", "committed", "communication", "customer service", "interpersonal", "initiative", "work under pressure"], "languages_combined": [{"language": "english", "language_level": ["proficiency", "advantage", "good command"]}, {"language": "chinese", "language_level": ["proficiency", "advantage", "good command"]}, {"language": "mandarin", "language_level": ["proficiency", "advantage", "good command"]}]}, "experience_required": {"duration": ["3 years", "1 year"], "field": ["customer service"]}}, {"job_id": "100003009054754", "location_code": "hk", "company": "Shopoholic Private Limited", "job_title": "E-Commerce Customer Support Specialist", "description": "Job Highlights:\n\n5-day work, overtime payment and shift allowance;\nAble to work flexibility working hour;\nFresh graduate welcome;\n\nJob Responsibilities:\n\nPerform project management for the corporate clients with all in house and non-in-house activities, monitor page turn, assure quality and deliver the documents to client on the timely basis;\nCommunicate and cooperation in a close working relationship between clients and the internal departments;\n\n\u00a0Job Requirements:\n\nUniversity graduates in any discipline;\n2 years of working experience in customer service, administration or financial printing will be an advantaged;\nFluent in both written and spoken English, Cantonese and Mandarin;\nAbility to work effectively in a team environment;\nMature, self-motivated and good communication skills to deal with corporate clients, investment bankers and lawyers;\nAble to work under pressure and meet tight deadline;\nRequired to work shift duties with shift allowance;\nWilling to work overtime;\nApplicants with less experience will be considered as Customer Service Assistant;\nFresh graduate is also welcome;\n\nWe offer an attractive remuneration package and fringe benefits to the right candidate.\n\nTo apply, please send your full resume and expected salary\u00a0by clicking \"Apply Now\".\n(Personal data provided will be used for recruitment purpose only)", "employment_types": ["Full Time", "Contract"], "selling_points": [], "locations": ["Tsim Sha Tsui"], "categories": ["Sales, CS & Business Devpt", "Customer Service - Supervisor / Officer"], "post_time": "2022-01-18T04:15:56Z", "salary": {"currency": "HKD", "max": 19999, "min": 17000, "period": "monthly", "term": null}, "salary_visible": true, "title_keywords": ["specialist"], "responsibilities": ["project management", "monitor", "quality"], "requirements": {"degrees": ["fresh graduate"], "majors": [], "languages": ["cantonese", "english", "mandarin"], "language_level": ["fluent"], "hard_skills": [], "soft_skills": ["work effectively", "communication skills", "self-motivated", "work overtime", "mature", "customer service", "meet tight deadline", "work under pressure"], "languages_combined": [{"language": "cantonese", "language_level": ["fluent"]}, {"language": "english", "language_level": ["fluent"]}, {"language": "mandarin", "language_level": ["fluent"]}]}, "experience_required": {"duration": ["2 years"], "field": ["customer service", "financial", "administration"]}}, {"job_id": "100003009048698", "location_code": "hk", "company": "Henderson Land Development Company Limited", "job_title": "CUSTOMER SERVICES OFFICER / ASSISTANT CUSTOMER SERVICES OFFICER", "description": "Job duty\n\nAs an E-Commerce Customer Experience Representative, you are tasked with the all-important responsibilities of caring for our customers' needs, building customer loyalty, and representing the brand. You will provide customer care support through chat, email, and calls to deliver #happier customer experience.\nTo provide customer service support/troubleshooting support through all social media chats/phone call/whatsapp to customers\nCollaborate with internal parties for customers' enquiries and/ or complaints\nTo work closely with team supervisors to ensure escalated issues are handled in a timely and correct manner\nGather customer feedback to enhance service and customer experience\nMaintain up-to-date member information\nWho are we looking for?\n\nShopline / jewels experience is an advantage\nAt least 2-3 years of CS and ecommerce experience would be an advantage\u00a0\nStrong communication skills with the ability to communicate effectively with internal and/or external contacts\nHighly self-motivated, energetic with positive attitude and a team player\nPassion for building customer loyalty by carefully listening, building rapport and providing extraordinary customer care, using strong written and verbal communication skills\nConfident computer excel skills are vital as you\u2019ll be using multiple tools and systems daily\nExcellent time management & multi-tasking skills\nBilingual in a combination of two of the following, Cantonese, Mandarin or English\nWorking hours:\n\n5 day work a week (Monday-Sunday, including Public Holiday);\n9 working hours required daily from 0900-1900\n2 days need to work at night shift\u00a0\nContract base", "employment_types": ["Full Time", "Permanent"], "selling_points": ["Medical Allowance", "Education Allowance", "Free Lunch"], "locations": ["North Point"], "categories": ["Sales, CS & Business Devpt", "Customer Service - Supervisor / Officer", "Property / Real Estate", "Others", "Others"], "post_time": "2022-01-14T07:03:50Z", "salary": {"currency": null, "max": null, "min": null, "period": "monthly", "term": null}, "salary_visible": false, "title_keywords": ["assistant customer services officer", "customer services officer"], "responsibilities": ["provide customer service", "troubleshooting support", "social media", "collaborate with", "maintain up-to-date member information", "management", "representing the brand", "customers' needs", "systems", "customer care support", "communication", "gather customer feedback", "building customer loyalty", "internal parties"], "requirements": {"degrees": [], "majors": [], "languages": ["cantonese", "english", "mandarin"], "language_level": [], "hard_skills": ["excel", "whatsapp", "e-commerce"], "soft_skills": ["confident", "communication skills", "self-motivated", "passion for", "timely", "troubleshooting", "positive attitude", "time management", "customer service", "multi-tasking skills", "team player", "energetic"], "languages_combined": [{"language": "cantonese", "language_level": []}, {"language": "english", "language_level": []}, {"language": "mandarin", "language_level": []}]}, "experience_required": {"duration": ["at least 2-3 years"], "field": ["ecommerce", "customer care", "brand", "e-commerce", "cs"]}}, {"job_id": "100003009055324", "location_code": "hk", "company": "Sinotrans (HK) Warehousing Limited", "job_title": "Customer Services Executive (Logistic/Freight Forwarding)", "description": "\u00a0Ref. No.: JDB/HLD30/CSO\n\nForm 7 / HKDSE or above\n3 - 5 years\u2019 working experience in customer services (particular in property handover and real estate aftersales services) is preferable, candidates with property management, building technical and sales knowledge is an advantage\nGood command of both written and spoken English and Chinese, fluency in Putonghua\nGood telephone manner\nProficiency in PC applications including Chinese word-processing is\u00a0a must\nMature, patient and self-motivated; good communication skill in collaboration with different people\nWilling to work overtime and attend on-site coordination works when required\nCandidates with less experience or lower qualification will be considered for the post of Assistant Customer Services Officer\n\nAttractive salary and fringe benefits will be offered to the successful candidates. Please apply with full resume by mail to\u00a0Human Resources Department, Henderson Land Development Co. Ltd., 71/F, Two International Finance Centre, 8 Finance Street, Central, Hong Kong\u00a0or by fax at\u00a02905 1855\u00a0or visit our homepage at\u00a0http://www.hld.com or\u00a0by clicking \"Apply Now\".\n\n(Please quote the ref. no. on letter)\u00a0\n\nPersonal data provided by job applicants will be used for recruitment purpose only.\u00a0", "employment_types": ["Full Time"], "selling_points": ["CS experience in Logistic/freight forwarding ind", "Provide quality services both internal/external", "Double Pay w/ competitive remuneration package"], "locations": ["Tin Shui Wai"], "categories": ["Sales, CS & Business Devpt", "Customer Service - Supervisor / Officer", "Transportation & Logistics", "Freight Forwarding", "Inventory / Warehousing"], "post_time": "2022-01-18T02:12:03Z", "salary": {"currency": null, "max": null, "min": null, "period": "monthly", "term": null}, "salary_visible": false, "title_keywords": ["executive"], "responsibilities": ["communication", "management", "site coordination", "customer services"], "requirements": {"degrees": ["hkdse"], "majors": [], "languages": ["putonghua", "english", "chinese"], "language_level": ["fluency", "proficiency", "good command"], "hard_skills": ["no", "chinese word-processing", "pc applications"], "soft_skills": ["self-motivated", "work overtime", "communication skill", "mature", "coordination", "patient", "telephone manner"], "languages_combined": [{"language": "putonghua", "language_level": ["fluency", "good command"]}, {"language": "english", "language_level": ["good command"]}, {"language": "chinese", "language_level": ["proficiency", "good command"]}]}, "experience_required": {"duration": ["3 - 5 years"], "field": ["management", "customer services"]}}, {"job_id": "100003009055858", "location_code": "hk", "company": "AIA Hong Kong and Macau", "job_title": "Customer Service Ambassador (Hotline - Agency & IFA Enquiry)", "description": "Job Responsibilities:\u00a0\u00a0\nTo\u00a0handle and follow up enquiries from customers, overseas agents and inner group company\u00a0\nTo collaborate closely with internal and external operations to deliver quality services\nTo\u00a0input data in operating system timely and accurately\n\nJob Requirements:\n\nProficiency in written and spoken English is a must.\nUniversity Graduate or above\n2-3 years relevant working experience in customer service in logistics / freight forwarding industries\nIndependent, responsible, well-organized & able to work under pressure\nProficiency in using MS Office applications\nImmediately available is preferable", "employment_types": ["Full Time"], "selling_points": ["Agency & IFA Enquiry", "Min. 2 years of work experience", "With IIQE license is an advantage"], "locations": ["Kowloon City Area"], "categories": ["Sales, CS & Business Devpt", "Customer Service - Supervisor / Officer"], "post_time": "2022-01-18T03:01:08Z", "salary": {"currency": null, "max": null, "min": null, "period": "monthly", "term": null}, "salary_visible": false, "title_keywords": ["customer service ambassador"], "responsibilities": ["collaborate", "operations", "quality", "data"], "requirements": {"degrees": ["university graduate or above"], "majors": [], "languages": ["english"], "language_level": ["proficiency"], "hard_skills": ["ms office"], "soft_skills": ["independent", "responsible", "well-organized", "customer service", "work under pressure"], "languages_combined": [{"language": "english", "language_level": ["proficiency"]}]}, "experience_required": {"duration": ["2-3 years"], "field": ["customer service", "logistics", "relevant working experience"]}}, {"job_id": "100003009055635", "location_code": "hk", "company": "The Legend Financial Consultancy", "job_title": "Customer Service Coordinator/ Customer Service Executive (welcome fresh graduate) CSO 0118", "description": "Bring your career aspirations to life with AIA!\n\nResponsible for handling customer inquires via telephone, email, or online platform\n\nRoles and Responsibilities:\n\nHotline Operation\n\nHandles customer enquiries and complaints regarding all activities in Operation process such as Underwriting, Policy Owner Service, and Claims for different line of business\nReports problems, potential crisis and complaint to supervisor for service improvement;\nMakes outbound call to customers for follow-up cases;\nExecutes empowerment guidelines;\n\nAdministrative Works\n\nDocuments call activities in system\nDocuments follow up items in log sheet or send email to AIAHK Business Partners\nWorks closely with AIAHK Business Partners to resolve the complaints and uncertain issues\n\u00a0\n\nOther responsibilities\n\nPerforms other responsibilities and duties periodically assigned by supervisor in order to meet operational and / or other requirements.\n\nMinimum Job Requirements:\n\nSecondary education graduate with 4 years working experience\nCandidates with higher academic qualification or more relevant working experience may be considered as Customer Service Advisor.\nMinimum 2-3 years relevant experience in Insurance / Customer Service / hotline service\nHands-on experience in customer service.\nBasic insurance or MPF knowledge would be definitely an advantage.\nYou are required to obtain relevant license if your job involves in regulated activities.\n\nBuild a career with us as we help our customers and the community live healthier, longer, better lives.\n\nYou must provide all requested information, including Personal Data, to be considered for this career opportunity. Failure to provide such information may influence the processing and outcome of your application. You are responsible for ensuring that the information you submit is accurate and up-to-date.", "employment_types": ["Full Time", "Part Time", "Permanent", "Contract"], "selling_points": [], "locations": ["Not Specified"], "categories": ["Sales, CS & Business Devpt", "Customer Service - Supervisor / Officer", "Others", "Management", "Management Trainee"], "post_time": "2022-01-18T02:48:59Z", "salary": {"currency": "HKD", "max": 24999, "min": 14000, "period": "monthly", "term": null}, "salary_visible": true, "title_keywords": ["customer service executive", "customer service coordinator"], "responsibilities": ["guidelines", "customer enquiries and complaints", "reports"], "requirements": {"degrees": ["secondary education"], "majors": [], "languages": [], "language_level": [], "hard_skills": ["processing", "basic"], "soft_skills": ["hands-on", "customer service", "accurate", "responsible"], "languages_combined": []}, "experience_required": {"duration": ["4 years", "minimum 2-3 years"], "field": ["relevant working experience", "education", "customer service", "relevant experience", "insurance"]}}, {"job_id": "100003009054894", "location_code": "hk", "company": "Emperor Financial Services Group", "job_title": "Customer Service Officer (Financial Services)", "description": "CS 0118\n\nResponsibilities :\n\nProvide excellent customer services and sales to customers\nPerform daily duties including quotations and related document preparation\nNegotiate and follow up with customers on maintenance renewal and value-added service status.\n\n\n\nRequirements:\u00a0 \u00a0\u00a0 \u00a0 \u00a0 \u00a0 \u00a0 \u00a0 \u00a0 \u00a0 \u00a0\n\nDiploma or above in business or related disciplines\nFresh graduates are also welcome\nCustomer-oriented mindset with a passion to provide excellent service\nStrong sense of responsibility, Outgoing & Willing to learn\nAbility to multi-task in a fast-paced environment\nProficiency in PC operations including Microsoft Office\n\n\n\nWe offer:\n\nAttractive incentive bonus & travel incentive\nCareer path\nStructured training program\nFlexible working hours \u00a0\n\nInterested parties, please send us a resume with\u00a0Date available and\u00a0EXPECTED SALARY\u00a0", "employment_types": ["Full Time", "Permanent"], "selling_points": ["customer service or financial related exp", "identify sales opportunities", "Shift duty is required"], "locations": ["Wan Chai"], "categories": ["Sales, CS & Business Devpt", "Customer Service - Supervisor / Officer", "Account Servicing", "Tele-sales (Telemarketing)"], "post_time": "2022-01-17T12:55:33Z", "salary": {"currency": null, "max": null, "min": null, "period": null, "term": null}, "salary_visible": false, "title_keywords": ["customer service officer"], "responsibilities": ["maintenance", "customer services"], "requirements": {"degrees": ["diploma or above"], "majors": ["related disciplines", "business"], "languages": [], "language_level": [], "hard_skills": ["pc operations", "microsoft office"], "soft_skills": ["outgoing", "multi-task", "sense of responsibility", "fast-paced environment", "willing to learn", "customer-oriented"], "languages_combined": []}, "experience_required": {"duration": [], "field": []}}, {"job_id": "100003009056108", "location_code": "hk", "company": "DHL EXPRESS (HONG KONG) LIMITED", "job_title": "Customer Service Executive (Claims & Complaint)", "description": "Responsibilities:\n\nProvide qualify customer services through inbound calls, emails, and live chats\nUnderstand customers' needs and identifying sales opportunities\nWork closely with the Business Development and Marketing team on latest products, services and campaigns\nRoute qualified opportunities to the appropriate sales executives for further development and closure\nShift duty is required\n\nRequirements:\n\nHigher diploma or above with at least 1 year' relevant experience\nType-3 SFC license and finance-related experience\u00a0is a plus\nProficiency in CRM software such as Salesforce would be an advantage\nProficiency in Microsoft Office and Chinese word processing\nExcellent communication skills in both verbal and written\n\nWe offer\u00a05-day-work\u00a0week\u00a0with competitive remuneration and benefit packages to the right candidate. Interested parties please send your application letter, resume, expected salary and availability to Human Resources Department, 28/F, Emperor Group Centre, 288 Hennessy Road, Wanchai, Hong Kong or\u00a0by clicking the\u00a0Apply Now\u00a0button below.\n\nWe are an equal opportunity employer and welcome applications from all qualified candidates. The information provided will be treated in strict confidence and be used only for consideration of your application for relevant / similar posts within the Emperor Group. Applicants not hearing from us within four weeks from the date of advertisement may consider their applications unsuccessful. We retain the unsuccessful applications for a maximum period of\u00a024 months.", "employment_types": ["Full Time", "Permanent"], "selling_points": ["Handle inquiries, complaints and claims", "Participating in customer loyalty program", "Reflecting customers' feedback to management,"], "locations": ["Ngau Tau Kok"], "categories": ["Sales, CS & Business Devpt", "Call Centre", "Customer Service - Supervisor / Officer", "Others"], "post_time": "2022-01-18T03:19:57Z", "salary": {"currency": null, "max": null, "min": null, "period": null, "term": null}, "salary_visible": false, "title_keywords": ["customer service executive"], "responsibilities": ["customers' needs", "customer services"], "requirements": {"degrees": ["higher diploma or above"], "majors": [], "languages": ["chinese"], "language_level": ["proficiency"], "hard_skills": ["plus", "chinese word processing", "salesforce", "microsoft office", "sfc license"], "soft_skills": ["communication skills"], "languages_combined": [{"language": "chinese", "language_level": ["proficiency"]}]}, "experience_required": {"duration": ["at least 1 year"], "field": ["related", "finance", "relevant experience"]}}, {"job_id": "100003009054685", "location_code": "hk", "company": "Nesta (Hong Kong) Limited", "job_title": "Customer Service Officer \u5546\u5834\u5ba2\u6236\u670d\u52d9\u4e2d\u5fc3\u5927\u4f7f15-17K (\u8343\u7063/\u4e5d\u9f8d\u7063/\u9285\u947c\u7063) \u4e94\u5929\u5de5\u4f5c", "description": "\u00a0Working Location :\u00a0\u00a0Ngau Tau Kok\n\nWorking Hours : Monday to Friday 9:00 a.m. - 6:30 p.m. and Saturday 9:00 a.m. - 1:00 p.m. (average 40 hours per week)\n\nResponsibilities:\n\nHandle inquiries, complaints and claims independently and professionally;\nParticipating in customer loyalty program; reflecting customers' feedback to management, providing solutions for improving customer service quality;\nWork with other team members to maintain overall performance standards and assisting in various projects responsible by the team;.\nWork closely with other departments/ international network/ insurance company to meet customer's request\u00a0\n\nRequirements:\n\n\nPost-secondary education\nAt least 3 years\u2019 customer service experience in complaint and claims handling\nGood spoken & written English, Chinese and Mandarin\nInitiative and self-motivated\nCustomer-focus, open-minded, flexible, logical and systematic thinking\nGood interpersonal skills and related well with customers and co-workers from all levels\nGood team-spirit and problem solving skills\nAble to work under pressure and independent\nBasic PC knowledge and good typing skills\nApplication:\nClick \"Apply Now\" or apply on line via the following link:\u00a0https://dhlexpress.taleo.net/careersection/ex/jobdetail.ftl?job=21008SP&iniurl.src=CWS-10001&tz=GMT%2B08%3A00&tzname=Asia%2FShanghai\u00a0also indicating your current and expected salary, and availability.\u00a0 For more job opportunities, please visit our website at\u00a0https://www.dpdhl.jobs/\n\nPersonal Information Collection Statement pertaining to Recruitment\n\nDHL Express (Hong Kong) Limited / DHL Aviation (Hong Kong) Limited (\u201cDHL\u201d) is committed to protecting and respecting your privacy in accordance with the Personal Data (Privacy) Ordinance of Hong Kong (the \u201cOrdinance\u201d) and DHL\u2019s Personal Data Protection Policy (the \u201cPolicy\u201d) at https://www.dhl.com/hk-en/home/footer/local-privacy-notice.html\nBy proceeding to respond to this recruitment advertisement, you consent that we may use, retain, process, transfer or otherwise handle the personal data that we collect from you for recruitment,\u00a0 application processing, assessment and communication purposes (including any other purposes directly related thereto) in accordance with the Policy.\nAll personal data of unsuccessful applicants will be retained for future recruitment purposes for a period of not more than two (2) years after which such data will be destroyed.\nYou have the right at any time to make a data access or correction request concerning your personal data held by us. In addition, you may request us to delete your personal data that is no longer required for the relevant purposes which you have given consent. Should you wish to exercise such rights or have any question in relation to your personal data or the Policy, please contact our Human Resources Division in writing at jobs@dhl.com", "employment_types": ["Full Time"], "selling_points": ["\u4e94\u5929\u5de5\u4f5c\uff0c42.5\u5c0f\u6642\u5de5\u4f5c\u5468", "\u6b61\u8fce\u61c9\u5c46\u7562\u696d\u751f", "\u5177\u5ba2\u6236\u670d\u52d9\u7d93\u9a57\u8005\u512a\u5148"], "locations": ["Not Specified"], "categories": ["Sales, CS & Business Devpt", "Call Centre", "Customer Service - Supervisor / Officer", "Hospitality / F & B", "Hospitality / Hotel Services"], "post_time": "2022-01-17T10:33:36Z", "salary": {"currency": "HKD", "max": 16999, "min": 14000, "period": "monthly", "term": null}, "salary_visible": true, "title_keywords": ["customer service officer"], "responsibilities": ["management", "quality", "work closely with other departments", "maintain", "customer service", "insurance"], "requirements": {"degrees": ["secondary education"], "majors": [], "languages": ["english", "chinese", "mandarin"], "language_level": ["good"], "hard_skills": ["no", "basic", "typing", "html", "make", "problem solving skills", "pc knowledge", "focus", "processing"], "soft_skills": ["flexible", "self-motivated", "independent", "open-minded", "systematic", "communication", "committed", "problem solving skills", "customer service", "interpersonal skills", "focus", "initiative", "work under pressure"], "languages_combined": [{"language": "english", "language_level": ["good"]}, {"language": "chinese", "language_level": ["good"]}, {"language": "mandarin", "language_level": ["good"]}]}, "experience_required": {"duration": ["at least 3 years"], "field": ["customer service"]}}, {"job_id": "100003009052312", "location_code": "hk", "company": "Harvey Nichols (Hong Kong) Limited", "job_title": "Customer Relations Assistant (Frontline)", "description": "Handling in-store and e-commerce customer enquiries and complaints via all communication channels, including but not limited to email, live chat, telephone and face-to-face; including products\u2019 promotion, logistics, products return;\nSupport the team in sales activities, including order processing and post-sales coordination;\nResponsible for in-store e-commerce work station operations, including maintain the e-commerce system, handle in-store pickup orders and provide excellent customer service at store.\nResponsible for the administration support including data input and coupon/GWP redemption;\nResponsible for Customer Service reports;\nAssist in handling ad-hoc assignments if needed.\n\nRequirements:\n\nHigher Diploma or above;\n1 year relevant experience from customer service field would be an advantage;\nDetail-minded, positive and proactive working attitude, with strong customer service mindset;\nGood command of both spoken & written English and Mandarin;\nShift duty\u00a0is required;\nNO\u00a0sales target need to be achieved;\nFresh graduate is also welcome to apply;\nCandidates with\u00a0more experience will be considered as senior position.\n\nWe offer:\n\n6.5 days off per month\n17 Public Holidays\n11 Annual Leave\nAttendance bonus\nShift allowance\nMedical benefits\n\nWe offer excellent career prospects, competitive salary and fringe benefits to the right candidate. Please apply in strict confidence by sending personal resume together with salary expected and date availability by email:\u00a0careers @ harveynichols. com .hk\u00a0or Whatsapp\u00a09828-0637.\n\nWe are an equal opportunity employer and welcome applications from all qualified candidates.\u00a0 Personal data provided by job applicants will be used strictly in accordance with our personal data policy and for recruitment purposes only.\u00a0 Candidates not notified within eight weeks may consider their application unsuccessful.\u00a0 All related information will be kept in our file for up to 24 months.\u00a0 A copy of our Personal Information Collection Statement will be provided upon request by contacting our Human Resources Division.", "employment_types": ["Full Time"], "selling_points": ["6.5 Day Off + 11 Annual Leave + PH", "Customer-oriented and positive working attitude", "Front-line position"], "locations": ["Tsim Sha Tsui"], "categories": ["Sales, CS & Business Devpt", "Customer Service - Supervisor / Officer", "Others"], "post_time": "2022-01-17T02:43:35Z", "salary": {"currency": null, "max": null, "min": null, "period": "monthly", "term": null}, "salary_visible": false, "title_keywords": ["assistant"], "responsibilities": ["sales activities", "operations", "ad-hoc assignments", "sales target", "data input", "communication", "maintain", "logistics", "customer service", "order processing", "coordination", "reports", "customer enquiries and complaints", "support the team", "administration"], "requirements": {"degrees": ["higher diploma or above", "fresh graduate"], "majors": [], "languages": ["english", "mandarin"], "language_level": ["good command"], "hard_skills": ["no", "order processing", "e-commerce"], "soft_skills": ["detail-minded", "responsible", "communication", "customer service", "coordination", "proactive", "positive"], "languages_combined": [{"language": "english", "language_level": ["good command"]}, {"language": "mandarin", "language_level": ["good command"]}]}, "experience_required": {"duration": ["1 year"], "field": ["customer service", "relevant experience"]}}, {"job_id": "100003009051974", "location_code": "hk", "company": "Ever Bloom Trading Limited", "job_title": "Customer Services Assistant", "description": "\u8655\u7406\u5ba2\u4eba\u9810\u7d04\u53ca\u51fa\u55ae\n\u8655\u7406\u5ba2\u4eba\u9867\u554f\u53ca\u6295\u8a34\n\u901a\u904e\u96fb\u90f5\u53ca\u5176\u4ed6\u7db2\u4e0a\u5e73\u53f0\u70ba\u5ba2\u4eba\u63d0\u4f9b\u67e5\u8a62\u670d\u52d9\u53ca\u89e3\u7c3d\u7591\u96e3\n\u5354\u52a9\u5beb\u5b57\u6a13\u8655\u7406\u65e5\u5e38\u4e8b\u52d9", "employment_types": ["Full Time"], "selling_points": [], "locations": ["Yuen Long"], "categories": ["Sales, CS & Business Devpt", "Customer Service - Supervisor / Officer"], "post_time": "2022-01-17T01:42:30Z", "salary": {"currency": "HKD", "max": 13999, "min": 11000, "period": "monthly", "term": null}, "salary_visible": true, "title_keywords": ["customer services assistant"], "responsibilities": [], "requirements": {"degrees": [], "majors": [], "languages": [], "language_level": [], "hard_skills": [], "soft_skills": [], "languages_combined": []}, "experience_required": {"duration": [], "field": []}}, {"job_id": "100003009051763", "location_code": "hk", "company": "2GoTrade Ltd", "job_title": "Customer Service Assistant / Project Assistant", "description": "Job Description:-\n\nThe primary focus of the role is to support customers by providing helpful information, resolve enquiries through hotline, emails and instant messages.\u00a0 Customer Service Assistant is the front line of support for customers and help to ensure that customers are satisfied with the products, services and features as well as maintaining expert knowledge about company products and services.\u00a0\n\nDuties:-\n\nProvide first line applications support to clients\nLiaise with internal departments to solve customer problems and request\nProvide system operation and administration tasks, include monitor and health check tasks\nAssist in any ad hoc project as required\n\n\u00a0Requirements:\u00a0\n\nRelevant experience in customer services preferably\nCustomer-oriented with proactive and good serving attitude\nGood command in both spoken and written Chinese and English, including Mandarin\nGood knowledge in Computer Software Application\nKnowledge in Computer Network is an advantage\nGood communication, interpersonal, problem solving skills\nImmediate availability is highly preferred\n\nBenefits & Others:\nOvertime pay, Education subsidy for job related learning, Performance bonus, Five-day work week, Birthday leave etc.\n\nThe Company offers an opportunity for those who are interested to participate in the hottest FinTech industry in Hong Kong and China.\u00a0\n\nRecruitment agency are not welcome.", "employment_types": ["Full Time", "Permanent"], "selling_points": ["5 days work, FinTech Co, competitive salary", "one of the local renowned BSS Vendors", "Annual Incentive and Performance Bonus"], "locations": ["Shatin Area"], "categories": ["Sales, CS & Business Devpt", "Customer Service - Supervisor / Officer", "Information Technology (IT)", "Support", "Others", "Student / Fresh Graduate / No Experience"], "post_time": "2022-01-17T00:56:33Z", "salary": {"currency": null, "max": null, "min": null, "period": "monthly", "term": null}, "salary_visible": false, "title_keywords": ["customer service assistant", "project assistant"], "responsibilities": ["ad hoc", "maintaining", "monitor", "customer service", "liaise with", "administration"], "requirements": {"degrees": [], "majors": [], "languages": ["english", "chinese", "mandarin"], "language_level": ["good command"], "hard_skills": ["problem solving skills"], "soft_skills": ["communication", "customer-oriented", "problem solving skills", "proactive", "interpersonal"], "languages_combined": [{"language": "english", "language_level": ["good command"]}, {"language": "chinese", "language_level": ["good command"]}, {"language": "mandarin", "language_level": ["good command"]}]}, "experience_required": {"duration": [], "field": ["relevant experience", "customer services"]}}, {"job_id": "100003009055388", "location_code": "hk", "company": "Scubapro Asia Pacific Ltd", "job_title": "Customer Service Representative (Temporary Post)", "description": "Scubapro is a world leader in manufacturing and distributing the Scuba Diving equipment.\u00a0 To facilitate our fast expanding organization in Asia market, we now invite caliber candidate to join our team.\n\n\u00a0Customer Service Representative (Temporary Post)\n\n\u00a0Responsibilities :\u00a0\n\n\u00a0Handle customer sales\u00a0order and process related transaction, prepare sales\u00a0 \u00a0order and documentation in a timely and accurate manner.\nProvide customer service and inquiries via phone and emails and work closely with the Customer Service team and Sales team.\nCoordinate with warehouse and local forwarder on the logistic arrangement. \u00a0\u00a0\nKeep accurate and up-to-date record. Sales and shipping document filing works.\u00a0\nSupport daily operation and ad-hoc assignments for the Customer Service Dept.\nTemporary position is about 3 months.\n\n\u00a0Requirements :\n\n\u00a0F6 or above.\nMinimum 2 years Customer Service experience.\nGood interpersonal and communication skills.\nGood command of spoken & written English and Chinese.\nExperience in ERP system application is an advantage. Familiar with MS Office.\u00a0\u00a0\u00a0\u00a0\u00a0\nIndependent, Initiative and good attitude.", "employment_types": ["Temporary"], "selling_points": ["Customer Service", "Temporary Post", "5 days work"], "locations": ["Chai Wan"], "categories": ["Admin & HR", "Clerical / Admin Staff", "Sales, CS & Business Devpt", "Call Centre", "Customer Service - Supervisor / Officer"], "post_time": "2022-01-18T02:25:56Z", "salary": {"currency": null, "max": null, "min": null, "period": "monthly", "term": null}, "salary_visible": false, "title_keywords": ["customer service representative"], "responsibilities": ["provide customer service", "ad-hoc assignments", "prepare sales", "coordinate with", "daily operation", "logistic arrangement", "customer service", "sales team", "documentation", "shipping document"], "requirements": {"degrees": [], "majors": [], "languages": ["english", "chinese"], "language_level": ["good command"], "hard_skills": ["erp system", "ms office"], "soft_skills": ["communication skills", "independent", "customer service", "interpersonal", "initiative"], "languages_combined": [{"language": "english", "language_level": ["good command"]}, {"language": "chinese", "language_level": ["good command"]}]}, "experience_required": {"duration": ["minimum 2 years"], "field": ["erp system", "customer service"]}}, {"job_id": "100003009055099", "location_code": "hk", "company": "Autotoll Limited", "job_title": "Operation and Customer Service Team Leader   (CS Support)", "description": "To cope with our expansion and continuous growth in the transportation and logistics related service, we are inviting talents to join our professional team.\nAbout the Role:\nAssist the Operation and Customer Service Team Head in manage the daily operation of the department\nEnsure timely handling of all customers\u2019 queries and complaints within the established timeframe\nBeing in-charge of operation of customer services centre, kiosks, outlets and other services channels\nTo ensure the services provided in all services channels are according to procedures and make suggestion for any improvement in daily process\nSupervise the operation in Tag management; dispute and complaint handling, Enforcement process\nPrepare the monthly report to the Operation and Customer Service Team Head regarding the operation of the department & those required to submit to Government Department\n\nAbout You:\n\nHolding a university degree or equivalent qualification\nAt least four years post-qualification full time working experience in customer service roles, of which at least two years shall be at managerial or supervisory level\n\nWhat you can get from us:\nOn-the-job training, learning and development\u00a0provided\nExecutive workshops, interest class, corporate purchase discount offered by SHKP\nCompetitive salary and annual leaves\nFlexible working opportunities\nInterested parties, please send full resume with\u00a0expected salary\u00a0and\u00a0available date\u00a0to Human Resources and Administration Department by e-mail or by fax 2111 9459.\n(Data collected will be used for recruitment purpose only.)", "employment_types": ["Full Time", "Permanent"], "selling_points": ["Assist manager to manage daily operation", "Ensure timely handling of all customers\u2019 queries", "Degree holder with at least 4 yrs exp."], "locations": ["Not Specified"], "categories": ["Sales, CS & Business Devpt", "Customer Service - Supervisor / Officer", "Others"], "post_time": "2022-01-18T01:15:11Z", "salary": {"currency": null, "max": null, "min": null, "period": "monthly", "term": null}, "salary_visible": false, "title_keywords": ["team leader", "customer service"], "responsibilities": ["management", "daily operation", "procedures", "customer services", "purchase", "customer service", "logistics", "monthly report"], "requirements": {"degrees": ["university degree"], "majors": [], "languages": [], "language_level": [], "hard_skills": ["workshops", "make"], "soft_skills": ["flexible", "timely", "customer service", "learning"], "languages_combined": []}, "experience_required": {"duration": ["at least two years", "at least four years"], "field": ["supervisory level", "managerial", "customer service", "post-qualification"]}}, {"job_id": "100003009051947", "location_code": "hk", "company": "Quantium Solutions (Hong Kong) Limited", "job_title": "Customer Service Supervisor/Executive", "description": "Quantium Solutions\n\nQS is an established eCommerce logistics services provider in the Asia Pacific Region. Headquartered in Singapore, we are ideally positioned to be the best gateway to Asia.\n\nOur serviced offices now serve the needs of enterprises and entrepreneurs across major 200 countries and 18 markets.\n\nAt QS, creating a workplace that provides opportunities for each of you and we believe in you and know you\u2019ll do great things. As an employer, our role is to empower you by bringing your true talents and best self to this dynamic digital world and people we serve.\n\n\n\n\nJob Description\n\nResponsibilities:\n\nProcess customer requests fast and efficiently.\nTake ownership of customer issues and follow through problems to solutions.\nResponsible for customer retention and relationship building with customers.\nAssess customers\u2019 needs and collaborate with other counterpart to provide quality service.\nClosely work with Operations, Sales and other counterpart for service enhancement.\nAssist in ad-hoc project when required.\n\nRequirements:\n\nBachelor\u2019s degree or equivalent in business, logistics or related disciplines;\nAt least 1 year working experience in customer services;\nProactive, customer-oriented with strong interpersonal and problem-solving skills;\nProficiency in MS Word, Excel and Power Point;\nGood communication in both written and verbal English, Chinese and Mandarin;\nImmediately available is highly preferred.\u00a0\u00a0\nCandidates with less experience will be considered as Customer Service Executive\n\nWe offer attractive remuneration package including medical insurance, life insurance, dental and other fringe benefits to the right candidate. Interested parties please send your full resume with date of availability, present and expected salaries to us\n\n\n", "employment_types": ["Full Time", "Permanent"], "selling_points": [], "locations": ["Wong Tai Sin Area"], "categories": ["Sales, CS & Business Devpt", "Call Centre", "Customer Service - Supervisor / Officer", "Transportation & Logistics", "Supply Chain"], "post_time": "2022-01-17T01:36:24Z", "salary": {"currency": null, "max": null, "min": null, "period": "monthly", "term": null}, "salary_visible": false, "title_keywords": ["customer service supervisor", "executive"], "responsibilities": ["collaborate with", "ad-hoc", "operations", "quality", "customer requests", "customer issues"], "requirements": {"degrees": ["degree", "bachelor"], "majors": ["related disciplines", "business"], "languages": ["english", "chinese", "mandarin"], "language_level": ["good"], "hard_skills": ["power point", "problem-solving skills", "excel", "ms word"], "soft_skills": ["communication", "customer-oriented", "customer service", "problem-solving skills", "proactive", "interpersonal"], "languages_combined": [{"language": "english", "language_level": ["good"]}, {"language": "chinese", "language_level": ["good"]}, {"language": "mandarin", "language_level": ["good"]}]}, "experience_required": {"duration": ["at least 1 year"], "field": ["customer service", "customer services"]}}, {"job_id": "100003009054576", "location_code": "hk", "company": "Manulife (International) Limited", "job_title": "Administrative Assistant ($15 to $20K)", "description": "Responsibilities\n\nPerform general office administrative and clerical supports\nSupport Senior Manager in the preparation of all documentations\nManage schedules, appointments and meetings\nReview and sort incoming emails and mails for relevant functions\nPlan and manage record keeping activities when required\nHandle and maintain confidential information and documents\n\nRequirements\n\nBachelor degree or above\nDetail-oriented, well-organized, excellent communication skills\nExcellent interpersonal skills to deal with all levels of people\nHigh proficiency in MS Office including Excel, Word, PowerPoint etc\nHigh proficiency of both spoken and written English, Cantonese and Mandarins\nImmediate available is preferred\n\nWe offer competitive remuneration and benefits, holidays, stable working environment to the right candidates. Interested parties please click \"Apply Now\" and send your\u00a0full resume\u00a0with expected salary\u00a0to us.\n\n*All personal data collected will be kept strictly confidential and used for recruitment-related purpose only.", "employment_types": ["Full Time", "Permanent"], "selling_points": ["Guaranteed Basic Income ($15 to $20K)", "5 days work with Double Pay", "Travel Allowance + Medical Insurance"], "locations": ["Not Specified"], "categories": ["Admin & HR", "Personal / Executive Assistant", "Sales, CS & Business Devpt", "Customer Service - Supervisor / Officer", "Marketing / Public Relations", "Marketing - General / Support"], "post_time": "2022-01-17T10:04:19Z", "salary": {"currency": "HKD", "max": 19999, "min": 14000, "period": "monthly", "term": null}, "salary_visible": true, "title_keywords": ["administrative assistant"], "responsibilities": ["manage record", "schedules", "review", "maintain", "plan"], "requirements": {"degrees": ["degree or above", "bachelor"], "majors": [], "languages": ["cantonese", "english"], "language_level": ["proficiency"], "hard_skills": ["excel", "word", "powerpoint", "ms office"], "soft_skills": ["communication skills", "well-organized", "interpersonal skills", "detail-oriented"], "languages_combined": [{"language": "cantonese", "language_level": ["proficiency"]}, {"language": "english", "language_level": ["proficiency"]}]}, "experience_required": {"duration": [], "field": []}}, {"job_id": "100003009052622", "location_code": "hk", "company": "Hong Kong Housing Society", "job_title": "Customer Services Officer", "description": "[Ref: JMC-CSO(Contract)]\n\n\u00a0The Job:\n\nAdminister tenancy management properly by visiting rental flats regularly to identify abnormalities, handling tenancy movements and changes, explaining tenancy details to tenants and updating tenancy records.\nProvide quality services and enhance relationship with tenants / owners by handling telephone enquiries, referring emergencies to appropriate staff, drafting notices / replies to tenants / owners promptly, taking meeting minutes and organising activities & interest classes etc.\nProvide customer services to tenants / owners when maintenance work is in progress by liaising with and coordinating relevant parties, scheduling works orders and following-up tenants/ owners\u2019 requests, monitoring maintenance works progress to minimise disruption to tenants/ owners.\nAssist in office logistics by preparing work schedules for manual staff, typing documents, maintaining and updating filing system.\n\nThe Person:\n\nMatriculated OR 5 subjects obtained Level 3 or above in HKDSEE, including English and Chinese with min. 1-2 years' experience in customer services in Property Management industry OR Degree/Diploma holders with relevant experience.\nBasic PC knowledge including Word Processing.\nGood communication, and interpersonal skills.\nMature, service-oriented and attentive to details.\n\nAttractive remuneration package will be offered to suitable candidates. To apply, please submit online application: https://careers.hkhs.com/ or send your application with full resume and reference quoted to Human Resources Manager by fax: 2882 4466.\n\nYou are welcome to visit our website www.hkhs.com to learn more about us.\nApplicants not invited for interview within 8 weeks may consider their applications unsuccessful.\n\nPersonal data provided by job applicants will be used strictly in accordance with the Housing Society\u2019s personal data policies which is available in our website and obtainable upon request. Please refer to the Policy Statement on Employment Related Data under Personal Data (Privacy) Ordinance in our website.", "employment_types": ["Temporary"], "selling_points": ["Administer tenancy management properly", "Provide customer services to tenants / owners", "1-2 years' experience in customer services"], "locations": ["Shatin Area"], "categories": ["Sales, CS & Business Devpt", "Customer Service - Supervisor / Officer"], "post_time": "2022-01-17T03:35:06Z", "salary": {"currency": null, "max": null, "min": null, "period": "monthly", "term": null}, "salary_visible": false, "title_keywords": ["customer services officer"], "responsibilities": ["management", "maintenance", "maintaining", "schedules", "monitoring", "quality", "liaising with", "customer services", "scheduling", "logistics"], "requirements": {"degrees": ["diploma", "degree"], "majors": [], "languages": ["english", "chinese"], "language_level": [], "hard_skills": ["pc knowledge", "basic", "word processing"], "soft_skills": ["attentive to details", "service-oriented", "mature", "communication", "interpersonal skills"], "languages_combined": [{"language": "english", "language_level": []}, {"language": "chinese", "language_level": []}]}, "experience_required": {"duration": ["1-2 years"], "field": ["management", "relevant experience", "customer services"]}}, {"job_id": "100003009056660", "location_code": "hk", "company": "NEC Hong Kong Limited", "job_title": "Customer Service Representative (fresh graduates are welcome)", "description": "Post-secondary or above, with relevant experience gained from customer service centre or call centre is an advantage;\nAnswer in-bound calls and escalate the customer requests to the related parties by prompt action\nPrepare weekly report and assist in daily routine clerical works;\nCheerful, pleasant, polite, patient and able to work independently;\nGood interpersonal and communication skills;\nAble to communicate in English and Mandarin is preferred; and\nShift duty is required\nPlease send your full detailed resume with expected salary and date available to The Human Resources Manager, NEC Hong Kong Limited, 25th Floor, The Metropolis Tower, 10 Metropolis Drive, Hunghom, Kowloon or by e-mail.\n\n\nPersonal data provided by job applicant will be used strictly in accordance with employer's personal data policy, a copy of which will be provided immediately upon request.", "employment_types": ["Full Time", "Permanent"], "selling_points": ["Handle telephone and email enquiries from customer", "Assist in daily routine clerical work", "Fresh graduates are welcome"], "locations": ["Kwai Hing"], "categories": ["Admin & HR", "Clerical / Admin Staff", "Sales, CS & Business Devpt", "Customer Service - Supervisor / Officer", "Information Technology (IT)", "Support"], "post_time": "2022-01-18T05:33:31Z", "salary": {"currency": null, "max": null, "min": null, "period": "monthly", "term": null}, "salary_visible": false, "title_keywords": ["customer service representative"], "responsibilities": ["communication", "customer service", "customer requests", "personal data", "report"], "requirements": {"degrees": [], "majors": [], "languages": ["english", "mandarin"], "language_level": [], "hard_skills": [], "soft_skills": ["communication skills", "work independently", "cheerful", "polite", "prompt", "pleasant", "customer service", "patient", "interpersonal", "detailed"], "languages_combined": [{"language": "english", "language_level": []}, {"language": "mandarin", "language_level": []}]}, "experience_required": {"duration": [], "field": ["customer service", "relevant experience"]}}, {"job_id": "100003009052510", "location_code": "hk", "company": "Job-Hunter Employment Agency", "job_title": "Senior Guest Services Officer", "description": "Responsibilities:\n\nTo handle order, inquiry and occasional complaint cases\nTo provide service and administrative support to Sales Teams in aspects of sales and after-sales activities\nTo liaise and co-ordinate with Logistic team for order delivery\nAd-hoc duties as assigned\n\nRequirements:\n\nF.5 or above\nMinimum of 1 year working experience, preferable in customer service field\nStrong communication and interpersonal skill with excellent telephone manner\nFluent in oral and listening in Cantonese, English and Mandarin\nProficient in Chinese word processing\nImmediate available is highly preferred\n\nWorking location:\u00a0Kwai Chung\n\nStaff Benefit:\n\nDiscretionary Bonus\nMedical & Life Insurance\nAnnual Leave\nPayable Sick Leave\nEncourage continuing education and on-job training\nOpen office working environment\nOffer promotion opportunities and long-term career path\u00a0\n\nWe offer a competitive remuneration package to the right candidate.\u00a0Interested parties\u00a0please click\u00a0\"Apply Now\"\u00a0to submit your application\u00a0or by email to\u00a0hr1 @twcoffee.com\n\n\u00a0(All personal data provided by applicants will be treated in strict confidence and used for employment-related purpose only.)", "employment_types": ["Full Time", "Permanent"], "selling_points": [], "locations": ["Not Specified"], "categories": ["Transportation & Logistics", "Aviation Services", "Sales, CS & Business Devpt", "Customer Service - Supervisor / Officer", "Hospitality / F & B", "Hospitality / Hotel Services"], "post_time": "2022-01-17T06:13:53Z", "salary": {"currency": null, "max": null, "min": null, "period": "monthly", "term": null}, "salary_visible": false, "title_keywords": ["guest services officer"], "responsibilities": ["liaise", "sales activities", "administrative support", "co-ordinate with", "teams", "ad-hoc duties"], "requirements": {"degrees": [], "majors": [], "languages": ["cantonese", "english", "chinese", "mandarin"], "language_level": ["proficient", "fluent"], "hard_skills": ["chinese word processing"], "soft_skills": ["oral", "interpersonal skill", "communication", "customer service", "telephone manner"], "languages_combined": [{"language": "cantonese", "language_level": ["fluent"]}, {"language": "english", "language_level": ["fluent"]}, {"language": "chinese", "language_level": ["proficient"]}, {"language": "mandarin", "language_level": ["fluent"]}]}, "experience_required": {"duration": ["minimum of 1 year"], "field": ["customer service"]}}, {"job_id": "100003009052677", "location_code": "hk", "company": "Hong Kong Housing Society", "job_title": "CES - Officer / Senior Customer Services Representative", "description": "[Ref: CES-O/SCSR]\n\nThe Job\n\nAttend the elderly lounge and arrange activities for the elderly tenants to promote home, health and social care.\nConduct regular home visits and/or telephone assurance to the elderly tenants, and deliver timely health assessments and match with suitable services.\nArrange the logistics with collaborators and organisations and offer onsite coordination with the contingency plan for implementation of activities.\nLiaise, monitor and train volunteers of all ages, and to maintain an up-to-date service records for annual award.\nProvide administrative support, including procurement and contract service payment, statistic and data entry, progress reporting and meeting minutes, inventory control, programme proposal and evaluation, and prepare other documentary work to support the operational needs of AIP scheme.\nHandle daily requests, enquiries and complaints of the elderly tenants and their families, local hospitals and other service units.\n\nThe Person\n\nDegree/Diploma holders in social work / social sciences / health sciences with relevant working experience in elderly services field and knowledge in event organising.\nGood manner, sociable and cheerful character with strong communication, interpersonal, organisation and customer services skills.\nAble to work independently and interested in communicating with elderly people.\nProficiency in MS Windows application, including Excel, Word, PowerPoint and Chinese Word processing.\nFresh Graduate will also be considered.\n\nAttractive remuneration package will be offered to suitable candidates. To apply, please submit online application: https://careers.hkhs.com/ or send your application with full resume and reference quoted to Human Resources Manager by fax: 2882 4466.\n\nYou are welcome to visit our website www.hkhs.com to learn more about us.\nApplicants not invited for interview within 8 weeks may consider their applications unsuccessful.\n\nPersonal data provided by job applicants will be used strictly in accordance with the Housing Society\u2019s personal data policies which is available in our website and obtainable upon request. Please refer to the Policy Statement on Employment Related Data under Personal Data (Privacy) Ordinance in our website.", "employment_types": ["Permanent"], "selling_points": ["Attend the elderly lounge and arrange activities", "Conduct regular home visits or telephone assurance", "Experience in elderly services field"], "locations": ["Others"], "categories": ["Sales, CS & Business Devpt", "Customer Service - Supervisor / Officer"], "post_time": "2022-01-17T03:41:19Z", "salary": {"currency": null, "max": null, "min": null, "period": "monthly", "term": null}, "salary_visible": false, "title_keywords": ["officer", "customer services representative"], "responsibilities": ["liaise", "reporting", "data entry", "coordination with", "monitor", "implementation", "payment", "maintain", "logistics", "inventory control", "plan", "evaluation", "provide administrative support"], "requirements": {"degrees": ["diploma", "degree", "fresh graduate"], "majors": ["social work", "social sciences"], "languages": ["chinese"], "language_level": ["proficiency"], "hard_skills": ["excel", "chinese word processing", "ms windows", "word", "powerpoint"], "soft_skills": ["work independently", "cheerful", "customer services skills", "interested in", "sociable", "communication", "organisation", "interpersonal"], "languages_combined": [{"language": "chinese", "language_level": ["proficiency"]}]}, "experience_required": {"duration": [], "field": ["relevant working experience"]}}, {"job_id": "100003009052482", "location_code": "hk", "company": "BSI Pacific Ltd", "job_title": "Part-Time Customer Service Officer", "description": "Job responsibilities\n\n\nCollect and maintain the customer database\nCollect feedback on the certification services to evaluate customer satisfaction and identify opportunities for improvement\nParticipating in the billing process\nBuild and maintain a close relationship with existing customers, understand their needs to provide support to ensure the provision of the desired services and enhance up-sell opportunities.\nSupport event management (if necessary)\nHandling ad hoc tasks and any other assigned duties as requested\n\nJob requirement\n\n\nDiploma or above\nMin 1-year job experience\nStrong telephone communication skills\nProactive, fast learner\nGood interpersonal skills\nFluent in English and Mandarin\nInterested parties please send us a full resume with your\u00a0CURRENT & EXPECTED SALARY\u00a0simply click \"APPLY NOW\".\u00a0\u00a0\n\n\nPersonal data provided by applicants will be treated in strict confidence and used for recruitment purposes only for no more than 6 months.", "employment_types": ["Part Time"], "selling_points": ["Customer database management", "Prepare the certification audit,testing and review", "Monitoring customer satisfaction"], "locations": ["Quarry Bay"], "categories": ["Sales, CS & Business Devpt", "Customer Service - Supervisor / Officer", "Account Servicing", "Sales Administration"], "post_time": "2022-01-17T03:09:22Z", "salary": {"currency": null, "max": null, "min": null, "period": "monthly", "term": null}, "salary_visible": false, "title_keywords": ["customer service officer"], "responsibilities": ["provide support", "management", "billing process", "ad hoc tasks", "evaluate", "maintain", "database"], "requirements": {"degrees": ["diploma or above"], "majors": [], "languages": ["english", "mandarin"], "language_level": ["fluent"], "hard_skills": [], "soft_skills": ["communication skills", "proactive", "fast learner", "interpersonal skills"], "languages_combined": [{"language": "english", "language_level": ["fluent"]}, {"language": "mandarin", "language_level": ["fluent"]}]}, "experience_required": {"duration": ["min 1-year"], "field": []}}, {"job_id": "100003009056021", "location_code": "hk", "company": "The Hong Kong Jockey Club", "job_title": "Guest Relationship Officer", "description": "The Department\nThe Customer and International Business Development Division (C&I) is responsible for providing quality wagering experience to local and overseas customers of The Hong Kong Jockey Club. It operates 88 Race Meetings a year, 33 Simulcasts days, a thrice-weekly Mark 6 Draw, 7X24 Digital Channels, 7X24 Football Betting Services on over 11,000 different leagues per year. The ultimate aim is to provide an impressive total customer experience leading to sustainable turnover growth in a responsible manner.\nThe Customer Digital Experience Department is responsible for leading and managing development projects of digital wagering experience and customer service digital transformation. Besides project management, its scope includes content requirement definition, user-interface and user experience design, as well as the look and feel based on customer insights and product requirements.\n\nThe Job\nYou will:\n\nwork at The Racing Club\u2019s dining venues, both Happy Valley Racecourse and Sha Tin Racecourses on racedays and non-racedays\nprocess table booking request from members who may call in or book through online\nmaximise seat and table utilisation of the venue, work out daily booking and seating plans and prepare venue utilisation reports\nwork on event logistics, cost control and provide on-site support to ensure successful execution of internal event\nwelcome Members and their guests at The Racing Club venues in a pleasant and warm manner to build up a friendly relationship\nanswer The Racing Club hotline and general enquiries from Members about the services and events\nwritten and e-correspondences to answer enquiries is needed and help on other office administration.\n\nAbout You\nYou should have:\n\n1-2 years of relevant experience, diploma holder in Hospitality Management or related disciplines is an advantage\nexcellent interpersonal and communication skills, good telephone manner\nto be customer-centric and attention to details and logistics\nprofessional manner on handling confidential information\ngood command of spoken and written English and Chinese, which includes Cantonese and Putonghua\nhands-on computer skills in MS Word & Excel\nto work on night races, non-office working hours and Public Holidays.\n\nTerms of employment\nThe level of appointment will be commensurate with qualifications and experience.\n\nHow to Apply\nPlease send your resume, complete with expected salary and job reference by clicking the\u00a0Apply Now\u00a0button.\n\nWe are an equal opportunity employer. Personal data provided by job applicants will be used strictly in accordance with the Club\u2019s notice to employees and prospective employees relating to the Personal Data (Privacy) Ordinance. A copy of which will be provided immediately upon request.", "employment_types": ["Full Time"], "selling_points": ["1-2 years of relevant experience", "good telephone manner", "work at The Racing Club\u2019s dining venues"], "locations": ["Not Specified"], "categories": ["Sales, CS & Business Devpt", "Customer Service - Supervisor / Officer", "Hospitality / F & B", "Others", "Others"], "post_time": "2022-01-18T03:11:53Z", "salary": {"currency": null, "max": null, "min": null, "period": null, "term": null}, "salary_visible": false, "title_keywords": ["officer"], "responsibilities": ["management", "office administration", "quality", "user experience", "design", "customer insights", "communication", "project management", "professional manner", "customer service", "reports", "booking", "logistics", "cost control", "plans", "personal data"], "requirements": {"degrees": ["diploma holder"], "majors": ["hospitality management", "related disciplines"], "languages": ["cantonese", "putonghua", "english", "chinese"], "language_level": ["good command"], "hard_skills": ["project management", "computer skills", "excel", "ms word"], "soft_skills": ["communication skills", "responsible", "pleasant", "project management", "hands-on", "customer service", "friendly", "attention to details", "telephone manner", "interpersonal"], "languages_combined": [{"language": "cantonese", "language_level": ["good command"]}, {"language": "putonghua", "language_level": ["good command"]}, {"language": "english", "language_level": ["good command"]}, {"language": "chinese", "language_level": ["good command"]}]}, "experience_required": {"duration": ["1-2 years"], "field": ["management", "related", "business development", "design", "project management", "customer service", "relevant experience", "digital", "development projects"]}}, {"job_id": "100003009052655", "location_code": "hk", "company": "Premier Strategy Marketing Limited", "job_title": "Customer Service Officer/ Assistant", "description": "Responsibilities:\u00a0\n\nDeliver highest level customer service and maintain good relationship with the customers in a professional manner;\nDevelop potential customers;\nCooperate with other teams and team members to ensure timely resolution of customer requests, problems and documenting actions.\nArrange customer appointments;\nHandle and follow-up on customer cases & sample;\nPerform ad hoc projects as assigned by manager.\n\nRequirements:\n\nHigher Diploma or above;\n1-2 years related experience in Customer Service/Sales/Admin is a plus;\nExperience in pregnancy & maternity services and products, medical fields are preferred;\nGood command of spoken Mandarin, Cantonese and English;\nProficient in computer skills, e.g. Microsoft Office, English and Chinese typing;\nExcellent communication and interpersonal skills;\nMature with a positive attitude, aggressive, self-motivated and strong desire to deliver exceptional results with great attention to accuracy and details;\nFresh graduates & IANG holders are welcomed;\nCandidate with less experience will be considered as Customer Service Assistant.", "employment_types": ["Full Time", "Permanent"], "selling_points": [], "locations": ["Shatin Area"], "categories": ["Sales, CS & Business Devpt", "Business Development", "Customer Service - Supervisor / Officer", "Account Servicing"], "post_time": "2022-01-17T03:38:59Z", "salary": {"currency": null, "max": null, "min": null, "period": "monthly", "term": null}, "salary_visible": false, "title_keywords": ["assistant", "customer service officer"], "responsibilities": ["professional manner", "teams", "develop", "maintain good relationship", "resolution", "customer service", "ad hoc projects", "customer requests", "cooperate with"], "requirements": {"degrees": ["higher diploma or above"], "majors": [], "languages": ["cantonese", "english", "chinese", "mandarin"], "language_level": ["good command"], "hard_skills": ["plus", "computer skills", "typing", "microsoft office"], "soft_skills": ["self-motivated", "mature", "positive attitude", "customer service", "communication and interpersonal skills"], "languages_combined": [{"language": "cantonese", "language_level": ["good command"]}, {"language": "english", "language_level": ["good command"]}, {"language": "chinese", "language_level": []}, {"language": "mandarin", "language_level": ["good command"]}]}, "experience_required": {"duration": ["1-2 years"], "field": ["related", "admin", "customer service", "medical"]}}, {"job_id": "100003009054330", "location_code": "hk", "company": "RecruitFirst Limited", "job_title": "Part-time Customer Service Coordinator", "description": "Responsibilities :\n\nProvide customer services and follow up with external clients and candidates including but not limited to in-bound calls handling and email/ message replying\nAssist in admin duties to support recruitment consultants such as rostering\nany ad hoc duties assigned by recruitment consultants or supervisor\n\n\n\nRequirements:\u00a0 \u00a0\u00a0\u00a0\u00a0 \u00a0 \u00a0 \u00a0 \u00a0 \u00a0 \u00a0 \u00a0\n\nDiploma or above in any disciplines\u00a0\nFresh graduates or candidates without recruitment experiences are also welcomed\u00a0\nCustomer-oriented mindset, willing to serve the best with patience\nAble to work under pressure with efficiency\nProficiency in both written & spoken Chinese & English\nTech savvy in Microsoft Office operations\nImmediate available is preferred\n\n\n\nWe offer:\n\nFlexible working hours\nWork from home\u00a0\u00a0\n\nCandidates please send us a resume with availability & expected salary by clicking APPLY NOW", "employment_types": ["Part Time", "Temporary", "Freelance"], "selling_points": [], "locations": ["Wan Chai"], "categories": ["Admin & HR", "Clerical / Admin Staff", "Sales, CS & Business Devpt", "Customer Service - Supervisor / Officer", "Account Servicing"], "post_time": "2022-01-17T09:11:08Z", "salary": {"currency": null, "max": null, "min": null, "period": "monthly", "term": null}, "salary_visible": false, "title_keywords": ["customer service coordinator"], "responsibilities": ["ad hoc duties", "recruitment", "customer services"], "requirements": {"degrees": ["diploma or above"], "majors": ["any disciplines"], "languages": ["english", "chinese"], "language_level": ["proficiency"], "hard_skills": ["microsoft office"], "soft_skills": ["work under pressure", "customer-oriented", "patience"], "languages_combined": [{"language": "english", "language_level": ["proficiency"]}, {"language": "chinese", "language_level": ["proficiency"]}]}, "experience_required": {"duration": [], "field": ["recruitment"]}}, {"job_id": "100003009052666", "location_code": "hk", "company": "Smart Talent International Education Centre Limited", "job_title": "Customer Service Officer (Education Industry) - (Basic salary + Attractive Commission + Bonus)", "description": "Job Description\n\nPromote and advise parents/ students on educational courses and packages\nMaintain good relationship with existing clients and identify their needs on educational services\nPrepare any sales activities related materials and presentation\nResponsible for closing deals with customers and preparing payment documents\nHandle sales related administrative works\nMonitor and follow up on the after-sales progress to meet customers\u2019 needs\n\nRequirement\n\nHigher diploma holder or above in any fields\nAt least 2-3 years of relevant working experience\nExperienced in educational services role is an advantage\nStrong sense of responsibility, a good team player while being able to work independently to close deal with customers\nGood communication and selling skills\nGood command of spoken Mandarin, Cantonese & English\nImmediate availability is highly preferred\n\nWe offer competitive remuneration package and good prospects to the right candidates. Interested parties please send your full resume with expected salary by clicking \u201cApply now\u201d\n\n*Data collected will be kept confidential and used for recruitment purposes only. All the applications will be destroyed after 6-month.", "employment_types": ["Full Time", "Permanent"], "selling_points": [], "locations": ["Tsim Sha Tsui"], "categories": ["Sales, CS & Business Devpt", "Customer Service - Supervisor / Officer", "Account Servicing", "Direct Sales"], "post_time": "2022-01-17T03:40:26Z", "salary": {"currency": null, "max": null, "min": null, "period": "monthly", "term": null}, "salary_visible": false, "title_keywords": ["customer service officer"], "responsibilities": ["sales activities", "payment", "monitor", "maintain good relationship"], "requirements": {"degrees": ["higher diploma holder"], "majors": [], "languages": ["cantonese", "english", "mandarin"], "language_level": ["good command"], "hard_skills": [], "soft_skills": ["communication", "good team player", "work independently", "sense of responsibility"], "languages_combined": [{"language": "cantonese", "language_level": ["good command"]}, {"language": "english", "language_level": ["good command"]}, {"language": "mandarin", "language_level": ["good command"]}]}, "experience_required": {"duration": ["at least 2-3 years"], "field": ["relevant working experience"]}}, {"job_id": "100003009052010", "location_code": "hk", "company": "Phonak Hearing Centre Hong Kong Ltd", "job_title": "Customer Services Co-ordinator (5 Days work)", "description": "KAM HEALTHCARE GROUP\n\n\u7518\u5cf0\u91ab\u7642\u4fdd\u5065\u96c6\u5718\n\nPhonak Hearing Centre HK Ltd\n\nA leading professional hearing centre in TST is seeking an applicant for the post of :\n\nCustomer Services Co-ordinator\n\n\u00a0 Responsibilities:\n\n\nCounter reception, Casher job\nTelephone & email enquiry, appointment booking\nFiling, data input & clerical work\nSales all company product\nProvide support to the centre's daily operation\n\n\u00a0Job Requirements:\n\n1 year related experience preferred\nPleasant, courteous & hardworking\nGood communication, presentation and customer service skills\nGood command of spoken English & Chinese\nPC knowledge such as Microsoft Word, Excel & Chinese Word Processing\n\nWe offer attractive salary and fringe benefits including upto 20 days\u2019 annual leave, 5 day work week, year-end bonus, medical insurance, provident fund, educational assistance to the right person.\u00a0", "employment_types": ["Full Time", "Permanent"], "selling_points": ["Attractive Salary Package & Benefit, 5 day work", "UP to 20 days annual Leave, Medical Insurance", "Education Allowance. Extra Year End Bonus,"], "locations": ["Not Specified"], "categories": ["Sales, CS & Business Devpt", "Customer Service - Supervisor / Officer", "Retail Sales", "Direct Sales"], "post_time": "2022-01-17T01:49:16Z", "salary": {"currency": null, "max": null, "min": null, "period": "monthly", "term": null}, "salary_visible": false, "title_keywords": [], "responsibilities": ["provide support", "daily operation", "booking", "data input"], "requirements": {"degrees": [], "majors": [], "languages": ["english", "chinese"], "language_level": ["good command"], "hard_skills": ["excel", "pc knowledge", "microsoft word", "chinese word processing"], "soft_skills": ["customer service skills", "courteous", "pleasant", "communication", "presentation", "hardworking"], "languages_combined": [{"language": "english", "language_level": ["good command"]}, {"language": "chinese", "language_level": ["good command"]}]}, "experience_required": {"duration": ["1 year"], "field": ["related"]}}, {"job_id": "100003009055742", "location_code": "hk", "company": "Hays", "job_title": "Customer Services Officer, Top-tier bank", "description": "Customer Services Officer, Top-tier bank, Banking Sector\n\nYour new company\nOur client is a top-tier bank and has established a market leading position in general and investment banking services. This company has always show pride in providing top services to their customers. To achieve this, they are currently looking for passionate Customer Services professionals who strives to deliver professionalism in banking products and address customers' needs.\n\nYour new role\nYou will be working as one of the key members in the Customer Service team, who strives to deliver the best customer experience through answering enquires via phone calls and emails. Your will be responsible for delivering quality services. As part of the day to day duties, you will also provide administrative support, such as timely completion of ad hoc projects and tasks, to ensure a seamless operating flow.\n\nWhat you'll need to succeed\n\nCustomer service phone banking experience are preferred\nCandidate certificated with HKSI will be a bonus\nHigh level of proficiency of English, Cantonese and Putonghua\nOutgoing and strong interpersonal skills\nPassionate in offer best-in-class customer services to customers\nPublic exam Maths, Chi, Eng passed\n\n\n\nWhat you'll get in return\n\nA rewarding career and competitive package in a sizeable bank\nExcellent career development prospects\nFlexi hour working schedules\nOpportunity to working at a bank with most market share\nOrganization provides strong stability\n\n\n\nWhat you need to do now\nIf you fulfil all the qualifications mentioned above and have the drive to succeed or are interested in similar roles within Banking, please contact me with an attached CV at yumi.yung@hays.com.hk or please call +852-2230-7982.", "employment_types": ["Full Time", "Permanent"], "selling_points": ["Fast-paced working environment", "Excellent career prospects", "Flex hour working schedules"], "locations": ["Not Specified"], "categories": ["Sales, CS & Business Devpt", "Customer Service - Supervisor / Officer"], "post_time": "2022-01-18T02:54:42Z", "salary": {"currency": null, "max": null, "min": null, "period": "monthly", "term": null}, "salary_visible": false, "title_keywords": ["customer services officer"], "responsibilities": ["customers' needs", "schedules", "quality", "customer services", "customer service", "ad hoc projects", "contact", "career development", "banking", "provide administrative support", "phone calls"], "requirements": {"degrees": [], "majors": [], "languages": ["cantonese", "putonghua", "english"], "language_level": ["proficiency"], "hard_skills": ["hksi"], "soft_skills": ["passionate", "outgoing", "responsible", "timely", "interested in", "customer service", "interpersonal skills"], "languages_combined": [{"language": "cantonese", "language_level": ["proficiency"]}, {"language": "putonghua", "language_level": ["proficiency"]}, {"language": "english", "language_level": ["proficiency"]}]}, "experience_required": {"duration": [], "field": ["customer service", "banking experience", "team"]}}, {"job_id": "100003009055493", "location_code": "hk", "company": "Hong Kong Housing Society", "job_title": "Customer Services Officer (9-month)", "description": "[Ref: CSO(S&M)]\n\nThe Job:\n\nAssist in managing sales arrangement and operation.\nResponsible for pre-handover inspection and flat handover to owners as well as coordination of defect rectification works.\nHandle customer enquiries and complaints to ensure that all customers are well served in a timely, courteous and professional manner.\nPerform logistics, administrative and clerical support duties.\nUndertake any other duties assigned by supervisor.\n\n\u00a0The Person:\n\nDiploma holder or above.\nRelevant experience in customer services and handling enquires are preferred.\nStrong common sense, interpersonal and communication skills.\nGood command of both written and spoken English and Chinese.\nKnowledge of MS Windows application, including Word, Excel, PowerPoint and Chinese Word Processing.\nAble to work on irregular hours and weekend.\nFresh graduate / flexible working hours will also be considered.\nImmediate available is preferred.\n\nAttractive remuneration package will be offered to suitable candidates. To apply, please submit online application: https://careers.hkhs.com/ or send your application with full resume and reference quoted to Human Resources Manager by fax: 2882 4466.\n\nYou are welcome to visit our website www.hkhs.com to learn more about us.\nApplicants not invited for interview within 8 weeks may consider their applications unsuccessful.\n\nPersonal data provided by job applicants will be used strictly in accordance with the Housing Society\u2019s personal data policies which is available in our website and obtainable upon request. Please refer to the Policy Statement on Employment Related Data under Personal Data (Privacy) Ordinance in our website.", "employment_types": ["Temporary"], "selling_points": ["Assist in managing sales arrangement and operation", "Pre-handover inspection and flat handover", "Handle customer enquiries and complaints"], "locations": ["Others"], "categories": ["Sales, CS & Business Devpt", "Customer Service - Supervisor / Officer"], "post_time": "2022-01-18T02:39:16Z", "salary": {"currency": null, "max": null, "min": null, "period": "monthly", "term": null}, "salary_visible": false, "title_keywords": ["customer services officer"], "responsibilities": ["any other duties", "rectification", "professional manner", "inspection", "logistics", "coordination", "administrative and clerical support", "customer enquiries and complaints"], "requirements": {"degrees": ["diploma holder", "fresh graduate"], "majors": [], "languages": ["english", "chinese"], "language_level": ["good command"], "hard_skills": ["excel", "chinese word processing", "ms windows", "word", "powerpoint"], "soft_skills": ["flexible", "communication skills", "interpersonal"], "languages_combined": [{"language": "english", "language_level": ["good command"]}, {"language": "chinese", "language_level": ["good command"]}]}, "experience_required": {"duration": [], "field": ["relevant experience", "customer services"]}}, {"job_id": "100003009053962", "location_code": "hk", "company": "CMB International Capital Corporation Limited", "job_title": "Customer Services Officer \u2013 Equities Department (1-Year Contract)", "description": "Major Responsibilities:\n\nResponsible for providing quality customer service to the Company clients from HK and China market;\nCoordinate with cross-department counterparts to enhance operation efficiency and customer experience.\nEstablish good relationship with clients\nHandle incoming telephone calls/Enquiry from electronic platform and greet visitors in a professional and courteous manner;\nHandling account opening and margin financing procedures;\n\n\u00a0Qualifications & Requirements:\n\nDegree Holder with major in Business, Finance or related disciplines;\n1 year of relevant experience in the similar position preferably;\nHolder of SFC Type 1 License is preferred;\nTactful customer services skills and good problem solving abilities;\nGood communication and interpersonal skills;\nGood written and spoken English and Chinese, with excellent command of Putonghua", "employment_types": ["Full Time", "Contract"], "selling_points": ["Customer Services", "SFC Type 1 License", "Brokerage"], "locations": ["Central"], "categories": ["Banking / Finance", "Financial Services", "Sales, CS & Business Devpt", "Customer Service - Supervisor / Officer"], "post_time": "2022-01-17T07:51:29Z", "salary": {"currency": null, "max": null, "min": null, "period": "monthly", "term": null}, "salary_visible": false, "title_keywords": ["customer services officer"], "responsibilities": ["account opening", "quality", "coordinate with", "procedures", "good relationship", "customer service"], "requirements": {"degrees": ["degree holder"], "majors": ["related disciplines", "finance", "business"], "languages": ["putonghua", "english", "chinese"], "language_level": ["excellent", "good"], "hard_skills": ["problem solving"], "soft_skills": ["problem solving", "communication and interpersonal skills", "tactful", "customer services skills"], "languages_combined": [{"language": "putonghua", "language_level": ["excellent", "good"]}, {"language": "english", "language_level": ["excellent", "good"]}, {"language": "chinese", "language_level": ["excellent", "good"]}]}, "experience_required": {"duration": ["1 year"], "field": ["relevant experience"]}}, {"job_id": "100003009052054", "location_code": "hk", "company": "PURE International (Hong Kong) Ltd", "job_title": "Pure Group - Customer Services Supervisor", "description": "Responsibilities:\n\nSupervise the team for the daily operations\nHandle member\u2019s request for membership issues including termination, suspension, transfer of membership, re-activation of membership etc.\nHandle complaint on billing and membership issues\nPrepare management report for analysis\nDocument filing and other administrative duties\nRequirements:\n\nPost-secondary or Degree holder\nAt least 4 years of customer services working experiences, in which 1 years in service industry at a supervisory level is an advantage\nExcellent in handling customer complaint and strong negotiation skills\nFamiliar with billing or customer enquiry system, and Excel will be advantage\nFluency of both spoken and written English, Cantonese, and Mandarin\nGood writing skills especially business correspondence\nAble to prioritize and work under pressure\nWorking Hours:\u00a0Monday to Friday 9am-6pm\n\n\n\nWorking Location:\u00a0Central\n\nWe provide excellent career opportunities, full training and support programs, attractive remuneration and a fun working environment. For further enquiry, please email us on\u00a0hr @pure-international.com\u00a0or WhatsApp 6792 4467.\n\nPersonal data provided by applicants will be used solely for recruitment purposes.", "employment_types": ["Full Time"], "selling_points": ["Premium lifestyle brand, 5 days work, 9-6pm", "Supervise team to handle membership issues", "Free access to Fitness club and Yoga"], "locations": ["Central"], "categories": ["Beauty Care / Health", "Athletics / Fitness / Sports & Recreation", "Sales, CS & Business Devpt", "Customer Service - Supervisor / Officer", "Others"], "post_time": "2022-01-17T01:58:54Z", "salary": {"currency": null, "max": null, "min": null, "period": "monthly", "term": null}, "salary_visible": false, "title_keywords": ["supervisor"], "responsibilities": ["document filing", "analysis", "daily operations", "administrative duties", "management report"], "requirements": {"degrees": ["degree holder"], "majors": [], "languages": ["cantonese", "english", "mandarin"], "language_level": ["fluency"], "hard_skills": ["excel", "writing skills"], "soft_skills": ["able to prioritize", "negotiation skills", "writing skills", "work under pressure"], "languages_combined": [{"language": "cantonese", "language_level": ["fluency"]}, {"language": "english", "language_level": ["fluency"]}, {"language": "mandarin", "language_level": ["fluency"]}]}, "experience_required": {"duration": ["at least 4 years", "1 years"], "field": ["supervisory level", "service industry", "customer services"]}}, {"job_id": "100003009053519", "location_code": "hk", "company": "Jones Lang LaSalle Management Services Ltd", "job_title": "\u591c\u66f4\u52a9\u7406\u5ba2\u6236\u670d\u52d9\u4e3b\u4efb (\u99d0\u5beb\u5b57\u6a13\u7e3d\u90e8)", "description": "\u5de5\u4f5c\u7bc4\u7587:\n\n\u76e3\u63a7\u4fdd\u5b89\u7cfb\u7d71\u53ca\u7dad\u6301\u65e5\u5e38\u904b\u4f5c\n\u63d0\u4f9b\u652f\u63f4\u670d\u52d9\u53ca\u8a0a\u606f\u50b3\u905e\n\u8655\u7406\u7a81\u767c\u4e8b\u60c5\uff0c\u5982\u4eba\u624b\u5b89\u6392\u3001\u6280\u8853\u652f\u63f4\u3001\u6295\u8a34\u53ca\u5371\u6a5f\u7b49\n\u5b9a\u671f\u5230\u6240\u5c6c\u5927\u5ec8\u9032\u884c\u7a81\u64ca\u6aa2\u67e5\u6216\u8655\u7406\u7a81\u767c\u60c5\u6cc1\n\u8ca0\u8cac\u90e8\u9580\u4e3b\u7ba1\u6d3e\u9063\u7684\u8a08\u5283\n\n\u8cc7\u6b77\u8981\u6c42:\n\n\u4e2d\u4e94\u5b78\u6b77\u6216\u4ee5\u4e0a\n\u64cd\u6d41\u5229\u7cb5\u8a9e\u3001\u82f1\u8a9e\u53ca\u666e\u901a\u8a71\n\u826f\u597d\u7d44\u7e54\u80fd\u529b\n\u96fb\u8166\u6587\u66f8\u8655\u7406\u53ca\u4e2d\u6587\u8f38\u5165\n\n\u00a0\u6b61\u8fce\u76f4\u63a5\u81f4\u96fb2922-4404\u8207\u9ec3\u5148\u751f\u67e5\u8a62\u3002\n\n\u00a0We offer attractive remuneration package and good career prospect for the right applicant.\n\nPlease apply by clicking\u00a0\"Apply Now\", or submit full resume and expected salary to the\u00a0HR Department, Room 1402, 14/F, Dorset House, Taikoo Place, 979 King's Road, Quarry Bay, HK\u00a0or\u00a0fax to 2968-4177.\u00a0\n\n(Please quote the reference number on the subject of email)\n\nApplicants not invited for interviews within 6 weeks may consider their applications unsuccessful. Information provided will be treated with strict confidential and be used for the purpose of employment only.", "employment_types": ["Full Time", "Permanent"], "selling_points": ["DSE or above is required", "Customer Services job in Head Office", "With hospitality exp will be an advantage"], "locations": ["Quarry Bay"], "categories": ["Sales, CS & Business Devpt", "Customer Service - Supervisor / Officer", "Hospitality / F & B", "Hospitality / Hotel Services", "Property / Real Estate", "Property Management"], "post_time": "2022-01-17T07:40:01Z", "salary": {"currency": null, "max": null, "min": null, "period": "monthly", "term": null}, "salary_visible": false, "title_keywords": [], "responsibilities": [], "requirements": {"degrees": [], "majors": [], "languages": [], "language_level": [], "hard_skills": [], "soft_skills": [], "languages_combined": []}, "experience_required": {"duration": [], "field": []}}, {"job_id": "100003009052156", "location_code": "hk", "company": "CKC Solutions Limited", "job_title": "Customer Services Officer (Airline Services Call Centre) - HKD16-21.5K+Bonus (Fresh Grad Welcome)", "description": "Responsibilities\n\nAnswering inbound call from customer related to the flight ticket booking, flight schdule and memebership information, etc.\nMaintain a positive, empathetic and professional attitude toward customers at all times\nGood communictaions needed with different partners\nNo sales is required\n3 months paid training will be provided\n\nRequirements\n\n\nDiploma or above,\u00a0Fresh Graduates will also be considered\n1 year customer services experience preferable\nExperience in airlines / travel agencies / hotel will be advantage\nGood command of spoken Chinese and English\n5 days work week,willing to work on shift and public holiday\nLocation: Tsuen Wan\nBenefits:\n\nComprehensive training with pay\nJoin-in Bonus $12,000\n14-day annual leave\nMPF/Provident Fund schemes\nMarriage leave\nMaternity leave\nPaternity leave\nCareer development opportunities\nMedical insurance\nStaff offer and staff recreation\nSponsorship of external study\nThis is a great opportunity to be part of the team and get more new exposure. If you are interested in this role please send us your CV or call us on +852 2552 7616 for a further discussion.", "employment_types": ["Full Time", "Permanent"], "selling_points": ["5 days work week, shift needed", "Bonus: $12,000", "permanent"], "locations": ["Tsuen Wan Area"], "categories": ["Transportation & Logistics", "Aviation Services", "Sales, CS & Business Devpt", "Call Centre", "Customer Service - Supervisor / Officer"], "post_time": "2022-01-17T02:17:07Z", "salary": {"currency": null, "max": null, "min": null, "period": "monthly", "term": null}, "salary_visible": false, "title_keywords": ["customer services officer"], "responsibilities": ["maintain", "booking"], "requirements": {"degrees": ["diploma or above"], "majors": [], "languages": ["english", "chinese"], "language_level": ["good command"], "hard_skills": ["wan", "airlines"], "soft_skills": [], "languages_combined": [{"language": "english", "language_level": ["good command"]}, {"language": "chinese", "language_level": ["good command"]}]}, "experience_required": {"duration": ["1 year"], "field": ["customer services"]}}, {"job_id": "100003009051933", "location_code": "hk", "company": "Octopus Holdings Limited", "job_title": "Customer Relations Assistant (Ref: OCL/OPS/2021-224)", "description": "Job Responsibilities:\nCreate and prepare communication collateral including content of company website and interactive\u00a0voice response system (IVRS).\nReview and develop new questions and answers for virtual assistant (chatbox) in company website.\nAssist the Manager, Customer Relations to manage and implement various projects for the\u00a0company.\nPerform general clerical support to the customer relations section.\nHandle ad-hoc projects as required.\nRequirements:\nUniversity graduate, fresh graduate is preferred.\nExcellent English and Chinese writing skills.\nGood command of spoken English and Cantonese.\nProficient in PC skills (MS Word / Excel / PowerPoint /Chinese Word Processing).\nProficient in Adobe application and video editing is a plus", "employment_types": ["Full Time", "Permanent"], "selling_points": ["Review and develop new questions", "University graduate, fresh graduate is preferred", "Handle ad-hoc projects as required"], "locations": ["Kowloon Bay"], "categories": ["Sales, CS & Business Devpt", "Customer Service - Supervisor / Officer", "Others"], "post_time": "2022-01-17T01:32:44Z", "salary": {"currency": null, "max": null, "min": null, "period": "monthly", "term": null}, "salary_visible": false, "title_keywords": ["assistant"], "responsibilities": ["review", "clerical support", "develop", "communication", "ad-hoc projects", "company website"], "requirements": {"degrees": ["university graduate", "fresh graduate"], "majors": [], "languages": ["cantonese", "english", "chinese"], "language_level": ["excellent", "good command", "proficient"], "hard_skills": ["excel", "plus", "chinese word processing", "powerpoint", "writing skills", "video editing", "adobe", "pc skills", "ms word"], "soft_skills": ["writing skills"], "languages_combined": [{"language": "cantonese", "language_level": ["good command"]}, {"language": "english", "language_level": ["excellent", "good command"]}, {"language": "chinese", "language_level": ["excellent", "proficient"]}]}, "experience_required": {"duration": [], "field": []}}, {"job_id": "100003009051055", "location_code": "hk", "company": "Cargotec Asia Limited", "job_title": "Customer Service Officer", "description": "We are looking for a high caliber candidate to develop his/her career in our Company\uff1a\n\nThe Job :\n\nTo handle customers' enquiries, orders and complaints in an efficient and professional manner;\nTo manage parts order processing, and monitor backlog status and parts delivery;\nTo follow up with customers for invoicing and payment arrangement;\nTo analyze GM% and freight cost of sales orders so as to improve the profitability;\nTo liaise with central service team for pricing and lead time checking;\nTo act as key user for Internal Service Program and solve the issues raised by service technicians (training will be provided);\nTo drive and grow parts sales by actively contacting customers and identifying their needs;\nTo support the service jobs schedule and maintenance service team;\nTo provide feedback on the efficiency of customer service process;\nAd-hoc projects assigned by line Manager.\n\nThe Person:\n\nDegree in Business Administration or equivalent;\nMin. 2 years relevant experience in customer service or sales administration. Proven track record in order processing\uff1b\nIndependent, fast learner, self-motivated, details-minded, well organized and able to work under pressure;\nBusiness\u00a0acumen and\u00a0Customer-oriented;\nGood interpersonal and negotiation skills;\nGood command of spoken and written English, Cantonese and Mandarin;\nKnowledge in SAP will be an advantage;\nFresh graduate will also be considered.\n\nWe offer competitive remuneration package and generous fringe benefits including 5-days work week, medical and dental insurance, discretionary bonus and excellent working condition. Interested candidates please apply through JobsDB.\n\nAll information received will be kept in strict confidence and only for employment-related purpose.\n\n\n\n", "employment_types": ["Full Time", "Permanent"], "selling_points": ["Fresh graduate will also be considered", "Well organized and self-motivated", "Good interpersonal and negotiation skills"], "locations": ["Kwai Fong"], "categories": ["Sales, CS & Business Devpt", "Customer Service - Supervisor / Officer", "Account Servicing", "Sales Administration"], "post_time": "2022-01-15T01:40:36Z", "salary": {"currency": null, "max": null, "min": null, "period": "monthly", "term": null}, "salary_visible": false, "title_keywords": ["customer service officer"], "responsibilities": ["cost", "maintenance", "monitor", "professional manner", "checking", "invoicing", "payment", "customer service", "schedule", "order processing", "liaise with", "ad-hoc projects"], "requirements": {"degrees": ["degree", "fresh graduate"], "majors": ["business administration"], "languages": ["cantonese", "english", "mandarin"], "language_level": ["good command"], "hard_skills": ["sap", "order processing", "acumen"], "soft_skills": ["self-motivated", "independent", "well organized", "customer-oriented", "customer service", "negotiation skills", "business acumen", "fast learner", "interpersonal", "work under pressure"], "languages_combined": [{"language": "cantonese", "language_level": ["good command"]}, {"language": "english", "language_level": ["good command"]}, {"language": "mandarin", "language_level": ["good command"]}]}, "experience_required": {"duration": ["2 years"], "field": ["sales administration", "customer service", "relevant experience"]}}, {"job_id": "100003009053592", "location_code": "hk", "company": "Principal Trust Company (Asia) Limited", "job_title": "Senior Officer, Customer Contact Center", "description": "Principal Hong Kong is one of the major service providers of total retirement solutions in Hong Kong.\u00a0We are one of the winners received \"The 2021 MPF Award\" by MPF Ratings.\n\nAs a Senior Officer in Customer Contact Center, you\u2019ll help our customers by answering their questions and concerns every day. The best way to describe our Customer Contact Center is friendly and busy. You will answer inbound calls within a call center environment and handle customer inquiries through multiple technology platforms. You will also assist walk-in customer and conduct outbound calls occasionally.\n\nOther responsibilities include:\n\nProvide service on processing member enrollments, terminations and group changes in accordance with the company procedures, policies and local regulations\nMaintain accurate records and complete documentation of customer contact center functions\nAssist in preparing relevant materials in response to client enquiry and requests and provide administrative support to other team within the departments in a professional manner\nAssist in any ad-hoc assignments or special projects as required\n\nEssential Skills, Experience and Competencies\n\nFor the best customer experience, we are looking for a fast-learner with customer service experience and excellent communication skills.\n\nOther key skills required for this role:\n\nAssociate Degree or High Diploma holder\nExperience working within call centers or customer service preferred\nKnowledge in MPF, ORSO and investment products will be an advantage\nFluent in spoken and written English and Chinese (both Cantonese and Mandarin)\nAttention to detail, ability to multi-task with proficient computer skills\nCandidate with less experience will be considered as Officer\n\nWhat We Offer\n\nPrincipal offers employees a competitive package and a comprehensive range of benefits to help meeting your needs now and in the future, including:\n\n5-Day Work Week\nYear-end Payment\nDiscretionary Bonus\nBirthday Leave\nMedical Plan\nLife Insurance\nPension Scheme\nEmployee Stock Purchase Plan\nAnd Growth Opportunities!", "employment_types": ["Full Time", "Permanent"], "selling_points": ["Friendly and supportive team culture", "Work experience in call center / customer services", "Excellent communicative skills and great attitude"], "locations": ["Kwun Tong"], "categories": ["Sales, CS & Business Devpt", "Call Centre", "Customer Service - Supervisor / Officer", "Banking / Finance", "Asset Management"], "post_time": "2022-01-17T07:12:35Z", "salary": {"currency": null, "max": null, "min": null, "period": "monthly", "term": null}, "salary_visible": false, "title_keywords": ["senior officer"], "responsibilities": ["regulations", "policies", "ad-hoc assignments", "customer service experience", "procedures", "professional manner", "communication", "maintain", "contact", "documentation", "provide administrative support"], "requirements": {"degrees": ["high diploma", "associate degree"], "majors": [], "languages": ["cantonese", "english", "chinese", "mandarin"], "language_level": ["fluent"], "hard_skills": ["investment products", "computer skills"], "soft_skills": ["customer service", "multi-task", "attention to detail"], "languages_combined": [{"language": "cantonese", "language_level": ["fluent"]}, {"language": "english", "language_level": ["fluent"]}, {"language": "chinese", "language_level": ["fluent"]}, {"language": "mandarin", "language_level": ["fluent"]}]}, "experience_required": {"duration": [], "field": ["customer service"]}}, {"job_id": "100003009049420", "location_code": "hk", "company": "TOYS WONDERLAND LIMITED", "job_title": "Customer Service Executive", "description": "Salary: $19,000 - $25,000\nShift Duty: (1) 10am-7pm/ (2) 1pm-10pm \u3010Optional\u3011\n\nKey Responsibilities:\n\n\nRespond to customer inquiries,\u00a0feedback, and compliments\u00a0in a timely manner\u00a0via email and Facebook Page\nDeliver a seamless online shopping experience to our\u00a0customers\nMaintain good relationships with premier customers\nProvide administrative/operational support to operation teams\nResponsible for ad-hoc duties as requested\nRequirements:\n\nThe permanent Hong Kong resident status\nThe minimum pass rate in 5 HKCEE/HKDSE subjects including the English Language; or equivalent\nProficiency in English (spoken and written).\nBasic computer skills including Microsoft Word, Excel.\nWhat's on Offer\n\nBank holiday Off\nGroup Medical Insurance\nMaternity Leave\nBereavement leave\n\u00a0Birthday Leave\nAnnual Leave\nThe interested party may send a full resume with current and expected salary to\u00a0us for consideration.\u00a0Personal data provided by job applicants will be used strictly in accordance with our personal data policy and for recruitment purposes only. Candidates not notified within six weeks may consider their application unsuccessful. All related information will be kept in our file for up to 24 months.", "employment_types": ["Full Time", "Permanent"], "selling_points": [], "locations": ["Kwai Fong"], "categories": ["Sales, CS & Business Devpt", "Customer Service - Supervisor / Officer"], "post_time": "2022-01-14T08:36:02Z", "salary": {"currency": null, "max": null, "min": null, "period": "monthly", "term": null}, "salary_visible": false, "title_keywords": ["customer service executive"], "responsibilities": ["operational support", "customer inquiries", "a timely manner", "teams", "maintain", "ad-hoc duties", "facebook"], "requirements": {"degrees": ["hkdse"], "majors": [], "languages": ["english"], "language_level": ["proficiency"], "hard_skills": ["computer skills", "microsoft word", "basic", "excel"], "soft_skills": [], "languages_combined": [{"language": "english", "language_level": ["proficiency"]}]}, "experience_required": {"duration": [], "field": []}}, {"job_id": "100003009053980", "location_code": "hk", "company": "Compass Offices", "job_title": "Receptionist / Client Service Executive (Fresh Graduate Welcome!)", "description": "Adventure, discovery, work hard play hard, a unique work-life balance, no weekend shifts and no night shifts; this is but a part of what you can experience as a valued employee of Compass Offices.\n\nBring your passion for working in a team and helping people!\n\nCompass Offices currently offers over 5,000 workstations in Hong Kong and many more in Australia, China, Japan, Malaysia, Philippines, Singapore and Vietnam, visit our company website to find out more.\n\n\n\nhttps://www.compassoffices.com\n\n\nFresh Graduates are welcome.\n\nWorking Hours: Monday to Friday \u2013 Office hours\n\n\nYour activities:\n\nWelcome all clients and guests and be a great first impression\nMaintain optimal client relations, manage clients\u2019 check-in and check-out, ad hoc requests and reservations\nProviding services and support in accordance with clients\u2019 preferences\nEnsure that all customer contact is handled politely and efficiently and accurately meets the needs\nInspect the front and back areas and make sure all is always impeccable\nPerform any other reasonable duties as required by the Management from time to time.\n\nWhat you bring:\n\nPrior experience in customer service and hospitality is a plus\nProficiency in written and spoken English\u00a0\nAn outgoing personality, strong communication skills and great team player\nA proactive, dynamic and enthusiastic attitude\nWillingness to learn and develop\n\nPlease submit your resume with current and expected salary. All applications will be treated strictly confidential for recruitment purpose only.\n\n\n", "employment_types": ["Full Time", "Permanent"], "selling_points": ["Top leading Serviced Office provider in HK", "5-Day work, NO night & NO weekend shift!", "Fresh graduate welcomed with Career Opportunity"], "locations": ["Central & Western Area"], "categories": ["Admin & HR", "Receptionist", "Sales, CS & Business Devpt", "Customer Service - Supervisor / Officer", "Hospitality / F & B", "Hospitality / Hotel Services"], "post_time": "2022-01-17T07:54:17Z", "salary": {"currency": null, "max": null, "min": null, "period": "monthly", "term": null}, "salary_visible": false, "title_keywords": ["receptionist", "service executive"], "responsibilities": ["management", "ad hoc requests", "develop", "communication", "maintain", "customer service", "contact", "recruitment", "company website"], "requirements": {"degrees": [], "majors": [], "languages": ["english"], "language_level": ["proficiency"], "hard_skills": ["no", "plus", "make", "dynamic", "compass"], "soft_skills": ["outgoing personality", "communication skills", "passion for", "unique", "customer service", "dynamic", "enthusiastic", "team player", "proactive"], "languages_combined": [{"language": "english", "language_level": ["proficiency"]}]}, "experience_required": {"duration": [], "field": ["customer service"]}}, {"job_id": "100003009048926", "location_code": "hk", "company": "Holimood Limited", "job_title": "Customer Service Specialist", "description": "Job Responsibilities:\n\nProvide high quality customer service and meet service goal\nAnswering telephone hotline in professional manner in order to respond users\u2019 requirements\nHandle customer service inquiries, reservations and complaints\nWork with internal departments to seek possible solution for customers\nEnsure a smooth running of the process with customers\nOrganize and manage daily operations of the office\n\nRequirements:\n\nAt least 2-year customer service/ travel industry related experience\nGood command of Cantonese, spoken English and Mandarin\nExperience in customer service or travel industry is preferred\nProficient in Chinese and English typing\nAble to use Microsoft Office, Computer Software and contain some basic computer knowledge\nHard-working, Careful, Active, Responsible, enable to work under pressure and fast-paced work environment\nAble to work on Sat, Sun and Public Holiday is preferred.\u00a0\n\nAbout Holimood\n\nHolimood is an online platform providing on-the-go booking experience for glamping, staycation, yachts and local activities based in Hong Kong.\u00a0Holimood has devoted ourselves to innovate, we are actively diversifying our offerings to provide highly curated experiences for consumers. Through synergy of our passionate team, Holimood grew from a start-up business to a major booking platform in a short time. Discover Hong Kong like you have never seen before, visit https://holimood.com.\n\nThat\u2019s about us\u2026 and what about you? If you\u2019re driven and up for a challenge, or if you\u2019re passionate about putting your ideas forward and see them happen, join us!", "employment_types": ["Full Time"], "selling_points": ["Free Snacks, Coke, Fruits & Cats | 5 Working Days", "Proficient in Chinese and English typing", "Able to work on Sat, Sun and Public Holiday"], "locations": ["Kwun Tong"], "categories": ["Sales, CS & Business Devpt", "Customer Service - Supervisor / Officer"], "post_time": "2022-01-14T07:43:30Z", "salary": {"currency": "HKD", "max": 16999, "min": 14000, "period": "monthly", "term": null}, "salary_visible": true, "title_keywords": ["specialist", "customer service"], "responsibilities": ["customer service", "quality", "professional manner", "manage daily operations"], "requirements": {"degrees": [], "majors": [], "languages": ["cantonese", "english", "chinese", "mandarin"], "language_level": ["good command", "proficient"], "hard_skills": ["go", "basic", "typing", "microsoft office"], "soft_skills": ["passionate", "careful", "responsible", "customer service", "hard-working", "devoted", "active", "driven", "passionate about", "work under pressure"], "languages_combined": [{"language": "cantonese", "language_level": ["good command"]}, {"language": "english", "language_level": ["good command", "proficient"]}, {"language": "chinese", "language_level": ["proficient"]}, {"language": "mandarin", "language_level": ["good command"]}]}, "experience_required": {"duration": ["at least 2-year"], "field": ["related", "customer service"]}}, {"job_id": "100003009052702", "location_code": "hk", "company": "Headsearch21 Consultancy Ltd", "job_title": "Logistic CS Supervisor (MNC)", "description": "To cope with the expansion of the Company, our client is now looking for high caliber candidate to join the Customer Services Team in Hong Kong:\n\nResponsibilities:\n\nWork closely with overseas agents, carriers, co-loaders, customers, suppliers and warehouse team\nResponsible for arranging inbound & outbound shipment for customers\nAnswer customers' enquiries and handle complaints\nFollow up shipment and achieve on-time delivery\nMaintain up-to-date record\nHandle pre-alert and general correspondence\n\nRequirements:\n\nAt least 4 years CS experience in\u00a0Logistic Co. / Freight-Forwarder / 3PL\nForm 5 or above\nGood knowledge of general procedures of I/E documentation and custom declaration\nProficiency in MS Office or SAP / WMS system\nGood command\u00a0of English and Mandarin\nCandidate with less experience will also be considered as \"Logistic CS Officer\"\n\nInterested parties, please click the \"Apply Now\" or send\u00a0 your updated resume with\u00a0 Current\u00a0and\u00a0Expected salary\u00a0in MS word format to cv @headsearch21.com\u00a0\n\nFor more information please contact Ms. Leung at 3188 3072.\n\nRef #: SD01005\n\nAll information collected will be treated in strict confidence and be used for recruitment purpose only\n\nCompany Web-Site:\u00a0www.headsearch21.com", "employment_types": ["Full Time", "Permanent"], "selling_points": ["4 years CS exp in Logistic Co. / Forwarder / 3PL", "SAP / WMS system (Prefer)", "Near MTR / Modern Office Design"], "locations": ["Not Specified"], "categories": ["Sales, CS & Business Devpt", "Customer Service - Supervisor / Officer", "Transportation & Logistics", "Freight Forwarding", "Shipping"], "post_time": "2022-01-17T03:45:08Z", "salary": {"currency": "HKD", "max": 19999, "min": 14000, "period": "monthly", "term": null}, "salary_visible": true, "title_keywords": ["supervisor"], "responsibilities": ["maintain", "inbound & outbound", "handle complaints"], "requirements": {"degrees": ["form 5 or above"], "majors": [], "languages": ["english", "mandarin"], "language_level": ["good command"], "hard_skills": ["documentation", "sap", "ms office"], "soft_skills": [], "languages_combined": [{"language": "english", "language_level": ["good command"]}, {"language": "mandarin", "language_level": ["good command"]}]}, "experience_required": {"duration": ["at least 4 years"], "field": ["cs"]}}, {"job_id": "100003009044977", "location_code": "hk", "company": "Harbour City Estates Ltd", "job_title": "CUSTOMER SERVICE AMBASSADOR", "description": "Job Responsibilities:\n\nTo handle enquiries from shoppers / tourists about the shopping mall\nTo offer assistance / services to shoppers as needed in a helpful manner\nShift duty from 8:00 a.m. to 10:00 p.m. is required\n\n\n\nRequirements:\n\nPassionate in retail and hospitality work\nPleasant, proactive and customer-oriented with good manners\nF. 5 / DSE / Diploma holder or above preferably in Hospitality / Travel / Business-related disciplines\n1 - 2 years of experience in customer service, hospitality or sales industry\nFresh university graduates with some part-time experience in customer service field will also be considered\nGood command of spoken Cantonese, English, Putonghua\nCandidate with more experience will be considered as Senior Customer Service Ambassador\n\n\nSuccessful candidates will be provided with a tailor-made induction course to get familiar with our shopping mall and to acquire necessary customer service skills. On-going classroom and on-the-job trainings will be provided where appropriate for a successful long-term career development within the Company.\n\nWe offer competitive remuneration package that commensurate with experience and qualifications. Interested parties are invited to send full resume stating contact telephone number, date available, present and expected salary, Chinese & English exam results in HKCEE / DSE / HKAL to our recruitment email address.\n\n(Personal data provided will be used strictly in accordance with the Company's personal data policy which is available upon request)", "employment_types": ["Full Time", "Permanent"], "selling_points": ["To handle enquiries from shoppers / tourists", "1 - 2 years of experience in customer service", "Fresh university graduates will also be considered"], "locations": ["Tsim Sha Tsui"], "categories": ["Sales, CS & Business Devpt", "Customer Service - Supervisor / Officer", "Hospitality / F & B", "Hospitality / Hotel Services", "Property / Real Estate", "Property Management"], "post_time": "2022-01-15T03:49:26Z", "salary": {"currency": null, "max": null, "min": null, "period": null, "term": null}, "salary_visible": false, "title_keywords": ["customer service ambassador"], "responsibilities": ["handle enquiries"], "requirements": {"degrees": ["diploma holder", "dse"], "majors": ["related disciplines", "hospitality", "business"], "languages": ["cantonese", "putonghua", "english"], "language_level": ["good command"], "hard_skills": [], "soft_skills": ["passionate", "customer service skills", "pleasant", "customer-oriented", "customer service", "proactive"], "languages_combined": [{"language": "cantonese", "language_level": ["good command"]}, {"language": "putonghua", "language_level": ["good command"]}, {"language": "english", "language_level": ["good command"]}]}, "experience_required": {"duration": ["1 - 2 years"], "field": ["customer service"]}}, {"job_id": "100003009055225", "location_code": "hk", "company": "Winfat Industrial Co., Limited", "job_title": "Sales Executive (Toys) (5 Days Work)", "description": "Responsibilities:\n\nLiaise with overseas customers in order confirmation and handle their daily enquiries;\nCommunicate with China factories and internal parties;\nEnsure accurate and on-time production orders, order status reports and delivery time schedule, etc;\nCoordinate samples development and delivery on time and prepare for customer presentation;\nFollow up the whole merchandising process from product development until production;\nPrepare product related documents and reports;\nHandle ad hoc assignments as required.\n\nRequirements:\n\nHigh diploma or above in Sales and Marketing or related discipline;\nMinimum 2 years experience of merchandising or\u00a0manufacturing\u00a0trading in TOYS\u00a0;\nFamiliar with US & EU market will be advantage;\nStrong interpersonal and time management skill;\nWell-organized, self-motivated, flexible and able to work independently;\nGood PC skill (MS Word, Excel, PowerPoint & Chinese WP is essential);\nImmediate available is preferred.\n\nAttractive salary package will be offered to the right candidates.\u00a0\n\nInterested parties. Please send your full resume including current and expected salary by clicking \u201cApply Now\u201d.\u00a0\u00a0 Personal data will be collected for recruitment purpose only.\n\nLearn us more at www.winfun.com", "employment_types": ["Full Time", "Permanent"], "selling_points": ["Sales order follow up, 2 yrs Toys exp", "Exp. in system entry and coordination", "Double pay, 5 work days, Med ins"], "locations": ["Tsim Sha Tsui"], "categories": ["Sales, CS & Business Devpt", "Customer Service - Supervisor / Officer", "Marketing / Public Relations", "Marketing - General / Support", "Account Servicing"], "post_time": "2022-01-18T01:52:03Z", "salary": {"currency": null, "max": null, "min": null, "period": "monthly", "term": null}, "salary_visible": false, "title_keywords": ["sales executive"], "responsibilities": ["communicate with", "related documents", "merchandising", "coordinate", "reports", "schedule", "ad hoc assignments", "liaise with", "internal parties"], "requirements": {"degrees": ["high diploma or above"], "majors": ["marketing"], "languages": ["chinese"], "language_level": ["good"], "hard_skills": ["excel", "chinese wp", "powerpoint", "pc skill", "ms word"], "soft_skills": ["flexible", "self-motivated", "work independently", "well-organized", "time management skill", "interpersonal"], "languages_combined": [{"language": "chinese", "language_level": ["good"]}]}, "experience_required": {"duration": ["minimum 2 years"], "field": ["toys", "manufacturing", "merchandising", "trading"]}}, {"job_id": "100003009055887", "location_code": "hk", "company": "Michael Page", "job_title": "Head  of frontline Cashier (Team leader of 30 ~ 40 Cashiers)", "description": "Heading the cashier team\n\nWork in a friendly working environment\n\nClient Details\n\nMy Client is looking for a head cashier to lead a team of 30 - 40 cashier in daily operations\n\nDescription\n\nManage a team of 30 - 40 Cashiers in:\n\n\u4e00\u822c\u6536\u9280\u5de5\u4f5c\uff0c\u5982\u73fe\u91d1\u9a57\u8b49\u3001\u9ede\u7b97\u53ca\u5206\u985e\n\nDaily cashier duties.\n\n\u63d0\u4f9b\u826f\u597d\u9867\u5ba2\u670d\u52d9\u548c\u8655\u7406\u5ba2\u4eba\u67e5\u8a62\u53ca\u7591\u554f\n\nProvide excellent customer services\n\n\u5168\u529b\u914d\u5408\u5206\u5e97\u524d\u7dda\u540c\u4e8b\u4e4b\u92b7\u552e\u5de5\n\nCooperate with retail staff with daily retail operation\n\n\u4f7f\u7528POS\u96f6\u552e\u7cfb\u7d71\n\nCoach junior cashier on POS system\n\n\u7ba1\u7406\u5009\u5b58\u53ca\u9ede\u6578\u7b49\u5de5\u4f5c\n\nManage inventory and warehouse matters\n\nProfile\n\n\u9069\u61c9\u529b\u5f37,\u80fd\u8655\u7406\u591a\u9805\u4efb\u52d9\u53ca\u52c7\u65bc\u63a5\u53d7\u6311\u6230\n\nHigh adaptive ability, able to handle multi-task and willing to take challenge\n\n\u5177\u76f8\u95dc\u6536\u9280\u6216\u9867\u5ba2\u670d\u52d9\u7d93\u9a57\u66f4\u4f73\n\nExperience in cashiering / customer service is preferable\n\n\u5177\u8cac\u4efb\u611f,\u7a4d\u6975\u6b63\u9762\u53ca\u4e3b\u52d5\n\nHigh sense of responsibility, positive and proactive\n\nJob Offer\n\nPromising career in well established company\n\nINterested applicant please send me your resume to Marcochong@michaelpage com hk Or you can call me @ 52909990.", "employment_types": ["Full Time", "Permanent"], "selling_points": ["Lead a team of 30 - 40 Cashiers", "Friendly working environments", "Attractive salary with great benefits"], "locations": ["Not Specified"], "categories": ["Accounting", "Others", "Sales, CS & Business Devpt", "Customer Service - Supervisor / Officer", "Retail Sales"], "post_time": "2022-01-18T03:03:13Z", "salary": {"currency": null, "max": null, "min": null, "period": "monthly", "term": null}, "salary_visible": false, "title_keywords": ["team leader"], "responsibilities": ["inventory", "customer services", "lead a team", "daily operations", "customer service", "cooperate with"], "requirements": {"degrees": [], "majors": [], "languages": [], "language_level": [], "hard_skills": ["pos system"], "soft_skills": ["multi-task", "high sense of responsibility", "customer service", "friendly", "proactive", "positive"], "languages_combined": []}, "experience_required": {"duration": [], "field": ["customer service"]}}, {"job_id": "100003009049800", "location_code": "hk", "company": "Scanwell Logistics (Hong Kong) Ltd", "job_title": "Customer Services / Senior Customer Services", "description": "Responsibilities:\n\nProvide quality services both internal / external\nData entry and generation of reports\nProvide general support to the team\nCommunicate and co-ordinate with overseas office\n\n\u00a0Requirements:\n\nHKCEE / HKDSE or above\n1 year working experience is preferable\nGood command of English and Chinese (including Mandarin)\nGood in MS Office applications\nAble to work outside office hours and public holidays\nImmediately available is highly preferred\n\n\u00a0Benefits:\n\nMedical / Hospitalization Insurance\nLife Insurance\n5-Day Work Week\nBank Holidays\nDouble Pay\nPaid Sick Leave\nOvertime Allowance\nPerformance Bonus\n\nWe offer attractive remuneration package and good career prospect to the right candidates.\u00a0 Interested parties please send your detailed resume with expected salary and position applied by clicking \"Apply Now\".\n\n\nAll information collected will be used for recruitment purpose only.\n", "employment_types": ["Full Time", "Permanent"], "selling_points": ["Provide quality services both internal / external", "Fresh graduate will also be considered", "5-day work week"], "locations": ["Kowloon Bay"], "categories": ["Sales, CS & Business Devpt", "Customer Service - Supervisor / Officer", "Transportation & Logistics", "Freight Forwarding", "Sales Administration"], "post_time": "2022-01-14T09:14:56Z", "salary": {"currency": null, "max": null, "min": null, "period": "monthly", "term": null}, "salary_visible": false, "title_keywords": [], "responsibilities": ["data entry", "co-ordinate with", "quality", "reports", "general support"], "requirements": {"degrees": ["hkdse"], "majors": [], "languages": ["english", "chinese", "mandarin"], "language_level": ["good command"], "hard_skills": ["ms office"], "soft_skills": [], "languages_combined": [{"language": "english", "language_level": ["good command"]}, {"language": "chinese", "language_level": ["good command"]}, {"language": "mandarin", "language_level": ["good command"]}]}, "experience_required": {"duration": ["1 year"], "field": []}}, {"job_id": "100003009044271", "location_code": "hk", "company": "EC Healthcare", "job_title": "Customer Service Officer", "description": "Responsibilities:\n\n\nHandle email, live chat, inbound and outbound call on all customer enquiries in a proactive and positive manner\nResponse promptly to client\u2019s inquiries\nHandle and resolve client\u2019s complaints\nObtain and evaluate all relevant information to handle products and service inquiries\nDirect requests and unresolved issues to the designated resource\nResearch questions using available information recourse\nRecord details of inquiries, comments and complaints\nRecord details of actions taken\nIdentify and escalate situations requiring urgent attention\nInform management of recurring problems\nManage administration\nCommunicate and coordinate with internal departments\nFollow up on customer interactions\nProvide feedback on the efficiency of the customer service process\nCommunicate with another region call centre regarding cases / complain handle\n\nRequirements:\n\nA HKCEE (Hong Kong Certificate of Education Examination) or HKDSE (Hong Kong Diploma of Secondary Education) holder with relevant working experience, or holder of associate degree, higher diploma or degree from a tertiary institution\nAt least 1-year experience in customer service environment preferably in medical or aesthetics industry / Call Centre or e-commerce Knowledge of customer service principles and practice\nKnowledge of relevant computer applications\nProblem analysis and problem-solving\nConfidence, patience, politeness, tact and diplomacy, when dealing with difficult situations\nListening skills, to understand exactly what customers require;\nAttention to detail and accuracy\nProactive and able to work under pressure\nAble to work as a team and willing to learn new techniques, concepts and system\nGood command of both spoken English, Cantonese and Mandarin\nImmediate available is highly preferred\nAttractive salary package (basic salary with commission or incentive bonus)\nCandidate with previous medical or aesthetics experience will consider a more competitive offer", "employment_types": ["Full Time", "Permanent"], "selling_points": ["Handle email, live chat, inbound and outbound call", "Proactive and able to work as a team", "Medical & Beauty industry highly preferred"], "locations": ["Mong Kok"], "categories": ["Sales, CS & Business Devpt", "Call Centre", "Customer Service - Supervisor / Officer", "Medical Services", "Others"], "post_time": "2022-01-13T03:36:50Z", "salary": {"currency": null, "max": null, "min": null, "period": "monthly", "term": null}, "salary_visible": false, "title_keywords": ["customer service officer"], "responsibilities": ["communicate with", "management", "customer enquiries", "comments", "coordinate with", "evaluate", "customer service", "recurring problems", "administration"], "requirements": {"degrees": ["degree", "secondary education", "certificate", "associate degree", "diploma", "hkdse"], "majors": [], "languages": ["cantonese", "english", "mandarin"], "language_level": ["good command"], "hard_skills": ["problem-solving", "analysis", "basic", "e-commerce"], "soft_skills": ["confidence", "work as a team", "problem-solving", "willing to learn", "customer service", "attention to detail", "patience", "proactive", "work under pressure"], "languages_combined": [{"language": "cantonese", "language_level": ["good command"]}, {"language": "english", "language_level": ["good command"]}, {"language": "mandarin", "language_level": ["good command"]}]}, "experience_required": {"duration": ["at least 1-year"], "field": ["e-commerce", "relevant working experience", "education", "customer service", "medical"]}}, {"job_id": "100003009055129", "location_code": "hk", "company": "PremierVisa Group", "job_title": "\u79fb\u6c11\u9500\u552e/\u79fb\u6c11\u9867\u554f", "description": "PremierVisa Group (Hong Kong) Limited\nTsim Sha Tsui\nCompetitive package + high commission\n\nJob Highlights\n\n\u6b61\u8fce\u6709\u92b7\u552e\u7d93\u9a57\u80cc\u666f\u4eba\u58eb\u512a\u5148\n\u6b61\u8fce\u6709\u6d77\u5916\u7559\u5b78\u6216\u79fb\u6c11\u80cc\u666f\u7d93\u9a57\u4eba\u58eb\n\u80fd\u9748\u6d3b\u8b80\u5beb\u8b1b\u82f1\u8a9e\uff0c\u5ee3\u6771\u8a71\uff0c\u666e\u901a\u8a71\n\n\u5de5\u4f5c\u8077\u8cac\uff1a\n\n\u5206\u6790\u5ba2\u6236\u7684\u80cc\u666f\u3001\u8cc7\u683c\u4e26\u70ba\u5ba2\u6236\u63d0\u4f9b\u5c08\u696d\n\u8a73\u7d30\u89e3\u7b54\u5ba2\u6236\u5c0d\u5404\u570b\u79fb\u6c11\u3001\u7559\u5b78\u3001\u6d77\u5916\u5275\u696d\u7b49\u5404\u7a2e\u554f\u984c\uff0c\u7cbe\u6e96\u63a8\u85a6\u9069\u5408\u7684\u79fb\u6c11\u9805\u76ee\u7d66\u5ba2\u6236\n\u8655\u7406\u96fb\u8a71,WhatsApp,\u96fb\u5b50\u90f5\u4ef6\u7b49\u6240\u6709\u793e\u4ea4\u5a92\u9ad4\u5e73\u53f0\u7684\u67e5\u8a62\n\u8207\u65b0\u8001\u5ba2\u6236\u5efa\u7acb\u4fe1\u8cf4\u95dc\u4fc2\uff0c\u7a4d\u6975\u63a2\u7d22\u548c\u767c\u5c55\u6f5b\u5728\u5ba2\u6236\n\u51fa\u5e2d\u516c\u53f8\u6d3b\u52d5\uff0c\u63a2\u8a0e\u6703\n\n\u4efb\u8077\u8981\u6c42\uff1a\n\n\u5f62\u8c61\u6c23\u8cea\u4f73\uff0c\u6709\u92b7\u552e\u80cc\u666f\u7d93\u9a57\u8005\u512a\u5148\n\u5177\u6709\u8cac\u4efb\u5fc3\uff0c\u89aa\u548c\u529b\uff0c\u6027\u683c\u958b\u6717\uff0c\u6709\u826f\u597d\u7684\u6e9d\u901a\u80fd\u529b\u548c\u8aaa\u670d\u6280\u5de7\n\u5177\u6709\u7a4d\u6975\u548c\u81ea\u6211\u8abf\u7bc0\u5fc3\u614b\n\u80fd\u9748\u6d3b\u8b80\u5beb\u82f1\u6587\uff0c\u5ee3\u6771\u8a71\uff0c\u666e\u901a\u8a71\n\n\u5f85\u9047\u53ca\u516c\u53f8\u512a\u52e2\uff1a\n\n\u4e94\u5929\u5de5\u4f5c\uff0c\u9031\u672b\u96d9\u4f11\uff0c\u5f48\u6027\u5f37\n\u54e1\u5de5\u798f\u5229\n\u64c1\u6709\u8c50\u5bcc\u7684\u79fb\u6c11\u57f9\u8a13\u8cc7\u6599\uff0c\u70ba\u54e1\u5de5\u63d0\u4f9b\u5c08\u696d\u57f9\u8a13\uff0c\u5b78\u7fd2\u6a5f\u6703\n\u57fa\u672c\u85aa\u91d1\u52a0\u9ad8\u4f63\u91d1\u6a21\u5f0f\uff0c\u5e74\u6536\u5165\u53ef\u905450-100\u842c\u4ee5\u4e0a", "employment_types": ["Full Time"], "selling_points": [], "locations": ["Tsim Sha Tsui"], "categories": ["Sales, CS & Business Devpt", "Customer Service - Supervisor / Officer"], "post_time": "2022-01-18T01:16:43Z", "salary": {"currency": null, "max": null, "min": null, "period": "monthly", "term": null}, "salary_visible": false, "title_keywords": [], "responsibilities": [], "requirements": {"degrees": [], "majors": [], "languages": [], "language_level": [], "hard_skills": ["whatsapp"], "soft_skills": [], "languages_combined": []}, "experience_required": {"duration": [], "field": []}}, {"job_id": "100003009050019", "location_code": "hk", "company": "V-Logic Limited", "job_title": "Customer Service Officer - Fulfillment Logistics (Next to Lai King Station)", "description": "The role is challenging and require high caliber person to manage logistics operation for our clients across different industries.\u00a0 You need to be a responsible, focused and proactive self-starter; with excellent organizational, analytical and problem-solving skills.\u00a0\n\nResponsibilities\n\nHandle, manage and follow up daily orders\nMaintain smooth operation with clients, related parties and internal departments\nAnalyze findings and follow up problem shipments\nManaging timely project plans\nPrepare and update documents and reports\nBuilding partnerships with various parties and identify business opportunities\nProvide analytical data and information to enhance process and workflow with Manager and Head of Department\n\nRequirements\n\nDegree holder in Supply Chain Management / Logistics or related disciplines\nMinimum 2 years of related working experience in logistics field (fresh graduate with mature mindset is also welcome)\nExtensive knowledge in logistics and freight\nExperience in warehouse management system is preferred\nPositive with mature and detail-oriented mindset\nStrong communication skills (written and verbal) with ability to work collaboratively in a cross-functional environment\nInitiative and eager to grow with the company\nProficiency in written and spoken English & Chinese\n\nOutstanding candidate with adequate experience would be considered for a more senior position\n\n\u00a0If you are the one we are looking for, please send your full resume with expected salary by clicking \"Apply Now\".\n\n\nResume without expected salary will not be considered.\n\nJob Location: Kwai Chung (Next to Lai King\u00a0MTR Station)", "employment_types": ["Full Time", "Permanent"], "selling_points": [], "locations": ["Kwai Tsing Area"], "categories": ["Sales, CS & Business Devpt", "Customer Service - Supervisor / Officer", "Transportation & Logistics", "Inventory / Warehousing", "Supply Chain"], "post_time": "2022-01-14T09:38:39Z", "salary": {"currency": null, "max": null, "min": null, "period": "monthly", "term": null}, "salary_visible": false, "title_keywords": ["logistics", "customer service officer"], "responsibilities": ["identify business opportunities", "data", "daily orders", "maintain", "reports", "plans"], "requirements": {"degrees": ["fresh graduate", "degree holder"], "majors": ["related disciplines"], "languages": ["english", "chinese"], "language_level": ["proficiency"], "hard_skills": [], "soft_skills": ["communication skills", "mature", "detail-oriented", "extensive", "initiative", "positive"], "languages_combined": [{"language": "english", "language_level": ["proficiency"]}, {"language": "chinese", "language_level": ["proficiency"]}]}, "experience_required": {"duration": ["minimum 2 years"], "field": ["related", "warehouse management", "logistics"]}}, {"job_id": "100003009048102", "location_code": "hk", "company": "Chinachem Group", "job_title": "Customer Service Ambassador (Food & Beverage Operations)", "description": "\n\u8077\u8cac :\u4e00\u822c\u7269\u696d\u7ba1\u7406\u54e1/\u4fdd\u5b89\u54e1\u5de5\u4f5c\n\n\u8cc7\u6b77 :\u5c0f\u516d\u7a0b\u5ea6; 2\u5e74\u7d93\u9a57; \u826f\u597d\u7cb5\u8a9e; \u4e00\u822c\u666e\u901a\u8a71; \u4e00\u822c\u82f1\u8a9e; \u61c2\u8b80\u5beb\u4e2d\u6587; \u6301\u6709\u4fdd\u5b89\u57f9\u8a13\u8ab2\u7a0b\u8b49\u66f8(QAS); \u6301\u6709\u4fdd\u5b89\u4eba\u54e1\u8a31\u53ef\u8b49\n\n\u5f85\u9047 :\u6bcf\u6708$14,000, \u6709\u8d85\u6642\u5de5\u4f5c\u6d25\u8cbc \u53ca\u91ab\u7642\u798f\u5229, \u4e0a\u53487\u6642\u81f3\u4e0b\u53487\u6642, \u6bcf\u9031\u5de5\u4f5c6\u5929,\u8f2a\u4f11, \u6bcf\u5929\u5de5\u4f5c 12 \u5c0f\u6642\n\n\u7533\u8acb\u9808\u77e5 :\u6c42\u8077\u8005\u53ef\u81f4\u96fb28152323\u8207\u767e\u5229\u597d\u5730\u7522\u7ba1\u696d\u6709\u9650\u516c\u53f8\u5f35\u5c0f\u59d0\u806f\u7d61\u3002\n\n", "employment_types": ["Full Time", "Contract"], "selling_points": ["Assist the operation of the food hall", "Knowledge in using online shopping mobile apps", "1-2 year experience in customer service / F&B"], "locations": ["Not Specified"], "categories": ["Sales, CS & Business Devpt", "Customer Service - Supervisor / Officer", "Hospitality / F & B", "Food & Beverage", "Others"], "post_time": "2022-01-14T06:29:29Z", "salary": {"currency": null, "max": null, "min": null, "period": "monthly", "term": null}, "salary_visible": false, "title_keywords": ["customer service ambassador", "operations"], "responsibilities": [], "requirements": {"degrees": [], "majors": [], "languages": [], "language_level": [], "hard_skills": [], "soft_skills": [], "languages_combined": []}, "experience_required": {"duration": [], "field": []}}, {"job_id": "100003009053488", "location_code": "hk", "company": "Plotio Property And Management Co Ltd", "job_title": "\u65e5\u73ed\u7269\u696d\u7ba1\u7406\u54e1(\u85cd\u7530)**", "description": "We are located in Kwun Tong and are currently looking for a Customer Service Representative to join our growing team. The incumbent will focus on the following main areas:\ndeal directly with customers either by telephone, electronically or face to face\nrespond promptly to customer inquiries\nhandle and resolve customer complaints\nperform administrative functions and invoicing\ncommunicate and coordinate with internal departments\nmay involve some tele-sales\nhandle Ac hoc works\nThe company provides excellent career development opportunities & the following benefits:\nCandidate with proven abilities will have the opportunity to take on bigger roles & build a bigger team.\nMedical & dental benefits\nWe are looking for a Customer Service Representative with the following attributes:\nA minimum of 1-2 year customer service experience and admin fields.\nIndependent and demonstrates initiative, good communication, and problem solving skills\nStrong ability to multi-task and also strong desire to provide high quality customer service\nGood command of English and Chinese\nProficient in MS office and good computer skills\nImmediate availability is preferred\nFor those interested in applying for this position, please e-mail your resume by clicking \"Apply Now\".\n", "employment_types": ["Full Time"], "selling_points": [], "locations": ["Kwun Tong Area"], "categories": ["Sales, CS & Business Devpt", "Customer Service - Supervisor / Officer", "Others", "Security / Safety Control"], "post_time": "2022-01-17T07:03:01Z", "salary": {"currency": null, "max": null, "min": null, "period": "monthly", "term": null}, "salary_visible": false, "title_keywords": [], "responsibilities": ["resolve customer complaints", "customer inquiries", "coordinate with", "invoicing", "customer service"], "requirements": {"degrees": [], "majors": [], "languages": [], "language_level": [], "hard_skills": ["focus"], "soft_skills": ["focus", "customer service"], "languages_combined": []}, "experience_required": {"duration": [], "field": []}}, {"job_id": "100003009047508", "location_code": "hk", "company": "Henry Schein Hong Kong Limited", "job_title": "Customer Service Representative", "description": "Supervisory Responsibilities\n\nPerform service quality audit for improving service provisions as well as implementing service related projects with internal and external parties\nCoordinate and collaborate with internal and external team to ensure delivery of best-in-class customer experience. Lead and manage functions of customer service hotline and logistic operation, etc\nIdentify training needs, design training modules, and conduct regular training in respect of operations and service standard\nDesign and manage different workflow to ensure smooth business operation. Manage different touch points to ensure a consistent brand exposure and service experience\n\nCustomer Services Responsibilities\n\nServe as a dedicated customer contact point\nDefine customer policy and procedure according to different market environment, continue enhancement based on customer and operation feedback\nRegularly review with customers and cooperate with the operation team to achieve the KPI agreed with the customers\nAchieve customer satisfaction and build relationships with customers; handle customer\u2019s enquiries, claims and complaints\nDefine, measure and ensure customer satisfaction across different stages\n\n\u00a0Strategical Responsibilities\n\nDevelop strategy with insights to uplift Century\u2019s service excellence in the industry\nMaximize operation efficiency through process automation and digital services support\nProvide different management reports to reflect operation preparation progress and performance\nQualification\n\n\nDegree holder with 3-5 years or above relevant experience in logistics industry, including relevant experience in leading and managing a customer service team in a sizable company\n\nGood command of written and spoken English and Chinese with fluency in Mandarin and Cantonese are essential\nExcellent leadership, interpersonal and communication skills with all levels, mature, strong enthusiasm with solution-oriented mindset are required\nKnowledge of the import and export customs declaration\nExpert in customer operations and workflow management. Understand functionality and KPI of different departments. Proven experience in setting up new workflow and process which lead to a smooth operation of new business. Able to prepare different customer policy with paying attention to details\nProficient in MS Office (e.g. Excel, PowerPoint etc.) and English / Chinese word processing\nPositive, confident, a good communicator and observer. Equipped with Global vision and respects to different culture\nPassion to make a difference, self-motivated, result-oriented with good customer services senses, analytical skills\n\nThe above is a description of the current essential functions and duties of your position as Customer Operations Analyst. At the Company\u2019s discretion, these essential functions, duties and responsibilities may be modified in the future to meet the business needs of the Company.\n\nSuccessful candidates must be passionate, self-driven and motivated to seek improvement.\n\nCentury is a financially strong company with the backing of a major global shipping company, offering a competitive compensation package and dynamic work environment to the right candidate.\n\nSend us your resume including your current and expected salary by clicking \"Apply Now\"\u00a0. Resumes without salary expectations will not be considered.\n\nAll personal data collected will be used for recruitment purposes only.\n\nhttp://www.cds-net.com", "employment_types": ["Full Time", "Permanent"], "selling_points": ["deal directly with customers either by telephone", "Medical & dental benefits", "A minimum of 1-2 year customer service experience"], "locations": ["Kwun Tong"], "categories": ["Sales, CS & Business Devpt", "Customer Service - Supervisor / Officer", "Tele-sales (Telemarketing)", "Sales Administration"], "post_time": "2022-01-14T04:27:04Z", "salary": {"currency": null, "max": null, "min": null, "period": "monthly", "term": null}, "salary_visible": false, "title_keywords": ["customer service representative"], "responsibilities": ["collaborate with", "shipping", "service standard", "operations", "internal and external parties", "quality", "audit", "design", "communication", "customer service", "personal data", "cooperate with", "customer services", "develop", "logistics", "management", "review", "contact", "business operation", "customs declaration", "coordinate", "management reports", "recruitment"], "requirements": {"degrees": ["degree holder"], "majors": [], "languages": ["cantonese", "english", "chinese", "mandarin"], "language_level": ["fluency", "good command"], "hard_skills": ["excel", "chinese word processing", "powerpoint", "import and export", "analytical skills", "make", "management reports", "dynamic", "ms office"], "soft_skills": ["confident", "communication skills", "self-motivated", "result-oriented", "passionate", "driven", "mature", "analytical skills", "customer service", "motivated", "dynamic", "attention to details", "smooth", "communicator", "leadership", "interpersonal", "positive"], "languages_combined": [{"language": "cantonese", "language_level": ["good command"]}, {"language": "english", "language_level": ["fluency", "good command"]}, {"language": "chinese", "language_level": ["fluency", "good command"]}, {"language": "mandarin", "language_level": ["good command"]}]}, "experience_required": {"duration": ["3-5 years"], "field": ["brand", "logistics industry", "customer service", "relevant experience", "operation", "business", "team"]}}, {"job_id": "100003009047202", "location_code": "hk", "company": "Century Distribution Systems (Hong Kong) Limited", "job_title": "Customer Operations Analyst", "description": "The successful candidate will assist the Accounts Department - Income Control Team in answering the telephone enquiries from tenants in respect of billing amounts, maintaining the data in respect of tenants\u2019 ledgers and providing supports to all matters related to Income Control.\nRequirements:\nDiploma in Accounting or LCCI third level or equivalent with 2 years of relevant experience\nRelevant experience in dealing with customers\nGood interpersonal skills, telephone skills and manner\nAble to work independently and efficiently in multi-tasking\nKnowledge of Microsoft applications including Excel, Word and Chinese Word processing\nGood command of written and spoken English, Cantonese and Mandarin\nImmediate availability is highly preferred\nWe offer attractive remuneration packages commensurate with experience and qualifications. If you aspire to an exciting and rewarding career, send your resume immediately, quoting your present and expected salaries by clicking the button\u00a0\u201cApply Now\u201d.\nIf the applicant does not receive a response by\u00a013 February 2022, the application will be considered unsuccessful.\u00a0 Please read our Personal Information Collection Statement at\u00a0https://www.sino.com/en-US/Careers/Personal-Information-Collection-Statement\u00a0before submitting your application. Information provided by applicants will be treated in strict confidence and used for recruitment purposes only.", "employment_types": ["Full Time", "Permanent"], "selling_points": ["Customer Operations and Services", "Serve Internal and External Customers", "Develop Strategy & maximize operation efficiency"], "locations": ["Kwun Tong"], "categories": ["Sales, CS & Business Devpt", "Customer Service - Supervisor / Officer", "Transportation & Logistics", "Shipping", "Account Servicing"], "post_time": "2022-01-14T02:34:37Z", "salary": {"currency": null, "max": null, "min": null, "period": "monthly", "term": null}, "salary_visible": false, "title_keywords": ["operations analyst"], "responsibilities": ["control", "maintaining", "data"], "requirements": {"degrees": ["diploma"], "majors": ["accounting"], "languages": ["cantonese", "english", "chinese", "mandarin"], "language_level": ["good command"], "hard_skills": ["excel", "chinese word processing", "word", "microsoft applications"], "soft_skills": ["work independently", "interpersonal skills", "multi-tasking"], "languages_combined": [{"language": "cantonese", "language_level": ["good command"]}, {"language": "english", "language_level": ["good command"]}, {"language": "chinese", "language_level": []}, {"language": "mandarin", "language_level": ["good command"]}]}, "experience_required": {"duration": ["2 years"], "field": ["accounting", "relevant experience"]}}, {"job_id": "100003009050072", "location_code": "hk", "company": "Sino Group", "job_title": "Customer Services Officer (Ref: AO/JDB)", "description": "\u7db2\u4e0a\u516c\u53f8\u8aa0\u8058:\u00a0\n\nAdministrative & Marketing Clerk\u884c\u653f\u6587\u54e1(full-time)\n\n\u00a0\u8077\u8cac\uff1a\n\n\u4e00\u822c\u6587\u66f8\u5de5\u4f5c\n\u5354\u52a9\u65e5\u5e38\u904b\u4f5c\uff0c\u63d0\u4f9b\u826f\u597d\u5ba2\u6236\u670d\u52d9\n\u8010\u5fc3\u89e3\u7b54\u67e5\u8a62\n\u5354\u52a9\u5e02\u5834\u71df\u92b7 / \u7db2\u4e0a\u71df\u92b7\n\u00a0\u8077\u4f4d\u8981\u6c42:\n\n\u5927\u5c08\u7a0b\u5ea6\n\u6709\u5ba2\u670d\u7d93\u9a57\u512a\u5148\n\u5e02\u5834\u71df\u92b7\u6216\u7db2\u4e0a\u5ba3\u50b3\u7d93\u9a57\u512a\u5148\n\u719f\u6089\u4e2d\u3001\u82f1\u6587\u96fb\u8166\u64cd\u4f5c (Word, Excel\u53ca\u4e2d\u82f1\u6587\u6253\u5b57)\n\u826f\u597d\u4e2d\u82f1\u6587\u5beb\u4f5c\n2\u5e74\u4ee5\u4e0a\u5de5\u4f5c\u7d93\u9a57\u512a\u5148\n\u57fa\u7763\u5f92\u512a\u5148(\u8acb\u8a3b\u660e)\n\n\u5168\u8077\u5de5\u4f5c\u5730\u5340: \u65b0\u84b2\u5d17\n\n\u6b61\u8fce\u6709\u610f\u61c9\u5fb5\u8005\u4e0a\u8f09CV(\u8a3b\u660e\u671f\u671b\u85aa\u916c)\n\n\n\u6240\u6536\u96c6\u7684\u500b\u4eba\u8cc7\u6599\u7d55\u5c0d\u4fdd\u5bc6\u53ca\u53ea\u4f5c\u62db\u8058\u7528\u9014", "employment_types": ["Full Time"], "selling_points": [], "locations": ["Not Specified"], "categories": ["Sales, CS & Business Devpt", "Customer Service - Manager", "Customer Service - Supervisor / Officer", "Others"], "post_time": "2022-01-14T09:44:49Z", "salary": {"currency": null, "max": null, "min": null, "period": null, "term": null}, "salary_visible": false, "title_keywords": ["customer services officer"], "responsibilities": [], "requirements": {"degrees": [], "majors": [], "languages": [], "language_level": [], "hard_skills": ["word"], "soft_skills": [], "languages_combined": []}, "experience_required": {"duration": [], "field": []}}, {"job_id": "100003009052170", "location_code": "hk", "company": "Faith Christian Limited", "job_title": "Administrative & Marketing Clerk\u884c\u653f\u6587\u54e1(Full-time)", "description": "RecruitFirst is part of HRnetGroup - A Singapore listed company with offices in 13 Asian cities.\n\nAs the Group HRBP, you will:\n\n\nHandle end-to-end local or regional recruitment by matching talents to our recruitment brands\nPerform full spectrum of internal recruitment process includes sourcing of candidates, interview assessments and on-boarding process\nDrive internship programs and campus recruitment to achieve the hiring goals of the Group\nConduct orientation and training on a regular basis and to support annual performance evaluation\nEnhance employer branding through participation in marketing activities such as CSR events, career fairs etc\nAssist in HR administration and support in various HR projects and functions\n\nRequirements:\n\nBachelor\u2019s degree with minimum 3 years of experience, previous experience in recruitment agency or human resources is preferred\nIndependent, proactive, good communication and possess strong problem-solving skills\nPassionate, organized with a positive attitude and is able to work under pressure\nGood communication skills and fluent in English & Chinese\nCandidate with less experience maybe considered as HR Executive", "employment_types": ["Full Time"], "selling_points": ["San Po Kong", "admin, customer service, digital marketing", "5 days work"], "locations": ["Kowloon City Area"], "categories": ["Admin & HR", "Clerical / Admin Staff", "Sales, CS & Business Devpt", "Customer Service - Supervisor / Officer", "Marketing / Public Relations", "Digital Marketing"], "post_time": "2022-01-17T02:19:52Z", "salary": {"currency": null, "max": null, "min": null, "period": "monthly", "term": null}, "salary_visible": false, "title_keywords": [], "responsibilities": ["work under pressure", "hr", "communication", "recruitment", "evaluation", "recruitment process", "administration"], "requirements": {"degrees": ["degree", "bachelor"], "majors": [], "languages": ["english", "chinese"], "language_level": ["fluent", "good"], "hard_skills": ["problem-solving skills"], "soft_skills": ["passionate", "organized", "communication skills", "independent", "communication", "positive attitude", "problem-solving skills", "proactive", "work under pressure"], "languages_combined": [{"language": "english", "language_level": ["fluent", "good"]}, {"language": "chinese", "language_level": ["fluent", "good"]}]}, "experience_required": {"duration": ["minimum 3 years"], "field": ["agency", "hr", "recruitment", "human resources"]}}, {"job_id": "100003009054569", "location_code": "hk", "company": "RecruitFirst Limited", "job_title": "HR Business Partner / HR Executive", "description": "\u5ba2\u6236\u670d\u52d9\u4e3b\u4efb (Customer Service Officer)\n\n\u8077\u8cac:\n\n\u63a8\u5ee3\u53ca\u92b7\u552e\u516c\u53f8\u7522\u54c1 (\u4fdd\u5065\u7522\u54c1)\n\u8ddf\u9032\u5ba2\u6236\u53ca\u89e3\u6c7a\u4ed6\u5011\u7684\u8a62\u554f\n\u8655\u7406\u71b1\u7dda\u4f86\u96fb\u67e5\u8a62\u53ca\u81f4\u96fb\u5ba2\u4eba\u00a0\u00a0(\u7121\u9700COLD CALL)\n\u8cc7\u6599\u8f38\u5165\u53ca\u5b58\u6a94\n\n\u5165\u8077\u8981\u6c42:\n\n\u53ef\u5373\u6642\u4e0a\u73ed\u8005\u53ef\u5148\u8003\u616e\n\u7d93\u9a57\u4e0d\u62d8\uff0c\u6b61\u8fce\u61c9\u5c46\u7562\u696d\u751f\n\u5177\u826f\u597d\u6e9d\u901a\u80fd\u529b\u3001\u5ba2\u6236\u670d\u52d9\u6280\u5de7\uff0c\u7a4d\u6975\u4e3b\u52d5\uff0c\u80fd\u7368\u7acb\u5de5\u4f5c\u53ca\u89e3\u6c7a\u554f\u984c\n\u5177\u6709\u57fa\u672c\u96fb\u8166\u64cd\u4f5c\u77e5\u8b58(MS Word, Excel)\u53ca\u61c2\u4e2d\u6587\u6253\u5b57\n\n\u5f85\u9047:\n\n\u4e0a\u73ed\u6642\u9593: \u4e0a\u53489\u6642\u534a\u81f3\u4e0b\u53486\u6642\uff0c\u6bcf\u9031\u5de5\u4f5c5\u5929\u81f36\u5929\uff0c\u6bcf\u5929\u5de5\u4f5c7.5\u5c0f\u6642 \uff0c\u661f\u671f\u65e5\u53ca\u516c\u773e\u5047\u671f\u4f11\u606f\n\u5e95\u85aa + \u4f63\u91d1 + \u65b0\u4eba\u6d25\u8cbc\n\n\u54e1\u5de5\u798f\u5229:\n\n\u96d9\u7ce7\u3001\u8a2d\u6709\u52e4\u5de5\u734e\u53ca\u52a0\u73ed\u6d25\u8cbc\n\u9280\u884c\u5047\u671f\u3001\u6709\u85aa\u5e74\u5047\u3001\u751f\u65e5\u5047\u671f\n\u4e2d/\u897f\u91ab\u7642\u6d25\u8cbc\u3001\u4eba\u58fd\u53ca\u610f\u5916\u4fdd\u96aa \u3001\u7259\u79d1\u798f\u5229 \u3001\u6bcf\u5e74\u8eab\u9ad4\u6aa2\u67e5\n\u54e1\u5de5\u8cfc\u7269\u512a\u60e0\u3001\u514d\u8cbb\u7522\u54c1\u6d25\u8cbc (\u6bcf\u5e74$20,000)\n\n\u5de5\u4f5c\u5730\u9ede\u00a0:\u00a0\u9285\u947c\u7063\n\n\u6709\u610f\u61c9\u5fb5\u8005,\u00a0\u8acb\u5c07\u500b\u4eba\u5c65\u6b77\u53ca\u8981\u6c42\u5f85\u9047 \u6309APPLY NOW\n\n\u5982\u6709\u67e5\u8a62\u53ef\u81f4\u96fb3974 9290\u00a0(\u8449\u5c0f\u59d0)\n\n\u7533\u8acb\u8005\u6240\u63d0\u4f9b\u7684\u8cc7\u6599\u5c07\u7d55\u5c0d\u4fdd\u5bc6\u53ca\u53ea\u4f9b\u62db\u8058\u4e4b\u7528", "employment_types": ["Full Time", "Permanent"], "selling_points": [], "locations": ["Wan Chai"], "categories": ["Sales, CS & Business Devpt", "Customer Service - Supervisor / Officer", "Admin & HR", "HR Supporting Staff", "Recruitment / Executive Search"], "post_time": "2022-01-17T10:06:54Z", "salary": {"currency": null, "max": null, "min": null, "period": "monthly", "term": null}, "salary_visible": false, "title_keywords": ["hr", "executive"], "responsibilities": ["customer service"], "requirements": {"degrees": [], "majors": [], "languages": [], "language_level": [], "hard_skills": ["word"], "soft_skills": ["customer service"], "languages_combined": []}, "experience_required": {"duration": [], "field": []}}, {"job_id": "100003009048780", "location_code": "hk", "company": "Zhongke Health International (H.K.) Co., Limited", "job_title": "\u5ba2\u6236\u670d\u52d9\u4e3b\u4efb (Customer Service Officer)", "description": "Job Responsibilities:\n\nTo handle enquiries from members of loyalty program at members' lounge and concierge\nTo handle membership acquisition and redemption of membership benefits and gifts\nTo maintain excellent relationship with members by providing quality service\nTo perform any other duties as assigned in a diligent and conscientious manner\nTo assist in organizing VIC events\n\n\u00a0Requirements:\n\nPassionate in retail and hospitality work\nPleasant, proactive and customer-oriented with good manners\nDiploma holder or above preferably in Hospitality/ Tourism/ Business related disciplines\n2 - 3 years of experience in membership management, hospitality or sales industry\nGood command of Cantonese, English, Putonghua\n\nSuccessful candidates will be provided with a tailor-made induction course to get familiar with our shopping mall and to acquire necessary customer service skills.\u00a0 On-going classroom and on-the-job trainings will be provided where appropriate for a successful long-term career development within the Company.\n\nWe offer competitive salary package that commensurate with experience and qualifications. Interested parties please send full resume stating contact telephone number, date available, present and expected salary, Chinese & English exam results in HKCEE / DSE / HKAL to our recruitment email address.\n\n(Personal data provided will be used strictly in accordance with the Company's personal data policy which is available upon request)", "employment_types": ["Full Time", "Permanent"], "selling_points": [], "locations": ["Causeway Bay"], "categories": ["Sales, CS & Business Devpt", "Call Centre", "Customer Service - Supervisor / Officer", "Others"], "post_time": "2022-01-14T07:16:57Z", "salary": {"currency": null, "max": null, "min": null, "period": "monthly", "term": null}, "salary_visible": false, "title_keywords": ["\u5ba2\u6236\u670d\u52d9\u4e3b\u4efb", "customer service officer"], "responsibilities": ["handle enquiries"], "requirements": {"degrees": [], "majors": [], "languages": [], "language_level": [], "hard_skills": [], "soft_skills": [], "languages_combined": []}, "experience_required": {"duration": [], "field": []}}, {"job_id": "100003009053216", "location_code": "hk", "company": "Sun Life Hong Kong Ltd", "job_title": "Assistant Administration Officer (Cashier - Insurance Service Centre)", "description": "Job Duties\n\nFollow-up shipment orders, track & trace, coordinate with offices and agents, as well as maintaining rate system & data quality\nWork closely with Operations Teams and Sales & Marketing Team for promoting company product and services\nPreparing reports and presentations\n\nRequirements\n\nF.5 or DSE graduates, candidate with higher academic qualification or experience in freight forwarding industry would be considered as Customer Services Officer\nProficient in spoken and written English and Chinese (Cantonese and Mandarin)\nPC literate in Microsoft Office (Word, Excel), advance in Excel is preferable\nAttention to details and capability of handling multi-tasks are required\nGood team player\nProactive, independent, responsible, well organized, able to work under pressure\nExperience in handling key account is an advantage\n\nJob Location: Chek Lap Kok\n\nWe offer attractive fringe benefits such as 40 hour work per week, medical insurance, double pay and on-job training to successful candidates. Interested party may send full resume with expected salary by clicking \"Apply Now\" for consideration.\n\n\n\nPersonal data collected will be used for recruitment purpose only.", "employment_types": ["Full Time", "Permanent"], "selling_points": ["Cashier / Payment / Service Centre / Mandarin", "Customer Service / Centre operation / Counter", "3 years working experience"], "locations": ["Hung Hom"], "categories": ["Sales, CS & Business Devpt", "Customer Service - Supervisor / Officer", "Insurance", "Others", "Others"], "post_time": "2022-01-17T06:27:35Z", "salary": {"currency": null, "max": null, "min": null, "period": "monthly", "term": null}, "salary_visible": false, "title_keywords": ["assistant administration officer"], "responsibilities": ["maintaining", "data", "operations", "quality", "coordinate with", "teams", "presentations", "preparing reports"], "requirements": {"degrees": ["dse"], "majors": [], "languages": ["cantonese", "english", "chinese", "mandarin"], "language_level": ["proficient"], "hard_skills": ["excel", "pc literate", "word", "microsoft office"], "soft_skills": ["good team player", "independent", "multi-tasks", "responsible", "well organized", "attention to details", "proactive", "work under pressure"], "languages_combined": [{"language": "cantonese", "language_level": ["proficient"]}, {"language": "english", "language_level": ["proficient"]}, {"language": "chinese", "language_level": ["proficient"]}, {"language": "mandarin", "language_level": ["proficient"]}]}, "experience_required": {"duration": [], "field": ["customer services"]}}, {"job_id": "100003009045772", "location_code": "hk", "company": "Air Sea Worldwide Logistics Ltd", "job_title": "Customer Services Clerk (5-days work week)", "description": "\n\u8077\u8cac :\u4e00\u822c\u7269\u696d\u7ba1\u7406\u54e1/\u4fdd\u5b89\u54e1\u5de5\u4f5c\n\n\u8cc7\u6b77 :\u5c0f\u516d\u7a0b\u5ea6; 2\u5e74\u7d93\u9a57; \u826f\u597d\u7cb5\u8a9e; \u61c2\u8b80\u5beb\u4e2d\u6587; \u6301\u6709\u4fdd\u5b89\u57f9\u8a13\u8ab2\u7a0b\u8b49\u66f8(QAS); \u6301\u6709\u4fdd\u5b89\u4eba\u54e1\u8a31\u53ef\u8b49\n\n\u5f85\u9047 :\u6bcf\u6708$14,000, \u6709\u8d85\u6642\u5de5\u4f5c\u6d25\u8cbc, \u91ab\u7642\u798f\u5229 \u53ca\u5176\u4ed6\u6d25\u8cbc/\u798f\u5229, \u4e0b\u53487\u6642\u81f3\u4e0a\u53487\u6642, \u6bcf\u9031\u5de5\u4f5c6\u5929,\u8f2a\u4f11, \u6bcf\u5929\u5de5\u4f5c 12 \u5c0f\u6642\n\n\u7533\u8acb\u9808\u77e5 :\u6c42\u8077\u8005\u53ef\u81f4\u96fb28152323\u8207\u767e\u5229\u597d\u5730\u7522\u7ba1\u696d\u6709\u9650\u516c\u53f8\u5f35\u5c0f\u59d0\u806f\u7d61\u3002\n\n", "employment_types": ["Full Time", "Permanent"], "selling_points": ["Good development prospects", "Provide professional and efficient service", "immediate available"], "locations": ["Airport Area"], "categories": ["Sales, CS & Business Devpt", "Customer Service - Supervisor / Officer", "Transportation & Logistics", "Freight Forwarding"], "post_time": "2022-01-13T08:39:30Z", "salary": {"currency": null, "max": null, "min": null, "period": "monthly", "term": null}, "salary_visible": false, "title_keywords": ["customer services clerk"], "responsibilities": [], "requirements": {"degrees": [], "majors": [], "languages": [], "language_level": [], "hard_skills": [], "soft_skills": [], "languages_combined": []}, "experience_required": {"duration": [], "field": []}}, {"job_id": "100003009054366", "location_code": "hk", "company": "DataLouder Company Limited", "job_title": "Sales and Marketing Consultant", "description": "Well established Trading co.\nGood Work Life Balance\nFriendly and stable Staff and Co.\n\nResponsibilities\n\nHandle incoming and dispatches orders\nPrepare delivery documents\nUpdate record in the system\n\nRequirement\n\n3 years or above of relevant experience\nCantonese, English and Mandarin\nStrong sense of responsibility and good communication skills\n\nPackage\n\nPermanent role\n5-day work\nDouble Pay plus Bonus\nDental plus Medical Allowance\n\nFeel free to explore with Ms. So at 35529113 or 98651077", "employment_types": ["Full Time", "Part Time"], "selling_points": ["Fintech and social media startup", "Basic salary with commission", "1-2 years of work experience in sales"], "locations": ["Admiralty"], "categories": ["Sales, CS & Business Devpt", "Customer Service - Supervisor / Officer", "Account Servicing", "Sales Administration"], "post_time": "2022-01-17T09:27:46Z", "salary": {"currency": null, "max": null, "min": null, "period": "monthly", "term": null}, "salary_visible": false, "title_keywords": ["consultant", "sales"], "responsibilities": [], "requirements": {"degrees": [], "majors": [], "languages": ["cantonese", "english", "mandarin"], "language_level": [], "hard_skills": ["plus"], "soft_skills": ["communication skills", "sense of responsibility"], "languages_combined": [{"language": "cantonese", "language_level": []}, {"language": "english", "language_level": []}, {"language": "mandarin", "language_level": []}]}, "experience_required": {"duration": ["3 years"], "field": ["relevant experience"]}}, {"job_id": "100003009053496", "location_code": "hk", "company": "Plotio Property And Management Co Ltd", "job_title": "\u591c\u73ed\u7269\u696d\u7ba1\u7406\u54e1(\u85cd\u7530)**", "description": "Build yourself an exciting future at the\n\nLEGOLAND Discovery Centre Hong Kong Here!\n\nBe a part of the Merlin magic by joining us as our\u00a0Host (Part Time)\u00a0based in our brand-new\u00a0LEGOLAND Discovery Centre in Hong Kong!\u00a0We hire and empower smart people who love what they do.\u00a0 Now\u2019s your chance to join us!\n\nWe are currently hiring for 3 frontline teams: Guest Experience, Admissions & Food & Beverage.\n\nLEGOLAND Discovery Centre is just like jumping into a giant box of LEGO\u00ae bricks with an abundance of all things LEGO-tastic! With two exciting LEGO rides, MINILAND featuring the iconic landmarks of Hong Kong, a 4D cinema, themed LEGO play and building zones, there are simply more LEGO bricks under one roof than you could ever imagine.\n\n\n\nScope of Job:\n\nTo provide high quality, courteous, efficient and helpful service to our guests at all times. To ensure Health & Safety is our number one priority whilst ensuring that our guests have the most memorable experience in our attractions. Responsible to ensure that maximum sales are generated, cash is accurately managed and cleanliness and merchandising are maximised.\n\nKey Objectives:\n\nTo provide high levels of customer service to all guests in line with Merlin Standards.\nTo have up to date product knowledge of the attraction to assist guests.\nTo actively promote the attraction and deliver interaction with guests in line with Brand guidelines.\n\nMain Responsibilities:\n\nPromoting Merlin Entertainments policy of quality customer care by ensuring a courteous, efficient, helpful and entertaining service to the public.\nEnsure all public areas have well stocked displays and point of sale, ready for the Attraction opening and that they are maintained and kept in a clean and tidy manner throughout the day.\nEnsure all transactions are processed accurately considering rates, promotions, vouchers, discounts, etc.\nTo ensure that all voucher redemptions are recorded and reconciled on a daily basis.\nEnsure the highest standards of accurate and efficient cash handling procedures, check floats, monitoring staff and customers during transactions.\nTo assist in monitoring and support management of queue lines when required.\nTo ensure the mystery visit criteria is adhered to at all times.\nTo follow opening and closing procedures as detailed in the department\u2019s operating plan.\nTo greet all visitors with eye contact, a smile and a verbal greeting on every transaction.\u00a0\nTo issue a receipt and a passing pleasantry on every transaction.\nTo contribute your ideas to improve the guest experience and continually strive to improve the department.\n\nAbout you:\n\nYou preferably have some previous experience in a guest service role.\nYou are passionate about delivering great guest service.\nYou are flexible and work well under pressure.\nYou have excellent communication skills.\nYou love working as part of a team.\n\nFinally the successful candidate must have the confidence to demonstrate the passion in the product, the people, and fully embody the \u201cLearning FUN\u201d of working at LEGOLAND Discovery Centre!\n\nOur hourly rate for Part Time Host role is HK$55 per hour.\n\nKindly note, only shortlisted candidates will be notified.", "employment_types": ["Full Time"], "selling_points": [], "locations": ["Kwun Tong Area"], "categories": ["Sales, CS & Business Devpt", "Customer Service - Supervisor / Officer", "Others", "Security / Safety Control"], "post_time": "2022-01-17T07:03:36Z", "salary": {"currency": null, "max": null, "min": null, "period": "monthly", "term": null}, "salary_visible": false, "title_keywords": [], "responsibilities": ["management", "ideas", "monitoring", "quality", "teams", "merchandising", "transactions", "procedures", "communication", "customer service", "brand guidelines", "contact", "plan"], "requirements": {"degrees": [], "majors": [], "languages": [], "language_level": [], "hard_skills": ["clean", "fun"], "soft_skills": ["efficient", "flexible", "courteous", "communication skills", "under pressure", "confidence", "responsible", "passion in", "customer service", "learning", "accurate", "passionate about", "detailed"], "languages_combined": []}, "experience_required": {"duration": [], "field": ["food"]}}, {"job_id": "100003009055051", "location_code": "hk", "company": "Gemini Personnel Limited", "job_title": "Sales Assistant (TST, 13mth/Salary plus Bonus, 5-Day, Permanent Role) 17~22K/Month KIO-J078126", "description": "\n\u8077\u8cac :\u4e00\u822c\u7269\u6d41\u4e2d\u5fc3\u4fdd\u5b89\u5de5\u4f5c\uff0c\u8ca0\u8cac\u4e00\u822c\u591c\u73ed\u4fdd\u5b89\u5de1\u908f\uff0c\u4ea4\u901a\u7ba1\u7406\u7b49\u65e5\u5e38\u5de5\u4f5c\n\n\u8cc7\u6b77 :\u5c0f\u4e94\u7a0b\u5ea6; 2\u5e74\u7d93\u9a57; \u4e00\u822c\u7cb5\u8a9e; \u7565\u61c2\u8b80\u5beb\u4e2d\u6587; \u6301\u6709\u4fdd\u5b89\u57f9\u8a13\u8ab2\u7a0b\u8b49\u66f8(QAS); \u6301\u6709\u4fdd\u5b89\u4eba\u54e1\u8a31\u53ef\u8b49\n\n\u5f85\u9047 :\u6bcf\u6708$16,000 - $18,000, \u6709\u96d9\u7ce7, \u52e4\u5de5\u734e\u91d1, \u5e74\u504714\u5929, \u9280\u884c\u5047\u671f, \u914c\u60c5\u6027\u82b1\u7d05, \u7259\u79d1\u798f\u5229 \u53ca\u4f9b\u81b3\u98df, \u4e0b\u53488\u6642\u81f3\u4e0a\u53488\u6642, \u6bcf\u9031\u5de5\u4f5c6\u5929,\u8f2a\u4f11, \u6bcf\u5929\u5de5\u4f5c 12 \u5c0f\u6642\n\n\u7533\u8acb\u9808\u77e5 :\u6c42\u8077\u8005\u53ef\u81f4\u96fb21297319\u8207\u62db\u5546\u5c40\u8239\u52d9\u4f01\u696d\u6709\u9650\u516c\u53f8\u9673\u5973\u58eb\u806f\u7d61\u3002\n\n", "employment_types": ["Full Time", "Permanent"], "selling_points": ["Sales Administration Permanent Role", "Electronic Trading Co. in TST", "3 Years of above Experience, 17-22K"], "locations": ["Tsim Sha Tsui"], "categories": ["Sales, CS & Business Devpt", "Customer Service - Supervisor / Officer", "Sales Administration"], "post_time": "2022-01-18T00:53:32Z", "salary": {"currency": null, "max": null, "min": null, "period": "monthly", "term": null}, "salary_visible": false, "title_keywords": ["sales assistant"], "responsibilities": [], "requirements": {"degrees": [], "majors": [], "languages": [], "language_level": [], "hard_skills": [], "soft_skills": [], "languages_combined": []}, "experience_required": {"duration": [], "field": []}}, {"job_id": "100003009052925", "location_code": "hk", "company": "LEGOLAND Discovery Centre Hong Kong", "job_title": "Host \u2013 Part Time (Guest Experience/Admissions/F&B)", "description": "JOB PURPOSE\n\nThrough your passion for the Burberry brand and product and your specialist, expert, product knowledge you will provide a personalised sensational experience for our global customers.\u00a0\n\n\n\nRESPONSIBILITIES\n\nAs the Customer Service Consultant you are the human face of the digital Burberry customer experience, connecting across the business to fulfil every customer need. Delivering World Class, Luxury Customer Service:\n\nYou will take ownership of each customer journey, resolving cases through accurate, appropriate and personalised solutions that enhance brand loyalty.\nBy demonstrating passion for the brand and expert product knowledge you will encourage customers to personally experience the style, look and quality of Burberry products\n\nPERSONAL PROFILE\n\nExcellent verbal and written communication skills in\u00a0English & Cantonese (Native)\nDemonstrable experience in front line Customer Service role, ideally within Contact Centre environment, e-commerce or luxury retail sector\nProactive team player : positive attitude and able to work collaboratively\u00a0\n5 day work week - flexible and able to work on rotation including weekends\n\nBurberry is an Equal Opportunities Employer and as such, treats all applications equally and recruits purely on the basis of skills and experience.\n\n\n\nAt Burberry, we believe that creativity open spaces for ourselves, our customers and our communities.", "employment_types": ["Part Time"], "selling_points": ["Part Time (9 hours shift)", "LEGO-themed indoor attraction", "Guest Service Focused"], "locations": ["Tsim Sha Tsui"], "categories": ["Sales, CS & Business Devpt", "Customer Service - Supervisor / Officer", "Hospitality / F & B", "Food & Beverage", "Hospitality / Hotel Services"], "post_time": "2022-01-17T04:34:19Z", "salary": {"currency": null, "max": null, "min": null, "period": "hourly", "term": null}, "salary_visible": false, "title_keywords": ["host"], "responsibilities": ["communication", "customer service", "quality", "contact"], "requirements": {"degrees": [], "majors": [], "languages": ["cantonese", "english"], "language_level": ["native", "excellent"], "hard_skills": ["e-commerce"], "soft_skills": ["flexible", "communication skills", "accurate", "passion for", "positive attitude", "customer service", "team player", "proactive"], "languages_combined": [{"language": "cantonese", "language_level": ["excellent"]}, {"language": "english", "language_level": ["native", "excellent"]}]}, "experience_required": {"duration": [], "field": ["brand", "e-commerce", "luxury retail", "business", "customer service", "digital"]}}, {"job_id": "100003009055812", "location_code": "hk", "company": "China Merchants Shipping and Enterprises Co Ltd", "job_title": "\u7269\u6d41\u4e2d\u5fc3\u4fdd\u5b89\u54e1(\u591c\u73ed)", "description": "Job Responsibilities:\n\nAssist teammate to handle customer enquiries and complaints\nSupport daily operations and promotional activities\nProvide support on credit assessment to supervisors according to lending policies\nCoach and train junior staff\n\nJob Requirements:\n\nF.5 HKCEE / F.6 HKDSE or above\nStrong customer services orientation\nDynamic, strong analytical skill, good interpersonal and communication skills\nGood command of spoken and written Chinese and English\nOn-the-job training will be provided\nExperience in loan assessment and approval\n\nWe offer attractive remuneration package which includes double pay and discretionary bonus. Interested parties please send your CV indicating your current salary, expected salary and availability to HR Department, by email via clicking \"Apply Now\".\n\n(Personal data collected will be treated in the strictest confidence and will be handled by authorized personnel for recruitment-related purposes only. Applicants who do not hear from us within 3 months may consider their application unsuccessful and their data will be destroyed within 24 months of receipt.)", "employment_types": ["Full Time"], "selling_points": [], "locations": ["Tsing Yi"], "categories": ["Sales, CS & Business Devpt", "Customer Service - Supervisor / Officer", "Others", "Security / Safety Control"], "post_time": "2022-01-18T02:58:22Z", "salary": {"currency": null, "max": null, "min": null, "period": "monthly", "term": null}, "salary_visible": false, "title_keywords": [], "responsibilities": ["provide support", "policies", "daily operations", "promotional activities", "customer enquiries and complaints"], "requirements": {"degrees": ["hkdse"], "majors": [], "languages": ["english", "chinese"], "language_level": ["good command"], "hard_skills": ["analytical skill", "dynamic"], "soft_skills": ["communication skills", "analytical skill", "dynamic", "interpersonal"], "languages_combined": [{"language": "english", "language_level": ["good command"]}, {"language": "chinese", "language_level": ["good command"]}]}, "experience_required": {"duration": [], "field": []}}, {"job_id": "100003009055170", "location_code": "hk", "company": "Burberry Asia Limited", "job_title": "Customer Services Consultant - English/Cantonese Speaking", "description": "Job Descriptions:\n\nProvide full range of secretarial, administration and personal support for the sales team; updates RSMs by consolidating, analyzing, and forwarding daily action summaries\nPrepare Pre-Sales document, such as quotation; communicate with suppliers of costs,information sourcing and selection, prepare presentation format and materials\nPerform sales support, communicate with different departments, oversea branch offices\u00a0and global clients via email and phone\nConduct sales report, tender document, maintain customer database, etc\nHandle ad-hoc projects as assigned\n\nJob Requirements:\n\nDiploma or Degree holder preferred\n1-2 years experience in sales support or customer services; experience in global or regional business is an advantage\nFlexible, patient, independent, good team player and willing to work under pressure\nProficiency in MS Office\nGood command of Cantonese, English and Mandarin\nKnowledge in SAP is an advantage\n\nWe offer 5-day work week, adorable and friendly working environment, medical and other fringe benefits to the successful candidate. Please send in your application with detailed resume, availability, present and expected salary, and also quoting our reference number.\n\nTo know more about us, please visit http://www.vega-global.com/ or Corporate Video http://youtu.be/APdIdtkIHeE", "employment_types": ["Temporary", "Contract"], "selling_points": ["English/Cantonese Native level", "5 days work per week, rotation including weekends", "Delivering World Class, Luxury Customer Service"], "locations": ["Quarry Bay"], "categories": ["Sales, CS & Business Devpt", "Call Centre", "Customer Service - Supervisor / Officer", "Tele-sales (Telemarketing)"], "post_time": "2022-01-18T01:36:53Z", "salary": {"currency": null, "max": null, "min": null, "period": "monthly", "term": null}, "salary_visible": false, "title_keywords": ["consultant"], "responsibilities": ["communicate with", "sales report", "quotation", "maintain", "sales team", "database", "ad-hoc projects", "tender document", "costs", "administration"], "requirements": {"degrees": ["diploma", "degree holder"], "majors": [], "languages": ["cantonese", "english", "mandarin"], "language_level": ["good command"], "hard_skills": ["sales support", "sap", "ms office"], "soft_skills": ["flexible", "good team player", "independent", "patient", "work under pressure"], "languages_combined": [{"language": "cantonese", "language_level": ["good command"]}, {"language": "english", "language_level": ["good command"]}, {"language": "mandarin", "language_level": ["good command"]}]}, "experience_required": {"duration": ["1-2 years"], "field": ["business", "sales support", "customer services"]}}, {"job_id": "100003009038293", "location_code": "hk", "company": "Lumenis (HK) Limited", "job_title": "Customer Service Specialist", "description": "Responsibilities:\n\nProvide quality customer service in cashier and skating school counter\nResponsible for class scheduling, coach arrangement and other related issues\nHandle customer enquiries at the skating school counter or telephone\nAssist in organizing or operating all the events and programs in the rink\nPerform other duties as assigned\n\nRequirements:\n\nDiploma in sports and recreation management or relevant disciplines\n1-2 years relevant work experience\nGood command of spoken and written English, Cantonese and Mandarin\nWorking on weekends and festive seasons may be required when necessary\n\nWe offer an attractive remuneration package and excellent career opportunities to the right candidate. Interested applicants please send your CV by email via \"Apply Now\" or by WhatsApp at 63173527.\n\nPersonal data provided by job applicants will be used strictly for recruitment purposes only.", "employment_types": ["Full Time", "Permanent"], "selling_points": [], "locations": ["Tsim Sha Tsui"], "categories": ["Sales, CS & Business Devpt", "Call Centre", "Customer Service - Supervisor / Officer", "Others"], "post_time": "2022-01-11T06:29:03Z", "salary": {"currency": null, "max": null, "min": null, "period": "monthly", "term": null}, "salary_visible": false, "title_keywords": ["specialist", "customer service"], "responsibilities": ["perform other duties", "handle customer enquiries", "quality", "scheduling", "customer service"], "requirements": {"degrees": ["diploma"], "majors": [], "languages": ["cantonese", "english", "mandarin"], "language_level": ["good command"], "hard_skills": [], "soft_skills": [], "languages_combined": [{"language": "cantonese", "language_level": ["good command"]}, {"language": "english", "language_level": ["good command"]}, {"language": "mandarin", "language_level": ["good command"]}]}, "experience_required": {"duration": ["1-2 years"], "field": []}}, {"job_id": "100003009053756", "location_code": "hk", "company": "United Asia Finance Limited", "job_title": "Specialist, Phone Credit", "description": "Role & Responsibilities:\nAnalyze and assess customers for effective negotiation\nIdentify the customers\u2019 need and acquire customers and business by phone calls\nMaintain good support with customers and keep abreast of market & industry development\nAggressive, self-motivated, customer oriented\nAttend sales meeting with reporting and share in markets where that is desired\nRequirements\n1-2 years working experience\nCustomer oriented, proactive in client management and development\nProficient in Excel\nWilling to learn, try and challenge new things\nHardworking, Self-motivated and able to work independently\nLearning opportunities\nBusiness development and intelligence\nCommercial awareness\nNegotiation skills\n\n\nAny candidate who is interested in 1 position is requested to send email to Mr. Matchy Yuen\u00a0 (email by clicking \"Apply Now\"\u00a0for internal review)", "employment_types": ["Full Time", "Permanent"], "selling_points": ["Provide support on credit assessment", "Coach and train junior staff", "F.5 HKCEE / F.6 HKDSE or above"], "locations": ["Wan Chai"], "categories": ["Admin & HR", "Clerical / Admin Staff", "Banking / Finance", "Loan", "Sales, CS & Business Devpt", "Customer Service - Supervisor / Officer"], "post_time": "2022-01-17T07:32:24Z", "salary": {"currency": null, "max": null, "min": null, "period": "monthly", "term": null}, "salary_visible": false, "title_keywords": ["specialist"], "responsibilities": ["reporting", "maintain", "phone calls"], "requirements": {"degrees": [], "majors": [], "languages": [], "language_level": [], "hard_skills": ["excel"], "soft_skills": ["self-motivated", "work independently", "interested in", "willing to learn", "negotiation skills", "learning", "proactive", "hardworking"], "languages_combined": []}, "experience_required": {"duration": ["1-2 years"], "field": []}}, {"job_id": "100003009051913", "location_code": "hk", "company": "VEGA Technology Limited", "job_title": "Sales Assistant", "description": "\n\u8077\u8cac :\u9632\u6b62\u672a\u7d93\u8a31\u53ef\u4eba\u58eb\u9032\u5165\u5927\u5ec8\u3002\u5982\u5728\u5927\u5ec8\u5167\u767c\u73fe\u53ef\u7591\u4eba\u58eb\uff0c\u9700\u4e0a\u524d\u67e5\u554f\uff0c\u5982\u61f7\u7591\u4ed6\u5011\u9055\u6cd5\uff0c\u9700\u7acb\u523b\u901a\u77e5\u8b66\u65b9\u3002\u6b64\u5916\u4ea6\u9808\u78ba\u4fdd\u5176\u4ed6\u64c5\u95d6\u8005\u96e2\u958b\u5927\u5ec8\uff1b\u767b\u8a18\u6240\u6709\u8a2a\u5ba2\u3001 \u4fee\u7406\u5de5\u4eba\u6216\u9001\u8ca8\u5de5\u4eba\u51fa\u5165\u5927\u5ec8\u7684\u8a73\u7d30\u8cc7\u6599\u7b49\u7b49\n\n\u8cc7\u6b77 :\u5c0f\u516d\u7a0b\u5ea6; \u4e00\u822c\u7cb5\u8a9e; \u7565\u61c2\u8b80\u5beb\u4e2d\u6587; \u6301\u6709\u4fdd\u5b89\u57f9\u8a13\u8ab2\u7a0b\u8b49\u66f8(QAS); \u6301\u6709\u4fdd\u5b89\u4eba\u54e1\u8a31\u53ef\u8b49\n\n\u5f85\u9047 :\u6bcf\u65e5$525.00, \u4e0b\u53487\u6642\u81f3\u4e0a\u53487\u6642, \u6bcf\u9031\u5de5\u4f5c6\u5929,\u8f2a\u4f11, \u6bcf\u5929\u5de5\u4f5c 12 \u5c0f\u6642\n\n\u7533\u8acb\u9808\u77e5 :\u6c42\u8077\u8005\u53ef\u81f4\u96fb37489794\u8207\u5408\u5b89\u7ba1\u7406\u6709\u9650\u516c\u53f8\u8521\u5148\u751f\u806f\u7d61\u3002\n\n", "employment_types": ["Full Time", "Permanent"], "selling_points": ["5-day work", "on job training", "work life balance"], "locations": ["Kwai Fong"], "categories": ["Admin & HR", "Clerical / Admin Staff", "Sales, CS & Business Devpt", "Customer Service - Supervisor / Officer", "Sales Administration"], "post_time": "2022-01-17T01:30:33Z", "salary": {"currency": null, "max": null, "min": null, "period": "monthly", "term": null}, "salary_visible": false, "title_keywords": ["sales assistant"], "responsibilities": [], "requirements": {"degrees": [], "majors": [], "languages": [], "language_level": [], "hard_skills": [], "soft_skills": [], "languages_combined": []}, "experience_required": {"duration": [], "field": []}}]