[{"job_id": "100003009055497", "location_code": "hk", "company": "\u5eb7\u8cfd\u59ae\u96c6\u5718\u6709\u9650\u516c\u53f8", "job_title": "Sales Executive / Senior Sales Executive / Sales Manager", "description": "Requirements:\n\n-\u00a0\u00a0\u00a0\u00a0\u00a0\u00a0\u00a0\u00a0 Experience in textile, fabric, yarn, fashion garment industry\n\n-\u00a0\u00a0\u00a0\u00a0\u00a0\u00a0\u00a0\u00a0 Have knowledge and good understanding of global market in textile, fabric, yarn, fashion garment industry is preferred\n\n-\u00a0\u00a0\u00a0\u00a0\u00a0\u00a0\u00a0\u00a0 Well organized, analytical and detail minded with high initiative, willing to learn and able to work under pressure\n\n-\u00a0\u00a0\u00a0\u00a0\u00a0\u00a0\u00a0\u00a0 Good interpersonal skills, problem solving, communication and presentation skills\u00a0\n\n-\u00a0\u00a0\u00a0\u00a0\u00a0\u00a0\u00a0\u00a0 Good command of spoken and written English, Cantonese and Mandarin, or can Speak in other language( Japanese, Korean, etc) is a plus\n\n-\u00a0\u00a0\u00a0\u00a0\u00a0\u00a0\u00a0\u00a0 Higher Diploma Holder or\u00a0 related discipline\n\n-\u00a0\u00a0\u00a0\u00a0\u00a0\u00a0\u00a0\u00a0 Travel to China and Overseas is frequently required\n\n-\u00a0\u00a0\u00a0\u00a0\u00a0\u00a0\u00a0\u00a0 Fresh Graduate is also acceptable if willing to be sales\n\nResponsibilities:\n\n-\u00a0\u00a0\u00a0\u00a0\u00a0\u00a0\u00a0\u00a0 To maintain good relationship with potential and existing customers\n\n-\u00a0\u00a0\u00a0\u00a0\u00a0\u00a0\u00a0\u00a0 Responsible for handling overseas customers inquires and looking for new customers\n\n-\u00a0\u00a0\u00a0\u00a0\u00a0\u00a0\u00a0\u00a0 Visiting Hong Kong local\u00a0and overseas customers constantly for sales and promotions\n\n-\u00a0\u00a0\u00a0\u00a0\u00a0\u00a0\u00a0\u00a0 Work closely with customers and factory for handling product development, sampling, production orders and quality inspection\n\n-\u00a0\u00a0\u00a0\u00a0\u00a0\u00a0\u00a0\u00a0 Attending oversea and local exhibitions seasonally\n\n-\u00a0\u00a0\u00a0\u00a0\u00a0\u00a0\u00a0\u00a0 Coordinate and communicate with both internal and external parties on orders follow up", "employment_types": ["Full Time", "Permanent"], "selling_points": ["- Manufacturing \uff1e Garment / Textile", "- Client Management", "- Searching for new customers"], "locations": ["Kwun Tong"], "categories": ["Sales, CS & Business Devpt", "Sales - Sales Management", "Others"], "post_time": "2022-01-18T04:00:29Z", "salary": {"currency": null, "max": null, "min": null, "period": "monthly", "term": null}, "salary_visible": false, "title_keywords": ["senior sales executive", "sales manager", "sales executive"], "responsibilities": ["communicate with", "internal and external parties", "quality", "inspection", "coordinate", "maintain good relationship"], "requirements": {"degrees": ["fresh graduate", "higher diploma holder"], "majors": [], "languages": ["cantonese", "english", "mandarin", "japanese", "korean"], "language_level": ["good command"], "hard_skills": ["garment industry", "plus", "problem solving"], "soft_skills": ["willing to learn", "well organized", "problem solving", "communication", "presentation skills", "interpersonal skills", "initiative", "work under pressure"], "languages_combined": [{"language": "cantonese", "language_level": ["good command"]}, {"language": "english", "language_level": ["good command"]}, {"language": "mandarin", "language_level": ["good command"]}, {"language": "japanese", "language_level": ["good command"]}, {"language": "korean", "language_level": ["good command"]}]}, "experience_required": {"duration": [], "field": ["textile", "garment"]}}, {"job_id": "100003009054711", "location_code": "hk", "company": "Cosway (HK) Limited", "job_title": "Sales Associate", "description": "Responsibilities\n\nTo provide high quality of service to the customer by demonstrating in-depth knowledge of the brand and products\n\u63d0\u4f9b\u512a\u8cea\u7684\u9867\u5ba2\u670d\u52d9\u53ca\u63d0\u4f9b\u5c08\u696d\u7522\u54c1\u5efa\u8b70\nResponsible for product selling and proactive to drive sales to achieve retail sales target\n\u92b7\u552e\u7522\u54c1\u53ca\u9054\u6210\u92b7\u552e\u6307\u6a19\nProvide excellent customer services to our clients and build customer loyalty through active client development\n\u4e3b\u52d5\u8207\u5ba2\u6236\u5efa\u7acb\u9577\u9060\u95dc\u4fc2\nSupport retail store daily operations, including visual merchandising, stock keeping and cashiering etc\n\u5354\u52a9\u5e97\u8216\u65e5\u5e38\u904b\u4f5c\uff0c\u5305\u62ec\u7522\u54c1\u9673\u5217\u3001\u5009\u5b58\u6574\u7406\u3001\u6536\u9280\u5de5\u4f5c\u7b49\nTo perform other related ad hoc tasks and projects where necessary\n\u5354\u52a9\u5e97\u92ea\u5b8c\u6210\u6240\u9700\u5de5\u4f5c\u00a0\n\nRequirement\n\nForm 5 and above\n\u4e2d\u4e94\u6216\u4ee5\u4e0a\u7a0b\u5ea6\nPrior exposure in FMCG/ retail industry is preferred\n\u7d93\u9a57\u4e0d\u62d8\uff0c\u5177\u96f6\u552e\u7d93\u9a57\u8005\u512a\u5148\nExcellent interpersonal skills with a pleasant personality\n\u5177\u826f\u597d\u7684\u4eba\u969b\u95dc\u4fc2\u53ca\u6e9d\u901a\u6280\u5de7\nGood command of Cantonese, English and Mandarin is preferred\n\u80fd\u64cd\u6d41\u5229\u5ee3\u6771\u8a71\uff0c\u666e\u901a\u8a71\u53ca\u82f1\u8a9e\nCandidates with immediate availability is highly preferred\n\u53ef\u5373\u6642\u4e0a\u73ed\u8005\u6703\u88ab\u512a\u5148\u8003\u616e\n\nAttractive remuneration package together with a wide range of fringe benefits including 5-day week and medical coverage will be offered. Interested applicant please send your resume with current and expected salary.", "employment_types": ["Full Time"], "selling_points": [], "locations": ["Tsim Sha Tsui"], "categories": ["Sales, CS & Business Devpt", "Business Development", "Others", "Direct Sales"], "post_time": "2022-01-17T10:41:14Z", "salary": {"currency": null, "max": null, "min": null, "period": "monthly", "term": null}, "salary_visible": false, "title_keywords": ["sales associate"], "responsibilities": ["sales target", "quality", "merchandising", "ad hoc tasks", "customer services", "daily operations", "visual", "drive sales"], "requirements": {"degrees": ["form 5"], "majors": [], "languages": ["cantonese", "english", "mandarin"], "language_level": ["good command"], "hard_skills": [], "soft_skills": ["interpersonal skills", "pleasant"], "languages_combined": [{"language": "cantonese", "language_level": ["good command"]}, {"language": "english", "language_level": ["good command"]}, {"language": "mandarin", "language_level": ["good command"]}]}, "experience_required": {"duration": [], "field": []}}, {"job_id": "100003009053813", "location_code": "hk", "company": "Quko Int'l Development Limited", "job_title": "\u92b7\u552e\u5de5\u7a0b\u5e2b**", "description": "\n\u8077\u8cac :\u4e00\u822c\u92b7\u552e\u5de5\u7a0b\u5e2b\u5de5\u4f5c, \u92b7\u552e\u53ca\u63a8\u5ee3\u5404\u985e\u578b\u5ba4\u5167\u7a7a\u6c23\u8cea\u7d20IAQ\u7522\u54c1\uff0c\u4f8b\u5982\u7a7a\u6c23\u6de8\u5316\u6a5f,\u9ad8\u6548\u7a7a\u6c23\u6de8\u5316\u6bba\u83cc\u6a5f,\u6bba\u83cc\u5668\u548c\u5100\u8868\u7b49\n\n\u8cc7\u6b77 :\u5c08\u4e0a\u6559\u80b2\uff1a\u6587\u6191/\u8b49\u66f8; 2\u5e74\u7d93\u9a57; \u826f\u597d\u7cb5\u8a9e; \u4e00\u822c\u666e\u901a\u8a71; \u826f\u597d\u82f1\u8a9e; \u61c2\u8b80\u5beb\u4e2d\u6587; \u61c2\u8b80\u5beb\u82f1\u6587; Sales experience is preferred, \u5177\u92b7\u552e\u91ab\u7642,\u8b77\u8001,\u6559\u80b2\u7b49\u7522\u54c1\u7d93\u9a57\u512a\u5148\n\n\u5f85\u9047 :\u6bcf\u6708$13,500 - $15,500, \u6709\u9280\u884c\u5047\u671f, \u7259\u79d1\u798f\u5229, \u5728\u8077\u57f9\u8a13, \u91ab\u7642\u4fdd\u96aa \u53ca\u4f63\u91d1, \u661f\u671f\u4e00\u81f3\u4e94: \u4e0a\u53489\u6642\u81f3\u4e0b\u53486\u6642, \u6bcf\u9031\u5de5\u4f5c5\u5929\n\n\u7533\u8acb\u9808\u77e5 :\u6c42\u8077\u8005\u53ef\u96fb\u90f5(Apply Now)\u5c65\u6b77\u8868\u7d66\u7ff9\u9ad8\u570b\u969b\u767c\u5c55\u6709\u9650\u516c\u53f8\u3002\u5982\u8981\u7d22\u53d6\u6536\u96c6\u500b\u4eba\u8cc7\u6599\u8072\u660e, \u8acb\u8207\u7f85\u5c0f\u59d0(Email)\u806f\u7d61\u3002\n\n", "employment_types": ["Full Time"], "selling_points": [], "locations": ["Kwun Tong"], "categories": ["Media & Advertising", "Others", "Engineering", "Others", "Sales, CS & Business Devpt", "Others"], "post_time": "2022-01-17T07:34:10Z", "salary": {"currency": null, "max": null, "min": null, "period": "monthly", "term": null}, "salary_visible": false, "title_keywords": [], "responsibilities": [], "requirements": {"degrees": [], "majors": [], "languages": [], "language_level": [], "hard_skills": [], "soft_skills": [], "languages_combined": []}, "experience_required": {"duration": [], "field": []}}, {"job_id": "100003009054945", "location_code": "hk", "company": "Bluetag Limited", "job_title": "Sales & Business Developer", "description": "I Duties and Responsibilities\n\nMake market research and analysis on potential customers and competitors;\nIdentify trends and customer needs\nBuild a short, medium, long-term sales pipeline in accordance with targets;\nDevelop new\u00a0B2B\u00a0opportunities\u00a0in Europe (France as priority);\nCreate and give presentations to clients and internal executives;\nNegotiate contract terms with clients and communicate with stakeholders;\nMonitor project management to ensure contracts are executed as agreed;\nInteract and liaise with merchandisers & clients;\nBuild, develop and maintain a solid and trusting relationship with clients;\nResolve key client issues and complaints;\nProduce regular sales forecast reports & propose new sales strategies to\u00a0stimulate growth.\n\nII Skills and Qualifications\n\nGeneral:\n\nBachelor Degree or above in sales, business or equivalent;\nKnowledge in Small Domestic Appliance (SDA) and outdoor furniture would be an advantage;\nFamiliarity with the trading industry (sourcing, production, logistics and supply-chain management);\nGood communicator, ability to interact & collaborate with cross-functional teams;\nGood listener, problem-solver, propose solutions and follow-up; \u00a0\nProficiency with word processing, excel spreadsheet and presentation software;\nStrong analytical skills and experience with reporting and data analysis;\nFluent in both English and French. Any other language will be a plus;\nPositive energy, entrepreneurial mindset, proactive multi-tasker; good team player;\nBe results-oriented and have a taste for challenge;\nStrategic thinker, ambitious and self-managed;\nDesire to improve processes, dedication to high-quality work.\n\nSales & Business Development\n\nExperience in B2B and B2C sales with strong negotiation skills;\nAbility to manage multiple projects at the same time in a fast-paced environment;\nFamiliarity with project management methodologies;\nAbility and willingness to travel for meetings with prospective and existing clients;\nProficiency in using a CRM and ERP.", "employment_types": ["Full Time", "Permanent"], "selling_points": [], "locations": ["Wan Chai"], "categories": ["Sales, CS & Business Devpt", "Business Development", "Others"], "post_time": "2022-01-17T14:50:47Z", "salary": {"currency": null, "max": null, "min": null, "period": "monthly", "term": null}, "salary_visible": false, "title_keywords": ["developer", "sales"], "responsibilities": ["collaborate with", "software", "quality", "maintain", "liaise with", "contracts", "monitor", "manage multiple projects", "presentations", "develop", "reports", "logistics", "forecast", "reporting", "management", "data analysis", "cross-functional teams", "communicate with", "analysis", "market research", "project management"], "requirements": {"degrees": ["degree or above", "bachelor"], "majors": ["business"], "languages": ["english", "french"], "language_level": ["fluent"], "hard_skills": ["small", "excel", "plus", "analysis", "word processing", "presentations", "analytical skills", "erp", "make", "project management", "spreadsheet"], "soft_skills": ["good team player", "fast-paced environment", "analytical skills", "self-managed", "project management", "negotiation skills", "communicator", "proactive", "presentation", "positive"], "languages_combined": [{"language": "english", "language_level": ["fluent"]}, {"language": "french", "language_level": ["fluent"]}]}, "experience_required": {"duration": [], "field": ["data analysis", "analytical"]}}, {"job_id": "100003009054270", "location_code": "hk", "company": "ARCHETYPAL LIMITED", "job_title": "Showroom Sales Assistant \u2013 Part Time", "description": "The job description below is intended to describe the general nature and level of work being performed by people assigned to this job. It is not an exhaustive list of responsibilities, and it is subject to changes and exceptions at the discretion of supervisors.\n\n(This position is ideal for individuals in the design industry, who would like to be involved in the more business side of this creative environment.)\n\nJob Nature\n\nShowroom Sales Assistant\n\nTo assist Showroom Sales Executive in everyday operations of the shop over weekends and occasional weekday. Candidate with Graphic Design experience will be preferred with negotiate rate.\n\nDaily Job Responsibility\n\nTo provide service to customers and handle basic inquiry at the shop.\nUnderstanding basic sales operation procedure for our POS system and order processing.\nLearn the basic product knowledge and technique in order to assist customers\u2019 varied enquiries.\nAssist in various aspect of this small dynamic team\n\nCandidate Requirement\n\nWe are looking for someone with the following attributes:\n\nMinimum of 1 years of Retail sales experience.\nOutgoing and able to initiate conversation. Great Interpersonal Skill\nresourceful, proactive, diligent\nexcellent spoken and written English and Chinese\npassionate about design\ncheerful and willing to go an extra mile for the company", "employment_types": ["Part Time"], "selling_points": [], "locations": ["Wan Chai"], "categories": ["Manufacturing", "Others", "Sales, CS & Business Devpt", "Others", "Direct Sales"], "post_time": "2022-01-17T09:00:16Z", "salary": {"currency": null, "max": null, "min": null, "period": "hourly", "term": null}, "salary_visible": false, "title_keywords": ["sales assistant"], "responsibilities": ["order processing"], "requirements": {"degrees": [], "majors": [], "languages": [], "language_level": [], "hard_skills": [], "soft_skills": [], "languages_combined": []}, "experience_required": {"duration": [], "field": []}}, {"job_id": "100003009054315", "location_code": "hk", "company": "I.Link Group Limited", "job_title": "Customer Services Executive", "description": "Responsibilities\n\nServe clients with a professional manner, including handle daily inquiries\u00a0and follow up project-related tasks\nCoordinate closely with internal departments, vendors and clients to ensure timely delivery of services\nGood team player, self-motivated and able to work under pressure\nAbility to handle multi-tasks and meet tight deadlines\nFresh graduate is also welcome\n\nRequirements\n\nDSE or above with experience in customer service or related sector preferred\n2 years or above experience in project management or customer service related roles will be an advantage\nProficiency in Microsoft Office (Words, Excel, PowerPoint and Outlook)\nGood communication and interpersonal skills\nGood command in both English and Mandarin\nA team player, hardworking, proactive, patient and organized\nAble to work under pressure and meet tight deadline\nImmediate available will definitely be an advantage\n\nWe offer competitive package and a long-term career development to the right candidate. Interested parties please send your CV with current and expected salary to HRA Department by clicking \u201cApply Now\u201d.\n\nAll information provided by applicants will be treated in strict confidence and be used for recruitment purpose only. Candidates not contacted 6 weeks after submission of applications and/or interviews may consider their application unsuccessful. Personal data provided will be used strictly in accordance with the Company's personal data policy.", "employment_types": ["Full Time", "Permanent"], "selling_points": ["2 years experience in project management or CS", "Good communication & interpersonal skills", "Immediate available will be an advantage"], "locations": ["Central"], "categories": ["Sales, CS & Business Devpt", "Customer Service - Supervisor / Officer", "Account Servicing", "Others"], "post_time": "2022-01-17T09:07:48Z", "salary": {"currency": null, "max": null, "min": null, "period": "monthly", "term": null}, "salary_visible": false, "title_keywords": ["executive"], "responsibilities": ["coordinate", "professional manner", "work under pressure"], "requirements": {"degrees": ["dse"], "majors": [], "languages": ["english", "mandarin"], "language_level": ["good command"], "hard_skills": ["excel", "words", "microsoft office", "powerpoint", "project management", "outlook"], "soft_skills": ["organized", "project management", "customer service", "communication and interpersonal skills", "meet tight deadline", "patient", "team player", "proactive", "hardworking", "work under pressure"], "languages_combined": [{"language": "english", "language_level": ["good command"]}, {"language": "mandarin", "language_level": ["good command"]}]}, "experience_required": {"duration": ["2 years"], "field": ["related", "project management", "customer service"]}}, {"job_id": "100003009054866", "location_code": "hk", "company": "Europe Group Holdings Ltd", "job_title": "Co-ordinator, Sales Administration", "description": "Responsibilities:\n\n\u00a0\u00a0\u00a0\u00a0\u00a0\u00a0\u00a0\u00a0 To communicate with wholesale brands on shipment, after-sales, sample, marketing, etc.\n\u00a0\u00a0\u00a0\u00a0\u00a0\u00a0\u00a0\u00a0 To assist sales manager on handling seasonal buy and executing marketing strategy\n\u00a0\u00a0\u00a0\u00a0\u00a0\u00a0\u00a0\u00a0 Responsible for daily clerical support includes data entry and invoice/document checking\n\u00a0\u00a0\u00a0\u00a0\u00a0\u00a0\u00a0\u00a0 To prepare regular Sales & Inventory Reports to Sales Team and Management\n\u00a0\u00a0\u00a0\u00a0\u00a0\u00a0\u00a0\u00a0 To follow up Goods receive, transfer and export in systems\n\u00a0\u00a0\u00a0\u00a0\u00a0\u00a0\u00a0\u00a0 To handle other admin doc assignments as required\n\nRequirements:\n\n\u00a0\u00a0\u00a0\u00a0\u00a0\u00a0\u00a0\u00a0 Degree or above;\n\u00a0\u00a0\u00a0\u00a0\u00a0\u00a0\u00a0\u00a0 Minimum 3 years\u2019 relevant working experience;\n\u00a0\u00a0\u00a0\u00a0\u00a0\u00a0\u00a0\u00a0 Proficiency in spoken in Chinese (including Cantonese and Mandarin) is a must;\n\u00a0\u00a0\u00a0\u00a0\u00a0\u00a0\u00a0\u00a0 Proficient computer knowledge in MS Office, Word, Excel, Power point & Chinese word processing\n\nInterested parties, please send your detailed resume with expected salary by clicking \"Apply Now\".\n\n\nData collected will be used for recruitment purpose only.", "employment_types": ["Full Time", "Permanent"], "selling_points": ["3 years\u2019 relevant working experience", "Proficiency in spoken in Chinese", "Travel to China if needed"], "locations": ["Tsim Sha Tsui"], "categories": ["Sales, CS & Business Devpt", "Wholesale", "Others", "Sales Administration"], "post_time": "2022-01-17T12:09:24Z", "salary": {"currency": null, "max": null, "min": null, "period": "monthly", "term": null}, "salary_visible": false, "title_keywords": ["sales"], "responsibilities": ["communicate with", "management", "data entry", "invoice", "inventory", "systems", "clerical support", "checking", "executing", "reports", "sales team"], "requirements": {"degrees": ["degree or above"], "majors": [], "languages": ["cantonese", "chinese", "mandarin"], "language_level": ["proficiency", "proficient"], "hard_skills": ["excel", "chinese word processing", "word", "power point", "ms office"], "soft_skills": [], "languages_combined": [{"language": "cantonese", "language_level": ["proficiency"]}, {"language": "chinese", "language_level": ["proficiency", "proficient"]}, {"language": "mandarin", "language_level": ["proficiency"]}]}, "experience_required": {"duration": ["minimum 3 years"], "field": ["relevant working experience"]}}, {"job_id": "100003009052795", "location_code": "hk", "company": "Lalamove", "job_title": "Customer Service Associate", "description": "JOIN US!!\u00a0\u52a0\u5165\u6211\u5011LALAMOVE!\n\nJob Purpose \u00a0\u5de5\u4f5c\u7c21\u4ecb:\n\nThis role is one of the most important positions in our company because you have the most touch points with our users and drivers. You will rush to answer every call on the first ring, and when you are on the phone, you are our lalamove ambassador. Whether our customers or drivers have a positive experience with us depends on you.\u00a0\n\nNo two days are ever the same in customer service and don't be surprised if you receive customer or driver complaints occasionally, it probably means that they are feeling frustrated and they need your help. Our best CS role model gives it a laugh and tries their best to turn around the situation. No hard feelings.\u00a0\n\nThis role suits someone who is positive, outgoing and customer-oriented. To succeed, you must be passionate about our business.\u00a0\n\n\u512a\u8cea\u7684\u5ba2\u6236\u670d\u52d9\u662fLalamove\u6700\u91cd\u8996\u7684\u50f9\u503c\uff0c\u800c\u5ba2\u6236\u670d\u52d9\u90e8\u7ad9\u5728\u516c\u53f8\u7684\u6700\u524d\u7dda\uff0c\u662f\u63d0\u4f9b\u512a\u8cea\u670d\u52d9\u7684\u95dc\u9375\u3002\u8207\u5ba2\u6236\u548c\u53f8\u6a5f\u6e9d\u901a\u6642\uff0c\u60a8\u5c07\u4ee3\u8868Lalamove\u5316\u8eab\u70baLalamove\u5927\u4f7f\uff0c\u60a8\u5c07\u6c7a\u5b9a\u5ba2\u6236\u53ca\u53f8\u6a5f\u7684\u9ad4\u9a57\u3002\u60a8\u5fc5\u9808\u81f4\u529b\u63d0\u4f9b\u6700\u4f73\u670d\u52d9\uff0c\u56e0\u70baLalamove\u7684\u5f62\u8c61\u662f\u7531\u60a8\u5efa\u7acb!\n\n\u5ba2\u6236\u670d\u52d9\u90e8\u6bcf\u65e5\u9700\u8981\u8655\u7406\u5404\u7a2e\u4e0d\u540c\u7684\u554f\u984c\uff0c\u60a8\u9700\u8981\u4ee5\u5e73\u5e38\u5fc3\u53bb\u9762\u5c0d\u6bcf\u4e00\u901a\u4f86\u96fb\u3001\u4ee5\u5c08\u696d\u614b\u5ea6\u5354\u52a9\u5ba2\u6236\u53ca\u53f8\u6a5f\u89e3\u6c7a\u554f\u984c\u3002\n\nResponsibilities\u00a0\u4e3b\u8981\u8077\u8cac\uff1a\n\nAnswer incoming customer and driver calls/ Handling chats enquiry and fulfill their request;\u00a0\n\u63a5\u807d\u71b1\u7dda\u96fb\u8a71/\u8655\u7406\u7dda\u4e0a\u5373\u6642\u5c0d\u8a71\uff0c\u6eff\u8db3\u9867\u5ba2\u53ca\u53f8\u6a5f\u7684\u9700\u8981\nUpdate customers on their order status and\u00a0manage their expectation;\n\u70ba\u5ba2\u6236\u8ddf\u9032\u8a02\u55ae\u9032\u5ea6\u53ca\u7ba1\u7406\u5ba2\u6236\u8981\u6c42\nMonitor fulfillment, and help customers find a vehicle if they have been waiting for a while;\n\u76e3\u63a7\u8a02\u55ae\u914d\u5c0d\u7387\uff0c\u5354\u52a9\u4e58\u5ba2\u5c0b\u6c42\u5408\u9069\u7684\u53f8\u6a5f\nManage corporate users and their request;\n\u5354\u52a9\u7ba1\u7406\u5546\u696d\u5ba2\u6236\uff0c\u4ee5\u6eff\u8db3\u4ed6\u5011\u7684\u9700\u6c42\nResolve user conflicts and performance issues related to drivers;\n\u8655\u7406\u9867\u5ba2\u6295\u8a34\uff0c\u5354\u52a9\u9867\u5ba2\u53ca\u53f8\u6a5f\u89e3\u6c7a\u554f\u984c\nMotivate your peers, and be a role model to others.\n\u8207\u540c\u4e8b\u5efa\u7acb\u826f\u597d\u95dc\u4fc2\uff0c\u6210\u70ba\u5718\u968a\u4e2d\u7684\u597d\u699c\u6a23\nShift Duty is needed \u9700\u8f2a\u73ed\u5de5\u4f5c\n(Hotline Operating hr:\u00a0\nMon - Sat: 08:00 -22:00,\u00a0Sun& P.H: 09:00 -22:00)\n\nRequirements\u00a0\u8cc7\u6b77\u8981\u6c42\uff1a\n\nDSE graduated or above\u00a0\n\u4e2d\u516d\u6216\u4ee5\u4e0a\u5b78\u6b77\u7a0b\u5ea6\n\u00a01 year relevant work experience (Fresh Graduates are also welcome)\n1 \u5e74\u76f8\u95dc\u5de5\u4f5c\u7d93\u9a57 (\u6b61\u8fce\u61c9\u5c46\u7562\u696d\u751f)\nAssertive with excellent interpersonal and communication skills\n\u826f\u597d\u6e9d\u901a\u6280\u5de7\nGood team player and responsible\n\u826f\u597d\u5718\u968a\u7cbe\u795e\uff0c\u6709\u8cac\u4efb\u611f\nFluent in written and spoken English and Cantonese\n\u6d41\u5229\u5ee3\u6771\u8a71\u53ca\u82f1\u8a9e\u66f8\u5beb\u53ca\u6703\u8a71\nKnowledge and understanding of mobile and web technologies\n\u6709\u57fa\u672c\u6d41\u52d5\u96fb\u8a71\u53ca\u96fb\u5b50\u79d1\u6280\u77e5\u8b58\nProficient in Chinese and English typing\n\u61c2\u4e2d\u82f1\u6587\u8f38\u5165\u6cd5\n\nWant to know more about us?\u00a0Please visit our website:\u00a0www.lalamove.com\n\nAll information received will be kept strictly confidential and used only for employment-related purpose.", "employment_types": ["Full Time", "Permanent"], "selling_points": ["5 working days per week", "Dental Plan", "Medical Plan"], "locations": ["Lai Chi Kok"], "categories": ["Sales, CS & Business Devpt", "Call Centre", "Customer Service - Supervisor / Officer", "Others"], "post_time": "2022-01-17T04:05:42Z", "salary": {"currency": null, "max": null, "min": null, "period": "monthly", "term": null}, "salary_visible": false, "title_keywords": ["customer service associate"], "responsibilities": ["hr", "fulfillment", "monitor", "sat"], "requirements": {"degrees": ["dse"], "majors": [], "languages": ["cantonese", "english", "chinese"], "language_level": ["proficient", "fluent"], "hard_skills": ["mobile", "web technologies", "typing"], "soft_skills": ["communication skills", "good team player", "responsible", "assertive", "interpersonal"], "languages_combined": [{"language": "cantonese", "language_level": ["fluent"]}, {"language": "english", "language_level": ["proficient", "fluent"]}, {"language": "chinese", "language_level": ["proficient"]}]}, "experience_required": {"duration": ["1 year"], "field": []}}, {"job_id": "100003009056119", "location_code": "hk", "company": "DHL EXPRESS (HONG KONG) LIMITED", "job_title": "Account Manager", "description": "Working Location: Ngau Tau Kok\n\nReporting to the Area Sales Manager, you will be responsible for:\nAchieve sales targets through promoting DHL products and services (including domestics service solution) to existing and potential customers in assigned customer database\nMaintain business relations with customers for fostering profitable sales\nCoordinate with internal departments to provide excellent services to customers\n\nRequirements:\nDegree holder\nMinimum two years' sales experience in service industry with solid experience in customer acquisition and account management\nStrong selling, presentation, analytical and problem solving skills\nAggressive, well-organized, customer focused and able to work under pressure\nGood command of both spoken and written English & Chinese (Cantonese and Mandarin)\nProficient in MS Office\n\nApplication:\n\nClick \"Apply Now\" or apply on line via the following link:\u00a0\u00a0\nhttps://dhlexpress.taleo.net/careersection/ex/jobdetail.ftl?job=19000D7&tz=GMT%2B08%3A00&tzname=\nand also indicating your current and expected salary, and availability.\u00a0 For more job opportunities, please visit our website at https://www.dpdhl.jobs/\nPersonal Information Collection Statement pertaining to Recruitment\nDHL Express (Hong Kong) Limited / DHL Aviation (Hong Kong) Limited (\u201cDHL\u201d) is committed to protecting and respecting your privacy in accordance with the Personal Data (Privacy) Ordinance of Hong Kong (the \u201cOrdinance\u201d) and DHL\u2019s Personal Data Protection Policy (the \u201cPolicy\u201d) at\u00a0https://www.dhl.com/hk-en/home/footer/local-privacy-notice.html\nBy proceeding to respond to this recruitment advertisement, you consent that we may use, retain, process, transfer or otherwise handle the personal data that we collect from you for recruitment,\u00a0 application processing, assessment and communication purposes (including any other purposes directly related thereto) in accordance with the Policy.\nAll personal data of unsuccessful applicants will be retained for future recruitment purposes for a period of not more than two (2) years after which such data will be destroyed.\nYou have the right at any time to make a data access or correction request concerning your personal data held by us. In addition, you may request us to delete your personal data that is no longer required for the relevant purposes which you have given consent. Should you wish to exercise such rights or have any question in relation to your personal data or the Policy, please contact our Human Resources Division in writing.", "employment_types": ["Full Time", "Permanent"], "selling_points": ["Good selling skills and interpersonal skills", "Minimum two years' sales experience", "Aggressive; good communication skills"], "locations": ["Ngau Tau Kok"], "categories": ["Sales, CS & Business Devpt", "Customer Service - Supervisor / Officer", "Account Servicing", "Others"], "post_time": "2022-01-18T03:21:44Z", "salary": {"currency": null, "max": null, "min": null, "period": null, "term": null}, "salary_visible": false, "title_keywords": ["account manager"], "responsibilities": ["reporting", "management", "data", "coordinate with", "website", "communication", "maintain", "recruitment", "contact", "database", "personal data", "work under pressure"], "requirements": {"degrees": ["degree holder"], "majors": [], "languages": ["cantonese", "english", "chinese", "mandarin"], "language_level": ["good command"], "hard_skills": ["no", "html", "make", "problem solving skills", "processing", "ms office"], "soft_skills": ["focused", "responsible", "well-organized", "communication", "analytical and problem solving skills", "committed", "presentation", "work under pressure"], "languages_combined": [{"language": "cantonese", "language_level": ["good command"]}, {"language": "english", "language_level": ["good command"]}, {"language": "chinese", "language_level": ["good command"]}, {"language": "mandarin", "language_level": ["good command"]}]}, "experience_required": {"duration": ["minimum two years"], "field": ["account management", "service industry"]}}, {"job_id": "100003009053820", "location_code": "hk", "company": "Quko Int'l Development Limited", "job_title": "\u71df\u696d\u4ee3\u8868**", "description": "\n\u8077\u8cac :\u92b7\u552e\u53ca\u63a8\u5ee3\u5404\u985e\u7a7a\u6c23\u6de8\u5316\u6bba\u83cc\u6a5f,\u7a7a\u6c23\u6de8\u5316\u6a5f,\u7a7a\u6c23\u8ca0\u58d3\u6a5f,\u958b\u95dc\u6bba\u83cc\u5668\u53ca\u5100\u8868\u5100\u5668\u7b49\u7522\u54c1, provding quality administrative service to our Clients\n\n\u8cc7\u6b77 :\u4e2d\u4e94\u7a0b\u5ea6; 2\u5e74\u7d93\u9a57; \u826f\u597d\u7cb5\u8a9e; \u4e00\u822c\u666e\u901a\u8a71; \u826f\u597d\u82f1\u8a9e; \u61c2\u8b80\u5beb\u4e2d\u6587; \u61c2\u8b80\u5beb\u82f1\u6587; \u5177\u8cac\u4efb\u5fc3, \u6e9d\u901a\u6280\u5de7, \u80fd\u7368\u7acb\u8655\u7406\u5de5\u4f5c, Team work,\u5177\u92b7\u552e\u91ab\u7642,\u8b77\u8001,\u6559\u80b2\u884c\u696d\u7b49\u7522\u54c1\u7d93\u9a57\u512a\u5148\n\n\u5f85\u9047 :\u6bcf\u6708$13,000 - $14,000, \u6709\u9280\u884c\u5047\u671f, \u7259\u79d1\u798f\u5229, \u91ab\u7642\u798f\u5229 \u53ca\u4f63\u91d1, \u661f\u671f\u4e00\u81f3\u4e94: \u4e0a\u53489\u6642\u81f3\u4e0b\u53486\u6642, \u6bcf\u9031\u5de5\u4f5c5\u5929\n\n\u7533\u8acb\u9808\u77e5 :\u6c42\u8077\u8005\u53ef\u96fb\u90f5(Apply Now)\u5c65\u6b77\u8868\u7d66\u7ff9\u9ad8\u570b\u969b\u767c\u5c55\u6709\u9650\u516c\u53f8\u3002\u5982\u8981\u7d22\u53d6\u6536\u96c6\u500b\u4eba\u8cc7\u6599\u8072\u660e, \u8acb\u8207\u7f85\u5c0f\u59d0(Email)\u806f\u7d61\u3002\n\n", "employment_types": ["Full Time"], "selling_points": [], "locations": ["Kwun Tong"], "categories": ["Sales, CS & Business Devpt", "Wholesale", "Others", "Direct Sales"], "post_time": "2022-01-17T07:34:47Z", "salary": {"currency": null, "max": null, "min": null, "period": "monthly", "term": null}, "salary_visible": false, "title_keywords": ["\u71df\u696d\u4ee3\u8868"], "responsibilities": ["quality"], "requirements": {"degrees": [], "majors": [], "languages": [], "language_level": [], "hard_skills": [], "soft_skills": [], "languages_combined": []}, "experience_required": {"duration": [], "field": []}}, {"job_id": "100003009055099", "location_code": "hk", "company": "Autotoll Limited", "job_title": "Operation and Customer Service Team Leader   (CS Support)", "description": "To cope with our expansion and continuous growth in the transportation and logistics related service, we are inviting talents to join our professional team.\nAbout the Role:\nAssist the Operation and Customer Service Team Head in manage the daily operation of the department\nEnsure timely handling of all customers\u2019 queries and complaints within the established timeframe\nBeing in-charge of operation of customer services centre, kiosks, outlets and other services channels\nTo ensure the services provided in all services channels are according to procedures and make suggestion for any improvement in daily process\nSupervise the operation in Tag management; dispute and complaint handling, Enforcement process\nPrepare the monthly report to the Operation and Customer Service Team Head regarding the operation of the department & those required to submit to Government Department\n\nAbout You:\n\nHolding a university degree or equivalent qualification\nAt least four years post-qualification full time working experience in customer service roles, of which at least two years shall be at managerial or supervisory level\n\nWhat you can get from us:\nOn-the-job training, learning and development\u00a0provided\nExecutive workshops, interest class, corporate purchase discount offered by SHKP\nCompetitive salary and annual leaves\nFlexible working opportunities\nInterested parties, please send full resume with\u00a0expected salary\u00a0and\u00a0available date\u00a0to Human Resources and Administration Department by e-mail or by fax 2111 9459.\n(Data collected will be used for recruitment purpose only.)", "employment_types": ["Full Time", "Permanent"], "selling_points": ["Assist manager to manage daily operation", "Ensure timely handling of all customers\u2019 queries", "Degree holder with at least 4 yrs exp."], "locations": ["Not Specified"], "categories": ["Sales, CS & Business Devpt", "Customer Service - Supervisor / Officer", "Others"], "post_time": "2022-01-18T01:15:11Z", "salary": {"currency": null, "max": null, "min": null, "period": "monthly", "term": null}, "salary_visible": false, "title_keywords": ["team leader", "customer service"], "responsibilities": ["management", "daily operation", "procedures", "customer services", "purchase", "customer service", "logistics", "monthly report"], "requirements": {"degrees": ["university degree"], "majors": [], "languages": [], "language_level": [], "hard_skills": ["workshops", "make"], "soft_skills": ["flexible", "timely", "customer service", "learning"], "languages_combined": []}, "experience_required": {"duration": ["at least two years", "at least four years"], "field": ["supervisory level", "managerial", "customer service", "post-qualification"]}}, {"job_id": "100003009055802", "location_code": "hk", "company": "PHC Medical Diagnostic Centre Limited", "job_title": "Call Team Clerk", "description": "Job Duties\n\n* Handle customer enquiries and complaint\uff1b\n\n* To handle clerical duties including data entry, filing and scanning\uff1b\n\n* Check and count the test sample\uff1b\n\n* Other related duties as assigned by the supervisor.\n\nQualification\n\n* Form 5 / HKDSE or above, no relevant experience are welcome\uff1b\n\n* Good command of spoken English, Cantonese and Chinese\uff1b\n\n* Able to work under pressure and independently\uff1b\n\n* Not afraid of blood samples and other samples\uff1b\n\n* Immediately available or short notice is highly preferred.", "employment_types": ["Full Time", "Permanent"], "selling_points": [], "locations": ["Kwai Hing"], "categories": ["Sales, CS & Business Devpt", "Call Centre", "Others"], "post_time": "2022-01-18T02:57:51Z", "salary": {"currency": null, "max": null, "min": null, "period": "monthly", "term": null}, "salary_visible": false, "title_keywords": ["clerk"], "responsibilities": ["scanning", "work under pressure", "handle customer enquiries", "data entry"], "requirements": {"degrees": ["form 5", "hkdse"], "majors": [], "languages": ["cantonese", "english", "chinese"], "language_level": ["good command"], "hard_skills": ["no"], "soft_skills": ["independently", "work under pressure"], "languages_combined": [{"language": "cantonese", "language_level": ["good command"]}, {"language": "english", "language_level": ["good command"]}, {"language": "chinese", "language_level": ["good command"]}]}, "experience_required": {"duration": [], "field": ["relevant experience"]}}, {"job_id": "100003009053393", "location_code": "hk", "company": "Phoelia (Far East) Company Ltd", "job_title": "Sales Manager", "description": "\nRequirements:\n\u2022 At least 2 years sales experience with related fields\n\u2022 Good negotiation and presentation skill\n\u2022 Organized personality and able to achieve sales target\n\u2022 Good Sales Orientation\n\u2022 Able to work under pressure & independent\n\u2022 Pleasant and out-going character\nResponsibilities:\n\u2022 Develops new client base\n\u2022 Explores and follow up current client leads\n\u2022 Maintains good customer relationships\n\u2022 Meets sales target\nRemuneration:\n\u2022 Good career path to management level\nBank holidays + Medical scheme\nBasic salary + attractive incentive package\n\u2022 Professional training is provided\nInterested parties please send your resume to Apply Now\n\n", "employment_types": ["Full Time"], "selling_points": [], "locations": ["Not Specified"], "categories": ["Sales, CS & Business Devpt", "Business Development", "Others", "Direct Sales"], "post_time": "2022-01-17T06:55:05Z", "salary": {"currency": null, "max": null, "min": null, "period": "monthly", "term": null}, "salary_visible": false, "title_keywords": ["sales manager"], "responsibilities": ["sales target", "client base", "management"], "requirements": {"degrees": [], "majors": [], "languages": [], "language_level": [], "hard_skills": ["presentation skill"], "soft_skills": ["presentation skill", "organized", "independent", "negotiation", "pleasant", "work under pressure"], "languages_combined": []}, "experience_required": {"duration": ["at least 2 years"], "field": ["related"]}}, {"job_id": "100003009055863", "location_code": "hk", "company": "33 Financial Services Limited", "job_title": "Part Time Customer Service Officer - Sales Support Operations", "description": "Responsibilities:\n\n\nProcessing Sales order for Prepare Gift Cards\nHandle walk in customer service inquiries\nReport daily sales volume\nSupport inventory control\nProvide outstanding branded customer service\nRequirements:\n\nMinimum Form 5 and above with at least 1-year solid sales experience\nProactive, result-oriented and flexible manner\nPossess excellent communication, customer service and interpersonal skill\nGood command of Cantonese, Mandarin and English\n2 working shifts from 10 am to 4 pm\u00a0 &\u00a0 4pm to 10 pm\u00a0\nProfessional Customer Service Oriented\u00a0", "employment_types": ["Part Time"], "selling_points": ["Young and Energetic Team", "Flexible working hours 10 am - 4 pm & 4 pm - 10 pm", "Allowance on nite shift & shifts on Sat Sun & PH"], "locations": ["Tsim Sha Tsui"], "categories": ["Sales, CS & Business Devpt", "Customer Service - Supervisor / Officer", "Others"], "post_time": "2022-01-18T03:08:26Z", "salary": {"currency": "HKD", "max": 74, "min": 40, "period": "hourly", "term": null}, "salary_visible": true, "title_keywords": ["sales", "operations", "customer service officer"], "responsibilities": ["inventory control", "customer service", "report"], "requirements": {"degrees": ["form 5"], "majors": [], "languages": ["cantonese", "english", "mandarin"], "language_level": ["good command"], "hard_skills": [], "soft_skills": ["flexible", "customer service oriented", "interpersonal skill", "communication", "customer service", "proactive", "result-oriented"], "languages_combined": [{"language": "cantonese", "language_level": ["good command"]}, {"language": "english", "language_level": ["good command"]}, {"language": "mandarin", "language_level": ["good command"]}]}, "experience_required": {"duration": ["at least 1-year"], "field": []}}, {"job_id": "100003009055136", "location_code": "hk", "company": "Bonkuchen Company Limited", "job_title": "\u696d\u52d9\u4ee3\u8868 Business Development", "description": "\u8077\u8cac :\n\n\u958b\u62d3\u65b0\u5ba2\u6236, \u8ddf\u9032\u5ba2\u6236\u53ca\u5de5\u7a0b\u9032\u5ea6\n\u8cc7\u6b77 :\n\n\u4e2d\u4e94\u7a0b\u5ea6\n10\u5e74\u7d93\u9a57\n\u4e00\u822c\u7cb5\u8a9e; \u4e00\u822c\u82f1\u8a9e; \u61c2\u95b1\u8b80\u4e2d\u6587; \u61c2\u95b1\u8b80\u82f1\u6587\n\u5f85\u9047 :\n\n\u6bcf\u6708$18,000 - $25,000\n\u661f\u671f\u4e00\u81f3\u4e94: \u4e0a\u53489\u6642\u81f3\u4e0b\u53486\u6642, \u6bcf\u9031\u5de5\u4f5c5\u5929\n\u7533\u8acb\u9808\u77e5 :\n\n\u6c42\u8077\u8005\u53ef\u50b3\u771f(21173001)\u6216\u96fb\u90f5\u5c65\u6b77\u8868\u7d66\u7279\u5eda\u5de5\u4f5c\u5ba4\u6709\u9650\u516c\u53f8\u3002\u5982\u8981\u7d22\u53d6\u6536\u96c6\u500b\u4eba\u8cc7\u6599\u8072\u660e, \u8acb\u8207\u5f6d\u5c0f\u59d0(Tel:21173008)\u806f\u7d61\u3002", "employment_types": ["Full Time"], "selling_points": ["\u6bcf\u6708$18,000 - $25,000", "\u6bcf\u9031\u5de5\u4f5c5\u5929, \u4e0a\u53489\u6642\u81f3\u4e0b\u53486\u6642", "10\u5e74\u7d93\u9a57"], "locations": ["Wong Tai Sin Area"], "categories": ["Sales, CS & Business Devpt", "Business Development", "Others", "Direct Sales"], "post_time": "2022-01-18T01:23:56Z", "salary": {"currency": null, "max": null, "min": null, "period": "monthly", "term": null}, "salary_visible": false, "title_keywords": [], "responsibilities": [], "requirements": {"degrees": [], "majors": [], "languages": [], "language_level": [], "hard_skills": [], "soft_skills": [], "languages_combined": []}, "experience_required": {"duration": [], "field": []}}, {"job_id": "100003009053530", "location_code": "hk", "company": "Million Yield Properties Limited", "job_title": "\u71df\u696d\u54e1", "description": "\n\u8077\u8cac :\u5c08\u71df\u4e8c\u624b\u5c4b\u82d1, \u4e0d\u9700\u505a\u6a13\u82b1, \u8cc7\u6e90\u7ba1\u7406\n\n\u8cc7\u6b77 :\u4e2d\u4e94\u7a0b\u5ea6; \u826f\u597d\u7cb5\u8a9e; \u4e00\u822c\u666e\u901a\u8a71; \u4e00\u822c\u82f1\u8a9e; \u61c2\u8b80\u5beb\u4e2d\u6587; \u61c2\u95b1\u8b80\u82f1\u6587; \u6301\u6709\u5730\u7522\u71df\u696d\u54e1\u724c\u7167\n\n\u5f85\u9047 :\u6bcf\u6708$9,200 - $12,000, \u6709\u4f63\u91d1, \u5728\u8077\u57f9\u8a13 \u53ca\u6649\u5347\u6a5f\u6703, \u4e0a\u534810\u6642\u534a\u81f3\u4e0b\u53485\u6642\u534a,\u4e2d\u534812\u6642\u81f3\u4e0b\u53487\u6642\u6216\u4e0b\u53482\u6642\u534a\u81f3\u4e0b\u53489\u6642, \u6bcf\u9031\u5de5\u4f5c6\u5929,\u8f2a\u73ed,\u8f2a\u4f11, \u6bcf\u5929\u5de5\u4f5c 6 \u5c0f\u6642\n\n\u7533\u8acb\u9808\u77e5 :\u6c42\u8077\u8005\u53ef\u81f4\u96fb66001200\u8207\u842c\u6021\u7f6e\u696d\u6709\u9650\u516c\u53f8\u65b9\u5c0f\u59d0\u806f\u7d61\u3002\n\n", "employment_types": ["Full Time"], "selling_points": [], "locations": ["Tuen Mun Area"], "categories": ["Sales, CS & Business Devpt", "Others", "Others", "Others", "Direct Sales"], "post_time": "2022-01-17T07:06:41Z", "salary": {"currency": null, "max": null, "min": null, "period": "monthly", "term": null}, "salary_visible": false, "title_keywords": ["\u71df\u696d\u54e1"], "responsibilities": [], "requirements": {"degrees": [], "majors": [], "languages": [], "language_level": [], "hard_skills": [], "soft_skills": [], "languages_combined": []}, "experience_required": {"duration": [], "field": []}}, {"job_id": "100003009053370", "location_code": "hk", "company": "Dell Hong Kong Limited", "job_title": "Account Executive", "description": "\n\u00a0 What you\u2019ll achieve\nAs an Account Executive, you will be responsible for building strong customer relationships in the field and ensuring an outstanding customer experience with existing and potential customers.\nYou will:\n\u2022 Develop an understanding of customers\u2019 business and solution requirements\n\u2022 Gain share of spend across Dell Technologies desk top portfolio of technology solutions\n\u2022 Run territory and or accounts, including account planning, sales forecasting, engaging cross-functional resources and working with the virtual teams to ensure alignment across the organizations\n\u2022 Regularly engage with decision makers at client facilities in performing primary duties\n\u2022 Provide sales leadership and experience on large, sophisticated opportunities\nTake the first step towards your dream career\nEvery Dell Technologies team member brings something unique to the table. Here\u2019s what we are looking for with this role:\n\nEssential Requirements\n\u2022 At least 5 to 8 years of experience selling technology solutions\n\u2022 Expert knowledge of market trends that impact on Dell Technologies customers\n\u2022 Outstanding customer management and strategic selling skills that will improve the success of our customers\u2019 business and the growth of Dell Technologies\n\u2022 Strong communication, collaboration, negotiation and executive presentation skills and the ability to provide insight and thought leadership to senior/CIO/CXO leadership and next two levels down\n\u2022 Ability to work in a fast-paced ambitious environment\nDesirable Requirements\n\u2022 Bachelor\u2019s degree\nInterested parties please click Apply Now to apply job.\nHere\u2019s our story; now tell us yours\nDell Technologies helps organizations and individuals build a brighter digital tomorrow. Our company is made up of more than 150,000 people, located in over 180 locations around the world. We\u2019re proud to be a diverse and inclusive team and have an endless passion for our mission to drive human progress.\n\nWhat\u2019s most important to us is that you are respected, feel like you can be yourself and have the opportunity to do the best work of your life - while still having a life. We offer excellent benefits, bonus programs, flexible work arrangements, a variety of career development opportunities, employee resource groups, and much more.\n\nWe started with computers, but we didn\u2019t stop there. We are helping customers move into the future with multi-cloud, AI and machine learning through the most innovative technology and services portfolio for the data era. Join us and become a part of what\u2019s next in technology, starting today.\n\nYou can also learn more about us by reading our latest Diversity and Inclusion Report and our plan to make the world a better place by 2030 here.\n\nApplication closing date: 31-03-2021\n\nDell is committed to the principle of equal employment opportunity for all employees and to providing employees with a work environment free of discrimination and harassment. All employment decisions at Dell are based on business needs, job requirements and individual qualifications, without regard to race, color, religion or belief, national, social or ethnic origin, sex (including pregnancy), age, physical, mental or sensory disability, HIV Status, sexual orientation, gender identity and/or expression, marital, civil union or domestic partnership status, past or present military service, family medical history or genetic information, family or parental status, or any other status protected by the laws or regulations in the locations where we operate. Dell will not tolerate discrimination or harassment based on any of these characteristics. Dell encourages applicants of all ages. Read the full Equal Employment Opportunity Policy here.\n\n", "employment_types": ["Full Time"], "selling_points": [], "locations": ["Not Specified"], "categories": ["Admin & HR", "Others", "Sales, CS & Business Devpt", "Business Development", "Others"], "post_time": "2022-01-17T06:52:42Z", "salary": {"currency": null, "max": null, "min": null, "period": "monthly", "term": null}, "salary_visible": false, "title_keywords": ["account executive"], "responsibilities": ["management", "teams", "develop", "communication", "forecasting", "planning"], "requirements": {"degrees": ["degree", "bachelor"], "majors": [], "languages": [], "language_level": [], "hard_skills": [], "soft_skills": ["sophisticated", "negotiation", "responsible", "unique", "communication", "presentation skills", "team member", "leadership"], "languages_combined": []}, "experience_required": {"duration": ["at least 5 to 8 years"], "field": []}}, {"job_id": "100003009053524", "location_code": "hk", "company": "Healthcare Medical & Paramedical Services Operations (HK) Limited", "job_title": "Senior Manager, Business Development (Health Care)", "description": "\nJob Purpose:\nDriving the business performance through optimizing its capabilities and renewed offerings.\nResponsibilities:\n\u2022 Generate and qualify leads; sharp and close new opportunities that align with the Group Health Care Business growth strategy\n\u2022 Pitch and win new contracts to achieve sales and revenue targets\n\u2022 Serve as the primary point of contact and relationship manager for assigned accounts\n\u2022 Meet regularly with current and prospective clients to build long-term, trusted relationships and to deepen our understanding of their needs and challenges, and to address these with the company offerings\n\u2022 Identify emerging high-interest projects and cross-selling opportunities; creating materials to engage clients\n\u2022 Work with internal supporting functions and the network doctors to provide good services to clients\n\u2022 Use marketing and sales information services and platforms to develop and manage a robust sales pipeline\n\u2022 Maintain account and contact updates, track activities and campaigns, and move opportunities through to closing\n\u2022 Work with the team to support the sales cycle; support acquisition of new doctors/clinics\n\u2022 Participate in account planning and sales pipeline meetings\n\u2022 Collaborate with client service teams, Group marketing teams etc. to strengthen the sales process and offerings\n\u2022 Build and maintain work relationship with different stakeholders to understand how key technical capabilities meet client needs and to deliver a high-quality customer experience\n\u2022 Contribute to market intelligence throuh sharing client experience and insights, participating in industry events, and from other sources as needed\n\u2022 Be accountable for the overall business performance\n\u2022 Handle ad-hoc projects/tasks or tasks assigned by supervisors\nRequirements:\n\u2022 University degree with minimum 10 years\u2019 working experience in Health Care industry\n\u2022 Strong in driving the business development and sales performance\n\u2022 Good business acumen with strong corporate mindset\n\u2022 Good management and leadership skills\n\u2022 Good knowledge of the health care market\n\u2022 Excellent communication, presentation skill, interpersonal and influencing skills\n\n", "employment_types": ["Full Time"], "selling_points": [], "locations": ["Not Specified"], "categories": ["Admin & HR", "Others", "Sales, CS & Business Devpt", "Business Development", "Others"], "post_time": "2022-01-17T07:05:51Z", "salary": {"currency": null, "max": null, "min": null, "period": "monthly", "term": null}, "salary_visible": false, "title_keywords": ["senior manager"], "responsibilities": ["collaborate with", "contracts", "teams", "quality", "develop", "maintain", "contact", "ad-hoc projects", "planning"], "requirements": {"degrees": ["university degree"], "majors": [], "languages": [], "language_level": [], "hard_skills": ["presentation skill", "acumen"], "soft_skills": ["presentation skill", "leadership skills", "communication", "business acumen", "interpersonal"], "languages_combined": []}, "experience_required": {"duration": ["minimum 10 years"], "field": ["health care"]}}, {"job_id": "100003009053399", "location_code": "hk", "company": "Phoelia (Far East) Company Ltd", "job_title": "Sales Manager-Healthway", "description": "\nRequirements:\n\u2022 At least 1-2 years sales experience with related fields of Air Purifier preferable\n\u2022 Good negotiation and presentation skill\n\u2022 Organized personality and able to achieve sales target\n\u2022 Able to work under pressure & independent\n\u2022 Pleasant and out-going character\nResponsibilities:\n\u2022 Works as the product manager of Air Purifier\n\u2022 Maintains good customer relationships\n\u2022 Develops new client base and Dealer/Reseller\n\u2022 Performs sales support/marketing\n\u2022 Meets sales target\nRemuneration:\nBank holidays + Medical scheme\nBasic salary + attractive incentive package\n\u2022 Professional training is provided\nInterested parties please send your resume to Apply Now\n\n", "employment_types": ["Full Time"], "selling_points": [], "locations": ["Not Specified"], "categories": ["Sales, CS & Business Devpt", "Business Development", "Others", "Direct Sales"], "post_time": "2022-01-17T06:55:40Z", "salary": {"currency": null, "max": null, "min": null, "period": "monthly", "term": null}, "salary_visible": false, "title_keywords": ["sales manager"], "responsibilities": ["sales target", "client base"], "requirements": {"degrees": [], "majors": [], "languages": [], "language_level": [], "hard_skills": ["presentation skill"], "soft_skills": ["presentation skill", "organized", "independent", "negotiation", "pleasant", "work under pressure"], "languages_combined": []}, "experience_required": {"duration": ["at least 1-2 years"], "field": ["related"]}}, {"job_id": "100003009053715", "location_code": "hk", "company": "Biotek Ozone Hong Kong Limited", "job_title": "\u71df\u696d\u4ee3\u8868", "description": "\n\u8077\u8cac :\u4e00\u822c\u71df\u696d\u4ee3\u8868\u5de5\u4f5c, \u92b7\u552e\u63a8\u5ee3\u7522\u54c1, \u96fb\u8a71\u63a8\u5ee3, \u4e00\u822c\u92b7\u552e\u53ca\u5e02\u5834\u63a8\u5ee3\u5de5\u4f5c (\u91ab\u7642\u7528\u54c1)\n\n\u8cc7\u6b77 :\u4e2d\u516d\u7a0b\u5ea6; \u4e00\u822c\u7cb5\u8a9e; \u4e00\u822c\u82f1\u8a9e; \u7565\u61c2\u8b80\u5beb\u4e2d\u6587; \u7565\u61c2\u8b80\u5beb\u82f1\u6587; \u61c2\u4e2d\u6587\u6253\u5b57\n\n\u5f85\u9047 :\u6bcf\u6708$11,000 - $14,000, \u6709\u96d9\u7ce7 \u53ca\u91ab\u7642\u798f\u5229, \u661f\u671f\u4e00\u81f3\u4e94: \u4e0a\u53489\u6642\u534a\u81f3\u4e0b\u53485\u6642\u534a, \u6bcf\u9031\u5de5\u4f5c5\u5929, \u6bcf\u5929\u5de5\u4f5c 8 \u5c0f\u6642\n\n\u7533\u8acb\u9808\u77e5 :\u6c42\u8077\u8005\u53ef\u96fb\u90f5(Apply Now)\u5c65\u6b77\u8868\u7d66\u767e\u7279\u9999\u6e2f\u6709\u9650\u516c\u53f8\u3002\u5982\u8981\u7d22\u53d6\u6536\u96c6\u500b\u4eba\u8cc7\u6599\u8072\u660e, \u8acb\u8207\u738b\u5148\u751f(Email)\u806f\u7d61\u3002\n\n", "employment_types": ["Full Time"], "selling_points": [], "locations": ["Lai Chi Kok"], "categories": ["Sales, CS & Business Devpt", "Wholesale", "Others", "Direct Sales"], "post_time": "2022-01-17T07:24:09Z", "salary": {"currency": null, "max": null, "min": null, "period": "monthly", "term": null}, "salary_visible": false, "title_keywords": ["\u71df\u696d\u4ee3\u8868"], "responsibilities": [], "requirements": {"degrees": [], "majors": [], "languages": [], "language_level": [], "hard_skills": [], "soft_skills": [], "languages_combined": []}, "experience_required": {"duration": [], "field": []}}, {"job_id": "100003009054063", "location_code": "hk", "company": "The Hong Kong Jockey Club", "job_title": "Customer Services Assistant (Part-time)", "description": "The Department\nThe Racing Club is the young elite Member Segment in the Hong Kong Jockey Club. It uncovers a unique way to savour racing and to explore the sport like never before. Its mission is to take the passion for horse racing to the next level through an endless stream of exclusive, tailor-made experiences. The candidate is responsible for assisting at various member\u2019s events to contribute premium and dedicated customer communication and services to enhance customer satisfaction and loyalty to The Racing Club.\n\nThe Job\nYou will\n\nAssist the Racing Club Experience Team to execute Members\u2019 events during racedays and non-racedays e.g. escort Members and their guests, taking photos and attendance, distributing souvenirs etc.\nWork closely under instruction from Racing Club Experience Team to ensure a smooth flow of events and minimise error\nWork for non-office working hours and Public Holidays at both Happy Valley and Sha Tin Racecourses, working hours will be notified per job\n\nAbout You\nYou should have\n\nHKCEE/ DSE or above\nRelevant working experience in Customer Service would be an advantage\nExcellent interpersonal and communication skills in both English and Cantonese, Mandarin is a plus\nResponsible, punctual and able to work independently\nAn out-going personality and high team spirit to work with others effectively\nBe customer-centric, self-motivated and attention to details and logistics\nA professional manner on handling confidential information\n\n\nTerms of Employment\nPay-rate:\nHK$88 per hour\n\nWorking Schedule:\nRacedays and Non-Racedays(4-6 hours per day / 6-7 days per month)\u00a0\n*Actual working hours would depend on operational needs.\n\nWorking Location\nHappy Valley Racecourse and Sha Tin Racecourse\n*Actual working location would depends on the event.\n\nHow to Apply\nPlease send your resume and job reference by clicking the Apply Now button or to:\nFax: 2881-7966\nMail: The Human Resources Department,\u00a0\u00a0\u00a0\u00a0\u00a0\u00a0\u00a0\u00a0\n\u00a0\u00a0\u00a0\u00a0\u00a0\u00a0\u00a0\u00a0\u00a0 The Hong Kong Jockey Club,\u00a0\u00a0\u00a0\u00a0\u00a0\n\u00a0\u00a0\u00a0\u00a0\u00a0\u00a0\u00a0\u00a0\u00a0 1 Sports Road, Happy Valley,\n\u00a0\u00a0\u00a0\u00a0\u00a0\u00a0\u00a0\u00a0\u00a0 Hong Kong\n\nFind out more about the remarkable opportunity today. Visit our website at www.hkjc.com now.\n\nWe are an equal opportunity employer.\n\nPersonal data collected will be used for recruitment purposes only.", "employment_types": ["Part Time"], "selling_points": ["The Hong Kong Jockey Club", "Part Time", "Customer Service"], "locations": ["Shatin Area"], "categories": ["Sales, CS & Business Devpt", "Others"], "post_time": "2022-01-17T08:17:26Z", "salary": {"currency": null, "max": null, "min": null, "period": "hourly", "term": null}, "salary_visible": false, "title_keywords": ["customer services assistant"], "responsibilities": ["attendance", "professional manner", "communication", "customer service", "logistics", "schedule"], "requirements": {"degrees": ["dse"], "majors": [], "languages": ["cantonese", "english", "mandarin"], "language_level": ["excellent"], "hard_skills": ["plus"], "soft_skills": ["communication skills", "work independently", "team spirit", "self-motivated", "responsible", "passion for", "unique", "communication", "customer service", "attention to details", "smooth", "interpersonal"], "languages_combined": [{"language": "cantonese", "language_level": ["excellent"]}, {"language": "english", "language_level": ["excellent"]}, {"language": "mandarin", "language_level": ["excellent"]}]}, "experience_required": {"duration": [], "field": ["customer service", "relevant working experience", "team"]}}, {"job_id": "100003009055376", "location_code": "hk", "company": "ADECCO", "job_title": "\u7f8e\u570b\u6642\u5c1a\u76ae\u5177\u54c1\u724cSales / Senior Sales", "description": "Responsibilities:\n\nProvides administrative and clerical supports to Preschool Sales Team\nPrepares presentation and promotion materials\nSupports sales activities, i.e. taking meeting minutes for weekly sales meeting, updating customer service database, coordinating sample order and delivery arrangement\nOther ad hoc duties as assigned\n\nRequirements:\n\nDSE or above\n1-2 years experience in office support\u00a0\nSelf-motivated, good team player with proactive working attitude\nGood communication skills and detail-minded\nGood in MS Office including Word, Excel, PowerPoint and Chinese typing skills\n\nWe offer excellent career development opportunities to unleash your potential, competitive remuneration package including a 5-day work week, comprehensive group medical insurance and dental scheme, discretionary bonus and staff purchasing discount, etc.\n\nInterested parties please apply with your full resume stating present and expected salary\u00a0by clicking\u00a0\"Apply Now\". \u00a0Only short-listed candidates will be contacted.\n\nYou are welcome to visit our\u00a0websites\u00a0to know more about us:\u00a0ephhk.popularworldhk.com\u00a0/\u00a0www.popular.com.hk\n\nPersonal data provided by job applicants will be kept strictly confidential and used for employment related purpose.\u00a0 Only short-listed candidates will be contacted.", "employment_types": ["Full Time", "Permanent"], "selling_points": [], "locations": ["Others"], "categories": ["Sales, CS & Business Devpt", "Retail Sales", "Others"], "post_time": "2022-01-18T02:23:05Z", "salary": {"currency": null, "max": null, "min": null, "period": "monthly", "term": null}, "salary_visible": false, "title_keywords": ["senior sales"], "responsibilities": ["ad hoc duties", "sales activities", "customer service", "sales team", "database"], "requirements": {"degrees": ["dse"], "majors": [], "languages": ["chinese"], "language_level": ["good"], "hard_skills": ["excel", "typing", "word", "powerpoint", "scheme", "ms office"], "soft_skills": ["detail-minded", "communication skills", "good team player", "self-motivated", "comprehensive", "proactive"], "languages_combined": [{"language": "chinese", "language_level": ["good"]}]}, "experience_required": {"duration": ["1-2 years"], "field": []}}, {"job_id": "100003009053267", "location_code": "hk", "company": "Intertek Testing Services Hong Kong Ltd", "job_title": "Customer Services Executive (Food)", "description": "Responsibilities :\n\n\u00a0\u7dad\u6301\u5e97\u8216\u65e5\u5e38\u904b\u4f5c\n\u00a0\u5e97\u5167\u7522\u54c1\u92b7\u552e\n\u00a0\u900f\u904e\u96fb\u8a71\u3001\u5373\u6642\u901a\u8a0a\u8edf\u4ef6\u8207\u5ba2\u6236\u4fdd\u6301\u9577\u9060\u53ca\u826f\u597d\u95dc\u4fc2\n\u00a0\u5354\u52a9\u9054\u6210\u516c\u53f8\u5b9a\u4e0b\u7684\u5718\u968a\u92b7\u552e\u76ee\u6a19\u3001\u500b\u4ebaKPI\n\u00a0\u8ca8\u5834\u53ca\u5009\u5b58\u7ba1\u7406\u4ee5\u78ba\u4fdd\u5b58\u8ca8\u5145\u8db3\n\u00a0\u6574\u7406\u8ca8\u7269\u53ca\u4fdd\u6301\u5e97\u5167\u6e05\u6f54\nExperience Requirements :\n\n\u00a0\u6d41\u5229\u5ee3\u6771\u8a71\u3001\u719f\u7df4\u7684\u5546\u696d\u7528\u666e\u901a\u8a71\u53ca\u82f1\u8a9e\n\uff11\u5e74\u6216\u4ee5\u4e0a\u96f6\u552e\u7d93\u9a57\u6703\u512a\u5148\u8003\u616e\n\u00a0\u6b61\u8fce\u6027\u683c\u9032\u53d6\uff0c\u62b1\u6709\u6a02\u65bc\u5b78\u7fd2\u5fc3\u614b\u8005\n\u00a0\u5c0d\u76ae\u9769 / \u76ae\u5177\u6709\u57fa\u672c\u8a8d\u8b58\n\u00a0\u63d0\u4f9b\u89aa\u5584\u6709\u79ae\u7684\u9867\u5ba2\u670d\u52d9\n\u54e1\u5de5\u798f\u5229\uff1a\n\n\u00a0 \u00a0 \u00a0 \u00a0 \u00a0 \u2022 \u8cfc\u7269\u512a\u60e0\n\u00a0 \u00a0 \u00a0 \u00a0 \u00a0 \u2022 \u91ab\u7642\u798f\u5229\n\u00a0 \u00a0 \u00a0 \u00a0 \u00a0 \u2022 \u7259\u79d1\u4fdd\u5065\n\u00a0 \u00a0 \u00a0 \u00a0 \u00a0 \u2022 \u5728\u8077\u5c08\u696d\u57f9\u8a13\n\u00a0 \u00a0 \u00a0 \u00a0 \u00a0 \u2022 \u5b8c\u5584\u6649\u5347\u7a7a\u9593\n\u00a0 \u00a0 \u00a0 \u00a0 \u00a0 \u2022 \u6bcf\u67087\u5929\u4f8b\u5047\u3001\u6bcf\u5e7412\u5929\u516c\u773e\u5047\u671f\u88dc\u5047\u300112\u5929\u5e74\u5047(\u53e6\u52a03\u5929\u984d\u5916\u734e\u8cde\u5e74\u5047)\n\u00a0 \u00a0 \u00a0 \u00a0 \u00a0 \u2022 \u6bcf\u59299\u5c0f\u6642\u5de5\u4f5c (\u5305\u62ec\u81b3\u98df\u6642\u9593)\n\n\nIf you're interested in this role, please CLICK HERE\u00a0or\u00a0click 'Apply Now' to apply the position via Adecco website with your CV, or if you would like to have a further discussion about this role, please contact Miss Wong+852 2899 6122 .\n\n\u5982\u60a8\u5c0d\u6b64\u8077\u4f4d\u611f\u8208\u8da3\uff0c\u8acb\u9ede\u64ca\u201cApply Now\u201d\u900f\u904eAdecco\u7db2\u7ad9\u4e0a\u8f09\u60a8\u7684\u7684\u500b\u4eba\u5c65\u6b77\u7533\u8acb\u6b64\u8077\u4f4d\uff0c\u82e5\u60a8\u5c0d\u6b64\u8077\u4f4d\u6709\u4efb\u4f55\u67e5\u8a62\u4ea6\u53ef\u81f4\u96fb +852 2899 6122 \u8207\u738b\u5c0f\u59d0\u806f\u7d61\u3002\n\nPlease note that only short listed candidates will be notified. All information gathered will be treated in strict confidence and solely used for recruitment purposes", "employment_types": ["Full Time"], "selling_points": [], "locations": ["Not Specified"], "categories": ["Sales, CS & Business Devpt", "Customer Service - Manager", "Others"], "post_time": "2022-01-17T06:37:11Z", "salary": {"currency": null, "max": null, "min": null, "period": "monthly", "term": null}, "salary_visible": false, "title_keywords": ["executive"], "responsibilities": [], "requirements": {"degrees": [], "majors": [], "languages": [], "language_level": [], "hard_skills": [], "soft_skills": ["interested in", "confidence"], "languages_combined": []}, "experience_required": {"duration": [], "field": []}}, {"job_id": "100003009054273", "location_code": "hk", "company": "Descente China Investment Limited", "job_title": "Senior Training Officer", "description": "\u70ba\u7968\u52d9\u4e2d\u5fc3\u548c\u6e9c\u51b0\u978b\u51fa\u79df\u6ac3\u6aaf\u63d0\u4f9b\u512a\u8cea\u7684\u5ba2\u6236\u670d\u52d9\n\u63a7\u5236\u4eba\u6d41\u3001\u7dad\u6301\u51b0\u9762\u5167\u5916\u7684\u79e9\u5e8f\n\u5354\u52a9\u7dad\u4fee\u53ca\u4fdd\u990a\u5728\u51b0\u5834\u5167\u7684\u8a2d\u65bd\u53ca\u6e9c\u51b0\u978b\n\u8655\u7406\u79c1\u4eba\u6d3e\u5c0d\u53ca\u79df\u7528\u6e9c\u51b0\u5834\u7684\u67e5\u8a62\n\u8655\u7406\u6703\u54e1\u62db\u52df\u548c\u8a3b\u518a\n\u5354\u52a9\u7d44\u7e54/\u71df\u904b\u6e9c\u51b0\u5834\u4e2d\u7684\u6240\u6709\u6d3b\u52d5\n\u5c65\u884c\u7531\u516c\u53f8\u5206\u914d\u7684\u5176\u4ed6\u8077\u8cac\nProvide quality customer service in ticketing and skate rental counter;\nCrowd management and maintenance order on and off ice in the ice rink ;\nAssist in repairing and maintaining the facilities and skates in the ice rink;\nHandle private party and rink rental enquiry;\nHandle registration and membership recruitment;\nAssist in organising/ operating all the events and programs in the rink;\nPerform other duties as assigned.\n\n\u9700\u5177\u5099\u4ee5\u4e0b\u689d\u4ef6Requirements:\n\n\u826f\u597d\u7684\u6e9d\u901a\u80fd\u529b\u53ca\u6280\u5de7\n\u5c0d\u670d\u52d9\u5145\u6eff\u71b1\u60c5\u548c\u9858\u610f\u5b78\u7fd2\n\u80fd\u4ee5\u6d41\u5229\u7684\u82f1\u8a9e\u3001\u5ee3\u6771\u8a71\u548c\u666e\u901a\u8a71\u5c0d\u7b54\u53ca\u5177\u6709\u4e00\u822c\u4e2d\u6587\u5beb\u4f5c\u80fd\u529b\n\u5982\u6709\u6e9c\u51b0\u5834\u3001\u5ba2\u6236\u670d\u52d9\u6216\u6703\u6240/\u4ff1\u6a02\u90e8\u76f8\u95dc\u5de5\u4f5c\u7d93\u9a57\u8005\u512a\u5148\n\u6709\u9700\u8981\u5728\u5468\u672b\u548c\u7bc0\u65e5\u671f\u9593\u5de5\u4f5c\nGood communication and personnel skill\nPassion to serve and willing to learn\nGood command of spoken and written English, Cantonese and Mandarin\nRelevant working experiences in ice rink, customer service or recreational clubs is an advantage\nWorking on weekends and festive seasons is required\n\n\u5de5\u4f5c\u5730\u9ede: \u65b0\u754c\u5c07\u8ecd\u6fb3\u65e5\u51fa\u5eb7\u57ce\u00a0\n\n\u6709\u8208\u8da3\u7684\u4eba\u58eb\uff0c\u8acb\u6309\"APPLY NOW\"\u905e\u4ea4\u60a8\u7684\u7c21\u6b77\u4ee5\u53ca\u9810\u671f\u85aa\u91d1\n\nWorking location: Lohas Park, Tseung Kwan O, New Territories\n\nInterested parties, please send your full resume in PDF format with present and expected by clicking the below \"Apply now\" button.\n\n(Personal data collected will be used for recruitment purposes only)\n", "employment_types": ["Full Time", "Permanent"], "selling_points": ["Retail Training", "Bachelor\u2019s Degree", "6 years\u2019 relevant working experience"], "locations": ["Kowloon Bay"], "categories": ["Admin & HR", "Training & Development", "Sales, CS & Business Devpt", "Others"], "post_time": "2022-01-17T09:00:19Z", "salary": {"currency": null, "max": null, "min": null, "period": "monthly", "term": null}, "salary_visible": false, "title_keywords": ["officer"], "responsibilities": ["management", "perform other duties", "maintaining", "maintenance", "quality", "communication", "customer service", "recruitment"], "requirements": {"degrees": [], "majors": [], "languages": ["cantonese", "english", "mandarin"], "language_level": ["good command"], "hard_skills": ["maintenance"], "soft_skills": ["communication", "customer service", "willing to learn"], "languages_combined": [{"language": "cantonese", "language_level": ["good command"]}, {"language": "english", "language_level": ["good command"]}, {"language": "mandarin", "language_level": ["good command"]}]}, "experience_required": {"duration": [], "field": ["customer service"]}}, {"job_id": "100003009056145", "location_code": "hk", "company": "PHC Medical Diagnostic Centre Limited", "job_title": "Sales Manager", "description": "Responsibilities:\n\nReport to the Training Manager to identify training needs of store operations\u00a0for designing the annual training plan and delivering training to drive for business result.\nDesign and deliver in-house shop training programs for all frontline staff levels\u00a0to enhance and polish shop sales\u2019 skill, sales and product knowledge, and attitude covering Product, Service, Business, and drive the culture.\nMonitor the sales performance to ensure that the deliverables are aligned with the training goals.\u00a0\nProvide performance feedback on shop staff to facilitate on-going staff performance review.\nTo align with the headquarter to implement and executive the group training programs/on-line training modules into a local practice such as classroom training, shop visit, face to face demonstration and case sharing.\nConduct the sales orientation to all retail new hires.\nOrganize various projects / events to align with the headquarter and corporate brand building.\nHandle all training related logistics, materials preparation, training evaluation, updating related records & logistics for the team.\nMonitor the shop training budget and actual expense.\n\nRequirements:\n\nBachelor\u2019s Degree in Training & Development, Human Resources Management or related disciplines.\nMinimum 6 years of solid training delivery experience preferably in\u00a0retail, ladies fashion, sports industry. \u00a0\nGood understanding of retail operational details is an advantage.\nGood attitude, positive, energetic and proactive for problem-solving & detailed-minded\nStrong presentation and interpersonal skills.\nExcellent planning and organizing skills.\nProficient in using MS Office, Excel, Chinese Word Processing, preferably with knowledge in Video shooting/editing experience.\nGood command of both spoken and written English and Chinese (Cantonese and Putonghua).\nOccasional travel is required.", "employment_types": ["Full Time", "Permanent"], "selling_points": [], "locations": ["Kwai Hing"], "categories": ["Sales, CS & Business Devpt", "Call Centre", "Others"], "post_time": "2022-01-18T03:24:07Z", "salary": {"currency": null, "max": null, "min": null, "period": "monthly", "term": null}, "salary_visible": false, "title_keywords": ["sales manager"], "responsibilities": ["evaluation", "operations", "sales performance", "review", "monitor", "budget", "design", "logistics", "plan", "designing", "report"], "requirements": {"degrees": ["degree", "bachelor"], "majors": ["related disciplines"], "languages": ["cantonese", "putonghua", "english", "chinese"], "language_level": ["good command", "proficient"], "hard_skills": ["excel", "problem-solving", "chinese word processing", "ms office"], "soft_skills": ["proactive", "problem-solving", "interpersonal skills", "energetic", "presentation", "positive", "detailed"], "languages_combined": [{"language": "cantonese", "language_level": ["good command"]}, {"language": "putonghua", "language_level": ["good command"]}, {"language": "english", "language_level": ["good command"]}, {"language": "chinese", "language_level": ["good command", "proficient"]}]}, "experience_required": {"duration": ["minimum 6 years"], "field": ["video shooting", "editing", "retail", "training"]}}, {"job_id": "100003009055146", "location_code": "hk", "company": "Ocean Network Express (East Asia) Limited", "job_title": "Manager - CRM Training (East Asia Region)", "description": "Supervisor\u00a0\u5e97\u92ea\u4e3b\u7ba1\u00a0\n\n\u00a0\u00a0\u00a0\u00a0\u00a0\u00a0\u00a0\u00a0\u00a0\u7dad\u6301\u5e97\u8216\u65e5\u5e38\u904b\u4f5c\n\u00a0\u00a0\u00a0\u00a0\u00a0\u00a0\u00a0\u00a0\u00a0\u57f7\u884c\u8a08\u5283\u4ee5\u63a8\u52d5\u95dc\u9375\u7e3e\u6548\u6307\u6a19\u4ee5\u6700\u5927\u9650\u5ea6\u5730\u63d0\u9ad8\u76c8\u5229\u80fd\u529b\n\u00a0\u00a0\u00a0\u00a0\u00a0\u00a0\u00a0\u00a0\u00a0\u6307\u5c0e\u548c\u6fc0\u52f5\u60a8\u7684\u5718\u968a\u4ee5\u6fc0\u767c\u6700\u4f73\u7e3e\u6548\u548c\u5353\u8d8a\u7684\u5ba2\u6236\u9ad4\u9a57\n\u00a0\u00a0\u00a0\u00a0\u00a0\u00a0\u00a0\u00a0\u00a0\u8a2d\u5b9a\u53ca\u9054\u6210\u516c\u53f8\u5b9a\u4e0b\u7684\u5718\u968a\u92b7\u552e\u76ee\u6a19\u3001\u500b\u4ebaKPI\n\u00a0\u00a0\u00a0\u00a0\u00a0\u00a0\u00a0\u00a0\u00a0\u5b9a\u671f\u8a2d\u5b9a\u53ca\u8abf\u6574\u5e97\u92ea\u7b56\u7565\n\u00a0\u00a0\u00a0\u00a0\u00a0\u00a0\u00a0\u00a0\u00a0\u7c21\u5831\n\u00a0\u00a0\u00a0\u00a0\u00a0\u00a0\u00a0\u00a0\u00a0\u6709\u6548\u63a7\u5236\u5e97\u92ea\u6210\u672c\n\u00a0\u00a0\u00a0\u00a0\u00a0\u00a0\u00a0\u00a0\u00a0\u5b9a\u671f\u958b\u6703\u6aa2\u8a0e\u53ca\u532f\u5831\u5e97\u92ea\u696d\u7e3e\n\u00a0\u00a0\u00a0\u00a0\u00a0\u00a0\u00a0\u00a0\u00a0\u8ca8\u5834\u53ca\u5009\u5b58\u7ba1\u7406\u4ee5\u78ba\u4fdd\u5b58\u8ca8\u5145\u8db3\n\u00a0\u00a0\u00a0\u00a0\u00a0\u00a0\u00a0\u00a0\u00a0\u54e1\u5de5\u66f4\u8868\u5b89\u6392\n\nSales\u00a0\u552e\u8ca8\u54e1\u00a0/ Senior Sales\u00a0\u8cc7\u6df1\u552e\u8ca8\u54e1\n\n\u00a0\u00a0\u00a0\u00a0\u00a0\u00a0\u00a0\u00a0\u00a0\u7dad\u6301\u5e97\u8216\u65e5\u5e38\u904b\u4f5c\u3001\u63d0\u4f9b\u512a\u8cea\u9867\u5ba2\u670d\u52d9\n\u00a0\u00a0\u00a0\u00a0\u00a0\u00a0\u00a0\u00a0\u00a0\u5e97\u5167\u7522\u54c1\u92b7\u552e\u3001\u70ba\u5ba2\u4eba\u4ecb\u7d39\u5408\u9069\u7684\u7522\u54c1\n\u00a0\u00a0\u00a0\u00a0\u00a0\u00a0\u00a0\u00a0\u00a0\u5354\u52a9\u9054\u6210\u516c\u53f8\u5b9a\u4e0b\u7684\u5718\u968a\u92b7\u552e\u76ee\u6a19\u3001\u500b\u4ebaKPI\n\u00a0\u00a0\u00a0\u00a0\u00a0\u00a0\u00a0\u00a0\u00a0\u8ca8\u5834\u53ca\u5009\u5b58\u7ba1\u7406\u4ee5\u78ba\u4fdd\u5b58\u8ca8\u5145\u8db3\n\n\u5de5\u4f5c\u8981\u6c42:\n\n\u00a0\u00a0\u00a0\u00a0\u00a0\u00a0\u00a0\u00a0\u00a0\u6d41\u5229\u5ee3\u6771\u8a71\u53ca\u666e\u901a\u8a71\uff0c\u5546\u696d\u7528\u82f1\u8a9e\n\u00a0\u00a0\u00a0\u00a0\u00a0\u00a0\u00a0\u00a0\u00a0\u5e97\u92ea\u7d93\u7406\u00a05\u5e74\u6216\u4ee5\u4e0a\u96f6\u552e\u7ba1\u7406\u7d93\u9a57\uff0c\u8cc7\u6df1\u552e\u8ca8\u54e12\u5e74\u6216\u4ee5\u4e0a\u96f6\u552e\u7d93\u9a57\u00a0\uff08\u6709\u904b\u52d5\u54c1\u724c\u7d93\u9a57\u512a\u5148\u8003\u616e\uff09\n\u00a0\u00a0\u00a0\u00a0\u00a0\u00a0\u00a0\u00a0\u00a0\u6b61\u8fce\u6027\u683c\u9032\u53d6\uff0c\u62b1\u6709\u6a02\u65bc\u5b78\u7fd2\u5fc3\u614b\u8005\uff0c\u7d93\u9a57\u4e0d\u62d8\n\u00a0\u00a0\u00a0\u00a0\u00a0\u00a0\u00a0\u00a0\u00a0\u5c0d\u6642\u88dd\u6709\u57fa\u672c\u8a8d\u8b58\n\u00a0\u00a0\u00a0\u00a0\u00a0\u00a0\u00a0\u00a0\u00a0\u63d0\u4f9b\u89aa\u5584\u6709\u79ae\u7684\u9867\u5ba2\u670d\u52d9\n\n\u798f\u5229\uff1a\n\n\u00a0\u00a0\u00a0\u00a0\u00a0\u00a0\u00a0\u00a0\u00a0\u512a\u539a\u5e95\u85aa\n\u00a0\u00a0\u00a0\u00a0\u00a0\u00a0\u00a0\u00a0\u00a0\u8c50\u539a\u4f63\u91d1\n\u00a0\u00a0\u00a0\u00a0\u00a0\u00a0\u00a0\u00a0\u00a0\u516c\u4f63\u200b\n\u00a0\u00a0\u00a0\u00a0\u00a0\u00a0\u00a0\u00a0\u00a0\u82b1\u7d05\n\u00a0\u00a0\u00a0\u00a0\u00a0\u00a0\u00a0\u00a0\u00a0\u6709\u85aa\u5e74\u5047\n\u00a0\u00a0\u00a0\u00a0\u00a0\u00a0\u00a0\u00a0\u00a0\u91ab\u7642\u53ca\u7259\u79d1\u6d25\u8cbc\n\u00a0\u00a0\u00a0\u00a0\u00a0\u00a0\u00a0\u00a0\u00a0\u826f\u597d\u7684\u6649\u5347\u6a5f\u6703\n\u00a0\u00a0\u00a0\u00a0\u00a0\u00a0\u00a0\u00a0\u00a0\u5b8c\u5584\u5de5\u4f5c\u57f9\u8a13\n\nApply for this job:\n\nInterested candidate please CLICK apply button to apply online or send your resume in MS word format to Fillture Group Limited\n\nFor more information please contact\u00a0Danvis Lau\u00a0+852 2814 9388.\n\nPlease note that only shortlisted candidate will be notified. All information will be treated in strict confidence and solely used for recruitment purposes.", "employment_types": ["Full Time", "Permanent"], "selling_points": ["Responsible for CRM Training", "Regional exposure\u00a0in East Asia", "Agility workplace, collaborative & fun activities"], "locations": ["Kwun Tong"], "categories": ["Admin & HR", "Training & Development", "Transportation & Logistics", "Shipping", "Sales, CS & Business Devpt", "Others"], "post_time": "2022-01-18T01:27:39Z", "salary": {"currency": null, "max": null, "min": null, "period": "monthly", "term": null}, "salary_visible": false, "title_keywords": ["manager"], "responsibilities": ["recruitment", "contact"], "requirements": {"degrees": [], "majors": [], "languages": [], "language_level": [], "hard_skills": ["ms word"], "soft_skills": ["confidence"], "languages_combined": []}, "experience_required": {"duration": [], "field": []}}, {"job_id": "100003009054388", "location_code": "hk", "company": "Superpower Pumping Engineering Co., Ltd.", "job_title": "Sales Coordinator", "description": "Responsibilities:\n\nVisit customers and reporting to management team in a regular basis;\nPromote services to clients and customers, network will be an advantage;\nCommunicate and reflect customer requirements;\nWork with the team to achieve sales targets;\nUpdate customer\u2019s status and market information to management team, etc.\nAny other duties as assigned by the Supervisor/ Manager of the Employer or other associated or subsidiary company(ies) of the Employer.\n\n\u00a0Qualification\n\nBachelor\u2019s Degree in Science or Biology related discipline is basic requirement, Master Degree or above preferred\nCandidate with more experience will be considered as Senior Sales Representative or Sales Manage\nGood interpersonal, presentation and communication skills, and teamwork\nMeticulous, well-organized, responsible, and self-motivated.\nProficiency in written and spoken English & Chinese (both Cantonese and Mandarin)", "employment_types": ["Full Time", "Permanent"], "selling_points": ["Provide support to Sales and Marketing team", "Handle customer enquiries", "Prepare quotations and arrange goods delivery"], "locations": ["Cheung Sha Wan"], "categories": ["Sales, CS & Business Devpt", "Business Development", "Sales - Sales Management", "Others"], "post_time": "2022-01-17T09:20:18Z", "salary": {"currency": null, "max": null, "min": null, "period": "monthly", "term": null}, "salary_visible": false, "title_keywords": ["sales coordinator"], "responsibilities": ["reporting", "management team"], "requirements": {"degrees": ["degree or above", "degree", "bachelor", "master"], "majors": ["science", "biology"], "languages": ["cantonese", "english", "chinese", "mandarin"], "language_level": ["proficiency"], "hard_skills": ["basic"], "soft_skills": ["communication skills", "meticulous", "self-motivated", "responsible", "teamwork", "well-organized", "interpersonal", "presentation"], "languages_combined": [{"language": "cantonese", "language_level": ["proficiency"]}, {"language": "english", "language_level": ["proficiency"]}, {"language": "chinese", "language_level": ["proficiency"]}, {"language": "mandarin", "language_level": ["proficiency"]}]}, "experience_required": {"duration": [], "field": []}}, {"job_id": "100003009054447", "location_code": "hk", "company": "Cityline (Hong Kong) Limited", "job_title": "Customer Services Officer (3-month contract)", "description": "Responsibilities:\n\nSupport and deliver the Training Delivery Guide in Customer Relationship Management (CRM) Training;\nCollaborate with Regional, Country Sales, and Customer Service teams to determine and evaluate their training requirements and effectiveness, as well as generate and distribute reports;\nParticipate in the User Acceptance Testing (UAT) for Customer Relationship Management (CRM) and assist in guiding designated users among the region.\n\n\u00a0Requirements:\n\nBachelor Degree in any discipline, major in shipping, logistics or business management is highly preferred;\nMinimum 10 years of relevant experience;\nStrong interpersonal skills such as communication and listening;\nTechnical skills including a competent understanding of customer service department workflows;\nExperience in training or teaching is a must;\nWillingness to learn and keep improving the knowledge;\nKnowledge in CRM system (preferably Salesforce) is an advantage but not a mandatory requirement;\nFamiliar with Microsoft Office or Google suite, e.g. Word, Excel, PowerPoint, G-sheets, G-Docs, G-Slides;\nGood command in spoken and written English and Chinese, Mandarin is a plus.", "employment_types": ["Contract"], "selling_points": ["5 day-work (Monday - Friday)", "Fixed shift (9 hours per shift)", "Answering & telephone enquiries"], "locations": ["Kwun Tong"], "categories": ["Sales, CS & Business Devpt", "Call Centre", "Others"], "post_time": "2022-01-17T09:35:06Z", "salary": {"currency": null, "max": null, "min": null, "period": "monthly", "term": null}, "salary_visible": false, "title_keywords": ["customer services officer"], "responsibilities": ["collaborate with", "management", "uat", "teams", "testing", "evaluate", "customer service", "reports"], "requirements": {"degrees": ["degree", "bachelor"], "majors": ["business"], "languages": ["english", "chinese", "mandarin"], "language_level": ["good command"], "hard_skills": ["business management", "excel", "plus", "salesforce", "microsoft office", "word", "powerpoint"], "soft_skills": ["competent", "communication", "customer service", "interpersonal skills", "technical skills"], "languages_combined": [{"language": "english", "language_level": ["good command"]}, {"language": "chinese", "language_level": ["good command"]}, {"language": "mandarin", "language_level": ["good command"]}]}, "experience_required": {"duration": ["minimum 10 years"], "field": ["teaching", "relevant experience", "training"]}}, {"job_id": "100003009055635", "location_code": "hk", "company": "The Legend Financial Consultancy", "job_title": "Customer Service Coordinator/ Customer Service Executive (welcome fresh graduate) CSO 0118", "description": "Job Responsibilities:\nProvide support to Sales and Marketing team\nHandle customer enquiries\nPrepare quotations and arrange goods delivery\n\nJob Requirements:\n\nForm 6 or above\nMinimum 2 years' relevant working experience\nProficient in PC applications is highly preferred\nGood initiative, courteous, well-organized, independent, pleasant and good communication skills\nImmediate available is preferred\n\nGood remuneration and attractive benefits will be offered to the right candidate. Interested parties please send full resume (MS Word Format) with expected salary and date of availability via \"APPLY NOW\" or by post to: The Human Resources and Administration Department \u2013 Recruitment & Selection Section, Superpower Pumping Engineering Co., Ltd, 16/F, World Tech Centre, 95 How Ming Street, Kwun Tong, Kowloon. Please quote reference number on letter.\u00a0\n\nWe are an Equal Opportunity Employer. Personal data will be kept strict confidence and used for recruitment-related purpose only.", "employment_types": ["Full Time", "Part Time", "Permanent", "Contract"], "selling_points": [], "locations": ["Not Specified"], "categories": ["Sales, CS & Business Devpt", "Customer Service - Supervisor / Officer", "Others", "Management", "Management Trainee"], "post_time": "2022-01-18T02:48:59Z", "salary": {"currency": "HKD", "max": 24999, "min": 14000, "period": "monthly", "term": null}, "salary_visible": true, "title_keywords": ["customer service executive", "customer service coordinator"], "responsibilities": ["provide support", "handle customer enquiries"], "requirements": {"degrees": [], "majors": [], "languages": [], "language_level": [], "hard_skills": ["pc applications"], "soft_skills": ["communication skills", "courteous", "independent", "well-organized", "pleasant", "initiative"], "languages_combined": []}, "experience_required": {"duration": ["minimum 2 years"], "field": ["relevant working experience"]}}, {"job_id": "100003009056732", "location_code": "hk", "company": "Educational Publishing House, Limited", "job_title": "Administrative Assistant (Preschool sales team) \u92b7\u552e\u884c\u653f\u52a9\u7406", "description": "Responsibilities:\n\nProvides administrative and clerical supports to Preschool Sales Team\nPrepares presentation and promotion materials\nSupports sales activities, i.e. taking meeting minutes for weekly sales meeting, updating customer service database, coordinating sample order and delivery arrangement\nOther ad hoc duties as assigned\n\nRequirements:\n\nDSE or above\n1-2 years experience in office support\u00a0\nSelf-motivated, good team player with proactive working attitude\nGood communication skills and detail-minded\nGood in MS Office including Word, Excel, PowerPoint and Chinese typing skills\n\nWe offer excellent career development opportunities to unleash your potential, competitive remuneration package including a 5-day work week, comprehensive group medical insurance and dental scheme, discretionary bonus and staff purchasing discount, etc.\n\nInterested parties please apply with your full resume stating present and expected salary\u00a0by clicking\u00a0\"Apply Now\". \u00a0Only short-listed candidates will be contacted.\n\nYou are welcome to visit our\u00a0websites\u00a0to know more about us:\u00a0ephhk.popularworldhk.com\u00a0/\u00a0www.popular.com.hk\n\nPersonal data provided by job applicants will be kept strictly confidential and used for employment related purpose.\u00a0 Only short-listed candidates will be contacted.", "employment_types": ["Full Time", "Permanent"], "selling_points": ["5 day work, bonus", "Medical & dental, staff purchase discount", "Assist in daily administrative operation"], "locations": ["Tsuen Wan Area"], "categories": ["Admin & HR", "Clerical / Admin Staff", "Sales, CS & Business Devpt", "Others", "Sales Administration"], "post_time": "2022-01-18T06:06:00Z", "salary": {"currency": null, "max": null, "min": null, "period": "monthly", "term": null}, "salary_visible": false, "title_keywords": ["administrative assistant", "sales"], "responsibilities": ["ad hoc duties", "sales activities", "customer service", "sales team", "database"], "requirements": {"degrees": ["dse"], "majors": [], "languages": ["chinese"], "language_level": ["good"], "hard_skills": ["excel", "typing", "word", "powerpoint", "scheme", "ms office"], "soft_skills": ["detail-minded", "communication skills", "good team player", "self-motivated", "comprehensive", "proactive"], "languages_combined": [{"language": "chinese", "language_level": ["good"]}]}, "experience_required": {"duration": ["1-2 years"], "field": []}}, {"job_id": "100003009056646", "location_code": "hk", "company": "LOHAS Rink Limited", "job_title": "\u6e9c\u51b0\u5834\u5834\u52d9\u54e1 (\u5168\u8077)  Marshal /Rink Assistant (Full-time)", "description": "\u70ba\u7968\u52d9\u4e2d\u5fc3\u548c\u6e9c\u51b0\u978b\u51fa\u79df\u6ac3\u6aaf\u63d0\u4f9b\u512a\u8cea\u7684\u5ba2\u6236\u670d\u52d9\n\u63a7\u5236\u4eba\u6d41\u3001\u7dad\u6301\u51b0\u9762\u5167\u5916\u7684\u79e9\u5e8f\n\u5354\u52a9\u7dad\u4fee\u53ca\u4fdd\u990a\u5728\u51b0\u5834\u5167\u7684\u8a2d\u65bd\u53ca\u6e9c\u51b0\u978b\n\u8655\u7406\u79c1\u4eba\u6d3e\u5c0d\u53ca\u79df\u7528\u6e9c\u51b0\u5834\u7684\u67e5\u8a62\n\u8655\u7406\u6703\u54e1\u62db\u52df\u548c\u8a3b\u518a\n\u5354\u52a9\u7d44\u7e54/\u71df\u904b\u6e9c\u51b0\u5834\u4e2d\u7684\u6240\u6709\u6d3b\u52d5\n\u5c65\u884c\u7531\u516c\u53f8\u5206\u914d\u7684\u5176\u4ed6\u8077\u8cac\nProvide quality customer service in ticketing and skate rental counter;\nCrowd management and maintenance order on and off ice in the ice rink ;\nAssist in repairing and maintaining the facilities and skates in the ice rink;\nHandle private party and rink rental enquiry;\nHandle registration and membership recruitment;\nAssist in organising/ operating all the events and programs in the rink;\nPerform other duties as assigned.\n\n\u9700\u5177\u5099\u4ee5\u4e0b\u689d\u4ef6Requirements:\n\n\u826f\u597d\u7684\u6e9d\u901a\u80fd\u529b\u53ca\u6280\u5de7\n\u5c0d\u670d\u52d9\u5145\u6eff\u71b1\u60c5\u548c\u9858\u610f\u5b78\u7fd2\n\u80fd\u4ee5\u6d41\u5229\u7684\u82f1\u8a9e\u3001\u5ee3\u6771\u8a71\u548c\u666e\u901a\u8a71\u5c0d\u7b54\u53ca\u5177\u6709\u4e00\u822c\u4e2d\u6587\u5beb\u4f5c\u80fd\u529b\n\u5982\u6709\u6e9c\u51b0\u5834\u3001\u5ba2\u6236\u670d\u52d9\u6216\u6703\u6240/\u4ff1\u6a02\u90e8\u76f8\u95dc\u5de5\u4f5c\u7d93\u9a57\u8005\u512a\u5148\n\u6709\u9700\u8981\u5728\u5468\u672b\u548c\u7bc0\u65e5\u671f\u9593\u5de5\u4f5c\nGood communication and personnel skill\nPassion to serve and willing to learn\nGood command of spoken and written English, Cantonese and Mandarin\nRelevant working experiences in ice rink, customer service or recreational clubs is an advantage\nWorking on weekends and festive seasons is required\n\n\u5de5\u4f5c\u5730\u9ede: \u65b0\u754c\u5c07\u8ecd\u6fb3\u65e5\u51fa\u5eb7\u57ce\u00a0\n\n\u6709\u8208\u8da3\u7684\u4eba\u58eb\uff0c\u8acb\u6309\"APPLY NOW\"\u905e\u4ea4\u60a8\u7684\u7c21\u6b77\u4ee5\u53ca\u9810\u671f\u85aa\u91d1\n\nWorking location: Lohas Park, Tseung Kwan O, New Territories\n\nInterested parties, please send your full resume in PDF format with present and expected by clicking the below \"Apply now\" button.\n\n(Personal data collected will be used for recruitment purposes only)\n", "employment_types": ["Full Time"], "selling_points": [], "locations": ["Tseung Kwan O"], "categories": ["Sales, CS & Business Devpt", "Others", "Others", "Student / Fresh Graduate / No Experience"], "post_time": "2022-01-18T05:27:56Z", "salary": {"currency": null, "max": null, "min": null, "period": "monthly", "term": null}, "salary_visible": false, "title_keywords": ["assistant"], "responsibilities": ["management", "perform other duties", "maintaining", "maintenance", "quality", "communication", "customer service", "recruitment"], "requirements": {"degrees": [], "majors": [], "languages": ["cantonese", "english", "mandarin"], "language_level": ["good command"], "hard_skills": ["maintenance"], "soft_skills": ["communication", "customer service", "willing to learn"], "languages_combined": [{"language": "cantonese", "language_level": ["good command"]}, {"language": "english", "language_level": ["good command"]}, {"language": "mandarin", "language_level": ["good command"]}]}, "experience_required": {"duration": [], "field": ["customer service"]}}, {"job_id": "100003009056718", "location_code": "hk", "company": "Fillture Group Limited", "job_title": "(\u6f6e\u6d41\u6642\u88dd\u96c6\u5718)\u53ef\u9078\u65d7\u4e0b\u670d\u88dd/\u9996\u98fe/\u6236\u5916\u7528\u54c1\u54c1\u724c  - \u4e3b\u7ba1/\u9ad8\u7d1a\u92b7\u552e\u54e1/\u92b7\u552e\u54e1 Supervisor / Senior Sales / Sales Associate", "description": "Supervisor\u00a0\u5e97\u92ea\u4e3b\u7ba1\u00a0\n\n\u00a0\u00a0\u00a0\u00a0\u00a0\u00a0\u00a0\u00a0\u00a0\u7dad\u6301\u5e97\u8216\u65e5\u5e38\u904b\u4f5c\n\u00a0\u00a0\u00a0\u00a0\u00a0\u00a0\u00a0\u00a0\u00a0\u57f7\u884c\u8a08\u5283\u4ee5\u63a8\u52d5\u95dc\u9375\u7e3e\u6548\u6307\u6a19\u4ee5\u6700\u5927\u9650\u5ea6\u5730\u63d0\u9ad8\u76c8\u5229\u80fd\u529b\n\u00a0\u00a0\u00a0\u00a0\u00a0\u00a0\u00a0\u00a0\u00a0\u6307\u5c0e\u548c\u6fc0\u52f5\u60a8\u7684\u5718\u968a\u4ee5\u6fc0\u767c\u6700\u4f73\u7e3e\u6548\u548c\u5353\u8d8a\u7684\u5ba2\u6236\u9ad4\u9a57\n\u00a0\u00a0\u00a0\u00a0\u00a0\u00a0\u00a0\u00a0\u00a0\u8a2d\u5b9a\u53ca\u9054\u6210\u516c\u53f8\u5b9a\u4e0b\u7684\u5718\u968a\u92b7\u552e\u76ee\u6a19\u3001\u500b\u4ebaKPI\n\u00a0\u00a0\u00a0\u00a0\u00a0\u00a0\u00a0\u00a0\u00a0\u5b9a\u671f\u8a2d\u5b9a\u53ca\u8abf\u6574\u5e97\u92ea\u7b56\u7565\n\u00a0\u00a0\u00a0\u00a0\u00a0\u00a0\u00a0\u00a0\u00a0\u7c21\u5831\n\u00a0\u00a0\u00a0\u00a0\u00a0\u00a0\u00a0\u00a0\u00a0\u6709\u6548\u63a7\u5236\u5e97\u92ea\u6210\u672c\n\u00a0\u00a0\u00a0\u00a0\u00a0\u00a0\u00a0\u00a0\u00a0\u5b9a\u671f\u958b\u6703\u6aa2\u8a0e\u53ca\u532f\u5831\u5e97\u92ea\u696d\u7e3e\n\u00a0\u00a0\u00a0\u00a0\u00a0\u00a0\u00a0\u00a0\u00a0\u8ca8\u5834\u53ca\u5009\u5b58\u7ba1\u7406\u4ee5\u78ba\u4fdd\u5b58\u8ca8\u5145\u8db3\n\u00a0\u00a0\u00a0\u00a0\u00a0\u00a0\u00a0\u00a0\u00a0\u54e1\u5de5\u66f4\u8868\u5b89\u6392\n\nSales\u00a0\u552e\u8ca8\u54e1\u00a0/ Senior Sales\u00a0\u8cc7\u6df1\u552e\u8ca8\u54e1\n\n\u00a0\u00a0\u00a0\u00a0\u00a0\u00a0\u00a0\u00a0\u00a0\u7dad\u6301\u5e97\u8216\u65e5\u5e38\u904b\u4f5c\u3001\u63d0\u4f9b\u512a\u8cea\u9867\u5ba2\u670d\u52d9\n\u00a0\u00a0\u00a0\u00a0\u00a0\u00a0\u00a0\u00a0\u00a0\u5e97\u5167\u7522\u54c1\u92b7\u552e\u3001\u70ba\u5ba2\u4eba\u4ecb\u7d39\u5408\u9069\u7684\u7522\u54c1\n\u00a0\u00a0\u00a0\u00a0\u00a0\u00a0\u00a0\u00a0\u00a0\u5354\u52a9\u9054\u6210\u516c\u53f8\u5b9a\u4e0b\u7684\u5718\u968a\u92b7\u552e\u76ee\u6a19\u3001\u500b\u4ebaKPI\n\u00a0\u00a0\u00a0\u00a0\u00a0\u00a0\u00a0\u00a0\u00a0\u8ca8\u5834\u53ca\u5009\u5b58\u7ba1\u7406\u4ee5\u78ba\u4fdd\u5b58\u8ca8\u5145\u8db3\n\n\u5de5\u4f5c\u8981\u6c42:\n\n\u00a0\u00a0\u00a0\u00a0\u00a0\u00a0\u00a0\u00a0\u00a0\u6d41\u5229\u5ee3\u6771\u8a71\u53ca\u666e\u901a\u8a71\uff0c\u5546\u696d\u7528\u82f1\u8a9e\n\u00a0\u00a0\u00a0\u00a0\u00a0\u00a0\u00a0\u00a0\u00a0\u5e97\u92ea\u7d93\u7406\u00a05\u5e74\u6216\u4ee5\u4e0a\u96f6\u552e\u7ba1\u7406\u7d93\u9a57\uff0c\u8cc7\u6df1\u552e\u8ca8\u54e12\u5e74\u6216\u4ee5\u4e0a\u96f6\u552e\u7d93\u9a57\u00a0\uff08\u6709\u904b\u52d5\u54c1\u724c\u7d93\u9a57\u512a\u5148\u8003\u616e\uff09\n\u00a0\u00a0\u00a0\u00a0\u00a0\u00a0\u00a0\u00a0\u00a0\u6b61\u8fce\u6027\u683c\u9032\u53d6\uff0c\u62b1\u6709\u6a02\u65bc\u5b78\u7fd2\u5fc3\u614b\u8005\uff0c\u7d93\u9a57\u4e0d\u62d8\n\u00a0\u00a0\u00a0\u00a0\u00a0\u00a0\u00a0\u00a0\u00a0\u5c0d\u6642\u88dd\u6709\u57fa\u672c\u8a8d\u8b58\n\u00a0\u00a0\u00a0\u00a0\u00a0\u00a0\u00a0\u00a0\u00a0\u63d0\u4f9b\u89aa\u5584\u6709\u79ae\u7684\u9867\u5ba2\u670d\u52d9\n\n\u798f\u5229\uff1a\n\n\u00a0\u00a0\u00a0\u00a0\u00a0\u00a0\u00a0\u00a0\u00a0\u512a\u539a\u5e95\u85aa\n\u00a0\u00a0\u00a0\u00a0\u00a0\u00a0\u00a0\u00a0\u00a0\u8c50\u539a\u4f63\u91d1\n\u00a0\u00a0\u00a0\u00a0\u00a0\u00a0\u00a0\u00a0\u00a0\u516c\u4f63\u200b\n\u00a0\u00a0\u00a0\u00a0\u00a0\u00a0\u00a0\u00a0\u00a0\u82b1\u7d05\n\u00a0\u00a0\u00a0\u00a0\u00a0\u00a0\u00a0\u00a0\u00a0\u6709\u85aa\u5e74\u5047\n\u00a0\u00a0\u00a0\u00a0\u00a0\u00a0\u00a0\u00a0\u00a0\u91ab\u7642\u53ca\u7259\u79d1\u6d25\u8cbc\n\u00a0\u00a0\u00a0\u00a0\u00a0\u00a0\u00a0\u00a0\u00a0\u826f\u597d\u7684\u6649\u5347\u6a5f\u6703\n\u00a0\u00a0\u00a0\u00a0\u00a0\u00a0\u00a0\u00a0\u00a0\u5b8c\u5584\u5de5\u4f5c\u57f9\u8a13\n\nApply for this job:\n\nInterested candidate please CLICK apply button to apply online or send your resume in MS word format to Fillture Group Limited\n\nFor more information please contact\u00a0Danvis Lau\u00a0+852 2814 9388.\n\nPlease note that only shortlisted candidate will be notified. All information will be treated in strict confidence and solely used for recruitment purposes.", "employment_types": ["Full Time", "Permanent"], "selling_points": ["Retail, fashion, Jewellery,  Outdoor, Lifestyle", "\u512a\u539a\u5e95\u85aa\uff0c\u8c50\u539a\u4f63\u91d1(\u53ef\u9078\u65d7\u4e0b\u670d\u88dd/\u9996\u98fe/\u6236\u5916\u7528\u54c1\u54c1\u724c)", "\u826f\u597d\u6649\u5347\u6a5f\u6703"], "locations": ["Not Specified"], "categories": ["Sales, CS & Business Devpt", "Retail Sales", "Sales - Sales Management", "Others"], "post_time": "2022-01-18T05:59:05Z", "salary": {"currency": null, "max": null, "min": null, "period": "monthly", "term": null}, "salary_visible": false, "title_keywords": ["\u92b7\u552e\u54e1", "supervisor", "senior sales", "sales associate"], "responsibilities": ["recruitment", "contact"], "requirements": {"degrees": [], "majors": [], "languages": [], "language_level": [], "hard_skills": ["ms word"], "soft_skills": ["confidence"], "languages_combined": []}, "experience_required": {"duration": [], "field": []}}, {"job_id": "100003009056120", "location_code": "hk", "company": "DHL EXPRESS (HONG KONG) LIMITED", "job_title": "Express Centre Representative", "description": "Job Specification:\n\n\nHandle inbound and outbound calls\u00a0on\u00a0ticketing services;\nThe main target is providing quality services to our customer with cheerful voice via phone.\n\nRequirements:\n\nDiploma\u00a0or above with one year call centre experience will be an advantage;\nGood telephone manner, customer-oriented and pleasant personality;\nProficiency in both English and Chinese (Cantonese & Mandarin).\n\nWorking Hours:\n5 day-work (Fixed shift, Monday to Friday)\n\n\nWe offer attractive remuneration based on experience and potential, and there is an opportunity to grow with a growing company. Please apply with full resume, contact details and expected salary.\n\n\n\nPersonal data will be collected for recruitment purposes and a copy of our Personal Information Collection Statement will be provided upon your request. We may transfer your personal data to other associated companies within the Lark International Group Limited which have other suitable vacancies.", "employment_types": ["Full Time", "Permanent"], "selling_points": ["HKALE / HKDSE or equivalent with full certificate", "Maintain the daily operation of service counter", "Promote value added services"], "locations": ["Not Specified"], "categories": ["Sales, CS & Business Devpt", "Retail Sales", "Others", "Direct Sales"], "post_time": "2022-01-18T03:21:45Z", "salary": {"currency": null, "max": null, "min": null, "period": null, "term": null}, "salary_visible": false, "title_keywords": ["representative"], "responsibilities": ["quality"], "requirements": {"degrees": ["diploma or above"], "majors": [], "languages": ["cantonese", "english", "chinese", "mandarin"], "language_level": ["proficiency"], "hard_skills": [], "soft_skills": ["customer-oriented", "cheerful", "telephone manner", "pleasant"], "languages_combined": [{"language": "cantonese", "language_level": []}, {"language": "english", "language_level": ["proficiency"]}, {"language": "chinese", "language_level": ["proficiency"]}, {"language": "mandarin", "language_level": []}]}, "experience_required": {"duration": ["one year"], "field": []}}, {"job_id": "100003009053365", "location_code": "hk", "company": "Strategic Alliance Limited", "job_title": "Business Development Manager / Assistant Business Development Manager", "description": "CS 0118\n\nResponsibilities :\n\nProvide excellent customer services and sales to customers\nPerform daily duties including quotations and related document preparation\nNegotiate and follow up with customers on maintenance renewal and value-added service status.\n\n\n\nRequirements:\u00a0 \u00a0\u00a0 \u00a0 \u00a0 \u00a0 \u00a0 \u00a0 \u00a0 \u00a0 \u00a0\n\nDiploma or above in business or related disciplines\nFresh graduates are also welcome\nCustomer-oriented mindset with a passion to provide excellent service\nStrong sense of responsibility, Outgoing & Willing to learn\nAbility to multi-task in a fast-paced environment\nProficiency in PC operations including Microsoft Office\n\n\n\nWe offer:\n\nAttractive incentive bonus & travel incentive\nCareer path\nStructured training program\nFlexible working hours \u00a0\n\nInterested parties, please send us a resume with\u00a0Date available and\u00a0EXPECTED SALARY\u00a0", "employment_types": ["Full Time"], "selling_points": [], "locations": ["Not Specified"], "categories": ["Admin & HR", "Others", "Sales, CS & Business Devpt", "Business Development", "Others"], "post_time": "2022-01-17T06:51:56Z", "salary": {"currency": null, "max": null, "min": null, "period": "monthly", "term": null}, "salary_visible": false, "title_keywords": ["business development manager", "assistant business development manager"], "responsibilities": ["maintenance", "customer services"], "requirements": {"degrees": ["diploma or above"], "majors": ["related disciplines", "business"], "languages": [], "language_level": [], "hard_skills": ["pc operations", "microsoft office"], "soft_skills": ["outgoing", "multi-task", "sense of responsibility", "fast-paced environment", "willing to learn", "customer-oriented"], "languages_combined": []}, "experience_required": {"duration": [], "field": []}}, {"job_id": "100003009054491", "location_code": "hk", "company": "GenRx Healthcare Limited", "job_title": "Assistant Officer - Client Servicing (Ref: H&P/AO-CS/JDB/04)", "description": "Sales Analyst (FMCG)\n\nOur client is a leading global FMCG company. They are looking for a Sales Analyst to join their global team.\n\nPosition Responsibilities\n\nReport to the Business Controller\nCover global wholesale and ecommerce channels\nDevelop and prepare reports, analysis, business case to analyze sales and operational data to support business decision\nUnderstand the business, and provide insights and actionable solutions\nSupport the process of KPI setup and review\nReview business terms/contracts\nConduct qualitative and quantitative analysis and translate the date to graph / charts,\nProvide insight, recommendation and action plans for decision making\nWork closely with business units to collect the user requirement and objectives, initiate business project and analysis to support their operations needs\nPerform ad-hoc project assigned by Manager\n\nPosition Requirements\n\nUniversity degree holder with 5 - 8 years of working experience in business/sales/finance analysis or consulting\nStrong analytical skills with acumen in numbers and information\nAdvanced level in MS Excel, PowerPoint\nExcellent language skills (English and Chinese) and presentation skills\nPassion on business planning / development\nProactive, flexible, result-oriented, self-motivated, team player\nFMCG / consumer brand experience\nMix working experience in both MNC and local firm\nRegional / Global / Multi-markets experience\n\nThis is an excellent opportunity to join a leading international organization who is able to offer the right individual to the chance to impact a global business.\n\nInterested individuals can apply now and send CV to Vivian Wong, or call +852 3972 5831 for more information. Only relevant candidates will be contacted\n\nFor a more comprehensive list of our vacancies, please visit: www.connectedgroup.com", "employment_types": ["Full Time", "Permanent"], "selling_points": ["Handle vouchers, invoices, payment and settlement", "Handle customers\u2019 hotline enquiries", "Work in Tsuen Wan"], "locations": ["Tsuen Wan Area"], "categories": ["Admin & HR", "Clerical / Admin Staff", "Sales, CS & Business Devpt", "Customer Service - Supervisor / Officer", "Others"], "post_time": "2022-01-17T09:46:00Z", "salary": {"currency": null, "max": null, "min": null, "period": null, "term": null}, "salary_visible": false, "title_keywords": ["assistant officer"], "responsibilities": ["ad-hoc", "provide insights", "user requirement", "data", "contracts", "analysis", "review", "operations", "develop", "prepare reports", "plans", "setup", "report"], "requirements": {"degrees": ["university degree"], "majors": ["finance", "business"], "languages": ["english", "chinese"], "language_level": ["excellent"], "hard_skills": ["analysis", "powerpoint", "analytical skills", "ms excel", "acumen"], "soft_skills": ["flexible", "self-motivated", "advanced", "analytical skills", "presentation skills", "comprehensive", "team player", "proactive", "result-oriented"], "languages_combined": [{"language": "english", "language_level": ["excellent"]}, {"language": "chinese", "language_level": ["excellent"]}]}, "experience_required": {"duration": ["5 - 8 years"], "field": ["fmcg", "brand", "consulting", "finance", "business"]}}, {"job_id": "100003009053786", "location_code": "hk", "company": "Hysan Development Co. Ltd.", "job_title": "Part-time Customer Services Representative", "description": "Reporting to the Express Centre Officer, you will be responsible for delivering quality customer service to our walk-in customers in service counter.\n\nResponsibilities:\n\nMaintain the daily operation of service counter\nHandle walk-in customers' enquiries, shipment drop-off and collection\nPromote value added services and sales promotional programs to customers\n\n\n\nRequirements:\n\nHKALE / HKDSE or equivalent with full certificate\nMinimum 2 years working experience, experience in customer service / retail field is an advantage\nWilling to perform shift duty\nEffective communication and problem solving skills\nGood command of spoken and written English and Chinese (Cantonese and Mandarin)\nFamiliar with PC skills and Chinese word processing\n\n\n\nApplication:\n\nClick \"Apply Now\" or apply on line via the following link:\n\nhttps://dhlexpress.taleo.net/careersection/ex/jobdetail.ftl?job=2100CDS&iniurl.src=CWS-10001&tz=GMT%2B08%3A00&tzname=Asia%2FShanghai\n\nPlease also indicating your current and expected salary, and availability.\u00a0 For more job opportunities, please visit our website at https://www.dpdhl.jobs/\n\n\nPersonal Information Collection Statement pertaining to Recruitment\nDHL Express (Hong Kong) Limited / DHL Aviation (Hong Kong) Limited (\u201cDHL\u201d) is committed to protecting and respecting your privacy in accordance with the Personal Data (Privacy) Ordinance of Hong Kong (the \u201cOrdinance\u201d) and DHL\u2019s Personal Data Protection Policy (the \u201cPolicy\u201d) at\u00a0https://www.dhl.com/hk-en/home/footer/local-privacy-notice.html\nBy proceeding to respond to this recruitment advertisement, you consent that we may use, retain, process, transfer or otherwise handle the personal data that we collect from you for recruitment,\u00a0 application processing, assessment and communication purposes (including any other purposes directly related thereto) in accordance with the Policy.\nAll personal data of unsuccessful applicants will be retained for future recruitment purposes for a period of not more than two (2) years after which such data will be destroyed.\nYou have the right at any time to make a data access or correction request concerning your personal data held by us. In addition, you may request us to delete your personal data that is no longer required for the relevant purposes which you have given consent. Should you wish to exercise such rights or have any question in relation to your personal data or the Policy, please contact our Human Resources Division in writing.", "employment_types": ["Part Time", "Temporary"], "selling_points": ["Provide high standard concierge service", "Handle customers' enquiries & requests", "Support marketing / promotional activities"], "locations": ["Causeway Bay"], "categories": ["Property / Real Estate", "Property Management", "Sales, CS & Business Devpt", "Others", "Others", "Student / Fresh Graduate / No Experience"], "post_time": "2022-01-17T07:30:51Z", "salary": {"currency": null, "max": null, "min": null, "period": "hourly", "term": null}, "salary_visible": false, "title_keywords": ["customer services representative"], "responsibilities": ["maintain", "daily operation"], "requirements": {"degrees": ["certificate", "hkdse"], "majors": [], "languages": ["cantonese", "english", "chinese", "mandarin"], "language_level": ["good command"], "hard_skills": ["no", "chinese word processing", "processing", "html", "make", "problem solving skills", "pc skills"], "soft_skills": ["communication", "committed", "problem solving skills", "customer service"], "languages_combined": [{"language": "cantonese", "language_level": ["good command"]}, {"language": "english", "language_level": ["good command"]}, {"language": "chinese", "language_level": ["good command"]}, {"language": "mandarin", "language_level": ["good command"]}]}, "experience_required": {"duration": ["minimum 2 years"], "field": ["customer service", "retail"]}}, {"job_id": "100003009053386", "location_code": "hk", "company": "Dell Hong Kong Limited", "job_title": "Presales Solution Architect", "description": "\nJob Responsibilities:\n\u2022 Supervise Sales team in China for Promotion, and sales and marketing;\n\u2022 Liaise with the China manufacturing facilities for the sample development as well as delivery schedule\n\u2022 Generate potential sales in new accounts that meet target budget ;\n\u2022 Prepare & deliver professional presentations, proposal and marketing materials to potential client;\n\u2022 Positive thinking, high degree of self-motivation, reliable and result-oriented;\n\u2022 travel to mainland when required;\nRequirement:\n\u2022 3 years marketing and sales experience in mainland market.\n\u2022 F.5 or above.\n\u2022 Good command of English, Chinese & Mandarin\nSalary offer: HK$18,000 - HK$22,000 or above (depends on experience)\nInterested parties, please apply together with a detailed resume, stating current and expected salary, and send it via Apply Now\nAPPLY NOW.\u00a0 (Reference no and Company name).\u00a0 Attractive remuneration will be offered in commensurate with qualifications and experience.\nAll personal information received will be treated in strict confidence for employment purpose only. Your application can be considered as unsuccessful if you have not been reached within 3 months. On the other hand, it may be transferred to other companies of our group for job openings. Unsuccessful applications will be destroyed for a period not more than 12 months.\n\n", "employment_types": ["Full Time"], "selling_points": [], "locations": ["Not Specified"], "categories": ["Sales, CS & Business Devpt", "Business Development", "Others", "Direct Sales"], "post_time": "2022-01-17T06:54:28Z", "salary": {"currency": null, "max": null, "min": null, "period": "monthly", "term": null}, "salary_visible": false, "title_keywords": [], "responsibilities": ["marketing materials", "budget", "presentations", "delivery schedule", "sales team", "liaise with"], "requirements": {"degrees": [], "majors": [], "languages": ["english", "chinese", "mandarin"], "language_level": ["good command"], "hard_skills": [], "soft_skills": [], "languages_combined": [{"language": "english", "language_level": ["good command"]}, {"language": "chinese", "language_level": ["good command"]}, {"language": "mandarin", "language_level": ["good command"]}]}, "experience_required": {"duration": ["3 years"], "field": ["marketing"]}}, {"job_id": "100003009052040", "location_code": "hk", "company": "TransUnion Limited", "job_title": "Sales Support Executive", "description": "The incumbent will provide administrative support to the daily operations.\n\u00a0\nResponsibilities:\nHandle vouchers, invoices, payment and settlement to ensure all transactions are processed in compliance with company requirements and timeline.\nHandle customers\u2019 hotline enquiries and pre-authorization request\nPrepare regular reports and participate in ad hoc projects as assigned\n\u00a0\nRequirements:\nHigher Diploma in Business Administration or related discipline preferred\nMinimum of 2 years\u2019 relevant work experience\nGood command of written and spoken English and Cantonese\nStrong communication skills\nWilling to work on Saturday\n\u00a0\nWork Location:\u00a0Tsuen Wan\n\u00a0\n\u00a0We offer competitive remuneration package including annual leave, discretionary bonus, dental and medical coverage and Top-up MPF.\u00a0We value our employees\u2019 career development and provide them with a variety of internal and external training opportunities.\n\nApplication Methods:\nOnline application \u2013 Visit our website\u00a0http://www.hkri.com\u00a0(Career Opportunities /\u00a0Humphrey & Partners Medical Services Management Limited\u00a0) to complete the online application form;\nEmail \u2013 Send your detailed resume and expected salary to \"Apply Now\";\nWhatsapp \u2013 5987 0673;\nFax \u2013 2902 2510\n\nApplicants not invited for interview within two months may consider their applications unsuccessful. All information will be used solely for recruitment purpose and will be destroyed when the recruitment process is finished. Personal data provided by job applicants will be used strictly in accordance with the employer\u2019s personal data policies, a copy of which will be provided upon request.", "employment_types": ["Full Time", "Permanent"], "selling_points": ["Prior experience in RFP/contract admin", "Attention to details", "Flexible work hours"], "locations": ["Tsim Sha Tsui"], "categories": ["Sales, CS & Business Devpt", "Others", "Sales Administration"], "post_time": "2022-01-17T01:55:10Z", "salary": {"currency": null, "max": null, "min": null, "period": "monthly", "term": null}, "salary_visible": false, "title_keywords": ["sales support executive"], "responsibilities": ["invoices", "compliance", "transactions", "payment", "reports", "ad hoc projects"], "requirements": {"degrees": ["diploma"], "majors": ["business administration"], "languages": ["cantonese", "english"], "language_level": ["good command"], "hard_skills": [], "soft_skills": ["communication skills"], "languages_combined": [{"language": "cantonese", "language_level": ["good command"]}, {"language": "english", "language_level": ["good command"]}]}, "experience_required": {"duration": ["minimum of 2 years"], "field": []}}, {"job_id": "100003009054542", "location_code": "hk", "company": "Bun Kee (International) Ltd", "job_title": "\u5e97\u8216\u8ddf\u55ae\u6587\u54e1", "description": "You will be responsible for providing high standard concierge service to our tenants and customers in our shopping mall.\u00a0 You need to handle customers' enquiries &\u00a0requests, support\u00a0marketing / promotional activities and the daily operations of our property management services.\n\nRequirements\n\n\nDiploma holder or above\nPleasant personality, outgoing and presentable\nExcellent customer service attitude and communication skills\nGood in spoken and written English and Chinese.\u00a0 Competent in spoken Putonghua.\nGood in PC skills\nWork location:\u00a0Causeway Bay\nWilling to work during\u00a012:00-21:00\u00a0/\u00a014:00-23:00\u00a0and\u00a0at least\u00a0two days per week\n\nAn attractive remuneration package will be offered to the right candidate.\u00a0 Interested please\u00a0press\u00a0\"Apply Now\".\n\n\nFor enquiries, please call/whatsapp 9760 3380.\n\nHysan is an equal opportunity employer.\u00a0 All information collected will be kept in strict confidence and used solely for recruitment related purposes within the Hysan Group Companies.\n\n\u00a0You may get to know more about us through the internet at www.hysan.com.hk", "employment_types": ["Full Time", "Permanent"], "selling_points": [], "locations": ["Mong Kok"], "categories": ["Sales, CS & Business Devpt", "Retail Sales", "Others", "Building & Construction", "Others"], "post_time": "2022-01-17T09:56:54Z", "salary": {"currency": null, "max": null, "min": null, "period": "monthly", "term": null}, "salary_visible": false, "title_keywords": [], "responsibilities": ["management", "communication", "daily operations", "customer service", "promotional activities"], "requirements": {"degrees": ["diploma holder"], "majors": [], "languages": ["putonghua", "english", "chinese"], "language_level": ["good"], "hard_skills": ["pc skills"], "soft_skills": ["outgoing", "communication skills", "responsible", "competent", "presentable", "pleasant", "customer service"], "languages_combined": [{"language": "putonghua", "language_level": []}, {"language": "english", "language_level": ["good"]}, {"language": "chinese", "language_level": ["good"]}]}, "experience_required": {"duration": [], "field": []}}, {"job_id": "100003009055063", "location_code": "hk", "company": "Osstem Hong Kong Ltd", "job_title": "Customer Service & Admin Clerk", "description": "\n\u00a0 Key Responsibilities:\nWorking together with our field sales teams, our Presales Solution Architect define the overall Dell Technologies solution for the customer using the full range of company products and services. You will support highly complex customer accounts, providing direct support to customers and our field sales teams.\nYou will:\n\u2022 Responsible for pre-sales consulting, including customer needs analysis, technical communication, PoC and solution design\n\u2022 Combine Dell's existing solutions, products, service types, in-depth mining of customer potential needs, to form a reasonable solution\n\u2022 Work with the supported sales team to develop a sales plan and complete quarterly sales targets\nEssential Requirements:\n\u2022 Solid IT professional and technical background, 5-8 years of storage/data center/cloud solutions pre-sales experience\n\u2022 Familiarize yourself with one or more of the following areas: storage, disaster recovery/backup, virtualization, cloud computing, big data, data centres, etc.\n\u2022 Technical degree or equivalent required, eight years or more of relevant work experience\nInterested parties please click Apply Now to apply job.\nHere\u2019s our story; now tell us yours\nDell Technologies helps organizations and individuals build a brighter digital tomorrow. Our company is made up of more than 150,000 people, located in over 180 locations around the world. We\u2019re proud to be a diverse and inclusive team and have an endless passion for our mission to drive human progress.\n\nWhat\u2019s most important to us is that you are respected, feel like you can be yourself and have the opportunity to do the best work of your life - while still having a life. We offer excellent benefits, bonus programs, flexible work arrangements, a variety of career development opportunities, employee resource groups, and much more.\n\nWe started with computers, but we didn\u2019t stop there. We are helping customers move into the future with multi-cloud, AI and machine learning through the most innovative technology and services portfolio for the data era. Join us and become a part of what\u2019s next in technology, starting today.\n\nYou can also learn more about us by reading our latest Diversity and Inclusion Report and our plan to make the world a better place by 2030 here.\n\nApplication closing date: 31-03-2022\n\nDell is committed to the principle of equal employment opportunity for all employees and to providing employees with a work environment free of discrimination and harassment. All employment decisions at Dell are based on business needs, job requirements and individual qualifications, without regard to race, color, religion or belief, national, social or ethnic origin, sex (including pregnancy), age, physical, mental or sensory disability, HIV Status, sexual orientation, gender identity and/or expression, marital, civil union or domestic partnership status, past or present military service, family medical history or genetic information, family or parental status, or any other status protected by the laws or regulations in the locations where we operate. Dell will not tolerate discrimination or harassment based on any of these characteristics. Dell encourages applicants of all ages. Read the full Equal Employment Opportunity Policy here.\n\n", "employment_types": ["Full Time", "Permanent"], "selling_points": ["Good knowledge about digital dentistry line-up", "Team Player with target oriented", "Good sales skill to promote Digital products"], "locations": ["Causeway Bay"], "categories": ["Medical Services", "Medical Services Technician", "Sales, CS & Business Devpt", "Technical Sales / Sales Engineer", "Others"], "post_time": "2022-01-18T01:07:49Z", "salary": {"currency": null, "max": null, "min": null, "period": "monthly", "term": null}, "salary_visible": false, "title_keywords": ["customer service", "admin clerk"], "responsibilities": ["consulting", "analysis", "teams", "design", "develop", "communication", "sales team", "plan"], "requirements": {"degrees": ["degree"], "majors": [], "languages": [], "language_level": [], "hard_skills": [], "soft_skills": [], "languages_combined": []}, "experience_required": {"duration": ["eight years", "5-8 years"], "field": ["it"]}}, {"job_id": "100003009055942", "location_code": "hk", "company": "Valuence International Limited", "job_title": "Concierge \u2013 Fast growing up Japanese Company with good benefit Valuence International Limited", "description": "What We'll Bring:\n\nAn exciting role has presented itself within TransUnion\u2019s growing business. You will be supporting Sales and BD teams, and working with different teams in TU HK to facilitate deal closing, and to assist on aftersales processes.\n\n\n\n\nImpact You'll Make:\n\nAssisting Sales and BD team to:\n\nPrepare quotations, contracts, and attend internal or external calls when necessary\nSubmit request for contract/quotation review, and follow up as required by the CRM system as the Sales Support role\nLiaise with internal and external customers, organize the responses to RFP, RFI and similar requests from Clients on a timely manner\nMaintain accurate account list and deal reports for sales meeting\nPost Sales and other responsibilities\n\nComplete internal signing procedures, consolidating supporting documents for internal teams to facilitate revenue booking\nMaintain electronic record for signed contracts according to the SOP\nFollow up with clients on aging accounts, work with Finance and MES team to expedite the collection\nManage team requisition by raising system request, including the accesses for new on boarding members to the sales team\nUndertake administrative job duties as it pertains to the sales department\nManage Sales Shared Service and document database\n\nWhat You'll Bring:\n\nBachelors\u2019 degree holder\nMinimum of 2 years\u2019 experience in Sales or Marketing departments\nExperience working on RFP response and tendering process is a great advantage\nExperience in using Salesforce is a plus, other similar CRM software experience would also count\nHigh organizational skills and ability to manage a number of projects at the same time\nDetailed minded and ability to prioritize workload\nStrong communication skills\nWell versed in MS PowerPoint, Excel and SalesForce", "employment_types": ["Full Time"], "selling_points": [], "locations": ["Tsim Sha Tsui"], "categories": ["Sales, CS & Business Devpt", "Customer Service - Supervisor / Officer", "Retail Sales", "Others"], "post_time": "2022-01-18T03:06:42Z", "salary": {"currency": null, "max": null, "min": null, "period": "monthly", "term": null}, "salary_visible": false, "title_keywords": [], "responsibilities": ["internal and external customers", "software", "contracts", "review", "quotation", "teams", "a timely manner", "procedures", "tendering", "communication", "maintain", "reports", "booking", "sales team", "database", "liaise with"], "requirements": {"degrees": ["degree holder"], "majors": [], "languages": [], "language_level": [], "hard_skills": ["excel", "plus", "salesforce", "sales support", "make", "ms powerpoint"], "soft_skills": ["organizational skills", "communication skills", "timely", "prioritize", "accurate", "detailed"], "languages_combined": []}, "experience_required": {"duration": ["minimum of 2 years"], "field": ["marketing"]}}, {"job_id": "100003009055195", "location_code": "hk", "company": "Inforich Asia Hong Kong Limited", "job_title": "CS & Business Support Assistant", "description": "\u8981\u6c42:\n\n\u4e2d\u4e94\u7a0b\u5ea6\n1\u5e74\u6709\u95dc\u7d93\u9a57\n\u61c2\u4e2d\u82f1\u6587\u96fb\u8166\u64cd\u4f5c\n\u5c0d\u6578\u5b57\u654f\u611f\n\u826f\u597d\u6e9d\u901a\u6280\u5de7\u53ca\u5177\u8cac\u4efb\u611f\n\n\u8077\u8cac:\n\n\u8ca0\u8cac\u6253\u55ae(\u96fb\u8166\u8f38\u5165)\n\u8655\u7406\u4e00\u822c\u6587\u66f8\n\n\u85aa\u916c\u5f85\u9047\uff1a 5\u5929\u5de5\u4f5c\uff08\u8f2a\u4f11\uff09\u3001\u52de\u5de5\u5047\u671f\u3001\u81b3\u98df\u6d25\u8cbc\u3001\u71df\u696d\u4f63\u91d1\u3001\u91ab\u7642\u798f\u5229\u3001\u5e74\u7d42\u914c\u60c5\u82b1\u7d05\u3001\u5a5a\u5047/\u55aa\u5047\u3001\u826f\u597d\u9032\u5347\u6a5f\u6703\u53ca\u5728\u8077\u57f9\u8a13\u7b49\n\n\n\n\u6709\u610f\u8005\u8acb\u96fb\u90f5\u81f3\u6309\u00a0\u7acb\u5373\u7533\u8acb [via\u00a0 Apply Now ]\n\n\u00a0**\u672c\u516c\u53f8\u6240\u6536\u96c6\u7684\u500b\u4eba\u8cc7\u6599\u53ea\u7528\u4f5c\u62db\u8058\u7528\u9014\u3002\u516c\u53f8\u4ea6\u6703\u5c07\u6536\u96c6\u7684\u500b\u4eba\u8cc7\u6599\u79fb\u8f49\u7d66\u516c\u53f8\u7684\u9644\u5c6c\u6216\u806f\u71df\u6a5f\u69cb\u3002\u5728\u4e00\u822c\u60c5\u6cc1\u4e0b\uff0c\u672a\u7372\u53d6\u9304\u7533\u8acb\u4eba\u7684\u8cc7\u6599\u5c07\u65bc\u62db\u8058\u7a0b\u5e8f\u5b8c\u6210\u5f8c6\u500b\u6708\u5168\u90e8\u92b7\u6bc0\u3002**", "employment_types": ["Full Time"], "selling_points": ["Friendly and team working environment", "Great Career", "Energetic with a can-do attitude"], "locations": ["Kwun Tong"], "categories": ["Sales, CS & Business Devpt", "Others"], "post_time": "2022-01-18T01:44:34Z", "salary": {"currency": null, "max": null, "min": null, "period": "monthly", "term": null}, "salary_visible": false, "title_keywords": ["assistant"], "responsibilities": [], "requirements": {"degrees": [], "majors": [], "languages": [], "language_level": [], "hard_skills": [], "soft_skills": [], "languages_combined": []}, "experience_required": {"duration": [], "field": []}}, {"job_id": "100003009055162", "location_code": "hk", "company": "RSH (Hong Kong) Limited", "job_title": "Nike Full time Sales \u5168\u8077\u552e\u8ca8\u54e1", "description": "Handle Customer Order (including Online Order System, prepare the stock and ship out)\nCommunicate with the lab in China to follow up the status of the customer order\nTechnical support such as prepare document for China lab technician\nProactively participate in team efforts to achieve company goals\n\nRequirements\n\nA team player with good interpersonal and communication skills\nGood command of written and spoken English and Chinese and Putonghua\nExperience with Dental Equipment / Dental software knowledge is highly desirable.\nDSA or dental job experience preferred\n\n\u00a0Remuneration\n\nOffer comprehensive product training to the candidate\nFriendly and dynamic working environment", "employment_types": ["Full Time", "Part Time", "Permanent"], "selling_points": ["Fresh Graduate Welcome \u6b61\u8fce\u61c9\u5c46\u7562\u696d\u751f", "\u5177\u96f6\u552e\u7d93\u9a57\u8005\u53ca\u80fd\u5373\u6642\u4e0a\u73ed\u8005\u512a\u5148", "\u5de5\u4f5c\u5730\u9ede: \u5c16\u6c99\u5480 / \u5c07\u8ecd\u6fb3 / \u89c0\u5858\uff0f\u9285\u947c\u7063"], "locations": ["Not Specified"], "categories": ["Sales, CS & Business Devpt", "Retail Sales", "Others", "Direct Sales"], "post_time": "2022-01-18T01:34:12Z", "salary": {"currency": null, "max": null, "min": null, "period": "monthly", "term": null}, "salary_visible": false, "title_keywords": ["sales"], "responsibilities": ["communicate with", "technical support", "communication", "software"], "requirements": {"degrees": [], "majors": [], "languages": ["putonghua", "english", "chinese"], "language_level": ["good command"], "hard_skills": ["dynamic"], "soft_skills": ["communication skills", "comprehensive", "friendly", "dynamic", "team player", "interpersonal"], "languages_combined": [{"language": "putonghua", "language_level": ["good command"]}, {"language": "english", "language_level": ["good command"]}, {"language": "chinese", "language_level": ["good command"]}]}, "experience_required": {"duration": [], "field": []}}, {"job_id": "100003009054379", "location_code": "hk", "company": "Superpower Pumping Engineering Co., Ltd.", "job_title": "Assistant Sales Manager", "description": "Job Description\n\nResponsibilities:\n- Willing to work on shift & wear with smart shoes and a formal shirt (self-prepared) - Responsible for shop daily operations, stock processing and replenishment, etc.\n- Provide good customer service & build rapport with walk-in customers\n- Communicate with HQ supporting team\n- On-job training will be provided\n- Excellent career path opportunity\n\nRequirements:\n- Diploma or above\n- Fresh graduate with part time service will also be considered\n- Conversational level in Japanese, JLPT N3 or above is preferred\n- Good command of spoken and written English, Cantonese and Mandarin\n- Knowledge or interest in branded/ luxury item is a plus\n- Sincere and positive working attitude\n- A good team player, with good communication and interpersonal skills.\n- Knowledge of MS Office (Word, Excel (VLOOKUP, pivot table etc.), PowerPoint\n\n\nBenefits:\n-\u00a0Fixed working hours 10:30-19:30\n-\u00a0Annual leave starting from 15 days (Max20days)\n-\u00a0Transport allowance\n-\u00a0Medical insurance\n-\u00a0Double pay\n-\u00a0Sick leave\n-\u00a0Discretionary Bonus\n-\u00a0Location: TST / Central / Kwun Tong\n\nplease send your application to Apply Now or via email to\u00a0 mo . lam @ valuence . inc", "employment_types": ["Full Time", "Permanent"], "selling_points": ["At least 6 years\u2019 working experience", "Holder of Degree in Engineering", "Good communication and interpersonal skills"], "locations": ["Cheung Sha Wan"], "categories": ["Sales, CS & Business Devpt", "Technical Sales / Sales Engineer", "Others"], "post_time": "2022-01-17T09:18:59Z", "salary": {"currency": null, "max": null, "min": null, "period": "monthly", "term": null}, "salary_visible": false, "title_keywords": ["assistant sales manager"], "responsibilities": ["communicate with", "daily operations", "customer service", "replenishment"], "requirements": {"degrees": ["fresh graduate", "diploma or above"], "majors": [], "languages": ["cantonese", "japanese", "english", "mandarin"], "language_level": ["conversational", "good command"], "hard_skills": ["excel", "plus", "pivot table", "word", "powerpoint", "vlookup", "ms office"], "soft_skills": ["positive working attitude", "sincere", "communication and interpersonal skills", "good team player"], "languages_combined": [{"language": "cantonese", "language_level": ["good command"]}, {"language": "japanese", "language_level": ["conversational"]}, {"language": "english", "language_level": ["good command"]}, {"language": "mandarin", "language_level": ["good command"]}]}, "experience_required": {"duration": [], "field": []}}, {"job_id": "100003009053798", "location_code": "hk", "company": "IMY Media Limited", "job_title": "\u5e74\u5bb5\u92b7\u552e\u54e1", "description": "\u00a0Responsibilities:\n\nCoordinate, liaise and review with department head for compiling all reports\nPrepare productivity analysis of sales Teams\nHandle merchant contract issues\nProvide overall administrative support to team\nAd hoc duty for sales support function\nTo understand customer service needed information, and answering enquiries for provide quality services\n\nRequirements:\u00a0 \u00a0 \u00a0 \u00a0 \u00a0 \u00a0 \u00a0 \u00a0 \u00a0 \u00a0 \u00a0 \u00a0 \u00a0 \u00a0 \u00a0\u00a0\u00a0\n\nDSE graduate / F.5 or above\u00a0\u00a0\u00a0\u00a0\u00a0\u00a0\nWith at least 1 years relevant experience\nCompetent computer skills\nTyping skill is highly preferred\nPositive, self-motivated with good communication skills\nGood command of English, Cantonese and Mandarin\nImmediate available is highly preferable", "employment_types": ["Part Time"], "selling_points": [], "locations": ["Tin Hau"], "categories": ["Sales, CS & Business Devpt", "Others", "Direct Sales", "Marketing / Public Relations", "Digital Marketing"], "post_time": "2022-01-17T07:32:11Z", "salary": {"currency": null, "max": null, "min": null, "period": "hourly", "term": null}, "salary_visible": false, "title_keywords": [], "responsibilities": ["liaise", "ad hoc", "administrative support", "analysis", "review", "teams", "quality", "coordinate", "customer service", "reports"], "requirements": {"degrees": ["dse"], "majors": [], "languages": ["cantonese", "english", "mandarin"], "language_level": ["good command"], "hard_skills": ["computer skills", "typing"], "soft_skills": ["communication skills", "self-motivated", "positive", "competent"], "languages_combined": [{"language": "cantonese", "language_level": ["good command"]}, {"language": "english", "language_level": ["good command"]}, {"language": "mandarin", "language_level": ["good command"]}]}, "experience_required": {"duration": ["at least 1 years"], "field": ["relevant experience"]}}, {"job_id": "100003009056108", "location_code": "hk", "company": "DHL EXPRESS (HONG KONG) LIMITED", "job_title": "Customer Service Executive (Claims & Complaint)", "description": "CHINA MOBILE HONG KONG COMPANY LIMITED\u00a0(\"CMHK\") is the wholly-owned subsidiary of China Mobile Limited (HKEx: 941) (NYSE: CHL), which ranks 65th on the Fortune Global 500.\u00a0\u00a0\n\nOur company strives to offer superior service experience and to become the preferable digital partner for customers. We are preserving an environment with trust, responsibility and caring. At CMHK, we commit to maximizing people\u2019s potential and paving the way toward success for every striver. We are now inviting high caliber professional to join us.\u00a0\n\nDivision:\u00a0Customer Service Division\n\nIn this position, you will:\n\nHandle customer enquiries in an efficient and accurate manner on various social media platform (Facebook, Whatsapp, live chat);\nEstablish and maintain good customer relationship by providing one-stop customer care services;\nInput and update customer record\u00a0accurately;\n\nTo be successful in this position, you should meet the following requirements:\n\nSecondary education or above;\n1 year relevant experience preferably in customer service;\nCustomer service oriented, willing to work under pressure, self-motivated, pleasant personality;\nGood communication and interpersonal skills;\nProficient in Cantonese, good command of English and Putonghua;\nCandidate with more experience and management skills may be considered as\u00a0Senior Customer Care Specialist.\n\nWhen you work:\u00a0\u00a0\n\n\n8.75 hours per day within 7:30am to 12:00am (including 1 hour\u00a0meal break)\n5-day per week in shift pattern (including Sunday and Public Holiday)\n\nWhat you enjoy:\n\nDouble pay\nDiscretionary Performance bonus\nAnnual Leave\nShift Allowance\nMonthly Performance Bonus\nLife insurance\nMedical insurance\nMeal allowance\nEducation subsidies\nBirthday gift\nMarriage leave\nBirthday leave\nStaff discount\n\nCMHK is committed to be an equal opportunity employer. We offer exceptional benefits package and the opportunity to work in a challenging environment. Personal data provided by applicants will be treated strictly in accordance with our personal data policy and for recruitment purposes only.\n\nPlease submit your application to us by clicking the APPLY NOW button and send your full resume with your availability, current and expected salary to us.", "employment_types": ["Full Time", "Permanent"], "selling_points": ["Handle inquiries, complaints and claims", "Participating in customer loyalty program", "Reflecting customers' feedback to management,"], "locations": ["Ngau Tau Kok"], "categories": ["Sales, CS & Business Devpt", "Call Centre", "Customer Service - Supervisor / Officer", "Others"], "post_time": "2022-01-18T03:19:57Z", "salary": {"currency": null, "max": null, "min": null, "period": null, "term": null}, "salary_visible": false, "title_keywords": ["customer service executive"], "responsibilities": ["social media", "management", "handle customer enquiries", "communication", "maintain", "customer service", "facebook", "insurance", "work under pressure"], "requirements": {"degrees": ["secondary education"], "majors": [], "languages": ["cantonese", "putonghua", "english"], "language_level": ["good command", "proficient"], "hard_skills": ["mobile", "facebook", "whatsapp"], "soft_skills": ["efficient", "self-motivated", "customer service oriented", "work under pressure", "pleasant", "committed", "customer service", "communication and interpersonal skills", "accurate", "superior"], "languages_combined": [{"language": "cantonese", "language_level": ["proficient", "good command"]}, {"language": "putonghua", "language_level": ["good command"]}, {"language": "english", "language_level": ["good command"]}]}, "experience_required": {"duration": ["1 year"], "field": ["management", "customer care", "customer service", "relevant experience", "digital"]}}, {"job_id": "100003009054334", "location_code": "hk", "company": "Orient Fair Development Ltd", "job_title": "Asst Retail Sales Manager (Casual & Sports Clothing & Footwear)", "description": "Job Responsibilities:\n\nPromote and sell water pumps, valves and plumbing\u00a0equipment\u00a0to customers\nPrepare promotional materials and implement marketing plans\nExpand customer base\u00a0and explore sales opportunities\nPrepare quotations after reviewing customers\u2019\u00a0requirements\n\nJob\u00a0Requirements:\n\nHolder of Degree in\u00a0Engineering, Sales & Marketing\u00a0or equivalent\nAt least\u00a06\u00a0years'\u00a0working\u00a0experience\u00a0in\u00a0sales and marketing\u00a0or engineering\u00a0(Engineering background is highly preferred)\nPossess good network with\u00a0consulting\u00a0companies, management companies and/or\u00a0and developers is preferred\nHardworking,\u00a0integrity,\u00a0initiative and able to work under pressure\n\nCandidates with less experience will be considered\u00a0for the post of Senior Sales Engineer.\n\nGood remuneration and attractive benefits will be offered to the right candidate. Interested parties please send full resume (MS Word Format) with expected salary and date of availability via \"APPLY NOW\" or by post to: The Human Resources and Administration Department \u2013 Recruitment & Selection Section, Superpower Pumping Engineering Co., Ltd, 16/F, World Tech Centre, 95 How Ming Street, Kwun Tong, Kowloon. Please quote reference number on letter.\u00a0\n\nWe are an Equal Opportunity Employer. Personal data will be kept strict confidence and used for recruitment-related purpose only.", "employment_types": ["Full Time", "Permanent"], "selling_points": ["Assistant Retail Sales Manager (Sports Clothing)", "experience in HK retail business at Mgt level", "Experience in Outdoor Activities Preferable"], "locations": ["Kwai Hing"], "categories": ["Sales, CS & Business Devpt", "Retail Sales", "Sales - Sales Management", "Others"], "post_time": "2022-01-17T09:11:15Z", "salary": {"currency": null, "max": null, "min": null, "period": null, "term": null}, "salary_visible": false, "title_keywords": ["manager", "retail sales"], "responsibilities": ["marketing plans", "promotional materials"], "requirements": {"degrees": ["degree"], "majors": ["marketing", "engineering"], "languages": [], "language_level": [], "hard_skills": [], "soft_skills": ["integrity", "initiative", "hardworking", "work under pressure"], "languages_combined": []}, "experience_required": {"duration": ["at least 6 years"], "field": ["marketing", "engineering"]}}, {"job_id": "100003009017955", "location_code": "hk", "company": "Total Nutrition Center Limited", "job_title": "Customer Service Representative", "description": "\n\u8077\u8cac :\u8ca0\u8cac\u92b7\u552e\u8ca8\u54c1(\u9bae\u82b1)\n\n\u8cc7\u6b77 :\u4e2d\u4e09\u7a0b\u5ea6; \u826f\u597d\u7cb5\u8a9e\u512a\u5148; \u826f\u597d\u666e\u901a\u8a71\u512a\u5148; \u826f\u597d\u82f1\u8a9e\u512a\u5148; \u61c2\u95b1\u8b80\u4e2d\u6587\n\n\u5f85\u9047 :\u6bcf\u5c0f\u6642$50.00 - $80.00, \u4e0a\u53489\u6642\u81f3\u4e0b\u534811\u6642, \u6bcf\u9031\u5de5\u4f5c5\u5929\u81f36\u5929,\u8f2a\u4f11, \u6bcf\u5929\u5de5\u4f5c 5 - 6 \u5c0f\u6642\n\n\u7533\u8acb\u9808\u77e5 :\u6c42\u8077\u8005\u53ef\u81f4\u96fb56143678\u8207\u570b\u4ed5\u5ee3\u544a\u50b3\u5a92\u6709\u9650\u516c\u53f8\u90ed\u5c0f\u59d0\u806f\u7d61\u3002\n\n", "employment_types": ["Full Time", "Permanent"], "selling_points": [], "locations": ["Wong Tai Sin Area"], "categories": ["Sales, CS & Business Devpt", "Others"], "post_time": "2022-01-17T09:37:23Z", "salary": {"currency": null, "max": null, "min": null, "period": "monthly", "term": null}, "salary_visible": false, "title_keywords": ["customer service representative"], "responsibilities": [], "requirements": {"degrees": [], "majors": [], "languages": [], "language_level": [], "hard_skills": [], "soft_skills": [], "languages_combined": []}, "experience_required": {"duration": [], "field": []}}, {"job_id": "100003009054446", "location_code": "hk", "company": "Yougov PLC", "job_title": "Executive/ Associate Manager - Business Development (Market Research)", "description": "\u00a0Working Location :\u00a0\u00a0Ngau Tau Kok\n\nWorking Hours : Monday to Friday 9:00 a.m. - 6:30 p.m. and Saturday 9:00 a.m. - 1:00 p.m. (average 40 hours per week)\n\nResponsibilities:\n\nHandle inquiries, complaints and claims independently and professionally;\nParticipating in customer loyalty program; reflecting customers' feedback to management, providing solutions for improving customer service quality;\nWork with other team members to maintain overall performance standards and assisting in various projects responsible by the team;.\nWork closely with other departments/ international network/ insurance company to meet customer's request\u00a0\n\nRequirements:\n\n\nPost-secondary education\nAt least 3 years\u2019 customer service experience in complaint and claims handling\nGood spoken & written English, Chinese and Mandarin\nInitiative and self-motivated\nCustomer-focus, open-minded, flexible, logical and systematic thinking\nGood interpersonal skills and related well with customers and co-workers from all levels\nGood team-spirit and problem solving skills\nAble to work under pressure and independent\nBasic PC knowledge and good typing skills\nApplication:\nClick \"Apply Now\" or apply on line via the following link:\u00a0https://dhlexpress.taleo.net/careersection/ex/jobdetail.ftl?job=21008SP&iniurl.src=CWS-10001&tz=GMT%2B08%3A00&tzname=Asia%2FShanghai\u00a0also indicating your current and expected salary, and availability.\u00a0 For more job opportunities, please visit our website at\u00a0https://www.dpdhl.jobs/\n\nPersonal Information Collection Statement pertaining to Recruitment\n\nDHL Express (Hong Kong) Limited / DHL Aviation (Hong Kong) Limited (\u201cDHL\u201d) is committed to protecting and respecting your privacy in accordance with the Personal Data (Privacy) Ordinance of Hong Kong (the \u201cOrdinance\u201d) and DHL\u2019s Personal Data Protection Policy (the \u201cPolicy\u201d) at https://www.dhl.com/hk-en/home/footer/local-privacy-notice.html\nBy proceeding to respond to this recruitment advertisement, you consent that we may use, retain, process, transfer or otherwise handle the personal data that we collect from you for recruitment,\u00a0 application processing, assessment and communication purposes (including any other purposes directly related thereto) in accordance with the Policy.\nAll personal data of unsuccessful applicants will be retained for future recruitment purposes for a period of not more than two (2) years after which such data will be destroyed.\nYou have the right at any time to make a data access or correction request concerning your personal data held by us. In addition, you may request us to delete your personal data that is no longer required for the relevant purposes which you have given consent. Should you wish to exercise such rights or have any question in relation to your personal data or the Policy, please contact our Human Resources Division in writing at jobs@dhl.com", "employment_types": ["Permanent"], "selling_points": [], "locations": ["Not Specified"], "categories": ["Sales, CS & Business Devpt", "Business Development", "Marketing / Public Relations", "Marketing - Market Research", "Others"], "post_time": "2022-01-17T09:40:03Z", "salary": {"currency": null, "max": null, "min": null, "period": null, "term": null}, "salary_visible": false, "title_keywords": ["executive", "associate manager"], "responsibilities": ["management", "quality", "work closely with other departments", "maintain", "customer service", "insurance"], "requirements": {"degrees": ["secondary education"], "majors": [], "languages": ["english", "chinese", "mandarin"], "language_level": ["good"], "hard_skills": ["no", "basic", "typing", "html", "make", "problem solving skills", "pc knowledge", "focus", "processing"], "soft_skills": ["flexible", "self-motivated", "independent", "open-minded", "systematic", "communication", "committed", "problem solving skills", "customer service", "interpersonal skills", "focus", "initiative", "work under pressure"], "languages_combined": [{"language": "english", "language_level": ["good"]}, {"language": "chinese", "language_level": ["good"]}, {"language": "mandarin", "language_level": ["good"]}]}, "experience_required": {"duration": ["at least 3 years"], "field": ["customer service"]}}, {"job_id": "100003009055114", "location_code": "hk", "company": "Autotoll Limited", "job_title": "Senior Business Development Manager", "description": "[Job Ref. No.: JD/ARSM/JUL2021/01]\n\nRequirement:\n\nFull Time University Graduate or Equivalent (Any Majors)\u00a0\u5168\u65e5\u5236\u5927\u5b78\u6216\u76f8\u7b49\u7a0b\u5ea6(\u4efb\u4f55\u5b78\u79d1)\u00a0\nFluent in spoken and written English and Chinese \u826f\u597d\u4e2d\u82f1\u6587\u6703\u8a71\u53ca\u66f8\u5beb\u80fd\u529b\nMin 3 years of working experience in Hong Kong in retail business at Management level. (Export & Merchandising experience is not applicable) \u4e09\u5e74\u4ee5\u4e0a\u4e4b\u96f6\u552e\u696d\u52d9\u7ba1\u7406\u5c64\u4e4b\u7d93\u9a57 (\u51fa\u53e3\u696d\u52d9\u53ca\u8cfc\u8ca8\u7d93\u9a57\u6055\u4e0d\u9069\u7528)\n\n\nExperience in any of the business required ; Sports / Outdoor Clothing or footwear, Casual / Trendy Apparel, Outdoor Goods. \u5177\u904b\u52d5 / \u91ce\u5916\u6d3b\u52d5\u65b9\u9762\u4e4b\u7528\u54c1, \u670d\u88dd, \u978b\u5c65, \u6f6e\u6d41, \u7b49\u76f8\u95dc\u4e4b\u696d\u52d9\u7d93\u9a57\n\n\nExperience in Outdoor Activities Preferable \u5177\u91ce\u5916\u6d3b\u52d5\u7d93\u9a57\u8005\u66f4\u4f73\u00a0\n\n\nWilling to travel to USA / Europe / Japan \u9700\u5f80\u7f8e / \u6b50 / \u65e5\u516c\u5e79\n\n\u655d\u516c\u53f8\u53e6\u6709\u5176\u4ed6\u7a7a\u7f3a\u4f9b\u5177\u5099\u904b\u52d5\u7528\u54c1\u6279\u767c\u6216\u96f6\u552e\u65b9\u9762\u7d93\u9a57\u4eba\u58eb\u7533\u8acb\u3002\n\nInterested parties please click apply now (Please quote the Job Ref. No. in your application)\n\nPersonal data collected will be used for recruitment purpose.", "employment_types": ["Full Time", "Permanent"], "selling_points": ["At least 10 years relevant experience", "experience in business development/sales", "5 days work"], "locations": ["Kowloon Bay"], "categories": ["Sales, CS & Business Devpt", "Business Development", "Others", "Others", "Others"], "post_time": "2022-01-18T01:15:17Z", "salary": {"currency": null, "max": null, "min": null, "period": "monthly", "term": null}, "salary_visible": false, "title_keywords": ["senior business development manager"], "responsibilities": ["management", "merchandising"], "requirements": {"degrees": ["university graduate"], "majors": [], "languages": ["english", "chinese"], "language_level": ["fluent"], "hard_skills": ["no"], "soft_skills": [], "languages_combined": [{"language": "english", "language_level": ["fluent"]}, {"language": "chinese", "language_level": ["fluent"]}]}, "experience_required": {"duration": ["min 3 years"], "field": ["business", "management", "retail", "merchandising"]}}, {"job_id": "100003009053827", "location_code": "hk", "company": "Louis Vuitton Hong Kong", "job_title": "Stylist", "description": "Job Duties:\n\n\n\nHandle incoming calls, emails on all customer enquiries in a proactive and positive manner;\nResponse promptly to client\u2019s products and service inquiries;\nResolve client\u2019s complaints;\nResponsible for various general office administrative duties including but not limited to data entry, arrange service schedules, etc.;\nOrganize and distribute incoming & outing correspondences and courier documents;\nHandle ad hoc tasks as assigned by Supervisor\n\nRequirement:\n\nHKALE/HKDSE or equivalent;\n1-2 years related experience;\nGood command of spoken and written English and Chinese.\u00a0 Knowledge of Mandarin is preferred;\nGood interpersonal skills,\u00a0well-organized, self-motivated and customer-oriented;\nProficient in using MS Office, such as Word, Excel, Outlook etc;\nResponsible, polite, punctual and willing to learn;\nImmediate availability preferred;\n\n\n\n(all data collected will be used for recruitment purpose only.)", "employment_types": ["Full Time", "Permanent"], "selling_points": ["Passionate in Louis Vuitton", "Deep knowledge of the fashion industry", "Deliver genuine and excellent client experience"], "locations": ["Not Specified"], "categories": ["Design", "Fashion", "Sales, CS & Business Devpt", "Others"], "post_time": "2022-01-17T07:35:22Z", "salary": {"currency": null, "max": null, "min": null, "period": "monthly", "term": null}, "salary_visible": false, "title_keywords": [], "responsibilities": ["data entry", "customer enquiries", "schedules", "ad hoc tasks", "administrative duties"], "requirements": {"degrees": ["hkdse"], "majors": [], "languages": ["english", "chinese", "mandarin"], "language_level": ["good command"], "hard_skills": ["excel", "outlook", "word", "ms office"], "soft_skills": ["self-motivated", "polite", "responsible", "well-organized", "willing to learn", "customer-oriented", "interpersonal skills"], "languages_combined": [{"language": "english", "language_level": ["good command"]}, {"language": "chinese", "language_level": ["good command"]}, {"language": "mandarin", "language_level": []}]}, "experience_required": {"duration": ["1-2 years"], "field": ["related"]}}, {"job_id": "100003009052298", "location_code": "hk", "company": "Quality HealthCare Medical Services Ltd", "job_title": "\u7259\u79d1\u8a3a\u6240\u63a5\u5f85\u54e1 (\u5143\u6717) Dental Receptionist (Yuen Long)", "description": "The Role\n\nYou will be marketing and driving the growth of YouGov\u2019s business, selling our exciting and innovative products and solutions. You will be working closely and supported by other internal departments to achieve your sales goal and generate new business for Hong Kong.\n\nWhat will I be delivering?\n\nAs a core member of the Business Development team, you will be working towards reaching an individual revenue target, you will do this by:\n\nActively identify new potential customers to sell our exciting and innovative products and solutions\nProactively prospecting, identifying, qualifying and exploring new potential business opportunities through cold calling and networking\nActively build good relationships with existing clients, exploring renewals and up-selling opportunities.\u00a0\nOversee, prepare, and deliver presentations of our solutions to potential clients\nIn charge of your personal target and take ownership in achieving the set-target\nWorking closely with other BU members to generate end-to-end solutions for your clients.\n\nWhat\u2019s in it for me?\n\nYou will join us as a core member of our expanding sales team, working with a group of dynamic and energetic individuals in the Asia Pacific region\nYou will have the chance to network with many senior business leaders across a variety of industries\nYou will working with companies to make better and more informed decisions though the purchase of\u00a0our market leading data and insights products and solutions\nQualifications\n\nWhat do I need to bring with me?\n\nDemonstrated knowledge and experience\n\nExcellent understanding of marketing issues related to consumer brands in Hong Kong\u00a0and across APAC\nMust have experience in the\u00a0media, advertising OR market research industry\nMust have experience in\u00a0new business B2B sales\nSeniority will be allocated based on interview performance and prior experience\nSales hunting experience\u00a0with the mentality of \u2018customer-first\u2019 approach\n\nTechnical skills and qualifications\n\nPreferably a bachelor\u2019s degree in business administration, marketing or related disciplines preferable\nStrong project management experience a plus\nExcellent written, oral and electronic communication skills\nCantonese language is must\nAbility to do client presentations to senior management\n\nBehavioral competencies\n\nA self-starter disposition and an entrepreneurial spirit, aspiring and results-oriented individual\nAbility to persuade, negotiate and work with a high level of autonomy\nGood listening skills to ensure the client's interest is captured correctly\nProblem Solver", "employment_types": ["Full Time", "Permanent"], "selling_points": ["\u751f\u65e5\u5047\uff0c\u914c\u60c5\u6027\u82b1\u7d05\uff0c\u7259\u79d1\u798f\u5229\uff0c\u5bb6\u5c6c\u91ab\u7642\u798f\u5229", "\u6b61\u8fce\u61c9\u5c46\u7562\u696d\u751f\u53ca\u7121\u76f8\u95dc\u5de5\u4f5c\u7d93\u9a57\u4eba\u58eb\u7533\u8acb", "\u5354\u52a9\u7259\u79d1\u8a3a\u6240\u524d\u53f0\u65e5\u5e38\u904b\u4f5c (5\u5929\u534a\u5de5\u4f5c)"], "locations": ["Yuen Long"], "categories": ["Medical Services", "Others", "Sales, CS & Business Devpt", "Others", "Others", "Student / Fresh Graduate / No Experience"], "post_time": "2022-01-17T02:40:16Z", "salary": {"currency": null, "max": null, "min": null, "period": "monthly", "term": null}, "salary_visible": false, "title_keywords": ["receptionist"], "responsibilities": ["advertising", "data", "business opportunities", "market research", "presentations", "communication", "project management", "purchase", "sales team", "senior management", "administration"], "requirements": {"degrees": ["degree", "bachelor"], "majors": ["related disciplines", "marketing", "business administration"], "languages": ["cantonese"], "language_level": [], "hard_skills": ["plus", "presentations", "goal", "make", "dynamic", "project management"], "soft_skills": ["communication skills", "oral", "problem solver", "innovative", "project management", "dynamic", "technical skills", "energetic"], "languages_combined": [{"language": "cantonese", "language_level": []}]}, "experience_required": {"duration": [], "field": ["advertising", "market research", "project management", "business", "media"]}}, {"job_id": "100003009050765", "location_code": "hk", "company": "CK Asset Holdings Limited", "job_title": "Customer Service Executive - Sales Department", "description": "To cope with our expansion and continuous growth in the transportation and logistics related service, we are inviting talents to join our professional team.\u00a0\n\n\nAbout The Role:\nLeading and oversee the Business Development teams for new Gov. projects\nPromotion of Smart solution to Gov. for Smart City development\nManage and execute complete sales cycle from prospecting, qualifying, closing and forecasting\nResponsible for preparing quotations and proposals, negotiating T&Cs and winning customer\u2019s contracts\nEstablish & maintain excellent relationship with potential & existing customers\nSell IT & Engineering services & solutions by leveraging expertise from the company and technologies from major global vendors\nAbout You:\nBachelor Degree holder or above\n10 years of BD/ Sales experience/ Key Account management\nSound knowledge of IT & Engineering services & solutions\nHave Gov. project experience will be an advantage\nExcellent client-facing and internal communication skills\nOutstanding writing and verbal communications skills in both English and Cantonese are required\nA good team leader and able to work under pressure and tight schedules\nHighly self-motivated, meticulous, customer focus and result-oriented\nStrong problem solving skills with a can do attitude\nCandidates with less experience will be considered as Business Development Manager\nWhat you can get from us\nOn-the-job training, learning and development tailored for your needs\nExecutive workshops, interest class, corporate purchase discount offered by SHKP\nCompetitive salary and annual leaves\nFlexible working opportunities\nInterested parties, please send full resume with\u00a0expected salary\u00a0and\u00a0available date\u00a0to Human Resources and Administration Department by e-mail or by fax 2111 9459.\n(Data collected will be used for recruitment purpose only)", "employment_types": ["Full Time", "Permanent"], "selling_points": ["Handle customer enquiries", "Degree or above", "At least 2 years' working experience"], "locations": ["Central"], "categories": ["Sales, CS & Business Devpt", "Customer Service - Supervisor / Officer", "Others"], "post_time": "2022-01-14T11:18:54Z", "salary": {"currency": null, "max": null, "min": null, "period": null, "term": null}, "salary_visible": false, "title_keywords": ["customer service executive", "sales"], "responsibilities": ["management", "schedules", "contracts", "teams", "communication", "purchase", "maintain", "logistics", "forecasting", "work under pressure"], "requirements": {"degrees": ["bachelor degree holder"], "majors": [], "languages": ["cantonese", "english"], "language_level": [], "hard_skills": ["workshops", "focus", "problem solving skills"], "soft_skills": ["result-oriented", "communication skills", "self-motivated", "meticulous", "flexible", "responsible", "problem solving skills", "learning", "customer focus", "good team leader", "client-facing", "work under pressure"], "languages_combined": [{"language": "cantonese", "language_level": []}, {"language": "english", "language_level": []}]}, "experience_required": {"duration": ["10 years"], "field": ["business development", "account management"]}}, {"job_id": "100003009056021", "location_code": "hk", "company": "The Hong Kong Jockey Club", "job_title": "Guest Relationship Officer", "description": "PRIMARY OBJECTIVE\n\nThis position will partner closely with our retail team to elevate the Louis Vuitton client experience through styling services and support them in exploring our different categories as a lifestyle connoisseur. As a trusted partner to the retail leaders, you will deliver strong business partnership through trend analysis, styling advice and training.\n\nJOB DUTIES & RESPONSIBILITIES\n\nSupport the retail team in delivering genuine and excellent client experience through on-the-floor styling advice to complete the Louis Vuitton silhouette.\nDeliver engaging, interactive training to our retail team on fashion trends and styling methodology.\nUnderstand and study our client base unique to each store to become a powerful partner to our retail team.\nPartner with Retail and Client Development teams to provide on-site styling support during exclusive events.\nDeliver frequent updates on trends and news on the current fashion landscape, maintain the market knowledge of our retail team.\u00a0\nShare best practices, resources, and inspirational stories amongst stores to create excitement and raise awareness on our products.\nAct as the ambassador of Vuitton products and maintain deep knowledge of our design inspiration by our designers.\n\nKEY REQUIREMENTS & COMPETENCIES\n\nPassion in Louis Vuitton, and deep knowledge of the fashion industry\nExcellent interpersonal and communication skills, confident in sharing conviction\nAgile, detailed-oriented and a team-player\nStrong business acumen\nFluent in English, Cantonese and Mandarin an advantage", "employment_types": ["Full Time"], "selling_points": ["1-2 years of relevant experience", "good telephone manner", "work at The Racing Club\u2019s dining venues"], "locations": ["Not Specified"], "categories": ["Sales, CS & Business Devpt", "Customer Service - Supervisor / Officer", "Hospitality / F & B", "Others", "Others"], "post_time": "2022-01-18T03:11:53Z", "salary": {"currency": null, "max": null, "min": null, "period": null, "term": null}, "salary_visible": false, "title_keywords": ["officer"], "responsibilities": ["maintain", "client base", "teams", "design"], "requirements": {"degrees": [], "majors": [], "languages": ["cantonese", "english", "mandarin"], "language_level": ["advantage", "fluent"], "hard_skills": ["agile", "acumen"], "soft_skills": ["confident", "communication skills", "agile", "passion in", "team-player", "deep", "business acumen", "interpersonal", "detailed"], "languages_combined": [{"language": "cantonese", "language_level": ["advantage", "fluent"]}, {"language": "english", "language_level": ["advantage", "fluent"]}, {"language": "mandarin", "language_level": ["advantage", "fluent"]}]}, "experience_required": {"duration": [], "field": []}}, {"job_id": "100003009052748", "location_code": "hk", "company": "Common Good Trading Limited", "job_title": "Business Development Executive:Plant-based food products for oversea market", "description": "\u5de5\u4f5c\u8077\u8cac:\n\n\n\u65bc\u7259\u79d1\u8a3a\u6240\u5de5\u4f5c\uff0c\u8ca0\u8cac\u63a5\u5f85\uff0c\u767b\u8a18\uff0c\u9810\u7d04\n\u89e3\u7b54\u75c5\u4eba\u67e5\u8a62\u4ee5\u53ca\u4e00\u822c\u6587\u66f8\u5de5\u4f5c\n5\u5929\u534a\u5de5\u4f5c\uff0c\u6bcf\u9031\u5de5\u4f5c46.5\u5c0f\u6642\u00a0(\u661f\u671f\u4e00\u81f3\u4e94 9:15am - 6:45pm, \u661f\u671f\u516d 9am - 5pm)\n\u661f\u671f\u65e5\u53ca\u516c\u773e\u5047\u671f\u4f11\u606f\n\u5de5\u4f5c\u8981\u6c42:\n\n\n\u6703\u8003/ \u6587\u6191\u8a66\u6216\u4ee5\u4e0a\u7a0b\u5ea6\n\u80fd\u64cd\u6d41\u5229\u5ee3\u6771\u8a71\u3001\u57fa\u672c\u82f1\u6587\u53ca\u666e\u901a\u8a71\uff0c\u61c2\u8b80\u5beb\u4e2d\u82f1\u6587\n\u6b61\u8fce\u61c9\u5c46\u7562\u696d\u751f\u53ca\u7121\u76f8\u95dc\u5de5\u4f5c\u7d93\u9a57\u4eba\u58eb\u7533\u8acb\n\u5b8c\u6210\u63a5\u7a2e\u5169\u5291\u65b0\u51a0\u75ab\u82d7\u8005\u53ef\u7372\u512a\u5148\u8003\u616e\n\u6709\u610f\u8005\u8acb\u5c07\u500b\u4eba\u5c65\u6b77\u3001\u73fe\u6642\u85aa\u916c\u53ca\u8981\u6c42\u5f85\u9047\uff0c\u5bc4\u5f80\u5353\u5065\u91ab\u7642\u670d\u52d9\u6709\u9650\u516c\u53f8\u4eba\u529b\u8cc7\u6e90\u90e8\u9580\uff0c\u4e5d\u9f8d\u7063\u5b8f\u5149\u905339\u865f\u5b8f\u5929\u5ee3\u58343\u6a13\uff0c\u6216\u6309\u201cApply Now\u201d\n\nJob Responsibilities\n\n\nPreform reception duties and handle bookings\nAnswer patients\u2019 inquiry and handle customers' feedback\nDeliver professional and high quality service experience at front desk of physiotherapy centre\n5.5 working days, 46.5 hours per week\u00a0(Mon - Fri 9:15am - 6:45pm, Sat 9am - 5pm)\nSunday and Public holiday off\nJob Requirements\n\n\nHKCE/ HKDSE or above\nGood spoken Cantonese, fair English and\u00a0Putonghua\nWelcome candidates without experience in medical industry\nCompleted 2 doses of COVID Vaccine is highly preferred\nWe offer\u00a0competitive pay\u00a0and fringe benefits. Interested parties please send your full resume with\u00a0current salary and expected salary to\u00a0People Team, Quality HealthCare Medical Services Limited, 3/F, Skyline Tower, 39 Wang Kwong Road, Kowloon Bay, Kowloon\u00a0or by clicking 'Apply Now\".", "employment_types": ["Full Time"], "selling_points": [], "locations": ["Not Specified"], "categories": ["Sales, CS & Business Devpt", "Business Development", "Others"], "post_time": "2022-01-17T03:54:56Z", "salary": {"currency": null, "max": null, "min": null, "period": "monthly", "term": null}, "salary_visible": false, "title_keywords": ["business development executive"], "responsibilities": ["sat", "quality"], "requirements": {"degrees": ["hkdse"], "majors": [], "languages": ["cantonese", "putonghua", "english"], "language_level": ["good"], "hard_skills": [], "soft_skills": [], "languages_combined": [{"language": "cantonese", "language_level": ["good"]}, {"language": "putonghua", "language_level": ["good"]}, {"language": "english", "language_level": ["good"]}]}, "experience_required": {"duration": [], "field": ["medical"]}}, {"job_id": "100003009053785", "location_code": "hk", "company": "Hysan Development Co. Ltd.", "job_title": "Customer Services Representative (Shopping Mall)", "description": "The Department\nThe Customer and International Business Development Division (C&I) is responsible for providing quality wagering experience to local and overseas customers of The Hong Kong Jockey Club. It operates 88 Race Meetings a year, 33 Simulcasts days, a thrice-weekly Mark 6 Draw, 7X24 Digital Channels, 7X24 Football Betting Services on over 11,000 different leagues per year. The ultimate aim is to provide an impressive total customer experience leading to sustainable turnover growth in a responsible manner.\nThe Customer Digital Experience Department is responsible for leading and managing development projects of digital wagering experience and customer service digital transformation. Besides project management, its scope includes content requirement definition, user-interface and user experience design, as well as the look and feel based on customer insights and product requirements.\n\nThe Job\nYou will:\n\nwork at The Racing Club\u2019s dining venues, both Happy Valley Racecourse and Sha Tin Racecourses on racedays and non-racedays\nprocess table booking request from members who may call in or book through online\nmaximise seat and table utilisation of the venue, work out daily booking and seating plans and prepare venue utilisation reports\nwork on event logistics, cost control and provide on-site support to ensure successful execution of internal event\nwelcome Members and their guests at The Racing Club venues in a pleasant and warm manner to build up a friendly relationship\nanswer The Racing Club hotline and general enquiries from Members about the services and events\nwritten and e-correspondences to answer enquiries is needed and help on other office administration.\n\nAbout You\nYou should have:\n\n1-2 years of relevant experience, diploma holder in Hospitality Management or related disciplines is an advantage\nexcellent interpersonal and communication skills, good telephone manner\nto be customer-centric and attention to details and logistics\nprofessional manner on handling confidential information\ngood command of spoken and written English and Chinese, which includes Cantonese and Putonghua\nhands-on computer skills in MS Word & Excel\nto work on night races, non-office working hours and Public Holidays.\n\nTerms of employment\nThe level of appointment will be commensurate with qualifications and experience.\n\nHow to Apply\nPlease send your resume, complete with expected salary and job reference by clicking the\u00a0Apply Now\u00a0button.\n\nWe are an equal opportunity employer. Personal data provided by job applicants will be used strictly in accordance with the Club\u2019s notice to employees and prospective employees relating to the Personal Data (Privacy) Ordinance. A copy of which will be provided immediately upon request.", "employment_types": ["Full Time", "Permanent"], "selling_points": ["Provide high standard customer service to shoppers", "Diploma holder with at least 1-year CS experience", "5-day work, 11-day AL, Dental, Double Pay + Bonus"], "locations": ["Causeway Bay"], "categories": ["Sales, CS & Business Devpt", "Customer Service - Supervisor / Officer", "Property / Real Estate", "Property Management", "Others"], "post_time": "2022-01-17T07:30:50Z", "salary": {"currency": "HKD", "max": 16999, "min": 14000, "period": "monthly", "term": null}, "salary_visible": true, "title_keywords": ["customer services representative"], "responsibilities": ["management", "office administration", "quality", "user experience", "design", "customer insights", "communication", "project management", "professional manner", "customer service", "reports", "booking", "logistics", "cost control", "plans", "personal data"], "requirements": {"degrees": ["diploma holder"], "majors": ["hospitality management", "related disciplines"], "languages": ["cantonese", "putonghua", "english", "chinese"], "language_level": ["good command"], "hard_skills": ["project management", "computer skills", "excel", "ms word"], "soft_skills": ["communication skills", "responsible", "pleasant", "project management", "hands-on", "customer service", "friendly", "attention to details", "telephone manner", "interpersonal"], "languages_combined": [{"language": "cantonese", "language_level": ["good command"]}, {"language": "putonghua", "language_level": ["good command"]}, {"language": "english", "language_level": ["good command"]}, {"language": "chinese", "language_level": ["good command"]}]}, "experience_required": {"duration": ["1-2 years"], "field": ["management", "related", "business development", "design", "project management", "customer service", "relevant experience", "digital", "development projects"]}}, {"job_id": "100003009054432", "location_code": "hk", "company": "China Telecom Global Limited", "job_title": "Sales Manager (Mobile Business)", "description": "Responsibilities:\n\nBe the AGENT to make change happen and make GREEN common!\nTo raise the awareness of Green Monday, Green Common and its affiliated brands, so do the awareness of health and sustainability;\nTo increase demand for plant-based products in overseas market;\nTo broaden the reach of F&B and retail channels that carry plant-based options;\nWork with overseas distributors/ partners closely to strategize sales plan;\nExplore partnership with different channels including hospitality & food service industry;\nPerform market and sales channel analysis as part of market research;\nWholesales marketing \u2013 collaborating with wholesale accounts on marketing events at partners\u2019 stores, and other incentive projects;\nCreate, maintain and update sales kits, marketing materials for wholesale, order forms and other related sales tools;\nTo support ad-hoc duties as assigned.\n\nRequirements:\n\nPassionate in promoting green lifestyle (knowledge in vegetarian/vegan product is a plus)\nDegree holder or above in Hospitality or Business Development;\nAt least 3 years\u2019 working experience in Business Development or F&B industry is preferable;\nHave project experience is definitely an advantage;\nPreferred oversea experience either for study or work related\nExcellent command in spoken and written English;\nProactive, responsible, organized and ability to work in a fast-paced environment;\nA good team player with good interpersonal and communication skills.\n\nInterested parties please apply with full resume stating availability, current and expected salaries by clicking \"APPLY NOW\"\n\nJob Type: Full-time\n\nSchedule:\n\nMonday to Friday\n\nEducation:\n\nBachelor's Degree (Preferred)\n\nExperience:\n\nF&B Industry: 3 years (Preferred)\nBusiness development: 3 years (Preferred)\n\nLanguage:\n\nEnglish (Preferred)\n\nWork Remotely:\n\nNo", "employment_types": ["Full Time", "Permanent"], "selling_points": ["Developing the potential mobile service clients", "Minimum 5 years\u2019 exp in sales of mobile service", "Competitive Salary/Double Pay/Bonus/Medical"], "locations": ["Wan Chai"], "categories": ["Sales, CS & Business Devpt", "Business Development", "Account Servicing", "Others"], "post_time": "2022-01-17T09:30:44Z", "salary": {"currency": null, "max": null, "min": null, "period": "monthly", "term": null}, "salary_visible": false, "title_keywords": ["sales manager"], "responsibilities": ["marketing events", "analysis", "market research", "maintain", "plan", "ad-hoc duties", "marketing materials"], "requirements": {"degrees": ["degree holder"], "majors": ["hospitality", "business"], "languages": ["english"], "language_level": ["excellent"], "hard_skills": ["plus"], "soft_skills": ["passionate", "organized", "good team player", "communication skills", "responsible", "fast-paced environment", "proactive", "interpersonal"], "languages_combined": [{"language": "english", "language_level": ["excellent"]}]}, "experience_required": {"duration": ["at least 3 years"], "field": ["related", "f&b", "business development"]}}, {"job_id": "100003009054337", "location_code": "hk", "company": "Orient Fair Development Ltd", "job_title": "\u517c\u8077\u5e97\u52d9\u54e1**", "description": "\nThe Job\n\n\nAn excellent career opportunity in a listed multinational corporation to deliver superior B2B services to food traders / food manufacturers / food caterers / overseas food retailer clients\nHandle inquiries and complaints from clients\nIntroduce and promote our services to clients proactively\nCoordinate between external clients and internal technical colleagues to monitor and follow up the progress of testing projects and all related events\nOn-the-job training will be provided to equip our staff to deliver the best service to clients\n\nThe Person\n\n\nDegree / Higher Diploma holder, preferably in Food Science or Chemistry discipline\nPossess strong client services mindset\nGood command of written and spoken English and Chinese (Cantonese / Mandarin)\nGood interpersonal and communication skill\nFresh graduates are welcome\nImmediately available would be an advantage\n\nThe Package\n\n\nDouble pay\nPerformance bonus\nMedical benefit\nDental plan with discount\n14 days annual leave\nLife insurance\nGood career prospects\n\nJoin us in bringing quality and safety to life.\n\nInterested parties please forward full resume stating your availability, present and expected salary to The Human Resources Manager, Intertek Testing Services HK Ltd., via ONE of the following channels: (Pls quote ref. no. on all correspondence.)\n\nAddress:\u00a02/F Garment Centre, 576 Castle Peak Rd., Kowloon, H.K.\n\nE-mail:\u00a0[via APPLY NOW]\u00a0; Fax:\u00a03403 2691\u00a0; Whatsapp: 6329 0464\n\nWelcome to visit our website http://www.intertek.com for corporate information\n\nConfidentiality assured and all applications will be kept solely for recruitment purpose for not more than 6 months.", "employment_types": ["Part Time"], "selling_points": ["\u4e2d\u4e94\u7a0b\u5ea6", "\u826f\u597d\u7cb5\u8a9e", "\u4e00\u822c\u666e\u901a\u8a71"], "locations": ["Kwun Tong Area"], "categories": ["Sales, CS & Business Devpt", "Business Development", "Others", "Direct Sales"], "post_time": "2022-01-17T09:11:47Z", "salary": {"currency": null, "max": null, "min": null, "period": "hourly", "term": null}, "salary_visible": false, "title_keywords": [], "responsibilities": ["coordinate", "inquiries and complaints", "monitor", "testing"], "requirements": {"degrees": ["degree", "higher diploma holder"], "majors": ["chemistry", "food science"], "languages": ["cantonese", "english", "chinese", "mandarin"], "language_level": ["good command"], "hard_skills": [], "soft_skills": ["communication skill", "interpersonal"], "languages_combined": [{"language": "cantonese", "language_level": ["good command"]}, {"language": "english", "language_level": ["good command"]}, {"language": "chinese", "language_level": ["good command"]}, {"language": "mandarin", "language_level": ["good command"]}]}, "experience_required": {"duration": [], "field": []}}, {"job_id": "100003009054272", "location_code": "hk", "company": "", "job_title": "Showroom Sales Clerk", "description": "Job Purpose\nTo provide high standard customer service to the shoppers in Hysan\u2019s shopping mall and create an enjoyable shopping experience for the shoppers.\n\nKey Responsibilities\n\nBe responsible for providing high standard concierge service to our tenants and customers in our shopping mall.\nHandle customers' enquiries & requests, support marketing / promotional activities and the daily operations of our property management services.\nSkills, Qualifications and Experience Requirements\n\nDiploma holder with at least 1 year's customer service experience focusing in frontline customer interaction, hotel or shopping mall concierge experience\nPleasant personality, outgoing and presentable Excellent customer service attitude and communication skills\nGood in spoken and written English and Chinese.\nCompetent in spoken Putonghua. Good in PC skills\nWilling to work on shift (5 days/week).\nEntitled to PH (17 days/year).\nWork location: Causeway Bay\nFresh Graduate will also be considered\n\nCandidate with more\u00a0experience will be considered as Senior Customer Services Representative.\n\nAn attractive remuneration package will be offered to the right candidate. \u00a0Interested parties please press \"Apply now\".\n\nFor enquiries, please call/whatsapp:\u00a09760 3380.\n\nHysan is an equal opportunity employer.\u00a0 All information collected will be kept in strict confidence and used solely for recruitment related purposes within the Hysan Group Companies.\n\nYou may get to know more about us through\u00a0www.hysan.com.hk", "employment_types": ["Full Time"], "selling_points": [], "locations": ["Wan Chai"], "categories": ["Sales, CS & Business Devpt", "Others", "Others", "Student / Fresh Graduate / No Experience"], "post_time": "2022-01-17T09:00:17Z", "salary": {"currency": null, "max": null, "min": null, "period": "monthly", "term": null}, "salary_visible": false, "title_keywords": ["sales clerk"], "responsibilities": ["management", "customer service experience", "communication", "daily operations", "customer service", "promotional activities"], "requirements": {"degrees": ["diploma holder"], "majors": ["hotel"], "languages": ["putonghua", "english", "chinese"], "language_level": ["good"], "hard_skills": ["pc skills"], "soft_skills": ["outgoing", "communication skills", "responsible", "competent", "presentable", "pleasant", "customer service"], "languages_combined": [{"language": "putonghua", "language_level": []}, {"language": "english", "language_level": ["good"]}, {"language": "chinese", "language_level": ["good"]}]}, "experience_required": {"duration": ["at least 1 year"], "field": ["customer service", "frontline customer interaction"]}}, {"job_id": "100003009053216", "location_code": "hk", "company": "Sun Life Hong Kong Ltd", "job_title": "Assistant Administration Officer (Cashier - Insurance Service Centre)", "description": "Responsibilities:\n\n\nDeveloping the potential mobile service clients and generating the leads\nMeeting or exceeding sales goals.\nPreparing the weekly and monthly sales reports\nPreparing and submitting the sales agreements for orders.\nVisiting clients and potential clients regularly to evaluate demands or promote products and services.\nMaintaining client records.\nPreparing presentations to a range of the potential clients.\nIn charge of handling outstanding of clients.\n\nRequirements:\n\nBachelor\u2019s degree in business, marketing, economics, or related field.\nMinimum 5 years\u2019 experience in sales of mobile service\nUnderstanding of the mobile service sales process and dynamics\nExcellent written and verbal communication skills in English, Mandarin and Cantonese.\nUndertaking the pressure from clients.\nSuperb interpersonal skills including the ability to quickly build report with both customers and suppliers.\n\n\n\nWe offer 5 days work, competitive salary package and attractive career development opportunities to the right candidate.\u00a0\n\nInterested parties please email your full resume with your current & expected salary to us.\n\nApplicants not invited for interview within 3 months may assume their applications unsuccessful.\u00a0\n\nPersonal data collected would be used for recruitment purpose only.\u00a0\n\n\n", "employment_types": ["Full Time", "Permanent"], "selling_points": ["Cashier / Payment / Service Centre / Mandarin", "Customer Service / Centre operation / Counter", "3 years working experience"], "locations": ["Hung Hom"], "categories": ["Sales, CS & Business Devpt", "Customer Service - Supervisor / Officer", "Insurance", "Others", "Others"], "post_time": "2022-01-17T06:27:35Z", "salary": {"currency": null, "max": null, "min": null, "period": "monthly", "term": null}, "salary_visible": false, "title_keywords": ["assistant administration officer"], "responsibilities": ["maintaining", "sales reports", "developing", "presentations", "evaluate", "promote products"], "requirements": {"degrees": ["degree", "bachelor"], "majors": ["economics", "business", "marketing"], "languages": ["cantonese", "english", "mandarin"], "language_level": ["excellent"], "hard_skills": ["mobile"], "soft_skills": ["communication skills", "interpersonal skills"], "languages_combined": [{"language": "cantonese", "language_level": ["excellent"]}, {"language": "english", "language_level": ["excellent"]}, {"language": "mandarin", "language_level": ["excellent"]}]}, "experience_required": {"duration": ["minimum 5 years"], "field": []}}, {"job_id": "100003009052755", "location_code": "hk", "company": "Common Good Trading Limited", "job_title": "International Business Development Executive (Plant-based food products)", "description": "JOIN US TO MAKE CHANGE HAPPEN MAKE GREEN COMMON\n\nGreen Monday is a multi-faceted award-winning social venture group that aims to tackle climate change, global food insecurity and public health issues. The once-a-week plant-based meal philosophy of Green Monday is practiced by over 1.6 million people at its origin in Hong Kong, and has spread to over 30 countries.\n\nGreen Common is the pioneer and leader in the \u201cbetter-for-you\u201d category in Asia, and are the distributor to many global leading brands in plant-based food industry (Beyond Meat & OmniPork etc), while Green Monday is an advocacy and movement platform to educate and mobilize people towards a healthy, sustainable plant-based diet. We are expanding our international outreach to other parts of Asia, to champion the Green Monday movement as well as introducing global food-tech innovations.\n\nResponsibilities:\nBe the AGENT to make change happen and make GREEN common!\nTo raise the awareness of Green Monday, Green Common and its affiliated brands, so do the awareness of health and sustainability;\nTo increase demand for plant-based products in overseas market;\nTo broaden the reach of F&B and retail channels that carry plant-based options;\nWork with overseas distributors/ partners closely to strategize sales plan;\nExplore partnership with different channels including hospitality & food service industry;\nPerform market and sales channel analysis as part of market research;\nWholesales marketing \u2013 collaborating with wholesale accounts on marketing events at partners\u2019 stores, and other incentive projects;\nCreate, maintain and update sales kits, marketing materials for wholesale, order forms and other related sales tools;\nTo support ad-hoc duties as assigned.\n\nRequirements:\nPassionate in promoting green lifestyle (knowledge in vegetarian/vegan product is a plus)\nDegree holder or above in Hospitality or Business Development;\nAt least 3 years\u2019 working experience in Business Development or F&B industry is preferable;\nHave project experience is definitely an advantage;\nPreferred oversea experience either for study or work related\nExcellent command in spoken and written English;\nProactive, responsible, organized and ability to work in a fast-paced environment;\nA good team player with good interpersonal and communication skills.\n\nInterested parties please apply with full resume stating availability, current and expected salaries by clicking \"APPLY NOW\"\nWe are an equal opportunity employer and welcome applications from qualified candidates. All information provided will be treated in strict confidence by authorized personnel and will be used only for recruitment related purpose. Applicants who do not hear from us within 6 weeks may consider their application unsuccessful. All personal data of unsuccessful applications will be destroyed after 6 months.", "employment_types": ["Full Time"], "selling_points": [], "locations": ["Not Specified"], "categories": ["Sales, CS & Business Devpt", "Business Development", "Others"], "post_time": "2022-01-17T03:55:58Z", "salary": {"currency": null, "max": null, "min": null, "period": "monthly", "term": null}, "salary_visible": false, "title_keywords": ["business development executive"], "responsibilities": ["marketing events", "analysis", "market research", "maintain", "plan", "ad-hoc duties", "marketing materials"], "requirements": {"degrees": ["degree holder"], "majors": ["hospitality", "business"], "languages": ["english"], "language_level": ["excellent"], "hard_skills": ["plus"], "soft_skills": ["passionate", "organized", "good team player", "communication skills", "responsible", "fast-paced environment", "proactive", "interpersonal"], "languages_combined": [{"language": "english", "language_level": ["excellent"]}]}, "experience_required": {"duration": ["at least 3 years"], "field": ["related", "f&b", "business development"]}}, {"job_id": "100003009049711", "location_code": "hk", "company": "BNI Association Limited", "job_title": "Marketing and Administration Executive", "description": "Job Duties:\n\nManage and monitor the company\u2018s official website, Facebook, Instagram etc;\nWork on Powerpoints, translations of documents and/or videos;\nResponsible to the whole process of workshops from planning, coordination and post event management;\nCoordinate with difference trainers in workshop preparation;\nAnswer inquiries from members and guests;\u00a0\nData entry and filling of member applications forms;\nAd hoc duties and assignment.\n\nRequirement:\n\nF.7 or above, preferably to have 1-2 years of event planning experiences;\nAn active and passionate team member with good team spirit;\nGood communication skills and customer service manner with good telephone manner;\nGood writing proficiency in English and Chinese;\nGood oral proficiency in English, Cantonese and Mandarin;\nAble to work under stress and ad hoc assignments\nFlexible working hours for occasionally events.\n\nPlease send full resume & expected salary to us.", "employment_types": ["Full Time"], "selling_points": ["F.7 or above, Marketing, Training, Event", "Full Time, Double Pay+, Bank Holiday", "Provide Medical, Office location near CWB MTR"], "locations": ["Causeway Bay"], "categories": ["Marketing / Public Relations", "Marketing - General / Support", "Sales, CS & Business Devpt", "Others", "Others", "Student / Fresh Graduate / No Experience"], "post_time": "2022-01-14T09:08:12Z", "salary": {"currency": null, "max": null, "min": null, "period": "monthly", "term": null}, "salary_visible": false, "title_keywords": ["administration executive"], "responsibilities": ["answer inquiries", "ad hoc duties", "management", "data entry", "workshop", "monitor", "website", "coordinate with", "coordination", "facebook", "planning"], "requirements": {"degrees": [], "majors": [], "languages": ["cantonese", "english", "chinese", "mandarin"], "language_level": ["proficiency", "good"], "hard_skills": [], "soft_skills": ["passionate", "communication skills", "oral", "team spirit", "flexible", "team member", "customer service", "active", "telephone manner"], "languages_combined": [{"language": "cantonese", "language_level": ["proficiency", "good"]}, {"language": "english", "language_level": ["proficiency", "proficiency", "good", "good"]}, {"language": "chinese", "language_level": ["proficiency", "good"]}, {"language": "mandarin", "language_level": ["proficiency", "good"]}]}, "experience_required": {"duration": ["1-2 years"], "field": ["planning"]}}, {"job_id": "100003009054173", "location_code": "hk", "company": "Auberge Hospitality Limited", "job_title": "And we are hiring \u2013 \u6a5f\u96fb\u5de5\u7a0b\u6280\u8853\u54e1(\u901a\u5bb5\u66f4), \u5927\u5dbc\u5c71\u904a\u8247\u6703", "description": "\u8077\u8cac\uff1a\n\n\u8ca0\u8cac\u6d77\u4e8b\u71df\u904b\u53ca\u6703\u6240\u7684\u6a5f\u96fb\u5de5\u7a0b\n\u9032\u884c\u65e5\u5e38\u4f8b\u884c\u6aa2\u67e5\u3001\u7dad\u4fee\u548c\u4fdd\u990a\u8a2d\u5099\uff0c\u5305\u62ec\u6703\u6240\u8a2d\u65bd\u3001\u904a\u8247\u78bc\u982d\u7b49\n\u5728\u7dca\u6025\u60c5\u6cc1\u53ca\u98b1\u98a8\u4e0b\u7576\u66f4(\u5982\u6709\u9700\u8981)\n\u5354\u52a9\u6d3b\u52d5\u53ca\u9805\u76ee\u7684\u5831\u7f6e\u548c\u6e96\u5099\u5de5\u4f5c\n\u8cc7\u6b77\uff1a\n\n\u4e2d\u4e94\u4ee5\u4e0a\u6216\u6587\u6191\u7a0b\u5ea6\n\u5177\u4e09\u5e74\u6216\u4ee5\u4e0a\u76f8\u95dc\u5de5\u4f5c\u7d93\u9a57\u70ba\u4f73\n\u5fc5\u9808\u6301\u6709\u9999\u6e2f\u6a5f\u96fb\u5de5\u7a0b\u8655\u767c\u51fa\u4e4b\u96fb\u5de5A\u724c\u6216B\u724c\n\u6301\u6709\u672c\u5730\u904a\u6a02\u8239\u4e8c\u7d1a\u8b49\u66f8\u3001\u9f8d\u9580\u8d77\u91cd\u6a5f\u8b49\u66f8\u3001\u5e73\u8861\u5f0f\u53c9\u8eca\u8b49\u66f8\u548c\u5176\u4ed6\u8239\u8236\u8a31\u53ef\u8b49\u8005\u512a\u5148\n\u826f\u597d\u4e2d\u82f1\u6587\u66f8\u5beb\u53ca\u6e9d\u901a\u6280\u5de7\n\u9808\u8f2a\u73ed\u5de5\u4f5c (\u516c\u53f8\u63d0\u4f9b\u5bbf\u820d\u4e88\u6709\u9700\u8981\u4e4b\u54e1\u5de5)\nWe offer an attractive remuneration package and excellent career opportunities to the right candidate. Interested applicants please send your CV by email to APPLY NOW or\u00a0by WhatsApp at 63173527.\n\nPersonal data provided by job applicants will be used strictly for recruitment purposes only.\n\n", "employment_types": ["Full Time", "Permanent"], "selling_points": ["\u8ca0\u8cac\u6d77\u4e8b\u71df\u904b\u53ca\u6703\u6240\u7684\u6a5f\u96fb\u5de5\u7a0b", "\u4e2d\u4e94\u4ee5\u4e0a\u6216\u6587\u6191\u7a0b\u5ea6 \u5177\u4e09\u5e74\u6216\u4ee5\u4e0a\u76f8\u95dc\u5de5\u4f5c\u7d93\u9a57\u70ba\u4f73", "\u5fc5\u9808\u6301\u6709\u9999\u6e2f\u6a5f\u96fb\u5de5\u7a0b\u8655\u767c\u51fa\u4e4b\u96fb\u5de5A\u724c\u6216B\u724c"], "locations": ["Lantau Island"], "categories": ["Sales, CS & Business Devpt", "Customer Service - Supervisor / Officer", "Others"], "post_time": "2022-01-17T08:40:34Z", "salary": {"currency": null, "max": null, "min": null, "period": "monthly", "term": null}, "salary_visible": false, "title_keywords": [], "responsibilities": [], "requirements": {"degrees": [], "majors": [], "languages": [], "language_level": [], "hard_skills": [], "soft_skills": [], "languages_combined": []}, "experience_required": {"duration": [], "field": []}}, {"job_id": "100003009055085", "location_code": "hk", "company": "Lander Grand Hotels (Holdings) Limited", "job_title": "Front Office Agent - Night Shift", "description": "Handling guests' check-in and check-out, reservation, telephone answering\nAssisting guests with inquiries\nResponsible for providing customer services to the guests\nAssisting in daily operations and reports of the front desk\u00a0\u00a0\nPerform ad hoc duties assigned by supervisors/managers\n\nJob\u00a0Requirements\n\nMinimum 1 year of experience in customer service or hospitality field\nCertificate in Hospitality or related\u00a0disciplines\nCheerful and a good team player\nGood communication and customer service skills\nGood in spoken Cantonese, Putonghua and English\nImmediately available is an advantage\nFresh Graduates will also be considered\nWork location: Mongkok\nFor interested parties, please send our full resume with current and expected salary by clicking \"Apply Now\".\u00a0", "employment_types": ["Full Time", "Permanent"], "selling_points": ["Meal provided", "Immediately available is an advantage", "Fresh Graduates will be considered"], "locations": ["Mong Kok"], "categories": ["Hospitality / F & B", "Hospitality / Hotel Services", "Sales, CS & Business Devpt", "Others"], "post_time": "2022-01-18T01:19:07Z", "salary": {"currency": null, "max": null, "min": null, "period": "monthly", "term": null}, "salary_visible": false, "title_keywords": [], "responsibilities": ["ad hoc duties", "customer services", "communication", "daily operations", "customer service", "reports"], "requirements": {"degrees": ["certificate"], "majors": ["related disciplines", "hospitality"], "languages": ["cantonese", "putonghua", "english"], "language_level": ["good"], "hard_skills": [], "soft_skills": ["customer service skills", "good team player", "cheerful", "responsible", "communication", "customer service"], "languages_combined": [{"language": "cantonese", "language_level": ["good"]}, {"language": "putonghua", "language_level": ["good"]}, {"language": "english", "language_level": ["good"]}]}, "experience_required": {"duration": ["minimum 1 year"], "field": ["customer service"]}}, {"job_id": "100003009054199", "location_code": "hk", "company": "The Bank of East Asia, Limited", "job_title": "Trade Product Manager, Trade Services", "description": "Trade Product Manager, Trade Services (Job ID3374)\nResponsibilities\nTo be a team member of Trade Services Department.\nTo set up trade product team and lead subordinate(s).\nTo work with sales team and operations team of Trade Services Department.\nTo timely identify opportunity to drive and develop new trade products and to maintain and revamp existing trade products to meet business requirements.\nTo monitor and manage performance of trade products.\nTo keep close track with market trend and update and to share them with working partners.\u00a0 \u00a0\nTo conduct trade product training to working partners.\nTo cooperate working partner on trade promotion campaigns.\nTo take up ad hoc tasks as assigned.\nRequirements\nUniversity graduate in Business Administration or related discipline.\nA minimum of 10 years' working experience in banking/financial service industry, of which at least 5 years in trade product at managerial level. Trade sales or operations experience is preferred.\nSound knowledge of trade products and commodity market. \u00a0\nFamiliar with UCP, URR, URC, URDG, ISP98, ISBP, BPO, Incoterms & SWIFT etc.\nKnowledge and experience in Microsoft application implementation.\nStrong communication and project management skills.\nFluent in English, Mandarin and Cantonese.\nGood command of written English and Chinese.\n(Candidate with more experiences will be considered for the post of Senior Trade Product Manager)\nPlease apply online via the BEA Careers website at\u00a0https://careers.hkbea.com/psp/hcmprd/EMPLOYEE/HRMS/c/HRS_HRAM.HRS_APP_SCHJOB.GBL?Page=HRS_APP_JBPST&Action=UFOCUS=Applicant&SiteId=1&JobOpeningId=3374&PostingSeq=1 or by clicking the \"Apply Now\" button below. Kindly note that if you are a new user, you have to first create your User Profile before you can apply.\nPersonal data provided by job applicants will be used for recruitment purposes only and will be treated in accordance with the Bank's Personal Information Collection (Employees) Statement and Privacy Policy Statement. Applicants who are not invited for interviews within six weeks may consider their applications unsuccessful and the personal data collected will be destroyed after six months.", "employment_types": ["Full Time"], "selling_points": ["Keep close track with market trend", "University graduate in Business Administration", "A minimum of 10 years' working experience"], "locations": ["Not Specified"], "categories": ["Admin & HR", "Administration / Operation Manager", "Sales, CS & Business Devpt", "Business Development", "Others"], "post_time": "2022-01-17T08:47:15Z", "salary": {"currency": null, "max": null, "min": null, "period": "monthly", "term": null}, "salary_visible": false, "title_keywords": ["product manager"], "responsibilities": ["revamp", "operations", "monitor", "ad hoc tasks", "develop", "maintain", "sales team", "promotion campaigns", "meet business requirements"], "requirements": {"degrees": ["university graduate"], "majors": ["business administration"], "languages": ["cantonese", "english", "chinese", "mandarin"], "language_level": ["good command", "fluent"], "hard_skills": ["swift", "project management", "c"], "soft_skills": ["communication", "project management skills"], "languages_combined": [{"language": "cantonese", "language_level": ["fluent"]}, {"language": "english", "language_level": ["good command", "fluent"]}, {"language": "chinese", "language_level": ["good command"]}, {"language": "mandarin", "language_level": ["fluent"]}]}, "experience_required": {"duration": ["at least 5 years", "minimum of 10 years"], "field": ["managerial", "service industry", "financial", "banking"]}}, {"job_id": "100003009050728", "location_code": "hk", "company": "Hutchison Telecommunications (Hong Kong) Limited", "job_title": "Business Operations Officer", "description": "Responsibilities:\n\n\nProvide the business supports to Sales Teams, including the sales order process, order submission, sales documentation handling, PR/PO preparation, customer billing arrangement\n\u00a0Liaison with internal departments and business partners to ensure effective sales logistics\nPrepare the regular sales management reports, presentation materials\nPrepare the operation manuals with prescribed procedure and workflows\nReview and ensure policies and procedures are in alignment with operation needs and in compliance\nTake initiative to assess workflow and process to improve business operations efficiency\nProvide the administrative supports to the Department, including oversee and maintain staffs records, coordinate the general IT related and system access right, organize the systematical filing system\nHandle ad hoc duties as required\u00a0\n\nRequirements:\n\n\nHigher Diploma or above\nMinimum 5 year\u2019s relevant experience in sales administration with telecom industry experience would be advantage\nExposure in telecom related industries is an advantage\nWell-organized, able to handle multi-tasks and prioritize works under tight schedule\nProficiency in MS office applications, especially in MS Excel (Pivot table & vlookup) and MS PowerPoint\nMore experience will be considered as Senior Business Support Officer\nApart from competitive remuneration package and exciting opportunity for career development within the Group, we provide attractive employee benefits such as free company shuttle, free company SIM card and preferential SIM plan offers, comprehensive medical & insurance schemes, as well as full range of other employee well-being provisions.\u00a0\n\nInterested parties, please apply with full resume, present and expected salary, by clicking \u201cAPPLY NOW\u201d. Please quote the reference number on the e-mail subject.\n\nWe are an equal opportunity employer and welcome applications from all qualified candidates. Personal data collected will be treated in the strictest confidence and handled confidentially by authorised personnel for recruitment-related purposes only within the CK Hutchison Group of companies. The personal data of unsuccessful applicants will be destroyed after the recruitment exercise pursuant to the requirements of the Personal Data (Privacy) Ordinance in Hong Kong.", "employment_types": ["Full Time", "Permanent"], "selling_points": [], "locations": ["Tsing Yi"], "categories": ["Admin & HR", "Clerical / Admin Staff", "Sales, CS & Business Devpt", "Others", "Sales Administration"], "post_time": "2022-01-14T11:14:58Z", "salary": {"currency": null, "max": null, "min": null, "period": "monthly", "term": null}, "salary_visible": false, "title_keywords": ["operations officer"], "responsibilities": ["ad hoc duties", "policies", "operations", "review", "teams", "procedures", "compliance", "coordinate", "maintain", "logistics", "reports", "documentation", "sales management"], "requirements": {"degrees": ["higher diploma or above"], "majors": [], "languages": [], "language_level": [], "hard_skills": ["pivot table", "ms excel", "ms powerpoint", "vlookup", "ms office"], "soft_skills": ["comprehensive", "well-organized", "prioritize", "multi-tasks"], "languages_combined": []}, "experience_required": {"duration": ["minimum 5 year"], "field": ["sales administration", "relevant experience", "business support"]}}, {"job_id": "100003009053381", "location_code": "hk", "company": "Wolters Kluwer Hong Kong Limited", "job_title": "Senior Sales Representative", "description": "\nRole:\nResponsible for all sales activities in assigned accounts or regions. Manage quality and consistency of product and service delivery. Focus on selling a CPM Software and Services.\nPrimary Responsibilities:\n\u2022 New business prospecting and development, including cold calling; scheduling client introductions and meetings; and preparing presentations, proposals, and bid specifications to strategically win new business.\n\u2022 Reviewing progress, pipeline and identifying opportunities for further sales and new areas for development\n\u2022 Present and sell company products and services to current and potential clients.\n\u2022 Prepare go-to market plans and schedules to identify specific targets and to project the number of contacts to be made.\n\u2022 Attending training and associated workshops to increase product knowledge and to stay abreast of company products and pricing as well as familiarity with competitor products and pricing.\n\u2022 Participating in trade shows, exhibits, open houses, and product demonstrations, promoting company image and its products and solutions.\n\n", "employment_types": ["Full Time"], "selling_points": [], "locations": ["Wan Chai"], "categories": ["Sales, CS & Business Devpt", "Business Development", "Others", "Direct Sales"], "post_time": "2022-01-17T06:53:55Z", "salary": {"currency": null, "max": null, "min": null, "period": "monthly", "term": null}, "salary_visible": false, "title_keywords": ["representative", "senior sales"], "responsibilities": ["service delivery", "sales activities", "software", "schedules", "quality", "presentations", "scheduling", "specifications", "plans"], "requirements": {"degrees": [], "majors": [], "languages": [], "language_level": [], "hard_skills": ["workshops", "focus", "go", "presentations"], "soft_skills": ["focus", "responsible"], "languages_combined": []}, "experience_required": {"duration": [], "field": []}}, {"job_id": "100003009052891", "location_code": "hk", "company": "Commercial Professional Consultancy", "job_title": "Workshop assistant \u5de5\u4f5c\u574a\u7d71\u7c4c\u52a9\u7406", "description": "\u8077\u8cac\uff1a\u5de5\u4f5c\u574a\u7d71\u7c4c\u52a9\u7406, \u6d3b\u52d5\u7d71\u7c4c\u53ca\u62db\u52df\u3002\n\n\u8cc7\u6b77\uff1a \u826f\u597d\u7cb5\u8a9e;\u00a0 \u826f\u597d\u6e9d\u901a\u6280\u5de7; \u9858\u610f\u5b78\u7fd2\uff0c\u6709\u5718\u968a\u5408\u4f5c\u7cbe\u795e\u3002\n\u6709\u66fe\u7d44\u7e54\u6d3b\u52d5\u7d93\u9a57\u8005\u512a\u5148\u3002\n\n\u5f85\u9047\uff1a \u6642\u85aa$80\u00a0\n\n\u5de5\u4f5c\u6642\u9593: \u517c\u8077, \u4e0a\u73ed\u6642\u9593\u5f48\u6027", "employment_types": ["Full Time", "Part Time"], "selling_points": [], "locations": ["Not Specified"], "categories": ["Sales, CS & Business Devpt", "Others"], "post_time": "2022-01-17T04:26:57Z", "salary": {"currency": null, "max": null, "min": null, "period": "monthly", "term": null}, "salary_visible": false, "title_keywords": ["assistant"], "responsibilities": [], "requirements": {"degrees": [], "majors": [], "languages": [], "language_level": [], "hard_skills": [], "soft_skills": [], "languages_combined": []}, "experience_required": {"duration": [], "field": []}}, {"job_id": "100003009055470", "location_code": "hk", "company": "HKT Consumer Group", "job_title": "Sales Representative (Call Center-Sales/ Retention Hotlines) (5-day work)", "description": "Your role\n\nHandle customer's telephone inquiries and requests in a tactful and timely manner\nPerform consultative and proactive selling of company products & services\nEstablish good customer relationship by offering one-stop-shop service\n\nWorking location\n\nLai Chi Kok (nearby Mei Foo MTR Station)\nShatin (nearby City One Town)\n\nWorking hours\n\n5-day work week including weekends & public holidays\n42.5 hours per week, willing to take up shift duties\n\nTo succeed in this role\n\nF.5 / DSE or above with some sales experience. Experienced Candidate with 2 years of sales experience will be considered as Sales Executive\nGood command in English and Cantonese\nGood telephone manner and service attitude\nGood communication and interpersonal skills\n\nWe offer you\n\nAttractive basic salary with commission & sales incentive\nSales target discount for new joiner\nNight shift allowance\nComprehensive training with pay\n14-day annual leave\nMarriage leave\nMaternity leave\nPaternity leave\nCareer development opportunities\nMedical insurance\nMPF/Provident Fund schemes\nStaff offer and staff recreation\nSponsorship of external study\n\nApplication method\u00a0\n\nI want to make an interview appointment:\u00a06029 4292\u00a0\u00a0https://bit.ly/3tidcUa\u00a0\n\nEnquiry hotline:\u00a028887388\u00a0\n\nEmail:\u00a0career-consumer@pccw.com \u00a0\n\nHKT is an equal opportunity employer and welcomes applications from all qualified candidates. Information provided will be treated in strict confidence and will only be used for recruitment-related purposes. Personal data provided by job applicants will be used strictly in accordance with the employer's privacy statement ( www.hkt.com/privacy-statement ), a copy of which will be provided immediately upon request.", "employment_types": ["Full Time"], "selling_points": [], "locations": ["Lai Chi Kok"], "categories": ["Sales, CS & Business Devpt", "Call Centre", "Others"], "post_time": "2022-01-18T02:37:51Z", "salary": {"currency": null, "max": null, "min": null, "period": "monthly", "term": null}, "salary_visible": false, "title_keywords": ["sales representative", "sales"], "responsibilities": [], "requirements": {"degrees": [], "majors": [], "languages": [], "language_level": [], "hard_skills": [], "soft_skills": ["timely", "proactive", "tactful"], "languages_combined": []}, "experience_required": {"duration": [], "field": []}}, {"job_id": "100003009052312", "location_code": "hk", "company": "Harvey Nichols (Hong Kong) Limited", "job_title": "Customer Relations Assistant (Frontline)", "description": "Handling in-store and e-commerce customer enquiries and complaints via all communication channels, including but not limited to email, live chat, telephone and face-to-face; including products\u2019 promotion, logistics, products return;\nSupport the team in sales activities, including order processing and post-sales coordination;\nResponsible for in-store e-commerce work station operations, including maintain the e-commerce system, handle in-store pickup orders and provide excellent customer service at store.\nResponsible for the administration support including data input and coupon/GWP redemption;\nResponsible for Customer Service reports;\nAssist in handling ad-hoc assignments if needed.\n\nRequirements:\n\nHigher Diploma or above;\n1 year relevant experience from customer service field would be an advantage;\nDetail-minded, positive and proactive working attitude, with strong customer service mindset;\nGood command of both spoken & written English and Mandarin;\nShift duty\u00a0is required;\nNO\u00a0sales target need to be achieved;\nFresh graduate is also welcome to apply;\nCandidates with\u00a0more experience will be considered as senior position.\n\nWe offer:\n\n6.5 days off per month\n17 Public Holidays\n11 Annual Leave\nAttendance bonus\nShift allowance\nMedical benefits\n\nWe offer excellent career prospects, competitive salary and fringe benefits to the right candidate. Please apply in strict confidence by sending personal resume together with salary expected and date availability by email:\u00a0careers @ harveynichols. com .hk\u00a0or Whatsapp\u00a09828-0637.\n\nWe are an equal opportunity employer and welcome applications from all qualified candidates.\u00a0 Personal data provided by job applicants will be used strictly in accordance with our personal data policy and for recruitment purposes only.\u00a0 Candidates not notified within eight weeks may consider their application unsuccessful.\u00a0 All related information will be kept in our file for up to 24 months.\u00a0 A copy of our Personal Information Collection Statement will be provided upon request by contacting our Human Resources Division.", "employment_types": ["Full Time"], "selling_points": ["6.5 Day Off + 11 Annual Leave + PH", "Customer-oriented and positive working attitude", "Front-line position"], "locations": ["Tsim Sha Tsui"], "categories": ["Sales, CS & Business Devpt", "Customer Service - Supervisor / Officer", "Others"], "post_time": "2022-01-17T02:43:35Z", "salary": {"currency": null, "max": null, "min": null, "period": "monthly", "term": null}, "salary_visible": false, "title_keywords": ["assistant"], "responsibilities": ["sales activities", "operations", "ad-hoc assignments", "sales target", "data input", "communication", "maintain", "logistics", "customer service", "order processing", "coordination", "reports", "customer enquiries and complaints", "support the team", "administration"], "requirements": {"degrees": ["higher diploma or above", "fresh graduate"], "majors": [], "languages": ["english", "mandarin"], "language_level": ["good command"], "hard_skills": ["no", "order processing", "e-commerce"], "soft_skills": ["detail-minded", "responsible", "communication", "customer service", "coordination", "proactive", "positive"], "languages_combined": [{"language": "english", "language_level": ["good command"]}, {"language": "mandarin", "language_level": ["good command"]}]}, "experience_required": {"duration": ["1 year"], "field": ["customer service", "relevant experience"]}}, {"job_id": "100003009049463", "location_code": "hk", "company": "Cordlife (Hong Kong) Limited", "job_title": "Customer Service Officer", "description": "Job Requirements:\n\nDSE / Associate Degree or Diploma holder with 2 years related work experience is highly preferred\nPleasant personality and patient attitude, good telephone manner together with excellent communication and interpersonal skills are a MUST\nBe responsible, well-organized, self-initiated and customer services oriented\u00a0\nProficient in both spoken and written Chinese, English and Mandarin\nProficient computer knowledge such as Microsoft and Chinese word processing\nStrong sense of team spirit\nWilling to perform shift duties including Sat/ Sun/ Public holidays\nCandidates with more experience will be considered as Senior\u00a0Customer Service Officer\n\nJob Responsibilities:\n\nHandle customer enquiries, email communications professionally and resolve any service issues in a timely manner\nCoordinate with various parties to ensure customer requests are handled promptly and accurately\nResponsible for after-sales operation supports\nPerform office admin duties and assist in client activity\nAny ad-hoc tasks as assigned by supervisor\n\nWe offer:\n\nAttractive remuneration package and staff benefits\nShuttle bus provided by Hong Kong Science Park\nComprehensive on-the-job and continuous trainings\nOpportunities for professional and personal development\nFriendly working environment\n\nIf you are interested in this position, please send your resume with details of qualification, experience, present and expected salary, address and contact number to HR by clicking \u201cAPPLY NOW\u201d.\n\nAll personal data collected would be used for recruitment purpose.", "employment_types": ["Full Time", "Permanent"], "selling_points": ["5-day work, Double pay, Performance bonus", "Medical, life insurance, Birthday & family leave", "fast-growing biotech, Friendly working environment"], "locations": ["Shatin Area"], "categories": ["Admin & HR", "Others", "Sales, CS & Business Devpt", "Customer Service - Supervisor / Officer", "Others"], "post_time": "2022-01-14T08:42:42Z", "salary": {"currency": null, "max": null, "min": null, "period": "monthly", "term": null}, "salary_visible": false, "title_keywords": ["customer service officer"], "responsibilities": ["handle customer enquiries", "ad-hoc tasks", "a timely manner", "coordinate with", "customer requests"], "requirements": {"degrees": ["diploma holder", "associate degree", "dse"], "majors": [], "languages": ["english", "chinese", "mandarin"], "language_level": ["proficient"], "hard_skills": ["chinese word processing"], "soft_skills": ["team spirit", "responsible", "well-organized", "pleasant", "communication and interpersonal skills", "customer service", "patient", "telephone manner"], "languages_combined": [{"language": "english", "language_level": ["proficient"]}, {"language": "chinese", "language_level": ["proficient", "proficient"]}, {"language": "mandarin", "language_level": ["proficient"]}]}, "experience_required": {"duration": ["2 years"], "field": ["related", "customer service"]}}, {"job_id": "100003009052616", "location_code": "hk", "company": "Everbest Insurance and Financial Services Limited", "job_title": "Marketing Assistant", "description": "Responsibilities:\n\nTo follow up client\u2019s application and to follow up pending documents in accordance with the rules and regulations of compliance, and also our standard of sales process.\u00a0\n\nTo update Sales and Marketing materials of products and sales process of all insurers and/or partners.\n\nRequirements:\n\nMinimum Form 6 or above, (PRC graduate is also welcome).\n\nMinimum \u00a02 years\u2019 experience in Sales of Life insurance industry.\n\nPossess Insurance License papers 1 and 3 is a must.\n\nFluent in Mandarin.\n\nExcellent communication and interpersonal skills.\u00a0\n\nBenefits: \u00a0- Group Insurance,\u00a0MPF and Year-End Performance Bonus.\n\nSalaries Range:\n\n1)\u00a0 For the MCV \u00a0Executive - Sales and Marketing:\u00a0\n\n\u00a0\u00a0\u00a0\u00a0 - Annual Package: HKD400,000.00 (around HKD28K-HKD33K per month)\n\n2) \u00a0For the Sales and Marketing Assistant:\n\n\u00a0 \u00a0\u00a0 - HKD18K-HKD20K per month\n\n\u00a04) Good promotion opportunities", "employment_types": ["Full Time"], "selling_points": ["Need professional base knowledge to Clients.", "follow up client\u2019s application and pending docs.", "Good promotion opportunities"], "locations": ["Tsim Sha Tsui"], "categories": ["Sales, CS & Business Devpt", "Others", "Others", "Others"], "post_time": "2022-01-17T03:33:38Z", "salary": {"currency": "HKD", "max": 29999, "min": 11000, "period": "monthly", "term": null}, "salary_visible": true, "title_keywords": ["marketing assistant"], "responsibilities": ["regulations", "marketing materials", "compliance"], "requirements": {"degrees": [], "majors": [], "languages": ["mandarin"], "language_level": ["fluent"], "hard_skills": [], "soft_skills": ["communication and interpersonal skills"], "languages_combined": [{"language": "mandarin", "language_level": ["fluent"]}]}, "experience_required": {"duration": ["2 years"], "field": ["insurance industry"]}}, {"job_id": "100003009050098", "location_code": "hk", "company": "Polar Air Cargo Worldwide, Inc", "job_title": "Reservations & Customer Service Coordinator", "description": "Position Summary:\u00a0\u00a0This position will be responsible for coordinating all sales & reservation related matters with the sales team of the territory.\n\nMajor Job Accountabilities:\n\n\nIdentifies, contacts customers and books cargo to fill flights.\nIdentifies and communicates problems in freight allocation and pallet build-up to terminal services and/or management and ensures solution.\nProactively solicits cargo from customers when booking is not sufficient to fill the flights, and to get approval from the management if spot rates are required to general demand.\nWhen requested or pre-approved, calculates, analyzes and provides appropriate spot rates to customers.\nIdentifies, researches and resolves customer service issues and/ or ensures resolution.\nTracks all on forwarded cargo to final destination via aircraft or truck. Coordinates truck movements with operations.\nTraces missing cargo and follow-up on tracers, provides freight status alert and/or customer call back-up support.\nResearches local claims and provides documentation to corporate customer service.\nCommunicates with Supervisor Reservation & Customer Service on ongoing basis.\nResponds to customers\u2019 questions, problems, requests and/or complaints.\nAssists sales by cross selling, upgrading and increasing existing customer use of Polar Air Cargo Worldwide.\nAssists sales by qualifying and selling new account.\nCreates an environment that encourages team work by informing sales manager unique or difficult situations.\nAssists Supervisor of Reservation and Customer Service in identification of department\u2019s potential.\nPerforms other duties as assigned.\nWilling to work on night shift (15:00-24:00) and on holidays.\u00a0\n\nQualifications:\u00a0\n\n\nBachelor Degree or equivalent combination of education and work experience\nMinimal 1 year of work experience, preferably air cargo industry experience\nKnowledge of logistics planning and pricing is preferably but not a must\nHigh degree of decision making skills and stress resistance.\nStrong ability to manage complex situations under time pressure.\nStrong analytical skills.\nExcellent communication skills.\nFluent in written and spoken English and Chinese\n\nPolar Air\u00a0offers attractive remuneration and fringe benefits. Please apply with full resume, current and expected salary.\n\n(The personal data provided with will be treated confidentially and used for recruitment purposes only)", "employment_types": ["Full Time", "Permanent"], "selling_points": ["Customer Service", "Handle Cargo Booking", "Attractive remuneration and fringe benefits"], "locations": ["Tung Chung"], "categories": ["Transportation & Logistics", "Aviation Services", "Sales, CS & Business Devpt", "Customer Service - Supervisor / Officer", "Others"], "post_time": "2022-01-14T09:46:40Z", "salary": {"currency": null, "max": null, "min": null, "period": "monthly", "term": null}, "salary_visible": false, "title_keywords": ["customer service coordinator"], "responsibilities": ["management", "other duties", "operations", "resolution", "communication", "customer service", "sales team", "booking", "logistics", "documentation", "planning"], "requirements": {"degrees": ["degree", "bachelor"], "majors": [], "languages": ["english", "chinese"], "language_level": ["fluent"], "hard_skills": ["documentation", "aircraft", "analytical skills"], "soft_skills": ["communication skills", "decision making skills", "responsible", "unique", "analytical skills", "customer service"], "languages_combined": [{"language": "english", "language_level": ["fluent"]}, {"language": "chinese", "language_level": ["fluent"]}]}, "experience_required": {"duration": ["1 year"], "field": ["education"]}}, {"job_id": "100003009051323", "location_code": "hk", "company": "Universal Marble (H.K.) Company Limited", "job_title": "Sales Executive (Double Pay)", "description": "Job Descriptions:\n\n\u2022\u00a0Explore and develop business opportunities for stonework in the construction field.\n\u2022\u00a0Conduct client meetings and provide presentations, specification and follow up service to prospective clients\n\u2022\u00a0Responsible for coordination work with architects, consultants, and sub-contractors.\n\u2022\u00a0Perform ad-hoc works\n\u00a0\n\n\nRequirements:\n\n\u2022\u00a0Form 5 (HKCEE) or Form 6 (DSE) or above\n\u2022\u00a0Fresh Graduates are welcome\n\u2022\u00a0Sales-orientated to identify and develop business opportunities\n\u2022\u00a0Good Mandarin and English\n\u2022\u00a0PC literate\n\nAttend to work on Saturday at bi-weekly intervals.\n\nOur web site:\u00a0https://www.umgg.biz/en/\n\n\n\nPlease apply with full resume and expected salary, email by clicking \"Apply Now\" for application.\n\n\nPersonal data collected will be used for recruitment purpose only.", "employment_types": ["Full Time", "Permanent"], "selling_points": [], "locations": ["Wan Chai"], "categories": ["Sales, CS & Business Devpt", "Business Development", "Sales - Sales Management", "Others"], "post_time": "2022-01-16T21:50:27Z", "salary": {"currency": null, "max": null, "min": null, "period": "monthly", "term": null}, "salary_visible": false, "title_keywords": ["sales executive"], "responsibilities": ["ad-hoc", "business opportunities", "presentations", "develop", "coordination"], "requirements": {"degrees": ["form 5", "dse"], "majors": [], "languages": ["english", "mandarin"], "language_level": ["good"], "hard_skills": ["bi", "pc literate", "web"], "soft_skills": [], "languages_combined": [{"language": "english", "language_level": ["good"]}, {"language": "mandarin", "language_level": ["good"]}]}, "experience_required": {"duration": [], "field": []}}, {"job_id": "100003009055713", "location_code": "hk", "company": "Bun Kee (International) Ltd", "job_title": "\u5e97\u8216\u7406\u8ca8\u54e1", "description": "\u8981\u6c42:\n\n\u4e2d\u4e09\u7a0b\u5ea6\n1\u5e74\u6709\u95dc\u5de5\u4f5c\u7d93\u9a57\n\u5de5\u4f5c\u614b\u5ea6\u52e4\u5feb\n\u826f\u597d\u6e9d\u901a\u6280\u5de7\u53ca\u5177\u8cac\u4efb\u611f\n\n\u8077\u8cac:\n\n\u8ca0\u8cac\u5e97\u8216\u51fa\u5165\u8ca8\u54c1\n\u7ba1\u7406\u5e97\u8216\u8ca8\u54c1\u64fa\u8a2d,\u5354\u52a9\u586b\u88dc\u53ca\u4fdd\u6301\u8ca8\u67b6\u4e4b\u6574\u6f54\n\n\u85aa\u916c\u5f85\u9047\uff1a 5\u5929\u5de5\u4f5c\uff08\u8f2a\u4f11\uff09\u3001\u52de\u5de5\u5047\u671f\u3001\u81b3\u98df\u6d25\u8cbc\u3001\u71df\u696d\u4f63\u91d1\u3001\u91ab\u7642\u798f\u5229\u3001\u5e74\u7d42\u914c\u60c5\u82b1\u7d05\u3001\u5a5a\u5047/\u55aa\u5047\u3001\u826f\u597d\u9032\u5347\u6a5f\u6703\u53ca\u5728\u8077\u57f9\u8a13\u7b49\n\n\n\n\u6709\u610f\u8005\u8acb\u96fb\u90f5\u81f3\u6309\u00a0\u7acb\u5373\u7533\u8acb [via\u00a0 Apply Now ]\n\n\u00a0**\u672c\u516c\u53f8\u6240\u6536\u96c6\u7684\u500b\u4eba\u8cc7\u6599\u53ea\u7528\u4f5c\u62db\u8058\u7528\u9014\u3002\u516c\u53f8\u4ea6\u6703\u5c07\u6536\u96c6\u7684\u500b\u4eba\u8cc7\u6599\u79fb\u8f49\u7d66\u516c\u53f8\u7684\u9644\u5c6c\u6216\u806f\u71df\u6a5f\u69cb\u3002\u5728\u4e00\u822c\u60c5\u6cc1\u4e0b\uff0c\u672a\u7372\u53d6\u9304\u7533\u8acb\u4eba\u7684\u8cc7\u6599\u5c07\u65bc\u62db\u8058\u7a0b\u5e8f\u5b8c\u6210\u5f8c6\u500b\u6708\u5168\u90e8\u92b7\u6bc0\u3002**", "employment_types": ["Full Time", "Permanent"], "selling_points": [], "locations": ["Mong Kok"], "categories": ["Transportation & Logistics", "Others", "Sales, CS & Business Devpt", "Retail Sales", "Others"], "post_time": "2022-01-18T02:52:47Z", "salary": {"currency": null, "max": null, "min": null, "period": "monthly", "term": null}, "salary_visible": false, "title_keywords": [], "responsibilities": [], "requirements": {"degrees": [], "majors": [], "languages": [], "language_level": [], "hard_skills": [], "soft_skills": [], "languages_combined": []}, "experience_required": {"duration": [], "field": []}}, {"job_id": "100003009056112", "location_code": "hk", "company": "Oxford University Press (China) Ltd", "job_title": "Sales Executive", "description": "Job Responsibilities:\nResponsible for sales of home learning products to customers;\nResponsible for the sales target;\nDeliver professional selling and post selling service for our users;\nActively participate in customer related activity and sales promotion event.\nJob Requirements:\n\n\nDegree or above with minimum 3 years\u2019 relevant selling experience;\nCollaborate with team to achieve better result;\nStrong presentation and communication skills;\nHigh motivation for sales;\nRelevant experience in working early childhood is definite an advantage;\nCandidates with more experience will be considered as Senior Sales Executive.\u00a0\nWe are committed to supporting diversity in our workforce, and ensuring an inclusive environment where all employees can thrive. We seek to employ a workforce representative of the markets that we serve, and encourage applications from people of all ethnic, cultural and social backgrounds.\u00a0\u00a0\nApplications, including curriculum vitae and expected salary, should be sent by clicking \u201cAPPLY NOW\u201d.\nPersonal data will be used for recruitment purposes only.\u00a0", "employment_types": ["Full Time", "Permanent"], "selling_points": ["Home learning products", "Promote retention and loyalty", "13th month salary, incentive & Discretionary Bonus"], "locations": ["Yau Ma Tei"], "categories": ["Sales, CS & Business Devpt", "Others"], "post_time": "2022-01-18T03:20:11Z", "salary": {"currency": null, "max": null, "min": null, "period": "monthly", "term": null}, "salary_visible": false, "title_keywords": ["sales executive"], "responsibilities": ["sales target"], "requirements": {"degrees": ["degree or above"], "majors": [], "languages": [], "language_level": [], "hard_skills": [], "soft_skills": ["communication skills", "committed", "presentation"], "languages_combined": []}, "experience_required": {"duration": ["minimum 3 years"], "field": ["relevant experience"]}}, {"job_id": "100003009052920", "location_code": "hk", "company": "HGC Global Communications Limited", "job_title": "Business Support Executive (Admin. Support)", "description": "\u00a0Responsibilities:\n\nCoordinate, liaise and review with internal departments for compiling all products commission reports\nPrepare productivity analysis of sales Teams\nHandle payment & PO issues with vendors\nProvide overall administrative support to team\nAd hoc duty for sales support function\u00a0\u00a0\u00a0\u00a0\u00a0\u00a0\u00a0\u00a0\u00a0\u00a0\u00a0\u00a0\u00a0\u00a0\u00a0\u00a0\u00a0\u00a0\n\nRequirements:\u00a0 \u00a0 \u00a0 \u00a0 \u00a0 \u00a0 \u00a0 \u00a0 \u00a0 \u00a0 \u00a0 \u00a0 \u00a0 \u00a0 \u00a0\u00a0\u00a0\n\nDSE graduate / F.5 or above\u00a0\u00a0\u00a0\u00a0\u00a0\u00a0\u00a0\u00a0\u00a0\u00a0\u00a0\u00a0\u00a0\u00a0\u00a0\u00a0\nAt least 2-3\u00a0 years\u2019 relevant working experience\nSelf-motivated, proactive and well-organized\nProficiency in MS Word, Excel & PowerPoint\n\nWe offer competitive salary package and career development opportunity. \u00a0Free company coach is provided. \u00a0Interested parties, please quote our reference number and apply with full resume,\u00a0present and expected salary, by clicking \"APPLY NOW\".\u00a0\n\nWe are an equal opportunity employer and welcome applications from all qualified candidates. Information provided will be treated in strict confidence and only be used for consideration of your application for the relevant post within HGC Global Communications Limited. Personal data provided by job applicants will be used strictly according to our Personal Information Collection Statement, a copy of which will be available upon written request. Information of unsuccessful candidates will be destroyed within six months.\n", "employment_types": ["Full Time", "Permanent"], "selling_points": ["Compiling all products commission reports", "Prepare productivity analysis", "Handle payment & PO issues"], "locations": ["North Point"], "categories": ["Accounting", "Accounting Clerk / Supervisor", "Admin & HR", "Clerical / Admin Staff", "Sales, CS & Business Devpt", "Others"], "post_time": "2022-01-17T04:32:01Z", "salary": {"currency": null, "max": null, "min": null, "period": "monthly", "term": null}, "salary_visible": false, "title_keywords": ["admin", "executive"], "responsibilities": ["liaise", "ad hoc", "administrative support", "analysis", "review", "teams", "coordinate", "payment", "reports"], "requirements": {"degrees": ["dse"], "majors": [], "languages": [], "language_level": [], "hard_skills": ["excel", "powerpoint", "ms word"], "soft_skills": ["self-motivated", "proactive", "well-organized"], "languages_combined": []}, "experience_required": {"duration": [], "field": ["relevant working experience"]}}, {"job_id": "100003009053296", "location_code": "hk", "company": "Shipco Transport (HK) Ltd", "job_title": "Indoor Sales Executive", "description": "Role & Responsibilities:\nAnalyze and assess customers for effective negotiation\nIdentify the customers\u2019 need and acquire customers and business by phone calls\nMaintain good support with customers and keep abreast of market & industry development\nAggressive, self-motivated, customer oriented\nAttend sales meeting with reporting and share in markets where that is desired\nRequirements\n1-2 years working experience\nCustomer oriented, proactive in client management and development\nProficient in Excel\nWilling to learn, try and challenge new things\nHardworking, Self-motivated and able to work independently\nLearning opportunities\nBusiness development and intelligence\nCommercial awareness\nNegotiation skills\n\n\nAny candidate who is interested in 1 position is requested to send email to Mr. Matchy Yuen\u00a0 (email by clicking \"Apply Now\"\u00a0for internal review)", "employment_types": ["Full Time", "Permanent"], "selling_points": ["Analyze & assess customers", "Maintain good support with customers", "1-2 years working experience"], "locations": ["Not Specified"], "categories": ["Sales, CS & Business Devpt", "Business Development", "Customer Service - Supervisor / Officer", "Others"], "post_time": "2022-01-17T06:42:54Z", "salary": {"currency": null, "max": null, "min": null, "period": "monthly", "term": null}, "salary_visible": false, "title_keywords": ["indoor sales executive"], "responsibilities": ["reporting", "maintain", "phone calls"], "requirements": {"degrees": [], "majors": [], "languages": [], "language_level": [], "hard_skills": ["excel"], "soft_skills": ["self-motivated", "work independently", "interested in", "willing to learn", "negotiation skills", "learning", "proactive", "hardworking"], "languages_combined": []}, "experience_required": {"duration": ["1-2 years"], "field": []}}, {"job_id": "100003009051672", "location_code": "hk", "company": "Care For You Company Limited", "job_title": "Part/Full Time Showroom Sales Executive - Medical Equipment", "description": "Responsibilities:\n\nProvide medical equipment introduction & demonstration\nPromote & sell products/services to customer\nDeliver excellent customer service in person, phone call and email\nProvide professional follow up service to solve the problem for customers\nEducate and support customers in person or via phone call and email.\n\n\u00a0Requirements:\n\nHigher Diploma or Degree holder\nMinimum 1 year working experience, preferred in indoor sales\nProactive, result oriented, strong sense of responsibility and excellent interpersonal & communication skill\nGood team player, be patient, able to work independently and problem solving\u00a0\nGood command of\u00a0 English, Mandarin and Cantonese", "employment_types": ["Full Time", "Permanent"], "selling_points": ["Promote & sell products/services to customers", "Handle product trial and customers' enquiries.", "Competitive package and medical & life insurances"], "locations": ["Tsim Sha Tsui"], "categories": ["Sales, CS & Business Devpt", "Customer Service - Supervisor / Officer", "Retail Sales", "Others"], "post_time": "2022-01-16T21:50:40Z", "salary": {"currency": null, "max": null, "min": null, "period": "monthly", "term": null}, "salary_visible": false, "title_keywords": ["sales executive"], "responsibilities": ["customer service"], "requirements": {"degrees": ["diploma", "degree holder"], "majors": [], "languages": ["cantonese", "english", "mandarin"], "language_level": ["good command"], "hard_skills": ["problem solving"], "soft_skills": ["good team player", "work independently", "sense of responsibility", "communication skill", "problem solving", "result oriented", "patient", "proactive", "interpersonal"], "languages_combined": [{"language": "cantonese", "language_level": ["good command"]}, {"language": "english", "language_level": ["good command"]}, {"language": "mandarin", "language_level": ["good command"]}]}, "experience_required": {"duration": ["minimum 1 year"], "field": []}}, {"job_id": "100003009053656", "location_code": "hk", "company": "Cheer Step Corporation Limited", "job_title": "\u526f\u5e97\u9577(\u624b\u6a5f\u914d\u4ef6Sales)", "description": "\n\u4e3b\u8981\u92b7\u552e\u96fb\u8a71\u914d\u4ef6\u7522\u54c1,\u6709\u4e00\u822c\u6578\u78bc\u7522\u54c1\u77e5\u8b58,\u8ca0\u8cac\u65e5\u5e38\u5e97\u92ea\u904b\u4f5c,\u7522\u54c1\u9673\u8a2d\u53ca\u6536\u9280,\u7dad\u6301\u5e97\u5167\u6574\u6f54\u885b\u751f,\u8aa0\u61c7\u6709\u79ae,\u6709\u8cac\u4efb\u5fc3,\u4e3b\u52d5\u8ddf\u5ba2,\u826f\u597d\u51fa\u52e4,\u80fd\u7368\u7acb\u8655\u4e8b,\u9054\u81f4\u92b7\u552e\u76ee\u6a19\n\u9700\u67092\u5e74\u4ee5\u4e0a\u96f6\u552e\u7d93\u9a57,\u6216\u6709\u76f8\u95dc\u7d93\u9a57,\u5177\u826f\u597d\u92b7\u552e\u6280\u5de7,\u91cd\u8996\u5718\u968a\u5408\u4f5c,\u826f\u597d\u4eba\u969b\u6e9d\u901a\n(\u8a66\u7528\u671f\u5167)\u85aa\u91d1\n\u85aa\u91d1:$60/\u5c0f\u6642\n\u5de5\u4f5c\u6642\u9593:\u6bcf\u5929\u5de5\u4f5c10\u5c0f\u6642,\u6bcf\u9031\u5de5\u4f5c6\u5929\n\u771f\u5fc3\u63fe\u5de5\u8acb\u76f4\u63a5Send CV\nWhatsapp:63544989\u9ec3\u5c0f\u59d0\n(\u5982\u5408\u9069\u4e00\u661f\u671f\u5167\u6703\u6536\u5230\u9762\u8a66\u901a\u77e5)\nThanks!\n\u5de5\u4f5c\u985e\u578b: \u5168\u8077, \u9577\u5de5\n\u85aa\u916c: \u6bcf\u6708 $15,000.00\n\u798f\u5229:\n\u2022 \u54e1\u5de5\u8cfc\u7269\u512a\u60e0\n\u2022 \u6649\u5347\u6a5f\u6703\n\u9060\u7a0b\u5de5\u4f5c:\n\u2022 \u5426\n\n", "employment_types": ["Full Time"], "selling_points": [], "locations": ["Not Specified"], "categories": ["Sales, CS & Business Devpt", "Business Development", "Others", "Direct Sales"], "post_time": "2022-01-17T07:18:09Z", "salary": {"currency": null, "max": null, "min": null, "period": "monthly", "term": null}, "salary_visible": false, "title_keywords": [], "responsibilities": [], "requirements": {"degrees": [], "majors": [], "languages": [], "language_level": [], "hard_skills": [], "soft_skills": [], "languages_combined": []}, "experience_required": {"duration": [], "field": []}}, {"job_id": "100003009040354", "location_code": "hk", "company": "Cheung Kong Center Property Management Limited", "job_title": "Concierge", "description": "Certificate / Diploma or above\n1\u00a0year frontline experience in\u00a0service industry preferred\nTo provide excellent customer service for a Grade A commercial building including managing visitors registration and enquiries\nPleasant,\u00a0possesses good\u00a0interpersonal & communication skills and able to work\u00a0independently\nProficiency in MS Office and\u00a0Chinese Word Processing\nFluent in spoken English and Mandarin\n\nFresh graduates will also be considered\n\nWe will offer attractive compensation package to the right candidate.\u00a0 Please send application enclosing resume stating career and salary history, expected salary and date of availability to The\u00a0Human Resources Manager, Cheung Kong\u00a0Center Property Management\u00a0Limited, 7/F Cheung Kong Center, 2 Queen's Road Central, Hong Kong or by clicking \u201cApply Now\u201d (in Word format).\u00a0 Please quote the reference of the position you apply for in all correspondences.\n\nWe are an equal opportunity employer and welcome applications from all qualified candidates. Personal data collected will be treated in strictest confidence and handled confidentially by authorized personnel for recruitment-related purposes within the Group. Applicants not hearing from us within six weeks from the date of advertisement may consider their applications unsuccessful.", "employment_types": ["Full Time", "Permanent"], "selling_points": ["Certificate / Diploma or above", "1 year frontline experience in service industry", "Fluent in spoken English, Cantonese and Putonghua"], "locations": ["Central & Western Area"], "categories": ["Hospitality / F & B", "Hospitality / Hotel Services", "Property / Real Estate", "Property Management", "Sales, CS & Business Devpt", "Others"], "post_time": "2022-01-16T21:50:12Z", "salary": {"currency": null, "max": null, "min": null, "period": "monthly", "term": null}, "salary_visible": false, "title_keywords": [], "responsibilities": ["management", "communication", "customer service", "recruitment", "personal data"], "requirements": {"degrees": ["certificate", "diploma or above"], "majors": [], "languages": ["english", "chinese", "mandarin"], "language_level": ["proficiency", "fluent"], "hard_skills": ["chinese word processing", "word", "ms office"], "soft_skills": ["communication skills", "work independently", "confidence", "pleasant", "customer service", "interpersonal"], "languages_combined": [{"language": "english", "language_level": ["fluent"]}, {"language": "chinese", "language_level": ["proficiency"]}, {"language": "mandarin", "language_level": ["fluent"]}]}, "experience_required": {"duration": ["1 year"], "field": ["service industry"]}}, {"job_id": "100003009051699", "location_code": "hk", "company": "ASM Technology Hong Kong Limited", "job_title": "Field Services Engineer", "description": "Responsibilities:\n\nCollaborate with overseas team to support customer services activities\nPerform installation and set up as well as repair semiconducting packaging equipment at customer's premises\nOptimize machine performance to fit customers' needs\nDeliver customer training\n\nRequirements:\n\nBachelor\u2019s degree or above in Electrical / Electronic / Mechanical Engineering or relevant disciplines (Higher diploma holder with solid relevant working experience may also be considered)\nStrong interpersonal and communication skills with ability to work independently\nGood analytical skills and familiar with problem solving tools will be asset.\nFluent in written and spoken English\nFrequent worldwide travel, mainly (1) Greater China and Asian countries or (2) America\n\nAttractive salary and fringe benefits package will be offered to the right candidates.\u00a0\nInterested parties please submit your application with cover letter, resume, certificate and transcripts.\nData collected will be used for recruitment purpose only. Suitable candidates may be referred to other vacancies within our company.", "employment_types": ["Full Time", "Permanent"], "selling_points": ["Higher Diploma or above in Electrical", "Frequent worldwide travel", "Collaborate with overseas team to support customer"], "locations": ["Tsing Yi"], "categories": ["Sales, CS & Business Devpt", "Business Development", "Technical Sales / Sales Engineer", "Others"], "post_time": "2022-01-16T21:50:54Z", "salary": {"currency": null, "max": null, "min": null, "period": "monthly", "term": null}, "salary_visible": false, "title_keywords": ["engineer"], "responsibilities": ["collaborate with", "installation", "customers' needs", "customer services", "repair"], "requirements": {"degrees": ["degree or above", "bachelor", "higher diploma holder"], "majors": ["mechanical engineering"], "languages": ["english"], "language_level": ["fluent"], "hard_skills": ["problem solving", "analytical skills"], "soft_skills": ["communication skills", "work independently", "analytical skills", "problem solving", "interpersonal"], "languages_combined": [{"language": "english", "language_level": ["fluent"]}]}, "experience_required": {"duration": [], "field": ["relevant working experience", "engineering"]}}, {"job_id": "100003009054796", "location_code": "hk", "company": "Public Finance Limited", "job_title": "Tagalog or Bahasa Speaker", "description": "Walk-IN INTERVIEW\nDate \u00a0\u00a0\u00a0 \u00a0: 17/1 \u2013 21/1 (Mon \u2013 Fri)\nTime\u00a0\u00a0 \u00a0 \u00a0\u00a0 \u00a0: 9:00am \u2013 12:00pm & 2:00pm - 5:30pm\u00a0\u00a0 \u00a0\nVenue \u00a0\u00a0 \u00a0: 11/F., Wing On House, 71 Des Voeux Rd. Central, H.K.\nResponsibilities & Requirements:\nProvide customer service and clerical support in branch\nIndoor duties only\nWilling to work on Saturday and Sunday (2 days off per week)\nH.K. permanent resident or holding a Dependent Visa\nBasic Salary + Overtime Pay + Double Pay + Year-end Bonus + Annual Leave + Medical Benefits covering staff and dependents\n_______________________________________________________________________\nYou can also send your application to:\nBy email via \"Apply Now\"\n\nBy whatsapp : 9309 2925\nBy fax\u00a0 : 2522 1635\nBenefits\nDouble Pay\nDiscretionary Bonus\nInsurance Benefits\nStudy subsidy\nPersonal data collected will be treated in the strictest confidence in accordance with our Personal Information Collection Statement and Privacy Policy and will be handled by authorized personnel for recruitment-related purposes only. All applications will be kept for a maximum period of one year as may be considered for other suitable positions within Public Finance Ltd. and its associated companies. For details, please visit the Company\u2019s website http://www.publicfinance.com.hk", "employment_types": ["Full Time", "Permanent"], "selling_points": [], "locations": ["Not Specified"], "categories": ["Admin & HR", "Clerical / Admin Staff", "Sales, CS & Business Devpt", "Customer Service - Supervisor / Officer", "Others"], "post_time": "2022-01-17T11:07:55Z", "salary": {"currency": null, "max": null, "min": null, "period": "monthly", "term": null}, "salary_visible": false, "title_keywords": [], "responsibilities": [], "requirements": {"degrees": [], "majors": [], "languages": [], "language_level": [], "hard_skills": [], "soft_skills": ["customer service"], "languages_combined": []}, "experience_required": {"duration": [], "field": []}}, {"job_id": "100003009052569", "location_code": "hk", "company": "Mitsui & Co (HK) Ltd", "job_title": "Sales Administrator", "description": "We are now inviting candidate of high calibre to join us in the following capacity in our Iron & Steel Division.\n\nJob Duties:\n\nTo handle import / export shipping documents\nTo support sales staff to contact customers or suppliers as necessary\nTo perform general administrative and clerical support for the division, such as car booking, meeting room booking, expense claims, arrange hotel booking and business trip etc.\nTo perform other ad-hoc projects and tasks as assigned\nRequirements:\n\nAt least 2 \u2013 5 years\u2019 relevant working experience in shipping area\nExperience in SAP system is preferable\nStrong communication & interpersonal skills\nAble to work under pressure and complete the jobs within time constraint\nGood command of English and Mandarin\nGood command of Microsoft Office Tools (e.g. Word, Excel) and Chinese Typing\nDiploma graduate, commercial studies\n\nInterested parties please apply with your full resume stating present and expected salary.\n\nAll information will be kept confidential and used for recruitment purpose only. Although we endeavour to respond to every applicant, this may not always be possible so if you receive no response within 60 days, please consider your application for this specific vacancy to be unsuccessful.\n\n", "employment_types": ["Full Time", "Permanent"], "selling_points": [], "locations": ["Admiralty"], "categories": ["Sales, CS & Business Devpt", "Others", "Others", "Trading", "Sales Administration"], "post_time": "2022-01-17T03:26:34Z", "salary": {"currency": null, "max": null, "min": null, "period": "monthly", "term": null}, "salary_visible": false, "title_keywords": ["sales administrator"], "responsibilities": ["shipping documents", "business trip", "contact", "administrative and clerical support", "booking", "ad-hoc projects"], "requirements": {"degrees": ["diploma"], "majors": [], "languages": ["english", "chinese", "mandarin"], "language_level": ["good command"], "hard_skills": ["excel", "sap", "microsoft office", "typing", "word"], "soft_skills": ["communication", "interpersonal skills", "work under pressure"], "languages_combined": [{"language": "english", "language_level": ["good command"]}, {"language": "chinese", "language_level": []}, {"language": "mandarin", "language_level": ["good command"]}]}, "experience_required": {"duration": ["5 years"], "field": ["relevant working experience"]}}, {"job_id": "100003009052135", "location_code": "hk", "company": "Champion Capital Industries Limited", "job_title": "Assistant Sales Manager", "description": "A public listed manufacturing company invites applicants to fill the following vacancy:\n\n- Diploma or Degree holder in Sales and Marketing or related discipline\n- Min 3-5 years solid experiences in optical industry is required\n- Independently follow up orders and correspondence\n- Good communication skill to work with designers and customers\n- Strong problem solving skills and result oriented\n- Good interpersonal skill, self-motivated and well-organized\n- Creative, proactive and good team-player\n- Good command in written & spoken English, Cantonese & Mandarin\n- Immediately available preferred\n\nWe offer attractive fringe benefits including 5 working days, bank holidays, bonus & medical insurance to the right candidates. Interested parties please send email to Human Resources Manager for further information.", "employment_types": ["Full Time", "Permanent"], "selling_points": [], "locations": ["Kwun Tong"], "categories": ["Marketing / Public Relations", "Marketing - Brand / Product Management", "Sales, CS & Business Devpt", "Others", "Sales Administration"], "post_time": "2022-01-17T02:13:23Z", "salary": {"currency": null, "max": null, "min": null, "period": "monthly", "term": null}, "salary_visible": false, "title_keywords": ["assistant sales manager"], "responsibilities": ["follow up orders", "communication"], "requirements": {"degrees": ["diploma", "degree holder"], "majors": ["marketing"], "languages": ["cantonese", "english", "mandarin"], "language_level": ["good command"], "hard_skills": ["problem solving skills"], "soft_skills": ["self-motivated", "independently", "proactive", "team-player", "communication skill", "well-organized", "interpersonal skill", "result oriented", "problem solving skills", "creative"], "languages_combined": [{"language": "cantonese", "language_level": ["good command"]}, {"language": "english", "language_level": ["good command"]}, {"language": "mandarin", "language_level": ["good command"]}]}, "experience_required": {"duration": ["min 3-5 years"], "field": []}}, {"job_id": "100003009052696", "location_code": "hk", "company": "Chanel Hong Kong Limited", "job_title": "Deputy Head of Boutique", "description": "Job Purpose :\u00a0The Deputy Head of Boutique plays an important role in inspiring and managing the boutique team to achieve the mission of the brand, and is the primary driver of effective day-to-day operations in the boutique.\n\nAs a bridge between the Head of Boutique and the Boutique team, the Deputy Head of Boutique supports the Head of Boutique to reinforce, communicate and execute The Chanel Difference on the Boutique floor to ensure luxury retail leadership.\n\nVision :\u00a0The ultimate house of luxury defining style and creating desire now and forever.\n\nMission:\u00a0Dedicated to inspiring and managing the boutique team to engage the consumer of today and tomorrow to the brand by providing unsurpassed service to all our customers (internal and external) while supporting the Head of Boutique in ensuring high image standards in the boutiques at all times while being committed to the employee\u2019s personal and professional development and growth.\n\nKey Responsibilities:\n\n\nUphold the Image of the Brand (VM Merchandising +BTQ Maintenance +Grooming)\nManage and inspire the Boutique team\nBuild a Client-centric Boutique team\nProperly manage Merchandise & Inventory\nEffectively manage day-to-day Operations\nFoster close partnerships\nForm close partnerships with W&FJ Division, and the relevant divisions (IT, Finance, ODHR, Logistics, Communications) as well as within the Fashion division (VM, Marketing, Product, PR, Training) to best execute and achieve business objective\n\n\nPerson Specifications:\n\n\nSecondary School Graduate. University graduate a plus\nFashion / retail / luxury background an advantage\nMinimum 2 years\u2019 experience in managing a team of no less than 5 members\nFluent in English and local language, Mandarin a plus\nKnowledge of shop operations such as stock organization, cash, and credit card handling stock count measures\n\n\nAt Chanel, we are focused on creating an inclusive culture that nurtures personal growth, contributing to collective progress. We believe the uniqueness of each individual increases the diversity, complementarity and effectiveness of our teams. We strongly encourage your application, as we value the perspective, experience and potential you could bring to CHANEL", "employment_types": ["Full Time"], "selling_points": [], "locations": ["Not Specified"], "categories": ["Sales, CS & Business Devpt", "Business Development", "Others"], "post_time": "2022-01-17T03:43:36Z", "salary": {"currency": null, "max": null, "min": null, "period": "monthly", "term": null}, "salary_visible": false, "title_keywords": [], "responsibilities": ["maintenance", "operations", "inventory", "merchandising", "day-to-day operations", "teams", "specifications", "logistics", "managing a team"], "requirements": {"degrees": ["university graduate"], "majors": [], "languages": ["english", "mandarin"], "language_level": ["fluent"], "hard_skills": ["no", "plus", "maintenance"], "soft_skills": ["committed", "leadership", "inspiring", "focused"], "languages_combined": [{"language": "english", "language_level": []}, {"language": "mandarin", "language_level": ["fluent"]}]}, "experience_required": {"duration": ["minimum 2 years"], "field": ["managing a team"]}}, {"job_id": "100003009054786", "location_code": "hk", "company": "Public Finance Limited", "job_title": "Tagalog or Bahasa Speaker - Direct Sales Executives (Personal Loan)", "description": "Responsibilities\n\nProactively solicit for loan business by promoting the Company\u2019s loan products to domestic helpers (Filipino and/or Indonesian)\nOutdoor duties\n\nRequirements\n\nProactive and result-oriented\nGood connection with Filipino and/or Indonesian domestic helpers\nWilling to work on Saturday and Sunday (2 days off per week)\nH.K. permanent resident or holding a Dependent Visa\nBasic salary plus commission\nTraining will be provided\n\nPlease send a full resume with expected salary to\n\n- e-mail by clicking \"Apply Now\"\n\n\n- by whatsapp : 9309 2925\n\n- by fax no. 25225 1635\n\nPersonal data collected will be treated in the strictest confidence in accordance with our\u00a0Personal Information Collection Statement\u00a0and\u00a0Privacy Policy\u00a0and will be handled by authorized personnel for recruitment-related purposes only. All applications will be kept for a maximum period of one year as may be considered for other suitable positions within Public Finance Ltd. and its associated companies. For details, please visit the Company\u2019s website\u00a0http://www.publicfinance.com.hk", "employment_types": ["Full Time", "Permanent"], "selling_points": [], "locations": ["Not Specified"], "categories": ["Sales, CS & Business Devpt", "Customer Service - Supervisor / Officer", "Others", "Direct Sales"], "post_time": "2022-01-17T11:04:41Z", "salary": {"currency": null, "max": null, "min": null, "period": "monthly", "term": null}, "salary_visible": false, "title_keywords": ["personal", "sales"], "responsibilities": [], "requirements": {"degrees": [], "majors": [], "languages": ["indonesian"], "language_level": ["good"], "hard_skills": ["no", "whatsapp", "plus", "basic"], "soft_skills": ["confidence", "proactive", "result-oriented"], "languages_combined": [{"language": "indonesian", "language_level": ["good"]}]}, "experience_required": {"duration": [], "field": []}}, {"job_id": "100003009056057", "location_code": "hk", "company": "Dyxnet Limited", "job_title": "Product Solution Manager", "description": "Job Responsibilities:\n\n\nSolid experience in network solution, such as MPLS VPN\u3001SD-WAN.\nSupport and contribution to the network solution project in Hong Kong and Taiwan. Assist and implement the project solutions plan.\nConduct the customer needs and responsible for in depth analysis for our customer and provide insights and recommendations for network solution.\nManage Price Book and Product P&L.\nKeep track on monitoring product/solution performance, including sales, GP, service level, customer satisfactions, in order to communicate with management and partner for better synergy with mutual benefits\n\nRequirements:\n\nBachelor\u2019s degree in Information Technology, Computer Science, or related disciplines.\n5 years\u2019 relevant experience in IT & Telecommunications industry is highly preferred.\nFamiliar with networking technologies (Such as SD-WAN, MPLS and VPN).\nExcellent presentation, communication, and interpersonal skills.\nKeep learning enthusiasm for new network products and new technologies.\nPositive attitude, fast-learning, energetic, able to perform in challenging environment.\nA good team player with analytical & problem-solving skills, self-motivation and good interpersonal skills, cost, and time conscious.\n\nAttractive remuneration and compensation package, including year end bonus, medical scheme, life insurance, as well as career development opportunities will be offered.\n\nInterested parties please send your resume with expected salary and availability to Human Resources Department, Dyxnet Group, 37/F, Tower 1, Metoplaza, 223 Hing Fong Road, Kwai Fong.\n\nWelcome to visit our website: http://www.dyxnet.com for further information of our company.\n\nData collected will be used for recruitment purpose only.", "employment_types": ["Full Time", "Permanent"], "selling_points": ["Experience in network solution", "5 years\u2019 relevant", "SD-WAN, MPLS and VPN"], "locations": ["Kwai Fong"], "categories": ["Information Technology (IT)", "Product Management / Business Analyst", "Network & System", "Sales, CS & Business Devpt", "Others"], "post_time": "2022-01-18T03:14:00Z", "salary": {"currency": null, "max": null, "min": null, "period": "monthly", "term": null}, "salary_visible": false, "title_keywords": ["manager"], "responsibilities": ["communicate with", "provide insights", "management", "analysis", "monitoring", "p&l", "plan"], "requirements": {"degrees": ["degree", "bachelor"], "majors": ["related disciplines", "computer science", "information technology"], "languages": [], "language_level": [], "hard_skills": ["problem-solving skills", "sd-wan", "vpn", "scheme"], "soft_skills": ["good team player", "fast-learning", "communication", "positive attitude", "learning", "interpersonal skills", "self-motivation", "problem-solving skills", "energetic", "presentation"], "languages_combined": []}, "experience_required": {"duration": ["5 years"], "field": ["telecommunications", "it", "relevant experience"]}}, {"job_id": "100003009055117", "location_code": "hk", "company": "Autotoll Limited", "job_title": "Senior Solution Specialist/ Solution Specialist", "description": "About the Role:\nResponsible for all business development activities\nWork closely with the management team to plan, drive and execute sales and business strategies o corporate marketing and business development plans to drive business growth and success\u00a0\nDevelop business strategic plans (Sales growth, major customer management, key projects identification, develop product road maps)\nSets and manage KPI's and budgets\nProvides regular progress reporting in sales and new opportunity development\u00a0\n\nAbout you:\n\nBachelor's Degree preferred\n3 years or above experience in business development/sales, in education/ logistics industry will e an advantage\u00a0\nStrong leadership with great analytical mind, organizational skills, and strong commercial acumen\nTeam player with excellent interpersonal skills\u00a0\nGood writing and verbal communications skills in English\nFluency in Mandarin will definitely be a plus\n\nWhat you can get from us:\n\n\nOn-the-job training, learning and development provided\nExecutive workshops, interest class, corporate purchase discount offered by SHKP\nCompetitive salary and annual leaves\nFlexible working opportunities\nInterested parties, please send full resume with expected salary and available date to Human Resources and Administration Department by e-mail\u00a0[via APPLY NOW]\u00a0or by fax\u00a02111 9459.\n\n(Data collected will be used for recruitment purpose only.)", "employment_types": ["Full Time", "Permanent"], "selling_points": ["Degree holder with 3 years exp.", "Fluency in Mandarin will definitely be a plus", "Responsible for business development activities"], "locations": ["Kowloon Bay"], "categories": ["Sales, CS & Business Devpt", "Business Development", "Tele-sales (Telemarketing)", "Others"], "post_time": "2022-01-18T01:15:52Z", "salary": {"currency": null, "max": null, "min": null, "period": "monthly", "term": null}, "salary_visible": false, "title_keywords": ["specialist"], "responsibilities": ["management team", "management", "budgets", "strategic plans", "reporting", "develop", "purchase", "logistics", "plan", "plans"], "requirements": {"degrees": ["degree", "bachelor"], "majors": [], "languages": ["english", "mandarin"], "language_level": ["fluency", "good"], "hard_skills": ["workshops", "plus", "acumen"], "soft_skills": ["flexible", "organizational skills", "responsible", "analytical mind", "interpersonal skills", "learning", "team player", "leadership"], "languages_combined": [{"language": "english", "language_level": ["good"]}, {"language": "mandarin", "language_level": ["fluency"]}]}, "experience_required": {"duration": ["3 years"], "field": ["logistics industry", "business development", "education"]}}, {"job_id": "100003009051395", "location_code": "hk", "company": "Chubb Hong Kong Limited", "job_title": "Administration Assistant (Ref: JB/CHB/ADM)", "description": "Responsibilities:\n\nTo perform administrate tasks such as quotation preparation, job arrangement and invoicing\nTo handle phone calls\n\nTo liaise and take immediate action when any internal/external customer enquiry occurs\nTo prepare various reports for management and other internal teams\nTo communicate with internal teams to resolve any issues arisen during project or service delivery\nTo perform any ad-hoc tasks and activities as assigned by management from time to time\n\nRequirements:\n\nFrom 7 or above\n2-3 years administrative work experience, fresh graduates are also welcome to apply\nProficiency in using MS Office and Chinese typing is essential\nProficiency in spoken and written English and Chinese (including Putonghua is a plus)\nWith experiences in customer services area and ERP system will be an advantage\nHigh accuracy, independent, strong sense of responsibility, good communication skills and able to work under pressure\nImmediate available is an advantage\n\u00a0\n\nAttractive compensation and benefits packages will be offered to the right candidate. Interested parties, please click \"Apply Now\"\u00a0& send your application together with a full resume stating your present and expected salary and date of availability to us (please quote the reference number); or\n\nBy mail\nThe Talent Acquisition Manager, Chubb Hong Kong Limited, 10/F, Habourside HQ, 8 Lam Chak Street, Kowloon Bay, Kowloon ; or\n\nBy fax\n2764 3098\n\n\u00a0\nYou may also contact us by our recruitment hotline at 5362 3810 (WhatsApp welcomed) in case you have any enquiries.\n\nPersonal data provided in your application will be kept in the strictest confidence. It will only be used for employment-related purposes by any entity within our Group. Applicants not notified within 1 month will be considered as unsuccessful. Unsuccessful application may be kept for another 6 months for new openings or consideration by another entity within our Group before properly shredded.\n\nSecurity Licence No. : 0961", "employment_types": ["Full Time", "Permanent"], "selling_points": ["To perform administrative support", "To handle phone calls", "5-day work, full range of benefits"], "locations": ["Kowloon Bay"], "categories": ["Admin & HR", "Clerical / Admin Staff", "Sales, CS & Business Devpt", "Others", "Sales Administration"], "post_time": "2022-01-15T14:18:49Z", "salary": {"currency": null, "max": null, "min": null, "period": "monthly", "term": null}, "salary_visible": false, "title_keywords": ["administration assistant"], "responsibilities": ["liaise", "communicate with", "management", "service delivery", "ad-hoc tasks", "quotation", "teams", "invoicing", "reports", "phone calls"], "requirements": {"degrees": [], "majors": [], "languages": ["putonghua", "english", "chinese"], "language_level": ["proficiency"], "hard_skills": ["plus", "erp system", "typing", "ms office"], "soft_skills": ["work under pressure", "communication skills", "independent", "sense of responsibility"], "languages_combined": [{"language": "putonghua", "language_level": ["proficiency"]}, {"language": "english", "language_level": ["proficiency"]}, {"language": "chinese", "language_level": ["proficiency", "proficiency"]}]}, "experience_required": {"duration": ["2-3 years"], "field": ["erp system", "administrative", "customer services"]}}, {"job_id": "100003009050565", "location_code": "hk", "company": "ADECCO", "job_title": "\u6b50\u7f8e\u7c21\u7d04\u7576\u4ee3\u6642\u88dd\u54c1\u724c - \u552e\u8ca8\u54e1 / \u8cc7\u6df1\u552e\u8ca8\u54e1 (\u5e95\u85aa 16K - 18K \u8d77)", "description": "Sales \u552e\u8ca8\u54e1 / Senior Sales \u8cc7\u6df1\u552e\u8ca8\u54e1\n\n\u7dad\u6301\u5e97\u8216\u65e5\u5e38\u904b\u4f5c\n\u5e97\u5167\u7522\u54c1\u92b7\u552e\n\u900f\u904e\u96fb\u8a71\u3001\u5373\u6642\u901a\u8a0a\u8edf\u4ef6\u8207\u5ba2\u6236\u4fdd\u6301\u9577\u9060\u53ca\u826f\u597d\u95dc\u4fc2\n\u5354\u52a9\u9054\u6210\u516c\u53f8\u5b9a\u4e0b\u7684\u5718\u968a\u92b7\u552e\u76ee\u6a19\u3001\u500b\u4ebaKPI\n\u8ca8\u5834\u53ca\u5009\u5b58\u7ba1\u7406\u4ee5\u78ba\u4fdd\u5b58\u8ca8\u5145\u8db3\n\u6574\u7406\u8ca8\u7269\u53ca\u4fdd\u6301\u5e97\u5167\u6e05\u6f54\n\n\u5de5\u4f5c\u8981\u6c42:\n\n\u6d41\u5229\u5ee3\u6771\u8a71\u53ca\u666e\u901a\u8a71\uff0c\u5546\u696d\u7528\u82f1\u8a9e\n2\u5e74\u6216\u4ee5\u4e0a\u96f6\u552e\u7d93\u9a57\u6703\u512a\u5148\u8003\u616e\uff08\u6709\u6642\u88dd\u7d93\u9a57\u66f4\u4f73\uff09\n\u6b61\u8fce\u6027\u683c\u9032\u53d6\uff0c\u62b1\u6709\u6a02\u65bc\u5b78\u7fd2\u5fc3\u614b\u8005\uff0c\u7d93\u9a57\u4e0d\u62d8\n\u5c0d\u6642\u88dd\u6709\u57fa\u672c\u8a8d\u8b58\n\u63d0\u4f9b\u89aa\u5584\u6709\u79ae\u7684\u9867\u5ba2\u670d\u52d9\n\n\u5de5\u4f5c\u5730\u9ede: \u4e2d\u74b0 / \u91d1\u9418 / \u9285\u947c\u7063 / \u5c16\u6c99\u5480 / \u6c99\u7530 / \u6771\u6d8c\n\n\u798f\u5229\uff1a\n\n\u512a\u539a\u5e95\u85aa (SA: 16k | SSA: 18k)\n\u8c50\u539a\u4f63\u91d1\n\u6bcf\u67087\u5929\u5047\u671f\n\u9280\u884c\u5047\n\u82b1\u7d05 (\u4e00\u5e743\u6b21)\n\u6709\u85aa\u5e74\u5047\n\u91ab\u7642\u53ca\u7259\u79d1\u6d25\u8cbc\n\u826f\u597d\u7684\u6649\u5347\u6a5f\u6703\n\u5b8c\u5584\u5de5\u4f5c\u57f9\u8a13\n\nIf you're interested in this role, please please\u00a0CLICK HERE\u00a0or\u00a0click 'Apply Now' to apply the position via Adecco website with your CV, or if you would like to have a further discussion about this role, please contact Mr. Luk on +852 2899 6103 .\n\n\u5982\u60a8\u5c0d\u6b64\u8077\u4f4d\u611f\u8208\u8da3\uff0c\u8acb\u9ede\u64ca\u201cApply Now\u201d\u900f\u904eAdecco\u7db2\u7ad9\u4e0a\u8f09\u60a8\u7684\u7684\u500b\u4eba\u5c65\u6b77\u7533\u8acb\u6b64\u8077\u4f4d\uff0c\u82e5\u60a8\u5c0d\u6b64\u8077\u4f4d\u6709\u4efb\u4f55\u67e5\u8a62\u4ea6\u53ef\u81f4\u96fb +852 2899 6103 \u8207\u9678\u5148\u751f\u806f\u7d61\u3002\n\nPlease note that only short listed candidates will be notified. All information gathered will be treated in strict confidence and solely used for recruitment purposes", "employment_types": ["Full Time", "Permanent"], "selling_points": [], "locations": ["Tsim Sha Tsui"], "categories": ["Sales, CS & Business Devpt", "Retail Sales", "Others"], "post_time": "2022-01-14T10:44:21Z", "salary": {"currency": "HKD", "max": 29999, "min": 25000, "period": "monthly", "term": null}, "salary_visible": true, "title_keywords": ["\u552e\u8ca8\u54e1"], "responsibilities": ["recruitment", "contact", "website"], "requirements": {"degrees": [], "majors": [], "languages": [], "language_level": [], "hard_skills": [], "soft_skills": ["interested in", "confidence"], "languages_combined": []}, "experience_required": {"duration": [], "field": []}}, {"job_id": "100003009053637", "location_code": "hk", "company": "Bare Limited", "job_title": "Trainee \u7f8e\u5bb9\u5b78\u5f99 / \u521d\u7d1a\u7f8e\u5bb9\u5e2b", "description": "\n\u5168\u884c\u6700\u9ad8\u4f63\u91d1\n\u5718\u968a\u734e\u91d1\u3001\u4ecb\u7d39\u4eba\u734e\u91d1\n\u534a\u5e74\u5305\u85aa $17k\n\u6bcf\u6708\u5e73\u5747 7-8 \u5929\u6709\u85aa\u4f8b\u5047\n\u9022\u661f\u671f\u65e5\u4f11\u606f\uff0c\u53ef\u8207\u661f\u671f\u65e5\u3001\u4e00\u53ca\u4e8c\u9023\u653e\u4e09\u5929\n\u6c23\u6c1b\u878d\u6d3d\u7121\u9b25\u722d\n\u6bcf\u6708\u76e1\u4eab\u514d\u8cbb\u7642\u7a0b\n\u54e1\u5de5\u7642\u7a0b\u512a\u60e0\n\u00a0 \u8077\u8cac\uff1a\n\u2022 \u5354\u52a9\u904b\u4f5c\u7f8e\u5bb9\u9662\u65e5\u5e38\u5de5\u4f5c\n\u2022 \u5411\u5ba2\u4eba\u63d0\u4f9b\u512a\u8cea\u5c08\u696d\u7f8e\u5bb9\u670d\u52d9\n\u2022 \u70ba\u5ba2\u6236\u9032\u884c\u7f8e\u5bb9\u53ca\u6fc0\u5149\u7642\u7a0b\n\u2022 \u8ddf\u9032\u5ba2\u4eba\u7642\u7a0b\u53ca\u552e\u5f8c\u670d\u52d9\n\u2022 \u8207\u5ba2\u4eba\u5efa\u7acb\u826f\u597d\u95dc\u4fc2\n\n\u8981\u6c42\uff1a\n\u2022 \u6d41\u5229\u5ee3\u6771\u8a71\n\u2022 \u6c92\u6709\u76f8\u95dc\u7f8e\u5bb9\u7d93\u9a57\u4ea6\u53ef\n\u2022 \u6301\u8a8d\u53ef\u5c08\u696d\u7f8e\u5bb9\u6587\u6191\u6216\u8b49\u66f8\u8005\u512a\u5148\n\u2022 \u7a4d\u6975\u4e3b\u52d5\n\u2022 \u601d\u60f3\u6b63\u9762\u3001\u5bcc\u8cac\u4efb\u611f\u3001\u670d\u52d9\u614b\u5ea6\u53cb\u5584\u3001\u6027\u683c\u958b\u6717\n\u2022 \u5c0d\u7f8e\u5bb9\u884c\u696d\u6709\u71b1\u8aa0\n\n\u524d\u7dda\u54e1\u5de5\u798f\u5229\ufe30\n\u2022 \u6bcf\u5929\u5de5\u4f5c9\u5c0f\u6642\n\u2022 \u661f\u671f\u516d\u53ca\u516c\u773e\u5047\u671f\u5747\u53ef\u65e9\u6536\n\u2022 \u7bc0\u65e5\u65e9\u653e\n\u2022 \u63d0\u4f9b\u5a5a\u5047\u3001\u751f\u65e5\u5047\u3001\u6069\u6064\u5047\n\u2022 \u52a0\u73ed\u88dc\u9418\n\u2022 \u5c08\u696d\u514d\u8cbb\u5728\u8077\u57f9\u8a13\n\u2022 \u7279\u5feb\u6649\u5347\u6a5f\u6703\n\u2022 \u8cfc\u7269\u512a\u60e0\u53ca\u514d\u8cbb\u7642\u7a0b\n\u2022 \u5bb6\u5c6c\u597d\u53cb\u6298\u6263\u512a\u60e0\n\u00a0 \u5de5\u4f5c\u5730\u9ede\ufe30\u65fa\u89d2 / \u9285\u947c\u7063 / \u89c0\u5858\n\n", "employment_types": ["Full Time"], "selling_points": [], "locations": ["Kwun Tong"], "categories": ["Admin & HR", "Others", "Sales, CS & Business Devpt", "Business Development", "Others"], "post_time": "2022-01-17T07:16:33Z", "salary": {"currency": null, "max": null, "min": null, "period": "monthly", "term": null}, "salary_visible": false, "title_keywords": ["trainee"], "responsibilities": [], "requirements": {"degrees": [], "majors": [], "languages": [], "language_level": [], "hard_skills": [], "soft_skills": [], "languages_combined": []}, "experience_required": {"duration": [], "field": []}}, {"job_id": "100003009053180", "location_code": "hk", "company": "Softcube Systems Limited", "job_title": "Sales Executive/ Sales Manager (5-day work)", "description": "JOB DUTIES:\n\nExplore potential\u00a0clients, develop and maintain the existing clients through the effective telephone call, internet;\nVisit potential customers for new business\nHandle new customer accounts from initial approach to closing the sales\nFollow up with customer requirement. Record and analyze customer information;\nProvide recommendations or various solutions to the clients that company offers;\nNegotiate/close deals;\nComplete the targets according to the sales plan.\n\nREQUIREMENT:\n\nForm 6 or HKDSE above; degree / diploma holder is preferred.\nFresh graduates are also welcome.\nExperience in Customer Services or Telesales is an advantage\nStrong interpersonal skills with good telephone manner\nSales result oriented, self-motivated, self-initiating and responsibility\nFluent in English and Cantonese language, a communicative level of Mandarin is preferred\nImmediate availability is highly preferred.\n\n\u00a0WHAT WE OFFER:\n\nA friendly and motivating environment\n5-day work week\nMedical allowance\nAttractive annual leave, maternity leave scheme\nHighly competitive basic salary, sales commission, performance bonus and MPF", "employment_types": ["Full Time"], "selling_points": ["5-day work week", "Performance bonus", "Friendly and motivating environment"], "locations": ["Ngau Tau Kok"], "categories": ["Sales, CS & Business Devpt", "Business Development", "Others", "Direct Sales"], "post_time": "2022-01-17T06:19:27Z", "salary": {"currency": null, "max": null, "min": null, "period": "monthly", "term": null}, "salary_visible": false, "title_keywords": ["sales manager", "sales executive"], "responsibilities": ["maintain", "telephone call", "develop"], "requirements": {"degrees": ["diploma holder", "degree", "hkdse"], "majors": [], "languages": ["cantonese", "english", "mandarin"], "language_level": ["fluent"], "hard_skills": [], "soft_skills": ["result oriented", "interpersonal skills", "self-motivated", "telephone manner"], "languages_combined": [{"language": "cantonese", "language_level": ["fluent"]}, {"language": "english", "language_level": ["fluent"]}, {"language": "mandarin", "language_level": ["fluent"]}]}, "experience_required": {"duration": [], "field": ["telesales", "customer services"]}}, {"job_id": "100003009052184", "location_code": "hk", "company": "UL International Limited", "job_title": "Senior Sales Executive (E&E background)", "description": "Works independently under minimal supervision and drives the sale of designated specialty TIC products and services in collaboration with account owners.\u00a0\n\nSupports development of GAM and SAM multi-year account plans in TIC by providing insight on area of specialization (specific product / service)\nContributes to the development of strategy for their assigned specialized TIC products / services by providing input on customer needs, pain points, trends, etc. to product / service manager\nMaintains ongoing plan to prioritize portfolio of accounts and maintain relationships throughout the year\nInterfaces with customer and UL delivery teams during sales that require additional technical expertise for highly technical TIC services\nUses technical credibility to build relationships with buyers and centers of influence, in support of GAM, SAM and KAMs (serving Global accounts)\nCommunicates value proposition of assigned specialty products / services to clients based on highly technical knowledge\nServes as main point of client contact for specialty TIC products / services throughout sales cycle\nWorks under minimal guidance of the sales leadership on proposals and closings in the field for assigned specialty TIC product / service sales as directed by GAM, SAM or regionally focused Global support KAM\nSeeks and actions on opportunities to sell specialty product / services\nWorks with the account managers on discovery and opportunity identification for assigned specialty products / services\nWorks with account managers (GAMs, SAMs, KAMs) to seamlessly work with customers throughout the sales cycle\nServes as primary point of contact for specialty products / services, responsible for articulating value proposition and managing client interactions\nBrings in additional technical resources (e.g., engineers) when needed to support sales opportunities of assigned specialty products / services\nProvides input to account owner during account planning process on potential growth opportunities within assigned solution area\nMakes connections and builds trusted advisor status with relevant account owners\nSupports smooth hand-off of customer to implementation teams or TIC customer success post-sale\n\nWhat you\u2019ll experience working at UL:\n\nMission: For UL, corporate and social responsibility isn\u2019t new.\u00a0 Making the world a safer, more secure and sustainable place has been our business model for the last 125 years and is deeply engrained in everything we do.\u00a0\nPeople: Ask any UL employee what they love most about working here, and you\u2019ll almost always hear, \u201cthe people.\u201d Going beyond what is possible is the standard at UL.\u00a0 We\u2019re able to deliver the best because we employ the best.\nInteresting work: Every day is different for us here as we eagerly anticipate the next innovation that our customers\u2019 create. We\u2019re inspired to take on the challenge that will transform how people live, work and play. And as a global company, in many roles,\u00a0you will get international experience working with colleagues around the world.\nGrow & achieve: We learn, work and grow together with targeted development, reward and recognition programs as well as our very own UL University that offers extensive training programs for employees at all stages, including a technical training track for applicable roles.\nTotal Rewards:\nCompetitive remuneration package\nFriendly environment and collaborative colleagues\nCasual dress code\nTraining and Development (provided by Talent & ULU)\n\nWhat makes you a great fit\uff1a\n\n\nBachelor\u2019s and/or graduate degree in engineering or related field\nProficient in MS Office (Word, PowerPoint, Excel, Outlook), and CRM software\nRelevant technical capabilities related to assigned specialty product / service\n6+ years of related sales experience\nDeep knowledge and experience with specialty product / services within assigned TIC portfolio\nProven ability to meet and exceed sales targets\nBusiness acumen and deep understanding of business sales processes", "employment_types": ["Full Time", "Permanent"], "selling_points": ["UL \u69ae\u7372\u6aa2\u6e2c\u8a8d\u8b49\u4eba\u529b\u767c\u5c55\u6a5f\u69cb\u734e", "Global collaboration and Exposure", "5-days work week, 13th salary, Competitive bonus"], "locations": ["Shatin Area"], "categories": ["Sales, CS & Business Devpt", "Sales - Sales Management", "Technical Sales / Sales Engineer", "Others"], "post_time": "2022-01-17T02:22:31Z", "salary": {"currency": null, "max": null, "min": null, "period": "monthly", "term": null}, "salary_visible": false, "title_keywords": ["senior sales executive"], "responsibilities": ["maintain relationships", "guidance", "software", "planning process", "teams", "implementation", "contact", "plan", "plans"], "requirements": {"degrees": ["degree", "bachelor"], "majors": ["engineering"], "languages": [], "language_level": [], "hard_skills": ["excel", "word", "powerpoint", "acumen", "outlook", "code", "gams", "ms office"], "soft_skills": ["independently", "focused", "responsible", "deep", "collaborative", "prioritize", "extensive", "friendly", "smooth", "business acumen", "leadership"], "languages_combined": []}, "experience_required": {"duration": ["6+ years"], "field": ["related"]}}, {"job_id": "100003009055108", "location_code": "hk", "company": "Autotoll Limited", "job_title": "Customer Liaison Assistant", "description": "\u5de5\u4f5c\u7bc4\u570d:\n\n\u4ee5\u96fb\u8a71\u63a8\u5ee3\u7522\u54c1\u53ca\u8ddf\u9032\u56de\u8a2a\u5ba2\u4eba\uff0c\u8655\u7406\u76f8\u95dc\u6587\u4ef6\u5de5\u4f5c\uff0c\u8ddf\u9032\u5408\u7d04\u4e8b\u5b9c\n\n\u5165\u8077\u8981\u6c42:\n\n\u6709\u4e00\u5e74\u6216\u4ee5\u4e0a\u96fb\u8a71\u92b7\u552e\u53ca\u6587\u8077\u76f8\u95dc\u5de5\u4f5c\u7d93\u9a57\n\u6709\u57fa\u672c\u96fb\u8166\u61c9\u7528\u77e5\u8b58\n\u5c0d\u6c7d\u8eca\u884c\u696d\u6709\u57fa\u672c\u8a8d\u8b58\u512a\u5148\n\u4e00\u822c\u570b\u8a9e\u53ca\u82f1\u6587\n\n\n\n\nWhat you can get from us\n\nOn-the-job training, learning and development\u00a0provided\nExecutive workshops, interest class, corporate purchase discount offered by SHKP\nCompetitive salary and annual leaves\nFlexible working opportunities\n\nInterested parties, please send full resume with\u00a0expected salary\u00a0and\u00a0available date\u00a0to Human Resources and Administration Department by e-mail or by fax 2111 9459.\n\n(Data collected will be used for recruitment purpose only.)", "employment_types": ["Temporary", "Contract"], "selling_points": ["\u6709\u4e00\u5e74\u6216\u4ee5\u4e0a\u96fb\u8a71\u92b7\u552e\u53ca\u6587\u8077\u76f8\u95dc\u5de5\u4f5c\u7d93\u9a57", "\u6709\u57fa\u672c\u96fb\u8166\u61c9\u7528\u77e5\u8b58", "\u5c0d\u6c7d\u8eca\u884c\u696d\u6709\u57fa\u672c\u8a8d\u8b58\u512a\u5148"], "locations": ["Kowloon Bay"], "categories": ["Sales, CS & Business Devpt", "Others"], "post_time": "2022-01-18T01:15:14Z", "salary": {"currency": null, "max": null, "min": null, "period": "monthly", "term": null}, "salary_visible": false, "title_keywords": ["assistant"], "responsibilities": ["purchase"], "requirements": {"degrees": [], "majors": [], "languages": [], "language_level": [], "hard_skills": ["workshops"], "soft_skills": ["flexible", "learning"], "languages_combined": []}, "experience_required": {"duration": [], "field": []}}, {"job_id": "100003009048801", "location_code": "hk", "company": "South Horizons Management Limited", "job_title": "ASSISTANT SPORTS & RECREATION OFFICER (RESIDENTIAL CLUB)", "description": "Diploma holder or above in Recreation Management or\u00a0Physical Education\nRelevant working experience preferred\nGood interpersonal and communication skills\nFluent in spoken and written English and Chinese\nGood PC knowledge preferred\nShift duty required\u00a0\n\nWe offer salary and benefits commensurate with qualifications and experience. Please send a full resume with contact telephone number and expected salary to Senior Estate Manager - South Horizons Management Limited, Management Office, G/F., Block 33A, South Horizons, Ap Lei Chau, Hong Kong (Please quote reference on envelope) or by clicking \"Apply now\".\n\nWe are an equal opportunity employer and welcome applications from all qualified candidates. The information provided will be treated in strict confidence and be used only for consideration of your application for relevant/similar post(s).\n\nApplicants not hearing from us within six weeks from the date of advertisement may consider their applications unsuccessful. All personal data of unsuccessful applicants will be destroyed after the recruitment exercise when no longer required.", "employment_types": ["Full Time", "Permanent"], "selling_points": ["Diploma holder", "Relevant working experience", "Good PC knowledge"], "locations": ["Aberdeen"], "categories": ["Admin & HR", "Clerical / Admin Staff", "Beauty Care / Health", "Athletics / Fitness / Sports & Recreation", "Sales, CS & Business Devpt", "Others"], "post_time": "2022-01-17T06:29:09Z", "salary": {"currency": null, "max": null, "min": null, "period": null, "term": null}, "salary_visible": false, "title_keywords": ["sports & recreation officer", "assistant"], "responsibilities": ["communication", "management"], "requirements": {"degrees": ["diploma holder"], "majors": [], "languages": ["english", "chinese"], "language_level": ["fluent"], "hard_skills": ["pc knowledge"], "soft_skills": ["communication skills", "interpersonal"], "languages_combined": [{"language": "english", "language_level": ["fluent"]}, {"language": "chinese", "language_level": ["fluent"]}]}, "experience_required": {"duration": [], "field": ["relevant working experience"]}}, {"job_id": "100003009052447", "location_code": "hk", "company": "Orient Overseas Container Line Ltd (OOCL)", "job_title": "Assistant / Deputy Manager, Strategic Planning, Trans-Atlantic Trade (Ref: AMDM/SP/TAT)", "description": "Responsibilities:\n\nTo review and optimize TAT network efficiency & vessel deployment strategy in conjunction with commercial requirement\nTo resolve commercial/traffic\u2019s concerns from network perspective\nTo conduct market research and analysis projects to assist the strategic planning for the trade; provide analytical works to support day-to-day commercial decisions\nTo prepare KPI reports on performance evaluation and analysis; yield assessment for various market segments\nTo monitor cost and risk exposure\nTo prepare marketing/PR promotion\nTo support Strategic Planning on reporting and perform other ad hoc task and project as assigned\n\n\u00a0Requirements:\n\nUniversity graduate in Business/Logistics and related disciplines\nMinimum 3 years\u2019 relevant working experience in Container Liner Shipping Company\nGood communication, analytical and problem solving skills\nAble to work independently and team-oriented\nProficiency in spoken and written English and Chinese; Putonghua is a plus\nCompetency in Windows applications\n\n\nInterested parties please send your application letter with detailed resume and expected salary by clicking\u00a0\"Apply Now\" .\n(Data collected will be used for recruitment purpose only.)", "employment_types": ["Full Time", "Permanent"], "selling_points": ["To review and optimize TAT network efficiency", "University graduate in Business/Logistics", "Minimum 3 years\u2019 relevant working experience"], "locations": ["Wan Chai"], "categories": ["Transportation & Logistics", "Shipping", "Marketing / Public Relations", "Marketing - Market Research", "Sales, CS & Business Devpt", "Others"], "post_time": "2022-01-17T03:03:52Z", "salary": {"currency": null, "max": null, "min": null, "period": "monthly", "term": null}, "salary_visible": false, "title_keywords": ["deputy manager", "assistant"], "responsibilities": ["reporting", "cost", "ad hoc", "strategic planning", "analysis", "conduct market research", "review", "monitor", "reports", "evaluation"], "requirements": {"degrees": ["university graduate"], "majors": ["related disciplines", "business"], "languages": ["putonghua", "english", "chinese"], "language_level": ["proficiency"], "hard_skills": ["problem solving skills", "container", "plus"], "soft_skills": ["communication", "analytical and problem solving skills", "work independently"], "languages_combined": [{"language": "putonghua", "language_level": []}, {"language": "english", "language_level": ["proficiency"]}, {"language": "chinese", "language_level": ["proficiency"]}]}, "experience_required": {"duration": ["minimum 3 years"], "field": ["relevant working experience"]}}, {"job_id": "100003009056320", "location_code": "hk", "company": "Sidefame Ltd", "job_title": "Senior Sales / Sales Associate - The Little Shop (Jewelry, Artwork and Artisanal Accessories)", "description": "The Little Shop\u81f4\u529b\u8a2a\u904d\u5168\u7403\u7cbe\u54c1\u5de5\u4f5c\u574a\uff0c\u7cbe\u5fc3\u532f\u805a\u4e00\u7cfb\u5217\u5de5\u85dd\u7d30\u81a9\u7684\u73e0\u5bf6\u98fe\u54c1\u3001\u624b\u5de5\u914d\u98fe\u3001\u85dd\u8853\u53ca\u751f\u6d3b\u8a2d\u8a08\u4f5c\u54c1\u3002\u6bcf\u4ef6\u7531\u5718\u968a\u89aa\u81ea\u641c\u7f85\u7684\u7cbe\u54c1\u90fd\u662f\u5de5\u5320\u5225\u51fa\u5fc3\u88c1\u6253\u9020\u7684\u7470\u5bf6\uff0c\u5c07\u7d93\u5178\u4e8b\u7269\u8207\u5927\u81ea\u7136\u6700\u7f8e\u597d\u7684\u4e00\u77ac\u5b9a\u683c\u5448\u73fe\uff0c\u6bcf\u500b\u7d30\u7bc0\u90fd\u5f77\u5f7f\u5728\u8a34\u8aaa\u5176\u7b87\u4e2d\u6545\u4e8b\uff0c\u70ba\u751f\u6d3b\u6ce8\u5165\u6642\u5149\u7684\u6eab\u5ea6\u3002\n\n\u5de5\u4f5c\u8077\u8cac:\n\n\u8ca0\u8cac\u92b7\u552e\u5de5\u4f5c\u3001\u63a8\u5ee3\u54c1\u724c\u548c\u63d0\u4f9b\u5c08\u696d\u914d\u642d\u670d\u88dd\u610f\u898b\n\u5354\u52a9\u5e97\u5185\u7684\u65e5\u5e38\u71df\u904b\u548c\u8ca8\u5b58\u7ba1\u7406\n\u8207\u9867\u5ba2\u5efa\u7acb\u53ca\u7dad\u6301\u826f\u597d\u95dc\u4fc2,\u4ee5\u9054\u81f3\u500b\u4eba\u92b7\u552e\u76ee\u6a19\u548c\u5e97\u92eaKPIs\n\n\u5165\u8077\u8981\u6c42:\n\n\u5177\u5099\u4e00\u5e74\u6216\u4ee5\u4e0a\u6642\u88dd\u96f6\u552e\u92b7\u552e\u7d93\u9a57\n\u80fd\u64cd\u6d41\u5229\u7cb5\u8a9e,\u57fa\u672c\u82f1\u8a9e\u53ca\u666e\u901a\u8a71\n\u4e3b\u52d5\u6709\u79ae\u53ca\u5177\u826f\u597d\u6e9d\u901a\u6280\u5de7\n\n\n\u54e1\u5de5\u798f\u5229:\n\nWork-life balance\n\u914c\u60c5\u6027\u82b1\u7d05\n\u5e74\u5047\u53ca\u751f\u65e5\u5047\u671f\n\u516c\u773e\u5047\u671f\n\u91ab\u751f\u3001\u7259\u91ab\u53ca\u57fa\u672c\u9ad4\u6aa2\u798f\u5229\n\u4ecb\u7d39\u4eba\u734e\u91d1\n\u96c6\u5718\u7522\u54c1\u8cfc\u7269\u512a\u60e0\n\u5c08\u696d\u5728\u8077\u57f9\u8a13\u53ca\u589e\u503c\u8ab2\u7a0b\u200b\n\u9032\u4fee\u6d25\u8cbc\n\u826f\u597d\u6649\u5347\u6a5f\u6703\n\n\n\u6709\u610f\u8005\u8acb\u6309 \"Apply Now\" \u7533\u8acb, \u4e26\u5217\u660e\u7533\u8acb\u8077\u4f4d\u548c\u85aa\u91d1\u8981\u6c42; \u6216\u53ef\u5faa\u4ee5\u4e0b\u9014\u5f91\u9810\u7d04\u9762\u8a66:\n\u62db\u8058\u71b1\u7dda :\u00a02956 9058/ 2956 9075\n\n\u62db\u8058 WhatsApp :\u00a06700 0580\n\nSidefame Limited \u4e43\u5e73\u7b49\u6a5f\u6703\u50f1\u4e3b\u2027\n<\u7533\u8acb\u4eba\u63d0\u4f9b\u4e4b\u5168\u90e8\u8cc7\u6599\u7d55\u5c0d\u4fdd\u5bc6\uff0c\u4e26\u53ea\u4f5c\u62db\u8058\u7528\u9014>\n\nOur Brands:-\n\nAnteprima\u00a0-\u00a0ig: anteprimaofficial\n\nAnteprima Wirebag\u00a0-\u00a0ig: anteprimaofficial\n\nCocktail\u00a0-\u00a0ig: cocktailselectshop\n\nAtsuro Tayama\u00a0-\u00a0ig: atsurotayama\n\nMarimekko\u00a0-\u00a0ig: marimekkohk\n\n45R\u00a0-\u00a0ig: 45r_hk\n\nThe Little Shop\u00a0-\u00a0ig: thelittleshop.hk\n\nWelcome to follow us on Instagram!", "employment_types": ["Full Time", "Permanent"], "selling_points": [], "locations": ["Causeway Bay"], "categories": ["Sales, CS & Business Devpt", "Retail Sales", "Others"], "post_time": "2022-01-18T03:56:59Z", "salary": {"currency": null, "max": null, "min": null, "period": "monthly", "term": null}, "salary_visible": false, "title_keywords": ["senior sales", "sales associate"], "responsibilities": [], "requirements": {"degrees": [], "majors": [], "languages": [], "language_level": [], "hard_skills": ["whatsapp"], "soft_skills": [], "languages_combined": []}, "experience_required": {"duration": [], "field": []}}, {"job_id": "100003009051398", "location_code": "hk", "company": "Chubb Hong Kong Limited", "job_title": "Administration Assistant (Tendering)", "description": "Responsibilities:\n\nTo manage new maintenance contract and contract renewal for customer\nTo coordinate in tender submission and maintenance agreement\n\nTo maintain customer management system records\nTo perform full range administrative support, including secretaries works data entry and reports preparation etc.\nTo perform any ad-hoc tasks assigned by management\n\nRequirements:\n\nFrom 7 or above\n2-3 years administrative work experience\nProficiency in using MS Office and Chinese typing is essential\nProficiency in spoken and written English and Chinese (including Putonghua is a plus)\nWith experiences in customer services area and ERP system will be an advantage\nHigh accuracy, independent, strong sense of responsibility, good communication skills and able to work under pressure\nImmediate available is an advantage\n\u00a0\n\nAttractive compensation and benefits packages will be offered to the right candidate. Interested parties, please click \"Apply Now\"\u00a0& send your application together with a full resume stating your present and expected salary and date of availability to us (please quote the reference number); or\n\nBy mail\nThe Talent Acquisition Manager, Chubb Hong Kong Limited, 10/F, Habourside HQ, 8 Lam Chak Street, Kowloon Bay, Kowloon ; or\n\nBy fax\n2764 3098\n\n\u00a0\nYou may also contact us by our recruitment hotline at 5362 3810 (WhatsApp welcomed) in case you have any enquiries.\n\nPersonal data provided in your application will be kept in the strictest confidence. It will only be used for employment-related purposes by any entity within our Group. Applicants not notified within 1 month will be considered as unsuccessful. Unsuccessful application may be kept for another 6 months for new openings or consideration by another entity within our Group before properly shredded.\n\nSecurity Licence No. : 0961", "employment_types": ["Full Time", "Permanent"], "selling_points": ["To perform administrative support", "To coordinate in tender submission", "5-day work, full range of benefits"], "locations": ["Kowloon Bay"], "categories": ["Admin & HR", "Clerical / Admin Staff", "Sales, CS & Business Devpt", "Others", "Sales Administration"], "post_time": "2022-01-15T14:23:48Z", "salary": {"currency": null, "max": null, "min": null, "period": "monthly", "term": null}, "salary_visible": false, "title_keywords": ["administration assistant"], "responsibilities": ["management", "maintenance", "administrative support", "data entry", "ad-hoc tasks", "coordinate", "maintain", "reports", "tender", "maintenance contract"], "requirements": {"degrees": [], "majors": [], "languages": ["putonghua", "english", "chinese"], "language_level": ["proficiency"], "hard_skills": ["plus", "erp system", "typing", "ms office"], "soft_skills": ["work under pressure", "communication skills", "independent", "sense of responsibility"], "languages_combined": [{"language": "putonghua", "language_level": ["proficiency"]}, {"language": "english", "language_level": ["proficiency"]}, {"language": "chinese", "language_level": ["proficiency", "proficiency"]}]}, "experience_required": {"duration": ["2-3 years"], "field": ["erp system", "administrative", "customer services"]}}, {"job_id": "100003009050620", "location_code": "hk", "company": "EC Healthcare", "job_title": "Training Assistant (Fresh graduates are also welcome)", "description": "Main Job Tasks & Responsibilities:\n\nTo provide general training administrative support, e.g. generating reports, updating training materials, SOP, guide books\nTo manage and support operation of Learning Project;\nTo assist in pre- and post-training logistics with internal or external parties to ensure smooth delivery of training initiative;\nTo assist in preparing training materials, including in-class training and e-learning/ mobile app learning materials in alignment with the prevailing operational developments and corporate training directives;\nTo manage customers' database, prepare and deliver promotion materials to potential customers and conduct marketing survey;\nTo conduct training evaluation and prepare training statistics in regular basis;\nTo assist in creating development plan for training service of the Association and promotion strategies;\n\nQualifications & Experience:\n\nBachelor\u2019s Degree holder, 5 passes in HKCEE\n1-2 years relevant experience in learning & development\nProficiency in both spoken and written Chinese and English\nGood interpersonal and communication skills\nProactive and willing to work overtime, under pressure, and with\nminimum supervision\nSelf-motivated, quick response, able to work independently and\nunder pressure\nProficient computer skills including Word, Excel and PowerPoint\nImmediate availability preferred", "employment_types": ["Full Time", "Permanent"], "selling_points": ["Fresh graduate (intern experience)", "Training administrative support", "Familiar with PowerPoint"], "locations": ["Mong Kok"], "categories": ["Admin & HR", "HR Supporting Staff", "Training & Development", "Sales, CS & Business Devpt", "Others"], "post_time": "2022-01-14T10:58:59Z", "salary": {"currency": null, "max": null, "min": null, "period": "monthly", "term": null}, "salary_visible": false, "title_keywords": ["assistant"], "responsibilities": ["mobile app", "administrative support", "external parties", "communication", "logistics", "reports", "database", "evaluation", "plan"], "requirements": {"degrees": ["bachelor", "degree holder"], "majors": [], "languages": ["english", "chinese"], "language_level": ["proficiency"], "hard_skills": ["excel", "word", "powerpoint", "mobile", "computer skills"], "soft_skills": ["communication skills", "work overtime", "proactive", "under pressure", "self-motivated", "work independently", "learning", "smooth", "initiative", "interpersonal"], "languages_combined": [{"language": "english", "language_level": ["proficiency"]}, {"language": "chinese", "language_level": ["proficiency"]}]}, "experience_required": {"duration": ["1-2 years"], "field": ["learning & development", "relevant experience"]}}]