[{"job_id": "100003009054782", "location_code": "hk", "company": "Asiaray Advertising Media Limited", "job_title": "Sales Coordination Supervisor", "description": "Responsibilities:\n\nProvide sales support to the sales team\nAssist in preparing advertising proposals and sales materials\nPrepare and follow up sales orders\nLiaise\u00a0with various internal and external stakeholders / department to ensure day-to-day operations running smoothly\nHandle logistic planning to ensure timely delivery and maintain effective and efficient daily workflow\n\nRequirements:\n\nForm 6 or above\nAt least 5 years related working experience\nDemonstrate good communication, interpersonal and customer services skills\nWell-organized, outgoing and a good team player\nProficiency in MS Office applications including Word, Excel, Outlook and PowerPoint\nFamiliar with common design software including Photoshop and Adobe Illustrator will be an advantage\nExperience in photo retouch and design mock up for proposal and censorship will be an advantage\nGood command in both spoken and written English and Chinese\nImmediate available is preferred\n\nWe offer a competitive remuneration package, 5-Day work, medical insurance, dental\u00a0insurance\u00a0to the right candidate. Interested parties are invited to send their applications with full resume stating availability date, present and expected salary to us.\n\n\nApplicants not invited for interview within 6 weeks may consider their applications unsuccessful. Personal data provided by job applicants will be used strictly in accordance with our personal data policy and for recruitment purposes only.\n", "employment_types": ["Full Time", "Permanent"], "selling_points": ["Sales administration support to sales team", "Project coordination", "Prepare and follow up sales orders"], "locations": ["Quarry Bay"], "categories": ["Sales, CS & Business Devpt", "Customer Service - Supervisor / Officer", "Account Servicing", "Sales Administration"], "post_time": "2022-01-17T11:03:49Z", "salary": {"currency": null, "max": null, "min": null, "period": "monthly", "term": null}, "salary_visible": false, "title_keywords": ["supervisor", "sales"], "responsibilities": ["advertising", "day-to-day operations", "maintain", "sales team", "liaise with", "planning"], "requirements": {"degrees": [], "majors": [], "languages": ["english", "chinese"], "language_level": ["good command"], "hard_skills": ["excel", "word", "powerpoint", "adobe illustrator", "outlook", "photoshop", "ms office"], "soft_skills": ["outgoing", "good team player", "customer services skills", "well-organized", "communication", "interpersonal"], "languages_combined": [{"language": "english", "language_level": ["good command"]}, {"language": "chinese", "language_level": ["good command"]}]}, "experience_required": {"duration": ["at least 5 years"], "field": ["related", "photo", "design"]}}, {"job_id": "100003009049742", "location_code": "hk", "company": "Jackel Porter Co Ltd", "job_title": "Sales Administrator", "description": "Responsibilities\n\nTo provide clerical and administrative support to sales and marketing team\nTo update and maintain the database\nMaintain good customer relationship and promote company services\nAssist in sales and marketing activities\nAssist in drafting quotations / proposals / agreement for clients\nMaintain relationships with existing customers\nAnswering customers calls\nRequirements\n\nForm 5/DSE or above qualification\n1-2 year of working experience in customer support, customer service or service admin\u00a0\nProficiency in MS Office Applications (MS Word, Excel)\nGood command in English & Chinese\u00a0\nShort notice and immediate available is preferred", "employment_types": ["Full Time"], "selling_points": ["Free shuttle bus provided", "Form 5/DSE or above qualification", "Experience in Sales Admin/Services Support role"], "locations": ["Tai Po Area"], "categories": ["Admin & HR", "Clerical / Admin Staff", "Sales, CS & Business Devpt", "Customer Service - Supervisor / Officer", "Sales Administration"], "post_time": "2022-01-14T09:11:24Z", "salary": {"currency": null, "max": null, "min": null, "period": "monthly", "term": null}, "salary_visible": false, "title_keywords": ["sales administrator"], "responsibilities": ["maintain relationships", "maintain", "database", "administrative support"], "requirements": {"degrees": ["form 5", "dse"], "majors": [], "languages": ["english", "chinese"], "language_level": ["good command"], "hard_skills": ["ms word", "excel", "ms office"], "soft_skills": ["customer service"], "languages_combined": [{"language": "english", "language_level": ["good command"]}, {"language": "chinese", "language_level": ["good command"]}]}, "experience_required": {"duration": ["1-2 year"], "field": ["admin", "customer service"]}}, {"job_id": "100003009054179", "location_code": "hk", "company": "Max Deco Company", "job_title": "Sales Co-ordinator / Sales Administration Clerk", "description": "Job Highlights:\u00a0\n\nHandle sales orders, reports, inventory control and account receivable\nProvide admin and customer services\u2019 support\n\nJob Description:\u00a0 \u00a0 \u00a0 \u00a0 \u00a0 \u00a0 \u00a0 \u00a0 \u00a0 \u00a0 \u00a0 \u00a0 \u00a0 \u00a0 \u00a0 \u00a0 \u00a0 \u00a0 \u00a0 \u00a0 \u00a0 \u00a0 \u00a0 \u00a0 \u00a0 \u00a0 \u00a0\n\nFollow up sales inquiries / sales leads\nResponsible for handling PO from customers and PO processing to vendor\nPrepare quotations / project costing and delivery documents\nProvide clerical and administrative support\nKeep track of sales orders and follow up delivery with suppliers\nHandle enquiries\u00a0phone\u00a0call, data entry and document filing\nPrepare various\u00a0sales related reports\u00a0\u00a0\nAssist in ad-hoc projects as assigned by supervisor\nOutdoor work is necessary\n\n\u00a0Requirements:\n\n\u00a0F.5\u00a0or above\u00a0\nGood command of spoken and written English\u00a0\nGood in MS office applications particularly with MS Word, Excel & Chinese word processing\nGood Presentation, communication and interpersonal skills\nAttentive, Self-motivated, well organized, good responsible and willing to learn\nSelf-motivated, willing to learn new things and\u00a0with positive attitude\nGoal oriented,\u00a0well organized, responsible, attentive to details and able to work on tight schedules", "employment_types": ["Full Time"], "selling_points": [], "locations": ["Kwun Tong"], "categories": ["Building & Construction", "Architectural Services", "Sales, CS & Business Devpt", "Customer Service - Supervisor / Officer", "Sales Administration"], "post_time": "2022-01-17T08:41:30Z", "salary": {"currency": null, "max": null, "min": null, "period": "monthly", "term": null}, "salary_visible": false, "title_keywords": ["clerk", "sales"], "responsibilities": ["document filing", "outdoor work", "administrative support", "data entry", "schedules", "customer services", "communication", "handle enquiries", "inventory control", "reports", "ad-hoc projects"], "requirements": {"degrees": [], "majors": [], "languages": ["english", "chinese"], "language_level": ["good command", "good"], "hard_skills": ["excel", "chinese word processing", "vendor", "goal", "processing", "ms office", "ms word"], "soft_skills": ["attentive", "self-motivated", "responsible", "attentive to details", "well organized", "willing to learn", "positive attitude", "communication and interpersonal skills", "presentation", "goal oriented"], "languages_combined": [{"language": "english", "language_level": ["good command", "good"]}, {"language": "chinese", "language_level": ["good"]}]}, "experience_required": {"duration": [], "field": []}}, {"job_id": "100003009053245", "location_code": "hk", "company": "Shiamas Limited", "job_title": "Sales Administrator", "description": "Responsibilities:\n\nTo assist in ordering, inventory control and sales administration\nLocal logistic co-ordination for shops and warehouse\nHandling invoicing and logistics for wholesales accounts\nGenerating monthly sales reports and analysis reports through POS system\u00a0\n\n\n\nRequirements:\n\nF.5 standard or above with at least 3 years experience in sales admin. of retail industry\nAnalytical mind, familiar with Microsoft Excel\nGood team player with excellent interpersonal and communications skills\nHighly independent and well organized, ability to work under pressure\n\n\n\nWe offer attractive remuneration with fringe benefits to the right candidate.\u00a0 Interested parties, please send your detail resume with expected salary, available date via email to our Human Resources Department by clicking 'Apply Now'.", "employment_types": ["Full Time"], "selling_points": ["At least 3 years experience in sales admin.", "Analytical mind, familiar with Microsoft Excel", "inventory control and sales administration"], "locations": ["Not Specified"], "categories": ["Admin & HR", "Clerical / Admin Staff", "Transportation & Logistics", "Inventory / Warehousing", "Sales, CS & Business Devpt", "Sales Administration"], "post_time": "2022-01-17T09:32:15Z", "salary": {"currency": null, "max": null, "min": null, "period": "monthly", "term": null}, "salary_visible": false, "title_keywords": ["sales administrator"], "responsibilities": ["sales administration", "sales reports", "analysis reports", "invoicing", "inventory control", "logistics"], "requirements": {"degrees": [], "majors": [], "languages": [], "language_level": [], "hard_skills": ["microsoft excel"], "soft_skills": ["highly independent", "good team player", "well organized", "analytical mind", "interpersonal", "work under pressure"], "languages_combined": []}, "experience_required": {"duration": ["at least 3 years"], "field": ["admin"]}}, {"job_id": "100003009055307", "location_code": "hk", "company": "SDL Atlas Limited", "job_title": "Sales & Services Coordinator", "description": "Duties:\n- Provide sales and administrative support to the Sales team.\n- Handle sales enquiries and order processing with customers, and liaising with factories and suppliers for delivery schedules\n- Monitor shipping schedules; arrange shipping documents & samples delivery/return\n- Data entry and generate to report\n- Able to work independently. No need for overseas travelling.\nRequirements:\n- DSE or above\n- 1 - 3 years experiences in sales or customer services related fields\n- Good command of written and spoken English as well as Mandarin.\n- Good communication skill & a team player\n- Proficient in MS office and Chinese word processing", "employment_types": ["Full Time"], "selling_points": ["Fresh graduates will be considered", "Provide support to the Sales team", "5 days work / Bank holidays / Double pay"], "locations": ["Lai Chi Kok"], "categories": ["Sales, CS & Business Devpt", "Sales Administration"], "post_time": "2022-01-18T02:07:31Z", "salary": {"currency": null, "max": null, "min": null, "period": "monthly", "term": null}, "salary_visible": false, "title_keywords": ["coordinator", "sales"], "responsibilities": ["shipping documents", "shipping", "administrative support", "schedules", "data entry", "monitor", "liaising with", "sales team", "order processing", "report"], "requirements": {"degrees": ["dse"], "majors": [], "languages": ["english", "chinese", "mandarin"], "language_level": ["good command", "proficient"], "hard_skills": ["chinese word processing", "ms office"], "soft_skills": ["team player", "communication skill"], "languages_combined": [{"language": "english", "language_level": ["good command"]}, {"language": "chinese", "language_level": ["proficient"]}, {"language": "mandarin", "language_level": ["good command"]}]}, "experience_required": {"duration": ["1 - 3 years"], "field": ["related", "customer services"]}}, {"job_id": "100003009052569", "location_code": "hk", "company": "Mitsui & Co (HK) Ltd", "job_title": "Sales Administrator", "description": "We are now inviting candidate of high calibre to join us in the following capacity in our Iron & Steel Division.\n\nJob Duties:\n\nTo handle import / export shipping documents\nTo support sales staff to contact customers or suppliers as necessary\nTo perform general administrative and clerical support for the division, such as car booking, meeting room booking, expense claims, arrange hotel booking and business trip etc.\nTo perform other ad-hoc projects and tasks as assigned\nRequirements:\n\nAt least 2 \u2013 5 years\u2019 relevant working experience in shipping area\nExperience in SAP system is preferable\nStrong communication & interpersonal skills\nAble to work under pressure and complete the jobs within time constraint\nGood command of English and Mandarin\nGood command of Microsoft Office Tools (e.g. Word, Excel) and Chinese Typing\nDiploma graduate, commercial studies\n\nInterested parties please apply with your full resume stating present and expected salary.\n\nAll information will be kept confidential and used for recruitment purpose only. Although we endeavour to respond to every applicant, this may not always be possible so if you receive no response within 60 days, please consider your application for this specific vacancy to be unsuccessful.\n\n", "employment_types": ["Full Time", "Permanent"], "selling_points": [], "locations": ["Admiralty"], "categories": ["Sales, CS & Business Devpt", "Others", "Others", "Trading", "Sales Administration"], "post_time": "2022-01-17T03:26:34Z", "salary": {"currency": null, "max": null, "min": null, "period": "monthly", "term": null}, "salary_visible": false, "title_keywords": ["sales administrator"], "responsibilities": ["shipping documents", "business trip", "contact", "administrative and clerical support", "booking", "ad-hoc projects"], "requirements": {"degrees": ["diploma"], "majors": [], "languages": ["english", "chinese", "mandarin"], "language_level": ["good command"], "hard_skills": ["excel", "sap", "microsoft office", "typing", "word"], "soft_skills": ["communication", "interpersonal skills", "work under pressure"], "languages_combined": [{"language": "english", "language_level": ["good command"]}, {"language": "chinese", "language_level": []}, {"language": "mandarin", "language_level": ["good command"]}]}, "experience_required": {"duration": ["5 years"], "field": ["relevant working experience"]}}, {"job_id": "100003009054840", "location_code": "hk", "company": "Hong Kong Parkview", "job_title": "SALES COORDINATOR", "description": "Requirements\n\nHigher Diploma graduate or above\n2 years relevant experience, preferably in trading company\nPrevious experience in sales administration and order follow up\nWell-organized, cheerful, flexible with good communication skills\nComputer knowledge in using MS Office including Word, Excel\nGood command of English and conversational Putonghua\nFresh graduates of degree or higher diploma are considered\nImmediate available will be an advantage\n\nResponsibilities\n\nHandle daily communications with customers, vendors and internal parties\nPrepare sales related documents including PO, invoice and delivery documents\nCoordinate delivery schedules and update the order information in SAP system\nParticipate in organizing trade fairs and ad hoc projects as assigned\n\nWe offer attractive remuneration package and promising career prospect to the right candidates. Interested parties please send full resume with expected/last salary and date of available by clicking \u2018Apply Now\u2019", "employment_types": ["Full Time", "Permanent"], "selling_points": ["5-day work week", "Guarantee 13 months pay", "Free duty meal and shuttle bus"], "locations": ["Wan Chai Area"], "categories": ["Hospitality / F & B", "Hospitality / Hotel Services", "Sales, CS & Business Devpt", "Sales Administration"], "post_time": "2022-01-17T11:39:11Z", "salary": {"currency": null, "max": null, "min": null, "period": "monthly", "term": null}, "salary_visible": false, "title_keywords": ["sales coordinator"], "responsibilities": ["communications with", "related documents", "invoice", "schedules", "prepare sales", "coordinate", "ad hoc projects", "internal parties"], "requirements": {"degrees": ["diploma", "degree"], "majors": [], "languages": ["putonghua", "english"], "language_level": ["conversational", "good command"], "hard_skills": ["excel", "word", "ms office"], "soft_skills": ["flexible", "communication skills", "cheerful", "well-organized"], "languages_combined": [{"language": "putonghua", "language_level": ["good command"]}, {"language": "english", "language_level": ["conversational", "good command"]}]}, "experience_required": {"duration": ["2 years"], "field": ["sales administration", "relevant experience", "trading"]}}, {"job_id": "100003009055660", "location_code": "hk", "company": "Dah Chong Hong, Limited", "job_title": "Sales Admin Clerk", "description": "Responsibilities:\nAssist the Sales Team in sales administration and all matters related to suite and\u00a0catering sales areas\nAnswer guest enquiries regarding general sales issues\nPrepare and distribute daily, weekly and monthly reports\nIssue License Agreement, confirmation and quotation for sales team\nIssues Event Orders and communicate with concerned departments\nRequirements:\n\nDegree or Diploma holder in Hospitality Management or related discipline\nA minimum of 6 months of post-graduate work experience\nGood command of English, Cantonese and Mandarin with strong interpersonal and communication skills\nGood computer proficiency\nExperience in hotel / Clubhouse with knowledge of Opera system is preferable\n\nWe offer competitive remuneration package including 5-day work week, family medical plan, birthday leave, duty meal and free shuttle bus (to and from Central; to Causeway Bay, Wanchai, Admiralty, and Aberdeen) and excellent career opportunities to the right candidate.\u00a0\n\nPlease send full resume, expected salary and contact telephone number to\nHong Kong Parkview\nHuman Resources Department\n88 Tai Tam Reservoir Road, Hong Kong\nConfidential Fax No. 28123490\nEmail by clicking \"Apply Now\".\n(All data collected will be used for recruitment purpose only)\nwww.hongkongparkview.com", "employment_types": ["Full Time", "Permanent"], "selling_points": [], "locations": ["Kowloon Bay"], "categories": ["Admin & HR", "Clerical / Admin Staff", "Sales, CS & Business Devpt", "Customer Service - Supervisor / Officer", "Sales Administration"], "post_time": "2022-01-18T02:50:10Z", "salary": {"currency": null, "max": null, "min": null, "period": "monthly", "term": null}, "salary_visible": false, "title_keywords": ["admin clerk", "sales"], "responsibilities": ["communicate with", "sales administration", "quotation", "sales team", "assist the sales", "weekly and monthly reports", "catering"], "requirements": {"degrees": ["diploma holder", "degree"], "majors": ["hospitality management"], "languages": ["cantonese", "english", "mandarin"], "language_level": ["good command"], "hard_skills": ["no"], "soft_skills": ["communication skills", "interpersonal"], "languages_combined": [{"language": "cantonese", "language_level": ["good command"]}, {"language": "english", "language_level": ["good command"]}, {"language": "mandarin", "language_level": ["good command"]}]}, "experience_required": {"duration": [], "field": []}}, {"job_id": "100003009053529", "location_code": "hk", "company": "Palace One Limited", "job_title": "Sales Coordinator", "description": "Job Descriptions:\u00a0\n\nProvide administration support to sales team\nPrepare sales order related documents and sales summary report\nLiaise with internal and external parties to follow up the order delivery and logistic arrangement\nSupport the sales team to implement sales and promotion activities\n\nThe ideal candidate should be:\n\nDiploma or above\nAt least\u00a01-2 years relevant experience in FMCG industry will be an advantage\nIndependent, self-motivated, hardworking and reliable\nGood communication skills and able to work under pressure\nProficiency in MS Office\nImmediate available is highly preferred\n\nPlease send your application with resume and expected salary to The HR Manager, Dah Chong Hong, Ltd, 8/F, DCH Building, 20 Kai Cheung Road, Kowloon Bay by post or email to click\u00a0\"Apply Now\".\n\nWe are equal opportunities employer. Applicants who are not invited within 2 months may consider their application unsuccessful. All applicants may be considered for other suitable positions with DCH Group / CITIC Pacific Group and will be deleted from our files after 6 months from the date of application.", "employment_types": ["Full Time"], "selling_points": [], "locations": ["Wan Chai"], "categories": ["Sales, CS & Business Devpt", "Business Development", "Account Servicing", "Sales Administration"], "post_time": "2022-01-17T07:06:32Z", "salary": {"currency": null, "max": null, "min": null, "period": "monthly", "term": null}, "salary_visible": false, "title_keywords": ["sales coordinator"], "responsibilities": ["administration", "related documents", "work under pressure", "hr", "internal and external parties", "prepare sales", "logistic arrangement", "communication", "sales team", "liaise with", "report"], "requirements": {"degrees": ["diploma or above"], "majors": [], "languages": [], "language_level": [], "hard_skills": ["fmcg industry", "ms office"], "soft_skills": ["communication skills", "self-motivated", "independent", "work under pressure", "reliable", "hardworking", "ideal"], "languages_combined": []}, "experience_required": {"duration": ["at least 1-2 years"], "field": ["fmcg", "relevant experience"]}}, {"job_id": "100003009055972", "location_code": "hk", "company": "Hong Kong Trade Development Council", "job_title": "Sales Support Coordinator (1-year Contract)", "description": "Responsibilities:\n\nResponsible for handling both retails and project team sales order and prepare sales document (such as quotation, sales invoice, delivery note etc)\nResponsible for handling incoming customers' enquiry\nSupport routine operation\nRequirements:\n\nCandidates with no relevant working experience are welcomed.\nWilling to learn, responsible.\nGood command of English is an advantage.\nComputer Literacy and familiar with Microsoft office (Excel, Word & Outlook, etc)\nBenefits:\n\n5 days, Competitive salary\n10 days Annual leave + Birthday leave + Bank Holiday\nInterested parties please send your resume with availability, expected salary by clicking \"APPLY NOW\" or contact Mr. Chan at 9368 6884 via whatsapp.", "employment_types": ["Full Time", "Contract"], "selling_points": ["Clerical and sales administrative support", "Stable working hours", "Renewable contract"], "locations": ["Wan Chai"], "categories": ["Admin & HR", "Clerical / Admin Staff", "Sales, CS & Business Devpt", "Account Servicing", "Sales Administration"], "post_time": "2022-01-18T03:08:36Z", "salary": {"currency": null, "max": null, "min": null, "period": "monthly", "term": null}, "salary_visible": false, "title_keywords": ["coordinator", "sales"], "responsibilities": ["invoice", "quotation", "prepare sales"], "requirements": {"degrees": [], "majors": [], "languages": ["english"], "language_level": ["advantage", "good command"], "hard_skills": ["excel", "no", "microsoft office", "word", "outlook"], "soft_skills": ["computer literacy", "willing to learn", "responsible"], "languages_combined": [{"language": "english", "language_level": ["advantage", "good command"]}]}, "experience_required": {"duration": [], "field": ["relevant working experience"]}}, {"job_id": "100003009052886", "location_code": "hk", "company": "3PL-Total Technology (HK) Limited", "job_title": "Sales Administration Officer", "description": "Ref. No.: 318/SSC/DGB/HKTDC\n\nResponsibilities:\n\n\nPrepare consolidated call lists from the databank and other internal systems for the sales team\nCreate and cross-check new customer accounts in CRM for the sales team\nHandle daily enquiries from customers\nProvide clerical and sales administrative support such as preparing sales reports\nProvide logistics support and prepare sales materials for the team\nCoordinate with other teams or departments for product display\nPerform on-site duties\n\nRequirements:\n\n\nHigh Diploma or Post-secondary graduate with minimum 2 years' of work experience\nMeticulous and organized\nA team player with excellent customer service skills\nGood communication and problem-solving skills\nProficient in MS Office applications including Excel and Chinese Word Processing\nGood command of English and Chinese\nAble to work under pressure and tight deadlines\n\nRemuneration and Benefits:\n\nThe successful candidate will be appointed on a fixed-term contract basis, renewable subject to operational needs. Salary will be commensurate with qualifications and experience.\u00a0\u00a0\n\nApplication Procedure:\n\nInterested candidates are invited to complete the application form on our website at http://www.hktdc.com/careers.html. Those who do not hear from us within EIGHT WEEKS after the closing date may assume their applications unsuccessful.\n\nAll information provided by applicants will be treated in strict confidence and used only for recruitment purposes. Applicants may be considered for other suitable positions within the Council. Their personal data will be destroyed six months after the selection is finalised.\n\n\n%MCEPASTEBIN%", "employment_types": ["Full Time", "Permanent"], "selling_points": ["1+ yr experience in sales support or CS", "Good chance to explore marketing knowledge & exp.", "Internet company culture"], "locations": ["Wong Tai Sin Area"], "categories": ["Sales, CS & Business Devpt", "Customer Service - Supervisor / Officer", "Marketing / Public Relations", "Marketing - General / Support", "Sales Administration"], "post_time": "2022-01-17T04:25:26Z", "salary": {"currency": null, "max": null, "min": null, "period": "monthly", "term": null}, "salary_visible": false, "title_keywords": ["administration officer", "sales"], "responsibilities": ["sales reports", "prepare sales", "coordinate with", "teams", "provide logistics support", "sales administrative support", "sales team", "internal systems"], "requirements": {"degrees": ["high diploma"], "majors": [], "languages": ["english", "chinese"], "language_level": ["good command", "proficient"], "hard_skills": ["problem-solving skills", "chinese word processing", "excel", "ms office"], "soft_skills": ["organized", "meticulous", "customer service skills", "communication", "problem-solving skills", "team player", "work under pressure"], "languages_combined": [{"language": "english", "language_level": ["good command"]}, {"language": "chinese", "language_level": ["good command", "proficient"]}]}, "experience_required": {"duration": ["minimum 2 years"], "field": []}}, {"job_id": "100003009054204", "location_code": "hk", "company": "Hellolulu Living Solutions Limited", "job_title": "Sales Coordinator (Sales Operation Based)", "description": "Job Responsibilities\n\nHandle daily sales orders and invoices, including Retail, Wholesale and Online channels\nPrepare regular weekly / monthly sales related report for team and management review\nProvide sales support to the sales team and coordinate with internal departments\nHandle customer enquiries regarding general sales issues product information or complaints\nManage stock return and exchange policy\nPerform ad-hoc tasks as required\n\nJob Requirements\n\nForm 5 or above, with 1-2 years of solid working experience in retail industry\nResponsible, good working attitude and communication skills\u00a0\nAble to manage multiple tasks and work independently\nProficiency in MS Office including PivotTable and VLOOKUP\nExperience in sales-oriented, order &amp; invoice processing is preferable\nImmediately availability is highly preferred\n\nWe offer 5-days work week and attractive remuneration package to right candidate. Interested parties please send detailed resume with expected salary and availability by clicking \"Apply Now\" to submit your application.\n\nOnly shortlisted candidates will be notified. Applicants who are not contacted within\u00a04 weeks may consider their applications unsuccessful.\u00a0All personal data collected will be treated in strict confidence and be used for recruitment purpose only.\n\nHellolulu Living Solution Limited is an equal opportunities employer.", "employment_types": ["Full Time", "Permanent"], "selling_points": ["Minimum 2 years of relevant working experience", "5-days work week", "Immediately availability is preferred"], "locations": ["Wong Tai Sin Area"], "categories": ["Sales, CS & Business Devpt", "Customer Service - Supervisor / Officer", "Wholesale", "Sales Administration"], "post_time": "2022-01-17T08:49:39Z", "salary": {"currency": null, "max": null, "min": null, "period": "monthly", "term": null}, "salary_visible": false, "title_keywords": ["sales coordinator", "sales"], "responsibilities": ["online channels", "handle customer enquiries", "invoices", "ad-hoc tasks", "coordinate with", "sales team", "management review", "report"], "requirements": {"degrees": ["form 5 or above"], "majors": [], "languages": [], "language_level": [], "hard_skills": ["vlookup", "processing", "ms office"], "soft_skills": ["communication skills", "good working attitude", "work independently", "responsible", "multiple tasks"], "languages_combined": []}, "experience_required": {"duration": ["1-2 years"], "field": ["retail industry"]}}, {"job_id": "100003009051659", "location_code": "hk", "company": "Tai Chi Solutions Limited", "job_title": "sales administrator / shipping assistant", "description": "- issuing quotation, purchase orders, invoices\n- issuing packing list and delivery note\n- arrange goods delivery\n- printing production and luxury packaging experience is an advantage", "employment_types": ["Full Time"], "selling_points": ["5 day work", "lunch including", "near MTR station"], "locations": ["Chai Wan"], "categories": ["Transportation & Logistics", "Shipping", "Sales, CS & Business Devpt", "Sales Administration"], "post_time": "2022-01-16T21:50:33Z", "salary": {"currency": null, "max": null, "min": null, "period": "monthly", "term": null}, "salary_visible": false, "title_keywords": ["sales administrator", "shipping", "assistant"], "responsibilities": ["purchase", "quotation", "invoices", "packing list"], "requirements": {"degrees": [], "majors": [], "languages": [], "language_level": [], "hard_skills": [], "soft_skills": [], "languages_combined": []}, "experience_required": {"duration": [], "field": []}}, {"job_id": "100003009053109", "location_code": "hk", "company": "SmarTone Telecommunications Limited", "job_title": "Senior Sales Operations Officer / Sales Operations Officer", "description": "Key responsibilities (Not limited to the following):\n\nCoordinating, monitoring, tracking, and processing incoming consignments\nOpening packages, verifying and labeling contents, creating a record of each item in the database\nKeeping items in database up to date and accurate, auditing contracts and other consignment paperwork for accuracy\nResearching the status of consignments\nProcessing shipping requests\nMonitor the progress of shipments and deliveries, conferring with suppliers to troubleshoot and rectify problems in a timely manner and ensuring that interested parties are apprised of the status of the shipment.\nParticipate in ad-hoc duties as requested, not limited to additional main and mid-season auction based duties which may include, but are not limited to, telephone and online bidding support\n\nQualification Requirements:\n\n\n\nHigh School Diploma is a must (College degree is preferred). Fresh graduate is also considered\nFluent verbal and written English and Chinese (including Mandarin)\nAbility to learn quickly and apply knowledge\nExcellent communication and interpersonal skills; demonstrated ability to communicate with all organizational levels\nAbility to work both independently and as a team member to complete the task at hand\nStrong organizational skills to set priorities, multi task and meet deadlines\nProficiency in Microsoft Offices skills\nDuring auction, flexibility to work overtime and weekend hours when necessary is required", "employment_types": ["Full Time", "Permanent"], "selling_points": ["Prepare user requirement for new process design", "Review system logic and perform UAT", "Conduct regular compliance check"], "locations": ["Ngau Tau Kok"], "categories": ["Marketing / Public Relations", "Marketing - General / Support", "Sales, CS & Business Devpt", "Sales - Sales Management", "Sales Administration"], "post_time": "2022-01-17T05:52:55Z", "salary": {"currency": null, "max": null, "min": null, "period": "monthly", "term": null}, "salary_visible": false, "title_keywords": ["sales", "operations officer", "senior sales"], "responsibilities": ["shipping", "contracts", "monitoring", "database", "contents", "auditing", "tracking"], "requirements": {"degrees": [], "majors": [], "languages": [], "language_level": [], "hard_skills": [], "soft_skills": [], "languages_combined": []}, "experience_required": {"duration": [], "field": []}}, {"job_id": "100003009053126", "location_code": "hk", "company": "Konew Financial Express Ltd", "job_title": "Operations Support Officer (Merchant Services)", "description": "Job Duties:\n\n\nAssist in sales order fulfilment process\u00a0\u00a0\nAssist in the advertisement censorship process to comply with necessary regulations\nPrepare reports and presentation for business update, revenue forecast and occupancy tracking\nProvide support in business development projects bidding and implementation\nConduct regular review on existing workflow to enhance efficiency and effectiveness of the approval process\nJob Requirements:\nForm 6 or above\n2 years of relevant working experience in sales administration, customer service or logistics operation\nExposure in advertising media is preferred\nMulti-task, able to work under pressure and meet tight deadline\nAttention to details, sensitive to figures, well-organized, with strong sense of responsibility\nProficient in MS applications including Word, Excel, PowerPoint and Outlook\nGood command of both spoken and written English, Cantonese and Mandarin\nCandidate with more experience would be considered for the position of Senior Sales Administration Executive\nImmediate availability is highly preferred\u00a0\n\nWe offer competitive remuneration package including 5-Day work, medical & dental insurance, birthday leave to the right candidate. Interested parties, please send your full resume with available date and expected salary to us.\n\nApplicants not invited for interview within 6 weeks may consider their applications unsuccessful. Personal data provided by job applicants will be used strictly in accordance with our personal data policy and for recruitment purposes only.", "employment_types": ["Full Time"], "selling_points": ["Monitor daily trade settlement & daily transaction", "Assist in reviewing merchant account opening", "Provide clerical support to operations team"], "locations": ["Central"], "categories": ["Admin & HR", "Clerical / Admin Staff", "E-commerce", "Business Development", "Sales, CS & Business Devpt", "Sales Administration"], "post_time": "2022-01-17T05:59:52Z", "salary": {"currency": null, "max": null, "min": null, "period": "monthly", "term": null}, "salary_visible": false, "title_keywords": ["operations", "officer"], "responsibilities": ["regulations", "provide support", "implementation", "regular review", "forecast", "prepare reports", "tracking"], "requirements": {"degrees": [], "majors": [], "languages": ["cantonese", "english", "mandarin"], "language_level": ["good command"], "hard_skills": ["excel", "ms applications", "word", "powerpoint", "outlook"], "soft_skills": ["multi-task", "sense of responsibility", "sensitive to figures", "well-organized", "customer service", "attention to details", "meet tight deadline", "work under pressure"], "languages_combined": [{"language": "cantonese", "language_level": ["good command"]}, {"language": "english", "language_level": ["good command"]}, {"language": "mandarin", "language_level": ["good command"]}]}, "experience_required": {"duration": ["2 years"], "field": ["sales administration", "relevant working experience", "customer service", "logistics", "operation"]}}, {"job_id": "100003009054804", "location_code": "hk", "company": "Asiaray Advertising Media Limited", "job_title": "Sales Administration Executive", "description": "Responsibility:\n\n\nProvide administrative support to merchandising team\u00a0including\u00a0execution issues in the store level to be well communicated to related parties\nAssist on monitoring the merchandising team and work closely with internal and external parties\nPrepare weekly and monthly report\u00a0\nAd hoc tasks assigned\u00a0\n\nRequirements:\n\nDiploma or above\nAt least 1 - 2years of related working experience\nGood Communication Skills, detail-minded, multi-tasking & willing to learn\u00a0\nGood knowledge of Excel and Word (Pivot-table and V-lookup is a must)\u00a0\nProficiency in English and Chinese\u00a0\n\nAll applications received will be used exclusively for recruitment purposes only. Applicants who are not contacted within 8 weeks should consider their application unsuccessful for the position advertised. Data supplied by applicants will be kept for 6 months.", "employment_types": ["Full Time", "Permanent"], "selling_points": ["Assist in sales order fulfilment process", "Prepare data for business update, revenue forecast", "Immediate availability is highly preferred"], "locations": ["Quarry Bay"], "categories": ["Sales, CS & Business Devpt", "Sales Administration"], "post_time": "2022-01-17T11:10:40Z", "salary": {"currency": null, "max": null, "min": null, "period": "monthly", "term": null}, "salary_visible": false, "title_keywords": ["administration executive", "sales"], "responsibilities": ["internal and external parties", "monitoring", "merchandising", "ad hoc tasks", "monthly report", "provide administrative support"], "requirements": {"degrees": ["diploma or above"], "majors": [], "languages": ["english", "chinese"], "language_level": ["proficiency"], "hard_skills": ["excel", "word"], "soft_skills": ["detail-minded", "communication skills", "multi-tasking", "willing to learn"], "languages_combined": [{"language": "english", "language_level": ["proficiency"]}, {"language": "chinese", "language_level": ["proficiency"]}]}, "experience_required": {"duration": [], "field": ["related"]}}, {"job_id": "100003009055702", "location_code": "hk", "company": "Integrated Market Services Asia Limited", "job_title": "Sales Admin", "description": "Job Duties:\n\n\nHandle customer inquiries of our product\nPrepare quotation, invoice, and chase payment\nPerform pre-sales and post-sales activities such as product demonstration\nPrepare sales and marketing materials such as PPT, brochure\nPromote and update new features of our product on social media\nAssist in developing training material and conducting product training\nOther daily tasks assigned by the manager\nRequirements:\n\nBachelor's degree in any discipline,\u00a0Business Administration, and design-related disciplines are preferred.\nOne-year work experience in the sales and customer support field is preferred;\nExcellent command of both spoken and written English and Chinese;\nKnowledge in video editing and design software such as After Effects and Photoshop will be an advantage;\nIndependent, flexible, willing to learn, a strong sense of responsibility, and detail-minded;\nGood presentation, problem solving, and communication skills\n\nWe offer a competitive remuneration package, excellent career development opportunities to the right candidates. If you are interested in our company and the position, please submit your cover letter, resume with expected salary, and earliest available date to us.", "employment_types": ["Full Time"], "selling_points": [], "locations": ["Kowloon Bay"], "categories": ["Admin & HR", "Clerical / Admin Staff", "Sales, CS & Business Devpt", "Sales Administration"], "post_time": "2022-01-18T02:52:03Z", "salary": {"currency": null, "max": null, "min": null, "period": "monthly", "term": null}, "salary_visible": false, "title_keywords": ["admin", "sales"], "responsibilities": ["sales activities", "social media", "customer inquiries", "invoice", "quotation", "prepare sales", "developing", "payment", "marketing materials"], "requirements": {"degrees": ["degree", "bachelor"], "majors": ["related disciplines", "business administration", "design"], "languages": ["english", "chinese"], "language_level": ["excellent"], "hard_skills": ["video editing", "after effects", "problem solving", "photoshop"], "soft_skills": ["flexible", "detail-minded", "communication skills", "independent", "sense of responsibility", "willing to learn", "problem solving", "presentation"], "languages_combined": [{"language": "english", "language_level": ["excellent"]}, {"language": "chinese", "language_level": ["excellent"]}]}, "experience_required": {"duration": [], "field": []}}, {"job_id": "100003009054876", "location_code": "hk", "company": "Kalloc Studio Asia Limited", "job_title": "Customer Support and Sales", "description": "Office Location: Tsim Sha Tsui\n\nJob Description\n\nThe position is directed to Branch/ Division managers,\n\n1)\u00a0\u00a0\u00a0\u00a0\u00a0 Provide all-round secretarial and administrative support in a timely, accurate and complete manner, including but not limited to:\n\n-\u00a0\u00a0\u00a0\u00a0\u00a0\u00a0\u00a0\u00a0\u00a0 Assist in preparing presentation materials\n\n-\u00a0\u00a0\u00a0\u00a0\u00a0\u00a0\u00a0\u00a0\u00a0 Assist in planning team engagement activities as requested\n\n-\u00a0\u00a0\u00a0\u00a0\u00a0\u00a0\u00a0\u00a0\u00a0 Maintain good relationship with internal and external parties\n\n2)\u00a0\u00a0\u00a0\u00a0\u00a0 Pre-job and onboard arrangement to associates, including but not limited to:\n\n-\u00a0\u00a0\u00a0\u00a0\u00a0\u00a0\u00a0\u00a0\u00a0 Initiate and monitor recruitment schemes\n\n-\u00a0\u00a0\u00a0\u00a0\u00a0\u00a0\u00a0\u00a0\u00a0 Arrange meetings and appointments with candidates and managers\n\n-\u00a0\u00a0\u00a0\u00a0\u00a0\u00a0\u00a0\u00a0\u00a0 Assist in planning team engagement activities as requested\n\nJob Requirement\n\n-\u00a0\u00a0\u00a0\u00a0\u00a0\u00a0\u00a0\u00a0\u00a0 Degree in any discipline\n\n-\u00a0\u00a0\u00a0\u00a0\u00a0\u00a0\u00a0\u00a0\u00a0 2 years' experience or above\n\n-\u00a0\u00a0\u00a0\u00a0\u00a0\u00a0\u00a0\u00a0\u00a0 Proficient use of Microsoft Office/ Excel/ PowerPoint and other illustration tools\n\n-\u00a0\u00a0\u00a0\u00a0\u00a0\u00a0\u00a0\u00a0\u00a0 Very strong sense of responsibility\n\n-\u00a0\u00a0\u00a0\u00a0\u00a0\u00a0\u00a0\u00a0\u00a0 Efficient, detail and performance oriented\n\n-\u00a0\u00a0\u00a0\u00a0\u00a0\u00a0\u00a0\u00a0\u00a0 Independent and self-motivated\n\n-\u00a0\u00a0\u00a0\u00a0\u00a0\u00a0\u00a0\u00a0\u00a0 Good command of spoken and written Chinese (both Cantonese and Mandarin), and English", "employment_types": ["Full Time"], "selling_points": [], "locations": ["Shatin Area"], "categories": ["Sales, CS & Business Devpt", "Account Servicing", "Technical Sales / Sales Engineer", "Sales Administration"], "post_time": "2022-01-17T12:17:27Z", "salary": {"currency": null, "max": null, "min": null, "period": "monthly", "term": null}, "salary_visible": false, "title_keywords": ["sales"], "responsibilities": ["administrative support", "internal and external parties", "monitor", "maintain good relationship", "recruitment", "arrange meetings", "planning"], "requirements": {"degrees": ["degree"], "majors": [], "languages": ["cantonese", "english", "chinese", "mandarin"], "language_level": ["good command"], "hard_skills": ["excel", "illustration", "powerpoint", "microsoft office"], "soft_skills": ["efficient", "self-motivated", "independent", "sense of responsibility"], "languages_combined": [{"language": "cantonese", "language_level": ["good command"]}, {"language": "english", "language_level": ["good command"]}, {"language": "chinese", "language_level": ["good command"]}, {"language": "mandarin", "language_level": ["good command"]}]}, "experience_required": {"duration": ["2 years"], "field": []}}, {"job_id": "100003009054495", "location_code": "hk", "company": "\u5b8f\u5de5\u6709\u9650\u516c\u53f8", "job_title": "Administrative Assistant/ Officer", "description": "Job Descriptions:\n\nProvide full range of secretarial, administration and personal support for the sales team; updates RSMs by consolidating, analyzing, and forwarding daily action summaries\nPrepare Pre-Sales document, such as quotation; communicate with suppliers of costs,information sourcing and selection, prepare presentation format and materials\nPerform sales support, communicate with different departments, oversea branch offices\u00a0and global clients via email and phone\nConduct sales report, tender document, maintain customer database, etc\nHandle ad-hoc projects as assigned\n\nJob Requirements:\n\nDiploma or Degree holder preferred\n1-2 years experience in sales support or customer services; experience in global or regional business is an advantage\nFlexible, patient, independent, good team player and willing to work under pressure\nProficiency in MS Office\nGood command of Cantonese, English and Mandarin\nKnowledge in SAP is an advantage\n\nWe offer 5-day work week, adorable and friendly working environment, medical and other fringe benefits to the successful candidate. Please send in your application with detailed resume, availability, present and expected salary, and also quoting our reference number.\n\nTo know more about us, please visit http://www.vega-global.com/ or Corporate Video http://youtu.be/APdIdtkIHeE", "employment_types": ["Full Time", "Permanent", "Contract"], "selling_points": ["5-day-work", "Considerable salary with development bonus", "Career path to Office Manager"], "locations": ["Tsim Sha Tsui"], "categories": ["Admin & HR", "Personal / Executive Assistant", "Recruitment / Executive Search", "Sales, CS & Business Devpt", "Sales Administration"], "post_time": "2022-01-17T09:47:28Z", "salary": {"currency": "HKD", "max": 19999, "min": 14000, "period": "monthly", "term": null}, "salary_visible": true, "title_keywords": ["administrative assistant", "officer"], "responsibilities": ["communicate with", "sales report", "quotation", "maintain", "sales team", "database", "ad-hoc projects", "tender document", "costs", "administration"], "requirements": {"degrees": ["diploma", "degree holder"], "majors": [], "languages": ["cantonese", "english", "mandarin"], "language_level": ["good command"], "hard_skills": ["sales support", "sap", "ms office"], "soft_skills": ["flexible", "good team player", "independent", "patient", "work under pressure"], "languages_combined": [{"language": "cantonese", "language_level": ["good command"]}, {"language": "english", "language_level": ["good command"]}, {"language": "mandarin", "language_level": ["good command"]}]}, "experience_required": {"duration": ["1-2 years"], "field": ["business", "sales support", "customer services"]}}, {"job_id": "100003009051913", "location_code": "hk", "company": "VEGA Technology Limited", "job_title": "Sales Assistant", "description": "Responsibilities:\n\n\u00a0\u00a0\u00a0\u00a0\u00a0\u00a0\u00a0\u00a0 To communicate with wholesale brands on shipment, after-sales, sample, marketing, etc.\n\u00a0\u00a0\u00a0\u00a0\u00a0\u00a0\u00a0\u00a0 To assist sales manager on handling seasonal buy and executing marketing strategy\n\u00a0\u00a0\u00a0\u00a0\u00a0\u00a0\u00a0\u00a0 Responsible for daily clerical support includes data entry and invoice/document checking\n\u00a0\u00a0\u00a0\u00a0\u00a0\u00a0\u00a0\u00a0 To prepare regular Sales & Inventory Reports to Sales Team and Management\n\u00a0\u00a0\u00a0\u00a0\u00a0\u00a0\u00a0\u00a0 To follow up Goods receive, transfer and export in systems\n\u00a0\u00a0\u00a0\u00a0\u00a0\u00a0\u00a0\u00a0 To handle other admin doc assignments as required\n\nRequirements:\n\n\u00a0\u00a0\u00a0\u00a0\u00a0\u00a0\u00a0\u00a0 Degree or above;\n\u00a0\u00a0\u00a0\u00a0\u00a0\u00a0\u00a0\u00a0 Minimum 3 years\u2019 relevant working experience;\n\u00a0\u00a0\u00a0\u00a0\u00a0\u00a0\u00a0\u00a0 Proficiency in spoken in Chinese (including Cantonese and Mandarin) is a must;\n\u00a0\u00a0\u00a0\u00a0\u00a0\u00a0\u00a0\u00a0 Proficient computer knowledge in MS Office, Word, Excel, Power point & Chinese word processing\n\nInterested parties, please send your detailed resume with expected salary by clicking \"Apply Now\".\n\n\nData collected will be used for recruitment purpose only.", "employment_types": ["Full Time", "Permanent"], "selling_points": ["5-day work", "on job training", "work life balance"], "locations": ["Kwai Fong"], "categories": ["Admin & HR", "Clerical / Admin Staff", "Sales, CS & Business Devpt", "Customer Service - Supervisor / Officer", "Sales Administration"], "post_time": "2022-01-17T01:30:33Z", "salary": {"currency": null, "max": null, "min": null, "period": "monthly", "term": null}, "salary_visible": false, "title_keywords": ["sales assistant"], "responsibilities": ["communicate with", "management", "data entry", "invoice", "inventory", "systems", "clerical support", "checking", "executing", "reports", "sales team"], "requirements": {"degrees": ["degree or above"], "majors": [], "languages": ["cantonese", "chinese", "mandarin"], "language_level": ["proficiency", "proficient"], "hard_skills": ["excel", "chinese word processing", "word", "power point", "ms office"], "soft_skills": [], "languages_combined": [{"language": "cantonese", "language_level": ["proficiency"]}, {"language": "chinese", "language_level": ["proficiency", "proficient"]}, {"language": "mandarin", "language_level": ["proficiency"]}]}, "experience_required": {"duration": ["minimum 3 years"], "field": ["relevant working experience"]}}, {"job_id": "100003009054866", "location_code": "hk", "company": "Europe Group Holdings Ltd", "job_title": "Co-ordinator, Sales Administration", "description": "Handle import and export documents\nHandle stock in&out documents for fine wines warehouse.\nAssist in customers in&out for wine cellars.\nAssist in system maintainence.\nAssist in daily administration work.\nAssist in sales and customer service work.\nDirectly report to Adminstration Manager and Director.\nResponsible and detailed minded.\nSelf-motivated and a team player.\u00a0\nGood communication skills.\nGood writting skills in English and Chinese.\nRelated working experience is preferred.\nWine industry working experience is preferred.", "employment_types": ["Full Time", "Permanent"], "selling_points": ["3 years\u2019 relevant working experience", "Proficiency in spoken in Chinese", "Travel to China if needed"], "locations": ["Tsim Sha Tsui"], "categories": ["Sales, CS & Business Devpt", "Wholesale", "Others", "Sales Administration"], "post_time": "2022-01-17T12:09:24Z", "salary": {"currency": null, "max": null, "min": null, "period": "monthly", "term": null}, "salary_visible": false, "title_keywords": ["sales"], "responsibilities": ["communication", "report", "customer service", "administration"], "requirements": {"degrees": [], "majors": [], "languages": ["english", "chinese"], "language_level": ["good"], "hard_skills": ["import and export"], "soft_skills": ["communication skills", "self-motivated", "responsible", "customer service", "team player", "detailed"], "languages_combined": [{"language": "english", "language_level": ["good"]}, {"language": "chinese", "language_level": ["good"]}]}, "experience_required": {"duration": [], "field": ["related"]}}, {"job_id": "100003009055792", "location_code": "hk", "company": "Smartech (H.K.) Limited", "job_title": "Operation Clerk", "description": "Job Highlights:\n\nAccurately place customer orders and shop replenishment within the specified time\nManaging stock levels and transferring stock between locations\nCoordinate all logistics operation including warehouse, retail locations and transportation\nHandle inventory control to keep stock record\nPrepare various report for operation review\nPerform ad-hoc duties as required\n\nRequirements:\n\nF.5/HKDSE or above\n1-2 years relevant working experience in\u00a0retail\u00a0industry;\nGood computer skills: Microsoft Word and Excel, Chinese word processing;\nExperience with ERP/WMS system is preferable, knowledge of \u00a0\u201c\u7e31\u6a6b\u7cfb\u7d71\u201d Dynamic System will be an advantage ;\nStrong sense of responsibility and able to work independently;\nAbility to perform multi-task, well-organized, self -motivated, efficient, detail-minded and able to work under pressure;\nImmediate availability is preferred\n\n\u00a0Interested candidates please send application with full resume, availability and expected salary.", "employment_types": ["Full Time"], "selling_points": [], "locations": ["Kwun Tong"], "categories": ["Admin & HR", "Administration / Operation Manager", "Clerical / Admin Staff", "Sales, CS & Business Devpt", "Sales Administration"], "post_time": "2022-01-18T02:58:47Z", "salary": {"currency": null, "max": null, "min": null, "period": "monthly", "term": null}, "salary_visible": false, "title_keywords": ["operation clerk"], "responsibilities": ["work under pressure", "review", "replenishment", "coordinate", "inventory control", "logistics", "wms", "ad-hoc duties", "report"], "requirements": {"degrees": ["hkdse"], "majors": [], "languages": ["chinese"], "language_level": ["good"], "hard_skills": ["excel", "microsoft word", "chinese word processing", "erp", "dynamic", "computer skills"], "soft_skills": ["efficient", "detail-minded", "work independently", "multi-task", "sense of responsibility", "well-organized", "dynamic", "ad-hoc duties", "work under pressure"], "languages_combined": [{"language": "chinese", "language_level": ["good"]}]}, "experience_required": {"duration": ["1-2 years"], "field": ["retail industry", "relevant working experience"]}}, {"job_id": "100003009054415", "location_code": "hk", "company": "Getinge Group Hong Kong Limited", "job_title": "Administration Assistant", "description": "Accompanying the company development, we are looking for you, the outstanding candidate for:-\n\nAdministration Assistant\n\n\nThe post is to assist the administration officer in:-\n\nVerifying and dispatching of daily customer purchase orders;\nPreparing tender document in high accuracy level;\nMaintaining office supplies, office equipment and environment;\nHandling incoming calls and greeting visitors in a professional and courteous manner when necessary;\nCommunicating with internal department for administrative issues;\nAny other administration tasks as assigned by supervisor and assist the team in ad-hoc\u00a0 projects\nContract-based, annual contract renewal is expected\n\nTo excel in this role, you will need to have the following requirements:\n\nDiploma graduate or above in related discipline. \u00a0\nMinimum 1 year sales administration and / or office administration experience;\nResponsible, detail oriented, independent, well-organized and good team player\nProficient in MS Word, Excel\nImmediately available is preferable\n\nInterested candidates, please send your resume, with present and expected salary to us.\n\n\u00a0Getinge Group Hong Kong\u00a0|\u00a0Internet:\u00a0www.getingegroup.com\u00a0\u00a0", "employment_types": ["Full Time", "Part Time", "Contract"], "selling_points": ["Strong international medical company background", "5-day work", "Immediately available is preferable"], "locations": ["Wong Tai Sin Area"], "categories": ["Admin & HR", "Clerical / Admin Staff", "Others", "Sales, CS & Business Devpt", "Sales Administration"], "post_time": "2022-01-17T09:26:30Z", "salary": {"currency": null, "max": null, "min": null, "period": "monthly", "term": null}, "salary_visible": false, "title_keywords": ["administration assistant"], "responsibilities": ["ad-hoc", "sales administration", "maintaining", "office supplies", "office administration", "greeting visitors", "preparing tender", "purchase", "communicating with", "administration"], "requirements": {"degrees": ["diploma"], "majors": [], "languages": [], "language_level": [], "hard_skills": ["excel", "ms word"], "soft_skills": ["courteous", "good team player", "independent", "responsible", "detail oriented", "well-organized"], "languages_combined": []}, "experience_required": {"duration": ["minimum 1 year"], "field": ["sales administration", "office administration"]}}, {"job_id": "100003009053184", "location_code": "hk", "company": "Tsit Wing Coffee Co Ltd", "job_title": "Customer Service Representative", "description": "Responsibilities:\n\nOversee order fulfillment process and assist in customer service\nWork with internal departments for PO management, including production timeline, delivery, invoicing and sampling\nProvide clerical and administrative supports to our Sales and E commerce Team\nOther ad hoc duties assigned\n\nRequirements:\n\nF.5 / DSE or above\n1-2 years working experience in customer services and sales support\nGood command of written and spoken English and Chinese\nProficient in MS office and Chinese Word Processing\nImmediate availability is preferred\n\nWe offer attractive compensation package to suitable candidates. Interested parties, please click \"Apply Now\" to\u00a0submit your application.\n\n(Personal data collected will be used for recruitment purposes only.)", "employment_types": ["Full Time", "Permanent"], "selling_points": [], "locations": ["Kwai Fong"], "categories": ["Admin & HR", "Clerical / Admin Staff", "Sales, CS & Business Devpt", "Customer Service - Supervisor / Officer", "Sales Administration"], "post_time": "2022-01-17T06:20:17Z", "salary": {"currency": null, "max": null, "min": null, "period": "monthly", "term": null}, "salary_visible": false, "title_keywords": ["customer service representative"], "responsibilities": ["ad hoc duties", "management", "invoicing", "order fulfillment", "customer service"], "requirements": {"degrees": ["dse"], "majors": [], "languages": ["english", "chinese"], "language_level": ["good command", "proficient"], "hard_skills": ["chinese word processing", "sales support", "ms office"], "soft_skills": [], "languages_combined": [{"language": "english", "language_level": ["good command"]}, {"language": "chinese", "language_level": ["good command", "proficient"]}]}, "experience_required": {"duration": ["1-2 years"], "field": ["sales support", "customer services"]}}, {"job_id": "100003009054517", "location_code": "hk", "company": "Action Medical Sundries Limited", "job_title": "Sales Coordinator / Clerk", "description": "Job Requirements\n\nHigher Diploma / Diploma holder\n2-3 years relevant experience in purchase order processing\nExperience in trading or manufacturing company is preferable\nWell-organized, energetic, detail-minded and good team player\nFamiliar with MS Office including Word, Excel and Outlook\nGood command of English and fair in spoken Mandarin\nImmediate available is highly preferred\n\nJob Responsibilities\n\nCoordinate with suppliers on follow up purchase and sales orders\nResponsible for preparing purchase order, quotation and delivery note\nAssist in price negotiation and delivery coordination with suppliers\nMaintain and update purchasing record and perform ad hoc tasks\n\nWe offer excellent fringe benefits and attractive development prospect to the right candidates. Interested parties, please apply with full resume stating expected & last salary and date of available by clicking \u2018Apply Now\u2019", "employment_types": ["Full Time"], "selling_points": [], "locations": ["Kwai Hing"], "categories": ["Sales, CS & Business Devpt", "Sales Administration"], "post_time": "2022-01-17T09:51:13Z", "salary": {"currency": null, "max": null, "min": null, "period": "monthly", "term": null}, "salary_visible": false, "title_keywords": ["sales coordinator", "clerk"], "responsibilities": ["price negotiation", "coordination with", "quotation", "coordinate with", "ad hoc tasks", "purchase", "maintain"], "requirements": {"degrees": ["diploma holder", "diploma"], "majors": [], "languages": ["english", "mandarin"], "language_level": ["good command"], "hard_skills": ["excel", "word", "outlook", "order processing", "ms office"], "soft_skills": ["detail-minded", "good team player", "energetic", "well-organized"], "languages_combined": [{"language": "english", "language_level": ["good command"]}, {"language": "mandarin", "language_level": ["good command"]}]}, "experience_required": {"duration": ["2-3 years"], "field": ["manufacturing", "relevant experience", "trading", "order processing"]}}, {"job_id": "100003008980854", "location_code": "hk", "company": "Shun Lee Building Materials and Sanitary Wares Ltd", "job_title": "Project Sales Coordinator", "description": "Responsibilities:\n\nAssist Project Sales Team on order management\nHandle sales documents such as quotations, purchasing orders, sales invoices and delivery notes\nManage the distribution of inventory control\nLiaise with customers and logistic parties\nFollow up shipping schedule, delivery and outstanding payment\nProvide administrative support to the team and perform ad hoc duties as assigned\n\nRequirements:\n\nDiploma or above in any discipline\n1-2 years relevant working experience on sales administration or related field\nGood communication skills and interpersonal skills\nGood command of written and spoken English, Chinese and Putonghua\nProficient in MS Word, Excel, PowerPoint and Chinese Word Processing\nSelf-motivated, well-organized, able to work under pressure and willing to work overtime\nImmediate available is an advantage\nCandidate with more experience will be considered as Sales Administrator\n\nWe offer a 5-day work week, competitive salary, attractive commission, discretionary performance bonus, medical benefits, marriage leave, compassionate leave, staff purchase discount and excellent career prospects.\n\nInterested parties please send your application letter and full resume with current / expected salary and availability to Human Resources Department by clicking APPLY NOW.\n\n\nFor more information about our Company, please visit our website at\u00a0https://shunlee.com.hk\u00a0\n\u00a0\nInformation collected will be treated in strict confidence and only be used for recruitment purpose.", "employment_types": ["Full Time", "Permanent"], "selling_points": [], "locations": ["Lai Chi Kok"], "categories": ["Admin & HR", "Secretary", "Merchandising & Purchasing", "Others", "Sales, CS & Business Devpt", "Sales Administration"], "post_time": "2022-01-16T21:50:05Z", "salary": {"currency": null, "max": null, "min": null, "period": "monthly", "term": null}, "salary_visible": false, "title_keywords": ["sales coordinator"], "responsibilities": ["shipping schedule", "ad hoc duties", "order management", "invoices", "payment", "inventory control", "sales team", "liaise with", "provide administrative support"], "requirements": {"degrees": ["diploma or above"], "majors": [], "languages": ["putonghua", "english", "chinese"], "language_level": ["good command", "proficient"], "hard_skills": ["excel", "chinese word processing", "powerpoint", "ms word"], "soft_skills": ["communication skills", "self-motivated", "work overtime", "well-organized", "interpersonal skills", "work under pressure"], "languages_combined": [{"language": "putonghua", "language_level": ["good command"]}, {"language": "english", "language_level": ["good command"]}, {"language": "chinese", "language_level": ["good command", "proficient"]}]}, "experience_required": {"duration": ["1-2 years"], "field": ["related", "sales administration", "relevant working experience"]}}, {"job_id": "100003009053996", "location_code": "hk", "company": "AnsWing\u2019s", "job_title": "Administrative Executive  ($17K ~ $25K)", "description": "Guaranteed Basic Income ($17K ~ $25K)\n\n5 days work with Double Pay\n\nTravel Allowance + Medical Insurance\n\nResponsibilities\n\n\u00a0Perform general office administrative and clerical supports\n\nSupport Senior Manager in the preparation of all documentations\n\nManage schedules, appointments and meetings\n\nReview and sort incoming emails and mails for relevant functions\n\nPlan and manage record keeping activities when required\n\nHandle and maintain confidential information and documents\n\n\n3Requirements\u00a0\n\nBachelor degree or above\n\nDetail-oriented, well-organized, excellent communication skills\n\nExcellent interpersonal skills to deal with all levels of people\n\nHigh proficiency in MS Office including Excel, Word, PowerPoint etc\n\nHigh proficiency of both spoken and written English, Cantonese and Mandarins\n\nImmediate available is preferred", "employment_types": ["Full Time", "Internship"], "selling_points": ["5-days Work Incentive Package +Be professionalism", "Provide professional administrative support", "Fresh graduate + any work experienced are welcome"], "locations": ["Not Specified"], "categories": ["Admin & HR", "Personal / Executive Assistant", "Marketing / Public Relations", "Marketing - General / Support", "Sales, CS & Business Devpt", "Sales Administration"], "post_time": "2022-01-17T07:59:13Z", "salary": {"currency": "HKD", "max": 24999, "min": 17000, "period": "monthly", "term": null}, "salary_visible": true, "title_keywords": ["administrative executive"], "responsibilities": ["manage record", "schedules", "review", "maintain", "plan"], "requirements": {"degrees": ["degree or above", "bachelor"], "majors": [], "languages": ["cantonese", "english"], "language_level": ["proficiency"], "hard_skills": ["excel", "word", "powerpoint", "ms office"], "soft_skills": ["communication skills", "well-organized", "interpersonal skills", "detail-oriented"], "languages_combined": [{"language": "cantonese", "language_level": ["proficiency"]}, {"language": "english", "language_level": ["proficiency"]}]}, "experience_required": {"duration": [], "field": []}}, {"job_id": "100003009052040", "location_code": "hk", "company": "TransUnion Limited", "job_title": "Sales Support Executive", "description": "Responsibilities\nProvide preliminary response to inquiries in various channels, such as email, WhatsApp & other online places, and hand-over case to salespersons\nParticipate at daily customer support for customer relationship nurturing\u00a0\u00a0\nManage and coordinate after-sales activities with customers and internal teams\nAssist at routine customer interactions, include billing follow up & deliveries coordination\nAssist at sales data refinement\nAssist at marketing activities & tasks, ad hoc & routine\nContribute to internal workflow improvement\nAssist at any other related tasks as assigned\n\nRequirements\n\nHigher Diploma or above in business, marketing, administration, communication or relevant disciplines.\n1-3 year relevant experience, in business support, administration, or B2B customer services.\nHighly organized, multi-tasking, & able to meet timeline under pressure.\nProactive, detail-oriented & communicative\nGood time management & able to prioritise and complete tasks with minimum supervision\nQuick learning skills and eager at self improvement\nBasic computer proficiency, familiar with excel & general e-communication tools.\u00a0 Experience in using CRM / ERP will be an advantage.\u00a0\nFluent in Cantonese, English (written and speaking) and Mandarin\n\nWe offer 5-day work week, bank holidays, medical insurance & company bonus.\u00a0 Member at this role with 2-year in-house experience, could be considered to prompt to different internal team for advance role.\u00a0\n\nInterested candidates please state clearly the I.T. experience and expected salary in your application.\u00a0", "employment_types": ["Full Time", "Permanent"], "selling_points": ["Prior experience in RFP/contract admin", "Attention to details", "Flexible work hours"], "locations": ["Tsim Sha Tsui"], "categories": ["Sales, CS & Business Devpt", "Others", "Sales Administration"], "post_time": "2022-01-17T01:55:10Z", "salary": {"currency": null, "max": null, "min": null, "period": "monthly", "term": null}, "salary_visible": false, "title_keywords": ["sales support executive"], "responsibilities": ["sales activities", "ad hoc", "data", "teams", "coordinate", "coordination"], "requirements": {"degrees": ["higher diploma or above"], "majors": ["business", "marketing"], "languages": ["cantonese", "english", "mandarin"], "language_level": ["fluent"], "hard_skills": ["excel", "basic", "erp"], "soft_skills": ["organized", "under pressure", "prioritise", "detail-oriented", "communication", "time management", "multi-tasking", "learning", "proactive"], "languages_combined": [{"language": "cantonese", "language_level": ["fluent"]}, {"language": "english", "language_level": ["fluent"]}, {"language": "mandarin", "language_level": ["fluent"]}]}, "experience_required": {"duration": ["1-3 year"], "field": ["relevant experience", "customer services", "business support", "administration"]}}, {"job_id": "100003009053870", "location_code": "hk", "company": "Genesis Block Limited", "job_title": "Customer Services Officer (Cryptocurrency)", "description": "What We'll Bring:\n\nAn exciting role has presented itself within TransUnion\u2019s growing business. You will be supporting Sales and BD teams, and working with different teams in TU HK to facilitate deal closing, and to assist on aftersales processes.\n\n\n\n\nImpact You'll Make:\n\nAssisting Sales and BD team to:\n\nPrepare quotations, contracts, and attend internal or external calls when necessary\nSubmit request for contract/quotation review, and follow up as required by the CRM system as the Sales Support role\nLiaise with internal and external customers, organize the responses to RFP, RFI and similar requests from Clients on a timely manner\nMaintain accurate account list and deal reports for sales meeting\nPost Sales and other responsibilities\n\nComplete internal signing procedures, consolidating supporting documents for internal teams to facilitate revenue booking\nMaintain electronic record for signed contracts according to the SOP\nFollow up with clients on aging accounts, work with Finance and MES team to expedite the collection\nManage team requisition by raising system request, including the accesses for new on boarding members to the sales team\nUndertake administrative job duties as it pertains to the sales department\nManage Sales Shared Service and document database\n\nWhat You'll Bring:\n\nBachelors\u2019 degree holder\nMinimum of 2 years\u2019 experience in Sales or Marketing departments\nExperience working on RFP response and tendering process is a great advantage\nExperience in using Salesforce is a plus, other similar CRM software experience would also count\nHigh organizational skills and ability to manage a number of projects at the same time\nDetailed minded and ability to prioritize workload\nStrong communication skills\nWell versed in MS PowerPoint, Excel and SalesForce", "employment_types": ["Full Time", "Permanent"], "selling_points": ["Growing Digital Assets Brokerage firm", "Great exposure to blockchain and crypto industry", "Fresh graduates and airline staff are welcome"], "locations": ["Tsim Sha Tsui"], "categories": ["Sales, CS & Business Devpt", "Customer Service - Supervisor / Officer", "Account Servicing", "Sales Administration"], "post_time": "2022-01-17T07:39:36Z", "salary": {"currency": null, "max": null, "min": null, "period": "monthly", "term": null}, "salary_visible": false, "title_keywords": ["customer services officer"], "responsibilities": ["internal and external customers", "software", "contracts", "review", "quotation", "teams", "a timely manner", "procedures", "tendering", "communication", "maintain", "reports", "booking", "sales team", "database", "liaise with"], "requirements": {"degrees": ["degree holder"], "majors": [], "languages": [], "language_level": [], "hard_skills": ["excel", "plus", "salesforce", "sales support", "make", "ms powerpoint"], "soft_skills": ["organizational skills", "communication skills", "timely", "prioritize", "accurate", "detailed"], "languages_combined": []}, "experience_required": {"duration": ["minimum of 2 years"], "field": ["marketing"]}}, {"job_id": "100003009056449", "location_code": "hk", "company": "Forsters & Company", "job_title": "Sales Administration Coordinator", "description": "Requirements\n\nHigher Diploma graduate or above\n2 years relevant experience, preferably in trading company\nPrevious experience in sales administration and order follow up\nWell-organized, cheerful, flexible with good communication skills\nComputer knowledge in using MS Office including Word, Excel\nGood command of English and conversational Putonghua\nFresh graduates of degree or higher diploma are considered\nImmediate available will be an advantage\n\nResponsibilities\n\nHandle daily communications with customers, vendors and internal parties\nPrepare sales related documents including PO, invoice and delivery documents\nCoordinate delivery schedules and update the order information in SAP system\nParticipate in organizing trade fairs and ad hoc projects as assigned\n\nWe offer attractive remuneration package and promising career prospect to the right candidates. Interested parties please send full resume with expected/last salary and date of available by clicking \u2018Apply Now\u2019", "employment_types": ["Full Time", "Permanent"], "selling_points": [], "locations": ["Not Specified"], "categories": ["Admin & HR", "Clerical / Admin Staff", "Marketing / Public Relations", "Marketing - General / Support", "Sales, CS & Business Devpt", "Sales Administration"], "post_time": "2022-01-18T06:10:16Z", "salary": {"currency": null, "max": null, "min": null, "period": "monthly", "term": null}, "salary_visible": false, "title_keywords": ["coordinator", "sales"], "responsibilities": ["communications with", "related documents", "invoice", "schedules", "prepare sales", "coordinate", "ad hoc projects", "internal parties"], "requirements": {"degrees": ["diploma", "degree"], "majors": [], "languages": ["putonghua", "english"], "language_level": ["conversational", "good command"], "hard_skills": ["excel", "word", "ms office"], "soft_skills": ["flexible", "communication skills", "cheerful", "well-organized"], "languages_combined": [{"language": "putonghua", "language_level": ["good command"]}, {"language": "english", "language_level": ["conversational", "good command"]}]}, "experience_required": {"duration": ["2 years"], "field": ["sales administration", "relevant experience", "trading"]}}, {"job_id": "100003009056412", "location_code": "hk", "company": "Stack's Bowers and Ponterio, Limited", "job_title": "Consignment and Shipping Assistant", "description": "Key responsibilities (Not limited to the following):\n\nCoordinating, monitoring, tracking, and processing incoming consignments\nOpening packages, verifying and labeling contents, creating a record of each item in the database\nKeeping items in database up to date and accurate, auditing contracts and other consignment paperwork for accuracy\nResearching the status of consignments\nProcessing shipping requests\nMonitor the progress of shipments and deliveries, conferring with suppliers to troubleshoot and rectify problems in a timely manner and ensuring that interested parties are apprised of the status of the shipment.\nParticipate in ad-hoc duties as requested, not limited to additional main and mid-season auction based duties which may include, but are not limited to, telephone and online bidding support\n\nQualification Requirements:\n\n\n\nHigh School Diploma is a must (College degree is preferred). Fresh graduate is also considered\nFluent verbal and written English and Chinese (including Mandarin)\nAbility to learn quickly and apply knowledge\nExcellent communication and interpersonal skills; demonstrated ability to communicate with all organizational levels\nAbility to work both independently and as a team member to complete the task at hand\nStrong organizational skills to set priorities, multi task and meet deadlines\nProficiency in Microsoft Offices skills\nDuring auction, flexibility to work overtime and weekend hours when necessary is required", "employment_types": ["Full Time", "Permanent"], "selling_points": [], "locations": ["Tsim Sha Tsui"], "categories": ["Admin & HR", "Clerical / Admin Staff", "Transportation & Logistics", "Shipping", "Sales, CS & Business Devpt", "Sales Administration"], "post_time": "2022-01-18T04:14:27Z", "salary": {"currency": null, "max": null, "min": null, "period": "monthly", "term": null}, "salary_visible": false, "title_keywords": ["shipping", "assistant"], "responsibilities": ["shipping", "contracts", "monitoring", "database", "contents", "auditing", "tracking"], "requirements": {"degrees": [], "majors": [], "languages": [], "language_level": [], "hard_skills": [], "soft_skills": [], "languages_combined": []}, "experience_required": {"duration": [], "field": []}}, {"job_id": "100003009056504", "location_code": "hk", "company": "DFV Fine Wines Limited", "job_title": "Shipping and Sales Adminstrative Assistant", "description": "Handle import and export documents\nHandle stock in&out documents for fine wines warehouse.\nAssist in customers in&out for wine cellars.\nAssist in system maintainence.\nAssist in daily administration work.\nAssist in sales and customer service work.\nDirectly report to Adminstration Manager and Director.\nResponsible and detailed minded.\nSelf-motivated and a team player.\u00a0\nGood communication skills.\nGood writting skills in English and Chinese.\nRelated working experience is preferred.\nWine industry working experience is preferred.", "employment_types": ["Full Time"], "selling_points": [], "locations": ["Kwun Tong"], "categories": ["Admin & HR", "Clerical / Admin Staff", "Transportation & Logistics", "Shipping", "Sales, CS & Business Devpt", "Sales Administration"], "post_time": "2022-01-18T04:43:15Z", "salary": {"currency": "HKD", "max": 16999, "min": 11000, "period": "monthly", "term": null}, "salary_visible": true, "title_keywords": ["shipping", "assistant", "sales"], "responsibilities": ["communication", "report", "customer service", "administration"], "requirements": {"degrees": [], "majors": [], "languages": ["english", "chinese"], "language_level": ["good"], "hard_skills": ["import and export"], "soft_skills": ["communication skills", "self-motivated", "responsible", "customer service", "team player", "detailed"], "languages_combined": [{"language": "english", "language_level": ["good"]}, {"language": "chinese", "language_level": ["good"]}]}, "experience_required": {"duration": [], "field": ["related"]}}, {"job_id": "100003009056511", "location_code": "hk", "company": "Gift Something", "job_title": "ECommerce Operations & Customer Service Executive", "description": "Our growing company is seeking an eCommerce operations administrative coordinator to join our young & creative team.\n\nThe primary objective of this role will see you working collaboratively with numerous team members by managing the efficient e-commerce operations.\n\nYour key responsibilities will include:\n\nDaily order fulfilment\nCustomer service\u00a0\nCustomer support\nLogistics management\nAssistant operational team leaders\nManage Ecommerce operations.\u00a0\nWork closely with all team & management\n\nThe successful candidate must have:\n\nBe a proven team player\nConfident and able to work independently\nKnowledge of HKTVMall\u00a0\nProven ability to prioritise workloads\nAttention to detail\nProven ability to achieve and exceed productivity targets.\nWillingness to learn quickly and grow within the position\nAbility to seek advice and accept feedback\nThe ability to work in a fast paced environment\nCompetent computer skills\nExcellent numeracy skills\nA high level of energy and enthusiasm\nA positive 'can do' attitude", "employment_types": ["Full Time"], "selling_points": ["Young & Energetic Team", "Fast Growing Company", "Attractive Package"], "locations": ["Tsuen Wan Area"], "categories": ["Sales, CS & Business Devpt", "Customer Service - Supervisor / Officer", "Account Servicing", "Sales Administration"], "post_time": "2022-01-18T04:35:51Z", "salary": {"currency": null, "max": null, "min": null, "period": "monthly", "term": null}, "salary_visible": false, "title_keywords": ["operations", "customer service executive"], "responsibilities": ["operations", "management", "customer service", "logistics"], "requirements": {"degrees": [], "majors": [], "languages": [], "language_level": [], "hard_skills": ["computer skills", "e-commerce"], "soft_skills": ["efficient", "confident", "work independently", "competent", "prioritise", "customer service", "attention to detail", "work in a fast paced environment", "team player", "creative", "positive"], "languages_combined": []}, "experience_required": {"duration": [], "field": []}}, {"job_id": "100003009054032", "location_code": "hk", "company": "NEC Hong Kong Limited", "job_title": "Purchasing Officer", "description": "Responsibilities:\n\nProvide full range administration support, including order input, delivery arrangement and invoice preparation in Oracle system.\nWork closely with internal and external customer for daily work of purchasing and business control.\nPrepare the monthly report.\nHandle ad hoc projects as assigned.\n\nRequirements:\n\nHigher Diploma or above with 4 years' relevant working experiences;\nExperience and knowledge in Oracle System is an advantage;\nExcellent communication and inter-personal skills;\nGood command of both written and spoken of Chinese and English;\nImmediate available is preferable.\nPlease send your full detailed resume with expected salary and date available to The Human Resources Manager, NEC Hong Kong Limited, 25th Floor, The Metropolis Tower, 10 Metropolis Drive, Hunghom, Kowloon or by e-mail.\n\n\nPersonal data provided by job applicant will be used strictly in accordance with employer's personal data policy, a copy of which will be provided immediately upon request.", "employment_types": ["Full Time"], "selling_points": ["Order input, prepare invoice", "Prepare the monthly report", "5-day work, Hunghom Station"], "locations": ["Hung Hom"], "categories": ["Admin & HR", "Clerical / Admin Staff", "Merchandising & Purchasing", "Others", "Sales, CS & Business Devpt", "Sales Administration"], "post_time": "2022-01-17T08:08:25Z", "salary": {"currency": null, "max": null, "min": null, "period": "monthly", "term": null}, "salary_visible": false, "title_keywords": ["purchasing officer"], "responsibilities": ["control", "invoice", "ad hoc projects", "monthly report", "administration"], "requirements": {"degrees": ["higher diploma or above"], "majors": [], "languages": ["english", "chinese"], "language_level": ["good command"], "hard_skills": ["oracle system"], "soft_skills": ["communication", "inter-personal skills", "detailed"], "languages_combined": [{"language": "english", "language_level": ["good command"]}, {"language": "chinese", "language_level": ["good command"]}]}, "experience_required": {"duration": ["4 years"], "field": []}}, {"job_id": "100003009052505", "location_code": "hk", "company": "Telford International Co Ltd", "job_title": "Sales Coordinator", "description": "Responsibilities\n\nProvide clerical support to daily sales activities, including preparation of issuing sales order, invoices, sales report and analysis, promotion report, etc.\nWell support for sales coordination with both internal and external parties\nProvide good and polite customer service\nMaintain department database records & good filing system\nHandle ad-hoc duties as assigned\n\n\nRequirements\n\nF.5 with 2 years+ work experience as Sales Coordinator\nProficient in Microsoft applications (Word and Excel are must)\nGood communication & interpersonal skills\nGood command of spoken and written skills in Chinese and English\nImmediately available is preferred\n\nWe offer attractive remuneration package and career prospects plus 5-day week and medical insurance. Interested parties please forward your full resume with\u00a0Expected Salary to us.\n\nAll data collected shall be solely for recruitment purpose.\n\nWebsite\u00a0\u00a0 :\u00a0\u00a0\u00a0\u00a0\u00a0\u00a0\u00a0http://www.telford.com.hk/", "employment_types": ["Full Time", "Permanent"], "selling_points": ["Clerical support to sales activities", "2 years+ Sales Coordinator experience", "Proficient in MS applications"], "locations": ["Kwai Hing"], "categories": ["Sales, CS & Business Devpt", "Customer Service - Supervisor / Officer", "Account Servicing", "Sales Administration"], "post_time": "2022-01-17T03:16:10Z", "salary": {"currency": null, "max": null, "min": null, "period": "monthly", "term": null}, "salary_visible": false, "title_keywords": ["sales coordinator"], "responsibilities": ["provide clerical support", "sales activities", "sales report", "invoices", "analysis", "coordination with", "internal and external parties", "customer service", "maintain", "database", "ad-hoc duties", "report"], "requirements": {"degrees": [], "majors": [], "languages": ["english", "chinese"], "language_level": ["good command"], "hard_skills": ["excel", "word", "microsoft applications"], "soft_skills": ["communication", "interpersonal skills"], "languages_combined": [{"language": "english", "language_level": ["good command"]}, {"language": "chinese", "language_level": ["good command"]}]}, "experience_required": {"duration": [], "field": []}}, {"job_id": "100003009052484", "location_code": "hk", "company": "Offmax Limited", "job_title": "Sales Support Clerk", "description": "\u00a0\u00a0Provide general administration and clerical support.\n\u00a0 Communicate with different parties for sales related issue.\n\u00a0 Assist in ad-hoc duties as assigned\n\n\u00a0Requirements\n\n\u00a0\u00a0DSE or above\n\u00a0 Fresh graduate will also be considered.\n\u00a0 Good command of English, Cantonese and Mandarin.\n\u00a0 Proficiency in MS Office and Chinese word processing.\n\u00a0 Responsible, self-motivated, service oriented thinking with good interpersonal skills.\n\u00a0 Immediate available is highly preferred.\n\nWe offer competitive remuneration package including annual leave, medical coverage, MPF and professional training to the right candidate.\n\nInterested parties, please send resume with CURRENT & EXPECTED SALARY by APPLY\u00a0\u00a0NOW.\n\nPersonal data providing by job applicant will be used strictly in accordance with the employer\u2019s personal data policies, and will be destroyed after recruitment period.", "employment_types": ["Full Time"], "selling_points": ["5 days work", "Near MTR Station", "Annual Leave 12 days"], "locations": ["North Point"], "categories": ["Admin & HR", "Clerical / Admin Staff", "Sales, CS & Business Devpt", "Sales Administration"], "post_time": "2022-01-17T03:09:50Z", "salary": {"currency": null, "max": null, "min": null, "period": "monthly", "term": null}, "salary_visible": false, "title_keywords": ["clerk", "sales"], "responsibilities": ["communicate with", "clerical support", "ad-hoc duties", "administration"], "requirements": {"degrees": ["fresh graduate", "dse"], "majors": [], "languages": ["cantonese", "english", "chinese", "mandarin"], "language_level": ["proficiency", "good command"], "hard_skills": ["chinese word processing", "ms office"], "soft_skills": ["self-motivated", "interpersonal skills", "responsible", "ad-hoc duties"], "languages_combined": [{"language": "cantonese", "language_level": ["good command"]}, {"language": "english", "language_level": ["good command"]}, {"language": "chinese", "language_level": ["proficiency"]}, {"language": "mandarin", "language_level": ["good command"]}]}, "experience_required": {"duration": [], "field": []}}, {"job_id": "100003009056732", "location_code": "hk", "company": "Educational Publishing House, Limited", "job_title": "Sales Assistant (Preschool sales team)", "description": "Responsibilities:\n\nProvides administrative and clerical supports to Preschool Sales Team\nPrepares presentation and promotion materials\nSupports sales activities, i.e. taking meeting minutes for weekly sales meeting, updating customer service database, coordinating sample order and delivery arrangement\nOther ad hoc duties as assigned\n\nRequirements:\n\nDSE or above\n1-2 years experience in office support\u00a0\nSelf-motivated, good team player with proactive working attitude\nGood communication skills and detail-minded\nGood in MS Office including Word, Excel, PowerPoint and Chinese typing skills\n\nWe offer excellent career development opportunities to unleash your potential, competitive remuneration package including a 5-day work week, comprehensive group medical insurance and dental scheme, discretionary bonus and staff purchasing discount, etc.\n\nInterested parties please apply with your full resume stating present and expected salary\u00a0by clicking\u00a0\"Apply Now\". \u00a0Only short-listed candidates will be contacted.\n\nYou are welcome to visit our\u00a0websites\u00a0to know more about us:\u00a0ephhk.popularworldhk.com\u00a0/\u00a0www.popular.com.hk\n\nPersonal data provided by job applicants will be kept strictly confidential and used for employment related purpose.\u00a0 Only short-listed candidates will be contacted.", "employment_types": ["Full Time", "Permanent"], "selling_points": ["5 day work, bonus", "Medical & dental, staff purchase discount", "Assist in daily administrative operation"], "locations": ["Tsuen Wan Area"], "categories": ["Admin & HR", "Clerical / Admin Staff", "Sales, CS & Business Devpt", "Others", "Sales Administration"], "post_time": "2022-01-18T06:06:00Z", "salary": {"currency": null, "max": null, "min": null, "period": "monthly", "term": null}, "salary_visible": false, "title_keywords": ["sales", "sales assistant"], "responsibilities": ["ad hoc duties", "sales activities", "customer service", "sales team", "database"], "requirements": {"degrees": ["dse"], "majors": [], "languages": ["chinese"], "language_level": ["good"], "hard_skills": ["excel", "typing", "word", "powerpoint", "scheme", "ms office"], "soft_skills": ["detail-minded", "communication skills", "good team player", "self-motivated", "comprehensive", "proactive"], "languages_combined": [{"language": "chinese", "language_level": ["good"]}]}, "experience_required": {"duration": ["1-2 years"], "field": []}}, {"job_id": "100003009056635", "location_code": "hk", "company": "Scents Limited", "job_title": "Merchandising Clerk", "description": "Are you interested to join a team of eco-conscious and positive people working hard to make a change in the beauty industry?\u00a0\n\nIf you are independent, proactive, highly motivated, willing to roll up your sleeves to get the job done then we have the perfect opportunity for you!\n\nWe are looking for an awesome full time Merchandising Clerk to work closely with our management, design and merchandiser and\u00a0be fully part of our team to get things done, learn, and grow.\u00a0\n\nJob Duties:\n\n+ Liaise with Beauty packaging factories to develop new products (haircare, perfume)\n+ Source new sustainable materials and suppliers (Alibaba, 1688, TaoBao)\n+ Follow-up on sampling, production, quality control and delivery\n+ Help to negotiate prices and quantities\n+ Coordinate with our Marketing and Design teams on new launches\n\nJob Requirements:\n\n+ 1 - 3 years working experience in Admin, Secretarial, Merchandising, Buying or Sourcing\n+ Positive attitude, detail minded, well organized\n+ Fluent in Spoken and Written of both English and Chinese are a must (Cantonese and Mandarin)\n+ Word, Excel, PowerPoint and Chinese word processing\n+ Experience working in English is a plus\n+ Immediate availability\u00a0is a plus\n\nWe offer :\n\n- A fun working environment,\n- 5-days work,\n- flexible working hours,\n- MPF,\n- 13 month\n- Performance Bonus\n- 12 days annual leave,\n- All hongkong bank Holiday,\n- Free product incentive,\u00a0\n- Staff-Discount\n- A Good salary package to the right candidate.\u00a0\n-\u00a0And a job in a company who truly care about the planet.\n\nIf you wish to learn, grow and you're up for a challenge ...\nPlease send your full resume with expected salary\u00a0and availability via\u00a0the \u201cAPPLY\u201d button\u00a0", "employment_types": ["Full Time", "Permanent"], "selling_points": [], "locations": ["Kwun Tong"], "categories": ["Admin & HR", "Clerical / Admin Staff", "Merchandising & Purchasing", "Procurement / Purchasing / Sourcing", "Sales, CS & Business Devpt", "Sales Administration"], "post_time": "2022-01-18T05:18:28Z", "salary": {"currency": "HKD", "max": 16999, "min": 14000, "period": "monthly", "term": null}, "salary_visible": true, "title_keywords": ["merchandising clerk"], "responsibilities": ["coordinate with", "teams", "design", "develop", "quality control", "liaise with"], "requirements": {"degrees": [], "majors": [], "languages": ["cantonese", "english", "chinese", "mandarin"], "language_level": ["fluent"], "hard_skills": ["excel", "plus", "chinese word processing", "word", "powerpoint"], "soft_skills": ["positive attitude", "well organized"], "languages_combined": [{"language": "cantonese", "language_level": ["fluent"]}, {"language": "english", "language_level": ["fluent"]}, {"language": "chinese", "language_level": ["fluent"]}, {"language": "mandarin", "language_level": ["fluent"]}]}, "experience_required": {"duration": ["1 - 3 years"], "field": ["secretarial", "admin", "merchandising"]}}, {"job_id": "100003009056665", "location_code": "hk", "company": "Hong Kong Taiyo Yuden Company Limited", "job_title": "Customer Service/ Sales Assistant", "description": "As a Customer Services Assistant, you are responsible for:\n\nProcessing sales orders by inputting data into system accurately, scheduling and monitoring shipment to ensure on-time delivery;\nPreparing and distributing various sales reports by tracking, consolidating, and summarizing sales databases;\nCommunicating with both internal and external parties to ensure customers' requests are fulfilled;\nHandling Ad hoc duties as assigned\n\n\nIn order to succeed in this role, you:\n\nare F.7 or DSE graduate or above\nhave a minimum of 2 year\u2019s relevant experience in customer service/ sales support\nhave good command of spoken, written and reading in English and Chinese (Mandarin and Cantonese)\nhave strong customer service-oriented mind, good time management and strong sense of responsibility\nare self-motivated , detail minded and deadline driven\nare competent in PC knowledge, MS Windows applications, including Outlook, Excel, PowerPoint and ERP system\nhave an advantage if you have experience in working in electronics field / Japanese electronic company\n\n\nWe offer:\n\n\nHealth Insurance: Medical and Dental\nDouble Pay\n\nBonuses: \u00a0Twice per year\nPaid Time Off:\u00a0 7 \u2013 14 days of Annual Leave, in addition to paid company holidays each year etc.\nPaid Sick Days\nOffice perks: 5-days work, Smart casual dress code, unlimited coffee and tea, excellent working location (5 mins walk from Hung Hom station), stable working hours (09:00-17:45), team outing etc.\n\nDid we catch your interest? Interested candidates please email your resume with expected salary to us.\n\nAll applications will be treated in strict confidence and used solely for recruitment purpose. Applicants who are not invited to an interview within four weeks may consider their applications unsuccessful. All personal data of unsuccessful applicants will be destroyed after two years.", "employment_types": ["Full Time", "Permanent"], "selling_points": [], "locations": ["Hung Hom"], "categories": ["Admin & HR", "Clerical / Admin Staff", "Sales, CS & Business Devpt", "Customer Service - Supervisor / Officer", "Sales Administration"], "post_time": "2022-01-18T05:34:57Z", "salary": {"currency": null, "max": null, "min": null, "period": "monthly", "term": null}, "salary_visible": false, "title_keywords": ["customer service", "sales assistant"], "responsibilities": ["ad hoc duties", "management", "sales reports", "data", "monitoring", "internal and external parties", "customer services", "scheduling", "communicating with", "customer service", "databases", "tracking"], "requirements": {"degrees": ["dse"], "majors": [], "languages": ["cantonese", "english", "mandarin", "japanese", "chinese"], "language_level": ["advantage", "good command"], "hard_skills": ["excel", "sales support", "ms windows", "powerpoint", "erp system", "outlook", "databases", "pc knowledge", "processing"], "soft_skills": ["self-motivated", "responsible", "sense of responsibility", "competent", "service-oriented", "customer service", "time management", "driven"], "languages_combined": [{"language": "cantonese", "language_level": ["good command"]}, {"language": "english", "language_level": ["good command"]}, {"language": "mandarin", "language_level": ["good command"]}, {"language": "japanese", "language_level": ["advantage"]}, {"language": "chinese", "language_level": ["good command"]}]}, "experience_required": {"duration": ["minimum of 2 year"], "field": ["customer service", "relevant experience", "sales support"]}}, {"job_id": "100003009051713", "location_code": "hk", "company": "ASM Technology Hong Kong Limited", "job_title": "Sales Administration Officer", "description": "Job description\nLiaise with business units for invoices and billing information\nPrepare and coordinate quotations and sales/purchase orders\nSupport sales activities, including preparing periodical sales reports and presentations, planning and follow-up\nManage customers' information, create, maintain and manage the system records regularly and accurately\nLiaise with internal and external stakeholders to ensure professional and smooth fulfillment to the customer\nJob requirements\nDegree or above in Business / Management / Engineering or relevant disciplines\n2- 3 years' working experience preferred (Higher Diploma holder with relevant working experience will also be considered)\nExperience in using SAP or relevant working experience gained from MNC is an advantage\nGood command of English and Mandarin\nGood communication and interpersonal skills\nProficient in Microsoft Word and Excel\nAttention to details, organized, logical thinking and self-initiative\nCandidate with more than 5 years' relevant working experience will be considered as Senior Sales Administration Officer\n\nAttractive salary and fringe benefits package will be offered to the right candidates.\n\nInterested parties please submit your application with cover letter, resume, certificate and transcripts.\n\nData collected will be used for recruitment purpose only. Suitable candidates may be referred to other vacancies within our company.", "employment_types": ["Full Time", "Permanent"], "selling_points": ["Degree in Business / Management", "2- 3 years' working experience", "Support sales activities"], "locations": ["Tsing Yi"], "categories": ["Sales, CS & Business Devpt", "Others", "Sales Administration"], "post_time": "2022-01-16T21:51:03Z", "salary": {"currency": null, "max": null, "min": null, "period": "monthly", "term": null}, "salary_visible": false, "title_keywords": ["administration officer", "sales"], "responsibilities": ["sales activities", "invoices", "sales reports", "fulfillment", "presentations", "coordinate", "purchase", "maintain", "liaise with", "planning"], "requirements": {"degrees": ["degree or above", "higher diploma holder"], "majors": ["business", "engineering"], "languages": ["english", "mandarin"], "language_level": ["good command"], "hard_skills": ["excel", "microsoft word", "sap"], "soft_skills": ["organized", "communication and interpersonal skills", "self-initiative", "attention to details"], "languages_combined": [{"language": "english", "language_level": ["good command"]}, {"language": "mandarin", "language_level": ["good command"]}]}, "experience_required": {"duration": ["5 years", "2- 3 years"], "field": ["sales administration", "relevant working experience"]}}, {"job_id": "100003009053258", "location_code": "hk", "company": "Getinge Group Hong Kong Limited", "job_title": "Assistant, Service Administration", "description": "Accompanying the company development, we are looking for you, the outstanding candidate for:-\n\nAssistant, Service Administration (Contract-based)\n\n\nResponsibilities:-\n\nSAP system input for service call creation and confirmation;\nTo prepare\u00a0 sales / service-related documents includes quotation...etc, in high standard of data accuracy;\nCoordinate and liaise closely with service team, to ensure timely information delivery and case follow-up;\nWorking with customer for their asset maintenance system update;\nAny other administration task as assigned by supervisor, assist the team for ad-hoc projects\n\nJob requirements:\n\nHigh diploma / Sub-degree holder, service admin related experience is preferred;\nWorking experience in medical equipment / healthcare market will be a strong advantage;\nExperience in SAP system is preferred;\nResponsible, able to prioritize, good team player and in good discipline;\nAble to communicate in Chinese and English (writing)\n\nThis job is a long term contract based and contract is supposed to be renewed yearly with gratuity.\nInterested candidates, please send your resume, with present and expected salary to us.\n\n\u00a0Getinge Group Hong Kong\u00a0|\u00a0Internet:\u00a0www.getingegroup.com\u00a0\u00a0", "employment_types": ["Full Time", "Part Time", "Permanent", "Temporary", "Contract"], "selling_points": ["A long term contract based administrative position", "SAP system knowledge is preferred, not mandatory", "5-day work"], "locations": ["Wong Tai Sin Area"], "categories": ["Admin & HR", "Clerical / Admin Staff", "Others", "Sales, CS & Business Devpt", "Sales Administration"], "post_time": "2022-01-17T06:35:48Z", "salary": {"currency": null, "max": null, "min": null, "period": "monthly", "term": null}, "salary_visible": false, "title_keywords": ["assistant"], "responsibilities": ["liaise", "maintenance", "data", "related documents", "system update", "quotation", "coordinate", "system input", "ad-hoc projects", "administration"], "requirements": {"degrees": ["high diploma", "degree holder"], "majors": [], "languages": ["english", "chinese"], "language_level": [], "hard_skills": ["sap"], "soft_skills": ["able to prioritize", "good team player", "responsible"], "languages_combined": [{"language": "english", "language_level": []}, {"language": "chinese", "language_level": []}]}, "experience_required": {"duration": [], "field": ["related", "healthcare", "admin", "medical equipment"]}}, {"job_id": "100003009054400", "location_code": "hk", "company": "Amway Hong Kong Ltd", "job_title": "Event Officer", "description": "Responsibilities\n\nMaintain good partnership and relationship with distributors and support them to develop business.\nAssist the manager to organize and execute sales recognition programs, meetings, training to enhance distributor image\nPrepare customer data analysis & regular report\nHandle ad-hoc projects as assigned.\n\nRequirements\n\nDegree holder in Marketing, Business or Travel, Event and Tourism Management\n1-2 year of work experience in customer services, sales or event management\nWilling to take up flexible working hours and occasional work on evenings, weekends and public holidays. Occasional overseas travel required.\nLess experience / qualification will be considered\n\nWe offer guaranteed 13 months\u2019 pay and comprehensive benefit scheme.\n\n\nInterested parties, please send your resume and expected salary to HR Department via email ahkhr @ amway.com\n\nFor further information about Amway Hong Kong Limited, please visit the Company\u2019s web site:www.amway.com.hk.", "employment_types": ["Full Time", "Permanent"], "selling_points": [], "locations": ["Quarry Bay"], "categories": ["Marketing / Public Relations", "Public Relations - Event Management", "Sales, CS & Business Devpt", "Account Servicing", "Sales Administration"], "post_time": "2022-01-17T09:22:56Z", "salary": {"currency": null, "max": null, "min": null, "period": "monthly", "term": null}, "salary_visible": false, "title_keywords": ["officer"], "responsibilities": ["analysis", "develop", "maintain", "customer data", "ad-hoc projects", "report"], "requirements": {"degrees": ["degree holder"], "majors": ["business", "marketing"], "languages": [], "language_level": [], "hard_skills": [], "soft_skills": ["flexible"], "languages_combined": []}, "experience_required": {"duration": ["1-2 year"], "field": ["management", "customer services"]}}, {"job_id": "100003009053266", "location_code": "hk", "company": "\u50a2\u5c45\u7ad9\u6709\u9650\u516c\u53f8", "job_title": "\u5168\u8077\u6587\u54e1", "description": "- \u8ca0\u8cac\u5354\u52a9\u9580\u5e02\u53ca\u5f8c\u53f0\u96fb\u8166\u7cfb\u7d71\u64cd\u4f5c\u7d00\u9304\u00a0\u00a0\n\n- \u9808\u719f\u8b58Microsoft Office \u8edf\u4ef6\uff0c\u5354\u52a9\u516c\u53f8\u88fd\u4f5c\u5b9a\u671f\u5831\u8868\u00a0\n\n- \u5354\u52a9\u8ddf\u9032\u9580\u5e02\u71df\u904b\u7d30\u7bc0\uff08\u5982\u50f9\u9322\u724c\u3001\u9580\u5e02\u6587\u4ef6\u6574\u5408\u7b49\uff09\n\n- \u6709\u96f6\u552e\u696d\u7d93\u9a57\u512a\u5148\u00a0\n\n- \u5de5\u4f5c\u5730\u9ede\uff1a\u89c0\u5858\u00a0\n\n- \u5de5\u4f5c\u6642\u9593\uff1a\u661f\u671f\u4e00\u81f3\u4e94 0900-1800", "employment_types": ["Full Time"], "selling_points": ["\u5168\u8077\u6587\u54e1", "Microsoft Office\u8edf\u4ef6", "\u96fb\u8166\u64cd\u4f5c"], "locations": ["Kwun Tong"], "categories": ["Sales, CS & Business Devpt", "Sales Administration"], "post_time": "2022-01-17T06:39:30Z", "salary": {"currency": null, "max": null, "min": null, "period": "monthly", "term": null}, "salary_visible": false, "title_keywords": [], "responsibilities": [], "requirements": {"degrees": [], "majors": [], "languages": [], "language_level": [], "hard_skills": [], "soft_skills": [], "languages_combined": []}, "experience_required": {"duration": [], "field": []}}, {"job_id": "100003009052282", "location_code": "hk", "company": "Ricoh Hong Kong Limited", "job_title": "Sales Support Clerk / Assistant", "description": "The Job:\n\nProvide after sales support e.g. Contract creation, termination and invoice billing\nResponsible for meter collection, tender submission and billing activities in timely manner\nHandle contract related inquiry independently, e.g. negotiation with customer on price increment\nSupport annuity business and follow up with customers proactively\nProvide general administration support e.g. document scanning and filing, courier arrangement, audit support and KPI reports\nCommunicate with internal and external customers via email or telephone on a regular basis\nThe Person:\nDSE or above with at least 3 year of clerical experience\nProficient in MS Office such as Word, Excel\u00a0and PowerPoint\nHands-on experience or knowledge in Marco is an advantage\nStrong sense of responsibility, well organized and a\u00a0good team player\nCustomer oriented with good communication and interpersonal skills\nGood command of written English and Chinese\nWe offer 5-day work, attractive remuneration and benefits package to the right candidate.\u00a0 \u00a0 \u00a0\u00a0\nInterested parties please forward your full resume (in Microsoft Word or PDF format) with current and expect salary to the\u00a0Human Resources & Facilities Services, Ricoh Hong Kong Limited, by clicking \"Apply Now\".\nInformation provided will be treated in strict confidence and only be used for recruitment related purposes. All personal data of unsuccessful candidates will be destroyed on completion of the recruitment exercise.", "employment_types": ["Full Time", "Permanent"], "selling_points": ["Provide after sales support", "Provide general administration support", "Handle customers enquiries"], "locations": ["Kowloon Bay"], "categories": ["Admin & HR", "Clerical / Admin Staff", "Sales, CS & Business Devpt", "Sales Administration"], "post_time": "2022-01-17T02:39:02Z", "salary": {"currency": null, "max": null, "min": null, "period": "monthly", "term": null}, "salary_visible": false, "title_keywords": ["clerk", "assistant", "sales"], "responsibilities": ["scanning", "communicate with", "internal and external customers", "invoice", "audit", "reports", "tender", "administration"], "requirements": {"degrees": ["dse"], "majors": [], "languages": ["english", "chinese"], "language_level": ["good command"], "hard_skills": ["excel", "word", "powerpoint", "marco", "ms office"], "soft_skills": ["good team player", "sense of responsibility", "well organized", "hands-on", "communication and interpersonal skills"], "languages_combined": [{"language": "english", "language_level": ["good command"]}, {"language": "chinese", "language_level": ["good command"]}]}, "experience_required": {"duration": ["at least 3 year"], "field": ["clerical"]}}, {"job_id": "100003009052090", "location_code": "hk", "company": "DKSH Hong Kong Limited", "job_title": "Assistant, Sales Order Processing, FMCG", "description": "Job Descriptions:\n\nResponsible for Sales Order Processing and provide sales administrative support to Sales Operations Team\nMaintain and update sales data and ensure all data is recorded in the system timely and accurately\nWork with internal departments for order related & AR issues\nRequirements:\n\nHigher diploma or above\n1 year of working experience is preferred\nFamiliar in using MS Excel, Word\nGood command of written and spoken English and Chinese\nFresh graduate will be considered\nWorking location: Wong Chuk Hang\n\nWe offer performance bonus and attractive benefits including medical insurance to the right candidate.\u00a0 Interested parties please apply in full resume with current and expected salaries to Human Resources Department, DKSH Hong Kong Limited, 23rd Floor, Tower A, Southmark, 11 Yip Hing Street, Wong Chuk Hang, Hong Kong.\n\nAll personal data collected will be used for recruitment purposes only. Candidates will be contacted within 2 weeks if the background and experience are closely relevant to the job requirement.\n\n\nDrive Growth. Be the Difference. Join DKSH.\n\nDKSH\u2019s strength lies in our great diversity of services, industries, clients, products, regions and employees from various nationalities. We are proud of our people: they are the reason we are successful. Our people are the best in the industry. They are passionate about their career growth and about business success. They work as part of an energetic and committed team, positively impacting millions of lives through the products and services we provide.\n\nJoin us today if you are ready to\u00a0\u201cDrive growth. Be the Difference.\u201d\u00a0With DKSH, you will experience a world of learning and development, own your career and take business responsibility and have a positive impact that touches people\u2019s lives.", "employment_types": ["Full Time", "Permanent"], "selling_points": ["Responsible for Sales Order Processing", "Maintain & update data at system", "Work with internal parties for orders issues"], "locations": ["Aberdeen"], "categories": ["Transportation & Logistics", "Others", "Sales, CS & Business Devpt", "Others", "Sales Administration"], "post_time": "2022-01-17T02:04:45Z", "salary": {"currency": null, "max": null, "min": null, "period": "monthly", "term": null}, "salary_visible": false, "title_keywords": ["sales", "assistant"], "responsibilities": ["ar", "data", "operations", "sales administrative support", "maintain", "sales order processing"], "requirements": {"degrees": ["higher diploma or above", "fresh graduate"], "majors": [], "languages": ["english", "chinese"], "language_level": ["good command"], "hard_skills": ["ms excel", "word"], "soft_skills": [], "languages_combined": [{"language": "english", "language_level": ["good command"]}, {"language": "chinese", "language_level": ["good command"]}]}, "experience_required": {"duration": ["1 year"], "field": []}}, {"job_id": "100003009052574", "location_code": "hk", "company": "Sunlight Jewelers Limited", "job_title": "Sales Administration  Executive", "description": "Responsibilities & Requirements\u8077\u8cac\u53ca\u8981\u6c42\n\n\u00a0\u00a0\u00a0\u00a0\u00a0\u00a0\u00a0 Minimum 1-2 years relevant experience in Jewellery industry\n\u00a0\u00a0\u00a0\u00a0\u00a0\u00a0\u00a0 Attend local & overseas trade activities & any other projects as required\n\u00a0\u00a0\u00a0\u00a0\u00a0\u00a0\u00a0 Provide support to Sales Team\n\u00a0\u00a0\u00a0\u00a0\u00a0\u00a0\u00a0 Willing to work under pressure in a dynamic & flexible environment\n\u00a0\u00a0\u00a0\u00a0\u00a0\u00a0\u00a0 Good interpersonal & communication skills, responsible and self-motivated\n\u00a0\u00a0\u00a0\u00a0\u00a0\u00a0\u00a0 Fluent in written and spoken English\n\u00a0\u00a0\u00a0\u00a0\u00a0\u00a0\u00a0 Frequent travel is required\n\u00a0\u00a0\u00a0\u00a0\u00a0\u00a0\u00a0 Experience with MS Office\n\u00a0\u00a0\u00a0\u00a0\u00a0\u00a0\u00a0 Familiar with shipping document will be an advantage\n\nWe offer 5 \u00bd-day work, Medical Scheme & Bank holidays to the right candidate.\u00a0 Interested parties, please send FULL RESUME with expected salary to: Apply Now", "employment_types": ["Full Time"], "selling_points": [], "locations": ["Not Specified"], "categories": ["Admin & HR", "Clerical / Admin Staff", "Sales, CS & Business Devpt", "Direct Sales", "Sales Administration"], "post_time": "2022-01-17T03:27:13Z", "salary": {"currency": null, "max": null, "min": null, "period": "monthly", "term": null}, "salary_visible": false, "title_keywords": ["executive", "sales"], "responsibilities": [], "requirements": {"degrees": [], "majors": [], "languages": ["english"], "language_level": ["fluent"], "hard_skills": ["dynamic", "shipping document", "ms office"], "soft_skills": ["flexible", "communication skills", "self-motivated", "responsible", "dynamic", "interpersonal", "work under pressure"], "languages_combined": [{"language": "english", "language_level": ["fluent"]}]}, "experience_required": {"duration": ["minimum 1-2 years"], "field": ["relevant experience"]}}, {"job_id": "100003009054345", "location_code": "hk", "company": "Magazzin Group Limited", "job_title": "Senior Sales Administrative, Wholesale Operations (5 Days Work)", "description": "What is your job about?\n\n\nManage day to day operation of e-commerce platform\nStrong sense of responsibility\nResponsible for sales reports and performance analysis\nResponsible for checking inventory transfer and sales order\nHandle ad hoc projects as assigned by supervisor\nWho will be our potential target?\n\n\nForm 5 or above\nMinimum 1 year relevant experience\nGood command of English and Chinese\nGood PC skills in MS Word, Excel, and PowerPoint\nCandidates with less experience will be considered as Senior Clerk\nImmediate available is highly preferred\n\nWe offer five days work week\u00a0and\u00a0attractive remuneration package to the right candidates. Interested parties please apply by clicking\u00a0\"Apply Now\"\u00a0with your resume, current and expected salary\n\n(Data collected will be used for recruitment purpose only.)\n\n\n", "employment_types": ["Full Time", "Permanent"], "selling_points": ["Operations of E-Commerce Platform", "1 Year or Above Relevant Experience", "Immediate Available is Highly Preferred"], "locations": ["Yau Ma Tei"], "categories": ["Sales, CS & Business Devpt", "Wholesale", "E-commerce", "Business Development", "Sales Administration"], "post_time": "2022-01-17T09:13:27Z", "salary": {"currency": null, "max": null, "min": null, "period": "monthly", "term": null}, "salary_visible": false, "title_keywords": ["operations", "senior sales"], "responsibilities": ["sales reports", "analysis", "inventory", "checking", "ad hoc projects", "e-commerce platform"], "requirements": {"degrees": ["form 5 or above"], "majors": [], "languages": ["english", "chinese"], "language_level": ["good command"], "hard_skills": ["excel", "e-commerce", "analysis", "powerpoint", "pc skills", "ms word"], "soft_skills": ["responsible", "sense of responsibility"], "languages_combined": [{"language": "english", "language_level": ["good command"]}, {"language": "chinese", "language_level": ["good command"]}]}, "experience_required": {"duration": ["minimum 1 year"], "field": ["relevant experience"]}}, {"job_id": "100003009051055", "location_code": "hk", "company": "Cargotec Asia Limited", "job_title": "Customer Service Officer", "description": "We are looking for a high caliber candidate to develop his/her career in our Company\uff1a\n\nThe Job :\n\nTo handle customers' enquiries, orders and complaints in an efficient and professional manner;\nTo manage parts order processing, and monitor backlog status and parts delivery;\nTo follow up with customers for invoicing and payment arrangement;\nTo analyze GM% and freight cost of sales orders so as to improve the profitability;\nTo liaise with central service team for pricing and lead time checking;\nTo act as key user for Internal Service Program and solve the issues raised by service technicians (training will be provided);\nTo drive and grow parts sales by actively contacting customers and identifying their needs;\nTo support the service jobs schedule and maintenance service team;\nTo provide feedback on the efficiency of customer service process;\nAd-hoc projects assigned by line Manager.\n\nThe Person:\n\nDegree in Business Administration or equivalent;\nMin. 2 years relevant experience in customer service or sales administration. Proven track record in order processing\uff1b\nIndependent, fast learner, self-motivated, details-minded, well organized and able to work under pressure;\nBusiness\u00a0acumen and\u00a0Customer-oriented;\nGood interpersonal and negotiation skills;\nGood command of spoken and written English, Cantonese and Mandarin;\nKnowledge in SAP will be an advantage;\nFresh graduate will also be considered.\n\nWe offer competitive remuneration package and generous fringe benefits including 5-days work week, medical and dental insurance, discretionary bonus and excellent working condition. Interested candidates please apply through JobsDB.\n\nAll information received will be kept in strict confidence and only for employment-related purpose.\n\n\n\n", "employment_types": ["Full Time", "Permanent"], "selling_points": ["Fresh graduate will also be considered", "Well organized and self-motivated", "Good interpersonal and negotiation skills"], "locations": ["Kwai Fong"], "categories": ["Sales, CS & Business Devpt", "Customer Service - Supervisor / Officer", "Account Servicing", "Sales Administration"], "post_time": "2022-01-15T01:40:36Z", "salary": {"currency": null, "max": null, "min": null, "period": "monthly", "term": null}, "salary_visible": false, "title_keywords": ["customer service officer"], "responsibilities": ["cost", "maintenance", "monitor", "professional manner", "checking", "invoicing", "payment", "customer service", "schedule", "order processing", "liaise with", "ad-hoc projects"], "requirements": {"degrees": ["degree", "fresh graduate"], "majors": ["business administration"], "languages": ["cantonese", "english", "mandarin"], "language_level": ["good command"], "hard_skills": ["sap", "order processing", "acumen"], "soft_skills": ["self-motivated", "independent", "well organized", "customer-oriented", "customer service", "negotiation skills", "business acumen", "fast learner", "interpersonal", "work under pressure"], "languages_combined": [{"language": "cantonese", "language_level": ["good command"]}, {"language": "english", "language_level": ["good command"]}, {"language": "mandarin", "language_level": ["good command"]}]}, "experience_required": {"duration": ["2 years"], "field": ["sales administration", "customer service", "relevant experience"]}}, {"job_id": "100003009054969", "location_code": "hk", "company": "SJS Products HK Ltd", "job_title": "Warehouse Keeper - Hong Kong", "description": "The Hong Kong Warehouse Keeper is responsible for ensuring proper receiving of product and documentation thereof.\u00a0 Ensures that all orders are properly prepared for shipment as required.\u00a0 Accountable for all transfers, paperwork and system functions.\u00a0 Responsible for maintaining the overall appearance and housekeeping of warehouse, and periodic maintenance of warehouse and office at the Hong Kong facility.\nYou must be motivated, organized, professional and timely.\u00a0 The hours for this position are generally 9:00 AM to 6:00 PM, Monday through Friday, but will be dependent on the department and customers\u2019 needs and ensuring that customer needs are fulfilled.Receive incoming material, process paperwork, inspection, disposition to stock/shipping\n\nNotify Loomis QC of incoming shipment for immediate receipt to SAP\nPull stock for orders\nPrint/prepare shippers for daily orders\nPackage orders for delivery\nComplete information required on shipping paperwork and place with the packaged order i.e. bill of lading, international invoices, shippers, security endorsements, etc.\nMeet \u201cOn-time\u201d delivery.\nBag and re-bag stock as needed.\nRecord all inventory movement on inventory cards, and logs, as necessary. (Shipments, receipts, samples, returns, transfers, reworks and MRB)\nComplete all receiving documentation with appropriate information i.e.: date received, qty. received, scale used, sample used, sample weight and initials.\nComplete any other documents necessary. i.e. Overage/Shortage, or rejection.\nAbility to repetitively lift, move and process packages weighing up to 19 kg.\n\n\u00a0JOB REQUIREMENTS\n\n\nThe hours for this position are generally 9:00 AM to 6:00 PM, Monday through Friday, but will be dependent on the department and customers\u2019 needs and ensuring that customer needs are fulfilled.\nBe motivated, organized, professional and timely.\nAbility to repetitively lift, move and process packages weighing up to 19 kg.\nClear telephone and email communication skills. Must be able to speak English clearly and be able to be understood clearly over the telephone and email. Be fluent in Cantonese.\nTyping skills and alpha/numeric data entry skills required.\nOne (1) year minimum warehouse experience.\nOne (1) year minimum of computer experience.\nCustomer Service or Sale Administration Officer experience preferred.", "employment_types": ["Full Time", "Contract"], "selling_points": ["5 days work", "Performance Bonus", "No Special Educational Requirement"], "locations": ["Kwun Tong"], "categories": ["Transportation & Logistics", "Inventory / Warehousing", "Shipping", "Sales, CS & Business Devpt", "Sales Administration"], "post_time": "2022-01-17T16:14:23Z", "salary": {"currency": null, "max": null, "min": null, "period": "monthly", "term": null}, "salary_visible": false, "title_keywords": ["warehouse keeper"], "responsibilities": ["shipping", "invoices", "maintenance", "maintaining", "housekeeping", "receipts", "inventory", "data entry", "inspection", "communication", "daily orders", "customer service", "documentation", "administration"], "requirements": {"degrees": [], "majors": [], "languages": ["cantonese", "english"], "language_level": ["fluent"], "hard_skills": ["documentation", "sap", "typing", "maintenance"], "soft_skills": ["organized", "communication skills", "responsible", "timely", "accountable", "clear", "motivated", "customer service"], "languages_combined": [{"language": "cantonese", "language_level": ["fluent"]}, {"language": "english", "language_level": []}]}, "experience_required": {"duration": [], "field": ["sale", "customer service", "administration"]}}, {"job_id": "100003009054368", "location_code": "hk", "company": "CTF Jewellery Academy Company Limited", "job_title": "Administrative Clerk", "description": "Responsibilities:\nHandle general clerical works such as input data, filing and scanning\nPerform general account duties, such as expenses reimbursement and invoice settlement\nAssist stock replenishment, inventory control, month end stock take\nHandle daily order and responsible for goods receipt\nLiaise with relevant parties to manage Jewellery Exhibition, such as follow up customers\u2019 booking & enquiries and consolidate attendance list\nSupport facilities management\nAssist in other ad-hoc tasks & projects as assigned\nShift duty is required\nWork Location: PMQ located at Central\nRequirements:\n\nForm 5 or above\nMinimum 2 years\u2019 experience in administration work, knowledge in jewellery is an advantage\nGood interpersonal and communication skills\nDetail-minded, well organized and high sense of responsibilities\nGood command of spoken English and Cantonese\nGood in MS Word, Excel and Chinese word processing\nWe offer excellent career opportunities, attractive remuneration package & benefits to the right candidate. Interested parties please\u00a0click\u00a0\"Apply Now\"\u00a0below or\u00a0apply with full resume by stating latest and expected salaries to\u00a022/F, Chow Tai Fook Centre, 580A-580F, Nathan Road, Mongkok, Kowloon, Hong Kong.\u00a0\nAll information collected will be used for recruitment purpose only.", "employment_types": ["Full Time"], "selling_points": ["Handle general clerical works", "Assist stock replenishment, inventory control", "Shift duty is required"], "locations": ["Central"], "categories": ["Admin & HR", "Clerical / Admin Staff", "Sales, CS & Business Devpt", "Retail Sales", "Sales Administration"], "post_time": "2022-01-17T09:18:07Z", "salary": {"currency": null, "max": null, "min": null, "period": "monthly", "term": null}, "salary_visible": false, "title_keywords": ["administrative clerk"], "responsibilities": ["scanning", "attendance", "management", "stock replenishment", "data", "invoice", "ad-hoc tasks", "expenses", "stock take", "inventory control", "booking", "liaise with"], "requirements": {"degrees": [], "majors": [], "languages": [], "language_level": [], "hard_skills": [], "soft_skills": [], "languages_combined": []}, "experience_required": {"duration": [], "field": []}}, {"job_id": "100003009051614", "location_code": "hk", "company": "Lo Lo's Workshop", "job_title": "Secretary", "description": "Responsibilities\n\nTo provide secretarial support to Senior Manager in insurance\u00a0company agency office\nPrepare agenda & minutes\nPrepare meeting clients' documents, scheduling meetings and appointments and so on\nAssist in monitoring admin progress and preparing status report\nMaintain up-to-date and systematic filing system; Administer and monitor clients calls\nAlso responsible for team administration\nNO SALES job and DON'T need to meet clients\n\nRequirements\n\nForm 7 or above with\u00a0secretarial or business training\u00a0\nOver\u00a05 years secretarial and administrative experience, advantageous to have relevant secretarial experience in insurance company / bank\nFamiliar with PC applications including MS Excel, Word and Chinese Word Processing ( Excel is important in this job post )\nGood command of both written and spoken English and Cantonese, Mandarin is a plus\nMature and independent, detail-minded, with initiatives and positive attitude\n\nPlease apply with full resume including expected salary and date availability\n\n\nAll applications will be treated in strict confidence.", "employment_types": ["Full Time", "Permanent"], "selling_points": [], "locations": ["Kwun Tong Area"], "categories": ["Admin & HR", "Secretary", "Insurance", "Others", "Sales, CS & Business Devpt", "Sales Administration"], "post_time": "2022-01-16T14:33:51Z", "salary": {"currency": null, "max": null, "min": null, "period": "monthly", "term": null}, "salary_visible": false, "title_keywords": ["secretary"], "responsibilities": ["administration", "monitoring", "monitor", "scheduling", "maintain", "secretarial support", "insurance", "report"], "requirements": {"degrees": [], "majors": [], "languages": ["cantonese", "english", "chinese", "mandarin"], "language_level": ["good command"], "hard_skills": ["excel", "plus", "chinese word processing", "word", "pc applications", "ms excel"], "soft_skills": ["detail-minded", "confidence", "independent", "mature", "positive attitude"], "languages_combined": [{"language": "cantonese", "language_level": ["good command"]}, {"language": "english", "language_level": ["good command"]}, {"language": "chinese", "language_level": []}, {"language": "mandarin", "language_level": ["good command"]}]}, "experience_required": {"duration": ["5 years"], "field": ["secretarial", "administrative", "insurance"]}}, {"job_id": "100003009052192", "location_code": "hk", "company": "Educational Publishing House, Limited", "job_title": "Senior Sales Coordinator (Order Processing) \u9ad8\u7d1a\u92b7\u552e\u7d71\u7c4c", "description": "\u8077\u8cac:\n\n\u8655\u7406\u92b7\u552e\u8a02\u55ae\uff0c\u8207\u5b78\u6821\u3001\u66f8\u5546\u53ca\u5176\u4ed6\u5ba2\u6236\u8ddf\u9032\u8a02\u55ae\n\u8655\u7406\u5ba2\u6236\u67e5\u8a62\u53ca\u5176\u4ed6\u8ddf\u9032\u5de5\u4f5c\n\u7ba1\u7406\u92b7\u552e\u6578\u64da\u5eab\u8a18\u9304\u3001\u92b7\u552e\u5831\u544a\n\u4e00\u822c\u6587\u66f8\u5de5\u4f5c\n\u5354\u52a9\u7ba1\u7406\u5718\u968a\n\n\u8981\u6c42:\n\n\u6587\u6191\u6216\u4ee5\u4e0a\u7a0b\u5ea6\n\u81f3\u5c115\u5e74\u8a02\u55ae\u8655\u7406 /\u00a0\u5ba2\u6236\u670d\u52d9\u5de5\u4f5c\u7d93\u9a57\uff0c\u4e26\u51772-3\u5e74\u7763\u5c0e\u7d93\u9a57\n\u719f\u6089MS Office\uff0c\u6709\u7cfb\u7d71\u8f38\u5165\u7d93\u9a57\n\u826f\u597d\u6e9d\u901a\u6280\u5de7\u548c\u5ba2\u6236\u670d\u52d9\u6280\u5de7\n\u53ef\u5373\u6642\u5230\u8077\u8005\u512a\u5148\u8003\u616e\n\n\u672c\u516c\u53f8\u63d0\u4f9b\u826f\u597d\u4e8b\u696d\u767c\u5c55\u6a5f\u6703\u53ca\u826f\u597d\u85aa\u916c\u53ca\u798f\u5229\u3002\u6709\u8208\u8da3\u8005\u8acb\u6309\"APPLY NOW\"\u63d0\u4ea4\u500b\u4eba\u5c65\u6b77\u6216\u900f\u904e Whatsapp 96887362 \u4e86\u89e3\u8a73\u60c5\u3002\n\n\u6b61\u8fce\u700f\u89bd\u672c\u516c\u53f8\u7db2\u9801\u00a0http://www.popular.com.hk\u00a0\u6216\u00a0http://ephhk.popularworldhk.com\u00a0.\n\n\u6240\u6709\u8077\u4f4d\u7533\u8acb\u5c07\u4f5c\u6a5f\u5bc6\u8cc7\u6599\u8655\u7406\u53ca\u53ea\u4f5c\u62db\u8058\u7528\u9014\u3002", "employment_types": ["Full Time", "Permanent"], "selling_points": ["\u8a02\u55ae\u8655\u7406\u3001\u5354\u52a9\u7ba1\u7406\u5718\u968a", "\u4e94\u5929\u5de5\u4f5c, \u91ab\u7642\u53ca\u7259\u79d1\u4fdd\u96aa, \u914c\u60c5\u82b1\u7d05", "\u5a5a\u5047, \u6559\u80b2\u6d25\u8cbc, \u8343\u7063"], "locations": ["Tsuen Wan Area"], "categories": ["Sales, CS & Business Devpt", "Customer Service - Supervisor / Officer", "Transportation & Logistics", "Fulfillment", "Sales Administration"], "post_time": "2022-01-17T02:25:29Z", "salary": {"currency": null, "max": null, "min": null, "period": "monthly", "term": null}, "salary_visible": false, "title_keywords": ["coordinator", "senior sales"], "responsibilities": [], "requirements": {"degrees": [], "majors": [], "languages": [], "language_level": [], "hard_skills": ["whatsapp"], "soft_skills": [], "languages_combined": []}, "experience_required": {"duration": [], "field": []}}, {"job_id": "100003009056339", "location_code": "hk", "company": "PVH Asia Limited", "job_title": "Part-time Retail Assistant", "description": "PRIMARY RESPONSIBILITIES:\n\n\n\nSupport dual brands\nSupport DS to do roster/ attendance record check, including location allowance and incentive\nAssist DS to draw all data from Xstore/ dashboard for weekly meeting\nUpdate Non-Merchandise inventory in office ( e.g. coupon, welcome kit, registration form) and arrange the distribution by regular basis\nSupport ad-hoc member registration form data entry during stores peak moments ( e.g. coupon end date, CG new members etc.)\u00a0\n\nREQUIREMENTS:\n\n\nBasic computer skills, especially MS Excel", "employment_types": ["Part Time"], "selling_points": ["2 - 3 days / week, Mon is a must", "6 months contract", "Immediate available is preferable"], "locations": ["Others"], "categories": ["Sales, CS & Business Devpt", "Sales Administration"], "post_time": "2022-01-18T04:00:30Z", "salary": {"currency": null, "max": null, "min": null, "period": "hourly", "term": null}, "salary_visible": false, "title_keywords": ["assistant"], "responsibilities": ["ad-hoc", "attendance", "data entry", "data", "inventory"], "requirements": {"degrees": [], "majors": [], "languages": [], "language_level": [], "hard_skills": ["computer skills", "ms excel", "basic"], "soft_skills": [], "languages_combined": []}, "experience_required": {"duration": [], "field": []}}, {"job_id": "100003009051147", "location_code": "hk", "company": "Controlled Medications Limited", "job_title": "Senior Sales Administrator", "description": "Job Duties:\n\nexecute order processing upon order in placed, including customer a/c set-up\nprepare delivery and shipping arrangements\nupdate system info and status, also documentation filing\nliaise with warehouse team for daily inbound / outbound delivery\nact as customer service to handle customer enquiries\ncoordinate supply chain activities from end to end\narrange invoicing to customer\nassist stock take execution\nbook all operation cost into system\nsupport various documentation per ISO standard\nperform ad hoc duties assigned by management\n\nJob Requirements:\n\nDSE certificate or above\n8 year or above relevant working experience including 3 years in supervisory role\nExperience in System Changeover will be an advantage\nMS Dynamic NAV/any ERP system usage experience\nAverage spoken and written English and Chinese\nAttention to details, work independently, high problem-solving skill\nless experience or fresh graduates are also welcome\nImmediate available is highly preferable\n\nWe offer a 5-day working week, an attractive remuneration package and excellent career opportunities to the right candidate.\u00a0\n\nInterested parties, please send full resume\u00a0with current and expected salary\u00a0by clicking 'Apply Now'.\n\n\nAll personal data collected will be used for recruitment purposes only. Applicants who are not contacted within 6 weeks may consider your applications unsuccessful and the personal data collected will be destroyed after six months.", "employment_types": ["Full Time", "Permanent"], "selling_points": ["5 days, 13-19 days AL, Group medical, PH", "8 sales admin relevant experience, Immediate", "customer, process & result oriented, team work"], "locations": ["Kwun Tong"], "categories": ["Admin & HR", "Administration / Operation Manager", "Sales, CS & Business Devpt", "Customer Service - Supervisor / Officer", "Sales Administration"], "post_time": "2022-01-15T03:32:27Z", "salary": {"currency": null, "max": null, "min": null, "period": "monthly", "term": null}, "salary_visible": false, "title_keywords": ["administrator", "senior sales"], "responsibilities": ["ad hoc duties", "cost", "shipping", "handle customer enquiries", "management", "stock take", "coordinate", "liaise with", "invoicing", "customer service", "order processing", "documentation"], "requirements": {"degrees": ["certificate", "dse"], "majors": [], "languages": ["english", "chinese"], "language_level": ["average"], "hard_skills": ["problem-solving", "erp system", "dynamic"], "soft_skills": ["problem-solving", "work independently", "dynamic", "attention to details"], "languages_combined": [{"language": "english", "language_level": ["average"]}, {"language": "chinese", "language_level": ["average"]}]}, "experience_required": {"duration": ["3 years", "8 year"], "field": ["supervisory", "erp system", "relevant working experience"]}}, {"job_id": "100003009054366", "location_code": "hk", "company": "DataLouder Company Limited", "job_title": "Sales and Marketing Consultant", "description": "Job Highlights\n\n\u00a0\u00a0\u00a0\u00a0\u00a0\u00a0 Start-up and energetic environment\n\u00a0\u00a0\u00a0\u00a0\u00a0\u00a0 Good communication and customer services skills\n\u00a0\u00a0\u00a0\u00a0\u00a0\u00a0 Basic salary with commission\n\u00a0\u00a0\u00a0\u00a0\u00a0\u00a0 Fresh university graduates will also be considered\n\nJob Description\n\nResponsibilities:\n\n\nPlan and execute sales strategies to achieve revenue targets\nDevelop new customer network to increase sales\nAchieve and drive B2C sales, projects and related training and development solutions\nEstablish and maintain good business relationships with clients\nHandling enquiries and customer follow-ups on various online platforms e.g. Whatsapp, Facebook etc.\nProvide professional consultation to our existing and potential clients\nPrepare course materials for after-sales tutorials/ services\nAssist in other ad-hoc projects as assigned\n\nRequirements:\n\n\nDegree holder in related disciplines with 1-2 years of work experience in sales; fresh graduate or IANG holder will also considered\nPossess problem-solving skills and good listening skills to tailor the best solution according to clients' needs\nGood command of written and spoken English, Cantonese and Mandarin\nGood communication & presentation skills, self-motivated and customer oriental\nCheerful, caring, patient, responsible and initiative\nInterested in stock market/ trading\nKnowledge on solutions / digital selling will be an added advantage\nKnowledge in PC operation, including Microsoft Word, Excel & PPT and Chinese word processing\nFind us on https://datalouder.com/\n\n\n\nA highly competitive remuneration package will be offered. Candidates with less experience will be considered as Sales and Marketing Assistant.", "employment_types": ["Full Time", "Part Time"], "selling_points": ["Fintech and social media startup", "Basic salary with commission", "1-2 years of work experience in sales"], "locations": ["Admiralty"], "categories": ["Sales, CS & Business Devpt", "Customer Service - Supervisor / Officer", "Account Servicing", "Sales Administration"], "post_time": "2022-01-17T09:27:46Z", "salary": {"currency": null, "max": null, "min": null, "period": "monthly", "term": null}, "salary_visible": false, "title_keywords": ["consultant", "sales"], "responsibilities": ["develop", "maintain", "plan", "facebook", "ad-hoc projects"], "requirements": {"degrees": ["fresh graduate", "degree holder"], "majors": ["related disciplines"], "languages": ["cantonese", "english", "chinese", "mandarin"], "language_level": ["good command"], "hard_skills": ["excel", "microsoft word", "chinese word processing", "problem-solving skills", "pc"], "soft_skills": ["self-motivated", "cheerful", "responsible", "interested in", "patient", "communication", "presentation skills", "problem-solving skills", "initiative"], "languages_combined": [{"language": "cantonese", "language_level": ["good command"]}, {"language": "english", "language_level": ["good command"]}, {"language": "chinese", "language_level": []}, {"language": "mandarin", "language_level": ["good command"]}]}, "experience_required": {"duration": ["1-2 years"], "field": ["related", "marketing"]}}, {"job_id": "100003009053984", "location_code": "hk", "company": "The Hong Kong Jockey Club", "job_title": "Part-time - Administrative Assistant (Archives)", "description": "Hourly Pay:\n\n$73.5/hour\n\nJob Duties:\n\nWork with Archives Team to conduct research as assigned\nAssist in archives\u2019 digitization projects such as scanning, photographing and indexing the archives collection\nAssist in processing of archives collection including physical arrangements\nAssist in other general office duties as required\n\nRequirements:\n\nHKDSE/HKALE or equivalent, preferably with data entry experience\nSound knowledge in history, prior work experiences in archives and museum would be an advantage\nHands-on IT skills with the ability to use MS office packages & Adobe Photoshop\nGood communication and interpersonal skills\n\nWork Hours:\n\nStaff is required to work at least 2 weekdays per week.\n\nWork Location:\n\nThe Hong Kong Jockey Club Headquarter, One Sports Road, Happy Valley\n\nWe are an equal opportunity employer.\nPersonal data collected will be used for recruitment purposes only.", "employment_types": ["Part Time", "Temporary", "Freelance"], "selling_points": ["conduct research as assigned", "Assist in archives\u2019 digitization projects", "Assist in processing of archives collection"], "locations": ["Causeway Bay"], "categories": ["Admin & HR", "Clerical / Admin Staff", "Hospitality / F & B", "Hospitality / Hotel Services", "Sales, CS & Business Devpt", "Sales Administration"], "post_time": "2022-01-17T07:55:20Z", "salary": {"currency": null, "max": null, "min": null, "period": null, "term": null}, "salary_visible": false, "title_keywords": ["administrative assistant"], "responsibilities": ["scanning", "conduct research"], "requirements": {"degrees": ["hkdse"], "majors": [], "languages": [], "language_level": [], "hard_skills": ["adobe photoshop", "ms office"], "soft_skills": ["hands-on", "communication and interpersonal skills"], "languages_combined": []}, "experience_required": {"duration": [], "field": []}}, {"job_id": "100003009047713", "location_code": "hk", "company": "Mountain Hill Company", "job_title": "Sales Support Coordinator", "description": "Requirements\n\nDegree or Higher Diploma holder\n2-3 years working experience in sales support coordination\nSolid experience in customer liaison and logistics arrangement\nExperience in trading or manufacturing company is preferred\nInitiative, detail-minded, energetic with cheerful personality\nGood communication of English and fair in spoken Putonghua\nWell-versed in using MS Word, Excel, Chinese WP and Outlook\nImmediate available is highly preferred\n\nResponsibilities\n\nFollow up sales orders with overseas customers and suppliers\nProvide support on preparing quotation, purchase orders and invoice\nAssist in logistics and delivery arrangement and prepare related documents\nResponsible for maintaining sales system and ad hoc tasks as assigned\n\nAttractive remuneration package and excellent career prospect will be offered to the successful candidates. For interested parties, please send full resume stating expected and last salary with date of available by clicking \u2018Apply Now\u2019", "employment_types": ["Full Time", "Permanent"], "selling_points": [], "locations": ["Not Specified"], "categories": ["Sales, CS & Business Devpt", "Customer Service - Supervisor / Officer", "Transportation & Logistics", "Shipping", "Sales Administration"], "post_time": "2022-01-15T01:51:20Z", "salary": {"currency": null, "max": null, "min": null, "period": "monthly", "term": null}, "salary_visible": false, "title_keywords": ["coordinator", "sales"], "responsibilities": ["provide support", "maintaining", "invoice", "related documents", "quotation", "ad hoc tasks", "purchase", "logistics"], "requirements": {"degrees": ["degree", "higher diploma holder"], "majors": [], "languages": ["putonghua", "english", "chinese"], "language_level": ["good"], "hard_skills": ["excel", "chinese wp", "sales support", "outlook", "ms word"], "soft_skills": ["detail-minded", "cheerful", "communication", "coordination", "energetic", "initiative"], "languages_combined": [{"language": "putonghua", "language_level": ["good"]}, {"language": "english", "language_level": ["good"]}, {"language": "chinese", "language_level": []}]}, "experience_required": {"duration": ["2-3 years"], "field": ["logistics", "manufacturing", "sales support", "trading"]}}, {"job_id": "100003009056336", "location_code": "hk", "company": "MIB Securities (Hong Kong) Limited", "job_title": "Sales Assistant", "description": "Responsibilities:\n\nProvide excellent customer services to internal stakeholders, external clients and business contacts\nAssist sales and account executives on handling client enquiries to provide effective solutions\nAssist in placing dealing orders for HK & different securities markets\nProvide administrative support to Department Heads and team members\nAssist in preparing business related documents\nWilling to handle other ad hoc duties when necessary\n\nRequirements:\n\nUniversity Degree in Finance, Banking, Economic, Business Administration or related discipline\nHolder of SFC Regulated Activity Type 1 License preferred\nMinimum 1 year of relevant experience in HK and overseas securities markets\nKnowledge of stocks, futures and options in HK and Global markets\nProactive, customer-oriented and responsible\nGood command in English, Cantonese and Mandarin\nProficient in computer skills\u00a0\n\nInterested parties please send full resume with contact telephone number and expected salary to Human Capital Department, MIB Securities (Hong Kong) Limited at 28/F, Lee Garden Three, 1 Sunning Road, Causeway Bay, Hong Kong or via e-mail (in MSWord form)\n\nThe personal data collected in the job application will only be used by MIB Securities (Hong Kong) Limited, its subsidiaries and/or affiliates (Maybank Investment Banking Group) internally to assess your suitability to assume the job duties of the position for which you have applied.\u00a0 All personal data will be handled in strict confidence and filed with Human Capital Department.\u00a0 It is the Company policy to retain the personal data of unsuccessful applicants for future recruitment opportunities for a period of maximum six (6) months, otherwise it will be destroyed.", "employment_types": ["Full Time", "Permanent"], "selling_points": [], "locations": ["Causeway Bay"], "categories": ["Banking / Finance", "Financial Services", "Sales, CS & Business Devpt", "Sales Administration"], "post_time": "2022-01-18T04:00:08Z", "salary": {"currency": null, "max": null, "min": null, "period": "monthly", "term": null}, "salary_visible": false, "title_keywords": ["sales assistant"], "responsibilities": ["provide administrative support", "related documents", "ad hoc duties", "customer services"], "requirements": {"degrees": ["university degree"], "majors": ["finance", "business administration"], "languages": ["cantonese", "english", "mandarin"], "language_level": ["good command"], "hard_skills": ["computer skills"], "soft_skills": ["customer-oriented", "proactive", "responsible"], "languages_combined": [{"language": "cantonese", "language_level": ["good command"]}, {"language": "english", "language_level": ["good command"]}, {"language": "mandarin", "language_level": ["good command"]}]}, "experience_required": {"duration": ["minimum 1 year"], "field": ["securities", "relevant experience"]}}, {"job_id": "100003009050776", "location_code": "hk", "company": "iDance International Limited", "job_title": "Sales Coordinator / Sales Executive", "description": "Job responsibilities\n\n\nCollect and maintain the customer database\nCollect feedback on the certification services to evaluate customer satisfaction and identify opportunities for improvement\nParticipating in the billing process\nBuild and maintain a close relationship with existing customers, understand their needs to provide support to ensure the provision of the desired services and enhance up-sell opportunities.\nSupport event management (if necessary)\nHandling ad hoc tasks and any other assigned duties as requested\n\nJob requirement\n\n\nDiploma or above\nMin 1-year job experience\nStrong telephone communication skills\nProactive, fast learner\nGood interpersonal skills\nFluent in English and Mandarin\nInterested parties please send us a full resume with your\u00a0CURRENT & EXPECTED SALARY\u00a0simply click \"APPLY NOW\".\u00a0\u00a0\n\n\nPersonal data provided by applicants will be treated in strict confidence and used for recruitment purposes only for no more than 6 months.", "employment_types": ["Full Time", "Permanent"], "selling_points": [], "locations": ["Ngau Tau Kok"], "categories": ["Merchandising & Purchasing", "Electronics", "Sales, CS & Business Devpt", "Account Servicing", "Sales Administration"], "post_time": "2022-01-14T11:21:12Z", "salary": {"currency": null, "max": null, "min": null, "period": "monthly", "term": null}, "salary_visible": false, "title_keywords": ["sales coordinator", "sales executive"], "responsibilities": ["provide support", "management", "billing process", "ad hoc tasks", "evaluate", "maintain", "database"], "requirements": {"degrees": ["diploma or above"], "majors": [], "languages": ["english", "mandarin"], "language_level": ["fluent"], "hard_skills": [], "soft_skills": ["communication skills", "proactive", "fast learner", "interpersonal skills"], "languages_combined": [{"language": "english", "language_level": ["fluent"]}, {"language": "mandarin", "language_level": ["fluent"]}]}, "experience_required": {"duration": ["min 1-year"], "field": []}}, {"job_id": "100003009055466", "location_code": "hk", "company": "Chandler Macleod Group (HK) Limited", "job_title": "Customer Care Team Lead (Up to 25K/mth)", "description": "Job Description:\n\nImplement sales plan to promote and sell product solutions to customers\nMaintain excellent relationship with customers\nDevelop future business opportunities for new customers\nExpand business with current customers\nCoordinate quotations, sales orders, contracts, tenders and proposals for customers\nCoordinate and handle customer enquiries and complaints\nAssist in any related added responsibilities assigned by Sales Manager\n\nRequirements:\n\nForm 5 (HKCEE) or Form 6 (DSE) or above\nWorking experience in sales, marketing, customer service or management would be advantageous\nFresh graduate will be considered\nExcellent interpersonal, communication and presentation skills\nGood computer knowledge (MS Office, Chinese word processing)\nGood command of English and Cantonese, Mandarin speaking would be advantageous\nMust be organized, self-motivated, willing to learn and able to work under pressure and over time when necessary\nOutdoor activities are required when necessary (including site visit, documents delivery)\n\nWorking Hours and Benefits:\n\nNormal working hours from 9:00 am to 6:00 pm (Mon to Fri), 9:00 am to 1:00pm (Sat)\nAlternate Saturday-off\nMedical plan after probation period (outpatient, dental, hospitalisation benefits)\nAttractive salary + Performance bonus\n\nCandidates who are interested please click \"APPLY NOW\" for interview arrangement\n\nPersonal Data collected will be used for recruitment purposes only\n\n-------------------------------------------------------------------------------------------------\n\n\u5de5\u4f5c\u8077\u8cac:\n\n\u00a0 \u00a0 \u00a0 \u00a0 \u00a0 \u00a0 \u00a0\u8655\u7406\u92b7\u552e\u8a08\u5283\uff0c\u63a8\u5ee3\u548c\u92b7\u552e\u7522\u54c1\u89e3\u6c7a\u65b9\u6848\u7d66\u5ba2\u6236\n\u00a0 \u00a0 \u00a0 \u00a0 \u00a0 \u00a0 \u00a0\u8207\u5ba2\u6236\u4fdd\u6301\u826f\u597d\u7684\u5408\u4f5c\u95dc\u4fc2\n\u00a0 \u00a0 \u00a0 \u00a0 \u00a0 \u00a0 \u00a0\u70ba\u65b0\u5ba2\u6236\u958b\u767c\u672a\u4f86\u7684\u696d\u52d9\u5408\u4f5c\u6a5f\u6703\n\u00a0 \u00a0 \u00a0 \u00a0 \u00a0 \u00a0 \u00a0\u64f4\u5927\u8207\u73fe\u6709\u5ba2\u6236\u7684\u696d\u52d9\n\u00a0 \u00a0 \u00a0 \u00a0 \u00a0 \u00a0 \u00a0\u8655\u7406\u5831\u50f9\uff0c\u92b7\u552e\u8a02\u55ae\uff0c\u5408\u540c\uff0c\u6a19\u66f8\u548c\u5efa\u8b70\n\u00a0 \u00a0 \u00a0 \u00a0 \u00a0 \u00a0 \u00a0\u5354\u8abf\u53ca\u8655\u7406\u5ba2\u6236\u7684\u8aee\u8a62\u53ca\u6295\u8a34\n\u00a0 \u00a0 \u00a0 \u00a0 \u00a0 \u00a0 \u00a0\u5354\u52a9\u92b7\u552e\u7d93\u7406\u8655\u7406\u5de5\u4f5c\u53ca\u6839\u64da\u92b7\u552e\u7d93\u7406\u7684\u6307\u793a\n\n\u8981\u6c42:\n\n\u00a0\u00a0\u00a0\u00a0\u00a0\u00a0\u00a0\u00a0\u00a0\u00a0\u00a0\u00a0 \u9999\u6e2f\u4e2d\u5b78\u6703\u8003 / \u4e2d\u5b78\u6587\u6191\u8003\u8a66\u6216\u4ee5\u4e0a\u7a0b\u5ea6\u5b78\u6b77\n\u00a0\u00a0\u00a0\u00a0\u00a0\u00a0\u00a0\u00a0\u00a0\u00a0\u00a0\u00a0 \u5177\u92b7\u552e\uff0c\u5e02\u5834\u71df\u92b7\uff0c\u5ba2\u6236\u670d\u52d9\u6216\u7ba1\u7406\u5de5\u4f5c\u7d93\u9a57\u512a\u5148\n\u00a0 \u00a0 \u00a0 \u00a0 \u00a0 \u00a0 \u00a0\u6b61\u8fce\u61c9\u5c46\u7562\u696d\u751f\u7533\u8acb\n\u00a0\u00a0\u00a0\u00a0\u00a0\u00a0\u00a0\u00a0\u00a0\u00a0\u00a0\u00a0 \u512a\u79c0\u7684\u4eba\u969b\u4ea4\u5f80\uff0c\u6e9d\u901a\u548c\u8868\u9054\u80fd\u529b\n\u00a0\u00a0\u00a0\u00a0\u00a0\u00a0\u00a0\u00a0\u00a0\u00a0\u00a0\u00a0 \u826f\u597d\u7684\u96fb\u8166\u77e5\u8b58 (MS Office\uff0c\u4e2d\u6587\u8f38\u5165\u6cd5)\n\u00a0\u00a0\u00a0\u00a0\u00a0\u00a0\u00a0\u00a0\u00a0\u00a0\u00a0\u00a0 \u826f\u597d\u82f1\u8a9e\u53ca\u7cb5\u8a9e, \u7565\u61c2\u666e\u901a\u8a71\u66f4\u4f73\n\u00a0\u00a0\u00a0\u00a0\u00a0\u00a0\u00a0\u00a0\u00a0\u00a0\u00a0\u00a0 \u5fc5\u9808\u662f\u6709\u689d\u7406\uff0c\u6709\u4e0a\u9032\u5fc3\uff0c\u80af\u5b78\u7fd2\uff0c\u4e26\u80fd\u5728\u58d3\u529b\u4e0b\u5de5\u4f5c\u53ca\u61c9\u4ed8\u8d85\u6642\u5de5\u4f5c\u7684\u9700\u8981\n\u00a0 \u00a0 \u00a0 \u00a0 \u00a0 \u00a0\u00a0 \u6709\u9700\u8981\u6642\u8981\u5916\u51fa\u5de5\u4f5c (\u5305\u62ec\u9805\u76ee\u8996\u5bdf\uff0c\u904b\u9001\u6587\u4ef6)\n\n\u5de5\u4f5c\u6642\u9593\u53ca\u798f\u5229:\n\n\u00a0\u00a0\u00a0\u00a0\u00a0\u00a0\u00a0\u00a0\u00a0\u00a0\u00a0\u00a0 \u6bcf\u9031\u5de5\u4f5c5.5\u65e5\uff0c\u661f\u671f\u4e00\u81f3\u4e94\u6bcf\u65e5\u7531\u4e0a\u5348\u4e5d\u6642\u81f3\u4e0b\u5348\u516d\u6642\uff0c\u661f\u671f\u516d\u7531\u4e0a\u5348\u4e5d\u6642\u81f3\u4e0b\u5348\u4e00\u6642\n\u00a0\u00a0\u00a0\u00a0\u00a0\u00a0\u00a0\u00a0\u00a0\u00a0\u00a0\u00a0 \u661f\u671f\u516d\u9577\u77ed\u9031\u5de5\u4f5c\n\u00a0\u00a0\u00a0\u00a0\u00a0\u00a0\u00a0\u00a0\u00a0\u00a0\u00a0\u00a0 \u8a66\u7528\u671f\u5f8c\u53ef\u4eab\u54e1\u5de5\u91ab\u7642\u798f\u5229 (\u5305\u62ec\u9580\u8a3a + \u7259\u79d1 + \u4f4f\u9662)\n\u00a0\u00a0\u00a0\u00a0\u00a0\u00a0\u00a0\u00a0\u00a0\u00a0\u00a0\u00a0 \u512a\u539a\u85aa\u916c + \u696d\u7e3e\u734e\u91d1\n\n\u6709\u610f\u8005\u8acb\u6309\"APPLY NOW\"\u63d0\u4ea4\u5c65\u6b77\u8868\n\n\u6240\u6536\u96c6\u7684\u500b\u4eba\u8cc7\u6599\u5c07\u50c5\u7528\u4f5c\u62db\u8058\u7528\u9014", "employment_types": ["Full Time", "Permanent"], "selling_points": ["A fast-growing fintech firm", "Westernized work environment", "Excellent work environment and culture"], "locations": ["Not Specified"], "categories": ["Sales, CS & Business Devpt", "Customer Service - Supervisor / Officer", "Account Servicing", "Sales Administration"], "post_time": "2022-01-18T02:37:35Z", "salary": {"currency": null, "max": null, "min": null, "period": "monthly", "term": null}, "salary_visible": false, "title_keywords": ["lead"], "responsibilities": ["contracts", "business opportunities", "develop", "coordinate", "maintain", "plan", "customer enquiries and complaints"], "requirements": {"degrees": ["fresh graduate", "form 5", "dse"], "majors": [], "languages": ["cantonese", "english", "chinese", "mandarin"], "language_level": ["good command", "good"], "hard_skills": ["chinese word processing", "ms office"], "soft_skills": ["organized", "self-motivated", "willing to learn", "communication", "presentation skills", "customer service", "interpersonal", "work under pressure"], "languages_combined": [{"language": "cantonese", "language_level": ["good command", "good"]}, {"language": "english", "language_level": ["good command", "good"]}, {"language": "chinese", "language_level": ["good"]}, {"language": "mandarin", "language_level": ["good command", "good"]}]}, "experience_required": {"duration": [], "field": ["management", "marketing", "customer service"]}}, {"job_id": "100003009051676", "location_code": "hk", "company": "Pre/View Design Limited", "job_title": "Project Assistant / Executive", "description": "\u6e96\u5099\u597d\u8fce\u63a5\u4e0d\u4e00\u6a23\u7684\u5e73\u51e1\uff1f\n\u60f3\u64fa\u812b\u671d\u4e5d\u665a\u516d\u6c89\u60b6\u5de5\u4f5c\uff0c\u7531\u88ab\u5de5\u4f5c\u91cd\u91cd\u675f\u7e1b\uff0c\u5230\u53ef\u4ee5\u81ea\u4e3b\u751f\u6d3b\uff1f\n\u52a0\u5165\u6211\u5011\uff0c\u8b93\u6211\u5011\u4e26\u80a9\u524d\u884c\u3002\n\n**\u5c08\u696d\u767c\u5c55\n\n\n\u57f9\u990a\u5ba2\u4eba\u7406\u8ca1\u89c0\u5ff5\n\n\u63d0\u4f9b\u7406\u8ca1\u5831\u544a\u7d66\u5ba2\u6236\uff0c\u5305\u62ec\u98a8\u96aa\u7ba1\u7406\u548c\u8ca1\u5bcc\u7ba1\u7406\u00a0\n\u5b9a\u671f\u70ba\u5ba2\u4eba\u8ddf\u9032\u4fdd\u55ae\u670d\u52d9\uff0c\u5305\u62ec\u7d22\u511f\u3001\u5b9a\u671f\u6aa2\u8a0e\u00a0\n\n\u70ba\u5ba2\u4eba\u6574\u5408MPF\n\n\u63d0\u4f9b\u4e00\u822c\u4fdd\u96aa\u7522\u54c1\u670d\u52d9\n\n\u4e86\u89e3\u793e\u6703\u7d93\u6fdf\u65b0\u805e\n\u8003\u53d6\u5c08\u696d\u8cc7\u683c\uff0c\u5982\u8a8d\u53ef\u8ca1\u52d9\u7b56\u5283\u5e2b\u00a0(CFP)\n\n**\u8c50\u539a\u56de\u5831\n\n\u9999\u6e2f\u4eba\u5718\u968a\n\n24\u500b\u6708\u8ca1\u52d9\u652f\u63f4 (\u6bcf\u6708\u6d25\u8cbc\u905415,000\u81f340,000)+\u00a0\u7121\u4e0a\u9650\u4f63\u91d1\n\u6bcf\u5e749\u6b21\u82b1\u7d05\n\n\u5168\u65b9\u4f4d\u5728\u8077\u5c08\u696d\u57f9\u8a13\n\u5f48\u6027\u5de5\u4f5c\u6642\u9593\uff0c\u81ea\u4e3b\u500b\u4eba\u751f\u610f\uff0c\u9054\u81f3\u5de5\u4f5c\u8207\u751f\u6d3b\u5e73\u8861\n\u5718\u9ad4\u91ab\u7642\u4fdd\u969c\u00a0& \u9000\u4f11\u91d1\n\u696d\u7e3e\u734e\u8cde\u53ef\u514d\u8cbb\u53c3\u52a0\u6d77\u5916\u65c5\u904a\u53ca\u6703\u8b70\n\u5efa\u7acb\u53ca\u7ba1\u7406\u5c08\u696d\u71df\u696d\u5718\u968a\n\n\u00a0**\u62db\u52df\u5c0d\u8c61\n\n\nHKID holder \u5fc5\u9808\u6301\u6709\u9999\u6e2f\u8eab\u5206\u8b49\n\u61c9\u5c46\u5927\u5c08\u7562\u696d\u751f/ \u526f\u5b78\u58eb\u7562\u696d\u751f/ \u9ad8\u7d1a\u6587\u6191\u7562\u696d\u751f\n\u878d\u5165\u5718\u968a,\u00a0\u771f\u8aa0\u5b78\u7fd2,\u00a0\u5de5\u4f5c\u52e4\u529b,\u00a0\u5fc3\u614b\u6b63\u9762\n\u826f\u597d\u6e9d\u901a\u6280\u5de7\n\n\u6709\u8208\u8da3\u7533\u8acb\u8005\u8acb\u6309Apply Now \u7533\u8acb\u3002\n[\u6240\u6536\u96c6\u7684\u500b\u4eba\u8cc7\u6599\u53ea\u4f5c\u62db\u8058\u7528\u9014]", "employment_types": ["Full Time"], "selling_points": [], "locations": ["Shau Kei Wan"], "categories": ["Admin & HR", "Clerical / Admin Staff", "Media & Advertising", "Account Servicing", "Sales, CS & Business Devpt", "Sales Administration"], "post_time": "2022-01-16T21:50:42Z", "salary": {"currency": null, "max": null, "min": null, "period": "monthly", "term": null}, "salary_visible": false, "title_keywords": ["executive", "project assistant"], "responsibilities": [], "requirements": {"degrees": [], "majors": [], "languages": [], "language_level": [], "hard_skills": [], "soft_skills": [], "languages_combined": []}, "experience_required": {"duration": [], "field": []}}, {"job_id": "100003009052967", "location_code": "hk", "company": "Telford International Co Ltd", "job_title": "Sales Trainee - Beverage Division", "description": "\n\u8077\u8cac :\u8ca0\u8cac\u8ddf\u55ae, \u806f\u7d61\u5ba2\u4eba, \u5b89\u6392\u51fa\u8ca8\n\n\u8cc7\u6b77 :\u4e2d\u516d\u7a0b\u5ea6; 2\u5e74\u7d93\u9a57; \u826f\u597d\u7cb5\u8a9e; \u4e00\u822c\u666e\u901a\u8a71; \u4e00\u822c\u82f1\u8a9e\u512a\u5148; \u61c2\u8b80\u5beb\u4e2d\u6587; \u61c2\u8b80\u5beb\u82f1\u6587; \u61c2MS Outlook; \u61c2MS Excel; \u61c2\u4e2d\u6587\u6253\u5b57 20 \u5b57(\u6bcf\u5206\u9418); \u719f\u6089\u8ddf\u55ae, \u5de5\u4f5c\u52e4\u596e\n\n\u5f85\u9047 :\u6bcf\u6708$14,000 - $17,000, \u6709\u96d9\u7ce7, \u9280\u884c\u5047\u671f\u53ca\u5e74\u7d42\u734e\u91d1, \u661f\u671f\u4e00\u81f3\u4e94: \u4e0a\u53488\u664245\u5206\u81f3\u4e0b\u53486\u6642, \u6bcf\u9031\u5de5\u4f5c5\u5929\n\n\u7533\u8acb\u9808\u77e5 :\u6c42\u8077\u8005\u53ef\u96fb\u90f5(Apply Now)\u5c65\u6b77\u8868\u7d66\u532f\u9032\u5be6\u696d\u767c\u5c55\u6709\u9650\u516c\u53f8\u3002\u5982\u8981\u7d22\u53d6\u6536\u96c6\u500b\u4eba\u8cc7\u6599\u8072\u660e, \u8acb\u8207\u912d\u5c0f\u59d0(Email)\u806f\u7d61\u3002\n\n", "employment_types": ["Full Time", "Permanent"], "selling_points": ["Diploma \u2013 major in business is preferred", "Fresh graduate are also welcomed", "Self-motivated, customer focused and result driven"], "locations": ["Kwai Hing"], "categories": ["Sales, CS & Business Devpt", "Business Development", "Account Servicing", "Sales Administration"], "post_time": "2022-01-17T04:44:10Z", "salary": {"currency": null, "max": null, "min": null, "period": "monthly", "term": null}, "salary_visible": false, "title_keywords": ["sales trainee"], "responsibilities": [], "requirements": {"degrees": [], "majors": [], "languages": [], "language_level": [], "hard_skills": ["excel", "outlook"], "soft_skills": [], "languages_combined": []}, "experience_required": {"duration": [], "field": []}}, {"job_id": "100003009055051", "location_code": "hk", "company": "Gemini Personnel Limited", "job_title": "Sales Assistant (TST, 13mth/Salary plus Bonus, 5-Day, Permanent Role) 17~22K/Month KIO-J078126", "description": "Responsibilities:\n\nSupport the Client Service Team in carrying out daily operational and administrative duties in a smooth and effective manner.\nClerical support in the CRM systems\u00a0\nAssist to prepare quotations and performing daily billing duties\u00a0\nAd-hoc duties as and when required\n\nRequirements:\n\nDiploma holder on business administrative studies, or equivalent\nMinimum 1-2 years of working experience\u00a0\u00a0\nFluent in Chinese and English\nFresh graduate will also be considered\n\nInterested parties please send your full resume with current and expected salary by clicking \u201cAPPLY NOW\u201d for application.\u00a0Please note that only shortlisted candidates will be notified.\n\nWe are an equal opportunity employer and welcome applications from all qualified candidates.\u00a0 All personal data collected will be treated in strict confidence and used solely for recruitment purposes.\u00a0 Applicants not hearing from us within 1 month may consider their applications unsuccessful.\u00a0\u00a0 All personal data collected will be destroyed within 12 months.", "employment_types": ["Full Time", "Permanent"], "selling_points": ["Sales Administration Permanent Role", "Electronic Trading Co. in TST", "3 Years of above Experience, 17-22K"], "locations": ["Tsim Sha Tsui"], "categories": ["Sales, CS & Business Devpt", "Customer Service - Supervisor / Officer", "Sales Administration"], "post_time": "2022-01-18T00:53:32Z", "salary": {"currency": null, "max": null, "min": null, "period": "monthly", "term": null}, "salary_visible": false, "title_keywords": ["sales assistant"], "responsibilities": ["systems", "administrative duties", "clerical support", "ad-hoc duties"], "requirements": {"degrees": ["diploma holder", "fresh graduate"], "majors": ["business"], "languages": ["english", "chinese"], "language_level": ["fluent"], "hard_skills": [], "soft_skills": [], "languages_combined": [{"language": "english", "language_level": ["fluent"]}, {"language": "chinese", "language_level": ["fluent"]}]}, "experience_required": {"duration": ["minimum 1-2 years"], "field": []}}, {"job_id": "100003009052853", "location_code": "hk", "company": "The Hongkong Electric Co., Ltd.", "job_title": "Community Business Executive / Customer Business Support Executive (Ref: CS-CBD-CBE-JD)", "description": "Job Responsibilities\n\nManage, develop, and support a multi-national team of 15-20 associates across Southeast Asia markets\nBe the team's professional focal point, ensuring they meet their performance goals, monitoring their calls/emails/chats/social media interactions and performing QA, Hands-on, analyzing and conducting effective feedback conversations\nIdentify areas for each associate's personal growth and development and guide them through professional advancement\nWork closely with business team, understanding the business needs in your responsible region and driving operational enhancement within customer care department\nManage projects and tasks related to the customer care department and APAC operations\n\nJob Requirements\n\n2 - 3 years of customer service or call center experience\nSolid managerial experience in multi-national environment is highly preferred\nStrong customer service skill and mindset\nExcellent verbal and written communication skills in English\nSelf-learning ability\nResponsibility and ownership taking\nProblem-solving ability\nCreative thinking and innovation\nProficient in MS Office", "employment_types": ["Full Time", "Permanent"], "selling_points": ["To assist the Managers to implement the Care Fund", "Bachelor Degree in Business Administration", "A minimum of 3 years\u2019 relevant work experience"], "locations": ["North Point"], "categories": ["Sales, CS & Business Devpt", "Business Development", "Public / Civil", "Social Services - Community / Non-profit Organization", "Sales Administration"], "post_time": "2022-01-17T04:17:02Z", "salary": {"currency": null, "max": null, "min": null, "period": "monthly", "term": null}, "salary_visible": false, "title_keywords": ["business executive", "executive"], "responsibilities": ["social media", "operations", "monitoring", "develop", "manage projects"], "requirements": {"degrees": [], "majors": [], "languages": ["english"], "language_level": ["excellent"], "hard_skills": ["problem-solving", "ms office"], "soft_skills": ["communication skills", "learning ability", "problem-solving", "customer service", "creative"], "languages_combined": [{"language": "english", "language_level": ["excellent"]}]}, "experience_required": {"duration": ["2 - 3 years"], "field": ["managerial", "customer service", "call center"]}}, {"job_id": "100003009056470", "location_code": "hk", "company": "Shopkyo Limited", "job_title": "Sales Specialist (2 vacancies)", "description": "Pre/view Design Limited\n\nPre/view Design Limited (http://previewdesign.hk/) is an interior design firm that we strive to achieve customer\u2019s needs and perfection. We plan, manage and concept holistically, by taking creative from concept to completion\n\nProject Assistant/ Executive\n\nWe are looking for competent candidates to join our team:\n\nResponsibilities:\n\n-\u00a0\u00a0\u00a0\u00a0\u00a0\u00a0\u00a0 Responsible for account management including but not limited to proposal write-up, schedule planning, project follow up & administrative work\n\n-\u00a0\u00a0\u00a0\u00a0\u00a0\u00a0\u00a0 Ensure that all projects are delivered on time, within scope and within budget\n\n-\u00a0\u00a0\u00a0\u00a0\u00a0\u00a0\u00a0 Keep good relationship with clients, internal departments & external parties\n\n-\u00a0\u00a0\u00a0\u00a0\u00a0\u00a0\u00a0 May travel to China or overseas from time to time for site inspections and on-site management to ensure full coordination of logistics and on-site teams\n\n-\u00a0\u00a0\u00a0\u00a0\u00a0\u00a0\u00a0 Work well under pressure\n\n-\u00a0\u00a0\u00a0\u00a0\u00a0\u00a0\u00a0 5 working days per week\n\n\u00a0Requirements\n\n-\u00a0\u00a0\u00a0\u00a0\u00a0\u00a0\u00a0\u00a0\u00a0\u00a0\u00a0 Working experience as an account executive or project administrator is an advantage\n\n-\u00a0\u00a0\u00a0\u00a0\u00a0\u00a0\u00a0\u00a0\u00a0\u00a0\u00a0 Hands-on, fast-paced, strong in project management\n\n-\u00a0\u00a0\u00a0\u00a0\u00a0\u00a0\u00a0\u00a0\u00a0\u00a0\u00a0 Excellent written and verbal communication skills\n\n-\u00a0\u00a0\u00a0\u00a0\u00a0\u00a0\u00a0\u00a0\u00a0\u00a0\u00a0 Organizational skills including attention to detail and multi-tasking skills\n\n-\u00a0\u00a0\u00a0\u00a0\u00a0\u00a0\u00a0\u00a0\u00a0\u00a0\u00a0 Proficient with MS Office", "employment_types": ["Full Time"], "selling_points": ["Market leading all-in-one smart logistic solution", "Start-up and energetic environment", "Great learning opportunity"], "locations": ["Tseung Kwan O"], "categories": ["Sales, CS & Business Devpt", "Sales - Sales Management", "Direct Sales", "Sales Administration"], "post_time": "2022-01-18T04:28:42Z", "salary": {"currency": null, "max": null, "min": null, "period": "monthly", "term": null}, "salary_visible": false, "title_keywords": ["sales specialist"], "responsibilities": ["project follow up", "management", "administrative work", "budget", "external parties", "site management", "teams", "good relationship", "logistics", "schedule", "coordination", "site inspections", "planning"], "requirements": {"degrees": [], "majors": [], "languages": [], "language_level": [], "hard_skills": ["project management", "ms office"], "soft_skills": ["communication skills", "organizational skills", "project management", "hands-on", "attention to detail", "multi-tasking skills"], "languages_combined": []}, "experience_required": {"duration": [], "field": []}}, {"job_id": "100003009052135", "location_code": "hk", "company": "Champion Capital Industries Limited", "job_title": "Assistant Sales Manager", "description": "\nWe are a consumer electronics trading company which located at Kwun Tong area and we are now seeking for the following position to cope our company expansion.\n\nSALES COORDINATOR / SALES EXECUTIVE\n\nResponsibilities:\n\u2022 Responsible for sales order processing and shipment follow up\n\u2022 Orders follow-up and preparation of documentation (issuing PI, PO, export documents)\n\u2022 Handle daily correspondences with customers and factories\n\u2022 Support on all kind of sales meeting and sales activities\n\u2022 Assist other duties and ad hoc projects as assigned\n\nRequirements:\n\u2022 Form 5 or above\n\u2022 Min. 3 years solid experience in electronic field is a MUST\n\u2022 Responsible, self-motivated and able to work independently\n\u2022 Fluent in spoken and written English, Cantonese and Mandarin\n\u2022 Immediately available\n\nInterested candidates, kindly send your detailed resume including Expected Salary.\n\n(All personal data will be collected for recruitment purposes only.)\u00a0", "employment_types": ["Full Time", "Permanent"], "selling_points": [], "locations": ["Kwun Tong"], "categories": ["Marketing / Public Relations", "Marketing - Brand / Product Management", "Sales, CS & Business Devpt", "Others", "Sales Administration"], "post_time": "2022-01-17T02:13:23Z", "salary": {"currency": null, "max": null, "min": null, "period": "monthly", "term": null}, "salary_visible": false, "title_keywords": ["assistant sales manager"], "responsibilities": ["sales activities", "documentation", "other duties", "ad hoc projects", "sales order processing"], "requirements": {"degrees": ["form 5 or above"], "majors": [], "languages": ["cantonese", "english", "mandarin"], "language_level": ["fluent"], "hard_skills": [], "soft_skills": ["self-motivated", "work independently", "responsible"], "languages_combined": [{"language": "cantonese", "language_level": ["fluent"]}, {"language": "english", "language_level": ["fluent"]}, {"language": "mandarin", "language_level": ["fluent"]}]}, "experience_required": {"duration": ["3 years"], "field": []}}, {"job_id": "100003009048638", "location_code": "hk", "company": "Karin Technology Holdings Ltd.", "job_title": "Sales Administrator", "description": "Well established Trading co.\nGood Work Life Balance\nFriendly and stable Staff and Co.\n\nResponsibilities\n\nHandle incoming and dispatches orders\nPrepare delivery documents\nUpdate record in the system\n\nRequirement\n\n3 years or above of relevant experience\nCantonese, English and Mandarin\nStrong sense of responsibility and good communication skills\n\nPackage\n\nPermanent role\n5-day work\nDouble Pay plus Bonus\nDental plus Medical Allowance\n\nFeel free to explore with Ms. So at 35529113 or 98651077", "employment_types": ["Full Time", "Permanent"], "selling_points": ["Working experience in sales administration duties", "Good command in both English and Chinese writing", "Good communication and interpersonal skills"], "locations": ["Kwun Tong"], "categories": ["Sales, CS & Business Devpt", "Customer Service - Supervisor / Officer", "Tele-sales (Telemarketing)", "Sales Administration"], "post_time": "2022-01-15T03:50:02Z", "salary": {"currency": null, "max": null, "min": null, "period": "monthly", "term": null}, "salary_visible": false, "title_keywords": ["sales administrator"], "responsibilities": [], "requirements": {"degrees": [], "majors": [], "languages": ["cantonese", "english", "mandarin"], "language_level": [], "hard_skills": ["plus"], "soft_skills": ["communication skills", "sense of responsibility"], "languages_combined": [{"language": "cantonese", "language_level": []}, {"language": "english", "language_level": []}, {"language": "mandarin", "language_level": []}]}, "experience_required": {"duration": ["3 years"], "field": ["relevant experience"]}}, {"job_id": "100003009053228", "location_code": "hk", "company": "\u50a2\u5c45\u7ad9\u6709\u9650\u516c\u53f8", "job_title": "\u517c\u8077\u9580\u5e02\u6587\u54e1\uff0f\u92b7\u552e\u54e1", "description": "Key performance areas: (Not Totally Inclusive)\n\nProvide adequate level of parts stock in our warehouse\nPotential parts sales forecast\nMake parts business plan for Key Account customers\nAchieve parts sales target (both on HQ and local level)\nActive participating on creation of spare parts promotions\nEstablishing and keeping positive and business orientated customer relationship\nParts technical support\nManaging customer discounts\nMarket information collection\nDelivery tracking\nParts business reporting to Head of After Sales\nHandle order processing, inventory control and coordinate all transportation including ocean and air freight forwarding\nPrepare quotation, handle purchase orders and shipping documents\nManage the claims process with manufacturer\nPrepare monthly KPI report for key account\n\nCore behavioural competencies:\u00a0\n\nMust possess analytical skills to identify and problem-solving skills\nMust have high level communication, interpersonal relations and negotiation skills\nMust possess solution orientated thinking and be customer orientated\nMust be able to create confidence and to manage a cooperative partnership\nMust be customer focused with a result driven approach\nMust be pro-active, highly motivated in achieving set objectives\nMust be able to work independently though being a team player\u00a0\nMust be assertive\n\nMinimum qualification and experience / skills required\n\nHigher Diploma or above, major in Supply Chain Management/Logistics, Business or equivalent\nFresh graduates with passion and willing to learn are welcomed\nGood knowledge of PC and Excel is essential. Experience in SAP is preferred.\nGood command of both spoken and written English and Chinese\nSelf-motivated, well organized, able to work independently and strong compliance with ability to meet deadlines\nCandidate with more experience will be consider as Officer\nValid HK driving licence (class 1, preferably 2)\nImmediately available is preferred", "employment_types": ["Part Time"], "selling_points": ["\u6642\u85aa$70", "Microsoft Office \u8edf\u4ef6", "\u96fb\u8166\u7cfb\u7d71\u64cd\u4f5c"], "locations": ["Lai Chi Kok"], "categories": ["Sales, CS & Business Devpt", "Sales Administration"], "post_time": "2022-01-17T06:29:36Z", "salary": {"currency": null, "max": null, "min": null, "period": "hourly", "term": null}, "salary_visible": false, "title_keywords": [], "responsibilities": ["shipping documents", "market information", "quotation", "communication", "purchase", "sales target", "compliance", "logistics", "forecast", "business plan", "report", "reporting", "management", "air freight", "inventory control", "tracking", "technical support", "coordinate", "order processing"], "requirements": {"degrees": ["higher diploma or above"], "majors": ["business"], "languages": ["english", "chinese"], "language_level": ["good command"], "hard_skills": ["excel", "sap", "analytical skills", "pc", "make", "order processing", "problem-solving skills"], "soft_skills": ["focused", "communication", "team player", "confidence", "cooperative", "meet deadlines", "interpersonal", "work independently", "assertive", "willing to learn", "analytical skills", "negotiation skills", "pro-active", "problem-solving skills", "active", "driven", "positive", "self-motivated", "well organized", "motivated"], "languages_combined": [{"language": "english", "language_level": ["good command"]}, {"language": "chinese", "language_level": ["good command"]}]}, "experience_required": {"duration": [], "field": []}}, {"job_id": "100003009055845", "location_code": "hk", "company": "Walters People (HK)", "job_title": "Key Account Executive (Garment; Up to 25k)", "description": "Responsibilities:\n\nReporting to the Community Business & Engagement Manager or Customer Business Support Manager, the appointees will mainly perform the following responsibilities:\n\n\nTo assist the Managers to implement the Smart Power Care Fund and Smart Power Services by establishing relationship with the NGOs or relevant stakeholders as well as organising engagement and publicity activities\nTo handle the administration work in relation to funding applications, from vetting to issuing the subsidy\nTo carry out tender enquiries for the supply of electrical appliances under the funding scheme\nTo handle Smart Power Services hotline and maintain a database for reporting and auditing purposes\n\nRequirements:\n\n\n\nBachelor Degree in Business Administration, Social Work or related disciplines\nA minimum of 3 years\u2019 relevant work experience, preferably in customer services, stakeholder engagement, community communication or community campaign administration\nGood PC skill and knowledge of MS Office including Powerpoint, Excel and Word. Knowledge of MS SharePoint or data analytics solution an advantage\nGood command of English and Chinese (including Mandarin) languages, both spoken and written\n\nWorking Location: North Point\n\nApplication:\n\nIf you are interested in this position, please send your resume\u00a0(in PDF format)\u00a0with details of qualification, experience, present and expected salary, and contact number to the\u00a0Human Resources Division, The Hongkong Electric Co., Ltd. on or before\u00a031 January 2022\u00a0and quote the reference number in your application. Please also visit our website to know more about our Company http://www.hkelectric.com.\n\nApplicants not invited for interview within\u00a0one month from the closing date may consider their applications unsuccessful. All unsuccessful applications will be kept for\u00a0six months after the date of this advertisement.\n\nWe are an equal opportunity employer.\u00a0 Personal data provided by job applicants will be treated in strictest confidence and used only for recruitment-related purposes in accordance with the laws and ordinance of the HKSAR.", "employment_types": ["Full Time", "Permanent"], "selling_points": ["Up to 25K + Double Pay; Stable", "non sales target; warm client focus", "Welcome Sales Engineer/ Sales Co."], "locations": ["Not Specified"], "categories": ["Sales, CS & Business Devpt", "Account Servicing", "Channel / Distribution", "Sales Administration"], "post_time": "2022-01-18T03:00:18Z", "salary": {"currency": "HKD", "max": 24999, "min": 20000, "period": "monthly", "term": null}, "salary_visible": true, "title_keywords": ["key account executive"], "responsibilities": ["reporting", "maintain", "database", "tender", "auditing", "administration"], "requirements": {"degrees": ["degree", "bachelor"], "majors": ["social work", "related disciplines", "business administration"], "languages": ["english", "chinese", "mandarin"], "language_level": ["good command"], "hard_skills": ["excel", "data analytics", "word", "powerpoint", "pc skill", "ms office"], "soft_skills": ["communication", "interested in", "confidence"], "languages_combined": [{"language": "english", "language_level": ["good command"]}, {"language": "chinese", "language_level": ["good command"]}, {"language": "mandarin", "language_level": ["good command"]}]}, "experience_required": {"duration": ["minimum of 3 years"], "field": ["administration", "human resources", "customer services"]}}, {"job_id": "100003009023299", "location_code": "hk", "company": "ScanTech (HK) Limited", "job_title": "Sales Coordinator Assistant", "description": "About Spaceship\n\nmarket leading smart logistic solution digital platform in Hong Kong since launch in 2019\nusers can instantly search and book global door-to-door shipment online within seconds\nwe aim to create a new era of seamless and effortless global shipment experience through technological advancements\nwe are actively expanding to Taiwan and other SEA countries\n\nResponsibilities:\u00a0\n\nAchieve sales and business targets through promoting Spaceship products and services to existing and potential clients\nEstablish, develop and maintain strong relationships with customers based on business needs\nCoordinate with business partners to provide to ensure all business and product needs are met\nHandle pricing request and guide the client on their on-boarding journey\nMaintain customer business data and update business activities in CRM system\nCoordinate with in-house logistics team and vendors to manage on-time delivery\nChannel feedback from customers for future value proposition enhancement\n\nRequirements:\n\nBachelor\u2019s degree\nMinimum\u00a0one\u00a0year sales/customer service experience in service industry with experience in customer acquisition\nProven sales and track record\nStrong selling, presentation, analytical and problem solving skills\nAbility to meet goals, stay organised and maintain a positive attitude Excellent attention to details\nPrevious experiences working in logistics, e-commerce and digital industry is an advantage\nGood command of both spoken and written English & Chinese (Cantonese and Mandarin)\nA team player, self-motivated and can work under pressure and meet tight deadlines;\nImmediate availability is an advantage\n\nOur offer:\n\nWe will give you the best support we possibly could for you to produce your best work. This includes providing you with:\nEducation reimbursement/subsidy\nCoaching/mentorship from industry veterans (ex. PayPal, Lalamove, Casetify, deloitte and more...)\nAlso, see the perks we provide below\n\nAdditional Perks:\n\nWork From Home Policy\nHealth Care\nFree Drinks, Snacks\nGym membership at Science Park\n\nMore about Spaceship\nWebsite:\u00a0https://www.spaceshipapp.com/zh-hk/\u00a0\nFacebook:\u00a0https://www.facebook.com/spaceship.hongkong\u00a0\nLinkedIn:\u00a0https://www.linkedin.com/company/spaceshiphk", "employment_types": ["Full Time"], "selling_points": ["Minimum 1 year relevant experience", "Sales Coordinator Assistant", "Discretionary Bonus"], "locations": ["Lai Chi Kok"], "categories": ["Sales, CS & Business Devpt", "Sales Administration"], "post_time": "2022-01-13T18:54:41Z", "salary": {"currency": null, "max": null, "min": null, "period": "monthly", "term": null}, "salary_visible": false, "title_keywords": ["sales coordinator", "assistant"], "responsibilities": ["data", "coordinate with", "develop", "maintain", "logistics", "business activities"], "requirements": {"degrees": ["degree", "bachelor"], "majors": [], "languages": ["cantonese", "english", "chinese", "mandarin"], "language_level": ["good command"], "hard_skills": ["problem solving skills", "e-commerce"], "soft_skills": ["self-motivated", "meet tight deadlines", "positive attitude", "analytical and problem solving skills", "customer service", "attention to details", "organised", "team player", "presentation", "work under pressure"], "languages_combined": [{"language": "cantonese", "language_level": ["good command"]}, {"language": "english", "language_level": ["good command"]}, {"language": "chinese", "language_level": ["good command"]}, {"language": "mandarin", "language_level": ["good command"]}]}, "experience_required": {"duration": ["minimum one year"], "field": ["e-commerce", "service industry", "customer service", "digital industry", "logistics"]}}, {"job_id": "100003009048135", "location_code": "hk", "company": "Saraya (Hong Kong Sales) Co., Limited", "job_title": "Senior Sales Coordinator (5 days, Japanese Company)", "description": "A public listed manufacturing company invites applicants to fill the following vacancy:\n\n- Diploma or Degree holder in Sales and Marketing or related discipline\n- Min 3-5 years solid experiences in optical industry is required\n- Independently follow up orders and correspondence\n- Good communication skill to work with designers and customers\n- Strong problem solving skills and result oriented\n- Good interpersonal skill, self-motivated and well-organized\n- Creative, proactive and good team-player\n- Good command in written & spoken English, Cantonese & Mandarin\n- Immediately available preferred\n\nWe offer attractive fringe benefits including 5 working days, bank holidays, bonus & medical insurance to the right candidates. Interested parties please send email to Human Resources Manager for further information.", "employment_types": ["Permanent"], "selling_points": [], "locations": ["North Point"], "categories": ["Sales, CS & Business Devpt", "Sales - Sales Management", "Others", "Sales Administration"], "post_time": "2022-01-14T06:15:01Z", "salary": {"currency": null, "max": null, "min": null, "period": "monthly", "term": null}, "salary_visible": false, "title_keywords": ["coordinator", "senior sales"], "responsibilities": ["follow up orders", "communication"], "requirements": {"degrees": ["diploma", "degree holder"], "majors": ["marketing"], "languages": ["cantonese", "english", "mandarin"], "language_level": ["good command"], "hard_skills": ["problem solving skills"], "soft_skills": ["self-motivated", "independently", "proactive", "team-player", "communication skill", "well-organized", "interpersonal skill", "result oriented", "problem solving skills", "creative"], "languages_combined": [{"language": "cantonese", "language_level": ["good command"]}, {"language": "english", "language_level": ["good command"]}, {"language": "mandarin", "language_level": ["good command"]}]}, "experience_required": {"duration": ["min 3-5 years"], "field": []}}, {"job_id": "100003009051734", "location_code": "hk", "company": "The University of Manchester Worldwide Limited", "job_title": "Recruitment and Marketing Assistant", "description": "In over 50 years, we have grown rapidly as one of the top-tier Hong Kong CPA firms with total 6 offices in China and Europe are actively are expanding our foothold across the globe.\u00a0 Please visit us at www.fungyucpa.com for more details. To support our fast-growing international business, we are seeking professionals with following expertise to be part of us.\n\nOpportunities:\n\nWe offer excellent career advancement opportunities to staff who join our firm\nYou will gain valuable experience in providing professional customer services to our clients across different geographies and sectors\n\u00a0We will be your biggest supporter in pursuing your professional qualification\n\nResponsibilities:\n\n\n\nHandle incoming enquiries follow up\nHandling corporate compliance work\nAnswering enquiries from client via email or phone\nProvide general administration clerical support\nPerform ad-hoc task assigned by supervisor\n\n\n\nRequirements:\n\n\n\nDiploma or University degree holder preferably in corporate governance/accounting disciplines\nGood interpersonal and communication skills\nAble to work independently and under pressure in a fast-paced environment with emphasis on accuracy and timeliness\nGood PC knowledge of MS Office and Chinese typing\nGood command of Cantonese, English and Mandarin\nImmediately available is preferred\n\n5 days work, 14\u00a0days annual leave with annual increment, birthday leave and medical allowance.\u00a0We offer a highly competitive salary and benefit package commensurate with qualifications and experience.\u00a0 Please submit your application by clicking \u201cApply Now\u201d button and visit our company website at http://www.harriscorps.com/\u00a0for more information.\n\nPersonal data collected will only be used for the purpose of recruitment.", "employment_types": ["Full Time", "Contract"], "selling_points": ["Degree, 2 yrs work exp, good English, IT skills", "Proactive, mature, outgoing, organised, & detailed", "Int'l exposure, training, immediate, salary expect"], "locations": ["Causeway Bay"], "categories": ["Education", "Others", "Marketing / Public Relations", "Marketing - General / Support", "Sales, CS & Business Devpt", "Sales Administration"], "post_time": "2022-01-16T21:51:17Z", "salary": {"currency": null, "max": null, "min": null, "period": "monthly", "term": null}, "salary_visible": false, "title_keywords": ["marketing assistant"], "responsibilities": [], "requirements": {"degrees": [], "majors": [], "languages": [], "language_level": [], "hard_skills": [], "soft_skills": [], "languages_combined": []}, "experience_required": {"duration": [], "field": []}}, {"job_id": "100003009043722", "location_code": "hk", "company": "Bansard International Hong Kong Limited", "job_title": "Sales Administrator", "description": "Requirements:\n\nUniversity graduate in business discipline or equivalent;\nAt least 3-5 years related working experience in sales administration duties,\u00a0\u00a0IT & Retail industry\u00a0is preferable;\nGood communication and interpersonal skills;\nGood command in both English and Chinese writing.\n\nWe offer a competitive remuneration package to the right candidate. Interested parties please send your full resume with\u00a0present and expected salary\u00a0by email to recruitment\u00aekarin.com.hk\u00a0or\u00a0clicking 'Apply Now'.\n\n(We are an Equal Opportunity Employer and personal data collected would be used for recruitment purpose only.)", "employment_types": ["Full Time", "Permanent"], "selling_points": ["Diploma or above in Business Admin, Commercial", "2+ years' work experience", "Good written and spoken English  & Chinese"], "locations": ["Kowloon Bay"], "categories": ["Sales, CS & Business Devpt", "Sales Administration"], "post_time": "2022-01-13T01:40:17Z", "salary": {"currency": null, "max": null, "min": null, "period": "monthly", "term": null}, "salary_visible": false, "title_keywords": ["sales administrator"], "responsibilities": ["communication", "sales administration"], "requirements": {"degrees": ["university graduate"], "majors": ["business"], "languages": ["english", "chinese"], "language_level": ["good command"], "hard_skills": [], "soft_skills": ["communication and interpersonal skills"], "languages_combined": [{"language": "english", "language_level": ["good command"]}, {"language": "chinese", "language_level": ["good command"]}]}, "experience_required": {"duration": ["at least 3-5 years"], "field": ["related", "sales administration", "it", "retail industry"]}}, {"job_id": "100003009052304", "location_code": "hk", "company": "Hong Kong Education City Limited", "job_title": "Assistant Business Operations Officer", "description": "My client is a US listed garment manufacturing and trading company.\n\nFor greater expansion in Hong Kong, they are currently looking for a new Supply China/ Logistic/ Sales Engineer talent to join their Key Account team for handling existing clients.\n\nMain responsibilities:\n\nManage the completion of order entry, allocation management, and order to delivery monitoring. Responsible for Order to Cash process\nUnderstand and Apply Pricing policy and procedures. Ensure accurate and timely invoicing\nProvide forecast input for monthly demand planning processes and validate allocation\nDelivering high quality customer service to both internal and external logistics team and supply customers\nAct as liaison between customer and internal stakeholders to successfully execute against customer supply chain.\n\nMain requirements:\n\nBachelor's Degree\n2-5 years working experience, perfectly in Logistics, Supply Chain, Manufacturing field\nGood command of Chinese and English\nProficiency in excel\nConcept on logistic procedure, inventory control, forecasting etc.\nImmediately available is highly preferred", "employment_types": ["Full Time"], "selling_points": ["Support business operations and admin functions", "Medical, Life Insurance, MPFVC, Incentive Payment", "5-day workweek, 14-21 days AL, education subsidies"], "locations": ["Shatin Area"], "categories": ["Sales, CS & Business Devpt", "Call Centre", "Account Servicing", "Sales Administration"], "post_time": "2022-01-17T02:42:20Z", "salary": {"currency": null, "max": null, "min": null, "period": "monthly", "term": null}, "salary_visible": false, "title_keywords": ["operations officer", "assistant"], "responsibilities": ["management", "demand planning", "monitoring", "procedures", "quality", "invoicing", "customer service", "logistics", "forecast"], "requirements": {"degrees": ["degree", "bachelor"], "majors": [], "languages": ["english", "chinese"], "language_level": ["good command"], "hard_skills": ["excel"], "soft_skills": [], "languages_combined": [{"language": "english", "language_level": ["good command"]}, {"language": "chinese", "language_level": ["good command"]}]}, "experience_required": {"duration": ["2-5 years"], "field": ["supply chain", "manufacturing", "logistics"]}}, {"job_id": "100003009052738", "location_code": "hk", "company": "ZS Technology HK Co., Limited", "job_title": "\u92b7\u552e\u6587\u54e1 (Sales Admin)", "description": "Job Responsibilities\n\n\u00a0\u00a0\u00a0\u00a0\u00a0\u00a0\u00a0Issue sales invoice, delivery notes and follow up sales order\n\u00a0\u00a0\u00a0\u00a0\u00a0\u00a0\u00a0Update and maintain system information and database\u00a0 \u00a0\n\u00a0\u00a0\u00a0\u00a0\u00a0\u00a0\u00a0Liaise with warehouse team for daily inbound / outbound delivery\u00a0\n\u00a0\u00a0\u00a0\u00a0\u00a0\u00a0\u00a0Provide clerical and administrative support\u00a0 \u00a0\n\u00a0\u00a0\u00a0\u00a0\u00a0\u00a0\u00a0Handling and follow up inquiries\u00a0\n\u00a0\u00a0\u00a0\u00a0\u00a0\u00a0\u00a0Perform as hoc duties as assigned\n\nJob Requirements:\n\n\n\n\u00a0\u00a0\u00a0\u00a0\u00a0\u00a0\u00a0Degree or diploma holder with a relevant business discipline\n\u00a0\u00a0\u00a0\u00a0\u00a0\u00a0\u00a0Minimum 1 year relevant experience\n\u00a0\u00a0\u00a0\u00a0\u00a0\u00a0\u00a0Independent, detail-minded, organized, responsible, self-motivated and good team work;\n\u00a0\u00a0\u00a0\u00a0\u00a0\u00a0\u00a0Organized, strong sense of responsibility and willing to lean\n\u00a0\u00a0\u00a0\u00a0\u00a0\u00a0\u00a0Proficiency in MS Word, MS Excel and Chinese Typing\n\u00a0\u00a0\u00a0\u00a0\u00a0\u00a0\u00a0Good command of spoken and written English & Chinese", "employment_types": ["Full Time", "Permanent"], "selling_points": ["\u4e94\u5929\u5de5\u4f5c", "\u91ab\u7642\u4fdd\u96aa", "\u5e74\u5047"], "locations": ["Hung Hom"], "categories": ["Sales, CS & Business Devpt", "Wholesale", "Sales Administration"], "post_time": "2022-01-17T04:05:06Z", "salary": {"currency": null, "max": null, "min": null, "period": "monthly", "term": null}, "salary_visible": false, "title_keywords": ["admin", "sales"], "responsibilities": ["follow up sales order", "invoice", "administrative support", "maintain", "database", "liaise with"], "requirements": {"degrees": ["diploma holder", "degree"], "majors": ["business"], "languages": ["english", "chinese"], "language_level": ["proficiency", "good command"], "hard_skills": ["lean", "ms excel", "typing", "ms word"], "soft_skills": ["detail-minded", "organized", "self-motivated", "good team work", "independent", "responsible", "sense of responsibility"], "languages_combined": [{"language": "english", "language_level": ["good command"]}, {"language": "chinese", "language_level": ["proficiency", "good command"]}]}, "experience_required": {"duration": ["minimum 1 year"], "field": ["relevant experience"]}}, {"job_id": "100003009055795", "location_code": "hk", "company": "Page Personnel", "job_title": "Sales Support Specialist - Health Care Solution", "description": "We are looking for a number of enthusiastic people to be part of our admissions teams supporting our applicants and programme teams, working collaboratively in accordance with good customer care principles. Alongside processing applications and acting as a first point of contact for queries, you will also support admissions events (either on-campus or virtual), interviews, and confirmation.\n\nSuccessful candidates will have experience of working with administrative processes in a customer facing office environment. The roles require applicants who thrive in a busy team environment who enjoy interacting and supporting a wide range of people and who are flexible and responsive to customer needs. Strong organisational and accuracy skills are essential alongside the ability to adapt to changing systems and platforms and work and communicate successfully across, emails, face to face and virtual channels.\n\nJob responsibilities\n\nTo monitor, implement and converting all enquiries to meet the KPIs\nTo build relations with enquirers, follow up and conversion\nTo offer\u00a0 responsive and professional services to all enquirers\nTo provide responsive consultations with prospective students\n\nTo manage databases of enquirers efficiently and effectively\n\nTo proactively support the promotional campaigns\nTo plan, monitor and implement all recruitment related activities\n\nTo prepare, analyse, and recommend necessary recruitment reporting\n\nTo support Marketing team to prepare promotional materials\n20 days annual leave, 5 days work, fringe benefits\u00a0 and working with global teams.", "employment_types": ["Full Time", "Permanent"], "selling_points": ["3+ years in sales administrative experience", "MNC, Global Exposure", "Immediately available"], "locations": ["Not Specified"], "categories": ["Information Technology (IT)", "Support", "Medical Services", "Medical Services Technician", "Sales, CS & Business Devpt", "Sales Administration"], "post_time": "2022-01-18T02:57:22Z", "salary": {"currency": "HKD", "max": 29999, "min": 25000, "period": "monthly", "term": null}, "salary_visible": true, "title_keywords": ["specialist", "sales"], "responsibilities": ["reporting", "systems", "monitor", "teams", "promotional materials", "recruitment", "contact", "databases", "kpis", "plan", "administrative processes", "analyse"], "requirements": {"degrees": [], "majors": [], "languages": [], "language_level": [], "hard_skills": ["processing", "databases"], "soft_skills": ["flexible", "responsive", "enthusiastic"], "languages_combined": []}, "experience_required": {"duration": [], "field": ["administrative"]}}, {"job_id": "100003009055559", "location_code": "hk", "company": "Chandler Macleod Group (HK) Limited", "job_title": "Merchandising Assistant (Luxury, 18K)", "description": "JOB RESPONSIBILITIES\n\nA bridge between salesman / customer and operation department\u00a0\n\nProvide administrative support to Sales Team\n\nPrepare reporting & documentations such as analysis reports / proposals / contracts, etc.\n\nPrepare and update presentation PowerPoints\n\nCommunicate and coordinate with internal and external parties\n\nAssist in sales activities\u00a0\n\nOther task assigned by management\n\nREQUIRMENTS\n\nDiploma or above in Business Admin, Commercial or related disciplines\n\nMinimum 2 years\u2019 work experience\n\nProficiency in MS Office Applications\n\nGood communication and interpersonal skill\n\nTeam player, proactive, can-do and result oriented\n\nGood command of both written and spoken English and Chinese (Cantonese & Mandarin)\n\nCandidate with lesser working experience but with sound academic background will be also considered", "employment_types": ["Full Time", "Permanent"], "selling_points": ["Market Leader in Retail Sector", "Genuine Development Opportunity", "A Growing Business"], "locations": ["Quarry Bay"], "categories": ["Sales, CS & Business Devpt", "Retail Sales", "Wholesale", "Sales Administration"], "post_time": "2022-01-18T02:43:16Z", "salary": {"currency": null, "max": null, "min": null, "period": "monthly", "term": null}, "salary_visible": false, "title_keywords": ["merchandising assistant"], "responsibilities": ["reporting", "sales activities", "management", "analysis reports", "contracts", "internal and external parties", "coordinate with", "sales team", "provide administrative support"], "requirements": {"degrees": ["diploma or above"], "majors": ["related disciplines", "business"], "languages": ["cantonese", "english", "chinese", "mandarin"], "language_level": ["good command"], "hard_skills": ["ms office"], "soft_skills": ["interpersonal skill", "communication", "result oriented", "can-do", "team player", "proactive"], "languages_combined": [{"language": "cantonese", "language_level": ["good command"]}, {"language": "english", "language_level": ["good command"]}, {"language": "chinese", "language_level": ["good command"]}, {"language": "mandarin", "language_level": ["good command"]}]}, "experience_required": {"duration": ["minimum 2 years"], "field": []}}, {"job_id": "100003009050296", "location_code": "hk", "company": "Plaza Premium Group", "job_title": "Sales Administration Executive", "description": "Responsibilities:\n\nAssist the Manager to develop and execute effective business operations strategies to achieve company's goals and KPIs.\nStimulate online and offline sales opportunities and follow them up through inbound and outbound leads.\nSupport business operations and administration functions to complete the sales cycle of all EdCity services.\nHandle and resolve users' inquiries.\nImprove customer intimacy, broaden and strengthen the stakeholders (including schools, teachers and education bodies) network and deliver customer satisfaction.\nSupport and participate in EdCity events/marketing activities to promote our services to stakeholders.\nPerform administrative duties including report generation and other ad-hoc tasks as assigned.\n\nRequirements:\n\n\nDegree or above in any discipline, preferably in Business Administration, Marketing, or Education.\nSolid experience in account servicing, sales administration, business operations support and customer services is preferred. Exposure in education industry will be an advantage.\nExcellent interpersonal and communication skills with engaging presentation technique.\nProficient in MS Word, Advanced-Excel and PowerPoint and Chinese word processing.\nFluency in written and spoken Chinese and English; Proficient in spoken Mandarin will be an advantage.\nAttention to detail, strong analytical thinking and business acumen, self- motivated, result-oriented, and skillful at multi-tasking.\nMature with good telephone manner and be a good team player.\nAble to work independently, and meet tight deadlines.\nPassionate to drive customer service excellence and innovative learning and teaching.\nShift duty is required. Operating hours: 08:00 - 22:00, \u00a0Monday to Saturday, excluding public holidays.\n\nWe provide attractive remuneration and fringe benefits to the right candidate:\n\n5-day workweek\n14 Days Annual Leave + 7 days seniority annual leave\nPerformance Incentive\nMedical and Dental Insurance (Including dependents)\nAnnual Health Check-up Benefit\nLife Insurance\nEmployer MPF Voluntary Contribution (No cap)\nTraining Subsidies\n\nInterested parties looking for a promising career, please send your application letter and resume stating your\u00a0English and Chinese result in public examination(s), current and expected salary\u00a0by clicking \"Apply Now\"\u00a0on or before 30 January 2022.\n\nPersonal data provided will be used strictly for recruitment and other employment-related purposes.\u00a0 Details of the Personal Information Collection Statement - Recruitment of the Company can be found at\u00a0https://www.hkedcity.net/hq/recruit/statement\n\nApplicants please submit one application for each post.\u00a0 Applicants not invited for interview after 8 weeks from the closing date may consider their applications unsuccessful.\u00a0 The Company reserves the right not to fill the post(s).", "employment_types": ["Full Time", "Permanent"], "selling_points": ["Provide admin. support to sales team", "5 days work, bank holiday, medical benefits", "Attentive to details and good organization skill"], "locations": ["Airport Area"], "categories": ["Sales, CS & Business Devpt", "Sales Administration"], "post_time": "2022-01-14T10:04:10Z", "salary": {"currency": null, "max": null, "min": null, "period": "monthly", "term": null}, "salary_visible": false, "title_keywords": ["administration executive", "sales"], "responsibilities": ["operations", "ad-hoc tasks", "develop", "administrative duties", "kpis", "report", "administration"], "requirements": {"degrees": ["degree or above"], "majors": ["marketing", "business administration"], "languages": ["english", "chinese", "mandarin"], "language_level": ["fluency", "advantage", "proficient"], "hard_skills": ["excel", "chinese word processing", "ms word", "powerpoint", "acumen"], "soft_skills": ["result-oriented", "communication skills", "good team player", "work independently", "meet tight deadlines", "advanced", "passionate", "mature", "innovative", "multi-tasking", "motivated", "customer service", "learning", "attention to detail", "business acumen", "interpersonal", "telephone manner", "presentation"], "languages_combined": [{"language": "english", "language_level": ["fluency"]}, {"language": "chinese", "language_level": ["fluency"]}, {"language": "mandarin", "language_level": ["proficient", "advantage"]}]}, "experience_required": {"duration": [], "field": ["sales administration", "business", "account servicing", "customer services"]}}, {"job_id": "100003009050728", "location_code": "hk", "company": "Hutchison Telecommunications (Hong Kong) Limited", "job_title": "Business Operations Officer", "description": "-\u00a0 \u8ca0\u8cac\u8207\u6bcd\u516c\u53f8\u5ba2\u6236\u5c0d\u63a5\uff0c\u5b8c\u6210\u92b7\u552e\u8a02\u55ae\u3002\u5305\u62ec\u4f46\u4e0d\u50c5\u9650\u65bc\u7533\u8acb\u92b7\u552e\u5408\u540c\u8a55\u5be9\uff0c\u64ec\u5b9a\u92b7\u552e\u5408\u540c/invoice/\u55ae\u64da\n\n-\u00a0 \u8ca0\u8cac\u5efa\u7acb\u516c\u53f8\u5ba2\u6236\u6a94\u6848\u3001\u5354\u52a9\u8655\u7406\u5ba2\u6236\u6295\u8a34\u7b49\uff0c\u6709\u6548\u670d\u52d9\u5ba2\u6236\u3002\n\n- \u8ca0\u8cac\u92b7\u552e\u696d\u52d9\u53ca\u696d\u52d9\u6a94\u6848\u7ba1\u7406\uff0c\u5305\u62ec\u4e0d\u50c5\u9650\u65bc\u5408\u540c\u3001\u767c\u7968\u3001\u92b7\u552e\u5408\u540c\u53f0\u8cec\u7b49\u6a94\u8cc7\u6599\u7684\u7ba1\u7406\u3001\u6b78\u985e\u3001\u6574\u7406\u3001\u5efa\u6a94\u548c\u4fdd\u7ba1\u3002\n\n- \u5354\u52a9\u516c\u53f8\u92b7\u552e\u696d\u52d9\u4eba\u54e1\u7533\u8acb\u92b7\u552e\u5408\u540c\u8a55\u5be9\u55ae\u3001\u64ec\u5b9a\u92b7\u552e\u5408\u540c\u3001\u55ae\u64da\uff0c\u5b8c\u6210\u5ba2\u6236\u76f8\u95dc\u696d\u52d9\u55ae\u64da\u7684\u7c3d\u8a02\uff0c\u5354\u52a9\u92b7\u552e\u5b8c\u6210\u92b7\u552e\u53ca\u975e\u92b7\u552e\u767c\u8ca8\u3002\u5b89\u6392\u9000\u8ca8\u7b49\u65e5\u5e38\u92b7\u552e\u5de5\u4f5c\u3002\n\n-\u00a0 \u5354\u52a9\u516c\u53f8\u7c4c\u5099\u5c55\u89bd\u5e76\u53c3\u52a0\u570b\u5167\u5916\u5c55\u89bd", "employment_types": ["Full Time", "Permanent"], "selling_points": [], "locations": ["Tsing Yi"], "categories": ["Admin & HR", "Clerical / Admin Staff", "Sales, CS & Business Devpt", "Others", "Sales Administration"], "post_time": "2022-01-14T11:14:58Z", "salary": {"currency": null, "max": null, "min": null, "period": "monthly", "term": null}, "salary_visible": false, "title_keywords": ["operations officer"], "responsibilities": ["invoice"], "requirements": {"degrees": [], "majors": [], "languages": [], "language_level": [], "hard_skills": [], "soft_skills": [], "languages_combined": []}, "experience_required": {"duration": [], "field": []}}, {"job_id": "100003009052189", "location_code": "hk", "company": "Modern Dental Laboratory Company Limited", "job_title": "Dental Lab Admin Assistant", "description": "A leading health care solution company is now seeking for a Sales Support to join their winning team. The chosen candidate will be responsible for providing sales support service to the team.\n\nClient Details\n\nOur client is one of the leading healthcare solution companies based in Europe with nearly 10 years of experience. They are well-known for their excellent experience in clinical support. They are currently seeking for a talent to join their vibrant team now.\n\nDescription\n\nResponsible for order processing and sales support\nBackup for sales team\nPrepare and follow up sales orders\nProvide after-sales service\nCoordinate with suppliers on quotation\nAssist with ad-hoc projects\n\nProfile\n\nDiploma holder or above\n3+ years in sales administrative experience\nSales support experience in healthcare devices or IT solution is highly preferable\nAbility to handle multiple tasks at the same time\nCommand on Thai, Bahasa Indonesian/ Malay, Vietnamese or other SEA region languages is an advantage\nFluent in spoken and written English, Mandarin and Cantonese\n\nJob Offer\n\nMedical Allowance\nOn-the-job training\nCareer progression\nAttractive salary package\nPerformance bonus\n\nTo apply online please click the 'Apply' button below. For a confidential discussion about this role please contact Coco Ng on +852 3602 2446.", "employment_types": ["Full Time", "Permanent"], "selling_points": ["Receptionist, Customer Services", "Administrative & Operations", "5.5 day work"], "locations": ["Central"], "categories": ["Admin & HR", "Clerical / Admin Staff", "Receptionist", "Sales, CS & Business Devpt", "Sales Administration"], "post_time": "2022-01-17T02:24:31Z", "salary": {"currency": null, "max": null, "min": null, "period": "monthly", "term": null}, "salary_visible": false, "title_keywords": ["admin assistant"], "responsibilities": ["quotation", "coordinate with", "after-sales service", "sales team", "contact", "order processing", "clinical support", "ad-hoc projects"], "requirements": {"degrees": ["diploma holder"], "majors": [], "languages": ["cantonese", "english", "mandarin", "thai", "vietnamese", "indonesian", "malay"], "language_level": ["advantage", "fluent"], "hard_skills": ["sales support", "order processing"], "soft_skills": ["handle multiple tasks", "responsible"], "languages_combined": [{"language": "cantonese", "language_level": ["fluent"]}, {"language": "english", "language_level": ["fluent"]}, {"language": "mandarin", "language_level": ["fluent"]}, {"language": "thai", "language_level": ["advantage"]}, {"language": "vietnamese", "language_level": ["advantage"]}, {"language": "indonesian", "language_level": ["advantage"]}, {"language": "malay", "language_level": ["advantage"]}]}, "experience_required": {"duration": ["10 years", "3+ years"], "field": ["healthcare", "sales support", "administrative", "it", "clinical"]}}, {"job_id": "100003009050194", "location_code": "hk", "company": "Belle Worldwide (Talent Management) Limited", "job_title": "Officer - Retail Operations", "description": "Our client, a Japanese Logistics Company, is looking for a suitable candidate for\u00a0Assistant Sales Supervisor / Indoor Sales :\n\nJobs Duties\n\n\n\u30fbSupport Outdoor Sales and teammates for sales related issues, not limited to rate inquiries or prepare quotations\n\u30fbPrepare tailor-made shipments and invoices reports\n\u30fbShipment coordination and problem solving for the stakeholders\n\u30fbFollow up invoice billing, chasing outstanding payment, and credit control.\n\u30fbAd-hoc duty\n\n\nRequirement\n\n\n\u30fbDegree holder\n\u30fbAt least 2 - 3 years relevant freight forwarding experience\n\u30fbBusiness level in written and spoken English and Mandarin\n\u30fbProactive, good interpersonal and analytical skills\n\n<Preferable Skill / Experience>\n\u30fbJapanese speaking is advantage\n\n\nPackage\n\n5-days-work\nDouble pay\nDiscretionary bonus\nMedical Insurance\nSick leave\nAnnual leave\nOT allowance\nInterested parties please send us your resume in MS Word/PDF format in English.\nAll information received will be kept in strict confidential and only for recruitment purpose.", "employment_types": ["Full Time", "Permanent"], "selling_points": ["Support frontline daily operation", "Handle customer service hotline", "Proactive and Strong in Excel"], "locations": ["Kwai Hing"], "categories": ["Admin & HR", "Clerical / Admin Staff", "Sales, CS & Business Devpt", "Customer Service - Manager", "Sales Administration"], "post_time": "2022-01-14T09:55:30Z", "salary": {"currency": null, "max": null, "min": null, "period": "monthly", "term": null}, "salary_visible": false, "title_keywords": ["officer", "operations"], "responsibilities": ["control", "invoices", "invoice", "payment", "reports", "coordination"], "requirements": {"degrees": [], "majors": [], "languages": ["english", "mandarin"], "language_level": [], "hard_skills": ["analytical skills"], "soft_skills": ["interpersonal", "analytical skills"], "languages_combined": [{"language": "english", "language_level": []}, {"language": "mandarin", "language_level": []}]}, "experience_required": {"duration": ["least 2 - 3 years"], "field": []}}, {"job_id": "100003009051531", "location_code": "hk", "company": "Everbest Logistics Co Ltd", "job_title": "Sales Executive (Building/Construction Materials)", "description": "Responsibilities\n\n\nUpdate daily / weekly / monthly sales report and analyze the market trend.\nFollow up with Asia Pacific markets stock request and arrange stock rebalancing.\nSupport the team in developing catalogues and selling tools.\nSupport the after sales services for Asia Pacific.\nProvide extensive day-to-day operational and administrative supports\nHandle other ad hoc, miscellaneous tasks and projects related to the business.\n\nRequirement\n\n\nTertiary education in Business Management, Fashion Merchandising, or related discipline.\n1 year working experience in buying & merchandising\nGood interpersonal skill, detail-oriented, willing to learn and able to work under pressure.\nGood command of spoken and written English, Cantonese and Mandarin.\nProficient in MS Office, Excel (pivot table, vlookup, etc.) and PowerPoint.\nImmediate availability preferred", "employment_types": ["Full Time", "Permanent"], "selling_points": [], "locations": ["Sheung Wan"], "categories": ["Sales, CS & Business Devpt", "Business Development", "Retail Sales", "Sales Administration"], "post_time": "2022-01-16T08:18:56Z", "salary": {"currency": null, "max": null, "min": null, "period": "monthly", "term": null}, "salary_visible": false, "title_keywords": ["sales executive"], "responsibilities": ["ad hoc", "monthly sales report", "support the team", "developing"], "requirements": {"degrees": [], "majors": [], "languages": ["cantonese", "english", "mandarin"], "language_level": ["good command"], "hard_skills": ["business management", "excel", "pivot table", "powerpoint", "vlookup", "ms office"], "soft_skills": ["detail-oriented", "work under pressure", "willing to learn", "interpersonal skill"], "languages_combined": [{"language": "cantonese", "language_level": ["good command"]}, {"language": "english", "language_level": ["good command"]}, {"language": "mandarin", "language_level": ["good command"]}]}, "experience_required": {"duration": ["1 year"], "field": ["merchandising"]}}, {"job_id": "100003009049085", "location_code": "hk", "company": "Jebsen Motors Limited", "job_title": "Sales Administrator (6 months contract) (Ref: Porsche - F041)", "description": "Job Scope\nThe incumbent will provide general administrative work and provide support to sales team daily operation, as well as to support managers to managing client accounts and maintain client records.\nJob Responsibilities\nPrepare and update admission instruction and coordinate with operations team to accommodate needs from clients.\nPrepare ad ho group quotation and reservation of PPL/PPF/Refreshh by Aerotel/M&G from incoming inquiry mailbox.\nPrepare weekly HKG and MFM outlets target achievement performance.\nUpdate new service menu items and pricing.\nAssist superiors to prepare sales proposal, agreements and relevant reports for management review.\nAssist superiors to provide client servicing like prepare agreement, assist superiors to resolve client-related issue and liaise system integration matter with client.\nAssist superiors to render system development support.\nHandle ad hoc projects assigned by superiors.\nJob Requirements\nHD or above in Business Administration, hospitality or related disciplines\u00a0\nStrong understanding of travel industry is a definite advantage\nCapable of working under pressure and prioritize work with excellent time management\nAttentive to details, efficient, well-planned with good business sense\nExperience in Salesforce or similar CRM is an advantage\nProficient in MS Office applications and Chinese word processing\nGood command of spoken and written skills in Chinese and English", "employment_types": ["Contract"], "selling_points": ["Jebsen Motors Limited", "Wan Chai", "Posted on 4-Nov-21"], "locations": ["Wan Chai"], "categories": ["Sales, CS & Business Devpt", "Sales Administration"], "post_time": "2022-01-14T08:05:41Z", "salary": {"currency": null, "max": null, "min": null, "period": "monthly", "term": null}, "salary_visible": false, "title_keywords": ["sales administrator"], "responsibilities": ["liaise", "relevant reports", "operations", "quotation", "prepare sales", "coordinate with", "ad hoc projects", "management review"], "requirements": {"degrees": [], "majors": [], "languages": ["english", "chinese"], "language_level": ["good command", "proficient"], "hard_skills": ["chinese word processing", "salesforce", "ms office"], "soft_skills": ["efficient", "under pressure", "capable", "attentive to details", "business sense", "prioritize", "time management"], "languages_combined": [{"language": "english", "language_level": ["good command"]}, {"language": "chinese", "language_level": ["good command", "proficient"]}]}, "experience_required": {"duration": [], "field": []}}, {"job_id": "100003009047057", "location_code": "hk", "company": "Automated Systems (HK) Ltd", "job_title": "Sales Administrator (Permanent, 5-days work)", "description": "Responsibilities:\n\n\nProvide the business supports to Sales Teams, including the sales order process, order submission, sales documentation handling, PR/PO preparation, customer billing arrangement\n\u00a0Liaison with internal departments and business partners to ensure effective sales logistics\nPrepare the regular sales management reports, presentation materials\nPrepare the operation manuals with prescribed procedure and workflows\nReview and ensure policies and procedures are in alignment with operation needs and in compliance\nTake initiative to assess workflow and process to improve business operations efficiency\nProvide the administrative supports to the Department, including oversee and maintain staffs records, coordinate the general IT related and system access right, organize the systematical filing system\nHandle ad hoc duties as required\u00a0\n\nRequirements:\n\n\nHigher Diploma or above\nMinimum 5 year\u2019s relevant experience in sales administration with telecom industry experience would be advantage\nExposure in telecom related industries is an advantage\nWell-organized, able to handle multi-tasks and prioritize works under tight schedule\nProficiency in MS office applications, especially in MS Excel (Pivot table & vlookup) and MS PowerPoint\nMore experience will be considered as Senior Business Support Officer\nApart from competitive remuneration package and exciting opportunity for career development within the Group, we provide attractive employee benefits such as free company shuttle, free company SIM card and preferential SIM plan offers, comprehensive medical & insurance schemes, as well as full range of other employee well-being provisions.\u00a0\n\nInterested parties, please apply with full resume, present and expected salary, by clicking \u201cAPPLY NOW\u201d. Please quote the reference number on the e-mail subject.\n\nWe are an equal opportunity employer and welcome applications from all qualified candidates. Personal data collected will be treated in the strictest confidence and handled confidentially by authorised personnel for recruitment-related purposes only within the CK Hutchison Group of companies. The personal data of unsuccessful applicants will be destroyed after the recruitment exercise pursuant to the requirements of the Personal Data (Privacy) Ordinance in Hong Kong.", "employment_types": ["Full Time", "Permanent"], "selling_points": ["Quotations Preparation", "Handle the collection for the overdue payment", "1 year of sales support/sales administration exp."], "locations": ["Shatin Area"], "categories": ["Sales, CS & Business Devpt", "Customer Service - Supervisor / Officer", "Others", "Sales Administration"], "post_time": "2022-01-14T02:12:11Z", "salary": {"currency": null, "max": null, "min": null, "period": "monthly", "term": null}, "salary_visible": false, "title_keywords": ["sales administrator"], "responsibilities": ["ad hoc duties", "policies", "operations", "review", "teams", "procedures", "compliance", "coordinate", "maintain", "logistics", "reports", "documentation", "sales management"], "requirements": {"degrees": ["higher diploma or above"], "majors": [], "languages": [], "language_level": [], "hard_skills": ["pivot table", "ms excel", "ms powerpoint", "vlookup", "ms office"], "soft_skills": ["comprehensive", "well-organized", "prioritize", "multi-tasks"], "languages_combined": []}, "experience_required": {"duration": ["minimum 5 year"], "field": ["sales administration", "relevant experience", "business support"]}}, {"job_id": "100003009048271", "location_code": "hk", "company": "Media-Go Engineering Ltd", "job_title": "Sales Coordinator / Sales Clerk", "description": "Job Responsibilities:\n\n\nPerform full reception function in a professional manner as required.\nHandle administrative work including but not limited to data entry, data generation & analysis\u00a0\nTo serve the walk-in internal customers politely to display professional image\nCoordinate between internal departments and clients to ensure timely delivery\nHandles ad-hoc assignments and customer programs\n\nJob Requirements:\n\n\n\nDiploma or above\n2+ years of solid experience, working in a\u00a0clinic will be an advantage.\nGood command of written and spoken English and Chinese\nGood telephone manner and communication skills\nKnowledge in MS Office\nGood working attitude, polite, punctual, responsible and self-motivated.\n\nCan work under general supervision\n5.5 days work\nCandidates with more experience will be considered as Assistant Officer.\n\n\nInterested Candidates,\u00a0please send your\u00a0full resume with your\u00a0recent photo, current & expected salary\u00a0by e-mail to\u00a0hr @moderndentallab.com\n\nAll personal data collected will be used for recruitment and employment related purpose only.", "employment_types": ["Full Time"], "selling_points": [], "locations": ["Kwun Tong"], "categories": ["Admin & HR", "Clerical / Admin Staff", "Sales, CS & Business Devpt", "Sales Administration"], "post_time": "2022-01-15T03:49:53Z", "salary": {"currency": null, "max": null, "min": null, "period": "monthly", "term": null}, "salary_visible": false, "title_keywords": ["sales coordinator", "sales clerk"], "responsibilities": ["administrative work", "data", "data entry", "ad-hoc assignments", "analysis", "professional manner", "coordinate"], "requirements": {"degrees": ["diploma or above"], "majors": [], "languages": ["english", "chinese"], "language_level": ["good command"], "hard_skills": ["ms office"], "soft_skills": ["communication skills", "good working attitude", "self-motivated", "polite", "responsible", "telephone manner"], "languages_combined": [{"language": "english", "language_level": ["good command"]}, {"language": "chinese", "language_level": ["good command"]}]}, "experience_required": {"duration": ["2+ years"], "field": ["clinic"]}}, {"job_id": "100003009050538", "location_code": "hk", "company": "The Cookware Company Global Sourcing Limited", "job_title": "Program Coordinator, Loyalty", "description": "Role & Key Responsibilities\n\nProvide administrative support for retail operations team including frontline staff duty roster, commission/incentive calculation etc.\nCompile regular reports through POS, Excel or other software for retail operations team and management review\nMaintain adequate and timely communication between office and frontline shop\nHandle customer service hotline to assist with customer\u2019s enquiries, requests or complaints to achieve total customer satisfaction\nPerform general clerical duties/other duties as assigned\n\nRequirements:\n\nDiploma holder or above in Services Operations, Business Administration or related discipline\nAt least 3 years\u2019 relevant experience in retail industry\nGood team player with good communication skills\nProactive, organized and detail-minded\nProficiency in MS Office and Chinese word processing\nGood command of spoken and written English, Cantonese and Mandarin\n\nInterested parties, please \"APPLY NOW\" or send your full resume with current and expected salary to Senior Human Resources Manager, 6/F, The Edge, 30-34 Kwai Wing Road, Kwai Chung, N.T., Hong Kong\n\n\u00a0For more information, please contact Ms. Wan at 39290621.\n\n\u00a0All information received will be kept strictly confidential and only for employment-related purposes.", "employment_types": ["Full Time", "Permanent"], "selling_points": ["Dynamic MNC environment", "Promising career path", "Energetic working team"], "locations": ["Kowloon Bay"], "categories": ["Marketing / Public Relations", "Marketing - General / Support", "Sales, CS & Business Devpt", "Account Servicing", "Sales Administration"], "post_time": "2022-01-14T10:42:09Z", "salary": {"currency": null, "max": null, "min": null, "period": "monthly", "term": null}, "salary_visible": false, "title_keywords": ["program coordinator"], "responsibilities": ["software", "other duties", "operations", "communication", "maintain", "reports", "customer service", "provide administrative support", "management review"], "requirements": {"degrees": ["diploma holder"], "majors": ["business administration"], "languages": ["cantonese", "english", "chinese", "mandarin"], "language_level": ["proficiency", "good command"], "hard_skills": ["chinese word processing", "ms office"], "soft_skills": ["detail-minded", "organized", "communication skills", "good team player", "proactive"], "languages_combined": [{"language": "cantonese", "language_level": ["good command"]}, {"language": "english", "language_level": ["good command"]}, {"language": "chinese", "language_level": ["proficiency"]}, {"language": "mandarin", "language_level": ["good command"]}]}, "experience_required": {"duration": ["at least 3 years"], "field": ["retail industry", "relevant experience"]}}, {"job_id": "100003009050404", "location_code": "hk", "company": "Digi-Key Electronics Asia Pacific Limited", "job_title": "Sales Coordinator (5 days work)", "description": "Responsibilities:\n\nPromote and sell a variety range of building products\nExplore and develop new business opportunities and potential clients\nPrepare technical submissions and assist on quotations\nHandle customers' enquiries and follow up orders\nMaintain good relationship with customers and update market and industry development\nHandle ad hoc assignments as required\n\nRequirements:\n\n\n\nHigher Diploma in Sales/Marketing/Construction/Engineering\u00a0or related disciplines\nMinimum 2 years\u00a0Sales experience\u00a0in Construction related Materials\nOrganized, self-motivated, outgoing, presentable and sales\u00a0oriented\nGood communication and presentation skills\nProficient in MS Office is essential\nMust have Driving Licence no. 1 & 2\u00a0\nCandidate with less experience will be considered as Sales Assistant\nImmediate availability is preferred", "employment_types": ["Full Time"], "selling_points": ["Handle customer order & sales admin", "Experience in Sales Support", "Proficient in written English and Chinese"], "locations": ["Kwai Hing"], "categories": ["Sales, CS & Business Devpt", "Account Servicing", "Sales - Sales Management", "Sales Administration"], "post_time": "2022-01-14T10:19:41Z", "salary": {"currency": null, "max": null, "min": null, "period": "monthly", "term": null}, "salary_visible": false, "title_keywords": ["sales coordinator"], "responsibilities": ["follow up orders", "develop new business", "ad hoc assignments", "maintain good relationship"], "requirements": {"degrees": ["diploma"], "majors": ["related disciplines", "marketing", "engineering"], "languages": [], "language_level": [], "hard_skills": ["no", "ms office"], "soft_skills": ["outgoing", "organized", "self-motivated", "presentable", "communication", "presentation skills"], "languages_combined": []}, "experience_required": {"duration": ["minimum 2 years"], "field": ["related", "construction"]}}, {"job_id": "100003009056064", "location_code": "hk", "company": "Wong\u2019s Electronics Company Limited", "job_title": "Assistant Manager, Marketing and Research Analytics", "description": "Responsibilities :\u00a0\n\n\nProvide administrative support in the New Car sales admin. team in order to achieve monthly delivery targets\nEnsure all the relevant documents are received for licensing\u00a0\nCheck and verify the sales contract information\u00a0\nCompile daily & monthly report for management review\u00a0\nEnsure all documents are filed properly and fulfill audit requirements\u00a0\nSupport and assist in implementation of various sales events/ promotional activities\nAny other duties as assigned by immediate supervisor\u00a0\nRequirements :\u00a0\n\n\nHigher Diploma or above\u00a0\nCandidates with at least 2 years experience in sales administration\u00a0\nDetail minded and outgoing, with good communication & interpersonal skills\u00a0 \u00a0\u00a0\nGood command of both written and spoken English and Chinese including Putonghua and Cantonese\nProficient in MS office (Word, Excel, Powerpoint)\nInterested parties please send your full resume and expected salary\u00a0to our mailbox by clicking \u201cApply now\u201d below.\n\nFor more information about Jebsen Group, please visit www.jebsen.com or follow us on:\n\nSina Weibo\u00a0\u00a0\u00a0\u00a0\u00a0http://weibo.com/jebsengroup\n\nWeChat\u00a0\u00a0\u00a0\u00a0\u00a0\u00a0\u00a0\u00a0\u00a0\u00a0 ID: jebsen1895\n\nLinkedIn\u00a0\u00a0\u00a0\u00a0\u00a0\u00a0\u00a0\u00a0\u00a0\u00a0 Jebsen Group\n\u00a0\n\n\nAll information provided by applicants will\u00a0be used for recruitment purposes only.\n\nAt Jebsen, success breeds success.", "employment_types": ["Full Time", "Permanent"], "selling_points": ["All-round market research", "Data analysis", "5 days work week"], "locations": ["Ngau Tau Kok"], "categories": ["Marketing / Public Relations", "Marketing - General / Support", "Marketing - Market Research", "Sales, CS & Business Devpt", "Sales Administration"], "post_time": "2022-01-18T03:14:43Z", "salary": {"currency": null, "max": null, "min": null, "period": "monthly", "term": null}, "salary_visible": false, "title_keywords": ["assistant manager,"], "responsibilities": ["any other duties", "implementation", "audit", "promotional activities", "monthly report", "provide administrative support", "management review"], "requirements": {"degrees": ["higher diploma or above"], "majors": [], "languages": ["cantonese", "putonghua", "english", "chinese"], "language_level": ["good command"], "hard_skills": ["excel", "word", "powerpoint", "ms office"], "soft_skills": ["outgoing", "interpersonal skills", "communication"], "languages_combined": [{"language": "cantonese", "language_level": ["good command"]}, {"language": "putonghua", "language_level": ["good command"]}, {"language": "english", "language_level": ["good command"]}, {"language": "chinese", "language_level": ["good command"]}]}, "experience_required": {"duration": ["at least 2 years"], "field": ["sales administration"]}}, {"job_id": "100003009047754", "location_code": "hk", "company": "Goldlok Holdings (Guangdong) Company Limited", "job_title": "Sales Coordinator (Toys)", "description": "We are a dynamic & fast-growing Toy manufacturer located in TST, we\u2019re now looking for high caliber candidate to fill the following position, selected candidate will be invited to join our energetic & dynamic team.\u00a0\n\n\nResponsibilities:\n\nReport and work closely with Senior Account Manager to manage the book of business\nAcquire new and potential customers and develop new sales leads through diverse channels and industry activities\nGrow existing customer portfolio, and manage day-to-day activities\nPrepare quotations, work order, sales report, order processing and follow up, as well as handle enquiries\nWork closely with design, engineering, and factory to ensure seamless production process (e.g. communicate detail production instructions and product briefing)\nPerform marketing research and ad hoc assignments from senior management\nStrong experience in handling large/complex customers are highly desirable\nHandle new enquiries, prepare quotations, arrange samples, and manage projects\nPrepare sales forecast, meeting report and any ad hoc reports as needed\nParticipate industry related conferences and exhibitions\n\nRequirements:\n\nDiploma or above with 3 years relevant experience in electronic toys industry\nGood command of written & spoken English is a must, Cantonese and Mandarin preferable\nSuperior people relationship skills\nDetail oriented\nMust be able to work and handle US/European customers independently\nStrong knowledge of MS Office\nSelf-motivated, independent and team player with strong communication skills\nMust be able to work independently, have strong multi-tasking abilities & resourceful\nMight require to travel to China\n\nWe offer attractive compensation including MPF, medical insurance, year-end bonus and excellent career prospect to the right candidates.\n\nPlease send email with a copy of resume to Apply Now\u00a0to arrange an interview.", "employment_types": ["Full Time"], "selling_points": [], "locations": ["Tsim Sha Tsui"], "categories": ["Sales, CS & Business Devpt", "Channel / Distribution", "Direct Sales", "Sales Administration"], "post_time": "2022-01-14T07:40:51Z", "salary": {"currency": null, "max": null, "min": null, "period": "monthly", "term": null}, "salary_visible": false, "title_keywords": ["sales coordinator"], "responsibilities": ["sales report", "production process", "ad hoc", "prepare sales", "design", "develop", "handle enquiries", "marketing research", "conferences", "reports", "ad hoc assignments", "order processing", "manage projects", "forecast", "senior management", "report"], "requirements": {"degrees": ["diploma or above"], "majors": [], "languages": ["cantonese", "english", "mandarin"], "language_level": ["good command"], "hard_skills": ["ms office"], "soft_skills": ["communication skills", "self-motivated", "independently", "independent", "work independently", "resourceful", "detail oriented", "multi-tasking", "team player", "superior"], "languages_combined": [{"language": "cantonese", "language_level": ["good command"]}, {"language": "english", "language_level": ["good command"]}, {"language": "mandarin", "language_level": ["good command"]}]}, "experience_required": {"duration": ["3 years"], "field": ["toys", "relevant experience"]}}, {"job_id": "100003009052257", "location_code": "hk", "company": "ALF Retail Hong Kong Limited", "job_title": "Retail Operations Supervisor (Brand: Marks and Spencer)", "description": "This role will be responsible for customer service, monitoring the customer journey, driving operational efficiency, controlling the shrinkage and fulfilling business internal control policies.\u00a0\n\nRoles & Responsibilities:\nDrive better customer service standards, improve customers' shopping experience and to provide solutions to customers' cases\nEnsure compliance with company policies, regulations and standardize all the workflow\nManage different projects as a project-in-charge to ensure standardization with business and brand\nEnsure the operations communication plan is delivered on time\u00a0\nTake responsibility in the operations administration to achieve company standard\nMaintain and provide efficient backup to stores and fulfil internal and external business needs\nAnalyse all opportunities and recommend ways to improve efficiency and reduce costs\nRequirements:\nDiploma educated with at least 2 years\u2019 relevant experience in Retail or FMCG industry\nPrevious experience as an operations supervisor or similar role\u00a0in Retail or FMCG industry is an advantage\u00a0\nExperience in handling customer service and monitoring customer shopping journey\u00a0\nHands-on experience implementing operational processes\nExperience in Retail SAP and stock take is a plus\nProficiency in MS Office\nFluent in verbal and written English\n\nIf you are interested in this role, please send your full resume together with your current and expected salary to us by clicking Apply Now.\nThe Human Resources Department (for interview):\u00a0\n1806B, Exchange Tower, 33 Wan Chiu Road, Kowloon Bay, Kowloon\n\n\nPersonal information received from applications will be kept confidential and used for employment-related purpose only.", "employment_types": ["Full Time", "Permanent"], "selling_points": ["Customer Service experience", "Hands-on experience in operational processes", "Retail SAP and stock take experience"], "locations": ["Kowloon Bay"], "categories": ["Sales, CS & Business Devpt", "Customer Service - Supervisor / Officer", "Retail Sales", "Sales Administration"], "post_time": "2022-01-17T02:35:39Z", "salary": {"currency": null, "max": null, "min": null, "period": "monthly", "term": null}, "salary_visible": false, "title_keywords": ["operations", "supervisor"], "responsibilities": ["regulations", "policies", "operations", "provide solutions", "ensure compliance", "communication", "customer service", "maintain", "plan", "analyse", "costs", "administration"], "requirements": {"degrees": ["diploma"], "majors": [], "languages": ["english"], "language_level": ["fluent"], "hard_skills": ["plus", "sap", "fmcg industry", "wan", "ms office", "exchange"], "soft_skills": ["interested in", "hands-on", "customer service"], "languages_combined": [{"language": "english", "language_level": ["fluent"]}]}, "experience_required": {"duration": ["at least 2 years"], "field": ["customer service", "retail", "relevant experience", "fmcg"]}}, {"job_id": "100003009050514", "location_code": "hk", "company": "Guardforce Ltd", "job_title": "Sales Administrative Coordinator", "description": "Responsibilities\n\n\n\nHandle sales coordination and administration duties\nPrepare quotation and sales proposals for Sales Team\nMaintain the accuracy of clients' data and records\u00a0\nCoordinate and liaise internally with various departments\nCollect market information regularly\nTo perform ad-hoc job assigned by the superior\n\nRequirements\n\n\nDiploma holder or above, preferably in Business related discipline\nMinimum 1-2 years experience in sales administration and support\nA good team player with pleasant and outgoing personality\nGood communication and interpersonal skills\nFamiliar with MS Office and Chinese Word Processing\nGood command of both spoken and written English and Chinese\n\nCome & Join Us! Attractive remuneration packages will be offered to the right candidate.\n\nInterested parties, please send your application together with a full resume stating your\u00a0present and expected salary & date of availability to:\n\nFax: 2333-3481; or\nMail: 1/F., Guardforce Centre, 3 Hok Yuen Street East, Hung Hom, Kowloon.\n\nPersonal data provided in your application will be kept in the strictest confidence. It will only be used for employment-related purposes by any entity within our Group. Applicants not notified within 1 month will be considered as unsuccessful. Unsuccessful application may be kept for another 3 months for new openings or consideration by another entity within our Group before properly shredded.\n\nSecurity Licence No. : 0092", "employment_types": ["Full Time", "Permanent"], "selling_points": [], "locations": ["Hung Hom"], "categories": ["Sales, CS & Business Devpt", "Sales Administration"], "post_time": "2022-01-14T10:36:08Z", "salary": {"currency": null, "max": null, "min": null, "period": "monthly", "term": null}, "salary_visible": false, "title_keywords": ["coordinator", "sales"], "responsibilities": ["liaise", "ad-hoc", "market information", "data", "quotation", "coordinate", "maintain", "sales team", "coordination", "administration"], "requirements": {"degrees": ["diploma holder"], "majors": ["business"], "languages": ["english", "chinese"], "language_level": ["good command"], "hard_skills": ["chinese word processing", "ms office"], "soft_skills": ["outgoing personality", "good team player", "communication and interpersonal skills", "pleasant"], "languages_combined": [{"language": "english", "language_level": ["good command"]}, {"language": "chinese", "language_level": ["good command"]}]}, "experience_required": {"duration": ["minimum 1-2 years"], "field": ["sales administration"]}}, {"job_id": "100003009047140", "location_code": "hk", "company": "Lane Crawford (Hong Kong) Limited", "job_title": "Sales Administrator", "description": "Job Purpose:\u00a0\n\n\u201cTo assist the buying function to ensure efficient PO management, weekly sales reporting and operations follow up\u201d\n\nKey Accountabilities:\n\nIn addition to following Lane Crawford\u2019s policies and procedures, key accountabilities include, but are not limited to:\n\nMerchandise Management\n\nTo support buying teams with PO creation and follow up according to Company guidelines\nTo work closely with warehouse and store teams to solve goods received problems\nTo follow up with online team on new items timely upload\nTo follow up on online stock level, alerting on OOS and slow movers\nTo update prices upon brand\u2019s request\nTo prepare reports on the sell through of agreed key items\n\nData Management & Admin\n\nTo prepare and run reports for the Central Buying Office, including but not limited to monthly sales report, monthly ranking report, monthly online sales report, yearly productivity report and floorplan and counter movements.\nTo help organize monthly beauty monthly meetings, including but not limited to SNS meeting, BNW team sharing meeting, store visits, online meeting and marketing debrief\nTo set up all codes required to effectively manage the business, including vendor codes, department, etc\nTo help in general admin tasks such as internal mail, expense claims consolidation and stationary orders\nAttend OBIEE and NEO enhancement meetings, providing insights for improvements and following up on changes implemented\n\nCommunication\n\nTo communicate regularly with Warehouse, Store, Logistics and Merchandise Planning & Allocation team to ensure merchandise management is smooth and timely\nTo handle brand enquiries and requests regarding merchandise promptly and efficiently to minimize any delay or disruption to the business\nTo handle payment enquiries from vendors and work with Finance on payment issues\n\n\u00a0Company Culture\n\nTo fully engage and live by the Lane Crawford Vision, Passion, Learning, Collaboration (PLC) Values, and deliver our Customer Service Promise at all times\nTo build collaborative working relationships with your colleagues to ensure the achievement of the Company Business Plan, your department and individual objectives\nThink proactively and work with an entrepreneurial spirit. We like candidates with a problem-solving attitude that are keen to take new challenges and take ownership\n\nJob Requirements:\n\nDiploma or above in business/logistic related discipline\nSome relevant experience, preferably in the luxury Lifestyle industry is a plus\nStrong analytical, negotiation and communication skills\nProactive, attentive to details and able to follow tight timeline\nExcellent command of written & spoken English & Chinese\nFamiliar with ERP system is a plus", "employment_types": ["Full Time", "Permanent"], "selling_points": ["PO follow up, Data Management & Admin", "Work closely with warehouse and store teams", "Merchandise Management"], "locations": ["Aberdeen"], "categories": ["Sales, CS & Business Devpt", "Sales Administration"], "post_time": "2022-01-14T02:26:26Z", "salary": {"currency": null, "max": null, "min": null, "period": null, "term": null}, "salary_visible": false, "title_keywords": ["sales administrator"], "responsibilities": ["data", "operations", "communication", "payment", "customer service", "monthly sales report", "sales report", "teams", "reports", "logistics", "business plan", "report", "reporting", "management", "procedures", "policies", "company guidelines", "working relationships", "prepare reports", "planning"], "requirements": {"degrees": ["diploma or above"], "majors": ["business"], "languages": ["english", "chinese"], "language_level": ["excellent"], "hard_skills": ["plus", "data management", "problem-solving", "plc", "vendor", "erp system", "codes"], "soft_skills": ["efficient", "communication skills", "negotiation", "attentive to details", "keen", "timely", "problem-solving", "collaborative", "communication", "learning", "customer service", "smooth", "proactive"], "languages_combined": [{"language": "english", "language_level": ["excellent"]}, {"language": "chinese", "language_level": ["excellent"]}]}, "experience_required": {"duration": [], "field": ["relevant experience"]}}, {"job_id": "100003009056652", "location_code": "hk", "company": "MAN Truck and Bus Hong Kong Limited", "job_title": "Service Advisor (m/f/d) - located in San Tin (Yuen Long)", "description": "Key performance areas: (Not Totally Inclusive)\n\nProvide effective customer contact regarding all aspects on the repairs undertaken on the customer\u2019s vehicle\nEnsure prior authorization of repairs/ servicing is obtained and customers\u2019 signature is obtained on the job card\nSchedule the work to be performed\nAssign, monitor and settle mechanics' working time for the orders\nCalculation of the workshop orders\nResponsible for the intake of customer vehicles through completing of job cards detailing work\nDescription, customer and vehicle details and confirmation of the payment method\nResponsible for supervising the 24-hour breakdown service\nPerform standby duties as per the set schedule\n\n\u00a0Core behavioural competencies:\n\nAble to work well under pressure and maintain good customer relations\nGood communication (oral and written) interpersonal relations skills\nCustomer oriented person with a result driven approach\nPro-active and highly motivated\nAble to work independently though being a team player\n\n\u00a0Minimum qualification and experience / skills required\n\nFull qualification in vehicle mechanics/mechatronic, a comparable completed country-specific training\nPrevious experience in a workshop with a good understanding of the commercial vehicles might be advantage\nGood commercial knowledge and experience in field of servicing\nMust be computer literate\nValid Hong Kong Driving license", "employment_types": ["Full Time", "Permanent"], "selling_points": ["Team Work", "Be part of something new", "Automotive Industry"], "locations": ["Yuen Long"], "categories": ["Sales, CS & Business Devpt", "Customer Service - Supervisor / Officer", "Account Servicing", "Sales Administration"], "post_time": "2022-01-18T05:31:21Z", "salary": {"currency": null, "max": null, "min": null, "period": "monthly", "term": null}, "salary_visible": false, "title_keywords": ["advisor"], "responsibilities": ["supervising", "workshop", "monitor", "communication", "payment", "maintain", "contact", "schedule"], "requirements": {"degrees": [], "majors": [], "languages": [], "language_level": [], "hard_skills": [], "soft_skills": ["oral", "work independently", "under pressure", "responsible", "driven", "communication", "motivated", "pro-active", "team player", "interpersonal"], "languages_combined": []}, "experience_required": {"duration": [], "field": ["commercial"]}}, {"job_id": "100003009052427", "location_code": "hk", "company": "Jeeves (HK) Limited", "job_title": "Digital Sales Manager", "description": "JEEVES, the Prestigious UK Dry Cleaning franchise is currently looking for a suitable candidate:\n\n\n\nDigital Sales Manager\u00a0\n\nResponsibilities:\u00a0\n\nlead our team in maintaining the efficiency of our existing electronic point of sales system (EPOS)\nInputting and updating data regularly\nCreating sales reports for department head\nTraining our retail team how to use sales software and features\nCommunicate with our UK service provider\nTraining our production team how to use software in the back end\nKeeping track of sales reports and records from EPOS system\nBeing a good representative of our company at our retail stores when visiting\nAssist the head of department to develop and streamline our current sales system and research other potential providers and software\nLiaise with customer service teams and marketing teams frequently\u00a0\n\nRequirements:\u00a0\n\nDegree is preferred in related field\nFluent in English and Cantonese\nMinimum 3 years work experience. Any experience in sales and retail preferred\nExcellent skillset with computer software need\nExperience with EPOS systems preferred\nWilling to work at our multiple locations in HK , Aberdeen, Central, Causeway Bay\nConfident individual who can also be a team player\nProactive, multi-tasking\nInterest in fashion brands, designer fashion would be preferred\u00a0\n\nBenefits:\u00a0\n\nBirthday Leave\nPerformance-based bonus\nStaff healthcare\u00a0\nStaff insurance\nStarting 14 days paid annual leave\nLunch provided Monday \u2013 Friday\u00a0\n\nWebsite:\u00a0http://www.jeeves.com.hk\n\n\u00a0If you consider yourself as an excellent multi-tasker with outstanding task management, please send a full resume with expected salary and availability by clicking \u201cApply Now\u201d for interview.\n\n\u00a0Personal data will be used for recruitment purpose only.", "employment_types": ["Full Time"], "selling_points": [], "locations": ["Aberdeen"], "categories": ["Sales, CS & Business Devpt", "Business Development", "Sales Administration"], "post_time": "2022-01-17T03:00:15Z", "salary": {"currency": null, "max": null, "min": null, "period": "monthly", "term": null}, "salary_visible": false, "title_keywords": ["sales manager"], "responsibilities": ["communicate with", "software", "sales reports", "maintaining", "data", "teams", "develop", "customer service", "liaise with"], "requirements": {"degrees": ["degree"], "majors": [], "languages": ["cantonese", "english"], "language_level": ["fluent"], "hard_skills": [], "soft_skills": ["confident", "team player", "proactive", "multi-tasking"], "languages_combined": [{"language": "cantonese", "language_level": ["fluent"]}, {"language": "english", "language_level": ["fluent"]}]}, "experience_required": {"duration": ["minimum 3 years"], "field": ["retail"]}}, {"job_id": "100003009051371", "location_code": "hk", "company": "Double C Intelligence Limited", "job_title": "Sales Assistant \u5be6\u7fd2\u71df\u696d\u52a9\u7406 - \u5168\u8077", "description": "-Higher Diploma or Degree holder\n-Self-motivated, good team player with proactive working attitude\n-Good command in spoken and written English & Chinese\n-Provide administrative and clerical supports to the Sales and Marketing teams\n-Prepare presentation and promotion material\n-Support sales and marketing activities, strengthen customer services\n-Perform ad-hoc jobs as assigned\n\n***Fresh graduates are also welcome", "employment_types": ["Full Time"], "selling_points": ["Higher Diploma or Degree holder", "Fresh graduates are also welcome", "Medical + Bonus"], "locations": ["Yau Ma Tei"], "categories": ["Sales, CS & Business Devpt", "Sales Administration"], "post_time": "2022-01-15T12:14:00Z", "salary": {"currency": "HKD", "max": 19999, "min": 14000, "period": "monthly", "term": null}, "salary_visible": true, "title_keywords": ["sales assistant"], "responsibilities": ["ad-hoc", "teams", "customer services"], "requirements": {"degrees": ["diploma", "degree holder"], "majors": [], "languages": ["english", "chinese"], "language_level": [], "hard_skills": [], "soft_skills": ["presentation", "good team player", "motivated", "proactive"], "languages_combined": [{"language": "english", "language_level": []}, {"language": "chinese", "language_level": []}]}, "experience_required": {"duration": [], "field": []}}, {"job_id": "100003009051395", "location_code": "hk", "company": "Chubb Hong Kong Limited", "job_title": "Administration Assistant (Ref: JB/CHB/ADM)", "description": "Responsibilities:\n\nTo perform administrate tasks such as quotation preparation, job arrangement and invoicing\nTo handle phone calls\n\nTo liaise and take immediate action when any internal/external customer enquiry occurs\nTo prepare various reports for management and other internal teams\nTo communicate with internal teams to resolve any issues arisen during project or service delivery\nTo perform any ad-hoc tasks and activities as assigned by management from time to time\n\nRequirements:\n\nFrom 7 or above\n2-3 years administrative work experience, fresh graduates are also welcome to apply\nProficiency in using MS Office and Chinese typing is essential\nProficiency in spoken and written English and Chinese (including Putonghua is a plus)\nWith experiences in customer services area and ERP system will be an advantage\nHigh accuracy, independent, strong sense of responsibility, good communication skills and able to work under pressure\nImmediate available is an advantage\n\u00a0\n\nAttractive compensation and benefits packages will be offered to the right candidate. Interested parties, please click \"Apply Now\"\u00a0& send your application together with a full resume stating your present and expected salary and date of availability to us (please quote the reference number); or\n\nBy mail\nThe Talent Acquisition Manager, Chubb Hong Kong Limited, 10/F, Habourside HQ, 8 Lam Chak Street, Kowloon Bay, Kowloon ; or\n\nBy fax\n2764 3098\n\n\u00a0\nYou may also contact us by our recruitment hotline at 5362 3810 (WhatsApp welcomed) in case you have any enquiries.\n\nPersonal data provided in your application will be kept in the strictest confidence. It will only be used for employment-related purposes by any entity within our Group. Applicants not notified within 1 month will be considered as unsuccessful. Unsuccessful application may be kept for another 6 months for new openings or consideration by another entity within our Group before properly shredded.\n\nSecurity Licence No. : 0961", "employment_types": ["Full Time", "Permanent"], "selling_points": ["To perform administrative support", "To handle phone calls", "5-day work, full range of benefits"], "locations": ["Kowloon Bay"], "categories": ["Admin & HR", "Clerical / Admin Staff", "Sales, CS & Business Devpt", "Others", "Sales Administration"], "post_time": "2022-01-15T14:18:49Z", "salary": {"currency": null, "max": null, "min": null, "period": "monthly", "term": null}, "salary_visible": false, "title_keywords": ["administration assistant"], "responsibilities": ["liaise", "communicate with", "management", "service delivery", "ad-hoc tasks", "quotation", "teams", "invoicing", "reports", "phone calls"], "requirements": {"degrees": [], "majors": [], "languages": ["putonghua", "english", "chinese"], "language_level": ["proficiency"], "hard_skills": ["plus", "erp system", "typing", "ms office"], "soft_skills": ["work under pressure", "communication skills", "independent", "sense of responsibility"], "languages_combined": [{"language": "putonghua", "language_level": ["proficiency"]}, {"language": "english", "language_level": ["proficiency"]}, {"language": "chinese", "language_level": ["proficiency", "proficiency"]}]}, "experience_required": {"duration": ["2-3 years"], "field": ["erp system", "administrative", "customer services"]}}, {"job_id": "100003009043613", "location_code": "hk", "company": "DKSH Hong Kong Limited", "job_title": "Coordinator, Customer Care", "description": "Job Responsibilities:\n\nPerform full chain of order fulfillment from various platforms timely and accurately\nMonitor consignment fill-up, replenishment and settlement\nLiaise with internal and external stakeholders on all order related issues\nDeliver quality service in handling inquiries, order status tracking, complaints\nManage inventory and maintain tidiness of the designated service room\nCreate and maintain customer profile and membership program\nDemonstrate call center professional manner and service excellence\nRecord, summarize and support system maintenance\nSupport and back up pricing update/maintenance (if necessary)\nPrepare periodic reports for management review\nAd hoc project support\n\nJob Requirements:\n\nSecondary education/Diploma holder and/or above\n1-2 years working experience in Order Processing / Sales Administration / Customer Services\nTeam player with good interpersonal and business communication skills\nGood command of English\nProficiency in MS Office applications\nKnowledge in SAP operations will be advantageous\nCandidates with more experience will be considered as Senior Coordinator, Customer Care\nWorking location:\u00a0Wong Chuk Hang\n\nWe offer performance bonus and attractive benefits including medical insurance and company shuttle bus services to the right candidate. Interested parties please apply in full resume with current and expected salaries to Human Resources Department , DKSH Hong Kong Limited, 23rd Floor, Tower A, Southmark, 11 Yip Hing Street, Wong Chuk Hang, Hong Kong or by clicking \"Apply Now\"\n\n\nAll personal data collected will be used for recruitment purposes only. \u00a0Candidates will be contacted within 2 weeks if the background and experience are closely relevant to the job requirement.\n\nDrive Growth. Be the Difference. Join DKSH.\n\nDKSH\u2019s strength lies in our great diversity of services, industries, clients, products, regions, and employees from various cultures. We are proud of our people: they are the best in the industry and the reason for our business success. They are passionate, energetic, and purposeful, positively touching millions of lives through the products and services we provide.\u00a0Join us today if you are ready to\u00a0\u201cDrive Growth. Be the Difference.\u201d\u00a0With DKSH, you will experience a world of learning and development, own your career and take business responsibility, and have a positive impact that touches people\u2019s lives.", "employment_types": ["Full Time", "Permanent"], "selling_points": ["Perform full chain of order fulfillment", "Quality customer service delivery", "1-2 years relevant working experience"], "locations": ["Aberdeen"], "categories": ["Sales, CS & Business Devpt", "Call Centre", "Customer Service - Supervisor / Officer", "Sales Administration"], "post_time": "2022-01-13T00:43:39Z", "salary": {"currency": null, "max": null, "min": null, "period": "monthly", "term": null}, "salary_visible": false, "title_keywords": ["coordinator"], "responsibilities": ["ad hoc", "maintenance", "inventory", "quality", "monitor", "replenishment", "professional manner", "order fulfillment", "maintain", "reports", "liaise with", "management review", "tracking"], "requirements": {"degrees": ["diploma holder", "secondary education"], "majors": [], "languages": ["english"], "language_level": ["good command"], "hard_skills": ["sap", "order processing", "ms office"], "soft_skills": ["communication skills", "team player", "interpersonal"], "languages_combined": [{"language": "english", "language_level": ["good command"]}]}, "experience_required": {"duration": ["1-2 years"], "field": ["sales administration", "customer care", "order processing", "customer services"]}}, {"job_id": "100003009049968", "location_code": "hk", "company": "Acuzio Visual Technology Engineering Co. Limited", "job_title": "Sales Administration", "description": "Acuzio Visual Technology Engineering Co. Ltd (AVT) is a professional system integration company which specializes in Audio & Visual, LED Display System and Automation Control System. Please visit us at www.avt-global.com\u00a0\u00a0\u00a0\u00a0\u00a0\n\n\nJob Duties:\n\nTo provide administrative support and assist order processing\nTo support the Sales and Engineer activities\nTo coordinate with suppliers , clients and internal business units for order processing\u00a0\nTo coordinate with internal business units for business processes to ensure smooth operation\nHandle ad-hoc tasks as assigned\n\nRequirement:\n\nDSE or above\nDiploma in Business Administration is an advantage\u00a0\nAt least 2 years of solid work experience\u00a0\nKnowledge in Video Technology, IT Technology is an advantage\nWell organized and strong sense of responsibility is a must\nFlexible and able to work under pressure\nProficient in using Microsoft Office and Project, China Word processing\nGood command of both spoken and written English and Chinese;\nImmediate available is preferred\n\n\u00a0We offer attractive salary and fringe benefit to the right candidate. Interested parties please email your full resume with expected salary to Human Resources Department,", "employment_types": ["Full Time"], "selling_points": ["At least 2 years of solid work experience", "Well organized and strong sense of responsibility", "Immediate available is preferred"], "locations": ["Mong Kok"], "categories": ["Admin & HR", "Clerical / Admin Staff", "Sales, CS & Business Devpt", "Sales Administration"], "post_time": "2022-01-14T09:32:41Z", "salary": {"currency": null, "max": null, "min": null, "period": "monthly", "term": null}, "salary_visible": false, "title_keywords": ["sales"], "responsibilities": ["provide administrative support", "ad-hoc tasks", "coordinate with", "order processing"], "requirements": {"degrees": ["diploma", "dse"], "majors": ["business administration"], "languages": ["english", "chinese"], "language_level": ["good command"], "hard_skills": ["word processing", "microsoft office"], "soft_skills": ["flexible", "work under pressure", "well organized", "sense of responsibility"], "languages_combined": [{"language": "english", "language_level": ["good command"]}, {"language": "chinese", "language_level": ["good command"]}]}, "experience_required": {"duration": ["at least 2 years"], "field": []}}, {"job_id": "100003009050433", "location_code": "hk", "company": "Ecolab Limited", "job_title": "Sales Support (5-day work)", "description": "Ecolab (ECL) is the global leader in water, hygiene and energy technologies and services that protect people and vital resources. We are looking for a high caliber to join our Pest Elimination team.\n\nWhat You Will Do\u00a0\n\nSupport sales team to improve their productivity by contacting customers to ensure Sales Team have high quality and up-to-date support material\nPerform administrative tasks to support sales team to gain and retain customers and ensure all orders are processed in a timely manner\nHandle sales orders (via online, phone, email and other channels), invoice preparation, sales record maintenance and filing\nAssist in ad-hoc tasks as assigned\n\nKey Requirement\n\nHigh Diploma with minimum 2 years+ solid experience in or Sales Support\nWell-organized, detail minded with strong sense of responsibility and time management skills\nTeam player, good problem-solving and communication skills\nMultitasking and capable to work in a fast-paced environment and meet deadlines\nProficiency in PC application & Chinese word processing\n\nPlease send your CV with current, expected salary and availability to us.\u00a0 For more information about ECOLAB, please visit www.ecolab.com\n\n\u00a0All personal data provided by job applicants will be used for recruitment purpose only.", "employment_types": ["Full Time", "Permanent"], "selling_points": ["MNC and Fortune Global 500", "Excellence Career Opportunity", "Market Leader in Food Safety and Water Treatment"], "locations": ["Kwun Tong"], "categories": ["Sales, CS & Business Devpt", "Others", "Sales Administration"], "post_time": "2022-01-14T10:24:58Z", "salary": {"currency": null, "max": null, "min": null, "period": "monthly", "term": null}, "salary_visible": false, "title_keywords": ["sales"], "responsibilities": ["management", "maintenance", "invoice", "ad-hoc tasks", "a timely manner", "quality", "communication", "hygiene", "sales team", "recruitment", "administrative tasks", "personal data"], "requirements": {"degrees": ["high diploma"], "majors": [], "languages": ["chinese"], "language_level": ["proficiency"], "hard_skills": ["chinese word processing", "sales support", "maintenance", "problem-solving", "pc"], "soft_skills": ["communication skills", "capable", "sense of responsibility", "time management skills", "fast-paced environment", "timely", "problem-solving", "well-organized", "team player", "meet deadlines"], "languages_combined": [{"language": "chinese", "language_level": ["proficiency"]}]}, "experience_required": {"duration": [], "field": ["sales support"]}}, {"job_id": "100003009051287", "location_code": "hk", "company": "Hutchison Telecommunications (Hong Kong) Limited", "job_title": "Assistant / Business Analysis Executive", "description": "Responsibilities:\n\n\nConduct sales productivity analysis and prepare management reports for performance forecast & review\nCoordinate & liaise with various stakeholders for preparing sales & commission reports\nProvide sales support and assist in ad hoc tasks and projects as assigned\n\nRequirements:\n\nDiploma in Business Administration, Accounting or related disciplines\nFresh graduate is welcome\nGood communication & interpersonal skills\nFigure sensitive and detail-minded with self-motivated character\nProficiency in MS office applications, with sound knowledge in Excel (Pivot table & vlookup)\n\nApart from competitive remuneration package and exciting opportunity for career development within the Group, we provide attractive employee benefits such as free company shuttle, free company SIM card and preferential SIM plan offers, comprehensive medical & insurance schemes, as well as full range of other employee well-being provisions.\u00a0\n\nInterested parties, please apply with full resume, present and expected salary, by clicking \u201cAPPLY NOW\u201d. Please quote the reference number on the e-mail subject.\n\nWe are an equal opportunity employer and welcome applications from all qualified candidates. Personal data collected will be treated in the strictest confidence and handled confidentially by authorised personnel for recruitment-related purposes only within the CK Hutchison Group of companies. The personal data of unsuccessful applicants will be destroyed after the recruitment exercise pursuant to the requirements of the Personal Data (Privacy) Ordinance in Hong Kong.", "employment_types": ["Full Time", "Permanent"], "selling_points": [], "locations": ["Tsing Yi"], "categories": ["Accounting", "Accounting Clerk / Supervisor", "Sales, CS & Business Devpt", "Sales Administration"], "post_time": "2022-01-15T07:17:39Z", "salary": {"currency": null, "max": null, "min": null, "period": "monthly", "term": null}, "salary_visible": false, "title_keywords": ["executive", "assistant"], "responsibilities": ["analysis", "review", "ad hoc tasks", "coordinate", "management reports", "reports", "forecast", "liaise with"], "requirements": {"degrees": ["diploma", "fresh graduate"], "majors": ["related disciplines", "accounting", "business administration"], "languages": [], "language_level": [], "hard_skills": ["excel", "pivot table", "vlookup", "ms office"], "soft_skills": ["detail-minded", "self-motivated", "communication", "comprehensive", "interpersonal skills", "sensitive"], "languages_combined": []}, "experience_required": {"duration": [], "field": []}}]