[{"job_id": "100003009053007", "location_code": "hk", "company": "Welland Investments Ltd", "job_title": "Outdoor Sales Representative (\u6279\u767c\u884c\u8857\u71df\u696d\u4ee3\u8868) / Sales Manager (\u6279\u767c\u71df\u696d\u7d93\u7406)", "description": "\n\u8077\u8cac :\u92b7\u552e\u53ca\u63a8\u5ee3\u5404\u985e\u7a7a\u6c23\u6de8\u5316\u6bba\u83cc\u6a5f,\u7a7a\u6c23\u6de8\u5316\u6a5f,\u7a7a\u6c23\u8ca0\u58d3\u6a5f,\u958b\u95dc\u6bba\u83cc\u5668\u53ca\u5100\u8868\u5100\u5668\u7b49\u7522\u54c1, provding quality administrative service to our Clients\n\n\u8cc7\u6b77 :\u4e2d\u4e94\u7a0b\u5ea6; 2\u5e74\u7d93\u9a57; \u826f\u597d\u7cb5\u8a9e; \u4e00\u822c\u666e\u901a\u8a71; \u826f\u597d\u82f1\u8a9e; \u61c2\u8b80\u5beb\u4e2d\u6587; \u61c2\u8b80\u5beb\u82f1\u6587; \u5177\u8cac\u4efb\u5fc3, \u6e9d\u901a\u6280\u5de7, \u80fd\u7368\u7acb\u8655\u7406\u5de5\u4f5c, Team work,\u5177\u92b7\u552e\u91ab\u7642,\u8b77\u8001,\u6559\u80b2\u884c\u696d\u7b49\u7522\u54c1\u7d93\u9a57\u512a\u5148\n\n\u5f85\u9047 :\u6bcf\u6708$13,000 - $14,000, \u6709\u9280\u884c\u5047\u671f, \u7259\u79d1\u798f\u5229, \u91ab\u7642\u798f\u5229 \u53ca\u4f63\u91d1, \u661f\u671f\u4e00\u81f3\u4e94: \u4e0a\u53489\u6642\u81f3\u4e0b\u53486\u6642, \u6bcf\u9031\u5de5\u4f5c5\u5929\n\n\u7533\u8acb\u9808\u77e5 :\u6c42\u8077\u8005\u53ef\u96fb\u90f5(Apply Now)\u5c65\u6b77\u8868\u7d66\u7ff9\u9ad8\u570b\u969b\u767c\u5c55\u6709\u9650\u516c\u53f8\u3002\u5982\u8981\u7d22\u53d6\u6536\u96c6\u500b\u4eba\u8cc7\u6599\u8072\u660e, \u8acb\u8207\u7f85\u5c0f\u59d0(Email)\u806f\u7d61\u3002\n\n", "employment_types": ["Full Time", "Part Time", "Permanent"], "selling_points": ["Wholesales and Distribution", "5-day Work Week", "Base Salary + Attractive Commission"], "locations": ["Lai Chi Kok"], "categories": ["Sales, CS & Business Devpt", "Business Development", "Retail Sales", "Wholesale"], "post_time": "2022-01-17T04:59:44Z", "salary": {"currency": null, "max": null, "min": null, "period": "monthly", "term": null}, "salary_visible": false, "title_keywords": ["sales representative", "sales manager"], "responsibilities": ["quality"], "requirements": {"degrees": [], "majors": [], "languages": [], "language_level": [], "hard_skills": [], "soft_skills": [], "languages_combined": []}, "experience_required": {"duration": [], "field": []}}, {"job_id": "100003009053820", "location_code": "hk", "company": "Quko Int'l Development Limited", "job_title": "\u71df\u696d\u4ee3\u8868**", "description": "\n\u8077\u8cac :\u4e00\u822c\u71df\u696d\u4ee3\u8868\u5de5\u4f5c, \u92b7\u552e\u63a8\u5ee3\u7522\u54c1, \u96fb\u8a71\u63a8\u5ee3, \u4e00\u822c\u92b7\u552e\u53ca\u5e02\u5834\u63a8\u5ee3\u5de5\u4f5c (\u91ab\u7642\u7528\u54c1)\n\n\u8cc7\u6b77 :\u4e2d\u516d\u7a0b\u5ea6; \u4e00\u822c\u7cb5\u8a9e; \u4e00\u822c\u82f1\u8a9e; \u7565\u61c2\u8b80\u5beb\u4e2d\u6587; \u7565\u61c2\u8b80\u5beb\u82f1\u6587; \u61c2\u4e2d\u6587\u6253\u5b57\n\n\u5f85\u9047 :\u6bcf\u6708$11,000 - $14,000, \u6709\u96d9\u7ce7 \u53ca\u91ab\u7642\u798f\u5229, \u661f\u671f\u4e00\u81f3\u4e94: \u4e0a\u53489\u6642\u534a\u81f3\u4e0b\u53485\u6642\u534a, \u6bcf\u9031\u5de5\u4f5c5\u5929, \u6bcf\u5929\u5de5\u4f5c 8 \u5c0f\u6642\n\n\u7533\u8acb\u9808\u77e5 :\u6c42\u8077\u8005\u53ef\u96fb\u90f5(Apply Now)\u5c65\u6b77\u8868\u7d66\u767e\u7279\u9999\u6e2f\u6709\u9650\u516c\u53f8\u3002\u5982\u8981\u7d22\u53d6\u6536\u96c6\u500b\u4eba\u8cc7\u6599\u8072\u660e, \u8acb\u8207\u738b\u5148\u751f(Email)\u806f\u7d61\u3002\n\n", "employment_types": ["Full Time"], "selling_points": [], "locations": ["Kwun Tong"], "categories": ["Sales, CS & Business Devpt", "Wholesale", "Others", "Direct Sales"], "post_time": "2022-01-17T07:34:47Z", "salary": {"currency": null, "max": null, "min": null, "period": "monthly", "term": null}, "salary_visible": false, "title_keywords": ["\u71df\u696d\u4ee3\u8868"], "responsibilities": [], "requirements": {"degrees": [], "majors": [], "languages": [], "language_level": [], "hard_skills": [], "soft_skills": [], "languages_combined": []}, "experience_required": {"duration": [], "field": []}}, {"job_id": "100003009053715", "location_code": "hk", "company": "Biotek Ozone Hong Kong Limited", "job_title": "\u71df\u696d\u4ee3\u8868", "description": "\u5730\u5340 :\u00a0 \u00a0\u65fa\u89d2 / \u7063\u4ed4\n\u884c\u696d :\u00a0 \u00a0\u5bb6\u5c45\u6982\u5ff5\u96f6\u552e\u5e97\n\n\u8077\u8cac :\n-\u00a0 \u00a0\u8ca0\u8cac\u9580\u5e02\u92b7\u552e\uff0c\u8ca8\u54c1\u9673\u5217\n-\u00a0 \u00a0\u8a02\u55ae\u8ddf\u9032\uff0c\u63d0\u4f9b\u5c08\u696d\u610f\u898b\uff0c\u5354\u52a9\u5e97\u8216\u65e5\u5e38\u904b\u4f5c\n\n\u8981\u6c42:\n-\u00a0 \u00a0\u4e2d\u4e94\u4ee5\u4e0a\u7a0b\u5ea6\uff0c\u5099\u6709\u826f\u597d\u4e2d\u6587\u53ca\u7c21\u55ae\u82f1\u6587\n-\u00a0 \u00a0\u5177\u6709\u57fa\u672c\u96fb\u8166\u64cd\u4f5c\u77e5\u8b58\n-\u00a0 \u00a0\u6709\u8cac\u4efb\u611f\u3001\u5b88\u6642\u3001\u8aa0\u5be6\n\n\u5f85\u9047 :\n-\u00a0 \u00a0\u6bcf\u6708$14,000 - $18,000, \u6709\u4f63\u91d1 \u53ca\u5728\u8077\u57f9\u8a13,\n-\u00a0 \u00a0\u661f\u671f\u4e00\u81f3\u516d: \u4e0a\u53489\u6642\u534a\u81f3\u4e0b\u53487\u6642\u534a\uff0c\u661f\u671f\u65e5:\u4e0b\u53481\u6642\u81f3\u4e0b\u53486\u6642\u534a\uff0c\u6bcf\u9031\u5de5\u4f5c5\u5929\u534a\uff0c\u8f2a\u4f11\n\u6c42\u8077\u8005\u53ef\u96fb\u90f5\u5c65\u6b77\u8868\u7d66\u6216Whatsapp: 6826 7978\u8207\u674e\u5c0f\u59d0\u806f\u7d61", "employment_types": ["Full Time"], "selling_points": [], "locations": ["Lai Chi Kok"], "categories": ["Sales, CS & Business Devpt", "Wholesale", "Others", "Direct Sales"], "post_time": "2022-01-17T07:24:09Z", "salary": {"currency": null, "max": null, "min": null, "period": "monthly", "term": null}, "salary_visible": false, "title_keywords": ["\u71df\u696d\u4ee3\u8868"], "responsibilities": [], "requirements": {"degrees": [], "majors": [], "languages": [], "language_level": [], "hard_skills": [], "soft_skills": [], "languages_combined": []}, "experience_required": {"duration": [], "field": []}}, {"job_id": "100003009045669", "location_code": "hk", "company": "Regent Building Material Supplies Company Limited", "job_title": "\u92b7\u552e\u54e1/\u5e97\u52d9\u54e1  Shop Sales / Assisstant", "description": "What is your job about?\n\n\nManage day to day operation of e-commerce platform\nStrong sense of responsibility\nResponsible for sales reports and performance analysis\nResponsible for checking inventory transfer and sales order\nHandle ad hoc projects as assigned by supervisor\nWho will be our potential target?\n\n\nForm 5 or above\nMinimum 1 year relevant experience\nGood command of English and Chinese\nGood PC skills in MS Word, Excel, and PowerPoint\nCandidates with less experience will be considered as Senior Clerk\nImmediate available is highly preferred\n\nWe offer five days work week\u00a0and\u00a0attractive remuneration package to the right candidates. Interested parties please apply by clicking\u00a0\"Apply Now\"\u00a0with your resume, current and expected salary\n\n(Data collected will be used for recruitment purpose only.)\n\n\n", "employment_types": ["Full Time"], "selling_points": ["\u4e2d\u4e94\u7a0b\u5ea6; 1\u5e74\u7d93\u9a57", "\u8ca0\u8cac\u9580\u5e02\u92b7\u552e  \u8ca8\u54c1\u9673\u5217  \u8a02\u55ae\u8ddf\u9032", "\u6bcf\u6708$14,000 - $18,000"], "locations": ["Mong Kok"], "categories": ["Design", "Interior", "Sales, CS & Business Devpt", "Retail Sales", "Wholesale"], "post_time": "2022-01-17T02:20:28Z", "salary": {"currency": null, "max": null, "min": null, "period": "monthly", "term": null}, "salary_visible": false, "title_keywords": ["sales", "\u92b7\u552e\u54e1", "\u5e97\u52d9\u54e1"], "responsibilities": ["sales reports", "analysis", "inventory", "checking", "ad hoc projects", "e-commerce platform"], "requirements": {"degrees": ["form 5 or above"], "majors": [], "languages": ["english", "chinese"], "language_level": ["good command"], "hard_skills": ["excel", "e-commerce", "analysis", "powerpoint", "pc skills", "ms word"], "soft_skills": ["responsible", "sense of responsibility"], "languages_combined": [{"language": "english", "language_level": ["good command"]}, {"language": "chinese", "language_level": ["good command"]}]}, "experience_required": {"duration": ["minimum 1 year"], "field": ["relevant experience"]}}, {"job_id": "100003009054345", "location_code": "hk", "company": "Magazzin Group Limited", "job_title": "Senior Sales Administrative, Wholesale Operations (5 Days Work)", "description": "Assist in developing and managing the wholesale business of the brand in Hong Kong, Macau, Southeast Asia as well as searching for opportunities in China.\u00a0 Develop new accounts, sales channel and distribution networks.\u00a0 Identify market segment opportunities and drive business performance.\n\n\u00a0\n\n\nRequirements :\n\nUniversity Graduate;\n4-6 years relevant experience in prestigious consumer products;\nFluent in English and Chinese (including Mandarin);\nStrong connection with relevant luxury products groups;\nRelevant wholesale business network is essential;\nSolid B2B sales experience is preferable;\nHighly strategic mind-set, independent and self-motivated;\nExcellent communication skills with all levels (including senior) of clients;\nStrong business acumen and sense of accountability.\n\n\n\nWe offer excellent career prospects, competitive salary and fringe benefits to the right candidate.\u00a0 Please apply in strict confidence (quoting reference on the envelope) by sending personal resume together with current & expected salary and date available to : Assistant Group Personnel Manager, T.S.T. P.O. Box 98537, Kowloon or our e-mail address : career@ dickson.com.hk\n\n* All personal data collected will be used for recruitment purposes only.", "employment_types": ["Full Time", "Permanent"], "selling_points": ["Operations of E-Commerce Platform", "1 Year or Above Relevant Experience", "Immediate Available is Highly Preferred"], "locations": ["Yau Ma Tei"], "categories": ["Sales, CS & Business Devpt", "Wholesale", "E-commerce", "Business Development", "Sales Administration"], "post_time": "2022-01-17T09:13:27Z", "salary": {"currency": null, "max": null, "min": null, "period": "monthly", "term": null}, "salary_visible": false, "title_keywords": ["operations", "senior sales"], "responsibilities": ["communication", "developing", "develop"], "requirements": {"degrees": ["university graduate"], "majors": [], "languages": ["english", "chinese", "mandarin"], "language_level": ["fluent"], "hard_skills": ["acumen"], "soft_skills": ["communication skills", "self-motivated", "independent", "accountability", "business acumen"], "languages_combined": [{"language": "english", "language_level": ["fluent"]}, {"language": "chinese", "language_level": ["fluent"]}, {"language": "mandarin", "language_level": []}]}, "experience_required": {"duration": ["4-6 years"], "field": ["relevant experience"]}}, {"job_id": "100003009055672", "location_code": "hk", "company": "S.T. Dupont Marketing Limited \u90fd\u5f6d\u5e02\u5834\u63a8\u5ee3\u6709\u9650\u516c\u53f8", "job_title": "Senior Wholesale Executive / Assistant Wholesale Manager", "description": "Job Title: (Full time / Part time) Sales Representative / Sales Manager (\u9700\u8981\u884c\u8857)\n\nOur Brand\nCervo was founded in 1954 in the crafts shop of a hunting goods maker in a small Italian city. As generations passed, the Cervo brand branched out into the production of leather goods accessories and apparel. To this day, Cervo retains its artisan roots through a strong focus on high quality materials and superior craftsmanship. Merging utility with aesthetics, Cervo now offers products that seamlessly blend taste with casualness.\n\nResponsibilities\n- Explore new business opportunities with local or overseas distributors, trading partners and online channels, required to cold call & meet with clients\n- Perform sales and marketing duties at outdoor, able to visit new customers independently\n- Collect and report on market developments and market intelligence\n- Handle customers' inquiries, trouble shooting and marketing activities such as trade fairs and industry events\n\nRequirements\n- Form 5 or above\n- Minimum 3 years sales or business development experience in related discipline\n- Existing business networks with local or overseas\u00a0department stores\u00a0or\u00a0retail chain stores\u00a0/ existing business networks on\u00a0handbags,\u00a0shoes\u00a0and\u00a0accessories\u00a0to promote our brand is a\u00a0must\n- Good command of written and spoken Chinese and English\n- Independent, Self-motivated, Proactive,\u00a0Good communication and organization\n-\u00a0Candidates with sales experiences in other categories will also be considered\n- Higher education or more experience will be considered as Sales Manager\n- Immediate available is preferred\n\n\u00a0Offers\n- 5-day work week\n-\u00a0Flexible working hours for part-time position\n- Basic Salary + Attractive Commission\n-\u00a0Discretionary Bonus\n\nInterested parties please send your full resume and expected salary for application.\n\n\nPersonal data provided by job applicants will be used strictly in accordance with the employer's personal data policies and for recruitment purposes only.\u00a0", "employment_types": ["Full Time", "Permanent"], "selling_points": [], "locations": ["Yau Tsim Mong Area"], "categories": ["Sales, CS & Business Devpt", "Wholesale"], "post_time": "2022-01-18T02:50:41Z", "salary": {"currency": null, "max": null, "min": null, "period": null, "term": null}, "salary_visible": false, "title_keywords": ["executive", "manager", "assistant"], "responsibilities": ["online channels", "customers' inquiries", "explore new business opportunities", "report"], "requirements": {"degrees": ["form 5 or above"], "majors": [], "languages": ["english", "chinese"], "language_level": ["good command"], "hard_skills": ["basic"], "soft_skills": ["flexible", "self-motivated", "independent", "communication", "proactive"], "languages_combined": [{"language": "english", "language_level": ["good command"]}, {"language": "chinese", "language_level": ["good command"]}]}, "experience_required": {"duration": ["minimum 3 years"], "field": ["related", "business development", "education"]}}, {"job_id": "100003009054761", "location_code": "hk", "company": "Kangaroo Pet Nutrition Limited", "job_title": "SALES REPRESENTATIVE", "description": "Job Description:\n\nExecute company sales strategies and achieve sales target\nMaintain good business relationship with key accounts / existing clients\nDevelop and establish new accounts and capture profitable businesses from clients\nPromote various company products\nBuild up relationship with all related parties to ensure / sustain business growth\n\nJob Requirements:\n\nDegree holder with minimum 2 years sales experiences will be an advantage.\nFresh graduate from university with major in Science is also accepted.\nIndependent and initiative, result-oriented and customer focused\nOutgoing personality with effective communication and interpersonal skills\nGood command of written and spoken English\nAble to work under pressure\n\nWe offer attractive remuneration package, 5 days\u2019 work plus alternate Saturday, banking holidays, 12 days annual leave to the right candidate. Interested parties, please email your full resume with present & expected salary by clicking \"Apply Now\" button.", "employment_types": ["Full Time"], "selling_points": [], "locations": ["Tsuen Wan Area"], "categories": ["Sales, CS & Business Devpt", "Wholesale"], "post_time": "2022-01-17T16:21:08Z", "salary": {"currency": null, "max": null, "min": null, "period": "monthly", "term": null}, "salary_visible": false, "title_keywords": ["sales representative"], "responsibilities": ["sales target", "maintain", "develop"], "requirements": {"degrees": ["fresh graduate", "degree holder"], "majors": ["science"], "languages": ["english"], "language_level": ["good command"], "hard_skills": [], "soft_skills": ["outgoing personality", "independent", "focused", "communication and interpersonal skills", "initiative", "result-oriented", "work under pressure"], "languages_combined": [{"language": "english", "language_level": ["good command"]}]}, "experience_required": {"duration": ["minimum 2 years"], "field": []}}, {"job_id": "100003009050745", "location_code": "hk", "company": "Fung Heung Yuen Bakery Ltd", "job_title": "Sales & Marketing Executive", "description": "Responsibilities\n\nTo develop and execute Sales and Marketing plan such as Handling social media and online marketing platform; and establish strong relationship with assigned accounts\nTo promote bakery products, focus on frozen product & retail market\nTo handle customer enquiries and complaints in order to maintains operations\nWork closely with Accounting Department for outstanding payment issue\nAssist in other ad-hoc projects as assigned\n\nRequirements\n\nDiploma or above\u00a0in\u00a0Business Administration\u00a0or\u00a0related\u00a0disciplines\nMinimum 1-2 years\u00a0related experience\u00a0in sales field\nProactive with good communication skills and teamwork\nWell organized, self-motivated, positive, service-oriented, customer-focused, multitask and able to work independent\nImmediately available is preferred", "employment_types": ["Full Time"], "selling_points": ["Sales and marketing", "On-going career development", "5 days per week with Bank Holiday"], "locations": ["Kwai Hing"], "categories": ["Sales, CS & Business Devpt", "Wholesale"], "post_time": "2022-01-14T11:15:31Z", "salary": {"currency": null, "max": null, "min": null, "period": "monthly", "term": null}, "salary_visible": false, "title_keywords": ["sales & marketing executive"], "responsibilities": ["social media", "operations", "develop", "marketing plan", "payment", "ad-hoc projects", "customer enquiries and complaints"], "requirements": {"degrees": ["diploma or above"], "majors": ["related disciplines", "business administration"], "languages": [], "language_level": [], "hard_skills": [], "soft_skills": ["communication skills", "self-motivated", "customer-focused", "independent", "service-oriented", "teamwork", "well organized", "multitask", "proactive", "positive"], "languages_combined": []}, "experience_required": {"duration": ["minimum 1-2 years"], "field": ["related"]}}, {"job_id": "100003009054866", "location_code": "hk", "company": "Europe Group Holdings Ltd", "job_title": "Co-ordinator, Sales Administration", "description": "Responsibilities:\n\n\u00a0\u00a0\u00a0\u00a0\u00a0\u00a0\u00a0\u00a0 To communicate with wholesale brands on shipment, after-sales, sample, marketing, etc.\n\u00a0\u00a0\u00a0\u00a0\u00a0\u00a0\u00a0\u00a0 To assist sales manager on handling seasonal buy and executing marketing strategy\n\u00a0\u00a0\u00a0\u00a0\u00a0\u00a0\u00a0\u00a0 Responsible for daily clerical support includes data entry and invoice/document checking\n\u00a0\u00a0\u00a0\u00a0\u00a0\u00a0\u00a0\u00a0 To prepare regular Sales & Inventory Reports to Sales Team and Management\n\u00a0\u00a0\u00a0\u00a0\u00a0\u00a0\u00a0\u00a0 To follow up Goods receive, transfer and export in systems\n\u00a0\u00a0\u00a0\u00a0\u00a0\u00a0\u00a0\u00a0 To handle other admin doc assignments as required\n\nRequirements:\n\n\u00a0\u00a0\u00a0\u00a0\u00a0\u00a0\u00a0\u00a0 Degree or above;\n\u00a0\u00a0\u00a0\u00a0\u00a0\u00a0\u00a0\u00a0 Minimum 3 years\u2019 relevant working experience;\n\u00a0\u00a0\u00a0\u00a0\u00a0\u00a0\u00a0\u00a0 Proficiency in spoken in Chinese (including Cantonese and Mandarin) is a must;\n\u00a0\u00a0\u00a0\u00a0\u00a0\u00a0\u00a0\u00a0 Proficient computer knowledge in MS Office, Word, Excel, Power point & Chinese word processing\n\nInterested parties, please send your detailed resume with expected salary by clicking \"Apply Now\".\n\n\nData collected will be used for recruitment purpose only.", "employment_types": ["Full Time", "Permanent"], "selling_points": ["3 years\u2019 relevant working experience", "Proficiency in spoken in Chinese", "Travel to China if needed"], "locations": ["Tsim Sha Tsui"], "categories": ["Sales, CS & Business Devpt", "Wholesale", "Others", "Sales Administration"], "post_time": "2022-01-17T12:09:24Z", "salary": {"currency": null, "max": null, "min": null, "period": "monthly", "term": null}, "salary_visible": false, "title_keywords": ["sales"], "responsibilities": ["communicate with", "management", "data entry", "invoice", "inventory", "systems", "clerical support", "checking", "executing", "reports", "sales team"], "requirements": {"degrees": ["degree or above"], "majors": [], "languages": ["cantonese", "chinese", "mandarin"], "language_level": ["proficiency", "proficient"], "hard_skills": ["excel", "chinese word processing", "word", "power point", "ms office"], "soft_skills": [], "languages_combined": [{"language": "cantonese", "language_level": ["proficiency"]}, {"language": "chinese", "language_level": ["proficiency", "proficient"]}, {"language": "mandarin", "language_level": ["proficiency"]}]}, "experience_required": {"duration": ["minimum 3 years"], "field": ["relevant working experience"]}}, {"job_id": "100003009054499", "location_code": "hk", "company": "Cometai Enterprises Limited", "job_title": "Sales Coordinator/ Executive (Willing to travel)  \u73e0\u5bf6\u92b7\u552e\u54e1", "description": "Job description:\n\n1. Overseas road trip travel\u00a0\n2. Attend jewellery exhibitions, mainly USA, both local and abroad\n3. Prepare quotations and invoices, regarding orders\n4. Email and fax correspondence\n5. Customer liaison and support\n6. Promote and maintain client relationship\n\nRequirements:\n\n1. Holder of valid driving license is preferred; USA Visa holder is an advantage\n2. Overseas sales and marketing experience in Jewelery field is mostly welcomed\n3. Fair command in spoken English\n4. Fluent in Cantonese /Mandarin\n5. Should possess a reliable, independent, self-motivated and good communication personality\n6. Immediate available is preferred\n\n*Tertiary Education or fresh graduate will be also considered*\n\nWe offer 5-day work, attractive remuneration packages including sales commission, End-of-Year Bonus, Discretionary Bonus, Medical Coverage and Bank holidays to the right candidates.", "employment_types": ["Full Time"], "selling_points": [], "locations": ["Hung Hom"], "categories": ["Sales, CS & Business Devpt", "Business Development", "Account Servicing", "Wholesale"], "post_time": "2022-01-17T09:48:21Z", "salary": {"currency": null, "max": null, "min": null, "period": "monthly", "term": null}, "salary_visible": false, "title_keywords": ["sales coordinator", "executive"], "responsibilities": ["maintain", "invoices"], "requirements": {"degrees": ["fresh graduate"], "majors": [], "languages": ["cantonese", "english", "mandarin"], "language_level": ["fluent"], "hard_skills": [], "soft_skills": ["communication", "self-motivated", "reliable", "independent"], "languages_combined": [{"language": "cantonese", "language_level": ["fluent"]}, {"language": "english", "language_level": []}, {"language": "mandarin", "language_level": ["fluent"]}]}, "experience_required": {"duration": [], "field": ["marketing"]}}, {"job_id": "100003009051662", "location_code": "hk", "company": "Aim Plus International Limited", "job_title": "\u92b7\u552e\u4e3b\u4efb Sales Executive", "description": "\u4e3b\u8981\u5de5\u4f5c\u7bc4\u570d\uff1a\n\n\u5916\u51fa\u62dc\u8a2a\u5ba2\u6236\uff0c\u63a5\u6536\u53ca\u8655\u7406\u5ba2\u6236\u8a02\u55ae\n\u89e3\u7b54\u5ba2\u6236\u67e5\u8a62\uff0c\u5411\u5ba2\u6236\u4ecb\u7d39\u516c\u53f8\u7522\u54c1\n\u8207\u5ba2\u6236\u4fdd\u6301\u826f\u597d\u95dc\u4fc2\uff0c\u63a5\u89f8\u65b0\u5ba2\u6236\n\n\u8077\u4f4d\u8981\u6c42\uff1a\n\n\u4e2d\u5b78\u7562\u696d\uff0c\u5168\u65e5\u5236\u8a3c\u66f8\uff0c\u6587\u6191\u6216\u4ee5\u4e0a\u7a0b\u5ea6\n2\u5e74\u6216\u4ee5\u4e0a\u5de5\u4f5c\u7d93\u9a57\n\u5177\u5099\u96f6\u552e\u3001\u92b7\u552e\u6216\u5ba2\u6236\u670d\u52d9\u76f8\u95dc\u7d93\u9a57\u512a\u5148\n\u826f\u597d\u4eba\u969b\u95dc\u4fc2\u53ca\u6e9d\u901a\u80fd\u529b\n\u7565\u61c2\u82f1\u8a9e\uff0c\u6d41\u5229\u5ee3\u6771\u8a71\n\u5f85\u4eba\u89aa\u5207\u6709\u79ae\uff0c\u7d30\u5fc3\uff0c\u6709\u8cac\u4efb\u611f\n\u4e3b\u52d5\u7a4d\u6975\uff0c\u6709\u611b\u5fc3\uff0c\u601d\u60f3\u6b63\u9762\uff0c\u5177\u6709\u5718\u968a\u7cbe\u795e\n\u5927\u90e8\u4efd\u5de5\u4f5c\u6642\u9593\u9700\u5916\u51fa\u5de5\u4f5c\n\u559c\u6b61\u5c0f\u52d5\u7269\uff0c\u8c93\u54aa\u72d7\u72d7\uff0c\u5c0d\u5bf5\u7269\u76f8\u95dc\u884c\u696d\u4e0d\u6297\u62d2\n\n\u54e1\u5de5\u798f\u5229\uff1a\n\n5\u5929\u5de5\u4f5c\uff0c\u516c\u773e\u5047\u671f\n\u5728\u8077\u92b7\u552e\u6280\u5de7\u57f9\u8a13\n\u54e1\u5de5\u512a\u60e0\n\u984d\u5916\u71df\u696d\u734e\u91d1\n\u516c\u53f8\u7db2\u7ad9\uff1ahttps://www.aim-plus.com\n\u6709\u610f\u61c9\u5fb5\u4eba\u58eb\uff0c \u8acb\u628a\u500b\u4eba\u5c65\u6b77\u53ca\u85aa\u91d1\u8981\u6c42\u96fb\u90f5\u7d66\u6211\u5011\uff0c\u8b1d\u8b1d\u4f60\u7684\u67e5\u8a62\n\n(\u7533\u8acb\u4eba\u63d0\u4f9b\u4e4b\u5168\u90e8\u8cc7\u6599\u7d55\u5c0d\u4fdd\u5bc6\u53ca\u53ea\u4f5c\u62db\u8058\u7528\u9014)", "employment_types": ["Full Time"], "selling_points": [], "locations": ["Kwun Tong"], "categories": ["Sales, CS & Business Devpt", "Account Servicing", "Channel / Distribution", "Wholesale"], "post_time": "2022-01-16T21:50:35Z", "salary": {"currency": "HKD", "max": 24999, "min": 17000, "period": "monthly", "term": null}, "salary_visible": true, "title_keywords": ["sales executive"], "responsibilities": [], "requirements": {"degrees": [], "majors": [], "languages": [], "language_level": [], "hard_skills": ["plus"], "soft_skills": [], "languages_combined": []}, "experience_required": {"duration": [], "field": []}}, {"job_id": "100003009054048", "location_code": "hk", "company": "Kee Wah Group Limited", "job_title": "Sales Executive (Corporate)", "description": "Responsibilities\n\nMaintain close relationship with existing customers and explore further opportunities\nHandle the daily sales orders and communicate with the clients\nCollaborate with internal parties to deliver good and efficient customer services\nHandle ad hoc duties as assigned\n\nRequirements\n\nHigher Diploma or above in related disciplines\nMinimum of 3 years relevant experience; experience in FMCG industry is highly preferred\nStrong interpersonal and communication skill\nProficient in written and spoken English & Chinese\n\nPlease apply with detailed resume, stating current and expected salary, availability and quoting the Employer Reference Number.\n\n(Personal data\u00a0relating to employment applications will be used for recruitment only)", "employment_types": ["Full Time", "Permanent"], "selling_points": ["Excellent career development opportunity", "Leading brand and sizable company", "Competitive pay and benefits"], "locations": ["Lai Chi Kok"], "categories": ["Sales, CS & Business Devpt", "Business Development", "Account Servicing", "Wholesale"], "post_time": "2022-01-17T08:12:23Z", "salary": {"currency": null, "max": null, "min": null, "period": "monthly", "term": null}, "salary_visible": false, "title_keywords": ["sales executive"], "responsibilities": ["communicate with", "collaborate with", "ad hoc duties", "customer services", "maintain", "internal parties"], "requirements": {"degrees": ["higher diploma or above"], "majors": ["related disciplines"], "languages": ["english", "chinese"], "language_level": ["proficient"], "hard_skills": ["fmcg industry"], "soft_skills": ["communication skill", "interpersonal", "detailed"], "languages_combined": [{"language": "english", "language_level": ["proficient"]}, {"language": "chinese", "language_level": ["proficient"]}]}, "experience_required": {"duration": ["minimum of 3 years"], "field": ["fmcg", "relevant experience"]}}, {"job_id": "100003009052738", "location_code": "hk", "company": "ZS Technology HK Co., Limited", "job_title": "\u92b7\u552e\u6587\u54e1 (Sales Admin)", "description": "-\u00a0 \u8ca0\u8cac\u8207\u6bcd\u516c\u53f8\u5ba2\u6236\u5c0d\u63a5\uff0c\u5b8c\u6210\u92b7\u552e\u8a02\u55ae\u3002\u5305\u62ec\u4f46\u4e0d\u50c5\u9650\u65bc\u7533\u8acb\u92b7\u552e\u5408\u540c\u8a55\u5be9\uff0c\u64ec\u5b9a\u92b7\u552e\u5408\u540c/invoice/\u55ae\u64da\n\n-\u00a0 \u8ca0\u8cac\u5efa\u7acb\u516c\u53f8\u5ba2\u6236\u6a94\u6848\u3001\u5354\u52a9\u8655\u7406\u5ba2\u6236\u6295\u8a34\u7b49\uff0c\u6709\u6548\u670d\u52d9\u5ba2\u6236\u3002\n\n- \u8ca0\u8cac\u92b7\u552e\u696d\u52d9\u53ca\u696d\u52d9\u6a94\u6848\u7ba1\u7406\uff0c\u5305\u62ec\u4e0d\u50c5\u9650\u65bc\u5408\u540c\u3001\u767c\u7968\u3001\u92b7\u552e\u5408\u540c\u53f0\u8cec\u7b49\u6a94\u8cc7\u6599\u7684\u7ba1\u7406\u3001\u6b78\u985e\u3001\u6574\u7406\u3001\u5efa\u6a94\u548c\u4fdd\u7ba1\u3002\n\n- \u5354\u52a9\u516c\u53f8\u92b7\u552e\u696d\u52d9\u4eba\u54e1\u7533\u8acb\u92b7\u552e\u5408\u540c\u8a55\u5be9\u55ae\u3001\u64ec\u5b9a\u92b7\u552e\u5408\u540c\u3001\u55ae\u64da\uff0c\u5b8c\u6210\u5ba2\u6236\u76f8\u95dc\u696d\u52d9\u55ae\u64da\u7684\u7c3d\u8a02\uff0c\u5354\u52a9\u92b7\u552e\u5b8c\u6210\u92b7\u552e\u53ca\u975e\u92b7\u552e\u767c\u8ca8\u3002\u5b89\u6392\u9000\u8ca8\u7b49\u65e5\u5e38\u92b7\u552e\u5de5\u4f5c\u3002\n\n-\u00a0 \u5354\u52a9\u516c\u53f8\u7c4c\u5099\u5c55\u89bd\u5e76\u53c3\u52a0\u570b\u5167\u5916\u5c55\u89bd", "employment_types": ["Full Time", "Permanent"], "selling_points": ["\u4e94\u5929\u5de5\u4f5c", "\u91ab\u7642\u4fdd\u96aa", "\u5e74\u5047"], "locations": ["Hung Hom"], "categories": ["Sales, CS & Business Devpt", "Wholesale", "Sales Administration"], "post_time": "2022-01-17T04:05:06Z", "salary": {"currency": null, "max": null, "min": null, "period": "monthly", "term": null}, "salary_visible": false, "title_keywords": ["admin", "sales"], "responsibilities": ["invoice"], "requirements": {"degrees": [], "majors": [], "languages": [], "language_level": [], "hard_skills": [], "soft_skills": [], "languages_combined": []}, "experience_required": {"duration": [], "field": []}}, {"job_id": "100003009054204", "location_code": "hk", "company": "Hellolulu Living Solutions Limited", "job_title": "Sales Coordinator (Sales Operation Based)", "description": "Job Responsibilities\n\nHandle daily sales orders and invoices, including Retail, Wholesale and Online channels\nPrepare regular weekly / monthly sales related report for team and management review\nProvide sales support to the sales team and coordinate with internal departments\nHandle customer enquiries regarding general sales issues product information or complaints\nManage stock return and exchange policy\nPerform ad-hoc tasks as required\n\nJob Requirements\n\nForm 5 or above, with 1-2 years of solid working experience in retail industry\nResponsible, good working attitude and communication skills\u00a0\nAble to manage multiple tasks and work independently\nProficiency in MS Office including PivotTable and VLOOKUP\nExperience in sales-oriented, order &amp; invoice processing is preferable\nImmediately availability is highly preferred\n\nWe offer 5-days work week and attractive remuneration package to right candidate. Interested parties please send detailed resume with expected salary and availability by clicking \"Apply Now\" to submit your application.\n\nOnly shortlisted candidates will be notified. Applicants who are not contacted within\u00a04 weeks may consider their applications unsuccessful.\u00a0All personal data collected will be treated in strict confidence and be used for recruitment purpose only.\n\nHellolulu Living Solution Limited is an equal opportunities employer.", "employment_types": ["Full Time", "Permanent"], "selling_points": ["Minimum 2 years of relevant working experience", "5-days work week", "Immediately availability is preferred"], "locations": ["Wong Tai Sin Area"], "categories": ["Sales, CS & Business Devpt", "Customer Service - Supervisor / Officer", "Wholesale", "Sales Administration"], "post_time": "2022-01-17T08:49:39Z", "salary": {"currency": null, "max": null, "min": null, "period": "monthly", "term": null}, "salary_visible": false, "title_keywords": ["sales coordinator", "sales"], "responsibilities": ["online channels", "handle customer enquiries", "invoices", "ad-hoc tasks", "coordinate with", "sales team", "management review", "report"], "requirements": {"degrees": ["form 5 or above"], "majors": [], "languages": [], "language_level": [], "hard_skills": ["vlookup", "processing", "ms office"], "soft_skills": ["communication skills", "good working attitude", "work independently", "responsible", "multiple tasks"], "languages_combined": []}, "experience_required": {"duration": ["1-2 years"], "field": ["retail industry"]}}, {"job_id": "100003009023458", "location_code": "hk", "company": "NewPower Worldwide Limited", "job_title": "Sales Account Manager", "description": "Job Overview\n\nThe Sales Account Manager is a critical member of the NewPower Worldwide Sales team and is responsible for driving revenue growth with new and existing customers. As a Sales Account Executive, your focus is to increase sales and contribute to our long-term business growth.\n\nJob Roles & Responsibilities\n\nIdentify and secure new sales opportunities through cold calling\nThoroughly qualify every opportunity such as identifying customer pain points, recognizing buy signals, and understanding the decision-making process\nServe as the primary person-in-charge for all day-to-day customer account management matters\nBuild, maintain, create strong relationships with new and existing customers\nProactively call assigned accounts to solicit new business\nEnsure the entire sales process is done with a high level of urgency and accuracy to exceed customer needs/expectations: RFQ, quote, order processing, and fulfillment\nAccurately document and update prospecting activity and new sales opportunities in our propriety CRM\nDrive and track weekly, monthly, and quarterly performance and sales metrics\n\nJob Requirement(s)\n\nMinimum a Diploma in any discipline\nPrevious sales experience in an extremely fast-paced, competitive sales environment highly preferred\nPrefer someone with at least 2-3 years of similar work experience in an Electronics Wholesale Distribution industry.\nSome experience in handling B2B sales preferred\nCandidates with little/zero experience will be considered for executive role.", "employment_types": ["Full Time", "Permanent"], "selling_points": ["Attractive Commission Remuneration", "Good Career Growth and Progression", "Friendly and Positive Work Environment"], "locations": ["Kwai Fong"], "categories": ["Sales, CS & Business Devpt", "Business Development", "Account Servicing", "Wholesale"], "post_time": "2022-01-17T01:43:05Z", "salary": {"currency": null, "max": null, "min": null, "period": "monthly", "term": null}, "salary_visible": false, "title_keywords": ["account manager", "sales"], "responsibilities": ["management", "maintain", "order processing", "fulfillment"], "requirements": {"degrees": ["diploma"], "majors": [], "languages": [], "language_level": [], "hard_skills": [], "soft_skills": [], "languages_combined": []}, "experience_required": {"duration": ["at least 2-3 years"], "field": []}}, {"job_id": "100003009052279", "location_code": "hk", "company": "Trinity Universal Limited", "job_title": "KEY ACCOUNTS EXECUTIVE", "description": "Key Responsibilities:\n\n\nKey customer account maintenance in HK and Greater China markets\nMaking offers, concluding orders and servicing post order management with customers including collections.\nIssue Sales related documents: Invoices, debit note, credit note etc.\nGaining product Knowledge\u00a0on the job to service customers effectively in coordination with Manager and team.\nGathering market information, trends, etc. and share with the team regularly\nWork closely with internal departments to ensure excellent results\n\nRequirements:\n\n\nBachelors degree or equivalent in any discipline.\u00a0\n2 years and above of work experience in customer account management.\nThose with lesser qualification/experience can be considered for junior positions.\nWillingness to travel as & when required (when safe travel resumes)\nTeam player, excellent interpersonal and communication skills\nFluent in Mandarin and Cantonese; Basic communication skills in English\nPositive, motivated, willingness to learn and result-oriented\nProficient PC and MS Excel skills\nFor the right candidate, the above requirements will not be a limiting factor.\u00a0\n\n\n\nWhat to expect:\n\n\nAn exciting work environment and career path\nA lively bunch of colleagues\nGreat work-life balance\n5 day work\nMedical , Life and Travel Insurance\nMinimum annual leave of 10 days increasing progressively with years of service\nAny personal data collected will be for recruitment purposes only.", "employment_types": ["Full Time", "Permanent"], "selling_points": ["Bachelors degree or equivalent", "Key accounts management, 5 day work week", "Medical Insurance, excellent growth opportunities"], "locations": ["Siu Sai Wan"], "categories": ["Sales, CS & Business Devpt", "Account Servicing", "Sales - Sales Management", "Wholesale"], "post_time": "2022-01-17T02:38:32Z", "salary": {"currency": null, "max": null, "min": null, "period": "monthly", "term": null}, "salary_visible": false, "title_keywords": ["executive"], "responsibilities": ["order management", "market information", "invoices", "related documents", "coordination with", "account maintenance"], "requirements": {"degrees": ["degree"], "majors": [], "languages": ["cantonese", "english", "mandarin"], "language_level": ["basic", "fluent"], "hard_skills": ["basic", "safe", "ms excel", "factor", "pc"], "soft_skills": ["result-oriented", "communication skills", "motivated", "team player", "interpersonal", "positive"], "languages_combined": [{"language": "cantonese", "language_level": ["fluent"]}, {"language": "english", "language_level": ["basic"]}, {"language": "mandarin", "language_level": ["fluent"]}]}, "experience_required": {"duration": ["2 years"], "field": ["account management"]}}, {"job_id": "100003009051866", "location_code": "hk", "company": "Ferrarini Pacific Limited", "job_title": "Sales Coordinator (Food)", "description": "Responsibilities:\n\nSupport the sales team\nAssist sales team on daily operation\nHandle the promotion event\nProcess the orders\nIssue the invoices\nKeep sales records\nWork closely with the warehouse\u00a0\nInventory calculation\nMaintain strong customer relationships\n\nRequirements:\n\nHigher Diploma or Degree with major in Sales & Marketing/ Hotel & Catering/ Economic related subjects\nPrefer 2 years or above related working experience\u00a0\nGood Team player and able to handle multi- tasks\u00a0\nExcellent communication and organizational skills\nProficient in spoken and written English and Chinese\nImmediate available is preferred\u00a0\u00a0\n\nWe offer attractive Salary & Commissions scheme to the right candidates.\u00a0Interested parties please click \"Apply Now\" button and email your full resume with availability, present and expected salary to us.\n\nInformation provided will be treated in strict confidence and used exclusively for recruitment and selection purposes. Applicants may be considered for other suitable vacancies within the company.", "employment_types": ["Full Time", "Permanent"], "selling_points": ["Support the sales team and handle promotion", "2 years customer service experience", "Process and keep the orders"], "locations": ["Tsuen Wan Area"], "categories": ["Sales, CS & Business Devpt", "Business Development", "Hospitality / F & B", "Food & Beverage", "Wholesale"], "post_time": "2022-01-17T01:42:31Z", "salary": {"currency": null, "max": null, "min": null, "period": "monthly", "term": null}, "salary_visible": false, "title_keywords": ["sales coordinator"], "responsibilities": ["invoices", "inventory", "daily operation", "maintain", "sales team"], "requirements": {"degrees": ["diploma", "degree"], "majors": ["hotel", "marketing"], "languages": ["english", "chinese"], "language_level": ["proficient"], "hard_skills": [], "soft_skills": ["communication", "organizational skills", "good team player"], "languages_combined": [{"language": "english", "language_level": ["proficient"]}, {"language": "chinese", "language_level": ["proficient"]}]}, "experience_required": {"duration": ["2 years"], "field": ["related"]}}, {"job_id": "100003009052268", "location_code": "hk", "company": "Trinity Universal Limited", "job_title": "KEY ACCOUNTS EXECUTIVE - JAPAN MARKET", "description": "Key Responsibilities:\n\n\nCustomer account maintenance in Japan Market.\nMaking offers, concluding orders and servicing post order management with customers including collections.\nIssue Sales related documents: Invoices, debit note, credit note etc.\nGaining product Knowledge\u00a0on the job to service customers effectively in coordination with Manager and team.\nBusiness development in Japan Market to expand Customer base.\nGathering market information, trends, etc. and share with the team regularly\nWork closely with internal departments to ensure excellent results\n\nRequirements:\n\n\nBachelors degree or equivalent in any discipline.\u00a0\n2 years and above of work experience in account management.\nThose with lesser qualification/experience but with language skills can be considered for junior positions.\nWillingness to travel as & when required (when safe travel resumes)\nTeam player, excellent interpersonal and communication skills\nGood grasp of Japanese language in both written and spoken is a must. You will be interacting with the team members primarily in English & Cantonese.\nPositive, motivated, willingness to learn and result-oriented\nProficient PC and MS Excel skills\nFor the right candidate, the above requirements will not be a limiting factor.\u00a0\n\n\n\nWhat to expect:\n\n\nAn exciting work environment and career path\nA lively bunch of colleagues\nGreat work-life balance\n5 day work\nMedical , Life and Travel Insurance\nMinimum annual leave of 10 days increasing progressively with years of service\nAny personal data collected will be for recruitment purposes only.", "employment_types": ["Full Time", "Permanent"], "selling_points": ["Bachelors degree or equivalent Japanese Language", "Key accounts management, Japan Market,", "Medical, Insurance, excellent growth opportunities"], "locations": ["Siu Sai Wan"], "categories": ["Sales, CS & Business Devpt", "Business Development", "Sales - Sales Management", "Wholesale"], "post_time": "2022-01-17T02:37:16Z", "salary": {"currency": null, "max": null, "min": null, "period": "monthly", "term": null}, "salary_visible": false, "title_keywords": ["executive"], "responsibilities": ["order management", "market information", "invoices", "related documents", "coordination with", "account maintenance"], "requirements": {"degrees": ["degree"], "majors": [], "languages": ["cantonese", "japanese", "english"], "language_level": ["good"], "hard_skills": ["pc", "safe", "ms excel", "factor"], "soft_skills": ["result-oriented", "communication skills", "motivated", "team player", "interpersonal", "positive"], "languages_combined": [{"language": "cantonese", "language_level": []}, {"language": "japanese", "language_level": ["good"]}, {"language": "english", "language_level": []}]}, "experience_required": {"duration": ["2 years"], "field": ["account management"]}}, {"job_id": "100003009054111", "location_code": "hk", "company": "Young Living Hong Kong Limited", "job_title": "\u5ba2\u6236\u670d\u52d9\u4e3b\u4efb Customer Service Officer (\u4e00\u81f3\u4e94\u5de5\u4f5c)", "description": "\u8077\u8cac:\n\n\u5728\u5ba2\u670d\u4e2d\u5fc3\u63d0\u4f9b\u5ba2\u6236\u670d\u52d9\n\u5354\u52a9\u9867\u5ba2\u4e0b\u55ae, \u6536\u6b3e\u548c\u53d6\u8ca8\n\u5354\u52a9\u7dad\u6301\u9867\u5ba2\u670d\u52d9\u90e8\u904b\u4f5c\n\n\u9700\u6c42:\n\n\u5177\u76f8\u95dc\u5de5\u4f5c\u7d93\u9a57, \u4ea6\u6b61\u8fce\u61c9\u5c46\u7562\u696d\u751f\n\u8f03\u5c11\u7d93\u9a57\u8005\u6703\u88ab\u8996\u70ba\u5ba2\u6236\u670d\u52d9\u52a9\u7406\n\u826f\u597d\u4e2d\u82f1\u6e9d\u901a\u6280\u5de7\n\u61c2\u96fb\u8166\u64cd\u4f5c\u548c\u4e2d\u82f1\u6587\u66f8\u8655\u7406\n\n\u00a0\u798f\u5229:\n\n\u91ab\u7642\u53ca\u7259\u79d1\u4fdd\u96aa\n\u751f\u65e5\u5047\n\u52e4\u5de5\u734e\n\u5e74\u7d42\u734e\u91d1\n\u514d\u8cbb\u516c\u53f8\u7522\u54c1\n\nInterested candidate please submit your application with detailed resume and\u00a0Expected Salary\u00a0by clicking \"Apply now\" button.\u00a0Only short-listed candidates will be notified.\u00a0 All personal data will be kept in strict confidence and only be used for recruitment purpose.", "employment_types": ["Full Time", "Permanent"], "selling_points": ["\u6b61\u8fce\u61c9\u5c46\u7562\u696d\u751f", "\u4e94\u5929\u5de5\u4f5c (\u4e00\u81f3\u4e94\u5de5\u4f5c)", "\u751f\u65e5\u5047, \u52e4\u5de5\u734e, \u5e74\u7d42\u734e\u91d1, \u91ab\u7642\u53ca\u7259\u79d1\u4fdd\u96aa"], "locations": ["Causeway Bay"], "categories": ["Sales, CS & Business Devpt", "Customer Service - Supervisor / Officer", "Retail Sales", "Wholesale"], "post_time": "2022-01-17T08:25:29Z", "salary": {"currency": null, "max": null, "min": null, "period": "monthly", "term": null}, "salary_visible": false, "title_keywords": ["\u5ba2\u6236\u670d\u52d9\u4e3b\u4efb", "customer service officer"], "responsibilities": ["personal data", "recruitment"], "requirements": {"degrees": [], "majors": [], "languages": [], "language_level": [], "hard_skills": [], "soft_skills": ["confidence", "detailed"], "languages_combined": []}, "experience_required": {"duration": [], "field": []}}, {"job_id": "100003009052846", "location_code": "hk", "company": "Chase Jewellery Manufactory Limited", "job_title": "Sales and Marketing Executive", "description": "Sales and Marketing Executive\n\n- Develop and maintain client relationships\n- Organize and attend Jewellery Shows, both in Hong Kong and overseas\n- Collaborate with sales team to develop effective sales strategies\n- Conduct quotations and invoices\n\nRequirement:\n- At least 1 year of sales and marketing experience\n- Basic knowledge of jewellery products\n- Proficient in English writing and speaking\n- Independent, ambitious, can work under pressure\n- Proficient in PC and MS Office applications\n- Attractive remuneration package with 5-days work week, year-end bonus, commission upon reaching sales target\n\n\u92b7\u552e\u53ca\u71df\u92b7\n\n- \u7dad\u7e6b\u5ba2\u6236\u95dc\u4fc2\u548c\u64f4\u5c55\u92b7\u552e\u7248\u5716\n- \u7c4c\u5099\u4e26\u51fa\u5e2d\u9999\u6e2f\u53ca\u6d77\u5916\u73e0\u5bf6\u5c55\u89bd\n- \u8207\u92b7\u552e\u90e8\u540c\u4e8b\u5408\u4f5c\uff0c\u898f\u5283\u4e26\u767c\u5c55\u6709\u6548\u7684\u92b7\u552e\u7b56\u7565\n- \u6839\u64da\u7522\u54c1\u50f9\u683c\u5411\u5ba2\u6236\u767c\u55ae\u4e26\u8ddf\u9032\u00a0\n\n\u8981\u6c42\uff1a\n- \u6700\u5c111\u5e74\u6216\u4ee5\u4e0a\u92b7\u552e\u53ca\u71df\u92b7\u7d93\u9a57\n- \u57fa\u672c\u73e0\u5bf6\u7522\u54c1\u77e5\u8b58\n- \u6d41\u5229\u7684\u82f1\u6587\u8b80\u5beb\u53ca\u5c0d\u8a71\n- \u7368\u7acb\u3001\u6709\u4e0a\u9032\u5fc3\u3001\u5728\u9ad8\u58d3\u74b0\u5883\u4e0b\u4ecd\u7136\u4fdd\u6301\u5de5\u4f5c\u6c34\u6e96\n- \u719f\u6089\u96fb\u8166\u53ca MS Office \u57fa\u672c\u4f7f\u7528\u77e5\u8b58\u53ca\u6280\u80fd\n- \u512a\u8d8a\u5f85\u9047\uff0c5\u5929\u5de5\u4f5c\u5929\u3001\u5e74\u7d42\u82b1\u7d05\u3001\u96a8\u8868\u73fe\u767c\u653e\u4f63\u91d1\uff08\u53ef\u9762\u8ac7\uff09", "employment_types": ["Full Time"], "selling_points": [], "locations": ["Hung Hom"], "categories": ["Marketing / Public Relations", "Marketing - Brand / Product Management", "Sales, CS & Business Devpt", "Wholesale", "E-commerce", "Business Development"], "post_time": "2022-01-17T04:16:26Z", "salary": {"currency": "HKD", "max": 19999, "min": 14000, "period": "monthly", "term": null}, "salary_visible": true, "title_keywords": ["sales and marketing executive"], "responsibilities": ["collaborate with", "year-end", "invoices", "sales target", "develop", "maintain", "sales team", "work under pressure"], "requirements": {"degrees": [], "majors": [], "languages": ["english"], "language_level": ["proficient"], "hard_skills": ["pc", "basic", "ms office"], "soft_skills": ["independent", "work under pressure"], "languages_combined": [{"language": "english", "language_level": ["proficient"]}]}, "experience_required": {"duration": ["at least 1 year"], "field": ["marketing"]}}, {"job_id": "100003009055070", "location_code": "hk", "company": "A.S. Watson Retail (HK) Limited", "job_title": "Procurement Officer - Retail Store Equipment", "description": "Come and join a Winning Team\n\nWe are Awesome!\n\nWhy Should You Join Us?\n\nAt ASW, we believe in our people, teamwork, and the importance of your personal growth.\u00a0If you are looking for the opportunity to join our award-winning international family with 15,000+ stores across 25 markets in Asia and Europe, the ASW family welcomes you\u2026\u00a0 #BePartofMORE\n\nYou can enjoy:\n\n\nComprehensive Medical and Life insurance coverage, including your spouse and children!\nProfessional training and career advancement opportunities!\nAttractive ACCA and CPA Australia Recognized Employee Partnership for F&A talents!\nExclusive company pension schemes!\u00a0 Marriage, Maternity, and Paternity Leave!\nConvenient office location, less than 5 min. walk from MTR!\nContemporary workplace, free drinks, and chill-out areas!\u00a0 Onsite Clinic and Lactation Room!\nWell-equipped Gym inside our office building, plus fitness and interest class packages!\nFree round-trip lunchtime shuttle bus services to Shatin!\nExclusive shopping discount, Bazaar Sales for our people only!\u00a0\n\nA typical day in this Role:\u00a0\n\n\nSupport in Project implementation including preparing and conducting tenders for special category (but not limited to), system deployment, improving process, developing KPI, driving for tender savings.\nPerform data collection, mining and database development.\nAssist the team to develop/execute savings plan according to the assigned target\nManage the relationship between suppliers and users, and provide supports to enhance suppliers management system\nMonitoring procurement project progress\nDevelop sourcing plan and monitoring market tracking index, to identify drivers to the commodity prices\nAble to communicate with all the related stakeholders\n\nThis job is a good fit for You if:\u00a0\n\nYou have\u00a0experience in managing the tender process\u00a0\nYou have\u00a0good communication and coordination skills and team working spirit\nYou enjoy working with Multi-cultural team & regional team\nWhat we look for:\n\n\nDegree/Diploma holder in Business Administration, Procurement, Supply Chain or related discipline\nAt least 2-3 years\u2019 Procurement or Supply Chain experience, with MNCs or China working experience is highly preferred.\nWith Project Management skillset and able to develop Project Performance Metrics/ Reports\nHands-on e-tender system utilization preferable\nFamiliar with tender process and general purchase contract terms and conditions\nStrong analytical skills with commercial sense and proactive attitude\nInterpersonal and negotiation skills is essential\nExcellent computer proficiency including excel, PowerPoint and access\nGood spoken and written English and Chinese.\nSome travel is required\u00a0\n\nWhat is holding you back?\u00a0\n\nDon\u2019t miss out on this great chance to shape Your life!\u00a0\n\nApply now!\n\nInterested parties please e-mail your full resume in WORD FORMAT with expected salary to our company email (shown in our Company Profile).\nWe are an equal opportunity employer and welcome applications from all qualified candidates. The information provided will be treated in strict confidence and be used only for consideration of your application for relevant / similar posts within the A.S. Watson Group.\nApplicants not hearing from us within 6 weeks from the date of advertisement may consider their applications unsuccessful. All personal data of unsuccessful applicants will be destroyed within 12 months from the date of application.\u00a0", "employment_types": ["Full Time", "Permanent"], "selling_points": ["Prepare tender process", "Identify effective & reliable sourcing strategies", "Enjoy working with Multi-cultural team & regional"], "locations": ["Shatin Area"], "categories": ["Transportation & Logistics", "Supply Chain", "Merchandising & Purchasing", "Procurement / Purchasing / Sourcing", "Sales, CS & Business Devpt", "Wholesale"], "post_time": "2022-01-18T01:09:27Z", "salary": {"currency": null, "max": null, "min": null, "period": "monthly", "term": null}, "salary_visible": false, "title_keywords": ["procurement officer"], "responsibilities": ["communication", "purchase", "database", "plan", "administration", "implementation", "developing", "develop", "project progress", "reports", "tender", "management", "monitoring", "data collection", "tracking", "communicate with", "performance metrics", "project management", "coordination", "insurance"], "requirements": {"degrees": ["diploma holder", "degree"], "majors": ["business administration"], "languages": ["english", "chinese"], "language_level": ["good"], "hard_skills": ["excel", "acca", "plus", "powerpoint", "analytical skills", "chill", "cpa", "project management", "deployment"], "soft_skills": ["coordination skills", "enjoy working", "teamwork", "analytical skills", "communication", "project management", "hands-on", "comprehensive", "negotiation skills", "team working", "proactive", "interpersonal"], "languages_combined": [{"language": "english", "language_level": ["good"]}, {"language": "chinese", "language_level": ["good"]}]}, "experience_required": {"duration": ["at least 2-3 years"], "field": ["supply chain", "procurement"]}}, {"job_id": "100003009052252", "location_code": "hk", "company": "ALF Retail Hong Kong Limited", "job_title": "Buying Assistant \u2013 Womenswear & Lingerie (Brand: Marks and Spencer)", "description": "Reporting to the Buyer, the incumbent will be responsible for:\n\nProviding clerical and administrative support to the buying team in an effective and timely manner\nRegular data entries and data maintenance in SAP & UK IRP systems\u00a0\nAssisting in the preparation/collation of weekly management reports\nSeasonal catalogue maintenance\nManaging stock allocation to all retail stores and price maintenance\nHandling administrative duties and responsible for ad hoc projects independently as required\nJob Requirements:\nSecondary educated with a minimum of 1 year working experience\nProficient in both Windows and MS Excel\nAttentive to details, good numerical sense and organisational skills\nSelf-driven, energetic, well-organised and able to play as a good team-player\nFast learner with positive working attitude\nExcellent communication, interpersonal and presentation skills\nSAP experience is an added advantage\nIf you are interested in this role, please send your full resume together with your current and expected salary to us.\u00a0\n\n\n\nApply by\u00a0clicking \"Apply Now\"\n\nThe Human Resources Department: Unit 1806B-10, 18/F, Exchange Tower, 33 Wang Chiu Road, Kowloon Bay, Kowloon, Hong Kong\n\nPersonal information received from applicants will be kept confidential and used for employment-related purposes only.", "employment_types": ["Full Time", "Permanent"], "selling_points": ["Secondary educated or fresh graduates", "Providing clerical and administrative support", "Proficient in both Windows and MS Excel"], "locations": ["Kowloon Bay"], "categories": ["Admin & HR", "Clerical / Admin Staff", "Merchandising & Purchasing", "Textiles", "Sales, CS & Business Devpt", "Wholesale"], "post_time": "2022-01-17T02:34:40Z", "salary": {"currency": null, "max": null, "min": null, "period": "monthly", "term": null}, "salary_visible": false, "title_keywords": ["buying assistant"], "responsibilities": ["reporting", "maintenance", "data", "administrative support", "stock allocation", "systems", "communication", "management reports", "administrative duties", "ad hoc projects", "price maintenance", "catalogue"], "requirements": {"degrees": [], "majors": [], "languages": [], "language_level": [], "hard_skills": ["sap", "maintenance", "management reports", "ms excel", "exchange"], "soft_skills": ["independently", "attentive to details", "responsible", "team-player", "interpersonal", "timely", "interested in", "communication", "positive working attitude", "presentation skills", "organisational skills", "well-organised", "energetic", "fast learner", "driven"], "languages_combined": []}, "experience_required": {"duration": ["minimum of 1 year"], "field": []}}, {"job_id": "100003009055559", "location_code": "hk", "company": "Chandler Macleod Group (HK) Limited", "job_title": "Merchandising Assistant (Luxury, 18K)", "description": "Responsibilities\n\n\nUpdate daily / weekly / monthly sales report and analyze the market trend.\nFollow up with Asia Pacific markets stock request and arrange stock rebalancing.\nSupport the team in developing catalogues and selling tools.\nSupport the after sales services for Asia Pacific.\nProvide extensive day-to-day operational and administrative supports\nHandle other ad hoc, miscellaneous tasks and projects related to the business.\n\nRequirement\n\n\nTertiary education in Business Management, Fashion Merchandising, or related discipline.\n1 year working experience in buying & merchandising\nGood interpersonal skill, detail-oriented, willing to learn and able to work under pressure.\nGood command of spoken and written English, Cantonese and Mandarin.\nProficient in MS Office, Excel (pivot table, vlookup, etc.) and PowerPoint.\nImmediate availability preferred", "employment_types": ["Full Time", "Permanent"], "selling_points": ["Market Leader in Retail Sector", "Genuine Development Opportunity", "A Growing Business"], "locations": ["Quarry Bay"], "categories": ["Sales, CS & Business Devpt", "Retail Sales", "Wholesale", "Sales Administration"], "post_time": "2022-01-18T02:43:16Z", "salary": {"currency": null, "max": null, "min": null, "period": "monthly", "term": null}, "salary_visible": false, "title_keywords": ["merchandising assistant"], "responsibilities": ["ad hoc", "monthly sales report", "support the team", "developing"], "requirements": {"degrees": [], "majors": [], "languages": ["cantonese", "english", "mandarin"], "language_level": ["good command"], "hard_skills": ["business management", "excel", "pivot table", "powerpoint", "vlookup", "ms office"], "soft_skills": ["detail-oriented", "work under pressure", "willing to learn", "interpersonal skill"], "languages_combined": [{"language": "cantonese", "language_level": ["good command"]}, {"language": "english", "language_level": ["good command"]}, {"language": "mandarin", "language_level": ["good command"]}]}, "experience_required": {"duration": ["1 year"], "field": ["merchandising"]}}, {"job_id": "100003009055644", "location_code": "hk", "company": "Michael Page", "job_title": "Regional Business Development Manager - Consumer Tech Products", "description": "A brand new opportunity has arisen for a regional sales candidate to join a international consumer tech company with a dynamic start-up culture!\n\nClient Details\n\nOur client is a consumer tech and ecommerce startup with multiple business areas. They are now recruiting a regional business development manager to join their consumer tech unit to help them grow their presence around the world!\n\nDescription\n\nThis role is a dynamic business development and key account management role. The coverage will be global with their key markets currently being USA, Greater China, Japan and Australia. You will be identifying new opportunities in the market, strategizing go-to-market plans and developing new distributors and partners to continue to grow different channels including retail and ecommerce. You will also be responsible for managing existing distributors and partners to grow the relationship and support them on sales activities and to ensure targets and objectives are met. You will work with teammates across different offices including China and Philippines. This is a hands-on role and requires someone with strong entrepreneurial spirit.\n\nProfile\n\nYou must have at least 3 years of experience in a regional distributor management role. You must have an entrepreneurial personality and commercial mindset. You must be organized, analytical, number sensitive and has a strong attention to detail. English is required for this position and any additional Asian language such as Mandarin or Japanese is preferred but not required.\n\nJob Offer\n\nThe company is offering a great company culture, a dynamic workstyle and an attractive salary package and bonus.\n\nTo apply online please click the Apply button below. For a confidential discussion about this role please contact Cherie Tam on +852 3412 4854", "employment_types": ["Full Time", "Permanent"], "selling_points": ["Hong Kong based, global coverage", "Distributor Management", "Dynamic Culture"], "locations": ["Not Specified"], "categories": ["Sales, CS & Business Devpt", "Business Development", "Account Servicing", "Wholesale"], "post_time": "2022-01-18T02:49:37Z", "salary": {"currency": null, "max": null, "min": null, "period": "monthly", "term": null}, "salary_visible": false, "title_keywords": ["business development manager"], "responsibilities": ["sales activities", "management", "developing", "contact", "plans"], "requirements": {"degrees": [], "majors": [], "languages": ["japanese", "english", "mandarin"], "language_level": [], "hard_skills": ["go", "dynamic"], "soft_skills": ["organized", "responsible", "hands-on", "dynamic", "attention to detail", "sensitive"], "languages_combined": [{"language": "japanese", "language_level": []}, {"language": "english", "language_level": []}, {"language": "mandarin", "language_level": []}]}, "experience_required": {"duration": ["at least 3 years"], "field": ["management"]}}, {"job_id": "100003009052093", "location_code": "hk", "company": "DKSH Hong Kong Limited", "job_title": "Key Account Executive, FMCG", "description": "Job Responsibilities:\n\nAssist Key Account Manager\u00a0on managing the assigned key accounts\nPlan and execute trade promotion and sales activities to achieve sales target\nConducting sales promotion analysis, sales performance, revenue and margin analysis\nAssist in planning & forecast, as well as other ad-hoc projects\n\nJob Requirements:\n\nAssociate Degree / Higher Diploma or above in Business Studies,\u00a0Marketing\u00a0or related disciplines\nA minimum of\u00a01-2 years experience with knowledge of key account management / key channels structure\nExperinece in\u00a0\"Buyer\" or \"Category\" of FMCG is definite an asset\nResult oriented, data sensitive and strong analytical skills\nGood Communication and presentation skills\n\nWorking location: Wong Chuk Hang\nWe offer performance bonus and attractive benefits including medical insurance and company shuttle bus services to the right candidate. Interested parties please apply in full resume with current and expected salaries to Human Resources Department , DKSH Hong Kong Limited, 23rd Floor, Tower A, Southmark, 11 Yip Hing Street, Wong Chuk Hang, Hong Kong or by clicking \"Apply Now\"\n\nAll personal data collected will be used for recruitment purposes only. Candidates will be contacted within 2 weeks if the background and experience are closely relevant to the job requirement.\n\nDrive Growth. Be the Difference. Join DKSH.\n\nDKSH\u2019s strength lies in our great diversity of services, industries, clients, products, regions and employees from various nationalities. We are proud of our people: they are the reason we are successful. Our people are the best in the industry. They are passionate about their career growth and about business success. They work as part of an energetic and committed team, positively impacting millions of lives through the products and services we provide.\n\nJoin us today if you are ready to \u201cDrive growth. Be the Difference.\u201d With DKSH, you will experience a world of learning and development, own your career and take business responsibility and have a positive impact that touches people\u2019s lives.", "employment_types": ["Full Time", "Permanent"], "selling_points": ["Conducting sales analysis", "FMCG Buyer or Category experience", "Good Communication and presentation skills"], "locations": ["Aberdeen"], "categories": ["Sales, CS & Business Devpt", "Retail Sales", "Wholesale", "Sales Administration"], "post_time": "2022-01-17T02:04:48Z", "salary": {"currency": null, "max": null, "min": null, "period": "monthly", "term": null}, "salary_visible": false, "title_keywords": ["key account executive"], "responsibilities": ["sales activities", "sales performance", "sales target", "analysis", "plan", "forecast", "ad-hoc projects", "planning"], "requirements": {"degrees": ["associate degree", "higher diploma or above"], "majors": ["related disciplines", "business", "marketing"], "languages": [], "language_level": [], "hard_skills": ["analytical skills"], "soft_skills": ["analytical skills", "communication", "result oriented", "presentation skills", "sensitive"], "languages_combined": []}, "experience_required": {"duration": ["minimum of 1-2 years"], "field": ["account management"]}}, {"job_id": "100003009051940", "location_code": "hk", "company": "Neo Derm (HK) Ltd", "job_title": "Bioderma - \u5c08\u6ac3\u7f8e\u5bb9\u9867\u554f", "description": "\u5de5\u4f5c\u5167\u5bb9\uff1a\n\n\u5411\u5ba2\u4eba\u63a8\u4ecb\u5408\u9069Bioderma\u8b77\u819a\u7522\u54c1\n\u4e86\u89e3\u5ba2\u4eba\u9700\u8981\u4e26\u63d0\u4f9b\u5c08\u696d\u8b77\u819a\u5efa\u8b70\uff0c\u89e3\u7b54\u5ba2\u4eba\u67e5\u8a62\n\u8207\u5ba2\u4eba\u5efa\u7acb\u4e26\u4fdd\u6301\u826f\u597d\u95dc\u4fc2\n\u8655\u7406\u5e97\u8216\u65e5\u5e38\u904b\u4f5c\u4e8b\u52d9\n\n\u5165\u8077\u8981\u6c42\uff1a\n\n1\u5e74\u6216\u4ee5\u4e0a\u96f6\u552e\u92b7\u552e\u7d93\u9a57 (\u8b77\u819a\u54c1\u92b7\u552e\u7d93\u9a57\u512a\u5148\u8003\u616e)\n\u5c0dBioderma\u54c1\u724c\u53ca\u7522\u54c1\u5177\u57fa\u672c\u8a8d\u8b58\u53ca\u71b1\u8aa0\n\u826f\u597d\u9867\u5ba2\u670d\u52d9\u53ca\u92b7\u552e\u6280\u5de7\n*\u53ef\u5373\u6642\u4e0a\u73ed\u512a\u5148\u8003\u616e*\n\n\u798f\u5229\u53ca\u5f85\u9047\uff1a\n\n*\u8a2d\u6709\u5305\u85aa\u5b89\u6392*\n*\u5c08\u696d\u5c0e\u5e2b\u63d0\u4f9b\u5168\u9762\u5165\u8077\u7522\u54c1\u53ca\u8b77\u819a\u77e5\u8b58\u57f9\u8a13*\n\u826f\u597d\u85aa\u91d1\uff0c\u4f63\u91d1\u53ca\u5e97\u8216\u9054\u6a19\u734e\u91d1\n\u826f\u597d\u6649\u5347\u6a5f\u6703\n\u5e74\u504712\u65e5\u8d77\uff0c\u751f\u65e5\u5047\n\u516c\u53f8\u7522\u54c1\u53ca\u7642\u7a0b\u512a\u60e0\n\u5e74\u7d42\u82b1\u7d05\n\u65b0\u589e\u75ab\u82d7\u5047\u671f\n\n\u8acb\u6309\u00a0APPLY NOW\u7533\u8acb\u6216WHATSAPP 97287360 (\u4eba\u529b\u8cc7\u6e90\u90e8) \u7533\u8acb\u8077\u4f4d\nWHATSAPP\u8acb\u63d0\u4f9b\u5c65\u6b77\u8868\u53ca\u8fd1\u71671\u5f35\n(\u7533\u8acb\u8cc7\u6599\u53ea\u4f5c\u62db\u8058\u7528\u9014\uff0c\u4e26\u7d55\u5c0d\u4fdd\u5bc6)", "employment_types": ["Full Time"], "selling_points": ["\u5411\u5ba2\u4eba\u63a8\u4ecb\u5408\u9069Bioderma\u8b77\u819a\u7522\u54c1", "\u4e86\u89e3\u5ba2\u4eba\u9700\u8981\u4e26\u63d0\u4f9b\u5c08\u696d\u8b77\u819a\u5efa\u8b70\uff0c\u89e3\u7b54\u5ba2\u4eba\u67e5\u8a62", "1\u5e74\u6216\u4ee5\u4e0a\u96f6\u552e\u92b7\u552e\u7d93\u9a57"], "locations": ["Causeway Bay"], "categories": ["Beauty Care / Health", "Others", "Sales, CS & Business Devpt", "Retail Sales", "Wholesale"], "post_time": "2022-01-17T01:34:05Z", "salary": {"currency": null, "max": null, "min": null, "period": "monthly", "term": null}, "salary_visible": false, "title_keywords": [], "responsibilities": [], "requirements": {"degrees": [], "majors": [], "languages": [], "language_level": [], "hard_skills": [], "soft_skills": [], "languages_combined": []}, "experience_required": {"duration": [], "field": []}}, {"job_id": "100003009049895", "location_code": "hk", "company": "Daniel & Co", "job_title": "Sales Executive", "description": "The job:\n\nWorking with Key Account Manager to formulate sales strategies to ensure meeting business objectives\nPlan and execute Department Store/CVS promotion and sales activities to achieve sales target\nMaintain business relationship with customers\nOutdoor work and assist promotion set up is required\nWork closely with key account buyers, supply chains and internal parties for sales order processing, inquiries and coordination\nSales analysis with market intelligence to develop right sales strategies for pricing, distribution, product range and promotion\nTrack business forecast performance and plan to achieve forecasting accuracy to maintain key brand levels\nManage the annual trade terms with chain accounts to maximize profit\nAssist in new channel development to expand the market share\n\nThe person:\n\nF.5 or above\nExperience in FMCG key account management relevant experience\nStrong analytical, interpersonal and communication skills\nAble to work under pressure, independent with tight schedule\nGood command of both written and spoken English and Chinese\nProficient in MS Word, Excel, PowerPoint & Chinese word processing\nImmediately available is highly preferred\nCandidate with less experience will be considered as Sales Assistant", "employment_types": ["Full Time", "Permanent"], "selling_points": ["Experience in FMCG key account management", "Plan and execute Department Store/CVS promotion", "Track business forecast performance"], "locations": ["Kwai Tsing Area"], "categories": ["Sales, CS & Business Devpt", "Business Development", "Sales - Sales Management", "Wholesale"], "post_time": "2022-01-14T09:24:58Z", "salary": {"currency": null, "max": null, "min": null, "period": "monthly", "term": null}, "salary_visible": false, "title_keywords": ["sales executive"], "responsibilities": ["sales activities", "outdoor work", "sales target", "analysis", "develop", "maintain", "plan", "coordination", "sales order processing", "forecast", "forecasting", "internal parties"], "requirements": {"degrees": [], "majors": [], "languages": ["english", "chinese"], "language_level": ["good command", "proficient"], "hard_skills": ["excel", "chinese word processing", "powerpoint", "ms word"], "soft_skills": ["communication skills", "independent", "interpersonal", "work under pressure"], "languages_combined": [{"language": "english", "language_level": ["good command"]}, {"language": "chinese", "language_level": ["good command", "proficient"]}]}, "experience_required": {"duration": [], "field": ["management", "fmcg key account", "relevant experience"]}}, {"job_id": "100003009050013", "location_code": "hk", "company": "Mani Limited", "job_title": "SENIOR SALES MANAGER/ SALES MANAGER", "description": "Responsibilities:\n\n\nDevelop and implement sales distribution plans, explore and prospect new business opportunities to expand existing customer list and generate new revenue.\nMaximize business turnover and product placement in market place.\nLead & motivate teammates to achieve preset sales objectives by providing direction, coaching and training.\nPlan, organize, and manage sales channel & distribution strategies for key accounts.\nManage P&L of assigned product categories to achieve business targets.\nLiaise and maintain\u00a0executive level relationships with new accounts and existing customers/ business partners.\nProvide professional new products/ projects presentation to key account customers.\nCoordinate closely with internal departments to meet delivery schedule and quality sales services.\nFormulate and review products pricing, product features enhancement and optimization.\n\nRequirements:\n\nUniversity graduate in Business Administration / Marketing or related disciplines.\nOver 6 years\u2019 experience in sales field with at least 3 years at management level.\u00a0 Experience in consumer products preferred.\nSound connection with local retailing network.\nProactive with strong sales technique and be aggressive to achieve sales targets.\nExcellent presentation, communication and interpersonal skills.\nExcellent command in both English and Chinese.\nProficient in MS office applications.\n\nWe offer 5-day work, attractive remuneration package and a challenging environment for professionals with immediate availability. Interested parties please send email with current and expected salary for application.\n\n\nFor more information about our company, please visit our facebook :\u00a0https://www.facebook.com/tclubfanshk/", "employment_types": ["Full Time", "Permanent"], "selling_points": [], "locations": ["Lai Chi Kok"], "categories": ["Sales, CS & Business Devpt", "Channel / Distribution", "Wholesale", "Direct Sales"], "post_time": "2022-01-14T09:37:50Z", "salary": {"currency": null, "max": null, "min": null, "period": "monthly", "term": null}, "salary_visible": false, "title_keywords": ["senior sales manager", "sales manager"], "responsibilities": ["product categories", "liaise", "business opportunities", "review", "quality", "p&l", "develop", "coordinate", "delivery schedule", "maintain", "plan", "providing direction", "plans"], "requirements": {"degrees": ["university graduate"], "majors": ["related disciplines", "marketing", "business administration"], "languages": ["english", "chinese"], "language_level": ["excellent"], "hard_skills": ["ms office"], "soft_skills": ["proactive", "presentation", "communication and interpersonal skills"], "languages_combined": [{"language": "english", "language_level": ["excellent"]}, {"language": "chinese", "language_level": ["excellent"]}]}, "experience_required": {"duration": ["6 years", "at least 3 years"], "field": ["management"]}}, {"job_id": "100003009052932", "location_code": "hk", "company": "Flora Floriculture Limited", "job_title": "Assist Sales Manager (Florist Brand)", "description": "Job Highlights\nPromoting poducts (flowers & gifts) and services\nImproving sales amount\nCommission with basic salary\nJob Description\n\nJob Duties\n\n*\u00a0Present, promote and sell products(flowers & gifts) and services to existing and prospective customers\n\n*\u00a0Ensure high levels of customer satisfaction through excellent sales service\n\n* Establish, develop and maintain positive business and customer relationships\n\n* Improve sales\n\nWork location: Sheung Wan\n\nFull-time working hours: 09:00-18:00 (Mon \u2013 Fri)\n\nJob Requirements\n\n* F.5 graduate or above\n\n* Good communication and interpersonal skills\n\n* Smart and responsible, able to work independently and proactively\n\n* 2 years sales experience / Fresh graduates from local universities\u00a0\n\nBasic salary: $15000 - $20000 + attractive commission (*basic salary depends on experience)\nLocation: Sheung Wan\n\nAll personal data collected will be used for recruitment purpose only will be treated in accordance with our Personal Data Policy, which is available immediately upon request.", "employment_types": ["Full Time"], "selling_points": [], "locations": ["Sheung Wan"], "categories": ["Sales, CS & Business Devpt", "Wholesale"], "post_time": "2022-01-17T04:34:52Z", "salary": {"currency": "HKD", "max": 34999, "min": 14000, "period": "monthly", "term": null}, "salary_visible": true, "title_keywords": ["sales manager"], "responsibilities": ["maintain", "develop"], "requirements": {"degrees": [], "majors": [], "languages": [], "language_level": [], "hard_skills": [], "soft_skills": [], "languages_combined": []}, "experience_required": {"duration": [], "field": []}}, {"job_id": "100003009050223", "location_code": "hk", "company": "Heng Lee Pearl Company Limited", "job_title": "Sales Manager / Assistant Sales Manager", "description": "Job Highlights\n\nImmediate availability is highly preferred\nKnowledgeable on Jewellery business expansion\n\nSales Manager / Assistant Sales Manager\n\nThe role is responsible to maximize sales in the international region, who leads the sales team to develop new & existing business and maintain key relationships with related parties ( in line with company core value, market specification & insights)\n\nJob Duties:\n\nDevelop new potential customers\nHas a proven track record of Sales & Business development in jewellery fields\nAchieve sales target through developing & exploring the online potential customers, trade fairs & business trips or tools\nContribute to define the sales target plan, budget plan & evaluating the actual vs future requirements of the global market\nWork closely with related parties on Product development and production arrangements\nExperience in silver & K-gold business is preferred\nTake part in exhibition, business trips\nWilling to travel to China factory\n\nRequirements:\n\nDiploma or above with at least 5 years jewellery sales working experience\nGood communications skills in verbal and written Chinese , English & Mandarin\nKnowledgeable on jewellery products and can handle product development projects would be an advantage\nGood Multi-task & time management & able to work under pressure\nProficient in MS office, MS Excel & word processing\nAgile, aggressive, result-oriented, data driven with strong interpersonal and communication skills\n\nOffice location: TST Area\n\n\u00a0Interested parties, please send full resume, last and expected salary to APPY NOW", "employment_types": ["Full Time", "Permanent"], "selling_points": [], "locations": ["Tsim Sha Tsui"], "categories": ["Sales, CS & Business Devpt", "Business Development", "Wholesale"], "post_time": "2022-01-14T09:58:04Z", "salary": {"currency": null, "max": null, "min": null, "period": "monthly", "term": null}, "salary_visible": false, "title_keywords": ["assistant sales manager", "sales manager"], "responsibilities": ["sales target", "budget", "developing", "develop", "plan"], "requirements": {"degrees": ["diploma or above"], "majors": [], "languages": ["english", "chinese", "mandarin"], "language_level": ["good"], "hard_skills": ["ms excel", "word processing", "agile", "ms office"], "soft_skills": ["communication skills", "multi-task", "agile", "interpersonal", "driven", "time management", "result-oriented", "work under pressure"], "languages_combined": [{"language": "english", "language_level": ["good"]}, {"language": "chinese", "language_level": ["good"]}, {"language": "mandarin", "language_level": ["good"]}]}, "experience_required": {"duration": ["at least 5 years"], "field": []}}, {"job_id": "100003009056342", "location_code": "hk", "company": "RecruitFirst Limited", "job_title": "\u7f8e\u570b\u77e5\u540d\u54c1\u724c\u552e\u8ca8\u54e1 - \u624b\u888b/\u6642\u88dd Sales (5\u5929\u5de5\u4f5c/\u96d9\u7ce7/\u516c\u8846\u5047\u671f/$20K+)", "description": "\u8077\u8cac:\n\n\u7a4d\u6975\u63a8\u4ecb\u7522\u54c1\u4ee5\u9054\u81f3\u5e97\u8216\u92b7\u552e\u76ee\u6a19\n\u4e86\u89e3\u9867\u5ba2\u9700\u6c42\uff0c\u5354\u52a9\u914d\u642d\u53ca\u9078\u8cfc\u7522\u54c1\n\u63d0\u4f9b\u4e00\u5c0d\u4e00\u5ba2\u6236\u670d\u52d9\uff0c\u5efa\u7acb\u53ca\u7dad\u7e6b\u826f\u597d\u9867\u5ba2\u95dc\u4fc2\n\u57f7\u884c\u5e97\u8216\u65e5\u5e38\u5546\u54c1\u53ca\u9053\u5177\u7684\u8996\u89ba\u9673\u5217\u5de5\u4f5c\n\u8981\u6c42 :\n\n\u4e00\u5e74\u6642\u5c1a\u54c1\u724c\u96f6\u552e\u7d93\u9a57 (\u5962\u4f88\u54c1\u724c\u66f4\u4f73)\n\u826f\u597d\u7cb5\u8a9e\u3001\u4e00\u822c\u82f1\u8a9e\u53ca\u666e\u901a\u8a71\n\u71b1\u8aa0\u4e3b\u52d5\u3001\u826f\u597d\u6e9d\u901a\u6280\u5de7\n\u80fd\u5373\u4f7f\u4e0a\u73ed\u8005\u512a\u5148\u8003\u616e\n\n\u54e1\u5de5\u798f\u5229:\n\n\u6bcf\u54685\u5929\u5de5\u4f5c\n17\u5929\u516c\u8846\u5047\u671f\n12-17\u5929\u6709\u85aa\u5e74\u5047\n\u8c50\u539a\u4f63\u91d1\u3001\u96d9\u7ce7\n\u826f\u597d\u91ab\u7642\u53ca\u7259\u79d1\u798f\u5229\n\u5b8c\u5584\u5de5\u4f5c\u57f9\u8a13\u53ca\u6649\u5347\u968e\u68af\n\u54e1\u5de5\u8cfc\u7269\u512a\u60e0\n\n\u6709\u610f\u61c9\u5fb5\u8005\u8acb\u7acb\u5373\u6309\u7533\u8acb(Apply Now)\n\n\u5982\u6709\u4efb\u4f55\u7591\u554f\uff0c\u6b61\u8fce\u806f\u7d61Hailey Chan 3702 3826\u67e5\u8a62\u3002", "employment_types": ["Full Time"], "selling_points": [], "locations": ["Not Specified"], "categories": ["Sales, CS & Business Devpt", "Retail Sales", "Wholesale", "Direct Sales"], "post_time": "2022-01-18T04:01:42Z", "salary": {"currency": null, "max": null, "min": null, "period": "monthly", "term": null}, "salary_visible": false, "title_keywords": ["sales"], "responsibilities": [], "requirements": {"degrees": [], "majors": [], "languages": [], "language_level": [], "hard_skills": [], "soft_skills": [], "languages_combined": []}, "experience_required": {"duration": [], "field": []}}, {"job_id": "100003009055342", "location_code": "hk", "company": "WilliamSelect", "job_title": "Travel Retail Assistant Manager / Senior Sales Executive (Beauty)", "description": "My client is an International Luxury Beauty Group. They are looking for a high caliber to join their team.\n\n\nJob Description\n\nSupport travel retail account management in the region\nForecast net sales and estimated projected gross sales\nPrepare and review sales analysis, sales budgets, sales plans, monthly reports.\nBuild product assortment and review marketing plan\nEnsure optimal stock and manage stock replenishment\nReview retailer's expected forecast\u00a0\nManage invoice and POs, support order confirmation procedures\u00a0\n\nJob Requirements\n\nDegree holder in business or relevant discipline\nMinimum 5 year of experience in beauty / travel retail industry\nDetail-oriented with strong analytical skills.\nFluent in both English and Chinese\nStrong skill set in Excel (Vlookup and Pivot Table)", "employment_types": ["Full Time"], "selling_points": ["International Luxury Beauty Group", "Travel Retail Account Management", "Strong Data Analysis skills and TR experience"], "locations": ["Not Specified"], "categories": ["Sales, CS & Business Devpt", "Business Development", "Account Servicing", "Wholesale"], "post_time": "2022-01-18T02:14:34Z", "salary": {"currency": "HKD", "max": 44999, "min": 30000, "period": "monthly", "term": null}, "salary_visible": true, "title_keywords": ["assistant manager", "senior sales executive"], "responsibilities": ["budgets", "management", "stock replenishment", "monthly reports", "invoice", "analysis", "review", "procedures", "marketing plan", "sales plans", "forecast"], "requirements": {"degrees": ["degree holder"], "majors": ["business"], "languages": ["english", "chinese"], "language_level": ["fluent"], "hard_skills": ["excel", "vlookup", "pivot table", "analytical skills"], "soft_skills": ["analytical skills", "detail-oriented"], "languages_combined": [{"language": "english", "language_level": ["fluent"]}, {"language": "chinese", "language_level": ["fluent"]}]}, "experience_required": {"duration": ["minimum 5 year"], "field": ["retail industry", "beauty"]}}, {"job_id": "100003009046811", "location_code": "hk", "company": "\u540c\u767c\u98df\u54c1\u6709\u9650\u516c\u53f8", "job_title": "Sales Manager (Chilled / Frozen food)", "description": "Job Description:\n\nFormulate and implement sales & marketing plans and strategies, explore new business opportunities, identifies the need for new sales prospects.\nExcel in achieving sales and GP targets.\nDevelop, maintain, and strengthen business relationships with customers and provide professional sales service.\nGain an understanding of customer base, competition, pricing, and other market variables to drive the business performance.\nLead and drive the overall development direction for the direct sales team to generate profitable sales to maximize sales achievements, profitability, and growth.\nDesign and manage business plans to expand company\u2019s client base and ensure its strong presence.\nManage sales forecasting and budgets, setting and achieving targets.\n\n\u00a0Requirements:\n\nDegree holder in Business, Marketing, or other related disciplines.\nMinimum 5 years sales experience, highly prefer candidate with frozen or chilled meat background.\nGood supervisory experience with excellent problem-solving communication skills.\nSound market knowledge with strong analytical skills and business acumen.\nExcellent communication skills with the ability to develop long-term relationships are essential.\nConfident, aggressive, positive & self-motivated; able to work independently and under pressure.\nGood command of written and spoken English and Chinese, Mandarin is required.\nProficiency in MS Office.\n\nWorking Location\uff1aTsuen Wan\n\nWe offer:\n\nMedical and dental insurance;\nAnnual body check;\nBirthday leave;\nBaby full moon celebration leave;\nMarriage and compassionate leave;\nPerformance bonus;\nEducation allowance;\nFree shuttle bus service;\nFree breakfast, snacks and drinks.\n\nInterested candidates\u00a0please click \"Apply Now\" which including your application and resume including present and expected salary and date available.\n\n(Applicants not invited for interviews within 2 months may assume their applications unsuccessful. Information provided will be treated with strict confidence, used and retained for recruitment purposes only for 2 years.)", "employment_types": ["Full Time", "Permanent"], "selling_points": ["Chilled / Frozen food", "Minimum 5 years sales experience", "highly prefer candidate with frozen or chilled mea"], "locations": ["Tsuen Wan Area"], "categories": ["Sales, CS & Business Devpt", "Wholesale", "Direct Sales"], "post_time": "2022-01-14T01:16:30Z", "salary": {"currency": null, "max": null, "min": null, "period": "monthly", "term": null}, "salary_visible": false, "title_keywords": ["sales manager"], "responsibilities": ["budgets", "explore new business opportunities", "marketing plans", "design", "develop", "business plans", "maintain", "sales team", "client base", "forecasting"], "requirements": {"degrees": ["degree holder"], "majors": ["related disciplines", "business", "marketing"], "languages": ["english", "chinese", "mandarin"], "language_level": ["good command"], "hard_skills": ["problem-solving", "acumen", "analytical skills", "wan", "ms office"], "soft_skills": ["confident", "communication skills", "self-motivated", "work independently", "under pressure", "problem-solving", "analytical skills", "business acumen", "positive"], "languages_combined": [{"language": "english", "language_level": ["good command"]}, {"language": "chinese", "language_level": ["good command"]}, {"language": "mandarin", "language_level": ["good command"]}]}, "experience_required": {"duration": ["minimum 5 years"], "field": ["supervisory experience"]}}, {"job_id": "100003009046714", "location_code": "hk", "company": "Julius Chen & Company (HK) Limited", "job_title": "Pharma Sales Representatives", "description": "Sales Careers\n\nWe take pride in helping our employees to build a career for themselves by giving opportunities to learn, perform and grow.\n\nWe also provide a training and attractive rewards to encourage our employees working with full dedication and moving to a higher advancement.\n\nNow, we are on a constant hunt for the talented and enthusiastic professional as follow:\n\nPrivate Clinics Sales Representatives.\nDrugstores/ Pharmacies Sales Representatives.\n\nIf you are an experienced sales professional in the same field or a new beginner who wishes to enter pharmaceutical industry. Please drop-in your full resume at : APPLY NOW", "employment_types": ["Full Time"], "selling_points": [], "locations": ["Not Specified"], "categories": ["Medical Services", "Pharmaceutical", "Sales, CS & Business Devpt", "Wholesale"], "post_time": "2022-01-13T22:52:47Z", "salary": {"currency": null, "max": null, "min": null, "period": "monthly", "term": null}, "salary_visible": false, "title_keywords": ["pharma sales representatives"], "responsibilities": [], "requirements": {"degrees": [], "majors": [], "languages": [], "language_level": [], "hard_skills": [], "soft_skills": ["enthusiastic"], "languages_combined": []}, "experience_required": {"duration": [], "field": []}}, {"job_id": "100003009043156", "location_code": "hk", "company": "YKK Hong Kong Limited", "job_title": "Sales & Marketing Executive", "description": "Job Descriptions:\n\nHandle customers' enquiries, provide product information;\nFollow customers' developments and provide advices;\nNegotiate price with customers and follow up sales orders;\nArrange vendor/customer-visit and build up relationship;\nPromote new products to vendors/customers;\nPrepare sales reports, analysis and sales forecast;\nAssist managers in various kinds of sales-related programs and meet sales targets;\n\nBusiness trip to is required, especially China / other Asian countries;\nAssist in ad hoc duties as assigned, i.e. market research, survey, etc.\n\nJob Requirements:\n\nTertiary education or above\u00a0with 1 - 2 years working experience in sales, manufacturing, garment or merchandising industry is preferred; knowledge in snap and button will be a plus;\u00a0FRESH graduate will also be considered;\nGood command of spoken and written English & Chinese (Cantonese and Mandarin);\nWell versed with PC applications like MS Word, Excel, PowerPoint & Chinese Word Processing,\u00a0proficiency in Excel Function (i.e. v-lookup, pivot table) is preferable;\nCustomer-oriented, teamwork spirit and outgoing characters are preferred;\nCandidates with less/more experience may be considered as Associate/Senior Sales & Marketing Executive respectively.\n\nBenefits:\n\n5-day work\u00a0(staggered working hours)\nDouble pay\nDiscretionary bonus\nGroup medical\nOT pay\nStatutory Annual Leave with extra\u00a07 days Company Annual Leave\nStatutory Holiday and Other General Holiday\nOther Special Leave i.e. Marriage Leave, etc.\n\nWe offer competitive remuneration and benefits, holidays, stable working environment to the right candidates. Interested parties please click \"Apply Now\" and send your full resume with expected salary in MS Word Format to us (Please quote Position Name & Reference No.)\n\n*All personal data collected will be kept strictly confidential and used for recruitment-related purpose only.", "employment_types": ["Full Time", "Permanent"], "selling_points": ["customer-visit, promote products, handle enquiries", "1 - 2 years exp.,Good command of English & Chinese", "5-day, 13-mth, discretionary bonus, extra leave"], "locations": ["Tsim Sha Tsui"], "categories": ["Manufacturing", "Garment / Textile", "Sales, CS & Business Devpt", "Account Servicing", "Wholesale"], "post_time": "2022-01-13T18:54:52Z", "salary": {"currency": null, "max": null, "min": null, "period": "monthly", "term": null}, "salary_visible": false, "title_keywords": ["sales & marketing executive"], "responsibilities": ["ad hoc duties", "provide advices", "analysis", "prepare sales", "market research", "assist managers", "reports", "business trip", "forecast"], "requirements": {"degrees": ["fresh graduate"], "majors": [], "languages": ["cantonese", "english", "chinese", "mandarin"], "language_level": ["proficiency", "good command"], "hard_skills": ["excel", "plus", "chinese word processing", "pivot table", "powerpoint", "pc applications", "ms word"], "soft_skills": ["outgoing", "customer-oriented", "teamwork spirit"], "languages_combined": [{"language": "cantonese", "language_level": ["good command"]}, {"language": "english", "language_level": ["good command"]}, {"language": "chinese", "language_level": ["proficiency", "good command"]}, {"language": "mandarin", "language_level": ["good command"]}]}, "experience_required": {"duration": ["1 - 2 years"], "field": ["garment", "manufacturing", "merchandising", "education", "marketing"]}}, {"job_id": "100003009050224", "location_code": "hk", "company": "Calzedonia Hong Kong Limited", "job_title": "Sales Assistant \u92b7\u552e\u52a9\u7406 (\u6bcf\u9031\u5169\u5929\u4f11\u5047) / \u670d\u88dd\u92b7\u552e", "description": "Calzedonia \u96c6\u5718\u662f\u4e00\u9593\u6642\u88dd\u96f6\u552e\u516c\u53f8\uff0c\u5c08\u9580\u5f9e\u4e8b\u896a\u5b50\u985e\uff0c\u6cf3\u88dd\u548c\u5167\u8863\u5e02\u5834\u3002\u7e3d\u516c\u53f8\u65bc1986\u5e74\u5728\u610f\u5927\u5229\u6210\u7acb\uff0c\u5728\u901930\u5e74\u591a\u7684\u6642\u9593\u5df2\u7d93\u5728\u8d85\u904e50\u500b\u570b\u5bb6\u5efa\u7acb\u4e86\u8d85\u904e4,900\u5bb6\u5e97\u8216\u7684\u7db2\u7d61\uff0c\u7576\u4e2d\u5305\u62ec\u8a31\u591a\u4e3b\u8981\u57ce\u5e02\uff0c\u5982\u7c73\u862d\u3001\u7f85\u99ac\u3001\u5df4\u9ece\u3001\u502b\u6566\u3001\u67cf\u6797\u3001\u6771\u4eac\u3001\u5df4\u585e\u9686\u7d0d\u3001\u7d10\u7d04\u53ca\u9999\u6e2f\uff0c\u4e26\u64c1\u6709\u8d85\u904e38,000\u540d\u54e1\u5de5\u3002\u672c\u96c6\u5718\u7684\u7db2\u7d61\u5c07\u900f\u904e\u6301\u7e8c\u5730\u5728\u4e16\u754c\u5404\u5730\u958b\u65b0\u5e97\u8216\u800c\u7e7c\u7e8c\u8fc5\u901f\u767c\u5c55\uff0c\u4ee5\u7e7c\u7e8c\u652f\u6301Calzedonia\u54c1\u724c\u64f4\u5f35\u548c\u65b0\u5e97\u958b\u5e55\uff0c\u6211\u5011\u9700\u8981\u6709\u80fd\u4e4b\u4ed5\u52a0\u5165\u6211\u5011\u4e26\u8207\u516c\u53f8\u4e00\u540c\u6210\u9577\uff0c\u4ee5\u4e0b\u54c1\u724c\u73fe\u6b63\u63a5\u53d7\u62db\u52df:\n\nCalzedonia\n\u5c08\u9580\u5f9e\u4e8b\u896a\u5b50\u985e\u3001\u8cbc\u8eab\u8932\u3001\u7d72\u896a\u53ca\u6cf3\u88dd\u3002\u5f62\u8c61\u5e74\u8f15\u800c\u6709\u6d3b\u529b\uff0c\u7522\u54c1\u8a2d\u8a08\u7dca\u8cbc\u6f6e\u6d41\uff0c\u5176\u5851\u8eab\u7cfb\u5217\u4ea6\u6df1\u53d7\u4e2d\u5916\u540d\u4eba\u71b1\u6367\u3002\n\nIntimissimi\nCalzedonia\u96c6\u5718\u65d7\u4e0b\u5167\u8863\u54c1\u724c\u3002\u81ea1996\u5e74\u5275\u7acb\u4ee5\u4f86\uff0c\u5df2\u6210\u70ba\u6b50\u6d32\u5167\u8863\u5e02\u5834\u7684\u9818\u5c0e\u8005\uff0c\u4e3b\u8981\u552e\u8ce3\u5167\u8863\u3001\u7761\u8863\u53ca\u5bb6\u5c45\u670d\u3002\u54c1\u724c\u7c21\u55ae\u800c\u7cbe\u7dfb\u7684\u98a8\u683c\u3001\u8212\u9069\u9ad8\u54c1\u8cea\u7684\u7522\u54c1\u3001\u6d6a\u6f2b\u512a\u96c5\u7684\u8a2d\u8a08\uff0c\u6df1\u53d7\u4e16\u754c\u5404\u5730\u4e0d\u540c\u5e74\u9f61\u5973\u4ed5\u7684\u937e\u611b\u3002\n\nFalconeri\n\u4ee5\u7f8a\u7d68\u3001\u7f8a\u6bdb\u91dd\u7e54\u54c1\u70ba\u4e3b\u8981\u5546\u54c1\uff0c\u6240\u6709\u5546\u54c1\u5747\u7531\u610f\u5927\u5229\u88fd\u9020\uff0c\u4ee5\u4fdd\u6301\u5176\u512a\u8d8a\u54c1\u8cea\u3002\u5728\u751f\u7522\u5929\u7136\u548c\u73cd\u8cb4\u7d17\u7dda\u65b9\u9762\u64c1\u6709\u8c50\u5bcc\u7684\u5c08\u696d\u77e5\u8b58\uff0c\u63d0\u4f9b\u7537\u58eb\u548c\u5973\u58eb\u91dd\u7e54\u54c1\u53ca\u7f8a\u7d68\u88fd\u54c1\u3002\u5168\u610f\u5927\u5229\u88fd\u9020\uff0c\u7d50\u5408\u4e86\u54c1\u8cea\u3001\u7cbe\u7dfb\u7684\u98a8\u683c\u8207\u76f8\u5b9c\u7684\u50f9\u683c\u65bc\u4e00\u8eab\u3002\n\n\u5de5\u4f5c\u5730\u9ede\uff1a\u5c16\u6c99\u5480\u5340 / \u6c99\u7530 / \u9285\u947c\u7063 / \u4e2d\u74b0\n\n\u5168\u8077\u92b7\u552e\u52a9\u7406\u8ca0\u8cac\n\n\u8655\u7406\u5e97\u8216\u65e5\u5e38\u904b\u4f5c\n\u63d0\u4f9b\u51fa\u8272\u7684\u9867\u5ba2\u670d\u52d9\u4ee5\u589e\u52a0\u5ba2\u6236\u6eff\u610f\u5ea6\n\u5efa\u7acb\u5ba2\u6236\u5fe0\u8aa0\u5ea6\n\u91cd\u65b0\u6392\u5217\u5e97\u92ea\u9673\u5217\u8207\u6574\u7406\u5b58\u8ca8\n\n\u9019\u500b\u8077\u4f4d\u975e\u5e38\u9069\u5408\u4f60\uff0c\u5982\u679c\u4f60\uff1a\n\n\u71b1\u8877\u6642\u5c1a\u754c\u548c\u71b1\u611b\u6211\u5011\u7684\u54c1\u724c\u548c\u7522\u54c1\n\u6709\u92b7\u552e\u5929\u8ce6\n\u6709\u6d3b\u529b\u800c\u4e14\u7a4d\u6975\n\u5177\u8cac\u4efb\u5fc3\u53ca\u4e0a\u9032\n\n\u5168\u8077\u92b7\u552e\u52a9\u7406\u7684\u85aa\u916c\u798f\u5229:\u00a0\n\n\u6bcf\u9031\u4e94\u5929\u5de5\u4f5c\uff0c\u5169\u5929\u4f8b\u5047\uff0c\u8f2a\u73ed\u8f2a\u4f11\n\u6bcf\u5929\u5de5\u4f5c\u516b\u5c0f\u6642\n\u53e6\u8a2d\u5e97\u8216\u4f63\u91d1\n\u52e4\u5de5\u734e\u53ca\u7279\u5225\u5e97\u8216\u6d25\u8cbc\n\u8d85\u6642\u5de5\u4f5c\u53ef\u7372\u88dc\u5047\n\u6709\u85aa\u52de\u5de5\u5047\u53ca\u5e74\u5047\n\u63a8\u85a6\u734e\u91d1\n\u5e74\u7d42\u96d9\u7ce7\n\u5b8c\u5584\u5728\u8077\u57f9\u8a13\n\u91ab\u7642\u4fdd\u96aa\u53ca\u7259\u91ab\u798f\u5229\n\u54e1\u5de5\u8cfc\u7269\u512a\u6075\n\u5167\u90e8\u6649\u5347\u6a5f\u6703\n\u4f60\u5c07\u6703\u52a0\u5165\u4e00\u500b\u7a69\u5065\u548c\u5e74\u8f15\u6709\u6d3b\u529b\uff0c\u4e26\u4ee5\u7522\u54c1\u548c\u670d\u52d9\u8cea\u7d20\u70ba\u540d\u7684\u570b\u969b\u96c6\u5718\u3002\n\n\n\u5982\u679c\u4f60\u6eff\u8db3\u9019\u4e9b\u8981\u6c42\uff0c\u4e26\u6709\u8208\u8da3\u52a0\u5165\u6211\u5011\uff0c\u53efWhatsApp 5500 2335\u6216\u81f4\u96fb 2627 6305 \u4e86\u89e3\u8a73\u60c5\uff0c\u6216\u6309Apply Now\u63d0\u4ea4\u5c65\u6b77\u9023\u540c\u8981\u6c42\u85aa\u91d1\u3002\n\n\u6309\u6b64\u4ee5WhatsApp \u767c\u51fa\u4f60\u7684\u7533\u8acb", "employment_types": ["Full Time", "Permanent"], "selling_points": ["\u5e95\u85aa\uff0c\u53e6\u8a2d\u4f63\u91d1\u3001\u52e4\u5de5\u734e\u53ca\u5176\u4ed6\u798f\u5229\u7b49\u7b49", "\u6bcf\u9031\u5169\u5929\u4f11\u5047\uff0c\u6bcf\u5929\u5de5\u4f5c\u516b\u5c0f\u6642\uff0c\u826f\u597d\u767c\u5c55\u6a5f\u6703\u53ca\u6649\u5347\u968e\u68af", "\u6b61\u8fce\u6709\u610f\u52a0\u5165\u670d\u88dd\u92b7\u552e\u884c\u696d\u7684\u4eba\u4ed5\u53ca\u7d93\u9a57\u8f03\u5c11\u8005"], "locations": ["Shatin Area"], "categories": ["Sales, CS & Business Devpt", "Retail Sales", "Wholesale", "Others", "Student / Fresh Graduate / No Experience"], "post_time": "2022-01-14T09:58:11Z", "salary": {"currency": null, "max": null, "min": null, "period": "monthly", "term": null}, "salary_visible": false, "title_keywords": ["\u92b7\u552e\u52a9\u7406", "sales assistant"], "responsibilities": [], "requirements": {"degrees": [], "majors": [], "languages": [], "language_level": [], "hard_skills": [], "soft_skills": [], "languages_combined": []}, "experience_required": {"duration": [], "field": []}}, {"job_id": "100003009045773", "location_code": "hk", "company": "ThreeSixty Sourcing Limited", "job_title": "Sales & Account Management Specialist", "description": "Who we are\n\nAn entrepreneurial, global team developing consumer products, brands, and retail store concepts of the future\nOver 20 brands sold in over 70,000 retail stores across the world\nOur signature brands include the iconic FAO Schwarz, Sharper Image and Vornado\nWe create experiential retail experiences and deliver them globally through retail franchise partnerships (New York, London, Dublin, Beijing, Milan)\nInhouse Industrial Design Lab and product Research and Design capabilities\nOver 500 employees worldwide \u2013 big enough for growth and lean enough for speed\nOffices across the globe, four in Asia, where they have been for more than 20 years\n\nWe believe in\n\nStart-up speed and high energy\nEntrepreneurial and winning culture\nCreative, dynamic, welcoming, hardworking and fun working environment\nEmpowering people and developing a culture from doers to drivers\nFrom impossible to inevitable\n\nWhy you will love us\n\nEndless development opportunities\nAbility to shape, create and build\nTransparency of direction, vision and strategy of the company\nA competitive salary\nAn attractive bonus scheme\nSocial and health coverage\nA mini UN with a team of over 15 nationalities\nGlobal exposure and potential to travel to support the company\u2019s international growth\nFun products to play with \u2026 really it is part of the job!\n\nHow you\u2019ll contribute\n\nManage our global wholesale customers\nKey account management including but not limited to:\u00a0developing strong relationships with customers, identifying new business opportunities among existing/new customers, putting together sales proposal, liaising between customers and cross-functional internal teams to ensure timely and successful delivery of our solutions according to client\u2019s sales plan.\u00a0\u00a0\nDrive revenue by organizing and supporting sales meetings\nCollaborate with cross-functional teams to support customers' orders\nSupport on customer forecasts, commitments, sample requests, and development of annual business plans\nWork with the marketing team on presentations and sales catalogues to customers\n\nWhy we will love you\n\nYou are a Diploma or degree holder\nYou have 5 years of professional experience with time spent in a sales or account management role, preferably in consumer goods\nYou are self-motivated with a can-do attitude\nYou get excited by challenges and are adept at finding creative solutions\nYou have a competitive spirit and a hunger to succeed and grow\nYou\u2019re naturally curious and have a strong desire to learn\nYou\u2019re not easily discouraged and always maintain a positive attitude\nYou are able to work under pressure, and possess excellent communication skills and are detailed-oriented\nYou are well-organized, able to multi-task, have strong problem-solving skills and are able to meet deadlines\nYou\u2019re passionate about organizing, setting systems and structures, and improving overall effectiveness\nYou are great at Excel and PowerPoint\nYou have excellent communication skills in English; Cantonese/Mandarin is an advantage\n\nLife at ThreeSixty Group\n\nWe believe that collaboration breeds great ideas. We support an environment where everyone can share their different experiences and perspectives. We have a diverse team which makes ThreeSixty Group an interesting and innovative place. We strive every day to make ThreeSixty Group a fun, friendly and inclusive place to work. We even designed our 22,000 sqft Hong Kong office to put our people first. A home away from home, our well-equipped kitchen and city skyline communal spaces inspires creativity and encourages togetherness \u2013 so much that it has won two international office design awards!\u00a0\n\nAs a family member of the ThreeSixty Group, you will make an impact and directly contribute to creating a world-class company. Are you ready to unleash your potential? If so, we\u2019d love to hear from you.", "employment_types": ["Full Time", "Permanent"], "selling_points": [], "locations": ["Kowloon Bay"], "categories": ["Sales, CS & Business Devpt", "Business Development", "Account Servicing", "Wholesale"], "post_time": "2022-01-13T08:38:33Z", "salary": {"currency": null, "max": null, "min": null, "period": "monthly", "term": null}, "salary_visible": false, "title_keywords": ["specialist", "sales"], "responsibilities": [], "requirements": {"degrees": [], "majors": [], "languages": [], "language_level": [], "hard_skills": [], "soft_skills": [], "languages_combined": []}, "experience_required": {"duration": [], "field": []}}, {"job_id": "100003009051066", "location_code": "hk", "company": "Aeon Stores (Hong Kong) Co Ltd", "job_title": "Assistant Buyer (Food / Cosmetics) (Ref.: JDB/AB)", "description": "Responsibilities:\n\nIdentify potential suppliers to source new products to enhance the product portfolio;\nNegotiate with suppliers to achieve competitive prices and terms;\nResponsible for budget control, outlet layout & merchandises display; and\n\nCoordinate sales promotion activities and visit stores occasionally.\n\nRequirements:\n\nTertiary educated or above in any discipline\nAt least\u00a01 year experience in the products Purchasing\n\nPrevious exposure in reputable chain-store operations will be advantageous\nGood product sense & well-organized\nExcellent communication & negotiation skills\nBe numerate, self-motivated as well as customer focus mindset\nAble to work independently & frequent store visit is required\nGood PC proficiency\nGood command of spoken & written English, spoken Cantonese\n\n\u00a0We offer attractive remuneration package, commensurate with experience to the successful applicant. Interested parties please click \"send full resume with current and expected salaries to The Human Resources Manager, AEON Stores (Hong Kong) Co., Limited, Units 7-11, 26 Floor, CDW Building, 388 Castle Peak Road, Tsuen Wan, New Territories, Hong Kong\n\n\u00a0\u00a0 \u201cAll application received will be kept strictly confidential and used exclusively for employment purpose only\u201d\u00a0\n\n(Please quote our reference no. for the position applied on the envelope)", "employment_types": ["Full Time", "Permanent"], "selling_points": ["Double Pay", "Discretionary Bonus", "Purchasing, negotiation, budget control"], "locations": ["Tsuen Wan Area"], "categories": ["Hospitality / F & B", "Food & Beverage", "Merchandising & Purchasing", "Procurement / Purchasing / Sourcing", "Sales, CS & Business Devpt", "Wholesale"], "post_time": "2022-01-15T01:41:26Z", "salary": {"currency": null, "max": null, "min": null, "period": "monthly", "term": null}, "salary_visible": false, "title_keywords": ["assistant"], "responsibilities": ["coordinate", "budget control"], "requirements": {"degrees": [], "majors": [], "languages": ["cantonese", "english"], "language_level": ["good command"], "hard_skills": ["pc", "focus"], "soft_skills": ["self-motivated", "work independently", "well-organized", "communication", "negotiation skills", "customer focus"], "languages_combined": [{"language": "cantonese", "language_level": ["good command"]}, {"language": "english", "language_level": ["good command"]}]}, "experience_required": {"duration": ["at least 1 year"], "field": ["purchasing"]}}, {"job_id": "100003009055659", "location_code": "hk", "company": "Manpower Services (Hong Kong) Limited", "job_title": "\u5e97\u8216\u92b7\u552e\u52a9\u7406 \u6708\u85aaHK$20,000 (\u8996\u4e4e\u7d93\u9a57) (\u5c0d\u96fb\u5b50\u7522\u54c1\u6709\u57fa\u672c\u8a8d\u8b58)", "description": "\u00a0\u5de5\u4f5c\u6642\u9593 : Mon-Sun 10:00a.m. - 9:00p.m.\n\n\u8077\u8cac\uff1a\n\n\u4ee5\u9867\u5ba2\u7232\u4e2d\u5fc3,\u00a0\u63d0\u4f9b\u6700\u4f73\u9867\u5ba2\u9ad4\u9a57\uff0c\u89e3\u7b54\u5ba2\u6236\u554f\u984c\uff0c\u5354\u52a9\u5e97\u8216\u65e5\u5e38\u71df\u904b\u5de5\u4f5c\n\n\u6b61\u8fce\u61c9\u5c46\u7562\u696d\u751f\n\n\u6d41\u5229\u5ee3\u6771\u8a71\uff0c\u57fa\u672c\u666e\u901a\u8a71\u53ca\u82f1\u8a9e\n\n\u6709\u610f\u52a0\u5165\u6211\u5011\uff0c\u8acb\u900f\u904e Apply Now \u905e\u4ea4\u5c65\u6b77\u8868/ \u53efWhatsApp 9171 6932 \u7533\u8acb", "employment_types": ["Full Time"], "selling_points": ["\u4ee5\u9867\u5ba2\u70ba\u4e2d\u5fc3\uff0c\u5354\u52a9\u5176\u9078\u64c7\u5408\u9069\u7684\u7522\u54c1\uff0c\u4e26\u63d0\u4f9b\u81ea\u7531\u9ad4\u9a57\u7684\u8cfc\u7269\u7a7a\u9593", "\u7b11\u5bb9\u958b\u6717\uff0c\u7a4d\u6975\u4e3b\u52d5\u53ca\u6ce8\u91cd\u5718\u968a\u7cbe\u795e", "\u5c0d\u96fb\u5b50\u7522\u54c1\u6709\u57fa\u672c\u8a8d\u8b58"], "locations": ["Not Specified"], "categories": ["Sales, CS & Business Devpt", "Retail Sales", "Wholesale", "Others"], "post_time": "2022-01-18T02:50:11Z", "salary": {"currency": null, "max": null, "min": null, "period": "monthly", "term": null}, "salary_visible": false, "title_keywords": [], "responsibilities": [], "requirements": {"degrees": [], "majors": [], "languages": [], "language_level": [], "hard_skills": [], "soft_skills": [], "languages_combined": []}, "experience_required": {"duration": [], "field": []}}, {"job_id": "100003009049635", "location_code": "hk", "company": "Felton Distribution Limited", "job_title": "ACCOUNT MANAGER (5 days work)", "description": "Job Description\n\n\u00a0Responsibilities:\n\nAchieve sales and GP target\nConduct sales activities including prospecting and cold-calls\nMaintain good relationship and develop new business with customers\nProvide sales and after-sales service to customer\n\n\u00a0Requirements:\n\nPost-Secondary or above\n1-2 years sales experience in gaming and DIY computer related industries\nConfident, self-motivated and result-oriented\nStrong presentation and communications skills\nGood command of both written and spoken English and Chinese", "employment_types": ["Full Time"], "selling_points": [], "locations": ["Kowloon Bay"], "categories": ["Sales, CS & Business Devpt", "Business Development", "Wholesale"], "post_time": "2022-01-14T09:00:34Z", "salary": {"currency": null, "max": null, "min": null, "period": "monthly", "term": null}, "salary_visible": false, "title_keywords": ["account manager"], "responsibilities": ["sales activities", "after-sales service", "develop new business", "maintain good relationship"], "requirements": {"degrees": [], "majors": [], "languages": ["english", "chinese"], "language_level": ["good command"], "hard_skills": [], "soft_skills": ["confident", "self-motivated", "presentation", "result-oriented"], "languages_combined": [{"language": "english", "language_level": ["good command"]}, {"language": "chinese", "language_level": ["good command"]}]}, "experience_required": {"duration": ["1-2 years"], "field": ["related"]}}, {"job_id": "100003009056255", "location_code": "hk", "company": "Osmium Consulting Group Limited", "job_title": "( Junior ) Relationship Manager, Corporates Banking", "description": "Responsibilities:\n\nAssist\u00a0Team Head\u00a0in managing and developing a portfolio of corporate banking customer with an aim to deepen and broaden relationships with our clients\nExplore new business opportunities and actively participate in the marketing and selling of bank\u2019s corporate financial services in the areas of corporate lending, structured transactions, syndication, treasury, trade financing or other financial products\nReview credit facilities, perform credit analysis and prepare credit proposals\nConduct review and take proactive measures to ensure credit quality\nHandle ad-hoc assignments / projects as and when needed\n\nRequirements:\n\nMinimum\u00a04 years of relevant experience in corporate lending, trade finance and syndication loans in the banking industry\nUniversity degree in Finance, Business Administration or related disciplines\nStrong self-motivation and ability to work under pressure\nStrong communication, interpersonal and analytical skills\nProficient in both English and Chinese, fluency in Putonghua an advantage", "employment_types": ["Full Time", "Permanent"], "selling_points": ["13 Months-pay", "Large Corporates", "Open to juniors"], "locations": ["Central"], "categories": ["Banking / Finance", "Corporate Banking", "Financial Services", "Sales, CS & Business Devpt", "Wholesale"], "post_time": "2022-01-18T03:43:15Z", "salary": {"currency": null, "max": null, "min": null, "period": "monthly", "term": null}, "salary_visible": false, "title_keywords": ["relationship manager", "junior"], "responsibilities": ["explore new business opportunities", "ad-hoc assignments", "analysis", "review", "quality", "developing", "transactions", "banking"], "requirements": {"degrees": ["university degree"], "majors": ["related disciplines", "finance", "business administration"], "languages": ["putonghua", "english", "chinese"], "language_level": ["fluency", "advantage", "proficient"], "hard_skills": ["analytical skills"], "soft_skills": ["analytical skills", "communication", "self-motivation", "interpersonal", "work under pressure"], "languages_combined": [{"language": "putonghua", "language_level": ["fluency", "advantage"]}, {"language": "english", "language_level": ["proficient", "fluency", "advantage"]}, {"language": "chinese", "language_level": ["proficient", "fluency", "advantage"]}]}, "experience_required": {"duration": ["minimum 4 years"], "field": ["finance", "banking industry", "relevant experience"]}}, {"job_id": "100003009055801", "location_code": "hk", "company": "Michael Page", "job_title": "Director of Sales, APAC (Toys)", "description": "This is a fantastic opportunity for strong sales professional to take on an exciting new role with a world leading Toys company. The company is now expanding their business and adding new headcounts to their sales team. They are now looking for a Director of Sales, APAC to join their business.\n\nClient Details\n\nThis is a fantastic opportunity for strong sales professional to take on an exciting new role with a world leading Toys company. They are now looking for a Director of Sales, APAC to join their business. The company is now expanding their business and adding new headcounts to their sales team.\n\nDescription\n\nYou will be responsible for developing and executing strategic plans to achieve sales targets and expand the customer base in HK and Asia (both retailer and distributors)\nYou will be responsible for distributor management and business development for retailers.\nYou will also be involved in the analysis of market and the competitors.\nYou will be responsible for owning and hitting/exceeding annual sales targets.\n\nProfile\n\nMinimum 8 - 10 years of relevant sales & distributor management experience, working in toys industry is mandatory.\nThe successful candidate must be determined and have strong business acumen.\nExcellent leadership skills\nYou must have the ability to develop long-term partnerships with clients and partners.\nFluency in Mandarin, Cantonese and English is mandatory.\n\nJob Offer\n\nThis is a great opportunity for a strong sales professional to take on a leadership role in this international company. They provide an attractive salary and benefits for the candidate.\n\nTo apply online please click the 'Apply' button below. For a confidential discussion about this role please contact Phoebe Leung on +852 3412 4853.", "employment_types": ["Full Time", "Permanent"], "selling_points": ["A world leading toys company", "APAC region", "Distributor Management"], "locations": ["Not Specified"], "categories": ["Sales, CS & Business Devpt", "Business Development", "Channel / Distribution", "Wholesale"], "post_time": "2022-01-18T02:57:47Z", "salary": {"currency": null, "max": null, "min": null, "period": "monthly", "term": null}, "salary_visible": false, "title_keywords": ["director", "sales"], "responsibilities": ["management", "strategic plans", "analysis", "developing", "develop", "sales team", "executing"], "requirements": {"degrees": [], "majors": [], "languages": ["cantonese", "english", "mandarin"], "language_level": ["fluency"], "hard_skills": ["analysis", "acumen"], "soft_skills": ["determined", "responsible", "leadership skills", "business acumen", "leadership"], "languages_combined": [{"language": "cantonese", "language_level": ["fluency"]}, {"language": "english", "language_level": ["fluency"]}, {"language": "mandarin", "language_level": ["fluency"]}]}, "experience_required": {"duration": ["minimum 8 - 10 years"], "field": ["toys", "management"]}}, {"job_id": "100003009044203", "location_code": "hk", "company": "Daniel & Co", "job_title": "\u7406\u8ca8\u54e1 (\u9808\u5916\u52e4)", "description": "\u8ca0\u8cac\u73a9\u5177\u767e\u8ca8\u5e97\u7684\u5c08\u6ac3\u4f4d\u5de5\u4f5c\uff0c\u5305\u62ec\u6574\u7406\u5e97\u5167\u8ca8\u54c1\u9673\u8a2d\uff0c\u843d\u55ae\u3001\u88dc\u8ca8\u53ca\u63a8\u92b7\u8ca8\u54c1\u7b49\u5de5\u4f5c\uff0c\u6bcf\u65e5\u8ca0\u8cac\u5230\u8a2a2-3\u9593\u5e97\u8216\u5de5\u4f5c\n\u4e2d\u4e94\u6216\u4ee5\u4e0a\u7a0b\u5ea6\n1\u5e74\u4ee5\u4e0a\u92b7\u552e/\u6279\u767c\u7d93\u9a57\n\u719f\u6089\u73a9\u5177\u77e5\u8b58\u512a\u5148\u8003\u616e\n\u52e4\u596e\u3001\u7a4d\u6975\u4e3b\u52d5\u53ca\u6709\u8cac\u4efb\u5fc3\n\u5177\u826f\u597d\u6e9d\u901a\u6280\u5de7\n\n\u7533\u8acb\u8005\u8acb\u5c07\u500b\u4eba\u5c65\u6b77\u53ca\u8981\u6c42\u5f85\u9047\u96fb\u90f5\u81f3\ufe55[via APPLY NOW]\n\n\u6709\u610f\u7533\u8acb\u8005\u8acb\u6309 APPLY NOW\u7533\u8acb \u00a0\u00a0\u00a0\n\n", "employment_types": ["Full Time"], "selling_points": [], "locations": ["Not Specified"], "categories": ["Transportation & Logistics", "Inventory / Warehousing", "Supply Chain", "Sales, CS & Business Devpt", "Wholesale"], "post_time": "2022-01-13T03:23:35Z", "salary": {"currency": null, "max": null, "min": null, "period": "monthly", "term": null}, "salary_visible": false, "title_keywords": ["\u7406\u8ca8\u54e1"], "responsibilities": [], "requirements": {"degrees": [], "majors": [], "languages": [], "language_level": [], "hard_skills": [], "soft_skills": [], "languages_combined": []}, "experience_required": {"duration": [], "field": []}}, {"job_id": "100003009045564", "location_code": "hk", "company": "Save The Duck Asia-Pacific Limited", "job_title": "Assistant Retail Merchandiser / Retail Merchandiser (retail/wholesale/e-commerce)", "description": "Responsibilities\n\nPurchase order creation and pricing upload\nMerchandising and delivery reports update and review stock status\nClose communication with wholesale, distributors and e-commerce partners on order and delivery issues\nMonitor stock level, merchandise distribution, stock allocation and sales performance\nPrepare sales and inventory analysis reports\n\nRequirements\n\nGood command of written & spoken English & Chinese\nFamiliar with logistics and experience in China market is preferable\nCollege or University Degree preferred\nAt least 2 years\u2019+ experience in merchandising is a must, less experience will be considered as assistant merchandiser\nProficient in MS Excel, MS Word and PowerPoint\nPositive, self-motivated, detail-minded, number sensitive and good interpersonal skills\nImmediate available is preferred\n\nWe offer an attractive package to the right candidates.\u00a0Interested applicants please send your detailed resume, contact number, current & expected salaries to us, by clicking the\u00a0\"Apply Now\"\u00a0button, or\u00a0call 3898 8502 for enquiry.\n\n(Data collected will be treated in strict confidence and used for recruitment purpose only.)", "employment_types": ["Full Time", "Permanent"], "selling_points": ["Merchandising and delivery reports update", "Purchase order creation and pricing upload", "Familiar with logistics and exp. in China market"], "locations": ["Quarry Bay"], "categories": ["Merchandising & Purchasing", "Procurement / Purchasing / Sourcing", "Sales, CS & Business Devpt", "Retail Sales", "Wholesale"], "post_time": "2022-01-13T08:05:17Z", "salary": {"currency": null, "max": null, "min": null, "period": "monthly", "term": null}, "salary_visible": false, "title_keywords": ["merchandiser", "assistant"], "responsibilities": ["delivery issues", "analysis reports", "stock allocation", "sales performance", "review", "merchandising", "monitor", "prepare sales", "inventory", "communication", "purchase", "reports"], "requirements": {"degrees": ["university degree"], "majors": [], "languages": ["english", "chinese"], "language_level": ["good command"], "hard_skills": ["ms excel", "powerpoint", "ms word"], "soft_skills": ["detail-minded", "self-motivated", "interpersonal skills", "sensitive", "positive"], "languages_combined": [{"language": "english", "language_level": ["good command"]}, {"language": "chinese", "language_level": ["good command"]}]}, "experience_required": {"duration": [], "field": ["merchandising", "logistics"]}}, {"job_id": "100003009050306", "location_code": "hk", "company": "Maxim's Caterers Ltd", "job_title": "Business Development Officer (Account Management)", "description": "Responsibilities\n\nDeal with different overseas distributors\nHandle customer enquiry\nFollow up sales order and marketing programs\u00a0\nHandle all sales related matter, including marketing programs, forecast coordination, administration support and account servicing\nWork closely with cross functional teams\nRequirements\n\nUniversity graduate in any discipline\nAt least 2 years' sales experience, with export sales background an advantage\nProficient in\u00a0Microsoft Excel and PowerPoint\nOrganized, self-motivated, strong sense of responsibility, multi-tasking, detail-minded, good communication skills, can cope with pressure & tight timeline\n\nGood command in spoken and written English, Chinese and Mandarin\n\n\nInterested parties please apply with full resume, state current and expected salaries by clicking \"Apply Now\". All applications and data collected will be treated in strict confidence and used exclusively for recruitment purposes.\u00a0 Only short listed candidates will be invited for interview. The company will retain the applications for a maximum period of 24 months and may refer suitable candidates to other vacancies within the Group.", "employment_types": ["Full Time", "Permanent"], "selling_points": ["Deal with different overseas distributors", "Follow up sales order and marketing programs", "Work closely with cross functional teams"], "locations": ["Not Specified"], "categories": ["Sales, CS & Business Devpt", "Account Servicing", "Wholesale", "Sales Administration"], "post_time": "2022-01-14T10:05:32Z", "salary": {"currency": null, "max": null, "min": null, "period": "monthly", "term": null}, "salary_visible": false, "title_keywords": ["business development officer"], "responsibilities": ["follow up sales order", "teams", "coordination", "forecast", "administration"], "requirements": {"degrees": ["university graduate"], "majors": [], "languages": ["english", "chinese", "mandarin"], "language_level": ["good command"], "hard_skills": ["powerpoint", "microsoft excel"], "soft_skills": ["detail-minded", "organized", "self-motivated", "communication skills", "sense of responsibility", "multi-tasking"], "languages_combined": [{"language": "english", "language_level": ["good command"]}, {"language": "chinese", "language_level": ["good command"]}, {"language": "mandarin", "language_level": ["good command"]}]}, "experience_required": {"duration": ["at least 2 years"], "field": []}}, {"job_id": "100003009047643", "location_code": "hk", "company": "Main Plan Limited", "job_title": "Sales & Marketing Executive (Export Dept)", "description": "Responsibilities\n\nHandle order processing, quotation, sampling and shipping arrangements\nInterface with overseas customers, engineers & R&D team\u00a0in our\u00a0factory for\u00a0product development\nCoordinate and participate local & overseas trade fairs\nDevelop the sales and marketing plan and activities for overseas market\nResearch, identify and propose potential business opportunities & solicit new business\nMaintain a good relationship with clients\n\nRequirements\n\nDegree holder with\u00a04 years or above relevant experience\nSelf-motivated, independent & with good communication skills\nFluent in English, Mandarin and Cantonese\nFamiliar with MS Office & Chinese WP\n\nAttractive remuneration will be offered to the right candidate. Please send full resume with contact telephone number, present and expected salary to The Human Resources Manager by email (Please quote the position & department in your email).\n\n\u00a0Candidates are welcome to visit our Company website:\u00a0http://www.mplhk.com/.\n\n\u00a0Personal data collected will be used for recruitment purpose only.", "employment_types": ["Full Time", "Permanent"], "selling_points": ["Handle order processing, quotation, sampling etc.", "Coordinate & participate trade fairs", "Develop the S&M plan & activities for overseas mkt"], "locations": ["Kwun Tong"], "categories": ["Sales, CS & Business Devpt", "Business Development", "Sales - Sales Management", "Wholesale"], "post_time": "2022-01-14T03:39:00Z", "salary": {"currency": null, "max": null, "min": null, "period": "monthly", "term": null}, "salary_visible": false, "title_keywords": ["sales & marketing executive"], "responsibilities": ["shipping", "business opportunities", "quotation", "develop", "coordinate", "marketing plan", "good relationship", "maintain", "order processing"], "requirements": {"degrees": ["degree holder"], "majors": [], "languages": ["cantonese", "english", "chinese", "mandarin"], "language_level": ["fluent"], "hard_skills": ["chinese wp", "ms office"], "soft_skills": ["communication skills", "self-motivated", "independent"], "languages_combined": [{"language": "cantonese", "language_level": ["fluent"]}, {"language": "english", "language_level": ["fluent"]}, {"language": "chinese", "language_level": []}, {"language": "mandarin", "language_level": ["fluent"]}]}, "experience_required": {"duration": ["4 years"], "field": ["relevant experience"]}}, {"job_id": "100003009044095", "location_code": "hk", "company": "Sportshouse Limited", "job_title": "Senior Sales Executive (Wholesale)", "description": "Responsibilities:\n\nFollow up orders, planning and coordinating\nResponsible for developing and expanding a strong wholesale network to achieve sales target and maintain customer base\nMonitoring customer feedback and maintain good working relationship with key accounts of wholesale business\nPresent regular sales report with updated information and detailed market analysis for management review\nMonitor sales performance and inventory level\u00a0 \u00a0 \u00a0 \u00a0 \u00a0\u00a0\u00a0\n\nRequirements:\n\nHigher Diploma or above\nMinimum 4 years\u2019 sales experience, with retail sales experience would be an advantage\n\nGood interpersonal and communication skills\nInitiative, responsible, hard-working and willing to work under pressure\nRelevant experience in marketing (digital and traditional) is preferred\n\nGood command of written and spoken English / Cantonese\nProficient in using MS Word, Excel, PowerPoint\n\nInterested parties please\u00a0send your resume with current and expected salary\u00a0by email or clicking\u00a0\"Apply Now\".\n\nData collected will be used for recruitment purpose only.\n\nFor company information, please visit our website www.sportshouse.com.hk", "employment_types": ["Full Time", "Permanent"], "selling_points": ["Follow up orders, planning and coordinating", "Develop and expand a strong wholesale network", "Maintain good working relationship with customers"], "locations": ["Tsuen Wan Area"], "categories": ["Marketing / Public Relations", "Marketing - Direct Marketing", "Sales, CS & Business Devpt", "Wholesale", "Digital Marketing"], "post_time": "2022-01-13T03:03:03Z", "salary": {"currency": null, "max": null, "min": null, "period": "monthly", "term": null}, "salary_visible": false, "title_keywords": ["senior sales executive"], "responsibilities": ["follow up orders", "sales report", "sales performance", "sales target", "monitoring", "monitor", "developing", "inventory", "maintain", "market analysis", "management review", "planning"], "requirements": {"degrees": ["higher diploma or above"], "majors": [], "languages": ["cantonese", "english"], "language_level": ["good command"], "hard_skills": ["excel", "powerpoint", "ms word"], "soft_skills": ["communication skills", "responsible", "hard-working", "interpersonal", "initiative", "work under pressure"], "languages_combined": [{"language": "cantonese", "language_level": ["good command"]}, {"language": "english", "language_level": ["good command"]}]}, "experience_required": {"duration": ["minimum 4 years"], "field": ["digital", "retail", "relevant experience", "marketing"]}}, {"job_id": "100003009044047", "location_code": "hk", "company": "M & A Toys Limited", "job_title": "SENIOR SALES EXECUTIVE / SALES EXECUTIVE (Toys)", "description": "Responsibilities\u00a0:\n- Maximize business turnover and product placement in the market place.\n- Liaise and maintain an executive level relationship with existing clients and business partners.\n- Handle customer enquiries and follow up sales orders, present new products/ projects to customers.\n- Coordinate closely with internal departments to meet delivery schedule and quality sales services.\n- Provide input and market intelligence information to senior management for competitive analysis.\n\nRequirements :\n- High Diploma holder or above.\n- Over 4 years in sales field with 2 years\u2019 experience in FMCG/Toys/Gift industry preferred.\n- Good connection with APAC retailing network.\n- Proficient in both written and spoken Chinese and English.\n- With strong sales techniques and be aggressive to achieve or exceed sales target.\n- Excellent presentation, communication and interpersonal skills.\n- Candidate with\u00a0less experience\u00a0will be considered as Sales Executive\n\nPersonal data collected will be used for recruitment purpose only.\n\nInterested parties, please apply with full resume stating expected & last salary and date of available by clicking \u2018Apply Now\u2019\n\n", "employment_types": ["Full Time"], "selling_points": [], "locations": ["Not Specified"], "categories": ["Sales, CS & Business Devpt", "Wholesale"], "post_time": "2022-01-13T03:02:15Z", "salary": {"currency": null, "max": null, "min": null, "period": "monthly", "term": null}, "salary_visible": false, "title_keywords": ["senior sales executive", "sales executive"], "responsibilities": ["liaise", "handle customer enquiries", "analysis", "quality", "coordinate", "delivery schedule", "maintain", "senior management"], "requirements": {"degrees": ["high diploma"], "majors": [], "languages": ["english", "chinese"], "language_level": ["proficient"], "hard_skills": [], "soft_skills": ["communication and interpersonal skills", "presentation"], "languages_combined": [{"language": "english", "language_level": ["proficient"]}, {"language": "chinese", "language_level": ["proficient"]}]}, "experience_required": {"duration": ["4 years", "2 years"], "field": ["toys", "fmcg", "gift industry"]}}, {"job_id": "100003009047742", "location_code": "hk", "company": "Thong Sia Watch Company Limited", "job_title": "Sales Executive", "description": "Let\u2019s work together\u00a0\n\nParticipate in sales and marketing strategies\nDaily work on any sales issue via email and phone\nWork closely with sales team members to achieve the company sales target and increase the distribution and penetration of products\nSales Negotiation, follow-up purchase orders, and coordinate sales activities with dealers\nVisit dealers regularly and maintain a good relationship with them\nHandle ad hoc assignments if required\n\n\u00a0We are looking for\n\nDiploma or above\nMinimum 2 years sales experience\nCandidate with more experience will be considered as Senior Sales Executive\nGood communication and coordination skills\nAble to work under pressure and work independently\nStrong selling, presenting analytical and problem-solving skills\u00a0\nProficient in\u00a0MS Word, Excel and PowerPoint and Chinese Word Processing\nGood command of\u00a0written and spoken English and Chinese\n\n\u00a0\u00a0Join us now:\u00a0\n\nPlease send\u00a0full resume stating your academic qualifications, career history, availability with current and expected salary\u00a0to: The\u00a0Human Resources Manager\n\nOn offer is a competitive package\n\nAttractive\u00a0Remuneration\n5 Days Work\nAnnual Leave\nFamily Leave\nPaternity Leave\nMonthly Early Release\nMarriage Leave with red packets\nMedical Scheme\nStaff Discount\n\nWebsite:\u00a0http://www.thongsia.com.hk", "employment_types": ["Full Time"], "selling_points": ["Sole distributor of Seiko", "Minimum 2 years sales experience", "Good communication and coordination skills"], "locations": ["Wong Tai Sin Area"], "categories": ["Sales, CS & Business Devpt", "Sales - Sales Management", "Wholesale", "Others"], "post_time": "2022-01-14T03:49:54Z", "salary": {"currency": null, "max": null, "min": null, "period": null, "term": null}, "salary_visible": false, "title_keywords": ["sales executive"], "responsibilities": ["sales activities", "marketing strategies", "sales target", "website", "coordinate", "good relationship", "purchase", "maintain", "sales team", "ad hoc assignments", "communication", "coordination", "work under pressure"], "requirements": {"degrees": ["diploma or above"], "majors": [], "languages": ["english", "chinese"], "language_level": ["good command", "proficient"], "hard_skills": ["excel", "chinese word processing", "scheme", "powerpoint", "problem-solving skills", "red", "ms word"], "soft_skills": ["work independently", "coordination skills", "negotiation", "communication", "problem-solving skills", "work under pressure"], "languages_combined": [{"language": "english", "language_level": ["good command"]}, {"language": "chinese", "language_level": ["good command", "proficient"]}]}, "experience_required": {"duration": ["minimum 2 years"], "field": []}}, {"job_id": "100003009051594", "location_code": "hk", "company": "RecruitFirst Limited", "job_title": "\u82f1\u570b\u6f6e\u6d41\u6642\u88dd\u552e\u8ca8\u54e1 Sales (5\u5929\u5de5\u4f5c/\u9996\u4e09\u500b\u6708\u5305\u85aa/\u4f63\u91d1\u7121\u5c01\u9802)", "description": "\u5de5\u4f5c\u8077\u8cac:\n\n\u5354\u52a9\u9054\u6210\u516c\u53f8\u5b9a\u4e0b\u7684\u92b7\u552e\u76ee\u6a19\n\u56e0\u61c9\u5ba2\u4eba\u9700\u8981\uff0c\u63d0\u4f9b\u5c08\u696d\u670d\u88dd\u610f\u898b\uff0c\u63d0\u5347\u9867\u5ba2\u6eff\u610f\u5ea6\n\u900f\u904e\u96fb\u8a71\u3001\u5373\u6642\u901a\u8a0a\u8edf\u4ef6\u8207\u5ba2\u6236\u4fdd\u6301\u9577\u9060\u53ca\u826f\u597d\u95dc\u4fc2\n\u7ba1\u7406\u8ca8\u5834\u53ca\u5009\u5b58\u4ee5\u78ba\u4fdd\u5b58\u8ca8\u5145\u8db3\n\n\u5de5\u4f5c\u8981\u6c42:\n\n\u4e00\u5e74\u6642\u88dd\u96f6\u552e\u7d93\u9a57\n\u6d41\u5229\u5ee3\u6771\u8a71\u3001\u57fa\u672c\u666e\u901a\u8a71\u53ca\u82f1\u8a9e\n\u71b1\u611b\u6642\u5c1a\u6f6e\u6d41\uff0c\u5c0d\u6642\u88dd\u92b7\u552e\u6709\u71b1\u60c5\n\u63d0\u4f9b\u89aa\u5584\u6709\u79ae\u7684\u9867\u5ba2\u670d\u52d9\n\n\u54e1\u5de5\u798f\u5229:\n\n\u6bcf\u90315\u5929\u5de5\u4f5c\n\u9996\u4e09\u500b\u6708\u5305\u85aa\n\u8c50\u539a\u4f63\u91d1(\u7121\u5c01\u9802)\n\u91ab\u7642\u798f\u5229\n\u5b8c\u5584\u5de5\u4f5c\u57f9\u8a13\u53ca\u6649\u5347\u968e\u68af\n\u54e1\u5de5\u8cfc\u7269\u512a\u60e0\n\n\u6709\u610f\u61c9\u5fb5\u8005\u8acb\u7acb\u5373\u6309\u7533\u8acb(Apply Now)\n\n\u5982\u6709\u4efb\u4f55\u7591\u554f\uff0c\u6b61\u8fce\u806f\u7d61Hailey Chan 3702 3826\u67e5\u8a62\u3002", "employment_types": ["Full Time"], "selling_points": [], "locations": ["Not Specified"], "categories": ["Sales, CS & Business Devpt", "Retail Sales", "Wholesale", "Direct Sales"], "post_time": "2022-01-16T13:37:59Z", "salary": {"currency": null, "max": null, "min": null, "period": "monthly", "term": null}, "salary_visible": false, "title_keywords": ["sales"], "responsibilities": [], "requirements": {"degrees": [], "majors": [], "languages": [], "language_level": [], "hard_skills": [], "soft_skills": [], "languages_combined": []}, "experience_required": {"duration": [], "field": []}}, {"job_id": "100003009040561", "location_code": "hk", "company": "b & h (Swiss) Limited", "job_title": "Sales Executive", "description": "Responsibilities\n\n\n\nAchieve the company's monthly sales target by acquiring new sales opportunities and enhancing existing customer base\nFollow-up orders and enquiries, provide after-sales services, follow up on customer enquiry and complaint\nProvide full range support to sales and marketing activities for retails Channels\nNecessary over-time work is needed\nPrepare sales report to Management\nAny ad hoc assigned by superiors\n\nRequirements:\n\nDiploma or above in Business, Marketing or equivalent;\n2-3 years of working experience in Marketing & Business development (previous experience in baby products and health care industry preferable.)\nProficiency in PC operations including MS Office and Chinese processing\nStrong sense of responsibility, well-organized and a good team player\nAggressive and work independent\nCandidate with experience in\u00a0baby products, health care or medical industry\u00a0would be an advantage.\nImmediate available is preferable\n\nA competitive remuneration package including benefits will be offered. Please send your detail resume include your present and expected salary as well as availability by clicking \"Apply Now\".\n\nPersonal data collected will be used for recruitment purpose only.", "employment_types": ["Full Time"], "selling_points": [], "locations": ["To Kwa Wan"], "categories": ["Sales, CS & Business Devpt", "Business Development", "Wholesale", "Direct Sales"], "post_time": "2022-01-12T02:46:30Z", "salary": {"currency": null, "max": null, "min": null, "period": "monthly", "term": null}, "salary_visible": false, "title_keywords": ["sales executive"], "responsibilities": ["management", "ad hoc", "sales target", "prepare sales", "report"], "requirements": {"degrees": ["diploma or above"], "majors": ["business", "marketing"], "languages": ["chinese"], "language_level": ["proficiency"], "hard_skills": ["processing", "pc operations", "ms office"], "soft_skills": ["good team player", "well-organized", "independent", "sense of responsibility"], "languages_combined": [{"language": "chinese", "language_level": ["proficiency"]}]}, "experience_required": {"duration": ["2-3 years"], "field": ["medical", "health care", "marketing", "business development"]}}, {"job_id": "100003009045599", "location_code": "hk", "company": "Ralph Lauren", "job_title": "Merchandising Assistant - Wholesale GCSEA (4-months contract)", "description": "Responsibilities:\n\nWork closely with internal and external stakeholders on stock management, product launches and promotional activities on e-commerce channels\nTo update Sales & Inventory Reports\nEnsure all buying records are well documented\nFollow-up orders with clients and internal departments until delivery\nTo assist other tasks as assigned\n\nRequirements:\n\n\nDiploma holder in Management, Business or relevant discipline\u00a0or above\nFresh graduates are welcome; Working/ Internship experiences in retailing industry ideally in high end fashion is a plus\nGood command of English\n\u00a0Proficiency PC knowledge (MS Word, Excel and Power Point)\nFamiliar with vlookup and Pivot Table\nDetail orientated, accurate, well-organized and patient\u00a0", "employment_types": ["Full Time", "Temporary"], "selling_points": ["Account Management", "Strong English communication skills", "Fresh graduates are welcome"], "locations": ["Tsim Sha Tsui"], "categories": ["Merchandising & Purchasing", "Others", "Sales, CS & Business Devpt", "Account Servicing", "Wholesale"], "post_time": "2022-01-13T08:10:23Z", "salary": {"currency": null, "max": null, "min": null, "period": "monthly", "term": null}, "salary_visible": false, "title_keywords": ["merchandising assistant"], "responsibilities": ["stock management", "inventory", "other tasks", "reports", "promotional activities"], "requirements": {"degrees": ["diploma holder"], "majors": ["business"], "languages": ["english"], "language_level": ["good command"], "hard_skills": ["excel", "plus", "pivot table", "vlookup", "power point", "pc knowledge", "ms word"], "soft_skills": ["patient", "accurate", "well-organized", "detail orientated"], "languages_combined": [{"language": "english", "language_level": ["good command"]}]}, "experience_required": {"duration": [], "field": []}}, {"job_id": "100003009051592", "location_code": "hk", "company": "RecruitFirst Limited", "job_title": "\u5fb7\u570b\u77e5\u540d\u76f8\u6a5f\u54c1\u724c\u552e\u8ca8\u54e1 Senior/Sales Advisor (\u9996\u4e09\u500b\u6708\u5305\u85aa/23K+/\u6b61\u8fce\u73e0\u5bf6\u96f6\u552e\u696d)", "description": "\u4e3b\u8981\u8077\u8cac:\n\n\u63a8\u5ee3\u53ca\u92b7\u552e\u5404\u7a2e\u9ad8\u7d1a\u76f8\u6a5f\uff0c\u4ee5\u9054\u81f4\u5e97\u92ea\u92b7\u552e\u76ee\u6a19\n\u63d0\u4f9b\u5c08\u696d\u610f\u898b\u4e26\u6559\u6388\u5ba2\u4eba\u651d\u5f71\u6280\u5de7\n\u5efa\u7acb\u4e26\u7dad\u6301\u826f\u597d\u5ba2\u6236\u95dc\u4fc2\n\u7ba1\u7406\u5eab\u5b58\u548c\u7dad\u6301\u65e5\u5e38\u5e97\u92ea\u904b\u71df\n\n\u8981\u6c42:\n\n\u4e00\u5e74\u76f8\u6a5f/\u73e0\u5bf6\u96f6\u552e\u7d93\u9a57\n\u5c0d\u76f8\u6a5f\u7522\u54c1\u6709\u8208\u8da3\u53ca\u57fa\u672c\u8a8d\u8b58\n\u4e3b\u52d5\u53ca\u7a4d\u6975\uff0c\u826f\u597d\u5ba2\u6236\u670d\u52d9\n\u826f\u597d\u7cb5\u8a9e\uff0c\u4e00\u822c\u82f1\u8a9e\u53ca\u666e\u901a\u8a71\n\n\u6709\u610f\u61c9\u5fb5\u8005\u8acb\u7acb\u5373\u6309\u7533\u8acb(Apply Now)\n\n\u5982\u6709\u4efb\u4f55\u7591\u554f\uff0c\u6b61\u8fce\u806f\u7d61Hailey Chan 3702 3826\u67e5\u8a62\u3002", "employment_types": ["Full Time"], "selling_points": [], "locations": ["Not Specified"], "categories": ["Sales, CS & Business Devpt", "Retail Sales", "Wholesale", "Direct Sales"], "post_time": "2022-01-16T13:30:37Z", "salary": {"currency": null, "max": null, "min": null, "period": "monthly", "term": null}, "salary_visible": false, "title_keywords": ["sales advisor"], "responsibilities": [], "requirements": {"degrees": [], "majors": [], "languages": [], "language_level": [], "hard_skills": [], "soft_skills": [], "languages_combined": []}, "experience_required": {"duration": [], "field": []}}, {"job_id": "100003009045902", "location_code": "hk", "company": "Antercare Limited", "job_title": "Sales Executive - Medical Solutions", "description": "\u00a0Job responsibility and requirement:\n\nPosition is responsible for promoting a range of medical devices and consumables to medical professionals in government and private sector.\nFocus on developing surgical instrument, infection control products and medical consumables in assigned territories\u00a0\n\u00a0Deliver professional knowledge and services to healthcare professionals\n\u00a0Develop action plans and strategies to achieve sales target\n\u00a0Organize, execute sales and marketing activities\n\u00a0Provide education and training to end-users\n\u00a0Manage the call plan for both existing and new customers and manage the assigned territories\n\u00a0Make regular visits to identify customers\u2019 needs and provide treatment solution to the healthcare professionals\nAnalyze sales data and prepare all the related reports and presentation as required.\nWilling to work under pressure and flexible working hours\nWilling to provide surgery support\nScience / Nursing / Medical-related background /OT experiences is preferred\n\nEssential knowledge and skills:\n\nPossess excellent sales, communication and rapport-building skills to establish strong relationships with customers\nNew graduate / Operation Theatre Assistant (OTA) are welcome\nGood communication and interpersonal skills in both English and Chinese (written or verbal)\n\n\u00a0We offer :\n\nFive-day work week\nMedical insurance\nPerformance Bonus\nCommission\nTravelling Allowance", "employment_types": ["Full Time", "Permanent"], "selling_points": ["Friendly and passionate working environment", "Focus in infection control and medical consumables", "Fresh Graduates are welcome"], "locations": ["Kowloon Bay"], "categories": ["Sales, CS & Business Devpt", "Business Development", "Wholesale", "Direct Sales"], "post_time": "2022-01-13T09:03:57Z", "salary": {"currency": null, "max": null, "min": null, "period": "monthly", "term": null}, "salary_visible": false, "title_keywords": ["sales executive"], "responsibilities": [], "requirements": {"degrees": [], "majors": [], "languages": ["english", "chinese"], "language_level": ["good"], "hard_skills": ["make", "focus"], "soft_skills": ["flexible", "responsible", "communication", "communication and interpersonal skills", "focus", "presentation", "work under pressure"], "languages_combined": [{"language": "english", "language_level": ["good"]}, {"language": "chinese", "language_level": ["good"]}]}, "experience_required": {"duration": [], "field": ["related", "medical"]}}, {"job_id": "100003009027484", "location_code": "hk", "company": "Galleon International Limited", "job_title": "Sales & Service Support Clerk", "description": "Job Responsibilities:\n\nDrafting, preparing and typing invoices from the sales department\nHandling customers' enquiries\u00a0\nAssist in ad-hoc assignments\n\nRequirements:\u00a0\n\nLevel 2 or above in Chinese and English in HKDSE / HKCEE\nGood knowledge of computer software applications including MS word, excel\nGood command in Chinese & English", "employment_types": ["Full Time"], "selling_points": ["12 days Annual Leave", "Bank Holiday", "Salary HK$14K to HK$16K"], "locations": ["Kwai Hing"], "categories": ["Sales, CS & Business Devpt", "Wholesale", "Others", "Sales Administration"], "post_time": "2022-01-13T18:54:42Z", "salary": {"currency": null, "max": null, "min": null, "period": "monthly", "term": null}, "salary_visible": false, "title_keywords": ["clerk", "sales"], "responsibilities": ["ad-hoc assignments", "invoices"], "requirements": {"degrees": ["hkdse"], "majors": [], "languages": ["english", "chinese"], "language_level": ["good command"], "hard_skills": ["excel", "ms word"], "soft_skills": [], "languages_combined": [{"language": "english", "language_level": ["good command"]}, {"language": "chinese", "language_level": ["good command"]}]}, "experience_required": {"duration": [], "field": []}}, {"job_id": "100003009039098", "location_code": "hk", "company": "JW Industrial Development Limited", "job_title": "\u92b7\u552e\u52a9\u7406 (Sales Assistant)", "description": "\u5de5\u4f5c\u5167\u5bb9\uff1a\n\n\u8ddf\u9032\u6587\u66f8\u5de5\u4f5c\n\u5ba2\u6236\u8a62\u554f\u53ca\u8a02\u55ae\n\u516c\u53f8\u65e5\u5e38\u5de5\u4f5c\u5831\u544a\n\u5916\u52e4\u898b\u5ba2\n\u8981\u6c42:\n\n\u4e3b\u52d5\u3001\u71b1\u60c5\u3001\u826f\u597d\u7684\u6e9d\u901a\u80fd\u529b\uff0c\u8cac\u4efb\u5fc3\uff0c\u6e96\u6642\n\u7121\u76f8\u95dc\u5de5\u4f5c\u7d93\u9a57\u3001\u61c9\u5c46\u7562\u696d\u751f\u4ea6\u53ef\n\u5177\u57fa\u672c\u96fb\u8166\u6587\u66f8\u8655\u7406\uff0c\u4e2d\u82f1\u6587\u6253\u5b57\n\u5177\u4e00\u822c\u4e92\u806f\u7db2\u77e5\u8b58\n\u798f\u5229:\n\n\u9022\u9280\u884c\u5047\u671f(\u7d05\u65e5)\u4f11\u606f\n5-5.5\u5de5\u4f5c\u5929,\u9577\u77ed\u9031;\u9054\u5230\u76ee\u6a19\u53ef\u984d\u5916\u6709\u5047\u671f\n\u91ab\u7642\u4fdd\u96aa\u00a0\n\u54e1\u5de5\u8cfc\u7269\u512a\u60e0\n\u5728\u8077\u57f9\u8a13\n\u6649\u5347\u6a5f\u6703\n\u4ea4\u901a\u6d25\u8cbc", "employment_types": ["Full Time"], "selling_points": [], "locations": ["Kwai Hing"], "categories": ["Sales, CS & Business Devpt", "Wholesale", "Direct Sales"], "post_time": "2022-01-11T08:41:15Z", "salary": {"currency": null, "max": null, "min": null, "period": "monthly", "term": null}, "salary_visible": false, "title_keywords": ["\u92b7\u552e\u52a9\u7406", "sales assistant"], "responsibilities": [], "requirements": {"degrees": [], "majors": [], "languages": [], "language_level": [], "hard_skills": [], "soft_skills": [], "languages_combined": []}, "experience_required": {"duration": [], "field": []}}, {"job_id": "100003009039974", "location_code": "hk", "company": "Nicedrape Solar Protection System Company Limited", "job_title": "Sales Assistant", "description": "Responsibilities:\n\n\u00a0Contact Architects & interior designers for product specification and tendering\n\u00a0Contact with Property Developer & consultant for product promotion\n\u00a0Accountable for sales target through proactive and aggressive selling manner\n\u00a0Perform outstanding and professional customer service to achieve sales-target\n\u00a0Able to multi-task & work in a fast pace environment\n\u00a0Anticipate customer needs and be able to instantly provide appropriate solutions\n\u00a0Develop and maintain long term relationship with existing and prospective clients\n\u00a0Assist the sales operation and work as a team to achieve monthly sales target\nMaintain proper merchandising display in accordance with brand\u2019s requirement\nImplement marketing plan achieving target\n\n\u00a0Requirements:\n\nDiploma holder or above\nAggressive, self-motivated, pro-active problem solver, logical thinker and outgoing\nGood communication, presentation, customer service attitude and negotiation skills\nPossess sharp business sense\nStrong selling and presentation skills and able to work under tight schedule\nPresentable and able to accumulate product knowledge and sell confidently to customers\nKeen, reliable, independent and an organized and detailed person.\nGood command of written & spoken English and Mandarin\nGood PC knowledge and Chinese word processing\nExperienced in sales of interior material and deal with architect & interior designer\nSales experience with min 1 year in is preferable\n\nBenefits:\n\nBasic salary\u00a0\u00a0with attractivecommission\nDiscretional Bonus\nMedical allowance\nBirthday holiday\nAnnual Leave\nStaff discount\nCareer Path\u00a0\n\nInterested parties please send full resume with expected salary. Please click \"Apply Now\" to submit your application.", "employment_types": ["Full Time"], "selling_points": ["Diploma holder or above", "Sales experience with min 1 year in is preferable", "Experienced in sales of interior material and deal"], "locations": ["Tsuen Wan Area"], "categories": ["Manufacturing", "Product Development / Management", "Sales, CS & Business Devpt", "Wholesale", "Building & Construction", "Others"], "post_time": "2022-01-11T16:02:28Z", "salary": {"currency": null, "max": null, "min": null, "period": "monthly", "term": null}, "salary_visible": false, "title_keywords": ["sales assistant"], "responsibilities": ["sales target", "merchandising", "tendering", "develop", "marketing plan", "customer service", "maintain", "contact", "assist the sales"], "requirements": {"degrees": ["diploma holder"], "majors": [], "languages": ["english", "chinese", "mandarin"], "language_level": ["good command", "good"], "hard_skills": ["pc knowledge", "chinese word processing"], "soft_skills": ["outgoing", "organized", "self-motivated", "independent", "problem solver", "business sense", "keen", "presentable", "communication", "negotiation skills", "customer service", "presentation skills", "pro-active", "reliable", "presentation", "detailed"], "languages_combined": [{"language": "english", "language_level": ["good command", "good"]}, {"language": "chinese", "language_level": ["good"]}, {"language": "mandarin", "language_level": ["good command", "good"]}]}, "experience_required": {"duration": ["min 1 year"], "field": []}}, {"job_id": "100003009045774", "location_code": "hk", "company": "Randstad Hong Kong Limited", "job_title": "Merchandise Planner", "description": "about the company.\nOur client is a leading fashion retail company with a strong presence in the world. Their headcounts have been expanded by 25% last year. Currently they are hiring a Merchandise Planner to join their team. This is a new headcount.\n\nabout the job.\nAs a Merchandise Planner, you will\n-Partner with franchise partners on determining seasonal OTB & alignment with financial targets\n-Forecast order quantity for the assigned category\n-Undertake tactical actions to hit KPIs which include sales target, sell through and achieve optimal inventory level closing stocks\n-Support execution of pre-season activities which include launch planning, allocation plan, pricing for new season & range planning\n-Build and maintain productive relationships within the team, cross-functional teams and franchise partners\n-Understand country/partner level nuances and competitive landscape to optimise business performance\n\nskills & experiences required.\n-Degree in Finance/Accountancy/Business/Retail Management / Supply Chain\n-Candidates without prior experience would be considered\n-Excellent computing skills, proficient in MS Excel\n-Excellent interpersonal, planning and organisation skills to multi-task in a fast-paced environment\n-Positive work attitude and able to work under pressure\n-Good interpersonal and leadership skills\n-Enjoy interacting with people of diverse cultures\n-Keen sense of fashion and a passion or the fashion industry\n\nabout the package\n-5 day work\n-Double Pay\n-Discretionary Bonus\n-Medical Insurance\n-Dental Insurance\n-Regional Exposure\n-New Headcount\n-Summer time\n\nIf you're interested in this role, click 'apply now' to forward an up-to-date copy of your CV, or email to sally.lo@randstad.com.hk", "employment_types": ["Full Time", "Permanent"], "selling_points": ["Market leader in the industry", "Regional office in Hong Kong", "Young and dynamic working culture"], "locations": ["Not Specified"], "categories": ["Transportation & Logistics", "Supply Chain", "Sales, CS & Business Devpt", "Wholesale", "E-commerce", "Supply Chain"], "post_time": "2022-01-13T08:38:54Z", "salary": {"currency": "HKD", "max": 29999, "min": 20000, "period": "monthly", "term": null}, "salary_visible": true, "title_keywords": [], "responsibilities": ["management", "work under pressure", "sales target", "inventory", "otb", "maintain", "plan", "kpis", "insurance", "cross-functional teams", "planning"], "requirements": {"degrees": [], "majors": [], "languages": [], "language_level": [], "hard_skills": ["planner", "ms excel"], "soft_skills": ["productive", "multi-task", "fast-paced environment", "leadership skills", "interested in", "diverse", "organisation", "interpersonal", "work under pressure"], "languages_combined": []}, "experience_required": {"duration": [], "field": []}}, {"job_id": "100003009040407", "location_code": "hk", "company": "Re:echo Asia Pacific Limited", "job_title": "E-commerce Sales Officer", "description": "Responsibilities:\n\nManage online shop and update website content (product listing, Sales report, translate product description from English to Chinese)\nMake ongoing recommendations on keywords discovery, expansion and optimization in order to improve the keywords ranking\nPerform data analysis and to review the effectiveness of the promotion and the optimization of SEO, SEM and Google Ads\nPerform SEO for onsite product pages and blog articles\nDesign, creates contents and manage promotions in print and on social media platforms (Facebook, Instagram, YouTube and others)\nImplementation & creation of promotion material, print ad banner, EDM.\nWork with internal teams to follow up customers\u2019 online order inquires and after-sales support services\n\nJob Requirement:\u00a0\u00a0\n\nDegree or above in Business, Marketing, Advertising, Communications, E-commerce, management, or related discipline\nMinimum of 3 years of experience in e-commerce\nProficient in\u00a0computer skills,\u00a0MS Office (Word, Excel, PowerPoint etc.)\nProficient in Adobe CS, including Adobe Illustrator, Photoshop, Video production. or other graphic design tools preferred\nGood communication skill in spoken and written English, Chinese\nOutgoing personality, aggressive, independent and able to work under pressure\nImmediate available is a definite advantage\n\nBenefits:\n\n\n5 working days, annual leave, bank holiday, medical benefits and education allowance, etc.\n\nWorking Hours: Monday to Friday (9:00am - 6:00pm)\nInterested parties please click \u201cApply Now\u201d to submit your resume w/expected salary.", "employment_types": ["Full Time"], "selling_points": ["E-commerce Sales Officer", "Full-time (5-day)", "Sales & performance analysis"], "locations": ["Shatin Area"], "categories": ["Sales, CS & Business Devpt", "Wholesale", "E-commerce", "Business Development", "Marketing - Brand / Product Management"], "post_time": "2022-01-12T02:32:19Z", "salary": {"currency": null, "max": null, "min": null, "period": "monthly", "term": null}, "salary_visible": false, "title_keywords": ["sales officer"], "responsibilities": ["sales report", "seo", "product listing", "edm", "review", "social media platforms", "website", "design", "implementation", "data analysis", "teams", "support services", "sem", "contents", "facebook"], "requirements": {"degrees": ["degree or above"], "majors": ["business", "e-commerce", "communications", "marketing"], "languages": ["english", "chinese"], "language_level": ["good"], "hard_skills": ["excel", "e-commerce", "word", "powerpoint", "adobe illustrator", "computer skills", "photoshop", "adobe cs", "ms office"], "soft_skills": ["outgoing personality", "communication skill", "independent", "work under pressure"], "languages_combined": [{"language": "english", "language_level": ["good"]}, {"language": "chinese", "language_level": ["good"]}]}, "experience_required": {"duration": ["minimum of 3 years"], "field": ["e-commerce"]}}, {"job_id": "100003009043069", "location_code": "hk", "company": "Synnex Technology International (HK) Ltd", "job_title": "Account Manager (Commercial/ Retail)", "description": "Responsibilities :\n\nPromote IT products, solutions and services\nResponsible for business development and daily channel business engagement, through customers visit and presentation, pipelines and order management, to build an intimate and board channel\nLiaise with various parties internally (telesales, product, finance, technical & logistic) to provide quality customer account services and support to drive the revenue growth and customer satisfaction of the channel assigned in great details\n\nRequirement :\n\nCollege / University graduate with 2 years working experience\nPositive, mature, disciplined, motivated with good interpersonal skill\nOutgoing, energetic and good at communication\nProficient in both spoken and written English and Chinese\nCandidate with\u00a0more experience will be considered as Account Executive\n\nWe offer attractive remuneration package to the right candidate.\u00a0\u00a0Including on-job training, 5 days work week, medical insurance, performance incentive, etc.\n\nFor more information about Synnex, please visit\u00a0http://www.synnex.com.hk\n\n\nAll information will be treated in strict confidence and will be used exclusively for recruitment related purpose only.", "employment_types": ["Full Time", "Permanent"], "selling_points": [], "locations": ["Kowloon Bay"], "categories": ["Sales, CS & Business Devpt", "Business Development", "Channel / Distribution", "Wholesale"], "post_time": "2022-01-12T09:42:16Z", "salary": {"currency": null, "max": null, "min": null, "period": "monthly", "term": null}, "salary_visible": false, "title_keywords": ["account manager"], "responsibilities": ["liaise with", "order management", "revenue growth", "quality"], "requirements": {"degrees": ["university graduate"], "majors": [], "languages": ["english", "chinese"], "language_level": ["proficient"], "hard_skills": [], "soft_skills": ["outgoing", "mature", "interpersonal skill", "communication", "motivated", "energetic", "positive"], "languages_combined": [{"language": "english", "language_level": ["proficient"]}, {"language": "chinese", "language_level": ["proficient"]}]}, "experience_required": {"duration": ["2 years"], "field": []}}, {"job_id": "100003009037568", "location_code": "hk", "company": "Venchi HK Limited", "job_title": "Business Development Specialist", "description": "Job Responsibilities:\u00a0\n\nASEAN DISTRIBUTORS\n\nMonitor merchandising solutions with existing accounts ensuring standards of brand and profitability are achieved in a geographic area\nIncrease territory sales and profitability through existing account development and provides solutions to generate add-on sales and profits\nAssist the Business Development Manager in strategic business reviews\nDeveloping and structuring and providing new key information on merchandising and sales trends in existing stores\nProvides distributors with product, merchandising and staff training to ensure brand quality standards and consistency through the store network\nAssist distributors in implementing Company and Regional Guidelines\n\nTRAVEL RETAIL APAC AND BTB\n\nAssist the Business Development manager in identifying new potential accounts suitable to company positioning in assigned geographic area, including operators in Asean, Greater China, Australia, Korea and Japan\nAssist the Business Development manager in monitoring client\u2019s credit status\nProvide BTB clients / existing TR key accounts with training and merchandising information. Creation and delivery of business proposals included of proposed assortment, sales tools, visual merchandising, price information and targets\nAssist the International Team in identifying and organising fairs and exhibitions\nProvide timely commercial proposal and proactively look for new commercial opportunities\nConduction of store checks and competitors screening in assigned geographic area\nTogether with Corporate Marketing team, help in identifying, create and implement new trade marketing tools to reach sales target and generate add-on sales and profit\n\nJob Requirements:\n\nAt least 1.5 to 3 years of work-related experience. Retail and/or Food background is a plus\nProficiency in both written and spoken English, Cantonese and Mandarin\nExperience abroad (12+ months) is a plus\nAbility to work variable hours, including evenings and weekends, and to travel extensively (up to 30% of the time)\nSelf-motivated, Well organized, Multi-tasking, Good analytical and detail-minded with strong sense of responsibilities\u00a0", "employment_types": ["Full Time"], "selling_points": ["APAC Travel Retail", "ASEAN Distributors", "Corporate Sales"], "locations": ["Wan Chai"], "categories": ["Sales, CS & Business Devpt", "Business Development", "Wholesale", "Others"], "post_time": "2022-01-11T03:10:19Z", "salary": {"currency": null, "max": null, "min": null, "period": "monthly", "term": null}, "salary_visible": false, "title_keywords": ["specialist"], "responsibilities": ["trade marketing", "guidelines", "sales target", "monitoring", "merchandising", "monitor", "developing", "quality", "visual"], "requirements": {"degrees": [], "majors": [], "languages": ["cantonese", "english", "mandarin"], "language_level": ["proficiency"], "hard_skills": ["plus"], "soft_skills": ["detail-minded", "self-motivated", "well organized", "multi-tasking", "sense of responsibilities"], "languages_combined": [{"language": "cantonese", "language_level": ["proficiency"]}, {"language": "english", "language_level": ["proficiency"]}, {"language": "mandarin", "language_level": ["proficiency"]}]}, "experience_required": {"duration": ["5 to 3 years"], "field": ["related"]}}, {"job_id": "100003009044123", "location_code": "hk", "company": "Vitasoy International Holdings Ltd", "job_title": "Senior Telesales/ Telesales (\u96fb\u8a71\u92b7\u552e\u4ee3\u8868)", "description": "Key Responsibilities:\nSelling and promoting products through tele-sales\nHandles customer' enquiries and complaints\u00a0\nMakes outbound calls for customer order taking and maintains accurate order records\nProvides professional pre-sales and post-sales services to customer via phone\nPerforms ad hoc\u00a0duties as assigned\nRequirements:\nDiploma or above\n1 year experience in customer service / tele-sales\nProfessional telephone manner with good communication skills\nGood command of PC and MS office knowledge\nGood command of both spoken and written English and Chinese, including Mandarin\nCandidates with more and supervisory experience will be consider as senior position\nWays to apply:\u00a0\u00a0\nInterested parties please send your detailed resume stating your available date, current & expected salary to Human Resources Manager, by clicking the \u201cAPPLY NOW\u201d button below.\n\n\n\nAll information provided by applicants will be treated in strict confidence and used only for recruitment purposes. If you do not provide the information mentioned in the advertisement, we may not be able to assess your job application. You have the right to request access to, and correction of, your personal data held by us and you may lodge such request with our Data Protection Officer at pdpo@ vitasoy.com, but any such data access request will only be processed after the completion of the recruitment process.", "employment_types": ["Full Time", "Permanent"], "selling_points": ["Work Hour 0900-1800/ No Shift", "Warm calls only/ Basic + Commission", "Tuen Mun/ Medical/ Free shuttle bus/ Staff canteen"], "locations": ["Tuen Mun Area"], "categories": ["Sales, CS & Business Devpt", "Business Development", "Tele-sales (Telemarketing)", "Wholesale"], "post_time": "2022-01-13T03:08:24Z", "salary": {"currency": null, "max": null, "min": null, "period": "monthly", "term": null}, "salary_visible": false, "title_keywords": ["telesales"], "responsibilities": ["ad hoc duties", "order taking"], "requirements": {"degrees": ["diploma or above"], "majors": [], "languages": ["english", "chinese", "mandarin"], "language_level": ["good command"], "hard_skills": ["pc", "ms office"], "soft_skills": ["communication skills", "customer service", "telephone manner"], "languages_combined": [{"language": "english", "language_level": ["good command"]}, {"language": "chinese", "language_level": ["good command"]}, {"language": "mandarin", "language_level": ["good command"]}]}, "experience_required": {"duration": ["1 year"], "field": ["customer service", "supervisory experience"]}}, {"job_id": "100003009037606", "location_code": "hk", "company": "Circle K Convenience Stores (HK) Ltd", "job_title": "\u65e5\u73ed\u517c\u8077\u5009\u52d9\u54e1(\u9752\u8863)", "description": "\u8077\u8cac :\n\n\u8ca0\u8cac\u65e5\u5e38\u5009\u52d9\u5de5\u4f5c\u5305\u62ec\u642c\u8ca8\u3001\u57f7\u8ca8\u53ca\u5206\u8ca8\u7b49\n\u8cc7\u6b77 :\n\n\u6c92\u6709\u5b78\u6b77\u8981\u6c42; \u826f\u597d\u7cb5\u8a9e; \u7565\u61c2\u8b80\u5beb\u4e2d\u6587\n\u5f85\u9047 :\n\n\u6bcf\u5c0f\u6642$54.00 - $57.00, \u6709\u54e1\u5de5\u8cfc\u7269\u512a\u60e0, \u5728\u8077\u57f9\u8a13, \u91ab\u7642\u798f\u5229\u53ca\u8d85\u6642\u5de5\u4f5c\u6d25\u8cbc, \u4e0a\u53489\u6642\u81f3\u4e0b\u53488\u6642, \u6bcf\u9031\u5de5\u4f5c4\u5929\u81f36\u5929,\u8f2a\u4f11, \u6bcf\u5929\u5de5\u4f5c 5 - 11 \u5c0f\u6642\n\u7533\u8acb\u9808\u77e5 :\u6c42\u8077\u8005\u53ef\u81f4\u96fb29916268\u8207OK\u4fbf\u5229\u5e97\u6709\u9650\u516c\u53f8\u9673\u5c0f\u59d0\u806f\u7d61\u3002\n\n\u6709\u610f\u7533\u8acb\u8005\u8acb \u6309 APPLY NOW\u7533\u8acb\u00a0", "employment_types": ["Part Time"], "selling_points": [], "locations": ["Tsing Yi"], "categories": ["Transportation & Logistics", "Inventory / Warehousing", "Sales, CS & Business Devpt", "Wholesale", "Others"], "post_time": "2022-01-11T03:16:44Z", "salary": {"currency": null, "max": null, "min": null, "period": "hourly", "term": null}, "salary_visible": false, "title_keywords": [], "responsibilities": [], "requirements": {"degrees": [], "majors": [], "languages": [], "language_level": [], "hard_skills": [], "soft_skills": [], "languages_combined": []}, "experience_required": {"duration": [], "field": []}}, {"job_id": "100003009037603", "location_code": "hk", "company": "Circle K Convenience Stores (HK) Ltd", "job_title": "\u591c\u73ed\u5009\u52d9\u54e1(6\u5929)(\u9752\u8863)", "description": "\u8077\u8cac :\n\n\u8ca0\u8cac\u65e5\u5e38\u5009\u52d9\u5de5\u4f5c\u5305\u62ec\u642c\u8ca8, \u57f7\u8ca8\u53ca\u5206\u8ca8\u7b49\n\u8cc7\u6b77 :\n\n\u6c92\u6709\u5b78\u6b77\u8981\u6c42; \u826f\u597d\u7cb5\u8a9e; \u7565\u61c2\u8b80\u5beb\u4e2d\u6587\n\u5f85\u9047 :\n\n\u6bcf\u6708$15,080, \u6709\u5e74\u504712\u5929, \u54e1\u5de5\u8cfc\u7269\u512a\u60e0, \u5728\u8077\u57f9\u8a13, \u91ab\u7642\u798f\u5229\u53ca\u8d85\u6642\u5de5\u4f5c\u6d25\u8cbc, \u661f\u671f\u4e00\u81f3\u516d: \u4e0b\u534810\u6642\u81f3\u4e0a\u53487\u6642, \u6bcf\u9031\u5de5\u4f5c6\u5929, \u6bcf\u5929\u5de5\u4f5c 8 \u5c0f\u6642\n\u7533\u8acb\u9808\u77e5 :\u6c42\u8077\u8005\u53ef\u81f4\u96fb29916268\u8207OK\u4fbf\u5229\u5e97\u6709\u9650\u516c\u53f8\u9673\u5c0f\u59d0\u806f\u7d61\u3002\n\n\u6709\u610f\u7533\u8acb\u8005\u8acb \u6309 APPLY NOW\u7533\u8acb\n\n", "employment_types": ["Full Time"], "selling_points": [], "locations": ["Tsing Yi"], "categories": ["Transportation & Logistics", "Inventory / Warehousing", "Sales, CS & Business Devpt", "Wholesale", "Sales Administration"], "post_time": "2022-01-11T03:16:18Z", "salary": {"currency": null, "max": null, "min": null, "period": "monthly", "term": null}, "salary_visible": false, "title_keywords": [], "responsibilities": [], "requirements": {"degrees": [], "majors": [], "languages": [], "language_level": [], "hard_skills": [], "soft_skills": [], "languages_combined": []}, "experience_required": {"duration": [], "field": []}}, {"job_id": "100003009034909", "location_code": "hk", "company": "Starlight Design Limited", "job_title": "Jewelry Sales Executive", "description": "Our client, a Japanese Trading company is looking for candidates Japanese Speaking\u00a0Product Management\u00a0roles.\u00a0\n\nResponsibilities:\n\n\u203b\u4e0b\u8a18\u696d\u52d9\u3092\u884c\u3046\u30c1\u30fc\u30e0\u3092\u30de\u30cd\u30b8\u30e1\u30f3\u30c8\u3057\u3066\u3044\u305f\u3060\u304d\u307e\u3059\u3002\n\n\n\n\u65b0\u898f\u53d6\u308a\u6271\u3044\u5546\u54c1\u306e\u793e\u5185\u30b7\u30b9\u30c6\u30e0\u3078\u306e\u767b\u9332\n\u60c5\u5831\u5909\u66f4\u6642\u306e\u793e\u5185\u30b7\u30b9\u30c6\u30e0\u306e\u30c7\u30fc\u30bf\u66f4\u65b0\n\u5728\u5eab\u30c7\u30fc\u30bf\u306e\u7ba1\u7406\n\u5165\u8377\u5546\u54c1\u306e\u691c\u54c1\u3068\u54c1\u8cea\u30c1\u30a7\u30c3\u30af\n\nRequirements:\n\n\n\u5e83\u6771\u8a9e\u30d3\u30b8\u30cd\u30b9\u30ec\u30d9\u30eb\u3001\u65e5\u672c\u8a9e\u30cd\u30a4\u30c6\u30a3\u30d6\u30ec\u30d9\u30eb\n\n\u30de\u30cd\u30b8\u30e1\u30f3\u30c8\u7d4c\u9a13\u8005\u3000\nPC\u3092\u4f7f\u3063\u305f\u4e8b\u52d9\u306b\u3042\u308b\u7a0b\u5ea6\u7cbe\u901a\u3057\u3066\u3044\u308b\u65b9\n\u65e5\u672c\u52e4\u52d9\u307e\u305f\u306f\u65e5\u7cfb\u4f01\u696d\u52e4\u52d9\u7d4c\u9a13\u8005\n\nInterested candidates, kindly send your detailed resume in MS Word including:\n\n\n1) Expected salary\n2) Current and last drawn salaries\n3) Reason for leaving current and past employments\n\u00a0\ndirectly to:\u00a0jac.hk\u00a0@jac-recruitment.com and CC to:\u00a0akihisa.watanabe\u00a0@jac-recruitment.com\n\nPersonal data collected will be used for employment-related purpose only. We regret to inform that only shortlisted candidates will be notified, thank you", "employment_types": ["Full Time"], "selling_points": [], "locations": ["Hung Hom"], "categories": ["Sales, CS & Business Devpt", "Wholesale", "Direct Sales"], "post_time": "2022-01-10T04:53:20Z", "salary": {"currency": null, "max": null, "min": null, "period": "monthly", "term": null}, "salary_visible": false, "title_keywords": ["sales executive"], "responsibilities": [], "requirements": {"degrees": [], "majors": [], "languages": [], "language_level": [], "hard_skills": [], "soft_skills": [], "languages_combined": []}, "experience_required": {"duration": [], "field": []}}, {"job_id": "100003009038048", "location_code": "hk", "company": "Young Living Hong Kong Limited", "job_title": "Part-time Customer Service Assistant \u517c\u8077\u5ba2\u670d\u52a9\u7406", "description": "Our client, a\u00a0Online Game company is looking for candidates\u00a0Head of Japan VIP.\u00a0\n\n\n\nStrategy Execution:\n\nResponsible for developing, executing, and continuously improving the complete VIP strategy for the Japanese market. This plan needs to incorporate elements of all the areas listed below and to be achieved by liaising with senior stakeholders and the relevant teams of each:\n\nTranslate Commercial objectives into VIP Goals & KPI target setting\nConnect the VIP program across brands and setup a cohesive service & offering guideline\nAchieve and report on the overall performance of the VIP Team\nWork with other teams across the company to ensure alignment of respective strategies & implementation (Communications, Rewards, Product, Sustainability) and a seamless VIP enablement\u00a0\nDevelop VIP models to optimize the players performance, compensation & satisfaction\n\nOperational:\n\nOwnership of the VIP budget, target, and bonus costs\nCommunication - Coordinate with the VIP Team to handle any inquiries from the VIP players\nRelationship building with the VIP Players, both online and offline\nTake actions to secure excellent service level\nMonitor VIP players performance and report to senior stakeholders accordingly\nImprove the player profiling system & integrate results into the team\u2019s operational activities\nResponsible for the managed accounts pool including the addition/removal of managed accounts as per set criteria and to consistently report on and profile the players included\n\nTeam Management:\n\nManage & develop the VIP Team Specialists\nSupport team in maintaining relationships with the VIP players\nManage and resolve any VIP escalations from the team\nMaintain and explain VIP dashboards and reports\nDevelop and execute training programs for all new starters and Customer Service\n\nRequirements:\n\nMust:\n\n\nNative level Japanese, fluent English\nBachelor or higher educational degree\nAnalytical and detailed oriented\nSales driven\n2-3 years managerial experience\nAmbitious, goals-oriented, organized, proactive, communicative, big-picture view\n\nPreferred:\n\n2-3 years of Account Management experience\n2-3 years Customer Support experience\nInternational experience and mindset\nGood Excel & PPT skills\nSolid understanding of the psychology behind consumer behavior\n\n\u00a0Interested candidates, kindly send your detailed resume in MS Word including:\n\n1) Expected salary\n2) Current and last drawn salaries\n3) Reason for leaving current and past employments\n\u00a0\ndirectly to:\u00a0jac.hk\u00a0@jac-recruitment.com and CC to:\u00a0akihisa.watanabe\u00a0@jac-recruitment.com\n\nPersonal data collected will be used for employment-related purpose only. We regret to inform that only shortlisted candidates will be notified, thank you", "employment_types": ["Part Time", "Temporary", "Internship"], "selling_points": ["Fresh graduates welcomed", "HK$60 per hour", "Near MTR Station and Flexible working hours"], "locations": ["Causeway Bay"], "categories": ["Sales, CS & Business Devpt", "Customer Service - Supervisor / Officer", "Retail Sales", "Wholesale"], "post_time": "2022-01-11T04:44:21Z", "salary": {"currency": null, "max": null, "min": null, "period": "hourly", "term": null}, "salary_visible": false, "title_keywords": ["customer service assistant"], "responsibilities": ["budget", "communication", "maintain", "customer service", "plan", "costs", "maintaining", "teams", "liaising with", "developing", "implementation", "develop", "monitor", "reports", "setup", "report", "management", "coordinate with", "executing"], "requirements": {"degrees": ["degree", "bachelor"], "majors": [], "languages": ["japanese", "english"], "language_level": ["native", "fluent"], "hard_skills": ["excel"], "soft_skills": ["organized", "detailed oriented", "responsible", "cohesive", "communication", "customer service", "proactive", "driven"], "languages_combined": [{"language": "japanese", "language_level": ["native"]}, {"language": "english", "language_level": ["fluent"]}]}, "experience_required": {"duration": ["2-3 years"], "field": ["managerial", "account management"]}}, {"job_id": "100003009034689", "location_code": "hk", "company": "Serial Microelectronics (HK) Ltd", "job_title": "Sales Engineer", "description": "Our client, a\u00a0Online Game company is looking for candidates\u00a0Japanese Customer Support Agent.\n\nResponsibilities:\n\n\n\nNurture and support player relationships via phone, e-mail, and live chat.\nSeek resolutions to customer queries and issues whilst maintaining a personalized and caring attitude.\nAssist in the alignment of promotions across all customer communication channels.\nReceive, handle, and translate customers\u2019 KYC documents.\nAssist in English to Japanese translation work for new games and promotions.\nAssist in various ad-hoc projects and tasks.\n\nRequirements:\n\n\n\nNative level of written and spoken Japanese.\nIntermediate to fluent level of written and spoken English.\nAbility to listen and come up with solutions to customer problems.\nStrong communication and interpersonal skills.\nAbility to work independently and as part of a team.\nWork well under pressure.\nGeneral PC skills (Microsoft Word and Excel).\nBe flexible when it comes to working hours and able to work on a five day a week shift basis.\u00a0\n\n\u00a0Interested candidates, kindly send your detailed resume in MS Word including:\n\n1) Expected salary\n2) Current and last drawn salaries\n3) Reason for leaving current and past employments\n\u00a0\ndirectly to:\u00a0jac.hk\u00a0@jac-recruitment.com and CC to:\u00a0akihisa.watanabe\u00a0@jac-recruitment.com\n\nPersonal data collected will be used for employment-related purpose only. We regret to inform that only shortlisted candidates will be notified, thank you", "employment_types": ["Full Time"], "selling_points": ["A five-day, 40-hour workweek", "Excellent career prospect", "A competitive compensation system"], "locations": ["Kwai Hing"], "categories": ["Sales, CS & Business Devpt", "Sales - Sales Management", "Technical Sales / Sales Engineer", "Wholesale"], "post_time": "2022-01-10T03:57:21Z", "salary": {"currency": null, "max": null, "min": null, "period": "monthly", "term": null}, "salary_visible": false, "title_keywords": ["sales engineer"], "responsibilities": ["maintaining", "communication", "kyc", "customer queries", "ad-hoc projects"], "requirements": {"degrees": [], "majors": [], "languages": ["japanese", "english"], "language_level": ["native", "fluent", "intermediate"], "hard_skills": ["excel", "pc skills", "microsoft word"], "soft_skills": ["flexible", "work independently", "communication and interpersonal skills", "under pressure"], "languages_combined": [{"language": "japanese", "language_level": ["native"]}, {"language": "english", "language_level": ["fluent", "intermediate"]}]}, "experience_required": {"duration": [], "field": []}}, {"job_id": "100003009034790", "location_code": "hk", "company": "FRECO International Co., Limited", "job_title": "Sales Assistant (5 days work)", "description": "What you'll be doing...\n\n\nResponsible for introducing and selling company products to customers\nMaintain daily store operation with back-end\nBuild and maintain a good long term relationship with customers\nHandling complaint management and assisting customers\nWork closely with the Procurement team to do cross-selling\nProvide market feedback to internal team for increasing the operation service more effective\nAd-hoc tasks assigned by Seniors\n\nWe are looking for...\n\nF.5 graduate or Diploma\n1-2 years\u2019 Sales experience in Retail/ Catering/ Fruit business is highly preferred\u00a0\u00a0\nWilling to learn the new product knowledge is an advantage\nOrganization and problem-solving skills\nGood command of spoke in Cantonese, Mandarin and English\nProactive, outgoing and energetic\nCustomer service oriented\nCandidate with more experience can be as a Senior Sales Assistant", "employment_types": ["Full Time", "Permanent"], "selling_points": [], "locations": ["Kwai Hing"], "categories": ["Sales, CS & Business Devpt", "Business Development", "Retail Sales", "Wholesale"], "post_time": "2022-01-10T04:15:30Z", "salary": {"currency": null, "max": null, "min": null, "period": "monthly", "term": null}, "salary_visible": false, "title_keywords": ["sales assistant"], "responsibilities": ["management", "ad-hoc tasks", "maintain", "customer service", "catering"], "requirements": {"degrees": ["diploma"], "majors": [], "languages": ["cantonese", "english", "mandarin"], "language_level": ["good command"], "hard_skills": ["problem-solving skills"], "soft_skills": ["outgoing", "responsible", "customer service oriented", "willing to learn", "energetic", "problem-solving skills", "proactive"], "languages_combined": [{"language": "cantonese", "language_level": ["good command"]}, {"language": "english", "language_level": ["good command"]}, {"language": "mandarin", "language_level": ["good command"]}]}, "experience_required": {"duration": ["1-2 years"], "field": ["business", "retail"]}}, {"job_id": "100003009038310", "location_code": "hk", "company": "Streamline Consultancy Limited", "job_title": "Business Development Specialist (Food Retail)", "description": "Our Client is an international food retail company. \u00a0They are currently looking for professional to join their company:\n\nResponsibilities:\n\nMonitor merchandising solutions with existing accounts ensuring standards of brand and profitability are achieved in a geographic area\nIncrease territory sales and profitability through existing account development and provides solutions to generate add-on sales and profits\nDeveloping and structuring and providing new key information on merchandising and sales trends in existing stores\nProvides distributors with product, merchandising and staff training to ensure brand quality standards and consistency through the store network\nAssist distributors in implementing Company and Regional Guidelines\nAssist the BD Manager in identifying new potential accounts suitable to company positioning in assigned geographic area, including operators in Asean\nProvide BTB clients / existing TR key accounts with training and merchandising information. Creation and delivery of business proposals included of proposed assortment, sales tools, visual merchandising, price information and targets\nAssist the International Team in identifying and organising fairs and exhibitions\nTogether with Corporate Marketing team, help in identifying, create and implement new trade marketing tools to reach sales target and generate add-on sales and profit\n\nRequirements:\n\nMinimum 3 years of working experience in account business development and sales.\nRetail and/or Food background is a plus\nProficiency in both written and spoken English, Cantonese and Mandarin\nExperience abroad is a plus\nSelf-motivated, Well organized, Multi-tasking, Good analytical and detail-minded with strong sense of responsibilities\u00a0\n\n\n\nInterested parties please\u00a0send\u00a0your\u00a0full resume\u00a0via\u00a0\"Application Email\"\u00a0or click the following\u00a0\"Apply Now\"\u00a0button to attach your CV.\u00a0\u00a0\u00a0\u00a0\n\nAll information collected will be treated in confidence and for recruitment purpose only.\u00a0\u00a0", "employment_types": ["Full Time", "Permanent"], "selling_points": ["Identify potential account (Travel Retail /APAC)", "3 yrs BD/ account sales experience", "Attractive remuneration package"], "locations": ["Not Specified"], "categories": ["Sales, CS & Business Devpt", "Business Development", "Sales - Sales Management", "Wholesale"], "post_time": "2022-01-11T06:36:07Z", "salary": {"currency": null, "max": null, "min": null, "period": "monthly", "term": null}, "salary_visible": false, "title_keywords": ["specialist"], "responsibilities": ["trade marketing", "guidelines", "sales target", "merchandising", "monitor", "developing", "quality", "visual"], "requirements": {"degrees": [], "majors": [], "languages": ["cantonese", "english", "mandarin"], "language_level": ["proficiency"], "hard_skills": ["plus"], "soft_skills": ["detail-minded", "self-motivated", "well organized", "multi-tasking", "sense of responsibilities"], "languages_combined": [{"language": "cantonese", "language_level": ["proficiency"]}, {"language": "english", "language_level": ["proficiency"]}, {"language": "mandarin", "language_level": ["proficiency"]}]}, "experience_required": {"duration": ["minimum 3 years"], "field": ["business development"]}}, {"job_id": "100003009020745", "location_code": "hk", "company": "Appolo Ice-Cream Co Ltd", "job_title": "Key Account Executive", "description": "Job Responsibilities :\n\nWork closely with key account customers (buyers)\nPlan and execute trade promotion and sales activities to achieve sales target\nPrepare document and sales analysis for KA customers and internal in need\nRegular store visits to ensure execution excellence at store level\n\nRequirements :\n\nF.6 with at least 3 years solid experience in FMCG industry\nGood communication & negotiation skills\nProficient in computer skills including MS Word, Excel & PowerPoint\nGood command of both written & spoken English & Chinese\n\nInterest parties please send your resume with date available, present and EXPECTED SALARY via email\n\n(Data collected will be used for recruitment purpose only)", "employment_types": ["Permanent"], "selling_points": ["F.6 or above", "3 years of solid sales experience", "Good communication & negotiation skills"], "locations": ["Kwai Fong"], "categories": ["Sales, CS & Business Devpt", "Business Development", "Marketing / Public Relations", "Marketing - Brand / Product Management", "Wholesale"], "post_time": "2022-01-06T16:07:47Z", "salary": {"currency": null, "max": null, "min": null, "period": "monthly", "term": null}, "salary_visible": false, "title_keywords": ["key account executive"], "responsibilities": ["sales activities", "sales target", "analysis", "plan"], "requirements": {"degrees": [], "majors": [], "languages": ["english", "chinese"], "language_level": ["good command"], "hard_skills": ["excel", "fmcg industry", "powerpoint", "computer skills", "ms word"], "soft_skills": ["communication", "negotiation skills"], "languages_combined": [{"language": "english", "language_level": ["good command"]}, {"language": "chinese", "language_level": ["good command"]}]}, "experience_required": {"duration": ["at least 3 years"], "field": ["fmcg"]}}, {"job_id": "100003009033295", "location_code": "hk", "company": "Rich Sources (HK) Limited", "job_title": "Sales Representative (5 days working)", "description": "Job Description\n\n\u652f\u63f4\u92b7\u552e\u90e8\u65e5\u5e38\u5de5\u4f5c\n\u8ddf\u9032\u53ca\u5354\u52a9\u5ba2\u6236\u8a02\u55ae\n\u5206\u6d41/\u89e3\u7b54\u4f86\u81ea\u5ba2\u6236\u53ca\u6d88\u8cbb\u8005\u7684\u54a8\u8a62\u53ca\u6295\u8a34\n\u652f\u63f4\u5e02\u5834\u90e8\u5be6\u884c\u5404\u985e\u63a8\u5ee3\u6d3b\u52d5\n\u6309\u7167\u884c\u7a0b\u8a08\u5283\u5230\u8ca0\u8cac\u5e97\u8216\u6574\u7406\u8ca8\u67b6\u53ca\u9673\u5217\u00a0\n\nRequirement\n\n\u6b63\u9762\u7684\u601d\u7dad\u3001\u5916\u5411\u4e26\u71b1\u8877\u65bc\u4e8b\u696d\u767c\u5c55\u7684\u4eba\u6750\uff0c\u80fd\u4ee5\u884c\u52d5\u611f\u67d3\u8eab\u908a\u7684\u4eba\n\u4ee5\u89e3\u6c7a\u554f\u984c\u70ba\u7d42\u59cb\u7684\u4eba\u6750\u70ba\u512a\u5148\u8003\u616e\n\u6a02\u65bc\u5718\u968a\u5408\u4f5c\u4e26\u4ee5\u5718\u9ad4\u7684\u6210\u529f\u70ba\u9996\u8981\u76ee\u6a19\n\u5099\u67091\u5e74\u6216\u4ee5\u4e0a\u92b7\u552e\u7d93\u9a57\uff0c\u6709\u98fc\u990a\u5bf5\u7269\u8005\u512a\u5148\u8003\u616e\n\u826f\u597d\u7684\u4e2d\u82f1\u6587\u8b80\u5beb\u80fd\u529b\n\u81ea\u4fe1\u4e26\u64c1\u6709\u826f\u597d\u7684\u6e9d\u901a\u53ca\u5f85\u4eba\u8655\u4e8b\u6280\u5de7\n\u57fa\u790e\u4e2d\u82f1\u6587\u66f8\u5165\u6cd5\u53ca\u96fb\u8166\u6587\u66f8\u8edf\u4ef6\u61c9\u7528\ufe59WORD, EXCEL, POWERPOINT \u7b49\ufe5a\n*\u6240\u6709\u65b0\u5165\u8077\u54e1\u5de5\u5747\u4eab\u6709\u57f9\u8a13\u8ab2\u7a0b\uff0c\u638c\u63e1\u6709\u95dc\u5bf5\u7269\u98df\u54c1/\u7528\u54c1\u7684\u57fa\u790e\u77e5\u8b58", "employment_types": ["Full Time"], "selling_points": [], "locations": ["Kowloon Bay"], "categories": ["Sales, CS & Business Devpt", "Business Development", "Wholesale", "Direct Sales"], "post_time": "2022-01-09T05:13:52Z", "salary": {"currency": "HKD", "max": 19999, "min": 17000, "period": "monthly", "term": null}, "salary_visible": true, "title_keywords": ["sales representative"], "responsibilities": [], "requirements": {"degrees": [], "majors": [], "languages": [], "language_level": [], "hard_skills": ["excel", "powerpoint"], "soft_skills": [], "languages_combined": []}, "experience_required": {"duration": [], "field": []}}, {"job_id": "100003009033858", "location_code": "hk", "company": "Branford Limited", "job_title": "Sales Lead for Asian market (mainly for Japan or Korea)", "description": "Sales Leadfor Asian market (mainly for Japan or Korea)\n\nBranford Limited is currently looking for a talented and motivated Sales Lead with excellent knowledge of Asian Toy markets (mainly Japanese and Korean) to develop the sales of our brands in these markets. Please check all of the brands on www.Battatco.com\n\nResponsibilities:\n\nProvide administrative support to sales in connection with processing of inquiries, sales planning and sales orders for retailers in Asian Market.\nWork closely with Digital Marketing team to provide data insights & ad hoc analyses of Asian market trends;\nPrepare and submit for approval, item presentations, quote sheets on customer specific format and requirements;\nRepresent the company at marketing events such as trade shows;\nAssist in general office work and other administrative tasks as required.\u00a0\n\nSkills, Competencies & Requirements:\u00a0\n\nKnowledge of Japanese/ Korean culture\nJapanese / Korean with Excellent knowledge of English to deal with foreign divisions and Japanese / Korean customers is an advantage\nStrong knowledge and experience using Microsoft Office including Outlook & Excel;\nAbility to work as a team;\nExceptional organizational, administrative skills and attention to detail;\nStrong sense of responsibility;\nAble to multitask effectively and manage priorities;\nAbility to adapt to a constantly changing and dynamic environment;\nSome travel required (10%);\nA university degree in a related field\n\nExperience:\u00a0\n\nMinimum 5 years of experience in toy industry\u00a0\u00a0\n\nPlease feel free to visit our current Web Sites: ogdolls.com, myglittergirls.com, woodzeez.com, terrauniverse.com, mybtoys.com and battatco.com.\u00a0\n\nWelfare & Benefit follow Branford Limited\u2019s policy.\n\nWe thank all applicants for their interest however only selected candidates will be contacted.\n\nPlease apply with full resume and expected salary though applies now.", "employment_types": ["Permanent"], "selling_points": [], "locations": ["Tsim Sha Tsui"], "categories": ["Marketing / Public Relations", "Marketing - Direct Marketing", "Sales, CS & Business Devpt", "Wholesale", "Others"], "post_time": "2022-01-10T01:57:56Z", "salary": {"currency": null, "max": null, "min": null, "period": "monthly", "term": null}, "salary_visible": false, "title_keywords": ["lead", "sales"], "responsibilities": ["marketing events", "ad hoc", "data", "presentations", "digital marketing", "provide administrative support", "administrative tasks", "planning"], "requirements": {"degrees": ["university degree"], "majors": [], "languages": ["japanese", "english", "korean"], "language_level": ["advantage", "excellent"], "hard_skills": ["excel", "web", "microsoft office", "dynamic", "outlook"], "soft_skills": ["dynamic environment", "work as a team", "sense of responsibility", "organizational", "multitask", "attention to detail"], "languages_combined": [{"language": "japanese", "language_level": ["advantage", "excellent", "excellent"]}, {"language": "english", "language_level": ["excellent"]}, {"language": "korean", "language_level": ["advantage", "excellent", "excellent"]}]}, "experience_required": {"duration": ["minimum 5 years"], "field": []}}, {"job_id": "100003009032465", "location_code": "hk", "company": "Active Distribution Limited", "job_title": "Sales Executive / Channel Account Manager (Fix + Commission)", "description": "We are looking for a couple of enthusiastic, independent and organized candidates to help marketing\u00a0a range of global brand electronic products including Anker, Jabra, Verbatim, Lexar, etc. to Hong Kong Retail Market.\n\nThe Job\n\u2022\u00a0Identify new business opportunities to achieve revenue targets\n\u2022\u00a0Approach and acquire existing to new clients\n\u2022\u00a0Maintain and build long-term relationship with customers via door-to-door visit, cold call, etc.\n\u2022\u00a0Provide after-sales services to ensure customer satisfaction\n\n\u2022\u00a0\u78ba\u5b9a\u65b0\u7684\u5546\u6a5f\u4ee5\u5be6\u73fe\u6536\u5165\u76ee\u6a19\n\u2022\u00a0\u7372\u53d6\u65b0\u5ba2\u6236, \u4e26\u4fdd\u6301\u63a5\u89f8\u73fe\u6709\u5ba2\u6236\n\u2022\u00a0\u901a\u904e\u4e0a\u9580\u62dc\u8a2a\uff0c\u96fb\u8a71cold call\u7b49\u65b9\u5f0f\u8207\u5ba2\u6236\u4fdd\u6301\u4e26\u5efa\u7acb\u9577\u671f\u95dc\u4fc2\n\u2022\u00a0\u63d0\u4f9b\u552e\u5f8c\u670d\u52d9\uff0c\u78ba\u4fdd\u5ba2\u6236\u6eff\u610f\n\nThe Person\n\u2022\u00a0Secondary School graduated\n\u2022\u00a01 years or above sales & account management experience\n\u2022\u00a0Experience in distribution / wholesaling of electronic goods is preferred\n\u2022\u00a0Positive thinking, customer-oriented with good interpersonal skills\n\u2022\u00a0Good presentation and communication skills\n\u2022\u00a0PC literacy (MS Office - Excel & PowerPoint)\n\u2022\u00a0More experience will consider to senior position\n\n\u2022\u00a0\u4e2d\u5b78\u7562\u696d\n\u2022\u00a01\u5e74\u4ee5\u4e0a\u92b7\u552e\u548c\u5ba2\u6236\u7ba1\u7406\u7d93\u9a57\n\u2022\u00a0\u5177\u6709\u96fb\u5b50\u7522\u54c1\u5206\u92b7/\u6279\u767c\u7d93\u9a57\u8005\u512a\u5148\n\u2022\u00a0\u7a4d\u6975\u601d\u8003\uff0c\u4ee5\u5ba2\u6236\u70ba\u5c0e\u5411\n\u2022\u00a0\u826f\u597d\u7684\u8868\u9054\u80fd\u529b\u548c\u6e9d\u901a\u80fd\u529b\n\u2022\u00a0\u57fa\u672c\u7684\u96fb\u8166\u80fd\u529b\uff08MS Office \u2013 Word , Excel\u548cPowerPoint\uff09\n\u2022\u00a0\u66f4\u591a\u7d93\u9a57\u5c07\u8003\u616e\u64d4\u4efb\u9ad8\u7d1a\u8077\u4f4d\n\nWe offer career prospect, attractive remuneration and benefits package to the right candidate. To discuss this opportunity further, please send your full resume, present and expected salary to the HR Department via \"APPLY NOW\".\n\nWe are an equal opportunity employer and welcome applications from all qualified candidates. All information provided will be treated in strict confidence and used for recruitment purposes only. Applicants not hearing from us within six weeks may consider their applications unsuccessful. All data of unsuccessful applications will be destroyed after six months.", "employment_types": ["Full Time", "Permanent"], "selling_points": ["10+ Days Annual Leave", "5 days work week", "medical"], "locations": ["Kwai Hing"], "categories": ["Sales, CS & Business Devpt", "Channel / Distribution", "Wholesale", "Direct Sales"], "post_time": "2022-01-07T11:12:59Z", "salary": {"currency": null, "max": null, "min": null, "period": "monthly", "term": null}, "salary_visible": false, "title_keywords": ["account manager", "sales executive"], "responsibilities": ["business opportunities", "maintain"], "requirements": {"degrees": [], "majors": [], "languages": [], "language_level": [], "hard_skills": ["excel", "word", "powerpoint", "pc", "ms office"], "soft_skills": ["communication skills", "positive thinking", "customer-oriented", "interpersonal skills", "presentation"], "languages_combined": []}, "experience_required": {"duration": ["1 years"], "field": ["account management"]}}, {"job_id": "100003009043841", "location_code": "hk", "company": "CODALAB INTERNATIONAL CO LTD", "job_title": "Sales Associates \u552e\u8ca8\u54e1", "description": "\u4eba\u6c23\u98fe\u7269\u54c1\u724c, \u73fe\u9080\u8acb\u5145\u6eff\u6d3b\u529b\u7684\u4f60\u52a0\u5165\u6211\u5011\u7684\u5de5\u4f5c\u5718\u968a\u3002\n\nwww.codalab.co\n\nhttps://www.instagram.com/codalabaccessory/\n\nhttps://www.facebook.com/codalabaccessory\n\n\u798f\u5229\u5305\u62ec:\n\n\u8c50\u539a\u5e95\u85aa\u53ca\u4f63\u91d1\n\u5e74\u5e95\u82b1\u7d05\n\u6bcf\u67085\u65e5\u4f8b\u5047\u8d77\n\u6700\u9ad815\u5929\u6709\u85aa\u5e74\u5047(\u6309\u5e74\u8cc7\u905e\u589e)\n\u8d85\u6642\u6d25\u8cbc\n\u6709\u85aa\u5a5a\u5047\n\u751f\u65e5\u5047\u671f\n\u514d\u8cbb\u7522\u54c1\n\u54e1\u5de5\u8cfc\u7269\u512a\u60e0\n\u826f\u597d\u6649\u5347\u968e\u68af\n\n\u5de5\u4f5c\u8077\u8cac:\n\n\u7dad\u6301\u5e97\u8216\u65e5\u5e38\u904b\u4f5c\n\u9054\u6210\u5e97\u8216\u6bcf\u6708\u92b7\u552e\u76ee\u6a19\n\u63d0\u4f9b\u512a\u8cea\u9867\u5ba2\u670d\u52d9\n\u512a\u8cea\u7684\u5ba2\u6236\u670d\u52d9, \u4fdd\u6301\u54c1\u724c\u5f62\u8c61\n\n\u5de5\u4f5c\u8981\u6c42:\n\n\u6d41\u5229\u7cb5\u8a9e\u3001\u82f1\u8a9e\u3001\u53ca\u666e\u901a\u8a71\n\u6709\u8cac\u4efb\u5fc3\u3001\u6709\u79ae\u53ca\u53cb\u5584,\u8457\u91cd\u5718\u9ad4\u5408\u4f5c\u7cbe\u795e\u53ca\u6709\u826f\u597d\u4eba\u969b\u95dc\u4fc2\n\u7d93\u9a57\u8f03\u8cc7\u6df1\u8005\u53ef\u88ab\u8003\u616e\u70ba\u5e97\u8216\u4e3b\u7ba1\n\u6709\u98fe\u7269\u88fd\u4f5c\u624b\u85dd\u512a\u5148\n\n\u5de5\u4f5c\u5730\u9ede:\n\n\u9285\u947c\u7063\n\u5c16\u6c99\u5480\n\u6c99\u7530\n\u65fa\u89d2\n\n\u5982\u6709\u8208\u8da3\u7533\u8acb\u8077\u4f4d\u8acb\u6309 APPLY NOW\u7533\u8acb\u6216\u767c\u9001\u5c65\u6b77\u81f4\u516c\u53f8\u90f5\u7bb1\u6216whatsapp\u00a051922898\u00a0\u67e5\u8a62\u3002\n\n\u5de5\u4f5c\u985e\u578b: \u5168\u8077, \u9577\u5de5\n\n\u85aa\u916c: \u6bcf\u6708 $13,000.00 \u8d77\n\n\u6642\u9593:\n\n\u65e5\u73ed\n\n\u798f\u5229:\n\n\u5728\u8077\u5c08\u696d\u57f9\u8a13\n\u54e1\u5de5\u8cfc\u7269\u512a\u60e0\n\u6649\u5347\u6a5f\u6703\n\u7522\u5047\n\n\u88dc\u5145\u85aa\u916c:\n\n\u5e74\u7d42\u734e\u91d1\n\u4f63\u91d1\n\u8d85\u6642\u52a0\u73ed\u8cbb\n\u52e4\u5de5\u734e\u91d1\n\u7e3e\u6548\u734e\u91d1\n\n\u9060\u7a0b\u5de5\u4f5c:\n\n\u5426", "employment_types": ["Full Time"], "selling_points": [], "locations": ["Not Specified"], "categories": ["Sales, CS & Business Devpt", "Retail Sales", "Wholesale", "Others"], "post_time": "2022-01-13T02:08:35Z", "salary": {"currency": null, "max": null, "min": null, "period": "monthly", "term": null}, "salary_visible": false, "title_keywords": ["\u552e\u8ca8\u54e1", "sales"], "responsibilities": ["facebook"], "requirements": {"degrees": [], "majors": [], "languages": [], "language_level": [], "hard_skills": ["facebook"], "soft_skills": [], "languages_combined": []}, "experience_required": {"duration": [], "field": []}}, {"job_id": "100003009039270", "location_code": "hk", "company": "Aspire Designs Limited", "job_title": "Senior Sales Co-ordinator \u2013 Jewellery Industry (5 days work)", "description": "Job Description:\n\nDaily monitoring of the customer service department situation and report\nResolve matter / discrepancies / follow up with China marketing department / customer enquiries\nProvide supports to the sales people\nAssist in the exhibitions in HK and overseas if required\nCoordination with shipping and accounts department\nOverall communications between HK and China marketing department\n\n\nRequirement:\n\nDegree holder with 2-3 years full time working experience in Customer Service\nWork experience in the field of Jewellery / Watch is a compulsory\nKnowledge of jewellery software (JDB) system is more preferable\nGood communication and interpersonal skill\nGood command of spoken and written English and Chinese\nGood computer skills\n\nWe are looking for the person who cares about their customer!\n\nWe offer competitive remuneration and benefits with great prospects for personal fulfillment and career development.\n\nIf you are interested in the above role, please send your resume with your expected salary to us.", "employment_types": ["Full Time", "Permanent"], "selling_points": [], "locations": ["Tsim Sha Tsui"], "categories": ["Admin & HR", "Clerical / Admin Staff", "Sales, CS & Business Devpt", "Customer Service - Supervisor / Officer", "Wholesale"], "post_time": "2022-01-11T09:14:53Z", "salary": {"currency": null, "max": null, "min": null, "period": "monthly", "term": null}, "salary_visible": false, "title_keywords": ["senior sales"], "responsibilities": ["shipping", "customer enquiries", "coordination with", "customer service", "daily monitoring", "report"], "requirements": {"degrees": ["degree holder"], "majors": [], "languages": ["english", "chinese"], "language_level": ["good command"], "hard_skills": ["computer skills"], "soft_skills": ["communication", "customer service", "interpersonal skill"], "languages_combined": [{"language": "english", "language_level": ["good command"]}, {"language": "chinese", "language_level": ["good command"]}]}, "experience_required": {"duration": ["2-3 years"], "field": ["customer service"]}}, {"job_id": "100003009035048", "location_code": "hk", "company": "Ocean Harvest Frozen Food Limited", "job_title": "Data Entry Clerk \u6253\u55ae\u6587\u54e1 (Double Pay) - Chai Wan", "description": "Job Descriptions:\n\n\nResponsible for daily data entry and document filing\u00a0\nPreform general clerical works\nAssist in office ad hoc duties as assigned\nRequirements:\n\n\nHKDSE or HKCEE or above with 1-2 years experience\nAccurate and fast typing 30 words per minute in Chinese (\u5009\u9821/\u901f\u6210) and English respectively\u00a0\nProficient in Excel\u00a0is an advantage\nGood command of spoken and written in English and Chinese\nLive in Eastern District is highly preferable\nImmediate availability is highly preferable\n\nEmployment Terms:\nWorking in Chai Wan\nDouble Pay and Good Attendance Bonus\nWe offer attractive remuneration package to the right candidate. Interested parties please attach full resume with salary expected to apply by clicking the\u00a0Apply Now\u00a0button.\u00a0\n\n", "employment_types": ["Full Time"], "selling_points": [], "locations": ["Chai Wan"], "categories": ["Admin & HR", "Clerical / Admin Staff", "Sales, CS & Business Devpt", "Business Development", "Wholesale"], "post_time": "2022-01-10T05:36:01Z", "salary": {"currency": null, "max": null, "min": null, "period": "monthly", "term": null}, "salary_visible": false, "title_keywords": ["data entry clerk"], "responsibilities": ["ad hoc duties", "document filing", "data entry"], "requirements": {"degrees": ["hkdse"], "majors": [], "languages": ["english", "chinese"], "language_level": ["good command"], "hard_skills": ["excel", "wan", "typing", "words"], "soft_skills": ["accurate"], "languages_combined": [{"language": "english", "language_level": ["good command"]}, {"language": "chinese", "language_level": ["good command"]}]}, "experience_required": {"duration": ["1-2 years"], "field": []}}, {"job_id": "100003009030887", "location_code": "hk", "company": "Circle K Convenience Stores (HK) Ltd", "job_title": "\u517c\u8077\u5305\u88dd\u54e1(\u9752\u8863)", "description": "\u8077\u8cac :\n\n\u8ca0\u8cac\u5305\u88dd\uff1b\u65e5\u5e38\u5009\u52d9\u5de5\u4f5c\u5305\u62ec\u642c\u8ca8\u3001\u57f7\u8ca8\u53ca\u5206\u8ca8\u7b49\n\u8cc7\u6b77 :\n\n\u6c92\u6709\u5b78\u6b77\u8981\u6c42; \u826f\u597d\u7cb5\u8a9e; \u7565\u61c2\u8b80\u5beb\u4e2d\u6587\n\u5f85\u9047 :\n\n\u6bcf\u5c0f\u6642$54.00 - $57.00, \u6709\u54e1\u5de5\u8cfc\u7269\u512a\u60e0, \u5728\u8077\u57f9\u8a13, \u91ab\u7642\u798f\u5229\u53ca\u8d85\u6642\u5de5\u4f5c\u6d25\u8cbc, \u4e0a\u53489\u6642\u81f3\u4e0b\u53488\u6642, \u6bcf\u9031\u5de5\u4f5c4\u5929\u81f36\u5929,\u8f2a\u4f11, \u6bcf\u5929\u5de5\u4f5c 5 - 11 \u5c0f\u6642\n\u7533\u8acb\u9808\u77e5 :\u6c42\u8077\u8005\u53ef\u81f4\u96fb29916268\u8207OK\u4fbf\u5229\u5e97\u6709\u9650\u516c\u53f8\u9673\u5c0f\u59d0\u806f\u7d61\u3002\n\n\u6709\u610f\u7533\u8acb\u8005\u8acb \u6309 APPLY NOW\u7533\u8acb\u00a0", "employment_types": ["Part Time"], "selling_points": [], "locations": ["Tsing Yi"], "categories": ["Transportation & Logistics", "Fulfillment", "Inventory / Warehousing", "Sales, CS & Business Devpt", "Wholesale"], "post_time": "2022-01-07T08:32:03Z", "salary": {"currency": null, "max": null, "min": null, "period": "hourly", "term": null}, "salary_visible": false, "title_keywords": [], "responsibilities": [], "requirements": {"degrees": [], "majors": [], "languages": [], "language_level": [], "hard_skills": [], "soft_skills": [], "languages_combined": []}, "experience_required": {"duration": [], "field": []}}, {"job_id": "100003009031080", "location_code": "hk", "company": "Circle K Convenience Stores (HK) Ltd", "job_title": "\u65e5\u73ed\u5009\u52d9\u54e1(5\u5929) (\u9752\u8863)", "description": "\u8077\u8cac :\n\n\u8ca0\u8cac\u65e5\u5e38\u5009\u52d9\u5de5\u4f5c\u5305\u62ec\u642c\u8ca8\u3001\u57f7\u8ca8\u53ca\u5206\u8ca8\u7b49\n\u8cc7\u6b77 :\n\n\u6c92\u6709\u5b78\u6b77\u8981\u6c42; \u826f\u597d\u7cb5\u8a9e; \u7565\u61c2\u8b80\u5beb\u4e2d\u6587\n\u5f85\u9047 :\n\n\u6bcf\u6708$14,340, \u6709\u54e1\u5de5\u8cfc\u7269\u512a\u60e0, \u5728\u8077\u57f9\u8a13, \u91ab\u7642\u798f\u5229\u53ca\u8d85\u6642\u5de5\u4f5c\u6d25\u8cbc, \u4e0a\u53489\u6642\u81f3\u4e0b\u53488\u6642, \u6bcf\u9031\u5de5\u4f5c5\u5929,\u8f2a\u4f11, \u6bcf\u5929\u5de5\u4f5c 10 \u5c0f\u6642\n\u7533\u8acb\u9808\u77e5 :\u6c42\u8077\u8005\u53ef\u81f4\u96fb29916268\u8207OK\u4fbf\u5229\u5e97\u6709\u9650\u516c\u53f8\u9673\u5c0f\u59d0\u806f\u7d61\u3002\n\n\u6709\u610f\u7533\u8acb\u8005\u8acb \u6309 APPLY NOW\u7533\u8acb\u00a0", "employment_types": ["Full Time"], "selling_points": [], "locations": ["Tsing Yi"], "categories": ["Transportation & Logistics", "Inventory / Warehousing", "Sales, CS & Business Devpt", "Wholesale", "Sales Administration"], "post_time": "2022-01-07T08:55:21Z", "salary": {"currency": null, "max": null, "min": null, "period": "monthly", "term": null}, "salary_visible": false, "title_keywords": [], "responsibilities": [], "requirements": {"degrees": [], "majors": [], "languages": [], "language_level": [], "hard_skills": [], "soft_skills": [], "languages_combined": []}, "experience_required": {"duration": [], "field": []}}, {"job_id": "100003009030588", "location_code": "hk", "company": "Wellcome", "job_title": "\u5009\u52d9\u6587\u54e1 (\u65e9/\u4e2d\u73ed)", "description": "\u8077\u8cac :\n\n\u8ca0\u8cac\u8cc7\u6599\u8f38\u5165\uff0c\u8655\u7406\u65e5\u5e38\u5009\u52d9\u6587\u4ef6\uff0c\u8cc7\u6599\u6838\u5c0d\uff0c\u96fb\u8166\u6587\u66f8\u8655\u7406\u53ca\u4e00\u822c\u5009\u52d9\u5de5\u4f5c\n\u8cc7\u6b77 :\n\n\u4e2d\u4e94\u7a0b\u5ea6; \u826f\u597d\u7cb5\u8a9e; \u4e00\u822c\u82f1\u8a9e; \u61c2\u8b80\u5beb\u4e2d\u6587; \u61c2\u8b80\u5beb\u82f1\u6587; \u61c2Microsoft Office; \u61c2\u82f1\u6587\u6253\u5b57; \u61c2\u4e2d\u6587\u6253\u5b57; \u5177\u6709\u57fa\u672c\u96fb\u8166\u64cd\u4f5c\u77e5\u8b58\n\u5f85\u9047 :\n\n\u6bcf\u6708$12,600 - $12,900, \u6709\u96d9\u7ce7, \u5e74\u504712\u5929, \u9280\u884c\u5047\u671f, \u54e1\u5de5\u8cfc\u7269\u512a\u60e0, \u91ab\u7642\u798f\u5229, \u65b0\u4eba\u734e \u53ca\u8d85\u6642\u5de5\u4f5c\u6d25\u8cbc, \u4e0a\u53487\u6642\u81f3\u4e0b\u53483\u6642\u534a\u6216\u4e0b\u53482\u6642\u534a\u81f3\u4e0b\u534811\u6642, \u6bcf\u9031\u5de5\u4f5c6\u5929,\u8f2a\u4f11, \u6bcf\u5929\u5de5\u4f5c 7.5 \u5c0f\u6642, \u56fa\u5b9a\u66f4\n\u7533\u8acb\u9808\u77e5 :\u6c42\u8077\u8005\u53ef\u81f4\u96fb22998150\u8207\u4e03\uff0e\u5341\u4e00\u4f55\u5c0f\u59d0\u806f\u7d61\u3002\n\n\u6709\u610f\u7533\u8acb\u8005\u8acb \u6309 APPLY NOW\u7533\u8acb\u00a0", "employment_types": ["Full Time"], "selling_points": [], "locations": ["Others"], "categories": ["Admin & HR", "Clerical / Admin Staff", "Transportation & Logistics", "Inventory / Warehousing", "Sales, CS & Business Devpt", "Wholesale"], "post_time": "2022-01-07T07:50:15Z", "salary": {"currency": null, "max": null, "min": null, "period": "monthly", "term": null}, "salary_visible": false, "title_keywords": ["\u5009\u52d9\u6587\u54e1"], "responsibilities": [], "requirements": {"degrees": [], "majors": [], "languages": [], "language_level": [], "hard_skills": [], "soft_skills": [], "languages_combined": []}, "experience_required": {"duration": [], "field": []}}, {"job_id": "100003009031248", "location_code": "hk", "company": "WE Lighting Ltd", "job_title": "Sales Executive / Senior Sales Executive", "description": "WE Lighting Ltd\n\nWE Lighting Ltd is a lighting supplier in project basic, our main business is focus on Hong Kong market. To cope with the business development, we invite high caliber individuals with a keen interest to develop a career with us.\n\nResponsibilities\n\nProvide customer service to professional client including interior designer, consultant, architectural, contractor\nPrepare lighting proposal and specification\nArrange customer visit, road show presentation and product introduction\nLiaise with other functional department for project coordination\n\nRequirements\n\nHigher Diploma or Bachelor degree in Business / Engineering\u00a0or related disciplines\n2 years working experience, lighting related discipline is an advantage\nA good team player, can work under pressure\nEnergetic and customer oriented\nGood computer literature in MS Office\nGood command of spoken and written English and Chinese\n\n5 day-work will be offered, birthday leave,\u00a0good career path & attractive remuneration packages for the right candidate.\u00a0 If you think you can accept this challenging work and if you think you are energetic, please send your full career details, together with your current and expected salary by clicking \"Apply Now\"", "employment_types": ["Full Time"], "selling_points": ["5 days work, Birthday Leave", "Good Career Path", "Fresh graduate are welcome"], "locations": ["Lai Chi Kok"], "categories": ["Engineering", "Electrical / Electronics", "Sales, CS & Business Devpt", "Technical Sales / Sales Engineer", "Wholesale"], "post_time": "2022-01-07T09:05:24Z", "salary": {"currency": null, "max": null, "min": null, "period": "monthly", "term": null}, "salary_visible": false, "title_keywords": ["senior sales executive", "sales executive"], "responsibilities": ["provide customer service", "liaise with", "project coordination"], "requirements": {"degrees": ["diploma", "degree", "bachelor"], "majors": ["related disciplines", "business", "engineering"], "languages": ["english", "chinese"], "language_level": ["good command"], "hard_skills": ["ms office"], "soft_skills": ["good team player", "energetic", "work under pressure"], "languages_combined": [{"language": "english", "language_level": ["good command"]}, {"language": "chinese", "language_level": ["good command"]}]}, "experience_required": {"duration": ["2 years"], "field": ["related"]}}, {"job_id": "100003009033323", "location_code": "hk", "company": "Chandler Macleod Group (HK) Limited", "job_title": "Merchandising Assistant (Luxury, 18K)", "description": "Responsibilities\n\nUpdate daily / weekly / monthly sales report and analyze the market trend.\nFollow up with Asia Pacific markets stock request and arrange stock rebalancing.\nSupport the team in developing catalogues and selling tools.\nSupport the after sales services for Asia Pacific.\nProvide extensive day-to-day operational and administrative supports\nHandle other ad hoc, miscellaneous tasks and projects related to the business.\n\nRequirement\n\nTertiary education in Business Management, Fashion Merchandising, or related discipline.\n1 year working experience in buying & merchandising\nGood interpersonal skill, detail-oriented, willing to learn and able to work under pressure.\nGood command of spoken and written English, Cantonese and Mandarin.\nProficient in MS Office, Excel (pivot table, vlookup, etc.) and PowerPoint.\nImmediate availability preferred", "employment_types": ["Full Time", "Permanent"], "selling_points": ["Market Leader in Retail Sector", "Genuine Development Opportunity", "A Growing Business"], "locations": ["Quarry Bay"], "categories": ["Sales, CS & Business Devpt", "Retail Sales", "Wholesale", "Sales Administration"], "post_time": "2022-01-09T08:06:03Z", "salary": {"currency": null, "max": null, "min": null, "period": "monthly", "term": null}, "salary_visible": false, "title_keywords": ["merchandising assistant"], "responsibilities": ["ad hoc", "monthly sales report", "support the team", "developing"], "requirements": {"degrees": [], "majors": [], "languages": ["cantonese", "english", "mandarin"], "language_level": ["good command"], "hard_skills": ["business management", "excel", "pivot table", "powerpoint", "vlookup", "ms office"], "soft_skills": ["detail-oriented", "work under pressure", "willing to learn", "interpersonal skill"], "languages_combined": [{"language": "cantonese", "language_level": ["good command"]}, {"language": "english", "language_level": ["good command"]}, {"language": "mandarin", "language_level": ["good command"]}]}, "experience_required": {"duration": ["1 year"], "field": ["merchandising"]}}, {"job_id": "100003009028256", "location_code": "hk", "company": "Common Good Trading Limited", "job_title": "\u5168\u8077\u552e\u8ca8\u54e1 (\u98df\u54c1)", "description": "\u5730\u5340 :\u7c89\u5dba,\u592a\u548c\n\u884c\u696d :\u96f6\u552e\u696d\n\u8077\u8cac :\u6536\u9280, \u8ca0\u8cac\u7522\u54c1\u4ecb\u7d39\u53ca\u92b7\u552e, \u5e97\u92ea\u65e5\u5e38\u7406\u8ca8\u53ca\u904b\u4f5c\n\u8cc7\u6b77 :\u4e2d\u4e09\u7a0b\u5ea6; \u826f\u597d\u7cb5\u8a9e; \u4e00\u822c\u666e\u901a\u8a71; \u4e00\u822c\u82f1\u8a9e; \u7565\u61c2\u8b80\u5beb\u4e2d\u6587; \u7565\u61c2\u8b80\u5beb\u82f1\u6587; \u6709\u8cac\u4efb\u611f, \u6709\u8010\u6027, \u6709\u79ae\u53ca\u826f\u597d\u6e9d\u901a\u6280\u5de7\n\u5f85\u9047 :\u6bcf\u6708$11,000 - $12,000, \u6709\u96d9\u7ce7, \u52e4\u5de5\u734e\u91d1, \u54e1\u5de5\u8cfc\u7269\u512a\u60e0 \u53ca\u65b0\u4eba\u734e$2000, \u4e0a\u53488\u6642\u534a\u81f3\u4e0b\u53485\u6642\u534a\u6216\u4e0a\u534811\u6642\u81f3\u4e0b\u53488\u6642, \u6bcf\u9031\u5de5\u4f5c5\u5929\u81f36\u5929,\u8f2a\u73ed,\u8f2a\u4f11, \u6bcf\u5929\u5de5\u4f5c 9 \u5c0f\u6642\n\u7533\u8acb\u9808\u77e5 :\u6c42\u8077\u8005\u8acb\u6309 APPLY NOW\u7533\u8acb", "employment_types": ["Full Time"], "selling_points": [], "locations": ["Fanling"], "categories": ["Sales, CS & Business Devpt", "Retail Sales", "Wholesale", "Others"], "post_time": "2022-01-07T01:54:10Z", "salary": {"currency": null, "max": null, "min": null, "period": "monthly", "term": null}, "salary_visible": false, "title_keywords": [], "responsibilities": [], "requirements": {"degrees": [], "majors": [], "languages": [], "language_level": [], "hard_skills": [], "soft_skills": [], "languages_combined": []}, "experience_required": {"duration": [], "field": []}}, {"job_id": "100003009030274", "location_code": "hk", "company": "CODALAB INTERNATIONAL CO LTD", "job_title": "Sales Associates \u552e\u8ca8\u54e1", "description": "\u4eba\u6c23\u98fe\u7269\u54c1\u724c, \u73fe\u9080\u8acb\u5145\u6eff\u6d3b\u529b\u7684\u4f60\u52a0\u5165\u6211\u5011\u7684\u5de5\u4f5c\u5718\u968a\u3002\n\nwww.codalab.co\n\nhttps://www.instagram.com/codalabaccessory/\n\nhttps://www.facebook.com/codalabaccessory\n\n\u798f\u5229\u5305\u62ec:\n\n\u8c50\u539a\u5e95\u85aa\u53ca\u4f63\u91d1\n\u5e74\u5e95\u82b1\u7d05\n\u6bcf\u67085\u65e5\u4f8b\u5047\u8d77\n\u6700\u9ad815\u5929\u6709\u85aa\u5e74\u5047(\u6309\u5e74\u8cc7\u905e\u589e)\n\u8d85\u6642\u6d25\u8cbc\n\u6709\u85aa\u5a5a\u5047\n\u751f\u65e5\u5047\u671f\n\u514d\u8cbb\u7522\u54c1\n\u54e1\u5de5\u8cfc\u7269\u512a\u60e0\n\u826f\u597d\u6649\u5347\u968e\u68af\n\n\u5de5\u4f5c\u8077\u8cac:\n\n\u7dad\u6301\u5e97\u8216\u65e5\u5e38\u904b\u4f5c\n\u9054\u6210\u5e97\u8216\u6bcf\u6708\u92b7\u552e\u76ee\u6a19\n\u63d0\u4f9b\u512a\u8cea\u9867\u5ba2\u670d\u52d9\n\u512a\u8cea\u7684\u5ba2\u6236\u670d\u52d9, \u4fdd\u6301\u54c1\u724c\u5f62\u8c61\n\n\u5de5\u4f5c\u8981\u6c42:\n\n\u6d41\u5229\u7cb5\u8a9e\u3001\u82f1\u8a9e\u3001\u53ca\u666e\u901a\u8a71\n\u6709\u8cac\u4efb\u5fc3\u3001\u6709\u79ae\u53ca\u53cb\u5584,\u8457\u91cd\u5718\u9ad4\u5408\u4f5c\u7cbe\u795e\u53ca\u6709\u826f\u597d\u4eba\u969b\u95dc\u4fc2\n\u7d93\u9a57\u8f03\u8cc7\u6df1\u8005\u53ef\u88ab\u8003\u616e\u70ba\u5e97\u8216\u4e3b\u7ba1\n\u6709\u98fe\u7269\u88fd\u4f5c\u624b\u85dd\u512a\u5148\n\n\u5de5\u4f5c\u5730\u9ede:\n\n\u9285\u947c\u7063\n\u5c16\u6c99\u5480\n\u6c99\u7530\n\u65fa\u89d2\n\n\u5982\u6709\u8208\u8da3\u7533\u8acb\u8077\u4f4d\u8acb\u6309 APPLY NOW\u7533\u8acb\u6216\u767c\u9001\u5c65\u6b77\u81f4\u516c\u53f8\u90f5\u7bb1\u6216whatsapp\u00a051922898\u00a0\u67e5\u8a62\u3002\n\n\u5de5\u4f5c\u985e\u578b: \u5168\u8077, \u9577\u5de5\n\n\u85aa\u916c: \u6bcf\u6708 $13,000.00 \u8d77\n\n\u6642\u9593:\n\n\u65e5\u73ed\n\n\u798f\u5229:\n\n\u5728\u8077\u5c08\u696d\u57f9\u8a13\n\u54e1\u5de5\u8cfc\u7269\u512a\u60e0\n\u6649\u5347\u6a5f\u6703\n\u7522\u5047\n\n\u88dc\u5145\u85aa\u916c:\n\n\u5e74\u7d42\u734e\u91d1\n\u4f63\u91d1\n\u8d85\u6642\u52a0\u73ed\u8cbb\n\u52e4\u5de5\u734e\u91d1\n\u7e3e\u6548\u734e\u91d1\n\n\u9060\u7a0b\u5de5\u4f5c:\n\n\u5426", "employment_types": ["Full Time"], "selling_points": ["\u7dad\u6301\u5e97\u8216\u65e5\u5e38\u904b\u4f5c", "\u9054\u6210\u5e97\u8216\u6bcf\u6708\u92b7\u552e\u76ee\u6a19", "\u6709\u98fe\u7269\u88fd\u4f5c\u624b\u85dd\u512a\u5148"], "locations": ["Not Specified"], "categories": ["Sales, CS & Business Devpt", "Retail Sales", "Wholesale", "Others"], "post_time": "2022-01-07T07:08:05Z", "salary": {"currency": null, "max": null, "min": null, "period": "monthly", "term": null}, "salary_visible": false, "title_keywords": ["\u552e\u8ca8\u54e1", "sales"], "responsibilities": ["facebook"], "requirements": {"degrees": [], "majors": [], "languages": [], "language_level": [], "hard_skills": ["facebook"], "soft_skills": [], "languages_combined": []}, "experience_required": {"duration": [], "field": []}}, {"job_id": "100003009031032", "location_code": "hk", "company": "Circle K Convenience Stores (HK) Ltd", "job_title": "\u65e5\u73ed\u4e09\u5929\u5009\u52d9\u54e1(\u9752\u8863)", "description": "\u8077\u8cac :\n\n\u8ca0\u8cac\u65e5\u5e38\u5009\u52d9\u5de5\u4f5c\u5305\u62ec\u642c\u8ca8\u3001\u57f7\u8ca8\u53ca\u5206\u8ca8\u7b49\n\u8cc7\u6b77 :\n\n\u6c92\u6709\u5b78\u6b77\u8981\u6c42; \u826f\u597d\u7cb5\u8a9e; \u7565\u61c2\u8b80\u5beb\u4e2d\u6587\n\u5f85\u9047 :\n\n\u6bcf\u6708$7,100 - $7,700, \u6709\u54e1\u5de5\u8cfc\u7269\u512a\u60e0, \u5728\u8077\u57f9\u8a13, \u91ab\u7642\u798f\u5229, \u8d85\u6642\u5de5\u4f5c\u6d25\u8cbc\u53ca\u6649\u5347\u6a5f\u6703, \u4e0a\u53489\u6642\u81f3\u4e0b\u53488\u6642, \u6bcf\u9031\u5de5\u4f5c3\u5929, \u8f2a\u73ed, \u8f2a\u4f11, \u6bcf\u5929\u5de5\u4f5c 10 \u5c0f\u6642\n\u7533\u8acb\u9808\u77e5 :\u6c42\u8077\u8005\u53ef\u81f4\u96fb29916268\u8207OK\u4fbf\u5229\u5e97\u6709\u9650\u516c\u53f8\u9673\u5c0f\u59d0\u806f\u7d61\u3002\n\n\u6709\u610f\u7533\u8acb\u8005\u8acb \u6309 APPLY NOW\u7533\u8acb\u00a0", "employment_types": ["Full Time"], "selling_points": [], "locations": ["Tsing Yi"], "categories": ["Transportation & Logistics", "Inventory / Warehousing", "Sales, CS & Business Devpt", "Sales - Sales Management", "Wholesale"], "post_time": "2022-01-07T08:50:39Z", "salary": {"currency": null, "max": null, "min": null, "period": "monthly", "term": null}, "salary_visible": false, "title_keywords": [], "responsibilities": [], "requirements": {"degrees": [], "majors": [], "languages": [], "language_level": [], "hard_skills": [], "soft_skills": [], "languages_combined": []}, "experience_required": {"duration": [], "field": []}}, {"job_id": "100003009031011", "location_code": "hk", "company": "Circle K Convenience Stores (HK) Ltd", "job_title": "\u4e09\u5929\u591c\u73ed\u5009\u52d9\u54e1(\u9752\u8863)", "description": "\u8077\u8cac :\n\n\u8ca0\u8cac\u65e5\u5e38\u5009\u52d9\u5de5\u4f5c\u5305\u62ec\u642c\u8ca8\u3001\u57f7\u8ca8\u53ca\u5206\u8ca8\u7b49\n\u8cc7\u6b77 :\n\n\u6c92\u6709\u5b78\u6b77\u8981\u6c42; \u826f\u597d\u7cb5\u8a9e; \u7565\u61c2\u8b80\u5beb\u4e2d\u6587\n\u5f85\u9047 :\n\n\u6bcf\u6708$8,400 - $9,100, \u6709\u54e1\u5de5\u8cfc\u7269\u512a\u60e0, \u5728\u8077\u57f9\u8a13, \u91ab\u7642\u798f\u5229\u53ca\u8d85\u6642\u5de5\u4f5c\u6d25\u8cbc, \u4e0b\u53488\u6642\u81f3\u4e0a\u53487\u6642, \u6bcf\u9031\u5de5\u4f5c3\u5929, \u8f2a\u4f11, \u6bcf\u5929\u5de5\u4f5c 10 \u5c0f\u6642\n\u7533\u8acb\u9808\u77e5 :\u6c42\u8077\u8005\u53ef\u81f4\u96fb29916268\u8207OK\u4fbf\u5229\u5e97\u6709\u9650\u516c\u53f8\u9673\u5c0f\u59d0\u806f\u7d61\u3002\n\n\u6709\u610f\u7533\u8acb\u8005\u8acb \u6309 APPLY NOW\u7533\u8acb\u00a0", "employment_types": ["Full Time"], "selling_points": [], "locations": ["Tsing Yi"], "categories": ["Transportation & Logistics", "Inventory / Warehousing", "Sales, CS & Business Devpt", "Sales - Sales Management", "Wholesale"], "post_time": "2022-01-07T08:49:10Z", "salary": {"currency": null, "max": null, "min": null, "period": "monthly", "term": null}, "salary_visible": false, "title_keywords": [], "responsibilities": [], "requirements": {"degrees": [], "majors": [], "languages": [], "language_level": [], "hard_skills": [], "soft_skills": [], "languages_combined": []}, "experience_required": {"duration": [], "field": []}}, {"job_id": "100003009030562", "location_code": "hk", "company": "Wellcome", "job_title": "\u5e97\u52d9\u7d44\u9577", "description": "\u8077\u8cac:\n\n\u8ca0\u8cac\u5354\u52a9\u7d93\u7406\u8655\u7406\u5e97\u8216\u4e8b\u52d9\u53ca\u5e97\u8216\u65e5\u5e38\u904b\u4f5c,\u5305\u62ec\u6536\u9280\u7406\u8ca8\ufe51\u8ca8\u54c1\u9673\u5217\ufe51\u5e97\u8216\u6574\u6f54\u53ca\u9867\u5ba2\u670d\u52d9\u7b49 [\u6709\u96c6\u5718\u8cfc\u7269\u512a\u60e0, \u7279\u5225\u5730\u5340\u6d25\u8cbc, \u54e1\u5de5\u53ca\u5bb6\u5c6c\u91ab\u7642\u512a\u60e0(\u4e2d\u897f\u91ab, \u8dcc\u6253\u53ca\u7259\u91ab), \u6709\u85aa\u5a5a\u5047\u53ca\u514d\u4f9b\u6b3e\u9000\u4f11\u8a08\u5283]\n\u8cc7\u6b77 :\n\n\u4e2d\u4e09\u7a0b\u5ea6; 2\u5e74\u7d93\u9a57; \u826f\u597d\u7cb5\u8a9e; \u61c2\u8b80\u5beb\u4e2d\u6587; \u61c2\u95b1\u8b80\u82f1\u6587; 2\u5e74\u6216\u4ee5\u4e0a\u96f6\u552e\u7d93\u9a57\n\u5f85\u9047 :\n\n\u6bcf\u6708$12,950 - $15,150, \u6709\u96d9\u7ce7, \u5e74\u504712\u5929, \u9280\u884c\u5047\u671f, \u5176\u4ed6\u6d25\u8cbc/\u798f\u5229, \u8d85\u6642\u5de5\u4f5c\u6d25\u8cbc, \u901a\u5bb5\u73ed\u6d25\u8cbc, \u92b7\u552e\u734e\u91d1, \u65e9\u73ed\u6216\u4e2d\u73ed\u6216\u901a\u5bb5\u73ed(\u4e0a\u53487\u6642\u81f3\u7fcc\u65e5\u4e0a\u53487\u6642), \u6bcf\u5929\u5de5\u4f5c9\u5c0f\u6642, \u6bcf\u9031\u5de5\u4f5c6\u5929, \u8f2a\u73ed, \u8f2a\u4f11\n\u7533\u8acb\u9808\u77e5 :\u50f1\u4e3b\u5c07\u65bc1\u670811\u65e5\u4e0b\u53482\u6642\u81f3\u4e0b\u53484:30\u5728\u8343\u7063\u5c31\u696d\u4e2d\u5fc3\u8209\u884c\u62db\u8058\u65e5(\u6c42\u8077\u8005\u8acb\u81f4\u96fb2417 6238\u9810\u7d04\u9762\u8a66\uff0c\u540d\u984d\u6709\u9650\uff0c\u5148\u5230\u5148\u5f97\uff0c\u984d\u6eff\u5373\u6b62)\n\n\u6709\u610f\u7533\u8acb\u8005\u8acb \u6309 APPLY NOW\u7533\u8acb\u00a0", "employment_types": ["Full Time"], "selling_points": [], "locations": ["Not Specified"], "categories": ["Sales, CS & Business Devpt", "Customer Service - Supervisor / Officer", "Retail Sales", "Wholesale"], "post_time": "2022-01-07T07:45:36Z", "salary": {"currency": null, "max": null, "min": null, "period": "monthly", "term": null}, "salary_visible": false, "title_keywords": [], "responsibilities": [], "requirements": {"degrees": [], "majors": [], "languages": [], "language_level": [], "hard_skills": [], "soft_skills": [], "languages_combined": []}, "experience_required": {"duration": [], "field": []}}, {"job_id": "100003009035172", "location_code": "hk", "company": "KAO (Hong Kong) Ltd", "job_title": "\u5916\u52e4\u7406\u8ca8\u54e1 (\u517c\u8077)", "description": "\u8077\u8cac\uff1a\n\n\u6574\u7406\u3001\u6e05\u6f54\u53ca\u88dc\u5145\u5316\u599d\u54c1\u96f6\u552e\u9023\u9396\u5e97\u9673\u5217\u4e4b\u8ca8\u54c1\uff0c\u78ba\u4fdd\u8ca8\u54c1\u8ca8\u91cf\u5145\u8db3\n\u6839\u64da\u5e97\u8216\u8ca8\u91cf\u63d0\u4f9b\u8a02\u8ca8\u5efa\u8b70\n\u6536\u96c6\u5e02\u5834\u8cc7\u6599\n\u8207\u96f6\u552e\u5546\u5efa\u7acb\u53ca\u7dad\u6301\u826f\u597d\u95dc\u4fc2\n\n\u8077\u4f4d\u8981\u6c42\uff1a\n\n\u5b78\u6b77\u4e0d\u62d8\uff0c\u5177\u76f8\u95dc\u7d93\u9a57\u512a\u5148\n\u826f\u597d\u7cb5\u8a9e\uff0c\u61c2\u8b80\u5beb\u4e2d\u6587\uff0c\u4e00\u822c\u82f1\u8a9e\u53ca\u666e\u901a\u8a71\uff0c\u7565\u61c2\u8b80\u5beb\u82f1\u6587\n\u61c2\u7c21\u55ae\u96fb\u8166\u64cd\u4f5c\u53ca\u4e2d\u6587\u8f38\u5165\u6cd5\n\u4e3b\u52d5\uff0c\u71b1\u8aa0\uff0c\u5177\u826f\u597d\u9867\u5ba2\u670d\u52d9\u53ca\u6e9d\u901a\u6280\u5de7\n\u5de5\u4f5c\u7d30\u5fc3\uff0c\u5177\u8cac\u4efb\u611f\n\u6bcf\u661f\u671f\u5de5\u4f5c\u7d0425\u5c0f\u6642\n\u5de5\u4f5c\u5730\u9ede\uff1a\u6e2f\u4e5d\u65b0\u754c\uff0c\u6bcf\u5929\u5148\u56de\u91d1\u9418\u8fa6\u516c\u5ba4\u5831\u5230\n\u6642\u85aa\u9762\u8b70\n\n\u6709\u610f\u7533\u8acb\u8005\u8acb\u81f4\u96fb\u4eba\u529b\u8cc7\u6e90\u90e8\u694a\u5c0f\u59d0(\u96fb\u8a71:2862-3390)\uff0c\u6216\u53efWhatsApp 9868-7297\uff0c\u4ea6\u53ef\u5c07\u8a73\u7d30\u5c65\u6b77\u96fb\u90f5\u81f3 career@ kaohk.com\u6216\u50b3\u771f\u81f32865-5846\u3002\n\n\u7533\u8acb\u4eba\u6240\u63d0\u4f9b\u4e4b\u8cc7\u6599\u7d55\u5c0d\u4fdd\u5bc6\u53ca\u53ea\u4f5c\u62db\u8058\u7528\u9014\u3002", "employment_types": ["Part Time", "Contract"], "selling_points": [], "locations": ["Admiralty"], "categories": ["Sales, CS & Business Devpt", "Channel / Distribution", "Wholesale", "Others"], "post_time": "2022-01-10T06:18:41Z", "salary": {"currency": null, "max": null, "min": null, "period": "hourly", "term": null}, "salary_visible": false, "title_keywords": [], "responsibilities": [], "requirements": {"degrees": [], "majors": [], "languages": [], "language_level": [], "hard_skills": [], "soft_skills": [], "languages_combined": []}, "experience_required": {"duration": [], "field": []}}, {"job_id": "100003009030836", "location_code": "hk", "company": "Passion Pet Nutrition Limited", "job_title": "Sales Representative", "description": "Job Description:\n\nResponsible for local markets\nDevelop and establish new accounts and capture profitable businesses from clients\nEstablish and maintain good business relationships with key accounts/existing customers\nExperience in pet food/pet related industry will be an advantage\nExcellent communication and negotiation skills\nCustomer oriented, self-motivated and proactive\n\n\u00a0Job Requirements:\n\nForm 7 or above, or\nFresh graduate from university is accepted\nGood PC knowledge in using MS office applications\nOutgoing personality with effective communication and interpersonal skills\nGood command of written and spoken English\nAble to work under pressure\nImmediate available is highly preferred\n\nWe offer a friendly working environment in Tsuen Wan, a five and a half day week and 12 days annual leave to the right candidate. Interested parties, please email your full resume with present & expected salary by clicking \"Apply Now\".\n\n\nPersonal data collected will be used for recruitment purpose only.", "employment_types": ["Full Time", "Permanent"], "selling_points": ["High commission rate + attractive base salary", "Market Leader in Pet Foods Sector", "Immediately available is an advantage"], "locations": ["Not Specified"], "categories": ["Sales, CS & Business Devpt", "Business Development", "Account Servicing", "Wholesale"], "post_time": "2022-01-07T08:25:54Z", "salary": {"currency": null, "max": null, "min": null, "period": "monthly", "term": null}, "salary_visible": false, "title_keywords": ["sales representative"], "responsibilities": ["communication", "maintain", "develop"], "requirements": {"degrees": ["fresh graduate"], "majors": [], "languages": ["english"], "language_level": ["good command"], "hard_skills": ["pc knowledge", "ms office"], "soft_skills": ["outgoing personality", "communication and interpersonal skills", "work under pressure"], "languages_combined": [{"language": "english", "language_level": ["good command"]}]}, "experience_required": {"duration": [], "field": []}}, {"job_id": "100003009029427", "location_code": "hk", "company": "Always (HK) Holdings Limited", "job_title": "\u71df\u696d\u4ee3\u8868", "description": "\n\u8077\u8cac :\u8ca0\u8cac\u92b7\u552e\u6279\u767c\u751f\u6d3b\u6e05\u6f54\u7528\u54c1\n\n\u8cc7\u6b77 :\u4e2d\u4e94\u7a0b\u5ea6; 2\u5e74\u7d93\u9a57; \u826f\u597d\u7cb5\u8a9e; \u4e00\u822c\u666e\u901a\u8a71; \u826f\u597d\u82f1\u8a9e; \u61c2\u8b80\u5beb\u4e2d\u6587; \u61c2\u8b80\u5beb\u82f1\u6587; \u61c2\u82f1\u6587\u6253\u5b57 35 \u5b57(\u6bcf\u5206\u9418); \u61c2\u4e2d\u82f1\u6587\u96fb\u8166\u64cd\u4f5c; \u61c2\u4e2d\u6587\u6253\u5b57 35 \u5b57(\u6bcf\u5206\u9418); \u51772\u5e74\u6216\u4ee5\u4e0a\u76f8\u95dc\u5de5\u4f5c\u7d93\u9a57, \u826f\u597d\u6e9d\u901a\u6280\u5de7\n\n\u5f85\u9047 :\u6bcf\u6708$15,000, \u6709\u4f63\u91d1 \u53ca\u5728\u8077\u57f9\u8a13, \u661f\u671f\u4e00\u81f3\u4e94: \u4e0a\u53489\u6642\u81f3\u4e0b\u53486\u6642, \u6bcf\u9031\u5de5\u4f5c5\u5929\n\n\u7533\u8acb\u9808\u77e5 :\u6c42\u8077\u8005\u53ef\u96fb\u90f5(Apply Now)\u5c65\u6b77\u8868\u7d66\u5967\u7dad\u65af(\u9999\u6e2f)\u6709\u9650\u516c\u53f8\u3002\u5982\u8981\u7d22\u53d6\u6536\u96c6\u500b\u4eba\u8cc7\u6599\u8072\u660e, \u8acb\u8207\u6f58\u5c0f\u59d0(Email)\u806f\u7d61\u3002\n\n", "employment_types": ["Full Time"], "selling_points": [], "locations": ["Kwai Tsing Area"], "categories": ["Sales, CS & Business Devpt", "Wholesale", "Others", "Direct Sales"], "post_time": "2022-01-07T05:13:55Z", "salary": {"currency": null, "max": null, "min": null, "period": "monthly", "term": null}, "salary_visible": false, "title_keywords": ["\u71df\u696d\u4ee3\u8868"], "responsibilities": [], "requirements": {"degrees": [], "majors": [], "languages": [], "language_level": [], "hard_skills": [], "soft_skills": [], "languages_combined": []}, "experience_required": {"duration": [], "field": []}}, {"job_id": "100003009032910", "location_code": "hk", "company": "Rich Sources (HK) Limited", "job_title": "Sales Representative (5 days working)", "description": "Job Description\n\n\u652f\u63f4\u92b7\u552e\u90e8\u65e5\u5e38\u5de5\u4f5c\n\u8ddf\u9032\u53ca\u5354\u52a9\u5ba2\u6236\u8a02\u55ae\n\u5206\u6d41/\u89e3\u7b54\u4f86\u81ea\u5ba2\u6236\u53ca\u6d88\u8cbb\u8005\u7684\u54a8\u8a62\u53ca\u6295\u8a34\n\u652f\u63f4\u5e02\u5834\u90e8\u5be6\u884c\u5404\u985e\u63a8\u5ee3\u6d3b\u52d5\n\u6309\u7167\u884c\u7a0b\u8a08\u5283\u5230\u8ca0\u8cac\u5e97\u8216\u6574\u7406\u8ca8\u67b6\u53ca\u9673\u5217\u00a0\n\nRequirement\n\n\u6b63\u9762\u7684\u601d\u7dad\u3001\u5916\u5411\u4e26\u71b1\u8877\u65bc\u4e8b\u696d\u767c\u5c55\u7684\u4eba\u6750\uff0c\u80fd\u4ee5\u884c\u52d5\u611f\u67d3\u8eab\u908a\u7684\u4eba\n\u4ee5\u89e3\u6c7a\u554f\u984c\u70ba\u7d42\u59cb\u7684\u4eba\u6750\u70ba\u512a\u5148\u8003\u616e\n\u6a02\u65bc\u5718\u968a\u5408\u4f5c\u4e26\u4ee5\u5718\u9ad4\u7684\u6210\u529f\u70ba\u9996\u8981\u76ee\u6a19\n\u5099\u67091\u5e74\u6216\u4ee5\u4e0a\u92b7\u552e\u7d93\u9a57\uff0c\u6709\u98fc\u990a\u5bf5\u7269\u8005\u512a\u5148\u8003\u616e\n\u826f\u597d\u7684\u4e2d\u82f1\u6587\u8b80\u5beb\u80fd\u529b\n\u81ea\u4fe1\u4e26\u64c1\u6709\u826f\u597d\u7684\u6e9d\u901a\u53ca\u5f85\u4eba\u8655\u4e8b\u6280\u5de7\n\u57fa\u790e\u4e2d\u82f1\u6587\u66f8\u5165\u6cd5\u53ca\u96fb\u8166\u6587\u66f8\u8edf\u4ef6\u61c9\u7528\ufe59WORD, EXCEL, POWERPOINT \u7b49\ufe5a\n*\u6240\u6709\u65b0\u5165\u8077\u54e1\u5de5\u5747\u4eab\u6709\u57f9\u8a13\u8ab2\u7a0b\uff0c\u638c\u63e1\u6709\u95dc\u5bf5\u7269\u98df\u54c1/\u7528\u54c1\u7684\u57fa\u790e\u77e5\u8b58", "employment_types": ["Full Time"], "selling_points": [], "locations": ["Kowloon Bay"], "categories": ["Sales, CS & Business Devpt", "Business Development", "Wholesale", "Direct Sales"], "post_time": "2022-01-08T02:45:50Z", "salary": {"currency": "HKD", "max": 19999, "min": 17000, "period": "monthly", "term": null}, "salary_visible": true, "title_keywords": ["sales representative"], "responsibilities": [], "requirements": {"degrees": [], "majors": [], "languages": [], "language_level": [], "hard_skills": ["excel", "powerpoint"], "soft_skills": [], "languages_combined": []}, "experience_required": {"duration": [], "field": []}}, {"job_id": "100003009027971", "location_code": "hk", "company": "Beyond Compare Limited", "job_title": "Sales Executive / Account Servicing", "description": "Job Highlights\nPassionate about being in the F&B sector\nDynamic Job Nature and Hands-on opportunities\nFlexible Role for Individuals Keen to Learn\nCan work\u00a0Independently\nHas a CAN DO attitude and is proactive\u00a0\nJob Description\n\nThe Company\nCook Beyond is a food solutions based startup building on a foundation of offering flexible licensed kitchen rental for food startups, budding chefs and anyone in need of a kitchen to start or continue their food business journey.\n\nOur goal is to maximise the potential of every person, company or products that are looking to find a way through the saturated and competitive food industry in Hong Kong.\u00a0 Needless to say, our main goal is the provide solutions throughout the supply chain of a food business, from sourcing ingredients, providing a licensed kitchen for product creation, and eventually finding sales and distribution channels to sell products or related services.\n\nWe are rapidly expanding to meet demand and would be delighted to meet individuals who share our vision and enthusiasm.\n\nPlease view more at www.cookbeyond.co or at\u00a0 facebook.com/cookbeyondhk\n\n\nResponsibilities\n\nStaying up-to-date with industry trends to keep ahead of competitors, conduct research, analyse consumers\u2019 behaviour and market data, present creative ideas to devise product/service sales plan and achieve the revenue targets.\nParticipate in product development/marketing projects, sales & promotion events and product launch.\nAchieve the company's monthly sales target by acquiring new sales opportunities and enhancing existing customer base\nAssist in managing social media campaigns, write and proofread document.\nOrder follow up, liaison with customers and make proposal.\nTo arrange promotions for sales target achievement\nAd-hoc project assigned by Director\n\nRequirement\n\nDiploma holder with at least 2 years sales experience in F&B industry. Fresh graduates may be considered.\nPassion in developing career in F&B industry is required.\nOutgoing, interested in meeting people, creative and ability to think out of the box.\nWell versed in spoken and written English and Cantonese.\u00a0 Mandarin is a plus.\u00a0\u00a0\nImmediately available is highly preferred.\n\n(Candidates with more experience would be considered for supervisory position)\n\n\u00a0 \u00a0 \u00a0 \u00a0 \u00a0 \u00a0 \u00a0 \u00a0 \u00a0 \u00a0 \u00a0 \u00a0 \u00a0 \u00a0 \u00a0 \u00a0 \u00a0\u00a0\n\n\nPlease quote your expected salary upon applying for this role to help speed up the process of finding suitable candidates.\u00a0 Candidates that do not supply such information may take a longer time for management to process and consider.\u00a0\u00a0\n\nPersonal data provided by job applicants will be used strictly in accordance with the employer's personal data policies and for recruitment purposes only.", "employment_types": ["Full Time"], "selling_points": ["Sales experience in F&B industry", "Proactive & Fun", "3 years of relevant working experience preferred"], "locations": ["Wong Tai Sin Area"], "categories": ["Hospitality / F & B", "Food & Beverage", "Sales, CS & Business Devpt", "Account Servicing", "Wholesale"], "post_time": "2022-01-07T00:41:18Z", "salary": {"currency": null, "max": null, "min": null, "period": "monthly", "term": null}, "salary_visible": false, "title_keywords": ["sales executive"], "responsibilities": ["ad-hoc", "creative ideas", "social media campaigns", "sales target", "marketing projects", "provide solutions", "plan", "facebook", "market data", "conduct research", "analyse"], "requirements": {"degrees": ["diploma holder"], "majors": [], "languages": ["cantonese", "english", "mandarin"], "language_level": [], "hard_skills": ["plus"], "soft_skills": ["outgoing", "interested in", "creative", "passion in"], "languages_combined": [{"language": "cantonese", "language_level": []}, {"language": "english", "language_level": []}, {"language": "mandarin", "language_level": []}]}, "experience_required": {"duration": ["at least 2 years"], "field": ["f&b", "supervisory"]}}, {"job_id": "100003009018624", "location_code": "hk", "company": "Trinity Universal Limited", "job_title": "KEY ACCOUNTS EXECUTIVE", "description": "Key Responsibilities:\n\n\nKey customer account maintenance in HK and Greater China markets\nMaking offers, concluding orders and servicing post order management with customers including collections.\nIssue Sales related documents: Invoices, debit note, credit note etc.\nGaining product Knowledge\u00a0on the job to service customers effectively in coordination with Manager and team.\nGathering market information, trends, etc. and share with the team regularly\nWork closely with internal departments to ensure excellent results\n\nRequirements:\n\n\nBachelors degree or equivalent in any discipline.\u00a0\n2 years and above of work experience in customer account management.\nThose with lesser qualification/experience can be considered for junior positions.\nWillingness to travel as & when required (when safe travel resumes)\nTeam player, excellent interpersonal and communication skills\nFluent in Mandarin and Cantonese; Basic communication skills in English\nPositive, motivated, willingness to learn and result-oriented\nProficient PC and MS Excel skills\nFor the right candidate, the above requirements will not be a limiting factor.\u00a0\n\n\n\nWhat to expect:\n\n\nAn exciting work environment and career path\nA lively bunch of colleagues\nGreat work-life balance\n5 day work\nMedical , Life and Travel Insurance\nMinimum annual leave of 10 days increasing progressively with years of service\nAny personal data collected will be for recruitment purposes only.", "employment_types": ["Full Time", "Permanent"], "selling_points": ["Bachelors degree or equivalent", "Key accounts management, 5 day work week", "Medical Insurance, excellent growth opportunities"], "locations": ["Siu Sai Wan"], "categories": ["Sales, CS & Business Devpt", "Account Servicing", "Sales - Sales Management", "Wholesale"], "post_time": "2022-01-07T06:03:59Z", "salary": {"currency": null, "max": null, "min": null, "period": "monthly", "term": null}, "salary_visible": false, "title_keywords": ["executive"], "responsibilities": ["order management", "market information", "invoices", "related documents", "coordination with", "account maintenance"], "requirements": {"degrees": ["degree"], "majors": [], "languages": ["cantonese", "english", "mandarin"], "language_level": ["basic", "fluent"], "hard_skills": ["basic", "safe", "ms excel", "factor", "pc"], "soft_skills": ["result-oriented", "communication skills", "motivated", "team player", "interpersonal", "positive"], "languages_combined": [{"language": "cantonese", "language_level": ["fluent"]}, {"language": "english", "language_level": ["basic"]}, {"language": "mandarin", "language_level": ["fluent"]}]}, "experience_required": {"duration": ["2 years"], "field": ["account management"]}}, {"job_id": "100003009031765", "location_code": "hk", "company": "Ferragamo Retail HK Limited", "job_title": "Assistant Marketing Manager, Travel Retail", "description": "JOB DESCRIPTION\n\nMedia planning for each market\nManage regional TR & Franchisee A&P, budgeting and forecasting\nBookkeeping on all A&P expenses\nEvents \u2013 liaise, coordinate and execute local events with clients, production house, corporate\nWorking with clients and their press/marketing/influencers during Asia Press day and Milan to build relationships and brand exposure\nProposing and supporting any digital platforms and opportunities for the channel\u00a0\nExplore and develop CRM opportunities especially for each Franchisee market\nLightbox changes and coordination for the region each season\nConsolidating, ordering and dispatching packaging, uniform, Chinse Moon cakes, Chinese NY red envelopes, GWP etc.\nProvide the highest level of service and build strong and lasting relationships with Travel Retail and Franchisee partners\nPROFESSIONAL REQUIREMENTS\n\nMinimum 5 years solid experience (marketing)\nExperience in Travel Retail business and luxury retail (is a bonus)\nHands-on candidate with initiative\nAbility to handle and resolve recurring problems\nGood computer skills (MS Office)\nFluent in written and spoken English and Chinese (Mandarin)\nAvailable for business travels\nSpoken Italian is a bonus\nPERSONAL REQUIREMENTS\n\nA self-motivated individual with good communication and interpersonal skills.\nTeam player, strong ownership & passion for the brand.\nAbility to take ownership over a section / products and act with an entrepreneurial mind-set\u00a0\nAbility to establish priorities, work independently and proceed with objectives without supervision.\n\n", "employment_types": ["Full Time", "Permanent"], "selling_points": ["Competitive and attractive remuneration package", "Flexible work environment", "Luxury Retail"], "locations": ["Southern Area"], "categories": ["Sales, CS & Business Devpt", "Wholesale"], "post_time": "2022-01-07T09:44:14Z", "salary": {"currency": null, "max": null, "min": null, "period": "monthly", "term": null}, "salary_visible": false, "title_keywords": ["assistant marketing manager"], "responsibilities": ["liaise", "budgeting", "expenses", "develop", "coordinate", "coordination", "forecasting", "planning"], "requirements": {"degrees": [], "majors": [], "languages": ["italian", "english", "chinese", "mandarin"], "language_level": ["fluent"], "hard_skills": ["computer skills", "ms office"], "soft_skills": ["self-motivated", "work independently", "passion for", "hands-on", "communication and interpersonal skills", "team player", "initiative"], "languages_combined": [{"language": "italian", "language_level": []}, {"language": "english", "language_level": ["fluent"]}, {"language": "chinese", "language_level": ["fluent"]}, {"language": "mandarin", "language_level": ["fluent"]}]}, "experience_required": {"duration": ["minimum 5 years"], "field": ["business", "luxury retail", "marketing", "retail"]}}, {"job_id": "100003009029992", "location_code": "hk", "company": "Aeon Stores (Hong Kong) Co Ltd", "job_title": "\u5009\u52d9\u54e1(\u6536\u8ca8\u90e8)", "description": "\u8077\u8cac :\n\n\u8ca0\u8cac\u6536\u8ca8\u9ede\u7b97\uff1b\u96fb\u8166\u8cc7\u6599\u8f38\u5165\uff1b\u8ca8\u7269\u5305\u88dd\u53ca\u8abf\u52d5(\u6709\u5d17\u4f4d\u6d25\u8cbc\uff0c\u5047\u671f\u6d25\u8cbc)\n\u8cc7\u6b77 :\n\n\u6c92\u6709\u5b78\u6b77\u8981\u6c42; \u4e00\u822c\u7cb5\u8a9e; \u4e00\u822c\u666e\u901a\u8a71; \u4e00\u822c\u82f1\u8a9e; \u7565\u61c2\u8b80\u5beb\u4e2d\u6587; \u61c2\u95b1\u8b80\u82f1\u6587\n\u5f85\u9047 :\n\n\u6bcf\u6708$10,000 - $12,000, \u6709\u96d9\u7ce7, \u5e74\u504710\u5929, \u6bcf\u6708\u52e4\u5de5\u734e\u91d1$500, \u914c\u60c5\u6027\u82b1\u7d05, \u91ab\u7642\u798f\u5229,\u54e1\u5de5\u8cfc\u7269\u512a\u60e0, \u4e0a\u53488\u664245\u5206\u81f3\u4e0b\u534810\u664215\u5206, \u6bcf\u9031\u5de5\u4f5c5\u5929\u81f36\u5929,\u8f2a\u73ed,\u8f2a\u4f11, \u6bcf\u5929\u5de5\u4f5c 8 \u5c0f\u6642\n\u7533\u8acb\u9808\u77e5 :\u6c42\u8077\u8005\u53ef\u81f4\u96fb26628813\u8207\u6c38\u65fa(\u9999\u6e2f)\u767e\u8ca8\u6709\u9650\u516c\u53f8\u9ece\u5c0f\u59d0\u806f\u7d61\u3002\n\n\u6709\u610f\u7533\u8acb\u8005\u8acb \u6309 APPLY NOW\u7533\u8acb\u00a0", "employment_types": ["Full Time"], "selling_points": [], "locations": ["Kowloon City"], "categories": ["Sales, CS & Business Devpt", "Retail Sales", "Wholesale", "Sales Administration"], "post_time": "2022-01-07T06:34:17Z", "salary": {"currency": null, "max": null, "min": null, "period": "monthly", "term": null}, "salary_visible": false, "title_keywords": [], "responsibilities": [], "requirements": {"degrees": [], "majors": [], "languages": [], "language_level": [], "hard_skills": [], "soft_skills": [], "languages_combined": []}, "experience_required": {"duration": [], "field": []}}, {"job_id": "100003009027978", "location_code": "hk", "company": "United Italian Corporation (H.K.) Limited", "job_title": "Product Specialist / Sales Executive  (Healthcare Products and Medical Consumables)", "description": "Responsibilities:\n\n-\u00a0\u00a0\u00a0\u00a0\u00a0\u00a0\u00a0\u00a0\u00a0\u00a0\u00a0 Responsible for promoting Healthcare Products and Medical Consumables to Trading Sector, Government Sector, including Schools, Universities and Corporate accounts.\n\n-\u00a0\u00a0\u00a0\u00a0\u00a0\u00a0\u00a0\u00a0\u00a0\u00a0\u00a0 To achieve sales objectives in assigned territory\n\n-\u00a0\u00a0\u00a0\u00a0\u00a0\u00a0\u00a0\u00a0\u00a0\u00a0\u00a0 To build up and develop an excellent relationship with customers\n\n\u00a0Requirements:\n\n-\u00a0\u00a0\u00a0\u00a0\u00a0\u00a0\u00a0\u00a0\u00a0\u00a0 Form 5 or above\n\n-\u00a0\u00a0\u00a0\u00a0\u00a0\u00a0\u00a0\u00a0\u00a0\u00a0 Sales and marketing experience preferred\n\n-\u00a0\u00a0\u00a0\u00a0\u00a0\u00a0\u00a0\u00a0\u00a0\u00a0 Good command of both English and Cantonese\n\n-\u00a0\u00a0\u00a0\u00a0\u00a0\u00a0\u00a0\u00a0\u00a0\u00a0 Self-motivated, Sales oriented, good communication skills, responsible & hard working", "employment_types": ["Full Time", "Permanent"], "selling_points": ["5-day work", "Basic salary + commission", "Healthcare Products and Medical Consumables"], "locations": ["Aberdeen"], "categories": ["Sales, CS & Business Devpt", "Wholesale"], "post_time": "2022-01-07T00:47:20Z", "salary": {"currency": null, "max": null, "min": null, "period": "monthly", "term": null}, "salary_visible": false, "title_keywords": ["product specialist", "sales executive"], "responsibilities": ["develop"], "requirements": {"degrees": ["form 5 or above"], "majors": [], "languages": ["cantonese", "english"], "language_level": ["good command"], "hard_skills": [], "soft_skills": ["communication skills", "self-motivated", "responsible", "hard working"], "languages_combined": [{"language": "cantonese", "language_level": ["good command"]}, {"language": "english", "language_level": ["good command"]}]}, "experience_required": {"duration": [], "field": ["marketing"]}}, {"job_id": "100003009037717", "location_code": "hk", "company": "Michael Page", "job_title": "Sales Director, APAC (Toys)", "description": "This is a fantastic opportunity for strong sales professional to take on an exciting new role with a world leading Toys company. The company is now expanding their business and adding new headcounts to their sales team.\n\nClient Details\n\nThis is a fantastic opportunity for strong sales professional to take on an exciting new role with a world leading Toys company. They are now looking for a Sales Director, Asia to join their business.\n\nThe company is now expanding their business and adding new headcounts to their sales team.\n\nDescription\n\nYou will be responsible for developing and executing strategic plans to achieve sales targets and expand the customer base in HK and Asia (both retailer and distributors)\nYou will be responsible for account management and business development for retailers.\nYou will also be involved in the analysis of market and the competitors.\nYou will be responsible for owning and hitting/exceeding annual sales targets.\n\nProfile\n\nMinimum 8 - 10 years of relevant sales experience, working in toys industry is mandatory.\nThe successful candidate must be determined and have strong business acumen.\nExcellent leadership skills\nYou must have the ability to develop long-term partnerships with clients and partners.\nFluency in Mandarin, Cantonese and English is mandatory.\n\nJob Offer\n\nThis is a great opportunity for a strong sales professional to take on a leadership role in this international company. They provide an attractive salary and benefits for the candidate.\n\nTo apply online please click the 'Apply' button below. For a confidential discussion about this role please contact Phoebe Leung on +852 3412 4853.", "employment_types": ["Full Time", "Permanent"], "selling_points": ["A world leading toys company", "Key Account Management", "Distributor Management"], "locations": ["Not Specified"], "categories": ["Sales, CS & Business Devpt", "Business Development", "Channel / Distribution", "Wholesale"], "post_time": "2022-01-11T03:36:30Z", "salary": {"currency": null, "max": null, "min": null, "period": "monthly", "term": null}, "salary_visible": false, "title_keywords": ["director", "sales"], "responsibilities": ["management", "strategic plans", "analysis", "developing", "develop", "sales team", "executing"], "requirements": {"degrees": [], "majors": [], "languages": ["cantonese", "english", "mandarin"], "language_level": ["fluency"], "hard_skills": ["analysis", "acumen"], "soft_skills": ["determined", "responsible", "leadership skills", "business acumen", "leadership"], "languages_combined": [{"language": "cantonese", "language_level": ["fluency"]}, {"language": "english", "language_level": ["fluency"]}, {"language": "mandarin", "language_level": ["fluency"]}]}, "experience_required": {"duration": ["minimum 8 - 10 years"], "field": ["toys"]}}, {"job_id": "100003009027165", "location_code": "hk", "company": "OPAC International Ltd", "job_title": "\u71df\u696d\u4ee3\u8868/Telesales", "description": "\n\u8077\u8cac :Generate new leads and prospects - Help to research and build a prospect database. Make cold calls to prospective customers to generate sales and achieve sales target\n\n\u8cc7\u6b77 :\u4e2d\u4e94\u7a0b\u5ea6; \u826f\u597d\u7cb5\u8a9e; \u826f\u597d\u666e\u901a\u8a71; \u826f\u597d\u82f1\u8a9e; \u61c2\u8b80\u5beb\u4e2d\u6587; \u61c2\u8b80\u5beb\u82f1\u6587\n\n\u5f85\u9047 :\u6bcf\u6708$10,000, \u6709\u4f63\u91d1, \u661f\u671f\u4e00\u81f3\u4e94: \u4e0a\u53489\u6642\u81f3\u4e0b\u53486\u6642\u53ca\u661f\u671f\u516d: \u4e0a\u53489\u6642\u81f3\u4e0b\u53481\u6642, \u6bcf\u9031\u5de5\u4f5c5\u5929\u534a, \u6bcf\u5929\u5de5\u4f5c 9 \u5c0f\u6642\n\n\u7533\u8acb\u9808\u77e5 :\u6c42\u8077\u8005\u53ef\u96fb\u90f5(Apply Now)\u5c65\u6b77\u8868\u7d66\u6fb3\u6822\u570b\u969b\u6709\u9650\u516c\u53f8\u3002\u5982\u8981\u7d22\u53d6\u6536\u96c6\u500b\u4eba\u8cc7\u6599\u8072\u660e, \u8acb\u8207\u674e\u5c0f\u59d0(Email)\u806f\u7d61\u3002\n\n", "employment_types": ["Full Time"], "selling_points": [], "locations": ["Kwai Tsing Area"], "categories": ["Sales, CS & Business Devpt", "Wholesale", "Others", "Direct Sales"], "post_time": "2022-01-06T09:13:44Z", "salary": {"currency": null, "max": null, "min": null, "period": "monthly", "term": null}, "salary_visible": false, "title_keywords": ["\u71df\u696d\u4ee3\u8868", "telesales"], "responsibilities": ["sales target", "database"], "requirements": {"degrees": [], "majors": [], "languages": [], "language_level": [], "hard_skills": ["make"], "soft_skills": [], "languages_combined": []}, "experience_required": {"duration": [], "field": []}}, {"job_id": "100003009034866", "location_code": "hk", "company": "Magic Search Limited", "job_title": "Sales Associate / Senior Sales (\u9ad8\u7d1a\u6642\u88dd /\u9418\u9336\u73e0\u5bf6\u54c1\u724c) ($20,000- 40,000)", "description": "\u70ba\u914d\u5408\u767c\u5c55\uff0c\u672c\u516c\u53f8\u73fe\u70ba\u570b\u969b\u6642\u88dd\u54c1\u724c\u62db\u8058 \u9ad8\u7d1a\u552e\u8ca8\u54e1/\u552e\u8ca8\u54e1\u00a0\n\n\u5c0d\u670d\u88dd\u5145\u6eff\u71b1\u8aa0, \u559c\u611b\u8207\u5ba2\u4eba\u4ea4\u6d41\n\u77ad\u89e3\u670d\u88dd\u6d41\u884c\u8da8\u52e2\n\u6700\u5c11\u5169\u5e74\u4ee5\u4e0a\u6642\u88dd\u92b7\u552e\u7d93\u9a57, \u6709\u9ad8\u7d1a\u6642\u88dd/\u9418\u9336\u73e0\u5bf6\u00a0\u7d93\u9a57\u8005\u512a\u5148\u8003\u616e\n\u826f\u597d\u4e2d\u82f1\u6587\u3001\u570b\u8a9e\u6e9d\u901a\u6280\u5de7\u53ca\u92b7\u552e\u80fd\u529b\n\u8457\u91cd\u5718\u968a\u7cbe\u795e\n\u4e3b\u52d5\u71b1\u8aa0\uff0c\u89aa\u5207\u6709\u79ae\n\u7d93\u9a57\u8f03\u591a\u8005\u53ef\u7533\u8acb\u8cc7\u6df1\u552e\u8ca8\u54e1\n\n\u6709\u610f\u8005\u8acb\u5c07\u500b\u4eba\u5c65\u6b77\u8868\u96fb\u90f5\u81f3 cv @magicsearch.com.hk \u6216\u6309 \"Apply Now\"\u00a0\u767c\u9001\u7c21\u6b77\u3002\n\nOur clients are well-known international fashion brand. To cope with their expansion, we are looking for Sales Associate / Senior Sales Associate to join their team\n\nPassion in fashion industry, customer service-oriented\nMinimum 2 years relevant working experience preferably in fashion/W&J industry\nPeople from\u00a0hospitality, airline servicing are welcomed\nEnergetic, outgoing and self-motivated\nGood command of English, Cantonese and Mandarin\nTeam Player\nMore experiences will be considered as Senior Sales Associate\n\nPlease e-mail your detailed resume to cv @magicsearch.com.hk for interview or click \"Apply Now\" for application", "employment_types": ["Full Time", "Permanent"], "selling_points": ["Luxury Fashion", "8 days + Public Holiday", "Basic Salary + High Commission"], "locations": ["Not Specified"], "categories": ["Sales, CS & Business Devpt", "Retail Sales", "Wholesale", "Direct Sales"], "post_time": "2022-01-10T04:26:53Z", "salary": {"currency": "HKD", "max": 34999, "min": 20000, "period": "monthly", "term": null}, "salary_visible": true, "title_keywords": ["senior sales", "sales associate"], "responsibilities": ["customer service"], "requirements": {"degrees": [], "majors": [], "languages": ["cantonese", "english", "mandarin"], "language_level": ["good command"], "hard_skills": ["airline"], "soft_skills": ["outgoing", "self-motivated", "passion in", "service-oriented", "team player", "energetic", "detailed"], "languages_combined": [{"language": "cantonese", "language_level": ["good command"]}, {"language": "english", "language_level": ["good command"]}, {"language": "mandarin", "language_level": ["good command"]}]}, "experience_required": {"duration": ["minimum 2 years"], "field": ["relevant working experience"]}}, {"job_id": "100003009030752", "location_code": "hk", "company": "IKEA", "job_title": "\u6536\u8ca8\u90e8\u4e3b\u4efb Goods Flow Team Leader", "description": "WHY YOU WILL LOVE US\n\nWe\u2019re a diverse group of down-to-earth, straightforward people with a passion for home furnishing. We come from all over the world, but we share an inspiring vision: \u201cto create a better everyday life for the many people\". How we realize this vision is based on our shared humanistic values. These values guide our work and build our inclusive, open and honest culture. It\u2019s all based on a spirit of togetherness and enthusiasm. We work hard, but we have fun doing it. We\u2019re always looking for people who share our positive attitude and values.\n\nWHY WE WILL LOVE YOU\n\nYou have 3 years experience of working in a retail and/or logistics role, including previous experience of leading others\nYou have problem-solving experience\nYou have proven record of meeting goals, deadlines\nYou are able to identify the need for and drive change in ways of working\nYou are experienced in creating and implementing short-term plans and following up goals\nYou are able to set and implement action plans and provide clear direction and follow up goals\nYou show the potential to apply tactical and operational thinking\nYou are able to inspire and engage others\nYou are able to reflect and find value and ideas in collaborating with other\n\nWHAT YOU WILL BE DOING DAY TO DAY\n\nResponsible for planning, organizing and monitoring store goods flow process from goods receiving to sales locations replenishment within my area of responsibility, contributing to fulfillment of the goal to be ready before store opening\nResponsible for ensuring all prerequisites are met in my area of responsibility, including resources, tools, working methods and internal communication, to contribute to an efficient range administration process in my store (space dimensioning, goods allocation)\nLead and manage my team in coordinating and optimizing goods flow operations in my store, resulting in agreed goods availability for customers at the lowest possible costs\nContribute to ensuring that store stock is available for customers in order to maximize sales by\u00a0 performing sales space replenishment according to the guidance of Sales Team & Communications and Interior Design Team\nWork actively to improve productivity by efficient resource planning including managing the quality\u00a0 of staff planning, flexibility of working and implementing efficient goods flow operations \u00a0\nMinimize handling damages in my store and working with my manager to identify the root cause of recurring damages and identifying ways to minimize future recurrence\nObserve the performance of contractors who deliver stocks from the Distribution Center to stores, and report any dis satisfactory contractor issues to the Distribution Center team\nGive input to my goods flow manager for the creation of business plan and goods flow action plans\nAnalyze the results of the Customer Satisfaction Survey, Voice and Commercial Reviews and using the insights gained from this to develop our business\nCommit to the development of my team. I work with my manager to secure the training of my team to ensure they are well informed, regarding coordination and optimization of goods flow operations\n\nSTAFF BENEFITS\n\nAnnual Fixed Bonus, 5-Day Work Week, 17 days Public Holiday, Paid Leave (Paid Annual Leave, 14 weeks Maternity Leave, 5 days Paternity Leave, 1 week Marriage Leave), Employee Medical Coverage, Non-Contributory Retirement Plan, Staff Purchase Discount, Birthday Coupon, Referral Bonus, Excellent Career Path\n\nInterested Candidate please click[via APPLY NOW] \u00a0\n\n\u6709\u610f\u7533\u8acb\u8005\u8acb \u6309 APPLY NOW\u7533\u8acb\u00a0", "employment_types": ["Full Time"], "selling_points": [], "locations": ["Not Specified"], "categories": ["Transportation & Logistics", "Inventory / Warehousing", "Sales, CS & Business Devpt", "Sales - Sales Management", "Wholesale"], "post_time": "2022-01-07T08:15:43Z", "salary": {"currency": null, "max": null, "min": null, "period": "monthly", "term": null}, "salary_visible": false, "title_keywords": ["team leader"], "responsibilities": ["ideas", "operations", "fulfillment", "quality", "design", "communication", "plans", "costs", "administration", "develop", "logistics", "business plan", "report", "guidance", "monitoring", "replenishment", "sales team", "coordination", "planning"], "requirements": {"degrees": [], "majors": [], "languages": [], "language_level": [], "hard_skills": ["goal", "problem-solving", "fun"], "soft_skills": ["efficient", "responsible", "passion for", "problem-solving", "positive attitude", "diverse", "clear", "communication", "inspiring", "honest", "coordination"], "languages_combined": []}, "experience_required": {"duration": ["3 years"], "field": ["retail", "logistics"]}}, {"job_id": "100003009023302", "location_code": "hk", "company": "Cam2 Limited", "job_title": "\u71df\u696d\u4ee3\u8868", "description": "\u5de5\u4f5c\u7bc4\u570d\uff1a\n\n\u884c\u8857\u62dc\u8a2a\u5ba2\u6236\n\u958b\u62d3\u65b0\u5ba2\u6236, \u62d3\u5c55\u5e02\u5834\n\u8ca0\u8cac\u92b7\u552e\u53ca\u63a8\u5ee3\u516c\u53f8\u7522\u54c1 (\u5065\u5eb7\u53ca\u904b\u52d5\u98df\u54c1)\n\u8207\u6f5b\u5728\u5ba2\u6236\u53ca\u73fe\u6709\u5ba2\u6236\u5efa\u7acb\u826f\u597d\u95dc\u4fc2\n\u5354\u52a9\u6536\u96c6\u5e02\u5834\u8cc7\u8a0a\u4ee5\u4fbf\u5236\u5b9a\u71df\u92b7\u7b56\u7565\n\u9054\u81f4\u516c\u53f8\u5236\u5b9a\u7684\u92b7\u552e\u76ee\u6a19\n\n\u00a0\u5165\u8077\u8981\u6c42\uff1a\n\n\u4e2d\u4e94\u2f84\u4e2d\u4e03\u6216DSE\u7a0b\u5ea6, \u9700\u5177\u5099\u4e00\u5e74\u6216\u4ee5\u4e0a\u92b7\u552e\u98df\u54c1\u7d93\u9a57\n\u9700\u6236\u5916\u5de5\u4f5c\n\u52e4\u596e , \u4e3b\u52d5 , \u6027\u683c\u958b\u6717 , \u5584\u65bc\u8207\u5ba2\u4eba\u6e9d\u901a , \u6709\u79ae\u8c8c\u53ca\u6709\u8cac\u4efb\u5fc3\n\u5c0d\u904b\u52d5\u7522\u54c1\u611f\u8208\u8da3\u8005\u512a\u5148", "employment_types": ["Full Time", "Permanent"], "selling_points": [], "locations": ["Mong Kok"], "categories": ["Sales, CS & Business Devpt", "Sales - Sales Management", "Wholesale"], "post_time": "2022-01-05T08:07:15Z", "salary": {"currency": null, "max": null, "min": null, "period": "monthly", "term": null}, "salary_visible": false, "title_keywords": ["\u71df\u696d\u4ee3\u8868"], "responsibilities": [], "requirements": {"degrees": [], "majors": [], "languages": [], "language_level": [], "hard_skills": [], "soft_skills": [], "languages_combined": []}, "experience_required": {"duration": [], "field": []}}]