[{"job_id": "100003009051943", "location_code": "hk", "company": "CML EurAsia", "job_title": "Purchasing Executive", "description": "Requirements\n\nDiploma or above in purchasing/supply chain or related disciplines\nAt least 1-year relevant experience\nElectronics and optical components focused\nImmediate availability will be an advantage\nFluency in both Mandarin and English will be a plus\n\n\u00a0Responsibilities\n\nThe purchasing officer will be responsible to schedule shipping, to prepare accurate and complete purchase orders for supplies, materials and raw goods.\n\nHe/she will work closely with vendors for placing orders, ensuring purchase are recorded at the time of request and manage inventory.", "employment_types": ["Full Time", "Permanent"], "selling_points": [], "locations": ["Hung Hom"], "categories": ["Manufacturing", "Production Planning / Control", "Merchandising & Purchasing", "Electronics", "Others", "Trading"], "post_time": "2022-01-17T01:35:40Z", "salary": {"currency": null, "max": null, "min": null, "period": "monthly", "term": null}, "salary_visible": false, "title_keywords": ["purchasing executive"], "responsibilities": ["shipping", "inventory", "purchase", "schedule", "placing orders"], "requirements": {"degrees": ["diploma or above"], "majors": ["related disciplines"], "languages": ["english", "mandarin"], "language_level": ["fluency"], "hard_skills": ["plus"], "soft_skills": ["focused"], "languages_combined": [{"language": "english", "language_level": ["fluency"]}, {"language": "mandarin", "language_level": ["fluency"]}]}, "experience_required": {"duration": ["at least 1-year"], "field": ["relevant experience"]}}, {"job_id": "100003009047948", "location_code": "hk", "company": "NewPower Worldwide Limited", "job_title": "Purchasing Representative", "description": "Responsibilities:\n\nTo handle\u00a0RFQ, PO processing and monitoring\nTo\u00a0keep close contact with customers and suppliers for quotation and follow up outstanding PO delivery status\nTo\u00a0maintain PO, invoice files and related purchasing records such as material, price, inventory and delivery records\nTo work with shipping team and support logistics operations with warehouse & forwarders where necessary\nTo assist other ad-hoc projects as assigned\n\n\nRequirements:\n\nForm 7 / DSE graduate or above\n2 years of relevant international trading experiences especially in electrical parts and components\nGood command of written and spoken English and Chinese, knowledge in Japanese is definitely an advantage\nProficient in MS Office\nGood communication skill, well organized and a fast learner\nMore experience will be considered as Procurement Officer\nImmediate available / short notice will be an advantage\n\nRemuneration will be commensurate with qualification and experience. Interested parties, please send your application with detailed resume indicating both existing & expected salary and date of availability to us.\n\nWe are an equal opportunity employer. All information provided by applicants will be treated in strict confidence and used for recruitment purpose only.", "employment_types": ["Full Time", "Permanent"], "selling_points": ["Attractive Commission Package", "Good Career Growth and Progression", "Friendly and Positive Work Environment"], "locations": ["Kwai Fong"], "categories": ["Merchandising & Purchasing", "Electronics", "Procurement / Purchasing / Sourcing"], "post_time": "2022-01-17T01:45:38Z", "salary": {"currency": null, "max": null, "min": null, "period": "monthly", "term": null}, "salary_visible": false, "title_keywords": ["representative"], "responsibilities": ["shipping", "invoice", "operations", "inventory", "quotation", "monitoring", "maintain", "logistics", "contact", "ad-hoc projects"], "requirements": {"degrees": ["dse"], "majors": [], "languages": ["japanese", "english", "chinese"], "language_level": ["advantage", "good command"], "hard_skills": ["ms office"], "soft_skills": ["fast learner", "communication skill", "well organized"], "languages_combined": [{"language": "japanese", "language_level": ["advantage", "good command"]}, {"language": "english", "language_level": ["advantage", "good command"]}, {"language": "chinese", "language_level": ["advantage", "good command"]}]}, "experience_required": {"duration": ["2 years"], "field": ["trading", "procurement"]}}, {"job_id": "100003009052676", "location_code": "hk", "company": "Canon Engineering Hong Kong Co Ltd", "job_title": "Procurement Clerk", "description": "Duties & Responsibilities\n\n\nLiaise with suppliers, follow-up purchase orders, delivery arrangement and inventory control\nManage and develop the assigned product category to drive sales and meet margin target\nKeeping up with market trends, to assist products category are developed in the correct direction\nClosely monitoring assign product\u2019s category and its market price to make sure we are at our most combative on all across channel included our ecommerce platform\nTo handle PO processing and monitoring\nManage quotations, documents & costing\nTo assist other ad-hoc projects as assigned\n\nExperience & Qualifications\n\n\nDiploma or above\n2-5 year work experience, experienced with trading/ FMCG/ electronics related industry will be an advantage\nGood command in spoken and written Chinese and English\nAdaptable to changes with good communication skills, able to work in a fast-paced environment\nImmediate availability is preferred\n\nWe offer attractive fringe benefits including: 5 days-work week, bank holidays & Attendance Bonus.\n\nOur website: http://www.dunamis.hk", "employment_types": ["Full Time", "Permanent"], "selling_points": [], "locations": ["Kwai Hing"], "categories": ["Merchandising & Purchasing", "Electronics", "Procurement / Purchasing / Sourcing"], "post_time": "2022-01-17T03:41:13Z", "salary": {"currency": null, "max": null, "min": null, "period": "monthly", "term": null}, "salary_visible": false, "title_keywords": ["procurement clerk"], "responsibilities": ["monitoring", "develop", "communication", "purchase", "inventory control", "drive sales", "ad-hoc projects", "liaise with suppliers"], "requirements": {"degrees": ["diploma or above"], "majors": [], "languages": ["english", "chinese"], "language_level": ["good command"], "hard_skills": ["make", "processing"], "soft_skills": ["adaptable", "communication skills", "fast-paced environment"], "languages_combined": [{"language": "english", "language_level": ["good command"]}, {"language": "chinese", "language_level": ["good command"]}]}, "experience_required": {"duration": ["2-5 year"], "field": ["related", "fmcg", "trading"]}}, {"job_id": "100003009048791", "location_code": "hk", "company": "SAE Magnetics (Hong Kong) Ltd", "job_title": "Buyer", "description": "Job Responsibilities:\n1. Responsible for full range of order management operations and activities, incl. handle all necessary documents and maintain all relevant data in ERP.\n2. Process New Product Integration (NPI), Engineering Change Notice (ECN) & transfer order in ERP system.\n3. Responsible and follow up all demand signals orders and agreement. (consignment, delivery schedule, KANBAN, outline frame contract)\n4. Ensure customer requirements are answered and delivered on-time through internal coordination.\n5. Support all activities related to claim handling relevant for order management.\n6. Report impacting and repeating factory issues to supplier management.\n7. Prepare and update Customer Specific Information (Ordering) for supervisor approval.\n8. Monitoring order booking performance for assigned customers and closely work with customer to get an update forecast and share to supplier if required.\n9. Monitor and follow up on order status to ensure on-time, correct and in-full shipment.\n10. Other tasks assigned by supervisor.\n\nJob Requirements:\n1. Professional education in technical or related field.\n2. Minimum 2-3 years of work experience in PCB related business environment.\u00a0\n3. Strong communication skills and fluent in Cantonese, English and Mandarin.\u00a0\u00a0\n4. Proficiency in all MS Office applications, ERP system experience.", "employment_types": ["Full Time", "Permanent"], "selling_points": ["Execute and monitor regular purchasing duties", "Working Location: HK Science Park, Shatin", "5-day work; Double Pay; Incentive Bonus; 12-19 AL"], "locations": ["Shatin Area"], "categories": ["Transportation & Logistics", "Supply Chain", "Merchandising & Purchasing", "Electronics", "Procurement / Purchasing / Sourcing"], "post_time": "2022-01-15T03:50:04Z", "salary": {"currency": null, "max": null, "min": null, "period": "monthly", "term": null}, "salary_visible": false, "title_keywords": [], "responsibilities": ["order management", "management", "data", "operations", "monitoring", "monitor", "delivery schedule", "other tasks", "maintain", "booking", "coordination", "forecast", "report"], "requirements": {"degrees": [], "majors": [], "languages": ["cantonese", "english", "mandarin"], "language_level": ["fluent"], "hard_skills": ["erp system", "ms office"], "soft_skills": ["business environment", "communication skills"], "languages_combined": [{"language": "cantonese", "language_level": ["fluent"]}, {"language": "english", "language_level": ["fluent"]}, {"language": "mandarin", "language_level": ["fluent"]}]}, "experience_required": {"duration": ["minimum 2-3 years"], "field": ["related", "erp system", "business"]}}, {"job_id": "100003009054660", "location_code": "hk", "company": "Acton Consulting Limited", "job_title": "(Senior) Buyers / Purchasers - Procurement Operation x 6 openings", "description": "Our client is a sizable company. Due to the rapid growth of the company, they are now looking for talented individuals to join the professional team.\n\nThe Role:\n\nMaintain up-to-date commercial and contractual knowledge of the market place and methods to ensure that best practices are continually developed and utilized within the group\nManage completed Purchasing cycles\nCoordinate Purchase requisitions from business, advise requestor on sourcing channel and execute tactical sourcing as needed.\nMaintain the contract repository (upload and archive contracts as needed)\nReview contract compliance and contracts due for renewal\nSupport complication of procurement operations / performance reports\nThe Job;\n\nDiploma or University graduate or professional qualification in a related discipline\n3+ years' relevant experience in purchasing in ICT or Tech products and service, Common computer software and office supplies\nhands-on experience in Procurement operations experience is essential\nWorking experience in regulatory requirements and procurement policies\nAbility to inspire, and build trust and respect among the stakeholders\nExcellent people skills; including the ability to negotiate and influence internal and external stakeholders\nA team player, assertive yet approachable and decisive\nproficiency in Excel (V-lookup, macros) and PowerPoint Presentation and procurement systems\nwww.ActonCL.com Unit 2302, 23/F, New World Tower 1, 18 Queen's Road Central. Hong Kong\n\nAll information received will be kept in strict confidence and only for employment-related purposes", "employment_types": ["Full Time", "Permanent", "Contract"], "selling_points": ["Purchaser , Buyer", "Procurement operation", "5 days work"], "locations": ["Not Specified"], "categories": ["Merchandising & Purchasing", "Electronics", "Stationery", "Procurement / Purchasing / Sourcing"], "post_time": "2022-01-17T12:50:42Z", "salary": {"currency": null, "max": null, "min": null, "period": "monthly", "term": null}, "salary_visible": false, "title_keywords": [], "responsibilities": ["software", "performance reports", "office supplies", "contracts", "operations", "review", "compliance", "regulatory requirements", "systems", "coordinate", "purchase", "maintain", "procurement policies"], "requirements": {"degrees": ["university graduate", "diploma"], "majors": [], "languages": [], "language_level": [], "hard_skills": ["excel", "powerpoint", "rapid"], "soft_skills": ["confidence", "approachable", "assertive", "hands-on", "decisive", "team player", "presentation"], "languages_combined": []}, "experience_required": {"duration": ["3+ years"], "field": ["purchasing", "tech", "relevant experience", "procurement"]}}, {"job_id": "100003009054421", "location_code": "hk", "company": "Zeeva International Limited", "job_title": "Operations Manager", "description": "Job Overview:\u00a0\nResponsible for supervising & improving the operations of our merchandising team\n\n\u00a0Responsibilities and Duties:\u00a0\n\nLead & supervise Merchandising Team on all projects & production related matters in an appropriate and cost-effective way\nOversee product management, project timeline and track on-time delivery performance\nManage project planning from concept, development, order taking, production to supply chain strategically\nMonitor production schedule with Vendors proactively\nEnsure smooth running of the whole merchandising process from project development, product management, supplier sourcing, vendor selection and quality management to product delivery\nReview streamline process and practices to cope with the latest technology, improving efficiency with data automation, and making recommendations for continuous improvement\nEstablish excellent working relationship and provide quality service, ensuring speedy resolution to both internal parties and external parties\nCommunicate effectively with the cross functional Team Leaders regarding any production, quality, testing, compliance or shipping related issues, with a focus on steps to improve our procedures or training needs\u00a0\u00a0\nIdentify risk areas, and achieve safety and quality standard, complying with product specification, global guidelines and regulatory requirements respectively\nPerform quality controls, monitor production KPI\u2019s, SOPs and overview reports\nHandle other ad-hoc tasks as assigned\nReport to Vice President\n\nRequirements:\n\n10+ years of experience in Merchandising/Supply Chain/Sourcing consumer electronics, toys, or sundries, of which at least 5 years in a similar senior role\nBachelor\u2019s degree in Business or Supply Chain management related discipline\nPrefer with 5+ years people management experience\nProven record in driving business result and operational performance\nKnowledge of organizational effectiveness and operations management\nDetail minded, well-organized with good analytical skill and problem-solving skills\nSelf-motivated, able to work independently under pressure, as well as work with teams and stakeholders across different regions to achieve company goals\nStrong business ethics and high level of integrity\nExtensive knowledge of the technical aspects\nExcellent computer skills, like Excel (eg Vlookup, Pivot Tables), Word and PowerPoint\nFluency in English, Cantonese and Mandarin, both verbally and in writing\nImmediate availability is preferable\n\nWe offer attractive remuneration, double pay, discretionary performance bonus, group medical insurance, to the right candidate. Interested parties please send your full resume with date of availability, present and expected salaries to us via JobsDB.\u00a0\u00a0\n\nApplicants not hearing from us within 6 weeks may consider their applications unsuccessful. We may also consider their application for other or future vacancies. Personal data of unsuccessful applicants will be retained for a maximum period of\u00a06 months.\u00a0", "employment_types": ["Full Time"], "selling_points": [], "locations": ["Kowloon Bay"], "categories": ["Manufacturing", "Production Planning / Control", "Merchandising & Purchasing", "Electronics", "Quality Assurance, Control & Testing / ISO"], "post_time": "2022-01-17T09:28:51Z", "salary": {"currency": null, "max": null, "min": null, "period": "monthly", "term": null}, "salary_visible": false, "title_keywords": ["operations manager"], "responsibilities": ["shipping", "data", "regulatory requirements", "external parties", "merchandising", "quality", "compliance", "monitor", "testing", "resolution", "reports", "schedule", "report", "cost", "management", "review", "procedures", "sops", "order taking", "manage project planning", "guidelines", "ad-hoc tasks", "internal parties"], "requirements": {"degrees": ["degree", "bachelor"], "majors": ["business"], "languages": ["cantonese", "english", "mandarin"], "language_level": ["fluency"], "hard_skills": ["excel", "analytical skill", "word", "powerpoint", "computer skills", "problem-solving skills", "vlookup"], "soft_skills": ["analytical skill", "self-motivated", "work independently", "under pressure", "organizational", "well-organized", "integrity", "problem-solving skills", "extensive"], "languages_combined": [{"language": "cantonese", "language_level": ["fluency"]}, {"language": "english", "language_level": ["fluency"]}, {"language": "mandarin", "language_level": ["fluency"]}]}, "experience_required": {"duration": ["at least 5 years", "5+ years", "10+ years"], "field": ["toys", "supply chain", "people management", "merchandising"]}}, {"job_id": "100003009054431", "location_code": "hk", "company": "Currys Sourcing Limited", "job_title": "Assistant to Product Manager (Consumer Electronics Products)", "description": "Responsibilities:\n\nSupplier Management \u2013 continuous management and review of supplier base on product, price, supply and quality\nProduct Management \u2013 support Product Manager to manage day-to-day operations\nCritical Path Maintenance and Reporting \u2013 support Product Manager to update and deliver to deadlines. Produce and maintain relevant reporting and summaries to support category.\nBuying Trip Preparation - support Product Manager to effectively prepare for buying trips\n\nRequirements:\n\nDiploma or above\nMature, responsible, strong initiation and attention to details\nAble to handle multi-tasks with tight deadlines and work under pressure\nFamiliar with Microsoft Office, such as Excel, Power point\nExperience in sourcing system is advantageous\n1 year of relevant product experience in sizable company, ideally in a buying office environment in EU for consumer electronics products\nStrong communication skills, team-player mindset\nWilling to learn, change, be curious and self-motivated\nExcellent command of English, Mandarin and Cantonese\n\nWe offer attractive remuneration package including work from home policy, 13-instalment salary, discretionary bonus,\u00a0life, medical, dental and eyecare insurances to the right candidate.\u00a0Interested\u00a0applicants\u00a0please send\u00a0your\u00a0detailed\u00a0resume with current and expected salary and the\u00a0availability to Human Resources Department by clicking \"APPLY NOW\"\u00a0or by post:\n\nHuman Resources Department\nCurrys Sourcing Limited\n31/F, AXA Tower, Landmark East\n100 How Mong Street, Kwun Tong\nKowloon\n\nPersonal Data collected will be used for recruitment purposes only.\u00a0\u00a0Applicants who are not invited within 2 months may consider their application unsuccessful. Personal data of unsuccessful applicants will be retained for a period of up to 6 months from the date of rejecting applicants and will then be destroyed.", "employment_types": ["Full Time", "Permanent"], "selling_points": ["Attractive Remuneration Package", "Comprehensive Wellbeing Programme", "Work-life Balance"], "locations": ["Kwun Tong"], "categories": ["Merchandising & Purchasing", "Electronics", "Home Appliances", "Procurement / Purchasing / Sourcing"], "post_time": "2022-01-17T09:30:37Z", "salary": {"currency": null, "max": null, "min": null, "period": "monthly", "term": null}, "salary_visible": false, "title_keywords": ["product manager", "assistant"], "responsibilities": ["reporting", "management", "maintenance", "review", "day-to-day operations", "quality", "maintain"], "requirements": {"degrees": ["diploma or above"], "majors": [], "languages": ["cantonese", "english", "mandarin"], "language_level": ["excellent"], "hard_skills": ["power point", "excel", "microsoft office"], "soft_skills": ["communication skills", "self-motivated", "multi-tasks", "responsible", "team-player", "willing to learn", "mature", "detailed", "attention to details", "work under pressure"], "languages_combined": [{"language": "cantonese", "language_level": ["excellent"]}, {"language": "english", "language_level": ["excellent"]}, {"language": "mandarin", "language_level": ["excellent"]}]}, "experience_required": {"duration": ["1 year"], "field": []}}, {"job_id": "100003009054884", "location_code": "hk", "company": "Strand Global Limited", "job_title": "Assistant Sourcing Manager", "description": "Job Overview\n\nThe Purchasing Representative is a critical member of the NewPower Worldwide Procurement team and is responsible for driving revenue growth through new and existing vendor relationship. Your focus is to increase the vendor base and contribute to our long-term business growth. Responsibilities include researching targeted/strategic vendors, developing relationships with potential new vendors, managing, and growing existing vendor revenue opportunities.\n\nJob Roles & Responsibilities\n\n\nIdentify, qualify new suppliers and vendors.\nMonitors pertinent markets and defines how changes will impact supply and pricing conditions.\nResponsible to retrieve service request enquiries from Sales team and update pricing into the CRM.\nBuild, maintain strong relationship with existing and new suppliers and/or vendors.\n\nJob Requirement(s)\n\n\n\u00a0\u00a0\u00a0\u00a0\u00a0\u00a0\u00a0 Minimum a Diploma in any discipline\n\u00a0\u00a0\u00a0\u00a0\u00a0\u00a0\u00a0 Some years of experience as a Buyer/Sourcing role preferred.\n\u00a0\u00a0\u00a0\u00a0\u00a0\u00a0\u00a0 Candidates with no experience are welcome to apply\n\nPersonality Trait(s)\n\n\u00a0\u00a0\u00a0\u00a0\u00a0\u00a0\u00a0 Possesses a highly energetic, outgoing, and friendly demeanor\n\u00a0\u00a0\u00a0\u00a0\u00a0\u00a0\u00a0 Good negotiation skills\n\u00a0\u00a0\u00a0\u00a0\u00a0\u00a0\u00a0 Good communication and presentation skills, both verbal and written.\n\u00a0\u00a0\u00a0\u00a0\u00a0\u00a0\u00a0 Ability to work in fast-paced environment and under pressure\n\u00a0\u00a0\u00a0\u00a0\u00a0\u00a0\u00a0 Self-motivated and self-directed\n\u00a0\u00a0\u00a0\u00a0\u00a0\u00a0\u00a0 Able to multitask, prioritize and manage time efficiently\n\u00a0\u00a0\u00a0\u00a0\u00a0\u00a0\u00a0 Possesses a positive and can-do attitude\n\u00a0\u00a0\u00a0\u00a0\u00a0\u00a0\u00a0 Ability to work independently and as a team", "employment_types": ["Full Time"], "selling_points": ["Source a range of mobile phone accessories", "At least 3 yrs merchandising experience", "Work with factories to obtain best pricing"], "locations": ["Aberdeen"], "categories": ["Merchandising & Purchasing", "Electronics"], "post_time": "2022-01-17T12:35:04Z", "salary": {"currency": null, "max": null, "min": null, "period": "monthly", "term": null}, "salary_visible": false, "title_keywords": ["assistant", "sourcing manager"], "responsibilities": ["maintain", "sales team"], "requirements": {"degrees": ["diploma"], "majors": [], "languages": [], "language_level": [], "hard_skills": ["no"], "soft_skills": ["outgoing", "self-motivated", "work independently", "under pressure", "can-do attitude", "prioritize", "communication", "multitask", "negotiation skills", "presentation skills", "friendly", "work in fast-paced environment", "energetic", "positive"], "languages_combined": []}, "experience_required": {"duration": [], "field": []}}, {"job_id": "100003009052834", "location_code": "hk", "company": "Panasonic Hong Kong Co., Limited", "job_title": "Purchasing Quality Officer (Japanese Speaking)", "description": "Responsibilities:\n\nTo manage business account registration\nTo manage master setting for procurement\nTo monitor and manage quotation record\nTo enter and maintain the shipping data\nTo support for procurement data analysis and report\nTo provide the system support for supplier\nTo provide the general clerical support\nAd hoc duties will be assigned\n\nRequirements:\n\nDegree holder in purchasing, logistic management, or related discipline\nAt least 1 - 2 years with relevant experience\nBe precise in handling ( Accuracy & Efficiency of Work)\nIndependently, detail-oriented and rational thinking\nGood communication and interpersonal skill\nGood command of written\u00a0and spoken English, Chinese; Knowledge in Japaness would be an advantage\nProficient in MS Applications such as MS Office (Word, Excel, etc.)\nImmediate availability is preferred.\n\nWe offer 5 days\u2019 work and a competitive remuneration package to the right candidate. Interested candidate, please send your resume with the expected salary through \"Apply Now\"\n\n(Personal data collected will be used for recruitment purposes only)", "employment_types": ["Full Time", "Permanent"], "selling_points": ["Implement factory audit", "Monitor and provide guidance on quality standard", "Stable MNC in-house environment"], "locations": ["Tsim Sha Tsui"], "categories": ["Merchandising & Purchasing", "Electronics", "Manufacturing", "Quality Assurance, Control & Testing / ISO"], "post_time": "2022-01-17T04:13:27Z", "salary": {"currency": null, "max": null, "min": null, "period": "monthly", "term": null}, "salary_visible": false, "title_keywords": ["quality officer"], "responsibilities": ["ad hoc duties", "shipping", "data", "quotation", "monitor", "clerical support", "data analysis", "maintain", "report"], "requirements": {"degrees": ["degree holder"], "majors": [], "languages": ["english", "chinese"], "language_level": ["good command"], "hard_skills": ["excel", "ms applications", "word", "ms office"], "soft_skills": ["independently", "interpersonal skill", "communication", "detail-oriented", "precise"], "languages_combined": [{"language": "english", "language_level": ["good command"]}, {"language": "chinese", "language_level": ["good command"]}]}, "experience_required": {"duration": ["at least 1 - 2 years"], "field": ["relevant experience"]}}, {"job_id": "100003009048722", "location_code": "hk", "company": "Schenker International (H.K.) Limited", "job_title": "Purchaser - Warehousing / Logistics (Ref. no.: JD/LOG/058/220114)", "description": "Responsibility\n- Execute regular purchasing duties, e.g. PO processing, price negotiation, vendor sourcing, etc.;\n- Co-ordinate with other departments and suppliers in the purchasing scope of work;\n- Monitor the service, quality, price, on-time delivery and reliability of the suppliers.\n- Perform other duties as assigned.\n\n\nRequirement\nAcademic Qualification: Bachelor Degree holder or above;\nField of Study: Logistic / Supply Chain Management / Manufacturing / Engineering / Business Administration or other relevant discipline;\nYears of Experience: 1 - 3 years of related working experience;\n*Fresh graduate will also be considered.\n- Knowledgeable and hands-on experience in SAP & MS Office.\n- Effective communication skill with good command of written and spoken English & Chinese.\n\nFringe Benefit\n- Double Pay;\n- Incentive Bonus;\n- 5-days Work;\n- 12-19 days annual leave;\n- Medical, Dental & Life Insurance Scheme.\n\nApplication Method\nInterested parties please click \"APPLY NOW\" or send your application with the title & expected salary to HK Human Resources via Application E-mail.\n\nAll personal data collected will be used for recruitment purpose only. Only short-listed candidates will be contacted for interview.", "employment_types": ["Full Time", "Permanent"], "selling_points": ["Prepare purchase orders", "Monitor suppliers' performance", "Coordinate with internal parties on purchasing"], "locations": ["Tsing Yi"], "categories": ["Transportation & Logistics", "Inventory / Warehousing", "Supply Chain", "Merchandising & Purchasing", "Electronics"], "post_time": "2022-01-14T07:08:19Z", "salary": {"currency": null, "max": null, "min": null, "period": "monthly", "term": null}, "salary_visible": false, "title_keywords": ["logistics"], "responsibilities": ["price negotiation", "perform other duties", "co-ordinate with", "quality", "monitor"], "requirements": {"degrees": ["fresh graduate", "bachelor degree holder"], "majors": [], "languages": ["english", "chinese"], "language_level": ["good command"], "hard_skills": ["scheme", "sap", "ms office"], "soft_skills": ["hands-on", "communication skill"], "languages_combined": [{"language": "english", "language_level": ["good command"]}, {"language": "chinese", "language_level": ["good command"]}]}, "experience_required": {"duration": ["1 - 3 years"], "field": ["related"]}}, {"job_id": "100003009049411", "location_code": "hk", "company": "Johnson Electric Industrial Manufactory Limited", "job_title": "Sourcing Manager, Electronic Components, Asia", "description": "Have existing knowledge of headphone and mobile accessory factories\nWork with factory to obtain best pricing, range, logistics, lead-times and packaging option information\nSharing pricing information with UK head office\nEvaluating product quality vs. competitors\u00a0\nUpon range confirmation creating product and sales presentations for selected items\nLiaising with factory and UK for orders management, product development, cost negotiation to production\nCoordinate with overseas customers and factories to meet the sample/order requirements\nAssist UK Design team on the packaging design and artwork approval\nSubmit relative certificates & arranging product testing upon customer requirements\nManage and follow up with the production line to ensure the product quality and on-time delivery\nTravel to China for onsite inspection\nIdentify gaps within the portfolio and propose new items to UK office\nPerform other duties as assigned\n\nEssential Skills & Requirements:\n\nDiploma or above in Electrical Engineering\nAt least 3 years merchandising experience in Electronic products\nExperience in handling Electronic products, including Earphone, Headphone, Mobile phone cable and etc.\nSolid knowledge about the safety and test requirements\u00a0\nFamiliar with UK & EU market is advantageous\nGood command of written and spoken English and Mandarin with good computer knowledge\nSelf-motivated, independent, proactive, responsible and able to work under pressure to meet tight deadlines\nStrong communication and interpersonal skills\nImmediately available is preferred", "employment_types": ["Full Time"], "selling_points": ["APAC Project Procurement", "Automotive and Industrial Supply Chain experience", "Competitive remuneration and benefits"], "locations": ["Tai Po Area"], "categories": ["Transportation & Logistics", "Supply Chain", "Merchandising & Purchasing", "Electronics", "Procurement / Purchasing / Sourcing"], "post_time": "2022-01-14T08:34:33Z", "salary": {"currency": null, "max": null, "min": null, "period": "monthly", "term": null}, "salary_visible": false, "title_keywords": ["sourcing manager"], "responsibilities": ["management", "cost", "perform other duties", "packaging design", "quality", "liaising with", "presentations", "coordinate with", "design", "testing", "inspection", "merchandising", "logistics", "communication", "work under pressure"], "requirements": {"degrees": ["diploma or above"], "majors": ["electrical engineering"], "languages": ["english", "mandarin"], "language_level": ["good command", "good"], "hard_skills": ["vs", "mobile", "presentations"], "soft_skills": ["self-motivated", "meet tight deadlines", "independent", "negotiation", "responsible", "communication and interpersonal skills", "proactive", "work under pressure"], "languages_combined": [{"language": "english", "language_level": ["good command", "good"]}, {"language": "mandarin", "language_level": ["good command", "good"]}]}, "experience_required": {"duration": ["at least 3 years"], "field": ["merchandising"]}}, {"job_id": "100003009055048", "location_code": "hk", "company": "IBS Technology Int'l HK Limited", "job_title": "Warehouse Assistant (Electronics)", "description": "The Purchaser is responsible for monitoring the entire flow from placing the purchase order to suppliers, following up the order status to delivering material to production site.\n\nYour tasks:\n\n\nPrepare the purchase orders\nMonitor suppliers\u2019 performance of delivery and quality\nUpdate material related report to the management and planning team\nCoordinate with internal parties on purchasing, e.g. production, QA and warehouse, etc.\nWork with suppliers proactively to improve the delivery schedule\nPerform any special duties / assignment as assigned by the management\nYour qualifications, experience and skills:\n\nHigher Diploma in Supply Chain Management / Purchasing or other related discipline\nMinimum 3\u00a0years relevant experience in purchasing, fresh graduate is also considered\nFamiliar with MRP / ERP system is a plus\nProficiency in MS office including MS Word, Excel and PowerPoint\nGood command of spoken and written English and Mandarin\nStrong interpersonal, communication and negotiation skills\nSelf-motivated\nWell-organized and energetic\nAble to work independently and under pressure\nWork location: Tsing Yi\n\nInterested? We are looking forward to receiving your online application including availability and salary expectations.\n\n(Please quote the job reference no. on the subject of your application.)\u00a0\n\n(All information collected will be used for recruitment purpose only.)\n\nTo know more about us, please visit\u00a0www.dbschenker.com/cn", "employment_types": ["Full Time"], "selling_points": ["Medical insurance", "Five-day work week", "Electronics"], "locations": ["Kwai Hing"], "categories": ["Merchandising & Purchasing", "Electronics"], "post_time": "2022-01-18T00:53:03Z", "salary": {"currency": null, "max": null, "min": null, "period": "monthly", "term": null}, "salary_visible": false, "title_keywords": ["warehouse assistant"], "responsibilities": ["management", "monitoring", "quality", "monitor", "coordinate with", "delivery schedule", "communication", "purchase", "planning", "internal parties", "report"], "requirements": {"degrees": ["diploma", "fresh graduate"], "majors": [], "languages": ["english", "mandarin"], "language_level": ["good command"], "hard_skills": ["excel", "plus", "powerpoint", "erp system", "ms office", "ms word"], "soft_skills": ["self-motivated", "work independently", "under pressure", "responsible", "well-organized", "communication", "negotiation skills", "energetic", "interpersonal"], "languages_combined": [{"language": "english", "language_level": ["good command"]}, {"language": "mandarin", "language_level": ["good command"]}]}, "experience_required": {"duration": ["minimum 3 years"], "field": ["purchasing", "relevant experience"]}}, {"job_id": "100003009049479", "location_code": "hk", "company": "", "job_title": "Senior Purchasing Manager", "description": "Job summary \u2013 The purpose of the Position:\n\nJohnson Electric Supply Chain Services team is looking for a\u00a0Sourcing Manager, Electronic Components, Asia.\u00a0 This role will manage and execute sourcing process on commodity purchase for all Automotive and Non Auto Products Group\u2019s programs in Asia region.\u00a0 As the point of contact with design teams and responsible for new project costing.\n\n\nKey Responsibilities:\n\nExecute sourcing decisions based on project/platform based BOM costing\nCross-check and ensure current/new vendors under Segmentation matrix offer the best match on cost-efficiency and quality\nCreate and maintain project database including but not limited to organizing samples, checking supplier capacity and capabilities\nSuggest purchasing guideline\nManage a stable and efficient team with highest integrity\nInitiate digitalization to facilitate sourcing direction from big data\nHave regular review meetings on supplier performances feedback on new projects\nRequirements of the Job:\n\nBachelor or above in Electronics Engineering or Business Administration or related disciplines\n10 years of work experience with at least 5 years in purchasing organization from sizable Manufacturing or Automotive firms.\nArea of specialization in electronic components, electronic assemblies and associated parts like PCB and others\nSound leadership skills in strategic orientation and details execution, also provide coaching and mentoring to team\nStrong negotiation-skills with ability to analyze and make the best decision\nAbility to establish professional relationships and communicate, both verbally and in writing in English and Chinese, is essential\nProficient computer use\u00a0\nTravel to China facility locations\n\nWe regret only shortlisted candidates will be notified.\u00a0 Personal data provided by job applicants will be used strictly for recruitment purpose only, a copy of which will be provided upon request. Unless otherwise instructed in writing by the applicant concerned, applicants may be considered for other suitable positions within the Company. Applicants who do not hear from us within 8 weeks may consider their application unsuccessful and their data will be destroyed within 24 months of receipt.", "employment_types": ["Full Time", "Permanent"], "selling_points": ["Purchasing Management", "Electronics Company", "Direct and indirect materials"], "locations": ["Others - China"], "categories": ["Merchandising & Purchasing", "Electronics", "Procurement / Purchasing / Sourcing"], "post_time": "2022-01-14T08:44:13Z", "salary": {"currency": null, "max": null, "min": null, "period": "monthly", "term": null}, "salary_visible": false, "title_keywords": ["purchasing manager"], "responsibilities": ["cost", "quality", "checking", "big data", "regular review", "maintain", "database"], "requirements": {"degrees": ["bachelor"], "majors": ["related disciplines", "business administration", "engineering"], "languages": ["english", "chinese"], "language_level": [], "hard_skills": ["make"], "soft_skills": ["ability to analyze", "leadership skills", "negotiation"], "languages_combined": [{"language": "english", "language_level": []}, {"language": "chinese", "language_level": []}]}, "experience_required": {"duration": ["10 years", "at least 5 years"], "field": ["purchasing", "manufacturing"]}}, {"job_id": "100003009048691", "location_code": "hk", "company": "Cornerstone Technologies Holdings Limited", "job_title": "Senior Procurement Officer", "description": "Job Highlights\n-- Form 5 or above, fresh grad\n-- 5-day work/week normal office hours in office-warehouse environment\n-- inspection of electronics components\n\n\nJob Description\n\nResponsibilities:\n-- perform warehouse operations for incoming and outgoing shipments.\n-- quality control inspection of electronics components.\n-- data encoding in system database, data entry for QC records\n-- warehouse inventory checking\n\nRequirements:\n-- team player with good interpersonal & communication skills\n-- computer knowledge in MS Excel, MS Word, Outlook Email\n-- attentive to quality details, and with good initiative\n-- able to work under pressure and willing to work overtime", "employment_types": ["Full Time", "Permanent"], "selling_points": ["Material Control, demand planning, suppliers mgt.", "Product sourcing and price negotiation", "3-year exp., preferably in electrical industry"], "locations": ["Wong Tai Sin Area"], "categories": ["Transportation & Logistics", "Supply Chain", "Merchandising & Purchasing", "Electronics", "Procurement / Purchasing / Sourcing"], "post_time": "2022-01-14T07:02:56Z", "salary": {"currency": null, "max": null, "min": null, "period": "monthly", "term": null}, "salary_visible": false, "title_keywords": ["procurement officer"], "responsibilities": ["data", "data entry", "inventory", "checking", "inspection", "database", "quality control", "warehouse operations"], "requirements": {"degrees": [], "majors": [], "languages": [], "language_level": [], "hard_skills": ["ms excel", "outlook", "ms word"], "soft_skills": ["attentive", "communication skills", "work overtime", "team player", "interpersonal", "initiative", "work under pressure"], "languages_combined": []}, "experience_required": {"duration": [], "field": []}}, {"job_id": "100003009047120", "location_code": "hk", "company": "Longshore Ltd", "job_title": "Senior Merchandiser / Merchandiser - Toys", "description": "Responsibilities:\n\n\nResponsible for direct and indirect materials and general supplies (including but not limited to equipment, automation, spare parts, facilities, service, etc.) sourcing and purchasing operations;\nSet up target of purchasing functions and responsible for budget preparation;\nDevelop, assess, evaluate and manage\u00a0suppliers' performance;\nNegotiate price and manage contract with the suppliers;\nClosely monitor and ensure the purchasing order management runs smoothly and efficiently;\nMonitor goods quality and follow up delivery;\nImprove the process of purchasing flow, system and operation;\nSupport RFQ and suppliers selection;\nLead, coach and strengthen the team to meet the requirement of internal customers;\nPerform material and BOM price analysis, and prepare related reports;\nConduct continuous material cost reduction;\nKeep update with the supplier market trend;\nPerform ad-hoc activities as required.\n\nRequirements:\n\n\nDegree or above in Business Administration, Engineering, Purchasing or Supply Chain Management;\nMinimum 8 years solid experience, with at least 3 years in management position, in sourcing and purchasing of direct electronics components and general purchasing in sizeable or multinational manufacturing companies;\nGood component and product knowledge with proven record in handling electronics OEM/ ODM projects in areas of sourcing, supplier selection and certification, procurement and supplier performance management;\nHands on experience in MRP system operation;\nExpert at negotiation skills with suppliers for terms, conditions, lead-time and cost down;\nPositive working attitude, self-motivated, responsible, good communication skill and a good team player;\nGood analytical and negotiation skills;\nResult-oriented, able to work independently and under pressure;\nGood command of spoken and written English;\nCandidate with less experience will be considered as Purchasing Manager.\nInterested candidates, please contact us at 59189131 for company details before applying.", "employment_types": ["Full Time", "Permanent"], "selling_points": ["Whole merchandising procedure", "Excellent career prospect", "Immediate Available is preferred"], "locations": ["Hung Hom"], "categories": ["Manufacturing", "Product Development / Management", "Merchandising & Purchasing", "Electronics", "Toy"], "post_time": "2022-01-14T02:22:51Z", "salary": {"currency": null, "max": null, "min": null, "period": "monthly", "term": null}, "salary_visible": false, "title_keywords": ["merchandiser", "senior merchandiser"], "responsibilities": ["ad-hoc", "order management", "cost", "operations", "analysis", "budget", "monitor", "quality", "develop", "evaluate", "reports"], "requirements": {"degrees": ["degree or above"], "majors": ["business administration", "engineering"], "languages": ["english"], "language_level": ["good command"], "hard_skills": [], "soft_skills": ["self-motivated", "good team player", "work independently", "under pressure", "responsible", "communication skill", "positive working attitude", "negotiation skills", "hands on", "result-oriented"], "languages_combined": [{"language": "english", "language_level": ["good command"]}]}, "experience_required": {"duration": ["at least 3 years", "minimum 8 years"], "field": ["management position", "operation", "manufacturing", "purchasing"]}}, {"job_id": "100003009048020", "location_code": "hk", "company": "Edwin McAuley Electronics Ltd", "job_title": "Senior Purchasing Officer/ Purchasing Officer", "description": "\u00a0 \u00a0 \u00a0 \u00a0 \u00a0 \u00a0 \u00a0 \u00a0 \u00a0 \u00a0 \u00a0 \u00a0 \u00a0 \u00a0 \u00a0 \u00a0 \u00a0 \u00a0 \u00a0 \u00a0 \u00a0 \u00a0 \u00a0 \u00a0 \u00a0 (Limited quota and subject to stop plan)\n\nIn this role, you will\nmonitor sales growth,\u00a0capture financial needs with prompt follow up on analytically driven leads\nengage end to end customer service including needs identification, solution recommendations, application fulfillment, and follows up\nmanage individual insurance portfolio to ensure the customer satisfaction and persistency\nestablish effective working relationships with teams in order to ensure a consistent approach.\nbuild and maintain a positive team culture, through ensuring quality business referrals and referral skills among team members, and contributing to product knowledge and skills sharing\nEnjoy team activities, such as local charity, learn cantonese, movie day, and BBQ night with team members.\nWe are looking for:\nUniversity degree holder or above, preferably in sales and finance, less experienced will be considered as Financial Planning Officer\u00a0\nBeing ambitious in developing your own career with independence\nEntrepreneurship, achievement orientation, initiative and customer services orientation\nExcellent interpersonal, communications, presentation skills\nEnjoy stay in Hong Kong and work with local/oversea graduate trainee, work smart, play hard.\nImmediately available preferred\u00a0\nWe offer:\nExcellent and fast track career path\u00a0\nComprehensive and professional on job training\nAttractive package with month allowance, performance bonus and annual bonus\u00a0\nLuxurious annual overseas conferences\u00a0\nGroup life and group medical\u00a0\nInterested parties please call Mr Raymond Li at 94312357 for confidential conservation.", "employment_types": ["Full Time", "Permanent"], "selling_points": ["Manage & implement systematic procurement policy", "To propose/or make proper purchasing strategy plan", "5 days work per week, mid-year bonus & double pay"], "locations": ["North Point"], "categories": ["Merchandising & Purchasing", "Electronics", "Others", "Procurement / Purchasing / Sourcing"], "post_time": "2022-01-14T04:32:23Z", "salary": {"currency": null, "max": null, "min": null, "period": "monthly", "term": null}, "salary_visible": false, "title_keywords": ["purchasing officer"], "responsibilities": ["fulfillment", "monitor", "teams", "quality", "developing", "customer services", "customer service", "maintain", "plan", "working relationships", "insurance", "planning"], "requirements": {"degrees": ["university degree"], "majors": ["finance"], "languages": ["cantonese"], "language_level": [], "hard_skills": ["charity"], "soft_skills": ["prompt", "driven", "presentation skills", "customer service", "work smart", "interpersonal", "initiative", "positive"], "languages_combined": [{"language": "cantonese", "language_level": []}]}, "experience_required": {"duration": [], "field": []}}, {"job_id": "100003009045445", "location_code": "hk", "company": "ACTS Consulting Co", "job_title": "Commodity Buyer/Manager", "description": "We are seeking high caliber people like you to join us to fast-track your career with\u00a0Cornerstone Technologies.\n\nResponsibilities:\u00a0\n\nManage and monitor the Material suppliers including demand planning, order processing and forecasting, suppliers' management and logistics arrangement\nResponsible for product sourcing and price negotiation (electronic components and electro-mechanical parts)\nWork closely with\u00a0supplier and monitor\u00a0material\u00a0receiving, kitting, stock ledger accuracy and finish goods delivery\nManage stock level & logistics to ensure on time delivery\nGenerate and maintain effective reports to control Suppliers' production and material plan.\nTravel to PRC is required upon request (after Covid-19)\nPerform other ad hoc tasks assigned by the Management\n\nRequirements:\n\nHigher Diploma or above\nDegree holder in\u00a0Logistics, Procurement, Material control, or related discipline is preferred\nAt least 3 years of relevant experience in Electrical industry / electrical product trading company - Export Trade / Business\nKnowledge in purchasing electrical material and mechanical parts is preferred.\nProficiency in Word, Excel and Chinese word processing\nFamiliar with SAP system is preferred.\nGood command of both written and spoken English and Chinese\nFluency in Putonghua in a PLUS.\nPleasant, mature, proactive, independent, and able to work under pressure\nImmediately available is preferred.\n\nWe offer 5-day work and medical benefits to the successful candidates. Interested parties please send your full CV with current and expected salary in MS Word format to the Human Resources & Administration Manager.\n\nTo know more about us, please visit our website at\u00a0https://www.cstl.com.hk.\n\nWe are an equal opportunity employer and welcome applications from all qualified candidates.\n\nPersonal data collected will be treated in strict confidence and used only for recruitment-related purpose. Applicants who have not heard from us within four weeks may consider their applications unsuccessful. All personal data will be destroyed after 6 months.", "employment_types": ["Full Time"], "selling_points": ["Sourcing and purchasing of electronic components", "Fluent in written and spoken Mandarin and English", "Occasional travel to Mainland China"], "locations": ["Not Specified"], "categories": ["Engineering", "Electrical / Electronics", "Merchandising & Purchasing", "Electronics", "Procurement / Purchasing / Sourcing"], "post_time": "2022-01-13T07:52:04Z", "salary": {"currency": null, "max": null, "min": null, "period": "monthly", "term": null}, "salary_visible": false, "title_keywords": ["manager"], "responsibilities": ["management", "price negotiation", "control", "logistics arrangement", "demand planning", "monitor", "ensure on time delivery", "ad hoc tasks", "material receiving", "logistics", "maintain", "order processing", "reports", "plan", "forecasting"], "requirements": {"degrees": ["higher diploma or above", "degree holder"], "majors": [], "languages": ["putonghua", "english", "chinese"], "language_level": ["fluency", "proficiency", "good command"], "hard_skills": ["excel", "plus", "chinese word processing", "sap", "word"], "soft_skills": ["independent", "mature", "pleasant", "proactive", "work under pressure"], "languages_combined": [{"language": "putonghua", "language_level": ["fluency"]}, {"language": "english", "language_level": ["good command"]}, {"language": "chinese", "language_level": ["proficiency", "good command"]}]}, "experience_required": {"duration": ["at least 3 years"], "field": ["business", "relevant experience", "trading"]}}, {"job_id": "100003009049616", "location_code": "hk", "company": "Smart Product Concepts Limited", "job_title": "Sourcing and Product Specialist", "description": "Responsibilities:\n\nImplement factory audit to suppliers located in mainland China/Asia Pacific Region\nProvide assistance on supplier selection on electronic/mechanical parts\nMonitor and provide guidance to suppliers on quality standard\nWork closely with vendors and internal teams in cost and quality monitoring\nPrepare quality monitoring and factory audit reports\nCoordinate and follow up quality related issues\n\nRequirements:\n\nHigh Diploma holder or above\nAt least 1 year work experience in manufacturing/electronic field\nKnowledge of ISO9000/IATF16949 is an advantage\nGood command of English, Cantonese and Mandarin\nFluent in Japanese (JLPT N2 or above)\nProficient in MS Office\nWell organized, multi-tasking, good communication skills and positive thinking\nFrequent travel is required for factory assessment/audit (mainly in PRC)\n\nRemuneration will be commensurate with qualification and experience. Interested parties, please send your application with detailed resume indicating both existing & expected salary and date of availability to us.\n\nWe are an equal opportunity employer. All information provided by applicants will be treated in strict confidence and used for recruitment purpose only.", "employment_types": ["Full Time"], "selling_points": ["Guarantee 13th Month Salary", "Stable Work Environment", "International Company with Great Culture"], "locations": ["Hung Hom"], "categories": ["Manufacturing", "Product Development / Management", "Merchandising & Purchasing", "Electronics", "Home Appliances"], "post_time": "2022-01-14T08:58:25Z", "salary": {"currency": null, "max": null, "min": null, "period": "monthly", "term": null}, "salary_visible": false, "title_keywords": ["product specialist"], "responsibilities": ["cost", "monitoring", "quality", "provide assistance", "monitor", "audit", "teams", "coordinate", "reports", "provide guidance"], "requirements": {"degrees": ["high diploma"], "majors": [], "languages": ["cantonese", "japanese", "english", "mandarin"], "language_level": ["good command", "fluent"], "hard_skills": ["ms office"], "soft_skills": ["communication skills", "multi-tasking", "well organized", "positive thinking"], "languages_combined": [{"language": "cantonese", "language_level": ["good command"]}, {"language": "japanese", "language_level": ["fluent"]}, {"language": "english", "language_level": ["good command"]}, {"language": "mandarin", "language_level": ["good command"]}]}, "experience_required": {"duration": ["at least 1 year"], "field": ["manufacturing"]}}, {"job_id": "100003009049225", "location_code": "hk", "company": "Arrow Asia Pac Ltd", "job_title": "Asset Specialist", "description": "Commodity Buyer/Manager (Ref :\u00a075206)\n\nDuties and Responsibilities:-\n\nDemand-oriented, holistic support for assigned suppliers, including the necessary processes on price determination within the scope of the functional procurement matrix organization\nAnalysis, evaluate and interpret of the global procurement market in the commodity\nEnsures expertise implementation of business processes and operational guidelines\nDeterminate and define all parameters of the price for purchasing of the commodity\nCoordinate with the operative areas for material supply\nParticipate in the development and global implementation of the commodity strategy derived from the cluster strategy.\nExecution of contract negotiations in accordance with company guidelines\nParticipate to prepare and execute the supplier audits\nDevelop and define the master data for purchasing (e.g.: price, batch size, payment terms, logistics)\nEnsures the creation and updating of purchasing master data\nParticipate in supplier classification in accordance with company guidelines and implementation of the supplier strategy in the defined commodity\nParticipate on the introduction, implementation and further development of optimization measures/action items\n\nExperience or skills required:-\n\nBachelor degree or above in related discipline or equivalent\nMinimum 10 years of relevant experience with electronics technologies\nSolid and Practical experience in Sourcing and purchasing of electronic components\nExperience in the industries of Automotive, Medical, Aviation, Industrial\nPractical experience in leadership would be preferential\nFluent in written and spoken Mandarin and English\nExperience with SAP System\nOccasional travel to Mainland China (Shanghai) is required\nStrong Communication and negotiation skills", "employment_types": ["Full Time"], "selling_points": ["Buyer/ merchandiser in supply chain preferred", "Fortune 102, US listed company", "Attractive salary and salary package"], "locations": ["Shatin Area"], "categories": ["Transportation & Logistics", "Inventory / Warehousing", "Supply Chain", "Merchandising & Purchasing", "Electronics"], "post_time": "2022-01-14T08:17:30Z", "salary": {"currency": null, "max": null, "min": null, "period": "monthly", "term": null}, "salary_visible": false, "title_keywords": ["specialist"], "responsibilities": ["data", "guidelines", "analysis", "coordinate with", "implementation", "company guidelines", "evaluate", "develop", "payment", "logistics", "audits"], "requirements": {"degrees": ["degree or above", "bachelor"], "majors": [], "languages": ["english", "mandarin"], "language_level": ["fluent"], "hard_skills": ["sap"], "soft_skills": ["communication", "negotiation skills", "leadership"], "languages_combined": [{"language": "english", "language_level": ["fluent"]}, {"language": "mandarin", "language_level": ["fluent"]}]}, "experience_required": {"duration": ["minimum 10 years"], "field": ["purchasing", "relevant experience", "medical"]}}, {"job_id": "100003008946162", "location_code": "hk", "company": "Zollner Electronics HK Limited", "job_title": "Commodity Buyer", "description": "We experience rapid expansion and are looking for Talents in our merchandising teams to fill our newly created headcounts.\n\n\nJob Duties:\n\nHandle product enquiries, sourcing, product development, order processing, artwork, packaging, factory audit, testing compliance, production control\nResearch, liaise and identify capable factories from product sourcing to price negotiation\nNegotiate with suppliers on in-market products to achieve cost savings\nResearch and identify new products\nFunctional deep test on samples received\nEnsure shipment timeliness\nHandle special and ad-hoc projects as assigned\n\nRequirements:\n\nTertiary education in Engineering, Marketing, Purchasing and Supply, IT or equivalent is an advantage\n5+ years solid merchandizing experience plus project management experience from start to delivery\nMUST have experience in Small Domestic Appliances products. Familiar with EU / US markets and kitchen appliances are advantage\nStrong experiences in the relevant product field of the team concerned\nGood knowledge of EU / UL standards and regulations concerning product safety and requirements\nStrong sense of responsibility, good interpersonal and negotiation skills\nStrong analytical and problem-solving capabilities\nHighly self-motivated, able to work independent, creative, organized and with an eye for details\nAble to handle multi-tasks and work under pressure in a fast-moving environment\nFluent in spoken and written English, Cantonese and Mandarin\nWhat we offer:\n\nDouble pay and discretionary bonus\nMedical Insurance\nLearning and Development Opportunities\nNicely-decorated Office\n5 day work week\nCompetitive Annual Leave and Staff Benefit\nCharity, Community and Staff Recreational Activities\n\nCome and join us in a multi-cultural, dynamic and stable work environment, experience the opportunity to develop your career and to work in different exciting projects in an nicely decorated office.\n\nWe are an Equal Opportunity Employer. Interested parties, please send us your job application, the position you apply, together with Current and Expected Salary. We look forward to your application.", "employment_types": ["Full Time"], "selling_points": ["Bachelor degree or above in related discipline", ">10 years experience with electronics technologies", "5-day work week, comprehensive fringe benefits"], "locations": ["Kowloon Bay"], "categories": ["Merchandising & Purchasing", "Electronics", "Others", "Procurement / Purchasing / Sourcing"], "post_time": "2022-01-12T23:26:07Z", "salary": {"currency": null, "max": null, "min": null, "period": "monthly", "term": null}, "salary_visible": false, "title_keywords": [], "responsibilities": ["liaise", "control", "price negotiation", "cost", "compliance", "audit", "testing", "order processing", "ad-hoc projects"], "requirements": {"degrees": [], "majors": [], "languages": ["cantonese", "english", "mandarin"], "language_level": ["fluent"], "hard_skills": ["small", "merchandizing", "plus", "problem-solving", "project management"], "soft_skills": ["organized", "self-motivated", "independent", "multi-tasks", "sense of responsibility", "problem-solving", "project management", "negotiation skills", "creative", "interpersonal", "work under pressure"], "languages_combined": [{"language": "cantonese", "language_level": ["fluent"]}, {"language": "english", "language_level": ["fluent"]}, {"language": "mandarin", "language_level": ["fluent"]}]}, "experience_required": {"duration": ["5+ years"], "field": ["project management", "team"]}}, {"job_id": "100003009043697", "location_code": "hk", "company": "evMega Technology Limited", "job_title": "Purchasing Clerk (Manufacturing)", "description": "What You\u2019ll Be Doing\n\nMaintaining relationship with suppliers, internal supply chain teams and relevant stakeholders\nResolving sales/supplier related issues/questions and negotiate special returns.\nMaintaining procurement plans for components.\nAssists with the maintenance of appropriate levels of inventory, fulfilling open sales orders and forecasting.\nIdentifies key issues and patterns from partial /conflicting data\nTakes a broad perspective to problem and spots new, less obvious solutions\nForecasting and inventory review, product life cycle management.\nPlacement of initial PO's and monitor to alter or cancel inventory orders.\nSludge report review\u2014write-offs, write-downs, returns\nMaximizing revenue quarterly in order to gain market share and commodity revenue\u00a0\n\nWhat We Are Looking For\n\nBachelor's Degree or above\nMinimum 2 years\u2019 experience as buyer, merchandiser in supply chain\nElectronic components industry is preferred\nCommunicative level of Chinese and English\nSounds knowledge of Oracle, EAP or other relevant system\nOutstanding communication skill\nAble to completes work under moderate supervision\n\nWhat\u2019s In It For You\n\nAt Arrow, we recognize that financial rewards and great benefits are important aspects of an ideal job. That\u2019s why we offer competitive financial compensation, including various compensation plans, and a solid benefits package.\n\nInsurance\nDouble Pay\nIncentive\nPaid Time Off\n5-Day Work Week\nGrowth Opportunities\nAnd more!", "employment_types": ["Full Time", "Temporary", "Freelance"], "selling_points": [], "locations": ["Tsuen Wan Area"], "categories": ["Engineering", "Manufacturing & Production", "Merchandising & Purchasing", "Electronics", "Sales, CS & Business Devpt", "Sales Administration"], "post_time": "2022-01-13T01:31:28Z", "salary": {"currency": null, "max": null, "min": null, "period": "monthly", "term": null}, "salary_visible": false, "title_keywords": ["purchasing clerk"], "responsibilities": ["management", "maintenance", "maintaining", "data", "inventory", "review", "teams", "monitor", "communication", "plans", "forecasting", "report"], "requirements": {"degrees": ["degree or above", "bachelor"], "majors": [], "languages": ["english", "chinese"], "language_level": [], "hard_skills": ["maintenance", "oracle"], "soft_skills": ["communication skill"], "languages_combined": [{"language": "english", "language_level": []}, {"language": "chinese", "language_level": []}]}, "experience_required": {"duration": ["minimum 2 years"], "field": ["supply chain"]}}, {"job_id": "100003009044396", "location_code": "hk", "company": "Lidl Asia Pte. Limited (Hong Kong Branch)", "job_title": "Assistant Merchandiser Hardgoods (HiTech)", "description": "Responsibilities:\n\nHandle and Coordinate Plastic & Paper product development cycle (including board games & puzzles) with factory\nResponsible in\u00a0managing suppliers, product development schedule,\u00a0costing comparison & calculation, sourcing material and vendors.\nFollow-up orders with factory, customers and internal parties to ensure customer satisfaction and on-time delivery\nHandle ad-hoc assignments as required\n\nRequirements:\n\nForm 7 or above\n3 years experiences in\u00a0OEM/ODM Plastic & Paper products (Experiences in Board game, Puzzle are preferred)\nStrong with plastic paper development cycle / schedule\u00a0is a definite advantage\nGood in English and good in PC/ERP knowledge\nExcellent communication skills with overseas customers and vendors are essential\nDetail-minded, well-organized, responsible and can work independently\nImmediately available is preferred\n\nAlternate Saturday, Double pay, Medical, Annual leave, Bonus\n\nWe offer attractive remuneration packages and excellent career opportunities. Interested parties please send resume states clearly expected salary by \"Apply Now\"", "employment_types": ["Full Time"], "selling_points": ["Fresh grads welcome", "Excellent introduction into merchandising", "Great benefits"], "locations": ["Tsim Sha Tsui"], "categories": ["Merchandising & Purchasing", "Electronics"], "post_time": "2022-01-13T03:57:19Z", "salary": {"currency": null, "max": null, "min": null, "period": "monthly", "term": null}, "salary_visible": false, "title_keywords": ["assistant merchandiser"], "responsibilities": ["coordinate", "ad-hoc assignments", "schedule", "internal parties"], "requirements": {"degrees": [], "majors": [], "languages": ["english"], "language_level": ["good"], "hard_skills": ["pc", "erp"], "soft_skills": ["detail-minded", "communication skills", "work independently", "responsible", "well-organized"], "languages_combined": [{"language": "english", "language_level": ["good", "good"]}]}, "experience_required": {"duration": ["3 years"], "field": []}}, {"job_id": "100003009050210", "location_code": "hk", "company": "JFE Consulting Limited", "job_title": "Senior Merchandiser (Sweater / Home Textiles / Digital & Electronic appliance)", "description": "Job Responsibilities:\n\nAssist to manage & implement systematic procurement policy, procedure and controlling the systems for the purchasing of goods and services.\nAssist to propose or make proper purchasing strategy plan to ensure different materials categories in right purchase at the best cost and maintain of the minimum inventory level.\u00a0 The plan has to be review regularly.\nTo supervise and monitor the daily works of RFQ,Purchasing /Material Control teams to ensure on time delivery.\u00a0\u00a0\nkeep doing suppliers comparison for categories group, and propose an optimum choice of suppliers to Purchasing Manager for material share re-allocation.\nDefine / Drive an alternative source approval, and make quick change once having unsolved problem from existing suppliers.\u00a0\u00a0\nTo involve / lead the teams to be strong in negotiation with suppliers in the best business & custom clearance terms.\nOther ad hoc projects as assigned by Management.\n\nJob Requirements:\n\nUniversity Degree;\nAt least 4\u00a0years\u00a0experience in electronics components purchasing;\nProficient in MS office;\nSAP knowledge is\u00a0advantageous;\nOccasionally Travel to Dongguan;\nMore relevant experience will be considered as Senior Purchasing Officer\n\nWe place much emphasis on the career development of our employees, respect the worthiness of individual contributions and expect strong commitment to performance excellence.\n\nWe offer 5 days work per week, competitive remuneration package and fringe benefits including year-end and mid-year bonuses, medical scheme, life & accident insurance etc to the right candidate.\n\nInterested parties please send full resume stating current salary, expected salary and availability by clicking 'Apply Now' .\n\nAll information received will strictly be kept confidential and be used for employment-related purposes only.", "employment_types": ["Full Time", "Permanent"], "selling_points": ["5-day work, attractive salary, medical insurance", "Global  sourcing company,5+Merchandising exp", "Sweater/Home Textiles/Digital&Electronic appliance"], "locations": ["Not Specified"], "categories": ["Merchandising & Purchasing", "Electronics", "Sweater", "Textiles"], "post_time": "2022-01-14T09:56:54Z", "salary": {"currency": null, "max": null, "min": null, "period": "monthly", "term": null}, "salary_visible": false, "title_keywords": ["senior merchandiser"], "responsibilities": ["cost", "control", "management", "inventory", "systems", "review", "monitor", "teams", "ensure on time delivery", "purchase", "maintain", "ad hoc projects", "plan", "custom clearance"], "requirements": {"degrees": ["university degree"], "majors": [], "languages": [], "language_level": [], "hard_skills": ["scheme", "sap", "ms office"], "soft_skills": [], "languages_combined": []}, "experience_required": {"duration": ["at least 4 years"], "field": ["purchasing", "relevant experience"]}}, {"job_id": "100003009050776", "location_code": "hk", "company": "iDance International Limited", "job_title": "Sales Coordinator / Sales Executive", "description": "LOCATION: TSUEN WAN\n\nJOB DUTY:\n\nSearching new suppliers for Electrical and Electronics products\nNegotiate price and terms with suppliers\nPreparing price comparisons for management review\nIssuing PO and arrange delivery schedule\nHandling logistics for goods delivery and product quality issues\nAssisting sales to prepare SI and DN\nPerform other ad hoc tasks as assigned /required by supervisorREQUIREMENTS:\nForm 5 or above\n5 years working experience in Construction or Manufacturing Industry with good relationship with E&M suppliers in HK\nKnowledge in ERP like Multiable and stock keeping\nGood interpersonal skill and business mind\nGood command of Cantonese and English", "employment_types": ["Full Time", "Permanent"], "selling_points": [], "locations": ["Ngau Tau Kok"], "categories": ["Merchandising & Purchasing", "Electronics", "Sales, CS & Business Devpt", "Account Servicing", "Sales Administration"], "post_time": "2022-01-14T11:21:12Z", "salary": {"currency": null, "max": null, "min": null, "period": "monthly", "term": null}, "salary_visible": false, "title_keywords": ["sales coordinator", "sales executive"], "responsibilities": ["quality", "ad hoc tasks", "delivery schedule", "good relationship", "logistics", "management review"], "requirements": {"degrees": ["form 5 or above"], "majors": [], "languages": ["cantonese", "english"], "language_level": ["good command"], "hard_skills": ["wan", "erp"], "soft_skills": ["interpersonal skill"], "languages_combined": [{"language": "cantonese", "language_level": ["good command"]}, {"language": "english", "language_level": ["good command"]}]}, "experience_required": {"duration": ["5 years"], "field": ["manufacturing industry", "construction"]}}, {"job_id": "100003009040099", "location_code": "hk", "company": "Panasonic Hong Kong Co., Limited", "job_title": "Procurement Supervisor", "description": "Our client is a global product sourcing company\n\nResponsibilities:\n\nTo develop existing regional sourcing partners and create synergy within business partners\nExperienced in Regional Sourcing (US/EU Markets), Global\u00a0Sourcing experience would be a plus\nMaintain a good relationship with customers to build the business\nPlay teamwork between Merchandising team and Logistics team to ensure a timely delivery\nExcellent communication and coordination skills with different parties\n\nRequirement:\n\nAt least 2 years relevant experience in Merchandising\nKnowledgeable of Sweater OR Home Textiles OR Digital & Electronic appliance\nFamiliar with US, Canada & EU markets and regional sourcing\nExcellent command of spoken and written Cantonese, Mandarin, and English\nLess experience will be considered as\u00a0Merchandiser/ Assistant\u00a0Merchandiser", "employment_types": ["Full Time", "Permanent"], "selling_points": ["Liaise with both customers and suppliers", "4 years of experience in trading or purchasing", "Stable MNC in-house environment"], "locations": ["Tsim Sha Tsui"], "categories": ["Transportation & Logistics", "Supply Chain", "Merchandising & Purchasing", "Electronics", "Procurement / Purchasing / Sourcing"], "post_time": "2022-01-12T03:31:46Z", "salary": {"currency": null, "max": null, "min": null, "period": "monthly", "term": null}, "salary_visible": false, "title_keywords": ["supervisor"], "responsibilities": ["merchandising", "develop", "good relationship", "communication", "maintain", "logistics", "coordination"], "requirements": {"degrees": [], "majors": [], "languages": ["cantonese", "english", "mandarin"], "language_level": ["excellent"], "hard_skills": [], "soft_skills": [], "languages_combined": [{"language": "cantonese", "language_level": ["excellent"]}, {"language": "english", "language_level": ["excellent"]}, {"language": "mandarin", "language_level": ["excellent"]}]}, "experience_required": {"duration": ["at least 2 years"], "field": ["merchandising", "relevant experience"]}}, {"job_id": "100003009037911", "location_code": "hk", "company": "Dunamis International Company Limited", "job_title": "Purchase Executive", "description": "Responsibilities:\n\nAssist our merchandising team including but not limited to:\n\nData input for issuing PI and PO\nUpdate the order processing system\nMonitor inspection schedule including inspection booking, samples and QC files\nAdmin support\nApplications without the expected salary requested will not be considered.", "employment_types": ["Full Time"], "selling_points": ["Diploma or above", "Experienced with trading/ FMCG/ electronics", "Immediate availability is preferred"], "locations": ["Kwun Tong"], "categories": ["Marketing / Public Relations", "Marketing - Direct Marketing", "Merchandising & Purchasing", "Electronics", "Procurement / Purchasing / Sourcing"], "post_time": "2022-01-11T04:13:19Z", "salary": {"currency": null, "max": null, "min": null, "period": "monthly", "term": null}, "salary_visible": false, "title_keywords": ["executive"], "responsibilities": ["monitor", "merchandising", "data input", "inspection", "admin support", "schedule", "order processing", "booking"], "requirements": {"degrees": [], "majors": [], "languages": [], "language_level": [], "hard_skills": ["order processing"], "soft_skills": [], "languages_combined": []}, "experience_required": {"duration": [], "field": []}}, {"job_id": "100003009037463", "location_code": "hk", "company": "evMega Technology Limited", "job_title": "Purchasing Officer (Construction)", "description": "Our client, a Japanese Electronic Company, is looking for a\u00a0Japanese speaking Purchasing Executive to join the team:\n\nJob Duties\n\nSearch new suppliers(Electrical and Electronics products)\nNegotiate the price and T&C with suppliers\nNegotiate the price with overseas branches\nPrepare purchase plan and purchase order\nArrange delivery schedule\nPrepare cost reduction plan\nOther ad hoc duties as assigned\nResponsibilities\n\nDiploma Holder or above\nFluent in Japanese(JLPT N2 or above), English, and Chinese\nAt least 3 years of purchasing experience in a Japanese electronics company\nProficient in MS Office, especially EXCEL\nPackage:\n\n5-days-work\nMedical Allowance\u00a0\nTransportation allowance\nAnnual leave (Over 10 days)\nSick leave\nDouble pay\nDiscretionary bonus\nInterested parties please send us your resume in MS Word/PDF format in English.\nAll information collected will be kept strictly confidential and only for recruitment purpose.", "employment_types": ["Full Time", "Temporary", "Freelance"], "selling_points": [], "locations": ["Tsuen Wan Area"], "categories": ["Engineering", "Manufacturing & Production", "Merchandising & Purchasing", "Electronics", "Sales, CS & Business Devpt", "Sales Administration"], "post_time": "2022-01-11T02:53:29Z", "salary": {"currency": null, "max": null, "min": null, "period": "monthly", "term": null}, "salary_visible": false, "title_keywords": ["purchasing officer"], "responsibilities": ["ad hoc duties", "cost", "delivery schedule", "purchase", "plan"], "requirements": {"degrees": ["diploma holder"], "majors": [], "languages": ["japanese", "english", "chinese"], "language_level": ["fluent"], "hard_skills": ["excel", "ms office"], "soft_skills": [], "languages_combined": [{"language": "japanese", "language_level": ["fluent"]}, {"language": "english", "language_level": ["fluent"]}, {"language": "chinese", "language_level": ["fluent"]}]}, "experience_required": {"duration": ["at least 3 years"], "field": ["purchasing"]}}, {"job_id": "100003009040085", "location_code": "hk", "company": "Multi Lines International Company Limited", "job_title": "Merchandiser", "description": "Responsibilities :\n\nResponsible for and support order & sales management of product line(s) assigned;\nAssist in inventory management and analysis to achieve company target;\nCoordinate among internal & external parties to ensure an efficient and timely order process;\nPrepare various reports & analysis to vendors and internal management for review\n\nRequirements:\n\nUniversity graduate with 2 years working experience preferred;\nDetail-minded, self- motivated and good interpersonal skills;\nGood numerical and analytical sense;\nProficient in both spoken and written English and Chinese;\nProficient PC skills in MS office, especially Excel;\nFresh graduate will also be considered\u00a0\n\nWe offer attractive remuneration package to the right candidate.\u00a0 Interested parties, please send us your resume with current and expected salary by clicking \"Apply Now\".\u00a0\n\nFor more information about Synnex, please visit http://www.synnex.com.hk\n\nAll information will be treated in strict confidence and will be used exclusively for recruitment related purpose only", "employment_types": ["Full Time", "Permanent"], "selling_points": ["Strong product knowledge", "Experiences in Europe market", "Orders follow up"], "locations": ["Kowloon Bay"], "categories": ["Merchandising & Purchasing", "Electronics", "Home Appliances", "Others", "Others"], "post_time": "2022-01-12T02:06:23Z", "salary": {"currency": null, "max": null, "min": null, "period": "monthly", "term": null}, "salary_visible": false, "title_keywords": ["merchandiser"], "responsibilities": ["management", "analysis", "external parties", "review", "inventory management", "coordinate", "reports", "sales management"], "requirements": {"degrees": ["university graduate", "fresh graduate"], "majors": [], "languages": ["english", "chinese"], "language_level": ["proficient"], "hard_skills": ["excel", "pc skills", "ms office"], "soft_skills": ["detail-minded", "motivated", "interpersonal skills"], "languages_combined": [{"language": "english", "language_level": ["proficient"]}, {"language": "chinese", "language_level": ["proficient"]}]}, "experience_required": {"duration": ["2 years"], "field": []}}, {"job_id": "100003009036066", "location_code": "hk", "company": "Repco Group Limited", "job_title": "Assistant Merchandiser", "description": "Summary\n\nWe value diversity at Lidl and this includes creating collaborative teams with colleagues with diverse experiences and backgrounds. Continue your career journey and make a difference with us here at Lidl!\n\nWhat will you do?\nAssist in the daily merchandising operations\u00a0\nAssist with the follow-up of orders from sampling, approval and production\u00a0\nHelp with pricing and supplier negotiation\nWork closely with cross-functional departments (QA, PD, Production, Sourcing, Artwork...)\nProvide clerical support, such as data entry, parcels handling\nWhat will you need?\nForm 6 or above (HKDSE)/ Form 7 or above (HKALE)\nMerchandising experience in the hardgoods industry is preferable\u00a0\nGood command of written and spoken English, Mandarin and Cantonese\nDetail-oriented mindset\nMust be self motivated, self organised, responsible, hardworking and independent\nGood working attitude, willing to learn, and a good team player\nProficient in MS Office (specifically Excel)\nFresh graduates with a degree in Supply Chain Management/ Business Administration/ International Business or equivalent discipline\u00a0will also be considered\nWhat do we offer?\n\nWe are dedicated to fostering a family-friendly culture and work environment and have been a proud member of the Caring Company Scheme since 2014. We are an equal opportunities employer and welcome applications from all candidates with the required skills and experience.\n\n\u00a0\nMarket Leading Remuneration Package:\n\nDouble pay and discretionary bonus\nChoice of MPF provider\nLife Insurance\nMedical Insurance\n\u00a0\n\nSupportive Environment:\n\nRental re-imbursement scheme\nOut-Of-Office leave for important appointments\nIn-house training courses\nTraining sponsorship scheme\nHealth Check\nVision Check\nSupporting your child\u2019s education with advice from a leading education consultant\n\nWork-Life Balance:\n\n5 day week\nCompetitive Annual Leave\nCharity, Community and Sporting Events\n\nWe are dedicated to fostering a family-friendly culture and work environment and have been a proud member of the Caring Company Scheme since 2014. We are an equal opportunities employer and welcome applications from all candidates with the required skills and experience.\n\n\u00a0\nMarket Leading Remuneration Package:\n\nDouble pay and discretionary bonus\nChoice of MPF provider\nLife Insurance\nMedical Insurance\n\u00a0\n\nSupportive Environment:\n\nRental re-imbursement scheme\nOut-Of-Office leave for important appointments\nIn-house training courses\nTraining sponsorship scheme\nHealth Check\nVision Check\nSupporting your child\u2019s education with advice from a leading education consultant\n\nWork-Life Balance:\n\n5 day week\nCompetitive Annual Leave\nCharity, Community and Sporting Events", "employment_types": ["Full Time"], "selling_points": [], "locations": ["Chai Wan"], "categories": ["Merchandising & Purchasing", "Electronics"], "post_time": "2022-01-10T09:13:59Z", "salary": {"currency": null, "max": null, "min": null, "period": "monthly", "term": null}, "salary_visible": false, "title_keywords": ["assistant merchandiser"], "responsibilities": ["provide clerical support", "data entry", "operations", "merchandising", "teams"], "requirements": {"degrees": ["hkdse"], "majors": [], "languages": ["cantonese", "english", "mandarin"], "language_level": ["good command"], "hard_skills": ["make"], "soft_skills": ["negotiation", "diverse", "collaborative"], "languages_combined": [{"language": "cantonese", "language_level": ["good command"]}, {"language": "english", "language_level": ["good command"]}, {"language": "mandarin", "language_level": ["good command"]}]}, "experience_required": {"duration": [], "field": ["merchandising"]}}, {"job_id": "100003009053751", "location_code": "hk", "company": "AP Infosense Limited", "job_title": "Purchasing Officer", "description": "Requirements\n\nDiploma or above in purchasing/supply chain or related disciplines\nAt least 1-year relevant experience\nElectronics and optical components focused\nImmediate availability will be an advantage\nFluency in both Mandarin and English will be a plus\n\n\u00a0Responsibilities\n\nThe purchasing officer will be responsible to schedule shipping, to prepare accurate and complete purchase orders for supplies, materials and raw goods.\n\nHe/she will work closely with vendors for placing orders, ensuring purchase are recorded at the time of request and manage inventory.", "employment_types": ["Full Time", "Contract"], "selling_points": ["Diploma or above with 1 year related experience", "Fluent in English and Mandarin", "5 days work and performance bonus"], "locations": ["Shatin Area"], "categories": ["Merchandising & Purchasing", "Electronics"], "post_time": "2022-01-18T02:44:48Z", "salary": {"currency": null, "max": null, "min": null, "period": "monthly", "term": null}, "salary_visible": false, "title_keywords": ["purchasing officer"], "responsibilities": ["shipping", "inventory", "purchase", "schedule", "placing orders"], "requirements": {"degrees": ["diploma or above"], "majors": ["related disciplines"], "languages": ["english", "mandarin"], "language_level": ["fluency"], "hard_skills": ["plus"], "soft_skills": ["focused"], "languages_combined": [{"language": "english", "language_level": ["fluency"]}, {"language": "mandarin", "language_level": ["fluency"]}]}, "experience_required": {"duration": ["at least 1-year"], "field": ["relevant experience"]}}, {"job_id": "100003009056410", "location_code": "hk", "company": "Panasonic Hong Kong Co., Limited", "job_title": "Procurement Coordinator / Officer", "description": "Responsibilities:\n\nTo handle\u00a0RFQ, PO processing and monitoring\nTo\u00a0keep close contact with customers and suppliers for quotation and follow up outstanding PO delivery status\nTo\u00a0maintain PO, invoice files and related purchasing records such as material, price, inventory and delivery records\nTo work with shipping team and support logistics operations with warehouse & forwarders where necessary\nTo assist other ad-hoc projects as assigned\n\n\nRequirements:\n\nForm 7 / DSE graduate or above\n2 years of relevant international trading experiences especially in electrical parts and components\nGood command of written and spoken English and Chinese, knowledge in Japanese is definitely an advantage\nProficient in MS Office\nGood communication skill, well organized and a fast learner\nMore experience will be considered as Procurement Officer\nImmediate available / short notice will be an advantage\n\nRemuneration will be commensurate with qualification and experience. Interested parties, please send your application with detailed resume indicating both existing & expected salary and date of availability to us.\n\nWe are an equal opportunity employer. All information provided by applicants will be treated in strict confidence and used for recruitment purpose only.", "employment_types": ["Full Time", "Permanent"], "selling_points": ["All round procurement exposure", "Attractive package with good career prospect", "Stable MNC in-house environment"], "locations": ["Tsim Sha Tsui"], "categories": ["Transportation & Logistics", "Supply Chain", "Merchandising & Purchasing", "Electronics", "Procurement / Purchasing / Sourcing"], "post_time": "2022-01-18T04:12:13Z", "salary": {"currency": null, "max": null, "min": null, "period": "monthly", "term": null}, "salary_visible": false, "title_keywords": ["officer", "coordinator"], "responsibilities": ["shipping", "invoice", "operations", "inventory", "quotation", "monitoring", "maintain", "logistics", "contact", "ad-hoc projects"], "requirements": {"degrees": ["dse"], "majors": [], "languages": ["japanese", "english", "chinese"], "language_level": ["advantage", "good command"], "hard_skills": ["ms office"], "soft_skills": ["fast learner", "communication skill", "well organized"], "languages_combined": [{"language": "japanese", "language_level": ["advantage", "good command"]}, {"language": "english", "language_level": ["advantage", "good command"]}, {"language": "chinese", "language_level": ["advantage", "good command"]}]}, "experience_required": {"duration": ["2 years"], "field": ["trading", "procurement"]}}, {"job_id": "100003009055775", "location_code": "hk", "company": "Dunamis International Company Limited", "job_title": "Purchase Executive", "description": "Duties & Responsibilities\n\n\nLiaise with suppliers, follow-up purchase orders, delivery arrangement and inventory control\nManage and develop the assigned product category to drive sales and meet margin target\nKeeping up with market trends, to assist products category are developed in the correct direction\nClosely monitoring assign product\u2019s category and its market price to make sure we are at our most combative on all across channel included our ecommerce platform\nTo handle PO processing and monitoring\nManage quotations, documents & costing\nTo assist other ad-hoc projects as assigned\n\nExperience & Qualifications\n\n\nDiploma or above\n2-5 year work experience, experienced with trading/ FMCG/ electronics related industry will be an advantage\nGood command in spoken and written Chinese and English\nAdaptable to changes with good communication skills, able to work in a fast-paced environment\nImmediate availability is preferred\n\nWe offer attractive fringe benefits including: 5 days-work week, bank holidays & Attendance Bonus.\n\nOur website: http://www.dunamis.hk", "employment_types": ["Full Time"], "selling_points": ["Diploma or above", "Experienced with trading/ FMCG/ electronics", "Immediate availability is preferred"], "locations": ["Kwun Tong"], "categories": ["Marketing / Public Relations", "Marketing - Direct Marketing", "Merchandising & Purchasing", "Electronics", "Procurement / Purchasing / Sourcing"], "post_time": "2022-01-18T02:56:14Z", "salary": {"currency": null, "max": null, "min": null, "period": "monthly", "term": null}, "salary_visible": false, "title_keywords": ["executive"], "responsibilities": ["monitoring", "develop", "communication", "purchase", "inventory control", "drive sales", "ad-hoc projects", "liaise with suppliers"], "requirements": {"degrees": ["diploma or above"], "majors": [], "languages": ["english", "chinese"], "language_level": ["good command"], "hard_skills": ["make", "processing"], "soft_skills": ["adaptable", "communication skills", "fast-paced environment"], "languages_combined": [{"language": "english", "language_level": ["good command"]}, {"language": "chinese", "language_level": ["good command"]}]}, "experience_required": {"duration": ["2-5 year"], "field": ["related", "fmcg", "trading"]}}, {"job_id": "100003009055179", "location_code": "hk", "company": "", "job_title": "Business Development Manager (Apply to IANG applicant)", "description": "\u00a0 \u00a0 \u00a0 \u00a0 \u00a0 \u00a0 \u00a0 \u00a0 \u00a0 \u00a0 \u00a0 \u00a0 \u00a0 \u00a0 \u00a0 \u00a0 \u00a0 \u00a0 \u00a0 \u00a0 \u00a0 \u00a0 \u00a0 \u00a0 \u00a0 (Limited quota and subject to stop plan)\n\nIn this role, you will\nmonitor sales growth,\u00a0capture financial needs with prompt follow up on analytically driven leads\nengage end to end customer service including needs identification, solution recommendations, application fulfillment, and follows up\nmanage individual insurance portfolio to ensure the customer satisfaction and persistency\nestablish effective working relationships with teams in order to ensure a consistent approach.\nbuild and maintain a positive team culture, through ensuring quality business referrals and referral skills among team members, and contributing to product knowledge and skills sharing\nEnjoy team activities, such as local charity, learn cantonese, movie day, and BBQ night with team members.\nWe are looking for:\nUniversity degree holder or above, preferably in sales and finance, less experienced will be considered as Financial Planning Officer\u00a0\nBeing ambitious in developing your own career with independence\nEntrepreneurship, achievement orientation, initiative and customer services orientation\nExcellent interpersonal, communications, presentation skills\nEnjoy stay in Hong Kong and work with local/oversea graduate trainee, work smart, play hard.\nImmediately available preferred\u00a0\nWe offer:\nExcellent and fast track career path\u00a0\nComprehensive and professional on job training\nAttractive package with month allowance, performance bonus and annual bonus\u00a0\nLuxurious annual overseas conferences\u00a0\nGroup life and group medical\u00a0\nInterested parties please call Mr Raymond Li at 94312357 for confidential conservation.", "employment_types": ["Full Time", "Permanent", "Contract", "Freelance"], "selling_points": [], "locations": ["Kwun Tong"], "categories": ["Hospitality / F & B", "Hospitality / Hotel Services", "Insurance", "Insurance Agent / Broker", "Merchandising & Purchasing", "Electronics"], "post_time": "2022-01-18T01:40:05Z", "salary": {"currency": null, "max": null, "min": null, "period": "monthly", "term": null}, "salary_visible": false, "title_keywords": ["business development manager"], "responsibilities": ["fulfillment", "monitor", "teams", "quality", "developing", "customer services", "customer service", "maintain", "plan", "working relationships", "insurance", "planning"], "requirements": {"degrees": ["university degree"], "majors": ["finance"], "languages": ["cantonese"], "language_level": [], "hard_skills": ["charity"], "soft_skills": ["prompt", "driven", "presentation skills", "customer service", "work smart", "interpersonal", "initiative", "positive"], "languages_combined": [{"language": "cantonese", "language_level": []}]}, "experience_required": {"duration": [], "field": []}}, {"job_id": "100003009046245", "location_code": "hk", "company": "RGF HR Agent Hong Kong Limited", "job_title": "Japanese speaking Purchasing Executive - Electronic Company (Up to 21K/Hung Hom/Good package)", "description": "Our client, a Japanese Electronic Company, is looking for a\u00a0Japanese speaking Purchasing Executive to join the team:\n\nJob Duties\n\nSearch new suppliers(Electrical and Electronics products)\nNegotiate the price and T&C with suppliers\nNegotiate the price with overseas branches\nPrepare purchase plan and purchase order\nArrange delivery schedule\nPrepare cost reduction plan\nOther ad hoc duties as assigned\nResponsibilities\n\nDiploma Holder or above\nFluent in Japanese(JLPT N2 or above), English, and Chinese\nAt least 3 years of purchasing experience in a Japanese electronics company\nProficient in MS Office, especially EXCEL\nPackage:\n\n5-days-work\nMedical Allowance\u00a0\nTransportation allowance\nAnnual leave (Over 10 days)\nSick leave\nDouble pay\nDiscretionary bonus\nInterested parties please send us your resume in MS Word/PDF format in English.\nAll information collected will be kept strictly confidential and only for recruitment purpose.", "employment_types": ["Full Time", "Permanent"], "selling_points": ["Japanese Electronic Company", "Japanese speaking Purchasing Executive /JLPT N1", "Up to 21K / Hung Hom"], "locations": ["Hung Hom"], "categories": ["Merchandising & Purchasing", "Electronics"], "post_time": "2022-01-13T10:05:17Z", "salary": {"currency": null, "max": null, "min": null, "period": "monthly", "term": null}, "salary_visible": false, "title_keywords": ["purchasing executive"], "responsibilities": ["ad hoc duties", "cost", "delivery schedule", "purchase", "plan"], "requirements": {"degrees": ["diploma holder"], "majors": [], "languages": ["japanese", "english", "chinese"], "language_level": ["fluent"], "hard_skills": ["excel", "ms office"], "soft_skills": [], "languages_combined": [{"language": "japanese", "language_level": ["fluent"]}, {"language": "english", "language_level": ["fluent"]}, {"language": "chinese", "language_level": ["fluent"]}]}, "experience_required": {"duration": ["at least 3 years"], "field": ["purchasing"]}}, {"job_id": "100003009043068", "location_code": "hk", "company": "Synnex Technology International (HK) Ltd", "job_title": "Procurement Officer", "description": "Responsibilities :\n\nResponsible for and support order & sales management of product line(s) assigned;\nAssist in inventory management and analysis to achieve company target;\nCoordinate among internal & external parties to ensure an efficient and timely order process;\nPrepare various reports & analysis to vendors and internal management for review\n\nRequirements:\n\nUniversity graduate with 2 years working experience preferred;\nDetail-minded, self- motivated and good interpersonal skills;\nGood numerical and analytical sense;\nProficient in both spoken and written English and Chinese;\nProficient PC skills in MS office, especially Excel;\nFresh graduate will also be considered\u00a0\n\nWe offer attractive remuneration package to the right candidate.\u00a0 Interested parties, please send us your resume with current and expected salary by clicking \"Apply Now\".\u00a0\n\nFor more information about Synnex, please visit http://www.synnex.com.hk\n\nAll information will be treated in strict confidence and will be used exclusively for recruitment related purpose only", "employment_types": ["Full Time", "Permanent"], "selling_points": [], "locations": ["Kowloon Bay"], "categories": ["Marketing / Public Relations", "Marketing - Brand / Product Management", "Merchandising & Purchasing", "Electronics", "Procurement / Purchasing / Sourcing"], "post_time": "2022-01-12T09:42:15Z", "salary": {"currency": null, "max": null, "min": null, "period": "monthly", "term": null}, "salary_visible": false, "title_keywords": ["procurement officer"], "responsibilities": ["management", "analysis", "external parties", "review", "inventory management", "coordinate", "reports", "sales management"], "requirements": {"degrees": ["university graduate", "fresh graduate"], "majors": [], "languages": ["english", "chinese"], "language_level": ["proficient"], "hard_skills": ["excel", "pc skills", "ms office"], "soft_skills": ["detail-minded", "motivated", "interpersonal skills"], "languages_combined": [{"language": "english", "language_level": ["proficient"]}, {"language": "chinese", "language_level": ["proficient"]}]}, "experience_required": {"duration": ["2 years"], "field": []}}, {"job_id": "100003009041398", "location_code": "hk", "company": "Find Asia Limited", "job_title": "Procurement Officer (Japanese Electronics)", "description": "We are looking for Talents in our merchandising teams\n\n\n\nThe Role\n\n\nIn charge of and coordinate inter-departmentally the project process from product enquiries, supplier selection, sourcing, product specifications, order processing, artwork, packaging, factory audit, testing compliance, product development, negotiation, contracting, streamline the production process and control, QC and the way till delivery\nStrengthen and maintain good relationship and strategic partnership with suppliers as well as assess and monitor supplier capabilities and their performance\nReview regularly the material price development and industry trends to get insight to negotiate for favorable price\nMonitor, control and evaluate the merchandising team activities to ensure they are on track. Identify key areas for improvement and to apply remedies / response plans when necessary\nEnsure all kinds of compliance with local country and client specific requirements, in partnership with our Technical / Quality Control Teams\nDevelop a diverse and confident team, provide development, coaching, motivation, support and feedback to team members. Create a positive atmosphere of teamwork, inclusion and collaboration, as well as high performing work teams\n\n\nThe Person\n\n\nTertiary education in Engineering, Marketing, Purchasing and Supply, IT or equivalent is an advantage\n10+ years solid merchandizing experience plus project management experience from start to delivery. For managerial position we expect leadership skills and experience\nExperience in Small Domestic Appliances, especially different kinds of Breakfast sets and Coffee Machines will be an\u00a0advantage\nFamiliar with EU markets advantage\nStrong experiences in the relevant product field of the team concerned\nGood knowledge of EU / UL standards and regulations concerning product safety and requirements\nStrong sense of responsibility and integrity, good interpersonal and negotiation skills\nStrong analytical, communication, leadership and problem-solving capabilities\nHighly self-motivated, able to work independently, creative, organized and with an eye for details, mature and reliable\n\nAble to handle multi-tasks and work under pressure in a fast-moving environment\nFluent in spoken and written English, Cantonese and Mandarin\nExperience in overseas buying office will be a definite advantage\n\nWhy work with us?\u00a0\n\nThis is a fabulous opportunity to join TGI\u2019s adventure and to actively contribute to the development of the business by becoming part of us that offers:\u00a0\n\nExtraordinary\u00a0remuneration package\nRewarding, attractive remuneration package includes Double Pay and discretionary bonus\u00a0\nComprehensive\u00a0Group Medical\u00a0and furthermore\u2026\u00a0\n\nPeople &\u00a0Talent focused\u00a0\nTGI cares about people and provides\u00a0flexible working hours,\u00a0on\u00a0the\u00a0job training\u00a0and nicely decorated office\u00a0\n\nBeing part of a pleasant, fun, successful growing business\u00a0\nTGI\u2019s business is expanding, and we need more talents to fulfil our growth.\n\nTGI is building a friendly and employee wellness focused workplace which gives:\u00a0\n\nRelax, Cheerful and joyful\u00a0working environment\u00a0\nDiverse\u00a0company events and\u00a0staff recreational\u00a0activities focusing on employee wellness\u00a0\n\nRich & Healthy Catering\u00a0\nFresh & Healthy snacks, food & drinks, refreshments, and pop-up buffets\u00a0are ready to\u00a0fulfil\u00a0your appetite\u00a0\n\nWant to know more what we have done? Go to\u00a0Link\u025bdIn\u00a0and search\u00a0with our company name\u00a0for more!\u00a0\n\n\nInterested parties, please send us your job application,\u202fstating the markets and products you have handled (A MUST, otherwise we cannot evaluate your application further), the position you apply, together with current and expected salary.\u00a0\n\nIf you have applied our positions before, you are welcome to re-apply, due to our expansions we are in urgent need of diverse talents.\u00a0\n\nWe are Equal Opportunity Employer and Registered Caring & Happy Workplace Company.\u00a0We look forward to your application and welcome you onboard to join our great workplace.\u00a0", "employment_types": ["Full Time", "Permanent"], "selling_points": ["Purchasing, Procurement", "Japanese Electronics, Officer/ Supervisor", "5 days, Double Pay, Bonus"], "locations": ["Yau Tsim Mong Area"], "categories": ["Transportation & Logistics", "Supply Chain", "Manufacturing", "Manufacturing Management", "Merchandising & Purchasing", "Electronics"], "post_time": "2022-01-12T03:50:18Z", "salary": {"currency": null, "max": null, "min": null, "period": "monthly", "term": null}, "salary_visible": false, "title_keywords": ["procurement officer"], "responsibilities": ["regulations", "production process", "merchandising", "audit", "communication", "plans", "work under pressure", "control", "compliance", "teams", "monitor", "testing", "maintain good relationship", "develop", "review", "specifications", "coordinate", "project management", "evaluate", "contracting", "order processing", "quality control", "catering"], "requirements": {"degrees": [], "majors": [], "languages": ["cantonese", "english", "mandarin"], "language_level": ["fluent"], "hard_skills": ["small", "merchandizing", "plus", "fun", "problem-solving", "project management", "order processing", "go"], "soft_skills": ["focused", "leadership skills", "communication", "comprehensive", "leadership", "work under pressure", "confident", "cheerful", "multi-tasks", "problem-solving", "integrity", "mature", "pleasant", "diverse", "creative", "reliable", "interpersonal", "organized", "work independently", "negotiation", "negotiation skills", "friendly", "positive", "flexible", "self-motivated", "sense of responsibility", "teamwork", "project management"], "languages_combined": [{"language": "cantonese", "language_level": ["fluent"]}, {"language": "english", "language_level": ["fluent"]}, {"language": "mandarin", "language_level": ["fluent"]}]}, "experience_required": {"duration": ["10+ years"], "field": ["project management", "managerial", "team"]}}, {"job_id": "100003009039167", "location_code": "hk", "company": "TGI Technology Limited", "job_title": "Head of Merchandising", "description": "Job Duties:\n\nResponds to customer inquiries, expedites critical orders, communicates dispositions, researches and resolves issues, and researches orders\nCoordinate with internal and external customers\nDaily shipment coordination\nHandle system transactions\nPrepare shipping documentations, filing and reports\nTo follow up daily operation to comply with the KPI\nAny ad-hoc support upon requested\n\nJob Requirements:\n\n\nHigh School / Diploma or above\nAt least 1 year related experience in warehouse or logistics industry\nBasic computer, email, phone and communication skills\nMust be able to multi-task and work in a fast paced environment\nGood command of spoken and written in English, Cantonese and Mandarin\nWith SAP knowledge will be an advantage\n\nInterested parties please submit your application together with details CV (including salary history and expected salary) to the HR Department via\u00a0our career website (Click Here)\u00a0or by email at hkrecruitment @avnet.com. Please quote clearly the position your apply for in the email subject.\n\n\nAll applications will be treated in strict confidence and personal data provided with be used solely for recruitment purpose. Unsuccessful candidates may be considered for other vacancies. Applicants who are not contacted within one month should consider their applications filed for future reference. All unsuccessful applications will be destroyed within six months.", "employment_types": ["Full Time", "Permanent"], "selling_points": ["Guarantee 13th Month Salary", "Job Security", "International Company with Great Culture"], "locations": ["Hung Hom"], "categories": ["Merchandising & Purchasing", "Electronics", "Home Appliances", "Procurement / Purchasing / Sourcing"], "post_time": "2022-01-11T08:55:10Z", "salary": {"currency": null, "max": null, "min": null, "period": "monthly", "term": null}, "salary_visible": false, "title_keywords": ["merchandising"], "responsibilities": ["ad-hoc", "internal and external customers", "shipping", "customer inquiries", "coordinate with", "daily operation", "transactions", "reports", "coordination"], "requirements": {"degrees": ["diploma or above", "high school"], "majors": [], "languages": ["cantonese", "english", "mandarin"], "language_level": ["good command"], "hard_skills": ["basic", "sap"], "soft_skills": ["communication skills", "multi-task", "work in a fast paced environment"], "languages_combined": [{"language": "cantonese", "language_level": ["good command"]}, {"language": "english", "language_level": ["good command"]}, {"language": "mandarin", "language_level": ["good command"]}]}, "experience_required": {"duration": ["at least 1 year"], "field": ["related", "logistics industry"]}}, {"job_id": "100003009045969", "location_code": "hk", "company": "Avnet Technology Hong Kong Limited", "job_title": "Logistics Clerk / Customer Service Representative", "description": "Responsibilities:\n\nMaintains close relationship and high level of satisfaction among key customers in order to create new business opportunities\nIdentifies and develops a network of suppliers capable of meeting the company\u2019s requirement\nLiaise with both customers and suppliers for favourable terms and long-term contracts. Follow up on quotation\nReviews operational issues and recommend strategies for price rationalization, quality improvements and process efficiencies\nSupervises subordinates and provide solutions to operational issues to ensure efficient delivery of materials\nParticipates in ad hoc operation and compliance projects\n\n\nRequirements:\n\nDegree in Supply Chain Management or other relevant disciplines\n4\u00a0years of experience in trading or purchasing of electronic parts or materials\nExperience in system enhancement/development projects is an advantage\u00a0\nSolid experience in dealing with suppliers in China and Southeast Asia\nGood command of spoken & written English, Mandarin. Knowledge in Japanese is definitely an advantage\nGood logical thinking & analytical mind\nRemuneration will be commensurate with qualification and experience. Interested parties, please send your application with detailed resume indicating both existing & expected salary and date of availability to us.\nWe are an equal opportunity employer. All information provided by applicants will be treated in strict confidence and used for recruitment purpose only.", "employment_types": ["Full Time", "Permanent"], "selling_points": ["Double Pay, Discretionary Incentive (Quarterly)", "At least 1 yr exp in warehouse/logistics industry", "Good command of spoken Eng., Mandarin & Cantonese"], "locations": ["Tsuen Wan Area"], "categories": ["Transportation & Logistics", "Inventory / Warehousing", "Shipping", "Merchandising & Purchasing", "Electronics"], "post_time": "2022-01-13T09:15:40Z", "salary": {"currency": null, "max": null, "min": null, "period": "monthly", "term": null}, "salary_visible": false, "title_keywords": ["logistics clerk", "customer service representative"], "responsibilities": ["ad hoc", "contracts", "business opportunities", "quotation", "quality", "compliance", "provide solutions", "liaise with"], "requirements": {"degrees": ["degree"], "majors": [], "languages": ["japanese", "english", "mandarin"], "language_level": ["advantage", "good command"], "hard_skills": [], "soft_skills": ["good logical thinking", "analytical mind"], "languages_combined": [{"language": "japanese", "language_level": ["advantage"]}, {"language": "english", "language_level": ["good command"]}, {"language": "mandarin", "language_level": ["good command"]}]}, "experience_required": {"duration": ["4 years"], "field": ["purchasing", "trading", "development projects"]}}, {"job_id": "100003009043617", "location_code": "hk", "company": "Wilson Communications Limited", "job_title": "Senior Merchandising Officer / Merchandising Officer (Mobile Phone)", "description": "Excellent opportunity for order fulfilment experts to work for a leading electronics trading company.\n\nClient Details\n\nOur client is one of the most reputable companies within the electronics industry. With over decades of history, they have been delivering the best products and services to the world. With steady and rapid expansion in business in Hong Kong, they are actively looking for an Order Administrator to join their dynamic company.\n\nDescription\n\nPrepare purchase order, shipping documents, invoices, quotation, etc.\nMaintain relationships with existing customers and exploring new customers for continual business growth\nCoordinate with multiple parties to ensure accurate product information, inventory level and delivery schedule\nAssist in ad-hoc duties as per assigned\n\nProfile\n\nHigher Diploma/Degree in Supply Chain Management/Logistics\nKnowledge in Excel - VLOOKUP and Pivot Table is a competitive advantage\nStrong analytical skills with numerical sense\nOrganized and detail-oriented individual\nExcellent command in both English and Chinese\n\nJob Offer\n\nWork-life balance\nCompetitive package", "employment_types": ["Full Time", "Permanent"], "selling_points": ["5-Day, Kwai Fong, Free Shuttle Bus", "Order follow up, sampling and price negotiations", "Prepare various analysis reports and statistics"], "locations": ["Kwai Fong"], "categories": ["Merchandising & Purchasing", "Electronics", "Home Appliances", "Procurement / Purchasing / Sourcing"], "post_time": "2022-01-13T00:47:17Z", "salary": {"currency": null, "max": null, "min": null, "period": "monthly", "term": null}, "salary_visible": false, "title_keywords": ["officer", "merchandising"], "responsibilities": ["shipping documents", "maintain relationships", "management", "invoices", "inventory", "quotation", "coordinate with", "delivery schedule", "purchase", "logistics", "ad-hoc duties"], "requirements": {"degrees": ["diploma", "degree"], "majors": [], "languages": ["english", "chinese"], "language_level": ["excellent"], "hard_skills": ["excel", "pivot table", "analytical skills", "dynamic", "rapid", "vlookup"], "soft_skills": ["organized", "analytical skills", "detail-oriented", "dynamic", "ad-hoc duties", "accurate"], "languages_combined": [{"language": "english", "language_level": ["excellent"]}, {"language": "chinese", "language_level": ["excellent"]}]}, "experience_required": {"duration": [], "field": []}}, {"job_id": "100003009043672", "location_code": "hk", "company": "Page Personnel", "job_title": "Order Administrator - Electronics Trading Company", "description": "LOCATION: TSUEN WAN\n\nJOB DUTY:\n\nSearching new suppliers for Electrical and Electronics products\nNegotiate price and terms with suppliers\nPreparing price comparisons for management review\nIssuing PO and arrange delivery schedule\nHandling logistics for goods delivery and product quality issues\nAssisting sales to prepare SI and DN\nPerform other ad hoc tasks as assigned /required by supervisor\n\nREQUIREMENTS:\n\nHigh Diploma or Certificate in Business, Logistics or related\n5 years working experience in Construction or Manufacturing Industry with good relationship with E&M suppliers in HK\nKnowledge in ERP like Multiable and stock keeping\nGood interpersonal skill and business mind\nGood command of Cantonese and English\nBasic + Incentive", "employment_types": ["Full Time", "Permanent"], "selling_points": ["Competitive package", "Flexible working hour", "Open to graduates"], "locations": ["Not Specified"], "categories": ["Sales, CS & Business Devpt", "Customer Service - Supervisor / Officer", "Merchandising & Purchasing", "Electronics", "Sales Administration"], "post_time": "2022-01-13T01:26:51Z", "salary": {"currency": null, "max": null, "min": null, "period": "monthly", "term": null}, "salary_visible": false, "title_keywords": ["administrator"], "responsibilities": ["quality", "ad hoc tasks", "delivery schedule", "good relationship", "logistics", "management review"], "requirements": {"degrees": ["high diploma", "certificate"], "majors": ["business"], "languages": ["cantonese", "english"], "language_level": ["good command"], "hard_skills": ["wan", "basic", "erp"], "soft_skills": ["interpersonal skill"], "languages_combined": [{"language": "cantonese", "language_level": ["good command"]}, {"language": "english", "language_level": ["good command"]}]}, "experience_required": {"duration": ["5 years"], "field": ["manufacturing industry", "construction"]}}, {"job_id": "100003009042981", "location_code": "hk", "company": "HongKong Suning.com Co., Limited", "job_title": "Buyer / Assistant Buyer", "description": "GENERAL MISSION\n\nHelps the Company to develop import from China, for Small Domestic Appliances product line she/he\u2019s in charge.\nDirect reporting to the Department manager.\n\nRESPONSIBILITIES\n\n\u00a0Coaching:\n\n\nAnimate his/her team, 1 Assistant Merchandiser.\nWeekly business unit meeting with all business unit including quality and logistic department.\nContribution as a trainer: transfer of know-how to the Assistant Merchandiser.\n\n\u00a0Sourcing:\n\nIdentify the competitive resource area for his product line.\nPropose and anticipate the new sourcing areas and production zones to her/his direct manager.\nBe creative and use new ways to source.\nSource most reliable and performing suppliers according to the quality requirements and policies of the Company.\nValidate suppliers data base.\nBe aware of the industry/product development tendency inside China.\nBe aware of the changes of client needs in customer market.\nAnswer the sourcing requirement of customer and actively provide new products sourcing in China.\nCollect information about our competitors\u2019 activity during frequent factory visits and propose opportunities and counter offers to our partners.\n\u00a0Product development:\n\nWork closely with the Product Manager in head quarter to support whenever necessary the relation with vendors.\u00a0\n\nShare, participate and bring his support on commercial side the following product development activities:\n\nEvaluate the potential manufacturers for new development.\nConcept, planning, design and execution stages of new products.\nProvides his opinion on the design options.\nEvaluate potential design feasibility with Product Development Engineer.\nInteract with cost-effectiveness.\nReview product documentation for accuracy including documentation intended for customers use.\nEvaluate product non-conformances and recommend design modifications.\n\u00a0Offering:\u00a0\n\nDevelop excellent relationships with our partners in order to collect all the products needs and market information.\nPrepare/validate product information and offer customer product datasheet.\nContinuously improving his knowledge of product and quality norms at customer market.\u00a0\nNegotiation:\u00a0\nNegotiate the order elements, such as supplier, price, PCB, quantity, delivery etc., before order placement.\nRespect and reinforce the ethical rules of the company with the suppliers.\n\u00a0Coordination:\n\nWork together with his team for her/his product line with consistent thinking and actions to achieve common goals.\nCoordinate between supplier and customer to achieve best solution for all.\nCoordinate with other departments for relevant issues such as delivery, payment, quality to smooth the daily operation concerning his product line.\nInvolve Quality team and R&D team in all the steps of the process: selection of the suppliers and anticipation of the product compliance.\nKeep Quality Dpt. and engineers informed about any changes of Product requested by the customers before ordering.\nAll the activities should be on the basis of the Company ethic rules.\n\n\u00a0PERFORMANCE APPRAISAL\n\nAnnual turnover evolution global and per destination market.\nAnnual supplier payment credit evolution.\nNumber of days in trip for sourcing.\nRatio of new supplier ordered compared with new supplier sourced.\nCustomer satisfaction rate (on-time delivery rate, answer on customers\u2019 needs with orders\u2026).\nOn-time ratio of order delivery.\nREQUIREMENTS\nCollege degree or above.\nExperience in relevant area and knowledge for export business for at least 10 years.\nExcellent skills of communication, market analyzing, sourcing and negotiation.\nWide range of product channel & sensitive taste of potential products.\nHigh commercial sense to realize market needs.\nHigh coordination ability with customers and suppliers.\nHigh sense of ethics and integrity, dynamic and honest, dedicated, systematic and initiative.\nWilling to undertake the pressure and frequent travel around.\nFluent Mandarin in spoken and English both in spoken & written.", "employment_types": ["Full Time"], "selling_points": ["Develop and manage buying and selling plan", "Follow up and issue purchase orders", "Immediately available is preferred"], "locations": ["Kwun Tong"], "categories": ["Merchandising & Purchasing", "Electronics", "Others"], "post_time": "2022-01-12T09:24:23Z", "salary": {"currency": null, "max": null, "min": null, "period": "monthly", "term": null}, "salary_visible": false, "title_keywords": ["assistant"], "responsibilities": ["cost", "market information", "data", "policies", "review", "quality", "coordinate with", "design", "develop", "evaluate", "coordinate", "payment", "daily operation", "compliance", "coordination", "documentation", "planning"], "requirements": {"degrees": ["degree or above"], "majors": [], "languages": ["english", "mandarin"], "language_level": ["fluent"], "hard_skills": ["dynamic"], "soft_skills": ["negotiation", "integrity", "systematic", "communication", "dynamic", "coordination", "sensitive", "honest", "initiative"], "languages_combined": [{"language": "english", "language_level": []}, {"language": "mandarin", "language_level": ["fluent"]}]}, "experience_required": {"duration": ["at least 10 years"], "field": ["business"]}}, {"job_id": "100003009038775", "location_code": "hk", "company": "Schneider Consumer Asia Limited", "job_title": "SENIOR MERCHANDISER / SMALL DOMESTIC APPLIANCES", "description": "CHINA MOBILE HONG KONG COMPANY LIMITED (\"CMHK\") is the wholly-owned subsidiary of China Mobile Limited (HKEx: 941) (NYSE: CHL), which ranks 65th on the Fortune Global 500.\n\nOur company strives to offer superior service experience and to become the preferable digital partner for customers. We are preserving an environment with trust, responsibility and caring. At CMHK, we commit to maximizing people\u2019s potential and paving the way toward success for every striver. We are now inviting high caliber professional to join us.\n\nDepartment: Procurement\n\nIn this position, you will:\n\nOversee and supervise procurement activities across different categories of Network Procurement\nHandle tender and ensure procurement activities are conducted in compliance with company standard\nHandle ad-hoc projects on procurement process and systems enhancement\nCollaborate with cross-functional teams, rationalize procurement needs and provide effective sourcing and purchasing support\nMonitor market situation and maintain relationship with major vendors\nIdentify cost saving opportunities and conduct vendor performance evaluation on a continued basis\nFormulate and update policy and work procedures of Procurement\nContribute to the on-going improvement of the procurement function\n\nTo be successful in this position, you should meet the following requirements:\n\nUniversity graduate on Procurement or Engineering\u00a0\nMinimum 8 years of procurement experience, with at least 5 years\u2019 experience on a managerial grade\nExcellent analytical ability and project management skills\nGood Communication, interpersonal and negotiation skill\nStrong supervisory and coaching skills\n\nCandidates with less experience will be considered as \"Procurement Officer\"\u00a0\n\n\u00a0When you work:\n\n5 days work\n8 hours/day\n\n\u00a0What you enjoy:\n\nDouble pay\nDiscretionary bonus\nPerformance bonus\nLife insurance\nMedical insurance\nMeal allowance\nEducation subsidies\nTransportation allowance\nBirthday gift\nMarriage leave\nBirthday leave\nStaff discount\n\nCMHK is committed to be an equal opportunity employer. We offer exceptional benefits package and the opportunity to work in a challenging environment. Personal data provided by applicants will be treated strictly in accordance with our personal data policy and for recruitment purposes only.\n\nPlease submit your application to us by clicking the APPLY NOW button and send your full resume with your availability, current and expected salary to us.", "employment_types": ["Full Time"], "selling_points": ["College degree or above.", "Experience in relevant and knowledge for 10 Years", "High commercial sense to realize market needs."], "locations": ["Causeway Bay"], "categories": ["Merchandising & Purchasing", "Electronics"], "post_time": "2022-01-11T07:47:11Z", "salary": {"currency": null, "max": null, "min": null, "period": "monthly", "term": null}, "salary_visible": false, "title_keywords": ["senior merchandiser"], "responsibilities": ["collaborate with", "cost", "compliance", "systems", "monitor", "procedures", "communication", "project management", "maintain", "tender", "evaluation", "ad-hoc projects", "insurance", "cross-functional teams"], "requirements": {"degrees": ["university graduate"], "majors": ["engineering"], "languages": [], "language_level": [], "hard_skills": ["mobile", "project management", "vendor"], "soft_skills": ["project management skills", "communication", "committed", "negotiation skill", "interpersonal", "superior"], "languages_combined": []}, "experience_required": {"duration": ["minimum 8 years", "at least 5 years"], "field": ["digital", "procurement", "managerial"]}}, {"job_id": "100003009037058", "location_code": "hk", "company": "China Mobile Hong Kong \u4e2d\u570b\u79fb\u52d5\u9999\u6e2f", "job_title": "Procurement Manager", "description": "Role Purpose:\n\nOur Senior Merchandiser is responsible for leading a team to implement potential sourcing projects, in co-operation with our sales divisions in worldwide.\n\nWhat you\u2019ll be handling:\n\nIn-charge of assortment management and product range development\nResponsible for sourcing, product development, price negotiation and order fulfilment of selected product range\nWork closely with internal teams and external suppliers to ensure product quality, costing, production and delivery issues\nActively communicate with customers to understand their needs and expectations\nAnalyze market and import share data to keep track with business trends\nAdvise buyers and suppliers on product requirements, market trends and related economic and social issues\nPrepare and lead buying and sourcing trips\nSupervise, train and engage the team to carry out daily operations\nTalent that we are looking for:\n\nStrong negotiation skills and problem-solving skills\nInnovative, proactive and result-oriented\nOpen-minded, highly flexible and capable to manage complex business content\nSolid leadership experience with ability to bring about change\nEnergetic to drive for customer success and excellent service\nStrong sense of ownership and high degree of independence\nPassionate in connecting with people and adopting high level of interpersonal skills\nWilling to travel\nExperience, knowledge and skills required:\n\nDegree holder in Business Administration / Supply Chain Management / International Business or equivalent discipline\nAt least 5 years\u2019 related work experience in procurement, sourcing and assortment building with focus on European Market\nStrong product knowledge in Commercial or Domestics Appliances\nExperience in sizeable multi-national buying office and manufacturing company will be a definite advantage\nProficient in both spoken and written English and Mandarin\nProficient in MS Office (Excel / Word / PowerPoint / Outlook) applications\nYou can enjoy:\nDiverse and Inclusive work environment\nFlexi Office Space with flexible working hours and home office option\n5-day work week, 13th month salary & performance bonus\nProfessional training and career advancement opportunities\nTraining Sponsorship for personal professional development\n\n\nJoin us and apply now!\n\n\nPlease send your full resume with available date, present and expected salary to us.\u00a0\nResume and personal data collected will be kept strictly confidential and used for recruitment purpose only.", "employment_types": ["Full Time", "Permanent"], "selling_points": ["Network Procurement", "Rationalize procurement needs", "Minimum 8 years\u2019 relevant experience"], "locations": ["Kwai Hing"], "categories": ["Transportation & Logistics", "Fulfillment", "Merchandising & Purchasing", "Electronics", "Procurement / Purchasing / Sourcing"], "post_time": "2022-01-11T01:34:06Z", "salary": {"currency": null, "max": null, "min": null, "period": null, "term": null}, "salary_visible": false, "title_keywords": ["manager"], "responsibilities": ["communicate with", "management", "price negotiation", "delivery issues", "data", "quality", "teams", "daily operations", "recruitment", "personal data", "administration"], "requirements": {"degrees": ["degree", "degree holder"], "majors": ["international business", "business administration"], "languages": ["english", "mandarin"], "language_level": ["proficient"], "hard_skills": ["excel", "word", "powerpoint", "outlook", "problem-solving skills", "focus", "ms office"], "soft_skills": ["flexible", "passionate", "proactive", "negotiation", "responsible", "capable", "open-minded", "diverse", "negotiation skills", "energetic", "interpersonal skills", "problem-solving skills", "focus", "innovative", "leadership", "result-oriented"], "languages_combined": [{"language": "english", "language_level": ["proficient"]}, {"language": "mandarin", "language_level": ["proficient"]}]}, "experience_required": {"duration": ["at least 5 years"], "field": ["related", "manufacturing", "procurement"]}}, {"job_id": "100003009037318", "location_code": "hk", "company": "METRO Sourcing International Limited", "job_title": "Senior Merchandiser (Electrical / Gastro Appliances)", "description": "We are seeking a Product Developer / Designer to work out their Hong Kong office, ideally with prior experience in LED lighting and/or contemporary furniture, with a passion for innovative use of technology as well as executing financially orientated solutions within the rapidly growing lighting industry.\n\nResponsibilities & Skills\n\nCandidates should have a good understanding of how products are manufactured and assembled, ideally within the lighting and/or furniture industry. They should also have a grasp of three dimensional modelling software, ideally using Solidworks competently. Understanding of how a product can be developed into components which are optimized for mass production, producing technical drawings and liasing with suppliers to turn these into a commercial offering.\n\nIdeally a degree or relevant experience for at least 1-2 years in Product Design, with at least 1-2 years\u2019 experience already working in furniture and/or OEM lighting design and development.\u00a0 For applicants with less experience, we shall consider as a Junior Product Developer / Junior Designer.\u00a0\n\nClosely communicate with all parties, including the original designers, factory engineers, packaging suppliers, testing house engineers as well as our European buyers and development office in London.\n\nIntermediate knowledge of Adobe Photoshop and Illustrator is also a must for helping to produce artwork for instruction booklets and packaging when required.\n\nWilling and able to travel to Mainland China, and have a firm grasp of both verbal and written Chinese and English. Prior experience in merchandising and buying is a bonus and ideal candidates would benefit from having this prior knowledge, handling orders with buyers in Europe and vendors in mainland China.\n\nPersonality\n\nYou are hardworking, clear, concise when communicating to colleagues and are organized when handling the multiple tasks at hand. You are keen to utilize your design and development skill set to generate commercially competitive products within the lighting industry. You have prior knowledge and genuine interest in the contemporary Lighting design world and are looking to expand on this.\n\nApplication\n\nRelevant candidates will be interviewed continuously.\n\nSee www.hay.dk / www.andtradition.com for further details about who we are and what we do.", "employment_types": ["Full Time", "Permanent"], "selling_points": ["Solid exp in EU mkt & Electrical Appliance", "Resp. for global sourcing & product development", "MNC, 5-day work, insurance, double pay, bonus"], "locations": ["Kowloon Bay"], "categories": ["Merchandising & Purchasing", "Electronics", "Home Appliances"], "post_time": "2022-01-11T16:01:39Z", "salary": {"currency": null, "max": null, "min": null, "period": "monthly", "term": null}, "salary_visible": false, "title_keywords": ["senior merchandiser"], "responsibilities": ["communicate with", "software", "merchandising", "design", "testing", "product design", "executing", "technical drawings", "booklets"], "requirements": {"degrees": ["degree"], "majors": ["design"], "languages": ["english", "chinese"], "language_level": [], "hard_skills": ["adobe photoshop", "solidworks", "illustrator"], "soft_skills": ["organized", "passion for", "multiple tasks", "keen", "genuine", "clear", "innovative", "hardworking", "ideal"], "languages_combined": [{"language": "english", "language_level": []}, {"language": "chinese", "language_level": []}]}, "experience_required": {"duration": ["at least 1-2 years"], "field": ["designer", "development", "merchandising", "design", "product design", "relevant experience", "developer"]}}, {"job_id": "100003009039115", "location_code": "hk", "company": "Nine United China Limited", "job_title": "Product Developer / Designer (Lighting) / Hong Kong", "description": "Responsibility\n\nResponsible for garment manufacturing & merchandising\nOrder follow up with both factory & customers is required\nHandle ad hoc tasks when required\nRequirement\n\nForm 5 graduate or above\nMinimum 3-year experience about garment manufacturing & merchandising\nExperience in handling OEM projects is preferable\nMinimum 2 years merchandising or trading experience in one of the below areas:\nSundries\nDecoration\nsouvenirs\nDIY Items / Toys\nIP products\nElectronic items / Lighting\nSporting items\nPaper & gift items\nWell organized, hardworking, self-motivated, energetic, and able to work under pressure\nPC knowledge of Excel, Word, and Chinese word processing\nFluent in spoken and written Cantonese, English and Mandarin", "employment_types": ["Full Time"], "selling_points": [], "locations": ["Tsim Sha Tsui"], "categories": ["Design", "Graphics", "Merchandising & Purchasing", "Electronics"], "post_time": "2022-01-11T08:44:21Z", "salary": {"currency": null, "max": null, "min": null, "period": "monthly", "term": null}, "salary_visible": false, "title_keywords": ["product developer", "designer"], "responsibilities": ["ad hoc tasks", "merchandising"], "requirements": {"degrees": ["form 5"], "majors": [], "languages": ["cantonese", "english", "chinese", "mandarin"], "language_level": ["fluent"], "hard_skills": ["excel", "chinese word processing", "word", "ip", "pc knowledge"], "soft_skills": ["self-motivated", "well organized", "energetic", "hardworking", "work under pressure"], "languages_combined": [{"language": "cantonese", "language_level": ["fluent"]}, {"language": "english", "language_level": ["fluent"]}, {"language": "chinese", "language_level": []}, {"language": "mandarin", "language_level": ["fluent"]}]}, "experience_required": {"duration": ["minimum 3-year", "minimum 2 years"], "field": ["garment", "manufacturing", "merchandising", "trading"]}}, {"job_id": "100003009044438", "location_code": "hk", "company": "\u59ff\u66fc\u570b\u969b\u6709\u9650\u516c\u53f8", "job_title": "Assistant Merchandiser/ Merchandiser", "description": "Specific responsibilities:\n\n\nResponsible for customer order processing\nHandle and follow-up customer's product enquires and complaints\nRoutine liaise with China factory and European sales office\nReview and update customer quotation\nCoordinate with our China factory, Taiwan R&D consultants and European office for project activities\nAssist Purchasing Dept. to source semi-conductors for production\nArrange and prepare the promotion materials including exhibition, magazines and online website\n\nQualifications:\n\n\nF.5 / HKDSE or above\n2 years working experience, electronics related background is an advantage\nHave the CAN-DO attitude and excellent communication & presentation skill\nEager to learn and be a good team player\nGood command of Cantonese, English and Mandarin\u00a0\nOccasionally travel and stay in our China factory (Dongguan)\n\n\u00a0Benefits:\n\n5-day work week and bonus\n12 days annual leave\nBank holiday\nMedical & life insurance", "employment_types": ["Full Time", "Permanent"], "selling_points": ["3-year experience about manufacturing & merchandis", "Follow-up on sales & production arrangement", "Experience in handling OEM projects is preferable"], "locations": ["Mong Kok"], "categories": ["Merchandising & Purchasing", "Electronics", "Woven / Knit", "Sundries"], "post_time": "2022-01-13T04:04:28Z", "salary": {"currency": null, "max": null, "min": null, "period": "monthly", "term": null}, "salary_visible": false, "title_keywords": ["merchandiser", "assistant merchandiser"], "responsibilities": ["quotation", "review", "coordinate with", "website", "communication", "order processing", "liaise with"], "requirements": {"degrees": ["hkdse"], "majors": [], "languages": ["cantonese", "english", "mandarin"], "language_level": ["good command"], "hard_skills": ["r&d", "presentation skill", "order processing"], "soft_skills": ["presentation skill", "good team player", "responsible", "can-do attitude", "communication", "eager to learn"], "languages_combined": [{"language": "cantonese", "language_level": ["good command"]}, {"language": "english", "language_level": ["good command"]}, {"language": "mandarin", "language_level": ["good command"]}]}, "experience_required": {"duration": ["2 years"], "field": ["related"]}}, {"job_id": "100003009040164", "location_code": "hk", "company": "Mainland Energy Conversion Ltd.", "job_title": "Customer service assistant", "description": "The Cookware Company is a global company with a high expertise in innovative cookware. Our organization is vertically integrated, allowing us to manage both the production and distribution of our products. We have sales offices in Europe, the United States and Asia as well as state-of-the-art production facilities in Korea, China and Europe. We have high quality standards (e.g. ISO-certificates) and work hard to reduce our environmental impact.\n\nThe Cookware Company has always been a pioneer in healthy ceramic non-stick cookware. Over the years we have extended our scope in order to offer smart cookware solutions for everyone. Innovation, flexibility, creativity and social responsibility are our main focus. However, our most important asset are our people. They\u2019re the heart of our company.\n\nReporting to the Senior Category Manager, you will be responsible for the sourcing of product assortment for the Global organization, especially focused on the US market and the European loyalty market.\n\nResponsibilities Include:\n\nDeveloping sourcing strategies\nIdentifying and evaluating vendors\nCreating sourcing agreements for new vendors\nSourcing samples and products\nEstablishing and maintaining quality standards in line with company direction\nAchievement of optimum results in product quality, on time delivery and vendor management.\nBuilding and maintaining business relationships with new product development, and sales teams in the group to promote products and identify gaps and issues throughout the process and create solutions for those gaps.\n\nYou will maintain regular and clear communications with all related functional areas (Vendors, Product Development, Sales).\n\n\n\nPROFILE\n\nA minimum of 5-10 years of solid experience in the field kitchenware such as cookware, kitchen knives, utensils\u00a0preferably in a merchandising role from a multinational company background.\nExpert knowledge in sourcing, procurement and market analysis skills\nExtensive knowledge in product development and production processes and ideally an understanding of materials and engineering terms.\nA wide network of vendor partnerships and had a proven track record of sourcing for a sizable cookware/ kitchenware brand\nUS and European (especially loyalty program) market experience is highly sought after\nA self-motivated team player, you will possess excellent negotiation and communication skills together with the ability to manage complexity and meet tight deadlines\nHigh level of organization, attention to detail, ability to manage multiple products at one time.\nMature and passionate about work and to be able to work independently\nStrong commercial sense is required while fluency in Chinese and English is required\nFrequent travel to factories in China is required\nAbility to address multiple time zones (China, Europe, US)\nImmediately available is preferred", "employment_types": ["Full Time"], "selling_points": [], "locations": ["Kwai Fong"], "categories": ["Sales, CS & Business Devpt", "Customer Service - Supervisor / Officer", "Marketing / Public Relations", "Marketing - Marketing Communication", "Merchandising & Purchasing", "Electronics"], "post_time": "2022-01-12T01:41:07Z", "salary": {"currency": null, "max": null, "min": null, "period": "monthly", "term": null}, "salary_visible": false, "title_keywords": ["customer service assistant"], "responsibilities": ["reporting", "management", "communications with", "maintaining", "quality", "developing", "teams", "merchandising", "communication", "maintain", "market analysis", "promote products"], "requirements": {"degrees": [], "majors": [], "languages": ["english", "chinese"], "language_level": ["fluency"], "hard_skills": ["focus", "analysis", "vendor"], "soft_skills": ["communication skills", "self-motivated", "meet tight deadlines", "work independently", "negotiation", "focused", "responsible", "mature", "clear", "team player", "attention to detail", "focus", "innovative", "extensive", "passionate about"], "languages_combined": [{"language": "english", "language_level": ["fluency"]}, {"language": "chinese", "language_level": ["fluency"]}]}, "experience_required": {"duration": ["minimum of 5-10 years"], "field": ["merchandising", "multinational company"]}}, {"job_id": "100003009033855", "location_code": "hk", "company": "The Cookware Company Global Sourcing Limited", "job_title": "Sourcing Specialist (Cookware)", "description": "Job Duties\n\nManage and maintain current inventory\nCreate effective strategies to manage variety of product categories\nReview and analysis inventory flow, predict and forecast future inventory need\nMeasure customer forecast accuracy\nCollaborate with factory to set priority of item production\nMaintain ERP order status, review and release new order to factories\nCollaborate with vendor to ensure delivery schedule on time and on demand\nCollaborate with QA team to ensure product quality in IQC\nSupport sales team to manage product shipping schedules\nRecommend and implement process improvement\nSupport new ERP system implementation\nOther Ad-hoc duties as assigned by senior staff or management.\u00a0\nRequirement\n\nDiploma or above\nAt least 2 years relevant working experience\nFresh graduates also welcomed to apply for a junior position\nPossess strong interpersonal communication skills\nStrong interests in data analysis, predictive analysis\nProactive collaboration within multi-culture team-work environment\nGood language skill in English and Chinese (including Mandarin)\nStrong computer skill, proficient in MS Excel, MSWord, ERP system\nWe are an equal opportunity employer, offers 5-day work, double Pay, 2 bonus per Year, 14 to 22 days annual leave, training opportunity, medical and life insurance. Interested applicants please submit a full resume indicating current and expected salary with earliest availability.", "employment_types": ["Permanent"], "selling_points": ["Dynamic MNC environment", "Rapid growing company", "Regional Exposure"], "locations": ["Kowloon Bay"], "categories": ["Merchandising & Purchasing", "Electronics", "Home Appliances", "Procurement / Purchasing / Sourcing"], "post_time": "2022-01-10T01:57:05Z", "salary": {"currency": null, "max": null, "min": null, "period": "monthly", "term": null}, "salary_visible": false, "title_keywords": ["specialist"], "responsibilities": ["product categories", "collaborate with", "management", "shipping", "schedules", "inventory", "review", "analysis", "quality", "implementation", "delivery schedule", "maintain", "sales team", "forecast", "ad-hoc duties"], "requirements": {"degrees": ["diploma or above"], "majors": [], "languages": ["english", "chinese", "mandarin"], "language_level": ["good"], "hard_skills": ["analysis", "erp system", "ms excel", "computer skill", "msword"], "soft_skills": ["communication skills", "proactive", "interpersonal"], "languages_combined": [{"language": "english", "language_level": ["good"]}, {"language": "chinese", "language_level": ["good"]}, {"language": "mandarin", "language_level": ["good"]}]}, "experience_required": {"duration": ["at least 2 years"], "field": ["relevant working experience"]}}, {"job_id": "100003009037391", "location_code": "hk", "company": "Senko Advanced Components (HK) Ltd", "job_title": "Inventory Planner", "description": "Job Responsibilities:\n\n-\u00a0\u00a0\u00a0\u00a0\u00a0\u00a0 Issuing Purchase orders, liaise with suppliers & monitoring purchase & production planning,\n\n-\u00a0\u00a0\u00a0\u00a0\u00a0\u00a0 Communicate with Suppliers, warehouse & internal departments for shipment & delivery arrangement\n\n-\u00a0\u00a0\u00a0\u00a0\u00a0\u00a0 To support Management & Internal departments for Price, delivery, quality issues with Suppliers\n\nRequirements:\n\n-\u00a0\u00a0\u00a0\u00a0\u00a0\u00a0 F.5 / DSE or above\n\n-\u00a0\u00a0\u00a0\u00a0\u00a0\u00a0 Good command of Mandarin for communicate with China Factory is a must\n\n-\u00a0\u00a0\u00a0\u00a0\u00a0\u00a0 PC proficiency in Word & Excel\n\n-\u00a0\u00a0\u00a0\u00a0\u00a0\u00a0 Knowledge on Microsoft AX system would be an added advantage\n\n-\u00a0\u00a0\u00a0\u00a0\u00a0\u00a0 Immediate available is highly preferred\n\n-\u00a0\u00a0\u00a0\u00a0\u00a0\u00a0 At least 1 year relevant working experience in shipping/operations/purchasing/documentation is an advantage\n\n-\u00a0\u00a0\u00a0\u00a0\u00a0\u00a0 Experience in Electronics industry is an added advantage\n\n-\u00a0\u00a0\u00a0\u00a0\u00a0\u00a0 Good command in English for mail and simple documentation\n\n-\u00a0\u00a0\u00a0\u00a0\u00a0\u00a0 Self-motivated and being a good team-player\n\n-\u00a0\u00a0\u00a0\u00a0\u00a0\u00a0 Good interpersonal and communication skills", "employment_types": ["Full Time", "Permanent"], "selling_points": ["Stable Business", "Work with people who are friendly and supportive", "Attractive package and benefits"], "locations": ["Kwun Tong"], "categories": ["Merchandising & Purchasing", "Electronics", "Others", "Procurement / Purchasing / Sourcing"], "post_time": "2022-01-11T02:42:00Z", "salary": {"currency": null, "max": null, "min": null, "period": "monthly", "term": null}, "salary_visible": false, "title_keywords": [], "responsibilities": ["communicate with", "management", "monitoring", "production planning", "quality", "purchase", "liaise with suppliers"], "requirements": {"degrees": ["dse"], "majors": [], "languages": ["english", "mandarin"], "language_level": ["good command"], "hard_skills": ["simple", "excel", "word", "documentation", "pc"], "soft_skills": ["team-player", "communication skills", "self-motivated", "interpersonal"], "languages_combined": [{"language": "english", "language_level": ["good command"]}, {"language": "mandarin", "language_level": ["good command"]}]}, "experience_required": {"duration": ["at least 1 year"], "field": ["purchasing", "relevant working experience"]}}, {"job_id": "100003009038810", "location_code": "hk", "company": "Aline Company Limited", "job_title": "Purchasing Executive (5 days, Cherung Sha Wan area)", "description": "Marketing Executive (devices/ gadgets buying)\n\nYour role\n\nResponsible for mobile handsets, accessories or gadgets sourcing and explore potential brands or product with market\u00a0trend analysis\nExplore potential brands or products with market trend analysis\nDevelop and manage good relationships with vendors to optimize business opportunities\nCoordinate and follow up with supplier, negotiating price, orders and logistics activities\nMonitor and analyze daily sales performance so as to prepare replenishment and allocation plan for sales channels to maintain optimal stock level\nupdated and gather latest market and sales trends and proactively source new products\nPlan and develop marketing and promotional strategies of new products\nPrepare regular reports and analyze for monitoring the effectiveness of the product & pricing strategies and daily stock management\nAssist in other ad hoc projects as assigned\n\nTo succeed in this role\n\nDegree holder in Business Administration, Marketing, Supply Chain & Logistics or other related disciplines\n3 years of relevant working experience in Marketing, Channel Management/ Sourcing, Business Operations, with work experience in mobile related industries would be an advantage\nGood command in both written and spoken English and Chinese\nProficient in using MS Office applications (including Word, Excel, Access & PowerPoint)\nProactive, flexible, good analytical thinking and with ability in handling multi-task\nKnowledge of marketing planning and program is preferable\n\nHKT is an equal opportunity employer and welcomes applications from all qualified candidates. Information provided will be treated in strict confidence and will only be used for recruitment-related purposes.\nPersonal data provided by job applicants will be used strictly in accordance with the employer's privacy statement (www.hkt.com/privacy-statement), a copy of which will be provided immediately upon request.", "employment_types": ["Temporary", "Contract"], "selling_points": ["Good Mandarin & immediate available", "1 year in shipping or purchasing work experience", "5days, Basically no OT, Medical insurance"], "locations": ["Sham Shui Po Area"], "categories": ["Others", "Junior Executive", "Merchandising & Purchasing", "Electronics"], "post_time": "2022-01-11T07:52:00Z", "salary": {"currency": null, "max": null, "min": null, "period": "monthly", "term": null}, "salary_visible": false, "title_keywords": ["purchasing executive"], "responsibilities": ["operations", "maintain", "plan", "personal data", "administration", "sales performance", "monitor", "develop", "logistics", "reports", "management", "stock management", "business opportunities", "monitoring", "analysis", "replenishment", "coordinate", "ad hoc projects", "recruitment", "planning"], "requirements": {"degrees": ["degree holder"], "majors": ["related disciplines", "marketing", "business administration"], "languages": ["english", "chinese"], "language_level": ["good command"], "hard_skills": ["excel", "analysis", "word", "powerpoint", "mobile", "ms office"], "soft_skills": ["flexible", "confidence", "multi-task", "responsible", "proactive"], "languages_combined": [{"language": "english", "language_level": ["good command"]}, {"language": "chinese", "language_level": ["good command"]}]}, "experience_required": {"duration": ["3 years"], "field": ["related", "relevant working experience", "channel management", "business", "marketing"]}}, {"job_id": "100003009039926", "location_code": "hk", "company": "csl.", "job_title": "Marketing Executive (devices/ gadgets buying)", "description": "Role Purpose:\nOur Junior Merchandiser / Merchandiser Assistant are responsible for everyday end to end merchandising activities and support in the global sourcing and chain supply projects.\nWhat you will be handling:\nResponsible for order follow-up, buying trips preparation, sample handling and showroom management\nEngage in merchandising process such as sourcing, product development, article & offer management and supplier management\nWork directly with overseas suppliers and customers to ensure smooth operations\nCoordinate with internal departments e.g. Packaging, Quality Assurance, Logistics and other external service providers to ensure on-time shipment\nMaintain accurate and updated order status and product information in supply chain system\nTalent that we are looking for:\nExperience and knowledge\u00a0in merchandising / trading industry\nGood negotiation skills and problem-solving skills\nOpen minded, right attitude to learn and bring about change\nEnergetic to drive for customer success and excellent service\nStrong sense of ownership and high degree of independence\nPassionate in connecting with people and adopting high level of interpersonal skills\nWilling to travel when needed\nExperience, knowledge and skills required:\nDegree holder in\u00a0Business Administration / Supply Chain Management / International Business or equivalent discipline\nAt least 2 years\u2019 relevant merchandising experience, EU market experience is preferred\nProficient in both spoken and written English and Mandarin\nProficient in MS Office (Excel / Word / PowerPoint / Outlook) applications\nCandidate with less experience will be considered as\u00a0Merchandiser Assistant\nFresh graduates are also welcome\nYou can enjoy:\nDiverse and Inclusive work environment\nFlexi Office Space with flexible working hours and home office option\n5-day work week, 13th month salary & performance bonus\nProfessional training and career advancement opportunities\nTraining Sponsorship for personal professional development\n\n\nJoin us\u00a0and\u00a0apply\u00a0now!\n\n\nPlease send your full resume with available date, present and expected salary to us.\nResume and personal data collected will be kept strictly confidential and used for recruitment purpose only.", "employment_types": ["Full Time"], "selling_points": ["Mobile handsets, accessories or gadgets sourcing", "Explore potential brands or products", "Develop and manage good relationships with vendors"], "locations": ["Quarry Bay"], "categories": ["Marketing / Public Relations", "Marketing - General / Support", "Merchandising & Purchasing", "Electronics", "Home Appliances"], "post_time": "2022-01-11T15:31:12Z", "salary": {"currency": null, "max": null, "min": null, "period": "monthly", "term": null}, "salary_visible": false, "title_keywords": ["marketing executive"], "responsibilities": ["management", "quality", "merchandising", "coordinate with", "maintain", "logistics", "ensure smooth operations", "recruitment", "personal data", "administration"], "requirements": {"degrees": ["degree", "degree holder"], "majors": ["international business", "business administration"], "languages": ["english", "mandarin"], "language_level": ["proficient"], "hard_skills": ["excel", "word", "powerpoint", "outlook", "problem-solving skills", "ms office"], "soft_skills": ["passionate", "flexible", "responsible", "diverse", "negotiation skills", "energetic", "interpersonal skills", "open minded", "smooth", "problem-solving skills", "accurate"], "languages_combined": [{"language": "english", "language_level": ["proficient"]}, {"language": "mandarin", "language_level": ["proficient"]}]}, "experience_required": {"duration": ["at least 2 years"], "field": ["merchandising", "trading"]}}, {"job_id": "100003009029371", "location_code": "hk", "company": "A.S. Watson Retail (HK) Limited", "job_title": "Senior Buyer / Buyer, Electrical & Electronics - Personal Care Products", "description": "CHINA MOBILE HONG KONG COMPANY LIMITED (\"CMHK\") is the wholly-owned subsidiary of China Mobile Limited (HKEx: 941) (NYSE: CHL), which ranks 65th on the Fortune Global 500.\n\nOur company strives to offer superior service experience and to become the preferable digital partner for customers. We are preserving an environment with trust, responsibility and caring. At CMHK, we commit to maximizing people\u2019s potential and paving the way toward success for every striver. We are now inviting high caliber professional to join us.\n\nDepartment: Procurement\n\nIn this position, you will:\n\nAssist in procurement activities including preparation of tender documents, tender evaluation, issue purchase orders and review contract documents in accordance with established policies and procedures\nWork with user departments to analyze and identify business needs and support development of best fit procurement and contracting strategies\nPrepare procurement related report analysis\nMonitor and evaluate vendor performance and internal customer satisfaction\n\nTo be successful in this position, you should meet the following requirements:\n\nDegree holder in Engineering, IT, Procurement or related discipline\u00a0\n0-1 years\u2019 relevant experience\nProficient in MS Office application\nExcellent communication, interpersonal and negotiation skills, with proactive attitude\nGood command in English and Putonghua\n\n\u00a0When you work:\n\n5 days work\n8 hours/day\n\nCMHK is committed to be an equal opportunity employer. We offer exceptional benefits package and the opportunity to work in a challenging environment. Personal data provided by applicants will be treated strictly in accordance with our personal data policy and for recruitment purposes only.\n\nPlease submit your application to us by clicking the APPLY NOW button and send your full resume with your availability, current and expected salary to us.", "employment_types": ["Full Time", "Permanent"], "selling_points": ["Product Sourcing / Development", "Identify and select vendors", "Market trend analysis"], "locations": ["Shatin Area"], "categories": ["Merchandising & Purchasing", "Electronics", "Home Appliances", "Sundries"], "post_time": "2022-01-07T19:19:55Z", "salary": {"currency": null, "max": null, "min": null, "period": "monthly", "term": null}, "salary_visible": false, "title_keywords": ["personal"], "responsibilities": ["tender documents", "policies", "analysis", "review", "procedures", "monitor", "evaluate", "communication", "purchase", "contracting", "tender", "evaluation", "report"], "requirements": {"degrees": ["degree holder"], "majors": ["it", "engineering"], "languages": ["putonghua", "english"], "language_level": ["good command"], "hard_skills": ["mobile", "analysis", "vendor", "ms office"], "soft_skills": ["communication", "committed", "negotiation skills", "proactive", "interpersonal", "superior"], "languages_combined": [{"language": "putonghua", "language_level": ["good command"]}, {"language": "english", "language_level": ["good command"]}]}, "experience_required": {"duration": ["0-1 years"], "field": ["digital", "relevant experience"]}}, {"job_id": "100003009026085", "location_code": "hk", "company": "China Mobile Hong Kong \u4e2d\u570b\u79fb\u52d5\u9999\u6e2f", "job_title": "Procurement Assistant", "description": "The Sourcing Engineer will explore and develop advance technology to facilitate the new product development and sourcing related opportunities in the coming 12 months. This role will be acting as the interface between supplier and design engineering to determine new and alternative sourcing strategy.\n\n\n\nResponsibilities\n\nDrive supplier exploration & selection process to develop a supply base that provides competitive advantage in quality, value/cost, delivery and technology.\nWith particular focus on Electro-mechanical / Electronics, review supplier base and identify improvement opportunities.\nWork with development team on new product development to ensure the selection of components are fulfilling the required specifications and up to the market technology. Continuous update the development team with latest market and technology information\nInteract with R&D teams to ensure suppliers are involved in development and review of specifications to promote design advancement.\nUse technical skills and knowledge to investigate alternate component technologies for reduced cost or improved availability and implement changes.\nConduct supplier performance review in compliance with GPE\u2019s goals and objectives.\nRequirements\n\nBachelor degree in Electronics Engineering or equivalent\nAt least 3-year experience in sourcing electronics and electro-mechanical components\nEnergetic, aggressive and self-initiative\nAble to work under pressure and tight schedule\nGood communication & interpersonal skills\nGood command of English, Chinese and Mandarin\nHigh mobility and willing to take overseas assignment is preferable\nTravelling to Shenzhen R&D Centre & Huizhou Factory is required\nCompany Benefits\n\nBesides promising career development opportunities, we work 5 days a week and offer competitive remuneration package including double pay, medical benefit, flexible working hour and free shuttle bus.\n\nApplication\n\nPlease submit your application via\u00a0https://form.jotform.me/GPEHK/jobapplication\n\nFor more information, please visit our company website at\u00a0www.gp-industries.com\u00a0and\u00a0www.kef.com.\n\nWe are an equal opportunities employer. Personal data collected will be treated as strictly confidential and used for recruitment purpose only.%MCEPASTEBIN%\nDrive supplier exploration & selection process to develop a supply base that provides competitive advantage in quality, value/cost, delivery and technology.\nWith particular focus on Electro-mechanical / Electronics, review supplier base and identify improvement opportunities.\nWork with development team on new product development to ensure the selection of components are fulfilling the required specifications and up to the market technology. Continuous update the development team with latest market and technology information\nInteract with R&D teams to ensure suppliers are involved in development and review of specifications to promote design advancement.\nUse technical skills and knowledge to investigate alternate component technologies for reduced cost or improved availability and implement changes.\nConduct supplier performance review in compliance with GPE\u2019s goals and objectives.", "employment_types": ["Full Time", "Permanent"], "selling_points": ["Prepare tender evaluation & issue purchase orders", "Identify effective & reliable sourcing strategies", "0-1 years\u2019 relevant experience"], "locations": ["Kwai Hing"], "categories": ["Transportation & Logistics", "Fulfillment", "Merchandising & Purchasing", "Electronics", "Procurement / Purchasing / Sourcing"], "post_time": "2022-01-06T07:17:52Z", "salary": {"currency": null, "max": null, "min": null, "period": null, "term": null}, "salary_visible": false, "title_keywords": ["procurement assistant"], "responsibilities": ["cost", "review", "quality", "teams", "design", "develop", "compliance", "specifications"], "requirements": {"degrees": ["degree", "bachelor"], "majors": ["engineering"], "languages": ["english", "chinese", "mandarin"], "language_level": ["good command"], "hard_skills": ["r&d"], "soft_skills": ["communication", "self-initiative", "interpersonal skills", "energetic", "mobility", "work under pressure"], "languages_combined": [{"language": "english", "language_level": ["good command"]}, {"language": "chinese", "language_level": ["good command"]}, {"language": "mandarin", "language_level": ["good command"]}]}, "experience_required": {"duration": ["at least 3-year"], "field": []}}, {"job_id": "100003009025736", "location_code": "hk", "company": "GP Electronics (HK) Limited", "job_title": "Sourcing Engineer", "description": "Programme Highlights\n\nOrganized for over 10 years, the Graduate Trainee Program \u2013 3-year Executive Development Programme has nurtured a number of business & technical elites in the Group. As a leading company of professional audio products, we are now offering an excellent long-term career development to high-caliber graduates from different discipline to cope with our company development in the Greater Bay Area.\n\nBesides promising career development opportunities, you will be offered a comprehensive training, job rotation, project-based exposure and bi-annual review in this programme.\n\nResponsibilities\n\nContribute ideas in sourcing purchasing in technological environment\nLearn a full spectrum of purchasing and other key functional units, as well as to build working network and broaden your perspectives\nHave regular technical trainings\nCollaborate with different departments within company\nHandle any ad hoc projects required\nRequirements\nBachelor degree in Electronics/ Materials Engineering or equivalent\nBeing energetic,aggressive and self-initiative\nGood communication & interpersonal skills\nGood command of English, Chinese and Mandarin\nHigh mobility and willing to take overseas assignment is preferable\nFresh graduates are preferred\nTravelling to Shenzhen R&D Centre & Huizhou Factory is required\n\nCompany Benefits\n\nBesides promising career development opportunities, we work 5 days a week and offer competitive remuneration package including double pay, medical benefit, flexible working hour and free shuttle bus.\n\nApplication\n\nPlease submit your application via\u00a0https://form.jotform.me/GPEHK/job-application\n\nFor more information, please visit our company website at\u00a0www.gp-industries.com\u00a0and\u00a0www.kef.com.\n\nWe are an equal opportunities employer. Personal data collected will be treated as strictly confidential and used for recruitment purpose only.", "employment_types": ["Full Time", "Permanent"], "selling_points": ["electronics and electro mechanical components", "Advanced Sourcing & vendor sourcing", "OEM / ODM Manufacturing"], "locations": ["Not Specified"], "categories": ["Transportation & Logistics", "Supply Chain", "Merchandising & Purchasing", "Electronics", "Procurement / Purchasing / Sourcing"], "post_time": "2022-01-06T06:25:21Z", "salary": {"currency": null, "max": null, "min": null, "period": "monthly", "term": null}, "salary_visible": false, "title_keywords": ["engineer"], "responsibilities": ["collaborate with", "ad hoc projects", "ideas"], "requirements": {"degrees": ["degree", "bachelor"], "majors": ["engineering"], "languages": ["english", "chinese", "mandarin"], "language_level": ["good command"], "hard_skills": ["r&d"], "soft_skills": ["communication", "self-initiative", "interpersonal skills", "energetic", "mobility"], "languages_combined": [{"language": "english", "language_level": ["good command"]}, {"language": "chinese", "language_level": ["good command"]}, {"language": "mandarin", "language_level": ["good command"]}]}, "experience_required": {"duration": [], "field": []}}, {"job_id": "100003009025784", "location_code": "hk", "company": "GP Electronics (HK) Limited", "job_title": "Purchasing Executive", "description": "The Materials Buyer is the responsible for the purchasing of materials to support the production-schedule. He/she will manage suppliers to ensure on-time delivery, and supporting material/ product-level revisions, while managing inventory-levels to prevent shortages and maximum turns. Will work with cross-functional team (Eng, Ops, Finance, CS, GCM, etc) in support of operations-management. Will be part of a dynamic, multi-disciplinary team, by utilizing, monitoring & developing the supply-chain to meet internal & customer-requirements.\n\nYour tasks:\n\nResponsible for the purchasing of materials process from placing the purchase order to suppliers, following up the order status to delivering material to the site in order to support the production-schedule.\nPlace purchase-orders in a timely manner, as required by the forecast and production-schedules.\nFollow-up on outstanding purchase-orders, develop and internally communicate recovery-planning, to ensure timely resolution, communication and mitigation of future potential problems.\nExpedite & defer PO as required, based on backlog / inventory-changes.\nManage suppliers to improve quality, control inventories and ensure timely-flow of materials.\nSolve day-to-day quality/ scheduling issues with suppliers.\nManage and resolve issues regarding PO to invoice discrepancies, returns, ASN issue, inbound arrangement and quality-problems with suppliers.\nMonitor & report shortages and supplier-performance.\nParticipate in supplier-reviews, evaluation/ scorecards & corrective-actions.\nEffectively interact cross-functionality with Engineering, Production & Finance.\nPrepare & analyze reporting as needed.\nDevelop thorough working-knowledge of assigned commodities and associated supplier base.\nEnsure and promote compliance to company procurement policies and procedures.\n\nYour qualifications, experience & skills:\n\nDegree level and/or equivalent work-experience.\nMinimum 2 years in similar role, in a production environment.\nWorking-knowledge of ERP/ MRP systems, INFOR preferred.\nExpert applied knowledge of forecasting, MRP, transportation, supply-chain, bills of material, inventory-management and warehouse disciplines.\nExcellent communication & interpersonal skills, with an ability to effectively interact at various levels of the organization, with a logical and organized approach.\nAbility to work independently, display initiative and solve problems with proficiency.\nMust be \u2018hands-on\u2019 with strong analytical-skills and good problem-solving skills, with an attention to detail.\nStrong ERP/ MRP system knowledge and proficient with Excel.\nMust speak English at a business-level.\nWork location: Tsing Yi\n\nInterested? We are looking forward to receiving your online application including availability and salary expectations.\n\n(Please quote the job reference no. on the subject of your application.)\u00a0\n\n(All information collected will be used for recruitment purpose only.)\n\nTo know more about us, please visit\u00a0www.dbschenker.com/cn\n", "employment_types": ["Full Time", "Permanent"], "selling_points": ["Purchasing", "Fresh Graduate", "Graduate Program"], "locations": ["Not Specified"], "categories": ["Transportation & Logistics", "Supply Chain", "Merchandising & Purchasing", "Electronics", "Procurement / Purchasing / Sourcing"], "post_time": "2022-01-06T06:28:09Z", "salary": {"currency": null, "max": null, "min": null, "period": "monthly", "term": null}, "salary_visible": false, "title_keywords": ["purchasing executive"], "responsibilities": ["schedules", "operations", "inventory", "quality", "communication", "purchase", "procurement policies", "evaluation", "control", "compliance", "monitor", "developing", "develop", "resolution", "schedule", "forecast", "forecasting", "report", "reporting", "management", "invoice", "monitoring", "procedures", "scheduling", "systems", "a timely manner", "planning"], "requirements": {"degrees": ["degree"], "majors": [], "languages": ["english"], "language_level": [], "hard_skills": ["problem-solving skills", "excel", "dynamic", "erp"], "soft_skills": ["organized", "work independently", "responsible", "timely", "communication", "solve problems", "hands-on", "dynamic", "interpersonal skills", "thorough", "attention to detail", "problem-solving skills", "initiative"], "languages_combined": [{"language": "english", "language_level": []}]}, "experience_required": {"duration": [], "field": []}}, {"job_id": "100003009029698", "location_code": "hk", "company": "Schenker International (H.K.) Limited", "job_title": "Materials Buyer - Warehousing / Logistics (Ref No: JD/LOG/091/220107)", "description": "What You\u2019ll Be Doing\n\n\nReview and verify all data are complete on the Quote status in SWB in Oracle (AQLR)\nPreparation and data entry of complex customer quotes into Supplier\u2019s system including verification of customer contract pricing\nTo Analyze and prepare quote processes recommendations to sales field\nRecognize cross selling opportunities and inform field sales\n\n\u00a0What We Are Looking For\n\n\nHas developed specialized skills or is multi-skilled through job-related training and considerable on-the-job experience\nCompletes work under moderate supervision\nIdentifies key issues and patterns from partial/conflicting data\nDegree in Purchasing/Supply/Business Management or equivalent\n1-3 years\u2019 relevant working experience\nWell-organized, work independent, self-motivated with good interpersonal skills and good team player\nAbility to work on multiple projects and work under pressure\nGood command of both spoken and written English, Cantonese, and Mandarin\n\n\u00a0What\u2019s In It For You\n\nAt Arrow, we recognize that financial rewards and great benefits are important aspects of an ideal job. That\u2019s why we offer competitive financial compensation, including various compensation plans, and a solid benefits package.\n\nDouble Pay\nPerformance Bonus\nMedical & Dental\nMPF with additional employer contributions\nLife Insurance\nPaid Time Off\nFree Shuttle to HKSTP Office\n5-Day Work Week\nGrowth Opportunities\nAnd More!", "employment_types": ["Full Time", "Permanent"], "selling_points": ["Purchasing of materials to support the production", "Manage suppliers to ensure on-time delivery", "Manage inventory-levels to prevent shortages"], "locations": ["Tsing Yi"], "categories": ["Transportation & Logistics", "Inventory / Warehousing", "Supply Chain", "Merchandising & Purchasing", "Electronics"], "post_time": "2022-01-07T05:57:26Z", "salary": {"currency": null, "max": null, "min": null, "period": "monthly", "term": null}, "salary_visible": false, "title_keywords": ["logistics"], "responsibilities": ["management", "data entry", "data", "review", "multiple projects", "work under pressure"], "requirements": {"degrees": ["degree"], "majors": ["business"], "languages": ["cantonese", "english", "mandarin"], "language_level": ["good command"], "hard_skills": ["business management", "inform", "oracle"], "soft_skills": ["good team player", "self-motivated", "independent", "well-organized", "interpersonal skills", "work under pressure"], "languages_combined": [{"language": "cantonese", "language_level": ["good command"]}, {"language": "english", "language_level": ["good command"]}, {"language": "mandarin", "language_level": ["good command"]}]}, "experience_required": {"duration": ["1-3 years"], "field": ["related", "relevant working experience", "training"]}}, {"job_id": "100003009023091", "location_code": "hk", "company": "TGI Technology Limited", "job_title": "Senior Merchandiser / Merchandiser", "description": "About Our Client\u00a0(Electronics\u00a0Company) &\u00a0Job Description\u00a0\n\nOur client, one of the Electronics trading companies, is now looking for a\u00a0Sales Engineer\u00a0\u00a0to join their team. The job duties are as follows,\u00a0\n\nCoordinate projects for electronic connection products and monitor its manufacturing process to meet company standards.\nAct as window for Quality Assurance between customer and supplier for defective products including the processing, investigation, implementation of corrective action and reporting.\nLiaison with internal and external multi-national teams to ensure smooth production process\nConduct on-site audit and provide guidance to suppliers in China and South \u2013East Asia\nProvide periodic reporting for project status and quality performance to team leader and manager.\nMaintain good relationship with customers and suppliers.\n\nRequirement\u00a0\u00a0\n\nGood Command of Japanese(Passed JLPT N2 or above), English & Mandarin\nDiploma or above, Bachelor degree holder preferred\n2-4\u00a0years\u2019 working experience related to Sales Engineer in electronic industry preferred.\u00a0\nFamiliar with manufacturing process, new product development and delivery arrangement\nWilling to perform business trips to China/South East Asia Area\u00a0\nPresentable, independent, attention to details and good communication skills\u00a0", "employment_types": ["Full Time", "Permanent"], "selling_points": ["Guarantee 13th Month Salary", "Stable Work Environment", "International Company with Great Culture"], "locations": ["Hung Hom"], "categories": ["Merchandising & Purchasing", "Electronics", "Home Appliances", "Procurement / Purchasing / Sourcing"], "post_time": "2022-01-05T07:27:15Z", "salary": {"currency": null, "max": null, "min": null, "period": "monthly", "term": null}, "salary_visible": false, "title_keywords": ["merchandiser", "senior merchandiser"], "responsibilities": ["reporting", "production process", "quality", "monitor", "implementation", "investigation", "coordinate", "teams", "audit", "maintain good relationship", "provide guidance"], "requirements": {"degrees": ["diploma or above", "bachelor degree holder"], "majors": [], "languages": ["english", "mandarin"], "language_level": ["good command"], "hard_skills": [], "soft_skills": ["communication skills", "independent", "attention to details", "presentable"], "languages_combined": [{"language": "english", "language_level": ["good command"]}, {"language": "mandarin", "language_level": ["good command"]}]}, "experience_required": {"duration": ["2-4 years"], "field": ["related"]}}, {"job_id": "100003009036050", "location_code": "hk", "company": "Find Asia Limited", "job_title": "Japanese speaking Sales Engineer (Electronics)", "description": "Responsibilities:\n\n\u2981\u00a0Manage and handle wide range of office administrative duties, e.g. petty cash, office equipment procurement\n\u2981\u00a0Assisting Purchasing team in liaising with suppliers\n\u2981\u00a0Prepare and follow up purchase orders with suppliers and related duties\n\u2981\u00a0Organizing outgoing shipment and documentations\n\u2981\u00a0Data entry; invoice matching; part set-up and other system updates\n\u2981\u00a0Handling ad-hoc tasks as assigned by management\n\nRequirements:\n\n\u2981\u00a0HKCEE/HKDSE or above. University preferred.\n\u2981\u00a0Good command of written and spoken English and Mandarin\n\u2981\u00a0Proficient in MS Office, and fast learner of software\n\u2981\u00a0Proactive, well-organized, good sense of responsibility\n\u2981\u00a0Immediate availability is preferred\n\u2981\u00a0Permanent resident with HKID\n\nInterested candidates please click \"Apply Now\" and send your resume with current and expected salary to us.", "employment_types": ["Full Time", "Permanent"], "selling_points": ["5 days work, Double pay, bonus", "medical benefits, OT pay, transportation allowance", "Sizable trading company! Good career path"], "locations": ["Yau Tsim Mong Area"], "categories": ["Merchandising & Purchasing", "Electronics", "Sales, CS & Business Devpt", "Technical Sales / Sales Engineer", "Sales Administration"], "post_time": "2022-01-10T09:12:06Z", "salary": {"currency": null, "max": null, "min": null, "period": "monthly", "term": null}, "salary_visible": false, "title_keywords": ["sales engineer"], "responsibilities": ["management", "data entry", "invoice", "system updates", "ad-hoc tasks", "liaising with", "purchase", "administrative duties"], "requirements": {"degrees": ["hkdse"], "majors": [], "languages": ["english", "mandarin"], "language_level": ["good command"], "hard_skills": ["ms office"], "soft_skills": ["proactive", "fast learner", "well-organized", "sense of responsibility"], "languages_combined": [{"language": "english", "language_level": ["good command"]}, {"language": "mandarin", "language_level": ["good command"]}]}, "experience_required": {"duration": [], "field": []}}, {"job_id": "100003009023913", "location_code": "hk", "company": "Active Components (HK) Ltd", "job_title": "Logistics and Office Administrator (5 days)", "description": "Responsibilities:\n\nSpecific activities will include:\n\nDevelop and present presentations to customers on Supply Chain solutions for proposals; while working collaboratively with the supply chain, engineering, sales and the customers.\nActive participation in bid process to develop competitive solutions.\nProactively work with commodity staff and supplier to deliver an improved supplier solution.\nDriving improvement of SCM KPls for a range of customers\nAreas of focus may include supplier selection, SCM processes and tools, as well as logistics offerings\n\nOverall Deliverable:\n\nDelivery of transformation business solutions for customers.\nAchievement of business growth objectives.\nPenetration of new customer divisions or lines of business\nImprovement of SCK KPls for existing customers\n\nRequirements:\n\nDegree holder in Electrical & Electronics, Business, Supply Chain Management or related subjects\nStrong lateral skills beyond supply chain, (most critical here are customer savvy and financial acumen)\nIn depth knowledge of mechanical and electro-mechanical commodities and products\nWilling and able to dig into the details when necessary\nFamiliarity with advanced supply chain applications and tools\nAble to influence groups without direct reporting control\nMinimum of 10 years relevant industry experience.\nIndustrial business experience preferred\n\nHow to apply:\n\nPlease submit your resume in Word format quoting the reference no. and expected salary to our company email (top in red) or by clicking \"APPLY NOW\" below\n\nWeb site: www.searchselect.net\n\n(Personal data collected will be used for recruitment purposes only.)", "employment_types": ["Full Time", "Permanent"], "selling_points": [], "locations": ["Kwun Tong"], "categories": ["Admin & HR", "Clerical / Admin Staff", "Transportation & Logistics", "Shipping", "Merchandising & Purchasing", "Electronics"], "post_time": "2022-01-05T10:01:21Z", "salary": {"currency": null, "max": null, "min": null, "period": "monthly", "term": null}, "salary_visible": false, "title_keywords": ["administrator", "logistics"], "responsibilities": ["logistics", "presentations", "develop"], "requirements": {"degrees": ["degree holder"], "majors": ["business"], "languages": [], "language_level": [], "hard_skills": ["no", "web", "word", "red", "acumen"], "soft_skills": ["advanced"], "languages_combined": []}, "experience_required": {"duration": ["minimum of 10 years"], "field": ["business"]}}, {"job_id": "100003009025948", "location_code": "hk", "company": "Search & Select International Limited", "job_title": "Customer Program Manager/ Strategic Sourcing Manager/ Supply Chain Manager (PH1989-JDB)", "description": "We invite now high caliber talent to apply for Merchandiser (m/f)\u00a0to join our rapidly growing sourcing team in Hong Kong. This position supports product development and commercialization with a fast-paced successful team.\n\nResponsibilities.\n\nPerform general sourcing duties as required by the Manager\nPrepare and ensures that all documents related to tender, submission, awarding of contracts and shipments are correct and completed\nFinalize submission comparison documents and identify preferred submission in line with company procedures\nEffectively communicate with Quality, CR, Admin and Logistics team members as well as ALDI International departments/ offices and other internal/external parties on behalf of Manager/ team\nFollow through the production process for all purchased products\nCarry out visits to trade fairs or suppliers in order to manage and develop the supplier pool within the commodity area\nProvides cover for the team members and supports the training of employees and trainees from other areas\n\n\u00a0Your Profile.\n\nAt least (Non-Degree) Tertiary education required.\nMinimum of 2 years' relevant working experience, preferably gained in sourcing/buying offices, working with consumer products.\nExcellent communication and interpersonal skills, team player.\nGood command of both verbal and written business English and fluency in Mandarin essential.\nAble to work independently, self-motivated, responsible, well-organized and willing to learn.\nAttention to detail and good organizing, coordination and planning skills.\nGeneral knowledge of MS office and Exchange essential.\nHigh level of maturity, integrity, trustworthiness.\n\nKey Benefits of working at ALDI.\n\nMarket leading remuneration package\n\nRewarding, attractive remuneration package.\nGroup Medical Insurance covering dental and maternity* benefits .\n\nWork-life balance\n\nFull time, permanent position, 5-day-work-week.\n20 days of paid Annual Leave.\n\nBeing part of a pleasant, successful, growing business\n\nALDI\u2019s business is expanding, same for the Hong Kong Office with lots of opportunities for growth and development.\nPleasant working atmosphere where proactive communication, teamwork and collaboration is highly valued.\n\nPeople Focused\n\nStructured, comprehensive orientation and on-the-job training.\nALDI empowers our people allowing staff ownership of their areas of responsibilities.\n\nTrust and Integrity\n\nWE DO WHAT WE SAY - \u00a0for us there is no grey area, we have robust business processes, procedures and strong governance in place.\nWe treat our staff members, customers, suppliers and service providers with trust and fairness as business partners.\n\n\u00a0* Maternity benefits only apply for female employees due to local Insurance policy\n\nHow to apply\u00a0\u00a0\n\nIf you are interested in applying for the job, we look forward to receiving your full application in English, including salary expectation and possible starting date. The application should be sent through JobsDB by clicking icon \u201cApply Now\u201d or addressed to ALDI HR Department,\u00a018/F, Millennium City 6, 392 Kwun Tong Road, Kwun Tong, Kowloon, Hong Kong.\n\nALDI is an Equal Opportunity employer. We are dedicated to create an equal opportunity throughout recruitment process and staff employment to build a diverse and inclusive workforce. We oppose all forms of unfair or unlawful discrimination in our selection process.\n\nAll personal data collected will be used for recruitment purposes only and be treated in strictest confidence and highest security level in accordance with Hong Kong Data (Privacy) Ordinance as well as ALDI internal Security Policy.\n\nNo part of this job content including but not limited to company information, logo and job description may be reproduced, presented, uploaded, transmitted, modified or distributed \u00a0in any form or by any means without prior permission of ALDI Services Asia Limited / ALDI Sourcing Asia Limited (\u201cthe Company\u201d). The Company reserves the right to take legal action on any unauthorized reproduction, presentation, upload, transmission, modification or distribution. Only applications submitted directly to the Company in response to this advertisement will be considered and any application received by the Company through unauthorized third party agents or via any other channels will not be considered.\n", "employment_types": ["Full Time", "Permanent"], "selling_points": ["Support design project & direct sourcing selection", ">9yrs supply chain mgmt exp in electronic mfr", "Good communicate ability w/ all levels & customers"], "locations": ["Others"], "categories": ["Engineering", "Mechanical", "Merchandising & Purchasing", "Electronics", "Procurement / Purchasing / Sourcing"], "post_time": "2022-01-06T16:08:10Z", "salary": {"currency": null, "max": null, "min": null, "period": "monthly", "term": null}, "salary_visible": false, "title_keywords": ["manager", "supply chain manager", "sourcing manager"], "responsibilities": ["communicate with", "production process", "contracts", "external parties", "procedures", "quality", "develop", "communication", "commercialization", "logistics", "tender", "coordination", "planning"], "requirements": {"degrees": ["degree"], "majors": [], "languages": ["english", "mandarin"], "language_level": ["fluency", "good command"], "hard_skills": ["exchange", "ms office"], "soft_skills": ["planning skills", "work independently", "self-motivated", "responsible", "well-organized", "willing to learn", "integrity", "communication and interpersonal skills", "attention to detail", "coordination", "team player"], "languages_combined": [{"language": "english", "language_level": ["fluency", "good command"]}, {"language": "mandarin", "language_level": ["good command"]}]}, "experience_required": {"duration": ["minimum of 2 years"], "field": ["buying offices", "relevant working experience"]}}, {"job_id": "100003009024302", "location_code": "hk", "company": "ALDI Services Asia Limited", "job_title": "Merchandiser - Electrical / SDA (m/f)", "description": "About the company\n\nOur client is one of the UK\u2019s leading retailers of grocery and non-food products. It has more than 146 years of heritage with 160,000 employees and 1,200 stores in UK. It strives to become the most trusted retailer where customers and colleagues enjoy shopping and working. They build a firm commitment to ethical trading practices by sustainable sourcing. Their sourcing office in HK source best quality products and rightest cost for customers. Upon expansion of their strategic sourcing, they are now looking for a confident and committable Assistant Quality Officer to join their enjoyable and winning team.\n\nJob Description\n\nyou will be the key person to perform the following duties:\n\nEnsure products meet quality, legal and safety requirements and due diligence\nSupport and advise merchandisers to ensure products selected comply with UK/European standards and internal company requirements\nEnsure working practices aligned with UK/HK team, understood and implemented by suppliers and third party inspection and testing companies\nCoordinate with external test laboratories to ensure appropriate testing of products\nPerform factory assessment in relation to Quality and Ethical standards\nManage the Quality Management System to ensure quality deliveries of products and services\nManage and respond to quality assurance issues with related divisions\nReport to management for any product incident investigation\nAccountable for internal process and supplier sourcing improvement projects\n\nWhy you?\n\nAt least 1 year of experience in Quality Assurance /Quality Control from sourcing / buying office / retail / manufacturing background\nWelcome fresh graduates\nDegree holder\nStress-resistant and able to make balanced decisions\nExcellent communication skills\nFluently written and spoken English, Cantonese and Mandarin\n\nHow to Apply?\n\nIf you are looking for career changes, you may send resume to resume @)sixpeoplemap.com , quoting Job Ref#TH-8405. You may also contact us via\u00a0Whatsapp. Action now and share with you friends for referral rewards.", "employment_types": ["Full Time", "Permanent"], "selling_points": ["Responsible for orders monitoring and follow-up", "Tender submission and shipment documents", "Communicate with Quality, CR, Admin and Logistics"], "locations": ["Kwun Tong"], "categories": ["Merchandising & Purchasing", "Electronics", "Home Appliances", "Procurement / Purchasing / Sourcing"], "post_time": "2022-01-05T13:54:32Z", "salary": {"currency": null, "max": null, "min": null, "period": "monthly", "term": null}, "salary_visible": false, "title_keywords": ["merchandiser"], "responsibilities": ["due diligence", "cost", "management", "quality", "coordinate with", "investigation", "inspection", "testing", "communication", "contact", "quality control", "third party", "report"], "requirements": {"degrees": ["degree holder"], "majors": [], "languages": ["cantonese", "english", "mandarin"], "language_level": [], "hard_skills": ["make", "whatsapp"], "soft_skills": ["confident", "communication skills", "accountable", "ethical"], "languages_combined": [{"language": "cantonese", "language_level": []}, {"language": "english", "language_level": []}, {"language": "mandarin", "language_level": []}]}, "experience_required": {"duration": ["at least 1 year"], "field": ["manufacturing", "retail", "quality control", "quality assurance"]}}, {"job_id": "100003009031200", "location_code": "hk", "company": "Six People Map", "job_title": "Assistant Quality Officer | UK's leading retailer | Sizable buying office| MNC", "description": "(mainly mobile + PC accessories, power, audio visual products, \u00a0electronic gadgets, digital clocks) (MHW001)\n\n\nJob responsibilities:\nTo handle product development, liaise with related parties for enquiries, sample arrangement, production and shipments follow up\nTo source qualified vendors and products\nTo coordinate relevant product category trip\nRequirements:\n\nDSE /Form 5 or above\n1-3 years of relevant experience in merchandising field\nGood product knowledge in the field of Consumer Electronics focusing on mobile + PC accessories, power, audio visual products,\u00a0 electronic gadgets.\nExcellent negotiation and sourcing skills\nFamiliar with European market and able to follow up orders/inquiries independently\nAttentive to details and able to work under pressure\nGood command of written & spoken English and Chinese (Cantonese & Putonghua)\nGood computer knowledge (MS office and Chinese Word Processing)\nOccasional travel to China is required\nWe offer attractive remuneration package including 5-day week, double pay, discretionary bonus, medical & dental insurance, travel allowance, etc. Interested parties, please send your CV with expected salary and availability, and by quoting reference number (MHW001)in the subject by clicking \"Apply Now\". . Candidates who are not contacted within 8 weeks should consider their application as unsuccessful.\n\u00a0\n(The information provided will be used for selection purpose only.)", "employment_types": ["Full Time", "Permanent"], "selling_points": ["UK\u2019s leading retailers", "Career Progression Opportunity", "Welcome fresh graduates"], "locations": ["Kwun Tong"], "categories": ["Engineering", "Manufacturing & Production", "Merchandising & Purchasing", "Electronics", "Toy"], "post_time": "2022-01-07T09:02:54Z", "salary": {"currency": null, "max": null, "min": null, "period": "monthly", "term": null}, "salary_visible": false, "title_keywords": ["quality officer", "assistant"], "responsibilities": ["liaise with", "coordinate"], "requirements": {"degrees": ["form 5 or above", "dse"], "majors": [], "languages": ["cantonese", "putonghua", "english", "chinese"], "language_level": ["good command", "good"], "hard_skills": ["pc", "mobile", "chinese word processing", "ms office"], "soft_skills": ["independently", "negotiation", "attentive to details", "work under pressure"], "languages_combined": [{"language": "cantonese", "language_level": ["good command", "good"]}, {"language": "putonghua", "language_level": ["good command", "good"]}, {"language": "english", "language_level": ["good command", "good"]}, {"language": "chinese", "language_level": ["good command", "good", "good"]}]}, "experience_required": {"duration": ["1-3 years"], "field": ["merchandising", "relevant experience"]}}, {"job_id": "100003009023075", "location_code": "hk", "company": "Tchibo Merchandising Hong Kong LP", "job_title": "Merchandiser - Consumer Electronics", "description": "Reporting to the Line of Business, you will be responsible for developing and implementing our product management programs and initiatives, aiming to drive continual business growth and strengthen our competitive & brand positioning..\n\n\n\nResponsibilities:\n\nLead & drive the product management activities, including product enhancement programs, new product introduction, and portfolio management\nPlan & execute the project development and capture the new business opportunities in specified market segments\nMonitor, analyze and evaluate market trend of focused applications, customer requirements, and competitor activities\nClosely collaborate with factory, sales & marketing, and overseas business partners, to ensure effective communication throughout business development\nOther ad hoc duties as assigned\n\nRequirements:\n\nBachelor Degree or above in Engineering / Business Administration or related disciplines\nMinimum 3 years of relevant experience in product and marketing management\nTechnical knowledge in electronics industry is\u00a0preferable\nStrong analytical thinking, business acumen and problem solving capability\nGood communication and presentation skills\nProficient in MS excel & PowerPoint is a must\nGood command of both spoken and written English and Chinese.\nFluency in Putonghua is a must\nStation in Hong Kong Headquarters\n\nCandidate with less experience will be considered as Senior Product Specialist\n\nWe offer attractive remuneration package, 5-day work week and long-term career development opportunities to the right candidate. Please email your full resume with current and expected salary to\u00a0recruit_gpbi@ goldpeak.com.\n\nWe are an equal opportunity employer.\u00a0The information provided by you will be treated in strict confidence and used for recruitment purpose only.\u00a0\n\n\nFor more company details, please visit our website at www.gpbatteries.com.", "employment_types": ["Full Time", "Permanent"], "selling_points": ["To handle product development, liaise with parties", "knowledge in the field of Consumer Electronics", "European Buying Office, Flexible Working Hours"], "locations": ["Tsim Sha Tsui"], "categories": ["Merchandising & Purchasing", "Electronics", "Others", "Procurement / Purchasing / Sourcing"], "post_time": "2022-01-05T07:23:15Z", "salary": {"currency": null, "max": null, "min": null, "period": "monthly", "term": null}, "salary_visible": false, "title_keywords": ["merchandiser"], "responsibilities": ["collaborate with", "ad hoc duties", "management", "business opportunities", "monitor", "evaluate", "communication", "plan"], "requirements": {"degrees": ["degree or above", "bachelor"], "majors": ["related disciplines", "business administration", "engineering"], "languages": ["putonghua", "english", "chinese"], "language_level": ["fluency", "good command"], "hard_skills": ["problem solving", "ms excel", "powerpoint", "acumen"], "soft_skills": ["business acumen", "presentation skills", "communication", "problem solving"], "languages_combined": [{"language": "putonghua", "language_level": ["fluency"]}, {"language": "english", "language_level": ["good command"]}, {"language": "chinese", "language_level": ["good command"]}]}, "experience_required": {"duration": ["minimum 3 years"], "field": ["management", "marketing", "relevant experience"]}}, {"job_id": "100003009029375", "location_code": "hk", "company": "", "job_title": "**Manager/Assistant Manager** (\"Manager Development Scheme\" + Monthly Income $30000 up)", "description": "Ensure the order processing flow in a timely manner\n\nEnsure all relevant project information from the client is received as well as all samples are collected on time as per schedule\nCreate project files and ensure test plans, project schedules, report issues meet client expectations\n\nAct as one contact window to clients after an order is created\n\nWork with laboratory and clients to provide timely feedback regards to project details\nHandle daily clients\u2019 inquiries and complaints\n\nJob Requirements:\n\nHigh Diploma or above in science or related field of study\nAt least 1 year\u2019s working experience in project management and/ customer services field\nExperience in testing laboratory industry is an advantage\nAbility to work on tight deadlines\nCompetency in MS Office skills including Work, Excel and Outlook\nRecent graduates will be considered\nCandidates with more experience will be considered as Senior Project Coordinator\n\nOther Benefits:\n\nPublic Holidays\nDouble Pay and Performance Bonus\nMedical, Dental and Life Insurance\nAnnual Leave, Maternity Leave, Paternity Leave, Marriage Leave, Compassionate Leave\nOn-the-job training as well as Training Sponsorship/ Subsidies\n\nApplications:\n\nInterested parties please send your full resume with expected salary and date available to the Human Resources Department by clicking \"Apply Now\".\n\nAll information received will be kept in strict confidence and used for employment purpose only. Applicants who are not invited for interview within\u00a05 weeks may assume their applications unsuccessful and their data will be retained for 6 months for other suitable vacancies in our organization and thereafter destroyed.", "employment_types": ["Full Time", "Permanent"], "selling_points": [], "locations": ["Not Specified"], "categories": ["Accounting", "Finance / Accounting Manager", "Information Technology (IT)", "Network & System", "Merchandising & Purchasing", "Electronics"], "post_time": "2022-01-07T04:55:45Z", "salary": {"currency": null, "max": null, "min": null, "period": "monthly", "term": null}, "salary_visible": false, "title_keywords": ["assistant manager", "manager"], "responsibilities": ["schedules", "a timely manner", "customer services", "testing", "inquiries and complaints", "project management", "schedule", "order processing", "contact", "plans", "report"], "requirements": {"degrees": ["high diploma or above"], "majors": ["science"], "languages": [], "language_level": [], "hard_skills": ["excel", "project management", "outlook", "order processing", "ms office"], "soft_skills": ["project management", "timely"], "languages_combined": []}, "experience_required": {"duration": ["at least 1 year"], "field": ["project management", "testing", "laboratory", "customer services"]}}, {"job_id": "100003009024796", "location_code": "hk", "company": "GP Batteries International Limited", "job_title": "Assistant Product Manager", "description": "Responsibilities:\n\nAssist in executing vendor management and sourcing strategy that aligns with TTI-group long-term objectives\nSource new products and vendors in the areas of Powertools, Electronics and related product categories\nWork closely with local new product development (NPD) teams and overseas sales/marketing teams throughout the NPD process\nDrive cost targets and cost reduction programs\nMonitor supplier scorecard and drive improvement\nCoordinate supply chain, logistics and commercial issues\nSupport team managers in preparation and implementation of projects\nTravel required throughout China, Taiwan and possibly other Asian countries\nRequirements:\n\nDegree in Business or related disciplines\nAt least 3 years sourcing/merchandising or related experience\nKnowledge of tools / durable consumer goods / engineering would be an advantage\nGood negotiation skills and excellent team working capabilities\n\nPro-active self-starter and well organized\n\nEnjoy working in a fast-paced and dynamic environment\n\nGood command of written and spoken English, Cantonese and Mandarin\nWe offer 5-day week, competitive remuneration package and good career prospects to the right candidate. Interested parties please send your resume with expected salary\u00a0by clicking APPLY NOW.\n(All personal data collected would be used for recruitment purpose only)", "employment_types": ["Full Time"], "selling_points": ["Lead & drive the product management activities", "Plan & execute the project development", "Monitor, analyze and evaluate market trend"], "locations": ["Shatin Area"], "categories": ["Manufacturing", "Product Development / Management", "Marketing / Public Relations", "Marketing - Brand / Product Management", "Merchandising & Purchasing", "Electronics"], "post_time": "2022-01-06T02:32:08Z", "salary": {"currency": null, "max": null, "min": null, "period": "monthly", "term": null}, "salary_visible": false, "title_keywords": ["assistant product manager"], "responsibilities": ["product categories", "cost", "management", "teams", "monitor", "coordinate", "implementation of projects", "executing", "logistics"], "requirements": {"degrees": ["degree"], "majors": ["related disciplines", "business"], "languages": ["cantonese", "english", "mandarin"], "language_level": ["good command"], "hard_skills": ["dynamic"], "soft_skills": ["dynamic environment", "enjoy working", "well organized", "negotiation skills", "pro-active", "team working"], "languages_combined": [{"language": "cantonese", "language_level": ["good command"]}, {"language": "english", "language_level": ["good command"]}, {"language": "mandarin", "language_level": ["good command"]}]}, "experience_required": {"duration": ["at least 3 years"], "field": ["related", "merchandising"]}}, {"job_id": "100003009023051", "location_code": "hk", "company": "TUV Rheinland Hong Kong Limited", "job_title": "Project Coordinator, Electrical", "description": "Offers and Benefits\n\nManager Development Scheme to Unit Manager Within 7 Months\n5-days work, 21 days annual leave, bank holidays\nHigh\u00a0Monthly Production Bonus + Year-end Bonus + Management income\nFirst Year Income approx. HK$400,000 to 500,000 or above\nOverseas Incentive trips, Recruitment Incentive and Managerial Awards\nLife & Medical Benefits, Company retirement scheme\nComprehensive and tailor-made professional training programs\nClient base provided\nFriendly working environment and recruitment support for team expansion\u00a0\n\nRequirements\n\nTertiary education or above, Degree holder preferred\nHKID cardholder a MUST\nCantonese and Mandarin speaker\n3 Years working experience or more\nNot necessary with finance experience\nMature, hard working, self-motivated and outgoing\u00a0\u00a0\nStrong Desire for a successful career\n\nJob Descriptions\n\nProvide Individual clients with Professional Financial Planning on life and medical protection, investment, retirement and MPF plan etc.\nProvide Corporate clients with service on MPF, Group life and medical plan, Business insurance etc.\nBuild your own Professional Agency team for Lifetime career development\u00a0\n\nInterested Candidates please send your full resume to HR\nBy email to cynthia _ c _ lee @manulife.com.hk\u00a0\nOr contact Miss Cynthia Lee at\u00a09474 8433 for an interview\n\n\u00a0*Only shortlisted candidates will be notified. All data collected will be used for recruitment purposes only and will be kept strictly confidential.", "employment_types": ["Full Time", "Permanent"], "selling_points": ["With working exp. in project mgmt. or CS field", "Exp. in testing laboratory industry is an advant", "Fresh graduates will be considered"], "locations": ["Tsuen Wan Area"], "categories": ["Sales, CS & Business Devpt", "Customer Service - Supervisor / Officer", "Merchandising & Purchasing", "Electronics", "Sciences, Lab, R&D", "Others"], "post_time": "2022-01-05T07:16:52Z", "salary": {"currency": null, "max": null, "min": null, "period": null, "term": null}, "salary_visible": false, "title_keywords": ["project coordinator"], "responsibilities": [], "requirements": {"degrees": [], "majors": [], "languages": [], "language_level": [], "hard_skills": [], "soft_skills": [], "languages_combined": []}, "experience_required": {"duration": [], "field": []}}, {"job_id": "100003009024915", "location_code": "hk", "company": "Techtronic Industries Co Ltd", "job_title": "Senior Executive, Sourcing and Supply Chain", "description": "Responsibilities:\n\n\nEnsure the smooth running of the whole product development and merchandising processes of multiple clients, including the timely and strategic execution of client briefs, vendor sourcing, sampling, production, quality control and delivery\nWork flexibly across a range of product categories, including Fashion Accessories, Jewellery and Watches, Electronics (including Smartwatches), Beauty Accessories and Sundries\nManage and coordinate client briefs, working with team members and factories to prepare responses\nAct as liaison between cross-functional departments to ensure effective communications across the organisation to uphold excellence in client service\nBuild/develop and maintain strong relationships with clients through effective project management and delivery and exceeding expectations with innovative solutions\nBuild/develop and maintain strong relationships with suppliers/factories, keeping factory base up-to-date and in line with clients\u2019 current and future needs and objectives\nHands-on resolution of day-to-day operational/supply chain issues and complications; identify, propose and implement workable solutions to existing and potential problems\nPrepare timely submission of up-to-date presentations on global and regional product, design, and industry trends and insights; coordinate with designers to develop seasonal concepts and proposals\nLead or participate in and contribute to in-person/virtual client meetings with excellent presentation skills, preparation, understanding of client needs, and fluency in the use of Microsoft Teams/Zoom and their tools\nPro-actively assist and report to Directors with business development plans with existing and potential clients to achieve growth and profitability targets\nRequirements:\nUniversity graduate, preferably in merchandising, fashion management, or related disciplines\n10 years of relevant hands-on experience in product development, merchandising and sourcing for the Europe/US markets\nBackground in multi-national trading/sourcing companies with client-facing experience and an understanding in manufacturing processes\nFluent in English, Mandarin, and Cantonese\nWorking knowledge in quality control and product regulatory compliance\nResponsible and flexible team player and leader with attention-to-detail and strong inter-personal, communication, organisational and negotiation skills\nAbility to cope with tight deadlines\nTravel is required\n\nExcellent career opportunities for promotion and remuneration for the right applicants. Please email your resume and cover letter with current and expected salary by clicking \"Apply Now\".\n\nWe thank all applicants for their interests, but only shortlisted candidates will be notified. All personal data collected will be treated as strictly confidential and used for recruitment purposes only.", "employment_types": ["Full Time", "Permanent"], "selling_points": ["Vendor Management", "Sourcing Strategy", "Project Management"], "locations": ["Kwai Hing"], "categories": ["Transportation & Logistics", "Supply Chain", "Merchandising & Purchasing", "Electronics", "Procurement / Purchasing / Sourcing"], "post_time": "2022-01-06T02:55:30Z", "salary": {"currency": null, "max": null, "min": null, "period": "monthly", "term": null}, "salary_visible": false, "title_keywords": ["senior executive"], "responsibilities": ["product categories", "merchandising", "coordinate with", "presentations", "develop", "coordinate", "project management", "resolution", "maintain", "design", "teams", "quality control", "plans", "report"], "requirements": {"degrees": ["university graduate"], "majors": ["related disciplines"], "languages": ["cantonese", "english", "mandarin"], "language_level": ["fluent"], "hard_skills": [], "soft_skills": ["flexible", "responsible", "inter-personal", "communication", "hands-on", "negotiation skills", "team player", "client-facing"], "languages_combined": [{"language": "cantonese", "language_level": ["fluent"]}, {"language": "english", "language_level": ["fluent"]}, {"language": "mandarin", "language_level": ["fluent"]}]}, "experience_required": {"duration": ["10 years"], "field": ["manufacturing", "merchandising", "product development", "trading", "client-facing"]}}, {"job_id": "100003009021973", "location_code": "hk", "company": "Uniqbe Limited", "job_title": "International Sales and Purchase Executive (Consumer Electronics) \u92b7\u552e\u52a9\u7406 (\u8cbf\u6613\u548c\u96fb\u5546)", "description": "About the company\n\nOur client is an EU retail sourcing company specialized in household and personal care productions. In line with their international growth strategies, they are looking for a Merchandiser to join the operation department and follow up the productions & keep track the shipment schedules.\n\nResponsibilities\n\nFollow up the production with PRC and offshore vendors\nMonitor the shipment schedules with 3PL and manage the lead time and ensure on time delivery\nSAP navigation\nAssist on system consolidation and prepare & verify the figures including date, quantity, lead-time for production planning\n\nRequirements\n\nDiploma or above\nMinimum 1.5 years in merchandising/ shipping/ logistics coordination\n* Proficiency in MS Excel & SAP system\nExcellent command of written and spoken English and Mandarin is essential\n\nApplication\n\nIf this above description fits your experience and is something you would like to explore, please click 'Apply Now' to submit your resume to us.\n\nAny questions, please feel free to contact Kenneth Leung at 3907 3939.", "employment_types": ["Full Time"], "selling_points": ["Opportunity to work travel internationally", "Yearly performance bonus and overtime provided", "Full-time staff medical insurance provided"], "locations": ["Kwai Fong"], "categories": ["Merchandising & Purchasing", "Electronics", "Sales, CS & Business Devpt", "Wholesale", "Information Technology (IT)", "Mobile / Wireless Communications"], "post_time": "2022-01-05T04:48:51Z", "salary": {"currency": null, "max": null, "min": null, "period": "monthly", "term": null}, "salary_visible": false, "title_keywords": ["executive", "\u92b7\u552e\u52a9\u7406", "sales"], "responsibilities": ["ensure on time delivery", "monitor", "shipment schedules", "production planning"], "requirements": {"degrees": ["diploma or above"], "majors": [], "languages": ["english", "mandarin"], "language_level": ["excellent"], "hard_skills": ["ms excel", "sap"], "soft_skills": ["coordination"], "languages_combined": [{"language": "english", "language_level": ["excellent"]}, {"language": "mandarin", "language_level": ["excellent"]}]}, "experience_required": {"duration": [], "field": []}}, {"job_id": "100003009023548", "location_code": "hk", "company": "Siu Success (Y.K.Y.) and Company Limited", "job_title": "General Merchandising Manager", "description": "Responsibilities:\n\n\nManage for all-round procurement duties including price negotiation, inventory level management, product sourcing and maintain relationship with suppliers\nAnalyze of products\u2019 trend, competition, pricing and merchandising strategies for management review\nCommunicate the sales and marketing campaigns with internal functional teams to drive continuous improvement\nDevelop and implement new business opportunities and merchandising strategy\n\n\u00a0Requirements:\n\n\nDegree or above in Business Administration or related disciplines\n4-7 years relevant experience in mobile phone merchandising\nGood negotiation skills and communications skills\nProficient in MS Office applications\nMature, well-organized, self-motivated and able to work independently under fast-paced working environment\n\nWe offer competitive salary package to the successful candidate. \u00a0Interested parties please contact us at 9435 2209 for company details.\n(Data collected will be used for recruitment purpose only)", "employment_types": ["Full Time"], "selling_points": [], "locations": ["Lai Chi Kok"], "categories": ["Merchandising & Purchasing", "Electronics", "Watch", "Others"], "post_time": "2022-01-05T09:10:54Z", "salary": {"currency": null, "max": null, "min": null, "period": "monthly", "term": null}, "salary_visible": false, "title_keywords": ["merchandising manager"], "responsibilities": ["price negotiation", "management", "inventory", "business opportunities", "merchandising", "teams", "develop", "maintain", "marketing campaigns", "management review"], "requirements": {"degrees": ["degree or above"], "majors": ["related disciplines", "business administration"], "languages": [], "language_level": [], "hard_skills": ["mobile", "ms office"], "soft_skills": ["self-motivated", "work independently", "well-organized", "mature", "negotiation skills"], "languages_combined": []}, "experience_required": {"duration": ["4-7 years"], "field": ["merchandising", "relevant experience"]}}, {"job_id": "100003009023562", "location_code": "hk", "company": "Morgan McKinley", "job_title": "Merchandiser (SAP, Production and Shipment Control)", "description": "Summary of the Position\u00a0\n\nWe are seeking a talented and passionate Sourcing Specialist to support our supply chain team. Our products enable construction companies to eliminate the need for diesel and drive the transition toward fully electrified construction sites. Our supply chain is complex and involves developing and managing a complex supply chain of advanced materials and components. We are in a growth stage so are looking for a dynamic, talented individual who will be integral in ramping up our manufacturing and supply chain team. Being a small, fast-moving team, this role will have a wide scope and there is lots of room to develop and learn. The role will report into the Head of Supply Chain.\u00a0\n\nYou should be motivated, reliable, thorough, and excited about being among the first in the world to work with game- changing products. You will be expected to be able to operate with a degree of autonomy and be a clear, candid, and effective communicator in both spoken and written English and Chinese.\u00a0\n\n\n\nKnowledge, Qualifications and Skills\u00a0\n\n\u00a0\u00a0\u00a0\u00a0\u00a0\u00a0 Bachelor degree or higher in Engineering discipline/ Purchasing/ Supply Chain or equivalent\n\u00a0\u00a0\u00a0\u00a0\u00a0\u00a0 0-3 years of relevant experience preferable in electronics or mechanical components\n\u00a0\u00a0\u00a0\u00a0\u00a0\u00a0 Naturally curious and with a strong personality and self-motivated\n\u00a0\u00a0\u00a0\u00a0\u00a0\u00a0 Strong at negotiation skills, price-quality assessment to enable operational decision-making or present clear recommendations to management.\n\u00a0\u00a0\u00a0\u00a0\u00a0\u00a0 Knowledge of ERP and/or Oracle NetSuite experience is a plus\n\u00a0\u00a0\u00a0\u00a0\u00a0\u00a0 Passionate, high energy, and display initiative for improving our working procedures.\n\u00a0\u00a0\u00a0\u00a0\u00a0\u00a0 Knowledge of Quality Management Systems (eg ISO9001) is preferable.\n\u00a0\u00a0\u00a0\u00a0\u00a0\u00a0 Knowledge of process qualification and part approval processes is preferable.\n\u00a0\u00a0\u00a0\u00a0\u00a0\u00a0 Fluent in English and Mandarin, good working proficiency in Cantonese is a plus.\u00a0\n\u00a0\u00a0\u00a0\u00a0\u00a0\u00a0 Permitted to work in Hong Kong.\n\nResponsibilities\n\n\u00a0\u00a0\u00a0\u00a0\u00a0\u00a0 Source and select the suitable electronic/mechanical components for the manufacturing of our products\n\u00a0\u00a0\u00a0\u00a0\u00a0\u00a0 Create multi-season forward looking plans for suppliers and prepare necessary documentation\n\u00a0\u00a0\u00a0\u00a0\u00a0\u00a0 Negotiate with vendors to obtain most favourable price, schedule, terms, and conditions\n\u00a0\u00a0\u00a0\u00a0\u00a0\u00a0 Effective review, track and adherence to all project management under sourcing scope to ensure they are executed throughout pipeline, with the right priorities and agreed performance level.\u00a0\n\u00a0\u00a0\u00a0\u00a0\u00a0\u00a0 Identify and understand sourcing and channel needs in line with the Engineering team for new product/project developments\n\u00a0\u00a0\u00a0\u00a0\u00a0\u00a0 Is aware and informed about Macroeconomics factors (political, economic & strategic) and is able to calculate a potential impact to business operations in the responsible regions\n\u00a0\u00a0\u00a0\u00a0\u00a0\u00a0 Drive and ensure the development and implementation of organizational structures, capabilities, processes and systems to successfully implement innovative Sourcing solutions\n\nBenefits\u00a0\n\n\u00a0\u00a0\u00a0\u00a0\u00a0\u00a0 Competitive salary.\n\u00a0\u00a0\u00a0\u00a0\u00a0\u00a0 Opportunity to develop and learn about multiple areas across the supply chain.\u00a0\n\u00a0\u00a0\u00a0\u00a0\u00a0\u00a0 Uber travel policy (for business travel & travel after 8pm).\u00a0\n\u00a0\u00a0\u00a0\u00a0\u00a0\u00a0 Creating something new and great for the world!\n\nHow to apply\n\nPlease send your detailed resume stating why you are interested and your availability.\n\nAll information provided will be treated in strict confidence and used solely for recruitment purposes. We regret that we are only able to notify short-listed candidates.\n\nAmpd Energy is an equal opportunity employer. All candidates will be assessed on merit without regard to race, gender, sexual orientation, religion, nationality, marital status, political affiliation or any other factor protected by law.", "employment_types": ["Full Time", "Permanent"], "selling_points": ["SAP", "Production", "Shipment control"], "locations": ["Not Specified"], "categories": ["Merchandising & Purchasing", "Electronics", "Woven / Knit", "PVC"], "post_time": "2022-01-05T09:07:20Z", "salary": {"currency": null, "max": null, "min": null, "period": "monthly", "term": null}, "salary_visible": false, "title_keywords": ["merchandiser"], "responsibilities": ["management", "operations", "systems", "quality", "developing", "procedures", "develop", "review", "project management", "implementation", "schedule", "documentation", "plans", "report"], "requirements": {"degrees": ["degree", "bachelor"], "majors": ["engineering"], "languages": ["cantonese", "english", "chinese", "mandarin"], "language_level": ["good", "proficiency", "fluent"], "hard_skills": ["small", "plus", "erp", "project management", "dynamic", "documentation", "oracle"], "soft_skills": ["passionate", "self-motivated", "advanced", "responsible", "organizational", "innovative", "clear", "project management", "negotiation skills", "dynamic", "motivated", "thorough", "communicator", "reliable", "initiative"], "languages_combined": [{"language": "cantonese", "language_level": ["proficiency", "good"]}, {"language": "english", "language_level": ["fluent", "proficiency", "good"]}, {"language": "chinese", "language_level": ["fluent", "proficiency"]}, {"language": "mandarin", "language_level": ["fluent", "proficiency", "good"]}]}, "experience_required": {"duration": ["0-3 years"], "field": ["relevant experience"]}}, {"job_id": "100003009021366", "location_code": "hk", "company": "", "job_title": "Merchandising Manager (Mobile Phone)", "description": "Key Responsibilities:\n\nSourcing different materials or services to meet business needs.\nPrice negotiation and comparison among various vendors and suppliers, aiming to minimize cost whilst maximizing quality.\nLiaise with customer, factory, forwarder, and other parties regarding sales and\u00a0purchases and the related shipments;\nCoordinate and follow up all transport and delivery arrangements\nCooperate the Commercial Manager to handle shipment with customer,\u00a0factory and forwarder;\nHandles I/E documentation, custom declaration, scheduling, logistics and distribution functions;\nAssist to support to purchasing/logistic activities and ad-hoc project if necessary.\n\nRequirements:\n\nF.5/ DSE graduate or above;\n1 year relevant experience, preferable from trading/manufacturing sector (Fresh graduate will also be considered);\nKnowledge of Import/ Export documentation, custom declaration, scheduling and logistic arrangement;\nGood command in both English and Mandarin;\nFamiliar with MS office including Word, Excel, Knowledge of custom declaration software will be an advantage;\nStrong communication and negotiation skills;\nPro-active, responsible and able to work under pressure;\nImmediate availability is highly preferred.", "employment_types": ["Full Time", "Permanent"], "selling_points": ["Maintain and build relationship with suppliers", "Explore new business opportunities", "Manage demand and supply"], "locations": ["Not Specified"], "categories": ["Merchandising & Purchasing", "Electronics", "Home Appliances", "Procurement / Purchasing / Sourcing"], "post_time": "2022-01-05T03:45:44Z", "salary": {"currency": null, "max": null, "min": null, "period": "monthly", "term": null}, "salary_visible": false, "title_keywords": ["merchandising manager"], "responsibilities": ["ad-hoc", "cost", "price negotiation", "documentation", "custom declaration", "quality", "coordinate", "scheduling", "logistics", "liaise with"], "requirements": {"degrees": ["fresh graduate", "dse"], "majors": ["manufacturing"], "languages": ["english", "mandarin"], "language_level": ["good command"], "hard_skills": ["documentation", "excel", "word", "ms office"], "soft_skills": ["responsible", "communication", "negotiation skills", "pro-active", "work under pressure"], "languages_combined": [{"language": "english", "language_level": ["good command"]}, {"language": "mandarin", "language_level": ["good command"]}]}, "experience_required": {"duration": ["1 year"], "field": ["manufacturing", "relevant experience", "trading"]}}, {"job_id": "100003009018476", "location_code": "hk", "company": "Ampd Energy Limited", "job_title": "Sourcing Specialist", "description": "Responsible for handling raw material sourcing especially in plastic resin and all regular purchasing duties such as monitoring the service, quality, price, delivery and reliability of the suppliers.\n\nDiploma or above in Purchasing, Engineering or related disciplines\nAt least 3 years experience in handling plastic resin and procurement in manufacturing industry\n\nExcellent negotiation, communication and sourcing skills\nGood command of English and Chinese\nOccasional travel to PRC is required\nFresh graduates will be considered as Purchasing Assistant\n\nWorking location: Wong Chuk Hang (3 minutes' walk from MTR station)\n\nWe offer\u00a0attractive remuneration package including 5-day work, bank holidays, group medical insurance etc to the right candidates.\u00a0 Interested parties please send your full resume including expected salary and date available to Human Resources Department by clicking \"Apply Now\" button.\n\nFor more details, please visit our web-site at www.simatelex.com.hk", "employment_types": ["Full Time", "Permanent"], "selling_points": ["Rapidly Growing Startup Environment", "0-3 years of Relevant Experience", "Fluent in English & Mandarin, preferably Cantonese"], "locations": ["Lai Chi Kok"], "categories": ["Manufacturing", "Production Planning / Control", "Merchandising & Purchasing", "Electronics", "Procurement / Purchasing / Sourcing"], "post_time": "2022-01-04T03:41:52Z", "salary": {"currency": null, "max": null, "min": null, "period": "monthly", "term": null}, "salary_visible": false, "title_keywords": ["specialist"], "responsibilities": ["communication", "monitoring", "quality"], "requirements": {"degrees": ["diploma or above"], "majors": ["related disciplines", "engineering"], "languages": ["english", "chinese"], "language_level": ["good command"], "hard_skills": [], "soft_skills": ["communication", "negotiation", "responsible"], "languages_combined": [{"language": "english", "language_level": ["good command"]}, {"language": "chinese", "language_level": ["good command"]}]}, "experience_required": {"duration": ["at least 3 years"], "field": ["manufacturing industry", "procurement"]}}, {"job_id": "100003009013078", "location_code": "hk", "company": "Transtech Optical Communication Co Ltd", "job_title": "Purchasing Assistant", "description": "Responsibilities:\n\nResponsible for new RFQ opportunity and identify the most suitable suppliers/components at competitive pricing & technical requirement\n\nCoordinate with internal and external teams to maintain a positive rapport\nDevelop, implement and drive the procurement strategies in order to facilitate company grow\nPerform regular review with suppliers to drive continuous improvements\n\n\nRequirements:\n\nBachelor's\u00a0degree in Engineering is preferred\nMinimum 8 years of solid experience in component sourcing and manufacturing field\n\nExperience in manufacturing process of electronic and electromechanical parts\n\nExcellent negotiation, interpersonal, analytical and problem solving skills\n\nProficient in English and Chinese (written and spoken)\nFrequent travel to PRC is required\u00a0\n\nA stable and team-based environment can be enjoyed. Comprehensive remuneration package will be offered to the right candidates, such as competitive pay, medical and dental coverage, generous annual leave entitlement etc.\n\n\nPersonal data collected will be used for recruitment purpose only.\n\nInterested candidates, please contact us at 51238635 for company details before applying.", "employment_types": ["Full Time", "Permanent"], "selling_points": [], "locations": ["Tai Po Area"], "categories": ["Transportation & Logistics", "Shipping", "Merchandising & Purchasing", "Electronics", "Others"], "post_time": "2022-01-03T01:19:18Z", "salary": {"currency": null, "max": null, "min": null, "period": "monthly", "term": null}, "salary_visible": false, "title_keywords": ["purchasing assistant"], "responsibilities": ["continuous improvements", "teams", "coordinate with", "develop", "regular review", "maintain"], "requirements": {"degrees": ["degree", "bachelor"], "majors": ["engineering"], "languages": ["english", "chinese"], "language_level": ["proficient"], "hard_skills": ["problem solving skills"], "soft_skills": ["negotiation", "analytical and problem solving skills", "comprehensive", "stable", "interpersonal"], "languages_combined": [{"language": "english", "language_level": ["proficient"]}, {"language": "chinese", "language_level": ["proficient"]}]}, "experience_required": {"duration": ["minimum 8 years"], "field": ["manufacturing"]}}, {"job_id": "100003009014010", "location_code": "hk", "company": "Simatelex Manufactory Co., Ltd.", "job_title": "Purchasing Officer", "description": "Responsibilities:\n\nHandle and Coordinate Plastic & Paper product development cycle (including board games & puzzles) with factory\nResponsible in\u00a0managing suppliers, product development schedule,\u00a0costing comparison & calculation, sourcing material and vendors.\nFollow-up orders with factory, customers and internal parties to ensure customer satisfaction and on-time delivery\nHandle ad-hoc assignments as required\n\nRequirements:\n\nForm 7 or above\n3 years experiences in\u00a0OEM/ODM Plastic & Paper products (Experiences in Board game, Puzzle are preferred)\nStrong with plastic paper development cycle / schedule\u00a0is a definite advantage\nGood in English and good in PC/ERP knowledge\nExcellent communication skills with overseas customers and vendors are essential\nDetail-minded, well-organized, responsible and can work independently\nImmediately available is preferred\n\nAlternate Saturday, Double pay, Medical, Annual leave, Bonus\n\nWe offer attractive remuneration packages and excellent career opportunities. Interested parties please send resume states clearly expected salary by \"Apply Now\"", "employment_types": ["Full Time", "Permanent"], "selling_points": [], "locations": ["Aberdeen"], "categories": ["Merchandising & Purchasing", "Electronics", "Home Appliances", "Procurement / Purchasing / Sourcing"], "post_time": "2022-01-03T02:57:33Z", "salary": {"currency": null, "max": null, "min": null, "period": null, "term": null}, "salary_visible": false, "title_keywords": ["purchasing officer"], "responsibilities": ["coordinate", "ad-hoc assignments", "schedule", "internal parties"], "requirements": {"degrees": [], "majors": [], "languages": ["english"], "language_level": ["good"], "hard_skills": ["pc", "erp"], "soft_skills": ["detail-minded", "communication skills", "work independently", "responsible", "well-organized"], "languages_combined": [{"language": "english", "language_level": ["good", "good"]}]}, "experience_required": {"duration": ["3 years"], "field": []}}, {"job_id": "100003009021202", "location_code": "hk", "company": "", "job_title": "Procurement Officer - Electronic", "description": "Buyer - Home & Lifestyle\n\nOur client is a retail group, they are currently looking for a Buyer for their expansion\n\nJob description:\n\n\n\nDevelop merchandise and product assortment mix for the store\nMaintain relationship with overseas and local vendors\nSource potential vendors for the expansion of product mix\nProvide reports, analysis and support to managers\nMonitor logistic arrangement\n\nRequirement:\n\nDegree holder\n\nExperience/ Passionate in home and lifestyle categories\nJunior one will be consider as Assistant Buyer\nExcellent skills in Excel\nDriven with good presentation and communication skills\nEnglish & Chinese is a MUST", "employment_types": ["Full Time", "Permanent"], "selling_points": ["RFQ and procurement activities", "Communicate with internal and external suppliers", "Comprehensive remuneration package"], "locations": ["Not Specified"], "categories": ["Manufacturing", "Others", "Merchandising & Purchasing", "Electronics", "Procurement / Purchasing / Sourcing"], "post_time": "2022-01-05T03:17:52Z", "salary": {"currency": null, "max": null, "min": null, "period": "monthly", "term": null}, "salary_visible": false, "title_keywords": ["procurement officer"], "responsibilities": ["analysis", "monitor", "provide reports", "develop", "logistic arrangement", "maintain"], "requirements": {"degrees": ["degree holder"], "majors": [], "languages": ["english", "chinese"], "language_level": [], "hard_skills": ["excel"], "soft_skills": ["passionate", "communication skills", "presentation", "driven"], "languages_combined": [{"language": "english", "language_level": []}, {"language": "chinese", "language_level": []}]}, "experience_required": {"duration": [], "field": []}}, {"job_id": "100003009016453", "location_code": "hk", "company": "Longshore Ltd", "job_title": "Senior Merchandiser / Merchandiser - Toys", "description": "Job Responsibilities\n\n\u8ca0\u8cac\u570b\u969b\u8cbf\u6613\u548c\u96fb\u5546\u5e73\u53f0\u7684\u96fb\u5b50\u7522\u54c1\u92b7\u552e\u696d\u52d9\n\u5354\u52a9\u92b7\u552e\u5718\u968a\u4e00\u5207\u7684\u92b7\u552e\u65e5\u5e38\u904b\u4f5c\n\n\u8ca0\u8cac\u8a02\u55ae\u00a0(\u8cbf\u6613\u548c\u96fb\u5546)\u7684\u65e5\u5e38\u904b\u4f5c\uff1a\u5ba2\u6236\u806f\u7e6b\uff0c\u8a02\u55ae\u5be9\u6838\uff0c\u8a02\u55ae\u8655\u7406\u548c\u767c\u8ca8\uff0c\u5ba2\u6236\u552e\u524d\u548c\u552e\u5f8c\u670d\u52d9\n\nTo identify, explore, liaise, negotiate and close deal with international suppliers and customers in Asia, Middle East and Europe\nTo maintain good relationships with business partners\nTo compile daily purchase and sales prices and disseminate to business partners\nTo identify potential profitable technological products to sell\nTo manage B2B platforms to identify new international suppliers and customers\nTo manage and follow-up on sales and purchase orders, deliveries, returns, warranty requirements and general enquiries\nTo work closely and harmoniously with internal colleagues to ensure an effective and efficient operation\nKeep track of business and competitive trends, and advise senior management on relevant product positioning strategies\n\nRequirements\n\nFresh graduates would be preferred\nGood presentation and pitching skills. Ability to negotiate deals and excellent with numbers\nAnalytical mindset and critical thinking\nExcellent communication and interpersonal skills\nRequired language (s): English, Mandarin and Cantonese\nHas a passion in new technology and gadgets\nAble to multi-task using computer and mobile\nAble to work under pressure and work from mobile during non-working hours is needed from time to time\n5.5 working days (Alternate Saturday off)", "employment_types": ["Full Time", "Permanent"], "selling_points": ["Whole merchandising procedure", "Excellent career prospect", "Immediate Available is preferred"], "locations": ["Hung Hom"], "categories": ["Manufacturing", "Product Development / Management", "Merchandising & Purchasing", "Electronics", "Toy"], "post_time": "2022-01-03T09:06:29Z", "salary": {"currency": null, "max": null, "min": null, "period": "monthly", "term": null}, "salary_visible": false, "title_keywords": ["merchandiser", "senior merchandiser"], "responsibilities": ["liaise", "purchase", "maintain", "senior management"], "requirements": {"degrees": [], "majors": [], "languages": ["cantonese", "english", "mandarin"], "language_level": [], "hard_skills": ["mobile"], "soft_skills": ["multi-task", "passion in", "communication and interpersonal skills", "presentation", "work under pressure"], "languages_combined": [{"language": "cantonese", "language_level": []}, {"language": "english", "language_level": []}, {"language": "mandarin", "language_level": []}]}, "experience_required": {"duration": [], "field": []}}, {"job_id": "100003009025144", "location_code": "hk", "company": "Links International", "job_title": "Buyer- Retail brand", "description": "Responsibilities\n\n\nProject management.\nLCD and TFT Display Module Design\n\nRequirements\n\nDiploma or above in electronic Engineering or related discipline\nAt least 2 years or above solid experience in product design on Electronic field.\nProficient in\u00a0Altium designer/ AutoCad / C language etc\nTeam work with strong communication skills\nAble to follow-through several design projects at the same time\nGood command of written and spoken English and Mandarin\nFresh graduates will also be considered", "employment_types": ["Full Time", "Permanent"], "selling_points": ["Develop merchandise mix", "Passionate in home /lifestyle", "Detailed, Organized"], "locations": ["Not Specified"], "categories": ["Merchandising & Purchasing", "Electronics", "Furniture"], "post_time": "2022-01-06T03:35:26Z", "salary": {"currency": null, "max": null, "min": null, "period": "monthly", "term": null}, "salary_visible": false, "title_keywords": [], "responsibilities": ["project management", "design"], "requirements": {"degrees": ["diploma or above"], "majors": ["engineering"], "languages": ["english", "mandarin"], "language_level": ["good command"], "hard_skills": ["c language", "autocad"], "soft_skills": ["communication skills"], "languages_combined": [{"language": "english", "language_level": ["good command"]}, {"language": "mandarin", "language_level": ["good command"]}]}, "experience_required": {"duration": ["at least 2 years"], "field": ["product design"]}}, {"job_id": "100003009028418", "location_code": "hk", "company": "Clover Display Limited", "job_title": "Electronic Engineer", "description": "This is a fixed-term contract position of minimum 2 years with possibility for renewal subject to organization need and individual performance.\n\nResponsibilities:\n\n\u2022\u00a0\u00a0 \u00a0Providing technical assistance in the design management and site supervision of E&M works;\n\u2022\u00a0\u00a0 \u00a0Ensuring that the consultants/contractors' proposals and works are technically sound and safe;\n\u2022\u00a0\u00a0 \u00a0Undertaking interface/coordination related to E&M works;\n\u2022\u00a0\u00a0 \u00a0Review of statutory submission and technical reports;\u00a0\n\u2022\u00a0\u00a0 \u00a0Monitoring statutory submission of the consultants\u2019 design works; and\n\u2022\u00a0\u00a0 \u00a0Providing technical support to site supervision teams including responding to request for information and preparing design change documents.\n\nRequirements:\u00a0\u00a0 \u00a0\n\n\u2022\u00a0\u00a0 \u00a0Bachelor\u2019s degree in Electrical/Mechanical Engineering, Building Services or other related disciplines with at least 6 years\u2019 relevant experience, of which minimum of 3 years should be in project management role\n\u2022\u00a0\u00a0 \u00a0Member of HKIE or other equivalent professional bodies\n\u2022\u00a0\u00a0 \u00a0Experience in the management of infrastructure/building E&M system design, planning, construction and site supervisory works\n\u2022\u00a0\u00a0 \u00a0Experience in the design and construction supervision of airport E&M works is preferred\n\u2022\u00a0\u00a0 \u00a0Strong communication, analytical and negotiation skills\n\u2022\u00a0\u00a0 \u00a0Good command of spoken and written English and Chinese\n\u2022\u00a0\u00a0 \u00a0Proficient in MS Office applications and project management software tools\n\u2022\u00a0\u00a0 \u00a0Knowledge of Putonghua is an advantage\n\u00a0", "employment_types": ["Full Time"], "selling_points": ["Five-day work, bank holiday, free lunch", "Work in HK, not stated in PRC", "Medical insurance, Attractive Performance bonus"], "locations": ["Wong Tai Sin Area"], "categories": ["Manufacturing", "Production Planning / Control", "Merchandising & Purchasing", "Electronics"], "post_time": "2022-01-07T03:49:49Z", "salary": {"currency": null, "max": null, "min": null, "period": "monthly", "term": null}, "salary_visible": false, "title_keywords": ["electronic engineer"], "responsibilities": ["site supervision", "technical support", "review", "monitoring", "teams", "design", "reports", "coordination", "design management", "technical assistance"], "requirements": {"degrees": ["degree", "bachelor"], "majors": ["related disciplines", "project management", "building services", "mechanical engineering"], "languages": ["putonghua", "english", "chinese"], "language_level": ["advantage", "good command"], "hard_skills": ["project management", "system design", "hkie", "ms office"], "soft_skills": ["communication", "project management", "negotiation skills"], "languages_combined": [{"language": "putonghua", "language_level": ["advantage"]}, {"language": "english", "language_level": ["good command"]}, {"language": "chinese", "language_level": ["good command"]}]}, "experience_required": {"duration": ["at least 6 years", "minimum of 3 years"], "field": ["management", "supervisory", "e&m system", "engineering", "related", "infrastructure", "design", "project management", "building services", "relevant experience", "construction", "planning"]}}, {"job_id": "100003009022752", "location_code": "hk", "company": "Airport Authority Hong Kong", "job_title": "Project Engineer, Electrical & Mechanical", "description": "We are seeking a Product Developer / Designer to work out their Hong Kong office, ideally with prior experience in LED lighting and/or contemporary furniture, with a passion for innovative use of technology as well as executing financially orientated solutions within the rapidly growing lighting industry.\n\nResponsibilities & Skills\n\nCandidates should have a good understanding of how products are manufactured and assembled, ideally within the lighting and/or furniture industry. They should also have a grasp of three dimensional modelling software, ideally using Solidworks competently. Understanding of how a product can be developed into components which are optimized for mass production, producing technical drawings and liasing with suppliers to turn these into a commercial offering.\n\nIdeally a degree or relevant experience for at least 1-2 years in Product Design, with at least 1-2 years\u2019 experience already working in furniture and/or OEM lighting design and development.\u00a0 For applicants with less experience, we shall consider as a Junior Product Developer / Junior Designer.\u00a0\n\nClosely communicate with all parties, including the original designers, factory engineers, packaging suppliers, testing house engineers as well as our European buyers and development office in London.\n\nIntermediate knowledge of Adobe Photoshop and Illustrator is also a must for helping to produce artwork for instruction booklets and packaging when required.\n\nWilling and able to travel to Mainland China, and have a firm grasp of both verbal and written Chinese and English. Prior experience in merchandising and buying is a bonus and ideal candidates would benefit from having this prior knowledge, handling orders with buyers in Europe and vendors in mainland China.\n\nPersonality\n\nYou are hardworking, clear, concise when communicating to colleagues and are organized when handling the multiple tasks at hand. You are keen to utilize your design and development skill set to generate commercially competitive products within the lighting industry. You have prior knowledge and genuine interest in the contemporary Lighting design world and are looking to expand on this.\n\nApplication\n\nRelevant candidates will be interviewed continuously.\n\nSee www.hay.dk / www.andtradition.com for further details about who we are and what we do.", "employment_types": ["Full Time"], "selling_points": ["Degree holder in E&M / Building Services Eng", "Professional Qualification in E&M", "At least 6 years' relevant working experience"], "locations": ["Airport Area"], "categories": ["Engineering", "Electrical / Electronics", "Mechanical", "Merchandising & Purchasing", "Electronics"], "post_time": "2022-01-05T06:26:56Z", "salary": {"currency": null, "max": null, "min": null, "period": "monthly", "term": null}, "salary_visible": false, "title_keywords": ["project engineer"], "responsibilities": ["communicate with", "software", "merchandising", "design", "testing", "product design", "executing", "technical drawings", "booklets"], "requirements": {"degrees": ["degree"], "majors": ["design"], "languages": ["english", "chinese"], "language_level": [], "hard_skills": ["adobe photoshop", "solidworks", "illustrator"], "soft_skills": ["organized", "passion for", "multiple tasks", "keen", "genuine", "clear", "innovative", "hardworking", "ideal"], "languages_combined": [{"language": "english", "language_level": []}, {"language": "chinese", "language_level": []}]}, "experience_required": {"duration": ["at least 1-2 years"], "field": ["designer", "development", "merchandising", "design", "product design", "relevant experience", "developer"]}}, {"job_id": "100003009014578", "location_code": "hk", "company": "Nine United China Limited", "job_title": "Product Developer / Designer (Lighting) / Hong Kong", "description": "\u8077\u8cac\uff1a\u00a0\u00a0\u00a0\u00a0\u00a0\u00a0\u00a0\u00a0\u00a0\u00a0\u00a0\u00a0\u00a0\u00a0\u00a0\u00a0 \u2460\u63a8\u52d5\u570b\u5167\u53ca\u8d8a\u5357\u5de5\u5ee0\u63a1\u8cfc\u5de5\u4f5c\n\n\u00a0\u00a0\u00a0\u00a0\u00a0\u00a0\u00a0\u00a0\u00a0\u00a0\u00a0\u00a0\u00a0\u00a0\u00a0\u00a0\u00a0\u00a0\u00a0\u00a0\u00a0\u00a0\u00a0\u00a0\u00a0\u00a0\u00a0\u00a0\u00a0\u00a0 \u2461\u767c\u5c55\u53ca\u5236\u5b9a\u63a1\u8cfc\u7b56\u7565\u548c\u5efa\u8b70\n\n\u00a0\u00a0\u00a0\u00a0\u00a0\u00a0\u00a0\u00a0\u00a0\u00a0\u00a0\u00a0\u00a0\u00a0\u00a0\u00a0\u00a0\u00a0\u00a0\u00a0\u00a0\u00a0\u00a0\u00a0\u00a0\u00a0\u00a0\u00a0\u00a0\u00a0 \u2462\u512a\u5316\u63a1\u8cfc\u548c\u4f9b\u61c9\u5546\u8cea\u91cf\u548c\u6578\u91cf\n\n\u00a0\u00a0\u00a0\u00a0\u00a0\u00a0\u00a0\u00a0\u00a0\u00a0\u00a0\u00a0\u00a0\u00a0\u00a0\u00a0\u00a0\u00a0\u00a0\u00a0\u00a0\u00a0\u00a0\u00a0\u00a0\u00a0\u00a0\u00a0\u00a0\u00a0 \u2463\u5b9a\u671f\u6e96\u5099\u5206\u6790\u5831\u544a\u4e88\u7ba1\u7406\u5c64\n\n\u00a0\u00a0\u00a0\u00a0\u00a0\u00a0\u00a0\u00a0\u00a0\u00a0\u00a0\u00a0\u00a0\u00a0\u00a0\u00a0\u00a0\u00a0\u00a0\u00a0\u00a0\u00a0\u00a0\u00a0\u00a0\u00a0\u00a0\u00a0\u00a0\u00a0 \u2464\u8655\u7406\u516c\u53f8\u5176\u5b83\u59d4\u6d3e\u7684\u5de5\u4f5c\n\n\u00a0\u00a0\u00a0\u00a0\u00a0\u00a0\u00a0\u00a0\u00a0\u00a0\u00a0\u00a0\u00a0\u00a0\u00a0\u00a0\u00a0\u00a0\u00a0\u00a0\u00a0\u00a0\u00a0\u00a0\u00a0\u00a0\u00a0\u00a0\u00a0\u00a0 \u2465\u9577\u99d0\u60e0\u5dde\u5de5\u5ee0\uff0c\u6709\u9700\u8981\u6642\uff0c\u51fa\u5dee\u8d8a\u5357\n\n\u00a0\u00a0\u00a0\u00a0\u00a0\u00a0\u00a0\u00a0\u00a0\u00a0\u00a0\u00a0\u00a0\u00a0\u00a0\u00a0\u00a0\u00a0\u00a0\u00a0\u00a0\u00a0\u00a0\u00a0\u00a0\u00a0\u00a0\u00a0\u00a0\u00a0 \u2466\u5de5\u4f5c\u6c47\u62a5\u5bf9\u8c61\uff1a\u8425\u8fd0\u526f\u603b\n\n\u8cc7\u6b77\uff1a\u00a0\u00a0\u00a0\u00a0\u00a0\u00a0\u00a0\u00a0\u00a0\u00a0\u00a0\u00a0\u00a0\u00a0\u00a0\u00a0 \u2460\u5b78\u58eb\u5b78\u4f4d\uff0c5\u5e74\u6216\u4ee5\u4e0a\u76f8\u95dc\u5de5\u4f5c\u7d93\u9a57\n\n\u00a0\u00a0\u00a0\u00a0\u00a0\u00a0\u00a0\u00a0\u00a0\u00a0\u00a0\u00a0\u00a0\u00a0\u00a0\u00a0\u00a0\u00a0\u00a0\u00a0\u00a0\u00a0\u00a0\u00a0\u00a0\u00a0\u00a0\u00a0\u00a0\u00a0 \u2461\u7cb5\u8a9e\u3001\u666e\u901a\u8a71\u3001\u82f1\u8a9e\u826f\u597d\n\n\u00a0\u00a0\u00a0\u00a0\u00a0\u00a0\u00a0\u00a0\u00a0\u00a0\u00a0\u00a0\u00a0\u00a0\u00a0\u00a0\u00a0\u00a0\u00a0\u00a0\u00a0\u00a0\u00a0\u00a0\u00a0\u00a0\u00a0\u00a0\u00a0\u00a0 \u2462\u6709\u5c08\u696d\u4f9b\u61c9\u93c8\u7ba1\u7406\u6216\u76f8\u95dc\u5b78\u4f4d\u512a\u5148\n\n\u00a0\u00a0\u00a0\u00a0\u00a0\u00a0\u00a0\u00a0\u00a0\u00a0\u00a0\u00a0\u00a0\u00a0\u00a0\u00a0\u00a0\u00a0\u00a0\u00a0\u00a0\u00a0\u00a0\u00a0\u00a0\u00a0\u00a0\u00a0\u00a0\u00a0 \u2463\u64c1\u6709\u4f9b\u61c9\u93c8\u8cc7\u6e90\u66f4\u4f73\n\n\u00a0\u00a0\u00a0\u00a0\u00a0\u00a0\u00a0\u00a0\u00a0\u00a0\u00a0\u00a0\u00a0\u00a0\u00a0\u00a0\u00a0\u00a0\u00a0\u00a0\u00a0\u00a0\u00a0\u00a0\u00a0\u00a0\u00a0\u00a0\u00a0\u00a0 \u2464\u6709\u826f\u597d\u7684\u804c\u4e1a\u64cd\u5b88", "employment_types": ["Full Time"], "selling_points": [], "locations": ["Tsim Sha Tsui"], "categories": ["Merchandising & Purchasing", "Electronics"], "post_time": "2022-01-03T03:43:49Z", "salary": {"currency": null, "max": null, "min": null, "period": "monthly", "term": null}, "salary_visible": false, "title_keywords": ["product developer", "designer"], "responsibilities": [], "requirements": {"degrees": [], "majors": [], "languages": [], "language_level": [], "hard_skills": [], "soft_skills": [], "languages_combined": []}, "experience_required": {"duration": [], "field": []}}, {"job_id": "100003009020725", "location_code": "hk", "company": "Xintechnology Electronics Company Limited", "job_title": "Purchasing Manager \u63a1\u8cfc\u7d93\u7406", "description": "Job Duties:\n\nResponds to customer inquiries, expedites critical orders, communicates dispositions, researches and resolves issues, and researches orders\nCoordinate with internal and external customers\nDaily shipment coordination\nHandle system transactions\nPrepare shipping documentations, filing and reports\nTo follow up daily operation to comply with the KPI\nAny ad-hoc support upon requested\n\nJob Requirements:\n\n\nHigh School / Diploma or above\nOne year or above of related experience\nBasic computer, email, phone and communication skills\nMust be able to multi-task and work in a fast paced environment\nGood command of spoken and written in English, Cantonese and Mandarin\nWith SAP knowledge will be an advantage\n\nInterested parties please submit your application together with details CV (including salary history and expected salary) to the HR Department via\u00a0our career website (Click Here)\u00a0or by email at hkrecruitment @avnet.com. Please quote clearly the position your apply for in the email subject.\n\n\nAll applications will be treated in strict confidence and personal data provided with be used solely for recruitment purpose. Unsuccessful candidates may be considered for other vacancies. Applicants who are not contacted within one month should consider their applications filed for future reference. All unsuccessful applications will be destroyed within six months.", "employment_types": ["Full Time"], "selling_points": ["\u570b\u5167\u63d0\u4f9b\u5bbf\u820d\u53ca\u81b3\u98df", "\u5f80\u8fd4\u4ea4\u901a\u8cbb\u7528\uff0c", "\u5e74\u50477\u5929\uff0c\u96d9\u85aa\uff0c\u82b1\u7d05\uff0c\u91ab\u7642\u4fdd\u96aa\u7b49\u3002"], "locations": ["Others - China"], "categories": ["Merchandising & Purchasing", "Electronics", "Others", "Procurement / Purchasing / Sourcing"], "post_time": "2022-01-05T01:23:30Z", "salary": {"currency": "HKD", "max": 34999, "min": 30000, "period": "monthly", "term": null}, "salary_visible": true, "title_keywords": ["purchasing manager"], "responsibilities": ["ad-hoc", "internal and external customers", "shipping", "customer inquiries", "coordinate with", "daily operation", "transactions", "reports", "coordination"], "requirements": {"degrees": ["diploma or above", "high school"], "majors": [], "languages": ["cantonese", "english", "mandarin"], "language_level": ["good command"], "hard_skills": ["basic", "sap"], "soft_skills": ["communication skills", "multi-task", "work in a fast paced environment"], "languages_combined": [{"language": "cantonese", "language_level": ["good command"]}, {"language": "english", "language_level": ["good command"]}, {"language": "mandarin", "language_level": ["good command"]}]}, "experience_required": {"duration": ["one year"], "field": ["related"]}}, {"job_id": "100003009016051", "location_code": "hk", "company": "Avnet Technology Hong Kong Limited", "job_title": "Customer Service Representative", "description": "Job Title: Merchandiser - Lighting\n\nIn order to cope with our expanding business we are looking for below candidate to strengthen our team:\n\nThe Merchandiser is able to handle pre-defined tasks under the supervision of the Senior Merchandisers. The job duties include (but are not limited to):\n\nContact and follow up with factories about ongoing projects\nLiaise with customers about ongoing orders\nMonitor and take measures to keep tight deadlines\nData input and order processing in the ERP system\nUpdating order status lists\nAttend meetings with factories\nFollow further tasks given by the Senior Merchandisers or Department Head\n\nRequirements:\n\nWorking experience as Merchandiser of 2-3 years\nExperience in Lighting industry\nExperience in dealing with Chinese factories\nExperience in liaising with buying offices\nExperience with order processing in ERP systems\nReliable and detailed working attitude\nLanguage skills (in order of importance) - fluent in English, Mandarin, Cantonese\nMS Office proficiency\n\nWe offer competitive salary, performance bonus, 5-day work, medical insurance, double pay.\u00a0\u00a0Interested party, please send CV with\u00a0expected salary by\u00a0clicking the APPLY NOW button", "employment_types": ["Full Time", "Permanent"], "selling_points": ["Double Pay, Discretionary Incentive (Quarterly)", "Good command of spoken Eng., Mandarin & Cantonese", "1 year experience in customer service"], "locations": ["Tsuen Wan Area"], "categories": ["Sales, CS & Business Devpt", "Customer Service - Supervisor / Officer", "Transportation & Logistics", "Inventory / Warehousing", "Merchandising & Purchasing", "Electronics"], "post_time": "2022-01-03T08:17:16Z", "salary": {"currency": null, "max": null, "min": null, "period": "monthly", "term": null}, "salary_visible": false, "title_keywords": ["customer service representative"], "responsibilities": ["systems", "monitor", "data input", "liaising with", "contact", "order processing", "attend meetings", "liaise with"], "requirements": {"degrees": [], "majors": [], "languages": ["cantonese", "english", "chinese", "mandarin"], "language_level": ["fluent"], "hard_skills": ["erp systems", "erp system", "order processing", "ms office"], "soft_skills": ["reliable", "detailed"], "languages_combined": [{"language": "cantonese", "language_level": []}, {"language": "english", "language_level": ["fluent"]}, {"language": "chinese", "language_level": []}, {"language": "mandarin", "language_level": ["fluent"]}]}, "experience_required": {"duration": ["of 2-3 years"], "field": ["buying offices", "order processing"]}}, {"job_id": "100003009012597", "location_code": "hk", "company": "Light Tec Limited", "job_title": "Merchandiser - Lighting", "description": "Job Description\n\nSourcing new products globally for consumer Audio products\nLiaise and negotiate with vendors\nDevelop and maintain good relationship with vendors and channel partners\nFacilitate marketing strategy deployments\nForecast and analyse market and product trends\nIdentify New Business Opportunities\nAble to pitch value proposition of initiatives to both resellers and end users\nResponsible in managing assigned product portfolio and drive new sales to achieve Revenue and GP targets\nBusiness and Revenue Forecast, including periodic reviews with relevant product vendors on business and sales activities\nTravel to China and abroad is required\n\nRequirements\n\nDegree holder, preferably in business, marketing, sales management\n2 years or above experience in sales, marketing or sourcing\nAble to work independently and under pressure\nExcellent negotiation skill and business sense\nExcellent in written and spoken English and\u00a0Mandarin\nCandidate with less experience will be considered as Assistant Product Manager", "employment_types": ["Full Time", "Permanent"], "selling_points": [], "locations": ["Ngau Tau Kok"], "categories": ["Merchandising & Purchasing", "Electronics", "Others", "Procurement / Purchasing / Sourcing"], "post_time": "2022-01-01T06:00:46Z", "salary": {"currency": null, "max": null, "min": null, "period": "monthly", "term": null}, "salary_visible": false, "title_keywords": ["merchandiser"], "responsibilities": ["liaise", "sales activities", "business opportunities", "maintain good relationship", "develop", "forecast", "audio", "analyse"], "requirements": {"degrees": ["degree holder"], "majors": ["business", "marketing"], "languages": ["english", "mandarin"], "language_level": ["excellent"], "hard_skills": [], "soft_skills": ["negotiation skill", "work independently", "under pressure", "business sense"], "languages_combined": [{"language": "english", "language_level": ["excellent"]}, {"language": "mandarin", "language_level": ["excellent"]}]}, "experience_required": {"duration": ["2 years"], "field": ["marketing"]}}, {"job_id": "100003009012022", "location_code": "hk", "company": "ECT Eichi Technology International Limited", "job_title": "Product Manager (5 days Work / Medical Insurance / Education Allowance/ Staff discount )", "description": "Our clients, an MNC manufacturing company, is now seeking for a high caliber individual to join their team as Sales.\n\n\nJob duties:\n\n- B2B Sales activity (Maintain good relationship with existing clients and develop new clients)\n- Communicate and coordinate with other department\n- Follow up order, delivery, payment etc.\n\nDesired Skills & Abilities:\n\n- 1 year sales experience (Fresh graduate are welcome)\n- Degree holder in any disciplines\n- Good comment in Japanese, English and Mandarin\n\n\n\nInterested parties please send your application via email to\u00a0Apply Now\u00a0or\u00a0riku_luk\u00a0@persolhk.com.\u00a0For any inquiries, please do not hesitate to contact me at\u00a0(852) 2971-2542.\n\nPlease note that only short-listed candidate will be notified.\n\nWe also have various job vacancies from our well-established clients in all kinds of fields, please feel free to contact us. We are always willing to give you support on your career development.\n\nOur company website:\u00a0http://www.persolhk.com\n\nAll information received will be treated in strict confidence and used for recruitment purpose only.", "employment_types": ["Full Time"], "selling_points": [], "locations": ["Lai Chi Kok"], "categories": ["Merchandising & Purchasing", "Electronics", "Procurement / Purchasing / Sourcing", "Sales, CS & Business Devpt", "Sales - Sales Management"], "post_time": "2022-01-02T22:54:13Z", "salary": {"currency": null, "max": null, "min": null, "period": "monthly", "term": null}, "salary_visible": false, "title_keywords": ["product manager", "staff"], "responsibilities": ["develop", "payment", "coordinate with", "maintain good relationship"], "requirements": {"degrees": ["fresh graduate", "degree holder"], "majors": ["any disciplines"], "languages": ["japanese", "english", "mandarin"], "language_level": ["good"], "hard_skills": [], "soft_skills": [], "languages_combined": [{"language": "japanese", "language_level": ["good"]}, {"language": "english", "language_level": ["good"]}, {"language": "mandarin", "language_level": ["good"]}]}, "experience_required": {"duration": ["1 year"], "field": []}}, {"job_id": "100003009020328", "location_code": "hk", "company": "PERSOL Hong Kong", "job_title": "Sales (Urgent!! / Japanese-Speaking / Fresh Graduate Welcome)", "description": "Logistic Cost Manager\n\nGlobal Buying office\nReport to Director and VP\nBase in Macau, Macau ID is a MUST\nWelcome logistic sales\n\nRequirement:\n\nOcean Freight bidding negotiation with service provides for shipment to US and EU\nCost analysis and update market update\nProvide the monthly freight report and full freight cost spending\nProvide proposal and suggestion to the director\nValidate freight invoices on a monthly basis\n\nRequirement:\n\nBachelor's degree in logistics/operation/supply chain\nAt least 5 years sales and business development working experience in freighting forwarding company\nGood negotiation skills and hands-on personality\nExcellent command in both spoken and written English and Chinese", "employment_types": ["Full Time", "Permanent"], "selling_points": ["MNC Electronic Company", "B2B sales, maintain and develop new clients", "Good Package / AL 15day / Transportation allowance"], "locations": ["Causeway Bay"], "categories": ["Sales, CS & Business Devpt", "Business Development", "Merchandising & Purchasing", "Electronics", "Account Servicing"], "post_time": "2022-01-04T10:56:27Z", "salary": {"currency": null, "max": null, "min": null, "period": "monthly", "term": null}, "salary_visible": false, "title_keywords": ["sales"], "responsibilities": ["cost", "invoices", "logistics", "cost analysis", "report"], "requirements": {"degrees": ["degree", "bachelor"], "majors": [], "languages": ["english", "chinese"], "language_level": ["excellent"], "hard_skills": ["id", "analysis"], "soft_skills": ["negotiation skills", "negotiation", "hands-on"], "languages_combined": [{"language": "english", "language_level": ["excellent"]}, {"language": "chinese", "language_level": ["excellent"]}]}, "experience_required": {"duration": ["at least 5 years"], "field": ["business development"]}}, {"job_id": "100003009014145", "location_code": "hk", "company": "ConnectedGroup Limited", "job_title": "Logistic Cost Manager - Macau ID MUST", "description": "Major Responsibilities:\n\n\u00a0 Perform the full spectrum of logistics and procurement function\n\u00a0 Liaise with vendors, shipping company and internal team to arrange shipment\n\u00a0 Responsible for handling import/export documents, shipment and logistics arrangement\n\u00a0 Coordinate with suppliers for quotation and price negotiation\n\u00a0 Liaise with overseas and local suppliers on all aspects of purchasing\n\u00a0 Communicate with Sales Department to source and develop new products\n\u00a0 Implement and review the procurement process, records of purchasing orders and stock management, etc.\n\nBasic Requirements:\n\n\u00a0 Hold a non-degree tertiary qualification or with over 2 years of relevant working experience,\n\u00a0 Experience in procurement of electronic components is preferred\n\u00a0 Good communication and negotiation skills, details oriented, willing to learn with positive attitude, and sense of responsibility\n\u00a0 Business communication of written and spoken Cantonese/English as well as for Putonghua a plus\n\u00a0 Understanding Dynamic Accounting System and ERP System\n\u00a0 Good interpersonal and organization skills and a proactive attitude\n\u00a0 Travel to China may be needed\n\n\nInterested parties, please visit our website at www.audio-technica.com.hk and send your resume with expected salary to our email address.\u00a0", "employment_types": ["Full Time", "Permanent"], "selling_points": ["Global Company", "Reporting to the Director", "Negotiation, Pricing"], "locations": ["Not Specified"], "categories": ["Transportation & Logistics", "Freight Forwarding", "Merchandising & Purchasing", "Electronics", "Sales, CS & Business Devpt", "Account Servicing"], "post_time": "2022-01-03T03:04:54Z", "salary": {"currency": "HKD", "max": 34999, "min": 30000, "period": "monthly", "term": null}, "salary_visible": true, "title_keywords": ["manager"], "responsibilities": ["communicate with", "price negotiation", "shipping", "stock management", "logistics arrangement", "quotation", "coordinate with", "review", "develop", "logistics", "liaise with"], "requirements": {"degrees": ["degree"], "majors": [], "languages": ["cantonese", "putonghua", "english"], "language_level": [], "hard_skills": ["plus", "basic", "erp system", "dynamic", "accounting system"], "soft_skills": ["sense of responsibility", "willing to learn", "communication", "positive attitude", "negotiation skills", "dynamic", "organization skills", "proactive", "interpersonal"], "languages_combined": [{"language": "cantonese", "language_level": []}, {"language": "putonghua", "language_level": []}, {"language": "english", "language_level": []}]}, "experience_required": {"duration": ["2 years"], "field": ["procurement", "relevant working experience"]}}, {"job_id": "100003009011632", "location_code": "hk", "company": "Audio - Technica (Greater China) Limited", "job_title": "Logistics and Procurement Officer", "description": "To cope with our fast expansion, we are looking for suitable candidates to join our\u00a0 Operations team.\u00a0\n\nResponsibilities\u00a0\n\nCommunicate with overseas customers on orders arrangement and scheduling\nResponsible for handling customers\u2019 enquiries and providing appropriate follow-up\nWarehouse management, stock in/out, inventory check and shipment\nPrepare sales documents and sales reports and maintain proper sales transactions & database in the system\nBuild and maintain a strong and trustworthy relationship with new and existing customers, manage assigned accounts in a professional manner, and identify up/cross-selling opportunities to grow profits per assigned sales KPI\nMaintain and update sales database, filing system and sales demo\nCoordinate logistic operation on order status and handle import and export document\nPerform other ad-hoc duties assigned by management from time to time\nRequirements\u00a0\n\nForm 7 or above\n2 years of sales coordinator experience\nWith Import/Export shipping experience is preferred\nPrevious experience in multinational trading\nPC skills in MS Excel, Word, and Chinese word processing\nGood communication of English and Mandarin\nMature, well-organized, self-motivated,\u00a0energetic with good interpersonal skills\nAble to work independently and under pressure\nFlexible in working hours may be needed in line with business requirements\nWe offer 5-day work, an attractive remuneration package to the successful candidate. Salary will be commensurate with qualifications and experience. Interested parties please send a detailed resume to our\u00a0Human Resources Department\u00a0by clicking here\u00a0Apply Now\u00a0button.\n\n\nWe are an equal opportunity employer. All information collected will be considered strictly confidential and will be used for recruitment purposes only.", "employment_types": ["Full Time", "Permanent", "Contract"], "selling_points": ["Procurement, Purchasing", "Logistics, I/E, Stock Management", "Dynamic System, ERP"], "locations": ["Hung Hom"], "categories": ["Transportation & Logistics", "Inventory / Warehousing", "Shipping", "Merchandising & Purchasing", "Electronics"], "post_time": "2021-12-31T07:59:55Z", "salary": {"currency": null, "max": null, "min": null, "period": "monthly", "term": null}, "salary_visible": false, "title_keywords": ["procurement officer", "logistics"], "responsibilities": ["communicate with", "management", "sales reports", "inventory check", "prepare sales", "professional manner", "transactions", "coordinate", "scheduling", "maintain", "database", "ad-hoc duties"], "requirements": {"degrees": [], "majors": [], "languages": ["english", "chinese", "mandarin"], "language_level": ["good"], "hard_skills": ["ms excel", "pc skills", "chinese word processing", "word"], "soft_skills": ["flexible", "self-motivated", "work independently", "under pressure", "well-organized", "mature", "communication", "interpersonal skills", "energetic"], "languages_combined": [{"language": "english", "language_level": ["good"]}, {"language": "chinese", "language_level": []}, {"language": "mandarin", "language_level": ["good"]}]}, "experience_required": {"duration": ["2 years"], "field": ["trading"]}}, {"job_id": "100003009018664", "location_code": "hk", "company": "Aurabeat Technology Limited", "job_title": "Customer Service & Operations Officer", "description": "Job Description:\n\nTo source and develop right products for our overseas buyers.\nTo find and develop new and potential suppliers.\nFollow up product sourcing process, including sampling & price negotiations\nWork closely with regional vendors, buyers & maintain strong relationship\nMonitor suppliers' performances\nManage quotations, documents & costing\nMust be very knowledgeable and hands on experience in\u00a0Small Domestic Appliances/ Consumer Electronics\n\nGeneral Requirements:\n\nDegree/Diploma holder in relevant disciplines\nGood command of spoken and written English, Mandarin and Cantonese.\nGood communication, interpersonal and negotiation skills.\nSelf-motivated, proactive and independent.\nHard working and able to work under pressure.\nWilling to travel to China.\nCandidate with less experience will be considered as Assistant Merchandiser.\nFresh graduates are welcome.", "employment_types": ["Full Time", "Permanent"], "selling_points": ["Operations & Administration Support", "Dynamic & Start-up working environment", "Career development Opportunities"], "locations": ["Tsuen Wan Area"], "categories": ["Sales, CS & Business Devpt", "Customer Service - Supervisor / Officer", "Transportation & Logistics", "Inventory / Warehousing", "Merchandising & Purchasing", "Electronics"], "post_time": "2022-01-04T04:17:19Z", "salary": {"currency": null, "max": null, "min": null, "period": "monthly", "term": null}, "salary_visible": false, "title_keywords": ["operations officer", "customer service"], "responsibilities": ["maintain", "monitor", "develop"], "requirements": {"degrees": ["diploma holder", "degree"], "majors": [], "languages": ["cantonese", "english", "mandarin"], "language_level": ["good command"], "hard_skills": [], "soft_skills": ["self-motivated", "independent", "hard working", "communication", "negotiation skills", "proactive", "interpersonal", "work under pressure"], "languages_combined": [{"language": "cantonese", "language_level": ["good command"]}, {"language": "english", "language_level": ["good command"]}, {"language": "mandarin", "language_level": ["good command"]}]}, "experience_required": {"duration": [], "field": []}}, {"job_id": "100003009012828", "location_code": "hk", "company": "e-Bench Limited", "job_title": "Merchandiser/ Assist. Merchandiser \u2013 Small Domestic Appliances/ Consumer Electronics (5 day work)", "description": "Responsibilities:\n\n\nMaintain the purchase database.\nDevelop and manage buying and selling plan to cope with company strategies and market sales trends.\nOrganized sales target, detail-minded and able to work independently in a fast-paced\u00a0environment.\nFollow up and issue purchase orders and arrange delivery schedule.\nAssist to ad-hoc tasks as assigned.\nCandidate with more experience will be considered as Buyer /Merchandiser\nQualification:\n\n\nBachelor degree with at least 2-3 years relevant experience in FMCG industry, preferably in Electronics.\nSkillful in computer (MS Word, Excel, PowerPointetc).\nFluent in Cantonese, English, Mandarin.\u00a0\nStrong business acumen with excellent negotiation and analytical skills.\u00a0\u00a0\nStrong communication & problem solving skills.\u00a0 \u00a0\u00a0\nReady to learn new things and willing to work under pressure and tight timeline.\nImmediately available is preferred\n\nRemark:\n\nWe offer attractive remuneration package including meal allowance, medical benefits and year-end bonus. Applicants please\u00a0send your full resume with expected salary to recruitment e-mail.\n\n\nInformation collected will be kept confidential and to be used for recruitment purpose.", "employment_types": ["Full Time", "Permanent"], "selling_points": [], "locations": ["Kwun Tong"], "categories": ["Merchandising & Purchasing", "Electronics", "Others", "Procurement / Purchasing / Sourcing"], "post_time": "2022-01-02T09:31:00Z", "salary": {"currency": null, "max": null, "min": null, "period": "monthly", "term": null}, "salary_visible": false, "title_keywords": ["merchandiser"], "responsibilities": ["sales target", "ad-hoc tasks", "develop", "delivery schedule", "communication", "purchase", "maintain", "plan", "database", "work under pressure"], "requirements": {"degrees": ["degree", "bachelor"], "majors": [], "languages": ["cantonese", "english", "mandarin"], "language_level": ["fluent"], "hard_skills": ["excel", "ms word", "fmcg industry", "analytical skills", "problem solving skills", "acumen"], "soft_skills": ["detail-minded", "organized", "work independently", "negotiation", "fast-paced environment", "analytical skills", "communication", "business acumen", "problem solving skills", "work under pressure"], "languages_combined": [{"language": "cantonese", "language_level": ["fluent"]}, {"language": "english", "language_level": []}, {"language": "mandarin", "language_level": []}]}, "experience_required": {"duration": ["at least 2-3 years"], "field": ["fmcg", "relevant experience"]}}, {"job_id": "100003009011114", "location_code": "hk", "company": "HongKong Suning.com Co., Limited", "job_title": "Buyer / Assistant Buyer", "description": "Merchandiser (Mainly US)\n\nBranford Limited is an international children\u2019s toy company and we are currently looking for a talented and motivated Merchandiser to cope with the growth of the company.\n\n\nRequirements:\n\nF. 7 level / HKDSE (Grade 4+ in English or Mathematics) or above\nMinimum 3 years merchandising and production planning experience\nProficient in Microsoft Word and Excel\nAdvanced Excel skills (Lookup, Pivot table)\nWell spoken and written English, fluent Putonghua as well as Cantonese\nSelf-motivated, able to work independently and follow through on required tasks\nDetail Oriented\nGood team player and good interpersonal skills\nStrong sense of responsibility\n\nResponsibilities:\u00a0\n\nWork closely with internal sales team in forecast planning\nMonitor inventory level and replenishment status in a timely basis\nIssue orders and follow up production with suppliers\nHandle customer\u2019s enquiries\nCoordinate with internal logistic team on delivery arrangement\nAssist in general office work and ad hoc tasks as required.\n\n\u00a0Benefits:\n\n5-days work week\n13th month salary\nMedical and detail coverage\n\nPlease feel free to visit our current Web Sites: ogdolls.com, myglittergirls.com, woodzeez.com, terrauniverse.com, mybtoys.com and battatco.com.\n\nPlease apply with full resume and expected salary though applies now.\n\nPersonal data collected will be used for recruitment purpose only.", "employment_types": ["Full Time"], "selling_points": ["Develop and manage buying and selling plan", "Follow up and issue purchase orders", "Immediately available is preferred"], "locations": ["Kwun Tong"], "categories": ["Merchandising & Purchasing", "Electronics", "Others"], "post_time": "2022-01-02T22:54:09Z", "salary": {"currency": null, "max": null, "min": null, "period": "monthly", "term": null}, "salary_visible": false, "title_keywords": ["assistant"], "responsibilities": ["inventory", "monitor", "replenishment", "coordinate with", "ad hoc tasks", "sales team", "forecast", "planning"], "requirements": {"degrees": ["hkdse"], "majors": ["mathematics"], "languages": ["cantonese", "putonghua", "english"], "language_level": ["fluent"], "hard_skills": ["excel", "pivot table", "microsoft word"], "soft_skills": ["self-motivated", "good team player", "work independently", "advanced", "sense of responsibility", "detail oriented", "interpersonal skills"], "languages_combined": [{"language": "cantonese", "language_level": ["fluent"]}, {"language": "putonghua", "language_level": ["fluent"]}, {"language": "english", "language_level": ["fluent"]}]}, "experience_required": {"duration": ["minimum 3 years"], "field": ["merchandising", "planning"]}}, {"job_id": "100003009014425", "location_code": "hk", "company": "Branford Limited", "job_title": "Merchandiser - Mainly US (13th month salary)", "description": "Responsibilities:\u00a0\n\nLead purchasing activities\u00a0for the mechanical component(s) (e.g. plastic, metal. grass etc.)of consumer electronic products \u00a0(Lighting / Audio / IOT products), to support the in-house manufacturing production\u00a0\nAssess/Evaluate potential suppliers from the perspective of (including but not limited to) Pricing, Quality, Capability, & Reliability\nConduct cost analysis to manage/monitor purchasing cost\nParticipate\u00a0new product development project with Sales Team, R&D Team\u00a0 & Operations Team\n\nRequirement:\n\nDegree Holder or above in any related disciplines\nAt least 8 years of relevant experience in Purchasing/Sourcing Field\nExperience in sourcing mechanical component is a must\nStrong Interpersonal and Communication skills\nEthical & Integrity\nGood Command of English , Cantonese & Mandarin\nStation at Mainland China is required (Dongguan Factory)\n\nWe offer an attractive remuneration package including 5-day work, competitive salary, double pay, bonus and medical insurance to the right candidate.\u00a0 Interested parties please send full resume with date of availability, current and expected salary via clicking 'Apply Now'.\n\n(All applications will be treated in strict confidence and used solely for recruitment purpose)", "employment_types": ["Permanent"], "selling_points": [], "locations": ["Tsim Sha Tsui"], "categories": ["Merchandising & Purchasing", "Electronics", "Toy", "Others"], "post_time": "2022-01-03T03:25:05Z", "salary": {"currency": null, "max": null, "min": null, "period": "monthly", "term": null}, "salary_visible": false, "title_keywords": ["merchandiser"], "responsibilities": ["cost", "operations", "monitor", "quality", "evaluate", "sales team", "cost analysis", "audio"], "requirements": {"degrees": ["degree holder"], "majors": ["related disciplines"], "languages": ["cantonese", "english", "mandarin"], "language_level": ["good command"], "hard_skills": [], "soft_skills": ["communication skills", "ethical", "integrity", "interpersonal"], "languages_combined": [{"language": "cantonese", "language_level": ["good command"]}, {"language": "english", "language_level": ["good command"]}, {"language": "mandarin", "language_level": ["good command"]}]}, "experience_required": {"duration": ["at least 8 years"], "field": ["purchasing", "relevant experience"]}}, {"job_id": "100003009008969", "location_code": "hk", "company": "Kee Tat Manufactory Holdings Limited", "job_title": "Assistant Purchasing Manager", "description": "Merchandiser (International)\n\nBranford Limited is an international children\u2019s toy company and we are currently looking for a talented and motivated Merchandiser to cope with the growth of the company.\n\nRequirements:\u00a0\n\n\u00a0\u00a0\u00a0\u00a0\u00a0\u00a0\u00a0 F. 7 level / HKDSE (Grade 4+ in English or Mathematics) or above\n\u00a0\u00a0\u00a0\u00a0\u00a0\u00a0\u00a0 Minimum 3 years merchandising experience\n\u00a0\u00a0\u00a0\u00a0\u00a0\u00a0\u00a0 Handle full set I/E documents and experience in ERP system is an asset\n\u00a0\u00a0\u00a0\u00a0\u00a0\u00a0\u00a0 Proficient in Microsoft Word and Excel\n\u00a0\u00a0\u00a0\u00a0\u00a0\u00a0\u00a0 Well spoken and written English, fluent Putonghua as well as Cantonese\n\u00a0\u00a0\u00a0\u00a0\u00a0\u00a0\u00a0 Self-motivated, able to work independently and follow through on required tasks\n\u00a0\u00a0\u00a0\u00a0\u00a0\u00a0\u00a0 Detail Oriented\n\u00a0\u00a0\u00a0\u00a0\u00a0\u00a0\u00a0 Good team player and good interpersonal skills\n\u00a0\u00a0\u00a0\u00a0\u00a0\u00a0\u00a0 Strong sense of responsibility\n\n\u00a0Responsibilities:\u00a0\n\n\u00a0\u00a0\u00a0\u00a0\u00a0\u00a0\u00a0 Issue orders and follow up production with suppliers\n\u00a0\u00a0\u00a0\u00a0\u00a0\u00a0\u00a0 Handle customer\u2019s enquiries\n\u00a0\u00a0\u00a0\u00a0\u00a0\u00a0\u00a0 Coordinate with suppliers and forwarders on delivery arrangement\n\u00a0\u00a0\u00a0\u00a0\u00a0\u00a0\u00a0 Prepare booking, issue invoice and packing list as well as export documents\n\u00a0\u00a0\u00a0\u00a0\u00a0\u00a0\u00a0 Follow up customer payment\n\u00a0\u00a0\u00a0\u00a0\u00a0\u00a0\u00a0 Assist in general office work and ad hoc tasks as required.\n\nBenefits:\n\n5-days work week\n13th month salary\nMedical and detail coverage\n\nPlease feel free to visit our current Web Sites: ogdolls.com, myglittergirls.com, woodzeez.com, terrauniverse.com, mybtoys.com and battatco.com.\n\nPlease apply with full resume and expected salary though applies now.\n\nPersonal data collected will be used for recruitment purpose only.", "employment_types": ["Full Time", "Permanent"], "selling_points": ["Purchasing / Supplier Management", "Mechanical Parts", "Stay @ Mainland Factory"], "locations": ["Ngau Tau Kok"], "categories": ["Merchandising & Purchasing", "Electronics", "Others", "Procurement / Purchasing / Sourcing"], "post_time": "2021-12-30T09:44:19Z", "salary": {"currency": null, "max": null, "min": null, "period": "monthly", "term": null}, "salary_visible": false, "title_keywords": ["purchasing manager", "assistant"], "responsibilities": ["invoice", "coordinate with", "ad hoc tasks", "packing list", "payment", "booking"], "requirements": {"degrees": ["hkdse"], "majors": ["mathematics"], "languages": ["cantonese", "putonghua", "english"], "language_level": ["fluent"], "hard_skills": ["excel", "erp system", "microsoft word"], "soft_skills": ["self-motivated", "work independently", "good team player", "sense of responsibility", "detail oriented", "interpersonal skills"], "languages_combined": [{"language": "cantonese", "language_level": ["fluent"]}, {"language": "putonghua", "language_level": ["fluent"]}, {"language": "english", "language_level": ["fluent"]}]}, "experience_required": {"duration": ["minimum 3 years"], "field": ["erp system", "merchandising"]}}, {"job_id": "100003009014557", "location_code": "hk", "company": "Branford Limited", "job_title": "Merchandiser - International (13th month salary)", "description": "Job Description:\n\nTo source and develop right products for our overseas buyers.\nTo find and develop new and potential suppliers.\nFollow up product sourcing process, including sampling & price negotiations\nWork closely with regional vendors, buyers & maintain strong relationship\nMonitor suppliers' performances\nManage quotations, documents & costing\nMust be very knowledgeable and hands on experience in\u00a0Small Domestic Appliances/ Consumer Electronics\n\nGeneral Requirements:\n\nDegree/Diploma holder in relevant disciplines\nGood command of spoken and written English, Mandarin and Cantonese.\nGood communication, interpersonal and negotiation skills.\nSelf-motivated, proactive and independent.\nHard working and able to work under pressure.\nWilling to travel to China.\nCandidate with less experience will be considered as Assistant Merchandiser.\nFresh graduates are welcome.", "employment_types": ["Permanent"], "selling_points": [], "locations": ["Tsim Sha Tsui"], "categories": ["Merchandising & Purchasing", "Electronics", "Toy", "Others"], "post_time": "2022-01-03T03:40:15Z", "salary": {"currency": null, "max": null, "min": null, "period": "monthly", "term": null}, "salary_visible": false, "title_keywords": ["merchandiser"], "responsibilities": ["maintain", "monitor", "develop"], "requirements": {"degrees": ["diploma holder", "degree"], "majors": [], "languages": ["cantonese", "english", "mandarin"], "language_level": ["good command"], "hard_skills": [], "soft_skills": ["self-motivated", "independent", "hard working", "communication", "negotiation skills", "proactive", "interpersonal", "work under pressure"], "languages_combined": [{"language": "cantonese", "language_level": ["good command"]}, {"language": "english", "language_level": ["good command"]}, {"language": "mandarin", "language_level": ["good command"]}]}, "experience_required": {"duration": [], "field": []}}, {"job_id": "100003009012652", "location_code": "hk", "company": "The Station Company Limited", "job_title": "Sourcing Executive - Small Appliance (5 day work week)", "description": "Responsibilities\n\n\nIssue purchase orders to suppliers.\nEnsure right cost source is selected to issue purchase orders.\nHandle changes in suppliers delivery schedules.\nGenerates and/or approves purchase order while maintaining inventory within company goals.\nHandle sales request for quotation (RFQ).\nCoordinate with sales team to do the order planning to match with customer request delivery.\nEnsures on-time delivery to customers from suppliers in proactive manner.\nExhausts all possibilities in obtaining product to satisfy critical customer requirements.\nExpands personal product knowledge to effectively support sales.\nPurchase inventory to achieve maximum quantities at lowest possible cost.\nEnsures integrity of system information, including cost, resale and packaging.\nReview and approves requests for new part numbers to be added to system.\n\nRequirements\n\n\nDiploma Degree in Electronics Engineer or related field.\nMinimum 2 years' related experience in Electronics Components, preferred on Passive Components.\nTeam player and willing to communicate with all levels.\nGood attitude, diligent, attention to the details and willing to learn.\nAble to multi-task and work under pressure in a fast-paced environment.\nFluency in spoken English and Chinese (in order to liaise with Mandarin speaking Associates).\nProficient in MS Office Applications.", "employment_types": ["Full Time", "Permanent"], "selling_points": [], "locations": ["Kwun Tong"], "categories": ["Merchandising & Purchasing", "Electronics", "Home Appliances", "Others"], "post_time": "2022-01-01T10:05:19Z", "salary": {"currency": null, "max": null, "min": null, "period": "monthly", "term": null}, "salary_visible": false, "title_keywords": ["sourcing executive"], "responsibilities": ["cost", "maintaining", "schedules", "inventory", "quotation", "coordinate with", "review", "purchase", "sales team", "planning"], "requirements": {"degrees": ["diploma", "degree"], "majors": [], "languages": ["english", "chinese", "mandarin"], "language_level": ["fluency"], "hard_skills": ["ms office"], "soft_skills": ["multi-task", "fast-paced environment", "willing to learn", "diligent", "team player", "work under pressure"], "languages_combined": [{"language": "english", "language_level": ["fluency"]}, {"language": "chinese", "language_level": ["fluency"]}, {"language": "mandarin", "language_level": ["fluency"]}]}, "experience_required": {"duration": ["minimum 2 years"], "field": ["related"]}}, {"job_id": "100003009010455", "location_code": "hk", "company": "TTI Hong Kong Limited", "job_title": "Product Specialist", "description": "Shipping Clerk\n\nBranford Limited is an international children\u2019s toy company and we are currently looking for a talented and motivated Shipping Clerk to cope with the growth of the company.\n\nRequirements:\n\n\u00a0 \u00a0 \u00a0 \u00a0 F. 5 level / HKDSE (Grade 3+ in English or Mathematics) or above\n\u00a0\u00a0\u00a0\u00a0\u00a0\u00a0\u00a0 Minimum 3 years logistic experience\n\u00a0\u00a0\u00a0\u00a0\u00a0\u00a0\u00a0 Handle full set I/E documents and experience in ERP system is an asset\n\u00a0\u00a0\u00a0\u00a0\u00a0\u00a0\u00a0 Proficient in Microsoft Word and Excel\n\u00a0\u00a0\u00a0\u00a0\u00a0\u00a0\u00a0 Good command of English and fluent Putonghua as well as Cantonese\n\u00a0\u00a0\u00a0\u00a0\u00a0\u00a0\u00a0 Self-motivated, able to work independently and follow through on required tasks\n\u00a0\u00a0\u00a0\u00a0\u00a0\u00a0\u00a0 Good team player and good interpersonal skills\n\u00a0\u00a0\u00a0\u00a0\u00a0\u00a0\u00a0 Strong sense of responsibility\n\n\u00a0Responsibilities:\n\n\u00a0 \u00a0 \u00a0 \u00a0 Work closely with internal merchandising team and suppliers\n\u00a0\u00a0\u00a0\u00a0\u00a0\u00a0\u00a0 Coordinate and follow up delivery arrangement with forwarders and suppliers\n\u00a0\u00a0\u00a0\u00a0\u00a0\u00a0\u00a0 Handle booking, export documents and customer payment\n\u00a0\u00a0\u00a0\u00a0\u00a0\u00a0\u00a0 Assist in general office work and ad hoc tasks as required.\n\n\u00a0Benefits:\n\n\u00a0 \u00a0 \u00a0 \u00a05-days work week\n\u00a0 \u00a0 \u00a0 13th month salary\n\u00a0 \u00a0 \u00a0 Medical and detail coverage\n\nPlease feel free to visit our current Web Sites: ogdolls.com, myglittergirls.com, woodzeez.com, terrauniverse.com, mybtoys.com and battatco.com.\n\nPlease apply with full resume and expected salary though applies now.\n\nPersonal data collected will be used for recruitment purpose only.", "employment_types": ["Full Time"], "selling_points": ["5 days work", "Passive Components", "Purchasing"], "locations": ["Kwun Tong"], "categories": ["Merchandising & Purchasing", "Electronics", "Others", "Procurement / Purchasing / Sourcing"], "post_time": "2021-12-31T03:50:55Z", "salary": {"currency": null, "max": null, "min": null, "period": "monthly", "term": null}, "salary_visible": false, "title_keywords": ["product specialist"], "responsibilities": ["ad hoc tasks", "merchandising", "coordinate", "payment", "booking"], "requirements": {"degrees": ["hkdse"], "majors": ["mathematics"], "languages": ["cantonese", "putonghua", "english"], "language_level": ["good command", "fluent"], "hard_skills": ["excel", "erp system", "microsoft word"], "soft_skills": ["good team player", "self-motivated", "work independently", "sense of responsibility", "interpersonal skills"], "languages_combined": [{"language": "cantonese", "language_level": ["good command"]}, {"language": "putonghua", "language_level": ["good command"]}, {"language": "english", "language_level": ["fluent", "good command"]}]}, "experience_required": {"duration": ["minimum 3 years"], "field": ["erp system"]}}, {"job_id": "100003009014475", "location_code": "hk", "company": "Branford Limited", "job_title": "Shipping Clerk (13th month salary)", "description": "Quality Assurance Executive\u00a0\n\n\nAbout the company\nOur client is a global leading corporation. They\u00a0are looking for a QA Specialist to join their team\n\n\nJob Description\n\n\u00b7\u00a0\u00a0\u00a0\u00a0\u00a0\u00a0\u00a0\u00a0 Maintain quality management system and quality control programs, review current standards and policies\n\n\u00b7\u00a0\u00a0\u00a0\u00a0\u00a0\u00a0\u00a0\u00a0 Establish and manage product quality plan to ensure the compliance of safety standards and\u00a0 requirements\n\n\u00b7\u00a0\u00a0\u00a0\u00a0\u00a0\u00a0\u00a0\u00a0 Devise procedures to inspect and report quality issues\n\n\u00b7\u00a0\u00a0\u00a0\u00a0\u00a0\u00a0\u00a0\u00a0 To identify the root cause of quality issues and determine the quality correction action plan\n\nRequirements\n\n\u00b7\u00a0\u00a0\u00a0\u00a0\u00a0\u00a0\u00a0\u00a0 Degree / Diploma holder in QA\n\n\u00b7\u00a0\u00a0\u00a0\u00a0\u00a0\u00a0\u00a0\u00a0 Minimum 6 years working experience in the QA area\n\n\u00b7\u00a0\u00a0\u00a0\u00a0\u00a0\u00a0\u00a0\u00a0 Excellent communication skills, detail-minded, well-organized and a team leader with a strong sense of responsibility\n\n\u00b7\u00a0\u00a0\u00a0\u00a0\u00a0\u00a0\u00a0\u00a0 Good command of spoken and written English & Mandarin\n\nIf you are interested in this position, please click the link to apply. If you would like to know more about this role, please contact us\u00a0for a confidential conversation.", "employment_types": ["Permanent"], "selling_points": [], "locations": ["Tsim Sha Tsui"], "categories": ["Merchandising & Purchasing", "Electronics", "Toy", "Others", "Trading"], "post_time": "2022-01-03T03:29:05Z", "salary": {"currency": null, "max": null, "min": null, "period": "monthly", "term": null}, "salary_visible": false, "title_keywords": ["shipping clerk"], "responsibilities": ["management", "maintain quality", "policies", "review", "compliance", "procedures", "quality", "quality control", "safety standards", "quality plan", "plan", "report"], "requirements": {"degrees": ["diploma holder", "degree"], "majors": [], "languages": ["english", "mandarin"], "language_level": ["good command"], "hard_skills": [], "soft_skills": ["detail-minded", "communication skills", "sense of responsibility", "interested in", "well-organized"], "languages_combined": [{"language": "english", "language_level": ["good command"]}, {"language": "mandarin", "language_level": ["good command"]}]}, "experience_required": {"duration": ["minimum 6 years"], "field": ["qa"]}}, {"job_id": "100003009016960", "location_code": "hk", "company": "Change Group Hong Kong Limited", "job_title": "Quality Assurance Executive up to 30 to 36K", "description": "We are currently searching for an energetic Demand Planner with excellent MS Excel skills.\u00a0 This role will be responsible for all forecasting activities associated with critical electronic components such MCUs, FETs, and sensors, supporting all business units of TTI including consumer and professional tools, outdoor power equipment, floorcare, and flagship Milwaukee Tool. Leveraging data consolidated from both internal ERP and external suppliers\u2019 databases, the position manages the overall process and team for delivery of accurate, timely forecasts to electronic component manufacturers to maximize overall supply continuity.\u00a0\n\n\nResponsibilities:\n\nReview historical purchase and forecast trends, research demand drivers including new product development (NPD) and sales promotion activity to prepare forecast data, develop statistical forecast models as needed, and monitor forecast accuracy\nInteract with Global Electronics Sourcing (GES) counterparts and business units as needed to consolidate NPD, promotional, or end-of-life plans to update a consolidated forecast across business units\u00a0\u00a0\nEnsure timely monthly distribution of forecast to multiple critical electronic device manufacturers\nWork with PowerBI Data Engineer, project leader, IT, and other TTi resources as needed to automate distribution of monthly rolling forecast to critical suppliers and improve overall forecasting process timeliness, accuracy, and efficiency\nDevelop metrics/scorecards on KPI's, including forecast accuracy, fill rate, inventory turns, and excess & obsolete inventory\nOther duties/projects related to demand forecasting as assigned\n\nRequirements:\n\n\nBachelor\u2019s degree in in Economics, Mathematics, Supply Chain/Logistics, Business or related discipline\n2-5 years directly related experience\nUnderstanding of ERP systems, preferably with electronic data interchange (EDI)\nGood communication skills\nGood command of written and spoken Mandarin,Chinese and English\nAnalytical skills and strong ability to manipulate Excel-based data sets\nKnowledge and understanding of Oracle ERP preferred\nExperience with forecasting in high SKU-mix, rapid-change consumer business environment preferred\nCandidate with more experience will be considered as Assistant Demand Planning Manager\nWe offer 5-day week, competitive remuneration package and good career prospects to the right candidate. Interested parties please send your resume with expected salary\u00a0by clicking APPLY NOW.\n(All personal data collected would be used for recruitment purpose only)", "employment_types": ["Full Time"], "selling_points": ["Work life balance", "good bonus", "good working location"], "locations": ["Central & Western Area"], "categories": ["Engineering", "Manufacturing & Production", "Merchandising & Purchasing", "Electronics", "Manufacturing", "Quality Assurance, Control & Testing / ISO"], "post_time": "2022-01-03T10:11:52Z", "salary": {"currency": null, "max": null, "min": null, "period": "monthly", "term": null}, "salary_visible": false, "title_keywords": ["executive"], "responsibilities": ["rolling forecast", "data", "other duties", "inventory", "review", "monitor", "develop", "purchase", "forecast", "plans", "forecasting"], "requirements": {"degrees": ["degree", "bachelor"], "majors": ["business", "mathematics", "economics"], "languages": ["english", "chinese", "mandarin"], "language_level": ["good command"], "hard_skills": ["erp systems", "excel", "demand planning", "oracle erp", "analytical skills", "rapid"], "soft_skills": ["business environment", "communication skills", "analytical skills"], "languages_combined": [{"language": "english", "language_level": ["good command"]}, {"language": "chinese", "language_level": ["good command"]}, {"language": "mandarin", "language_level": ["good command"]}]}, "experience_required": {"duration": ["2-5 years"], "field": ["related", "business", "planning"]}}, {"job_id": "100003009011466", "location_code": "hk", "company": "Techtronic Industries Co Ltd", "job_title": "Demand Planner", "description": "Job Description:\nTo be responsible for the company\u2019s end to end sourcing of products and services essential for our operations.\u00a0 In addition, the individual will be responsible for all phases of sourcing that require the skills necessary to identify cost saving opportunities, create competitive environments, creatively negotiate, generate contracts to assure seamless availability of all products to support the company objectives.\u00a0\u00a0\n\n\u00a0Job Responsibilities:\n\nTake overall responsibility for the strategic sourcing management goals of the company and implement action items to ensure that those goals are achieved.\nResponsible for negotiations for best possible cost service guarantee and develop \u201cwin-win\u201d strategies that achieve sustainable relationships with suppliers.\nEvaluate supplier core competencies and competitive positioning using industry cost models.\nImplement supplier agreements/contracts when beneficial by working with cross-functional stakeholders and suppliers to reach agreement on contract terms and conditions.\nAnalyze industry trends and evolving technology to proactively identify supply base issues to minimize risk, protect continuity of supply, and utilize emerging opportunities.\nMaintain and develop supplier relationships (trade shows, supplier meetings, conferences, etc.).\nDevelop a supplier management program with key suppliers including metrics, performance goals and improvement initiatives.\nEstablish purchasing policies and ensures compliance within the department.\nDevelop forecasts for future demand and place orders in a timely fashion based upon lead-time.\nDevelop and implement sourcing and supplier selection strategies.\nTo define and monitor supplier portfolio development with Management.\nTo partner with internal brand owners to define their requirements and align brands requirement in category sourcing for common buy.\nTo sustain supplier competitiveness on pricing, quality and delivery.\nTo develop and select potential and capable ODM & OEM partners/suppliers in Asia.\nTo track KPIs for developing supplier scorecard reports.\nTo work closely with product development team, engineering team, production team, quality assurance team, product marketing team, as well as management to define merchandising requirements.\nTo be able to meet product development schedules and deadlines.\n\n\u00a0Job Requirements:\n\nBachelor\u2019s degree and at least five (5) years purchasing/strategic sourcing experience along with 3+ year\u2019s relevant operations/supply chain experience.\nODM/OEM vendor experience in Mobile Accessories, Travel Accessories, Mobile Communication Products as well as Lifestyle products is necessary.\nAbility to manage OEM/ODM product developments and establish goals and accountabilities to ensure successful delivery (on time, within budget, meeting agreed upon success criteria).\nSolid sourcing or merchandising experience in electronics or computer accessories buying / sourcing offices, with solid experience in capacity planning, product development, costing, sourcing and placement.\nHaving strong knowledge in quality, process analysis, action calendar planning and management of deadlines.\nPossess strong skills in negotiation externally with vendors, self-motivated & aggressive, strong verbal and written communication, data consolidation and analysis, handling multi-tasks and problem solving.\nWilling to travel occasionally and work under pressure and overtime.\n\nJob Location: Kowloon Bay or the Hong Kong Science Parks, Shatin\n\nWe offer competitive remuneration packages plus medical insurance, life insurance, performance bonus, travel allowance for senior positions and good career prospects to the right candidates. Please apply with full resume, stating current and expected salaries and date of availability by email or send to HR Manager, Global Cyberworks Ltd., GPO BOX 10160, Central, Hong Kong.\n\n(Data collected will be treated as strictly confidential and will be used for recruitment purpose only.)", "employment_types": ["Full Time", "Permanent"], "selling_points": ["Solid experience in forecast and analysis", "Excellent in MS Excel skills", "Strong communication skills"], "locations": ["Kwai Hing"], "categories": ["Manufacturing", "Manufacturing Management", "Production Planning / Control", "Merchandising & Purchasing", "Electronics"], "post_time": "2021-12-31T07:22:49Z", "salary": {"currency": null, "max": null, "min": null, "period": "monthly", "term": null}, "salary_visible": false, "title_keywords": [], "responsibilities": ["cost", "management", "schedules", "operations", "contracts", "policies", "compliance", "monitor", "quality", "develop", "evaluate", "developing", "conferences", "maintain", "reports", "merchandising", "kpis"], "requirements": {"degrees": ["degree", "bachelor"], "majors": [], "languages": [], "language_level": [], "hard_skills": ["plus", "analysis", "vendor", "problem solving", "mobile", "gpo"], "soft_skills": ["self-motivated", "negotiation", "multi-tasks", "communication", "problem solving", "work under pressure"], "languages_combined": []}, "experience_required": {"duration": ["3+ year"], "field": ["purchasing", "supply chain", "merchandising", "product development", "planning"]}}, {"job_id": "100003009003993", "location_code": "hk", "company": "Global Cyberworks Limited", "job_title": "Sourcing Officers / Sourcing Supervisors / Sourcing Managers", "description": "Responsibilities:\n\nResponsible for the suppliers\u2019 capability to comply with the company\u2019s quality requirements and guidelines\nAssessment of external test certificates in accordance with the set standards\nResponsible for the suppliers\u2019 fulfilment of all quality requirements; formulation of remedial and preventive measures to achieve continuous improvement\nReview and monitor the performance of suppliers. Thus, frequent trips to the production areas are necessary.\nDevelopment of quality standards and solutions in co-operation with the central QM department\nObserve and report on technical changes in regional testing laboratories\nProcess monitoring esp. concerning to error rate and failure rate\u00a0\n\nRequirements:\n\nTertiary education in Quality Assurance or similar relevant disciplines\nAt least 6 years\u2019 working experience in DIY products\nWork independently, self-motivated with strong communication skills and interpersonal skills\nFamiliar with local and \u00a0western culture and business practices\nAble to collaborate with others to develop solutions and resolve problems\nMust develop solutions to meet the customers\u2019 needs\nExcellent command of spoken and written English and Putonghua\nAnalytical, problem-solving and time-management skills\nImmediate availability is preferred\nExcellent organizational and analytical skills\nOccasional traveling to China and overseas required", "employment_types": ["Full Time", "Permanent"], "selling_points": ["Product Development and Project Management", "Experience in Electronics / Healthcare Products", "Vendor Management"], "locations": ["Kowloon Bay"], "categories": ["Merchandising & Purchasing", "Electronics", "Home Appliances", "Procurement / Purchasing / Sourcing"], "post_time": "2021-12-28T14:43:12Z", "salary": {"currency": null, "max": null, "min": null, "period": "monthly", "term": null}, "salary_visible": false, "title_keywords": [], "responsibilities": ["guidelines", "review", "quality", "monitoring", "testing", "monitor the performance", "report"], "requirements": {"degrees": [], "majors": [], "languages": ["putonghua", "english"], "language_level": ["excellent"], "hard_skills": ["problem-solving", "analytical skills"], "soft_skills": ["communication skills", "work independently", "self-motivated", "organizational", "problem-solving", "analytical skills", "interpersonal skills"], "languages_combined": [{"language": "putonghua", "language_level": ["excellent"]}, {"language": "english", "language_level": ["excellent"]}]}, "experience_required": {"duration": ["at least 6 years"], "field": []}}, {"job_id": "100003009008243", "location_code": "hk", "company": "Hornbach Asia Limited", "job_title": "Assistant Quality Assurance Manager", "description": "Excellent opportunity for Procurement experts to work for a Top Tier IT Company. The chosen candidate will be responsible for IT and non-IT Procurement to the team.\n\nClient Details\n\nOur client is a leading IT service provider company with over hundreds of employees and more than millions of customers in the world. With significant business expansion in their regional business, they are currently looking to recruit a young and energetic Procurement Specialist to support future operations.\n\nDescription\n\nAssist in developing procurement strategies to achieve company savings targets\nMaintain good relationships with vendors and other stakeholders\nReview and negotiate procurement contract terms to maximize the benefits for the company\nEvaluate vendor performance for future operation improvement\nAssist in ad-hoc duties as per assigned\n\nProfile\n\nDegree holder in Procurement, Supply Chain, Engineering, IT or other related field\nMinimum 2 years of procurement experience in large scale company, preferably from a IT Company\nStrong analytical skills with numerical sense\nOrganized and detail-oriented individual\nExcellent command in both English and Chinese\n\nJob Offer\n\nFlexible working environment\nExcellent career progression\n5-day work", "employment_types": ["Full Time", "Permanent"], "selling_points": ["Familiar with local and western culture", "Dental & Medical Insurance/Travel Allowance", "6 years\u2019 working experience in DIY products"], "locations": ["Lai Chi Kok"], "categories": ["Manufacturing", "Production Planning / Control", "Merchandising & Purchasing", "Electronics", "Quality Assurance, Control & Testing / ISO"], "post_time": "2021-12-30T21:58:09Z", "salary": {"currency": null, "max": null, "min": null, "period": "monthly", "term": null}, "salary_visible": false, "title_keywords": ["assistant quality assurance manager"], "responsibilities": ["it service", "operations", "developing", "maintain", "it procurement"], "requirements": {"degrees": [], "majors": [], "languages": [], "language_level": [], "hard_skills": [], "soft_skills": ["energetic", "responsible"], "languages_combined": []}, "experience_required": {"duration": [], "field": []}}]