[{"job_id": "100003009054158", "location_code": "hk", "company": "AMERICAN EAGLE OUTFITTERS ASIA LTD", "job_title": "Fabric Merchandiser", "description": "Key Responsibilities:\n\n\nResponsible for mill\u2019s management, fabric development and cost control\nAssist Fabric Manager in fabric & wash development\nConduct new fabric development & evaluation, including participate in fabric shows and research new fabrications, techniques and finishes\nCoordinate with US fabric team to align on seasonal development plans\nProvide mills with idea and assistant for new development and ensure mills use correct technique to meet quality requirement\nMaintain daily communication with mills and internal counter parts\nElaborate testing protocol to mills and guide them thru American Eagle quality standard\nEvaluate fabrics and callout potential quality & delivery issue to US fabric team when needed\nManage signed off fabric library, and manage seasonal sample yardages Update and report seasonal adoption rate to manager\nVisit fabric mills to update latest production technology, follow up sample and bulk quality etc\nStay focus at proper mill to provide best cost option\nNegotiate with mill according to HK sourcing & US production cost control guidelines\nDevelop strong connection with US cross functional teams\nOther projects and responsibilities as assigned\n\nRequirements:\n\nDiploma or Degree in Textile Science or related disciplines is preferred\nMinimum 3-year experience of fabric development with proven track record\nTechnical knowledge of yarns, fabrics, dyeing, printing and finish processes is needed\nAbility to facilitate effective communication internally and externally\nFirm understanding of global fabric sourcing, especially mill base in Asia with advance knowledge of raw material, fabric & finishing process or other variables driving cost\nGood communication and organizational skills\n\n\nTo apply, please email your full resume (as an attachment) together with your latest and expected package to us by clicking 'Apply Now'.\n\nAEO is Equal Opportunity Employer. All personal information received from applications will be kept confidential and used for employment-related purpose only.\n", "employment_types": ["Full Time", "Permanent"], "selling_points": ["Work From Home policy", "Friendly and casual culture", "Multi national company"], "locations": ["Kwai Fong"], "categories": ["Merchandising & Purchasing", "Fabrics", "Woven / Knit", "Textiles"], "post_time": "2022-01-17T08:37:04Z", "salary": {"currency": null, "max": null, "min": null, "period": "monthly", "term": null}, "salary_visible": false, "title_keywords": ["fabric merchandiser"], "responsibilities": ["management", "cost", "guidelines", "coordinate with", "quality", "teams", "testing", "communication", "evaluate", "develop", "maintain", "cost control", "evaluation", "plans", "report"], "requirements": {"degrees": ["diploma", "degree"], "majors": ["related disciplines", "science"], "languages": [], "language_level": [], "hard_skills": [], "soft_skills": ["communication", "organizational skills"], "languages_combined": []}, "experience_required": {"duration": ["minimum 3-year"], "field": ["development"]}}, {"job_id": "100003009054818", "location_code": "hk", "company": "Victoria\u2019s Secret", "job_title": "Technologist, Raw Materials / Colorist (6 months contract)", "description": "PURPOSE/GENERAL SUMMARY:\n\nSupport the end to end process of all raw material components of lingerie and/or apparel products from development to production including quality assurance, risk assessment to assure final product quality.\n\nPRINCIPAL DUTIES & RESPONSIBILITIES:\n\nSupport sourcing and developments of all raw material components including color and print for lingerie and/or apparel products to meet the design\u2019s expectation\nMaintain internal systems for record update after raw material approval, lab dips/print development approval and bulk submission approval.\u00a0Data entry/ system input/ simple data drawing with analysis from FlexPLM and shared drive.\nSupport bulk management, e.g. color management, physical performance and quality check\nApply effective systems of Quality Management and regulatory standards, both internally and with vendors to support the fabric and color development process and assure final product quality\nCoordinate with mills to gather information on raw material production lead time and machine capacity for analysis and planning\nSupport mills\u2019 evaluation, onboarding and calibration to ensure their capabilities meet the business expectations\nTake control of the submissions with responsibility for the interpretation and communication of all departmental laboratory testing\nFollow the business calendar timeline to assure the operations on track\n\nREQUIREMENTS:\n\nBachelor Degree holder of Technical Education in Textile Science or equivalent\n3-5 years of related experience in fabric, print and color development in related product category(-ies), as well as in quality assurance in textile industry\nGood command of written and spoken English and Chinese\nGood command of computer skills.\u00a0Experience in FlexPLM system is highly preferable\nProactive and willing to learn\n\nCandidates not invited for interview within 8 weeks may consider their applications unsuccessful. All personal information will be treated as confidential and be used for recruitment purposes only.", "employment_types": ["Temporary", "Contract"], "selling_points": ["6 months renewable contract", "fabric development and color approval", "5 days work week; flexible work hours"], "locations": ["Kowloon Bay"], "categories": ["Manufacturing", "Garment / Textile", "Merchandising & Purchasing", "Fabrics", "Textiles"], "post_time": "2022-01-17T11:21:36Z", "salary": {"currency": null, "max": null, "min": null, "period": "monthly", "term": null}, "salary_visible": false, "title_keywords": [], "responsibilities": ["management", "quality check", "control", "data entry", "data", "operations", "analysis", "systems", "quality", "coordinate with", "design", "testing", "communication", "maintain", "system input", "evaluation", "internal systems", "planning"], "requirements": {"degrees": ["bachelor degree holder"], "majors": ["science"], "languages": ["english", "chinese"], "language_level": ["good command"], "hard_skills": ["computer skills"], "soft_skills": ["proactive", "willing to learn"], "languages_combined": [{"language": "english", "language_level": ["good command"]}, {"language": "chinese", "language_level": ["good command"]}]}, "experience_required": {"duration": ["3-5 years"], "field": ["related", "development", "print", "textile", "quality assurance"]}}, {"job_id": "100003009054817", "location_code": "hk", "company": "Victoria\u2019s Secret", "job_title": "Technologist, Raw Materials", "description": "PURPOSE/GENERAL SUMMARY:\n\nSupport the end to end process of all raw material components of lingerie and/or apparel products from development to production including quality assurance, risk assessment to assure final product quality.\n\nPRINCIPAL DUTIES & RESPONSIBILITIES:\n\nSupport sourcing and developments of all raw material components including specification set up, physical performance validation, quality approval, color and print approval for lingerie and/or apparel products to meet the design\u2019s expectation\nMaintain internal systems for record update after raw material approval, lab dips/print development approval and bulk submission approval.\u00a0Data entry/ system input/ simple data drawing with analysis from FlexPLM and shared drive.\nCoordinate with mills to gather information on raw material production lead time and machine capacity for analysis and planning\nApply effective systems of Quality Management and regulatory standards, both internally and with vendors to support the fabric and color development process and assure final product quality\nSupport mills\u2019 evaluation, onboarding and calibration to ensure their capabilities meet the business expectations\nSupport bulk management, e.g. color management, physical performance, quality check and problem solving\nTake control of the submissions with responsibility for the interpretation and communication of all departmental laboratory testing\nFollow the business calendar timeline to assure the operations on track\n\n\n\nREQUIREMENTS:\n\nBachelor\u2019s degree holder of Technical Education in Textile Science or equivalent\n3-5 years of related experience in synthetic fabric, lace and embroidery products, print and color development in related product category(-ies), as well as in quality assurance in textile industry\nGood command of written and spoken English and Chinese\nGood command of computer skills.\u00a0Experience in FlexPLM system is highly preferable\nProactive and willing to learn\n\nCandidates not invited for interview within 8 weeks may consider their applications unsuccessful. All personal information will be treated as confidential and be used for recruitment purposes only.", "employment_types": ["Full Time", "Permanent"], "selling_points": ["Fabric technical development", "Lace/embroidery/intimate experience is a plus", "5 days' work week; flexible work model"], "locations": ["Kowloon Bay"], "categories": ["Manufacturing", "Garment / Textile", "Merchandising & Purchasing", "Fabrics", "Textiles"], "post_time": "2022-01-17T11:21:35Z", "salary": {"currency": null, "max": null, "min": null, "period": "monthly", "term": null}, "salary_visible": false, "title_keywords": [], "responsibilities": ["management", "quality check", "control", "data entry", "data", "operations", "analysis", "systems", "quality", "coordinate with", "design", "testing", "communication", "maintain", "system input", "evaluation", "internal systems", "planning"], "requirements": {"degrees": ["bachelor", "degree holder"], "majors": ["science"], "languages": ["english", "chinese"], "language_level": ["good command"], "hard_skills": ["computer skills"], "soft_skills": ["proactive", "willing to learn"], "languages_combined": [{"language": "english", "language_level": ["good command"]}, {"language": "chinese", "language_level": ["good command"]}]}, "experience_required": {"duration": ["3-5 years"], "field": ["related", "development", "print", "textile", "quality assurance"]}}, {"job_id": "100003009053947", "location_code": "hk", "company": "MGA Entertainment (H.K.) Ltd", "job_title": "Assistant Costing Manager", "description": "Diploma or above in engineering disciplines\nMinimum 8 years costing and\u00a0tooling experience in toys field, especially in soft toys and fabric material\nKnowledge of manufacturing processes and product design is an added advantage\nSound computer knowledge, especially in Microsoft software\nGood communication skills in English and Chinese (both written and spoken), Putonghua speaking is an advantage\nLocate the fabric source with product development and reach out for cost\nWork on cost comparison on the fabric source and confirm the fabric supplier with Product Development team\nVerify and negotiate the fabric cost with the fabric vendor and sewn goods on production factory\nProvide internal cost estimate and cost reduction suggestions on the sewn goods\n\nInterested parties with relevant experience and qualification, please send detailed resume and expected salary to HR Department, MGA Entertainment,\u00a0Suite 301, Chinachem Golden Plaza, 77 Mody Road, TST East, Kowloon or via email.\n\n(All information collected is used for recruitment purpose only)", "employment_types": ["Full Time", "Permanent"], "selling_points": [], "locations": ["Tsim Sha Tsui"], "categories": ["Engineering", "Engineering Project Management", "Merchandising & Purchasing", "Fabrics", "Toy"], "post_time": "2022-01-17T07:49:15Z", "salary": {"currency": null, "max": null, "min": null, "period": "monthly", "term": null}, "salary_visible": false, "title_keywords": ["manager", "assistant"], "responsibilities": ["communication", "cost", "product design", "software"], "requirements": {"degrees": ["diploma or above"], "majors": ["engineering"], "languages": ["putonghua", "english", "chinese"], "language_level": ["advantage", "good"], "hard_skills": ["vendor"], "soft_skills": ["communication skills"], "languages_combined": [{"language": "putonghua", "language_level": ["advantage", "good"]}, {"language": "english", "language_level": ["advantage", "good"]}, {"language": "chinese", "language_level": ["advantage", "good"]}]}, "experience_required": {"duration": ["minimum 8 years"], "field": ["toys"]}}, {"job_id": "100003009053945", "location_code": "hk", "company": "MGA Entertainment (H.K.) Ltd", "job_title": "Senior Project Engineer", "description": "Higher diploma or university graduate in textile/merchandising/fashion design/garment\nMinimum 3-5 years\u2019 hands-on experience in\u00a0design, material sourcing and fabric development, preferably with strong project coordination experience\nKnowledge of plastic resin, fabric material, tooling and mechanical design in toys and consumer products is an added advantage\nProficient in written and spoken English\n\nInterested parties with relevant experience and qualification, please send detailed resume and expected salary to HR Department, MGA Entertainment, Suite 301, 3/F., Chinachem Golden Plaza, No. 77 Mody Road, Tsimshatsui, Kowloon or via email.\n\n(All information collected is used for recruitment purpose only)\n", "employment_types": ["Full Time", "Permanent"], "selling_points": [], "locations": ["Tsim Sha Tsui"], "categories": ["Engineering", "Engineering Project Management", "Merchandising & Purchasing", "Fabrics", "Textiles"], "post_time": "2022-01-17T07:48:47Z", "salary": {"currency": null, "max": null, "min": null, "period": "monthly", "term": null}, "salary_visible": false, "title_keywords": ["senior project engineer"], "responsibilities": ["mechanical design", "merchandising", "design", "project coordination"], "requirements": {"degrees": ["university graduate", "diploma"], "majors": ["design"], "languages": ["english"], "language_level": ["proficient"], "hard_skills": [], "soft_skills": ["hands-on", "coordination"], "languages_combined": [{"language": "english", "language_level": ["proficient"]}]}, "experience_required": {"duration": ["minimum 3-5 years"], "field": ["development", "design"]}}, {"job_id": "100003009048470", "location_code": "hk", "company": "M. Magtague International Ltd.", "job_title": "Fabric Manager (Woven & Knit Fabric)", "description": "Minimum\u00a010 years' merchandising experience on both woven & knit fabric\nExperienced in handling fabric sourcing & development for both ladies' & men's wear\nStrong\u00a0fabric sourcing network with excellent price negotiation skills\nSolid fabric knowledge and able to provide the\u00a0suggestions to the clients for meeting their targets\nGood\u00a0communications with overseas designers and buyers\nGood\u00a0command of spoken and written English & able to communicate in Mandarin\nPresentable, detail-oriented and able to work under pressure\nWilling to travel\n\nWe offer attractive remuneration package to the right candidate. \u00a0Interested parties please send your\u00a0detailed CV with expected salary and available date\u00a0to the Human Resources Department by clicking the Apply Now button.\n\nPersonal data collected will be used for recruitment purpose only.\n", "employment_types": ["Full Time", "Permanent"], "selling_points": ["Good communication w/ overseas designers & buyers", "Solid experience in both woven & knit fabric", "Strong fabric sourcing supplier networks"], "locations": ["Not Specified"], "categories": ["Merchandising & Purchasing", "Fabrics"], "post_time": "2022-01-14T06:37:54Z", "salary": {"currency": null, "max": null, "min": null, "period": "monthly", "term": null}, "salary_visible": false, "title_keywords": ["fabric manager"], "responsibilities": ["communications with", "price negotiation", "merchandising", "work under pressure"], "requirements": {"degrees": [], "majors": [], "languages": ["english", "mandarin"], "language_level": ["good command"], "hard_skills": [], "soft_skills": ["detail-oriented", "negotiation skills", "work under pressure", "presentable"], "languages_combined": [{"language": "english", "language_level": ["good command"]}, {"language": "mandarin", "language_level": ["good command"]}]}, "experience_required": {"duration": ["minimum 10 years"], "field": ["merchandising"]}}, {"job_id": "100003009051225", "location_code": "hk", "company": "Easy Job Centre", "job_title": "Fabric Merchandiser / Senior Fabric Merchandiser (5 days)", "description": "Company Description\u00a0\n\nOur client is a fast expanding F&B group with business in cafe and coffee trading. Because of business expansion, they are looking for someone who is enthusiastic about coffee bean and coffee to join and main/enhance the coffee quality.\n\nResponsibilities\u00a0\n\nSourcing coffee beans globally and identify potential supplier\nEnsure the highest standard of coffee bean is purchased and the best coffee is served to customers.\nAct as quality control for the coffee made\nNegotiate with coffee suppliers to ensure the right price is offered\n\nRequirements\u00a0\n\nExperienced in coffee business\nAble to tell the difference of coffee beans, origins and different roast process\nConnection and network with coffee bean supplier is a plus\nStrong in communications with good working attitude\nFluency in Cantonese and English is a must.\n\nInterested parties please send your updated resume in WORD format with current and expected salaries (quoting Employer Ref:)", "employment_types": ["Full Time"], "selling_points": [], "locations": ["Yau Tsim Mong Area"], "categories": ["Manufacturing", "Garment / Textile", "Merchandising & Purchasing", "Fabrics", "Textiles"], "post_time": "2022-01-15T05:19:57Z", "salary": {"currency": null, "max": null, "min": null, "period": "monthly", "term": null}, "salary_visible": false, "title_keywords": ["fabric merchandiser"], "responsibilities": ["quality control"], "requirements": {"degrees": [], "majors": [], "languages": ["cantonese", "english"], "language_level": ["fluency"], "hard_skills": ["plus"], "soft_skills": ["good working attitude"], "languages_combined": [{"language": "cantonese", "language_level": ["fluency"]}, {"language": "english", "language_level": ["fluency"]}]}, "experience_required": {"duration": [], "field": []}}, {"job_id": "100003009030604", "location_code": "hk", "company": "Sun Kam Kwong Printing & Dyeing Factory Limited", "job_title": "Merchandising Manager (station in China- Jiang Su)", "description": "Company Description\n\nOur client is one of the largest Food & Beverage well-established group in Hong Kong. For the business needs, they are inviting an experienced & creative talent to join the energetic research & development team as R&D Manager to develop new product.\n\nResponsibilities\n\nCoordinate with different departments and external parties for new product development\nManage the entire new development cycle from prototype and production trial to product launch\nResponsible for food & non-food material sample testing and design\nCommunicate closely with kitchen and production team in order to maintain the production flow run smoothly\nPrepare the product receipt, calculate the cost and conduct risk analysis\nConduct market research to understand the market trend for new product development and existing product improvement\nLead product improvement or other adhoc projects\n\nRequirements\n\nDegree or above in Food Science or related disciplines\nMinimum 8 years working experience in mass production field\nStrong business sense on product positioning\nGood team player, self-initiative and strong sense of responsibility\nFluent in written and spoken English and Cantonese\nInterested parties please send your updated resume in WORD format with current and expected salaries (quoting Employer Ref:)", "employment_types": ["Full Time"], "selling_points": ["Min. 12 yrs experience in (knit/cut) merchandising", "Strong Leadership", "14 days annual leave"], "locations": ["Others - China"], "categories": ["Merchandising & Purchasing", "Fabrics"], "post_time": "2022-01-07T10:32:49Z", "salary": {"currency": null, "max": null, "min": null, "period": null, "term": null}, "salary_visible": false, "title_keywords": ["merchandising manager"], "responsibilities": ["cost", "conduct market research", "external parties", "coordinate with", "design", "testing", "maintain", "risk analysis"], "requirements": {"degrees": ["degree or above"], "majors": ["related disciplines", "food science"], "languages": ["cantonese", "english"], "language_level": ["fluent"], "hard_skills": [], "soft_skills": ["good team player", "sense of responsibility", "self-initiative", "business sense"], "languages_combined": [{"language": "cantonese", "language_level": ["fluent"]}, {"language": "english", "language_level": ["fluent"]}]}, "experience_required": {"duration": ["minimum 8 years"], "field": []}}, {"job_id": "100003009029885", "location_code": "hk", "company": "Headsearch21 Consultancy Ltd", "job_title": "Merchandising Manager / Fabric Merchandiser (Men's Shirts)", "description": "Company Description\n\nOur client is a global hospitality group. Continue expanding their business, they are looking for a high caliber to join their Corporate Development team as Corporate Development Manager.\n\nResponsibilities\n\nAssess and create or develop business cases and investment proposals for divisional and corporate projects\nExamine and coordinate business plans, inspect plan assumptions, and identify and resolve any issue that may arise\nAnalyze new investment and business opportunities through valuation models\nEvaluate cross-company activities for best-practices efficiency opportunities\nDevelop and implement a model or methodology that maximizes lost profits\nRecord, interpret, and report financial information in support of general business operations and long-range tactical plan functions\nPrepare materials for senior management presentations for the board of directors, and also assist with the preparation of annual reports, financial statement forecasts, and variances\nProduce ad-hoc analysis, research, financial report, and progress reports to senior management\nTrain managers and directors on the budget process\n\nRequirements\n\nBachelor Degree in Finance, Accounting, Business Management or a quantitative discipline from a reputable university.\nStrong commercial and analytical mindset, financial modeling and excel skills.\nAbility to work proactively, independently and under pressure, and able to meet tight deadlines.\nHigh level of professionalism and accuracy in financial analysis is a must.\nAt least 4 years\u2019 experience in finance or business analytics fields, with solid exposure in corporate finance transactions and or multinational corporate environments. Fresh graduates with exceptional academic performance and able to demonstrate exceptional business thinking will be considered.\nGrowth mindset, negotiation skills and strong team spirit.\nStrong communication and presentation skills, with excellent command of both written and spoken English is a must.\nCFA or CPA is an advantage.\nAbility to work independently and under pressure, and meet tight deadlines.\u00a0\nInterested parties please send your updated resume in WORD format with current and expected salaries (quoting Employer Ref:)", "employment_types": ["Full Time", "Permanent"], "selling_points": ["Exp in Men's Shirts", "Exp in both woven and knit", "With manufacturing background"], "locations": ["Not Specified"], "categories": ["Manufacturing", "Garment / Textile", "Merchandising & Purchasing", "Fabrics", "Woven / Knit"], "post_time": "2022-01-07T19:19:58Z", "salary": {"currency": null, "max": null, "min": null, "period": "monthly", "term": null}, "salary_visible": false, "title_keywords": ["merchandising manager", "fabric merchandiser"], "responsibilities": ["ad-hoc", "valuation", "progress reports", "operations", "business opportunities", "analysis", "budget", "business plans", "develop", "coordinate", "evaluate", "presentations", "reports", "financial report", "plan", "financial statement", "senior management", "report"], "requirements": {"degrees": ["degree", "bachelor"], "majors": ["business", "finance", "accounting"], "languages": ["english"], "language_level": ["excellent"], "hard_skills": ["business management", "excel", "cfa", "financial analysis", "cpa"], "soft_skills": ["meet tight deadlines", "independently", "under pressure", "team spirit", "work independently", "communication", "negotiation skills", "presentation skills"], "languages_combined": [{"language": "english", "language_level": ["excellent"]}]}, "experience_required": {"duration": ["at least 4 years"], "field": ["finance", "business", "corporate finance"]}}, {"job_id": "100003009047104", "location_code": "hk", "company": "Randstad Hong Kong Limited", "job_title": "Sourcing  Specialist (Home Textile, Softline)", "description": "Company Description\n\nOur client is a one of the well-established and leading F&B groups in Hong Kong. Due to the business needs, they are inviting potential candidate to join their Information Technology team as Network & System Administrator which involved in Support, design and deploy corporate IT infrastructure.\n\nResponsibilities\n\nProvide daily technical support for both network and system infrastructure\nResponsible for the installation, administration, maintenance and configuration the enterprise network\nEnsure the stability, reliability, security and performance of the network infrastructure based on corporate standard\nMonitor the capacity and usage and maintain the infrastructure under a healthy threshold\nInvestigate the root-cause and provide the solution for solving the network and system problems\nEnsure all system and network changes are followed through company policies and procedures\nPrepare and maintain documentation of network and system infrastructure related information\n\nRequirements\n\nDiploma or above in information technology, computer science or related discipline\n3 years of work experience in IT Industry with CCNA / CCNP or other relevant qualification\nHands-on experience in Palo Alto Firewall, Fortigate Firewall, Cisco product and MS Windrows Server.\nProficiency in SD WAN technology, VMware ESXI 6.0 or above, SAN Storage, Redhat Linux is a plus\nKnowledge on Information Security Standard ISO27001 is an advantage\nGood command of spoken and written English and Chinese\nInterested parties please send your updated resume in WORD format with current and expected salaries (quoting Employer Ref:)", "employment_types": ["Full Time", "Permanent"], "selling_points": ["Experience in softhome, home textile", "Buying Office", "US market experience"], "locations": ["Not Specified"], "categories": ["Merchandising & Purchasing", "Fabrics", "Others", "Procurement / Purchasing / Sourcing"], "post_time": "2022-01-14T02:19:58Z", "salary": {"currency": null, "max": null, "min": null, "period": "monthly", "term": null}, "salary_visible": false, "title_keywords": ["specialist"], "responsibilities": ["network infrastructure", "installation", "maintenance", "technical support", "configuration", "policies", "infrastructure", "monitor", "procedures", "maintain", "maintain documentation", "administration"], "requirements": {"degrees": ["diploma or above"], "majors": ["computer science", "information technology"], "languages": ["english", "chinese"], "language_level": ["good command"], "hard_skills": ["linux", "plus", "vmware", "ccnp", "ccna", "firewall", "server", "wan"], "soft_skills": ["hands-on"], "languages_combined": [{"language": "english", "language_level": ["good command"]}, {"language": "chinese", "language_level": ["good command"]}]}, "experience_required": {"duration": ["3 years"], "field": ["it"]}}, {"job_id": "100003009053359", "location_code": "hk", "company": "Pasona Asia Co., Limited", "job_title": "Japanese Speaking Assistant Merchandiser (Multinational Corporation, Welcome Fresh Graduates)", "description": "Company Description\n\nOur client own and operate a lifestyle concept cafe and casual dining restaurant in Central, an unique and stylish venue feature combine with shopping and dining experience. It also set as an ideal venue to host events such as press conference and product launch.\n\nIn view of the business need, they are now inviting experience candidate to join as Restaurant Manager.\n\nResponsibilities\n\nReport to the founder, your primary focus is to ensure the smooth operation of the restaurant.\nFull P&L responsibilities.\nAct as ambassador, being on the floor to interact with customers, provide menu recommendations.\nWork closely with the Head Chef on menu design, seasonal promotion.\nConduct service and product training to the team.\nRestaurant hygiene, F&B marketing promotion, budgeting and manpower planning.\nAd hoc project include new store expansion.\n\nRequirements\n\nHigher diploma in Hospitality Management.\nMinimum 6 years working experience with hotel / casual free standing restaurant, at least 2 years in Restaurant Manager capacity.\nEnergetic and enthusiastic, passionate to develop the career in F&B industry.\nGood in written and spoken English and Chinese (Mandarin would be a plus).\nPeople oriented, excellent team player.\n\nInterested parties please send your updated resume in WORD format with current and expected salaries (quoting Employer Ref:)\u00a0", "employment_types": ["Full Time", "Permanent"], "selling_points": ["Support daily merchandising duties", "Eager to work in fast paced environment", "More experience will be considered as Merchandiser"], "locations": ["Tsim Sha Tsui"], "categories": ["Merchandising & Purchasing", "Fabrics", "Textiles", "Others"], "post_time": "2022-01-17T06:51:05Z", "salary": {"currency": null, "max": null, "min": null, "period": "monthly", "term": null}, "salary_visible": false, "title_keywords": ["assistant merchandiser"], "responsibilities": ["ad hoc", "budgeting", "design", "p&l", "hygiene", "planning", "report"], "requirements": {"degrees": ["diploma"], "majors": ["hospitality management"], "languages": ["english", "chinese", "mandarin"], "language_level": ["good"], "hard_skills": ["plus"], "soft_skills": ["passionate", "team player", "energetic", "enthusiastic"], "languages_combined": [{"language": "english", "language_level": ["good"]}, {"language": "chinese", "language_level": ["good"]}, {"language": "mandarin", "language_level": ["good"]}]}, "experience_required": {"duration": ["at least 2 years", "minimum 6 years"], "field": ["restaurant"]}}, {"job_id": "100003009051224", "location_code": "hk", "company": "Easy Job Centre", "job_title": "Merchandiser / Senior Merchandiser  (Garment) (5 days)", "description": "Company Description\n\nOur client, a well-regarded asset & wealth management group, is seeking a VP, Marketing Strategy & Planning. Reporting to the regional marketing head, the successful candidate will be responsible for managing the marketing process from research / analysis to planning & execution for various marketing initiatives (including digital).\n\nResponsibilities\n\nAct as the go-to person for all regional marketing programs (online and offline) to ensure consistency on brand and product messages across Asia (ex-Japan)\nManage conception, development and implementation of marketing plans / strategies to achieve KPIs for brand presence, campaign efficiency evaluations, , digital performance, etc\nCollaborate with local business teams to ensure regional effort is fulfilling individual market needs\nWork closely with regional data analytics team to uncover insights and to integrate such findings in marketing programs\nConstantly analyze campaign data and make data informed decisions for in-flight optimization and improving outcome\nWork alongside with global digital / marketing technology teams to contribute to the company\u2019s marketing & communications standards\nDrive sharing of best practices with local marketing teams\nManage agency providers on various regional projects and liaise closely with in-house design team\n\nRequirements\n\nUniversity graduate with degree in BBA / Marketing / related discipline\nAt least 10 years of marketing planning & execution experience from agencies or financial sector\nA proven track record in managing complex (regional) marketing projects from end to end in a multi-national firm is important\nKnowledge of wealth management /investment funds products is a bonus\nStrong project management skills, including KPI tracking, and attention to detail\nA strong team player with proven experience in managing stakeholders across the region\nExcellent communication skills in English and Chinese, and be able to pitch strategic marketing ideas using data\nInterested parties please send your updated resume in WORD format with current and expected salaries (quoting Employer Ref:)", "employment_types": ["Full Time"], "selling_points": [], "locations": ["Yau Tsim Mong Area"], "categories": ["Manufacturing", "Garment / Textile", "Merchandising & Purchasing", "Fabrics", "Woven / Knit"], "post_time": "2022-01-15T05:19:56Z", "salary": {"currency": null, "max": null, "min": null, "period": "monthly", "term": null}, "salary_visible": false, "title_keywords": ["merchandiser", "senior merchandiser"], "responsibilities": ["collaborate with", "liaise", "data", "marketing plans", "teams", "implementation", "design", "kpis"], "requirements": {"degrees": ["university graduate", "degree"], "majors": ["bba", "marketing"], "languages": ["english", "chinese"], "language_level": ["excellent"], "hard_skills": ["project management"], "soft_skills": ["communication skills", "project management skills", "team player", "attention to detail"], "languages_combined": [{"language": "english", "language_level": ["excellent"]}, {"language": "chinese", "language_level": ["excellent"]}]}, "experience_required": {"duration": ["at least 10 years"], "field": ["team", "marketing", "financial", "planning"]}}, {"job_id": "100003009030545", "location_code": "hk", "company": "Randstad Hong Kong Limited", "job_title": "Senior Buying Manager (Station in GuangZhou)", "description": "about the company.\n\nOur client in a Hong Kong clothing retailer with main focus in Asia. They have over 2000 stores around the world. The position will be based in GuangZhou. Travel allowance is provided for weekly travel to Hong Kong once travel restrictions have been lifted.\nabout the job.\nDevelop new business with potential clients across multiple categories\nLead the merchandising team for the whole buying lifecycle such as OTB planning & management, buying, allocation & replenishment etc.\nParticipate in seasonal buying campaign, lead assortment and product strategy\nEnsure the brand proposition executed across products, concepts, promotion and pricing strategies\nMaximize business opportunities and meet the KPI such as Net Sales, Retail Price, Margin, Sell-thru and Product Productivity\nEstablish and lead an effective logistics team to take up the shipment and on-time delivery\nDevelop, manage and lead sourcing and production teams across various product categories\nHands on, proactive management of day to day product development and production issues/challenges.\nskills & experiences required.\nDegree in related discipline\n15+ years of solid experience in fashion retail industry\nWork experience in China market is a plus\nGood command of written and spoken English, Cantonese and Mandarin\nStation in Guangzhou\n\nabout the package.\n\n5 days work\nFast Track Promotion\nDouble Pay\nHousing provided\nFriendly Working Culture\nMedical\n\nIf you're interested in this role, click 'apply now' or email cecilia.ng@randstad.com.hk to forward an up-to-date copy of your CV, or call Cecilia NG at 2232 3444. If this is not your ideal job but you are looking out, please contact us for a discussion on your career preferences.", "employment_types": ["Full Time", "Permanent"], "selling_points": [], "locations": ["Not Specified"], "categories": ["Merchandising & Purchasing", "Fabrics", "Others", "Procurement / Purchasing / Sourcing"], "post_time": "2022-01-07T07:42:42Z", "salary": {"currency": null, "max": null, "min": null, "period": "monthly", "term": null}, "salary_visible": false, "title_keywords": ["buying manager"], "responsibilities": ["product categories", "management", "develop new business", "business opportunities", "merchandising", "replenishment", "teams", "otb", "develop", "logistics", "contact", "planning"], "requirements": {"degrees": ["degree"], "majors": [], "languages": ["cantonese", "english", "mandarin"], "language_level": ["good command"], "hard_skills": ["focus", "plus"], "soft_skills": ["interested in", "hands on", "friendly", "focus", "proactive", "ideal"], "languages_combined": [{"language": "cantonese", "language_level": ["good command"]}, {"language": "english", "language_level": ["good command"]}, {"language": "mandarin", "language_level": ["good command"]}]}, "experience_required": {"duration": ["15+ years"], "field": ["retail industry"]}}, {"job_id": "100003009025568", "location_code": "hk", "company": "Win Paradise Limited", "job_title": "ASST MERCH/MERCHANDISER/SR MERCH/MERCH MGR (GARMENT/FABRIC/GARMENT ACC/FASHION ACC/HANDBAG/SUNDRIES)", "description": "F.5/TI\nMin 2 yrs Merchandising/Sales & Marketing/Purchasing experience in either one of below:\n\nWoven / Knit / Sweater / Silk / Denim\u00a0/\u00a0Garment, Casual Wear,\u00a0 Fashion, Underwear, Mould Cup, Bra Bonding, Sleepwear, Babywear, Kidswear, Outerwear, Sportswear, Swimwear, Jeans, Jacket, Suit, Board Shorts, Uniform, Fur, Leatherwear, Costume, Safety Wear Merchandising;\n\n\u00a0\u00a0\u00a0\u00a0\u00a0\u00a0\u00a0\u00a0\u00a0\u00a0\u00a0\u00a0 or\n\nWoven / Knit / Silk / Denim / Washed Fabric Merchandising and Purchasing and Sourcing and Development / Selling / Weaving / Dyeing / Printing;\n\n\u00a0\u00a0\u00a0\u00a0\u00a0\u00a0\u00a0\u00a0\u00a0\u00a0\u00a0\u00a0 or\n\nGarment Accessories / Underwear Accessories / Yarn / Garment Packaging / Embroidery / Logo / Cup Mould / Lace / Woven Label / Interlining / Purchasing and Sourcing and Librarian;\u00a0\n\u00a0\u00a0 or\nFashion Accessories / Cold Weather Items / Soft Accessories-Kids / Handbag / Fashion Bag / Casual Bag / Cosmetic Bag / Backpack / Tools Bag / Luggage / Shoes / Hat / Cap / Gloves / PVC Products / Socks / Home Textile / Bedding / Fine Jewellery / Fashion Jewellery / Baby Products / Infant Textile Products / Beauty Products / Cosmetic / Toiletries / Hair Care Products.\n\u00a0 or\nHard Toys / Soft Toys / Watch / Eyeglasses / Fine Jewellery / Imitation Jewellery / Houseware / Kitchenware / Kitchen Gadget / Home DIY / Dining Ware / Tableware / Ceramic / Sundries / Stationery / Seasonal Items\u00a0/\u00a0Artificial Flower / Art & Craft / Home Decoration /\u00a0Lighter / Gift Items /\u00a0Electrical Appliance / Audio / Electronic Products / Mobile Phone Accessories / Stationery /\u00a0Toiletries / Bath Room Acc / Sanitary Ware / Baby Products / Baby Textile / Make Up Acc / Office Supplies / Furniture\u00a0/\u00a0Bodycare /\u00a0Cosmetic / Beauty Products / Hair Care Products / Lighting / Sports Goods\u00a0/\u00a0Paper Products / Paper Raw Materials / Computer Parts / Tools / Assembly Kit / Steel Product / Outdoor Products / BBQ / Gardening / Bicycle / Pet Accessories / Camping Goods / Outdoor Goods / Canned Foods / Frozen Foods / Snack / Machine / Surf Accessories / Swim Accessories / Hotel Supplies / Bldg Materials / Sanitary Ware / Hotel Supplies / Home Textile / Bedding / Tools / Hardware / Glassware / Drinkware / Candle / Display / Label / Party Goods / PC Accessories / Jewellery Packaging / Jewellery Box / Electric Fan / Heater / Make Up Accessories / Cosmetic / Beauty Acc / Cosmetic Packaging / Metal Parts / Industrial Device / Electrical Device / Battery / Plastic Material / Home Care Products / Elec Alarm / Industrial Safety Products / Marine Equipment / Door & Window Hardware / Window Display Frame / Medical Protective Device / Face Mask / Baby Feed Products / Cake Tool / Pet Accessories / Home Technology / Printing & Packaging / Photoframe / Sports Goods / Glass / Fitness Equipment / Inflatable Swimming Goods / Swimming Acc / PVC Products.\u00a0\n\n\u00a0 or\nPurchaser / Purchasing Officer / Purchasing Manager / Supply Chain Director\u00a0 for\u00a0 Electronic Parts / Mechanical Parts\u00a0/ Watch Parts\u00a0/ Smart Watch / Eyeswear Parts / Handbag Accessories / Backpack Accessories / Shoes Materials / Leather Material\u00a0/ Chemical / Dyeing Stuff / Office Supplies / Office Equipment & Furniture / Toys Parts / Packaging Materials / Building Materials / Marble / Renovation Materials / Tile / Frozen Foods / Canned Foods / Dried Seafoods / Food Packaging / FMCG / Supermarket Commodities / Food Raw Material / F&B / Kitchen Equipment / E&M.\n\nProficient in English/Proficient in\u00a0Mandarin, Japanese/Korean Speaking preferred but not essential.\u00a0\u00a0\u00a0\u00a0\u00a0\u00a0\u00a0\u00a0\u00a0\nWork in HK/China Stay/Cambodia/Vietnam/Offshore Stay.\u00a0\nSalary Range: HK$13K-$60K / Month\n\n*** Please send your detailed resume in \u201cword format\u201d including \" Expected Salary \", \u201cCompany Nature & Product\u201d & \u201cAvailability Date\u201d to our \u201cE-mail Address\u201d shown above or fax to \u201c2780 2672\u201d or by clicking \u201cApply Now\u201d.", "employment_types": ["Full Time", "Permanent"], "selling_points": ["- F.5/Dip in BA/Textile/Garment/other", "- 2-8 yrs relevant Merch/Pur exp.", "- Garment/Fabric/Yarn/Fashn Acc/Toys/Wth/Gift/Sund"], "locations": ["Not Specified"], "categories": ["Merchandising & Purchasing", "Fabrics", "Sweater", "Woven / Knit"], "post_time": "2022-01-09T16:25:41Z", "salary": {"currency": null, "max": null, "min": null, "period": "monthly", "term": null}, "salary_visible": false, "title_keywords": ["merchandiser"], "responsibilities": ["office supplies", "renovation", "merchandising", "stationery", "hardware", "industrial safety", "audio"], "requirements": {"degrees": [], "majors": [], "languages": ["japanese", "english", "mandarin", "korean"], "language_level": ["proficient"], "hard_skills": ["acc", "word", "mobile", "hardware", "make", "pc", "logo"], "soft_skills": ["detailed"], "languages_combined": [{"language": "japanese", "language_level": []}, {"language": "english", "language_level": ["proficient", "proficient"]}, {"language": "mandarin", "language_level": []}, {"language": "korean", "language_level": []}]}, "experience_required": {"duration": [], "field": ["purchasing", "marketing", "merchandising"]}}, {"job_id": "100003009025579", "location_code": "hk", "company": "Win Paradise Limited", "job_title": "QC / TECHNICIAN / QC MGR / PRODUCTION MGR (GARMENT / FABRIC / HANDBAG / ELEC / TOYS / SUNDRIES)", "description": "F.5 / Diploma in Textile / Garment / Chemistry preferred\nMin 4 yrs exp in either one of below:\n\n\nQC / QC Supervisor / Sampling Supervisor / Production Planner / QC Manager / IQC Manager / Production Planning Manager / Production Manager / Factory Manager\u00a0 with\u00a0 Woven / Knit / Sweater / Denim /\u00a0Leather\u00a0Garment,\u00a0 Fashion, Casual Wear,\u00a0Underwear, Lingerie, Shapewear, Sportswear, Sportsbra, Swimwear, Bra Bonding, Mould Cup, Interlining, Kidswear, Outerwear, Jeans, Suit, Shirt, T-Shirt, Safety Wear, Printing & Embroidery, Woven Fabric, Knit Fabric, Garment Accessories, Fashion Accessories, Handbag, Backpack, Tools Bag, Pouches, Shoes, Hat, Gloves, Home Textile, Electrical Appliance, Electronic Products, LCD Module, Audio, Video, Watch, Fashion Jewellery, Stationery, Sports Goods, Toys, Seasonal Items, Furniture, Houseware, Home DIY, Kitchenware, Auto Accessories, Bath Acc, AV Products, Phone, PCBA, SMT, Injection Moulding, Lighting, LED, Knift, Camping Goods, Outdoor Goods, Packaging, Beauty Products, Incoming Garment Materials, Building Construction, Catering, Home Textile, Cosmetic, Ceramic, Gift Items, Home Decoration, Electrical Device, Pet Accessories, Frozen Foods, Condiment, Snack, Soft Drink, Industrial Safety Products, Lighting, E&M, Lift, Foods, Packaging, EVA Box, Medicine exp.\n\u00a0\u00a0\u00a0\u00a0\u00a0\u00a0\u00a0\u00a0 \u00a0\u00a0 or\n\n\nGarment Technician / 3D Technician / Technical Manager\u00a0 with\u00a0 Woven / Knit / Sweater Garment, Fashion, Casual Wear, Sportswear, Swimwear, Shirt, Bottoms, Underwear, Bra Mould Cup, Bra Bonding, Kidswear, Babywear, Outerwear, Denim, Checking of Paper Pattern, Sample Approval, Fitting, Grading, Technical Advise, Costing, Sewing Advisory, Gerber, Lectra, Optitex, Apex, CLO.\n\n\n\u00a0\u00a0\u00a0\u00a0\u00a0\u00a0\u00a0\u00a0\u00a0\u00a0\u00a0 or\n\nSample Technician / QA Technician / Technical Manager with Fashion Accessories, Handbag, Backpack, Shoes, Socks, Home Textile, Baby Acc., Furniture, Houseware, Kitchenware, Garment Accessories, Trims, Leather Material, Foods, Cosmetic, Beauty Products, EVA Box exp.\n\u00a0\u00a0\u00a0\u00a0\u00a0\u00a0\u00a0\u00a0\u00a0\u00a0 or\n\n\nFactory Compliance Officer / Environmental Sustainability Officer / Traceability Officer / ISO Officer / Manager\u00a0 with\u00a0 Garment / Fabric / Fashion Accessories / Toys Fields for Factory Compliance / Product Safety / Material Traceability / Environmental Health & Safety / ISO Compliance / Chemical Compliance.\n\u00a0\u00a0\u00a0\u00a0\u00a0\u00a0\u00a0\u00a0\u00a0\u00a0\u00a0 or\n\n\nFabric Technician / Fabric Q.A. / Printing Technician / Color Technician / Washing Technician / Factory Manager\u00a0 with\u00a0 Woven Fabric or Knit Fabric or Yarn or Leather Material / Fabric Weaving / Fabric Dyeing / Milling / Fabric Development / Fabric Quality Control /\u00a0Fabric Printing / Laundry / Fabric Production exp.\n\u00a0\u00a0\u00a0\u00a0\u00a0\u00a0\u00a0\u00a0\u00a0 \u00a0\u00a0 or\n\n\nPattern Maker / Grader\u00a0 with\u00a0 Woven / Knit / Fashion / Casual Wear / Kidswear / Pants / Outerwear / Underwear / Sportswear\u00a0exp.\u00a0\n\n\u00a0\u00a0\u00a0\u00a0\u00a0\u00a0\u00a0\u00a0 \u00a0\u00a0 or\u00a0\n\n\u00a0Laboratory Technician / Testing Engineer / Lab Super / Lab Manager\u00a0 with Fabric / Garment / Kidswear / Interlining / Garment Trims / Baby Products /\u00a0Chemical / Pharmaceutic / Medicine / Toys / Shoes / Foods / Houseware / Kitchenware / Product Safety / Furniture / Tools / Electrical Appliance / Electronic Products / Sports Goods / Packaging exp.\n\u00a0\u00a0\u00a0\u00a0\u00a0\u00a0\u00a0\u00a0 \u00a0\u00a0 or\u00a0\n\n\n\u00a0Sewer / Beading / Cutting Supervisor / Post-Production Supervisor\u00a0 for\u00a0 Woven / Cotton Knit / Fashion / Casual Wear / Denim / Underwear / Ironing / Packing / Beading\n\u00a0\u00a0\u00a0\u00a0\u00a0\u00a0\u00a0\u00a0\u00a0\u00a0\u00a0 or\n\n\n\u00a0QC Coordinator / Production Coordinator / Production Planner / Project Coordinator\u00a0 with\u00a0 Woven / Knit / Sweater / Underwear / Sleepwear / Sportswear / Kidswear / Shoes / Trdg / Buying Office / Manufacturing / Building Service / Building Construction / Lighting exp.\n\u00a0\u00a0\u00a0\u00a0\u00a0\u00a0\u00a0\u00a0\u00a0\u00a0\u00a0 or\n\n\n\u00a0Sample Coordinator / Sample Supervisor / Sample Manager\u00a0 with\u00a0 F.5 / T.I., 2-8 yrs Woven / Knit / Sweater / Fashion / Casual Wear / Underwear / Swimwear / Handbag / Fashion Acc exp.\n\n\n\u00a0\u00a0\u00a0\u00a0\u00a0\u00a0\u00a0\u00a0\u00a0\u00a0\u00a0 or\n\nAsst Chemist / Chemist / Chemical Management Officer / Manager in Textile / Toys / Electronic Fields with good knowledge and experience in Chemical Characteristic & Safety Standard / Chemical Analysis / Chemical Risk / Material Development / Testing / Wet Process / Laundry / RSL / ZDHC MRSL.\n\n\n\nProficient\u00a0English and Mandarin writing\u00a0& speaking\nWork in HK / China Stay / Cambodia / Thailand / Vietnam / Bangladesh / Philippines / Myanmar / Offshore Stay.\nSalary Range: HK$13K-$55K/Month\n\n\n\n\n*** Please send your detailed resume in \u201cword format\u201d including \" Expected Salary \", \u201cCompany Nature & Product\u201d & \u201cAvailability Date\u201d to our \u201cE-mail Address\u201d shown above or fax to \u201c2780 2672\u201d or by clicking \u201cApply Now\u201d.", "employment_types": ["Full Time", "Permanent"], "selling_points": ["F.5/Dip in Textile/Garment/Chemistry/Engineering", "4-10 yrs QC/Prodn/Technical/Fty Compliance exp", "Garment/Fabric/Hdbg/Shoes/Home Txtle/Watch/Toys"], "locations": ["Not Specified"], "categories": ["Sciences, Lab, R&D", "Laboratory", "Merchandising & Purchasing", "Fabrics", "Manufacturing", "Quality Assurance, Control & Testing / ISO"], "post_time": "2022-01-09T16:25:41Z", "salary": {"currency": null, "max": null, "min": null, "period": "monthly", "term": null}, "salary_visible": false, "title_keywords": ["technician"], "responsibilities": ["management", "analysis", "compliance", "production planning", "stationery", "checking", "testing", "industrial safety", "quality control", "audio", "catering"], "requirements": {"degrees": ["diploma"], "majors": ["chemistry"], "languages": ["english", "mandarin"], "language_level": ["proficient"], "hard_skills": ["planner", "acc", "apex", "analysis", "word", "rsl"], "soft_skills": ["detailed"], "languages_combined": [{"language": "english", "language_level": ["proficient"]}, {"language": "mandarin", "language_level": ["proficient"]}]}, "experience_required": {"duration": [], "field": ["toys", "management", "development", "testing", "textile"]}}, {"job_id": "100003009025810", "location_code": "hk", "company": "", "job_title": "Merchandiser / Merchandising Manager (Garment - Outerwear) - 5 day work", "description": "Merchandiser\u00a0\n\n\nHKCEE/HKDSE or above\u00a0\nAt least 5 years working experience in garment merchandising preferable with\u00a0outerwear / technical outerwear / Sportwear items in manufacturing background\u00a0\nAble to handle production sheet, material calculation and work out cost sheets throuth system\nResponsible for following up order from sample to bulk production, liaise with factory and customers\u00a0\nKnowldge of I-Net system is preferable\u00a0\n\nMerchandising Manager\u00a0\n\nAt least 10 years garment merchandising experience in managerial role\nOuterwear apparel experience preferabe with technical outerwear\u00a0\nWorking Experience in manufacturing company is required\u00a0\nAble to lead a team of 3 - 4 merchandisers\nFamiliar with PLM and ERP system will be an advantage\u00a0\nGood in English and Mandarin\u00a0\n\n\u00a0Company offers fringe benefits e.g. 5-day work, banking holiday,\u00a0 double pay, medical scheme ' to right candidates.\n\nInterested parties please send email to roco@biznetvigator.com or contact 2309 2138 for further details and to obtain application form.\n\n(Data collected is used for recruitment purpose only)", "employment_types": ["Full Time", "Permanent"], "selling_points": ["Experince in Woven Outerwear/Functional/Sportwear", "With garment manufacturing background peferable", "Merchandiser 5+ years exp, Manager 10+ years exp"], "locations": ["Kwai Fong"], "categories": ["Merchandising & Purchasing", "Fabrics", "Woven / Knit", "Procurement / Purchasing / Sourcing"], "post_time": "2022-01-06T06:32:57Z", "salary": {"currency": null, "max": null, "min": null, "period": "monthly", "term": null}, "salary_visible": false, "title_keywords": ["merchandiser", "merchandising manager"], "responsibilities": ["liaise with", "lead a team", "cost", "merchandising"], "requirements": {"degrees": ["hkdse"], "majors": [], "languages": ["english", "mandarin"], "language_level": ["good"], "hard_skills": ["erp system"], "soft_skills": ["responsible"], "languages_combined": [{"language": "english", "language_level": ["good"]}, {"language": "mandarin", "language_level": ["good"]}]}, "experience_required": {"duration": ["at least 10 years", "at least 5 years"], "field": ["garment", "managerial", "manufacturing", "merchandising"]}}, {"job_id": "100003009014981", "location_code": "hk", "company": "", "job_title": "Purchasing clerk/ Trims Sales / Trims Coordinator -- Fabric/Garment/Trims", "description": "Responsibilities\n\n\n\n1. Provide office administration support for the company\n\n2. Provide secretarial support to the management\n\n3. Handle\u00a0and submit\u00a0motor vehicle license application\u00a0\n\n4. Handle leave applications and recuitment\n\n5. Perform general clerical duties including data entry, filing records\n\n6. Support front desk duty (answering calls, greeting guests, handling courier/mail)\n\nQualification\n\n1. Good command of both written and spoken English, Chinese & Putonghua\n\n2. Well-versed with internet and MS Office and Chinese word processing\n\n3. Self-motivated, responsible, multi-tasked and able to meet tight deadline and work under pressure\n\n4. Good communication and interpersonal skills and well-organized\n\n5. Experience in handling insurance license matter is a definite plus.\n\n6. Immediate availability is preferred", "employment_types": ["Full Time", "Permanent"], "selling_points": [], "locations": ["Cheung Sha Wan"], "categories": ["Manufacturing", "Garment / Textile", "Merchandising & Purchasing", "Fabrics", "Printing"], "post_time": "2022-01-03T04:46:15Z", "salary": {"currency": null, "max": null, "min": null, "period": "monthly", "term": null}, "salary_visible": false, "title_keywords": ["coordinator", "purchasing clerk", "sales"], "responsibilities": ["management", "office administration support", "data entry", "communication", "secretarial support", "license application", "insurance", "work under pressure"], "requirements": {"degrees": [], "majors": [], "languages": ["putonghua", "english", "chinese"], "language_level": ["good command"], "hard_skills": ["plus", "chinese word processing", "ms office"], "soft_skills": ["self-motivated", "responsible", "well-organized", "multi-tasked", "communication and interpersonal skills", "meet tight deadline", "work under pressure"], "languages_combined": [{"language": "putonghua", "language_level": ["good command"]}, {"language": "english", "language_level": ["good command"]}, {"language": "chinese", "language_level": ["good command"]}]}, "experience_required": {"duration": [], "field": ["insurance"]}}, {"job_id": "100003009019742", "location_code": "hk", "company": "Sung IL International Company Limited", "job_title": "HR & Admin Assistant", "description": "Responsibilities:\u00a0\n\nSource and develop seasonal fabric to meet the business need\nMonitor sample fabric ordering process, testing and inspection\nNegotiate with supplier for cost, agreement, quality and other production issues\nResearch on new fabric development and fashion trend and prose to design team for new concept\nMaintain and expand wide sourcing network\nWork with Production team and factories to solve any fabric issues that may arise at the bulk stage\nReview and evaluate the performance of fabric mill and propose changes whenever necessary\n\nRequirements:\n\nDegree in Textile Design or Technology\nMinimum 8 years relevant working experience with 2 years at supervisory level\nExtensive knowledge in fiber, weaving, dyeing and finishing, testing and inspection with strong fashion sense\nSolid experience in fashion fabric development, with knowledge in China fabric market a MUST\nStrong communication, negotiation and organization skill\nGood computer skills including MS Excel, MS Word and Chinese word processing\nGood command of spoken and written English and Chinese (including Cantonese & Mandarin)\n\nWe offer an attractive package, good prospects and fringe benefits to the right candidate. Interested parties, please apply with full resume, current and expected salary to: Group Human Resources Manager of High Fashion Group. By click below \"APPLY NOW\"(in MS Word format), or by mail: 11/F., High Fashion Centre, 1-11 Kwai Hei Street, Kwai Chung, New Territories\n\n(The information received will be used for consideration of employment only and all personal data supplied will be destroyed within 6 months.)", "employment_types": ["Full Time"], "selling_points": [], "locations": ["Kwai Fong"], "categories": ["Manufacturing", "Garment / Textile", "Merchandising & Purchasing", "Fabrics", "Textiles"], "post_time": "2022-01-04T08:35:13Z", "salary": {"currency": null, "max": null, "min": null, "period": "monthly", "term": null}, "salary_visible": false, "title_keywords": ["hr & admin assistant"], "responsibilities": ["cost", "review", "monitor", "quality", "design", "testing", "inspection", "develop", "evaluate", "maintain"], "requirements": {"degrees": ["degree"], "majors": ["design"], "languages": ["cantonese", "english", "chinese", "mandarin"], "language_level": ["good command", "good"], "hard_skills": ["chinese word processing", "ms excel", "computer skills", "ms word"], "soft_skills": ["communication", "extensive", "negotiation", "organization skill"], "languages_combined": [{"language": "cantonese", "language_level": ["good command", "good"]}, {"language": "english", "language_level": ["good command", "good"]}, {"language": "chinese", "language_level": ["good command", "good", "good"]}, {"language": "mandarin", "language_level": ["good command", "good"]}]}, "experience_required": {"duration": ["minimum 8 years", "2 years"], "field": ["supervisory level", "development", "relevant working experience"]}}, {"job_id": "100003009014316", "location_code": "hk", "company": "High Fashion Group", "job_title": "Fabric Manager", "description": "Takara Company\n\nPurchasing clerk/ Trims Sales / Trims Coordinator --\u00a0 Fabric/Garment/Trims/Zipper/label\n\u00a0\n-\u00a0F.5, IVE, Poly Graduate, Fresh Grad\u00a0\n- Good English & Mandarin\n- Factory experiences and advantage\n- Good knowledge of Sourcing, sampling and following orders\n\u00a0 - MUST Be immediate available\n\u00a0\n\u00a0\n\n\n\nPlease send your application with detailed resume and expected salary to\nhr@takara.hk\u00a0\u00a0\n**Personal data collected will be used for recruitment purpose only**\n", "employment_types": ["Full Time", "Permanent"], "selling_points": ["5 days, bonus, medical & life insurance", "Lunch allowance, birthday leave", "Flexible working hours"], "locations": ["Kwai Fong"], "categories": ["Manufacturing", "Garment / Textile", "Product Development / Management", "Merchandising & Purchasing", "Fabrics"], "post_time": "2022-01-03T03:16:05Z", "salary": {"currency": null, "max": null, "min": null, "period": "monthly", "term": null}, "salary_visible": false, "title_keywords": ["fabric manager"], "responsibilities": ["personal data", "recruitment"], "requirements": {"degrees": [], "majors": [], "languages": ["english", "mandarin"], "language_level": ["good"], "hard_skills": [], "soft_skills": ["detailed"], "languages_combined": [{"language": "english", "language_level": ["good"]}, {"language": "mandarin", "language_level": ["good"]}]}, "experience_required": {"duration": [], "field": []}}, {"job_id": "100003009011357", "location_code": "hk", "company": "Baikai (HK) Industrial Limited", "job_title": "Merchandiser (Base in Hong Kong \u2013 Kwun Tong)", "description": "Qualification:\nWorking experience of around 2-3 years in merchandising, preferably with manufacturing\nProficiency in MS Office Application and Chinese word processing\nGood command of spoken and written English and Chinese (both Cantonese and Mandarin)\n\u00a0Job Duties:\n\nWork closely with internal/external teams on lab dip issues and bulk order follow up, to ensure on time delivery and that quality meets requirements\nmaintain good relationship with clients\nMake sure the merchandising and production process is smooth and information is correct to all relevant departments\nInvolve product development procedures\n\u00a0Benefits\n\n5 days work\n10 days annual leaves\nBanking holidays\nPlease apply by sending a detailed resume stating employment history with dates and expected salary by clicking \"Apply Now\"\n\nData collected will be used for recruitment purposes only.", "employment_types": ["Full Time", "Permanent"], "selling_points": [], "locations": ["Kwun Tong"], "categories": ["Merchandising & Purchasing", "Fabrics", "Woven / Knit", "Sales, CS & Business Devpt", "Others"], "post_time": "2021-12-31T07:00:14Z", "salary": {"currency": null, "max": null, "min": null, "period": "monthly", "term": null}, "salary_visible": false, "title_keywords": ["merchandiser"], "responsibilities": ["production process", "ensure on time delivery", "quality", "teams", "merchandising", "maintain good relationship", "procedures"], "requirements": {"degrees": ["dip"], "majors": [], "languages": ["cantonese", "english", "chinese", "mandarin"], "language_level": ["proficiency", "good command"], "hard_skills": ["make", "chinese word processing", "ms office"], "soft_skills": ["smooth"], "languages_combined": [{"language": "cantonese", "language_level": ["good command"]}, {"language": "english", "language_level": ["good command"]}, {"language": "chinese", "language_level": ["proficiency", "good command"]}, {"language": "mandarin", "language_level": ["good command"]}]}, "experience_required": {"duration": ["2-3 years"], "field": ["manufacturing", "merchandising"]}}, {"job_id": "100003009012142", "location_code": "hk", "company": "Eternity Consultants (HK) Ltd", "job_title": "Merchandiser / Senior Merchandiser  (Product Development)-  Sportswear / Activewear- Buying office", "description": "Requirements:\n\nF.7, Diploma or above\nAt least \u00a06-8 years in Merchandising in Activewear or Sportswear in Trading / Buying office\nProduct Development and Costing\u00a0\nWork with buyer to product development\nPrice negotiation with vendors to achieve margin.\nReview all salesman samples and make sure all products are meeting requirement.\nManage supplier relationships and monitoring supplier performance.\nWork with compliance and quality team to ensure all vendors are meeting compliance and quality standards.\nUsing Vlook up, pivot table\nPrepare collection overview and order confirmation reports. Analyse style hit rate and order index monthly\n\nMany positions are not been posted in media.\u00a0 If you are looking for job in merchandising field, we are welcome you send your resume to us direct.\n\n*Interested parties, please send full resume with current & expected salary & date available in MS WORD FORMAT ONLY to our email address\u00a0or fax to 3527 0634*\n\nFor more jobs, please visit our website:\u00a0www.hketernity.com\n\n(Personal data submitted are for recruitment purpose only.)", "employment_types": ["Full Time", "Permanent"], "selling_points": ["Diploma or above", "6 -8 years in merchandising in activewear", "Sportswear in trading, Buying office"], "locations": ["Not Specified"], "categories": ["Merchandising & Purchasing", "Fabrics", "Woven / Knit", "Procurement / Purchasing / Sourcing"], "post_time": "2021-12-31T16:58:31Z", "salary": {"currency": null, "max": null, "min": null, "period": "monthly", "term": null}, "salary_visible": false, "title_keywords": ["merchandiser", "product development", "senior merchandiser"], "responsibilities": ["price negotiation", "compliance", "review", "merchandising", "monitoring", "quality", "reports", "analyse"], "requirements": {"degrees": ["diploma or above"], "majors": [], "languages": [], "language_level": [], "hard_skills": ["make", "pivot table"], "soft_skills": ["negotiation"], "languages_combined": []}, "experience_required": {"duration": [], "field": []}}, {"job_id": "100003009010080", "location_code": "hk", "company": "Super Hunter Services Co. Limited", "job_title": "Merchandising Clerk ( Textile Corporation )", "description": "Responsibilities\n\nSupport and coordinationfrom product development, sampling, production orders to delivery\nPrepare and handle various shippingdocuments, eg. invoices and P/L, etc., work with shipping company for the shipment arrangement\nManage goods return, ATA carnet and payment follow-up\nEstablish and maintain good rapport with customers and factory\nAny ad hoc assignments\n\n\u00a0Requirements\n\nDiploma or above.\n1-2 years\u2019 relevant experience in garment/ textile industry is an advantage.\nProficiency in spoken and written English and Chinese (Cantonese & Mandarin).\nSound knowledge in PC operations.\nGood interpersonal and communication skills, well-organized, patient, self-initiative.\nFresh graduate will also be considered(with textile or garment education background).\n\n\u00a0Interested parties please\u00a0send\u00a0your detail resume in MS WORD\u00a0format\u00a0with current and expected salary\u00a0through\u00a0\u201cAPPLY NOW\u201d\n\nAll data collected will be used for recruitment purpose only & will be used strictly confidential\n\nOnly shortlisted candidates will be notified", "employment_types": ["Permanent"], "selling_points": ["Good working location, convenient.", "Good package.", "Fresh graduate will be considered."], "locations": ["Not Specified"], "categories": ["Merchandising & Purchasing", "Fabrics", "Textiles"], "post_time": "2021-12-31T03:01:49Z", "salary": {"currency": null, "max": null, "min": null, "period": "monthly", "term": null}, "salary_visible": false, "title_keywords": ["merchandising clerk"], "responsibilities": ["shipping", "invoices", "shipment arrangement", "payment", "maintain", "ad hoc assignments", "ata carnet"], "requirements": {"degrees": ["fresh graduate", "diploma or above"], "majors": [], "languages": ["cantonese", "english", "chinese", "mandarin"], "language_level": ["proficiency"], "hard_skills": ["pc operations"], "soft_skills": ["communication skills", "well-organized", "self-initiative", "patient", "interpersonal"], "languages_combined": [{"language": "cantonese", "language_level": ["proficiency"]}, {"language": "english", "language_level": ["proficiency"]}, {"language": "chinese", "language_level": ["proficiency"]}, {"language": "mandarin", "language_level": ["proficiency"]}]}, "experience_required": {"duration": ["1-2 years"], "field": ["garment", "relevant experience", "textile"]}}, {"job_id": "100003009000721", "location_code": "hk", "company": "Carrefour Global Sourcing Asia Limited", "job_title": "Technical Engineer (Textile)", "description": "Responsibilities\n\nResponsible for the on time fitting development, respecting criteria and comments from counterparts in Europe and managing communication with the suppliers. (Measurement chart, patterns, product construction).\nManage the good respect of the wear & safety legislation (included in Carrefour Quality charter)\nResponsible for the respect of the technical comments done by DCG\nManage the development timing respect in order to avoid any delay to start production\nClose communication with Technical Department & Merchandisers for a good understanding of the buyer's requirement, and with the suppliers for a close follow-up (comments respect and timing)\nProvide technical comment on the look & comfort aspect of the garment (fabric aspect, shape, assembling and finishing)\n\nRequirements\n\n\nDegree holder in clothing technology and production\n3 years minimum fitting experience in industry\nExpertise in garment making, assembly and fitting\nKnowledge for the category is a plus but not mandatory\nGood understanding of customers perceived quality and quality expectation\nGood communication skills, detail-orientated\nSolid experience directly work with manufacturing factories in China and Far East\nGood skills in Excel and system\nFast thinking, excellent problem solving and teamwork sense\nFluent in English and Mandarin\n\nShortlisted candidates will be invited to our digital interview platform for the next round of interview process.", "employment_types": ["Full Time", "Permanent"], "selling_points": [], "locations": ["Kowloon Bay"], "categories": ["Merchandising & Purchasing", "Fabrics", "Textiles"], "post_time": "2021-12-27T16:04:09Z", "salary": {"currency": null, "max": null, "min": null, "period": "monthly", "term": null}, "salary_visible": false, "title_keywords": ["technical engineer"], "responsibilities": ["communication", "quality", "comments", "measurement"], "requirements": {"degrees": ["degree holder"], "majors": [], "languages": ["english", "mandarin"], "language_level": ["fluent"], "hard_skills": ["problem solving", "excel", "plus"], "soft_skills": ["problem solving", "communication skills", "teamwork"], "languages_combined": [{"language": "english", "language_level": ["fluent"]}, {"language": "mandarin", "language_level": ["fluent"]}]}, "experience_required": {"duration": ["3 years"], "field": ["manufacturing"]}}, {"job_id": "100003009008385", "location_code": "hk", "company": "ConnectedGroup Limited", "job_title": "Assistant Production Manager (Apparel)", "description": "Assistant Production Manager (Apparel)\n\n\nOur client is a US sportswear buying office and they are looking for an Assistant Production Manager (Apparel). Working closely with the Manager, you will be supervising 1-2 staffs for operations across 3 main sourcing regions: China, Vietnam, Cambodia.\n\n\nKey responsibilities: -\n\nVendor management\nAnalyse, evaluate and improve vendor's capabilities and performance\nExpand or consolidate vendor base when appropriate\nPrice negotiation and create detailed cost saving plans and methods\nLead-time negotiation along with regular trouble shooting issues such as deliveries and quality issues\nMerchandising Activities\nSupervise and lead the merchandising operations\nFollow production plans to ensure all orders are shipped on time\nConstant interaction and consultation on vendor capacity, order allocation etc.\nObserve and understand in detail the buyer's needs and provide as much support as possible\nCommunications with internal support teams\nAssist in certain quality driven initiatives\nAssist in any quality issues, claims or disputes between buyers/QA with vendors\nMonitor potential quality issues and execute relative solutions to ensure they can be avoided\n\nRequirements: -\n\n(Must) Bachelor's degree of above in Textiles / Fashion or related discipline\nPositive, flexible\nMinimum 8 years relevant sourcing experience\nStrong experience managing production\n\n\nInterested parties pls send your CV Angela Tsui angela.tsui@connectedgroup.com for more details.\n\nFor other available opportunities, please visit www.connectedgroup.com\n\n", "employment_types": ["Full Time", "Permanent"], "selling_points": ["US sportswear buying office", "Leads 1-2 staffs, reports to Manager", "Production focused"], "locations": ["Not Specified"], "categories": ["Merchandising & Purchasing", "Fabrics", "Procurement / Purchasing / Sourcing"], "post_time": "2021-12-30T07:49:14Z", "salary": {"currency": null, "max": null, "min": null, "period": "monthly", "term": null}, "salary_visible": false, "title_keywords": ["assistant production manager"], "responsibilities": ["cost", "management", "price negotiation", "communications with", "operations", "quality", "merchandising", "teams", "monitor", "evaluate", "plans", "analyse"], "requirements": {"degrees": ["degree", "bachelor"], "majors": [], "languages": [], "language_level": [], "hard_skills": [], "soft_skills": ["flexible", "positive"], "languages_combined": []}, "experience_required": {"duration": ["minimum 8 years"], "field": []}}, {"job_id": "100003009002616", "location_code": "hk", "company": "TMS Holding Limited", "job_title": "Product Coordinator", "description": "A\u00a0leading designer and distribution agent of interior design fabrics is looking for a\u00a0Product Coordinator to join their team.\n\nResponsibilities\u00a0\n\nProduct sourcing (interior furnishing fabric)\u00a0\nOrder handling from sample development to bulk order\u00a0\nCoordinate between different internal and external parties\u00a0\nMaintain accurate and comprehensive data records in the system\u00a0\nHandle in and out inventory and maintain proper stock records\u00a0\u00a0\n\nRequirements\u00a0\n\nHigh Diploma in Textile or\u00a0has knowledge through working experience\nPassionate in interior furnishing industry\u00a0\nSelf-driven, excellent organizational skill with demonstrated initiative\u00a0\nProficiency in computer skill, especially MS Excel\u00a0\nGood command of both written and spoken English & Chinese (Cantonese and Mandarin)\u00a0\n\nInterested parties please click \"Apply now\" and attached your full resume with expected salary.", "employment_types": ["Full Time", "Permanent"], "selling_points": ["Interior furnishing industry", "Have textile/ fabrics knowledge", "Passionate in interior design/ furnishing"], "locations": ["Aberdeen"], "categories": ["Manufacturing", "Garment / Textile", "Merchandising & Purchasing", "Fabrics", "Furniture"], "post_time": "2021-12-28T06:33:59Z", "salary": {"currency": null, "max": null, "min": null, "period": "monthly", "term": null}, "salary_visible": false, "title_keywords": ["coordinator"], "responsibilities": ["data", "inventory", "internal and external parties", "coordinate", "maintain"], "requirements": {"degrees": ["high diploma"], "majors": [], "languages": ["cantonese", "english", "chinese", "mandarin"], "language_level": ["good command"], "hard_skills": ["ms excel", "computer skill"], "soft_skills": ["passionate", "initiative", "organizational skill", "driven"], "languages_combined": [{"language": "cantonese", "language_level": ["good command"]}, {"language": "english", "language_level": ["good command"]}, {"language": "chinese", "language_level": ["good command"]}, {"language": "mandarin", "language_level": ["good command"]}]}, "experience_required": {"duration": [], "field": ["textile"]}}, {"job_id": "100003009003411", "location_code": "hk", "company": "Marks and Spencer (Hong Kong) Investments Limited", "job_title": "Fit Technologist (Lingerie)", "description": "Convenient location: Harbour City,\u00a0Tsim Sha Tsui\n\nJob Description:\nProactively communicate with and provide technical support to factory on pattern grading\nAttend product risk assessment meetings with suppliers,\u00a0evaluate the sampling for the production, identify the difficulties that may arise during the pre-production stage and estimate the production efficiency\nPre screen all first fits and c/seals in region before sample to counterpart for final approval\nArrange wearer trials, provide fitting comment and technical advice to ensure the products or samples meet the standards\nResponsible for fitting approval locally on grade and pilot for all direct suppliers\nWork closely with supplier on PU cup development\n\nRequirement:\nTertiary education with technical qualification in Lingerie\nAt least 5 years\u2019 relevant experience for the UK / European market\nFamiliar with the UK Retail industry and/or European garment buying processes\nFamiliar with fitting approval on lingerie product, able to provide correction, direction and issue comment\nStrong knowledge of\u00a0 Pattern Making, Grading, Fitting, garment construction and sewing technique\nKnowledge of fabric and raw material of Lingerie product\nBuild strong relationships with buyers and technologists in the UK and suppliers in country\nSelf-motivated, independent, result-oriented\nExcellent communication skills in English; good level of both written & spoken Putonghua is highly preferred\nFamiliar with MS Office; proficient in PLM system is an advantage\n\nYou Can Enjoy:\u00a0\n\nDouble Pay\nDiscretionary Bonus\nMedical & Life Insurance\nFree Health Checkup\nFlexible Working Hour\nSpecial Leaves\nWellness Program\nConvenient Location: Tsim Sha Tsui\nInterested parties please apply with full resume, state current and expected salaries by clicking\u00a0\"Apply Now\".\n\n\nAll applications and data collected will be treated in strict confidence and used exclusively for recruitment purposes.\u00a0 Only short listed candidates will be invited for interview. The company will retain the applications for a maximum period of 24 months and may refer suitable candidates to other vacancies\u00a0", "employment_types": ["Full Time", "Permanent"], "selling_points": ["5 years\u2019 Lingerie Fit Tech exp. for EU market", "MNC exposure and development", "Double Pay & Comprehensive Benefit Scheme"], "locations": ["Tsim Sha Tsui"], "categories": ["Manufacturing", "Garment / Textile", "Merchandising & Purchasing", "Fabrics", "Quality Assurance, Control & Testing / ISO"], "post_time": "2021-12-28T09:05:32Z", "salary": {"currency": null, "max": null, "min": null, "period": "monthly", "term": null}, "salary_visible": false, "title_keywords": [], "responsibilities": ["communicate with", "technical support", "technical advice", "evaluate", "pre-production"], "requirements": {"degrees": [], "majors": [], "languages": ["putonghua", "english"], "language_level": ["excellent", "good"], "hard_skills": ["ms office"], "soft_skills": ["flexible", "communication skills", "self-motivated", "independent", "result-oriented"], "languages_combined": [{"language": "putonghua", "language_level": ["good"]}, {"language": "english", "language_level": ["excellent"]}]}, "experience_required": {"duration": ["at least 5 years"], "field": ["relevant experience"]}}, {"job_id": "100003009002303", "location_code": "hk", "company": "TAL Apparel Limited", "job_title": "Fabric Development Executive", "description": "To achieve our Company\u2019s business targets, the incumbent shall manage the research, collection and development of fabrics and mill sources in order to secure orders from external customers. Details as below:\n\nKey Responsibilities\n\nResearch and stay abreast of new technologies, new mill sources, new fabrications, new collections that are coming into market and may be of interest to the teams.\nWorking closely and in collaboration with Fabric Sourcing team to insure synergy in all fabric sourcing initiatives and tasks.\nWorking closely with Senior Product Development Manager to align on market trends and support the garment development with the right fabrics\nSource sample fabrics and trims required for Collection development and share the sourced materials with all internal partners and external customers\nManage good supplier relationships\nWilling to travel occasionally within Asia\n\nRequirements\n\nBachelor degree holder with preference in Textile & Clothing\n4-5 years of experience preferably in supply chain management functions under a manufacturing, consumer goods or retail (including buying offices) setting.\nExperience in textile/apparel industry is a plus\nGood understand of supply chain management concepts such as supplier management, lead time, quality etc.\nStrong communication and customer servicing mindset\nExcellent command in English & Mandarin\nProficient in MS Office (e.g. Word, Excel and PowerPoint)\n\nWe offer a 5-day working week, a competitive remuneration package and generous fringe benefits. Excellent on-the-job training and development will also be provided.\n\nTo apply, please send your full resume, including salary expectation and availability, to Human Capital Management Department. Only shortlisted applicants will be contacted. All information will be kept in strict confidence and will be used for employment purpose only.", "employment_types": ["Full Time", "Permanent"], "selling_points": ["Manage good supplier relationships", "Bachelor degree holder with preference", "4-5 years of experience preferably in supply chain"], "locations": ["Yau Tsim Mong Area"], "categories": ["Merchandising & Purchasing", "Fabrics", "Woven / Knit", "Procurement / Purchasing / Sourcing"], "post_time": "2021-12-28T04:30:00Z", "salary": {"currency": null, "max": null, "min": null, "period": "monthly", "term": null}, "salary_visible": false, "title_keywords": ["executive"], "responsibilities": ["teams"], "requirements": {"degrees": ["bachelor degree holder"], "majors": [], "languages": ["english", "mandarin"], "language_level": ["excellent"], "hard_skills": ["excel", "plus", "word", "powerpoint", "ms office"], "soft_skills": ["communication"], "languages_combined": [{"language": "english", "language_level": ["excellent"]}, {"language": "mandarin", "language_level": ["excellent"]}]}, "experience_required": {"duration": ["4-5 years"], "field": ["management", "manufacturing", "buying offices", "supply chain", "textile", "retail"]}}, {"job_id": "100003009004127", "location_code": "hk", "company": "TRI-Come Recruitment Search", "job_title": "Sourcing Manager / Purchasing Manager / Senior Merchandiser  (Fabric/ Garment Trims/ Home Textile)", "description": "Minimum 5 years Merchandising experience in Fabric/ Garment Trims / Home Textile items\nEquip with strong product knowledge to work with designers and garment factories to turn out quality products with justifiable value.\nEquip with strong communication and negotiation skill to work with both suppliers and buyers.\nGood product sourcing.\n\u00a0\nTextile & Clothing\u00a0Certificate or similar qualification in Technical Institute.\nGood written and spoken English\u00a0/ Mandarin is preferable\nWilling to travelling", "employment_types": ["Full Time", "Permanent"], "selling_points": [], "locations": ["Yau Tsim Mong Area"], "categories": ["Merchandising & Purchasing", "Electronics", "Fabrics", "Woven / Knit"], "post_time": "2021-12-29T01:20:24Z", "salary": {"currency": null, "max": null, "min": null, "period": "monthly", "term": null}, "salary_visible": false, "title_keywords": ["purchasing manager", "senior merchandiser", "sourcing manager"], "responsibilities": ["communication", "quality", "merchandising"], "requirements": {"degrees": ["certificate"], "majors": [], "languages": ["english", "mandarin"], "language_level": ["good"], "hard_skills": [], "soft_skills": ["communication", "negotiation skill"], "languages_combined": [{"language": "english", "language_level": ["good"]}, {"language": "mandarin", "language_level": ["good"]}]}, "experience_required": {"duration": ["minimum 5 years"], "field": ["garment", "merchandising", "textile"]}}, {"job_id": "100003008996411", "location_code": "hk", "company": "PVH Far East Limited", "job_title": "Manager, Raw Material (Knit)", "description": "Job Responsibilities:\n\nResponsible for managing the overall process of new and seasonal fabrics that meet designer's aesthetic vision while balancing quality, cost and speed\nProvide inspirational leadership to direct reports\nEffectively executes against design briefs\nManage and train mills across defined region\nPerform periodic SWOT analysis of mill performance and alignment to strategic sourcing needs\nOversee fabric testing and ensure mills understand expectations\nProactively monitor and meet calendar deadlines for approvals and mill executive\nMaintain a supply chain that supports the overarching strategic vision\nCollaborate with Mills, Raw Material team, and Supply Chain Partners\nJob Requirements:\n\nDegree in Textile or related subject with 8 years or above relevant industry experience\nExtensive knowledge of raw materials, construction, costing, macro-economic trends, capacity planning and Chemicals\nStrong organizational skills\nResults & solutions driven\nAble to drive change, inspire, coach, mentor and develop a high performing team\nAble to establish and maintain strong working relationships cross-functionally and cross-divisionally, as well as externally\nStrong negotiating skills in diverse cultural environments\nAbility to balance competing priorities in a fast-paced environment\nComputer literate, knowledge of Web PLM preferred\u00a0\nGood command of both spoken and written English\nPrevious people management experience is a plus\nInterested parties please send your full resume, current package, salary expectation and date of availability to us by clicking \u201cApply Now\u201d.\n(Applicants not contacted within six weeks should consider their application unsuccessful. Personal data provided by applicants will be treated confidence and used solely for recruitment purpose only.)", "employment_types": ["Full Time", "Permanent"], "selling_points": ["Responsible for managing the overall process", "Provide inspirational leadership to direct reports", "8 years or above relevant industry experience"], "locations": ["Lai Chi Kok"], "categories": ["Manufacturing", "Garment / Textile", "Merchandising & Purchasing", "Fabrics"], "post_time": "2021-12-23T07:05:59Z", "salary": {"currency": null, "max": null, "min": null, "period": "monthly", "term": null}, "salary_visible": false, "title_keywords": ["manager"], "responsibilities": ["collaborate with", "cost", "quality", "monitor", "testing", "design briefs", "maintain", "reports", "swot analysis"], "requirements": {"degrees": ["degree"], "majors": [], "languages": ["english"], "language_level": ["good command"], "hard_skills": ["macro", "web", "plus"], "soft_skills": ["organizational skills", "fast-paced environment", "diverse", "extensive", "driven"], "languages_combined": [{"language": "english", "language_level": ["good command"]}]}, "experience_required": {"duration": ["8 years"], "field": ["textile", "people management", "related"]}}, {"job_id": "100003009001943", "location_code": "hk", "company": "Randstad Hong Kong Limited", "job_title": "APAC Head of Product Management - Household accessory", "description": "APAC Head of Product Management - Household accessory\n\nWe're partnering with a rapidly growing ecommerce business focusing on household accessories in finding a newly created Head of Product Management for their growing with a regional scope.\n\nThe Head of Product Management will be responsible in leading the product management team in developing, modifying and launching new products onto the ecommerce platform across the APAC region. This will include formulating commercial go-to-market strategies, collaborating & communicating with different stakeholders (internally & externally), market/competition analysis and providing business strategies to minimize competition gaps.\n\nJob responsibilities:\n\nTake lead in business directions and strategies related to the responsible product category including formulating tailored go-to-market strategies, new product development etc.\nPerform analysis to understand the market competition (digital & ecommerce), identify gaps and provide recommendations and solutions to minimize the gap\nCommunication and collaboration with internal (sales, marketing, digital, logistics etc.) and external (agencies, factories, manufacturers) stakeholders across the region to ensure timely and accurate execution of project/campaigns\nResponsible for P&L and budgeting to ensure product management team is providing the necessary support to reach business objectives\nResponsible in providing coaching and training to the team to ensure high performance and motivation\n\nJob requirements:\n\nDegree holder\nMinimum 10 years experience in product management, preferably in the household/consumer accessories category\nExperience in an e-commerce business is a bonus\nStrong interpersonal, negotiation and communication skills\nTeam player and ability to lead a cross-regional and multicultural team\nSelf-motivated, entrepreneurial and result driven\nStrong project management skills\nFluent in both spoken and written English, Cantonese and Mandarin communication. Any additional language is a bonus\n\nInterested candidates, please send updated resume to Tommy Wong at tommy.wong@randstad.com.hk", "employment_types": ["Full Time", "Permanent"], "selling_points": [], "locations": ["Not Specified"], "categories": ["Manufacturing", "Product Development / Management", "Merchandising & Purchasing", "Fabrics", "E-commerce", "Marketing - Brand / Product Management"], "post_time": "2021-12-28T03:22:52Z", "salary": {"currency": "HKD", "max": 89999, "min": 70000, "period": "monthly", "term": null}, "salary_visible": true, "title_keywords": [], "responsibilities": ["management team", "budgeting", "analysis", "p&l", "communication", "logistics", "provide recommendations"], "requirements": {"degrees": ["degree holder"], "majors": [], "languages": ["cantonese", "english", "mandarin"], "language_level": ["fluent"], "hard_skills": ["project management", "e-commerce"], "soft_skills": ["communication skills", "self-motivated", "negotiation", "project management skills", "driven", "communication", "team player", "interpersonal"], "languages_combined": [{"language": "cantonese", "language_level": ["fluent"]}, {"language": "english", "language_level": ["fluent"]}, {"language": "mandarin", "language_level": ["fluent"]}]}, "experience_required": {"duration": ["minimum 10 years"], "field": ["product management", "business", "e-commerce"]}}, {"job_id": "100003008989635", "location_code": "hk", "company": "Epic Group", "job_title": "Senior Fabric Merchandiser (Knit/Athleisure/Activewear)", "description": "The role will be responsible for actively managing core functions of development and procurement of fabric for Athleisure/ Sportswear/ Active wear. And will identify, negotiate, and penetrate new opportunities with vendors, suppliers, and mills to effectively achieve customer needs.\nThe role will report to and support the Merchandising team to accomplish the Fabric procurement roadmap and set standards through vendor management matrix and process enhancements.\n\nJob Responsibilities\u00a0include -\u00a0but not limited to -\n\nActively managing the global procurement for fabrics, coordinate and negotiate with vendors on price, quality, quantity, lead times.\nResearch and keep abreast of fabric trends and technological developments.\nResponsible for all testing and quality assurance control for all fabrics.\nCollaborate proactively with suppliers, designers, and merchandisers in identifying core and novel fabrics aligned with overall procurement strategy & direction.\nAdhere to all sourcing schedules to meet customer delivery requirements.\nPlace orders for test fabric, proto yardage, and track accordingly\nCreate and maintain seasonal fabric detail chart, fabric library for each season.\nCoordinate goods between fabric mill and garment factory.\nAssist & support the team in delivering, leading & executing the overall procurement strategy & vision.\nWork along with senior team members to continually add-value for customers and reduce costs of purchasing for the company.\nPlan and monitor production deliveries, plus review and track vendor performance\u00a0 \u00a0 \u00a0\nOversee updating of Work in Progress tracking and validating dates corresponding to production calendar.\nWork on projects and tasks as assigned with the Senior Management aligned with the vision and strategy of the company.\nQualifications the candidate must possess\n\n\nForm 5 or above, Diploma in Business/ Clothing /Textile/ Merchandising or related discipline.\nMinimum 5-8 years\u2019 of relevant experience in Manufacturing/RMG industry.\nKnowledge of development and sourcing Knit fabric is a must.\nExperience in Sportwear/ Athleisure /Activewear is preferred.\nExcellent negotiation skills.\nExcellent command of written and spoken English, Mandarin.\nGood knowledge of MS Office tools.\nWe offer a competitive remuneration package, including\u00a0medical insurance, double pay and 5 days week\u00a0and good career opportunities to the qualified candidate. Interested candidates, please email full resume with expected salary to HR Department by clicking 'Apply Now'.\n\nFor company information, please refer to the web site\u00a0www.EpicHK.com\n\nAll information received will be kept in strict confidence and only for employment-related purpose.", "employment_types": ["Full Time", "Permanent"], "selling_points": ["5-8 yrs Fabric Dev. & Sourcing exp.", "Knit wear, Sportswear, Activewear, Athleisure", "5 day work week, Double pay, Medical Insurance"], "locations": ["Kwun Tong"], "categories": ["Manufacturing", "Garment / Textile", "Merchandising & Purchasing", "Fabrics", "Woven / Knit"], "post_time": "2021-12-21T04:42:24Z", "salary": {"currency": null, "max": null, "min": null, "period": "monthly", "term": null}, "salary_visible": false, "title_keywords": ["fabric merchandiser"], "responsibilities": ["schedules", "quality", "merchandising", "maintain", "plan", "senior management", "costs", "collaborate", "control", "monitor", "testing", "report", "management", "review", "executing", "support the team", "tracking", "coordinate", "insurance"], "requirements": {"degrees": ["diploma", "form 5 or above"], "majors": ["business"], "languages": ["english", "mandarin"], "language_level": ["excellent"], "hard_skills": ["plus", "vendor", "ms office"], "soft_skills": ["novel", "active", "negotiation skills", "responsible"], "languages_combined": [{"language": "english", "language_level": ["excellent"]}, {"language": "mandarin", "language_level": ["excellent"]}]}, "experience_required": {"duration": ["minimum 5-8 years"], "field": ["manufacturing", "relevant experience"]}}, {"job_id": "100003008991129", "location_code": "hk", "company": "BW Global (HK) Limited", "job_title": "Merchandiser / Sales Operations (Fashion Software)", "description": "Browzwear\u00a0is the leading provider of 3D fashion design, development, and merchandising solutions. Our mission is to revolutionize the apparel industry with our truly disruptive 3D technology, providing the exact tools needed to exploit the extensive opportunities in the market to achieve that goal. We work with some of the biggest and most well-known global companies in the industry.\n\nWe are looking for a talented full-time Merchandiser / Sales Operations to join our growing\u00a0Sales team.\u00a0\u00a0\n\n\u00a0The Role:\u00a0\n\nThe Fashion Merchandiser / Sales Operations\u00a0role supports our sales team, across regions. This role acts as a business enabler to the sales team, helping them achieve revenue goals by ensuring process consistency and quality, implementing new processes to improve efficiency for the pre & post-sales activities.\u00a0\n\nThe role will provide structured sales administration, Salesforce (CRM) support, License Activation,\u00a0back-to-back\u00a0coordination of Fabric Analyzer inventory management & Order refilling, data analysis and investigation, reporting, and data management/entry support.\u00a0\u00a0\n\nThe Merchandiser / Sales Operations Executive\u00a0will report to the\u00a0Business Development Manager. They will build knowledge and understanding of the Sales systems such as\u00a0Salesforce\u00a0and\u00a0Netsuite, multiple databases. The role may include working with Marketing for the set-up and management of Sales campaigns within Salesforce, liaising with relevant business unit Sales leaders to assign sales campaigns to individual sales team members. Furthermore, the role will support the management of data quality,\u00a0accuracy\u00a0and consistency, whilst also being on hand to support specific business unit reporting or analysis requirements.\u00a0\n\nJob Scope:\n\n\u00a0CRM / License activation / Fabric analyzer support to sales teams\u00a0\n\nHelp team to use system functionality\u00a0\nManage\u00a0Admin &\u00a0IT service requests for\u00a0Hong Kong\u00a0Office\u00a0\nResponsible for contract, quotation, invoice\u00a0creation within Order Processing systems\u00a0\nServe on Salesforce business process for sales teams\u00a0\n\nReporting, Data Analysis & Investigation\u00a0\n\nPerform reporting and develop reports as required for Sales & leadership\u00a0\nActively looking at Salesforce to observe usage, movement of Sales opportunities and keeping Sales leadership informed\u00a0\nInvestigate analysis to spot trends in performance and understand causes\u00a0\nManage local focus areas to improve performance\u00a0\nMonitoring performance of events and products using both financial and customer-centric\u00a0metrics\u00a0\n\nData Management & QA\u00a0\n\nManage data quality,\u00a0accuracy\u00a0and consistency\u00a0\nProactively identify and rectify data errors shown in reporting\u00a0\nManage local initiatives and coach teams to improve data quality\u00a0\n\nSales Administration & Event Support\u00a0\n\nManaging the administration and set up process for new starters (Sales & Support) including the ordering of equipment.\u00a0\u00a0\nOversight of Fabric Analyzer & parts inventory\u00a0\nAssist\u00a0Sales\u00a0to create proposals & invoices\u00a0\u00a0\nSupport the BD Director by representing the event internally and\u00a0externally,\u00a0attending,\u00a0organising\u00a0and hosting events and meetings and making connections with customers and industry figures.\u00a0\nRaise purchase orders\u00a0(working with Finance to raise requisite)\u00a0\nRequirement\n\n2 or more years of experience in Merchandising, B2B sales operations, post-sales support, or sales administration function\nProficient in written and spoken English and Chinese\nBackground in merchandising, fashion/apparel, and SaaS industry and companies preferred\nFamiliar with Microsoft 365, CRMs, Google Suite\nProficient with excel - able to manipulate, clean and analyse data for sales functions\nAble to work in a fast-paced environment\nAble to work in an international work environment", "employment_types": ["Full Time"], "selling_points": ["Supporting Sales Team", "Customer services / client servicing", "Proficient in English and Mandarin"], "locations": ["Kowloon City Area"], "categories": ["Merchandising & Purchasing", "Fabrics", "Sales, CS & Business Devpt", "Sales Administration"], "post_time": "2021-12-22T03:00:27Z", "salary": {"currency": "HKD", "max": 24999, "min": 17000, "period": "monthly", "term": null}, "salary_visible": true, "title_keywords": ["merchandiser", "operations", "sales"], "responsibilities": ["it service", "data", "operations", "inventory", "quotation", "merchandising", "quality", "design", "inventory management", "purchase", "business process", "administration", "invoices", "teams", "liaising with", "develop", "reports", "report", "sales administration", "reporting", "management", "invoice", "monitoring", "investigation", "data analysis", "sales activities", "analysis", "systems", "sales team", "coordination", "databases", "order processing", "analyse"], "requirements": {"degrees": [], "majors": [], "languages": ["english", "chinese"], "language_level": ["proficient"], "hard_skills": ["clean", "excel", "salesforce", "data management", "sales support", "analysis", "goal", "databases", "order processing", "focus"], "soft_skills": ["exact", "responsible", "fast-paced environment", "leadership", "coordination", "focus", "structured", "extensive"], "languages_combined": [{"language": "english", "language_level": ["proficient"]}, {"language": "chinese", "language_level": ["proficient"]}]}, "experience_required": {"duration": [], "field": ["sales administration", "merchandising", "sales support"]}}, {"job_id": "100003008995979", "location_code": "hk", "company": "Win Paradise Limited", "job_title": "ASST MERCH/MERCHANDISER/SR MERCH/MERCH MGR (GARMENT/FABRIC/GARMENT ACC/FASHION ACC/HANDBAG/SUNDRIES)", "description": "F.5/TI\nMin 2 yrs Merchandising/Sales & Marketing/Purchasing experience in either one of below:\n\nWoven / Knit / Sweater / Silk / Denim\u00a0/\u00a0Garment, Casual Wear,\u00a0 Fashion, Underwear, Mould Cup, Bra Bonding, Sleepwear, Babywear, Kidswear, Outerwear, Sportswear, Swimwear, Jeans, Jacket, Suit, Board Shorts, Uniform, Fur, Leatherwear, Costume, Safety Wear Merchandising;\n\n\u00a0\u00a0\u00a0\u00a0\u00a0\u00a0\u00a0\u00a0\u00a0\u00a0\u00a0\u00a0 or\n\nWoven / Knit / Silk / Denim / Washed Fabric Merchandising and Purchasing and Sourcing and Development / Selling / Weaving / Dyeing / Printing;\n\n\u00a0\u00a0\u00a0\u00a0\u00a0\u00a0\u00a0\u00a0\u00a0\u00a0\u00a0\u00a0 or\n\nGarment Accessories / Underwear Accessories / Yarn / Garment Packaging / Embroidery / Logo / Cup Mould / Lace / Woven Label / Interlining / Purchasing and Sourcing and Librarian;\u00a0\n\u00a0\u00a0 or\nFashion Accessories / Cold Weather Items / Soft Accessories-Kids / Handbag / Fashion Bag / Casual Bag / Cosmetic Bag / Backpack / Tools Bag / Luggage / Shoes / Hat / Cap / Gloves / PVC Products / Socks / Home Textile / Bedding / Fine Jewellery / Fashion Jewellery / Baby Products / Infant Textile Products / Beauty Products / Cosmetic / Toiletries / Hair Care Products.\n\u00a0 or\nHard Toys / Soft Toys / Watch / Eyeglasses / Fine Jewellery / Imitation Jewellery / Houseware / Kitchenware / Kitchen Gadget / Home DIY / Dining Ware / Tableware / Ceramic / Sundries / Stationery / Seasonal Items\u00a0/\u00a0Artificial Flower / Art & Craft / Home Decoration /\u00a0Lighter / Gift Items /\u00a0Electrical Appliance / Audio / Elec Products / Elec Fan / Heater / Stationery /\u00a0Toiletries / Bath Room Acc / Sanitary Ware / Baby Products / Baby Textile / Make Up Acc / Office Supplies / Furniture\u00a0/\u00a0Bodycare /\u00a0Cosmetic / Beauty Products / Hair Care Products / Lighting / Sports Goods\u00a0/\u00a0Paper Products / Paper Raw Materials / Computer Parts / Tools / Assembly Kit / Steel Product / Outdoor Products / BBQ / Gardening / Bicycle / Pet Accessories / Camping Goods / Outdoor Goods / Canned Foods / Frozen Foods / Snack / Machine / Surf Accessories / Swim Accessories / Hotel Supplies / Bldg Materials / Sanitary Ware / Hotel Supplies / Home Textile / Bedding / Tools / Hardware / Glassware / Drinkware / Candle / Display / Label / Party Goods / PC Accessories / Jewellery Packaging / Jewellery Box / Electric Fan / Heater / Make Up Accessories / Cosmetic / Beauty Acc / Cosmetic Packaging / Metal Parts / Industrial Device / Electrical Device / Battery / Plastic Material / Home Care Products / Elec Alarm / Industrial Safety Products / Marine Equipment / Door & Window Hardware / Window Display Frame / Medical Protective Device / Face Mask / Baby Feed Products / Cake Tool / Pet Accessories / Home Technology / Printing & Packaging / Photoframe / Sports Goods / Glass / Fitness Equipment / Inflatable Swimming Goods / Swimming Acc / PVC Products.\u00a0\n\n\u00a0 or\nPurchaser / Purchasing Officer / Purchasing Manager / Supply Chain Director\u00a0 for\u00a0 Electronic Parts / Mechanical Parts\u00a0/ Watch Parts\u00a0/ Smart Watch / Eyeswear Parts / Handbag Accessories / Backpack Accessories / Shoes Materials / Leather Material\u00a0/ Chemical / Dyeing Stuff / Office Supplies / Office Equipment & Furniture / Toys Parts / Packaging Materials / Building Materials / Marble / Renovation Materials / Tile / Frozen Foods / Canned Foods / Dried Seafoods / Food Packaging / FMCG / Supermarket Commodities / Food Raw Material / F&B / Kitchen Equipment / E&M.\n\nProficient in English/Proficient in\u00a0Mandarin, Japanese/Korean Speaking preferred but not essential.\u00a0\u00a0\u00a0\u00a0\u00a0\u00a0\u00a0\u00a0\u00a0\nWork in HK/China Stay/Cambodia/Vietnam/Offshore Stay.\u00a0\nSalary Range: HK$13K-$60K / Month\n\n*** Please send your detailed resume in \u201cword format\u201d including \" Expected Salary \", \u201cCompany Nature & Product\u201d & \u201cAvailability Date\u201d to our \u201cE-mail Address\u201d shown above or fax to \u201c2780 2672\u201d or by clicking \u201cApply Now\u201d.", "employment_types": ["Full Time", "Permanent"], "selling_points": ["- F.5/Dip in BA/Textile/Garment/other", "- 2-8 yrs relevant Merch/Pur exp.", "- Garment/Fabric/Yarn/Fashn Acc/Toys/Wth/Gift/Sund"], "locations": ["Not Specified"], "categories": ["Merchandising & Purchasing", "Fabrics", "Sweater", "Woven / Knit"], "post_time": "2021-12-27T16:03:58Z", "salary": {"currency": null, "max": null, "min": null, "period": "monthly", "term": null}, "salary_visible": false, "title_keywords": ["merchandiser"], "responsibilities": ["office supplies", "renovation", "merchandising", "stationery", "hardware", "industrial safety", "audio"], "requirements": {"degrees": [], "majors": [], "languages": ["japanese", "english", "mandarin", "korean"], "language_level": ["proficient"], "hard_skills": ["acc", "word", "make", "hardware", "pc", "logo"], "soft_skills": ["detailed"], "languages_combined": [{"language": "japanese", "language_level": []}, {"language": "english", "language_level": ["proficient", "proficient"]}, {"language": "mandarin", "language_level": []}, {"language": "korean", "language_level": []}]}, "experience_required": {"duration": [], "field": ["purchasing", "marketing", "merchandising"]}}, {"job_id": "100003008993845", "location_code": "hk", "company": "PNH Asia Ltd", "job_title": "Assistant Merchandiser (Garment / Labelling)", "description": "Follow-up orders with vendors, customers and internal parties to ensure customer satisfaction and on-time delivery\nInvolve in the product development process, production follow-up, material testing, quality control and shipping arrangement\nArrange sample submission to customers for approval\n\nJob Requirement\n\nDSE / F.5 or above\n1-2 years working experience in garment merchandising\nFresh graduate will also be considered\nMust be self-motivated, detail-minded, responsible, able to work under pressure & hardworking\nGood command of Cantonese, English and Mandarin\nProficient in use of MS Office, Adobe illustrator, Photoshop, AutoCAD, etc. is preferred.\nWilling to work overtime and travel to PRC when required", "employment_types": ["Full Time", "Permanent"], "selling_points": [], "locations": ["Tuen Mun Area"], "categories": ["Manufacturing", "Product Development / Management", "Merchandising & Purchasing", "Fabrics", "Procurement / Purchasing / Sourcing"], "post_time": "2021-12-22T09:30:56Z", "salary": {"currency": null, "max": null, "min": null, "period": "monthly", "term": null}, "salary_visible": false, "title_keywords": ["assistant merchandiser"], "responsibilities": ["shipping", "merchandising", "testing", "quality control", "internal parties", "work under pressure"], "requirements": {"degrees": ["fresh graduate", "dse"], "majors": [], "languages": ["cantonese", "english", "mandarin"], "language_level": ["good command"], "hard_skills": ["adobe illustrator", "autocad", "photoshop", "ms office"], "soft_skills": ["detail-minded", "self-motivated", "work overtime", "responsible", "hardworking", "work under pressure"], "languages_combined": [{"language": "cantonese", "language_level": ["good command"]}, {"language": "english", "language_level": ["good command"]}, {"language": "mandarin", "language_level": ["good command"]}]}, "experience_required": {"duration": ["1-2 years"], "field": ["garment", "merchandising"]}}, {"job_id": "100003008993858", "location_code": "hk", "company": "PNH Asia Ltd", "job_title": "Merchandiser (Garment)", "description": "Follow-up orders with vendors, customers and internal parties to ensure customer satisfaction and on-time delivery\nInvolve in the product development process, production follow-up, material testing, quality control and shipping arrangement\nArrange sample submission to customers for approval\n\nJob Requirement\n\nDSE / F.5 or above\nAt least 2 years working experience in garment merchandising\nMust be self-motivated, detail-minded, responsible, able to work under pressure & hardworking\nGood command of Cantonese, English and Mandarin\nProficient in use of MS Office, Adobe illustrator, Photoshop, AutoCAD, etc. is preferred.\nWilling to work overtime and travel to PRC when required", "employment_types": ["Full Time", "Permanent"], "selling_points": [], "locations": ["Tuen Mun Area"], "categories": ["Manufacturing", "Product Development / Management", "Merchandising & Purchasing", "Fabrics", "Procurement / Purchasing / Sourcing"], "post_time": "2021-12-22T09:35:07Z", "salary": {"currency": null, "max": null, "min": null, "period": "monthly", "term": null}, "salary_visible": false, "title_keywords": ["merchandiser"], "responsibilities": ["shipping", "merchandising", "testing", "quality control", "internal parties", "work under pressure"], "requirements": {"degrees": ["dse"], "majors": [], "languages": ["cantonese", "english", "mandarin"], "language_level": ["good command"], "hard_skills": ["adobe illustrator", "autocad", "photoshop", "ms office"], "soft_skills": ["detail-minded", "self-motivated", "work overtime", "responsible", "hardworking", "work under pressure"], "languages_combined": [{"language": "cantonese", "language_level": ["good command"]}, {"language": "english", "language_level": ["good command"]}, {"language": "mandarin", "language_level": ["good command"]}]}, "experience_required": {"duration": ["at least 2 years"], "field": ["garment", "merchandising"]}}, {"job_id": "100003008989409", "location_code": "hk", "company": "Eralda Industries Ltd", "job_title": "Assistant Merchandiser", "description": "F.5 graduated or above.\n1-2 years experience in ladies\u2019\u00a0woven garment manufacturing business.\nConversant with PC skills including Microsoft Excel, Email and Word.\nPerform data entry and clerical support to the merchandising team.\nWilling to provide ad hoc support.\nHave good communication, hardworking, well organized and a fast learner\nImmediate availability is high preferred.\n\nPlease send full resume indicating salary expected.", "employment_types": ["Full Time", "Permanent"], "selling_points": [], "locations": ["Kwun Tong"], "categories": ["Merchandising & Purchasing", "Fabrics", "Woven / Knit", "Textiles"], "post_time": "2021-12-21T03:38:12Z", "salary": {"currency": null, "max": null, "min": null, "period": "monthly", "term": null}, "salary_visible": false, "title_keywords": ["assistant merchandiser"], "responsibilities": ["ad hoc", "data entry", "merchandising", "clerical support", "communication"], "requirements": {"degrees": [], "majors": [], "languages": [], "language_level": [], "hard_skills": ["pc skills", "word", "microsoft excel"], "soft_skills": ["communication", "fast learner", "well organized", "hardworking"], "languages_combined": []}, "experience_required": {"duration": ["1-2 years"], "field": ["garment", "manufacturing", "business"]}}]