[{"job_id": "100003009052732", "location_code": "hk", "company": "Descente China Investment Limited", "job_title": "Assistant Merchandiser", "description": "Responsibilities:\n\nmonitor our footwear project orders from product development/sampling -> order processing -> production scheduling -> testing -> manufacturing control -> quality assurance and shipping documentation\nsome travel to China is required\nother ad hoc duties assigned\n\n\nRequirements :\n\n\nExperience in footwear trading will be an advantage\nMature, independent, responsible, positive attitude, well-organized\nExcellent communication\u00a0skill and comprehensive ability\nGood command of written English and spoken Mandarin\nProficiency in MS Excel, Word and Photoshop, Chinese word processing\nWilling to travel to China, if needed\nAble to work under pressure\n\n\nCompetitive remuneration package offer to the right candidates will be commensurate\u00a0according to their work experience.\u00a0\u00a0Interested party, please click \"Apply Now\"\u00a0to submit your full resume, current and expected salary.\n\nData collected would be used for recruitment purpose only.", "employment_types": ["Full Time", "Permanent"], "selling_points": ["2-3 years\u2019 of outdoor sports buying experience", "Degree holder in related disciplines", "Immediate available"], "locations": ["Kowloon Bay"], "categories": ["Merchandising & Purchasing", "Footwear", "Others"], "post_time": "2022-01-17T03:51:50Z", "salary": {"currency": null, "max": null, "min": null, "period": "monthly", "term": null}, "salary_visible": false, "title_keywords": ["assistant merchandiser"], "responsibilities": ["ad hoc duties", "control", "shipping", "monitor", "quality", "testing", "scheduling", "order processing", "documentation"], "requirements": {"degrees": [], "majors": [], "languages": ["english", "chinese", "mandarin"], "language_level": ["proficiency", "good command"], "hard_skills": ["ms excel", "chinese word processing", "word", "photoshop"], "soft_skills": ["independent", "responsible", "communication skill", "well-organized", "mature", "positive attitude", "comprehensive", "work under pressure"], "languages_combined": [{"language": "english", "language_level": ["good command"]}, {"language": "chinese", "language_level": ["proficiency"]}, {"language": "mandarin", "language_level": ["good command"]}]}, "experience_required": {"duration": [], "field": ["trading"]}}, {"job_id": "100003009052343", "location_code": "hk", "company": "Bally GC Retail Co. Limited", "job_title": "Temporary Merchandising Assistant (1-year Renewal Contract)", "description": "Responsibilities:\n\nResponsible for outdoor apparel, footwear and accessories buy;\nHandle annual / seasonal buying process from budgeting to launching;\nFormulate buying strategies, develop OTB plans and product mix allocation to optimize sales plan and gross margin;\nRegularly keep track of sales trend to provide relevant strategies accomplishing business objectives;\nResponsible for shipment and order follow up;\nHandle full set I/E documents independently;\nLiaise and coordinate internally and externally on shipping / local transportation;\nPrepare packing list, invoice and delivery note;\nCommunicate with China headquarter and forwarding company for shipment arrangement;\nAnalyze the data to formulate a right product plan and solutions to fit for the business needs and cater for the market trend;\nConduct and analyze regular buying and selling related report;\nShop visit and regular travel for trade shows are required.\n\nRequirements:\n\nA Bachelor's degree in related disciplines is preferred;\nMinimum 2-3 years\u2019 of solid outdoor sports buying experience including planning & budgeting;\nWorking experience in I/E firm or shipping related company is preferred;\nStrong fashion sense, detail-oriented with good analytical and reporting skills;\nEnergetic, proactive, self-motivated, able to work independently and meet tight deadline;\nGood team player with strong sense of responsibility;\nProficient in MS Word and Excel;\nGood command of written and spoken Chinese and English;\nOccasional travel is required;\nImmediate available is highly preferable.", "employment_types": ["Temporary", "Contract"], "selling_points": ["Fashion Merchandising experience", "Stock allocation and rebalancing", "Tertiary education"], "locations": ["Causeway Bay"], "categories": ["Merchandising & Purchasing", "Footwear", "Handbag", "Others"], "post_time": "2022-01-17T02:48:38Z", "salary": {"currency": null, "max": null, "min": null, "period": "monthly", "term": null}, "salary_visible": false, "title_keywords": ["merchandising assistant"], "responsibilities": ["liaise", "communicate with", "shipping", "shipment arrangement", "data", "invoice", "budgeting", "otb", "develop", "coordinate", "packing list", "plan", "plans", "report"], "requirements": {"degrees": ["degree", "bachelor"], "majors": ["related disciplines"], "languages": ["english", "chinese"], "language_level": ["good command"], "hard_skills": ["excel", "ms word"], "soft_skills": ["work independently", "self-motivated", "proactive", "good team player", "sense of responsibility", "detail-oriented", "meet tight deadline", "energetic"], "languages_combined": [{"language": "english", "language_level": ["good command"]}, {"language": "chinese", "language_level": ["good command"]}]}, "experience_required": {"duration": ["minimum 2-3 years"], "field": ["related", "planning"]}}, {"job_id": "100003009054801", "location_code": "hk", "company": "BOA Technology Hong Kong Limited", "job_title": "Project Specialist (Operations/Supply Chain)", "description": "WORK WITH US.\n\nPursue your passion for adventure and innovation at BOA.\n\nLIFE AT BOA.\n\nWe are a team of innovators, disruptors, creators, and so much more. We know the importance of actively pursuing goals and the excitement of taking calculated risks to push what\u2019s possible and create what\u2019s next.\n\nDoes life as a pioneer at BOA sound like the place for you? If so, check out our open position below and submit your application today!\n\nOVERVIEW OF THE ROLE\n\nReporting to Project Leader \u2013 this position is to work proactively and independently with internal function heads and project leaders to ensure successful delivery of operations/supply chain projects. You will be responsible for developing process charts and standard templates for project management. You are expected to lead cross functional communication and drive improvement for meeting KPI targets.\n\n\u00a0CORE RESPONSIBILITIES\n\nSupport to establish project management policies, standards, methodologies, and best practices to drive consistencies and successful project implementations in Asia Operations team\nPrepare the project plan, design the overall project delivery plan, and execute the delivery and close the project on schedule base on the PMP methodology.\nAccurately analyze and clearly communicate problems to coordinate with related teams to identify improvement opportunities\nCoordinate with internal departments to ensure on time delivery of KPI and metrics.\nDrive and measure engagement reviews (project review meeting, workshops, trainings) with tools & procedures in place to ensure the effective delivery of project\nIdentify and implement various tools to support different departments for continued process improvement\nPerform various analysis and report for developing business strategies.\nPerform ad-hoc assignment/project when required.\n\n\u00a0\u00a0REQUIRED QUALIFICATIONS\n\nDegree holder in Supply Chain / Operations Management or related discipline\nOccasional travel in the region is required\nAt least 5 years project management & implementation experience with shoe/garment manufacturing is an advantage\nPMP Certificate holder is an advantage\nExperience with compliance or sustainability is an advantage\nStrong analytical skill and conceptual thinking skill\nPassionate about continuous improvement and hands-on mentality\nMotivated to grow and learn, energetic and organized. Flexible and be able to work under pressure\nStrong MS-Office skills (Excel, PowerPoint, Word, Visio)\nFluent in written and spoken English and Mandarin is a must\n\nBENEFITS\n\nWe\u2019re committed to helping our people be themselves, be well, and grow. We\u2019re proud to offer a creative work environment with a range of benefits no matter where you are around the world.\u00a0\n\nFun, friendly workplace with social adventures and activities.\nHealth and Wellness program.\nSupport for local communities.\nLearning and development opportunities.\nCompetitive remuneration package.\n\nWe are an equal opportunity employer.\u00a0 We offer competitive remuneration package to the right candidates.\u00a0 Interested parties please send full resume with current and expected salary and availability by clicking the \"Apply Now\" button. All Personal data collected will be kept in strict confidence and will be used for recruitment related purpose only.", "employment_types": ["Full Time", "Permanent"], "selling_points": ["Project implementations experience", "Learning and development opportunities", "Multi-national environment"], "locations": ["Shatin Area"], "categories": ["Merchandising & Purchasing", "Footwear"], "post_time": "2022-01-17T11:09:12Z", "salary": {"currency": null, "max": null, "min": null, "period": "monthly", "term": null}, "salary_visible": false, "title_keywords": ["specialist", "operations"], "responsibilities": ["ad-hoc", "operations", "design", "communication", "plan", "work under pressure", "compliance", "teams", "developing", "implementation", "schedule", "report", "reporting", "management", "review", "coordinate with", "procedures", "policies", "analysis", "ensure on time delivery", "project plan", "project management"], "requirements": {"degrees": ["certificate", "degree holder"], "majors": [], "languages": ["english", "mandarin"], "language_level": ["fluent"], "hard_skills": ["excel", "analytical skill", "ms-office", "analysis", "word", "powerpoint", "project management", "workshops", "pmp"], "soft_skills": ["flexible", "organized", "analytical skill", "independently", "responsible", "passion for", "communication", "project management", "hands-on", "motivated", "energetic", "passionate about", "work under pressure"], "languages_combined": [{"language": "english", "language_level": ["fluent"]}, {"language": "mandarin", "language_level": ["fluent"]}]}, "experience_required": {"duration": ["at least 5 years"], "field": ["garment", "manufacturing", "compliance", "sustainability", "project management"]}}, {"job_id": "100003009054333", "location_code": "hk", "company": "Orient Fair Development Ltd", "job_title": "Senior Purchasing Executive (Casual & Sports Clothing & Footwear)", "description": "JOB OVERVIEW\n\nSupporting Director of Buying and Planning APAC in daily coordination between HQ and countries; providing merchandising support for APAC region (retail stores, e-commerce and outlet) on full Men and Women categories including shoes and leather goods\nWork closely with local teams to drive sales and ST, collect product feedback and cater requests\nMAIN TASKS & RESPONSIBILITIES\n\nMerchandising Analysis\n\nProvide weekly and monthly reports to analyze business trends, draw insights and propose action plans\nSupport regular pricing study to ensure appropriate price and positioning in all currencies\nMonitor new launches and ST performance\nSeasonal Buying Support\n\nFacilitate sales forecast, OTB and assortment plan review for all stores and countries\nSupport buying campaigns on regional level and conduct buying for countries where necessary\nSales and Stock Management\n\nTrace and ensure timely delivery of seasonal collections\nLiaise with Planning Team to manage stock transfer among countries to maximize ST\nPropose reorders and cancellations to react to sales trends\nConduct competitor study to identify business opportunities and provide timely feedback to Paris HQ\nJOB REQUIREMENTS\n\nMinimum 5 years\u2019 of relevant experience from luxury retail industry\nExperience with shoes for multiple markets preferred\nPassionate with fashion, sensitive to trends and capability to depict essence for future merchandise development\nExcellent communications with all levels\nGreat with numbers and analyses, good business acumen, a go-getter\nAgile and efficient\nProficiency in Microsoft Office with good Excel skills\nFluent English, Cantonese and Mandarin\nPlease send us a full resume including present and expected salary and availability to Human Resources Department.\n\nAll information provided by applicants will be used strictly for recruitment purpose. Applicants who are not contacted within one month may consider their applications unsuccessful.", "employment_types": ["Full Time", "Permanent"], "selling_points": ["solid experience in purchasing in sports field", "Casual & Sports Clothing & Footwear,", "Experience in Outdoor Activities"], "locations": ["Kwai Hing"], "categories": ["Marketing / Public Relations", "Marketing - Brand / Product Management", "Merchandising & Purchasing", "Footwear", "Procurement / Purchasing / Sourcing"], "post_time": "2022-01-17T09:11:14Z", "salary": {"currency": null, "max": null, "min": null, "period": null, "term": null}, "salary_visible": false, "title_keywords": ["purchasing executive"], "responsibilities": ["stock management", "identify business opportunities", "analysis", "review", "merchandising", "monitor", "otb", "analyze business trends", "forecast", "plan", "liaise with", "plans", "weekly and monthly reports", "planning"], "requirements": {"degrees": [], "majors": [], "languages": ["cantonese", "english", "mandarin"], "language_level": ["fluent"], "hard_skills": ["excel", "agile", "microsoft office", "go", "acumen"], "soft_skills": ["passionate", "efficient", "agile", "sensitive to", "business acumen"], "languages_combined": [{"language": "cantonese", "language_level": ["fluent"]}, {"language": "english", "language_level": ["fluent"]}, {"language": "mandarin", "language_level": ["fluent"]}]}, "experience_required": {"duration": ["minimum 5 years"], "field": ["luxury retail", "relevant experience"]}}, {"job_id": "100003009055091", "location_code": "hk", "company": "RSH (Hong Kong) Limited", "job_title": "Planner", "description": "Job Duties\n\nReport to Merchandising Director, Great China, to handle stock allocation and rebalancing work for HK market (RTL and OLT)\nCoordinate with Retail team, VM team and Logistic team for actions follow up\nExecute HK Promotion activities and follow up\nPrepare HK Merchandising Analysis and Reporting\nProvide on-site follow up on product knowledge coaching after seasonal training\nCollect merchandise feedback and monitor competitors activities\nPerform other ad-hoc duties as assigned by manager\n\n\u00a0Requirement\n\nTertiary education in Business Management, Fashion Merchandising, or related discipline\nAt least 1 year relevant working experience in merchandising\nGood interpersonal skill, detail-oriented, willing to learn and able to work under pressure.\nGood command of spoken and written English, Cantonese and Mandarin\nProficient in MS Office, Excel (pivot table, vlookup, etc.) and PowerPoint\n\nInterested parties please send your resume with current and expected salary and date of availability to Human Resources Department by clicking \"APPLY NOW\".\n\n**Data collected will be used for recruitment purpose only.**\n\n\n\n", "employment_types": ["Full Time", "Permanent"], "selling_points": ["Buying function", "Category/brand management function", "Analytical and statistic acumen"], "locations": ["Tsim Sha Tsui"], "categories": ["Merchandising & Purchasing", "Footwear"], "post_time": "2022-01-18T01:13:48Z", "salary": {"currency": null, "max": null, "min": null, "period": "monthly", "term": null}, "salary_visible": false, "title_keywords": [], "responsibilities": ["reporting", "vm team", "stock allocation", "analysis", "merchandising", "coordinate with", "monitor", "ad-hoc duties", "report"], "requirements": {"degrees": [], "majors": [], "languages": ["cantonese", "english", "mandarin"], "language_level": ["good command"], "hard_skills": ["business management", "excel", "pivot table", "powerpoint", "vlookup", "ms office"], "soft_skills": ["detail-oriented", "work under pressure", "willing to learn", "interpersonal skill"], "languages_combined": [{"language": "cantonese", "language_level": ["good command"]}, {"language": "english", "language_level": ["good command"]}, {"language": "mandarin", "language_level": ["good command"]}]}, "experience_required": {"duration": ["at least 1 year"], "field": ["merchandising", "relevant working experience"]}}, {"job_id": "100003009054481", "location_code": "hk", "company": "The Wing On Department Stores (Hong Kong) Limited", "job_title": "Assistant Buyer (Household/Apparel/Fashion)", "description": "[Job Ref. No.: JD/SPE/MAR2021/01]\n\nFull Time University Graduate or\u00a0Equivalent (Any majors)\u00a0\u5168\u65e5\u5236\u5927\u5b78\u6216\u76f8\u7b49\u7a0b\u5ea6(\u4efb\u4f55\u5b78\u79d1)\u00a0\nMin 3 years solid experience in Purchasing in Sports Chains Store or Department Stores in Hong Kong\u00a0 \u4e09\u5e74\u4ee5\u4e0a\u5728\u9999\u6e2f\u6709\u95dc\u904b\u52d5\u7528\u54c1\u9023\u9396\u5e97\u6216\u767e\u8ca8\u516c\u53f8\u4e4b\u63a1\u8cfc\u7d93\u9a57\nCo-ordinate the management of marketing / branding content \u5177\u7b56\u5283\u53ca\u7d71\u7c4c\u5e02\u5834\u71df\u92b7\u6216\u54c1\u724c\u7ba1\u7406\u4e4b\u7d93\u9a57\nExperience in Outdoor Activities \u5177\u91ce\u5916\u6d3b\u52d5\u7d93\u9a57\nFluent in spoken and written English and Chinese\u00a0\u826f\u597d\u4e2d\u82f1\u6587\u6703\u8a71\u53ca\u66f8\u5beb\u80fd\u529b\nGood Analytical skills in reporting \u826f\u597d\u5206\u6790\u6578\u64da\u80fd\u529b\nProficient in using Excel e.g. Pivot Table, V lookup etc. \u5b70\u6089\u904b\u7528Excel\u7a0b\u5f0f\nWilling to travel to USA / Europe / Japan\u00a0\u9700\u5f80\u7f8e\u00a0/\u00a0\u6b50\u00a0/\u00a0\u65e5\u516c\u5e79\n\n(Without any experience of product management in Hong Kong will\u00a0not be considered\u00a0\u7121\u9999\u6e2f\u5730\u5340\u4e4b\u7522\u54c1\u7ba1\u7406\u7d93\u9a57\u8005\u6055\u4e0d\u8003\u616e)\u00a0\n\n\u655d\u516c\u53f8\u53e6\u6709\u5176\u4ed6\u7a7a\u7f3a\u4f9b\u5177\u5099\u904b\u52d5\u7528\u54c1\u6279\u767c\u6216\u96f6\u552e\u65b9\u9762\u7d93\u9a57\u4eba\u58eb\u7533\u8acb\u3002\n\nInterested parties please click apply now (Please quote the Job Ref. No. in your application)\n\nPersonal data collected will be used for recruitment purpose.", "employment_types": ["Full Time", "Permanent"], "selling_points": [], "locations": ["Kowloon Bay"], "categories": ["Merchandising & Purchasing", "Footwear", "Handbag", "Procurement / Purchasing / Sourcing"], "post_time": "2022-01-17T09:43:28Z", "salary": {"currency": null, "max": null, "min": null, "period": "monthly", "term": null}, "salary_visible": false, "title_keywords": ["assistant"], "responsibilities": ["reporting", "management"], "requirements": {"degrees": ["university graduate"], "majors": [], "languages": ["english", "chinese"], "language_level": ["fluent"], "hard_skills": ["excel", "no", "pivot table", "analytical skills"], "soft_skills": ["analytical skills"], "languages_combined": [{"language": "english", "language_level": ["fluent"]}, {"language": "chinese", "language_level": ["fluent"]}]}, "experience_required": {"duration": ["min 3 years"], "field": ["purchasing", "product management"]}}, {"job_id": "100003009044820", "location_code": "hk", "company": "Max Harvest International Holdings Limited", "job_title": "Footwear Merchandizer", "description": "Summary\nThe role\u00a0holder\u00a0is\u00a0responsible\u00a0for\u00a0providing support in formulating the\u00a0planning\u00a0strategies, and in season management of assortments and inventory level for\u00a0brand/category.\u00a0\n\n\n\nCore Responsibilities:\u00a0\n\nPrepares\u00a0brand/category\u00a0MIS analytics based on actual sales, sales forecasts, company order parameters, inventory checks, forth coming events, replenishment needs etc.\u00a0\nCollects\u00a0sales figures of stores and prepare periodic reports to analyze sales performance per product per store\u00a0\nMaintains and analysis\u00a0information on\u00a0brand/category sales history, stock budget, current inventory level, and prepares\u00a0sales forecast by\u00a0brand/category\u00a0and season to ensure quarterly \u2018open-to-buy\u2019 (OTB) figures are calculated for each store\u00a0\nMonitors\u00a0brand/category\u00a0plans\u00a0based on insights gained from\u00a0store\u00a0analytics, customer preference, historical trends and future outlook projected by the Buying team\u00a0\nCoordinates with the buying team to\u00a0for necessary execution\u00a0and\u00a0ensures\u00a0effective in season management across\u00a0retails stores/areas\u00a0(stock balancing, markdown management,\u00a0stock analysis, stock vs sales performance)\u00a0\nKeep abreast of the latest trends in\u00a0planning\u00a0to assess alignment/realignment of existing processes\u00a0\nPrepares\u00a0capacity plan and control inventories at each store; tracks and monitors\u00a0inventory levels\u00a0for each\u00a0brand/category,\u00a0keeping in mind store requirements as well as working capital constraints\u00a0\nEnsures\u00a0that no instances of stock outs occur on account of any discrepancy on part of planning\u00a0\nEnsures\u00a0excess inventory is not maintained at the warehouses or the stores and there is proper adherence to the\u00a0GMG\u00a0policies and procedures\u00a0\nEnsures proper coordination with the store managers and distribution centers to ensure that the goods are delivered to respective stores as per the requested quantities and agreed timelines\u00a0\nEnsures identification of obsolete/slow moving\u00a0stock and obtain management approval on markdowns and product discounts to ensure stock is liquidated as per retail /brand SOP guidelines\u00a0\nPrepares variance analysis reports pf stocks and sales against budgeted figures, identify\u00a0brand/category growth opportunities to\u00a0minimize down trending business\u00a0\nMonitors and sets targets by\u00a0brand/category for GMROII and densities to increase profitability\n\nSelf-Management:\u00a0\nDefines performance goals at the start of the year in discussion with the reporting manager and ensures that the goals are achieved during the course of the year\u00a0\u00a0\nTakes ownership of his/her own learning agenda by identifying development needs in consultation with the manager and agreeing on the individual development plan which goes beyond just training and development\u00a0\u00a0\nKeeps abreast of professional developments, new techniques and current issues through continued education and professional growth\u00a0\n\n", "employment_types": ["Full Time"], "selling_points": ["Attractive salary will be offered to right", "candidate. Good career development.", "Bonus can be considered."], "locations": ["Mong Kok"], "categories": ["Merchandising & Purchasing", "Footwear"], "post_time": "2022-01-14T04:10:04Z", "salary": {"currency": null, "max": null, "min": null, "period": "monthly", "term": null}, "salary_visible": false, "title_keywords": [], "responsibilities": ["open-to-buy", "inventory", "budget", "coordination with", "otb", "plan", "plans", "control", "sales performance", "reports", "forecast", "reporting", "management", "procedures", "providing support", "variance analysis reports", "guidelines", "policies", "analysis", "replenishment", "planning"], "requirements": {"degrees": [], "majors": [], "languages": [], "language_level": [], "hard_skills": ["no", "analysis", "outlook", "vs", "forth"], "soft_skills": ["coordination", "learning", "responsible"], "languages_combined": []}, "experience_required": {"duration": [], "field": []}}, {"job_id": "100003009050142", "location_code": "hk", "company": "Lane Crawford (Hong Kong) Limited", "job_title": "Merchandise Coordinator - Fashion (Fresh graduate is also welcomed)", "description": "JOB OVERVIEW\nBuild sales projections, prepare strategies and buy plans for the APAC region by working closely with HQ. Create annual open-to-buy/open-to-sell budgets and plans, and insure these plans are executed properly by working closely with merchandising teams (the buyers). The position is responsible for maximising financial objectives (sales and margins) and productivity (sell through, inventory). The APAC buy and allocation plans should benefit the whole region by pulling together Countries\u2019 inputs. It also leads price index recommendation, stock transfers among APAC, and mark down strategies.\n\nMAIN TASKS & RESPONSIBILITIES\n\nSales Forecasts & OTB\n\nBuild sales projections for budgets & forecasts, and 3YPs from a business perspective for Retail and Merchandising, for discussion with country heads and Finance\nDevelop OTB budgets based upon sales history & projections, and assortment (width, depth, collection), define investment by SKUs, insure Countries\u2019 budgets and buy plans are executed in accordance to HQ and APAC strategies\nPrepare analysis with insights from historical sales performance, sales trends and target financial KPIs by working closely with HQs and country planners, to facilitate future buys\nSupervise and support country planners to ensure merchandise appear in the right store at the right time and in the right quantities and assortment, involving planning stock levels and monitoring sales performance\nAnalyse and reforecast businesses to flag risks and identify growth opportunities\nSet up OTB procedures for the region so that country heads and buyers are clear of objectives and actions for their buys\nPartner with Merchandising and Retail to lay out action plans for risks and opportunities identified\nCore & Continuative Planning\n\nPlan sales and forecasts appropriate inventory levels by SKU for core\nBuild planning modules (e.g. stock plans, SKU plans, store ranking/attributes & key demographics) that will help the team to plan, manage and analyse business\nManage core receipts and inventory against targeted months of supply objectives\nPropose action plan to sustain sales trend and guarantee ideal stock cover (reorders/transfers/buys)\nBusiness Analysis\n\nConsolidate weekly/monthly sales analysis for APAC and HQ\nRegularly work with country planners and buyers to understand best sellers/slow movers, to anticipate consolidation strategies, allocation/reallocation, and replenishment\nRecommend price index and gross margins (maximise ROI) for the region and for each country\nAnalyse end of season markdowns and propose markdown strategies based on inventory and sales analysis by countries, by locations to ensure cohesive flow from one season to the next\nAnalyse intended orders and determine whether the orders (on APAC basis) are coherent to the business objectives\nHarmonise report standards among APAC\nInventory Management\n\nAnticipate shipments, receipting capacity, display, BOH of each country to minimise congestions, maximise sales opportunities, sell through, and margins by working closely with logistics\nPerform effective inventory control, inventory management best practices\nOthers\n\nBe the key point of contact and the superuser for EPM project, including training and deployment\nAd hoc projects as assigned\nJOB REQUIREMENTS\n\nMin. undergraduate degree in merchandising, retail management, fashion management or similar discipline\n10 to 15 years of relevant experience in merchandising planning from luxury retail industry, with APAC coverage\nSome experience in buy/retail management/retail sales a definite plus\nExcellent Excel ability\nExcellent communication and negotiation skill sets, entrepreneurial mindset (business driven), and hands on\nFluent English and Mandarin\nPlease send us a full resume including present and expected salary and availability to Human Resources Department.\n\nAll information provided by applicants will be used strictly for recruitment purpose. Applicants who are not contacted within one month may consider their applications unsuccessful.", "employment_types": ["Permanent"], "selling_points": ["To manage all aspects of the buying process", "To check all invoices thoroughly", "To prepare buying reports for analysis"], "locations": ["Aberdeen"], "categories": ["Merchandising & Purchasing", "Footwear", "Handbag", "Furniture"], "post_time": "2022-01-14T09:51:41Z", "salary": {"currency": null, "max": null, "min": null, "period": null, "term": null}, "salary_visible": false, "title_keywords": ["coordinator"], "responsibilities": ["receipts", "inventory", "merchandising", "otb", "inventory management", "planning", "plan", "plans", "sales performance", "develop", "logistics", "kpis", "report", "monitoring", "procedures", "inventory control", "contact", "gross margins", "budgets", "analysis", "replenishment", "ad hoc projects", "business analysis", "analyse"], "requirements": {"degrees": ["degree"], "majors": [], "languages": ["english", "mandarin"], "language_level": ["fluent"], "hard_skills": ["excel", "plus"], "soft_skills": ["communication", "hands on", "driven", "negotiation skill"], "languages_combined": [{"language": "english", "language_level": ["fluent"]}, {"language": "mandarin", "language_level": ["fluent"]}]}, "experience_required": {"duration": ["10 to 15 years"], "field": ["management", "merchandising", "relevant experience", "luxury retail", "retail", "planning"]}}, {"job_id": "100003009037102", "location_code": "hk", "company": "Rag United Works Limited", "job_title": "Clothing & Footwear designer (5 Days work)", "description": "Responsibilities:\n\nResponsible for the development of products, e.g. household, fashion, shoes & handbags, children & infants, and execution of merchandise assortment as well as buying plans\nSource and develop commercial opportunities, including sourcing new vendors/suppliers to maintain a unique selling proposition for the company\nMonitor inventory through appropriate stock planning and allocation\nCollaborate closely with internal departments to provide product information for supporting marketing campaigns and in-store activities\nNegotiate with suppliers to achieve competitive prices and terms\n\nRequirements:\n\nDegree or above in Supply Chain Management or Business related discipline\n2 years of buying/merchandising experience in retail industry\nHaving overseas buying experiences and supplier network is highly preferable\nStrong market and business sense\nSelf-motivated and able to work under pressure and tight deadlines\nExcellent negotiation and communication skills\nStrong analytical and problem solving skills, perform multi-tasks and good time management skills\nGood command of spoken and written English and Chinese\nImmediately available is highly preferred\n\nCommensurate remuneration and other fringe benefits will be offered to the right candidate. Interested parties please send your\u00a0full resume\u00a0including\u00a0expected salary\u00a0to Human Resources Division, 3/F, Wing On Godown Building, 1 Wang Kee Street, Kowloon Bay, Kowloon, or by click \"APPLY NOW\" button below.\n\n(Candidates not invited for interview within one month may consider their applications filed for future reference.\u00a0 All information collected will be used for recruitment purpose only and will be destroyed after 6 months.)", "employment_types": ["Full Time", "Permanent"], "selling_points": [], "locations": ["Tsim Sha Tsui"], "categories": ["Design", "Fashion", "Graphics", "Merchandising & Purchasing", "Footwear"], "post_time": "2022-01-11T02:14:55Z", "salary": {"currency": null, "max": null, "min": null, "period": "monthly", "term": null}, "salary_visible": false, "title_keywords": ["designer"], "responsibilities": ["collaborate", "inventory", "monitor", "develop", "maintain", "marketing campaigns", "plans", "stock planning"], "requirements": {"degrees": ["degree or above"], "majors": ["business"], "languages": ["english", "chinese"], "language_level": ["good command"], "hard_skills": ["problem solving skills"], "soft_skills": ["communication skills", "self-motivated", "negotiation", "multi-tasks", "business sense", "time management skills", "analytical and problem solving skills", "work under pressure"], "languages_combined": [{"language": "english", "language_level": ["good command"]}, {"language": "chinese", "language_level": ["good command"]}]}, "experience_required": {"duration": ["2 years"], "field": ["retail industry", "merchandising"]}}, {"job_id": "100003009035291", "location_code": "hk", "company": "Private Shop Limited", "job_title": "Assistant Buyer/ Buyer", "description": "~ We are an international footwear trading company with offices in Hong Kong, Dongguan China & Vietnam.\n\n~ Handling the Costing on a daily basis.\u00a0\n\n~ Follow up Sales Administration and Costing on a daily basis.\n\n~ At least 7 years of solid merchandising experience in the women's footwear manufacturing field. American market is an advantage.\n\n~ Must have good knowledge of different footwear materials, components, and constructions.\n~ Must have good knowledge of different production procedures.\n\n~ Strong in Mathematics and computers.\n\n~ Good command of written English and spoken Mandarin.\n\n~ Please provide your expected salary in your resume\u00a0", "employment_types": ["Full Time", "Permanent"], "selling_points": ["5-day work, Competitive Pay and Benefits", "Plan and execute all merchandising functions", "Lingerie/Apparel/ Footwear"], "locations": ["Kwai Tsing Area"], "categories": ["Merchandising & Purchasing", "Footwear", "Sweater", "Procurement / Purchasing / Sourcing"], "post_time": "2022-01-10T06:41:35Z", "salary": {"currency": null, "max": null, "min": null, "period": "monthly", "term": null}, "salary_visible": false, "title_keywords": ["assistant"], "responsibilities": ["sales administration", "merchandising", "procedures"], "requirements": {"degrees": [], "majors": [], "languages": ["english", "mandarin"], "language_level": ["good command"], "hard_skills": [], "soft_skills": [], "languages_combined": [{"language": "english", "language_level": ["good command"]}, {"language": "mandarin", "language_level": ["good command"]}]}, "experience_required": {"duration": ["at least 7 years"], "field": ["manufacturing", "merchandising"]}}, {"job_id": "100003009038973", "location_code": "hk", "company": "ASICS HongKong Limited", "job_title": "Merchandising Assistant, Onitsuka Tiger Hong Kong", "description": "Job Responsibilities:\nTo manage all aspects of the buying process for the designated portfolio\nTo check all invoices thoroughly, maintain\u00a0accurate data entry in PO system\nTo record merchandise details and complete product information in timely manner\nTo prepare buying reports for analysis, follow up orders and monitor stock levels\nTo communicate\u00a0and work regularly with vendors, warehouse, store operations, logistics and sales\nTo provide administrative support\u00a0to buying team\n\nJob Requirements:\n\nStrong Passion in Fashion\u00a0\nDegree in Textile/Fashion Design or related discipline\nSome relevant experience, preferably in the luxury Lifestyle industry\nStrong analytical, negotiation and communication skills\nProactive, attentive to details and able to follow tight timeline\nExcellent command of written & spoken English & Chinese\nImmediate availability preferred\n\nAt Lane Crawford we support our employees with a range of benefits reflecting the importance we place\u00a0on\u00a0the well being of our staff. In addition to a competitive salary, discretionary bonus, annual leave, provident fund, medical and dental coverage and staff purchase privileges,\u00a0 we provide shuttle buses to the Company Head Office, various social recreation activities, Staff Assistance Programme, best in-class training and development and regional work opportunities for the right candidate.\n\nAll information provided will be treated in strict confidence and used for recruitment purposes only", "employment_types": ["Full Time", "Permanent"], "selling_points": ["Product Management, Merchandising", "Market Research, Lifestyle", "Fashion, Retail, Wholesales"], "locations": ["Kwun Tong"], "categories": ["Merchandising & Purchasing", "Footwear"], "post_time": "2022-01-11T08:17:05Z", "salary": {"currency": null, "max": null, "min": null, "period": "monthly", "term": null}, "salary_visible": false, "title_keywords": ["merchandising assistant"], "responsibilities": ["follow up orders", "invoices", "data entry", "operations", "analysis", "monitor", "maintain", "reports", "logistics", "provide administrative support"], "requirements": {"degrees": ["degree"], "majors": ["design"], "languages": ["english", "chinese"], "language_level": ["excellent"], "hard_skills": [], "soft_skills": ["communication skills", "negotiation", "attentive to details", "passion in", "proactive"], "languages_combined": [{"language": "english", "language_level": ["excellent"]}, {"language": "chinese", "language_level": ["excellent"]}]}, "experience_required": {"duration": [], "field": ["relevant experience"]}}, {"job_id": "100003009043933", "location_code": "hk", "company": "Page Personnel", "job_title": "Customer Service Officer - Back office", "description": "Job Description\n\nThe incumbent will be responsible for the execution of buying activities and ensure a smooth communication with shops so as to achieve turnover, gross profit and inventory target.\n\nJob Duties and Responsibilities:\n\nPlan and execute all merchandising functions, including merchandise planning and monitoring seasonal OTB and sales\nAnalyse sales performance, sell through and manage markdown during sale period to maximize and maintain planned GP\nDeploy effective merchandise ordering, replenishment and inventory control to achieve sell-through and GP target\nControl designated brands OTB from given sales targets\nAllocate goods accurately to different stores based on demand and store profile, forecast and manage inventory level from store to store\nConduct consolidation to maintain optimal stock/SKUs holding at store level, PO allocation/ replenishment order/ price change/ Shipment schedule and others\nPrepare regular analysis & reports for management review\nConduct regular product training to sales team\nWork closely with Retail operation and Marketing team to maximize sales performance\nRecommend and exploit potential products/brands from market knowledge and data analysis, buy the right products in coherence with the retail chain's positioning\n\nRequirements:\n\nUniversity graduate\nMinimum 2 years' relevant buying experience with knowledge in buying and inventory management of Lingerie/Apparel/ Footwear, Less experience will be considered as assistant buyer\nStrong business sense, attentive to figures and strong analytical skills\nPassionate, Proactive, Good communication and negotiation skills, and able to work under pressure\nProficiency in English and Chinese\nProficient in MS Word, Excel, PowerPoint\n\nWe are equal opportunity employer with good work environment. We offer attractive salary, training opportunity, and\u00a0staff purchase discount. Please send your application with resume and expected salary to HR Department,\u00a0Office Tower 8/F, 807-811, Hutchison Logistics Centre, 18 Container Port Road South, Kwai Chung or send your application by clicking \u201cApply Now\u201d.\n\nAll applications will be treated in strict confidence and all personal data collected will be used for recruitment purposes only.", "employment_types": ["Full Time", "Permanent"], "selling_points": ["Competitive salary package", "Monday to Friday", "Discretionary bonus"], "locations": ["Not Specified"], "categories": ["Sales, CS & Business Devpt", "Customer Service - Supervisor / Officer", "Merchandising & Purchasing", "Footwear", "Others", "Others"], "post_time": "2022-01-13T02:30:52Z", "salary": {"currency": "HKD", "max": 24999, "min": 20000, "period": "monthly", "term": null}, "salary_visible": true, "title_keywords": ["customer service officer"], "responsibilities": ["inventory", "merchandising", "otb", "communication", "maintain", "planning", "plan", "deploy", "management review", "control", "sales performance", "reports", "schedule", "forecast", "monitoring", "data analysis", "inventory control", "analysis", "replenishment", "sales team", "analyse"], "requirements": {"degrees": ["university graduate"], "majors": [], "languages": ["english", "chinese"], "language_level": ["proficiency"], "hard_skills": ["ms word", "excel", "powerpoint", "analytical skills"], "soft_skills": ["attentive", "passionate", "business sense", "analytical skills", "communication", "negotiation skills", "proactive", "work under pressure"], "languages_combined": [{"language": "english", "language_level": ["proficiency"]}, {"language": "chinese", "language_level": ["proficiency"]}]}, "experience_required": {"duration": ["minimum 2 years"], "field": ["inventory management"]}}, {"job_id": "100003009035161", "location_code": "hk", "company": "Swire Resources Ltd", "job_title": "Product Executive", "description": "Responsibilities:\nCreate sketches/Illustrator CADs and spec/detail technical specifications\nCollaborate and clearly communicate with\u00a0 factories to ensure design objectives are reflected in the creation and execution of the product\nStay abreast of competitive brands and market trends\nWork closely with executive team to develop and execute product designs for Ladies Footwear.\nAdhere to design calendar and deadlines.\nGenerate detailed tech packs/specs for pass off to factories\nHave a thorough understanding of footwear construction, sampling and manufacturing\nPossess superior multitasking and time management skills\nEffectively balance creative thinking with commercial viability\nMust be a collaborative, team player with excellent interpersonal and communication skills\nRequirements:\nBachelor\u2019s degree in fashion or related field, or equivalent combination of education and experience in footwear design required\n5-7 years industry experience designing women\u2019s fashion footwear is a must; fast fashion experience a plus!\nExperience developing product directly with Asia based factories preferred\nDemonstrated proficiency in illustrator/Photoshop/Google Suite as well as hand sketching\nProviding a digital portfolio or examples of work strongly recommended for serious consideration\nGood interpersonal and listening skills; Excellent written & oral English & Chinese including Putonghua is a plus\nThis position is based in Hong Kong\n\n\n\nBenefits:\n\nDouble Pay\nAnnual leave 11 days\nPaid sick leave\n5 days work", "employment_types": ["Full Time", "Permanent"], "selling_points": ["Resp for product management, selection & pricing", "U grad, 2-3 yrs buying & product management exp", "Exp gained from fashion / footwear / accessories"], "locations": ["Kowloon Bay"], "categories": ["Merchandising & Purchasing", "Footwear", "Handbag", "Others"], "post_time": "2022-01-10T06:15:09Z", "salary": {"currency": null, "max": null, "min": null, "period": null, "term": null}, "salary_visible": false, "title_keywords": ["executive"], "responsibilities": ["collaborate", "communicate with", "management", "sketches", "design", "develop", "communication", "specifications"], "requirements": {"degrees": ["degree", "bachelor"], "majors": ["design"], "languages": ["putonghua", "english", "chinese"], "language_level": ["excellent"], "hard_skills": ["plus", "illustrator", "photoshop"], "soft_skills": ["oral", "interpersonal"], "languages_combined": [{"language": "putonghua", "language_level": []}, {"language": "english", "language_level": ["excellent"]}, {"language": "chinese", "language_level": ["excellent"]}]}, "experience_required": {"duration": ["5-7 years"], "field": ["related", "developing", "design", "education"]}}, {"job_id": "100003009036358", "location_code": "hk", "company": "Swire Resources Ltd", "job_title": "Assistant Buyer (Sport shoes/ Accessories)", "description": "SUMMARY:\n\n\nThe objective of this position is to plan and manage inventory allocation in order to maximize sales and margin across both Full Price and Outlet channels within Hong Kong/Macao, and extend regional support to Taiwan/Australia.\u00a0\n\nJOB RESPONSIBILITIES\n\nBe responsible for allocation / replenishment / rebalancing for selected product categories within Hong Kong/Macao and support Taiwan/Australia for regional allocation\nAllocate, replenish, and rebalance inventory by store, according to\n- Seasonal flow, including seasonal launch, floor sets, markdown, and liquidation\n- Product lifecycle and markdown risk (such as core/carryover items vs. fashion newness)\n- Sales performance by store, down to the SKU level\n- Optimal inventory levels by store according to store type, sales performance and store capacity\n- Anticipate peak / slow shopping periods and holidays\n- Anticipate future product (such as reserving and rebalancing) according to store opening plan\nPrioritize key stores and understand product substitutes in limited stock situations\nPrepare inventory for new store openings\nPromotion and markdown management, update relevant system\nDevelop stock clearance plan, organize and coordinate return\nAct as key stakeholder to provide GC Merch team, the insight of HK/Macao business, from merchandising planning point of view\nHandle assortment planning including price and discount setting for Sogo Thankful event and Brand sale\nIssue TN and SO for HK, Macao and Taiwan orders.\u00a0 Coordinate with HK logistics and EU team for Australia orders\nPartner with other team members and functions as needed, for example\n- Partner with logistics to ensure timely execution of allocation / replenishment\n- Communicate with stores on store requests and needs; enforce efficient transfers / returns from stores\n- Work with buyers to understand launching schedule, product needs by store and substitutes in limited stock situations\n- Partner with marketing and VM to support special marketing requests (e.g. store events) and VM (e.g. mannequin looks)\n\u00a0SKILLS and WORK EXPERIENCE\n\nBachelor\u2019s Degree or above\nStrong record of academic and professional performance, with references\n6-8 years\u2019 inventory management experience in the retail industry (experience in APAC management is preferred)\nExtremely sensitive to number; strong data analysis and Excel skills\nEstablish and develop the inventory management team\nHonest, open, and non-hierarchical attitude\nExcellent communication and interpersonal skills\nStrong prioritization and organizational skills\nDriven to execute efficiently and accurately\nProfessional demeanor\nProactive, ambitious, flexible, and entrepreneurial; able to work in a startup environment\nComputer and systems literate\nFluent in English, good Mandarin is a plus\n\nWe offer remuneration package\u00a0commensurate with qualification and experience to the successful candidate.\u00a0 If you would like to apply for this position or find out more, please press 'Apply Now'.\n\n(Data collected will be treated as strict confidential and will be used for recruitment purpose only.)", "employment_types": ["Full Time", "Permanent"], "selling_points": ["1-2 years of relevant buying experience", "Attentive to figures and strong analytical skills", "Sport & Sport fashion lovers welcome!"], "locations": ["Kowloon Bay"], "categories": ["Merchandising & Purchasing", "Footwear", "Others", "Procurement / Purchasing / Sourcing"], "post_time": "2022-01-10T10:09:04Z", "salary": {"currency": null, "max": null, "min": null, "period": "monthly", "term": null}, "salary_visible": false, "title_keywords": ["assistant"], "responsibilities": ["product categories", "communicate with", "management", "sales performance", "inventory", "systems", "merchandising", "replenishment", "coordinate with", "develop", "coordinate", "inventory management", "data analysis", "communication", "logistics", "schedule", "plan", "planning"], "requirements": {"degrees": ["degree or above", "bachelor"], "majors": [], "languages": ["english", "mandarin"], "language_level": ["good", "fluent"], "hard_skills": ["vs", "excel", "analysis", "plus"], "soft_skills": ["efficient", "organizational skills", "flexible", "responsible", "timely", "prioritize", "sensitive to", "communication and interpersonal skills", "honest", "proactive", "driven"], "languages_combined": [{"language": "english", "language_level": ["fluent"]}, {"language": "mandarin", "language_level": ["good", "fluent"]}]}, "experience_required": {"duration": ["6-8 years"], "field": ["inventory management", "management", "retail industry"]}}, {"job_id": "100003009031067", "location_code": "hk", "company": "initial Fashion Co Limited", "job_title": "Merchandiser - Footwear & Accessories", "description": "Reports to: Sr. Merchandising Executive\n\nResponsibilities:\n\nRelated Product Management\nWork with Sr Merchandising Executive on Seasonal merchandising plan and all analysis report\nWork with logistic team and Operations to follow up all deliveries and allocation\nAssist accurate follow up on all order confirmation, actual receipts of all merchandise\nUpdate the team on all actual deliveries and allocation to all channels\nRegister product master when new products arrives\nManage the efficient operation of product launch, supply, rotation and return of products on all channels\nOperate SAP, POS and PLM System\nHelp on all samples arrangement and keep the show room and storage room tidy\nHelp update the daily, weekly inventory status and sell thru report\nSupport the seasonal tradeshow\nHandle office admin/ operation work if needed\nRequirements:\n\n1-3 year experience related with merchandising role in Fashion industry or Lifestyle industry\nCustomer focus with business sense and strong interests in fashion trend\nGood skill in Microsoft Excel, Words and Power-point\nSensitive on numbers and good analytical skill\nAdapt to environmental changes with flexibility\nGood team work and self-motivation\n\nWe offer attractive remuneration package to the right candidate. If you are interested in this exciting opportunity, please click \u201cApply Now\u201d to submit applications with detailed resume stating career history, present & expected salary and date available.\n\nPersonal data collected will be used for recruitment purpose only. Applicants not hearing from us within 6 weeks may consider their applications unsuccessful and all related information will be destroyed after 6 months.", "employment_types": ["Full Time", "Permanent"], "selling_points": ["Diploma in Fashion, Clothing & Textile", "Minimum 3 years' solid experience", "Strong product knowledge"], "locations": ["Kwun Tong"], "categories": ["Merchandising & Purchasing", "Footwear", "Handbag", "Sundries"], "post_time": "2022-01-07T08:54:16Z", "salary": {"currency": null, "max": null, "min": null, "period": "monthly", "term": null}, "salary_visible": false, "title_keywords": ["merchandiser"], "responsibilities": ["management", "receipts", "analysis report", "operations", "inventory", "merchandising", "plan", "report"], "requirements": {"degrees": [], "majors": [], "languages": [], "language_level": [], "hard_skills": ["focus", "analytical skill", "words", "microsoft excel"], "soft_skills": ["good team work", "analytical skill", "business sense", "self-motivation", "sensitive", "customer focus"], "languages_combined": []}, "experience_required": {"duration": ["1-3 year"], "field": ["related", "merchandising"]}}, {"job_id": "100003009029171", "location_code": "hk", "company": "Bally GC Retail Co. Limited", "job_title": "Temporary Merchandising Assistant (1-year Renewal Contract)", "description": "The incumbent will be responsible for formulating buy and product management strategies of the assigned brand(s), working closely with the Principal(s) and internal teams to maximize sales.\n\nResponsibilities:\n\nManage product planning and seasonal buy covering both Retail and Wholesale\nMonitor sales trend and inventory control to meet depletion target\nEnsure smooth delivery and supply of products to meet launch deadlines\nFoster close relationship with the Principal(s)\nAnalyze market trend and competitors to drive additional sales\nWork closely with Retail, Sales and Marketing teams to deliver sales and promotions\n\n\u00a0Requirements:\n\nUniversity graduate in related disciplines\n2-3 years'\u00a0experience in\u00a0buying / category management / business development experience\u00a0gained from fashion / footwear / accessories\nStrong business sense with\u00a0analytical mind\nPro-active, result-oriented, good communication skill and able to work under pressure\nProficiency in English and Chinese\nProficient in MS Word, Excel, PowerPoint and Chinese Word Processing\n\nWe offer competitive remuneration package with\u00a0a wide range of fringe benefits including\n\n5-day work week\nDiscretionary Bonus\nComprehensive Medical Coverage\nStaff Shopping Discount\nNon-contributory Retirement Benefits Scheme\nBirthday Leave\u00a0\n\nInterested parties please send resume with present and expected salary to Human Resources Department, Swire Resources Limited,\u00a012/F Kingston International Centre, 19 Wang Chiu Road Kowloon Bay, Hong Kong or by\u00a0clicking the below \"Apply Now\" button.\n\nSwire Resources Limited is Equal Opportunity Employer\n", "employment_types": ["Temporary", "Contract"], "selling_points": ["Fashion Merchandising experience", "Stock allocation and rebalancing", "Tertiary education"], "locations": ["Causeway Bay"], "categories": ["Merchandising & Purchasing", "Footwear", "Handbag", "Others"], "post_time": "2022-01-07T04:09:13Z", "salary": {"currency": null, "max": null, "min": null, "period": "monthly", "term": null}, "salary_visible": false, "title_keywords": ["merchandising assistant"], "responsibilities": ["teams", "inventory control", "monitor", "planning"], "requirements": {"degrees": ["university graduate"], "majors": ["related disciplines"], "languages": ["english", "chinese"], "language_level": ["proficiency", "proficient"], "hard_skills": ["excel", "chinese word processing", "powerpoint", "ms word"], "soft_skills": ["business sense", "communication skill", "analytical mind", "pro-active", "result-oriented", "work under pressure"], "languages_combined": [{"language": "english", "language_level": ["proficiency"]}, {"language": "chinese", "language_level": ["proficiency", "proficient"]}]}, "experience_required": {"duration": ["2-3 years"], "field": ["management", "business development"]}}, {"job_id": "100003009030988", "location_code": "hk", "company": "J. Choo (Asia) Limited", "job_title": "Merchandising Assistant (12 months contract)", "description": "The incumbent will be responsible for the execution of buying activities and ensure a smooth communication with shops for designated brand so as to achieve turnover, gross profit and inventory target.\n\nJob Duties and Responsibilities:\n\nBe responsible for the selection, achieve sales , GP and inventory target of the designated brand(s)\nControl the OTB of designated brand(s), develop buying strategy which is consistent with the business strategy\nWell execution of sales and stock management process include allocation, replenishment and consolidation to achieve T/O, GP% and inventory targets\nRegular review and tracking sales performance through creating timely and accurate weekly/ monthly sales report and analysis\nKeep abreast of industry both online and offline, particular key market competitors, and initiate effective sale and marketing promotion to achieve sales and GP target\nNegotiate with suppliers for exclusive merchandise, special marketing support, additional discount, or stock exchange to achieve the best assortment for retail chain of different shop profile\nRecommend and exploit potential products/brands from market knowledge both online/ offline and data analysis, buy the right products in coherence with the retail chain\u2019s positioning\nPrepare monthly merchandise focus and communicate with inter-departments to achieve monthly target\n\nRequirements:\n\nBachelor\u2019s Degree in Fashion Retailing, or other related disciplines\n1-2 years of relevant buying experience in retail and/or digital platforms with knowledge in OTB planning, buying and inventory management of Apparel/Footwear/Accessories\nStrong business sense, attentive to figures and strong analytical skills\nCurious and sensitive to market, embrace changes and act fast\u00a0\nStrong interpersonal skill & negotiation skill, and able to work under pressure\nPassion for Sport fashion will be preferred\nProficiency in Mandarin, English and Chinese\nProficiency in MS Word, Excel, PowerPoint & Chinese Word Processing\n\nWe offer competitive remuneration package with\u00a0a wide range of fringe benefits including\n\n5-day work week\nDiscretionary Bonus\nComprehensive Medical Coverage\nStaff Shopping Discount\nNon-contributory Retirement Benefits Scheme\nBirthday Leave\n\nPlease send resume with present and expected salary to Human Resources Department, Swire Resources Limited,\u00a012/F Kingston International Centre\u00a019 Wang Chiu Road Kowloon Bay\u00a0Hong Kong or by clicking the \"Apply Now\" button below.\n\nSwire Resources Limited is Equal Opportunity Employer\n", "employment_types": ["Full Time", "Contract", "Internship"], "selling_points": ["Luxury fashion", "Five-day work week", "Merchandising"], "locations": ["Tsim Sha Tsui"], "categories": ["Merchandising & Purchasing", "Footwear", "Handbag", "Others"], "post_time": "2022-01-07T11:13:54Z", "salary": {"currency": null, "max": null, "min": null, "period": "monthly", "term": null}, "salary_visible": false, "title_keywords": ["merchandising assistant"], "responsibilities": ["communicate with", "control", "stock management", "sales performance", "inventory", "analysis", "replenishment", "develop", "otb", "regular review", "data analysis", "monthly sales report", "tracking"], "requirements": {"degrees": ["degree", "bachelor"], "majors": ["related disciplines"], "languages": ["english", "chinese", "mandarin"], "language_level": ["proficiency"], "hard_skills": ["excel", "chinese word processing", "powerpoint", "analytical skills", "ms word"], "soft_skills": ["attentive", "business sense", "passion for", "interpersonal skill", "analytical skills", "sensitive to", "negotiation skill", "work under pressure"], "languages_combined": [{"language": "english", "language_level": ["proficiency"]}, {"language": "chinese", "language_level": ["proficiency", "proficiency"]}, {"language": "mandarin", "language_level": ["proficiency"]}]}, "experience_required": {"duration": ["1-2 years"], "field": ["inventory management", "digital", "retail", "planning"]}}, {"job_id": "100003009028850", "location_code": "hk", "company": "PVH Far East Limited", "job_title": "Project Supervisor (Business Analysis)", "description": "A leading luxury company based in Europe is now seeking a Customer Service Officer who are passionate in developing their career with the company. Please do not hesitate to apply now if you are interested in joining a winning team!\n\nClient Details\n\nOur client is a luxury company over 90 years of history. They are definitely the market leader across APAC region. They are currently expanding their business and seeking for a high calibre candidate to join their customer service team.\n\nDescription\n\nHandle inbound calls\nResolve complaints from customers\nProvide after-sales service to customers\nFollow up with existing customer on their request\nProvide additional information to the customer on their seasonal promotion\n\nProfile\n\nDiploma holder or above\nCall centre experience in highly preferred\nFresh graduate is also welcomed\nStrong interpersonal and communication skills\nAble to work as a team and good problem-solving skills\nExcellent command in both spoken and written English, Mandarin and Cantonese\n\nJob Offer\n\nMedical Allowance\nOn-the-job training\nCareer progression\nMPF / ORSO\nDiscretionary bonus\n\nTo apply online please click the 'Apply' button below. For a confidential discussion about this role please contact Coco Ng on +852 3602 2446.", "employment_types": ["Full Time", "Permanent"], "selling_points": ["System Implementation, Project Management", "Data Management, Process Analysis", "Excel, VBA, Macro, Power Pivot"], "locations": ["Lai Chi Kok"], "categories": ["Information Technology (IT)", "Product Management / Business Analyst", "Merchandising & Purchasing", "Footwear"], "post_time": "2022-01-07T03:23:53Z", "salary": {"currency": null, "max": null, "min": null, "period": "monthly", "term": null}, "salary_visible": false, "title_keywords": ["project supervisor"], "responsibilities": ["mpf", "developing", "communication", "after-sales service", "customer service", "contact"], "requirements": {"degrees": ["diploma holder", "fresh graduate"], "majors": [], "languages": ["cantonese", "english", "mandarin"], "language_level": ["excellent"], "hard_skills": ["problem-solving skills"], "soft_skills": ["passionate", "communication skills", "work as a team", "interested in", "customer service", "problem-solving skills", "interpersonal"], "languages_combined": [{"language": "cantonese", "language_level": ["excellent"]}, {"language": "english", "language_level": ["excellent"]}, {"language": "mandarin", "language_level": ["excellent"]}]}, "experience_required": {"duration": [], "field": []}}, {"job_id": "100003009020329", "location_code": "hk", "company": "Swire Resources Ltd", "job_title": "Buying Assistant (Footwear)", "description": "Job Duties\n\nReport to Merchandising Director, Great China, to handle stock allocation and rebalancing work for HK market (RTL and OLT)\nCoordinate with Retail team, VM team and Logistic team for actions follow up\nExecute HK Promotion activities and follow up\nPrepare HK Merchandising Analysis and Reporting\nProvide on-site follow up on product knowledge coaching after seasonal training\nCollect merchandise feedback and monitor competitors activities\nPerform other ad-hoc duties as assigned by manager\n\n\u00a0Requirement\n\nTertiary education in Business Management, Fashion Merchandising, or related discipline\nAt least 1 year relevant working experience in merchandising\nGood interpersonal skill, detail-oriented, willing to learn and able to work under pressure.\nGood command of spoken and written English, Cantonese and Mandarin\nProficient in MS Office, Excel (pivot table, vlookup, etc.) and PowerPoint\n\nInterested parties please send your resume with current and expected salary and date of availability to Human Resources Department by clicking \"APPLY NOW\".\n\n**Data collected will be used for recruitment purpose only.**\n\n\n\n", "employment_types": ["Full Time", "Permanent"], "selling_points": ["Resp for product management, selection & pricing", "Fresh grad/ 1yr fashion buying exp", "Knowledge on OTB, sports lover preferred"], "locations": ["Kowloon Bay"], "categories": ["Marketing / Public Relations", "Marketing - Brand / Product Management", "Merchandising & Purchasing", "Footwear", "Others", "Student / Fresh Graduate / No Experience"], "post_time": "2022-01-04T10:37:16Z", "salary": {"currency": null, "max": null, "min": null, "period": null, "term": null}, "salary_visible": false, "title_keywords": ["buying assistant"], "responsibilities": ["reporting", "vm team", "stock allocation", "analysis", "merchandising", "coordinate with", "monitor", "ad-hoc duties", "report"], "requirements": {"degrees": [], "majors": [], "languages": ["cantonese", "english", "mandarin"], "language_level": ["good command"], "hard_skills": ["business management", "excel", "pivot table", "powerpoint", "vlookup", "ms office"], "soft_skills": ["detail-oriented", "work under pressure", "willing to learn", "interpersonal skill"], "languages_combined": [{"language": "cantonese", "language_level": ["good command"]}, {"language": "english", "language_level": ["good command"]}, {"language": "mandarin", "language_level": ["good command"]}]}, "experience_required": {"duration": ["at least 1 year"], "field": ["merchandising", "relevant working experience"]}}, {"job_id": "100003009008555", "location_code": "hk", "company": "FnF Hong Kong Limited", "job_title": "Assistant Buying Manager / Senior Buyer", "description": "\u00a0Responsibilities\n\nPrepare reports but not limited to forecasts, sell-thru, re-orders and OTB sheets\nSupport the line manager in the buying process by providing detailed product analysis\nResponsible for stock replenishment and allocation\nProvide clerical support and data entry for the department\nLiaise with various parties for stock adjustment\nPerform any other duties as assigned by the manager\n\nParticular Skills/knowledge required\n\nUndergraduate / associate degree or higher diploma in any discipline\nMinimum 1 year relevant experience in retail industry\nGood personality, responsible, detail-minded, able to work under pressure\nStrong computer knowledge especially at Excel (e.g. Pivot Table, vlookup)\nGood command of spoken and written English and Chinese\nAble to work in a dynamic, multi-task and fast paced environment\n\nWe offer excellent career opportunities to the successful candidates. Interested parties please send your full resume with both current and expected salary through the below \"Apply Now\" button\n\n\u00a0(Personal data collected will be treated in strict confidence and used for recruitment purpose only)", "employment_types": ["Full Time", "Permanent"], "selling_points": ["Buying Role", "Nice, young and energetic work environment", "Start-up fashion retail experience"], "locations": ["Tsim Sha Tsui"], "categories": ["Merchandising & Purchasing", "Footwear", "Handbag", "Others"], "post_time": "2021-12-30T08:19:14Z", "salary": {"currency": null, "max": null, "min": null, "period": "monthly", "term": null}, "salary_visible": false, "title_keywords": ["buying manager", "assistant"], "responsibilities": ["provide clerical support", "any other duties", "stock replenishment", "data entry", "analysis", "otb", "liaise with", "prepare reports", "work under pressure"], "requirements": {"degrees": ["associate degree", "diploma"], "majors": [], "languages": ["english", "chinese"], "language_level": ["good command"], "hard_skills": ["excel", "analysis", "pivot table", "dynamic", "vlookup"], "soft_skills": ["detail-minded", "multi-task", "responsible", "detailed", "dynamic", "work under pressure"], "languages_combined": [{"language": "english", "language_level": ["good command"]}, {"language": "chinese", "language_level": ["good command"]}]}, "experience_required": {"duration": ["minimum 1 year"], "field": ["retail industry", "relevant experience"]}}, {"job_id": "100003009019920", "location_code": "hk", "company": "Swire Resources Ltd", "job_title": "Assistant Buyer (Catalog)", "description": "The incumbent will be responsible for formulating buy and product management strategies of the assigned brand(s), working closely with the Principal(s) and internal teams to maximize sales.\n\nResponsibilities:\n\nResponsible for product management including product line planning and forecast, product selection and segmentation, pricing, sample and bulk order placement\nAnalyze sales data and monitor business performance for implementation of relevant product strategies\nAssist management to prepare annual budget on turnover and GP, and exercise budgetary control on sampling\nMaster and schedule seasonal tradeshow, define order policy and timeline\nClosely communicate local product needs to brands, request right and relevant product offering, negotiating trade term, payment term, subsidy or royalty, and to communicate product compliance requirements\nMonitor closely and report on the international trends of assigned brands/product lines in terms of styling, materials, technology etc., so as to maximize product potential of assigned brands to assist management in identifying new business opportunities or line extension of current brands\n\n\u00a0Requirements:\n\nUniversity graduate in related disciplines\nAround\u00a01 year's experience in\u00a0buying / category management / business development experience\u00a0gained from fashion / footwear / accessories / swimwear\nStrong business sense with\u00a0analytical mind\nPro-active, result-oriented, good communication skill and able to work under pressure\nProficient in Excel\nFluent in English, knowledge on OTB is a plus, sports lover preferred\n\nWe offer competitive remuneration package with\u00a0a wide range of fringe benefits including\n\n5-day work week\nDiscretionary Bonus\nComprehensive Medical Coverage\nStaff Shopping Discount\nNon-contributory Retirement Benefits Scheme\nBirthday Leave\u00a0\n\nPlease send resume with present and expected salary to Human Resources Department, Swire Resources Limited,\u00a012/F Kingston International Centre, 19 Wang Chiu Road Kowloon Bay, Hong Kong or by\u00a0clicking the below \"Apply Now\" button.\n\nSwire Resources Limited is Equal Opportunity Employer\n", "employment_types": ["Full Time", "Permanent"], "selling_points": ["1-2 years of relevant buying experience", "Attentive to figures and strong analytical skills", "Fashion lovers welcome!"], "locations": ["Kowloon Bay"], "categories": ["Merchandising & Purchasing", "Footwear", "Others", "Procurement / Purchasing / Sourcing"], "post_time": "2022-01-04T09:32:00Z", "salary": {"currency": null, "max": null, "min": null, "period": "monthly", "term": null}, "salary_visible": false, "title_keywords": ["assistant"], "responsibilities": ["management", "control", "data", "business opportunities", "budget", "monitor", "implementation", "compliance", "payment", "schedule", "forecast", "report", "planning"], "requirements": {"degrees": ["university graduate"], "majors": ["related disciplines"], "languages": ["english"], "language_level": ["fluent"], "hard_skills": ["excel", "plus"], "soft_skills": ["business sense", "communication skill", "analytical mind", "pro-active", "result-oriented", "work under pressure"], "languages_combined": [{"language": "english", "language_level": ["fluent"]}]}, "experience_required": {"duration": ["1 year"], "field": ["management", "business development"]}}, {"job_id": "100003009020243", "location_code": "hk", "company": "Fabulous Talent Search Company Limited", "job_title": "Senior Buyer / Buyer / Assistant", "description": "RESPONSIBILITIES\n\nIn-charge of the elicitation stage of the system related projects\nData analysis and data management\nConsolidate and manage online and offline data\nRedesign data structure (online / offline) for future data migration\nAnalyze data and identify improvement areas that support business\nMake sure that end to end business status is always available\nUnderstand business need and build database for new systems\nProcess analysis and improvement\nStudy processes, pain points and potential improvement area with justifiable evidence\nDraft, formalize and propose new process with convincing advantage\nCreate workshop with related teams for further analysis and brainstorming\nImplementation and change management\nProject management\nCreate project scope, coordinate project team and pilot projects\nSupport the project and provide guidance and leadership\nEnsure the respect of project deadlines within your project team\nTeam support, training and knowledge management\nRaise team efficiency by providing support or training\nFacilitate knowledge and information sharing among teams\nQUALIFICATIONS\n\nUniversity graduate\nMin 3 years' experience in data management and system implementation\nSolid experience in data management\nExperience of international supply chain and/or manufacturing is a plus\nCompetence in MS Excel\nVBA Macros and Power Pivot are preferred\nPMP/PMI certification, CBAP certification are preferred\nAbility to synthesize complex issues\nPriority management skills\nStrong analytical mind\nProcess oriented mindset\nFluency in English and Mandarin\n\nInterested parties please send your full resume, current package, salary expectation and date of availability to us by clicking \"Apply Now\".\n\n(Applicants not contacted within six weeks should consider their application unsuccessful. Personal data provided by applicants will be treated confidence and used solely for recruitment purpose only.)", "employment_types": ["Full Time", "Permanent"], "selling_points": ["Top-performing category in Fashion Apparel", "Fresh Graduate will be considered as Assistant", "Competitive salary package"], "locations": ["Others"], "categories": ["Merchandising & Purchasing", "Footwear", "Woven / Knit", "Textiles"], "post_time": "2022-01-04T10:16:09Z", "salary": {"currency": null, "max": null, "min": null, "period": "monthly", "term": null}, "salary_visible": false, "title_keywords": ["assistant"], "responsibilities": ["management", "provide guidance", "change management", "data", "analysis", "systems", "workshop", "teams", "implementation", "data analysis", "project management", "coordinate", "database", "providing support", "analyze data", "migration"], "requirements": {"degrees": ["university graduate"], "majors": [], "languages": ["english", "mandarin"], "language_level": ["fluency"], "hard_skills": ["vba", "plus", "data management", "analysis", "make", "project management", "ms excel", "pilot", "system implementation", "pmp"], "soft_skills": ["project management", "analytical mind", "leadership"], "languages_combined": [{"language": "english", "language_level": ["fluency"]}, {"language": "mandarin", "language_level": ["fluency"]}]}, "experience_required": {"duration": ["min 3 years"], "field": ["supply chain", "management", "manufacturing"]}}, {"job_id": "100003009020874", "location_code": "hk", "company": "Belle Worldwide (Talent Management) Limited", "job_title": "Buying Assistant", "description": "RESPONSIBILITIES\n\nSpecific responsibilities include but are not restricted to:-\n\nResponsible for leading a team to manage the whole process of buying activities\u00a0\u00a0\u00a0\u00a0\u00a0\u00a0\u00a0\u00a0\u00a0\u00a0\u00a0\u00a0\u00a0\u00a0\u00a0\u00a0\u00a0\u00a0\u00a0\u00a0\u00a0\u00a0\u00a0\u00a0\nFormulate and develop buying strategies and budget proposals to achieve sales, profit and inventory targets\nFormulate OTB planning, merchandise mix and assortment planning\nDeploy effective stock replenishment, inventory control, competitive pricing, potential markdowns and margin control strategies and action plans to optimize sales targets\nAnalyze market trends and sales performance on merchandise categories\nWork closely with retail operations, marketing and visual merchandising departments to formulate sales and marketing strategies\nFormulating and developing buying plan in terms of category ratio and size ratio and allocate the right merchandise in right locations\nAssuring achievement of volume, gross margin and profit goals through effective\u00a0merchandise selection, buying, timing and promotion\n\n\u00a0REQUIREMENTS\n\nUniversity graduate in Fashion and Clothing or related disciplines\nMinimum 5 years experience in a retail or wholesale\u00a0buying with 3 years in supervisory level\nGood understanding of supply and demands, retail operation, product cycle and fashion retail knowledge for Hong Kong market\nExcellent fashion and market sense in apparel and retail industry\nSelf-motivated, passionate, with strong analytical presentation and leadership skills\nStrong analytical mind & sensitive to figures\nGood command of both spoken and written English, Cantonese and Mandarin\nCandidates with less experiences will be considered as Senior Buyer", "employment_types": ["Full Time", "Permanent"], "selling_points": ["Assist buying team & prepare sales analyze reports", "Provide admin support to buying team", "Strong knowledge in Excel"], "locations": ["Kwai Hing"], "categories": ["Merchandising & Purchasing", "Footwear", "Others"], "post_time": "2022-01-05T02:21:50Z", "salary": {"currency": null, "max": null, "min": null, "period": "monthly", "term": null}, "salary_visible": false, "title_keywords": ["buying assistant"], "responsibilities": ["control", "stock replenishment", "marketing strategies", "sales performance", "inventory", "budget", "operations", "merchandising", "developing", "otb", "develop", "inventory control", "visual", "plan", "deploy", "plans", "planning"], "requirements": {"degrees": ["university graduate"], "majors": ["related disciplines"], "languages": ["cantonese", "english", "mandarin"], "language_level": ["good command"], "hard_skills": [], "soft_skills": ["passionate", "self-motivated", "leadership skills", "sensitive to figures", "analytical mind", "presentation"], "languages_combined": [{"language": "cantonese", "language_level": ["good command"]}, {"language": "english", "language_level": ["good command"]}, {"language": "mandarin", "language_level": ["good command"]}]}, "experience_required": {"duration": ["3 years", "minimum 5 years"], "field": ["supervisory level", "retail"]}}, {"job_id": "100003009020269", "location_code": "hk", "company": "CTL Recruitment & Consultation Service Limited", "job_title": "Shipping Officer/ Order Management Officer - International Team (Global Sportswear Brand)", "description": "The incumbent will be responsible for the execution of buying activities and ensure a smooth communication with shops for Catalog so as to achieve turnover, gross profit and inventory target.\n\nJob Duties and Responsibilities:\n\nBe responsible for the selection, achieve sales , GP and inventory target of the designated brand(s)\nControl the OTB of designated brand(s), develop buying strategy which is consistent with the business strategy\nWell execution of sales and stock management process include allocation, replenishment and consolidation to achieve T/O, GP% and inventory targets\nRegular review and tracking sales performance through creating timely and accurate weekly/ monthly sales report and analysis\nKeep abreast of industry both online and offline, particular key market competitors, and initiate effective sale and marketing promotion to achieve sales and GP target\nNegotiate with suppliers for exclusive merchandise, special marketing support, additional discount, or stock exchange to achieve the best assortment for retail chain of different shop profile\nRecommend and exploit potential products/brands from market knowledge both online/ offline and data analysis, buy the right products in coherence with the retail chain\u2019s positioning\nPrepare monthly merchandise focus and communicate with inter-departments to achieve monthly target\n\nRequirements:\n\nBachelor\u2019s Degree in Fashion Retailing, or other related disciplines\n1-2 years of relevant buying experience in retail and/or digital platforms with knowledge in OTB planning, buying and inventory management of Footwear\nStrong business sense, attentive to figures and strong analytical skills\nCurious and sensitive to market, embrace changes and act fast\u00a0\nStrong interpersonal skill & negotiation skill, and able to work under pressure\nPassion for Sport fashion will be preferred\nProficiency in Mandarin, English and Chinese\nProficiency in MS Word, Excel, PowerPoint & Chinese Word Processing\n\nWe offer competitive remuneration package with\u00a0a wide range of fringe benefits including\n\n5-day work week\nDiscretionary Bonus\nComprehensive Medical Coverage\nStaff Shopping Discount\nNon-contributory Retirement Benefits Scheme\nBirthday Leave\n\nPlease send resume with present and expected salary to Human Resources Department, Swire Resources Limited,\u00a012/F Kingston International Centre\u00a019 Wang Chiu Road Kowloon Bay\u00a0Hong Kong\u00a0or by clicking the \"Apply Now\" button below.\n\nSwire Resources Limited is Equal Opportunity Employer", "employment_types": ["Full Time", "Permanent"], "selling_points": ["3-4 years exp. in overseas import/export shipping", "5 days work, double pay, medical insurance", "Immediately available is highly preferred"], "locations": ["Not Specified"], "categories": ["Management", "General Management", "Merchandising & Purchasing", "Footwear", "Sales, CS & Business Devpt", "Wholesale"], "post_time": "2022-01-04T10:19:37Z", "salary": {"currency": null, "max": null, "min": null, "period": "monthly", "term": null}, "salary_visible": false, "title_keywords": ["officer", "shipping officer"], "responsibilities": ["communicate with", "control", "stock management", "sales performance", "inventory", "analysis", "replenishment", "develop", "otb", "regular review", "data analysis", "monthly sales report", "tracking"], "requirements": {"degrees": ["degree", "bachelor"], "majors": ["related disciplines"], "languages": ["english", "chinese", "mandarin"], "language_level": ["proficiency"], "hard_skills": ["excel", "chinese word processing", "powerpoint", "analytical skills", "ms word"], "soft_skills": ["attentive", "business sense", "passion for", "interpersonal skill", "analytical skills", "sensitive to", "negotiation skill", "work under pressure"], "languages_combined": [{"language": "english", "language_level": ["proficiency"]}, {"language": "chinese", "language_level": ["proficiency", "proficiency"]}, {"language": "mandarin", "language_level": ["proficiency"]}]}, "experience_required": {"duration": ["1-2 years"], "field": ["inventory management", "digital", "retail", "planning"]}}, {"job_id": "100003009008558", "location_code": "hk", "company": "G.A. Operations Hong Kong Limited", "job_title": "Assistant Merchandiser - R&D Footwear", "description": "Multiple Buying positions in Retail industry:\u00a0\n\nResponsibilities:\u00a0\n\nAssist in OTB plan development\u00a0\nAchieve sales, profits as well as inventory targets through increasing accuracy of buying plan\nMonitor inventory and re-order if necessary\nAnalyze market trends and sales performance on merchandise categories\nAnalyse competitors' performance, customers' profiles, price and product performance\u00a0\nWork on retail price setting and sell-through rate\nForecast seasonal orders\u00a0\u00a0\nProvide feedback to design team on new collection\nCollaborate with internal parties for all product launches and promotions\u00a0\n\nRequirements:\u00a0\u00a0\n\n1 -4 years' working exp. in apparel industry\nSolid\u00a0buying/ planning / merchandising experience in clothing\nStrong\u00a0business and numerical senses\nGood communication and presentation skills\n\nCandidates with less experience will be considered as Buying Assistant\u00a0", "employment_types": ["Full Time", "Permanent"], "selling_points": [], "locations": ["Kowloon Bay"], "categories": ["Merchandising & Purchasing", "Footwear"], "post_time": "2021-12-30T08:21:00Z", "salary": {"currency": null, "max": null, "min": null, "period": "monthly", "term": null}, "salary_visible": false, "title_keywords": ["assistant merchandiser"], "responsibilities": ["collaborate with", "sales performance", "inventory", "monitor", "design", "otb", "plan", "forecast", "internal parties", "analyse"], "requirements": {"degrees": [], "majors": [], "languages": [], "language_level": [], "hard_skills": [], "soft_skills": ["communication", "presentation skills"], "languages_combined": []}, "experience_required": {"duration": [], "field": ["merchandising", "planning"]}}, {"job_id": "100003009056622", "location_code": "hk", "company": "Harvest Strong Limited", "job_title": "Merchandiser - Footwear", "description": "Responsibilities:\n\nmonitor our footwear project orders from product development/sampling -> order processing -> production scheduling -> testing -> manufacturing control -> quality assurance and shipping documentation\nsome travel to China is required\nother ad hoc duties assigned\n\n\nRequirements :\n\n\nExperience in footwear trading will be an advantage\nMature, independent, responsible, positive attitude, well-organized\nExcellent communication\u00a0skill and comprehensive ability\nGood command of written English and spoken Mandarin\nProficiency in MS Excel, Word and Photoshop, Chinese word processing\nWilling to travel to China, if needed\nAble to work under pressure\n\n\nCompetitive remuneration package offer to the right candidates will be commensurate\u00a0according to their work experience.\u00a0\u00a0Interested party, please click \"Apply Now\"\u00a0to submit your full resume, current and expected salary.\n\nData collected would be used for recruitment purpose only.", "employment_types": ["Full Time", "Permanent"], "selling_points": [], "locations": ["Tsim Sha Tsui"], "categories": ["Merchandising & Purchasing", "Footwear"], "post_time": "2022-01-18T05:11:42Z", "salary": {"currency": "HKD", "max": 34999, "min": 20000, "period": "monthly", "term": null}, "salary_visible": true, "title_keywords": ["merchandiser"], "responsibilities": ["ad hoc duties", "control", "shipping", "monitor", "quality", "testing", "scheduling", "order processing", "documentation"], "requirements": {"degrees": [], "majors": [], "languages": ["english", "chinese", "mandarin"], "language_level": ["proficiency", "good command"], "hard_skills": ["ms excel", "chinese word processing", "word", "photoshop"], "soft_skills": ["independent", "responsible", "communication skill", "well-organized", "mature", "positive attitude", "comprehensive", "work under pressure"], "languages_combined": [{"language": "english", "language_level": ["good command"]}, {"language": "chinese", "language_level": ["proficiency"]}, {"language": "mandarin", "language_level": ["good command"]}]}, "experience_required": {"duration": [], "field": ["trading"]}}, {"job_id": "100003009056390", "location_code": "hk", "company": "Christian Louboutin Asia Limited", "job_title": "Assistant Merchandiser, APAC", "description": "JOB OVERVIEW\n\nSupporting Director of Buying and Planning APAC in daily coordination between HQ and countries; providing merchandising support for APAC region (retail stores, e-commerce and outlet) on full Men and Women categories including shoes and leather goods\nWork closely with local teams to drive sales and ST, collect product feedback and cater requests\nMAIN TASKS & RESPONSIBILITIES\n\nMerchandising Analysis\n\nProvide weekly and monthly reports to analyze business trends, draw insights and propose action plans\nSupport regular pricing study to ensure appropriate price and positioning in all currencies\nMonitor new launches and ST performance\nSeasonal Buying Support\n\nFacilitate sales forecast, OTB and assortment plan review for all stores and countries\nSupport buying campaigns on regional level and conduct buying for countries where necessary\nSales and Stock Management\n\nTrace and ensure timely delivery of seasonal collections\nLiaise with Planning Team to manage stock transfer among countries to maximize ST\nPropose reorders and cancellations to react to sales trends\nConduct competitor study to identify business opportunities and provide timely feedback to Paris HQ\nJOB REQUIREMENTS\n\nMinimum 5 years\u2019 of relevant experience from luxury retail industry\nExperience with shoes for multiple markets preferred\nPassionate with fashion, sensitive to trends and capability to depict essence for future merchandise development\nExcellent communications with all levels\nGreat with numbers and analyses, good business acumen, a go-getter\nAgile and efficient\nProficiency in Microsoft Office with good Excel skills\nFluent English, Cantonese and Mandarin\nPlease send us a full resume including present and expected salary and availability to Human Resources Department.\n\nAll information provided by applicants will be used strictly for recruitment purpose. Applicants who are not contacted within one month may consider their applications unsuccessful.", "employment_types": ["Full Time", "Permanent"], "selling_points": ["Analyze business trends, draw insights", "Facilitate sales forecast, OTB and assortment plan", "Seasonal buying support"], "locations": ["Aberdeen"], "categories": ["Merchandising & Purchasing", "Footwear"], "post_time": "2022-01-18T04:08:31Z", "salary": {"currency": null, "max": null, "min": null, "period": "monthly", "term": null}, "salary_visible": false, "title_keywords": ["assistant merchandiser"], "responsibilities": ["stock management", "identify business opportunities", "analysis", "review", "merchandising", "monitor", "otb", "analyze business trends", "forecast", "plan", "liaise with", "plans", "weekly and monthly reports", "planning"], "requirements": {"degrees": [], "majors": [], "languages": ["cantonese", "english", "mandarin"], "language_level": ["fluent"], "hard_skills": ["excel", "agile", "microsoft office", "go", "acumen"], "soft_skills": ["passionate", "efficient", "agile", "sensitive to", "business acumen"], "languages_combined": [{"language": "cantonese", "language_level": ["fluent"]}, {"language": "english", "language_level": ["fluent"]}, {"language": "mandarin", "language_level": ["fluent"]}]}, "experience_required": {"duration": ["minimum 5 years"], "field": ["luxury retail", "relevant experience"]}}, {"job_id": "100003009055274", "location_code": "hk", "company": "Christian Louboutin Asia Limited", "job_title": "Merchandise Planning Manager", "description": "JOB OVERVIEW\nBuild sales projections, prepare strategies and buy plans for the APAC region by working closely with HQ. Create annual open-to-buy/open-to-sell budgets and plans, and insure these plans are executed properly by working closely with merchandising teams (the buyers). The position is responsible for maximising financial objectives (sales and margins) and productivity (sell through, inventory). The APAC buy and allocation plans should benefit the whole region by pulling together Countries\u2019 inputs. It also leads price index recommendation, stock transfers among APAC, and mark down strategies.\n\nMAIN TASKS & RESPONSIBILITIES\n\nSales Forecasts & OTB\n\nBuild sales projections for budgets & forecasts, and 3YPs from a business perspective for Retail and Merchandising, for discussion with country heads and Finance\nDevelop OTB budgets based upon sales history & projections, and assortment (width, depth, collection), define investment by SKUs, insure Countries\u2019 budgets and buy plans are executed in accordance to HQ and APAC strategies\nPrepare analysis with insights from historical sales performance, sales trends and target financial KPIs by working closely with HQs and country planners, to facilitate future buys\nSupervise and support country planners to ensure merchandise appear in the right store at the right time and in the right quantities and assortment, involving planning stock levels and monitoring sales performance\nAnalyse and reforecast businesses to flag risks and identify growth opportunities\nSet up OTB procedures for the region so that country heads and buyers are clear of objectives and actions for their buys\nPartner with Merchandising and Retail to lay out action plans for risks and opportunities identified\nCore & Continuative Planning\n\nPlan sales and forecasts appropriate inventory levels by SKU for core\nBuild planning modules (e.g. stock plans, SKU plans, store ranking/attributes & key demographics) that will help the team to plan, manage and analyse business\nManage core receipts and inventory against targeted months of supply objectives\nPropose action plan to sustain sales trend and guarantee ideal stock cover (reorders/transfers/buys)\nBusiness Analysis\n\nConsolidate weekly/monthly sales analysis for APAC and HQ\nRegularly work with country planners and buyers to understand best sellers/slow movers, to anticipate consolidation strategies, allocation/reallocation, and replenishment\nRecommend price index and gross margins (maximise ROI) for the region and for each country\nAnalyse end of season markdowns and propose markdown strategies based on inventory and sales analysis by countries, by locations to ensure cohesive flow from one season to the next\nAnalyse intended orders and determine whether the orders (on APAC basis) are coherent to the business objectives\nHarmonise report standards among APAC\nInventory Management\n\nAnticipate shipments, receipting capacity, display, BOH of each country to minimise congestions, maximise sales opportunities, sell through, and margins by working closely with logistics\nPerform effective inventory control, inventory management best practices\nOthers\n\nBe the key point of contact and the superuser for EPM project, including training and deployment\nAd hoc projects as assigned\nJOB REQUIREMENTS\n\nMin. undergraduate degree in merchandising, retail management, fashion management or similar discipline\n10 to 15 years of relevant experience in merchandising planning from luxury retail industry, with APAC coverage\nSome experience in buy/retail management/retail sales a definite plus\nExcellent Excel ability\nExcellent communication and negotiation skill sets, entrepreneurial mindset (business driven), and hands on\nFluent English and Mandarin\nPlease send us a full resume including present and expected salary and availability to Human Resources Department.\n\nAll information provided by applicants will be used strictly for recruitment purpose. Applicants who are not contacted within one month may consider their applications unsuccessful.", "employment_types": ["Full Time", "Permanent"], "selling_points": ["Build sales projections, open-to-buy/open-to-sell", "Develop OTB budgets", "Maximize productivity"], "locations": ["Aberdeen"], "categories": ["Merchandising & Purchasing", "Footwear"], "post_time": "2022-01-18T02:00:09Z", "salary": {"currency": null, "max": null, "min": null, "period": "monthly", "term": null}, "salary_visible": false, "title_keywords": ["manager"], "responsibilities": ["receipts", "inventory", "merchandising", "otb", "inventory management", "planning", "plan", "plans", "sales performance", "develop", "logistics", "kpis", "report", "monitoring", "procedures", "inventory control", "contact", "gross margins", "budgets", "analysis", "replenishment", "ad hoc projects", "business analysis", "analyse"], "requirements": {"degrees": ["degree"], "majors": [], "languages": ["english", "mandarin"], "language_level": ["fluent"], "hard_skills": ["excel", "plus"], "soft_skills": ["communication", "hands on", "driven", "negotiation skill"], "languages_combined": [{"language": "english", "language_level": ["fluent"]}, {"language": "mandarin", "language_level": ["fluent"]}]}, "experience_required": {"duration": ["10 to 15 years"], "field": ["management", "merchandising", "relevant experience", "luxury retail", "retail", "planning"]}}, {"job_id": "100003009056284", "location_code": "hk", "company": "ConnectedGroup Limited", "job_title": "Senior Merchandise Planner, APAC (Fashion 40K)", "description": "Representing our global retail client, who is a reputable sports brand. They are now inviting a Retail Sales Planner to join the team. Main mission of this planner is to support the achievement of key product sales forecasting and planning objectives for the brand. To influence forecasting, order tracking, assortment mix analysis and supply management to ensure the achievement of business objective of the DAP distribution business in Asia- Pacific.\n\n\nJob Duties\n\nConsolidate distributor forecast and prepare summary including category growth trends\nProvide information to distributors of product changes, additions & SMUs made\nProvide real time information to Product sales and customer service teams to the sales operations team after each seasonal buy\nCollect and consolidate sample order from distributors\nConfirm launch month of each style based on GTM calendar\nAnalysis of sales meeting forecast to ensure support of category and hero product strategy and growth in line with budget\nPrepare regular reports for business analysis from gathering markdown plans from distributors\nFollow-up with costing team on outstanding pricings and update distributors/subsidiaries for any price changes\n\n\nRequirement\n\n5+ years of regional merchandising and sales planning experience, must have experience in Sports / Fashion industry\nProven success in sales reporting and working with Management team\nHigh regard and attention for detail, accuracy and displays analytical and numeracy skills\nExcellent in planning, organizing and problem solving\nHigh level of proficiency in Excel and PowerPoint is a must\nPost Covid Travel is required\n\n\n\nInterested individuals please send CV (word format) to Eleanor Chan (Eleanor . Chan @connectedgroup.com) for more information", "employment_types": ["Full Time", "Permanent"], "selling_points": ["key product sales forecasting", "planning objectives", "assortment mix analysis"], "locations": ["Overseas"], "categories": ["Merchandising & Purchasing", "Footwear", "Sales, CS & Business Devpt", "Retail Sales"], "post_time": "2022-01-18T03:50:22Z", "salary": {"currency": null, "max": null, "min": null, "period": "monthly", "term": null}, "salary_visible": false, "title_keywords": [], "responsibilities": ["operations", "analysis", "budget", "teams", "customer service", "reports", "forecast", "business analysis", "plans"], "requirements": {"degrees": [], "majors": [], "languages": [], "language_level": [], "hard_skills": ["problem solving", "excel", "word", "powerpoint"], "soft_skills": ["problem solving"], "languages_combined": []}, "experience_required": {"duration": ["5+ years"], "field": ["merchandising", "planning"]}}, {"job_id": "100003009041520", "location_code": "hk", "company": "Michael Kors (HK) Limited", "job_title": "Senior Planner / Associate Planning Manager", "description": "SUMMARY:\n\n\nThe objective of this position is to plan and manage inventory allocation in order to maximize sales and margin across both Full Price and Outlet channels within Hong Kong/Macao, and extend regional support to Taiwan/Australia.\u00a0\n\nJOB RESPONSIBILITIES\n\nBe responsible for allocation / replenishment / rebalancing for selected product categories within Hong Kong/Macao and support Taiwan/Australia for regional allocation\nAllocate, replenish, and rebalance inventory by store, according to\n- Seasonal flow, including seasonal launch, floor sets, markdown, and liquidation\n- Product lifecycle and markdown risk (such as core/carryover items vs. fashion newness)\n- Sales performance by store, down to the SKU level\n- Optimal inventory levels by store according to store type, sales performance and store capacity\n- Anticipate peak / slow shopping periods and holidays\n- Anticipate future product (such as reserving and rebalancing) according to store opening plan\nPrioritize key stores and understand product substitutes in limited stock situations\nPrepare inventory for new store openings\nPromotion and markdown management, update relevant system\nDevelop stock clearance plan, organize and coordinate return\nAct as key stakeholder to provide GC Merch team, the insight of HK/Macao business, from merchandising planning point of view\nHandle assortment planning including price and discount setting for Sogo Thankful event and Brand sale\nIssue TN and SO for HK, Macao and Taiwan orders.\u00a0 Coordinate with HK logistics and EU team for Australia orders\nPartner with other team members and functions as needed, for example\n- Partner with logistics to ensure timely execution of allocation / replenishment\n- Communicate with stores on store requests and needs; enforce efficient transfers / returns from stores\n- Work with buyers to understand launching schedule, product needs by store and substitutes in limited stock situations\n- Partner with marketing and VM to support special marketing requests (e.g. store events) and VM (e.g. mannequin looks)\n\u00a0SKILLS and WORK EXPERIENCE\n\nBachelor\u2019s Degree or above\nStrong record of academic and professional performance, with references\n6-8 years\u2019 inventory management experience in the retail industry (experience in APAC management is preferred)\nExtremely sensitive to number; strong data analysis and Excel skills\nEstablish and develop the inventory management team\nHonest, open, and non-hierarchical attitude\nExcellent communication and interpersonal skills\nStrong prioritization and organizational skills\nDriven to execute efficiently and accurately\nProfessional demeanor\nProactive, ambitious, flexible, and entrepreneurial; able to work in a startup environment\nComputer and systems literate\nFluent in English, good Mandarin is a plus\n\nWe offer remuneration package\u00a0commensurate with qualification and experience to the successful candidate.\u00a0 If you would like to apply for this position or find out more, please press 'Apply Now'.\n\n(Data collected will be treated as strict confidential and will be used for recruitment purpose only.)", "employment_types": ["Full Time", "Permanent"], "selling_points": ["At least 6 years\u2019 exp. inventory management", "Computer and systems literate", "Fluent in English, good Mandarin is a plus."], "locations": ["Tsim Sha Tsui"], "categories": ["Merchandising & Purchasing", "Footwear", "Handbag", "Textiles"], "post_time": "2022-01-12T03:59:40Z", "salary": {"currency": null, "max": null, "min": null, "period": "monthly", "term": null}, "salary_visible": false, "title_keywords": ["associate", "manager"], "responsibilities": ["product categories", "communicate with", "management", "sales performance", "inventory", "systems", "merchandising", "replenishment", "coordinate with", "develop", "coordinate", "inventory management", "data analysis", "communication", "logistics", "schedule", "plan", "planning"], "requirements": {"degrees": ["degree or above", "bachelor"], "majors": [], "languages": ["english", "mandarin"], "language_level": ["good", "fluent"], "hard_skills": ["vs", "excel", "analysis", "plus"], "soft_skills": ["efficient", "organizational skills", "flexible", "responsible", "timely", "prioritize", "sensitive to", "communication and interpersonal skills", "honest", "proactive", "driven"], "languages_combined": [{"language": "english", "language_level": ["fluent"]}, {"language": "mandarin", "language_level": ["good", "fluent"]}]}, "experience_required": {"duration": ["6-8 years"], "field": ["inventory management", "management", "retail industry"]}}]