[{"job_id": "100003009055407", "location_code": "hk", "company": "Pricerite Stores Ltd", "job_title": "Senior Officer, Merchandising Administration and Process Control", "description": "Job Responsibilities:\n\nResponsible for merchandising administration to support buying activities\nStreamline merchandising workflow, including but not limit to product & supplier information management, process flow, approval flow\nSet up and update guidelines and policies for process control\nManage and ensure data input quality and accuracy of subordinates\nHandle ad hoc projects assigned by management\n\nJob Requirements:\n\nHigher Diploma or above in Business Administration or related discipline\n5 years administrative experience, preferably from retail or merchandising sector\nSensitive to large amount of data and attentive to details\nExperience with PIM system is desirable\nTeamwork players, result-oriented, fast learning, self-motivated\nProficiency in MS Word, Excel, PowerPoint & Chinese Word Processing\nGood written in English and Cantonese\nImmediate available is preferable", "employment_types": ["Full Time", "Permanent"], "selling_points": ["Streamline merchandising workflow", "Purchase Discount", "Birthday Leave"], "locations": ["Kowloon Bay"], "categories": ["Admin & HR", "Clerical / Admin Staff", "Merchandising & Purchasing", "Furniture", "Home Appliances"], "post_time": "2022-01-18T02:28:28Z", "salary": {"currency": null, "max": null, "min": null, "period": "monthly", "term": null}, "salary_visible": false, "title_keywords": ["senior officer", "merchandising"], "responsibilities": ["management", "control", "guidelines", "policies", "merchandising", "data input", "quality", "ad hoc projects", "administration"], "requirements": {"degrees": ["higher diploma or above"], "majors": ["business administration"], "languages": ["cantonese", "english", "chinese"], "language_level": ["proficiency", "good"], "hard_skills": ["excel", "chinese word processing", "powerpoint", "ms word"], "soft_skills": ["self-motivated", "attentive to details", "teamwork", "sensitive to", "learning", "result-oriented"], "languages_combined": [{"language": "cantonese", "language_level": ["good"]}, {"language": "english", "language_level": ["good"]}, {"language": "chinese", "language_level": ["proficiency"]}]}, "experience_required": {"duration": ["5 years"], "field": ["administrative", "merchandising", "retail"]}}, {"job_id": "100003009054193", "location_code": "hk", "company": "aimHigher Consultancy Limited", "job_title": "Buyer / Buying Manager \u2013 Luxury Consumer Lifestyle Group", "description": "Company Description\n\nOur client is a leading luxury lifestyle retailer with a large amount of retail POS in Hong Kong. Due to upcoming expansion planning, they are planning to expand their product portfolio. They have reserved a huge amount of budget for the upcoming aggressive expansion. Therefore, they are looking for\u00a0Buyer/Assistant Buyer to join their expanding Buying team.\n\nResponsibilities\n\nAct as the lead buyer to manage the overall category product assortment and product portfolio.\nIdentify potential suppliers to source new products to enhance the product portfolio.\nManage merchandising mix and promotion campaigns for both existing and new products for stores in different locations.\nNegotiate with suppliers to achieve competitive prices and terms.\nWork with retail operation team to identity hero products and slow moving stocks to improve the replenishment plan for upcoming promotion activities.\nConduct sales forecast and analysis in order to develop the pricing strategies and buying category.\n\nRequirements\n\nDegree in Business Administration or related discipline.\n5- 10 years buying/ category management experience in luxury brands, experience within lifestyle would be an added bonus.\nOpen candidate from luxury fashion brand to apply too.\nGood command in spoken and written English and Chinese.\nLess experience will be considered as a Assistant Buyer.\n\nInterested parties please send your updated resume in WORD format with current and expected salaries (quoting Employer Ref:)", "employment_types": ["Full Time", "Permanent"], "selling_points": ["Exposure To New Buy Category, Career Development.", "Welcoming Candidates from Luxury Fashion Masion", "Young Working Environment With High Autonomy."], "locations": ["Not Specified"], "categories": ["Merchandising & Purchasing", "Fabrics", "Woven / Knit", "Furniture"], "post_time": "2022-01-17T08:45:40Z", "salary": {"currency": null, "max": null, "min": null, "period": "monthly", "term": null}, "salary_visible": false, "title_keywords": ["buying manager"], "responsibilities": ["analysis", "merchandising", "replenishment", "develop", "promotion campaigns", "forecast", "plan"], "requirements": {"degrees": ["degree"], "majors": ["business administration"], "languages": ["english", "chinese"], "language_level": ["good command"], "hard_skills": [], "soft_skills": [], "languages_combined": [{"language": "english", "language_level": ["good command"]}, {"language": "chinese", "language_level": ["good command"]}]}, "experience_required": {"duration": ["5- 10 years"], "field": ["management"]}}, {"job_id": "100003009052176", "location_code": "hk", "company": "Champion Global Services Limited", "job_title": "Project Officer \u2013 FF&E and OS&E", "description": "Responsibilities:\n\nAssist in handling and managing FF&E andOS&E projects including but not limited to budget control, project schedule and tender process\nSupport procurement goods & services by obtaining competitive quotes from reliable vendors\nIdentify potential suppliers and manage the relationships with suppliers to support the procurement function\nCoordinate with all relevant parties to ensure timely delivery and installation as per approved and prescribed procedure\nIssue tender, verify and input evaluation and analysis documents\nIssue and track Purchase Orders from issuance, shop drawing, production, QA&QC of goods, deliveries and payment to suppliers.\nHandle ad hoc projects as assigned\n\nRequirements:\n\nDegree or above in Procurement, Supply Chain or other related disciplines\n2 \u2013 3 years\u2019 experience in managing FF&E andOS&E procurement projects; experience gained in hotel industry or sizeable organization is an advantage\nExperience in managing overseas projects is an advantage\nGood knowledge in interior design is an advantage\nWell-organized, independent and able to work under pressure\nGood communication and problem-solving analytical skills\nSelf-motivate, proactive and high integrity with trustworthy personality\nProficient in MS Office applications\nGood command of both spoken and written English and Chinese (including Putonghua)\nCandidates with less experience and qualifications will be considered as Senior Project Officer\n\nSalary and benefits will be commensurate with qualifications and experience.\u00a0 Interested parties, please send a full resume with present and expected salary, and date available to The Human Resources Department, 32/F., Great Eagle Centre, 23 Harbour Road, Wanchai, Hong Kong or e-mail to us.\u00a0\u00a0\u00a0(Please quote the reference no. on the envelope and the covering letter.)\n\nTo know more about us, please visit our website at http://www.greateagle.com.hk\n\nWe are an equal opportunity employer and welcome applications from all qualified candidates.\n\nPersonal data collected will be treated in strict confidence and used only for recruitment-related purpose. Applicants who have not heard from us within four weeks may consider their applications unsuccessful. All personal data will be destroyed after 12 months.", "employment_types": ["Full Time", "Permanent"], "selling_points": ["FF&E and OS&E projects", "Prcourement consultancy services", "Hospitality industry"], "locations": ["Wan Chai"], "categories": ["Hospitality / F & B", "Others", "Merchandising & Purchasing", "Furniture", "Procurement / Purchasing / Sourcing"], "post_time": "2022-01-17T02:21:22Z", "salary": {"currency": null, "max": null, "min": null, "period": "monthly", "term": null}, "salary_visible": false, "title_keywords": ["project officer"], "responsibilities": ["installation", "analysis", "coordinate with", "purchase", "payment", "ad hoc projects", "schedule", "tender", "evaluation", "budget control"], "requirements": {"degrees": ["degree or above"], "majors": ["related disciplines"], "languages": ["putonghua", "english", "chinese"], "language_level": ["good command"], "hard_skills": ["problem-solving", "ms office", "analytical skills"], "soft_skills": ["independent", "trustworthy", "problem-solving", "well-organized", "integrity", "analytical skills", "communication", "proactive", "work under pressure"], "languages_combined": [{"language": "putonghua", "language_level": ["good command"]}, {"language": "english", "language_level": ["good command"]}, {"language": "chinese", "language_level": ["good command"]}]}, "experience_required": {"duration": ["3 years"], "field": ["hotel industry", "procurement"]}}, {"job_id": "100003009051745", "location_code": "hk", "company": "Amazin Consultants Limited", "job_title": "Merchandiser / Project Assistant", "description": "Our client is a reputable manufacturer of commercial furniture, supplying to multinational hospitality group and commercial industry.\u00a0 They are seeking for a merchandiser / project assistant to join the team.\n\n\nDevelopment project coordination\nChina factory liaison\nFollow up clients' order and\u00a0inquires\nResponsibilities:\n\nHandle inquiries from potential clients and prepare quotation as needed.\nFollow-up clients orders and development projects.\u00a0 Liaise with production unit in China to ensure projects deliver on a timely manner.\nBe a project owner and assist to resolve any issue during production when arise.\nWork closely with designers, production team, logistics team etc.\n\nRequirements:\n\nDiploma or above\nMinimum 3 years of working experience preferable in manufacturing or trading business.\nExposure furniture, fit-out project, interior design would be an advantage.\nExperience in Auto Cad is a plus.\nGood communication skills in English, Putonghua and Cantonese.\nResponsible, high-sense of ownership, good team work spirit.\n\n\n\nFor interested parties, please send your full resume\u00a0 to resume@ amazinhr.com\n\nPersonal information is collected and used for the purposes of recruitment only. We use your personal information to contact you for the position you apply and/or for the vacancy that matches with your profile.", "employment_types": ["Full Time"], "selling_points": ["Development project coordination", "Client and factory liaison", "Follow up clients order"], "locations": ["Not Specified"], "categories": ["Manufacturing", "Product Development / Management", "Merchandising & Purchasing", "Furniture"], "post_time": "2022-01-16T23:56:21Z", "salary": {"currency": "HKD", "max": 19999, "min": 17000, "period": "monthly", "term": null}, "salary_visible": true, "title_keywords": ["merchandiser", "project assistant"], "responsibilities": ["liaise with", "logistics", "quotation", "a timely manner"], "requirements": {"degrees": ["diploma or above"], "majors": [], "languages": ["cantonese", "putonghua", "english"], "language_level": ["good"], "hard_skills": ["plus", "auto cad"], "soft_skills": ["good team work", "communication skills", "responsible"], "languages_combined": [{"language": "cantonese", "language_level": ["good"]}, {"language": "putonghua", "language_level": ["good"]}, {"language": "english", "language_level": ["good"]}]}, "experience_required": {"duration": ["minimum 3 years"], "field": ["business", "manufacturing", "trading"]}}, {"job_id": "100003009056154", "location_code": "hk", "company": "API Lab Testing Limited", "job_title": "Senior Customer Service Executive", "description": "Responsibilities:\u00a0 \u00a0\n\nPrimary customer interface to coordinate customer requirement to lab operations.\nProvide friendly and professional pre-sale and post-sales throughout order transaction.\nHandle sample registration and release of test report.\nHandle customer enquiry on service capacity, quotation, reporting status, report contents and complaints.\nFollow up with customer on missing information and samples.\nProvide regular summary report to customer regarding the lab service.\n\nRequirements:\n\nMinimum 3 years\u2019 relevant experience in laboratory testing company (Candidates with less experience will be considered as Customer Service Executive).\nHighly-organized, able to work independently and capable of working under pressure with multi-task assignments.\nGood command of English and Chinese.\nGood computer skills.\nFamiliar with European regulations/standards is an advantage.\nHaving the experience of component sorting is an advantage.\n\nIMMEDIATELY AVAILABLE is PREFERRED\n\n5 days work (overtime and weekend work required if necessary).\n\n*Interested parties please send your full resume stating date of availability, present and expected salary\u00a0via\u00a0APPLY NOW Button.*", "employment_types": ["Full Time"], "selling_points": ["Customer service", "English and Chinese", "Good computer skills"], "locations": ["Tsuen Wan Area"], "categories": ["Sales, CS & Business Devpt", "Customer Service - Supervisor / Officer", "Merchandising & Purchasing", "Furniture", "Toy"], "post_time": "2022-01-18T03:25:49Z", "salary": {"currency": null, "max": null, "min": null, "period": "monthly", "term": null}, "salary_visible": false, "title_keywords": ["senior customer service executive"], "responsibilities": ["reporting", "operations", "quotation", "coordinate", "contents", "report"], "requirements": {"degrees": [], "majors": [], "languages": ["english", "chinese"], "language_level": ["good command"], "hard_skills": ["computer skills"], "soft_skills": ["organized", "work independently", "under pressure", "capable", "multi-task", "customer service"], "languages_combined": [{"language": "english", "language_level": ["good command"]}, {"language": "chinese", "language_level": ["good command"]}]}, "experience_required": {"duration": ["minimum 3 years"], "field": ["laboratory testing", "customer service", "relevant experience"]}}, {"job_id": "100003009051223", "location_code": "hk", "company": "Easy Job Centre", "job_title": "Merchandiser / Senior Merchandiser (Sundries / Seasonal / Furniture / Home Appliance)", "description": "Job Responsibilities:\nTo manage all aspects of the buying process for the designated portfolio\nTo check all invoices thoroughly, maintain\u00a0accurate data entry in PO system\nTo record merchandise details and complete product information in timely manner\nTo prepare buying reports for analysis, follow up orders and monitor stock levels\nTo communicate\u00a0and work regularly with vendors, warehouse, store operations, logistics and sales\nTo provide administrative support\u00a0to buying team\n\nJob Requirements:\n\nStrong Passion in Fashion\u00a0\nDegree in Textile/Fashion Design or related discipline\nSome relevant experience, preferably in the luxury Lifestyle industry\nStrong analytical, negotiation and communication skills\nProactive, attentive to details and able to follow tight timeline\nExcellent command of written & spoken English & Chinese\nImmediate availability preferred\n\nAt Lane Crawford we support our employees with a range of benefits reflecting the importance we place\u00a0on\u00a0the well being of our staff. In addition to a competitive salary, discretionary bonus, annual leave, provident fund, medical and dental coverage and staff purchase privileges,\u00a0 we provide shuttle buses to the Company Head Office, various social recreation activities, Staff Assistance Programme, best in-class training and development and regional work opportunities for the right candidate.\n\nAll information provided will be treated in strict confidence and used for recruitment purposes only", "employment_types": ["Full Time"], "selling_points": [], "locations": ["Yau Tsim Mong Area"], "categories": ["Merchandising & Purchasing", "Furniture", "Home Appliances", "Sundries"], "post_time": "2022-01-15T05:19:56Z", "salary": {"currency": null, "max": null, "min": null, "period": "monthly", "term": null}, "salary_visible": false, "title_keywords": ["merchandiser", "senior merchandiser"], "responsibilities": ["follow up orders", "invoices", "data entry", "operations", "analysis", "monitor", "maintain", "reports", "logistics", "provide administrative support"], "requirements": {"degrees": ["degree"], "majors": ["design"], "languages": ["english", "chinese"], "language_level": ["excellent"], "hard_skills": [], "soft_skills": ["communication skills", "negotiation", "attentive to details", "passion in", "proactive"], "languages_combined": [{"language": "english", "language_level": ["excellent"]}, {"language": "chinese", "language_level": ["excellent"]}]}, "experience_required": {"duration": [], "field": ["relevant experience"]}}, {"job_id": "100003009050142", "location_code": "hk", "company": "Lane Crawford (Hong Kong) Limited", "job_title": "Merchandise Coordinator - Fashion (Fresh graduate is also welcomed)", "description": "1 Post for Seasonal / Party / Toys / Gift Premium\n1 Post for Fashion Accessories / Bags / Footwear\n1 Post for Household / Kitchenware / Bathroom\n1 Post for Home Appliance / Lighting / Furniture\n1 Post for Consumer Electronics\n\nRequirements\u00a0\u00a0\n\n2-8 years of working experience of product development, sourcing and merchandising\nExtensive knowledge in Toys / Gift Premium / Home Appliance / Household products is a preferable, Sundries items are also consider\nSupplier selection and vendor management, ensuring best buy and good services from suppliers\nSource and review new suppliers\u2019 capabilities to establish long term strategic vendor management program\nWork with Engineering and QA team to ensure product comply with US, European and other countries regulations\nManage sample development and follow up production run for all projects\nPrepare merchandising information and report for project updates ie cost sheets, purchase orders and relevant documents\nCoordinate with QA and/or Technical team on sample process, production orders and delivery status\nWork with factories and internal shipping team to ensure all shipping documents are in plan for on time shipment\nFacilitate order placement process with suppliers\nExcellent communication and interpersonal skills\nGood command of both written and spoken English and Chinese (Putonghua)\nLess experienced candidates will also be considered as Assistant Merchandiser\n\nInterested parties, please send your resume with expected salary by clicking the below \"apply now\" button.\u00a0You can ask click on the website\u00a0www.easyjobhk.com\u00a0for more details about the company", "employment_types": ["Permanent"], "selling_points": ["To manage all aspects of the buying process", "To check all invoices thoroughly", "To prepare buying reports for analysis"], "locations": ["Aberdeen"], "categories": ["Merchandising & Purchasing", "Footwear", "Handbag", "Furniture"], "post_time": "2022-01-14T09:51:41Z", "salary": {"currency": null, "max": null, "min": null, "period": null, "term": null}, "salary_visible": false, "title_keywords": ["coordinator"], "responsibilities": ["regulations", "shipping documents", "management", "cost", "shipping", "review", "merchandising", "coordinate with", "project updates", "communication", "purchase", "plan", "report"], "requirements": {"degrees": [], "majors": [], "languages": ["putonghua", "english", "chinese"], "language_level": ["good command"], "hard_skills": ["vendor"], "soft_skills": ["communication and interpersonal skills", "extensive"], "languages_combined": [{"language": "putonghua", "language_level": ["good command"]}, {"language": "english", "language_level": ["good command"]}, {"language": "chinese", "language_level": ["good command"]}]}, "experience_required": {"duration": ["2-8 years"], "field": ["product development", "merchandising"]}}, {"job_id": "100003009043115", "location_code": "hk", "company": "Maven Furniture (Hong Kong) Limited", "job_title": "Project Manager/Assistant Project Manager", "description": "Responsibilities\n\nreport to Project Director to manage assigned account\nmanage project team with size of 10~20 staff\nliaise with client/designer/factory on luxury retail millwork supply\n\nRequirements\n\nDiploma in design, project management or related disciplines\n5 years or above experience within retail millwork/bespoke furniture/fitting-out industry\nKnowledge with wooden, glass and metal materials are necessary\nAble to tackle problems on drawing and furniture fitting\nHard working and able to handle pressure\nStrong communication and interpersonal skills\nGood command of English, Mandarin and Cantonese\nKnowledge in AutoCAD is preferred but not necessary\nFrequent travel and station in Dongguan is REQUIRED\nLess experience will consider as Assistant Project Manager\n\nWe offer competitive remuneration package to the right candidate. Interested parties are invited to send full resume, present and expected salary to\u00a0email address by clicking \"Apply Now\"\n\n\nPersonal data will be used for recruitment purpose only.\n", "employment_types": ["Full Time", "Permanent"], "selling_points": ["Diploma in design, project management", "5 years or above experience within retail millwork", "5 days work"], "locations": ["Mong Kok"], "categories": ["Design", "Interior", "Engineering", "Engineering Project Management", "Merchandising & Purchasing", "Furniture"], "post_time": "2022-01-12T09:50:34Z", "salary": {"currency": null, "max": null, "min": null, "period": "monthly", "term": null}, "salary_visible": false, "title_keywords": ["project manager", "assistant project manager"], "responsibilities": ["liaise with client", "report"], "requirements": {"degrees": ["diploma"], "majors": ["related disciplines", "project management", "design"], "languages": ["cantonese", "english", "mandarin"], "language_level": ["good command"], "hard_skills": ["project management", "autocad"], "soft_skills": ["project management", "hard working", "communication and interpersonal skills"], "languages_combined": [{"language": "cantonese", "language_level": ["good command"]}, {"language": "english", "language_level": ["good command"]}, {"language": "mandarin", "language_level": ["good command"]}]}, "experience_required": {"duration": ["5 years"], "field": ["retail"]}}, {"job_id": "100003009043123", "location_code": "hk", "company": "Maven Furniture (Hong Kong) Limited", "job_title": "Project Coordinator", "description": "Responsibilities\n\nreport to Project Director and assist Project Manager on assigned project\ncoordinate with factory production, visit site to coordinate with all other contractor\n\nRequirements\n\nDiploma or above in design, project management or related disciplines\nExperience from retail millwork manufacturer or fitting out contractor is preferred\nGood command of spoken/written English and Mandarin\nFamiliar with words, excels, outlook, Chinese input is necessary\nIndependent, mature, responsible and self-motivated\nKnowledge in AutoCAD is preferred but not necessary\nFrequent travel and station in Dongguan is REQUIRED\n\nWe offer competitive remuneration package to the right candidate. Interested parties are invited to send full resume, present and expected salary to email address\u00a0by clicking \"Apply Now\"\n\n\nPersonal data will be used for recruitment purpose only.\n", "employment_types": ["Full Time", "Permanent"], "selling_points": ["Diploma in design, project management", "Experience within retail millwork", "5 days work"], "locations": ["Mong Kok"], "categories": ["Design", "Interior", "Engineering", "Engineering Project Management", "Merchandising & Purchasing", "Furniture"], "post_time": "2022-01-12T09:51:10Z", "salary": {"currency": null, "max": null, "min": null, "period": "monthly", "term": null}, "salary_visible": false, "title_keywords": ["project coordinator"], "responsibilities": ["coordinate with", "report"], "requirements": {"degrees": ["diploma or above"], "majors": ["related disciplines", "project management", "design"], "languages": ["english", "chinese", "mandarin"], "language_level": ["good command"], "hard_skills": ["chinese input", "words", "project management", "outlook", "autocad"], "soft_skills": ["self-motivated", "independent", "responsible", "mature", "project management"], "languages_combined": [{"language": "english", "language_level": ["good command"]}, {"language": "chinese", "language_level": []}, {"language": "mandarin", "language_level": ["good command"]}]}, "experience_required": {"duration": [], "field": ["retail"]}}, {"job_id": "100003009042690", "location_code": "hk", "company": "Simplylife Limited", "job_title": "Merchandising Manager / Senior Merchandiser", "description": "Job Highlight\n\nMin 10 years\u2019 experience in Retail preferably in Furniture,\u00a0 Household, Home appliances,\u00a0less experience should be consider as Senior Merchandiser\u00a0\nExcellent negotiation skills, entre preneurship\nDetail-minded, able to work independently and under tight schedule\nStrong leadership, good communication and problem solving skills\nProficiency in both spoken and written English and Mandarin\nPresentable, initiative, aggressive with good communication skills\u00a0\nExperience in factory manufacturing is preferable\n\nJob Description\n\nFormulate and Implement merchandise strategies to achieve sales and margin growth target\nDevelop annual, seasonal and monthly merchandise plans\nResponsible for product development\nOptimize and plan inventory into the warehouse and stock turnover\nBuild collaboration with supplier, internal and external stakeholders\nNegotiate trading terms and manager supplier\u2019s portfolio\u00a0 \u00a0 \u00a0\u00a0\n\nResponsibilities:\n\nDevelop oversea merchandising strategy and category management on Furniture, House and Home Appliances.\nLead product development including strategy, sourcing, negotiation, promotion planning.", "employment_types": ["Full Time"], "selling_points": [], "locations": ["Kwai Tsing Area"], "categories": ["Merchandising & Purchasing", "Furniture"], "post_time": "2022-01-12T08:24:30Z", "salary": {"currency": null, "max": null, "min": null, "period": "monthly", "term": null}, "salary_visible": false, "title_keywords": ["merchandising manager", "senior merchandiser"], "responsibilities": ["management", "inventory", "merchandising", "develop", "communication", "schedule", "plan", "plans", "planning"], "requirements": {"degrees": [], "majors": [], "languages": ["english", "mandarin"], "language_level": ["proficiency"], "hard_skills": ["problem solving skills"], "soft_skills": ["detail-minded", "communication skills", "work independently", "negotiation", "responsible", "presentable", "communication", "negotiation skills", "problem solving skills", "leadership", "initiative"], "languages_combined": [{"language": "english", "language_level": ["proficiency"]}, {"language": "mandarin", "language_level": ["proficiency"]}]}, "experience_required": {"duration": ["min 10 years"], "field": ["manufacturing", "retail"]}}, {"job_id": "100003009008924", "location_code": "hk", "company": "Mint Furniture Limited", "job_title": "PROJECT COORDINATOR (FURNITURE)", "description": "Requirements:\n\nHigh Diploma holder or above.\nMinimum 2-3 years working experience in project management and coordination for F&B, residential or FF&E projects, preferred in furniture products or interior fitting-out industry.\u00a0\u00a0\nGood knowledge of shop drawing.\nResponsible, well-organized, detailed-minded and self-motivated.\u00a0\nAble to work independently with good coordination skills.\u00a0\nGood command of spoken and written\u00a0in Cantonese, English and Mandarin.\u00a0\nProficiency with AutoCAD, Photoshop and Microsoft Office applications.\nWilling to travel.\u00a0\nCandidate with more experience will be considered as senior role.\u00a0\nResponsibilities:\n\n\nProject coordination with clients, contractors and vendors.\nPlan, organise and handle projects from commencement to completion to deliver projects on time and on budget.\u00a0\nHandle the\u00a0preparation and submission of material, sample, shop drawing and the relevant document. \u00a0\nTake part in project meetings/site meetings, occasionally travel to Mainland, China for inspection.\u00a0\nHandle ad-hoc duties as assigned.\n\nWe offer the\u00a0competitive remuneration package to the right candidate.\n\n\n\n\nWORKING LOCATION\n\n\n\nTsuen Wan, which is 10 minutes walk from Tsuen Wan West MTR station.\n\n\nPlease apply this post with your portfolio and resume with the expected salary if you are interested in joining with us. All information shall be treated in confidence and used for the purpose of employment only. \u00a0", "employment_types": ["Full Time"], "selling_points": [], "locations": ["Tsuen Wan Area"], "categories": ["Building & Construction", "Building / Construction / QS", "Merchandising & Purchasing", "Furniture", "Sales, CS & Business Devpt", "Sales Administration"], "post_time": "2021-12-30T09:47:37Z", "salary": {"currency": null, "max": null, "min": null, "period": "monthly", "term": null}, "salary_visible": false, "title_keywords": ["project coordinator"], "responsibilities": ["site meetings", "project coordination", "budget", "inspection", "plan", "ad-hoc duties"], "requirements": {"degrees": ["high diploma"], "majors": [], "languages": ["cantonese", "english", "mandarin"], "language_level": ["good command"], "hard_skills": ["microsoft office", "project management", "photoshop", "autocad"], "soft_skills": ["self-motivated", "work independently", "coordination skills", "responsible", "well-organized", "project management", "coordination", "detailed"], "languages_combined": [{"language": "cantonese", "language_level": ["good command"]}, {"language": "english", "language_level": ["good command"]}, {"language": "mandarin", "language_level": ["good command"]}]}, "experience_required": {"duration": ["minimum 2-3 years"], "field": ["project management", "f&b"]}}, {"job_id": "100003009002399", "location_code": "hk", "company": "MUJI (Hong Kong) Company Limited", "job_title": "Assistant Category Manager / Senior Category Planner - Household", "description": "A\u00a0leading designer and distribution agent of interior design fabrics is looking for a\u00a0Product Coordinator to join their team.\n\nResponsibilities\u00a0\n\nProduct sourcing (interior furnishing fabric)\u00a0\nOrder handling from sample development to bulk order\u00a0\nCoordinate between different internal and external parties\u00a0\nMaintain accurate and comprehensive data records in the system\u00a0\nHandle in and out inventory and maintain proper stock records\u00a0\u00a0\n\nRequirements\u00a0\n\nHigh Diploma in Textile or\u00a0has knowledge through working experience\nPassionate in interior furnishing industry\u00a0\nSelf-driven, excellent organizational skill with demonstrated initiative\u00a0\nProficiency in computer skill, especially MS Excel\u00a0\nGood command of both written and spoken English & Chinese (Cantonese and Mandarin)\u00a0\n\nInterested parties please click \"Apply now\" and attached your full resume with expected salary.", "employment_types": ["Full Time", "Permanent"], "selling_points": ["Plan sales & merchandising strategy in household", "Work w/ suppliers in order & delivery arrangement", "Any degree holder, with min. of 6 yrs relevant exp"], "locations": ["Tsim Sha Tsui"], "categories": ["Merchandising & Purchasing", "Furniture", "Sundries", "Procurement / Purchasing / Sourcing"], "post_time": "2021-12-28T05:03:43Z", "salary": {"currency": null, "max": null, "min": null, "period": "monthly", "term": null}, "salary_visible": false, "title_keywords": ["assistant category manager"], "responsibilities": ["data", "inventory", "internal and external parties", "coordinate", "maintain"], "requirements": {"degrees": ["high diploma"], "majors": [], "languages": ["cantonese", "english", "chinese", "mandarin"], "language_level": ["good command"], "hard_skills": ["ms excel", "computer skill"], "soft_skills": ["passionate", "initiative", "organizational skill", "driven"], "languages_combined": [{"language": "cantonese", "language_level": ["good command"]}, {"language": "english", "language_level": ["good command"]}, {"language": "chinese", "language_level": ["good command"]}, {"language": "mandarin", "language_level": ["good command"]}]}, "experience_required": {"duration": [], "field": ["textile"]}}, {"job_id": "100003009001317", "location_code": "hk", "company": "Innomobel Limited", "job_title": "CLERK (5 DAY WORK)", "description": "Responsibilities:\n\nAssisting Purchasing Manager in purchasing functions\nIssue Purchasing order and then follow up vendor/factory production\nData Entry and provide general clerical support to the Purchasing Department\n\nRequirements:\n\nForm 5 or above\nMinimum 1 year relevant experience\nProficient in MS Office and Chinese Word Processing\nGood command of spoken and written Chinese & English and Mandarin\nHard-working, proactive, good communication & interpersonal skills\nImmediate available is preferable\n\nWe offer competitive remuneration package including 5 days work to the right candidate. Interested parties, please send full resume with expected salary and date of availability to us.", "employment_types": ["Full Time"], "selling_points": [], "locations": ["North Point"], "categories": ["Merchandising & Purchasing", "Furniture", "Others", "Procurement / Purchasing / Sourcing"], "post_time": "2021-12-28T02:12:31Z", "salary": {"currency": null, "max": null, "min": null, "period": "monthly", "term": null}, "salary_visible": false, "title_keywords": ["clerk"], "responsibilities": ["clerical support", "data entry"], "requirements": {"degrees": ["form 5 or above"], "majors": [], "languages": ["english", "chinese", "mandarin"], "language_level": ["good command", "proficient"], "hard_skills": ["chinese word processing", "ms office"], "soft_skills": ["communication", "proactive", "hard-working", "interpersonal skills"], "languages_combined": [{"language": "english", "language_level": ["good command"]}, {"language": "chinese", "language_level": ["good command", "proficient"]}, {"language": "mandarin", "language_level": ["good command"]}]}, "experience_required": {"duration": ["minimum 1 year"], "field": ["relevant experience"]}}, {"job_id": "100003008987740", "location_code": "hk", "company": "Manpower Services (Hong Kong) Limited", "job_title": "Merchandiser 25K x 14 (Home Appliances)", "description": "\u00a0 Responsible to perform merchandising duties to generate business for the company\n\n\u2022\u00a0\u00a0 \u00a0Developing new product range with suppliers\n\u2022\u00a0\u00a0 \u00a0Product Category : Kitchen appliances (motor driven , Breakfast set and beverage)\n\u2022\u00a0\u00a0 \u00a0Strong market intelligent, researching and monitoring industry trends and consumer behaviour to anticipate demand and changes in buying patterns\n\u2022\u00a0\u00a0 \u00a0Research, liaise and identify capable factories from product sourcing, development to price negotiation\n\u2022\u00a0\u00a0 \u00a0Monitor order tracking activities to meet market requirements in terms of quality & specification to ensure on time delivery\n\u2022\u00a0\u00a0 \u00a0Negotiations with supplier\n\u2022\u00a0\u00a0 \u00a0Co-ordinating with cross functional teams (QA, Production, Artwork & Logistic teams)\n\u2022\u00a0\u00a0 \u00a0Ensure validate samples to have a complete evaluation to meet customer expectation\n\nWhat will you need?\n\n\n\u2022\u00a0 \u00a0\u00a0Minimum 2 years of merchandising experience & relevant product knowledge in the European market for Electrical Home Appliances\n\u2022\u00a0\u00a0 \u00a0Experience in motor driven (food preparation) , Breakfast set and beverage (Kettle, Toaster, coffee maker, espresso, machine)\n\u2022\u00a0\u00a0 \u00a0Testing & product compliance knowledge (GS compliance, FFU & Chemical test) is a plus\n\u2022\u00a0\u00a0 \u00a0High degree of work ethics and integrity\n\u2022\u00a0\u00a0 \u00a0Detail orientated mindset to ensure the deadlines are met\n\u2022\u00a0\u00a0 \u00a0Good working attitude & proactive\n\u2022\u00a0\u00a0 \u00a0Must be self motivated, self organized, responsible, hard working and independent\n\u2022\u00a0\u00a0 \u00a0Good communication skills in both spoken and written English and Chinese\n\u2022\u00a0\u00a0 \u00a0Good command in English and Mandarin, PC knowledge including MS office is essential\n\u2022\u00a0\u00a0 \u00a0Travel required", "employment_types": ["Full Time"], "selling_points": ["Home Appliances experience", "merchandising", "understand EU standard"], "locations": ["Not Specified"], "categories": ["Merchandising & Purchasing", "Electronics", "Furniture", "Home Appliances"], "post_time": "2021-12-20T07:49:33Z", "salary": {"currency": null, "max": null, "min": null, "period": "monthly", "term": null}, "salary_visible": false, "title_keywords": ["merchandiser"], "responsibilities": ["liaise", "order tracking", "price negotiation", "monitoring", "merchandising", "developing", "monitor", "quality", "ensure on time delivery", "teams", "testing", "compliance", "communication", "evaluation"], "requirements": {"degrees": ["degree"], "majors": [], "languages": ["english", "chinese", "mandarin"], "language_level": ["good command", "good"], "hard_skills": ["plus", "pc knowledge", "ms office"], "soft_skills": ["good working attitude", "organized", "communication skills", "independent", "negotiation", "capable", "responsible", "hard working", "integrity", "self motivated", "detail orientated", "proactive", "driven"], "languages_combined": [{"language": "english", "language_level": ["good command", "good", "good"]}, {"language": "chinese", "language_level": ["good"]}, {"language": "mandarin", "language_level": ["good command", "good"]}]}, "experience_required": {"duration": ["minimum 2 years"], "field": ["food", "merchandising"]}}, {"job_id": "100003008985961", "location_code": "hk", "company": "Universal Design (International) Limited", "job_title": "Administrative Assistant", "description": "We welcome an attentive and well-organized candidate for the position of Administrative Assistant. This requires interacting with clients from prestigious international luxury brands and provides international project exposure.\n\nResponsibilities:\n\nProvide clerical and administrative support to the project team\nComputerized clerical work and answer client inquiries\nFiling, answer phone\nPrepare quotations, invoices\u00a0and shipping documents\nArrange shipping / transportation\nPrepare defect reports\ndata entry and checking for costing sheet\ncheck supplier and vendor invoice\n\nRequirements:\n\nF.5 or above, preferably with 1 or more years of administration experience\nWell organized, careful and attention to details are musts\nProficient with Excel and Word\nGood in spoken and written English and Mandarin\nKnowledge in quotation/invoice, shipping, scheduling and coordination are at an advantage\n\nCompetitive salary with additional bonus and medical benefits available. Interested parties should send your CV, expected salary and availability by email to us.\n\nAll personal data collected will be used for recruitment purposes only.", "employment_types": ["Full Time", "Permanent"], "selling_points": ["Clerical, administration and coordination support", "F.5 or above, preferably with work experience", "Competitive salary, performance bonus, medical"], "locations": ["Tsuen Wan Area"], "categories": ["Admin & HR", "Clerical / Admin Staff", "Building & Construction", "Building / Construction / QS", "Merchandising & Purchasing", "Furniture"], "post_time": "2021-12-20T01:40:57Z", "salary": {"currency": null, "max": null, "min": null, "period": "monthly", "term": null}, "salary_visible": false, "title_keywords": ["administrative assistant"], "responsibilities": ["shipping documents", "shipping", "invoices", "administrative support", "data entry", "invoice", "checking", "reports"], "requirements": {"degrees": [], "majors": [], "languages": ["english", "mandarin"], "language_level": ["good"], "hard_skills": ["excel", "word"], "soft_skills": ["careful and attention to details", "well organized", "coordination"], "languages_combined": [{"language": "english", "language_level": ["good"]}, {"language": "mandarin", "language_level": ["good"]}]}, "experience_required": {"duration": [], "field": ["administration"]}}, {"job_id": "100003008988860", "location_code": "hk", "company": "API Lab Testing Limited", "job_title": "Customer Service Executive / Customer Service Coordinator", "description": "Responsibilities:\u00a0\n\nPrimary customer interface to coordinate customer requirement to Lab operations\nProvide friendly and professional pre-sale and post-sales throughout order transactions\nHandle sample registration and release of test report\nHandle customer enquiry on service capacity, quotation, reporting status, report contents and complaints\nFollow up with customers on missing information and samples\nProvide regular summary report to customers regarding the lab service\n\nRequirements:\n\nBachelor graduated (If nil but with relevant experience will also be considered)\n\nMinimum 2 years\u2019 relevant experience in laboratory testing company (Candidates with less experience will be considered as Customer Service Coordinator)\nFRESH GRAD CANDIDATE IS WELCOMED\nHigh-organized, able to work independently and capable of working under pressure with multi-task assignments\nGood command of English and Chinese\nGood computer skills\nFamiliar with European regulations/standard is an advantage\nHaving the experience of component sorting is an advantage\nIMMEDIATELY AVAILABLE is an advantage\nExcellent communication and interpersonal skills\nWell-organised, independent, responsible, multi-tasking\nIMMEDIATELY AVAILABLE is an advantage and kindly provide expected salary when apply\n\n5 days work (overtime and weekend work required if necessary)", "employment_types": ["Full Time"], "selling_points": ["Customer service", "English and Chinese", "Fresh grad"], "locations": ["Tsuen Wan Area"], "categories": ["Sales, CS & Business Devpt", "Customer Service - Supervisor / Officer", "Merchandising & Purchasing", "Furniture", "Toy"], "post_time": "2021-12-21T01:43:18Z", "salary": {"currency": null, "max": null, "min": null, "period": "monthly", "term": null}, "salary_visible": false, "title_keywords": ["customer service executive", "customer service coordinator"], "responsibilities": ["reporting", "operations", "quotation", "transactions", "coordinate", "contents", "report"], "requirements": {"degrees": ["bachelor"], "majors": [], "languages": ["english", "chinese"], "language_level": ["good command"], "hard_skills": ["computer skills"], "soft_skills": ["organized", "work independently", "under pressure", "capable", "multi-task", "independent", "responsible", "multi-tasking", "customer service", "communication and interpersonal skills", "well-organised"], "languages_combined": [{"language": "english", "language_level": ["good command"]}, {"language": "chinese", "language_level": ["good command"]}]}, "experience_required": {"duration": ["minimum 2 years"], "field": ["laboratory testing", "customer service", "relevant experience"]}}, {"job_id": "100003008988622", "location_code": "hk", "company": "Eternity Consultants (HK) Ltd", "job_title": "Merchandiser / Senior Merchandiser -Toy / Packaging / Packaging", "description": "Responsibilities:\n\nProactive lead and organize the daily execution of merchandising activities from sample to shipment\nFollow-up orders with vendors, customers and internal parties to ensure customer satisfaction and on-time delivery\nAssist in the product development process to ensure that products meet customers' quality and budget requirements\nHandle sample arrangement to customers for approval and lab testing\nMaintain and update order-processing system\nPerform other ad hoc duties\n\nRequirements:\n\nDiploma Graduates/ HKCEE / DSE Graduates\nAt least 3\u00a0- 8 year relevant working experience with\u00a0\u00a0Toys / Packaging\n\nDetail-oriented, well organized, energetic, able to meet deadline\nGood command in both written and spoken English & Mandarin\nProficient in MS Office (Excel, Word, Outlook), Adobe Illustrator & Photoshop\nImmediate available is preferred\nMore experience will consider to be Merchandiser / Senior Merchandiser\n\nMany positions are not been posted in media.\u00a0 If you are looking for job in merchandising field, we are welcome you send your resume to us direct.\n\n*Interested parties, please send full resume with current & expected salary & date available in MS WORD FORMAT ONLY to us\u00a0or fax to 3527 0634*\n\nWe are welcome applicants resend resumes to us even you have applied jobs in our company before.\n\nFor more jobs, please visit our website: www.hketernity.com\n\n(Personal data submitted are for recruitment purpose only.)\u00a0", "employment_types": ["Full Time", "Permanent"], "selling_points": ["merchandising in Toys / Gift, Packaging", "packaging, printing, sourcing new vendors", "5 days, double pay, bonus, medical"], "locations": ["Not Specified"], "categories": ["Merchandising & Purchasing", "Furniture", "Sundries", "Procurement / Purchasing / Sourcing"], "post_time": "2021-12-20T14:12:11Z", "salary": {"currency": null, "max": null, "min": null, "period": "monthly", "term": null}, "salary_visible": false, "title_keywords": ["merchandiser", "senior merchandiser"], "responsibilities": ["ad hoc duties", "budget", "quality", "merchandising", "testing", "maintain", "internal parties"], "requirements": {"degrees": ["diploma", "dse"], "majors": [], "languages": ["english", "mandarin"], "language_level": ["good command"], "hard_skills": ["excel", "word", "adobe illustrator", "outlook", "photoshop", "ms office"], "soft_skills": ["energetic", "well organized", "detail-oriented"], "languages_combined": [{"language": "english", "language_level": ["good command"]}, {"language": "mandarin", "language_level": ["good command"]}]}, "experience_required": {"duration": ["at least 3 - 8 year"], "field": ["toys", "relevant working experience"]}}]