[{"job_id": "100003009054481", "location_code": "hk", "company": "The Wing On Department Stores (Hong Kong) Limited", "job_title": "Assistant Buyer (Household/Apparel/Fashion)", "description": "Responsibilities:\n\nResponsible for the development of products, e.g. household, fashion, shoes & handbags, children & infants, and execution of merchandise assortment as well as buying plans\nSource and develop commercial opportunities, including sourcing new vendors/suppliers to maintain a unique selling proposition for the company\nMonitor inventory through appropriate stock planning and allocation\nCollaborate closely with internal departments to provide product information for supporting marketing campaigns and in-store activities\nNegotiate with suppliers to achieve competitive prices and terms\n\nRequirements:\n\nDegree or above in Supply Chain Management or Business related discipline\n2 years of buying/merchandising experience in retail industry\nHaving overseas buying experiences and supplier network is highly preferable\nStrong market and business sense\nSelf-motivated and able to work under pressure and tight deadlines\nExcellent negotiation and communication skills\nStrong analytical and problem solving skills, perform multi-tasks and good time management skills\nGood command of spoken and written English and Chinese\nImmediately available is highly preferred\n\nCommensurate remuneration and other fringe benefits will be offered to the right candidate. Interested parties please send your\u00a0full resume\u00a0including\u00a0expected salary\u00a0to Human Resources Division, 3/F, Wing On Godown Building, 1 Wang Kee Street, Kowloon Bay, Kowloon, or by click \"APPLY NOW\" button below.\n\n(Candidates not invited for interview within one month may consider their applications filed for future reference.\u00a0 All information collected will be used for recruitment purpose only and will be destroyed after 6 months.)", "employment_types": ["Full Time", "Permanent"], "selling_points": [], "locations": ["Kowloon Bay"], "categories": ["Merchandising & Purchasing", "Footwear", "Handbag", "Procurement / Purchasing / Sourcing"], "post_time": "2022-01-17T09:43:28Z", "salary": {"currency": null, "max": null, "min": null, "period": "monthly", "term": null}, "salary_visible": false, "title_keywords": ["assistant"], "responsibilities": ["collaborate", "inventory", "monitor", "develop", "maintain", "marketing campaigns", "plans", "stock planning"], "requirements": {"degrees": ["degree or above"], "majors": ["business"], "languages": ["english", "chinese"], "language_level": ["good command"], "hard_skills": ["problem solving skills"], "soft_skills": ["communication skills", "self-motivated", "negotiation", "multi-tasks", "business sense", "time management skills", "analytical and problem solving skills", "work under pressure"], "languages_combined": [{"language": "english", "language_level": ["good command"]}, {"language": "chinese", "language_level": ["good command"]}]}, "experience_required": {"duration": ["2 years"], "field": ["retail industry", "merchandising"]}}, {"job_id": "100003009054249", "location_code": "hk", "company": "Grown-Up Manufactory Limited", "job_title": "Senior Merchandising Manager / Senior Project Manager", "description": "OUR COMPANY\u00a0\n\nGROWN UP GROUP (Listed at the Hong Kong Stock Exchange, HKEX: 1842) is one of the world\u2019s leading companies within the bags and luggage industry.\n\nWe manufacture and design for a wide range of international brands, such as Adidas, Samsonite, Wilson and a strong portfolio of licensed and own brands like LEGO, Caterpillar, New Balance and Ellehammer.\n\nWe manufacture at both our own factories and at our numerous partner factories in \u00a0\u00a0Southeast Asia. We serve our customers from our global head office in Hong Kong, our R&D center in Shenzhen, our sales and design offices in Asia, Europe and the USA.\n\n\u00a0\nYOUR ROLE\n\nYou will be a member of our Merchandising Team and report directly to \u00a0 Head of Product Development, Merchandising, Sourcing and Design.\n\nYou have past record of successfully managing a small team.\n\nYou are leading a merchandising team in full merchandising duties from customer inquiry, product development, execute sourcing strategies, production and quality follow up, lab test submission, and handling incident etc., until shipment is completed, so as to ensure proper execution of schedule and timely delivery.\nYou are analyzing costing of products and materials, negotiating with suppliers for better price and target on company\u2019s cost improvement aim.\nYou are maintaining close communication with Brand & Licenses Team and customers\nYou are training the merchandising team on problem solving, product knowledge, merchandising skills and overall abilities\nThe post is based in Shenzhen Office. Frequent travelling is required.\n\n\nYOUR CHARACTER & COMPETENCES\n\nDiploma or above, in fashion, clothing or related discipline will be an advantage\nAt least 8 years of Merchandising experience, preferably in travel goods, garment, apparel, accessories or sports goods, and experience in order follow up and correspondence independently.\nDetailed-minded, flexible and be able to work well under pressure and meet strict deadlines.\nGood problem solving, interpersonal, communication and negotiation skills.\nGood command of both written and spoken English and Chinese, as well as Putonghua.\nAvailable by March 2022.\nWE OFFER YOU\nCompetitive salary\n5-day work week\nMedical insurance\nAnnual leave starting from 14 days\nWork experience with exposure to European markets\nA friendly work environment\n\nYOUR APPLICATION\n\n\u00a0\u00a0\u00a0\u00a0\u00a0 Please send us your application and CV with salary expected today.", "employment_types": ["Full Time", "Permanent"], "selling_points": [], "locations": ["Tai Po Area"], "categories": ["Manufacturing", "Product Development / Management", "Merchandising & Purchasing", "Handbag", "Procurement / Purchasing / Sourcing"], "post_time": "2022-01-17T09:06:51Z", "salary": {"currency": null, "max": null, "min": null, "period": "monthly", "term": null}, "salary_visible": false, "title_keywords": ["merchandising manager", "senior project manager"], "responsibilities": ["cost", "maintaining", "quality", "merchandising", "design", "communication", "schedule", "report"], "requirements": {"degrees": ["diploma or above"], "majors": [], "languages": ["putonghua", "english", "chinese"], "language_level": ["good command"], "hard_skills": ["r&d", "small", "problem solving", "exchange"], "soft_skills": ["flexible", "independently", "under pressure", "timely", "communication", "problem solving", "negotiation skills", "interpersonal", "detailed"], "languages_combined": [{"language": "putonghua", "language_level": ["good command"]}, {"language": "english", "language_level": ["good command"]}, {"language": "chinese", "language_level": ["good command"]}]}, "experience_required": {"duration": ["at least 8 years"], "field": ["garment", "merchandising"]}}, {"job_id": "100003009052082", "location_code": "hk", "company": "TUMI Asia, Limited", "job_title": "Tumi - Product Development Assistant (4-month Contracted)", "description": "Job Responsibilities:\u00a0\n\nAssist Product Development Manager on material development (prepare and send swatch cards to design, vendor and Tumi lab)\nPrepare weekly sample development status report\nHandle daily courier shipment\nTake sample photo, assist Product Development Manager\u00a0prepare sample evaluation report\nMaterial master filing\nJob Requirement:\u00a0\n\nDegree holder in any disciplines\nMinimum 2 years of relevant experience in administration/ operation and fresh graduates will be considered\nProficiency in Microsoft Office, Excel and Word\nGood spoken and written English and Cantonese/Chinese\nInterested parties please send your Full Resume with current and expected salary to us by clicking the \"Apply Now\" button below.\n\nTUMI is an equal opportunity employer and welcome applications from all qualified candidates. All information provided by candidates will be used solely for recruitment purposes. Candidates not notified within eight weeks may consider their application unsuccessful. Unsuccessful applications will be destroyed in strict confidence upon completion of recruitment process.", "employment_types": ["Full Time", "Contract"], "selling_points": ["Five-day work week", "2 years of relevant experience", "Fresh Graduates are welcome to apply"], "locations": ["Tsim Sha Tsui"], "categories": ["Manufacturing", "Product Development / Management", "Others", "Merchandising & Purchasing", "Handbag"], "post_time": "2022-01-17T09:19:47Z", "salary": {"currency": null, "max": null, "min": null, "period": "monthly", "term": null}, "salary_visible": false, "title_keywords": ["product development assistant"], "responsibilities": ["evaluation", "design", "report"], "requirements": {"degrees": ["degree holder"], "majors": ["any disciplines"], "languages": ["cantonese", "english", "chinese"], "language_level": ["good"], "hard_skills": ["excel", "word", "microsoft office"], "soft_skills": [], "languages_combined": [{"language": "cantonese", "language_level": ["good"]}, {"language": "english", "language_level": ["good"]}, {"language": "chinese", "language_level": ["good"]}]}, "experience_required": {"duration": ["minimum 2 years"], "field": ["operation", "relevant experience", "administration"]}}, {"job_id": "100003009052343", "location_code": "hk", "company": "Bally GC Retail Co. Limited", "job_title": "Temporary Merchandising Assistant (1-year Renewal Contract)", "description": "Job Duties\n\nReport to Merchandising Director, Great China, to handle stock allocation and rebalancing work for HK market (RTL and OLT)\nCoordinate with Retail team, VM team and Logistic team for actions follow up\nExecute HK Promotion activities and follow up\nPrepare HK Merchandising Analysis and Reporting\nProvide on-site follow up on product knowledge coaching after seasonal training\nCollect merchandise feedback and monitor competitors activities\nPerform other ad-hoc duties as assigned by manager\n\n\u00a0Requirement\n\nTertiary education in Business Management, Fashion Merchandising, or related discipline\nAt least 1 year relevant working experience in merchandising\nGood interpersonal skill, detail-oriented, willing to learn and able to work under pressure.\nGood command of spoken and written English, Cantonese and Mandarin\nProficient in MS Office, Excel (pivot table, vlookup, etc.) and PowerPoint\n\nInterested parties please send your resume with current and expected salary and date of availability to Human Resources Department by clicking \"APPLY NOW\".\n\n**Data collected will be used for recruitment purpose only.**\n\n\n\n", "employment_types": ["Temporary", "Contract"], "selling_points": ["Fashion Merchandising experience", "Stock allocation and rebalancing", "Tertiary education"], "locations": ["Causeway Bay"], "categories": ["Merchandising & Purchasing", "Footwear", "Handbag", "Others"], "post_time": "2022-01-17T02:48:38Z", "salary": {"currency": null, "max": null, "min": null, "period": "monthly", "term": null}, "salary_visible": false, "title_keywords": ["merchandising assistant"], "responsibilities": ["reporting", "vm team", "stock allocation", "analysis", "merchandising", "coordinate with", "monitor", "ad-hoc duties", "report"], "requirements": {"degrees": [], "majors": [], "languages": ["cantonese", "english", "mandarin"], "language_level": ["good command"], "hard_skills": ["business management", "excel", "pivot table", "powerpoint", "vlookup", "ms office"], "soft_skills": ["detail-oriented", "work under pressure", "willing to learn", "interpersonal skill"], "languages_combined": [{"language": "cantonese", "language_level": ["good command"]}, {"language": "english", "language_level": ["good command"]}, {"language": "mandarin", "language_level": ["good command"]}]}, "experience_required": {"duration": ["at least 1 year"], "field": ["merchandising", "relevant working experience"]}}, {"job_id": "100003009051253", "location_code": "hk", "company": "Chantal Supplies Limited", "job_title": "SENIOR MERCHANDISER / MERCHANDISER (HANDBAG PRODUCTION)", "description": "\u00a0REQUIREMENTS:\n\n\u00a0\u00a0\u00a0\u00a0\u00a0\u00a0\u00a0\u00a0 At least 5 years of solid experience in\u00a0leather/ nylon handbags & small leather goods.\n\u00a0\u00a0\u00a0\u00a0\u00a0\u00a0\u00a0\u00a0 Working experience in companies with own factory is preferable.\n\u00a0\u00a0\u00a0\u00a0\u00a0\u00a0\u00a0\u00a0 Detail-minded, flexible and self-initiative.\n\u00a0\u00a0\u00a0\u00a0\u00a0\u00a0\u00a0\u00a0 Proven proficiency of written & spoken English and Mandarin.\n\u00a0\u00a0\u00a0\u00a0\u00a0\u00a0\u00a0\u00a0 Proficiency in MS Office applications including Word, Excel\u00a0\n\u00a0\u00a0\u00a0\u00a0\u00a0\u00a0\u00a0\u00a0 Mature and able to work\u00a0independently\u00a0with our major clients and reporting directly to the team leader.\n\u00a0\u00a0\u00a0\u00a0\u00a0\u00a0\u00a0\u00a0 Candidates with less experience will be considered as Merchandiser.\n\nDUTIES:\n\n\u00a0\u00a0\u00a0\u00a0\u00a0\u00a0\u00a0\u00a0 Follow-up and monitor orders, seeking a smooth production plan, supervising purchases, schedules, and quality.\n\u00a0\u00a0\u00a0\u00a0\u00a0\u00a0\u00a0\u00a0 Liaison duties with our China team and occasional travel is required (circumstances permission).\n\nBENEFITS:\n\n\u00a0\u00a0\u00a0\u00a0\u00a0\u00a0\u00a0\u00a0 Five-day work week\n\u00a0\u00a0\u00a0\u00a0\u00a0\u00a0\u00a0\u00a0 Thirteen months\u2019 salary\n\u00a0\u00a0\u00a0\u00a0\u00a0\u00a0\u00a0\u00a0 Medical insurance\n\u00a0\u00a0\u00a0\u00a0\u00a0\u00a0\u00a0\u00a0 Discretionary annual bonus\n\nInterested applicants please send your resume by clicking apply now.", "employment_types": ["Full Time", "Permanent"], "selling_points": [], "locations": ["Causeway Bay"], "categories": ["Merchandising & Purchasing", "Handbag", "Procurement / Purchasing / Sourcing"], "post_time": "2022-01-15T06:21:39Z", "salary": {"currency": null, "max": null, "min": null, "period": "monthly", "term": null}, "salary_visible": false, "title_keywords": ["merchandiser", "senior merchandiser"], "responsibilities": ["supervising", "schedules", "quality", "monitor", "plan"], "requirements": {"degrees": [], "majors": [], "languages": ["english", "mandarin"], "language_level": ["proficiency"], "hard_skills": ["small", "excel", "word", "ms office"], "soft_skills": ["detail-minded", "flexible", "work independently", "mature", "self-initiative"], "languages_combined": [{"language": "english", "language_level": ["proficiency"]}, {"language": "mandarin", "language_level": ["proficiency"]}]}, "experience_required": {"duration": ["at least 5 years"], "field": []}}, {"job_id": "100003009048493", "location_code": "hk", "company": "Cato Overseas Limited", "job_title": "Merchandiser (Ladies Handbag)", "description": "Responsibilities :\n\nAssist in managing all aspects of products being sourced and the actual production of those products to insure best pricing, quality, design, construction and timeliness;\nCoordinate with factories to ensure on-time delivery;\nStay in daily contact with factories to manage work-in-progress report in real time;\nNegotiate with manufacturers when needed;\nCommunicate production status to superior/US counterparts in a timely manner;\nProvide analytical reports and maintain data up-to-date;\nRequirements :\n\nCollege graduate or equivalent;\nA minimum of 4 years\u2019 merchandising experience;\nGood product knowledge of ladies handbags made from PU and fabric materials;\nHands on experience in handbags production management;\nExperience in handling\u00a0other fashion accessories such as belts will be an added advantage;\nStrong organizational skills and attention to details;\nGood written & spoken English, Cantonese & Mandarin", "employment_types": ["Full Time", "Permanent"], "selling_points": [], "locations": ["Ngau Tau Kok"], "categories": ["Merchandising & Purchasing", "Handbag"], "post_time": "2022-01-14T06:52:28Z", "salary": {"currency": null, "max": null, "min": null, "period": "monthly", "term": null}, "salary_visible": false, "title_keywords": ["merchandiser"], "responsibilities": ["quality", "coordinate with", "design", "a timely manner", "reports", "contact", "maintain data", "report"], "requirements": {"degrees": [], "majors": [], "languages": ["cantonese", "english", "mandarin"], "language_level": ["good"], "hard_skills": [], "soft_skills": ["organizational skills", "hands on", "attention to details"], "languages_combined": [{"language": "cantonese", "language_level": ["good"]}, {"language": "english", "language_level": ["good"]}, {"language": "mandarin", "language_level": ["good"]}]}, "experience_required": {"duration": ["minimum of 4 years"], "field": ["management", "merchandising"]}}, {"job_id": "100003009054610", "location_code": "hk", "company": "DFS Hong Kong Limited", "job_title": "Assistant Planning Manager, Watches & Jewellry", "description": "We are seeking a self-motivated and meticulous Assistant Planning Manager to join our well-established team. With guidance from the Planning Manager, you will work on stock forecast, ordering and allocation for one category of product. You will closely monitor the inventory flow to achieve the worldwide gross margin plans, and to maximize sales and profitability in your assigned location.\n\nResponsibilities\n\nSeasonal Sales Planning\n\n\nDevelop worldwide seasonal sales, margin and mix plans for one segment of a category based on strategic direction and financial guidelines\nDevelop location-specific sales ratify with region plans; tie to location profiles and assist plans\nDevelop monthly financial plans at department level for one segment of a category\n\nOrder Placement and Replenishment\n\n\nProvide analysis necessary for the development of the monthly Open-to-Buy based on planning variances to the financial plans\nRecommend quantities to place for fashion orders based on stock projection\nReview and update replenishment forecasts as required based on stock projection\nMonitor Open-To-Buy weekly and make recommendations as appropriate\nCommunicate and follow up with vendors to support merchandise flow requirements\n\nInventory Management\n\n\nSupply the SKU Team with appropriate initialization information to activate distribution\nWork with Distributors to ensure on-order needs matches with location sales needs\nIdentify fast and slow sellers and develop action plan with team\nProvide monthly analysis to report and implement discontinued SKU action plans\nDevelop and recommend markdown strategy and manage markdown budgets\n\nKey Requirements\n\n\nBachelor\u2019s Degree or above\n1-2 years\u2019 experience in merchandising and/or planning with a major retailer\nExperience in the luxury market and international business preferred\nAble to create and maintain sophisticated Excel spreadsheets\nNegotiation experience required\nStrong interpersonal skills and be able to deliver high-level presentations\nProficient in both written and spoken English", "employment_types": ["Full Time", "Permanent"], "selling_points": ["World's Leading Luxury Travel Retailer", "Work Life Balance, Five-day Work Week", "International & Dynamic Working Environment"], "locations": ["Quarry Bay"], "categories": ["Accounting", "Others", "Merchandising & Purchasing", "Handbag", "Watch"], "post_time": "2022-01-17T10:14:11Z", "salary": {"currency": null, "max": null, "min": null, "period": "monthly", "term": null}, "salary_visible": false, "title_keywords": ["manager", "assistant"], "responsibilities": ["make recommendations", "budgets", "open-to-buy", "markdown strategy", "guidelines", "analysis", "review", "monitor", "replenishment", "develop", "inventory management", "report", "plan", "plans", "financial plans", "planning"], "requirements": {"degrees": ["degree or above", "bachelor"], "majors": [], "languages": ["english"], "language_level": ["proficient"], "hard_skills": ["excel", "presentations"], "soft_skills": ["sophisticated", "interpersonal skills", "negotiation"], "languages_combined": [{"language": "english", "language_level": ["proficient"]}]}, "experience_required": {"duration": ["1-2 years"], "field": ["business", "merchandising", "planning"]}}, {"job_id": "100003009054967", "location_code": "hk", "company": "GS Consultants Limited", "job_title": "Assistant Merchandise Manager / Senior Merchandiser (Max: 25K)", "description": "An international well-known brand is hiring a Assistant Merchandising Manager / Senior Merchandiser join their company.\n\n\n\n\u00a0Responsibilities\u00a0\n\nFormulate, review and develop budget, sales target, promotion and assortment plans\nAnalyze date for budget and vendor meetings, recommend action plans to management.\nReview and analyze exception reports, formulate action plan including IMU management and best sellers management.\nBuild and maintain strong rapport and relationship with vendor. Work on and monitor sales promotions, trainings and visual presentation standard & develop promotional collateral for in-store marketing.\nCompile different computer techniques as necessary such as Excel, Power Point for reporting, strategy books and other presentation.\n\nJob Requirements\n\nDegree or above in Business, marketing or related discipline\nMerchandising / planning experiences preferred\nExcellent problem solving, interpersonal, communication and negotiation skill\nExcellent command of both written and spoken English and Chinese\nFresh Gradute is also welcomed\u00a0\n\nInterested parties, please send your CV to Cyrus.chan(a)gsc-hk.com with\u00a0current & expected package.\n\nAll information collected will be used by recruitment purpose only.", "employment_types": ["Full Time", "Permanent"], "selling_points": ["Merchandising / Planning experience preferred", "MNC Culture", "Work from Home Policy"], "locations": ["Not Specified"], "categories": ["Marketing / Public Relations", "Marketing - General / Support", "Merchandising & Purchasing", "Handbag", "Others"], "post_time": "2022-01-17T16:10:26Z", "salary": {"currency": null, "max": null, "min": null, "period": "monthly", "term": null}, "salary_visible": false, "title_keywords": ["assistant merchandise", "manager", "senior merchandiser"], "responsibilities": ["reporting", "management", "sales target", "review", "budget", "monitor", "develop", "maintain", "reports", "plan", "visual presentation", "plans"], "requirements": {"degrees": ["degree or above"], "majors": ["business", "marketing"], "languages": ["english", "chinese"], "language_level": ["excellent"], "hard_skills": ["problem solving"], "soft_skills": ["problem solving", "communication", "interpersonal", "negotiation skill"], "languages_combined": [{"language": "english", "language_level": ["excellent"]}, {"language": "chinese", "language_level": ["excellent"]}]}, "experience_required": {"duration": [], "field": ["merchandising", "planning"]}}, {"job_id": "100003009050142", "location_code": "hk", "company": "Lane Crawford (Hong Kong) Limited", "job_title": "Merchandise Coordinator - Fashion (Fresh graduate is also welcomed)", "description": "Job Responsibilities:\nTo manage all aspects of the buying process for the designated portfolio\nTo check all invoices thoroughly, maintain\u00a0accurate data entry in PO system\nTo record merchandise details and complete product information in timely manner\nTo prepare buying reports for analysis, follow up orders and monitor stock levels\nTo communicate\u00a0and work regularly with vendors, warehouse, store operations, logistics and sales\nTo provide administrative support\u00a0to buying team\n\nJob Requirements:\n\nStrong Passion in Fashion\u00a0\nDegree in Textile/Fashion Design or related discipline\nSome relevant experience, preferably in the luxury Lifestyle industry\nStrong analytical, negotiation and communication skills\nProactive, attentive to details and able to follow tight timeline\nExcellent command of written & spoken English & Chinese\nImmediate availability preferred\n\nAt Lane Crawford we support our employees with a range of benefits reflecting the importance we place\u00a0on\u00a0the well being of our staff. In addition to a competitive salary, discretionary bonus, annual leave, provident fund, medical and dental coverage and staff purchase privileges,\u00a0 we provide shuttle buses to the Company Head Office, various social recreation activities, Staff Assistance Programme, best in-class training and development and regional work opportunities for the right candidate.\n\nAll information provided will be treated in strict confidence and used for recruitment purposes only", "employment_types": ["Permanent"], "selling_points": ["To manage all aspects of the buying process", "To check all invoices thoroughly", "To prepare buying reports for analysis"], "locations": ["Aberdeen"], "categories": ["Merchandising & Purchasing", "Footwear", "Handbag", "Furniture"], "post_time": "2022-01-14T09:51:41Z", "salary": {"currency": null, "max": null, "min": null, "period": null, "term": null}, "salary_visible": false, "title_keywords": ["coordinator"], "responsibilities": ["follow up orders", "invoices", "data entry", "operations", "analysis", "monitor", "maintain", "reports", "logistics", "provide administrative support"], "requirements": {"degrees": ["degree"], "majors": ["design"], "languages": ["english", "chinese"], "language_level": ["excellent"], "hard_skills": [], "soft_skills": ["communication skills", "negotiation", "attentive to details", "passion in", "proactive"], "languages_combined": [{"language": "english", "language_level": ["excellent"]}, {"language": "chinese", "language_level": ["excellent"]}]}, "experience_required": {"duration": [], "field": ["relevant experience"]}}, {"job_id": "100003009054211", "location_code": "hk", "company": "Eternity Consultants (HK) Ltd", "job_title": "Merchandising Clerk  / Assistant Merchandiser - 5 days works - (Fresh graduate)", "description": "Buying office\n\nRequirements:\n\nF.5 or above\n1--2 yrs exp in merchandising in Trading\nFollow up order, sampling\nContact with laboratory\nCommunicate with vendor, overseas buyer\nProduct development\n\n\u00a0Many positions are not been posted in media.\u00a0 If you are looking for job in merchandising field, we are welcome you send your resume to us direct.\n\n*Interested parties, please send full resume with current & expected salary & date available in MS WORD FORMAT ONLY to our email address\u00a0or fax to 3527 0634*\n\nFor more jobs, please visit our website: www.hketernity.com\n\n(Personal data submitted are for recruitment purpose only.)\n", "employment_types": ["Full Time", "Permanent"], "selling_points": ["F.5 or above. 0-2 years exp in merchandising in", "contact with vendor", "Follow up order, sampling. Contact w/ buyer"], "locations": ["Not Specified"], "categories": ["Merchandising & Purchasing", "Woven / Knit", "Handbag", "Sundries"], "post_time": "2022-01-17T08:49:27Z", "salary": {"currency": null, "max": null, "min": null, "period": "monthly", "term": null}, "salary_visible": false, "title_keywords": ["merchandising clerk", "assistant merchandiser"], "responsibilities": ["communicate with", "merchandising", "contact"], "requirements": {"degrees": [], "majors": [], "languages": [], "language_level": [], "hard_skills": ["vendor"], "soft_skills": [], "languages_combined": []}, "experience_required": {"duration": [], "field": []}}, {"job_id": "100003009037909", "location_code": "hk", "company": "Taibon Co Ltd", "job_title": "Senior Merchandiser (Gift and Premium)", "description": "JOB DUTIES\n\nResponsible for overall merchandising activities from product development to order follow up.\nManage daily communications with internal sales team & factories\nParticipate in price negotiation and cost engineering to meet client\u2019s goal.\nAssist Sales Team for orders and production follow-up\n\nTHE REQUIREMENTS\n\nUniversity degree graduated with good PC skills/English/Mandarin\nExpected to work with high efficiency and under pressure\nMature, self-motivated and\u00a0strong sense of responsibility.\nGood communication and negotiation skills in English & Mandarin\nOccasional travel to China and Oversea may be needed\n\nWe are offering highly competitive package 5 days work, medical benefit, double pay and performance bonus", "employment_types": ["Full Time"], "selling_points": ["Merchandiser", "Senior Merchandiser", "Gift and premium"], "locations": ["Lai Chi Kok"], "categories": ["Merchandising & Purchasing", "Handbag", "Sundries", "Others"], "post_time": "2022-01-11T04:13:09Z", "salary": {"currency": null, "max": null, "min": null, "period": "monthly", "term": null}, "salary_visible": false, "title_keywords": ["senior merchandiser"], "responsibilities": ["cost", "communications with", "price negotiation", "merchandising", "sales team"], "requirements": {"degrees": ["university degree"], "majors": [], "languages": ["english", "mandarin"], "language_level": ["good"], "hard_skills": ["pc skills"], "soft_skills": ["self-motivated", "under pressure", "sense of responsibility", "mature", "communication", "negotiation skills"], "languages_combined": [{"language": "english", "language_level": ["good", "good"]}, {"language": "mandarin", "language_level": ["good", "good"]}]}, "experience_required": {"duration": [], "field": []}}, {"job_id": "100003009040048", "location_code": "hk", "company": "S.O.I. (Hong Kong) Limited", "job_title": "MERCHANDISER (HANDBAG)", "description": "MERCHANDISER (HANDBAG)\n\nForm 7 above/diploma or degree holder of merchandising/marketing\nAt least 5 years work experience in fashion handbag\nHand-on-experience from sample development to final production\nGood sourcing/product knowledge in a wide range of ladies handbags, from leather, PU and canvas.\nProven leadership and managerial skills with strong interpersonal and communication ability to lead a merchandising team.\nLead the merchandising team members from sample development to final production\nCan work with customers/suppliers independently and hand-on-experience\u00a0to team members for order follow\n\nCo-ordinate and willing to share with team members\nStrong capabilities to negotiate prices with factories and vendors\nProvide business information to the management periodically\nResponsible, independent, aggressive, self-motivated, team work, problem solver and can work under pressure\nBusiness trip to China is necessary\nGood command of English and Chinese, fluent Mandarin\n\nWe offer competitive remuneration package including 5 day work a week, Banking holiday, medical insurance and double-pay.\n\nPlease send your curriculum vitae with photo, current and expected salary to Ms. Emily Choi by email to echoi@soi .com.hk.", "employment_types": ["Full Time"], "selling_points": [], "locations": ["Kwun Tong"], "categories": ["Merchandising & Purchasing", "Handbag"], "post_time": "2022-01-12T01:02:38Z", "salary": {"currency": null, "max": null, "min": null, "period": "monthly", "term": null}, "salary_visible": false, "title_keywords": ["merchandiser"], "responsibilities": ["management", "merchandising", "communication", "business trip", "work under pressure"], "requirements": {"degrees": ["diploma", "degree holder"], "majors": ["marketing"], "languages": ["english", "chinese", "mandarin"], "language_level": ["good command", "fluent"], "hard_skills": [], "soft_skills": ["self-motivated", "independently", "independent", "problem solver", "responsible", "communication", "leadership", "interpersonal", "work under pressure"], "languages_combined": [{"language": "english", "language_level": ["fluent", "good command"]}, {"language": "chinese", "language_level": ["fluent", "good command"]}, {"language": "mandarin", "language_level": ["good command"]}]}, "experience_required": {"duration": ["at least 5 years"], "field": ["development", "team"]}}, {"job_id": "100003009048705", "location_code": "hk", "company": "JAC Recruitment Hong Kong Co., Limited", "job_title": "Assistant Merchandise Manager", "description": "OVERVIEW\nOur client is looking for an Assistant Merchandising Manager to work in brand/design teams to drive projects and communication with our global customers and suppliers. The role will be reporting to a Senior Manager. We are looking for candidate who is proactive, organized and detail-minded to work with the young and dynamic teams.\n\nJOB RESPONSIBILITIES\nLiaise and communicate with customers as well as different departments including brands, suppliers and logistics providers to further grow our business\nProvide end-to end service to our customers across the areas of customer care, product development, data entry, purchasing, supply planning, production, and quality control\nManage multi-projects at the same time including project planning, calculations, products/suppliers sourcing, negotiations and benchmarking as well as artwork & sample development and tender submissions\nDaily operational activities to ensure order fulfilment through effective production & logistics planning, sales & purchase order creation, invoicing, as well as after sales services\nEnsure the key business projects and orders for your region are delivered efficiently and with high quality\n\nJOB REQUIREMENTS\nDegree holder, preferably in Business Administration, Supply Chain, Merchandising or related disciplines\n>7 years working experience in trading industry / merchandising / purchasing is preferable. Candidate will less experience will be consider as Senior Officer\nStrong sense of responsibility and ownership\nFlexible approach, able to work under pressure\u00a0\nFluent command of spoken and written English, Cantonese and Mandarin\u00a0\nExcellent command of computer literacy in Word, Excel and PowerPoint\nA good team player, pro-active, mature, outgoing, and self-motivated\nPositive, Confident and Smart\nImmediate availability is preferred\nPersonal data collected will be used for employment-related purposes only. We regret to inform that only shortlisted candidates will be notified.\n\n\n#LI-JACHK\n#countryhongkong", "employment_types": ["Full Time"], "selling_points": ["Work from Home Policy", "15 days AL, Life & Medical Insurance", "Young & Dynamic Culture"], "locations": ["Not Specified"], "categories": ["Merchandising & Purchasing", "Handbag"], "post_time": "2022-01-14T07:05:44Z", "salary": {"currency": null, "max": null, "min": null, "period": "monthly", "term": null}, "salary_visible": false, "title_keywords": ["assistant merchandise", "manager"], "responsibilities": ["liaise", "communicate with", "project planning", "data entry", "business projects", "quality", "invoicing", "purchase", "logistics", "quality control", "tender", "planning"], "requirements": {"degrees": ["degree holder"], "majors": ["related disciplines", "business administration"], "languages": ["cantonese", "english", "mandarin"], "language_level": ["fluent"], "hard_skills": ["excel", "inform", "word", "powerpoint"], "soft_skills": ["flexible", "outgoing", "good team player", "self-motivated", "confident", "sense of responsibility", "mature", "computer literacy", "pro-active", "positive", "work under pressure"], "languages_combined": [{"language": "cantonese", "language_level": ["fluent"]}, {"language": "english", "language_level": ["fluent"]}, {"language": "mandarin", "language_level": ["fluent"]}]}, "experience_required": {"duration": ["7 years"], "field": ["purchasing", "merchandising", "trading"]}}, {"job_id": "100003009049961", "location_code": "hk", "company": "P & A Consultant Limited", "job_title": "Asst. Merchandiser/Merchandiser/Sr. Merch/Asst. Merchandising Manager(Toys/Seasonal/Handbag) X10", "description": "Assistant Merchandising Manager/ Sr. Merchandiser/Merchandiser/ Assistant Merchandiser(Toys/ Sundries/ Gift & Premium/ Seasonal/ Gardening/ Plastic/ Home Decoration/ Polyresin/ Metal/ Wooden product/ Electronic Consumer/ Sport products/ Watch/ Handbag)- Urgent X10\u00a0\nSalary : 16-34K,\u00a0Location : Hung Hom/ Lai Chi Kok/ Tsuen Wan/ Kwun Tong ( 5 Days )\u00a0\u00a0\nRequirements\u00a0 :\u00a0\n\nF.5 or above,\u00a0\nAt Least 5-10 years of Merchandiser exp in Toys( Plastic/ Hard/ Wood/ Paper /Board game\u00a0) or Seasonal or Sundries, Gift and premium /\u00a0Electronic Consumer/ Sport\u00a0/ Watch\u00a0Product\nProduct development, sourcing, follow up order & sample\nWork independently\nGood command of English & Mandarin\nCandidate have less exp also will be consider as Assistant Merchandiser\u00a0\nSr. Merchandiser/Merchandiser- Seasonal/Gardening (Urgent)\u00a0\n(Lai Chi Kok) 5 days,\u00a0salary:23-28K\u00a0\nRequirements\u00a0 :\u00a0\n\nDiploma/ Degree holder,\u00a0\nAt Least 5-10 years of Merchandiser exp in Seasonal/ Gardening\u00a0\nstrong Product development/ one man bank\u00a0\nsourcing, follow up order & sample, contact client & mfg\u00a0\nWork independently\nHave Canton Fair exp\u00a0\nGood command of Cantonese, English & Mandarin\nImmediate available is preferred\nCandidates have less exp also will be consider as Merchandiser\u00a0\n\n*** Personal data will be treated with strict confidential and used for recruitment purpose only.\n\n\nP & A consultant Ltd will not charge any fees from the above-stated job-seeker, your job apply to our company means your acceptance of our terms and conditions.", "employment_types": ["Full Time"], "selling_points": [], "locations": ["Lai Chi Kok"], "categories": ["Merchandising & Purchasing", "Handbag", "Toy", "Sundries"], "post_time": "2022-01-15T03:50:45Z", "salary": {"currency": null, "max": null, "min": null, "period": "monthly", "term": null}, "salary_visible": false, "title_keywords": ["merchandiser", "merchandising", "asst. merchandiser"], "responsibilities": ["recruitment", "personal data", "merchandising", "contact"], "requirements": {"degrees": ["diploma", "degree holder"], "majors": [], "languages": ["cantonese", "english", "mandarin"], "language_level": ["good command"], "hard_skills": ["wan", "sr", "x10"], "soft_skills": ["work independently"], "languages_combined": [{"language": "cantonese", "language_level": ["good command"]}, {"language": "english", "language_level": ["good command", "good command"]}, {"language": "mandarin", "language_level": ["good command", "good command"]}]}, "experience_required": {"duration": [], "field": []}}, {"job_id": "100003009046108", "location_code": "hk", "company": "Formia Limited", "job_title": "ASSISTANT MERCHANDISING MANAGER", "description": "GENERAL DESCRIPTION:\n\nWe are looking for an Assistant Merchandising\u00a0Manager (Assistant Account Manager)\u00a0to work in our operations team driving projects and communication with our global airline customers, brand partners, suppliers as well as multifunctional organization.\n\nOur ideal candidate, who is reporting to the Senior Operations Manager, comes with a detail-oriented mindset, is well organized and demonstrates personal ownership in a proactive and solution oriented working approach. This is combined with a positive outlook, the relentless drive to learn and the openness to effectively collaborate within young and dynamic teams.\n\nIn return, we offer a professional and energetic work environment, competitive compensation programs, comprehensive benefits coverage and much more.\n\n\nESSENTIAL JOB DESCRIPTION:\n\nEffectively liaise and communicate with international airline customers as well as brands, suppliers and logistics providers to further grow our business\nProvide world-class end-to end service to our customers across the areas of customer care, product development, data entry, purchasing, supply planning, production, and quality control\nEffectively manage multifunctional projects including project planning, calculations, products/suppliers sourcing, negotiations and benchmarking as well as artwork & sample development and tender submissions\nCoordinate daily operational activities to ensure order fulfilment through effective production & logistics planning, sales & purchase order creation, invoicing, as well as after sales services\nConstantly review existing workflows and provide improvement recommendations to enhance efficiency, eliminate losses and deliver cost savings \u00a0\nEnsure the key business projects and orders for your region are delivered efficiently and with high quality\nAssist and support ad hoc projects to help the overall progression of the company\n\nJOB REQUIREMENTS:\n\nDegree holder, preferably in Business Administration, Supply Chain, Merchandising or related disciplines\n>7 years working experience in trading industry / merchandising / purchasing is preferable. Candidate will less experience will be consider as Senior Officer\nStrong sense of responsibility and ownership\nFlexible approach, able to work under pressure\u00a0\nFluent command of spoken and written English, Cantonese and Mandarin\u00a0\nExcellent command of computer literacy in Word, Excel and PowerPoint\nA good team player, pro-active, mature, outgoing, and self-motivated\nPositive, Confident and Smart\nImmediate availability is preferred\nWe offer attractive remuneration and benefits including, 5 days work per week (9am-6pm), work from home policy, 15 days annual leave, bonus, medical scheme. Interested parties please send full resume with your availability, present and expected salary, by clicking \"Apply Now\" button.\nPersonal data provided by applicants will be treated strictly in accordance with our personal data policy and for recruitment purposes only.", "employment_types": ["Full Time", "Permanent"], "selling_points": ["Merchandiser in gifts & premiums products", "5 days work week, 15 days AL", "Excellent career development"], "locations": ["Lai Chi Kok"], "categories": ["Merchandising & Purchasing", "Handbag", "Sundries", "Others"], "post_time": "2022-01-13T09:38:30Z", "salary": {"currency": null, "max": null, "min": null, "period": "monthly", "term": null}, "salary_visible": false, "title_keywords": ["merchandising manager", "assistant"], "responsibilities": [], "requirements": {"degrees": [], "majors": [], "languages": [], "language_level": [], "hard_skills": [], "soft_skills": [], "languages_combined": []}, "experience_required": {"duration": [], "field": []}}, {"job_id": "100003009048432", "location_code": "hk", "company": "Hillman Ross", "job_title": "Sourcing Manager (Luggage and bags)", "description": "Our client is a European company and they are looking for a Sourcing Manager to take care of luggage and bags category. This person will be an individual contributor, reporting to the Category Manager.\n\nWe are now seeking for Sourcing Manager (Luggage and bags)\n\nRESPONSIBILITIES\n\nWell organization skills of dealing with complex product categories, manage high sku and multi-countries production base.\nDevelop product and vendor strategies to drive for continue business growth.\nWork with the Sourcing Managers to evaluate the performance of factories and assess the business risk that support clients' business needs.\nSupervise and guide a team of merchandisers and coordinate with cross functional teams to achieve excellent KPI to meet client's expectation.\nStrong and in-depth negotiation skills to drive cost saving and costing margin for clients' continue business growth.\nFull ownership of the whole supply chain from factory sourcing, development till shipment with in-depth technical knowledge, proactive on problem precaution & strong decision maker.\nManage the team to ensure they are up to the company standard\nMotivate the team by sharing knowledge and expertise, ensuring attention to detail and seeking continuous improvements\nDevelop a close relationship with existing suppliers and develop new suppliers through personal connections, trade fairs and sourcing trips\nProduct, payment and business term negotiations with suppliers.\n\nTo succeed in this key role, you will have at least 10 years experience in sourcing with at least 6 years in managerial capacity.\n\nQUALIFICATIONS:\n\nTertiary educated\nSelf-motivated and have strong sense of responsibility.\nStrong people and process management skills\nStrong analytical and interpersonal skills\nIndependent and excellent time management in meeting deadline.\nStrong communication skills and fluent in English, Mandarin and Cantonese\nExperience in handling bags is a Must\nExperience working in European market is a MUST\n\nAPPLY FOR THIS JOB\n\nInterested candidate please CLICK apply button to apply online or send your resume in MS word format to Hillman Ross Recruitment Solution Professional\n\nPlease note that only shortlisted candidate will be notified. All information will be treated in strict confidence and solely used for recruitment purposes.", "employment_types": ["Full Time", "Permanent"], "selling_points": ["European Company", "Experience in handling bags is a Must", "Experience working in European market is a MUST"], "locations": ["Not Specified"], "categories": ["Merchandising & Purchasing", "Handbag", "Others", "Procurement / Purchasing / Sourcing"], "post_time": "2022-01-14T06:34:00Z", "salary": {"currency": null, "max": null, "min": null, "period": "monthly", "term": null}, "salary_visible": false, "title_keywords": ["sourcing manager"], "responsibilities": ["product categories", "reporting", "cost", "continuous improvements", "management", "coordinate with", "teams", "develop", "evaluate", "communication", "payment", "support clients", "recruitment"], "requirements": {"degrees": [], "majors": [], "languages": ["cantonese", "english", "mandarin"], "language_level": ["fluent"], "hard_skills": ["vendor", "ms word"], "soft_skills": ["communication skills", "self-motivated", "confidence", "independent", "sense of responsibility", "time management", "negotiation skills", "interpersonal skills", "attention to detail", "organization skills", "proactive"], "languages_combined": [{"language": "cantonese", "language_level": ["fluent"]}, {"language": "english", "language_level": ["fluent"]}, {"language": "mandarin", "language_level": ["fluent"]}]}, "experience_required": {"duration": ["at least 10 years", "at least 6 years"], "field": ["managerial"]}}, {"job_id": "100003009049787", "location_code": "hk", "company": "Eco Ring Hong Kong Limited", "job_title": "Full-time Appraiser (\u5168\u8077\u9451\u5b9a\u5e2b)", "description": "Eco Ring Hong Kong Limited is employing Full-Time Appraiser for business expansion. We provide on the job training and great promotion opportunity. We welcome all candidates who are interested in luxury brands.\n\n\u00a0\u00a0Job Duties:\n\nTo explain the purchasing process and provide the quotation to the customer\nOn the job training for the appraising of brand items\nTo handle daily work, like data entry.\n\nRequirements:\n\nMinimum Level 2 in 5 New Senior Secondary School Subjects in HKDSE or F.7 standard or above, no working experience is required\nNative Cantonese and Good Command of written and spoken English\nBasic computer skills\nInterested in brand products.\nGood communication skills and willing to learn\n\nBenefit:\n\n8-18 days annual leave\nDouble pay\nStaff discount\nDental insurance\nMedical insurance\nBody check\n8-10 Rest Days per month\nTransport allowance\nOver time allowance\n\nGreat promotion opportunities, with satisfactory performance, may get promoted to shop manager.\n\n\u70ba\u914d\u5408\u696d\u52d9\u767c\u5c55\uff0cEco Ring Hong Kong Limited\u73fe\u8aa0\u8058\u9451\u5b9a\u5e2b\u591a\u540d\uff0c\u672c\u516c\u53f8\u63d0\u4f9b\u5728\u8077\u57f9\u8a13\u53ca\u826f\u597d\u6649\u5347\u6a5f\u6703\uff0c\u6b61\u8fce\u5c0d\u540d\u724c\u6709\u8208\u8da3\u7684\u4eba\u58eb\u61c9\u5fb5\u3002\n\n\u8077\u8cac\uff1a\n\n\u5411\u5ba2\u4eba\u8b1b\u89e3\u8ca8\u54c1\u6536\u8cfc\u7684\u7a0b\u5e8f\u53ca\u63d0\u4f9b\u5831\u50f9\n\u65bc\u5de5\u4f5c\u4e2d\u5b78\u7fd2\u9451\u5b9a\u540d\u724c\u8ca8\u54c1\u7684\u6280\u5de7\n\u8ca0\u8cac\u65e5\u5e38\u5e97\u52d9\u5de5\u4f5c\uff0c\u5982\u8f38\u5165\u8ca8\u54c1\u8cc7\u6599\n\n\u8981\u6c42\uff1a\n\n\u4e2d\u5b78\u7a0b\u5ea6\uff0c\u7121\u9700\u7d93\u9a57\n\u826f\u597d\u7cb5\u8a9e\u53ca\u82f1\u8a9e\n\u57fa\u672c\u96fb\u8166\u64cd\u4f5c\u6280\u5de7\n\u5c0d\u540d\u724c\u8ca8\u54c1\u6709\u8208\u8da3\n\u5584\u65bc\u6e9d\u901a\u53ca\u4e3b\u52d5\n\n\u798f\u5229\uff1a\n\n8-18\u5929\u5e74\u5047\n\u96d9\u7ce7\n\u54e1\u5de5\u8cfc\u7269\u512a\u60e0\n\u7259\u79d1\u798f\u5229\n\u91ab\u7642\u4fdd\u96aa\n\u8eab\u9ad4\u6aa2\u67e5\n\u6bcf\u67088-10\u5929\u4f11\u5047\n\u4ea4\u901a\u6d25\u8cbc\n\u8d85\u6642\u6d25\u8cbc\n\n\u826f\u597d\u6649\u5347\u6a5f\u6703\uff0c\u8868\u73fe\u826f\u597d\u8005\uff0c\u6709\u6a5f\u6703\u6649\u5347\u81f3\u5e97\u9577\u3002\u00a0", "employment_types": ["Full Time"], "selling_points": ["No working experience required", "Double Pay", "OT allowance"], "locations": ["Others"], "categories": ["Merchandising & Purchasing", "Handbag", "Sales, CS & Business Devpt", "Others", "Direct Sales"], "post_time": "2022-01-14T09:14:19Z", "salary": {"currency": "HKD", "max": 19999, "min": 17000, "period": "monthly", "term": null}, "salary_visible": true, "title_keywords": ["appraiser"], "responsibilities": [], "requirements": {"degrees": [], "majors": [], "languages": [], "language_level": [], "hard_skills": [], "soft_skills": [], "languages_combined": []}, "experience_required": {"duration": [], "field": []}}, {"job_id": "100003009039368", "location_code": "hk", "company": "Page Personnel", "job_title": "Senior Merchandiser - Bags and Accessories", "description": "Excellent opportunity for merchandising experts to work for a leading trading company.\n\nClient Details\n\nOur client is a leading trading company with over hundreds of customers in the globe. With significant business expansion in their local business, they are currently looking to recruit a Senior Merchandiser to support future operations.\n\nDescription\n\nManage end-to-end merchandising project including sourcing, product development, cost control, schedule monitoring, on time delivery and after-sales handling\nMaintain good relationship with suppliers, service providers and customers to ensure smooth operation process and generate business growth\nInitiate operation improvement to optimize business performance, cost savings, working efficiency\nAssist in ad-hoc duties as per assigned\n\nProfile\n\n5 years of experience in merchandising/procurement experience in Bags/Accessories\nStrong analytical skills with numerical sense\nOrganized and detail-oriented individual\nExcellent command in both English and Chinese\n\nJob Offer\n\nMNC Culture\nMedical covered\nCompetitive pay", "employment_types": ["Full Time", "Permanent"], "selling_points": ["Bags and Accessories", "Competitive package", "Flexible working arrangement"], "locations": ["Not Specified"], "categories": ["Merchandising & Purchasing", "Fabrics", "Handbag", "Sundries"], "post_time": "2022-01-11T09:31:31Z", "salary": {"currency": null, "max": null, "min": null, "period": "monthly", "term": null}, "salary_visible": false, "title_keywords": ["senior merchandiser"], "responsibilities": ["cost", "operations", "monitoring", "merchandising", "maintain good relationship", "schedule", "cost control", "ad-hoc duties"], "requirements": {"degrees": [], "majors": [], "languages": ["english", "chinese"], "language_level": ["excellent"], "hard_skills": ["analytical skills"], "soft_skills": ["organized", "detail-oriented", "analytical skills", "smooth", "ad-hoc duties"], "languages_combined": [{"language": "english", "language_level": ["excellent"]}, {"language": "chinese", "language_level": ["excellent"]}]}, "experience_required": {"duration": ["5 years"], "field": ["merchandising", "procurement"]}}, {"job_id": "100003009043941", "location_code": "hk", "company": "International Operations & Services Company (HK) Limited", "job_title": "Category Management Planner, Fashion & WJA APAC", "description": "As a member of our Global Category Management community you will be responsible to\u00a0support\u00a0Brand Management and Promotion processes for the Fashion and WJA Category in Asia\u00a0and acting as the interface to the regional category management activities.\n\nThe position is based in Hong Kong\n\nKey Accountabilities\n\nAssist the Category Manager in preparing and implementing the Commercial Plan for the\u00a0Category\nEnsure implementation of the novelties and promotions program to deliver sales and profit targets\nManaging the\u00a0assortments at global and local level.\nMaintain a strong relationship with local operational teams and external suppliers to drive sales and performance\nAssist with allocating space for brands in new shop developments and layouts in partnership with Global Shop Development\nReview the monthly report on\u00a0assortment performance by vendor, brand and SKU (top brands 80/20), sales and margin\nManage implementation of agreed Promotions with the local operations\nCompile and update information packs for pricing policies, co-ordinate the validation of pricing policies and track PAX profiles for all airports.\nAssist the central team with research about product and market trends\nExperience and Skills\n\nDegree holder in business or related disciplines\n3 - 4 years\u2019 experience within travel retail or fast-paced high volume retail businesses\nGood commercial acumen - ability to analyze business performance and identify new opportunities for sales and margin growth\nExcellent analytical skills - good attention to detail with problem solving skills\nGood interpersonal skills - able to communicate with multiple stakeholders at different levels and influence decision making for the category\nSelf-driven and reliable - able to work independently\nStrong PC skills - Advanced knowledge of Excel and other Microsoft programs. SAP knowledge would be helpful\u00a0 \u00a0 \u00a0 \u00a0 \u00a0 \u00a0 \u00a0 \u00a0 \u00a0\nInterested parties, please send full CV with availability, current and expected salary to us by clicking below button \u201cApply Now\u201d.\n\n\nWe are an equal opportunity employer and welcome applications from all qualified candidates. Personal data collected will be treated in strict confidence and handled confidentially by authorized personnel for recruitment-related purposes only within Dufry Group of companies.\n\u00a0 \u00a0 \u00a0 \u00a0 \u00a0 \u00a0 \u00a0", "employment_types": ["Full Time", "Permanent"], "selling_points": [], "locations": ["Hung Hom"], "categories": ["Merchandising & Purchasing", "Handbag", "Watch", "Procurement / Purchasing / Sourcing"], "post_time": "2022-01-13T02:32:40Z", "salary": {"currency": null, "max": null, "min": null, "period": "monthly", "term": null}, "salary_visible": false, "title_keywords": [], "responsibilities": ["communicate with", "management", "operations", "policies", "review", "teams", "implementation", "maintain", "plan", "monthly report", "drive sales"], "requirements": {"degrees": ["degree holder"], "majors": ["related disciplines", "business"], "languages": [], "language_level": [], "hard_skills": ["excel", "airports", "sap", "vendor", "analytical skills", "problem solving skills", "pc skills", "acumen"], "soft_skills": ["work independently", "advanced", "responsible", "analytical skills", "ability to analyze", "interpersonal skills", "attention to detail", "problem solving skills", "reliable", "driven", "decision making"], "languages_combined": []}, "experience_required": {"duration": ["3 - 4 years"], "field": ["retail"]}}, {"job_id": "100003009039654", "location_code": "hk", "company": "Magic Search Limited", "job_title": "Men's Buying Manager (Fashion Group)", "description": "Our client is a renowned fashion brand and and their shops locate in prestigious business area. To cope with their business expansion, they are looking for a\u00a0Men's Buying Manager to join the team.\n\nThe Job :\n\nBuild sales projections from a business perspective for Retail and Merchandising\nDevelop OTB budgets to insure Countries\u2019 budgets and buy plans are executed in accordance to company strategies\nPrepare analysis with insights, regular business reviews to flag risks and opportunities\nSupervise and support planners to ensure merchandise appear in the right store at the right time and in the right quantities and assortment, involving planning stock levels and monitoring sales performance\nSet up OTB procedures for the region so that country heads and buyers are clear of objectives and actions for their buys\nPartner with Merchandising and Retail to lay out action plans for risks and opportunities identified\nBuild planning modules for core & continuative merchandise\nConsolidate weekly/monthly sales analysis for regular working with planners and buyers to understand business\nRecommend price index and gross margins (maximise ROI) for the region and for each country\nAnalyze end of season markdowns and propose markdown strategies based on inventory and sales analysis by countries, by locations to ensure cohesive flow from one season to the next\nAnalyze intended orders and determine whether the orders are coherent to the business objectives\nAnticipate shipments, receipting capacity, display, BOH of each country to minimize congestions, maximize sales opportunities, sell through, and margins by working closely with logistics\nPerform effective inventory control, inventory management best practices\nAd hoc projects as assigned\n\nThe Candidate:\n\nBachelor\u2019s degree with a minimum of 5 - 8 years merchandising/ buying experience in related business or brand\nAn accomplished individual, able to demonstrate excellent people management skills\nMust have fashion or premium product background\nBe a strong communicator, with the gravitas to report to the top level within the business\nDemonstrate proven results in driving sales\nStrong leadership skills with the ability to motivate and develop a team\nExcellent command of both written and spoken English & Mandarin\nImmediate available is preferred\n\n\nAll information provided will be treated in strict confidence and used solely for recruitment purposes. To apply, please quote current and expected salary and send your CV through \" APPLY NOW\"", "employment_types": ["Full Time", "Permanent"], "selling_points": ["Buying Manager", "OTB Planning", "Attractive salary package"], "locations": ["Not Specified"], "categories": ["Merchandising & Purchasing", "Handbag", "Textiles", "Sales, CS & Business Devpt", "Wholesale"], "post_time": "2022-01-11T10:23:25Z", "salary": {"currency": null, "max": null, "min": null, "period": "monthly", "term": null}, "salary_visible": false, "title_keywords": ["buying manager"], "responsibilities": ["inventory", "merchandising", "otb", "inventory management", "plans", "sales performance", "develop", "logistics", "report", "management", "monitoring", "procedures", "inventory control", "gross margins", "budgets", "analysis", "ad hoc projects", "recruitment", "planning"], "requirements": {"degrees": ["degree", "bachelor"], "majors": ["business"], "languages": ["english", "mandarin"], "language_level": ["excellent"], "hard_skills": ["analysis"], "soft_skills": ["confidence", "leadership skills", "coherent", "cohesive", "clear", "communicator"], "languages_combined": [{"language": "english", "language_level": ["excellent"]}, {"language": "mandarin", "language_level": ["excellent"]}]}, "experience_required": {"duration": ["minimum of 5 - 8 years"], "field": ["related", "business", "merchandising", "brand"]}}, {"job_id": "100003009034490", "location_code": "hk", "company": "Maverick Concept Limited", "job_title": "Senior Merchandising Specialist", "description": "Responsibilities:\n\nTo execute and support the overall product development from costing, sampling, production to quality assurance\n\nAnalyse market trend, sales performance, revenues and current inventory levels to forecast inventory needs and determine purchase quantities\n\nFollow-up and monitor production schedule to make sure on-time delivery\n\nAnalyse product trend, competition, pricing and propose merchandising strategies for management review\n\nPossess strong and in-depth negotiation skills to drive better cost margin, payment and business terms\n\nDevelop a close relationship with existing suppliers and develop new suppliers through personal connections and other sourcing channels\n\nCommunicate with internal functional teams to drive continuous improvement\n\nRequirements:\n\nHigher Diploma or above, preferably major in Business Administration, Supply Chain, Merchandising or related disciplines\n\n5 Years + working experience in merchandising with at least 3 years in bags & accessories\n\nStrong product knowledge on the production of bags and accessories for high-end markets\n\nGood command of spoken and written English and Chinese including Cantonese and Mandarin\n\nGood Interpersonal relations, strong supervision, communication, negotiation and problem solving skill, assertive with high integrity\nDetailed oriented, highly organized, reliable, capable of working independently and under pressure, able to meet deadlines with good time management\nWilling to travel", "employment_types": ["Full Time", "Permanent"], "selling_points": ["5 years + Merchandising Experience", "E-commerce, Bags & Accessories", "5-Day Work, Performance Bonus, Medical Insurance"], "locations": ["Kwun Tong"], "categories": ["Merchandising & Purchasing", "Handbag"], "post_time": "2022-01-10T03:34:34Z", "salary": {"currency": null, "max": null, "min": null, "period": "monthly", "term": null}, "salary_visible": false, "title_keywords": ["specialist", "merchandising"], "responsibilities": ["communicate with", "cost", "sales performance", "inventory", "quality", "monitor", "merchandising", "develop", "teams", "purchase", "payment", "schedule", "forecast", "management review", "analyse"], "requirements": {"degrees": ["higher diploma or above"], "majors": ["related disciplines", "business administration"], "languages": ["cantonese", "english", "chinese", "mandarin"], "language_level": ["good command"], "hard_skills": ["problem solving"], "soft_skills": ["organized", "independently", "detailed oriented", "negotiation", "capable", "assertive", "under pressure", "integrity", "communication", "time management", "problem solving skill", "reliable", "meet deadlines", "interpersonal"], "languages_combined": [{"language": "cantonese", "language_level": ["good command"]}, {"language": "english", "language_level": ["good command"]}, {"language": "chinese", "language_level": ["good command"]}, {"language": "mandarin", "language_level": ["good command"]}]}, "experience_required": {"duration": ["5 years +", "at least 3 years"], "field": ["merchandising"]}}, {"job_id": "100003009029949", "location_code": "hk", "company": "The Vertical Collective Limited", "job_title": "Senior Merchandiser / Merchandiser \u2013 Bags & Accessories", "description": "Job Responsibilities:\n\n\u00a0\u00a0\u00a0\u00a0\u00a0\u00a0\u00a0Responsible for the coordination of daily merchandising activities in costing, product development through mass production\n\u00a0\u00a0\u00a0\u00a0\u00a0\u00a0\u00a0Must have good technical bag knowledge as well as general sourcing experience for new products categories from qualified vendors\n\u00a0\u00a0\u00a0\u00a0\u00a0\u00a0\u00a0Communicate with the Sales and Product Development team in US on daily basis\n\u00a0\u00a0\u00a0\u00a0\u00a0\u00a0\u00a0Proactively work with the fellow merchandising team, vendors and technical team to ensure quality and timely production is delivered\n\u00a0\u00a0\u00a0\u00a0\u00a0\u00a0\u00a0Responsible for product innovation and proposing cost saving opportunities that are aligned with sourcing and vendor strategies\n\u00a0\u00a0\u00a0\u00a0\u00a0\u00a0\u00a0Identify, address and resolve any issues in different stages and provide recommendations to facilitate effective business decision making\n\u00a0\u00a0\u00a0\u00a0\u00a0\u00a0\u00a0Maintain and\u00a0update samples and production records, system data, etc.\n\u00a0\u00a0\u00a0\u00a0\u00a0\u00a0\u00a0Perform ad hoc tasks as assigned by immediate supervisor\u00a0\n\nJob Requirements:\n\n\u00a0\u00a0\u00a0\u00a0\u00a0\u00a0\u00a05 years merchandising experience in sourcing & product development\u00a0\n\u00a0\u00a0\u00a0\u00a0\u00a0\u00a0\u00a0Open minded, flexible, organised and independent\n\u00a0\u00a0\u00a0\u00a0\u00a0\u00a0\u00a0Self-motivated, hard-working and able to work under pressure\n\u00a0\u00a0\u00a0\u00a0\u00a0\u00a0\u00a0Good negotiation skills and problem solving skills\n\u00a0\u00a0\u00a0\u00a0\u00a0\u00a0\u00a0Good command of English, Cantonese and Mandarin\n\u00a0\u00a0\u00a0\u00a0\u00a0\u00a0\u00a0Proficient in MS office and Chinese word-processing", "employment_types": ["Full Time", "Permanent"], "selling_points": [], "locations": ["Southern Area"], "categories": ["Merchandising & Purchasing", "Handbag"], "post_time": "2022-01-07T06:56:05Z", "salary": {"currency": null, "max": null, "min": null, "period": "monthly", "term": null}, "salary_visible": false, "title_keywords": ["merchandiser", "senior merchandiser"], "responsibilities": ["communicate with", "cost", "quality", "merchandising", "ad hoc tasks", "system data", "maintain", "provide recommendations", "coordination"], "requirements": {"degrees": [], "majors": [], "languages": ["cantonese", "english", "chinese", "mandarin"], "language_level": ["good command", "proficient"], "hard_skills": ["problem solving skills", "chinese word-processing", "ms office"], "soft_skills": ["flexible", "self-motivated", "independent", "negotiation skills", "hard-working", "open minded", "organised", "problem solving skills", "work under pressure"], "languages_combined": [{"language": "cantonese", "language_level": ["good command"]}, {"language": "english", "language_level": ["good command"]}, {"language": "chinese", "language_level": ["proficient"]}, {"language": "mandarin", "language_level": ["good command"]}]}, "experience_required": {"duration": ["5 years"], "field": ["product development", "merchandising"]}}, {"job_id": "100003009035161", "location_code": "hk", "company": "Swire Resources Ltd", "job_title": "Product Executive", "description": "The incumbent will be responsible for formulating buy and product management strategies of the assigned brand(s), working closely with the Principal(s) and internal teams to maximize sales.\n\nResponsibilities:\n\nManage product planning and seasonal buy covering both Retail and Wholesale\nMonitor sales trend and inventory control to meet depletion target\nEnsure smooth delivery and supply of products to meet launch deadlines\nFoster close relationship with the Principal(s)\nAnalyze market trend and competitors to drive additional sales\nWork closely with Retail, Sales and Marketing teams to deliver sales and promotions\n\n\u00a0Requirements:\n\nUniversity graduate in related disciplines\n2-3 years'\u00a0experience in\u00a0buying / category management / business development experience\u00a0gained from fashion / footwear / accessories\nStrong business sense with\u00a0analytical mind\nPro-active, result-oriented, good communication skill and able to work under pressure\nProficiency in English and Chinese\nProficient in MS Word, Excel, PowerPoint and Chinese Word Processing\n\nWe offer competitive remuneration package with\u00a0a wide range of fringe benefits including\n\n5-day work week\nDiscretionary Bonus\nComprehensive Medical Coverage\nStaff Shopping Discount\nNon-contributory Retirement Benefits Scheme\nBirthday Leave\u00a0\n\nInterested parties please send resume with present and expected salary to Human Resources Department, Swire Resources Limited,\u00a012/F Kingston International Centre, 19 Wang Chiu Road Kowloon Bay, Hong Kong or by\u00a0clicking the below \"Apply Now\" button.\n\nSwire Resources Limited is Equal Opportunity Employer\n", "employment_types": ["Full Time", "Permanent"], "selling_points": ["Resp for product management, selection & pricing", "U grad, 2-3 yrs buying & product management exp", "Exp gained from fashion / footwear / accessories"], "locations": ["Kowloon Bay"], "categories": ["Merchandising & Purchasing", "Footwear", "Handbag", "Others"], "post_time": "2022-01-10T06:15:09Z", "salary": {"currency": null, "max": null, "min": null, "period": null, "term": null}, "salary_visible": false, "title_keywords": ["executive"], "responsibilities": ["teams", "inventory control", "monitor", "planning"], "requirements": {"degrees": ["university graduate"], "majors": ["related disciplines"], "languages": ["english", "chinese"], "language_level": ["proficiency", "proficient"], "hard_skills": ["excel", "chinese word processing", "powerpoint", "ms word"], "soft_skills": ["business sense", "communication skill", "analytical mind", "pro-active", "result-oriented", "work under pressure"], "languages_combined": [{"language": "english", "language_level": ["proficiency"]}, {"language": "chinese", "language_level": ["proficiency", "proficient"]}]}, "experience_required": {"duration": ["2-3 years"], "field": ["management", "business development"]}}, {"job_id": "100003009023287", "location_code": "hk", "company": "JSP Group Limited", "job_title": "Merchandiser / Sales Executive [Gift & Premium, Cosmetic Bag]", "description": "The role will be a\u00a0member of our project team who\u00a0is responsible for coordinating, optimizing and executing sourcing and sales related projects with co-effort from various departments.\u00a0 \u00a0\n\nKey responsibilities:\n\nAssist Director to handle sales and product development projects associated with the cosmetic bags product (Europe & US market);\u00a0 \u00a0\nCarry out order management activity from quotation to invoicing and record progress in CRM (Salesforce) and ERP system;\u00a0 \u00a0\nSource factory supplier via 1688 and other\u00a0e-platforms, if necessary;\u00a0 \u00a0\nLiaised with China factory and sub-contractor to ensure the production schedule and material delivery can meet the project\u00a0requirement;\u00a0 \u00a0\n\n\u00a0Requirements:\n\nMinimum 2 \u2013 3 years\u2019 experience in cosmetic bag industry, less experience will be\u00a0considered as Assistant Merchandiser;\nBasic knowledge in fabric material and manufacturing know how of bags production;\nSolid experience in sourcing factory supplier in 1688,\u00a0etc;\u00a0 \u00a0\nGood PC knowledge in using MS office applications;\u00a0\u00a0\nGood command of spoken and written English and Chinese (Cantonese and Mandarin);\nNew immigrants from Mainland are also welcome\n\nWe offer a friendly working environment near Kowloon Bay MTR with 5-day workweek,\u00a0fringe benefits and\u00a0incentive scheme. Interested candidates apply with full CV with work experience, current and expected salary.", "employment_types": ["Full Time"], "selling_points": [], "locations": ["Kowloon Bay"], "categories": ["Sales, CS & Business Devpt", "Business Development", "Merchandising & Purchasing", "Handbag", "Procurement / Purchasing / Sourcing"], "post_time": "2022-01-06T16:07:52Z", "salary": {"currency": null, "max": null, "min": null, "period": "monthly", "term": null}, "salary_visible": false, "title_keywords": ["merchandiser", "sales executive"], "responsibilities": ["invoicing", "order management", "quotation", "schedule"], "requirements": {"degrees": [], "majors": [], "languages": ["cantonese", "english", "chinese", "mandarin"], "language_level": ["good command"], "hard_skills": ["pc knowledge", "basic", "ms office"], "soft_skills": [], "languages_combined": [{"language": "cantonese", "language_level": ["good command"]}, {"language": "english", "language_level": ["good command"]}, {"language": "chinese", "language_level": ["good command"]}, {"language": "mandarin", "language_level": ["good command"]}]}, "experience_required": {"duration": ["3 years"], "field": []}}, {"job_id": "100003009041520", "location_code": "hk", "company": "Michael Kors (HK) Limited", "job_title": "Senior Planner / Associate Planning Manager", "description": "SUMMARY:\n\n\nThe objective of this position is to plan and manage inventory allocation in order to maximize sales and margin across both Full Price and Outlet channels within Hong Kong/Macao, and extend regional support to Taiwan/Australia.\u00a0\n\nJOB RESPONSIBILITIES\n\nBe responsible for allocation / replenishment / rebalancing for selected product categories within Hong Kong/Macao and support Taiwan/Australia for regional allocation\nAllocate, replenish, and rebalance inventory by store, according to\n- Seasonal flow, including seasonal launch, floor sets, markdown, and liquidation\n- Product lifecycle and markdown risk (such as core/carryover items vs. fashion newness)\n- Sales performance by store, down to the SKU level\n- Optimal inventory levels by store according to store type, sales performance and store capacity\n- Anticipate peak / slow shopping periods and holidays\n- Anticipate future product (such as reserving and rebalancing) according to store opening plan\nPrioritize key stores and understand product substitutes in limited stock situations\nPrepare inventory for new store openings\nPromotion and markdown management, update relevant system\nDevelop stock clearance plan, organize and coordinate return\nAct as key stakeholder to provide GC Merch team, the insight of HK/Macao business, from merchandising planning point of view\nHandle assortment planning including price and discount setting for Sogo Thankful event and Brand sale\nIssue TN and SO for HK, Macao and Taiwan orders.\u00a0 Coordinate with HK logistics and EU team for Australia orders\nPartner with other team members and functions as needed, for example\n- Partner with logistics to ensure timely execution of allocation / replenishment\n- Communicate with stores on store requests and needs; enforce efficient transfers / returns from stores\n- Work with buyers to understand launching schedule, product needs by store and substitutes in limited stock situations\n- Partner with marketing and VM to support special marketing requests (e.g. store events) and VM (e.g. mannequin looks)\n\u00a0SKILLS and WORK EXPERIENCE\n\nBachelor\u2019s Degree or above\nStrong record of academic and professional performance, with references\n6-8 years\u2019 inventory management experience in the retail industry (experience in APAC management is preferred)\nExtremely sensitive to number; strong data analysis and Excel skills\nEstablish and develop the inventory management team\nHonest, open, and non-hierarchical attitude\nExcellent communication and interpersonal skills\nStrong prioritization and organizational skills\nDriven to execute efficiently and accurately\nProfessional demeanor\nProactive, ambitious, flexible, and entrepreneurial; able to work in a startup environment\nComputer and systems literate\nFluent in English, good Mandarin is a plus\n\nWe offer remuneration package\u00a0commensurate with qualification and experience to the successful candidate.\u00a0 If you would like to apply for this position or find out more, please press 'Apply Now'.\n\n(Data collected will be treated as strict confidential and will be used for recruitment purpose only.)", "employment_types": ["Full Time", "Permanent"], "selling_points": ["At least 6 years\u2019 exp. inventory management", "Computer and systems literate", "Fluent in English, good Mandarin is a plus."], "locations": ["Tsim Sha Tsui"], "categories": ["Merchandising & Purchasing", "Footwear", "Handbag", "Textiles"], "post_time": "2022-01-12T03:59:40Z", "salary": {"currency": null, "max": null, "min": null, "period": "monthly", "term": null}, "salary_visible": false, "title_keywords": ["associate", "manager"], "responsibilities": ["product categories", "communicate with", "management", "sales performance", "inventory", "systems", "merchandising", "replenishment", "coordinate with", "develop", "coordinate", "inventory management", "data analysis", "communication", "logistics", "schedule", "plan", "planning"], "requirements": {"degrees": ["degree or above", "bachelor"], "majors": [], "languages": ["english", "mandarin"], "language_level": ["good", "fluent"], "hard_skills": ["vs", "excel", "analysis", "plus"], "soft_skills": ["efficient", "organizational skills", "flexible", "responsible", "timely", "prioritize", "sensitive to", "communication and interpersonal skills", "honest", "proactive", "driven"], "languages_combined": [{"language": "english", "language_level": ["fluent"]}, {"language": "mandarin", "language_level": ["good", "fluent"]}]}, "experience_required": {"duration": ["6-8 years"], "field": ["inventory management", "management", "retail industry"]}}, {"job_id": "100003009029171", "location_code": "hk", "company": "Bally GC Retail Co. Limited", "job_title": "Temporary Merchandising Assistant (1-year Renewal Contract)", "description": "Job Duties\n\nReport to Merchandising Director, Great China, to handle stock allocation and rebalancing work for HK market (RTL and OLT)\nCoordinate with Retail team, VM team and Logistic team for actions follow up\nExecute HK Promotion activities and follow up\nPrepare HK Merchandising Analysis and Reporting\nProvide on-site follow up on product knowledge coaching after seasonal training\nCollect merchandise feedback and monitor competitors activities\nPerform other ad-hoc duties as assigned by manager\n\n\u00a0Requirement\n\nTertiary education in Business Management, Fashion Merchandising, or related discipline\nAt least 1 year relevant working experience in merchandising\nGood interpersonal skill, detail-oriented, willing to learn and able to work under pressure.\nGood command of spoken and written English, Cantonese and Mandarin\nProficient in MS Office, Excel (pivot table, vlookup, etc.) and PowerPoint\n\nInterested parties please send your resume with current and expected salary and date of availability to Human Resources Department by clicking \"APPLY NOW\".\n\n**Data collected will be used for recruitment purpose only.**\n\n\n\n", "employment_types": ["Temporary", "Contract"], "selling_points": ["Fashion Merchandising experience", "Stock allocation and rebalancing", "Tertiary education"], "locations": ["Causeway Bay"], "categories": ["Merchandising & Purchasing", "Footwear", "Handbag", "Others"], "post_time": "2022-01-07T04:09:13Z", "salary": {"currency": null, "max": null, "min": null, "period": "monthly", "term": null}, "salary_visible": false, "title_keywords": ["merchandising assistant"], "responsibilities": ["reporting", "vm team", "stock allocation", "analysis", "merchandising", "coordinate with", "monitor", "ad-hoc duties", "report"], "requirements": {"degrees": [], "majors": [], "languages": ["cantonese", "english", "mandarin"], "language_level": ["good command"], "hard_skills": ["business management", "excel", "pivot table", "powerpoint", "vlookup", "ms office"], "soft_skills": ["detail-oriented", "work under pressure", "willing to learn", "interpersonal skill"], "languages_combined": [{"language": "cantonese", "language_level": ["good command"]}, {"language": "english", "language_level": ["good command"]}, {"language": "mandarin", "language_level": ["good command"]}]}, "experience_required": {"duration": ["at least 1 year"], "field": ["merchandising", "relevant working experience"]}}, {"job_id": "100003009030988", "location_code": "hk", "company": "J. Choo (Asia) Limited", "job_title": "Merchandising Assistant (12 months contract)", "description": "\u00a0Responsibilities\n\nPrepare reports but not limited to forecasts, sell-thru, re-orders and OTB sheets\nSupport the line manager in the buying process by providing detailed product analysis\nResponsible for stock replenishment and allocation\nProvide clerical support and data entry for the department\nLiaise with various parties for stock adjustment\nPerform any other duties as assigned by the manager\n\nParticular Skills/knowledge required\n\nUndergraduate / associate degree or higher diploma in any discipline\nMinimum 1 year relevant experience in retail industry\nGood personality, responsible, detail-minded, able to work under pressure\nStrong computer knowledge especially at Excel (e.g. Pivot Table, vlookup)\nGood command of spoken and written English and Chinese\nAble to work in a dynamic, multi-task and fast paced environment\n\nWe offer excellent career opportunities to the successful candidates. Interested parties please send your full resume with both current and expected salary through the below \"Apply Now\" button\n\n\u00a0(Personal data collected will be treated in strict confidence and used for recruitment purpose only)", "employment_types": ["Full Time", "Contract", "Internship"], "selling_points": ["Luxury fashion", "Five-day work week", "Merchandising"], "locations": ["Tsim Sha Tsui"], "categories": ["Merchandising & Purchasing", "Footwear", "Handbag", "Others"], "post_time": "2022-01-07T11:13:54Z", "salary": {"currency": null, "max": null, "min": null, "period": "monthly", "term": null}, "salary_visible": false, "title_keywords": ["merchandising assistant"], "responsibilities": ["provide clerical support", "any other duties", "stock replenishment", "data entry", "analysis", "otb", "liaise with", "prepare reports", "work under pressure"], "requirements": {"degrees": ["associate degree", "diploma"], "majors": [], "languages": ["english", "chinese"], "language_level": ["good command"], "hard_skills": ["excel", "analysis", "pivot table", "dynamic", "vlookup"], "soft_skills": ["detail-minded", "multi-task", "responsible", "detailed", "dynamic", "work under pressure"], "languages_combined": [{"language": "english", "language_level": ["good command"]}, {"language": "chinese", "language_level": ["good command"]}]}, "experience_required": {"duration": ["minimum 1 year"], "field": ["retail industry", "relevant experience"]}}, {"job_id": "100003009027080", "location_code": "hk", "company": "Lululemon HK Limited", "job_title": "Senior Merchandiser (Hard Goods Accessories)", "description": "\u00a0ALL candidates\u00a0MUST\u00a0complete\u00a0their application\u00a0directly\u00a0through the below link to receive updates on their application\u00a0status:\u00a0https://careers.lululemon.com/en_US/careers/JobDetail/Hong-Kong-Senior-Merchandiser-Hard-Goods-Accessories-Hong-Kong/14136\n\nWho we are\n\nlululemon is an innovative performance apparel company for yoga, running, training, and other athletic pursuits. Setting the bar in technical fabrics and functional design, we create transformational products and experiences that support people in moving, growing, connecting, and being well. We owe our success to our innovative product, emphasis on stores, commitment to our people, and the incredible connections we make in every community we're in. As a company, we focus on creating positive change to build a healthier, thriving future. In particular, that includes creating an equitable, inclusive and growth-focused environment for our people.\n\n\u00a0About this team\n\nThe lululemon Liaison Office (LLO) team is dedicated to ensuring our components are produced of the highest quality, delivered when we need them, and manufactured with partners who share our commitment to elevating the world. Not only do we manage the production of great product, we also build great relationships.\n\n\u00a0A day in the life:\n\nSupport the Merchandising Manager to manage costing, production and shipment\nTrain the vendors on lululemon costing, production and logistics policies, processes and IT systems; roll out new processes and systems to assigned vendors as needed\u00a0\nCosting \u2013 manage the critical path from tech pack handoff through to buy released\no\u00a0 \u00a0Core tasks include costing analysis and negotiation\no\u00a0\u00a0\u00a0 Analyze and validate cost breakdown and negotiate cost as needed, excellent at costing \u2013 strive for vendor\u2019s costing SOP adherence\no\u00a0\u00a0\u00a0 Understand style details and can communicate comments to vendors. Input to and action new processes in tracking and costing product\no\u00a0\u00a0\u00a0 Support the Vancouver development and sourcing teams to solve the proto/costing issues\no\u00a0\u00a0\u00a0 Update costing to system\u00a0\n\n\nProduction \u2013 handle the buy confirmation and solve the daily production issues\nAnalyze the capacity and work the best delivery with vendors during buy process\nManage production process which including lead times (T&A), PO systems (WIP), PO change, and packaging (WWMT) etc\nReview Past Due Date and Delay Reason Code report\nCommunicate delivery statuses and issues to appropriate SSC counterparts in a timely and concise manner\nSupport liability tracker validation\nWork closely with our Compliance and Quality teams in ensuring that our social compliance and quality standards are adhered to and goals are met\nArrange and attend quarterly vendors review meeting\nVisit factories for production tracking\n\u00a0Shipment - manage shipment booking and shipping process with Logistic partner and vendors\n\n\u00a0Qualifications:\n\nYour ideal background: Bachelor\u2019s degree in Textiles or related fields; 7+ years experience in a similar role within a production environment; strong knowledge of Hardgoods - Accessories\nYou are able to analyze work flow and are able to access bottlenecks; are fluent in Mandarin, Cantonese and English;\nStrong IT skills needed \u2013 you are an MS Excel guru! And you love working with a lot of Microsoft Office, and MRP and PDM softwares!\nExperience working on PLM and PO systems like Flex PLM and Tradestone.\n\n\u00a0Must haves:\n\nAcknowledges the presence of choice in every moment and takes personal responsibility for their life.\nPossesses an entrepreneurial spirit and continuously innovates to achieve great results.\nCommunicates with honesty and kindness, and creates the space for others to do the same.\nLeads with courage, knowing the possibility of greatness is bigger than the fear of failure.\nFosters connection by putting people first and building trusting relationships.\nIntegrates fun and joy as a way of being and working, aka doesn\u2019t take themselves too seriously.\n\n\u00a0NOTE: Only those applicants under consideration will be contacted. Please accept our utmost appreciation for your interest. lululemon is an Equal Employment Opportunity employer. Employment decisions are based on merit and business needs, and not on race, color, creed, age, sex, gender, sexual orientation, national origin, religion, marital status, medical condition, physical or mental disability, military service, pregnancy, childbirth and related medical conditions or any other classification protected by federal, state or provincial and local laws and ordinances. Reasonable accommodation is available for qualified individuals with disabilities, upon request. This Equal Employment Opportunity policy applies to all practices relating to recruitment and hiring, compensation, benefits, discipline, transfer, termination and all other terms and conditions of employment. While management is primarily responsible for seeing that lululemon equal employment opportunity policies are implemented, you share in the responsibility for assuring that, by your personal actions, the policies are effective.", "employment_types": ["Full Time", "Permanent"], "selling_points": ["Costing breakdown, analysis and negotiation", "Manage production process", "Work closely with Compliance and Quality teams"], "locations": ["Tin Hau"], "categories": ["Merchandising & Purchasing", "Handbag", "Others"], "post_time": "2022-01-06T09:05:34Z", "salary": {"currency": null, "max": null, "min": null, "period": "monthly", "term": null}, "salary_visible": false, "title_keywords": ["senior merchandiser"], "responsibilities": [], "requirements": {"degrees": [], "majors": [], "languages": [], "language_level": [], "hard_skills": [], "soft_skills": [], "languages_combined": []}, "experience_required": {"duration": [], "field": []}}, {"job_id": "100003009023639", "location_code": "hk", "company": "P & A Consultant Limited", "job_title": "Asst. Merchandiser/Merchandiser/Sr. Merch/Asst. Merchandising Manager(Toys/Seasonal/Handbag)", "description": "Assistant Merchandising Manager/ Sr. Merchandiser/Merchandiser/ Assistant Merchandiser(Toys/ Sundries/ Gift & Premium/ Seasonal/ Plastic/ Home Decoration/ Polyresin/ Metal/ Wooden product/ Electronic Consumer/ Sport products)- Urgent\u00a0\nSalary : 16-30K,\u00a0Location : Hung Hom/ Lai Chi Kok/ Tsuen Wan/ Kwun Tong ( 5 Days )\u00a0\u00a0\nRequirements\u00a0 :\u00a0\n\nF.5 or above,\u00a0\nAt Least 5-10 years of Merchandiser exp in Toys( Plastic/ Hard/ Wood/ Paper /Board game\u00a0) or Seasonal or Sundries, Gift and premium /\u00a0Electronic Consumer/ Sport\u00a0Product\nProduct development, sourcing, follow up order & sample\nWork independently\nGood command of English & Mandarin\nCandidate have less exp also will be consider as Assistant Merchandiser\u00a0\nSr. Merchandiser/ Merchandiser- Handbag( Urgent )\u00a0\n(Kwun Tong) 5 days,\u00a0salary:18-30K\u00a0\nRequirements\u00a0 :\u00a0\n\nDiploma/ Degree holder,\u00a0\nAt Least 3-8 years of Merchandiser exp in Handbag( PVC, Nylon, Leather )\nstrong Product development\nsourcing, follow up order & sample, contact client & mfg\u00a0\nWork independently\nGood command of Cantonese, English & Mandarin\nImmediate available is preferred\nCandidates have less exp also will be consider as Assistant Merchandiser\u00a0\n\n*** Personal data will be treated with strict confidential and used for recruitment purpose only.\n\n\nP & A consultant Ltd will not charge any fees from the above-stated job-seeker, your job apply to our company means your acceptance of our terms and conditions.", "employment_types": ["Full Time"], "selling_points": [], "locations": ["Lai Chi Kok"], "categories": ["Merchandising & Purchasing", "Handbag", "Toy", "Sundries"], "post_time": "2022-01-07T19:19:19Z", "salary": {"currency": null, "max": null, "min": null, "period": "monthly", "term": null}, "salary_visible": false, "title_keywords": ["merchandiser", "merchandising", "asst. merchandiser"], "responsibilities": ["recruitment", "personal data", "merchandising", "contact"], "requirements": {"degrees": ["diploma", "degree holder"], "majors": [], "languages": ["cantonese", "english", "mandarin"], "language_level": ["good command"], "hard_skills": ["wan", "sr"], "soft_skills": ["work independently"], "languages_combined": [{"language": "cantonese", "language_level": ["good command"]}, {"language": "english", "language_level": ["good command", "good command"]}, {"language": "mandarin", "language_level": ["good command", "good command"]}]}, "experience_required": {"duration": [], "field": []}}, {"job_id": "100003009020311", "location_code": "hk", "company": "Siu Siu Style Company Limited", "job_title": "Product Development Merchandiser - Backpack", "description": "Responsibilities\n\nAssist Design Team with product design process\nAccountable for sourcing of fabrics, accessories, trimming, hardware and manufacturers\nCoordinate design process with designers, supply chain and factories\nNegotiate pricing and production time frames with suppliers\nManage price quotations and initial price negotiations with suppliers\nArrange and schedule inspection with QCs and factories\nAssist merchandising manager to set inspection guidelines\u00a0\n\n\u00a0Requirements\n\n\n2 or more years of experience in fashion industry or backpack development\nStrong awareness of global fashion and material trends\nProactive problem solver\n\nBenefits:\n\nAttractive Salary Package\nMonthly\u00a0Attendance\u00a0Bonus\nYear-end Performance Bonus\n10-20 days Annual Leave\nPaid Sick Leave\u00a0\n5-day work week\nBirthday\u00a0Leave\nBirthday gift", "employment_types": ["Full Time", "Permanent"], "selling_points": ["Sourcing of fabrics, accessories, trimming", "Negotiate pricing & production time frames", "5-day work, Travel Allowance, Birthday Leave"], "locations": ["Lai Chi Kok"], "categories": ["Merchandising & Purchasing", "Handbag", "Others", "Procurement / Purchasing / Sourcing"], "post_time": "2022-01-04T10:31:34Z", "salary": {"currency": null, "max": null, "min": null, "period": "monthly", "term": null}, "salary_visible": false, "title_keywords": ["merchandiser", "product development"], "responsibilities": ["guidelines", "merchandising", "design", "inspection", "coordinate", "hardware", "product design", "schedule"], "requirements": {"degrees": [], "majors": [], "languages": [], "language_level": [], "hard_skills": [], "soft_skills": ["proactive", "problem solver"], "languages_combined": []}, "experience_required": {"duration": [], "field": ["development"]}}, {"job_id": "100003009019749", "location_code": "hk", "company": "PRADA Asia Pacific Ltd", "job_title": "Repair Centre Manager", "description": "The incumbent is responsible for managing the repair centre to ensure that repair work is carried out on a timely basis and in compliance with the Company\u2019s standard\n\nResponsibilities:\n\nHandle customers\u2019 enquiries, request and complaints, co-ordinate with Customer Service Manager to handle and response to customers\u2019 complaints.\nCheck and review the products returned by customers for appropriate action on repair.\nProvide feedback to the Merchandising Department on production defect and problem.\nSupport Legal Affairs Department on anti-counterfeiting activities representing the Company to verify product authenticity\nMonitor the quality of all out-sourcing repair works and provide feedback to the Retail Teams\nSupervise Repair Technicians and ensure the quality and the productivity of repair works\nLiaise with the HQ for communication on managing the repair works\nManage the inventory of all spare part to ensure timely replenishment; supervise local procumbent of spare part if needed\nWork Location: Tsuen Wan\nRequirements:\n\nAround 10 years or above experience in managing the repair works in the luxury brands\nIf not luxury brands, the dedicated experience in managing the leathergoods repair\nEssential to have an experience in managing the team especially technicians\n\u00a0Fluent in English\nWe offer attractive remuneration in commensurate with qualifications and experience.\u00a0Interested parties please send your\u00a0detailed curriculum vitae together with current and expected salary\u00a0to us.\u00a0\n\n\n\u00a0All information provided will be treated in strict confidence and used for recruitment purposes only", "employment_types": ["Full Time", "Permanent"], "selling_points": ["10 years or above experience", "Supervise Repair Technicians", "work location: Tsuen Wan"], "locations": ["Tsuen Wan Area"], "categories": ["Merchandising & Purchasing", "Handbag", "Others", "Technician"], "post_time": "2022-01-04T08:36:12Z", "salary": {"currency": null, "max": null, "min": null, "period": "monthly", "term": null}, "salary_visible": false, "title_keywords": ["centre manager"], "responsibilities": ["co-ordinate with", "inventory", "review", "merchandising", "monitor", "quality", "teams", "communication", "replenishment", "repair", "customer service", "liaise with"], "requirements": {"degrees": [], "majors": [], "languages": [], "language_level": [], "hard_skills": [], "soft_skills": [], "languages_combined": []}, "experience_required": {"duration": [], "field": []}}, {"job_id": "100003009010827", "location_code": "hk", "company": "Lonson Enterprise Limited", "job_title": "Senior Merchandiser\uff08Handbag\uff09", "description": "Job Responsibilities\n\nBuild & maintain effective\u00a0and\u00a0good business relationship with clients and factories.\nResponsible for negotiate with factories for costing,delivery date, quality etc. to meet client\u2019s requirement\nTo work closely with Design Teams,Product Development teams and Sourcing teams to meet client\u2019s requirements.\nIdentify, address and resolve any issues in different stages, in particular, to provide options and recommendations to the management to facilitate effective business decision making.\nCoordinate with internal and external stakeholders on factory audit,sample approval ect.quality and factory compliance.\nSales data, costing and delivery analysis.\nPerform ad-hoc assignments as required.\n\nJob Requirements\n\nOver 7 years working experience in merchandising and sourcing, extensive knowledge in fashion handbag and accessories items.\nSolid working experience with EU FAST FASHION retailers, preferably with Trading /Buying Office Background.\nExcellent interpersonal skills to contact directly overseas customers and suppliers\nDetail-minded, flexible, self-initiative with excellent interpersonal skills.\nNeed to be able to work under pressure, be very clear-minded to handle multi-tasks and project details.\nExcellent\u00a0communication,negotiation\u00a0and problem solving skills.\nProficiency in spoken and written English & Mandarin.\nProficiency in MS Office applications including Word, Excel\u00a0\nOccasional travel is required.\nImmediate available is preferable.\nWe offer\u00a0double pay, 5 days work and competitive remuneration package to the right candidate.Interested parties please state clearly the position you are applying and email us a full resume with expected salary.", "employment_types": ["Full Time", "Permanent"], "selling_points": ["Solid experience in fast fashion handbags", "Double Pay", "Immediate available is preferable"], "locations": ["Kowloon Bay"], "categories": ["Merchandising & Purchasing", "Handbag"], "post_time": "2022-01-01T19:40:22Z", "salary": {"currency": null, "max": null, "min": null, "period": "monthly", "term": null}, "salary_visible": false, "title_keywords": [], "responsibilities": ["maintain", "quality", "negotiate with factories"], "requirements": {"degrees": [], "majors": [], "languages": ["english", "mandarin"], "language_level": ["proficiency"], "hard_skills": ["excel", "analysis", "word", "problem solving skills", "ms office"], "soft_skills": ["detail-minded", "flexible", "negotiation", "multi-tasks", "work under pressure", "clear", "communication", "interpersonal skills", "self-initiative", "problem solving skills", "extensive", "decision making"], "languages_combined": [{"language": "english", "language_level": ["proficiency"]}, {"language": "mandarin", "language_level": ["proficiency"]}]}, "experience_required": {"duration": ["7 years"], "field": ["merchandising", "trading"]}}, {"job_id": "100003009017068", "location_code": "hk", "company": "Chantal Supplies Limited", "job_title": "SENIOR MERCHANDISER / MERCHANDISER (HANDBAG PRODUCTION)", "description": "\u00a0REQUIREMENTS:\n\n\u00a0\u00a0\u00a0\u00a0\u00a0\u00a0\u00a0\u00a0 At least 5 years of solid experience in\u00a0leather/ nylon handbags & small leather goods.\n\u00a0\u00a0\u00a0\u00a0\u00a0\u00a0\u00a0\u00a0 Working experience in companies with own factory is preferable.\n\u00a0\u00a0\u00a0\u00a0\u00a0\u00a0\u00a0\u00a0 Detail-minded, flexible and self-initiative.\n\u00a0\u00a0\u00a0\u00a0\u00a0\u00a0\u00a0\u00a0 Proven proficiency of written & spoken English and Mandarin.\n\u00a0\u00a0\u00a0\u00a0\u00a0\u00a0\u00a0\u00a0 Proficiency in MS Office applications including Word, Excel\u00a0\n\u00a0\u00a0\u00a0\u00a0\u00a0\u00a0\u00a0\u00a0 Mature and able to work\u00a0independently\u00a0with our major clients and reporting directly to the team leader.\n\u00a0\u00a0\u00a0\u00a0\u00a0\u00a0\u00a0\u00a0 Candidates with less experience will be considered as Merchandiser.\n\nDUTIES:\n\n\u00a0\u00a0\u00a0\u00a0\u00a0\u00a0\u00a0\u00a0 Follow-up and monitor orders, seeking a smooth production plan, supervising purchases, schedules, and quality.\n\u00a0\u00a0\u00a0\u00a0\u00a0\u00a0\u00a0\u00a0 Liaison duties with our China team and occasional travel is required (circumstances permission).\n\nBENEFITS:\n\n\u00a0\u00a0\u00a0\u00a0\u00a0\u00a0\u00a0\u00a0 Five-day work week\n\u00a0\u00a0\u00a0\u00a0\u00a0\u00a0\u00a0\u00a0 Thirteen months\u2019 salary\n\u00a0\u00a0\u00a0\u00a0\u00a0\u00a0\u00a0\u00a0 Medical insurance\n\u00a0\u00a0\u00a0\u00a0\u00a0\u00a0\u00a0\u00a0 Discretionary annual bonus\n\nInterested applicants please send your resume by clicking apply now.", "employment_types": ["Full Time", "Permanent"], "selling_points": [], "locations": ["Causeway Bay"], "categories": ["Merchandising & Purchasing", "Handbag", "Procurement / Purchasing / Sourcing"], "post_time": "2022-01-03T10:27:56Z", "salary": {"currency": null, "max": null, "min": null, "period": "monthly", "term": null}, "salary_visible": false, "title_keywords": ["merchandiser", "senior merchandiser"], "responsibilities": ["supervising", "schedules", "quality", "monitor", "plan"], "requirements": {"degrees": [], "majors": [], "languages": ["english", "mandarin"], "language_level": ["proficiency"], "hard_skills": ["small", "excel", "word", "ms office"], "soft_skills": ["detail-minded", "flexible", "work independently", "mature", "self-initiative"], "languages_combined": [{"language": "english", "language_level": ["proficiency"]}, {"language": "mandarin", "language_level": ["proficiency"]}]}, "experience_required": {"duration": ["at least 5 years"], "field": []}}, {"job_id": "100003009010828", "location_code": "hk", "company": "Lonson Enterprise Limited", "job_title": "Merchandiser(Handbag)", "description": "Job Responsibilities\u00a0 \u00a0 \u00a0 \u00a0 \u00a0\n\nOrder and Samples follow-up and samples approval of details and color.\nMonitor bulk production schedule and factories performance to ensure quality and on-time delivery.\nCost and delivery negotiation with factories.\nCommunicate client\u2019s requirements and order details to factories.\nMaintain the order deta accuracy and integrity of the internal ERP systems.\nHandle ad hoc tasks when required.\n\nJob Requirements:\n\nAt least 5 years\u2019 experience in trading/buying office\nGood\u00a0in both written and spoken English and Mandarin\nSelf-motivated, independent, responsible and well-organized\nHigh levels of attention to detail\nGood coordination and communication skills.\nExcellent time management skills and ability to work with tight deadlines\nOccasional travel is required\nImmediately available is preferred\nWe offer\u00a0double pay, 5 days work and competitive remuneration package to the right candidate.Interested parties please state clearly the position you are applying and email us a full resume with expected salary.", "employment_types": ["Full Time", "Permanent"], "selling_points": ["Solid experience in fast fashion handbags", "Double Pay", "Immediate available is preferable"], "locations": ["Kowloon Bay"], "categories": ["Merchandising & Purchasing", "Handbag"], "post_time": "2022-01-01T19:40:22Z", "salary": {"currency": null, "max": null, "min": null, "period": "monthly", "term": null}, "salary_visible": false, "title_keywords": [], "responsibilities": ["cost", "systems", "quality", "monitor", "ad hoc tasks", "maintain", "schedule", "client\u2019s requirements"], "requirements": {"degrees": [], "majors": [], "languages": ["english", "mandarin"], "language_level": ["good"], "hard_skills": [], "soft_skills": ["communication skills", "self-motivated", "independent", "responsible", "time management skills", "well-organized", "attention to detail", "coordination"], "languages_combined": [{"language": "english", "language_level": ["good"]}, {"language": "mandarin", "language_level": ["good"]}]}, "experience_required": {"duration": ["at least 5 years"], "field": ["trading"]}}, {"job_id": "100003009016709", "location_code": "hk", "company": "HARVEY NICHOLS (HONG KONG) LIMITED", "job_title": "Assistant Buyer (Womenswear)", "description": "Responsibilities:\n\nAssist and support Merchandising Manager\u00a0 in all matters relating to buying, operations, and promotion initiatives;\nRegularly conduct market research; May attend overseas trade fairs with\u00a0Merchandising Manager;\nMonitor sales performance closely and execute stock transfer;\nPerform relevant business analysis in order to develop appropriate action plans to achieve financial targets set by Company;\nWork closely with Operations, Visual Merchandising team, and other counterparts to maximize sales performance of responsible category;\nConduct product training for the sales team. \u00a0\n\nRequirements:\n\nDegree holder preferably in fashion design or merchandising;\nMinimum\u00a02 years\u2019 relevant working experience in high-end fashion;\nStrong fashion sense, detail-oriented with good analytical and reporting skills;\nGood team player with a strong sense of responsibility;\nExcellent command of spoken English & Chinese;\nProficient in MS Word and Excel.\n\nWe offer excellent career prospects, competitive salary and fringe benefits to the right candidate.\u00a0 Please apply in strict confidence by sending personal resume together with salary expected and date available\n\nby e-mail to:\u00a0h r d\u00a0 _ h n @ h a r v e y n i c h o l s . c o m . h k\n\nWe are an equal opportunity employer and welcome applications from all qualified candidates. Personal data provided by job applicants will be used strictly in accordance with our personal data policy and for recruitment purposes only. Candidates not notified within eight weeks may consider their application unsuccessful. All related information will be kept in our file for up to 24 months. A copy of our Personal Information Collection Statement will be provided upon request by contacting our Human Resources Division.\u00a0", "employment_types": ["Full Time", "Permanent"], "selling_points": ["Assistant Buyer", "min 2 years' relevant working experience", "Strong fashion sense, detail-oriented"], "locations": ["Yau Tsim Mong Area"], "categories": ["Merchandising & Purchasing", "Footwear", "Handbag", "Textiles"], "post_time": "2022-01-03T09:40:40Z", "salary": {"currency": null, "max": null, "min": null, "period": "monthly", "term": null}, "salary_visible": false, "title_keywords": ["assistant"], "responsibilities": ["operations", "conduct market research", "sales performance", "merchandising", "monitor", "develop", "sales team", "visual", "business analysis", "plans"], "requirements": {"degrees": ["degree holder"], "majors": ["design"], "languages": ["english", "chinese"], "language_level": ["excellent"], "hard_skills": ["excel", "ms word"], "soft_skills": ["good team player", "sense of responsibility", "detail-oriented"], "languages_combined": [{"language": "english", "language_level": ["excellent"]}, {"language": "chinese", "language_level": ["excellent"]}]}, "experience_required": {"duration": ["minimum 2 years"], "field": ["relevant working experience"]}}, {"job_id": "100003009008555", "location_code": "hk", "company": "FnF Hong Kong Limited", "job_title": "Assistant Buying Manager / Senior Buyer", "description": "RESPONSIBILITIES\n\nSpecific responsibilities include but are not restricted to:-\n\nResponsible for leading a team to manage the whole process of buying activities\u00a0\u00a0\u00a0\u00a0\u00a0\u00a0\u00a0\u00a0\u00a0\u00a0\u00a0\u00a0\u00a0\u00a0\u00a0\u00a0\u00a0\u00a0\u00a0\u00a0\u00a0\u00a0\u00a0\u00a0\nFormulate and develop buying strategies and budget proposals to achieve sales, profit and inventory targets\nFormulate OTB planning, merchandise mix and assortment planning\nDeploy effective stock replenishment, inventory control, competitive pricing, potential markdowns and margin control strategies and action plans to optimize sales targets\nAnalyze market trends and sales performance on merchandise categories\nWork closely with retail operations, marketing and visual merchandising departments to formulate sales and marketing strategies\nFormulating and developing buying plan in terms of category ratio and size ratio and allocate the right merchandise in right locations\nAssuring achievement of volume, gross margin and profit goals through effective\u00a0merchandise selection, buying, timing and promotion\n\n\u00a0REQUIREMENTS\n\nUniversity graduate in Fashion and Clothing or related disciplines\nMinimum 5 years experience in a retail or wholesale\u00a0buying with 3 years in supervisory level\nGood understanding of supply and demands, retail operation, product cycle and fashion retail knowledge for Hong Kong market\nExcellent fashion and market sense in apparel and retail industry\nSelf-motivated, passionate, with strong analytical presentation and leadership skills\nStrong analytical mind & sensitive to figures\nGood command of both spoken and written English, Cantonese and Mandarin\nCandidates with less experiences will be considered as Senior Buyer", "employment_types": ["Full Time", "Permanent"], "selling_points": ["Buying Role", "Nice, young and energetic work environment", "Start-up fashion retail experience"], "locations": ["Tsim Sha Tsui"], "categories": ["Merchandising & Purchasing", "Footwear", "Handbag", "Others"], "post_time": "2021-12-30T08:19:14Z", "salary": {"currency": null, "max": null, "min": null, "period": "monthly", "term": null}, "salary_visible": false, "title_keywords": ["buying manager", "assistant"], "responsibilities": ["control", "stock replenishment", "marketing strategies", "sales performance", "inventory", "budget", "operations", "merchandising", "developing", "otb", "develop", "inventory control", "visual", "plan", "deploy", "plans", "planning"], "requirements": {"degrees": ["university graduate"], "majors": ["related disciplines"], "languages": ["cantonese", "english", "mandarin"], "language_level": ["good command"], "hard_skills": [], "soft_skills": ["passionate", "self-motivated", "leadership skills", "sensitive to figures", "analytical mind", "presentation"], "languages_combined": [{"language": "cantonese", "language_level": ["good command"]}, {"language": "english", "language_level": ["good command"]}, {"language": "mandarin", "language_level": ["good command"]}]}, "experience_required": {"duration": ["3 years", "minimum 5 years"], "field": ["supervisory level", "retail"]}}, {"job_id": "100003009015989", "location_code": "hk", "company": "Montaigne Hong Kong Limited", "job_title": "Shipping Coordinator (Leather Goods)", "description": "Position Objectives:\n\nManaging full process of shipping. Providing routing information, issuing shipping instructions to ensure delivery is fulfilling the business window.\n\n\nJob Descriptions:\n\nAble to independently handle full set of Import/ Export document, purchase orders follow up with overseas and local suppliers;\nCoordinate the inbound and outbound shipments with warehouse, internal departments, forwarders, and suppliers. It includes responding to customer or shippers\u2019 daily operations and communications;\nMonitor the shipment status, packing lists, reports, and system updates;\nLiaise with account for the preparation of invoices;\nPerform other ad-hoc tasks as assigned\n\nQualifications:\n\nForm 7 or above with 4-5 years relevant experience;\nGood command of written and spoken English, Mandarin and Cantonese;\nStrong communication, negotiation, multi-tasking, and problem-solving skills;\nSelf-motivated, independent, good communication & interpersonal skill;\nAble to work under pressure;\nExcellent Microsoft Office skills (Excel, Word, PowerPoint)\n\nInterested parties please apply with detailed resume with current & expected salary.\n\n\u00a0Personal data collected will be used for recruitment purposes only.", "employment_types": ["Full Time", "Permanent"], "selling_points": [], "locations": ["Wan Chai"], "categories": ["Transportation & Logistics", "Supply Chain", "Merchandising & Purchasing", "Handbag"], "post_time": "2022-01-03T08:03:51Z", "salary": {"currency": null, "max": null, "min": null, "period": "monthly", "term": null}, "salary_visible": false, "title_keywords": ["shipping coordinator"], "responsibilities": ["shipping", "invoices", "system updates", "ad-hoc tasks", "monitor", "coordinate", "communication", "purchase", "daily operations", "reports", "liaise with", "work under pressure"], "requirements": {"degrees": [], "majors": [], "languages": ["cantonese", "english", "mandarin"], "language_level": ["good command"], "hard_skills": ["excel", "microsoft office", "word", "powerpoint", "problem-solving skills"], "soft_skills": ["self-motivated", "independently", "independent", "negotiation", "interpersonal skill", "communication", "multi-tasking", "problem-solving skills", "work under pressure"], "languages_combined": [{"language": "cantonese", "language_level": ["good command"]}, {"language": "english", "language_level": ["good command"]}, {"language": "mandarin", "language_level": ["good command"]}]}, "experience_required": {"duration": ["4-5 years"], "field": ["relevant experience"]}}, {"job_id": "100003009002925", "location_code": "hk", "company": "Hermes Asia Pacific Limited", "job_title": "Sales Associate", "description": "Responsibilities:\u00a0\n\nResponsible for all sales activities in store within Herm\u00e8s standards of image and services worldwide\nDeliver quality and consistency of service including identifying customers\u2019 needs, developing client relationships, sale, and delivering post-sale services\nAchieving sales target and maintaining a high level of customer service, product knowledge and basic operational procedures\nBuild and maintain long-term relationship with customers by providing excellent customer experience\nAssist with inventory and special projects as needed\nOther duties as assigned\nRequirements:\u00a0\n\nMinimum 3 years relevant retail management or operation experience in luxury brands, high-end fashion, jewelry and watch retailing industry or in similar capacity\nStrong motivation towards becoming a Hermes Ambassador and providing excellent customer service\nStrong commitment towards teamwork\nEnergetic, passionate and positive working attitude\nExcellent in presentation, interpersonal and communication skills\nGood command of Cantonese, English and Mandarin\n\nInterested parties, please send your resume with expected salary and date of availability to:\u00a0recruitment.hap.hk@ hermes.com or by clicking \"Apply Now\"\n\n(Data collected will be treated in strict confidence and used for recruitment purpose only.)", "employment_types": ["Full Time", "Permanent"], "selling_points": ["Stable and family-oriented culture", "Energetic, passionate, and positive individual", "Excellent in customer service and CRM"], "locations": ["Not Specified"], "categories": ["Merchandising & Purchasing", "Handbag", "Sales, CS & Business Devpt", "Retail Sales", "Sales - Sales Management"], "post_time": "2021-12-28T07:37:53Z", "salary": {"currency": null, "max": null, "min": null, "period": "monthly", "term": null}, "salary_visible": false, "title_keywords": ["sales associate"], "responsibilities": ["sales activities", "maintaining", "other duties", "sales target", "inventory", "quality", "developing", "customer service", "operational procedures", "maintain"], "requirements": {"degrees": [], "majors": [], "languages": ["cantonese", "english", "mandarin"], "language_level": ["good command"], "hard_skills": ["hermes"], "soft_skills": ["passionate", "communication skills", "interpersonal", "teamwork", "positive working attitude", "customer service", "energetic", "presentation"], "languages_combined": [{"language": "cantonese", "language_level": ["good command"]}, {"language": "english", "language_level": ["good command"]}, {"language": "mandarin", "language_level": ["good command"]}]}, "experience_required": {"duration": ["minimum 3 years"], "field": ["operation", "management", "retail"]}}, {"job_id": "100003008990063", "location_code": "hk", "company": "Taibon Co Ltd", "job_title": "Senior Merchandiser (Gift and Premium/Plastic Molding)", "description": "JOB DUTIES\n\nResponsible for overall merchandising activities(especially for plastic molding) from product development to order follow up.\nManage daily communications with internal sales team & factories\nParticipate in price negotiation and cost engineering to meet client\u2019s goal.\nAssist Sales Team for orders and production follow-up\n\nTHE REQUIREMENTS\n\nUniversity degree graduated with good PC skills/English/Mandarin\nExpected to work with high efficiency and under pressure\nMature, self-motivated and\u00a0strong sense of responsibility.\n3 years+ experience in plastic molding factory or toys development/manufacturing\nGood communication and negotiation skills in English & Mandarin\nOccasional travel to China and Oversea may be needed\n\nWe are offering highly competitive package 5 days work, medical benefit, double pay and performance bonus", "employment_types": ["Full Time"], "selling_points": ["Plastic Molding/Toy Manufacturing", "Senior Merchandiser", "Gift and premium"], "locations": ["Lai Chi Kok"], "categories": ["Merchandising & Purchasing", "Handbag", "Sundries", "Others"], "post_time": "2021-12-21T07:29:01Z", "salary": {"currency": null, "max": null, "min": null, "period": "monthly", "term": null}, "salary_visible": false, "title_keywords": ["senior merchandiser"], "responsibilities": ["cost", "communications with", "price negotiation", "merchandising", "sales team"], "requirements": {"degrees": ["university degree"], "majors": [], "languages": ["english", "mandarin"], "language_level": ["good"], "hard_skills": ["pc skills"], "soft_skills": ["self-motivated", "under pressure", "sense of responsibility", "mature", "communication", "negotiation skills"], "languages_combined": [{"language": "english", "language_level": ["good", "good"]}, {"language": "mandarin", "language_level": ["good", "good"]}]}, "experience_required": {"duration": [], "field": ["toys", "development", "manufacturing"]}}, {"job_id": "100003008996378", "location_code": "hk", "company": "G.A. Operations Hong Kong Limited", "job_title": "Merchandiser - Accessories (Bags)", "description": "This position will provide quality merchandising support to the team and work closely with suppliers to ensure the new products are developed according to the product specification.\n\nResponsibilities\n\nResearch and develop new sources and vendors to influence and meet design expectation\nOrganize and consolidate all relevant vendors information\nWork closely\u00a0with suppliers to ensure the new products are developed according to the product specification\nFollow up and keep track of timeline\nSupport ad. hoc duties as required\n\nRequirements\n\nDiploma\u00a0in Fashion or equivalent, with focus on accessories\nAt least 2-3 years of merchandising experience in accessories (bags and leather goods) for a fashion brand\nPossess fashion sense and good technical knowledge\nGood\u00a0communication skills in both English & Chinese (Cantonese & Mandarin)\nProficient in MS Word and Excel\nSelf-motivated, a positive and good team player\nCandidates with more experience will be considered as SENIOR MERCHANDISER", "employment_types": ["Full Time", "Permanent"], "selling_points": [], "locations": ["Kowloon Bay"], "categories": ["Merchandising & Purchasing", "Handbag"], "post_time": "2021-12-23T06:57:18Z", "salary": {"currency": null, "max": null, "min": null, "period": "monthly", "term": null}, "salary_visible": false, "title_keywords": ["merchandiser"], "responsibilities": ["design", "develop"], "requirements": {"degrees": ["diploma"], "majors": [], "languages": ["cantonese", "english", "chinese", "mandarin"], "language_level": ["good"], "hard_skills": ["excel", "focus", "ms word"], "soft_skills": ["communication skills", "self-motivated", "good team player", "focus", "positive"], "languages_combined": [{"language": "cantonese", "language_level": ["good"]}, {"language": "english", "language_level": ["good"]}, {"language": "chinese", "language_level": ["good"]}, {"language": "mandarin", "language_level": ["good"]}]}, "experience_required": {"duration": ["at least 2-3 years"], "field": ["merchandising", "brand"]}}, {"job_id": "100003008999460", "location_code": "hk", "company": "Christian Dior Far East Limited", "job_title": "Assistant Merchandising Manager - Hong Kong & Macau", "description": "Responsibilities\n\n\n\u25ba Merchandising\n\nInitiate and execute merchandising strategies of Hong Kong & Macau to align with Global and Regional guidelines\nSynchronize merchandising related issues between Hong Kong, Macau and Regional Team\nDefine and propose suitable merchandising assortment by stores\nManage stock transfer and handle stock requests from Boutiques to maximize sales\nMonitor shipment fulfillment and delivery schedule to ensure merchandise are delivered to stores on time for successful seasonal launch\nHandle product replenishment and allocation for each Boutique with Regional Team and ensure productive and efficient stock management\nProduct performance analysis and propose incentive or product push to the Boutiques for performance improvement and business maximization\nMonitor the stock level for each product line closely and propose strategy to reach optimum level\nMonitor physical inventory take and reconciliation on stock discrepancy\nAnalyze clients buying behavior for better understanding of the market\nMonitor on product qualities and report on defective items\nParticipate in buying trip to provide quantitative and qualitative feedback and support other coordination work when required\n\n\u25ba Coordination with Retail Team\n\nDevelop and maintain proper communication channels between Merchandising & Retail Operation\nConduct collection training to retail team in the part of inventory & logistics\nReview order assortment in partnership with retail team\nTake charge and provide on-site support to the merchandising issues in Boutique events such as trunk show\n\n\u25ba Reporting\n\nRegular update of order maps\nWeekly and monthly internal report generation and analysis\nRequirement\n\nDiploma or university graduate in Fashion & Textile, Merchandising, Business Administration or related discipline\nMinimum 7 years of relevant working experience with at least 3 years at supervisory level in luxury retail industry\nStrategic thinking for driving business goals\nWell-organized and detail-minded\nGood numerical sense\nAble to work independently but also as a team player\nGood communication and interpersonal skills\nAble to work in a fast-paced and diverse environment\nProficient in computer knowledge especially in Excel\nProficient in Cantonese, Mandarin and English\n\nInterested parties please send your full resume and salary expectation to :\u00a0recruit@ hk.christiandior.com.\u00a0\n\n\n* All applications will be treated in strict confidence and used only for recruitment purpose. Applicants who are not invited for an interview within 4 weeks may be considered for other suitable positions within the Group over a one year period, after which their personal data will be destroyed.*", "employment_types": ["Full Time", "Permanent"], "selling_points": ["Initiate and execute merchandising strategies", "Product performance analysis", "Hong Kong & Macau"], "locations": ["Causeway Bay"], "categories": ["Merchandising & Purchasing", "Woven / Knit", "Handbag"], "post_time": "2021-12-24T07:19:06Z", "salary": {"currency": null, "max": null, "min": null, "period": "monthly", "term": null}, "salary_visible": false, "title_keywords": ["merchandising manager", "assistant"], "responsibilities": ["fulfillment", "coordination with", "merchandising", "inventory", "communication", "maintain", "monitor", "inventory take", "develop", "logistics", "report", "reporting", "stock management", "review", "delivery schedule", "guidelines", "analysis", "replenishment", "coordination"], "requirements": {"degrees": ["university graduate", "diploma"], "majors": ["business administration"], "languages": ["cantonese", "english", "mandarin"], "language_level": ["proficient"], "hard_skills": ["excel"], "soft_skills": ["detail-minded", "work independently", "strategic thinking", "well-organized", "diverse", "communication and interpersonal skills", "team player"], "languages_combined": [{"language": "cantonese", "language_level": ["proficient"]}, {"language": "english", "language_level": ["proficient"]}, {"language": "mandarin", "language_level": ["proficient"]}]}, "experience_required": {"duration": ["at least 3 years", "minimum 7 years"], "field": ["luxury retail", "supervisory level", "relevant working experience"]}}, {"job_id": "100003008999139", "location_code": "hk", "company": "Kwok Hang Holdings Limited", "job_title": "Merchandising Coordinator", "description": "Job Responsibilities:\n\nResponsible for all merchandising issue\nTo provide clerical support to the merchandising team, which include download data, photo and compiling report and printouts\nWork closely with various internal departments to ensure smooth operation of merchandising function including marketing, operations, wholesale and retail teams\nHandle ad hoc project as assigned\n\nPrerequisite:\n\nTertiary education with at least 2 years working experience in retail industry is an advantage\nGood command of both English and Chinese, and be able to well communicate in Putonghua\nGood analytical skills and numerical sense\nProficient in MS Office applications: Excel (vlookup / pivot table), Word, PowerPoint\nKnowledge of Chinese word processing is an advantage\n\nExcellent working environment at premium sea view office. 10 minutes walking distance from MTR station.\n\nWe offer good career prospects with attractive remuneration packages including 5-day working week to the right candidate.\n\nInterested parties, please apply with full resume stating current and\u00a0expected salary\u00a0and date available to the Human Resources Department by clicking\u00a0Apply Now\u00a0bottom below.\n\nInformation collected will be used for recruitment purpose only.", "employment_types": ["Full Time", "Permanent"], "selling_points": [], "locations": ["Kowloon Bay"], "categories": ["Merchandising & Purchasing", "Footwear", "Woven / Knit", "Handbag"], "post_time": "2021-12-24T06:19:15Z", "salary": {"currency": null, "max": null, "min": null, "period": "monthly", "term": null}, "salary_visible": false, "title_keywords": ["merchandising coordinator"], "responsibilities": ["provide clerical support", "ad hoc", "data", "operations", "merchandising", "teams", "report"], "requirements": {"degrees": [], "majors": [], "languages": ["putonghua", "english", "chinese"], "language_level": ["advantage", "good command"], "hard_skills": ["excel", "chinese word processing", "pivot table", "word", "powerpoint", "analytical skills", "vlookup", "ms office"], "soft_skills": ["analytical skills"], "languages_combined": [{"language": "putonghua", "language_level": ["good command"]}, {"language": "english", "language_level": ["good command"]}, {"language": "chinese", "language_level": ["advantage", "good command"]}]}, "experience_required": {"duration": ["at least 2 years"], "field": ["retail industry", "education"]}}, {"job_id": "100003008987280", "location_code": "hk", "company": "Morgan McKinley", "job_title": "Assistant Sourcing Manager (FMCG/ Personal & Beauty Care) 40k", "description": "Responsibilities\n\nResponsible for vendor sourcing and support the price negotiation with PRC and offshore vendors\nManage a team of 5 in Sourcing department, provide support on team hiring, redundancy and training\nConduct continuous evaluation and support on vendor performance and alignment of resources including KPI measurements and buying program\nConduct market research & analysis covering the trends, client portfolio, segmentations and competitors' analysis (personal care and beauty care)\nConduct continuous evaluation and support on capacity planning and alignment of resources\n\nRequirements\n\nDiploma or above\nMinimum 6 years relevant experience in handling FMCG/ Personal Care/ Cosmetic products\n* Strong leadership experience\nExcellent command of written and spoken English and Mandarin is essential\n\nApplication\n\nIf this above description fits your experience and is something you would like to explore, please click 'Apply Now' to submit your resume to us.\n\nAny questions, please feel free to contact Kenneth Leung at 3907 3939.", "employment_types": ["Full Time", "Permanent"], "selling_points": ["Vendor Sourcing", "Sales Planning", "People Management"], "locations": ["Not Specified"], "categories": ["Merchandising & Purchasing", "Handbag", "Furniture", "Procurement / Purchasing / Sourcing"], "post_time": "2021-12-20T05:45:18Z", "salary": {"currency": null, "max": null, "min": null, "period": "monthly", "term": null}, "salary_visible": false, "title_keywords": ["personal", "assistant", "sourcing manager"], "responsibilities": ["price negotiation", "provide support", "analysis", "conduct market research", "evaluation", "planning"], "requirements": {"degrees": ["diploma or above"], "majors": [], "languages": ["english", "mandarin"], "language_level": ["excellent"], "hard_skills": [], "soft_skills": ["leadership"], "languages_combined": [{"language": "english", "language_level": ["excellent"]}, {"language": "mandarin", "language_level": ["excellent"]}]}, "experience_required": {"duration": ["minimum 6 years"], "field": ["personal care", "fmcg", "relevant experience"]}}, {"job_id": "100003008986119", "location_code": "hk", "company": "Furla Hong Kong Retail Limited", "job_title": "Merchandising Manager Asia", "description": "Reports to:\u00a0Merchandising Director APAC\n\nMain Purpose\n\nTo lead the overall full price merchandising capability for Asia market\n\nFocus on buying analysis, assortment profiling and sell through management.\n\nMerchandise Strategy\n\nDuties and responsibilities:\n\n\nPartner with HQ merchandising team formulating an assortment strategy that is consistent with overall business strategy.\nDefines and leads the development and execution of the key business drivers ( key items and stores) in the market\nManages the proper execution of strategy in the market with partnership with retail, VM, marketing/PR, eCOM team; takes appropriate action when necessary.\nWorks closely with the team partners to ensure they are aligned with the merchandise strategy and executing appropriately.\nEvaluates ongoing performance with Key members and act as appropriate.\nDevelops product transition plan and product strategies with P&A team\nMonitor performance on new products and determines further opportunities based on results.\nInterprets trends appropriate to local and tourist customers.\nCreates category / collections level sales plan by location.\n\n\nBuying\n\n\nEnsures accurate and timely completion of buying budget at category level\nMaintains purchase orders to manage forward buys in-line with inventory targets.\nProvides ongoing feedback and information to team members on sales results, competitive practices, and delivery issues with HQ and other specific information which could impact the performance of the business.\nIdentify and prioritize sales opportunities including plan to execute;\nMonitor and report on top selling items, provide recommendations for improvement and ensure the follow up;\nDeliver regular channel insight report to share with both channel\nMaintain up-to-date records for the stock receipts, stock holding, stock for sale etc. information for management\u2019s review.\nCoordinate with visual merchandising and retail operations department to ensure that all shops are presented to customers in line with the Company\u2019s policy.\nCompile and submit all necessary sales, inventory, forecasts, budgets, etc. information as may be required by management from time to time.\nProvide merchandising related training to retail staff\nResolve issues within a timely manner while working to continuously create and or improve internal and external processes and procedures\nPeople Management\nSupervising team members\nCoach team to develop product strategy to fit the markets\nDevelop necessary skills to drive the sales via product\nProvide necessary information to support the team and other partners\n\nQualifications\n\n\n\nDegree holder in business administration / planning management /merchandising;\nAt least 8 years\u2019 experience in Merchandising supervisor or above\nIndustrial relevant is important;\nStrong data analysis skills\nGood interpersonal & communication skills, independent, friendly and outgoing;\nStrong problem-solving and meticulous, able to work under pressure with minimal supervision, highly self-motivated and directed, detail-minded;\nStrong analytical skills to identify the root cause\nFluent in English both writing and speaking\nInterested parties please send your resume by clicking \"APPLY NOW\"", "employment_types": ["Full Time", "Permanent"], "selling_points": ["Buying & Merchandising function in Asia", "8 years\u2019 experience in Merchandising supervisor", "MNC environment"], "locations": ["Causeway Bay"], "categories": ["Merchandising & Purchasing", "Handbag"], "post_time": "2021-12-20T02:07:07Z", "salary": {"currency": null, "max": null, "min": null, "period": "monthly", "term": null}, "salary_visible": false, "title_keywords": ["merchandising manager"], "responsibilities": ["supervising", "receipts", "operations", "inventory", "budget", "merchandising", "communication", "purchase", "maintain", "plan", "administration", "work under pressure", "monitor performance", "monitor", "develop", "reports", "visual", "report", "competitive practices", "management", "delivery issues", "review", "coordinate with", "procedures", "data analysis", "executing", "provide recommendations", "support the team", "sales results", "budgets", "analysis", "a timely manner", "planning"], "requirements": {"degrees": ["degree holder"], "majors": ["business administration"], "languages": ["english"], "language_level": ["fluent"], "hard_skills": ["problem-solving", "analysis", "visual merchandising", "analytical skills", "focus"], "soft_skills": ["outgoing", "communication skills", "meticulous", "self-motivated", "independent", "detail-minded", "timely", "problem-solving", "prioritize", "analytical skills", "friendly", "focus", "accurate", "interpersonal", "work under pressure"], "languages_combined": [{"language": "english", "language_level": ["fluent"]}]}, "experience_required": {"duration": ["at least 8 years"], "field": ["merchandising"]}}, {"job_id": "100003008989461", "location_code": "hk", "company": "Hillman Ross", "job_title": "Sourcing Manager (Luggage and bags)", "description": "Our client is a European company and they are looking for a Sourcing Manager to take care of luggage and bags category. This person will be an individual contributor, reporting to the Category Manager.\n\nWe are now seeking for Sourcing Manager (Luggage and bags)\n\nRESPONSIBILITIES\n\nWell organization skills of dealing with complex product categories, manage high sku and multi-countries production base.\nDevelop product and vendor strategies to drive for continue business growth.\nWork with the Sourcing Managers to evaluate the performance of factories and assess the business risk that support clients' business needs.\nSupervise and guide a team of merchandisers and coordinate with cross functional teams to achieve excellent KPI to meet client's expectation.\nStrong and in-depth negotiation skills to drive cost saving and costing margin for clients' continue business growth.\nFull ownership of the whole supply chain from factory sourcing, development till shipment with in-depth technical knowledge, proactive on problem precaution & strong decision maker.\nManage the team to ensure they are up to the company standard\nMotivate the team by sharing knowledge and expertise, ensuring attention to detail and seeking continuous improvements\nDevelop a close relationship with existing suppliers and develop new suppliers through personal connections, trade fairs and sourcing trips\nProduct, payment and business term negotiations with suppliers.\n\nTo succeed in this key role, you will have at least 10 years experience in sourcing with at least 6 years in managerial capacity.\n\nQUALIFICATIONS:\n\nTertiary educated\nSelf-motivated and have strong sense of responsibility.\nStrong people and process management skills\nStrong analytical and interpersonal skills\nIndependent and excellent time management in meeting deadline.\nStrong communication skills and fluent in English, Mandarin and Cantonese\nExperience in handling bags is a Must\nExperience working in European market is a MUST\n\nAPPLY FOR THIS JOB\n\nInterested candidate please CLICK apply button to apply online or send your resume in MS word format to Hillman Ross Recruitment Solution Professional\n\nPlease note that only shortlisted candidate will be notified. All information will be treated in strict confidence and solely used for recruitment purposes.", "employment_types": ["Full Time", "Permanent"], "selling_points": ["European Company", "Experience in handling bags is a Must", "Experience working in European market is a MUST"], "locations": ["Not Specified"], "categories": ["Merchandising & Purchasing", "Handbag", "Others", "Procurement / Purchasing / Sourcing"], "post_time": "2021-12-21T03:48:32Z", "salary": {"currency": null, "max": null, "min": null, "period": "monthly", "term": null}, "salary_visible": false, "title_keywords": ["sourcing manager"], "responsibilities": ["product categories", "reporting", "cost", "continuous improvements", "management", "coordinate with", "teams", "develop", "evaluate", "communication", "payment", "support clients", "recruitment"], "requirements": {"degrees": [], "majors": [], "languages": ["cantonese", "english", "mandarin"], "language_level": ["fluent"], "hard_skills": ["vendor", "ms word"], "soft_skills": ["communication skills", "self-motivated", "confidence", "independent", "sense of responsibility", "time management", "negotiation skills", "interpersonal skills", "attention to detail", "organization skills", "proactive"], "languages_combined": [{"language": "cantonese", "language_level": ["fluent"]}, {"language": "english", "language_level": ["fluent"]}, {"language": "mandarin", "language_level": ["fluent"]}]}, "experience_required": {"duration": ["at least 10 years", "at least 6 years"], "field": ["managerial"]}}]