[{"job_id": "100003009054861", "location_code": "hk", "company": "Abouthai (Hong Kong) Limited", "job_title": "Category Manager (Convenience Store)", "description": "Responsibilities:\n\nExecute and implement programs per category strategies as defined in budget and strategic planning\nLiaise with Marketing Team for developing an attractive promotional event which follow pre-agreed selling plan\nMonitor daily inventory, set up order forecast and implement daily replenishment to ensure sufficient stock level in stores\nEnsure stable stock level by good promotion plan and SKU management\nNegotiate and work with vendors to build mutually beneficial relationships to ensure long term strategic partnership, leading to lower costs and higher margin\nMonitor & identify of new trends, new brands, merchandising programs and ad-hoc strategies to optimize category growth and performance\nAnalyze market data and campaigns to ensure effectiveness and positive ROI\u00a0\u00a0\u00a0\u00a0\u00a0\u00a0\u00a0\nSupport any ad hoc projects as assigned\n\nRequirements:\n\nDegree holder in Business, Marketing, or other related disciplines\nMinimum 8 years working experience\u00a0in category management or trade marketing from Convenience Store or Supermarkets\nStrong negotiation skills & interpersonal relationships, leadership skill and presentation skill\nGood network and relationship with different kinds of organization and business sector\nResult-oriented, Self-motivated, aggressive, energetic and a good team player\nRegular travel and outdoor activities are expected\nExcellent command in written and spoken English and Chinese (including Cantonese and Mandarin)\nImmediately available is preferable\n\nWe offer 5-days work week, double pay and good career prospect to the right candidates. Interested parties, please send full resume with\u00a0present & expected\u00a0salaries & date availability to HR Department by \u201cApply Now\u201d below.\n\nAll information will be treated in strict confidence and will be used for recruitment related purpose only. Information of unsuccessful applicants will be destroyed upon completion of the recruitment process.", "employment_types": ["Full Time", "Permanent"], "selling_points": ["Category Management", "SKU Management", "Convenience store"], "locations": ["Tsuen Wan Area"], "categories": ["Merchandising & Purchasing", "Others", "Procurement / Purchasing / Sourcing"], "post_time": "2022-01-17T12:00:00Z", "salary": {"currency": null, "max": null, "min": null, "period": "monthly", "term": null}, "salary_visible": false, "title_keywords": ["category manager"], "responsibilities": ["ad-hoc", "management", "strategic planning", "inventory", "budget", "monitor", "developing", "replenishment", "merchandising", "order forecast", "ad hoc projects", "plan", "liaise with", "market data", "costs"], "requirements": {"degrees": ["degree holder"], "majors": ["related disciplines", "business", "marketing"], "languages": ["cantonese", "english", "chinese", "mandarin"], "language_level": ["excellent"], "hard_skills": ["presentation skill"], "soft_skills": ["presentation skill", "self-motivated", "good team player", "negotiation skills", "energetic", "leadership skill", "interpersonal", "result-oriented"], "languages_combined": [{"language": "cantonese", "language_level": ["excellent"]}, {"language": "english", "language_level": ["excellent"]}, {"language": "chinese", "language_level": ["excellent"]}, {"language": "mandarin", "language_level": ["excellent"]}]}, "experience_required": {"duration": ["minimum 8 years"], "field": ["management", "marketing"]}}, {"job_id": "100003009055771", "location_code": "hk", "company": "ConnectedGroup Limited", "job_title": "Merchandiser- Food", "description": "Our Client is a Well-established buying office, they are looking for a Merchandiser to join their expanding team.\n\nKey Job Responsibilities include:\n\n\n\nResponsible for the whole merchandising process and ensure products meet customers' requirements\nResponsible for order follow-up, sampling, product development, price negotiations, quality control, and shipments, etc.\nWork closely with internal parties to ensure production schedules are aligned with company strategy.\nWork closely with the quality team and ensure products meet QA requirements\nMaintain & update product record to prepare related documents\nMaintain strong business relationships with supplier for product development and production\n\n\nOther requirements include:\n\nTertiary education with a minimum of 2 years experience in merchandising, experience in food and near food items\nExperienced in product and project development, follow up and negotiation\nGood communication skills, self-motivated, proactive, and open-minded\nExcellent in English, Cantonese, and Mandarin, both spoken and written\nTravel if necessary", "employment_types": ["Full Time", "Permanent"], "selling_points": ["Well-established buying office", "Food experience is preferred", "Attractive Remuneration Package"], "locations": ["Not Specified"], "categories": ["Merchandising & Purchasing", "Others", "Procurement / Purchasing / Sourcing"], "post_time": "2022-01-18T02:55:57Z", "salary": {"currency": null, "max": null, "min": null, "period": "monthly", "term": null}, "salary_visible": false, "title_keywords": ["merchandiser"], "responsibilities": ["schedules", "related documents", "merchandising", "quality", "maintain", "quality control", "internal parties"], "requirements": {"degrees": [], "majors": [], "languages": ["cantonese", "english", "mandarin"], "language_level": ["excellent"], "hard_skills": [], "soft_skills": ["communication skills", "self-motivated", "negotiation", "open-minded", "proactive"], "languages_combined": [{"language": "cantonese", "language_level": ["excellent"]}, {"language": "english", "language_level": ["excellent"]}, {"language": "mandarin", "language_level": ["excellent"]}]}, "experience_required": {"duration": ["minimum of 2 years"], "field": ["food", "merchandising", "education"]}}, {"job_id": "100003009052350", "location_code": "hk", "company": "RPT International Limited", "job_title": "Ecommerce Assistant", "description": "Job description and responsibilities\n- Handle daily ecommerce operation such as online customer service and order fulfillment.\u00a0\n- Update information in our online shop backend.\n- Some product research.\n\nJob requirements\n- Form 6 graduate or above.\n- Good command in written and spoken Cantonese and English.\n- Proactive, ability to multi-task and work under pressure.\n- Good interpersonal, communication skills.\n\n", "employment_types": ["Full Time"], "selling_points": [], "locations": ["Kwun Tong"], "categories": ["Sales, CS & Business Devpt", "Customer Service - Supervisor / Officer", "Merchandising & Purchasing", "Others", "E-commerce", "Others"], "post_time": "2022-01-17T02:53:04Z", "salary": {"currency": null, "max": null, "min": null, "period": "monthly", "term": null}, "salary_visible": false, "title_keywords": ["assistant"], "responsibilities": ["order fulfillment", "online customer service"], "requirements": {"degrees": [], "majors": [], "languages": ["cantonese", "english"], "language_level": ["good command"], "hard_skills": [], "soft_skills": ["communication skills", "multi-task", "proactive", "interpersonal", "work under pressure"], "languages_combined": [{"language": "cantonese", "language_level": ["good command"]}, {"language": "english", "language_level": ["good command"]}]}, "experience_required": {"duration": [], "field": []}}, {"job_id": "100003009053600", "location_code": "hk", "company": "Gotendo Beauty and Healthcare Group Limited", "job_title": "\u63a1\u8cfc\u7d93\u7406", "description": "\n\u8077\u8cac :\u8ca0\u8cac\u806f\u7d61\u4f9b\u61c9\u5546\u8ddf\u9032\u53ca\u7d22\u53d6\u5831\u50f9,\u5b89\u6392\u8a02\u8ca8,\u8ddf\u9032\u63a1\u8cfc\u8a02\u55ae,\u70ba\u516c\u53f8\u63a1\u8cfc\u4e16\u754c\u5404\u5730\u4e0d\u540c\u7522\u54c1 (\u5177\u98df\u54c1/\u8b77\u819a\u54c1/\u767e\u8ca8\u884c\u696d\u7684\u63a1\u8cfc\u7d93\u9a57,\u5177\u826f\u597d\u5e02\u5834\u610f\u8b58)\n\n\u8cc7\u6b77 :\u4e2d\u4e94\u7a0b\u5ea6; 3\u5e74\u7d93\u9a57; \u826f\u597d\u7cb5\u8a9e; \u4e00\u822c\u666e\u901a\u8a71; \u61c2\u8b80\u5beb\u4e2d\u6587; \u61c2\u8b80\u5beb\u82f1\u6587; \u51773\u5e74\u6216\u4ee5\u4e0a\u63a1\u8cfc\u7d93\u9a57, \u80fd\u7368\u7acb\u8655\u7406\u63a1\u8cfc\u5de5\u4f5c, \u826f\u597d\u6e9d\u901a\u53ca\u8b70\u50f9\u8ac7\u5224\u6280\u5de7\n\n\u5f85\u9047 :\u6bcf\u6708$12,000 - $20,000, \u661f\u671f\u4e00\u81f3\u4e94: \u4e0a\u53489\u6642\u81f3\u4e0b\u53486\u6642, \u6bcf\u9031\u5de5\u4f5c5\u5929\n\n\u7533\u8acb\u9808\u77e5 :\u6c42\u8077\u8005\u53ef\u81f4\u96fb28891317\u8207\u5fa1\u6bbf\u5802\u85e5\u599d\u6709\u9650\u516c\u53f8\u85cd\u5c0f\u59d0\u806f\u7d61\u3002\n\n", "employment_types": ["Full Time"], "selling_points": [], "locations": ["Kwun Tong"], "categories": ["Merchandising & Purchasing", "Others", "Procurement / Purchasing / Sourcing"], "post_time": "2022-01-17T07:13:23Z", "salary": {"currency": null, "max": null, "min": null, "period": "monthly", "term": null}, "salary_visible": false, "title_keywords": [], "responsibilities": [], "requirements": {"degrees": [], "majors": [], "languages": [], "language_level": [], "hard_skills": [], "soft_skills": [], "languages_combined": []}, "experience_required": {"duration": [], "field": []}}, {"job_id": "100003009056200", "location_code": "hk", "company": "ME Job Personnel Limited", "job_title": "Merchandiser & Senior Merchandiser  (Label / Packaging )", "description": "Three Sizable Non-Garment\u00a0Companies (Two \"USA Buying Office\" & One \"EEC Buying Office\")\u00a0are URGENTLY looking for a suitable candidate for the Merchandising position.\n\nRequirements:\n\nF.5 or above\nAt least 3-5 years experience in\u00a0merchandising which one in\u00a0(Label /Packaging) items\nGood communicate across teams involving multiple partners\nDeliver and succeed in the challenging arena of Hardline\nDetail and a strong sense of pro-activity will also be part of your arsenal\nGood command of written and spoken English and Chinese\nCommunication skills to analyze, projects manage and delivery\n\nSalary : Negotiable\n\nLocation : Kwai Chung\n\nOurclients have offered a comprehensive benefits package to the successful candidate.\n\nInterested parties, please send a detailed resume by clicking \"Apply Now\" or visit our company website find email address (ATTN : Eddy.Tse) Hotline : 27066333.\n\nTo learn more about Me Job Personnel Limited., visit http://www.mejob.com.hk/ .\n\nAll information collected is strictly for recruitment purpose.", "employment_types": ["Full Time"], "selling_points": [], "locations": ["Kwai Tsing Area"], "categories": ["Merchandising & Purchasing", "Sundries", "Others", "Procurement / Purchasing / Sourcing"], "post_time": "2022-01-18T03:32:01Z", "salary": {"currency": null, "max": null, "min": null, "period": "monthly", "term": null}, "salary_visible": false, "title_keywords": ["merchandiser", "senior merchandiser"], "responsibilities": ["communication", "teams", "merchandising"], "requirements": {"degrees": [], "majors": [], "languages": ["english", "chinese"], "language_level": ["good command"], "hard_skills": [], "soft_skills": ["communication skills"], "languages_combined": [{"language": "english", "language_level": ["good command"]}, {"language": "chinese", "language_level": ["good command"]}]}, "experience_required": {"duration": ["at least 3-5 years"], "field": ["merchandising"]}}, {"job_id": "100003009054997", "location_code": "hk", "company": "Angie International Limited", "job_title": "Sales Assistant", "description": "A well-established holding company is starting new supermarket business, we need professional staff and expert who is having thorough planning for running/operating/managing supermarket business professionally and smoothly. With his or her sound ancillary measures and diversified promotional activities, Retail Concepts, believe we can have profitable market share in this new area of business.\u7d93\u7406/\n\nPurchasing Clerk(Supermarket)\n\n(INMU SHOP LIMITED) \u701b\u6728\u8d85\u7d1a\u5e02\u57f8\u6709\u9650\u516c\u53f8\n\nNgau Tau Kok\n\nProactive, Flexible, Self-starter\n\nSupermarket/ eCommerce background welcomed\nStrong supplier network a plus\nRetails\nresponsibilities\nHandle daily / seasonal buying process from budgeting to launching\nWork closely with Sales and Business Development team for maximizing top line and minimizing inventory\nConduct and analyze regular buying and selling related report\nMaintain the database accuracy\nJob Requirements:\n\nPlan and execute regular product sourcing activities; ensure quality of products and on-time delivery to maintain suitable stock levels\nCoordinate and liaise with suppliers on product sourcing, trading terms and contract development; build a network of suppliers and maintain long-term vendor relationships\nAnalyse market trends to forecast upcoming product demands and potential sales volumes\nDevelop categorical selection of products and enhance sales by identifying and sampling new products\nSet seasonal OTB budget, formulate assortment and allocation plan, conduct inventory analysis and management, and set prices for products\nAnalyse sales and consolidate information of a variety of reports and plans (e.g. buying plan, delivery scheduling, stock clearance plan)\nMonitor sales with stock level, product efficiency, merchandise distribution, replenishment consolidation on a timely basis\nHandle merchandising related issues to ensure a timely management for all orders and deliveries\nLead team members (i.e. assistant buyers) and providing guidance\nCollaborate with marketing team and operation department and participate in major corporate sales, promotion events, visual merchandising and other ad-hoc projects\n\nRequirements Qualifications\n\nDiploma or above\nMinimum 2-3 years of relevant experience, preferably on the food or grocery department in supermarket industry\nKnowledge of category management\nAnalytical, open to change, well-organized and self-motivated with strong market sense and awareness\nStrong organizational and planning skills\nStrong desire to take initiative and able to work independently under pressure\nOutstanding interpersonal skills and negotiating abilities\nGood command of English and Chinese\nProficient in MS Office and Chinese Word Processing\nCandidate with more experience will be considered as Senior Buyer\n\nInterested parties please email detailed resume with expected salary to [email redacted, apply via company websitePlease click Apply Now to submit your application.\n\nWe\u00a0offer:\n\n5 days\u2019 work week + Alternate Saturday\n\nCompetitive Salary Package\n\n13 months' End-end bonus\n\nPerformance Incentives\n\nGroup Medical Scheme\n\nEnergetic & Dynamic Culture\n\n\u00a0\u00a0Interested parties please send your full resume and expected salary for application.", "employment_types": ["Full Time"], "selling_points": ["Knowledge of Garment /Uniform", "Medical with dental benefits, Bank holiday", "Immediate available is preferred"], "locations": ["Mong Kok"], "categories": ["Merchandising & Purchasing", "Others"], "post_time": "2022-01-17T16:22:52Z", "salary": {"currency": null, "max": null, "min": null, "period": "monthly", "term": null}, "salary_visible": false, "title_keywords": ["sales assistant"], "responsibilities": ["budgeting", "inventory", "maintain", "database", "report"], "requirements": {"degrees": ["diploma or above"], "majors": [], "languages": ["english", "chinese"], "language_level": ["good command", "proficient"], "hard_skills": ["chinese word processing", "analysis", "visual merchandising", "vendor", "ms office"], "soft_skills": ["self-motivated", "work independently", "under pressure", "organizational and planning skills", "timely", "well-organized", "interpersonal skills", "strong market sense", "initiative"], "languages_combined": [{"language": "english", "language_level": ["good command"]}, {"language": "chinese", "language_level": ["good command", "proficient"]}]}, "experience_required": {"duration": ["minimum 2-3 years"], "field": ["food", "relevant experience"]}}, {"job_id": "100003009040321", "location_code": "hk", "company": "REWE Far East Limited", "job_title": "Junior Merchandiser", "description": "A well-established holding company is starting new supermarket business, we need professional staff and expert who is having thorough planning for running/operating/managing supermarket business professionally and smoothly. With his or her sound ancillary measures and diversified promotional activities, Retail Concepts, believe we can have profitable market share in this new area of business.\u7d93\u7406/\n\nPurchasing Clerk(Supermarket)\n\n(INMU SHOP LIMITED) \u701b\u6728\u8d85\u7d1a\u5e02\u57f8\u6709\u9650\u516c\u53f8\n\nNgau Tau Kok\n\nProactive, Flexible, Self-starter\n\nSupermarket/ eCommerce background welcomed\nStrong supplier network a plus\nRetails\nresponsibilities\nHandle daily / seasonal buying process from budgeting to launching\nWork closely with Sales and Business Development team for maximizing top line and minimizing inventory\nConduct and analyze regular buying and selling related report\nMaintain the database accuracy\nJob Requirements:\n\nPlan and execute regular product sourcing activities; ensure quality of products and on-time delivery to maintain suitable stock levels\nCoordinate and liaise with suppliers on product sourcing, trading terms and contract development; build a network of suppliers and maintain long-term vendor relationships\nAnalyse market trends to forecast upcoming product demands and potential sales volumes\nDevelop categorical selection of products and enhance sales by identifying and sampling new products\nSet seasonal OTB budget, formulate assortment and allocation plan, conduct inventory analysis and management, and set prices for products\nAnalyse sales and consolidate information of a variety of reports and plans (e.g. buying plan, delivery scheduling, stock clearance plan)\nMonitor sales with stock level, product efficiency, merchandise distribution, replenishment consolidation on a timely basis\nHandle merchandising related issues to ensure a timely management for all orders and deliveries\nLead team members (i.e. assistant buyers) and providing guidance\nCollaborate with marketing team and operation department and participate in major corporate sales, promotion events, visual merchandising and other ad-hoc projects\n\nRequirements Qualifications\n\nDiploma or above\nMinimum 2-3 years of relevant experience, preferably on the food or grocery department in supermarket industry\nKnowledge of category management\nAnalytical, open to change, well-organized and self-motivated with strong market sense and awareness\nStrong organizational and planning skills\nStrong desire to take initiative and able to work independently under pressure\nOutstanding interpersonal skills and negotiating abilities\nGood command of English and Chinese\nProficient in MS Office and Chinese Word Processing\nCandidate with more experience will be considered as Senior Buyer\n\nInterested parties please email detailed resume with expected salary to [email redacted, apply via company websitePlease click Apply Now to submit your application.\n\nWe\u00a0offer:\n\n5 days\u2019 work week + Alternate Saturday\n\nCompetitive Salary Package\n\n13 months' End-end bonus\n\nPerformance Incentives\n\nGroup Medical Scheme\n\nEnergetic & Dynamic Culture\n\n\u00a0\u00a0Interested parties please send your full resume and expected salary for application.", "employment_types": ["Full Time", "Permanent"], "selling_points": ["Seasonal and Decoration items, Merchandising, S&D", "EU buying office, Mobile Working, Flex Working Hr", "13th Month Bonus, Discretionary Bonus"], "locations": ["Kwun Tong Area"], "categories": ["Merchandising & Purchasing", "Sundries", "Others"], "post_time": "2022-01-16T21:50:04Z", "salary": {"currency": null, "max": null, "min": null, "period": "monthly", "term": null}, "salary_visible": false, "title_keywords": ["junior merchandiser"], "responsibilities": ["budgeting", "inventory", "maintain", "database", "report"], "requirements": {"degrees": ["diploma or above"], "majors": [], "languages": ["english", "chinese"], "language_level": ["good command", "proficient"], "hard_skills": ["chinese word processing", "analysis", "visual merchandising", "vendor", "ms office"], "soft_skills": ["self-motivated", "work independently", "under pressure", "organizational and planning skills", "timely", "well-organized", "interpersonal skills", "strong market sense", "initiative"], "languages_combined": [{"language": "english", "language_level": ["good command"]}, {"language": "chinese", "language_level": ["good command", "proficient"]}]}, "experience_required": {"duration": ["minimum 2-3 years"], "field": ["food", "relevant experience"]}}, {"job_id": "100003009052342", "location_code": "hk", "company": "Chinese Pharmaceuticals (HK) Co., Limited", "job_title": "Purchasing clerk / executive", "description": "Responsibilities:\n\nPerform day-to-day merchandising duties, includes handling orders from sample development to bulk delivery.\nAble to work independently with local clients\nAble to handle customer inquiries including fabrics sourcing, sample arrangement, product development, and price quotation.\nResearch and link up with new customers and explore business opportunities in the markets.\n\nRequirements:\n\nAt least 3 years relevant working experience in the garment industry\u00a0\nGood command of written and spoken English, Mandarin, and Cantonese.\nMature, self-motivated, target-oriented, and good analytical mind.\nGood communication, negotiation, and problem-solving skills.", "employment_types": ["Full Time"], "selling_points": [], "locations": ["Kwun Tong"], "categories": ["Admin & HR", "Clerical / Admin Staff", "Merchandising & Purchasing", "Others", "Procurement / Purchasing / Sourcing"], "post_time": "2022-01-17T16:20:57Z", "salary": {"currency": null, "max": null, "min": null, "period": "monthly", "term": null}, "salary_visible": false, "title_keywords": ["executive", "purchasing clerk"], "responsibilities": ["business opportunities", "quotation", "merchandising", "customer inquiries"], "requirements": {"degrees": [], "majors": [], "languages": ["cantonese", "english", "mandarin"], "language_level": ["good command"], "hard_skills": ["garment industry", "problem-solving skills"], "soft_skills": ["self-motivated", "negotiation", "mature", "communication", "analytical mind", "problem-solving skills"], "languages_combined": [{"language": "cantonese", "language_level": ["good command"]}, {"language": "english", "language_level": ["good command"]}, {"language": "mandarin", "language_level": ["good command"]}]}, "experience_required": {"duration": ["at least 3 years"], "field": ["garment", "relevant working experience"]}}, {"job_id": "100003009051777", "location_code": "hk", "company": "Citistore (Hong Kong) Limited", "job_title": "Merchandising Assistant", "description": "Key Responsibilities\n\nSupport daily operations in merchandising team to ensure smooth order processing and on-time delivery.\nAssist offer preparation and follow up from order placement until shipment for all purchased products.\nFacilitate effective communication with internal and external stakeholders such as German headquarters, suppliers, quality department and logistics department.\nEnsure order, costing and vendor information are recorded in appointed systems accurately and timely.\nWork closely with Quality Assurance team to meet company\u2019s quality requirements.\n\n\n\nJob Requirements\n\nBachelor\u2019s degree in a business-related subject is preferred but also other proficiencies are welcomed.\nExperience in merchandising positions or in a sourcing office is preferred. Fresh graduates are also welcomed to apply.\nEager to learn more about international trade business and ability to work in cross-cultural teams.\nAttention to details, a positive work attitude, structured, and able to organize multi-task is crucial.\nGood command of both written and spoken English and Chinese (Cantonese and Mandarin) is a must.\nGood computer knowledge (Microsoft office).\nImmediately available is preferable.\nFlexible to have business travel when required.\n\nIf you are interested in the position, please submit your full resume with cover letter, current and expected salary and available date via JobsDB.\n\nAll\u00a0personal information is collected for recruitment purpose only and will be treated in strict confidentiality.\u00a0\u00a0", "employment_types": ["Full Time", "Permanent"], "selling_points": ["Degree holder in related discipline", "Administrative support to merchandising team", "Immediate available is preferred"], "locations": ["Tsuen Wan Area"], "categories": ["Merchandising & Purchasing", "Sundries", "Others", "Procurement / Purchasing / Sourcing"], "post_time": "2022-01-17T01:03:24Z", "salary": {"currency": null, "max": null, "min": null, "period": "monthly", "term": null}, "salary_visible": false, "title_keywords": ["merchandising assistant"], "responsibilities": ["systems", "quality", "merchandising", "communication", "daily operations", "logistics", "order processing"], "requirements": {"degrees": ["degree", "bachelor"], "majors": ["business"], "languages": ["cantonese", "english", "chinese", "mandarin"], "language_level": ["good command"], "hard_skills": ["microsoft office"], "soft_skills": ["flexible", "multi-task", "interested in", "eager to learn", "attention to details", "structured", "positive work attitude"], "languages_combined": [{"language": "cantonese", "language_level": ["good command"]}, {"language": "english", "language_level": ["good command"]}, {"language": "chinese", "language_level": ["good command"]}, {"language": "mandarin", "language_level": ["good command"]}]}, "experience_required": {"duration": [], "field": ["merchandising"]}}, {"job_id": "100003009056081", "location_code": "hk", "company": "Wellcome", "job_title": "Category Executive - Wellcome", "description": "Responsibilities:\n- Handle purchase orders and follow up with suppliers on delivery schedule;\n- Carry out administrative work and clerical support for the department;\n- Handle other ad hoc project as assigned\n\nRequirements:\n- Higher Diploma or above;\n- 1-2 years of working experience in supplement or beauty is preferred;\n- Detail oriented with good numeric sense and strong negotiation and analytical skills;\n- Able to work under pressure with good multi-tasking skills;\n- Good command of written and spoken English and Chinese;\n- Proficiency in MS Office, including MS Word, MS Excel;\n- Immediate available is highly preferred", "employment_types": ["Permanent"], "selling_points": ["FMCG merchandising", "Product category management", "1 year of relevant experience in buying"], "locations": ["Quarry Bay"], "categories": ["Merchandising & Purchasing", "Others"], "post_time": "2022-01-18T03:15:19Z", "salary": {"currency": null, "max": null, "min": null, "period": "monthly", "term": null}, "salary_visible": false, "title_keywords": ["executive"], "responsibilities": ["ad hoc", "administrative work", "clerical support", "delivery schedule", "purchase"], "requirements": {"degrees": ["higher diploma or above"], "majors": [], "languages": ["english", "chinese"], "language_level": ["good command"], "hard_skills": ["ms word", "ms excel", "ms office", "analytical skills"], "soft_skills": ["negotiation", "detail oriented", "analytical skills", "multi-tasking skills", "work under pressure"], "languages_combined": [{"language": "english", "language_level": ["good command"]}, {"language": "chinese", "language_level": ["good command"]}]}, "experience_required": {"duration": ["1-2 years"], "field": ["beauty"]}}, {"job_id": "100003009054046", "location_code": "hk", "company": "Smith & Associates Far East Ltd", "job_title": "Logistics Coordinator/ Operation Admin Support", "description": "KEY RESPONSIBILITIES:\n\nContact supplier to consolidate product and promotion information\nHandle price and promotion setup\nPrepare sales report and work out presentation file\nProvide general administrative support to the team\nAssist in ad-hoc duties as per assigned\n\n\u00a0JOB REQUIREMENTS:\n\nBachelor\u2019s Degree holder or above\nAt least 1 year of retail buying experience\nSelf-motivated, energetic, well-organized and able to work under pressure\nGood communication skills and good command of spoken & written English and Chinese\nProficiency in PC knowledge; familiar with Excel & Chinese Word\nImmediate available is highly preferred\n\nAn attractive remuneration package together with fringe benefits will be offered to the right candidate.\u00a0\u00a0Interested parties are invited to send your full resume with current and expected salary\u00a0by clicking \"Apply Now\".\n\nPersonal data collected will be used for recruitment purpose only.", "employment_types": ["Full Time", "Permanent"], "selling_points": ["Well established MNC", "Nice Warehouse Environment", "Stable and friendly work environment"], "locations": ["Kowloon Bay"], "categories": ["Transportation & Logistics", "Shipping", "Supply Chain", "Merchandising & Purchasing", "Others"], "post_time": "2022-01-17T08:12:02Z", "salary": {"currency": null, "max": null, "min": null, "period": "monthly", "term": null}, "salary_visible": false, "title_keywords": ["admin", "logistics coordinator"], "responsibilities": ["general administrative support", "prepare sales", "contact", "ad-hoc duties", "setup", "report"], "requirements": {"degrees": ["bachelor", "degree holder"], "majors": [], "languages": ["english", "chinese"], "language_level": ["good command", "good"], "hard_skills": ["excel", "pc knowledge", "word"], "soft_skills": ["communication skills", "self-motivated", "well-organized", "energetic", "work under pressure"], "languages_combined": [{"language": "english", "language_level": ["good command", "good"]}, {"language": "chinese", "language_level": ["good command", "good"]}]}, "experience_required": {"duration": ["at least 1 year"], "field": ["retail"]}}, {"job_id": "100003009055409", "location_code": "hk", "company": "initial Fashion Co Limited", "job_title": "Merchandiser (Ladieswear)", "description": "The Job\n\nAssist Category Manager to manage the assigned product category\nArrange logistic, stocks allocation and return of purchased products\nCoordinate with vendors to implement promotion plan, promotional display for stores\nMaintain records of business transactions and product inventories control\nBuild good relationship with internal departments to facilitate smooth operations\nSupport team to prepare categories sales analysis and system data maintenance\nProvide routine administrative support i.e new vendor/new item creation, follow up of item launching and promotion plan etc\n\nThe Person\n\nDegree or above in Business related disciplines\nMinimum 1 year of relevant experience in buying\nPassionate about retail, food products and sales driven\nProficient in MS Office and Chinese Word Processing\nHigh accuracy in data input\nGood command of both spoken and written English & Chinese\nGood interpersonal skills\nImmediate availability is preferred", "employment_types": ["Full Time", "Permanent"], "selling_points": ["To take initiate to search for new fabric", "Have daily communication with designers & vendor", "Minimum 3 years' relevant experience"], "locations": ["Kwun Tong"], "categories": ["Merchandising & Purchasing", "Sweater", "Woven / Knit", "Others"], "post_time": "2022-01-18T02:29:22Z", "salary": {"currency": null, "max": null, "min": null, "period": "monthly", "term": null}, "salary_visible": false, "title_keywords": ["merchandiser"], "responsibilities": ["control", "maintenance", "administrative support", "operations", "analysis", "coordinate with", "transactions", "system data", "good relationship", "maintain", "plan"], "requirements": {"degrees": ["degree or above"], "majors": ["related disciplines", "business"], "languages": ["english", "chinese"], "language_level": ["good command", "proficient"], "hard_skills": ["chinese word processing", "ms office"], "soft_skills": ["interpersonal skills", "driven", "passionate about"], "languages_combined": [{"language": "english", "language_level": ["good command"]}, {"language": "chinese", "language_level": ["good command", "proficient"]}]}, "experience_required": {"duration": ["minimum 1 year"], "field": ["relevant experience"]}}, {"job_id": "100003009054032", "location_code": "hk", "company": "NEC Hong Kong Limited", "job_title": "Purchasing Officer", "description": "Key Responsibilities\n\nUnload all inbound shipments from carriers, open boxes and place shipments in bins\nPerform order verification process. Identify and verify Purchase Order information and determine if there is a Sales Order associated with the product\nTo ensure all shipments coming inbound and going outbound move as quickly as possible and are delivered within their schedule\nTo ensure all shipments are proactively expedited through customs and are imported in accordance with customs compliance\nUtilize delivery systems, i.e. UPS, FEDEX, DHL, TNT, or Freight Forwarders, to ship product worldwide\nTo proactively research missing freight and file claim if needed\nTo provide timely international and domestic quotes for any Smith & Associates or Consignment shipment at a minimum cost where service is not jeopardized\nWhen needed, move shipments as quickly as possible (next flight outs, hot shots, drop shipments, etc.)\nAssist with other projects as necessary.\nProvide office administrative, clerical support when needed\n\nRequirements\n\nForm 7 or above with 2-3 years' working experience\nWritten and spoken Cantonese, Mandarin and English\nCommunication, negotiation, multi-tasking and problem solving skills\nMature, detail-orientated, team player and able to work under pressure", "employment_types": ["Full Time"], "selling_points": ["Order input, prepare invoice", "Prepare the monthly report", "5-day work, Hunghom Station"], "locations": ["Hung Hom"], "categories": ["Admin & HR", "Clerical / Admin Staff", "Merchandising & Purchasing", "Others", "Sales, CS & Business Devpt", "Sales Administration"], "post_time": "2022-01-17T08:08:25Z", "salary": {"currency": null, "max": null, "min": null, "period": "monthly", "term": null}, "salary_visible": false, "title_keywords": ["purchasing officer"], "responsibilities": ["cost", "compliance", "systems", "clerical support", "purchase", "schedule"], "requirements": {"degrees": [], "majors": [], "languages": ["cantonese", "english", "mandarin"], "language_level": [], "hard_skills": ["problem solving skills"], "soft_skills": ["negotiation", "mature", "communication", "multi-tasking", "team player", "problem solving skills", "work under pressure"], "languages_combined": [{"language": "cantonese", "language_level": []}, {"language": "english", "language_level": []}, {"language": "mandarin", "language_level": []}]}, "experience_required": {"duration": ["2-3 years"], "field": []}}, {"job_id": "100003009053046", "location_code": "hk", "company": "Lauris Walton International Limited", "job_title": "Merchandising Assistant / Merchandiser / Product Assistant - Urgent Hire - MNC - Work Life Balance", "description": "Responsibilities\u00a0\u00a0\nFollow up costing, sample development, bulk production and ensure high quality of output\nWork closely with Design team, Buying team and Vendors to ensure the whole merchandising procedures are in timely manner\nPrepare quotations and details for buy meeting\nAttend fitting session and follow up all designers' fit comments with vendors\nControl cost sheets and conduct negotiation with vendors for getting competitive prices\nManage product development till bulk production in line with buy calendar\nDay to day communication with factories for tracking production & delivery schedule without delay\nRequirements\nDiploma in Fashion, Clothing & Textile or related discipline preferable\nMinimum 3 years' solid experience in Garment items\nStrong fashion sense, detail minded, well organized and strong sense of responsibility\nGood communication, interpersonal and negotiation skills\nGood command of written and spoken English, Mandarin and Cantonese\nProficiency in MS Word, Excel and Chinese Word Processing\nWe are looking for candidates who have forward-looking vision, creative, energetic and strong fashion sense candidate. We offer the good development as well as regional and local career advancement opportunities.\nWe are a Hong Kong-based fashion label, established in 2000. We are now have business presence in Hong Kong, Macau and the Chinese Mainland.\u00a0We create a culture rather than just a piece of clothing.\u00a0 Unlike the usual practices of branding that are normally seen in the consumer goods industry, the branding philosophy in the fashion and lifestyle goods industry is unique and personality based, we bring \u201cThe Unusual Experience\u201d to our customers.\n\n\nInterested parties please send your resume with expected salary to Human Resources Department via email by clicking \"Apply Now\".\nPlease visit our company website at http://www.initialfashion.com for company information.\n\n\nAll information received will be treated in strict confidence and for recruitment purpose only.", "employment_types": ["Full Time", "Permanent"], "selling_points": [], "locations": ["Central"], "categories": ["Admin & HR", "Others", "Merchandising & Purchasing", "Others", "Procurement / Purchasing / Sourcing"], "post_time": "2022-01-17T05:21:59Z", "salary": {"currency": null, "max": null, "min": null, "period": "monthly", "term": null}, "salary_visible": false, "title_keywords": ["merchandiser", "product assistant", "merchandising assistant"], "responsibilities": ["control", "cost", "comments", "merchandising", "quality", "design", "procedures", "communication", "delivery schedule", "tracking"], "requirements": {"degrees": ["diploma"], "majors": [], "languages": ["cantonese", "english", "chinese", "mandarin"], "language_level": ["proficiency", "good command"], "hard_skills": ["excel", "chinese word processing", "ms word"], "soft_skills": ["sense of responsibility", "well organized", "communication", "negotiation skills", "energetic", "creative", "interpersonal"], "languages_combined": [{"language": "cantonese", "language_level": ["good command"]}, {"language": "english", "language_level": ["good command"]}, {"language": "chinese", "language_level": ["proficiency"]}, {"language": "mandarin", "language_level": ["good command"]}]}, "experience_required": {"duration": ["minimum 3 years"], "field": ["garment"]}}, {"job_id": "100003009051683", "location_code": "hk", "company": "Special Happy Limited", "job_title": "Merchandiser / Junior Merchandiser", "description": "Responsibilities:\n\nProvide full range administration support, including order input, delivery arrangement and invoice preparation in Oracle system.\nWork closely with internal and external customer for daily work of purchasing and business control.\nPrepare the monthly report.\nHandle ad hoc projects as assigned.\n\nRequirements:\n\nHigher Diploma or above with 4 years' relevant working experiences;\nExperience and knowledge in Oracle System is an advantage;\nExcellent communication and inter-personal skills;\nGood command of both written and spoken of Chinese and English;\nImmediate available is preferable.\nPlease send your full detailed resume with expected salary and date available to The Human Resources Manager, NEC Hong Kong Limited, 25th Floor, The Metropolis Tower, 10 Metropolis Drive, Hunghom, Kowloon or by e-mail.\n\n\nPersonal data provided by job applicant will be used strictly in accordance with employer's personal data policy, a copy of which will be provided immediately upon request.", "employment_types": ["Full Time", "Permanent"], "selling_points": [], "locations": ["Tsuen Wan Area"], "categories": ["Merchandising & Purchasing", "Sundries", "Others", "Others", "Trading"], "post_time": "2022-01-16T21:50:45Z", "salary": {"currency": null, "max": null, "min": null, "period": "monthly", "term": null}, "salary_visible": false, "title_keywords": ["merchandiser", "junior merchandiser"], "responsibilities": ["control", "invoice", "ad hoc projects", "monthly report", "administration"], "requirements": {"degrees": ["higher diploma or above"], "majors": [], "languages": ["english", "chinese"], "language_level": ["good command"], "hard_skills": ["oracle system"], "soft_skills": ["communication", "inter-personal skills", "detailed"], "languages_combined": [{"language": "english", "language_level": ["good command"]}, {"language": "chinese", "language_level": ["good command"]}]}, "experience_required": {"duration": ["4 years"], "field": []}}, {"job_id": "100003009053297", "location_code": "hk", "company": "Loyal Trade Limited", "job_title": "Clerk / Assistant Merchandiser / Merchandiser", "description": "Degree holder or at least 1 year relevant experience\nArrangement of samples, costing and follow up orders\nProactive & independent, aggressive & capable to cooperate with a team\nGood command of English & Mandarin\nAbility to work independently with overseas customers\nTo be responsible, hardworking and willing to work under pressure\nLess experience will consider to assist Merchandisers on paper work\n\n\nInterested parties, please apply by click Apply Now\n\nPersonal data will be used for recruitment purpose only.\n", "employment_types": ["Full Time"], "selling_points": [], "locations": ["Kwai Hing"], "categories": ["Admin & HR", "Clerical / Admin Staff", "Merchandising & Purchasing", "Others", "Procurement / Purchasing / Sourcing"], "post_time": "2022-01-17T06:43:22Z", "salary": {"currency": null, "max": null, "min": null, "period": "monthly", "term": null}, "salary_visible": false, "title_keywords": ["merchandiser", "clerk", "assistant merchandiser"], "responsibilities": ["follow up orders", "cooperate with", "work under pressure"], "requirements": {"degrees": ["degree holder"], "majors": [], "languages": ["english", "mandarin"], "language_level": ["good command"], "hard_skills": [], "soft_skills": ["work independently", "independent", "capable", "responsible", "proactive", "hardworking", "work under pressure"], "languages_combined": [{"language": "english", "language_level": ["good command"]}, {"language": "mandarin", "language_level": ["good command"]}]}, "experience_required": {"duration": ["at least 1 year"], "field": ["relevant experience"]}}, {"job_id": "100003009055888", "location_code": "hk", "company": "Randstad Hong Kong Limited", "job_title": "Merchandise Assistant - Fresh Grad Welcome", "description": "Requirements:\n\n-\u00a0\u00a0\u00a0\u00a0\u00a0\u00a0\u00a0 F.5 / DSE or above education\n\n-\u00a0\u00a0\u00a0\u00a0\u00a0\u00a0\u00a0 1-2 years relevant working experience in Artificial Flowers and Christmas items. (Candidate with less experience will be considered as Clerk or Assistant Merchandiser)\n\n-\u00a0\u00a0\u00a0\u00a0\u00a0\u00a0\u00a0 Fresh graduate will be also considered\n\n-\u00a0\u00a0\u00a0\u00a0\u00a0\u00a0\u00a0 Good command of written and spoken English, Cantonese and Mandarin\n\n-\u00a0\u00a0\u00a0\u00a0\u00a0\u00a0\u00a0 Strong communication, interpersonal and analytical skills\n\n-\u00a0\u00a0\u00a0\u00a0\u00a0\u00a0\u00a0 Proficiency in PC skills\n\n-\u00a0\u00a0\u00a0\u00a0\u00a0\u00a0\u00a0 Require to travel to China periodically\n\n-\u00a0\u00a0\u00a0\u00a0\u00a0\u00a0\u00a0 Immediate available is preferable\n\nWe offer bank holidays and medical allowance etc. to the right candidates.", "employment_types": ["Full Time", "Permanent"], "selling_points": ["Fresh Grad Welcome", "US Sourcing Office", "Fortune 500 Company"], "locations": ["Not Specified"], "categories": ["Merchandising & Purchasing", "Others", "Procurement / Purchasing / Sourcing"], "post_time": "2022-01-18T03:03:18Z", "salary": {"currency": "HKD", "max": 19999, "min": 17000, "period": "monthly", "term": null}, "salary_visible": true, "title_keywords": ["assistant"], "responsibilities": ["communication"], "requirements": {"degrees": ["fresh graduate", "dse"], "majors": [], "languages": ["cantonese", "english", "mandarin"], "language_level": ["good command"], "hard_skills": ["pc skills", "analytical skills"], "soft_skills": ["communication", "interpersonal", "analytical skills"], "languages_combined": [{"language": "cantonese", "language_level": ["good command"]}, {"language": "english", "language_level": ["good command"]}, {"language": "mandarin", "language_level": ["good command"]}]}, "experience_required": {"duration": ["1-2 years"], "field": ["relevant working experience"]}}, {"job_id": "100003009053510", "location_code": "hk", "company": "Bape Hong Kong Limited", "job_title": "Buying Assistant - Aape", "description": "about the company.\n\nOur client is a well-known US Sourcing Office with a fun and dynamic working culture. They have over 300,000 employees over the world and 5,000 stores in their portfolio. With their growing business, they are looking for an Merchandising Assistant for their Home team. Fluency in English is a must. Fresh Grad welcome.\nabout the job.\nMananage the assigned category through precise executive of process\nFollow up orders with suppliers/ factories to ensure on-time delivery\nProvide support in sample handling, prepare the quotation for buyer evaluation\nMaintain strong business partnership with suppliers\nProvide support to team leader\nskills & experiences required.\nUniversity graduate in Merchandising, Business or related discipline\nSmart, motivated and independent\nExcellent communication and interpersonal skills\nGood command of English Cantonese and Mandarin\nabout the package.\n\n5 days work\nMedical and Dental\nDiscretionary Bonus\nFast Track Promotion\nIf you're interested in this role, click 'apply now' or email cecilia.ng@randstad.com.hk to forward an up-to-date copy of your CV, or call Cecilia NG at 2232 3444. If this is not your ideal job but you are looking out, please contact us for a discussion on your career preferences.", "employment_types": ["Full Time"], "selling_points": ["1-2 years of working experience in buying", "Assist OTB planning, sell through, mark down", "Prepare merchandising reports"], "locations": ["Southern Area"], "categories": ["Merchandising & Purchasing", "Textiles", "Others", "Procurement / Purchasing / Sourcing"], "post_time": "2022-01-17T07:04:30Z", "salary": {"currency": null, "max": null, "min": null, "period": "monthly", "term": null}, "salary_visible": false, "title_keywords": ["buying assistant"], "responsibilities": ["follow up orders", "provide support", "quotation", "merchandising", "communication", "business partnership", "maintain", "contact", "evaluation"], "requirements": {"degrees": ["university graduate"], "majors": ["business"], "languages": ["cantonese", "english", "mandarin"], "language_level": ["fluency", "good command"], "hard_skills": ["dynamic", "fun"], "soft_skills": ["independent", "interested in", "dynamic", "motivated", "communication and interpersonal skills", "precise", "ideal"], "languages_combined": [{"language": "cantonese", "language_level": ["good command"]}, {"language": "english", "language_level": ["fluency", "good command"]}, {"language": "mandarin", "language_level": ["good command"]}]}, "experience_required": {"duration": [], "field": []}}, {"job_id": "100003009051249", "location_code": "hk", "company": "Chu Kong Optical Mfy Ltd", "job_title": "Shipping Assistant / Operations Officer", "description": "Accountabilities \u2013 Key Result Areas\n\n\n\nAssist buying team in execute buying activities, stock planning and allocation, and merchandise delivery and reordering situations to meet company business objectives\nPrepare merchandising reports for management review on business performance and inventory turn\nAssist OTB planning, sell through, mark down logistics\nWork closely with production and sourcing team to ensure the smooth flow of merchandise delivery\nWork with marketing and retail teams in regard to speedy response to market dynamics and promotions\n\nExperience / Qualification Requirements\n\n\nDegree holder in Fashion & Textiles or business discipline\nWith 1-2 years of experience in\u00a0buying and merchandising, preferably in the fashion / lifestyle / retail industry\nProactive, sensitive to figures and strong analytical and negotiation skills\nAdequate product sensibility and understanding of competitive retail landscape\nAttention to detail with high level of accuracy\n\nCompetitive remuneration and benefit package will be offered to the right candidate. Please submit your application by clicking \"Apply Now\" below.\n\n\n\nAll data collected is for recruitment purpose only.", "employment_types": ["Full Time"], "selling_points": ["5 days work", "Modern Office Environment", "FREE shuttle bus service provided"], "locations": ["Kwai Tsing Area"], "categories": ["Transportation & Logistics", "Shipping", "Manufacturing", "Manufacturing Management", "Merchandising & Purchasing", "Others"], "post_time": "2022-01-15T06:15:09Z", "salary": {"currency": null, "max": null, "min": null, "period": "monthly", "term": null}, "salary_visible": false, "title_keywords": ["operations officer", "shipping", "assistant"], "responsibilities": ["data", "inventory", "merchandising", "teams", "otb", "reports", "logistics", "recruitment", "stock planning", "management review", "planning"], "requirements": {"degrees": ["degree holder"], "majors": ["business"], "languages": [], "language_level": [], "hard_skills": [], "soft_skills": ["sensitive to figures", "negotiation skills", "attention to detail", "smooth", "proactive"], "languages_combined": []}, "experience_required": {"duration": ["1-2 years"], "field": ["retail industry", "merchandising"]}}, {"job_id": "100003009044488", "location_code": "hk", "company": "Shiamas Limited", "job_title": "Assistant Merchandiser", "description": "JOB DESCRIPTION:\n\nHandle customer orders and data input into system\nGeneral Sales order process incl. prepare Invoices & quotations\nUpdate the order status in the system and maintain the database\nTo provide sales administration support to Sales Team\nHandle full set of I/E documents and declaration\nHandle all transportation arrangement including ocean and air freight forwarding, as well as local transportation\nCoordinate with factories for cargo ready date and delivery\n\n\u00a0REQUIREMENTS:\n\nF.6 or above with 2 year\u00a0experience at manufacturing field, fresh graduate is also welcome\nFluency in spoken & written English, Mandarin & Cantonese\nProficient in\u00a0operating MS Office & Chinese Word Processing\nResponsible, self-motivated, independent and a good team player\n\nABOUT US:\n\n\nInformation for you to know more about us, please click >\u00a0COMPANY PROFILE\nOur newly renovation office will make your everyday work happier, please see >\u00a0NEW OFFICE\nOur office is near Kwai Fong MTR station with\u00a0FREE\u00a0shuttle bus service provided.\nJoin us!\u00a0Immediate available is preferred\u00a0", "employment_types": ["Full Time"], "selling_points": ["Diploma holder in Purchasing or equivalent", "At least 2 years\u2019 relevant working experience", "Immediate available preferred"], "locations": ["Not Specified"], "categories": ["Merchandising & Purchasing", "Sundries", "Others", "Procurement / Purchasing / Sourcing"], "post_time": "2022-01-13T08:02:48Z", "salary": {"currency": null, "max": null, "min": null, "period": "monthly", "term": null}, "salary_visible": false, "title_keywords": ["assistant merchandiser"], "responsibilities": ["sales administration", "invoices", "air freight", "coordinate with", "data input", "maintain", "sales team", "database"], "requirements": {"degrees": ["fresh graduate"], "majors": ["manufacturing"], "languages": ["cantonese", "english", "chinese", "mandarin"], "language_level": ["fluency", "proficient"], "hard_skills": ["make", "chinese word processing", "ms office"], "soft_skills": ["good team player", "self-motivated", "independent", "responsible"], "languages_combined": [{"language": "cantonese", "language_level": ["fluency"]}, {"language": "english", "language_level": ["fluency"]}, {"language": "chinese", "language_level": ["proficient"]}, {"language": "mandarin", "language_level": ["fluency"]}]}, "experience_required": {"duration": ["2 year"], "field": ["manufacturing"]}}, {"job_id": "100003009049933", "location_code": "hk", "company": "Sportshouse Limited", "job_title": "Buyer", "description": "Job Responsibilities:\n\nTo Assist Merchandising Manager in day-to-day operations\nIssue and follow up purchase orders and arrange delivery\nCheck system PO and supplier invoices and follow up with Accounts Team & Suppliers\nProvide clerical support to the team e.g. data entry, housekeep purchase database and documents\nPrepare regular reports regarding analyzing the sales and suggestion to stock replenishment\nNegotiate with suppliers to achieve competitive prices and terms\nPlan and coordinate sales promotion activities\nPerform other ad hoc duties as assigned\u00a0\n\nJob Requirements:\n\nDiploma holder in Purchasing or equivalent\nPossess with at least 2 years\u2019 relevant working experience in merchandising/supply chain field, preferably retail/accessory business\nDetail-minded, self-motivated, well-organized, good team player\nGood command of both spoken and written English, Cantonese and Mandarin\nProficiency in MS Office applications \u2013 Excel, Word, PowerPoint and Chinese Word Processing (especially at Excel e.g. Pivot Table, vlookup)\nImmediate available preferred\u00a0\n\nWe offer 5-day working week, attractive remuneration package, benefits and good prospect of career opportunities to the right candidate. \u00a0To apply, please email detailed resume with expected salary to", "employment_types": ["Full Time", "Permanent"], "selling_points": ["Responsible for performing market research", "Products sourcing & sell-thru analysis", "Degree holder or above"], "locations": ["Tsuen Wan Area"], "categories": ["Merchandising & Purchasing", "Textiles", "Others", "Procurement / Purchasing / Sourcing"], "post_time": "2022-01-14T09:27:47Z", "salary": {"currency": null, "max": null, "min": null, "period": "monthly", "term": null}, "salary_visible": false, "title_keywords": [], "responsibilities": ["provide clerical support", "ad hoc duties", "stock replenishment", "invoices", "data entry", "day-to-day operations", "merchandising", "plan and coordinate", "purchase", "reports", "database"], "requirements": {"degrees": ["diploma holder"], "majors": [], "languages": ["cantonese", "english", "chinese", "mandarin"], "language_level": ["proficiency", "good command"], "hard_skills": ["excel", "chinese word processing", "pivot table", "word", "powerpoint", "vlookup", "ms office"], "soft_skills": ["detail-minded", "good team player", "self-motivated", "well-organized"], "languages_combined": [{"language": "cantonese", "language_level": ["good command"]}, {"language": "english", "language_level": ["good command"]}, {"language": "chinese", "language_level": ["proficiency"]}, {"language": "mandarin", "language_level": ["good command"]}]}, "experience_required": {"duration": ["at least 2 years"], "field": ["supply chain", "merchandising", "relevant working experience", "business", "retail"]}}, {"job_id": "100003008980854", "location_code": "hk", "company": "Shun Lee Building Materials and Sanitary Wares Ltd", "job_title": "Project Sales Coordinator", "description": "Responsibilities:\n\nResponsible for performing market research on the up-coming fashion trend;\nAssemble and execute plans for seasonal brand assortment and OTB in order to meet the company\u2019s business objective;\nProducts sourcing and sell-thru analysis;\nLiaise with suppliers on order placing efficiency and ensure appropriate levels of stock of designated product categories are maintained;\nAllocate merchandises and coordinate with shops and warehouse to smooth the stock replenishment issue;\nWork closely with operations, visual merchandising team and other counterparts to maximize sales performance of responsible category;\nCultivate and maintain partnership relationship with suppliers\n\nRequirements:\n\nBachelor\u2019s degree holder\nMin. 4 years\u2019 apparel / footwear buying experience\nSolid experience in branded merchandise buying, store replenishment, merchandise consolidation and product management is a must\nStrong business sense with excellent negotiation, interpersonal, numerical and analytical skills\nFluent in spoken and written English, Chinese and Mandarin\nProficient in MS Excel (Pivot Table, VLookup and other formula functions)\nWilling to travel\nCandidate with less experience will be considered as Assistant Buyer\n\nInterested parties please\u00a0send your resume with current and expected salary\u00a0by clicking\u00a0\"Apply Now\".\n\n\nData collected will be used for recruitment purpose only.\n\nFor company information, please visit our website www.sportshouse.com.hk", "employment_types": ["Full Time", "Permanent"], "selling_points": [], "locations": ["Lai Chi Kok"], "categories": ["Admin & HR", "Secretary", "Merchandising & Purchasing", "Others", "Sales, CS & Business Devpt", "Sales Administration"], "post_time": "2022-01-16T21:50:05Z", "salary": {"currency": null, "max": null, "min": null, "period": "monthly", "term": null}, "salary_visible": false, "title_keywords": ["sales coordinator"], "responsibilities": ["product categories", "stock replenishment", "operations", "analysis", "sales performance", "coordinate with", "market research", "merchandising", "otb", "maintain", "visual", "plans", "liaise with suppliers"], "requirements": {"degrees": ["bachelor", "degree holder"], "majors": [], "languages": ["english", "chinese", "mandarin"], "language_level": ["fluent"], "hard_skills": ["pivot table", "ms excel", "vlookup", "analytical skills"], "soft_skills": ["interpersonal", "negotiation", "analytical skills", "business sense"], "languages_combined": [{"language": "english", "language_level": ["fluent"]}, {"language": "chinese", "language_level": ["fluent"]}, {"language": "mandarin", "language_level": ["fluent"]}]}, "experience_required": {"duration": ["4 years"], "field": ["product management", "consolidation"]}}, {"job_id": "100003009050984", "location_code": "hk", "company": "Vocational Training Council", "job_title": "Officer (Supplies)", "description": "Responsibilities:\n\nAssist Project Sales Team on order management\nHandle sales documents such as quotations, purchasing orders, sales invoices and delivery notes\nManage the distribution of inventory control\nLiaise with customers and logistic parties\nFollow up shipping schedule, delivery and outstanding payment\nProvide administrative support to the team and perform ad hoc duties as assigned\n\nRequirements:\n\nDiploma or above in any discipline\n1-2 years relevant working experience on sales administration or related field\nGood communication skills and interpersonal skills\nGood command of written and spoken English, Chinese and Putonghua\nProficient in MS Word, Excel, PowerPoint and Chinese Word Processing\nSelf-motivated, well-organized, able to work under pressure and willing to work overtime\nImmediate available is an advantage\nCandidate with more experience will be considered as Sales Administrator\n\nWe offer a 5-day work week, competitive salary, attractive commission, discretionary performance bonus, medical benefits, marriage leave, compassionate leave, staff purchase discount and excellent career prospects.\n\nInterested parties please send your application letter and full resume with current / expected salary and availability to Human Resources Department by clicking APPLY NOW.\n\n\nFor more information about our Company, please visit our website at\u00a0https://shunlee.com.hk\u00a0\n\u00a0\nInformation collected will be treated in strict confidence and only be used for recruitment purpose.", "employment_types": ["Full Time"], "selling_points": ["Assist in development and implementation", "A recognised degree preferably in Purchasing", "At least two years\u2019 relevant work experience"], "locations": ["Not Specified"], "categories": ["Merchandising & Purchasing", "Others", "Procurement / Purchasing / Sourcing"], "post_time": "2022-01-17T06:00:29Z", "salary": {"currency": null, "max": null, "min": null, "period": "monthly", "term": null}, "salary_visible": false, "title_keywords": ["officer"], "responsibilities": ["shipping schedule", "ad hoc duties", "order management", "invoices", "payment", "inventory control", "sales team", "liaise with", "provide administrative support"], "requirements": {"degrees": ["diploma or above"], "majors": [], "languages": ["putonghua", "english", "chinese"], "language_level": ["good command", "proficient"], "hard_skills": ["excel", "chinese word processing", "powerpoint", "ms word"], "soft_skills": ["communication skills", "self-motivated", "work overtime", "well-organized", "interpersonal skills", "work under pressure"], "languages_combined": [{"language": "putonghua", "language_level": ["good command"]}, {"language": "english", "language_level": ["good command"]}, {"language": "chinese", "language_level": ["good command", "proficient"]}]}, "experience_required": {"duration": ["1-2 years"], "field": ["related", "sales administration", "relevant working experience"]}}, {"job_id": "100003009051979", "location_code": "hk", "company": "", "job_title": "Assistant Merchandiser", "description": "Ref. no :\u00a0C/VOU/OFF(SUPP)/11/21-AP2\n\u00a0\nMajor Duties:\n(a)\n\u00a0 \u00a0\u00a0 \u00a0To administer procurement operations including issue and acceptance of purchase orders / tenders, sourcing, contract monitoring, orders / tenders and contract negotiations;\n(b) \u00a0\u00a0 \u00a0To assist and coordinate Supplies team to ensure efficient and effective supplies service deliveries;\n(c)\n\u00a0 \u00a0\u00a0 \u00a0To supervise subordinates for provision of quality, professional procurement and supplies services, including integrity and ethics;\n(d) \u00a0\u00a0 \u00a0To offer professional advice / guidance to users on procurement and supplies matters;\n(e) \u00a0\u00a0 \u00a0To implement procurement policies, and conduct periodic review where necessary;\n(f) \u00a0\u00a0 \u00a0To help maintain operations of computerised procurement and supplies systems effectively;\n(g) \u00a0\u00a0 \u00a0To coordinate stock-taking and supervise the data maintenance of the inventory management system; and\n(h) \u00a0\u00a0 \u00a0To assist in development and implementation of projects as assigned.\n\u00a0\nRequirements:\n(a)\n\u00a0 \u00a0\u00a0 \u00a0A recognised degree preferably in Purchasing and Supply Management, Supply Chain Management, Business Administration or equivalent;\n(b) \u00a0\u00a0 \u00a0At least two years\u2019 relevant work experience, preferably in sizeable or comparable organisations;\n(c) \u00a0\u00a0 \u00a0Proficiency in Microsoft Office Software and computerised accounting / purchasing systems;\n(d) \u00a0\u00a0 \u00a0Good negotiation, problem-solving, time management, interpersonal and communication skills;\n(e) \u00a0\u00a0 \u00a0Good team spirit, be proactive and able to work independently under pressure; and\n(f) \u00a0\u00a0 \u00a0Good command of English and Chinese.\n\u00a0\nNotes:\n(1) \u00a0\u00a0 \u00a0Shortlisted candidates may be required to attend a written test in English.\n(2) \u00a0\u00a0 \u00a0The appointee may be required to perform duties outside normal office hours and in designated places as assigned.\n\nApplication Procedures:\nA completed application form [VTC-1 (Rev. 1/2018)], together with a full curriculum vitae, should be sent to the Human Resources Division, 18/F, VTC Tower, 27 Wood Road, Wanchai, Hong Kong.\u00a0 Please specify on the envelope the reference of the post being applied for.\n\u00a0\nClosing date for application:\u00a07 February 2022\n\n\u00a0Applicants not invited for interview within 10 weeks from the closing date may consider their applications unsuccessful.\n\u00a0\nThe Council reserves the right not to fill the post(s).\n\u00a0\nPersonal data collected will be used for recruitment purposes only. Information on unsuccessful candidates will normally be destroyed 12 months after the completion of the recruitment exercise.", "employment_types": ["Full Time", "Permanent"], "selling_points": [], "locations": ["Hung Hom"], "categories": ["Merchandising & Purchasing", "Sundries", "Others", "Procurement / Purchasing / Sourcing"], "post_time": "2022-01-17T01:44:45Z", "salary": {"currency": null, "max": null, "min": null, "period": "monthly", "term": null}, "salary_visible": false, "title_keywords": ["assistant merchandiser"], "responsibilities": ["guidance", "maintenance", "data", "operations", "monitoring", "quality", "review", "systems", "coordinate", "inventory management", "purchase", "procurement policies", "maintain", "implementation of projects"], "requirements": {"degrees": ["degree"], "majors": ["business administration"], "languages": ["english", "chinese"], "language_level": ["good command"], "hard_skills": ["microsoft office software", "problem-solving", "c"], "soft_skills": ["communication skills", "work independently", "team spirit", "proactive", "negotiation", "under pressure", "perform duties", "problem-solving", "time management", "interpersonal"], "languages_combined": [{"language": "english", "language_level": ["good command"]}, {"language": "chinese", "language_level": ["good command"]}]}, "experience_required": {"duration": ["at least two years"], "field": []}}, {"job_id": "100003009051674", "location_code": "hk", "company": "\u6a13\u4e0a\u6709\u9650\u516c\u53f8 / HK JEBN LIMITED", "job_title": "Purchasing officer\uff0fPurchaser (Wine & Spirits, Frozen Food Global Sourcing)", "description": "Key Responsibilities :\n\nSupport the daily operations in CR team to ensure that social and environmental compliance programs are implemented.\nArrange and follow-up on BSCI or other social compliance audits and ensure the related records are maintained and updated.\nArrange and follow-up on environmental compliance audits & consulting, and ensure the related records are maintained and updated.\nSupport the implementation of company\u2019s corporate responsibility policy and the related compliance processes.\nSupport the execution of defined sustainability projects in cooperation with the Merchandising, Buying and Sustainability departments in Germany and respective service providers/business partners.\nEnsure the effective communication with internal stakeholders (such as merchandising team, quality, supply chain, packaging, etc.) on REWE Group\u2019s CR requirements and goals.\nSupport the team to execute continuous improvement projects in RFE to enhance the standard of social and environmental compliance and achieve the CR\u2019s goals.\nJob Requirements\u00a0:\n\nUniversity degree in Social Responsibility, Sustainability and Compliance, Business Administration, or related disciplines.\nMin. 1 years of working experience in a social compliance role.\nGood interpersonal and communication skills, be a team player in a cross-cultural working environment.\nSelf-motivated, detailed minded, and with good problem-solving skills.\u00a0\u00a0Independent, pro-active working style is required.\nKnowhow on BSCI & BEPI requirements and China labour legislation.\u00a0\u00a0Knowledge on the labour legislation in any other south-east Asia countries is preferable.\nKnowledge on social compliance standards such as BSCI, SA8000, ICTI, ETI, etc. is an advance.\nKnowledge on environmental compliance standards such as BEPI, ISO 14001, Detox, Higg, STeP, etc. is an advance.\nGood knowledge on MS Office, especially MS Excel (including pivot tables).\nGood command of both written and spoken English and Chinese (Cantonese and Mandarin) is a must.\nFlexible to have business travel when required.\n\nIf you are interested in the position, please submit your full resume with cover letter, current and expected salary and available date via JobsDB.\n\nAll personal information is collected for recruitment purpose only and will be treated in strict confidentiality.", "employment_types": ["Full Time"], "selling_points": ["5-day work, Free lunch, 12 day annual leave", "Birthday leave, Tai wai Area", "Worldwide Sourcing & Trading"], "locations": ["Shatin Area"], "categories": ["Merchandising & Purchasing", "Others"], "post_time": "2022-01-16T21:50:41Z", "salary": {"currency": null, "max": null, "min": null, "period": "monthly", "term": null}, "salary_visible": false, "title_keywords": [], "responsibilities": ["consulting", "compliance", "merchandising", "implementation", "quality", "communication", "daily operations", "audits"], "requirements": {"degrees": ["university degree"], "majors": ["related disciplines", "business administration"], "languages": ["cantonese", "english", "chinese", "mandarin"], "language_level": ["good command"], "hard_skills": ["problem-solving skills", "ms excel", "ms office"], "soft_skills": ["flexible", "communication skills", "self-motivated", "independent", "interested in", "pro-active", "problem-solving skills", "team player", "interpersonal", "detailed"], "languages_combined": [{"language": "cantonese", "language_level": ["good command"]}, {"language": "english", "language_level": ["good command"]}, {"language": "chinese", "language_level": ["good command"]}, {"language": "mandarin", "language_level": ["good command"]}]}, "experience_required": {"duration": ["1 years"], "field": ["compliance"]}}, {"job_id": "100003009054967", "location_code": "hk", "company": "GS Consultants Limited", "job_title": "Assistant Merchandise Manager / Senior Merchandiser (Max: 25K)", "description": "A MEDIUM SIZED EXPORT FIRM IN\u00a0HUNG HOM\u00a0REQUIRES:\n\n-\u00a0 F.6\u00a0 or above\u00a0\n- Quotation, Sampling and Orders follow up etc.\n- Handle customers enquire\n- English is required and Mandarin is preferred\n- PC knowledge (Ms office, Email) is required\n- Minimum 2-3 years working experience\n- 5-Day work week\n- Bank Holidays\n\n\u00a0For any enquiries,\u00a0 please \u00a0Call 2303-0343.\u00a0", "employment_types": ["Full Time", "Permanent"], "selling_points": ["Merchandising / Planning experience preferred", "MNC Culture", "Work from Home Policy"], "locations": ["Not Specified"], "categories": ["Marketing / Public Relations", "Marketing - General / Support", "Merchandising & Purchasing", "Handbag", "Others"], "post_time": "2022-01-17T16:10:26Z", "salary": {"currency": null, "max": null, "min": null, "period": "monthly", "term": null}, "salary_visible": false, "title_keywords": ["assistant merchandise", "manager", "senior merchandiser"], "responsibilities": ["quotation"], "requirements": {"degrees": [], "majors": [], "languages": ["english", "mandarin"], "language_level": [], "hard_skills": ["pc knowledge", "ms office"], "soft_skills": [], "languages_combined": [{"language": "english", "language_level": []}, {"language": "mandarin", "language_level": []}]}, "experience_required": {"duration": ["minimum 2-3 years"], "field": []}}, {"job_id": "100003009052732", "location_code": "hk", "company": "Descente China Investment Limited", "job_title": "Assistant Merchandiser", "description": "[Steam A: Certified WSET Level 3-4 student, English Speaking,\u00a0plus Native Cantonese]\n[Steam B: Global Food Sourcing\u00a0+ 3 years or above stated/lived in Europe]\n[Steam C: Certified\u00a0WSET Level 1-2 student, Frozen\u00a0Food Sourcing,\u00a0English Speaking,\u00a0plus Native Cantonese]\n\u00a0\nMain Duties:\nDevelop table\u00a0wine and spirits products, relevant frozen meat and seafood;\nAssess the quality of wine, sales and promotion planning, storage and logistic support, etc;\nAble to provide suggestion on food pairing with wine tasting;\nMeet overseas suppliers(Occasionally contact suppliers during overseas time zone);\nTravel to overseas(US, UK, Northern Europe, India, Southeast Asia, Australia, etc),source and audit new suppliers;\nHandle price negotiation in local market, cost comparison & analysis;\nMaintain weekly price update and promotion programs;\nAble to host, provide guiding and training to colleagues in internal wine tasting event;\nImportant:\u00a0Instead of related experience in the field, good intuitive and common senses are overwhelmingly important requirements for the above position. Candidate with multi-language skill is highly preferred (i.e. Good command in 3 or more languages: English / Mandarin / Japanese / Korean / etc.)\n\nOther duties of the above position are:\nAct as a sourcing & general support officer in purchasing department;\nHandle sourcing, price negotiation, payment terms, PO, Shipping Documents, order follow up as well as payment arrangement , etc;\nCommunicate between with suppliers and production teams;\nMaintain current product supply and ensure in stable quality;\nLiaise with factories for production schedule & quality checking;\nHandle shipping Documents, Delivery Control;\nInternal communication with warehouse for stock management, food quality control, etc;\n\u00a0\nRequirements:\n2-5 years' work experience, preferably in sales or trading, purchasing office, food industry;\nHolder of driving license (Hong Kong and IDP)\nDegree holder, preferably in Business administration, supply chain, food science disciplines;\nEnglish typing speed\u00a040wpm\u00a0is a must;\nGood written and spoken English;\nIn-depth knowledge in EXCEL spreadsheet; with ERP experience, data analytic skill;\nAble to work multi-tasks under pressure and deliver on schedule;\nSelf-motivated, positive, energetic and keen on learning;\nBe honest, loyal;\nGood adaptability to different and fast-changing company/procurement policies is a plus;\nStrong team player and communicator;\nDisciplinary, punctual.\nWe offer\u00a05-day work, Free lunch, Monthly incentive, 12 days annual leave, Birthday leave, 10 days paternity leave, Employee purchase discount, Medical insurance and Annual body check\u00a0to the above position.\n\u00a0\nInterested parties please send Full resume to HK JEBN LIMITED, including the following details:\n\u00a0\n1)\u00a0\u00a0\u00a0\u00a0 Availability\n2)\u00a0\u00a0\u00a0\u00a0 Expected salary\n3)\u00a0\u00a0\u00a0\u00a0 Present salary\n\n*HK JEBN Group policies on non-recruitment of smokers or other tobacco users.\n\u00a0\nAll personal data collected will be treated in strict confidential and be used for recruitment purpose solely.", "employment_types": ["Full Time", "Permanent"], "selling_points": ["2-3 years\u2019 of outdoor sports buying experience", "Degree holder in related disciplines", "Immediate available"], "locations": ["Kowloon Bay"], "categories": ["Merchandising & Purchasing", "Footwear", "Others"], "post_time": "2022-01-17T03:51:50Z", "salary": {"currency": null, "max": null, "min": null, "period": "monthly", "term": null}, "salary_visible": false, "title_keywords": ["assistant merchandiser"], "responsibilities": ["shipping documents", "price negotiation", "quality", "audit", "communication", "payment", "maintain", "liaise with", "control", "other duties", "teams", "develop", "schedule", "general support", "cost", "quality checking", "stock management", "logistic support", "contact suppliers", "analysis", "quality control", "planning"], "requirements": {"degrees": ["degree holder"], "majors": ["business administration", "food science"], "languages": ["english"], "language_level": ["good"], "hard_skills": ["excel", "plus", "typing", "erp", "spreadsheet"], "soft_skills": ["self-motivated", "under pressure", "multi-tasks", "keen", "learning", "adaptability", "honest", "loyal", "team player", "energetic", "positive", "communicator"], "languages_combined": [{"language": "english", "language_level": ["good"]}]}, "experience_required": {"duration": ["2-5 years"], "field": ["purchasing", "trading", "food industry"]}}, {"job_id": "100003009052611", "location_code": "hk", "company": "Million (Far East) Limited", "job_title": "Purchasing Officer (Frozen Food)", "description": "An international well-known brand is hiring a Assistant Merchandising Manager / Senior Merchandiser join their company.\n\n\n\n\u00a0Responsibilities\u00a0\n\nFormulate, review and develop budget, sales target, promotion and assortment plans\nAnalyze date for budget and vendor meetings, recommend action plans to management.\nReview and analyze exception reports, formulate action plan including IMU management and best sellers management.\nBuild and maintain strong rapport and relationship with vendor. Work on and monitor sales promotions, trainings and visual presentation standard & develop promotional collateral for in-store marketing.\nCompile different computer techniques as necessary such as Excel, Power Point for reporting, strategy books and other presentation.\n\nJob Requirements\n\nDegree or above in Business, marketing or related discipline\nMerchandising / planning experiences preferred\nExcellent problem solving, interpersonal, communication and negotiation skill\nExcellent command of both written and spoken English and Chinese\nFresh Gradute is also welcomed\u00a0\n\nInterested parties, please send your CV to Cyrus.chan(a)gsc-hk.com with\u00a0current & expected package.\n\nAll information collected will be used by recruitment purpose only.", "employment_types": ["Full Time", "Permanent"], "selling_points": ["Purchasing and Sourcing", "Food Trade - Frozen Food", "Diploma or above in related discipline"], "locations": ["Kwai Fong"], "categories": ["Hospitality / F & B", "Food & Beverage", "Merchandising & Purchasing", "Others", "Procurement / Purchasing / Sourcing"], "post_time": "2022-01-17T03:32:26Z", "salary": {"currency": null, "max": null, "min": null, "period": "monthly", "term": null}, "salary_visible": false, "title_keywords": ["purchasing officer"], "responsibilities": ["reporting", "management", "sales target", "review", "budget", "monitor", "develop", "maintain", "reports", "plan", "visual presentation", "plans"], "requirements": {"degrees": ["degree or above"], "majors": ["business", "marketing"], "languages": ["english", "chinese"], "language_level": ["excellent"], "hard_skills": ["problem solving"], "soft_skills": ["problem solving", "communication", "interpersonal", "negotiation skill"], "languages_combined": [{"language": "english", "language_level": ["excellent"]}, {"language": "chinese", "language_level": ["excellent"]}]}, "experience_required": {"duration": [], "field": ["merchandising", "planning"]}}, {"job_id": "100003009049008", "location_code": "hk", "company": "Cathay Pacific Catering Services (H.K.) Limited", "job_title": "Procurement Officer", "description": "Lauris Walton is exclusively partnering with a fast growing multinational online accessories firm, and we have an opportunity for a Product Assistant based in Hong Kong. This role will play a key role in supporting the product team on the daily organization of files, researching for new suppliers, office administration and operation matters.\n\nKey responsibilities:\n\nProvided administration and operation support to product manager\u00a0 \u00a0\nCommunicate with suppliers on quality control and finding new factories\nPerform quality checks and ensure accuracy of the product\nMaintain database and order management system\nAssist in organizing team building activities in Hong Kong\u00a0\nHandle office expenses and other ad-hoc requests\nRole requirements:\u00a0\n\nFluent in English and Chinese (Cantonese and Mandarin)\nMinimum of 1 year of relevant work experience\nDetail minded, well organized, punctual\nPositive mindset with a can-do attitude\u00a0\nWorking location:\u00a0Central (Prime location, excellent work environment)\u00a0", "employment_types": ["Full Time", "Permanent"], "selling_points": ["Source, assess and select products/suppliers", "Investigate issues with products/suppliers", "Maintain and upkeep purchasing database & records"], "locations": ["Airport Area"], "categories": ["Merchandising & Purchasing", "Sundries", "Others", "Procurement / Purchasing / Sourcing"], "post_time": "2022-01-14T07:54:18Z", "salary": {"currency": null, "max": null, "min": null, "period": "monthly", "term": null}, "salary_visible": false, "title_keywords": ["procurement officer"], "responsibilities": ["communicate with", "order management", "ad-hoc requests", "expenses", "quality", "maintain", "quality control", "database", "administration"], "requirements": {"degrees": [], "majors": [], "languages": ["cantonese", "english", "chinese", "mandarin"], "language_level": ["fluent"], "hard_skills": [], "soft_skills": ["can-do attitude", "well organized", "positive mindset"], "languages_combined": [{"language": "cantonese", "language_level": []}, {"language": "english", "language_level": ["fluent"]}, {"language": "chinese", "language_level": ["fluent"]}, {"language": "mandarin", "language_level": []}]}, "experience_required": {"duration": ["minimum of 1 year"], "field": []}}, {"job_id": "100003009056575", "location_code": "hk", "company": "Ka Hung Gloves Industrial Co Ltd", "job_title": "Purchasing Clerk - Procurement for Supermarket business", "description": "A well-established holding company is starting new supermarket business, we need professional staff and expert who is having thorough planning for running/operating/managing supermarket business professionally and smoothly. With his or her sound ancillary measures and diversified promotional activities, Retail Concepts, believe we can have profitable market share in this new area of business.\u7d93\u7406/\n\nPurchasing Clerk(Supermarket)\n\n(INMU SHOP LIMITED) \u701b\u6728\u8d85\u7d1a\u5e02\u57f8\u6709\u9650\u516c\u53f8\n\nNgau Tau Kok\n\nProactive, Flexible, Self-starter\n\nSupermarket/ eCommerce background welcomed\nStrong supplier network a plus\nRetails\nresponsibilities\nHandle daily / seasonal buying process from budgeting to launching\nWork closely with Sales and Business Development team for maximizing top line and minimizing inventory\nConduct and analyze regular buying and selling related report\nMaintain the database accuracy\nJob Requirements:\n\nPlan and execute regular product sourcing activities; ensure quality of products and on-time delivery to maintain suitable stock levels\nCoordinate and liaise with suppliers on product sourcing, trading terms and contract development; build a network of suppliers and maintain long-term vendor relationships\nAnalyse market trends to forecast upcoming product demands and potential sales volumes\nDevelop categorical selection of products and enhance sales by identifying and sampling new products\nSet seasonal OTB budget, formulate assortment and allocation plan, conduct inventory analysis and management, and set prices for products\nAnalyse sales and consolidate information of a variety of reports and plans (e.g. buying plan, delivery scheduling, stock clearance plan)\nMonitor sales with stock level, product efficiency, merchandise distribution, replenishment consolidation on a timely basis\nHandle merchandising related issues to ensure a timely management for all orders and deliveries\nLead team members (i.e. assistant buyers) and providing guidance\nCollaborate with marketing team and operation department and participate in major corporate sales, promotion events, visual merchandising and other ad-hoc projects\n\nRequirements Qualifications\n\nDiploma or above\nMinimum 2-3 years of relevant experience, preferably on the food or grocery department in supermarket industry\nKnowledge of category management\nAnalytical, open to change, well-organized and self-motivated with strong market sense and awareness\nStrong organizational and planning skills\nStrong desire to take initiative and able to work independently under pressure\nOutstanding interpersonal skills and negotiating abilities\nGood command of English and Chinese\nProficient in MS Office and Chinese Word Processing\nCandidate with more experience will be considered as Senior Buyer\n\nInterested parties please email detailed resume with expected salary to [email redacted, apply via company websitePlease click Apply Now to submit your application.\n\nWe\u00a0offer:\n\n5 days\u2019 work week + Alternate Saturday\n\nCompetitive Salary Package\n\n13 months' End-end bonus\n\nPerformance Incentives\n\nGroup Medical Scheme\n\nEnergetic & Dynamic Culture\n\n\u00a0\u00a0Interested parties please send your full resume and expected salary for application.", "employment_types": ["Full Time"], "selling_points": ["F 6 abv min 2 - 3 yrs sourcing exp. in supermarket", "Close relation w/food/non food/grocery suppliers", "Double pay,Discretionary bonus,medical insurance"], "locations": ["Ngau Tau Kok"], "categories": ["Hospitality / F & B", "Food & Beverage", "Merchandising & Purchasing", "Others", "Procurement / Purchasing / Sourcing"], "post_time": "2022-01-18T04:53:29Z", "salary": {"currency": null, "max": null, "min": null, "period": "monthly", "term": null}, "salary_visible": false, "title_keywords": ["purchasing clerk"], "responsibilities": ["budgeting", "inventory", "maintain", "database", "report"], "requirements": {"degrees": ["diploma or above"], "majors": [], "languages": ["english", "chinese"], "language_level": ["good command", "proficient"], "hard_skills": ["chinese word processing", "analysis", "visual merchandising", "vendor", "ms office"], "soft_skills": ["self-motivated", "work independently", "under pressure", "organizational and planning skills", "timely", "well-organized", "interpersonal skills", "strong market sense", "initiative"], "languages_combined": [{"language": "english", "language_level": ["good command"]}, {"language": "chinese", "language_level": ["good command", "proficient"]}]}, "experience_required": {"duration": ["minimum 2-3 years"], "field": ["food", "relevant experience"]}}, {"job_id": "100003009056482", "location_code": "hk", "company": "Ka Hung Gloves Industrial Co Ltd", "job_title": "Buyer - Procurement for Supermarket business", "description": "A well-established holding company is starting new supermarket business, we need professional staff and expert who is having thorough planning for running/operating/managing supermarket business professionally and smoothly. With his or her sound ancillary measures and diversified promotional activities, Retail Concepts, believe we can have profitable market share in this new area of business.\u7d93\u7406/\n\nPurchasing Clerk(Supermarket)\n\n(INMU SHOP LIMITED) \u701b\u6728\u8d85\u7d1a\u5e02\u57f8\u6709\u9650\u516c\u53f8\n\nNgau Tau Kok\n\nProactive, Flexible, Self-starter\n\nSupermarket/ eCommerce background welcomed\nStrong supplier network a plus\nRetails\nresponsibilities\nHandle daily / seasonal buying process from budgeting to launching\nWork closely with Sales and Business Development team for maximizing top line and minimizing inventory\nConduct and analyze regular buying and selling related report\nMaintain the database accuracy\nJob Requirements:\n\nPlan and execute regular product sourcing activities; ensure quality of products and on-time delivery to maintain suitable stock levels\nCoordinate and liaise with suppliers on product sourcing, trading terms and contract development; build a network of suppliers and maintain long-term vendor relationships\nAnalyse market trends to forecast upcoming product demands and potential sales volumes\nDevelop categorical selection of products and enhance sales by identifying and sampling new products\nSet seasonal OTB budget, formulate assortment and allocation plan, conduct inventory analysis and management, and set prices for products\nAnalyse sales and consolidate information of a variety of reports and plans (e.g. buying plan, delivery scheduling, stock clearance plan)\nMonitor sales with stock level, product efficiency, merchandise distribution, replenishment consolidation on a timely basis\nHandle merchandising related issues to ensure a timely management for all orders and deliveries\nLead team members (i.e. assistant buyers) and providing guidance\nCollaborate with marketing team and operation department and participate in major corporate sales, promotion events, visual merchandising and other ad-hoc projects\n\nRequirements Qualifications\n\nDiploma or above\nMinimum 2-3 years of relevant experience, preferably on the food or grocery department in supermarket industry\nKnowledge of category management\nAnalytical, open to change, well-organized and self-motivated with strong market sense and awareness\nStrong organizational and planning skills\nStrong desire to take initiative and able to work independently under pressure\nOutstanding interpersonal skills and negotiating abilities\nGood command of English and Chinese\nProficient in MS Office and Chinese Word Processing\nCandidate with more experience will be considered as Senior Buyer\n\nInterested parties please email detailed resume with expected salary to [email redacted, apply via company websitePlease click Apply Now to submit your application.\n\nWe\u00a0offer:\n\n5 days\u2019 work week + Alternate Saturday\n\nCompetitive Salary Package\n\n13 months' End-end bonus\n\nPerformance Incentives\n\nGroup Medical Scheme\n\nEnergetic & Dynamic Culture\n\n\u00a0\u00a0Interested parties please send your full resume and expected salary for application.", "employment_types": ["Full Time"], "selling_points": ["F 6 abv min 2 - 3 yrs sourcing exp. in supermarket", "Close relation w/food/non food/grocery suppliers", "Double pay,Discretionary bonus,medical insurance"], "locations": ["Ngau Tau Kok"], "categories": ["Hospitality / F & B", "Food & Beverage", "Merchandising & Purchasing", "Others", "Procurement / Purchasing / Sourcing"], "post_time": "2022-01-18T04:32:25Z", "salary": {"currency": null, "max": null, "min": null, "period": "monthly", "term": null}, "salary_visible": false, "title_keywords": [], "responsibilities": ["budgeting", "inventory", "maintain", "database", "report"], "requirements": {"degrees": ["diploma or above"], "majors": [], "languages": ["english", "chinese"], "language_level": ["good command", "proficient"], "hard_skills": ["chinese word processing", "analysis", "visual merchandising", "vendor", "ms office"], "soft_skills": ["self-motivated", "work independently", "under pressure", "organizational and planning skills", "timely", "well-organized", "interpersonal skills", "strong market sense", "initiative"], "languages_combined": [{"language": "english", "language_level": ["good command"]}, {"language": "chinese", "language_level": ["good command", "proficient"]}]}, "experience_required": {"duration": ["minimum 2-3 years"], "field": ["food", "relevant experience"]}}, {"job_id": "100003009056681", "location_code": "hk", "company": "Global Packaging Limited", "job_title": "Account Executive", "description": "Job Descriptions:\n\nLiaise with overseas clients and factories independently\nIndependently in handling projects follow up from sampling development to production\nHandle orders and monitor production process\nPrepare quotations, sampling and monthly reports\nOccasional travel to overseas if needed\n\nRequirements:\n\nHigh Diploma or above with 2 years relevant working experience\nWith solid printing knowledge\u00a0for garment accessories is preferred\nFluent language skills (written and oral) in English, Mandarin and Cantonese\nAble to work independent, detailed oriented, well organized & under pressure within a tight schedule\nProficient in MS office and English + Chinese word processing\nGood team player and work independently\n\nSalary Range: Negotiable\n\nBenefits:\n\n-Bank holiday\n\n-12~25 days annual leave or above\n\n-5 days working per week\n\n-Medical scheme\n\n-13 months salary\n\n-Performance based Bonus (not guarantee)\n\nWe provide attractive remuneration packages to the right candidates. Interested parties please send following by clicking \"APPLY NOW\".\n\nDetailed curriculum vitae/resume\nDate of availability\nExpected salary\n\n(All personal data provided will be treated in strict confidence and used for recruitment purposed only.)", "employment_types": ["Full Time"], "selling_points": ["High Diploma or above with 2 years relevant work", "With solid printing knowledge is preferred", "5 days working"], "locations": ["Kwai Hing"], "categories": ["Merchandising & Purchasing", "Others", "Manufacturing", "Printing", "Others", "Trading"], "post_time": "2022-01-18T05:44:24Z", "salary": {"currency": null, "max": null, "min": null, "period": "monthly", "term": null}, "salary_visible": false, "title_keywords": ["account executive"], "responsibilities": ["liaise with", "monitor", "production process", "monthly reports"], "requirements": {"degrees": ["high diploma or above"], "majors": [], "languages": ["cantonese", "english", "chinese", "mandarin"], "language_level": ["proficient", "fluent"], "hard_skills": ["chinese word processing", "ms office"], "soft_skills": ["oral", "good team player", "under pressure", "independent", "detailed oriented", "work independently", "well organized"], "languages_combined": [{"language": "cantonese", "language_level": ["fluent"]}, {"language": "english", "language_level": ["proficient", "fluent"]}, {"language": "chinese", "language_level": ["proficient"]}, {"language": "mandarin", "language_level": ["fluent"]}]}, "experience_required": {"duration": ["2 years"], "field": ["relevant working experience"]}}, {"job_id": "100003009040315", "location_code": "hk", "company": "REWE Far East Limited", "job_title": "Assistant Corporate Responsibility Officer", "description": "Key Responsibilities :\n\nSupport the daily operations in CR team to ensure that social and environmental compliance programs are implemented.\nArrange and follow-up on BSCI or other social compliance audits and ensure the related records are maintained and updated.\nArrange and follow-up on environmental compliance audits & consulting, and ensure the related records are maintained and updated.\nSupport the implementation of company\u2019s corporate responsibility policy and the related compliance processes.\nSupport the execution of defined sustainability projects in cooperation with the Merchandising, Buying and Sustainability departments in Germany and respective service providers/business partners.\nEnsure the effective communication with internal stakeholders (such as merchandising team, quality, supply chain, packaging, etc.) on REWE Group\u2019s CR requirements and goals.\nSupport the team to execute continuous improvement projects in RFE to enhance the standard of social and environmental compliance and achieve the CR\u2019s goals.\nJob Requirements\u00a0:\n\nUniversity degree in Social Responsibility, Sustainability and Compliance, Business Administration, or related disciplines.\nMin. 1 years of working experience in a social compliance role.\nGood interpersonal and communication skills, be a team player in a cross-cultural working environment.\nSelf-motivated, detailed minded, and with good problem-solving skills.\u00a0\u00a0Independent, pro-active working style is required.\nKnowhow on BSCI & BEPI requirements and China labour legislation.\u00a0\u00a0Knowledge on the labour legislation in any other south-east Asia countries is preferable.\nKnowledge on social compliance standards such as BSCI, SA8000, ICTI, ETI, etc. is an advance.\nKnowledge on environmental compliance standards such as BEPI, ISO 14001, Detox, Higg, STeP, etc. is an advance.\nGood knowledge on MS Office, especially MS Excel (including pivot tables).\nGood command of both written and spoken English and Chinese (Cantonese and Mandarin) is a must.\nFlexible to have business travel when required.\n\nIf you are interested in the position, please submit your full resume with cover letter, current and expected salary and available date via JobsDB.\n\nAll personal information is collected for recruitment purpose only and will be treated in strict confidentiality.", "employment_types": ["Full Time", "Permanent"], "selling_points": ["Sustainability, Environmental Compliance, CR/SC", "EU buying office, Mobile Working, Flex Working Hr", "13th month Bonus, Discretionary Bonus"], "locations": ["Kwun Tong Area"], "categories": ["Admin & HR", "Clerical / Admin Staff", "Marketing / Public Relations", "Others", "Merchandising & Purchasing", "Others"], "post_time": "2022-01-16T21:50:03Z", "salary": {"currency": null, "max": null, "min": null, "period": "monthly", "term": null}, "salary_visible": false, "title_keywords": ["officer", "assistant"], "responsibilities": ["consulting", "compliance", "merchandising", "implementation", "quality", "communication", "daily operations", "audits"], "requirements": {"degrees": ["university degree"], "majors": ["related disciplines", "business administration"], "languages": ["cantonese", "english", "chinese", "mandarin"], "language_level": ["good command"], "hard_skills": ["problem-solving skills", "ms excel", "ms office"], "soft_skills": ["flexible", "communication skills", "self-motivated", "independent", "interested in", "pro-active", "problem-solving skills", "team player", "interpersonal", "detailed"], "languages_combined": [{"language": "cantonese", "language_level": ["good command"]}, {"language": "english", "language_level": ["good command"]}, {"language": "chinese", "language_level": ["good command"]}, {"language": "mandarin", "language_level": ["good command"]}]}, "experience_required": {"duration": ["1 years"], "field": ["compliance"]}}, {"job_id": "100003009051993", "location_code": "hk", "company": "Change Group Hong Kong Limited", "job_title": "Senior Merchandiser / Merchandiser \u2013 new openings - hardgoods", "description": "Responsibilities:\n\nResponsible for outdoor apparel, footwear and accessories buy;\nHandle annual / seasonal buying process from budgeting to launching;\nFormulate buying strategies, develop OTB plans and product mix allocation to optimize sales plan and gross margin;\nRegularly keep track of sales trend to provide relevant strategies accomplishing business objectives;\nResponsible for shipment and order follow up;\nHandle full set I/E documents independently;\nLiaise and coordinate internally and externally on shipping / local transportation;\nPrepare packing list, invoice and delivery note;\nCommunicate with China headquarter and forwarding company for shipment arrangement;\nAnalyze the data to formulate a right product plan and solutions to fit for the business needs and cater for the market trend;\nConduct and analyze regular buying and selling related report;\nShop visit and regular travel for trade shows are required.\n\nRequirements:\n\nA Bachelor's degree in related disciplines is preferred;\nMinimum 2-3 years\u2019 of solid outdoor sports buying experience including planning & budgeting;\nWorking experience in I/E firm or shipping related company is preferred;\nStrong fashion sense, detail-oriented with good analytical and reporting skills;\nEnergetic, proactive, self-motivated, able to work independently and meet tight deadline;\nGood team player with strong sense of responsibility;\nProficient in MS Word and Excel;\nGood command of written and spoken Chinese and English;\nOccasional travel is required;\nImmediate available is highly preferable.", "employment_types": ["Full Time"], "selling_points": ["New openings", "excellent work environment", "good market sense"], "locations": ["Central & Western Area"], "categories": ["Merchandising & Purchasing", "Others"], "post_time": "2022-01-17T01:46:37Z", "salary": {"currency": null, "max": null, "min": null, "period": "monthly", "term": null}, "salary_visible": false, "title_keywords": ["merchandiser", "senior merchandiser"], "responsibilities": ["liaise", "communicate with", "shipping", "shipment arrangement", "data", "invoice", "budgeting", "otb", "develop", "coordinate", "packing list", "plan", "plans", "report"], "requirements": {"degrees": ["degree", "bachelor"], "majors": ["related disciplines"], "languages": ["english", "chinese"], "language_level": ["good command"], "hard_skills": ["excel", "ms word"], "soft_skills": ["work independently", "self-motivated", "proactive", "good team player", "sense of responsibility", "detail-oriented", "meet tight deadline", "energetic"], "languages_combined": [{"language": "english", "language_level": ["good command"]}, {"language": "chinese", "language_level": ["good command"]}]}, "experience_required": {"duration": ["minimum 2-3 years"], "field": ["related", "planning"]}}, {"job_id": "100003009052343", "location_code": "hk", "company": "Bally GC Retail Co. Limited", "job_title": "Temporary Merchandising Assistant (1-year Renewal Contract)", "description": "Responsibilities:\n\nResponsible for procurement activities including sourcing, price and terms negotiation with suppliers, order follow up;\nMonitor the inventory level and prepare stock forecasting;\nConduct regular vendors\u2019 evaluation and assessment;\nDeal with quality complaints;\nMaintain supplier databases and purchase records;\nPrepare cost comparison to assist decision making;\nCoordinate with internal teams to achieve smooth operation process;\nAd hoc assignments.\n\nRequirements:\n\nDiploma or above in Procurement,\u00a0Supply Chain Management or related discipline;\nAt least 2 years of work experience in procurement and sourcing preferably in food trading;\nFresh graduates\u00a0are also\u00a0welcome;\nCandidate with less experience will be considered as Assistant Purchasing Officer;\nGood command of spoken and written Chinese (both Cantonese & Mandarin) and English;\nProficient in MS office applications;\nSelf-motivated, well-organized with excellent analytical and negotiation skills;\nImmediate availability will be an advantage.\n\nWe offer competitive remuneration and fringe benefits including discretionary bonus, medical insurance, annual leave and 5-day workweek. Interested party please send detailed resume in both Chinese and English version with expected salary & date of availability by clicking \"Apply Now\".\n\nPersonal data will be used for recruitment purpose only.", "employment_types": ["Temporary", "Contract"], "selling_points": ["Fashion Merchandising experience", "Stock allocation and rebalancing", "Tertiary education"], "locations": ["Causeway Bay"], "categories": ["Merchandising & Purchasing", "Footwear", "Handbag", "Others"], "post_time": "2022-01-17T02:48:38Z", "salary": {"currency": null, "max": null, "min": null, "period": "monthly", "term": null}, "salary_visible": false, "title_keywords": ["merchandising assistant"], "responsibilities": ["cost", "terms negotiation", "inventory", "monitor", "quality", "coordinate with", "teams", "purchase", "maintain", "ad hoc assignments", "databases", "evaluation", "forecasting"], "requirements": {"degrees": ["diploma or above"], "majors": [], "languages": ["cantonese", "english", "chinese", "mandarin"], "language_level": ["good command"], "hard_skills": ["ms office"], "soft_skills": ["self-motivated", "well-organized", "negotiation skills"], "languages_combined": [{"language": "cantonese", "language_level": ["good command"]}, {"language": "english", "language_level": ["good command"]}, {"language": "chinese", "language_level": ["good command"]}, {"language": "mandarin", "language_level": ["good command"]}]}, "experience_required": {"duration": ["at least 2 years"], "field": ["purchasing", "food", "trading", "procurement"]}}, {"job_id": "100003009055467", "location_code": "hk", "company": "Chandler Macleod Group (HK) Limited", "job_title": "Procurement Operations Support / Buyer (Up to 40K/mth)", "description": "Responsibilities\nSource, assess and select products and suppliers in order to achieve the Company target on the cost and quality performance of assigned product categories, as well as the relevant suppliers\nNegotiate with suppliers for best deals\nMaintain and update the purchasing database and records\nPerform source planning, conduct market research and develop a supply market\nInvestigate product and supplier issues and coordinate for solutions\nMeasure and analyze the performance of assigned product categories\nAssist in inter-departmental projects to achieve the Company goals and objectives\nRequirements\nDiploma / higher diploma or above in any discipline\nMinimum 2 years\u2019 working experience, preferably with relevant experience in food purchasing\nCandidate possesses a degree in any discipline with less than 2 years working experience will also be considered\nStrong problem solving, numerical and analytical skills\nGood interpersonal and communication skills\nGood price negotiation and cost control skills\nAble to work under pressure and meet stretching targets\nGood command in both written and spoken English and Chinese.\u00a0 Knowledge in Putonghua would be an advantage\nProficient in Microsoft Office, especially MS Word and Excel\nCandidates with more experience will be considered for the position of Senior Procurement Officer\n\nWe offer a competitive remuneration package and a full range of benefits. Interested parties please send your resume with your current and expected salary to Head of People,11 Catering Road East, Hong Kong International Airport, Lantau, Hong Kong or by clicking the \"Apply Now\" button on or before 10 February 2022.\n\nPersonal data collected will be treated in the strictest confidence and only be used for recruitment-related purposes. Applicants who do not receive notification for an interview within six weeks may consider their application unsuccessful.", "employment_types": ["Full Time", "Contract"], "selling_points": ["A multinational technology corporation", "Well-rounded procurement exposure", "Immediately available highly preferred"], "locations": ["Not Specified"], "categories": ["Merchandising & Purchasing", "Others", "Procurement / Purchasing / Sourcing"], "post_time": "2022-01-18T02:37:41Z", "salary": {"currency": null, "max": null, "min": null, "period": "monthly", "term": null}, "salary_visible": false, "title_keywords": ["operations"], "responsibilities": ["product categories", "cost", "conduct market research", "quality", "develop", "coordinate", "maintain", "database", "planning"], "requirements": {"degrees": ["diploma", "higher diploma or above", "degree"], "majors": [], "languages": ["putonghua", "english", "chinese"], "language_level": ["advantage", "good command"], "hard_skills": ["excel", "microsoft office", "analytical skills", "problem solving", "ms word"], "soft_skills": ["communication skills", "negotiation", "analytical skills", "problem solving", "interpersonal", "work under pressure"], "languages_combined": [{"language": "putonghua", "language_level": ["advantage"]}, {"language": "english", "language_level": ["good command"]}, {"language": "chinese", "language_level": ["good command"]}]}, "experience_required": {"duration": ["2 years", "minimum 2 years"], "field": ["purchasing", "food", "relevant experience", "procurement"]}}, {"job_id": "100003009056274", "location_code": "hk", "company": "Puleo Asia Limited", "job_title": "Merchandise/ Assistant Merchandiser (Seasonal, Home Decorations & Gifts)", "description": "Senior Merchandiser / Merchandiser \u2013 new openings - hardgoods\u00a0\n\nJob Description\n\nLiaise with vendors and negotiate with suppliers in PRC/APAC\nSource and develop new suppliers according to market trend\u00a0\nEnhance vendor relationships and strengthen supplier network\nNegotiate price, contract terms and conditions with stakeholders\nManage quotation, product presentation and samples\nProvide support for ad hoc assignments to management\n\nRequirements\n\nAt least 2-year related working experience. Buying office/ trading background is preferred.\nGood regulations knowledge: Candidates who demonstrate extensive Home market knowledge is a plus\nProactive; quick learner; good team player\nEffective bilingual skill\n\nWe offer attractive remuneration packages to the right candidates. Please send your full resume and expected salary by clicking \"Apply Now\u201d", "employment_types": ["Full Time", "Permanent"], "selling_points": [], "locations": ["Hung Hom"], "categories": ["Merchandising & Purchasing", "Others"], "post_time": "2022-01-18T03:47:20Z", "salary": {"currency": null, "max": null, "min": null, "period": "monthly", "term": null}, "salary_visible": false, "title_keywords": ["assistant merchandiser"], "responsibilities": ["provide support", "management", "quotation", "develop", "ad hoc assignments", "liaise with"], "requirements": {"degrees": [], "majors": [], "languages": [], "language_level": [], "hard_skills": ["plus"], "soft_skills": ["good team player", "proactive", "extensive", "quick learner"], "languages_combined": []}, "experience_required": {"duration": ["at least 2-year"], "field": ["related"]}}, {"job_id": "100003009049764", "location_code": "hk", "company": "Moiselle (Hong Kong) Limited", "job_title": "Part Time Merchandising Clerk", "description": "Job Duties\n\nReport to Merchandising Director, Great China, to handle stock allocation and rebalancing work for HK market (RTL and OLT)\nCoordinate with Retail team, VM team and Logistic team for actions follow up\nExecute HK Promotion activities and follow up\nPrepare HK Merchandising Analysis and Reporting\nProvide on-site follow up on product knowledge coaching after seasonal training\nCollect merchandise feedback and monitor competitors activities\nPerform other ad-hoc duties as assigned by manager\n\n\u00a0Requirement\n\nTertiary education in Business Management, Fashion Merchandising, or related discipline\nAt least 1 year relevant working experience in merchandising\nGood interpersonal skill, detail-oriented, willing to learn and able to work under pressure.\nGood command of spoken and written English, Cantonese and Mandarin\nProficient in MS Office, Excel (pivot table, vlookup, etc.) and PowerPoint\n\nInterested parties please send your resume with current and expected salary and date of availability to Human Resources Department by clicking \"APPLY NOW\".\n\n**Data collected will be used for recruitment purpose only.**\n\n\n\n", "employment_types": ["Part Time"], "selling_points": ["Merchandising", "Luxury Fashion", "welcome fresh graduates"], "locations": ["Quarry Bay"], "categories": ["Merchandising & Purchasing", "Others"], "post_time": "2022-01-14T09:12:26Z", "salary": {"currency": null, "max": null, "min": null, "period": "hourly", "term": null}, "salary_visible": false, "title_keywords": ["merchandising clerk"], "responsibilities": ["reporting", "vm team", "stock allocation", "analysis", "merchandising", "coordinate with", "monitor", "ad-hoc duties", "report"], "requirements": {"degrees": [], "majors": [], "languages": ["cantonese", "english", "mandarin"], "language_level": ["good command"], "hard_skills": ["business management", "excel", "pivot table", "powerpoint", "vlookup", "ms office"], "soft_skills": ["detail-oriented", "work under pressure", "willing to learn", "interpersonal skill"], "languages_combined": [{"language": "cantonese", "language_level": ["good command"]}, {"language": "english", "language_level": ["good command"]}, {"language": "mandarin", "language_level": ["good command"]}]}, "experience_required": {"duration": ["at least 1 year"], "field": ["merchandising", "relevant working experience"]}}, {"job_id": "100003009051230", "location_code": "hk", "company": "Easy Job Centre", "job_title": "Account Executive / Customer Services", "description": "Job Responsibilities\n\nConduct new sourcing requests, contract renewals, contract re-negotiation and transactional tasks of tactical sourcing projects.\nConduct detailed spend analysis and compile spend dashboard\nManage purchase requisitions from business, advise requestor on sourcing channel and execute tactical sourcing as needed.\nManage PO issuance (if needed) and review PO status / follow-up with suppliers\nMaintain the contract repository (upload and archive contracts as needed)\nReview contract compliance and contracts due for renewal\nSupport supplier identification, qualification and onboarding process\nSupport master data management\nSupport complication of procurement operations / performance reports\n\nJob Requirements\n\nUniversity graduate or professional qualification in a related discipline\nAbout 3 years' relevant experience\nProcurement operations experience is essential\nAbility to adapt and learn rapidly to be able to talk the language of the stakeholders\nUnderstanding of regulatory requirements and procurement policies\nAbility to inspire, and build trust and respect among the stakeholders\nExcellent people skills; including the ability to negotiate and influence internal and external stakeholders\nA team player, assertive yet approachable and decisive\nPossess of proficiency in Excel (V-lookup, macros) and PowerPoint Presentation and procurement systems\nImmediately available is highly preferred but not a must", "employment_types": ["Full Time"], "selling_points": [], "locations": ["Wan Chai"], "categories": ["Sales, CS & Business Devpt", "Customer Service - Supervisor / Officer", "Merchandising & Purchasing", "Others", "Sales Administration"], "post_time": "2022-01-15T05:19:58Z", "salary": {"currency": null, "max": null, "min": null, "period": "monthly", "term": null}, "salary_visible": false, "title_keywords": ["account executive"], "responsibilities": ["management", "performance reports", "data", "contracts", "analysis", "review", "compliance", "operations", "purchase", "maintain"], "requirements": {"degrees": ["university graduate"], "majors": [], "languages": [], "language_level": [], "hard_skills": ["excel", "powerpoint"], "soft_skills": ["approachable", "assertive", "decisive", "team player", "presentation"], "languages_combined": []}, "experience_required": {"duration": ["3 years"], "field": ["relevant experience", "procurement"]}}, {"job_id": "100003009040324", "location_code": "hk", "company": "REWE Far East Limited", "job_title": "Project Manager, Corporate Responsibility", "description": "Requirements\n\nF.5 graduated or above\nMinimum 3 years of merchandising and trading experiences is a MUST\nFluent Written and Spoken English and Mandarin\nWell organized, with good interpersonal & communication skill\nIndependent, responsible and willing to learn\nProficiency in on-hand computer skill : MS Excel, Chinese Word processing & Outlook Knowledge\nMature, stable, detail-minded and self-motivated and being a good team player, able to work under pressure\nAble to work in a fast pace environment & overtime\nLess experience will be considered as Assistant Merchandiser\nImmediate available is preferable\n\n\n\nWe offer competitive remuneration package. For Interested parties, please submit your resume by clicking ''Apply Now'' button as below.\u00a0\n\nAll the information provide by applicants will be used for\u00a0recruitment purpose only.\u00a0", "employment_types": ["Full Time", "Permanent"], "selling_points": ["Project management, Sustainability", "EU buying office, Mobile Working, Flex Working Hr", "13th Month Bonus, Discretionary Bonus"], "locations": ["Kwun Tong Area"], "categories": ["Marketing / Public Relations", "Others", "Merchandising & Purchasing", "Others"], "post_time": "2022-01-16T21:50:04Z", "salary": {"currency": null, "max": null, "min": null, "period": "monthly", "term": null}, "salary_visible": false, "title_keywords": ["project manager"], "responsibilities": ["communication", "merchandising", "work under pressure"], "requirements": {"degrees": [], "majors": [], "languages": ["english", "chinese", "mandarin"], "language_level": ["proficiency", "fluent"], "hard_skills": ["chinese word processing", "ms excel", "computer skill", "outlook"], "soft_skills": ["detail-minded", "self-motivated", "good team player", "independent", "responsible", "communication skill", "well organized", "willing to learn", "mature", "stable", "interpersonal", "work under pressure"], "languages_combined": [{"language": "english", "language_level": ["fluent"]}, {"language": "chinese", "language_level": ["proficiency"]}, {"language": "mandarin", "language_level": ["fluent"]}]}, "experience_required": {"duration": ["minimum 3 years"], "field": ["merchandising", "trading"]}}, {"job_id": "100003009037193", "location_code": "hk", "company": "Able Engineering Holdings Limited", "job_title": "Procurement Officer", "description": "\u8077\u8cac\n\n\u5b89\u6392\u9ede\u7b97\u6a23\u8fa6\n\u6587\u4ef6\u8655\u7406\u53ca\u8cc7\u6599\u8f38\u5165\n\u8207\u5ee0\u5546\u806f\u7d61\u8ddf\u9032\u8a02\u55ae\u9032\u5ea6\n\u5bc4\u6a23\u8fa6\u56de\u5ee0\u5546\n\u5354\u52a9\u8a18\u9304\u6a21\u7279\u5152\u8a66\u7a7f\u904e\u7a0b\n\n\u8981\u6c42\n\n\u6709\u8cac\u4efb\u5fc3\n\u719f\u6089\u96fb\u8166\u64cd\u4f5c\uff0c\u4e2d\u82f1\u6587\u8f38\u5165(\u5009\u9821 / \u901f\u6210)\n\u6709Merchandising\u7d93\u9a57\u8005\u512a\u5148\n\u5373\u6642\u4e0a\u73ed\u8005\u512a\u5148\u8003\u616e\n\u6b61\u8fce\u61c9\u5c46\u7562\u696d\u751f\u7533\u8acb\n\n\u6642\u9593: \u661f\u671f\u4e00\u81f3\u4e94\u65e9\u4e0a9:00\u81f3\u4e0b\u534818:00 (\u6bcf\u9031\u5de5\u4f5c\u6700\u5c113\u5929)", "employment_types": ["Full Time"], "selling_points": [], "locations": ["Not Specified"], "categories": ["Merchandising & Purchasing", "Others", "Procurement / Purchasing / Sourcing"], "post_time": "2022-01-15T19:11:31Z", "salary": {"currency": null, "max": null, "min": null, "period": "monthly", "term": null}, "salary_visible": false, "title_keywords": ["procurement officer"], "responsibilities": [], "requirements": {"degrees": [], "majors": [], "languages": [], "language_level": [], "hard_skills": [], "soft_skills": [], "languages_combined": []}, "experience_required": {"duration": [], "field": []}}, {"job_id": "100003009047756", "location_code": "hk", "company": "Kwong Chak Fat Manufactory Limited", "job_title": "Merchandiser / Senior Merchandiser", "description": "Key Responsibilities\n\nManage the successful execution of defined sustainability projects in cooperation with the Merchandising, Buying and Sustainability departments in Germany and respective service providers / business partners.\nSupport the CR Manager with the development and implementation of Co\u2019s CR strategy.\nDriving constant CR process review and continuous improvement.\nResponsible to prepare and analyze CR-related data to ensure accurate reporting.\nEnsure the effective communication with internal stakeholders, suppliers and business partners on Company\u2019s CR requirements and targets.\nProvide appropriate training to both internal and external stakeholders.\nPerform corporate responsibility research and feasibility studies.\n\n\nJob Requirements\n\nUniversity degree or above in Social Responsibility, Sustainability and Compliance, Business Administration, or related disciplines.\nAt least 5 years of experience in project management roles in social / environmental compliance topics and geographically covers China and/or south-east Asia.\nStrong project management skill and vendor management skill.\nExperience with social compliance standards (such as BSCI, SA8000, ICTI) and/or environmental compliance standards (such as BEPI, ISO 14001, Detox, Higg Index).\nExcellent interpersonal and communication skills, be a team player in the cross-cultural working environment.\nPro-active, detailed minded, and with good problem-solving skills.\nGood knowledge of MS office, especially MS Excel (pivot tables).\nGood command of both written and spoken English and Chinese (Cantonese and Mandarin) is a must.\nWilling to travel when necessary.\n\nIf you are interested in the position, please submit your full resume with cover letter, current and expected salary and available date via JobsDB.\n\nAll\u00a0personal information is collected for recruitment purpose only and will be treated in strict confidentiality.\u00a0\u00a0", "employment_types": ["Full Time"], "selling_points": [], "locations": ["Shatin Area"], "categories": ["Manufacturing", "Product Development / Management", "Merchandising & Purchasing", "Others", "Procurement / Purchasing / Sourcing"], "post_time": "2022-01-14T03:53:24Z", "salary": {"currency": null, "max": null, "min": null, "period": "monthly", "term": null}, "salary_visible": false, "title_keywords": ["merchandiser", "senior merchandiser"], "responsibilities": ["reporting", "data", "review", "merchandising", "implementation", "communication"], "requirements": {"degrees": ["degree or above"], "majors": ["related disciplines", "business administration"], "languages": ["cantonese", "english", "chinese", "mandarin"], "language_level": ["good command"], "hard_skills": ["vendor", "project management", "ms excel", "problem-solving skills", "ms office"], "soft_skills": ["communication skills", "pro-active", "interested in", "project management", "project management skill", "problem-solving skills", "team player", "interpersonal", "detailed"], "languages_combined": [{"language": "cantonese", "language_level": ["good command"]}, {"language": "english", "language_level": ["good command"]}, {"language": "chinese", "language_level": ["good command"]}, {"language": "mandarin", "language_level": ["good command"]}]}, "experience_required": {"duration": ["at least 5 years"], "field": ["project management", "compliance", "environmental"]}}, {"job_id": "100003009037909", "location_code": "hk", "company": "Taibon Co Ltd", "job_title": "Senior Merchandiser (Gift and Premium)", "description": "Higher Diploma or above ;\nAt least 4 years' relevant working experience, with construction industry experience is preferred;\nGood communication and interpersonal skills;\nResponsible, well-organized and self-motivated;\nGood command of written and spoken English and Chinese;\nCandidate with less experience will be considered as Assistant Procurement Officer.\n\nWe offer competitive salary package and career development opportunity to the successful candidate. Interested parties may send your full resume, present and expected salary, available date and contact number by clicking \"Apply Now\"\n\nTo visit our website for more information:\u00a0www.ableeng.com.hk\n\n(As an Equal Opportunities Employer, Able is committed to eliminating discrimination in employment. The vacancy advertised is open to all applicants meeting the basic entry requirement irrespective of their disability, sex, marital status, pregnancy, age, family status, sexual orientation or race etc. Applicants not hearing from us within 6 months may consider their applications unsuccessful. Personal data collected will be used for recruitment related purposes only.)", "employment_types": ["Full Time"], "selling_points": ["Merchandiser", "Senior Merchandiser", "Gift and premium"], "locations": ["Lai Chi Kok"], "categories": ["Merchandising & Purchasing", "Handbag", "Sundries", "Others"], "post_time": "2022-01-11T04:13:09Z", "salary": {"currency": null, "max": null, "min": null, "period": "monthly", "term": null}, "salary_visible": false, "title_keywords": ["senior merchandiser"], "responsibilities": ["communication"], "requirements": {"degrees": ["higher diploma or above"], "majors": [], "languages": ["english", "chinese"], "language_level": ["good command"], "hard_skills": [], "soft_skills": ["self-motivated", "communication and interpersonal skills", "well-organized", "responsible"], "languages_combined": [{"language": "english", "language_level": ["good command"]}, {"language": "chinese", "language_level": ["good command"]}]}, "experience_required": {"duration": ["at least 4 years"], "field": ["procurement", "construction industry", "relevant working experience"]}}, {"job_id": "100003009039261", "location_code": "hk", "company": "Dolce Vita Group Limited", "job_title": "General Clerk", "description": "JOB DUTIES\n\nResponsible for overall merchandising activities from product development to order follow up.\nManage daily communications with internal sales team & factories\nParticipate in price negotiation and cost engineering to meet client\u2019s goal.\nAssist Sales Team for orders and production follow-up\n\nTHE REQUIREMENTS\n\nUniversity degree graduated with good PC skills/English/Mandarin\nExpected to work with high efficiency and under pressure\nMature, self-motivated and\u00a0strong sense of responsibility.\nGood communication and negotiation skills in English & Mandarin\nOccasional travel to China and Oversea may be needed\n\nWe are offering highly competitive package 5 days work, medical benefit, double pay and performance bonus", "employment_types": ["Full Time"], "selling_points": [], "locations": ["Ngau Tau Kok"], "categories": ["Merchandising & Purchasing", "Others"], "post_time": "2022-01-13T07:33:43Z", "salary": {"currency": null, "max": null, "min": null, "period": "monthly", "term": null}, "salary_visible": false, "title_keywords": ["general clerk"], "responsibilities": ["cost", "communications with", "price negotiation", "merchandising", "sales team"], "requirements": {"degrees": ["university degree"], "majors": [], "languages": ["english", "mandarin"], "language_level": ["good"], "hard_skills": ["pc skills"], "soft_skills": ["self-motivated", "under pressure", "sense of responsibility", "mature", "communication", "negotiation skills"], "languages_combined": [{"language": "english", "language_level": ["good", "good"]}, {"language": "mandarin", "language_level": ["good", "good"]}]}, "experience_required": {"duration": [], "field": []}}, {"job_id": "100003009049896", "location_code": "hk", "company": "Paladone Products Limited", "job_title": "Merchandiser", "description": "Main responsibilities would be:\n\nFull supervision and handling of our retail clients, mainly consisting of large multinational chain stores.\nMerchandiser role at MA is independent beginning-to-end handling of client\u2019s accounts, from quotes to shipment.\nHandling new enquiries: costing analysis, quote preparations, samples, and supervising OEM developments.\nPreparation of various order documents e.g. P/I, P/O\u2019s, vendor registration documents.\nOverseeing & organizing pre-production scheduling, lab testing issues, artwork development, and factory audit issues. Must have experience in supervising all these tasks.\nHandle full set of shipping and payment documents including L/C.\nSupervising our China based staff and vendors to ensure orders on track.\nDaily communications with customers for ongoing orders and new opportunities.\nStrong experience in merchandising role for international trading company is a must, with strength in all areas from marketing, operations, documents, logistics, payments.\nExperience handling large western retailer accounts, especially for European market, are highly desirable.\nExperience in toys industry/trading is highly desirable.\nEnergetic individual required with great communication skills in English + Cantonese + Mandarin, both verbal and written.\nMust be able to work independently, have strong \u2018multi-tasking\u2019 abilities, resourceful & pro-active.\nStrong computer skills in regular MS Office programs.\nMust be professional, high-calibre, with consistently high performance throughout career.\nImmediately available is required.\n\nPlease include resume, reference letters, and expected salary.\u00a0 Information collected will be solely for recruitment purpose.", "employment_types": ["Full Time", "Permanent"], "selling_points": [], "locations": ["Tsim Sha Tsui"], "categories": ["Merchandising & Purchasing", "Toy", "Others", "Procurement / Purchasing / Sourcing"], "post_time": "2022-01-14T09:25:29Z", "salary": {"currency": null, "max": null, "min": null, "period": "monthly", "term": null}, "salary_visible": false, "title_keywords": ["merchandiser"], "responsibilities": ["communications with", "supervising", "shipping", "artwork development", "operations", "merchandising", "audit", "letters", "testing", "communication", "scheduling", "payment", "logistics", "payments", "recruitment", "costing analysis", "pre-production"], "requirements": {"degrees": [], "majors": [], "languages": ["cantonese", "english", "mandarin"], "language_level": [], "hard_skills": ["analysis", "vendor", "c", "computer skills", "ms office"], "soft_skills": ["communication skills", "work independently", "independent", "resourceful", "multi-tasking", "pro-active", "energetic"], "languages_combined": [{"language": "cantonese", "language_level": []}, {"language": "english", "language_level": []}, {"language": "mandarin", "language_level": []}]}, "experience_required": {"duration": [], "field": ["toys", "merchandising", "marketing", "logistics", "trading"]}}, {"job_id": "100003009054572", "location_code": "hk", "company": "Skincentral Dermatology, Aesthetics & Lasers", "job_title": "Clinic Assistant (Central & 5 Day Work)", "description": "Responsibilities:\n\nHandle clerical duties including invoicing data entry and filing\nHandle artwork, samples and prepare documents\nFollow up sales orders & purchase order process\nHandle incoming phone calls and courier\nPerform ad-hoc tasks or projects as assigned.\n\nRequirements:\n\nF.5 (HKCEE / HKDSE) or above\nIndependent, self-motivated, detail-minded, able to work under pressure\u00a0\nGood command of written and spoken English and\u00a0Mandarin\nComputer knowledge in MS Office including Word, Excel, Outlook,etc.\nImmediate available is preferable", "employment_types": ["Full Time", "Part Time", "Permanent"], "selling_points": [], "locations": ["Central"], "categories": ["Beauty Care / Health", "Therapist", "Medical Services", "Nursing", "Merchandising & Purchasing", "Others"], "post_time": "2022-01-17T10:02:43Z", "salary": {"currency": "HKD", "max": 19999, "min": 14000, "period": "monthly", "term": null}, "salary_visible": true, "title_keywords": ["clinic assistant"], "responsibilities": ["data entry and filing", "ad-hoc tasks", "incoming phone calls", "invoicing", "purchase", "prepare documents"], "requirements": {"degrees": ["hkdse"], "majors": [], "languages": ["english", "mandarin"], "language_level": ["good command"], "hard_skills": ["excel", "outlook", "word", "ms office"], "soft_skills": ["detail-minded", "self-motivated", "independent", "work under pressure"], "languages_combined": [{"language": "english", "language_level": ["good command"]}, {"language": "mandarin", "language_level": ["good command"]}]}, "experience_required": {"duration": [], "field": []}}, {"job_id": "100003009048203", "location_code": "hk", "company": "Sainsbury's Argos Asia Limited", "job_title": "Assistant Merchandiser - Home", "description": "We are a UK owned gift and health & beauty company located in TST East. Our office is a convenient 10 minute walk from the TST East or Hung Hom MTR station. We offer an interesting and diverse product range to our international retailers and distributors.\u00a0We are looking to recruit a Merchandiser with experience in managing direct to retail global accounts for mass market.\u00a0\u00a0\n\n\u00a0Role KPIs include:\n\n\n\nEfficiently processing stock/customers POs across your assigned factory base\nBespoke product & packaging development (where required) on your retail accounts\nEfficiently processing POs and managing the critical path end to end\nDriving on time deliveries\nDriving cost downs\nDeveloping & maintaining strong/cooperative relationships with your factory contacts; retail customers and your colleagues across the NPD/Design \u2013 QA/QC \u2013 Shipping teams\nEnsuring efficient processing of all admin functions in relation to retailer set up forms etc.\nAssisting the merchandising team with multiple admin duties across your slow season\n\nIf you are looking for a career move, not just a \u201cjob\u201d \u2013 we are interested in talking to you. You need to be highly motivated, organised and calm under pressure. You must have experience working in a fast-paced environment. You must have a good command (spoken and written) in English, Mandarin and Cantonese. You will have at least 3 years\u2019 experience in a merchandising role. You will be a natural problem-solver and excellent communicator. You must be proficient in Microsoft Excel, Word and Outlook. Experience with an ERP system is highly regarded, but not necessary as full training will be provided.\u00a0 Immediate availability is preferred.\u00a0\n\nFor the right candidate we offer flexible working hours, 13th month salary and discretionary bonus. If you are interested in joining our team, please email your cover letter, CV, expected starting salary, title of the position you are applying for in email subject and available starting date by clicking \u201cApply Now\u201d \u2013 note if you don\u2019t include all just listed, your application will be discarded! Attention to detail is a critical requirement for this role. Previous applicants\u2019 please do NOT apply.", "employment_types": ["Full Time", "Permanent"], "selling_points": [], "locations": ["Ngau Tau Kok"], "categories": ["Merchandising & Purchasing", "Others", "Procurement / Purchasing / Sourcing"], "post_time": "2022-01-14T05:51:41Z", "salary": {"currency": null, "max": null, "min": null, "period": "monthly", "term": null}, "salary_visible": false, "title_keywords": ["assistant merchandiser"], "responsibilities": [], "requirements": {"degrees": [], "majors": [], "languages": [], "language_level": [], "hard_skills": [], "soft_skills": [], "languages_combined": []}, "experience_required": {"duration": [], "field": []}}, {"job_id": "100003009049342", "location_code": "hk", "company": "Monty Limited", "job_title": "Senior Merchandiser", "description": "Clinical Assistant at Skincentral\n\nWhy Should You Join Us?\n\nWe are one of the largest dermatology specialist clinics in Hong Kong. We give you options and possibilities to the freedom to believe in what you believe. \u00a0We are a family guided by shared values and a commitment. We are a group of people with growth mindset who are always ready to tackle challenges and value the opportunities to solve complex problems. We are a passionate team who are committed to provide the highest quality possible to our clients. If this sounds exciting to you, Welcome to Skincentral.\n\nYou have a purpose, unique talents and NOW is the time to embrace it, live it and put it to work. At Skincentral, we value incredible people with incredible skills -but your commitment to a greater cause is something we value even more. This is the heartbeat of our organization and your time will be spent in a supportive, team environment with resources to help you flourish.\n\nSkincentral\u2019s Clinical Assistants are highly-valued and professional team members with an important voice in this organization. \u00a0In this role, you will help to perform a variety of medical and cosmetic procedures, as well as certain clerical services. We are looking for an attentive and dedicated individual, with a fine-tuned sense of responsibility, the ability to work collaboratively in a team-oriented atmosphere, and a commitment to delivering the highest quality medical and cosmetic care to our valued clients.\n\nWhat You Can Bring To Us?\u00a0\n\nAssist Doctors with medical, cosmetic consultations procedures\nPerform \u00a0routine clinical and administrative tasks to assist with keeping the clinic running smoothly\nEducate patients about pertinent treatment and procedures\nAssist patients with their enquiries on various communication channels\nFront desk duties- be the faces of Skincentral that we can be proud of\n\nWe need individuals who possess the following skillsets:\n\nExcellent customer service skills\nStrong interpersonal skills\u00a0\u00a0\nA good command of English, Cantonese & Putonghua (written and spoken)\u00a0\nAbility to work under high pressure and a good team player\nA growth mindset to pick up new skills and knowledge quickly\nGenuine interests in the field of medical and aesthetics treatments\n\nSkincentral offers our people a true opportunity to live their calling to care while experiencing the support of a comprehensive network, professional growth, trusted leadership, generous benefits and an amazing quality of life with an attractive clinic location at Central. We are proud to provide high quality service to our clients through state-of-the-art technology, clinical resources and professional expertise with a patient-centered approach that emphasizes Skincentral's mission and commitment to quality, compassion and service.", "employment_types": ["Full Time"], "selling_points": [], "locations": ["Kowloon Bay"], "categories": ["Merchandising & Purchasing", "Others"], "post_time": "2022-01-14T08:30:36Z", "salary": {"currency": null, "max": null, "min": null, "period": "monthly", "term": null}, "salary_visible": false, "title_keywords": ["senior merchandiser"], "responsibilities": ["quality", "procedures", "communication", "customer service", "administrative tasks"], "requirements": {"degrees": [], "majors": [], "languages": ["cantonese", "putonghua", "english"], "language_level": ["good command"], "hard_skills": [], "soft_skills": ["passionate", "attentive", "supportive", "customer service skills", "good team player", "compassion", "sense of responsibility", "unique", "communication", "committed", "comprehensive", "interpersonal skills", "work under high pressure", "patient", "genuine", "leadership"], "languages_combined": [{"language": "cantonese", "language_level": ["good command"]}, {"language": "putonghua", "language_level": ["good command"]}, {"language": "english", "language_level": ["good command"]}]}, "experience_required": {"duration": [], "field": []}}, {"job_id": "100003009047181", "location_code": "hk", "company": "Continental Conair Ltd", "job_title": "Senior Merchandiser / Merchandiser", "description": "This key objective of the role is to assure the smooth operations of our agriculture product supply chain to safeguard our investments. Highlight of the job involves the followings :\n\nFollow closely the product price in multiple markets\nAllocation of products sales through various brokers\nAssure quality assurance activities are timely performed\nMonitor logistic arrangements to effectively support product delivery\nEnsure the purchases of supply and equipment follow established guideline\nEvaluate brokers performance for business priority decision\n\nWe invite interested party with different supply chain backgrounds to apply. We strongly believe right personality and determination, together with our training, will assure a right fit.\n\n\n\nQualifications and personality :\u00a0\nDegree holder with at least 5 years merchandising experience\nOpen minded, confident and determined to success \u00a0\u00a0\nExcellent communicator with all levels\nAn individual who highly values integrity\nFluent in English, Cantonese and Mandarin. Spanish will be an advantage\n\nWe offer an attractive remuneration package to the right candidate. Interested parties are welcome to send your full resume with present and expected salary by clicking \"Apply Now\". All personal data will be used for recruitment purpose only.\u00a0\u00a0", "employment_types": ["Full Time", "Permanent"], "selling_points": [], "locations": ["Not Specified"], "categories": ["Manufacturing", "Production Planning / Control", "Merchandising & Purchasing", "Others", "Procurement / Purchasing / Sourcing"], "post_time": "2022-01-15T03:49:46Z", "salary": {"currency": null, "max": null, "min": null, "period": "monthly", "term": null}, "salary_visible": false, "title_keywords": ["merchandiser", "senior merchandiser"], "responsibilities": ["operations", "monitor", "quality", "merchandising", "evaluate"], "requirements": {"degrees": ["degree holder"], "majors": [], "languages": ["cantonese", "english", "spanish", "mandarin"], "language_level": ["advantage", "fluent"], "hard_skills": [], "soft_skills": ["confident", "determined", "timely", "integrity", "open minded", "smooth", "communicator"], "languages_combined": [{"language": "cantonese", "language_level": ["fluent"]}, {"language": "english", "language_level": ["fluent"]}, {"language": "spanish", "language_level": ["advantage"]}, {"language": "mandarin", "language_level": ["fluent"]}]}, "experience_required": {"duration": ["at least 5 years"], "field": ["merchandising"]}}, {"job_id": "100003009042270", "location_code": "hk", "company": "ConnectedGroup Limited", "job_title": "Merchandiser- Food", "description": "Overview:\n\nOrenji Creation Limited is a design, gift and premium company that provides professional one-stop service to international well-known brands in Asia Pacific. To Cope with our rapid expansion, we are now inviting high caliber candidate pursuing to join our team in Hong Kong.\n\nJob Requirement:\n\nDiploma holder or above\n1-2 years or above relevant working experience (Fresh Graduate are also welcomed)\nSolid knowledge of gift & premium industry\nStrong in Product Development\nHardworking, Self-motivated, Independent, Attention to detail, Teamwork spirit\nStrong negotiation skill\nAble to work under pressure and tight deadline\nProficiency in PC skills\nFluent in written and spoken English and Mandarin\nImmediate available preferred\n\nResponsibilities:\n\nTo source factories for quality comparison\nTo coordinate with internal parities and follow up production from product development to delivery\nClosely Monitor the production process\nTo solve problem with the factories to ensure product quality and meet tight schedule\nCoordinate with Lab Test Company, ensure the product meet Client\u2019s product safety standard\nFrequent Travel to PRC is required\n\nInterested parties please send a cover letter stating your expected salary, resume and a full set of your portfolio to us.\n\n*All information will be treated as confidential and used solely for recruitment purposes.\n\nInterested parties, please click Apply Now to submit your full resume.", "employment_types": ["Full Time", "Permanent"], "selling_points": ["Well-established buying office", "Food experience is preferred", "Attractive Remuneration Package"], "locations": ["Not Specified"], "categories": ["Merchandising & Purchasing", "Others", "Procurement / Purchasing / Sourcing"], "post_time": "2022-01-12T06:47:37Z", "salary": {"currency": null, "max": null, "min": null, "period": "monthly", "term": null}, "salary_visible": false, "title_keywords": ["merchandiser"], "responsibilities": ["production process", "monitor", "quality", "coordinate with", "schedule"], "requirements": {"degrees": ["diploma holder", "fresh graduate"], "majors": [], "languages": ["english", "mandarin"], "language_level": ["fluent"], "hard_skills": ["pc skills"], "soft_skills": ["self-motivated", "independent", "teamwork spirit", "attention to detail", "negotiation skill", "hardworking", "work under pressure"], "languages_combined": [{"language": "english", "language_level": ["fluent"]}, {"language": "mandarin", "language_level": ["fluent"]}]}, "experience_required": {"duration": ["1-2 years"], "field": ["relevant working experience"]}}, {"job_id": "100003009047876", "location_code": "hk", "company": "Wright Life Pharmaceutical Limited", "job_title": "Merchandiser", "description": "Responsibilities:\n\nSupply chain and order management\nProject management on product development\nSourcing for new vendors and new products\nActively involve and coordinate with the team on problem solving related to material and component supply; quality and engineering issues, to keep product development schedule and order schedule on time.\nPrice negotiation\nHandle sample approval and delivery processes\nLiaise with vendors, internal departments and oversea customers to ensure timely and accurate response at all time.\nBusiness travel (China or other countries) is required\n\nRequired Qualifications:\n\nAt least 5 years or above merchandising experience in electric appliance\nDegree holder\nProficiency in PC application\nHard working, details minded, well-organized.\nAble to work under pressure and well team oriented\nAvailable to make frequent trips outside office, to mainland China or Overseas are required\nFluent in Chinese and English\n\nWe offer an attractive remuneration package and comprehensive fringe benefits to suitable candidate.\u00a0 Interested parties, please send your application together with a detail resume including availability, present and expected salary,by e-mail via \"Apply now\" . Your interest will be treated in strict confidence and only shortlisted candidates will be notified. All personal data will be treated in strict confidence and collected for recruitment purposes only.", "employment_types": ["Full Time"], "selling_points": ["5\u5929\u5de5\u4f5c+\u9280\u884c\u5047\u671f+\u96d9\u7ce7", "\u8ddf\u9032OEM\u53caODM\u5ba2\u6236\u53ca\u4f9b\u61c9\u5546\u8a02\u55ae", "\u5177\u4fdd\u5065\u98df\u54c1\u6216\u4e2d\u6210\u85e5\u7d93\u9a57\u8005\u512a\u5148"], "locations": ["Tsuen Wan Area"], "categories": ["Manufacturing", "Product Development / Management", "Production Planning / Control", "Merchandising & Purchasing", "Others"], "post_time": "2022-01-14T10:06:27Z", "salary": {"currency": null, "max": null, "min": null, "period": "monthly", "term": null}, "salary_visible": false, "title_keywords": ["merchandiser"], "responsibilities": ["order management", "price negotiation", "coordinate with", "quality", "merchandising", "project management", "schedule", "liaise with", "work under pressure"], "requirements": {"degrees": ["degree holder"], "majors": [], "languages": ["english", "chinese"], "language_level": ["fluent"], "hard_skills": ["problem solving", "project management", "make", "pc"], "soft_skills": ["negotiation", "timely", "hard working", "well-organized", "problem solving", "project management", "accurate", "work under pressure"], "languages_combined": [{"language": "english", "language_level": ["fluent"]}, {"language": "chinese", "language_level": ["fluent"]}]}, "experience_required": {"duration": ["at least 5 years"], "field": ["merchandising"]}}, {"job_id": "100003009051731", "location_code": "hk", "company": "Asia Airfreight Terminal Co Ltd", "job_title": "Purchasing Supervisor", "description": "Our Client is a Well-established buying office, they are looking for a Merchandiser to join their expanding team.\n\nKey Job Responsibilities include:\n\n\n\nResponsible for the whole merchandising process and ensure products meet customers' requirements\nResponsible for order follow-up, sampling, product development, price negotiations, quality control, and shipments, etc.\nWork closely with internal parties to ensure production schedules are aligned with company strategy.\nWork closely with the quality team and ensure products meet QA requirements\nMaintain & update product record to prepare related documents\nMaintain strong business relationships with supplier for product development and production\n\n\nOther requirements include:\n\nTertiary education with a minimum of 2 years experience in merchandising, experience in food and near food items\nExperienced in product and project development, follow up and negotiation\nGood communication skills, self-motivated, proactive, and open-minded\nExcellent in English, Cantonese, and Mandarin, both spoken and written\nTravel if necessary", "employment_types": ["Full Time", "Permanent"], "selling_points": ["5-day week, double pay, performance bonus", "Provide procurement services", "Capable to work on cost analysis"], "locations": ["Airport Area"], "categories": ["Admin & HR", "Clerical / Admin Staff", "Merchandising & Purchasing", "Others", "Procurement / Purchasing / Sourcing"], "post_time": "2022-01-16T21:51:15Z", "salary": {"currency": null, "max": null, "min": null, "period": "monthly", "term": null}, "salary_visible": false, "title_keywords": ["supervisor"], "responsibilities": ["schedules", "related documents", "merchandising", "quality", "maintain", "quality control", "internal parties"], "requirements": {"degrees": [], "majors": [], "languages": ["cantonese", "english", "mandarin"], "language_level": ["excellent"], "hard_skills": [], "soft_skills": ["communication skills", "self-motivated", "negotiation", "open-minded", "proactive"], "languages_combined": [{"language": "cantonese", "language_level": ["excellent"]}, {"language": "english", "language_level": ["excellent"]}, {"language": "mandarin", "language_level": ["excellent"]}]}, "experience_required": {"duration": ["minimum of 2 years"], "field": ["food", "merchandising", "education"]}}, {"job_id": "100003009048049", "location_code": "hk", "company": "Manpower Services (Hong Kong) Limited", "job_title": "Assistant Procurement Manager (Performance & Excellence)(Energy Company)(60K-70K)(850K-1M)", "description": "\u8077\u4f4d\u8077\u8cac:\n\n\u8ca0\u8cacODM/OEM\u9805\u76ee\uff0c\u7368\u7acb\u8ddf\u9032\u6574\u500b\u6d41\u7a0b\n\u8a2d\u8a08\u53ca\u751f\u7522\u9032\u5ea6\u63a7\u5236\uff0c\u78ba\u4fdd\u7522\u54c1\u8cea\u91cf\n\u8ddf\u9032\u5ba2\u6236\u53ca\u4f9b\u61c9\u5546\u8a02\u55ae\uff0c\u8207\u5ba2\u6236\u4fdd\u6301\u826f\u597d\u95dc\u4fc2\n\u8655\u7406\u5831\u50f9\u548c\u767c\u7968\uff0c\u7269\u6d41\u5b89\u6392\n\u8077\u4f4d\u8981\u6c42:\n\n\u4e2d\u4e94\u6216\u4ee5\u4e0a\u7a0b\u5ea6\n3\u5e74\u6216\u4ee5\u4e0aODM/OEM\u9805\u76ee\u5de5\u4f5c\u7d93\u9a57\uff0c\u5177\u4fdd\u5065\u98df\u54c1\u6216\u4e2d\u6210\u85e5\u7d93\u9a57\u8005\u512a\u5148\u8003\u616e\n\u826f\u597d\u7cb5\u8a9e\u3001\u826f\u597d\u666e\u901a\u8a71\u53ca\u826f\u597d\u82f1\u8a9e\n\u5177\u6709\u57fa\u672c\u96fb\u8166\u64cd\u4f5c\u77e5\u8b58\uff0cMicrosoft Office\u53ca\u61c2\u5009\u9821/\u901f\u6210\u8f38\u5165\u6cd5\n\u826f\u597d\u6e9d\u901a\u6280\u5de7\u3001\u7d30\u5fc3\u53ca\u5177\u7d44\u7e54\u529b\n\u7d93\u9a57\u8f03\u5c11\u8005\u53ef\u8003\u616e\u70ba\u8ddf\u55ae\u6587\u54e1", "employment_types": ["Permanent"], "selling_points": ["Good Salary Package", "Excellent Salary Package with Bouns (Extra ORSO)", "Strong Support from Company"], "locations": ["Others"], "categories": ["Merchandising & Purchasing", "Others", "Procurement / Purchasing / Sourcing"], "post_time": "2022-01-14T04:36:30Z", "salary": {"currency": null, "max": null, "min": null, "period": "monthly", "term": null}, "salary_visible": false, "title_keywords": ["manager", "assistant"], "responsibilities": [], "requirements": {"degrees": [], "majors": [], "languages": [], "language_level": [], "hard_skills": [], "soft_skills": [], "languages_combined": []}, "experience_required": {"duration": [], "field": []}}, {"job_id": "100003009042081", "location_code": "hk", "company": "Artech Design & Productions Company Limited", "job_title": "General Clerk / Office Clerk / Administrative Assistant (6 Months Contract/ Full Time)", "description": "A globally reputable company is looking for a Procurement Manager (Corporate & Marketing). With a rapid growing business, they are looking for the right talent to join their business.\n\nResponsibilities:\n\nAs a Procurement Manager (Corporate & Marketing), you will direct report to the Senior Manager. You will be responsible for supporting complex procurement projects across all department / categories. You will be responsible for ensuring all project procurement execution align with internal policy. You will be responsible for leading global procurement strategy and precise vendor selection for all aspects of corporate services. You will be responsible for managing T&Cs negotiation with suppliers. You will be responsible for updating internal procurement policy and procedures. You will be responsible for any ad hoc tasks.\n\nRequirements:\n\nDegree holder in Procurement, Supply Chain, Sourcing, Purchasing, Facilities Management or Business Administration related discipline\nProcurement qualifications will be an advantage\nKnowledge of procurement control and governance\nMinimum of 4 to 5 years working experience in sizeable organizations, highly preferred large size of companies\nWilling to learn and have can-do attitude\nMS office applications (Word, Excel, Power Point)\nThe ability to communicate effectively to all levels of the organization and interface with cross-functional people in the group is essential\nPossesses excellent communication skills with good command in both written and spoken English and Chinese\n\nThis is an excellent opportunity for individuals seeking a Procurement Manager (Corporate & Marketing) role for a large reputable corporation that is able to offer a great package and excellent working environment.\n\nTo apply online, please click the \"Apply\" button below. For a confidential discussion about this role, please contact Candice Yung on +3907 3934", "employment_types": ["Full Time", "Contract"], "selling_points": ["6 Months Contract/ Full Time", "5 day work per week", "Good communication and interpersonal skills"], "locations": ["Tuen Mun Area"], "categories": ["Admin & HR", "Clerical / Admin Staff", "Receptionist", "Merchandising & Purchasing", "Others"], "post_time": "2022-01-12T05:59:21Z", "salary": {"currency": null, "max": null, "min": null, "period": "monthly", "term": null}, "salary_visible": false, "title_keywords": ["administrative assistant", "office clerk", "general clerk"], "responsibilities": ["ad hoc tasks", "procedures", "report"], "requirements": {"degrees": ["degree holder"], "majors": ["business administration"], "languages": ["english", "chinese"], "language_level": ["excellent", "good command"], "hard_skills": ["excel", "word", "facilities management", "power point", "ms office"], "soft_skills": ["communication skills", "willing to learn", "can-do attitude"], "languages_combined": [{"language": "english", "language_level": ["excellent", "good command"]}, {"language": "chinese", "language_level": ["excellent", "good command"]}]}, "experience_required": {"duration": ["minimum of 4 to 5 years"], "field": []}}, {"job_id": "100003009041176", "location_code": "hk", "company": "Mid Ocean Hong Kong Ltd", "job_title": "Procurement Officer (Promotional Products)", "description": "Duties\n\n\nHandle end to end procurement cycle from vendor sourcing, tendering , cost analysis, supplier negotiation to fulfillment\nCommunicate and co-ordinate with internal stakeholders regarding their purchasing needs and feedback to vendors\nTake a proactive role to negotiate with vendors for obtaining the better terms and conditions for the Company\u2019s interest\nEnsure the procurement cycle compliance to the internal policy; capable to work on cost analysis and vendor recommendation and selection\nExpand and consolidate vendor base to support business objectives\n\n\u00a0Requirements\u00a0\n\n\nBachelor Degree in Supply Chain, Business Administration, Procurement or related discipline\nMinimum 4 years\u2019 of experience in procurement or related disciplines with at least 1 year in supervisory level\nExperience in managing tender process and preparation of tender documents will be a plus\nProficiency in MS Office especially Excel, Word, PowerPoint\nGood command of both written and spoken English and Chinese\nProficiency in written English will be an advantage\nAble to work independently and under pressure\nHonest, responsible and self-motivated\nStrong communication, negotiation and analytical skills\n\nWe offer the right incumbent attractive remuneration package including 5-day work week, 13 days annual leave, double pay, performance bonus, medical scheme, life insurance, travel allowance and education subsidy.\n\nInterested parties please send your full resume with reference no., recent and expected salary to: Human Resources Department, Asia Airfreight Terminal Co. Ltd., 10 Chun Ping Road, Hong Kong International Airport, Lantau, Hong Kong OR Fax to 2286 0374 OR Please click \u201cApply Now\u201d to submit your application.\n\nTo know more about AAT, please visit http://www.aat.com.hk\n\nWe are an equal opportunity employer and welcome applications from all qualified candidates. We will not be responsible for any disclosure or the loss of personal data during transmission. All personal data collected will be used for recruitment only. Information of unsuccessful candidates will be destroyed after 3 months from the date of application.", "employment_types": ["Full Time", "Permanent"], "selling_points": ["Good command in English and Mandarin", "2 years relevant experience", "Salary negotiable ; 5 days working ; double pay"], "locations": ["Lai Chi Kok"], "categories": ["Merchandising & Purchasing", "Sundries", "Others", "Procurement / Purchasing / Sourcing"], "post_time": "2022-01-13T05:33:57Z", "salary": {"currency": null, "max": null, "min": null, "period": "monthly", "term": null}, "salary_visible": false, "title_keywords": ["procurement officer"], "responsibilities": ["co-ordinate with", "fulfillment", "compliance", "tendering", "cost analysis"], "requirements": {"degrees": ["degree", "bachelor"], "majors": ["business administration"], "languages": ["english", "chinese"], "language_level": ["advantage", "proficiency", "good command"], "hard_skills": ["excel", "plus", "word", "powerpoint", "analytical skills", "scheme", "ms office"], "soft_skills": ["work independently", "self-motivated", "under pressure", "negotiation", "responsible", "analytical skills", "communication", "honest"], "languages_combined": [{"language": "english", "language_level": ["proficiency", "advantage", "good command"]}, {"language": "chinese", "language_level": ["proficiency", "good command"]}]}, "experience_required": {"duration": ["minimum 4 years", "at least 1 year"], "field": ["related", "supervisory level", "procurement"]}}, {"job_id": "100003009046206", "location_code": "hk", "company": "Shiseido Hong Kong Limited", "job_title": "Assistant Manager - Demand Planning, Shiseido Fragrance Division and DG Beauty", "description": "Responsibilities:\n\nPerform general Reception and Administrative duties;\nHandling telephone calls and incoming & outgoing courier arrangements;\nInventory control and maintenance of office equipment;\nHandle and follow up of purchase orders and quotation for materials purchase;\nManage and update all purchasing documents and records;\nDaily communications with suppliers;\nAssist in handling purchasing orders with suppliers and arranging delivery schedule;\nProvide clerical and administrative support to the team.\nRequirements:\nHigher diploma or above;\nProficiency in MS Word/ MS Excel;\n1-year working experience or above (Fresh graduates will be also considered);\nSelf-motivated, hardworking, and willing to learn;\nFair of both spoken and written in English, Chinese and Mandarin.", "employment_types": ["Full Time"], "selling_points": ["Maximize sales and inventory management", "Sales analysis and strategy development", "Demand planning and product ordering"], "locations": ["Kowloon Bay"], "categories": ["Professional Services", "Business Analysis / Data Analysis", "Sales, CS & Business Devpt", "Business Development", "Merchandising & Purchasing", "Others"], "post_time": "2022-01-13T09:56:56Z", "salary": {"currency": null, "max": null, "min": null, "period": "monthly", "term": null}, "salary_visible": false, "title_keywords": ["assistant manager"], "responsibilities": ["communications with", "administrative support", "maintenance of office equipment", "quotation", "delivery schedule", "purchase", "inventory control", "administrative duties"], "requirements": {"degrees": ["higher diploma or above"], "majors": [], "languages": ["english", "chinese", "mandarin"], "language_level": [], "hard_skills": ["ms excel", "ms word"], "soft_skills": ["self-motivated", "willing to learn", "hardworking"], "languages_combined": [{"language": "english", "language_level": []}, {"language": "chinese", "language_level": []}, {"language": "mandarin", "language_level": []}]}, "experience_required": {"duration": ["1-year"], "field": []}}, {"job_id": "100003009050586", "location_code": "hk", "company": "NET-A-PORTER", "job_title": "Inventory Manager", "description": "In a nutshell\n\nProvide support to the department to deliver great product at supermarket price by fulfilling our Global Sourcing Strategy and successfully achieve our targets of the department\n\nWhat I need to do\n\nAssist Merchandiser / Senior Merchandiser on implementing all aspects of the department strategy to deliver all KPIs including shipment and sales participation targets\nUnderstand the use of Periodic Shipment Report in the management of shipment position of the department\nSupport Merchandiser / Senior Merchandiser in the sourcing processes, administrative work and documentations filing, from supplier engagement, supplier set up through to shipment delivery\nLiaise with suppliers on quotation sheets submission and ensuring samples are delivered to our UK colleagues on a timely basis\nSupport the order management process from purchase order to shipment delivery; maintain accurate purchase order records and critical path trackers, monitoring delivery and flagging potential risk on a timely manner\nAssist in the sealing and approval process from order through to delivery with accurate record keeping\nEstablish strong communication with UK & Asia colleagues and suppliers via weekly progress meetings, e-mails, SKYPE and trips, etc.\nAttend weekly progress meetings with cross functional colleagues in Asia, UK colleagues and suppliers to provide a clear visibility of order status\nHave a clear understanding of our operating procedures and be familiar with all necessary systems and our ways-of-working\nUnderstand our business vision and goal and play a positive role in making Sainsbury\u2019s Asia a great place to work\n\nWhat I need to know\n\n1-2 years working experience in Merchandising is preferred but not limited to.\nGood written and spoken English and Chinese (Cantonese & Mandarin)\nGood communication skills\nUniversity degree and above is prefer\nWe offer a competitive package, including a 5 day week, 17 days Annual Leave, double pay,\u00a0performance bonus,\u00a0MPF, a medical scheme, flexible working environment, plenty of work variety and a great team atmosphere. Interested candidates please go to the website below for application.\nhttps://sainsburys.jobs/asia/", "employment_types": ["Full Time", "Permanent"], "selling_points": ["Lead the inventory team to meet outline KPI", "Experience of leading teams in warehouse/retail", "13 AL, bank holiday"], "locations": ["Tsing Yi"], "categories": ["Transportation & Logistics", "Others", "Inventory / Warehousing", "Merchandising & Purchasing", "Others"], "post_time": "2022-01-14T10:50:32Z", "salary": {"currency": null, "max": null, "min": null, "period": "monthly", "term": null}, "salary_visible": false, "title_keywords": ["manager"], "responsibilities": ["provide support", "management", "order management", "administrative work", "mpf", "quotation", "monitoring", "a timely manner", "procedures", "systems", "communication", "merchandising", "purchase", "maintain", "kpis", "liaise with suppliers", "report"], "requirements": {"degrees": ["university degree"], "majors": [], "languages": ["cantonese", "english", "chinese", "mandarin"], "language_level": ["good"], "hard_skills": ["goal", "scheme", "documentations"], "soft_skills": ["flexible", "communication skills", "timely", "communication", "clear", "accurate", "positive"], "languages_combined": [{"language": "cantonese", "language_level": ["good"]}, {"language": "english", "language_level": ["good"]}, {"language": "chinese", "language_level": ["good"]}, {"language": "mandarin", "language_level": ["good"]}]}, "experience_required": {"duration": ["1-2 years"], "field": ["merchandising"]}}, {"job_id": "100003009049079", "location_code": "hk", "company": "Sa Sa Cosmetic Company Limited", "job_title": "Brand Executive (Private Label)", "description": "YOOX NET-A-PORTER GROUP is the e-commerce leader in online luxury and fashion.\u00a0Operations are now seeking a talented Inventory Manager to join the Inventory team base in Tsing Yi Warehouse.\n\n\n\nHere is a breakdown of what you\u2019ll be doing:\n\nMeasure the inventory performance against outlined KPIs\nAssist in the modification and development of the company\u2019s inventory management system\nPlan,\u00a0manage and deliver stock-taking activities including PI, stock adjustments and cycle counting\nIdentify, evaluate, and implement where appropriate new Inventory Management methodologies\nManage the stock conditioning program ensuring that value added services including cleaning, repair and refurbishment of items is undertaken in a considerate, timely and cost-effective manner\nSource and purchase relevant packaging materials\nPlan, organize and maintain suitable systems to monitor and purchase packaging materials necessary to fulfil orders as per forecasts\nThe type of person we are looking for:\n\nProven commercial experience of leading teams in a warehouse/logistics/retail environment ( clothing/manufacture industry preferred but not necessary)\u00a0\nSignificant experience of motivating teams to achieve deadlines in a target-driven environment\nStrong leadership skills with experience of performance management, coaching and mentoring\nExcellent written and oral communication skills (both Chinese and English)\nHigh computer literacy\nWorking Hours\n\nMonday to Friday 930am-630pm\nLocation\n\nTsing Yi (10 mins shuttle bus away from Tsing Yi station)\n\nBesides a competitive salary, we can offer you:\n\nPerformance bonus schemes\n13 Days Annual Leaves & Bank Holiday\nCareer path & training\nOur famous staff discount along with exclusive staff sales\nPrivate healthcare\nFor Interested parties, please email your CV and expected salary to\u00a0hkrecruitment@ net-a-porter.com\u00a0or WhatsApp 6651 2251 for further enquiries.", "employment_types": ["Full Time", "Permanent"], "selling_points": ["Drive sales and brand development", "Knowledge and understanding of cosmetics market", "Experience in FMCG"], "locations": ["Chai Wan"], "categories": ["Marketing / Public Relations", "Marketing - Brand / Product Management", "Merchandising & Purchasing", "Others", "Procurement / Purchasing / Sourcing"], "post_time": "2022-01-14T08:04:48Z", "salary": {"currency": null, "max": null, "min": null, "period": null, "term": null}, "salary_visible": false, "title_keywords": ["executive"], "responsibilities": ["cost", "management", "operations", "inventory", "systems", "monitor", "teams", "inventory management", "evaluate", "repair", "purchase", "maintain", "logistics", "plan", "cleaning", "communication", "kpis"], "requirements": {"degrees": [], "majors": [], "languages": ["english", "chinese"], "language_level": ["excellent"], "hard_skills": ["e-commerce"], "soft_skills": ["communication skills", "oral", "timely", "leadership skills", "computer literacy", "driven"], "languages_combined": [{"language": "english", "language_level": ["excellent"]}, {"language": "chinese", "language_level": ["excellent"]}]}, "experience_required": {"duration": [], "field": ["commercial", "retail", "logistics", "performance management"]}}, {"job_id": "100003009046959", "location_code": "hk", "company": "Ka Hung Gloves Industrial Co Ltd", "job_title": "Sourcing Manager - Supermarket business", "description": "Responsibilities:\nPlan & execute the sales and promotions for frequent sales events for both online & offline\nAssist in preparing business analysis reports, and dealing with shop inquiries\nEnsure inventory levels of various product categories are controlled within reasonable size during both slack and peak seasons\nAnalyze business trends and consumer insights to deliver brand sales and market share targets\nDevelop marketing collaterals such as product display and promotional material to enhance brand image\nCoordinate with internal and external parties to maintain daily operation and ensure excellent execution of brand building\nDevelop and sustain strong working relationships with all internal stakeholders\nRequirements:\nDegree holder with at least 3-4 years relevant working experience. Experience in FMCG/ Beauty is a plus\nStrong market sense and awareness\nStrong analytical ability with excellent negotiation and communication skills\nProactive, detail-minded and able to work independently\nProficiency in Microsoft applications, particularly in excel applications\nExcellent spoken and written English and Chinese, proficiency in Mandarin will be an advantage\nCandidates with more experience will be considered as Senior Brand Executive\n\nWe offer\n\n5 - day work week\nMedical Benefits\nPerformance Bonus\nStaff Purchase Discounts\nStaff Recreation Activity\nShuttle Bus Service\nEducation Sponsorship\n\nInterested parties please send a full resume with current and expected salary\u00a0by clicking APPLY NOW.\n\nPlease visit our corporate website at\u00a0http://corp.sasa.com/en/home\u00a0to know more about us.\n\n(Sa Sa is an Equal Opportunity Employer and all qualified applicants will receive consideration for employment. Personal data collected will be kept confidential and used for recruitment purpose only)", "employment_types": ["Full Time"], "selling_points": ["University w/8 yrs sourcing exp. in supermarket", "Close relation w/food/non food/grocery suppliers", "Double pay,Discretionary bonus,medical insurance"], "locations": ["Ngau Tau Kok"], "categories": ["Hospitality / F & B", "Food & Beverage", "Merchandising & Purchasing", "Others", "E-commerce", "Business Development"], "post_time": "2022-01-14T01:52:34Z", "salary": {"currency": null, "max": null, "min": null, "period": "monthly", "term": null}, "salary_visible": false, "title_keywords": ["sourcing manager"], "responsibilities": ["product categories", "consumer insights", "preparing business analysis reports", "inventory", "marketing collaterals", "coordinate with", "internal and external parties", "develop", "daily operation", "analyze business trends", "maintain", "plan", "working relationships"], "requirements": {"degrees": ["degree holder"], "majors": [], "languages": ["english", "chinese", "mandarin"], "language_level": ["advantage", "excellent", "proficiency"], "hard_skills": ["excel", "plus", "microsoft applications"], "soft_skills": ["detail-minded", "communication skills", "work independently", "negotiation", "strong market sense", "proactive"], "languages_combined": [{"language": "english", "language_level": ["advantage", "excellent"]}, {"language": "chinese", "language_level": ["advantage", "excellent"]}, {"language": "mandarin", "language_level": ["proficiency", "advantage", "excellent"]}]}, "experience_required": {"duration": ["at least 3-4 years"], "field": ["brand", "fmcg", "beauty", "relevant working experience"]}}, {"job_id": "100003009049682", "location_code": "hk", "company": "TDF Asia Limited", "job_title": "Project Coordinator (Manufacturing for Props, Window Display, Pop-up Store)", "description": "The Role\nTo support our Fragrance Division, we are currently recruiting an Assistant Manager \u2013 Demand Planning, who will be refining the advantages and moving our business to ensure delivery of the annual goal and objectives\n\nJob Responsibilities:\n\nDrive business objectives and to maximize sales and inventory management with the support of teammates.\nManage the demand planning, product ordering and inventory status including monitoring, forecasting and distribution of stocks.\nDevelop effective forecast models based on market trends, demand assumption and demand. Ensure the forecast accuracy and performance meet KPIs.\nCollaborate with marketing and sales to ensure the forecast accurately reflects new product launches and changes to existing products.\nCollaborate and drive a consensus approach by working with the internal team, Headquarters, Finance and Supply chain partners to obtain accurate and current information for demand forecasts.\nPrepare and share data visualizations, reports, briefings, and concise summary analyses to internal parties to drive the delivery of our plans and budgets.\nProvide business analysis, market research and market intelligence studies\nParticipate in ad hoc projects as assigned\n\nJob Requirements:\n\nDegree holder in Business Management or related disciplines\nMinimum 4 years of relevant experience with strong business acumen and solid experience in retail\nProven track record in demand planning\nSensitive to figures with strong analytical skills\nProficient with analysis and presentations\nForward thinking and result oriented.\nDetail-minded, mature, well-organized and able to work under pressure\nGood presentation and communication skills\nGood command of written and oral English\nProficiency in Mandarin is an added advantage\n\nWhat's on offer:\nBe part of a growing global organization with a portfolio of around 18 brands, competitive discretionary bonus, quarterly free goods across brands, medical benefits, birthday leave, flexible working hours, wellness facilities, learning sponsorship, and more.\u00a0\n\nInterested?\nPlease apply with your latest resume stating your notice period, current and expected remuneration package.\u00a0\nWe regret that only shortlisted candidates will be contacted.\u00a0\n\nShiseido Hong Kong is an Equal Opportunities Employer. All applications received will be treated in strict confidentiality and be used exclusively for employment purpose only.", "employment_types": ["Full Time", "Permanent"], "selling_points": [], "locations": ["Sham Shui Po"], "categories": ["Manufacturing", "Others", "Marketing / Public Relations", "Marketing - General / Support", "Merchandising & Purchasing", "Others"], "post_time": "2022-01-14T09:11:55Z", "salary": {"currency": null, "max": null, "min": null, "period": "monthly", "term": null}, "salary_visible": false, "title_keywords": ["project coordinator"], "responsibilities": ["collaborate with", "collaborate", "budgets", "data", "demand planning", "inventory", "monitoring", "market research", "develop", "inventory management", "reports", "ad hoc projects", "forecast", "plans", "business analysis", "kpis", "forecasting", "internal parties"], "requirements": {"degrees": ["degree holder"], "majors": ["related disciplines", "business"], "languages": ["english", "mandarin"], "language_level": ["advantage", "proficiency", "good command"], "hard_skills": ["business management", "demand planning", "analysis", "presentations", "analytical skills", "acumen"], "soft_skills": ["detail-minded", "communication skills", "oral", "flexible", "sensitive to figures", "well-organized", "mature", "analytical skills", "result oriented", "learning", "business acumen", "presentation", "work under pressure"], "languages_combined": [{"language": "english", "language_level": ["good command"]}, {"language": "mandarin", "language_level": ["proficiency", "advantage"]}]}, "experience_required": {"duration": ["minimum 4 years"], "field": ["business", "relevant experience", "retail"]}}, {"job_id": "100003009050195", "location_code": "hk", "company": "FnF Hong Kong Limited", "job_title": "Assistant Buyer / Assistant Merchandiser", "description": "Responsibilities\n\u00a0\u00a0\u00a0\u00a0\u00a0 coordinate multiple VM props & window display production projects\u00a0\n\u00a0\u00a0\u00a0\u00a0\u00a0 Assist to keep track on the project performance\u00a0\u00a0\n\u00a0\u00a0\u00a0\u00a0\u00a0 Handle ad hoc duties as assigned\nRequirements:\n\u00a0\u00a0\u00a0\u00a0\u00a0 Higher diploma holder or above, degree in Marketing, Event Management, Communication, Business Administration is preferable.\n\u00a0\u00a0\u00a0\u00a0\u00a0 At least 3 years in project management of Events & Exhibition, VM industries experiences.\n\u00a0\u00a0\u00a0\u00a0\u00a0 candidates with more experience will be considered for the position of Assistant Manager.\n\u00a0\u00a0\u00a0\u00a0\u00a0 Detailed - minded, independent & presentable; able to prioritize job tasks in tight timeline & organized manner.\n\u00a0\u00a0\u00a0\u00a0\u00a0 Good verbal and written communication in English, Cantonese, and Mandarin.\n\u00a0\u00a0\u00a0\u00a0\u00a0 Travelling is required.\n\u00a0\u00a0\u00a0\u00a0\u00a0 Office Location: Sham Shui Po\n\nWe offer:\n\n\u00a0\u00a0\u00a0\u00a0\u00a0 Birthday leave\n\u00a0\u00a0\u00a0\u00a0\u00a0 Performance bonus\n\nInterested candidates please send your full resume with expected salary and date of availability by \"Apply Now \". Consideration of applications will continue until the position is filled. Applications will be treated in strict confidential. Personal data collected will be used for recruitment purpose only", "employment_types": ["Full Time", "Permanent"], "selling_points": ["Follow through on delivery, stock allocation", "Replenishment and consolidation", "E-shop operation"], "locations": ["Yau Tsim Mong Area"], "categories": ["Merchandising & Purchasing", "Others", "Procurement / Purchasing / Sourcing", "E-commerce", "Product Management / Business Analyst"], "post_time": "2022-01-14T09:55:30Z", "salary": {"currency": null, "max": null, "min": null, "period": "monthly", "term": null}, "salary_visible": false, "title_keywords": ["assistant merchandiser", "assistant"], "responsibilities": ["coordinate", "ad hoc duties"], "requirements": {"degrees": ["degree", "higher diploma holder"], "majors": ["marketing", "business administration"], "languages": ["cantonese", "english", "mandarin"], "language_level": ["good"], "hard_skills": ["project management"], "soft_skills": ["organized", "independent", "able to prioritize", "presentable", "communication", "project management", "detailed"], "languages_combined": [{"language": "cantonese", "language_level": ["good"]}, {"language": "english", "language_level": ["good"]}, {"language": "mandarin", "language_level": ["good"]}]}, "experience_required": {"duration": ["at least 3 years"], "field": ["project management"]}}, {"job_id": "100003009053359", "location_code": "hk", "company": "Pasona Asia Co., Limited", "job_title": "Japanese Speaking Assistant Merchandiser (Multinational Corporation, Welcome Fresh Graduates)", "description": "Job Responsibilities:\n\nHandling full set I/E documents / shipping procedures and L/C document;\nFollow up shipment schedule and arrangement;\nPrepare Purchase Order liaise with overseas and China vendors;\nClerical works, Filing and Data Entry\n\nJob Requirements:\n\nF.6 or above with at least 3 years in shipping working experience;\nWell versed in MS Office applications including Word and Excel;\nFluent in English, Cantonese and Mandarin;\nPositive work attitude, able to work under pressure & independently;\nProficient in MS Office (including Word, Excel) and Chinese Word Processing;\nSelf-motivated, mature, responsible and detail-minded;\nImmediate availability is highly preferred\n\nWe Offer\n\nAlternative Saturday off,\nPublic holidays\nMarriage Leave\nMedical benefit, Education allowance", "employment_types": ["Full Time", "Permanent"], "selling_points": ["Support daily merchandising duties", "Eager to work in fast paced environment", "More experience will be considered as Merchandiser"], "locations": ["Tsim Sha Tsui"], "categories": ["Merchandising & Purchasing", "Fabrics", "Textiles", "Others"], "post_time": "2022-01-17T06:51:05Z", "salary": {"currency": null, "max": null, "min": null, "period": "monthly", "term": null}, "salary_visible": false, "title_keywords": ["assistant merchandiser"], "responsibilities": ["shipping", "data entry", "procedures", "purchase", "schedule", "liaise with"], "requirements": {"degrees": [], "majors": [], "languages": ["cantonese", "english", "chinese", "mandarin"], "language_level": ["proficient", "fluent"], "hard_skills": ["excel", "chinese word processing", "word", "ms office"], "soft_skills": ["detail-minded", "self-motivated", "independently", "responsible", "mature", "positive work attitude", "work under pressure"], "languages_combined": [{"language": "cantonese", "language_level": ["fluent"]}, {"language": "english", "language_level": ["fluent"]}, {"language": "chinese", "language_level": ["proficient"]}, {"language": "mandarin", "language_level": ["fluent"]}]}, "experience_required": {"duration": ["at least 3 years"], "field": []}}, {"job_id": "100003009050407", "location_code": "hk", "company": "Links International", "job_title": "Senior Supervisor - Merchandising", "description": "Our client, a reputable multinational garment firm, is seeking for a Japanese speaking Merchandiser to join their team in Hong Kong.\n\n\u00a0Responsibilities:\n\nHandle clients\u2019 orders from product development, sampling, production orders to delivery\nPerform quality inspection at the factory\nWork closely with vendors for issues settlement during production process\nMaintain and update production records and system data\nAssist in any ad hoc projects assigned by supervisor\n\n\u00a0Requirements:\n\nDiploma or above\n1-2 years\u2019 relevant experience in garment/ textile industry is preferred\nProficiency in spoken and written English and Mandarin. Business level in Japanese (JLPT Level 2 or above)\nSound knowledge in PC operations\nGood interpersonal and communication skills, well-organized, patient, self-initiative\nBusiness travel is required (China and Asia Pacific)\nImmediate available is preferred\nCandidates with more relevant experience, especially in Japanese apparel market, will be considered as Merchandiser\n\n\u00a0**Data collected will be used for recruitment purpose only**\n\u00a0**Interested parties please send resume in \"ENGLISH\" with CURRENT & EXPECTED salary and DATE OF AVAILABILITY or WhatsApp us at 9320 3296 for details**", "employment_types": ["Full Time", "Permanent"], "selling_points": ["Building material exp preferred", "Focus on sales & merchandising", "Double Pay + Bonus, 5 day work week"], "locations": ["Not Specified"], "categories": ["Engineering", "Manufacturing & Production", "Manufacturing", "Manufacturing Management", "Merchandising & Purchasing", "Others"], "post_time": "2022-01-14T10:20:06Z", "salary": {"currency": "HKD", "max": 34999, "min": 30000, "period": "monthly", "term": null}, "salary_visible": true, "title_keywords": ["merchandising", "supervisor"], "responsibilities": ["production process", "quality", "system data", "inspection", "maintain", "ad hoc projects"], "requirements": {"degrees": ["diploma or above"], "majors": [], "languages": ["japanese", "english", "mandarin"], "language_level": ["proficiency"], "hard_skills": ["pc operations"], "soft_skills": ["communication skills", "well-organized", "self-initiative", "patient", "interpersonal"], "languages_combined": [{"language": "japanese", "language_level": []}, {"language": "english", "language_level": ["proficiency"]}, {"language": "mandarin", "language_level": ["proficiency"]}]}, "experience_required": {"duration": ["1-2 years"], "field": ["garment", "relevant experience", "textile"]}}, {"job_id": "100003008946162", "location_code": "hk", "company": "Zollner Electronics HK Limited", "job_title": "Commodity Buyer", "description": "RESPONSIBILITIES\n\nSpecific responsibilities include but are not restricted to:-\n\nResponsible for merchandise mix and assortment planning in accordance to business objectives\nPlan and execute buying activities of designated product categories for maximizing sales and inventory productivity\nFollow through on delivery, stock allocation, replenishment and consolidation\nAnalyse sales, sell-through performance and share recommendations for achieving quantitative and qualitative goals\nManage e-shop operation including product listings, pricing, UAT and sales supporting tasks\nRegularly conduct market research and consistently strive to buy better in order to upgrade responsible merchandise assortment and department\u2019s sales performance\nPrepare weekly and monthly merchandising reports for management review\nDeliver administration and assistant duties to ensure smooth running of the team\nWork closely with Retail / Visual Merchandising / Marketing teams to ensure smooth operations\n\n\u00a0REQUIREMENTS\n\nDegree holder in Fashion, Textile and Clothing or business-related disciplines with minimum 3-4 years solid merchandising / buying experience in fashion retail company\nStrong knowledge and passion for fashion retail / business\nPositive working attitude, self-motivated and able to work under pressure and fast pace environment\nGood interpersonal, communication and presentation skills\nProficient in MS Office, strong in Excel (e.g. vlookup & pivot table)\nProficiency in both spoken and written English and Chinese\nImmediate available is prefered", "employment_types": ["Full Time"], "selling_points": ["Bachelor degree or above in related discipline", ">10 years experience with electronics technologies", "5-day work week, comprehensive fringe benefits"], "locations": ["Kowloon Bay"], "categories": ["Merchandising & Purchasing", "Electronics", "Others", "Procurement / Purchasing / Sourcing"], "post_time": "2022-01-12T23:26:07Z", "salary": {"currency": null, "max": null, "min": null, "period": "monthly", "term": null}, "salary_visible": false, "title_keywords": [], "responsibilities": ["inventory", "conduct market research", "merchandising", "planning", "plan", "management review", "administration", "product categories", "sales supporting tasks", "uat", "sales performance", "teams", "reports", "visual", "stock allocation", "manage e-shop", "ensure smooth operations", "product listings", "replenishment", "analyse"], "requirements": {"degrees": ["degree holder"], "majors": ["related disciplines", "business"], "languages": ["english", "chinese"], "language_level": ["proficiency"], "hard_skills": ["excel", "vlookup", "pivot table", "ms office"], "soft_skills": ["self-motivated", "passion for", "communication", "positive working attitude", "presentation skills", "interpersonal", "work under pressure"], "languages_combined": [{"language": "english", "language_level": ["proficiency"]}, {"language": "chinese", "language_level": ["proficiency"]}]}, "experience_required": {"duration": ["minimum 3-4 years"], "field": ["related", "merchandising", "business", "textile", "retail"]}}, {"job_id": "100003009044584", "location_code": "hk", "company": "Pacific Building Material (Project) Limited", "job_title": "Project Merchandiser", "description": "Senior Purchasing Supervisor - Building Material\n\nJob Description\n\n\nResponsible for building material e.g. aluminum/glass (glass curtain wall) quotation, contract, purchasing orders, order follow up, on time delivery, as well as handling client enquiries.\nWorking closely with own factories (South China) follow up purchasing orders to ensure on time delivery\nHandle client independently on construction project tendering and quotation, planning & organization skills and able to follow up details closely\nWorking independently in full Sales & purchasing duties from follow up the orders with clients, mass production quality control until shipment completed\n\nRequirements\n\n\nMinimum of 5 years of experience in building material sales & merchandising position\nKnowledge in building materials or aluminum/glass (glass curtain wall) products\nStrong analytical and project management skills, attention to details\nHigh sense of accountability and ownership\nGood interpersonal & communication skills and able to work under pressure\nGood command of written and spoken English and Chinese, Mandarin\nAbility to multi-task, highly adaptable in a dynamic growing environment.\nWilling to travel to China (for 1sttime training only)", "employment_types": ["Full Time", "Permanent"], "selling_points": [], "locations": ["Wan Chai"], "categories": ["Merchandising & Purchasing", "Others", "Procurement / Purchasing / Sourcing"], "post_time": "2022-01-13T04:39:46Z", "salary": {"currency": null, "max": null, "min": null, "period": "monthly", "term": null}, "salary_visible": false, "title_keywords": ["project merchandiser"], "responsibilities": ["quotation", "ensure on time delivery", "tendering", "quality control", "planning"], "requirements": {"degrees": [], "majors": [], "languages": ["english", "chinese", "mandarin"], "language_level": ["good command"], "hard_skills": ["project management", "dynamic"], "soft_skills": ["communication skills", "multi-task", "accountability", "adaptable", "project management skills", "dynamic", "attention to details", "interpersonal", "work under pressure"], "languages_combined": [{"language": "english", "language_level": ["good command"]}, {"language": "chinese", "language_level": ["good command"]}, {"language": "mandarin", "language_level": ["good command"]}]}, "experience_required": {"duration": ["minimum of 5 years"], "field": ["merchandising"]}}, {"job_id": "100003009047860", "location_code": "hk", "company": "Michaels Global Sourcing, LLC", "job_title": "Sourcing Specialist", "description": "Duties and Responsibilities:-\n\n\nDemand-oriented, holistic support for assigned suppliers, including the necessary processes on price determination within the scope of the functional procurement matrix organization\nAnalysis, evaluate and interpret of the global procurement market in the commodity\nEnsures expertise implementation of business processes and operational guidelines\nDeterminate and define all parameters of the price for purchasing of the commodity\nCoordinate with the operative areas for material supply\nParticipate in the development and global implementation of the commodity strategy derived from the cluster strategy.\nExecution of contract negotiations in accordance with company guidelines\nParticipate to prepare and execute the supplier audits\nDevelop and define the master data for purchasing (e.g.: price, batch size, payment terms, logistics)\nEnsures the creation and updating of purchasing master data\nParticipate in supplier classification in accordance with company guidelines and implementation of the supplier strategy in the defined commodity\nParticipate on the introduction, implementation and further development of optimization measures/action items\nExperience or skills required:\n\nBachelor degree or above in related discipline or equivalent\nMinimum 10 years of relevant experience with electronics technologies\nSolid and Practical experience in Sourcing and purchasing of electronic components\nExperience in the industries of Automotive, Medical, Aviation, Industrial\nPractical experience in leadership would be preferential\nFluent in written and spoken Mandarin and English\nOccasional travel to Mainland China (Shanghai) is required\nStrong Communication and negotiation skills\n\nWe offer attractive remuneration, 5-day work week, discretionary bonus and comprehensive fringe benefits to the right candidate. Interested parties please send your resume, expected salary and available date by clicking \"Apply Now\".\u00a0 You can also visit https://www.zollner-electronics.com for more information of our company.\n\nAll information provided by the applicants will be treated in strict confidence and used for recruitment purposes only.", "employment_types": ["Full Time", "Permanent"], "selling_points": ["New Headcount!", "Sourcing Process Execution and Vendor Management", "Hardgoods. Largest US Arts & Crafts retailer"], "locations": ["Kowloon Bay"], "categories": ["Merchandising & Purchasing", "Sundries", "Others", "Procurement / Purchasing / Sourcing"], "post_time": "2022-01-14T04:03:39Z", "salary": {"currency": null, "max": null, "min": null, "period": "monthly", "term": null}, "salary_visible": false, "title_keywords": ["specialist"], "responsibilities": ["data", "guidelines", "analysis", "coordinate with", "implementation", "company guidelines", "evaluate", "develop", "payment", "logistics", "audits"], "requirements": {"degrees": ["degree or above", "bachelor"], "majors": [], "languages": ["english", "mandarin"], "language_level": ["fluent"], "hard_skills": [], "soft_skills": ["communication", "negotiation skills", "leadership"], "languages_combined": [{"language": "english", "language_level": ["fluent"]}, {"language": "mandarin", "language_level": ["fluent"]}]}, "experience_required": {"duration": ["minimum 10 years"], "field": ["purchasing", "relevant experience", "medical"]}}, {"job_id": "100003009039073", "location_code": "hk", "company": "Nissin Foods (H.K.) Management Co., Ltd.", "job_title": "Clerk/Buyer", "description": "We are looking for high caliber candidate to join us and work together for the growth\u00a0of both our Company and individual.\n\nWhat will you be doing?\nThis position is responsible for executing and improving end-to-end best practices in Global Sourcing for assigned product categories. This role is accountable for developing and managing vendors, as well as maintaining existing vendor relationships and driving projects to ensure that vendors meet or exceed their contractual obligations by delivering innovative, quality products on time.\n\nRoles & Responsibility:-\n\nSourcing Process Execution and Vendor Management:\nExecute and improve the end-to-end sourcing processes including vendor management, liaison with agents, price negotiation, product development and sample assessment to meet the on-time delivery, quality and commercial KPIs\nSource and develop potential vendors as well as drive a respectful and collaborative vendor relationship with existing vendors to ensure they meet all company\u2019s requirements including value, quality and innovation.\nManage Request for Proposal, category costing bids and product development independently in conjunction with and product development and sourcing teams.\nEnsure smooth arrangement of product development trip, sourcing trip and finalization events\nExecute order management to ensure accuracy of database; Monitor and regular update on project status of assigned product categories\nProvide support in streamlining sourcing process and enhancement of product specification for price negotiation, cost reduction initiatives and high quality of products.\u00a0 Handle cost and commercial terms negotiation with vendors.\n\nAdditional duties as assigned including:-\n\nCollect latest market intelligence for Sourcing Manager to share with management, product development and sourcing teams.\u00a0\nProvide data for Sourcing Manager to conduct cost and supplier performance analysis in order to generate cost saving opportunities.\nTrain new Associate Sourcing Specialists and assist in their ongoing skills development\nOther duties as assigned\nKnowledge, Skills and Abilities requirement:-\nDegree/Associate Degree/Diploma holder in Merchandising/ Business Management or related discipline\nHands-on computer knowledge in MS word, Excel, Outlook, Power Point & Chinese Word Processing\nMinimum 3 years\u2019 relevant working experience\nEnergetic, self-motivated, detail-oriented and independent working style\nGood communication and interpersonal skills\nEager to work in a team in order to achieve best results\nDemonstrate a high sense of initiative, hardworking and responsible\nThe ability to work in a demanding but collegial, team-oriented environment\nGood command of both written and spoken English and Mandarin\nFrequent travel is required; Up to 30% travel\nSolid sourcing experience preferably gained from US buying office/ retailer\nWe offer competitive pay package and attractive fringe benefits including employer voluntary contribution on MPF scheme, Medical Insurance such as out-patient, hospitalization and dental coverage for employee, spouse and dependents. For interested parties, please make your application by stating the current and expected salaries.\n\nPersonal data collected will be used strictly for recruitment purpose only.", "employment_types": ["Full Time", "Permanent"], "selling_points": [], "locations": ["Tai Po Area"], "categories": ["Manufacturing", "Others", "Merchandising & Purchasing", "Others", "Procurement / Purchasing / Sourcing"], "post_time": "2022-01-11T08:36:05Z", "salary": {"currency": null, "max": null, "min": null, "period": "monthly", "term": null}, "salary_visible": false, "title_keywords": ["clerk"], "responsibilities": ["product categories", "management", "price negotiation", "order management", "provide support", "cost", "terms negotiation", "data", "additional duties", "analysis", "other duties", "quality", "teams", "monitor", "develop", "database", "kpis"], "requirements": {"degrees": ["diploma holder", "associate degree", "degree"], "majors": ["business"], "languages": ["english", "chinese", "mandarin"], "language_level": ["good command"], "hard_skills": ["business management", "excel", "chinese word processing", "scheme", "outlook", "power point", "ms word"], "soft_skills": ["self-motivated", "independent", "responsible", "detail-oriented", "hands-on", "communication and interpersonal skills", "patient", "energetic", "initiative", "hardworking"], "languages_combined": [{"language": "english", "language_level": ["good command"]}, {"language": "chinese", "language_level": []}, {"language": "mandarin", "language_level": ["good command"]}]}, "experience_required": {"duration": ["minimum 3 years"], "field": ["relevant working experience"]}}, {"job_id": "100003009036826", "location_code": "hk", "company": "Reliable Medicine Technology Company Limited", "job_title": "\u8fa6\u516c\u5ba4\u8ddf\u55ae\u6703\u8a08\u6587\u54e1", "description": "Job Description\n\nProvide clerical support to the Department\nSource, maintain and update\u00a0vendor database system\u00a0based on past vendor assessment, pricing, quality and other useful information.\nUpdate, organize and maintain systematic filing system for the Department\nPerform ad-hoc assignments and other duties as required\n\nJob Specification\n\nForm\u00a05 or above.\nRelevant experience\u00a0in\u00a0food industry is preferred.\nExperience in manufacturing working environment is an advantage.\nInitiative and be a good team player.\nGood command\u00a0in using MS Office applications (i.e. Excel, Word & PowerPoint).\u00a0\nApplicant please email DETAILED RESUME with present & expected salary to Human Resources Dept.\n\n\n(All personal data collected\u00a0will be\u00a0used for recruitment purpose only)", "employment_types": ["Full Time"], "selling_points": [], "locations": ["Kwai Hing"], "categories": ["Merchandising & Purchasing", "Others"], "post_time": "2022-01-10T16:08:10Z", "salary": {"currency": null, "max": null, "min": null, "period": "monthly", "term": null}, "salary_visible": false, "title_keywords": [], "responsibilities": ["provide clerical support", "other duties", "ad-hoc assignments", "quality", "maintain", "recruitment", "database", "personal data"], "requirements": {"degrees": ["form 5 or above"], "majors": [], "languages": [], "language_level": [], "hard_skills": ["excel", "vendor", "powerpoint", "word", "ms office"], "soft_skills": ["good team player", "initiative", "systematic", "detailed"], "languages_combined": []}, "experience_required": {"duration": [], "field": ["manufacturing", "relevant experience", "food industry"]}}, {"job_id": "100003009048438", "location_code": "hk", "company": "Hillman Ross", "job_title": "Assistant Sourcing Manager (Toys)", "description": "\u8981\u6c42/\u8077\u8cac:\n\n\u62db\u8058\u8fa6\u516c\u5ba4\u8ddf\u55ae\u6703\u8a08\u6587\u54e1:\n- \u8655\u7406\u65e5\u5e38\u6279\u767c\u548c\u96f6\u552e\u8a02\u55ae\n- \u6253\u5831\u50f9\u55ae\uff0c \u6708\u7d50\u55ae\uff0c \u9001\u8ca8\u55ae\n- \u9280\u884c\u6708\u7d50\u5c0d\u6578, \u958b\u7968 - \u5c11\u91cf\u5916\u52e4\u5de5\u4f5c\u5982\u9280\u884c\u5165\u7968\uff0c\u9001\u4ef6\n- \u5c11\u91cf\u8fa6\u516c\u5ba4\u884c\u653f\u5de5\u4f5c\n- \u9700\u61c2\u96fb\u8166\u5de5\u4f5c\uff0c\u4e2d\u82f1\u6587\u6253\u5b57\uff0c \u64cd\u4f5cMicrosoft office.\n\n\u8acb\u63d0\u4f9b\u500b\u4eba\u5c65\u6b77\u53ca\u4eba\u5de5\u8981\u6c42\u4e88\u9673\u5c0f\u59d0 (\u6240\u6709\u500b\u4eba\u8cc7\u6599\u53ea\u4f5c\u62db\u8058\u7528\u9014).", "employment_types": ["Full Time", "Permanent"], "selling_points": ["European company", "Toys category", "Experience in handling plush is a Must"], "locations": ["Not Specified"], "categories": ["Merchandising & Purchasing", "Toy", "Others", "Procurement / Purchasing / Sourcing"], "post_time": "2022-01-14T06:35:00Z", "salary": {"currency": null, "max": null, "min": null, "period": "monthly", "term": null}, "salary_visible": false, "title_keywords": ["assistant", "sourcing manager"], "responsibilities": [], "requirements": {"degrees": [], "majors": [], "languages": [], "language_level": [], "hard_skills": [], "soft_skills": [], "languages_combined": []}, "experience_required": {"duration": [], "field": []}}, {"job_id": "100003009049080", "location_code": "hk", "company": "Sa Sa Cosmetic Company Limited", "job_title": "Merchandising Assistant (Fresh Graduate Welcome)", "description": "Our client is a European company and they are looking for an Assistant Sourcing Manager to take care of toys category. This person will be an individual contributor, reporting to the Sourcing Manager.\n\nWe are now seeking for Assistant Sourcing Manager (Toys)\n\nRESPONSIBILITIES\n\nWell organization skills of dealing with complex product categories, manage high sku and multi-countries production base.\nDevelop product and vendor strategies to drive for continue business growth.\nWork with the Sourcing Managers to evaluate the performance of factories and assess the business risk that support clients' business needs.\nSupervise and guide a team of merchandisers and coordinate with cross functional teams to achieve excellent KPI to meet client's expectation.\nStrong and in-depth negotiation skills to drive cost saving and costing margin for clients' continue business growth.\nFull ownership of the whole supply chain from factory sourcing, development till shipment with in-depth technical knowledge, proactive on problem precaution & strong decision maker.\nManage the team to ensure they are up to the company standard\nMotivate the team by sharing knowledge and expertise, ensuring attention to detail and seeking continuous improvements\nDevelop a close relationship with existing suppliers and develop new suppliers through personal connections, trade fairs and sourcing trips\nProduct, payment and business term negotiations with suppliers.\n\nTo succeed in this key role, you will have at least 10 years experience in sourcing with at least 6 years in managerial capacity.\n\nQUALIFICATIONS:\n\nTertiary educated\nSelf-motivated and have strong sense of responsibility.\nStrong people and process management skills\nStrong analytical and interpersonal skills\nIndependent and excellent time management in meeting deadline.\nStrong communication skills and fluent in English, Mandarin and Cantonese\nExperience in handling plush is a Must\nExperience working in European market is a MUST\n\nAPPLY FOR THIS JOB\n\nInterested candidate please CLICK apply button to apply online or send your resume in MS word format to Hillman Ross Recruitment Solution Professional\n\nPlease note that only shortlisted candidate will be notified. All information will be treated in strict confidence and solely used for recruitment purposes.", "employment_types": ["Full Time", "Permanent"], "selling_points": ["Assist in sales & marketing activities", "Prepare business analysis reports", "Proficiency in Microsoft applications"], "locations": ["Chai Wan"], "categories": ["Marketing / Public Relations", "Marketing - Brand / Product Management", "Merchandising & Purchasing", "Others", "Procurement / Purchasing / Sourcing"], "post_time": "2022-01-14T08:04:49Z", "salary": {"currency": null, "max": null, "min": null, "period": null, "term": null}, "salary_visible": false, "title_keywords": ["merchandising assistant"], "responsibilities": ["product categories", "reporting", "cost", "continuous improvements", "management", "coordinate with", "teams", "develop", "evaluate", "communication", "payment", "support clients", "recruitment"], "requirements": {"degrees": [], "majors": [], "languages": ["cantonese", "english", "mandarin"], "language_level": ["fluent"], "hard_skills": ["vendor", "ms word"], "soft_skills": ["communication skills", "self-motivated", "confidence", "independent", "sense of responsibility", "time management", "negotiation skills", "interpersonal skills", "attention to detail", "organization skills", "proactive"], "languages_combined": [{"language": "cantonese", "language_level": ["fluent"]}, {"language": "english", "language_level": ["fluent"]}, {"language": "mandarin", "language_level": ["fluent"]}]}, "experience_required": {"duration": ["at least 10 years", "at least 6 years"], "field": ["managerial"]}}, {"job_id": "100003009038154", "location_code": "hk", "company": "Shing Wai Brass & Metal Wares Fty Ltd", "job_title": "Merchandiser", "description": "Responsibilities:\nAssist in purchase coordination, prepare business analysis reports, and deal with shop inquiries\nAnalyze business trends and consumer insights to deliver brand sales and market share targets\nDevelop marketing collaterals such as product display and promotional material to enhance brand image\nCoordinate with internal and external parties to maintain daily operation and ensure excellent execution of brand building\nDevelop and sustain strong working relationships with all internal stakeholders\nRequirements:\nDegree holder with 1 year relevant working experience\nStrong market sense and awareness\nStrong analytical ability with excellent negotiation and communication skills\nProactive, detail-minded and able to work independently\nProficiency in Microsoft applications, particularly in excel applications\nExcellent spoken and written English and Chinese, proficiency in Mandarin will be an advantage\nFresh graduate will also be considered\nWe offer\n5 - day work week\nMedical Benefits\nPerformance Bonus\nStaff Purchase Discounts\nStaff Recreation Activity\nShuttle Bus Service\nEducation Sponsorship\nInterested parties please send a full resume with current and expected salary\u00a0by clicking APPLY NOW.\nPlease visit our corporate website at\u00a0http://corp.sasa.com/en/home\u00a0to know more about us.\n\n(Sa Sa is an Equal Opportunity Employer and all qualified applicants will receive consideration for employment. Personal data collected will be kept confidential and used for recruitment purpose only)", "employment_types": ["Full Time", "Permanent"], "selling_points": ["At least one year relevant working experience", "Self-motivated,Personable,Creative,Problem solver", "Competitive remuneration package"], "locations": ["Kowloon Bay"], "categories": ["Merchandising & Purchasing", "Furniture", "Home Appliances", "Others"], "post_time": "2022-01-11T05:36:59Z", "salary": {"currency": null, "max": null, "min": null, "period": "monthly", "term": null}, "salary_visible": false, "title_keywords": ["merchandiser"], "responsibilities": ["consumer insights", "marketing collaterals", "coordinate with", "internal and external parties", "daily operation", "develop", "business analysis reports", "purchase", "analyze business trends", "maintain", "coordination", "working relationships"], "requirements": {"degrees": ["fresh graduate", "degree holder"], "majors": [], "languages": ["english", "chinese", "mandarin"], "language_level": ["advantage", "excellent", "proficiency"], "hard_skills": ["excel", "microsoft applications"], "soft_skills": ["detail-minded", "communication skills", "work independently", "negotiation", "strong market sense", "proactive"], "languages_combined": [{"language": "english", "language_level": ["advantage", "excellent"]}, {"language": "chinese", "language_level": ["advantage", "excellent"]}, {"language": "mandarin", "language_level": ["proficiency", "advantage", "excellent"]}]}, "experience_required": {"duration": ["1 year"], "field": ["relevant working experience"]}}, {"job_id": "100003009048570", "location_code": "hk", "company": "Urban Fruit International Limited", "job_title": "\u591c\u73ed\u63a1\u8cfc\u54e1", "description": "Job Responsibilities:\u00a0\n\nOrder follow up from salesman sample to bulk (Strong in knit items)\nCost negotiation\nOrganize fit meeting between designer & technician, ensure all detailed / accurate info for production\nMonitor on-time delivery for salesman sample & bulk\nAd-hoc project may be required\n\nJob\u00a0Requirements:\u00a0\n\nPractical merchandising experience that contributes to fit approval, development of new shape, best costing and right material is an advantage\nSelf-motivate, detailed-orientated, independent, proactive, responsible, decisive working style.\u00a0 Able to work under pressure calmly\nGood management skills in communication, co-ordination and overall controlling of order progress from sourcing, sample development to production monitoring\nWilling to travel to China factory occasionally\n\nWe offer a 5-days work, MPF, bank holiday\u00a0and competitive remuneration package to the right candidates.\u00a0\u00a0\n\nAll information collected will be used for recruitment related purpose only and will be treated in strict confidence. Applicants who are not notified within 8 weeks may consider their application unsuccessful. All applications will be retained for maximum 6 months and will be destroyed.", "employment_types": ["Full Time"], "selling_points": [], "locations": ["Yau Ma Tei"], "categories": ["Merchandising & Purchasing", "Others", "Others", "Others"], "post_time": "2022-01-14T06:49:48Z", "salary": {"currency": null, "max": null, "min": null, "period": "monthly", "term": null}, "salary_visible": false, "title_keywords": [], "responsibilities": ["ad-hoc", "cost", "monitor"], "requirements": {"degrees": [], "majors": [], "languages": [], "language_level": [], "hard_skills": [], "soft_skills": ["independent", "responsible", "work under pressure", "communication", "decisive", "proactive", "detailed"], "languages_combined": []}, "experience_required": {"duration": [], "field": ["development", "merchandising"]}}, {"job_id": "100003009051012", "location_code": "hk", "company": "PARKnSHOP", "job_title": "Merchandising Planning Officer", "description": "\n\u8077\u8cac :\u8207\u65e5\u9593\u63a1\u8cfc\u540c\u4e8b\u5b89\u6392\u7db2\u7ad9\u7522\u54c1\u4e0a\u67b6, \u6536\u96c6\u665a\u9593\u63a1\u8cfc\u8cb7\u8ca8\u6e05\u55ae, \u8ca0\u8cac\u63a1\u8cfc, \u6aa2\u67e5\u8ca8\u54c1, \u78ba\u4fdd\u7522\u54c1\u4fdd\u6301\u826f\u597d\u8cea\u7d20\u51fa\u8ca8, \u5354\u52a9\u8cc7\u6599\u641c\u96c6, \u4ecb\u7d39\u751f\u679c\u53ca\u8655\u7406\u4e0a\u53f8\u6307\u6d3e\u7684\u5de5\u4f5c\n\n\u8cc7\u6b77 :\u4e2d\u4e94\u7a0b\u5ea6; 2\u5e74\u7d93\u9a57; \u826f\u597d\u7cb5\u8a9e; \u4e00\u822c\u82f1\u8a9e; \u61c2\u8b80\u5beb\u4e2d\u6587; \u7565\u61c2\u8b80\u5beb\u82f1\u6587\n\n\u5f85\u9047 :\u6bcf\u6708$21,000, \u6709\u91ab\u7642\u798f\u5229, \u5728\u8077\u57f9\u8a13 \u53ca\u6649\u5347\u6a5f\u6703, \u4e0b\u53486\u6642\u81f3\u51cc\u66683\u6642, \u6bcf\u9031\u5de5\u4f5c5\u5929,\u8f2a\u4f11, \u6bcf\u5929\u5de5\u4f5c 9 \u5c0f\u6642, \u4f11\u606f\u65e5\u6bcf\u67088\u5929\n\n\u7533\u8acb\u9808\u77e5 :\u6c42\u8077\u8005\u53ef\u81f4\u96fb24121008\u8207URBAN FRUIT INTERNATIONAL LIMITED\u8a31\u5c0f\u59d0\u806f\u7d61\u3002\n\n", "employment_types": ["Full Time"], "selling_points": [], "locations": ["Shatin Area"], "categories": ["Merchandising & Purchasing", "Others"], "post_time": "2022-01-15T00:47:51Z", "salary": {"currency": null, "max": null, "min": null, "period": null, "term": null}, "salary_visible": false, "title_keywords": ["officer", "merchandising"], "responsibilities": [], "requirements": {"degrees": [], "majors": [], "languages": [], "language_level": [], "hard_skills": [], "soft_skills": [], "languages_combined": []}, "experience_required": {"duration": [], "field": []}}, {"job_id": "100003009048432", "location_code": "hk", "company": "Hillman Ross", "job_title": "Sourcing Manager (Luggage and bags)", "description": "You can enjoy:\u00a0\nComprehensive Medical and Life insurance coverage, including your spouse and children\nExclusive company pension schemes\nMarriage, Maternity and Paternity Leave\nExclusive shopping discount, Bazaar Sales for our people only\u00a0\nProfessional training and career advancement opportunities\nConvenient office location, less than 5 min. walk from MTR\nContemporary workplace with Onsite Clinic, Lactation Rooms, free drinks and chill out areas\nWell-equipped Gym inside our office building, plus fitness and interest class packages\nFree round-trip lunchtime shuttle bus services to Shatin\nResponsibilities:\nOptimizing sales & profits intensity and display efficiency (right product to the right stores and right display)\nAssist in planning in-store product display and product range change by analyzing and reviewing item sales performance\nUse internal system to plan and design items display\nLiaise with internal departments include but not limited to Trading, Operations team etc. and external parties, to plan and execute product display and product range change\nRequirements:\nTertiary Education or above\n2-3 years relevant experience in FMCG industry, with retail operations experience is preferable\nStrong in analytical and PC skills\nGood understanding in planogram tools, such as Spaceman, will be an advantage\nGood team player and able to work under pressure\nAn attractive salary and benefit package will be offered. Interested parties please forward detailed resume stating expected salary to: People Department, PARKnSHOP (HK) Limited, Watson House, 1-5 Wo Liu Hang Road, Fo Tan, N.T. or email to us.\u00a0\n\nWe are an equal opportunity employer and welcome applications from all qualified candidates. The information provided will be treated in strict confidence and be used only for consideration of your application for relevant / similar posts within the A.S. Watson Group. All personal data of unsuccessful applicants will be destroyed within 12 months from the date of application.", "employment_types": ["Full Time", "Permanent"], "selling_points": ["European Company", "Experience in handling bags is a Must", "Experience working in European market is a MUST"], "locations": ["Not Specified"], "categories": ["Merchandising & Purchasing", "Handbag", "Others", "Procurement / Purchasing / Sourcing"], "post_time": "2022-01-14T06:34:00Z", "salary": {"currency": null, "max": null, "min": null, "period": "monthly", "term": null}, "salary_visible": false, "title_keywords": ["sourcing manager"], "responsibilities": ["sales performance", "operations", "external parties", "design", "plan", "liaise with", "planning"], "requirements": {"degrees": [], "majors": [], "languages": [], "language_level": [], "hard_skills": ["pc skills", "fmcg industry"], "soft_skills": ["good team player", "work under pressure"], "languages_combined": []}, "experience_required": {"duration": ["2-3 years"], "field": ["retail operations", "fmcg", "relevant experience"]}}, {"job_id": "100003009048020", "location_code": "hk", "company": "Edwin McAuley Electronics Ltd", "job_title": "Senior Purchasing Officer/ Purchasing Officer", "description": "Main tasks & responsibilities:\n\nTo process efficient and effectively the daily inquiries and orders within the given product categories and according to our quality and compliance standards. The tasks involves\u00a0quoting, procurement, monitoring production and logistics. The goal is to increase the\u00a0number orders and service level to our customers.\n\nDuties\n\nProcess inquiries > prioritize and provide good quality replies within the service level agreement\nTake full responsibility from the inquiry stage; order received till shipment.\nKeep track of suppliers\u2019 production plan to ensure on time delivery\nBe result orientated > offer solutions, alternatives: each inquiry and order is a chance.\nHandle complaints and discuss/negotiate solutions with the factories and/or sales.\n\n\u00a0Your experience\n\nOrganized and an eye for detail;\nResult-orientated team-player;\nGood command in English and Mandarin\nMerchandising or procurement experience\nGood command of Excel, Word, PPT and so on for office software.\n\n\u00a0What\u2019s in it for you?\n\nWe offer you a challenging and exciting job in an enthusiastic team and pleasant working environment with a competitive salary, performance bonus, double pay, life insurance, medical insurance, five-day work week and 15 days holidays per year.\n\nAre you a starter? Don\u2019t hesitate to apply!", "employment_types": ["Full Time", "Permanent"], "selling_points": ["Manage & implement systematic procurement policy", "To propose/or make proper purchasing strategy plan", "5 days work per week, mid-year bonus & double pay"], "locations": ["North Point"], "categories": ["Merchandising & Purchasing", "Electronics", "Others", "Procurement / Purchasing / Sourcing"], "post_time": "2022-01-14T04:32:23Z", "salary": {"currency": null, "max": null, "min": null, "period": "monthly", "term": null}, "salary_visible": false, "title_keywords": ["purchasing officer"], "responsibilities": ["product categories", "software", "monitoring", "compliance", "quality", "ensure on time delivery", "handle complaints", "merchandising", "logistics", "plan", "insurance"], "requirements": {"degrees": [], "majors": [], "languages": ["english", "mandarin"], "language_level": ["good command"], "hard_skills": ["excel", "word", "goal", "service level agreement", "office software"], "soft_skills": ["efficient", "organized", "team-player", "prioritize", "pleasant", "eye for detail", "enthusiastic"], "languages_combined": [{"language": "english", "language_level": ["good command"]}, {"language": "mandarin", "language_level": ["good command"]}]}, "experience_required": {"duration": [], "field": ["merchandising", "procurement"]}}, {"job_id": "100003009046092", "location_code": "hk", "company": "Match Pacific Recruitment Consultancy", "job_title": "Sales Coordinator (5 days)", "description": "Our client is a European company and they are looking for a Sourcing Manager to take care of luggage and bags category. This person will be an individual contributor, reporting to the Category Manager.\n\nWe are now seeking for Sourcing Manager (Luggage and bags)\n\nRESPONSIBILITIES\n\nWell organization skills of dealing with complex product categories, manage high sku and multi-countries production base.\nDevelop product and vendor strategies to drive for continue business growth.\nWork with the Sourcing Managers to evaluate the performance of factories and assess the business risk that support clients' business needs.\nSupervise and guide a team of merchandisers and coordinate with cross functional teams to achieve excellent KPI to meet client's expectation.\nStrong and in-depth negotiation skills to drive cost saving and costing margin for clients' continue business growth.\nFull ownership of the whole supply chain from factory sourcing, development till shipment with in-depth technical knowledge, proactive on problem precaution & strong decision maker.\nManage the team to ensure they are up to the company standard\nMotivate the team by sharing knowledge and expertise, ensuring attention to detail and seeking continuous improvements\nDevelop a close relationship with existing suppliers and develop new suppliers through personal connections, trade fairs and sourcing trips\nProduct, payment and business term negotiations with suppliers.\n\nTo succeed in this key role, you will have at least 10 years experience in sourcing with at least 6 years in managerial capacity.\n\nQUALIFICATIONS:\n\nTertiary educated\nSelf-motivated and have strong sense of responsibility.\nStrong people and process management skills\nStrong analytical and interpersonal skills\nIndependent and excellent time management in meeting deadline.\nStrong communication skills and fluent in English, Mandarin and Cantonese\nExperience in handling bags is a Must\nExperience working in European market is a MUST\n\nAPPLY FOR THIS JOB\n\nInterested candidate please CLICK apply button to apply online or send your resume in MS word format to Hillman Ross Recruitment Solution Professional\n\nPlease note that only shortlisted candidate will be notified. All information will be treated in strict confidence and solely used for recruitment purposes.", "employment_types": ["Full Time", "Permanent"], "selling_points": ["order follow up / export market", "5 days commerical office", "bank holiday 13mths medical mpf 12 annual leave"], "locations": ["Kwun Tong"], "categories": ["Merchandising & Purchasing", "Others", "Procurement / Purchasing / Sourcing", "Sales, CS & Business Devpt", "Sales Administration"], "post_time": "2022-01-13T09:36:09Z", "salary": {"currency": null, "max": null, "min": null, "period": "monthly", "term": null}, "salary_visible": false, "title_keywords": ["sales coordinator"], "responsibilities": ["product categories", "reporting", "cost", "continuous improvements", "management", "coordinate with", "teams", "develop", "evaluate", "communication", "payment", "support clients", "recruitment"], "requirements": {"degrees": [], "majors": [], "languages": ["cantonese", "english", "mandarin"], "language_level": ["fluent"], "hard_skills": ["vendor", "ms word"], "soft_skills": ["communication skills", "self-motivated", "confidence", "independent", "sense of responsibility", "time management", "negotiation skills", "interpersonal skills", "attention to detail", "organization skills", "proactive"], "languages_combined": [{"language": "cantonese", "language_level": ["fluent"]}, {"language": "english", "language_level": ["fluent"]}, {"language": "mandarin", "language_level": ["fluent"]}]}, "experience_required": {"duration": ["at least 10 years", "at least 6 years"], "field": ["managerial"]}}, {"job_id": "100003009050474", "location_code": "hk", "company": "Chevalier Group - Lifts and Escalators", "job_title": "Purchasing Assistant", "description": "Job Responsibilities:\n\nAssist to manage & implement systematic procurement policy, procedure and controlling the systems for the purchasing of goods and services.\nAssist to propose or make proper purchasing strategy plan to ensure different materials categories in right purchase at the best cost and maintain of the minimum inventory level.\u00a0 The plan has to be review regularly.\nTo supervise and monitor the daily works of RFQ,Purchasing /Material Control teams to ensure on time delivery.\u00a0\u00a0\nkeep doing suppliers comparison for categories group, and propose an optimum choice of suppliers to Purchasing Manager for material share re-allocation.\nDefine / Drive an alternative source approval, and make quick change once having unsolved problem from existing suppliers.\u00a0\u00a0\nTo involve / lead the teams to be strong in negotiation with suppliers in the best business & custom clearance terms.\nOther ad hoc projects as assigned by Management.\n\nJob Requirements:\n\nUniversity Degree;\nAt least 4\u00a0years\u00a0experience in electronics components purchasing;\nProficient in MS office;\nSAP knowledge is\u00a0advantageous;\nOccasionally Travel to Dongguan;\nMore relevant experience will be considered as Senior Purchasing Officer\n\nWe place much emphasis on the career development of our employees, respect the worthiness of individual contributions and expect strong commitment to performance excellence.\n\nWe offer 5 days work per week, competitive remuneration package and fringe benefits including year-end and mid-year bonuses, medical scheme, life & accident insurance etc to the right candidate.\n\nInterested parties please send full resume stating current salary, expected salary and availability by clicking 'Apply Now' .\n\nAll information received will strictly be kept confidential and be used for employment-related purposes only.", "employment_types": ["Full Time", "Permanent"], "selling_points": ["Assist in procurement activities", "Provide ad hoc support to the team", "Degree holder with 1-year working experience"], "locations": ["Kowloon Bay"], "categories": ["Admin & HR", "Clerical / Admin Staff", "Merchandising & Purchasing", "Others", "Procurement / Purchasing / Sourcing"], "post_time": "2022-01-14T10:29:05Z", "salary": {"currency": null, "max": null, "min": null, "period": null, "term": null}, "salary_visible": false, "title_keywords": ["purchasing assistant"], "responsibilities": ["cost", "control", "management", "inventory", "systems", "review", "monitor", "teams", "ensure on time delivery", "purchase", "maintain", "ad hoc projects", "plan", "custom clearance"], "requirements": {"degrees": ["university degree"], "majors": [], "languages": [], "language_level": [], "hard_skills": ["scheme", "sap", "ms office"], "soft_skills": [], "languages_combined": []}, "experience_required": {"duration": ["at least 4 years"], "field": ["purchasing", "relevant experience"]}}, {"job_id": "100003009048838", "location_code": "hk", "company": "G.A. Operations Hong Kong Limited", "job_title": "Merchandiser, Production (Accessories - Bags) One-year Contract", "description": "\nPosition :Sales Coordinator\u00a0\n\nRequirement:\u00a0\n\n- HKCEE / HKDSE or Diploma holder\u00a0\n- Over 2 years order follow / coordination / merchandising / purchasing experience\u00a0\n- Work closely with internal department for order processing\u00a0\n- Proficiency in Ms Office\u00a0\n- Good command of English and Mandarin\u00a0\n\nInterested parties, please click APPLY NOW for post application or email resume to us directly\u00a0\nAll personal details only for recruitment puropose and confidential\u00a0\n\n\n\n", "employment_types": ["Contract"], "selling_points": [], "locations": ["Kowloon Bay"], "categories": ["Merchandising & Purchasing", "Others"], "post_time": "2022-01-14T07:23:46Z", "salary": {"currency": null, "max": null, "min": null, "period": "monthly", "term": null}, "salary_visible": false, "title_keywords": ["merchandiser"], "responsibilities": ["merchandising", "coordination", "order processing"], "requirements": {"degrees": ["diploma holder", "hkdse"], "majors": [], "languages": ["english", "mandarin"], "language_level": ["good command"], "hard_skills": ["order processing", "ms office"], "soft_skills": ["coordination"], "languages_combined": [{"language": "english", "language_level": ["good command"]}, {"language": "mandarin", "language_level": ["good command"]}]}, "experience_required": {"duration": ["2 years"], "field": ["purchasing", "merchandising"]}}, {"job_id": "100003009050791", "location_code": "hk", "company": "Green Delta Limited", "job_title": "Merchandiser", "description": "Chevalier (HK) Limited is now inviting high calibre persons to apply for this position:\n\n\nResponsibilities\n\nAssist in procurement activities including preparing purchase orders, purchase planning, price negotiation, etc\nMonitor stock inventory and maintain an updated purchasing database and filing system\nWork closely with suppliers and factories for order follow up and delivery schedule\nHandle ad hoc projects assigned by manager\n\n\nRequirements\n\nDegree in Business Administration or related disciplines\nMinimum 1 year relevant working experience in construction and engineering industry\nGood command of spoken and written English and Chinese\nProficient in MS Office applications and Chinese Word Processing\nImmediately available is highly preferred\n\n\nAttractive remuneration package will be offered to the right candidate. Interested parties, please send us your resume with current and expected salary by clicking \"Apply Now\" or mail to:\n\nThe Human Resources Manager, Chevalier Group, 22/F, Chevalier Commercial Centre, 8 Wang Hoi Road, Kowloon Bay, Hong Kong\n\nWe are an equal opportunity employer and welcome applications from all qualified candidates. Personal data collected would be used for recruitment purpose only.", "employment_types": ["Full Time", "Permanent"], "selling_points": [], "locations": ["Lai Chi Kok"], "categories": ["Merchandising & Purchasing", "Others"], "post_time": "2022-01-15T03:51:14Z", "salary": {"currency": null, "max": null, "min": null, "period": "monthly", "term": null}, "salary_visible": false, "title_keywords": ["merchandiser"], "responsibilities": ["price negotiation", "inventory", "monitor", "delivery schedule", "purchase", "maintain", "ad hoc projects", "database", "planning"], "requirements": {"degrees": ["degree"], "majors": ["related disciplines", "business administration"], "languages": ["english", "chinese"], "language_level": ["good command", "proficient"], "hard_skills": ["chinese word processing", "ms office"], "soft_skills": [], "languages_combined": [{"language": "english", "language_level": ["good command"]}, {"language": "chinese", "language_level": ["good command", "proficient"]}]}, "experience_required": {"duration": ["minimum 1 year"], "field": ["construction", "engineering", "relevant working experience"]}}, {"job_id": "100003009048188", "location_code": "hk", "company": "Kingsway Personnel Ltd", "job_title": "Japanese Speaking Purchasing Executive ~22K", "description": "Job Description\n\nProject order follow up is required\nPerform day-to-day merchandising duties, includes handling orders from quotation to\u00a0shipment.\nResponsible for order follow up to ensure on-time delivery.\nSupport the team in project coordination from production to delivery\nClose contact with customers & factories.\nAble to work independently.\nCollaborate with cross-functioning team including Sales team, shipping team, suppliers, to ensure multiple projects are being executed according to plan or timeline;\n\nRequirements\n\n\n\nMin 3-5years experience in a merchandising job\nPC knowledge of Excel, Word and Chinese word processing\nFluent in spoken and written Cantonese, English and Mandarin\nBe a team-player and willing to learn\nBe hardworking with a sense of responsibility and able to work independently and under pressure in a dynamic environment\nHave computer skills (MS office and outlook)\nGood command of both spoken & written English and Chinese\u00a0\nImmediately available is highly preferred", "employment_types": ["Full Time", "Permanent"], "selling_points": ["Business level in Japanese and English speaking", "Exp. in Purchasing/Buying/Product development", "~22K, double pay, bonus, transportation allowance"], "locations": ["Tsing Yi"], "categories": ["Manufacturing", "Product Development / Management", "Merchandising & Purchasing", "Others", "Procurement / Purchasing / Sourcing"], "post_time": "2022-01-15T19:11:34Z", "salary": {"currency": null, "max": null, "min": null, "period": "monthly", "term": null}, "salary_visible": false, "title_keywords": ["purchasing executive"], "responsibilities": ["collaborate with", "shipping", "project coordination", "quotation", "merchandising", "sales team", "contact", "plan", "multiple projects", "support the team"], "requirements": {"degrees": [], "majors": [], "languages": ["cantonese", "english", "chinese", "mandarin"], "language_level": ["good command", "fluent"], "hard_skills": ["excel", "chinese word processing", "word", "dynamic", "computer skills", "outlook", "pc knowledge", "ms office"], "soft_skills": ["work independently", "dynamic environment", "under pressure", "sense of responsibility", "team-player", "willing to learn", "hardworking"], "languages_combined": [{"language": "cantonese", "language_level": ["fluent"]}, {"language": "english", "language_level": ["fluent", "good command"]}, {"language": "chinese", "language_level": ["fluent", "good command"]}, {"language": "mandarin", "language_level": ["fluent"]}]}, "experience_required": {"duration": [], "field": ["merchandising"]}}, {"job_id": "100003009039200", "location_code": "hk", "company": "Potential Personnel Consultancy", "job_title": "Sales and Development Manager \u2013 APAC ( Textile/Garment Accessories ) - 5 days work", "description": "This position will be responsible to make sure the vendors production of our accessory products from planning to pre-production, into bulk and quality control phases.\n\nResponsibilities:\n\nReview the comments and samples before passing to suppliers for sample making, check and measure the approval samples before sending to Italy\nMonitor the whole sample approval status, together with delivery of products to ensure no delay for production\nSolve all technical and quality problems with Italy, factories and all related suppliers during both sample making and bulk production\nSettle and reconcile the gap analysis between Italy, factories and suppliers over requirements and feasibility\nProvide necessary information and help to QC team, and clarify the acceptance guidance for QC inspection\nMonitor the production status to secure the product delivery and co-operate with shipping department to ensure bulk shipment is accurate and on time\n\nRequirements:\n\nDiploma\u00a0in Fashion or equivalent, with focus with accessories (bags and small leather goods)\nAt least 2-3 years of merchandising experience in accessories (bags and small leather goods) for a fashion brand\nGood technical knowledge specifically on accessories bags with solid manufacturing experience\nGood\u00a0communication skill in\u00a0English & Chinese (Cantonese & Mandarin)\nStrong interpersonal skill and negotiation skill\nComputer literacy (MS Word, Excel)\nSelf-motivated, positive and a team player", "employment_types": ["Full Time"], "selling_points": [], "locations": ["Kwun Tong"], "categories": ["Merchandising & Purchasing", "Fabrics", "Others", "Procurement / Purchasing / Sourcing"], "post_time": "2022-01-11T08:59:56Z", "salary": {"currency": "HKD", "max": 44999, "min": 35000, "period": "monthly", "term": null}, "salary_visible": true, "title_keywords": ["manager", "sales"], "responsibilities": ["guidance", "shipping", "analysis", "comments", "quality", "review", "monitor", "inspection", "co-operate with"], "requirements": {"degrees": ["diploma"], "majors": [], "languages": ["cantonese", "english", "chinese", "mandarin"], "language_level": ["good"], "hard_skills": ["small", "excel", "focus", "ms word"], "soft_skills": ["self-motivated", "communication skill", "interpersonal skill", "computer literacy", "team player", "negotiation skill", "focus", "positive"], "languages_combined": [{"language": "cantonese", "language_level": ["good"]}, {"language": "english", "language_level": ["good"]}, {"language": "chinese", "language_level": ["good"]}, {"language": "mandarin", "language_level": ["good"]}]}, "experience_required": {"duration": ["at least 2-3 years"], "field": ["manufacturing", "merchandising", "brand"]}}, {"job_id": "100003009035814", "location_code": "hk", "company": "Hong Kong Yamazaki Baking Co Ltd", "job_title": "Assistant Purchasing Officer / Purchasing Officer", "description": "A young and innovative company in General Merchandise looks for a qualified and experienced Merchandiser. Our Head Office is in Hong Kong with additional worldwide offices. We design, manufacture and export to major mass market and retailers exporting to over 30 countries worldwide. Major markets include Belgium, France, Germany and USA.\n\nMerchandiser\n\nResponsibilities:\n\n-\u00a0\u00a0\u00a0\u00a0\u00a0\u00a0\u00a0\u00a0\u00a0 Responsible for product sourcing, quotation and sampling\n-\u00a0\u00a0\u00a0\u00a0\u00a0\u00a0\u00a0\u00a0\u00a0 Organize/accompany sourcing trips with buyers\n-\u00a0\u00a0\u00a0\u00a0\u00a0\u00a0\u00a0\u00a0\u00a0 Follow-up orders with factories & buyers to ensure on-time delivery\n-\u00a0\u00a0\u00a0\u00a0\u00a0\u00a0\u00a0\u00a0\u00a0 Arrange inspection and prepare reports\n-\u00a0\u00a0\u00a0\u00a0\u00a0\u00a0\u00a0\u00a0\u00a0 Monitor shipment and prepare shipping document\n\nRequirement:\n\n-\u00a0\u00a0\u00a0\u00a0\u00a0\u00a0\u00a0\u00a0\u00a0 At least 5 years general merchandising experience, preferable in pet products.\n-\u00a0\u00a0\u00a0\u00a0\u00a0\u00a0\u00a0\u00a0\u00a0 Experience in handling shipping documents or sourcing is a plus.\n-\u00a0\u00a0\u00a0\u00a0\u00a0\u00a0\u00a0\u00a0\u00a0 Fluency in English and Mandarin\n-\u00a0\u00a0\u00a0\u00a0\u00a0\u00a0\u00a0\u00a0\u00a0 Detail-minded, well-organized, responsible and can work independently\n\nWe offer competitive remuneration package including 5-day work, double pay & discretionary bonus to the right candidate. Please do not apply if you do not meet the above criteria as your application will NOT be considered. We regret that we shall only contact suitable applicants.\u00a0\u00a0", "employment_types": ["Full Time", "Permanent"], "selling_points": [], "locations": ["Sheung Shui"], "categories": ["Transportation & Logistics", "Shipping", "Merchandising & Purchasing", "Others"], "post_time": "2022-01-10T08:27:39Z", "salary": {"currency": null, "max": null, "min": null, "period": "monthly", "term": null}, "salary_visible": false, "title_keywords": ["purchasing officer", "assistant purchasing officer"], "responsibilities": ["quotation", "monitor", "inspection", "prepare reports", "shipping document"], "requirements": {"degrees": [], "majors": [], "languages": ["english", "mandarin"], "language_level": ["fluency"], "hard_skills": ["plus"], "soft_skills": ["detail-minded", "work independently", "well-organized", "responsible"], "languages_combined": [{"language": "english", "language_level": ["fluency"]}, {"language": "mandarin", "language_level": ["fluency"]}]}, "experience_required": {"duration": ["at least 5 years"], "field": ["merchandising"]}}, {"job_id": "100003009050964", "location_code": "hk", "company": "Chandler Macleod Group (HK) Limited", "job_title": "Regional Merchandising Director (Luxury retail, RTW)", "description": "Employer Ref: NR09468\nNature of Business: Japan based Trading Company\u00a0\u00a0\nWorking Days: 5 Days\nWorking Location: Tsing Yi Area\n\nBenefits:\n- Double pay\n- Discretionary Bonus\n- Transportation Allowance\n- OT Allowance\n- Attendance allowance\n- Medical insurance\n\nRequirements:\n- Degree holder\n- Min. 3 years exp. in Purchasing/Buying/Product development\n- Business level in Japanese and English\n\nDuties:\n- Handle daily purchasing and product development duties\n- Maintain good relationship with overseas suppliers\n- Responsible for data entry and managements\n\nInterested in the above vacancy?\u00a0 Send your resume to us NOW!\nOnly short-listed candidates will be notified. Personal data collected will be used for recruitment purpose only", "employment_types": ["Full Time", "Permanent"], "selling_points": ["Market Leader", "Multinational working environment", "Competitive remuneration with multiple benefits"], "locations": ["Not Specified"], "categories": ["Merchandising & Purchasing", "Sweater", "Woven / Knit", "Others"], "post_time": "2022-01-14T12:08:05Z", "salary": {"currency": null, "max": null, "min": null, "period": "monthly", "term": null}, "salary_visible": false, "title_keywords": ["merchandising", "director"], "responsibilities": [], "requirements": {"degrees": [], "majors": [], "languages": [], "language_level": [], "hard_skills": [], "soft_skills": [], "languages_combined": []}, "experience_required": {"duration": [], "field": []}}, {"job_id": "100003009049538", "location_code": "hk", "company": "PARKnSHOP", "job_title": "Trading Controller (Fresh Food)", "description": "- Diploma or above, at least 3 years relevant experience with fluent English and Mandarin", "employment_types": ["Full Time"], "selling_points": [], "locations": ["Shatin Area"], "categories": ["Merchandising & Purchasing", "Others"], "post_time": "2022-01-15T00:51:45Z", "salary": {"currency": null, "max": null, "min": null, "period": null, "term": null}, "salary_visible": false, "title_keywords": [], "responsibilities": [], "requirements": {"degrees": ["diploma or above"], "majors": [], "languages": ["english", "mandarin"], "language_level": ["fluent"], "hard_skills": [], "soft_skills": [], "languages_combined": [{"language": "english", "language_level": ["fluent"]}, {"language": "mandarin", "language_level": ["fluent"]}]}, "experience_required": {"duration": ["at least 3 years"], "field": ["relevant experience"]}}, {"job_id": "100003009039572", "location_code": "hk", "company": "Trendy Group International Holdings Limited", "job_title": "Diamond & Stone Buyer", "description": "Job duty\n\nSupport the daily operation of purchasing and sourcing functions\nResponsible for purchasing activities from sourcing, price negotiation, stock management\nLiaise with suppliers on terms and conditions, pricing, ordering and delivery\nEnsure orders fulfillment meet scheduled timeline\nMonitor suppliers\u2019 performance\nPrepare purchasing and analysis reports\nHandle ad hoc assignments\n\nRequirement\n\nPost-secondary or above, preferably with professional diploma in purchasing & supply management\nOver 2 years proven experience in souring food/ non-food materials (in F&B/ catering service/ club house/ bakery)\nHandle shipping documents\nTalent in negotiations and networking\nDetailed-minded and good problem solving skills\nGood communication, negotiation skill with positive attitudes, enthusiasm\nProficiency in MS Word, Excel and Outlook\nOffice\u00a0in Sheung Shui\u00a0(Occasionally visit to Tai Po office is required)\n5 day work (Shift off on Saturday may be required)\nCandidates with more experience will be considered as Purchasing Officer\n\nCandidates with less experience will also be considered as Assistant Purchasing Officer.\n\nInterested parties please send full resume stating availability, salary history and expected salary by email via clicking \"Apply Now\"\n\nFor further information, please visit our website: www.yamazaki.hk\n\n(Personal data collected will be used for recruitment purpose only)", "employment_types": ["Full Time"], "selling_points": ["Preferably Gemologist or equivalent", "At least 5 years experience", "Immediate Available"], "locations": ["Hung Hom"], "categories": ["Merchandising & Purchasing", "Others", "Procurement / Purchasing / Sourcing"], "post_time": "2022-01-11T10:08:47Z", "salary": {"currency": null, "max": null, "min": null, "period": "monthly", "term": null}, "salary_visible": false, "title_keywords": [], "responsibilities": ["shipping documents", "price negotiation", "management", "stock management", "analysis reports", "fulfillment", "daily operation", "monitor", "communication", "ad hoc assignments", "liaise with suppliers", "catering"], "requirements": {"degrees": ["diploma"], "majors": [], "languages": [], "language_level": [], "hard_skills": ["excel", "analysis", "outlook", "problem solving skills", "ms word"], "soft_skills": ["negotiation", "responsible", "communication", "negotiation skill", "problem solving skills", "positive", "detailed"], "languages_combined": []}, "experience_required": {"duration": ["2 years"], "field": ["purchasing", "food", "f&b"]}}, {"job_id": "100003009043825", "location_code": "hk", "company": "Hero Cross Company Limited", "job_title": "Assistant Merchandiser", "description": "Responsibilities:\n\nFormulate merchandising strategies and prepare briefing on sales, sell -thru result, assortment mix and price structure\nManage Merchandising teams\nAnalyse and summarise analytical reports including weekly, monthly and seasonal reviews of the collection performance and relevant KPI\nConsolidate, verify and release country assortment plans and buying plans in line with overall budget objectives\nMonitor open to buy inventory and sales plan\nSupport countries with season end promotion planning in order to maximize sales and margins\n\nRequirements\n\nDegree holder in fashion & clothing or related discipline\nAt least 15 years of experience as Retail Buyer in Men's & Women's RTW\nStrong analytical and communication skills\nStrong computer skills especially in MS Word and Excel\nFluent in English\nWilling to travel", "employment_types": ["Full Time"], "selling_points": ["At least 2 years working experience", "Higher Diploma or above in Manufacturing", "Follow up order and sampling"], "locations": ["Kowloon Bay"], "categories": ["Merchandising & Purchasing", "Others", "Procurement / Purchasing / Sourcing"], "post_time": "2022-01-13T02:05:52Z", "salary": {"currency": null, "max": null, "min": null, "period": "monthly", "term": null}, "salary_visible": false, "title_keywords": ["assistant merchandiser"], "responsibilities": ["overall budget", "inventory", "teams", "merchandising", "monitor", "planning", "reports", "plan", "plans", "analyse"], "requirements": {"degrees": ["degree holder"], "majors": [], "languages": ["english"], "language_level": ["fluent"], "hard_skills": ["excel", "computer skills", "ms word"], "soft_skills": ["communication skills"], "languages_combined": [{"language": "english", "language_level": ["fluent"]}]}, "experience_required": {"duration": ["at least 15 years"], "field": ["retail"]}}, {"job_id": "100003009044513", "location_code": "hk", "company": "Global Packaging Limited", "job_title": "Account Executive", "description": "You can enjoy:\nComprehensive Medical and Life insurance coverage, including your spouse and children\nExclusive company pension schemes\nMarriage, Maternity and Paternity Leave\nExclusive shopping discount, Bazaar Sales for our people only\nProfessional training and career advancement opportunities\nContemporary workplace with Gym, Onsite Clinic, Lactation Rooms, and chill out areas\nFitness and wellbeing programmes\nConvenient office location, less than 5 min. walk from MTR\nFree round-trip lunchtime shuttle bus services to Shatin\nResponsibilities:\nWe are looking for a Trading Controller to lead Fresh Food Trading team in ensuring that the brand is delivering balanced, cohesive and innovative products and services throughout all channels within the business. Driving category growth in close partnership with key vendors and using data analysis together with customer insights to put a smile on our customers faces. Key job tasks including:\nEnsuring excellent execution of strategies to achieve Sales and Profitability\nEstablishing/managing relationships with key suppliers to develop programmes that build categories, drive differentiation and strengthen customer value\nImplementing strategic business development projects across categories especially those that will grow own brands sales participation and strengthen CRM member participation\nEnsuring compliance to existing policies and regulations within the company as well as government-mandated licenses and regulations\nRequirements:\nUniversity graduate with no less than 8 years\u2019 experience in managing Fresh Food trading in a sizable retailer chain\nStrong sourcing experience in Fruit & Veg, Meat and Seafood\nDemonstrating a proactive and agile approach to lead change and create competitive advantage\nBeing curious about how customer behaviours and trends shape the market\nBeing passionate about developing creative strategies that capture the attention of the customer\nAble to interpret data on customer habits and translate that into products/services that exceed customer expectations\nKnowledge in food production would be an advantage\nAn attractive salary and benefit package will be offered. Interested parties please forward detailed resume stating expected salary to: People Department, PARKnSHOP (HK) Limited, Watson House, 1-5 Wo Liu Hang Road, Fo Tan, N.T. or email to us.\nWe are an equal opportunity employer and welcome applications from all qualified candidates. The information provided will be treated in strict confidence and be used only for consideration of your application for relevant / similar posts within the A.S. Watson Group. All personal data of unsuccessful applicants will be destroyed within 12 months from the date of application.", "employment_types": ["Full Time"], "selling_points": ["High Diploma or above with 2 years relevant work", "With solid printing knowledge is preferred", "5 days working"], "locations": ["Kwai Hing"], "categories": ["Merchandising & Purchasing", "Others", "Manufacturing", "Printing", "Others", "Trading"], "post_time": "2022-01-14T01:23:12Z", "salary": {"currency": null, "max": null, "min": null, "period": "monthly", "term": null}, "salary_visible": false, "title_keywords": ["account executive"], "responsibilities": ["regulations", "policies", "compliance", "customer insights", "develop", "data analysis"], "requirements": {"degrees": ["university graduate"], "majors": [], "languages": [], "language_level": [], "hard_skills": ["no", "agile"], "soft_skills": ["creative", "proactive", "agile", "passionate about"], "languages_combined": []}, "experience_required": {"duration": ["8 years"], "field": ["food", "trading"]}}, {"job_id": "100003009047857", "location_code": "hk", "company": "Michaels Global Sourcing, LLC", "job_title": "Associate Sourcing Specialist / Assistant Merchandiser", "description": "Job Duties:\n\nl\u00a0\u00a0 Purchasing of Diamond and Stone materials\n\nl\u00a0\u00a0 In charge of Purchasing Dept\n\nl\u00a0\u00a0 Monitoring inventory and keep track of price trends\n\nl\u00a0\u00a0 Maintain accurate Purchasing Data and record\n\nl\u00a0\u00a0 Assortment of Diamond and Stone\n\nRequirement:\n\nl\u00a0\u00a0 Preferably Gemologist or equivalent academic qualification\n\nl\u00a0\u00a0 At least 5 years experience in purchase of diamond and gemstone\n\nl\u00a0\u00a0 Good knowledge in pricing and grading is preferable\n\nl\u00a0\u00a0 Knowledge in Jewellery Production;\n\nl\u00a0\u00a0 Good arithmetic, communication, problem solving and negotiation skills\n\nl\u00a0\u00a0 Good command of English and PC Knowledge\n\nl\u00a0\u00a0 Honest, Hardworking, Responsible and Organised\n\nl\u00a0\u00a0 Able to work independently;\n\nl\u00a0\u00a0 Occasional travel to PRC.\n\nl\u00a0\u00a0Immediate Available", "employment_types": ["Full Time", "Permanent"], "selling_points": ["Sourcing Process Execution and Vendor Management", "Michaels Stores, Largest US Arts & Crafts retailer", "End to end sourcing exposure"], "locations": ["Kowloon Bay"], "categories": ["Merchandising & Purchasing", "Sundries", "Others"], "post_time": "2022-01-14T04:03:38Z", "salary": {"currency": null, "max": null, "min": null, "period": "monthly", "term": null}, "salary_visible": false, "title_keywords": ["specialist", "associate", "assistant merchandiser"], "responsibilities": ["maintain", "inventory", "monitoring", "data"], "requirements": {"degrees": [], "majors": [], "languages": ["english"], "language_level": ["good command"], "hard_skills": ["problem solving", "pc knowledge"], "soft_skills": ["work independently", "responsible", "communication", "problem solving", "negotiation skills", "honest", "organised", "hardworking"], "languages_combined": [{"language": "english", "language_level": ["good command"]}]}, "experience_required": {"duration": ["at least 5 years"], "field": []}}, {"job_id": "100003009039122", "location_code": "hk", "company": "ImagineX Management Co Ltd", "job_title": "Part Time Clerk - Merchandising", "description": "Responsibilities:\n\nFollow up order and sampling to ensure on time delivery\nLiaise with factory on production schedule\nMonitor inspection booking, QC samples and reports\nWork closely and effectively with Marketing, Sales, Design & Quality Team\n\nRequirement\n\nHigher Diploma or above in Manufacturing/ Industry Engineering or related disciplines\nfamiliar with factory production\nExperience in toy field is as advantage\nGeneral knowledge of toy safety regulations\nGood command of English and Mandarin\nGood command of PC operation in MS Office (Word, Excel, PowerPoint) and Chinese Input\nWell organized, responsible, problem solving and proactive.\nAt least 2 years working experience\u00a0\n\n12-15k negotiable\n\nCandidate with less experience will be considered as the Merchandising Clerk", "employment_types": ["Part Time"], "selling_points": ["Undergraduates are welcomed", "Able to work 3 days per week", "Free Shuttle Bus"], "locations": ["Southern Area"], "categories": ["Admin & HR", "Clerical / Admin Staff", "Merchandising & Purchasing", "Textiles", "Others"], "post_time": "2022-01-11T08:46:14Z", "salary": {"currency": null, "max": null, "min": null, "period": "hourly", "term": null}, "salary_visible": false, "title_keywords": ["part time clerk", "merchandising"], "responsibilities": ["monitor", "ensure on time delivery", "design", "inspection", "quality", "reports", "schedule", "booking", "liaise with"], "requirements": {"degrees": ["higher diploma or above"], "majors": ["related disciplines", "manufacturing", "engineering"], "languages": ["english", "chinese", "mandarin"], "language_level": ["good command"], "hard_skills": ["chinese input", "excel", "word", "powerpoint", "problem solving", "pc", "ms office"], "soft_skills": ["problem solving", "proactive", "well organized", "responsible"], "languages_combined": [{"language": "english", "language_level": ["good command"]}, {"language": "chinese", "language_level": ["good command"]}, {"language": "mandarin", "language_level": ["good command"]}]}, "experience_required": {"duration": ["at least 2 years"], "field": ["merchandising"]}}, {"job_id": "100003009046426", "location_code": "hk", "company": "Eternity Consultants (HK) Ltd", "job_title": "Sourcing Manager / Senior Buyer ~ Supermarket (Food and Non-food Products)", "description": "We are looking for high caliber candidate to join us and work together for the growth\u00a0of both our Company and individual.\n\nWhat will you be doing?\nThis position is responsible for supporting the execution and improvement of end-to-end best practices in Global Sourcing for assigned product categories.\u00a0\u00a0 This role is accountable for supporting the development and management of vendors, as well as maintaining existing vendor relationships and driving projects to ensure that vendors meet or exceed their contractual obligations by delivering innovative, quality products on time.\n\nRoles & Responsibility:-\n\nAssist the team in Sourcing Process Execution and Vendor Management\nExecute and improve the end-to-end sourcing processes including vendor management, price negotiation, product development and sample assessment to meet the on-time delivery, quality and commercial KPIs\nSource and develop potential vendors as well as drive a respectful and collaborative vendor relationship with existing vendors to ensure they meet all company\u2019s requirements including value, quality and innovation\nLiaise with various parties in sample handling, order management, laboratory testing, packaging artwork creation and approval processes\nSupport on Request for Proposal, category costing bids and product development independently in conjunction with and product development and sourcing teams\nAssists in product development trip, sourcing trip and finalization events to ensure its smooth arrangement\nExecute order management to ensure accuracy of database; Monitor and regular update on project status of assigned product categories\nPerform data entry and provide other administrative support in the team; Support ad hoc assignments and projects if necessary\n\nKnowledge, Skills and Abilities requirement:-\n\nDegree/Associate Degree/Diploma holder in Merchandising/ Business Management or related discipline\nHands-on computer knowledge in MS word, Excel, Outlook, Power Point & Chinese Word Processing\nMinimum 1 years\u2019 relevant working experience\nEnergetic, self-motivated, detail-oriented and independent working style\nGood communication and interpersonal skills\nEager to work in a team in order to achieve best results\nThe ability to work in a demanding but collegial, team-oriented environment\nGood command of both written and spoken English and Mandarin\nFrequent travel is required; Up to 30% travel\nWe offer competitive pay package and attractive fringe benefits including employer voluntary contribution on MPF scheme, Medical Insurance such as out-patient, hospitalization and dental coverage for employee, spouse and dependents. For interested parties, please make your application by stating the current and expected salaries.\n\nPersonal data collected will be used strictly for recruitment purpose only.", "employment_types": ["Full Time", "Permanent"], "selling_points": ["Daily buying process from budgeting to launching", "Manage supply chain and logistics functions", "Strong organizational and planning skills"], "locations": ["Not Specified"], "categories": ["Merchandising & Purchasing", "Sundries", "Others", "Procurement / Purchasing / Sourcing"], "post_time": "2022-01-13T11:03:03Z", "salary": {"currency": null, "max": null, "min": null, "period": "monthly", "term": null}, "salary_visible": false, "title_keywords": ["sourcing manager"], "responsibilities": ["product categories", "management", "price negotiation", "order management", "data entry", "administrative support", "quality", "teams", "monitor", "develop", "testing", "ad hoc assignments", "database", "liaise with", "kpis"], "requirements": {"degrees": ["diploma holder", "associate degree", "degree"], "majors": ["business"], "languages": ["english", "chinese", "mandarin"], "language_level": ["good command"], "hard_skills": ["business management", "excel", "chinese word processing", "scheme", "outlook", "power point", "ms word"], "soft_skills": ["self-motivated", "independent", "detail-oriented", "hands-on", "communication and interpersonal skills", "patient", "energetic"], "languages_combined": [{"language": "english", "language_level": ["good command"]}, {"language": "chinese", "language_level": []}, {"language": "mandarin", "language_level": ["good command"]}]}, "experience_required": {"duration": ["minimum 1 years"], "field": ["relevant working experience"]}}, {"job_id": "100003009039670", "location_code": "hk", "company": "Grand Concord Garment (HK) Limited", "job_title": "Senior Merchandiser", "description": "Are you a passionate and yet creative talent who can think out of the box to driving the people agenda with a new approach? ImagineX Group is a premier retail, brand management and distribution company. We build luxury, designer and premium contemporary fashion, beauty and lifestyle businesses with an entrepreneurial approach and the passion and flair of a brand owner.\n\n\nWe are now inviting a creative, self-motivated, energetic and talented Part Time Clerk - Merchandising to join us.\u00a0\n\n\nWHAT YOU WILL BE DOING?\n\nAssist and support buyers in all matters relating to buying, operations and promotion initiatives\nProvide clerical support the team\nPerform other ad-hoc projects as assigned\nYOU NEED TO BE\u2026\nBachelor degree or above, undergraduate students are also welcome\u00a0\nStrong analytical and communication skills\nGood knowledge in MS Word, Excel and PowerPoint\nAble to work 3 days per week\nWE OFFER YOU\u2026\n\nFlexible working hour (total 3 working days a week)\nFree shuttle bus services\n\n\nInterested parties please send your Full resume with expected salary to us through \"Apply Now\"\u00a0 or\u00a0WhatsApp 6411 4891\n\nInformation provided will be treated in strict confidence and only be used for recruitment purpose. The Company may refer suitable applicants to other vacancies within the associated Group of companies.\nFor more information of ImagineX Group, please visit our web site at\u00a0http://www.imaginex.com.", "employment_types": ["Full Time"], "selling_points": ["Merchandising & Product Development", "5-day work", "Double pay"], "locations": ["Quarry Bay"], "categories": ["Merchandising & Purchasing", "Woven / Knit", "Others"], "post_time": "2022-01-11T10:25:51Z", "salary": {"currency": null, "max": null, "min": null, "period": "monthly", "term": null}, "salary_visible": false, "title_keywords": ["senior merchandiser"], "responsibilities": ["provide clerical support", "management", "operations", "merchandising", "communication", "ad-hoc projects"], "requirements": {"degrees": ["degree or above", "bachelor"], "majors": [], "languages": [], "language_level": [], "hard_skills": ["excel", "powerpoint", "ms word"], "soft_skills": ["passionate", "communication skills", "self-motivated", "energetic", "creative"], "languages_combined": []}, "experience_required": {"duration": [], "field": []}}, {"job_id": "100003009042981", "location_code": "hk", "company": "HongKong Suning.com Co., Limited", "job_title": "Buyer / Assistant Buyer", "description": "A well-established holding company is starting new supermarket business, is URGENTLY seeking for:\n\nSourcing Manager / Senior Buyer ~ Supermarket (Food and Non-food Products)\n\nResponsibilities:\n\nWork closely with Sales & Business Development Team for maximizing top line and minimizing inventory\nStrong at daily / seasonal buying process from budgeting to launching\nStrong at analyze regular buying to spot out the most sellable goods in order to achieve the great sales performance\nManage supply chain and logistics functions for the imported goods / food\n\nRequirements:\n\nDegree of Business Administration or related disciplines\nMinimum 5 years of relevant experience, preferably on the food and non-food products or grocery section / frozen food in supermarket industry\nIdentify and evaluate cost saving opportunities, reliable supplier base and quality vendors\nKeep abreast of concurrent food and non-food statutory regulations as to ensure all the ordered item are comply with safety and regulatory rules\nStrong organizational and planning skills\nLess experience is also considered as \u201cSenior Buyer\u201d\n\n*Interested parties, please send full resume with current & expected salary & date available in MS WORD FORMAT ONLY to email: \u00a0jobs@HKETERNITY. com \u00a0\u00a0\u00a0or fax to 3527 0634\n\nHotline: (852) 3542 5082\n\nFor more jobs, please visit our website: www.hketernity.com\n\nWe are welcome applicants resend resumes to us even you have applied jobs in our company before.\n\n(Personal data submitted are for recruitment purpose only.)\u00a0", "employment_types": ["Full Time"], "selling_points": ["Develop and manage buying and selling plan", "Follow up and issue purchase orders", "Immediately available is preferred"], "locations": ["Kwun Tong"], "categories": ["Merchandising & Purchasing", "Electronics", "Others"], "post_time": "2022-01-12T09:24:23Z", "salary": {"currency": null, "max": null, "min": null, "period": "monthly", "term": null}, "salary_visible": false, "title_keywords": ["assistant"], "responsibilities": ["budgeting", "inventory", "sales performance", "logistics"], "requirements": {"degrees": ["degree"], "majors": ["related disciplines", "business administration"], "languages": [], "language_level": [], "hard_skills": [], "soft_skills": ["reliable", "organizational and planning skills"], "languages_combined": []}, "experience_required": {"duration": ["minimum 5 years"], "field": ["food", "relevant experience"]}}, {"job_id": "100003009037391", "location_code": "hk", "company": "Senko Advanced Components (HK) Ltd", "job_title": "Inventory Planner", "description": "Job Description:\n\n\u00a0 \u00a0 \u00a0 \u00a0 \u00a0Assess product construction based on fabrics, trims and treatments and to build the Smart product to achieve the aesthetics and margin goals\n\u00a0 \u00a0 \u00a0 \u00a0 \u00a0Call out any risks on quality, capability and capacity at the early development stage and escalate to supervisor\n\u00a0 \u00a0 \u00a0 \u00a0 \u00a0Assess risks early to pull in CFT and QA expertise and work on solutions\u00a0\n\u00a0 \u00a0 \u00a0 \u00a0 \u00a0Obtain and apply an understanding of fact-based costing\u00a0\n\u00a0 \u00a0 \u00a0 \u00a0 \u00a0Come up with different cost options to achieve the business goals\u00a0\n\u00a0 \u00a0 \u00a0 \u00a0 \u00a0Coordinate for the design trip. E.g. Work with vendors on the newness, innovation and samples. Post trip follow up with vendors.\n\u00a0 \u00a0 \u00a0 \u00a0 \u00a0Drive Calendars for new styles\u00a0\n\u00a0 \u00a0 \u00a0 \u00a0 \u00a0Participate the meeting with vendor for reviewing the details of the tech pack of meeting sample.\n\u00a0 \u00a0 \u00a0 \u00a0 \u00a0Communicate with counterpart or design on the tech pack clarification.\u00a0\n\u00a0 \u00a0 \u00a0 \u00a0 \u00a0Work on costing details and price negotiation with vendors.\u00a0\n\u00a0 \u00a0 \u00a0 \u00a0 \u00a0Work closely with vendors on costing engineering.\u00a0\n\u00a0 \u00a0 \u00a0 \u00a0 \u00a0Fill in and review compliance questionnaires\u00a0\n\u00a0 \u00a0 \u00a0 \u00a0 \u00a0Facilitate the risk assessment meeting.\u00a0\n\u00a0 \u00a0 \u00a0 \u00a0 \u00a0Co-ordinate with cross functional teams including Fit approval and style duplications\n\u00a0 \u00a0 \u00a0 \u00a0 \u00a0Call out any hurdles on the meeting samples for the brand meetings\u00a0\n\u00a0 \u00a0 \u00a0 \u00a0 \u00a0Update and tracking BOM\u00a0\n\u00a0 \u00a0 \u00a0 \u00a0 \u00a0Learn and work on enterprise software (e.g. ERP)\u00a0\n\u00a0 \u00a0 \u00a0 \u00a0 \u00a0Build manufacturing and product knowledge by spending time at the development centers and manufacturing sites\n\n\u00a0Requirements:\u00a0\n\n\u00a0 \u00a0 \u00a0 \u00a0 \u00a0 \u00a0 \u00a0 \u00a0 5+ years related experience in following up time and action\u00a0\n\u00a0 \u00a0 \u00a0 \u00a0 \u00a0 \u00a0 \u00a0 \u00a0 Relevant capability in Merchandising/ Product Development \u2013 costing, consumption, risk assessment, product development.\u00a0 Experience in Cut & Sew knit \u00a0is preferable\n\u00a0 \u00a0 \u00a0 \u00a0 \u00a0 \u00a0 \u00a0 \u00a0 Qualifications/experience in cost engineering or technical design would be an advantage\n\u00a0 \u00a0 \u00a0 \u00a0 \u00a0 \u00a0 \u00a0 \u00a0 Proficient in Word, Excel and Powerpoint\u00a0\n\u00a0 \u00a0 \u00a0 \u00a0 \u00a0 \u00a0 \u00a0 \u00a0 Good command in spoken and written English and Chinese\u00a0\n\u00a0 \u00a0 \u00a0 \u00a0 \u00a0 \u00a0 \u00a0 \u00a0 Certificate/Diploma or equivalent\u00a0", "employment_types": ["Full Time", "Permanent"], "selling_points": ["Stable Business", "Work with people who are friendly and supportive", "Attractive package and benefits"], "locations": ["Kwun Tong"], "categories": ["Merchandising & Purchasing", "Electronics", "Others", "Procurement / Purchasing / Sourcing"], "post_time": "2022-01-11T02:42:00Z", "salary": {"currency": null, "max": null, "min": null, "period": "monthly", "term": null}, "salary_visible": false, "title_keywords": [], "responsibilities": ["communicate with", "cost", "business goals", "price negotiation", "software", "co-ordinate with", "clarification", "review", "quality", "compliance", "design", "teams", "coordinate", "assess risks", "tracking"], "requirements": {"degrees": ["certificate", "diploma"], "majors": [], "languages": ["english", "chinese"], "language_level": ["good command"], "hard_skills": ["excel", "word", "powerpoint"], "soft_skills": [], "languages_combined": [{"language": "english", "language_level": ["good command"]}, {"language": "chinese", "language_level": ["good command"]}]}, "experience_required": {"duration": ["5+ years"], "field": ["related", "engineering", "design"]}}, {"job_id": "100003009042303", "location_code": "hk", "company": "HKT", "job_title": "Assistant Manager, Group Purchasing (General Services & Special Projects)", "description": "Responsibilities:\n\n\nMaintain the purchase database.\nDevelop and manage buying and selling plan to cope with company strategies and market sales trends.\nOrganized sales target, detail-minded and able to work independently in a fast-paced\u00a0environment.\nFollow up and issue purchase orders and arrange delivery schedule.\nAssist to ad-hoc tasks as assigned.\nCandidate with more experience will be considered as Buyer /Merchandiser\nQualification:\n\n\nBachelor degree with at least 2-3 years relevant experience in FMCG industry, preferably in Electronics.\nSkillful in computer (MS Word, Excel, PowerPointetc).\nFluent in Cantonese, English, Mandarin.\u00a0\nStrong business acumen with excellent negotiation and analytical skills.\u00a0\u00a0\nStrong communication & problem solving skills.\u00a0 \u00a0\u00a0\nReady to learn new things and willing to work under pressure and tight timeline.\nImmediately available is preferred\n\nRemark:\n\nWe offer attractive remuneration package including meal allowance, medical benefits and year-end bonus. Applicants please\u00a0send your full resume with expected salary to recruitment e-mail.\n\n\nInformation collected will be kept confidential and to be used for recruitment purpose.", "employment_types": ["Full Time"], "selling_points": [], "locations": ["Wan Chai"], "categories": ["Merchandising & Purchasing", "Others", "Procurement / Purchasing / Sourcing"], "post_time": "2022-01-12T06:56:48Z", "salary": {"currency": null, "max": null, "min": null, "period": "monthly", "term": null}, "salary_visible": false, "title_keywords": ["assistant manager,"], "responsibilities": ["sales target", "ad-hoc tasks", "develop", "delivery schedule", "communication", "purchase", "maintain", "plan", "database", "work under pressure"], "requirements": {"degrees": ["degree", "bachelor"], "majors": [], "languages": ["cantonese", "english", "mandarin"], "language_level": ["fluent"], "hard_skills": ["excel", "ms word", "fmcg industry", "analytical skills", "problem solving skills", "acumen"], "soft_skills": ["detail-minded", "organized", "work independently", "negotiation", "fast-paced environment", "analytical skills", "communication", "business acumen", "problem solving skills", "work under pressure"], "languages_combined": [{"language": "cantonese", "language_level": ["fluent"]}, {"language": "english", "language_level": []}, {"language": "mandarin", "language_level": []}]}, "experience_required": {"duration": ["at least 2-3 years"], "field": ["fmcg", "relevant experience"]}}, {"job_id": "100003009048047", "location_code": "hk", "company": "Manpower Services (Hong Kong) Limited", "job_title": "Procurement Manager (Asset&Equipment)(Energy Company)(80K-90K)(1M-1.3M)", "description": "Job Duties\n\nManage and maintain current inventory\nCreate effective strategies to manage variety of product categories\nReview and analysis inventory flow, predict and forecast future inventory need\nMeasure customer forecast accuracy\nCollaborate with factory to set priority of item production\nMaintain ERP order status, review and release new order to factories\nCollaborate with vendor to ensure delivery schedule on time and on demand\nCollaborate with QA team to ensure product quality in IQC\nSupport sales team to manage product shipping schedules\nRecommend and implement process improvement\nSupport new ERP system implementation\nOther Ad-hoc duties as assigned by senior staff or management.\u00a0\nRequirement\n\nDiploma or above\nAt least 2 years relevant working experience\nFresh graduates also welcomed to apply for a junior position\nPossess strong interpersonal communication skills\nStrong interests in data analysis, predictive analysis\nProactive collaboration within multi-culture team-work environment\nGood language skill in English and Chinese (including Mandarin)\nStrong computer skill, proficient in MS Excel, MSWord, ERP system\nWe are an equal opportunity employer, offers 5-day work, double Pay, 2 bonus per Year, 14 to 22 days annual leave, training opportunity, medical and life insurance. Interested applicants please submit a full resume indicating current and expected salary with earliest availability.", "employment_types": ["Permanent"], "selling_points": ["Good Salary Package", "Excellent Salary Package with Bouns (Extra ORSO)", "Strong Support from Company"], "locations": ["Others"], "categories": ["Merchandising & Purchasing", "Others", "Procurement / Purchasing / Sourcing"], "post_time": "2022-01-14T04:36:20Z", "salary": {"currency": null, "max": null, "min": null, "period": "monthly", "term": null}, "salary_visible": false, "title_keywords": ["manager"], "responsibilities": ["product categories", "collaborate with", "management", "shipping", "schedules", "inventory", "review", "analysis", "quality", "implementation", "delivery schedule", "maintain", "sales team", "forecast", "ad-hoc duties"], "requirements": {"degrees": ["diploma or above"], "majors": [], "languages": ["english", "chinese", "mandarin"], "language_level": ["good"], "hard_skills": ["analysis", "erp system", "ms excel", "computer skill", "msword"], "soft_skills": ["communication skills", "proactive", "interpersonal"], "languages_combined": [{"language": "english", "language_level": ["good"]}, {"language": "chinese", "language_level": ["good"]}, {"language": "mandarin", "language_level": ["good"]}]}, "experience_required": {"duration": ["at least 2 years"], "field": ["relevant working experience"]}}, {"job_id": "100003009038029", "location_code": "hk", "company": "Monty Limited", "job_title": "Senior Merchandiser", "description": "Responsibilites :\n\n\nResponsible for merchandise order and planning in accordance with respective merchandising strategies from US\nWork closely with US team to arrange prompt shipment\nCollaborate with internal parties to ensure the timeline\nGood communication skill. Able to email direct with oversea customer for US market\nDetail oriented, flexible minded with self confidence, able to work under pressure and overtime\n\nRequirements :\n\n\nAt least one year relevant working experience.\nx and Problem solver\nFluent English and Mandarin. PC knowledge. Immediate available is preferred\nWe offer competitive remuneration package with comprehensive fringe benefits to the right candidate.\n\n\nInterested parties please send full resume with expected salary via \"Apply NOW\"\n", "employment_types": ["Full Time"], "selling_points": [], "locations": ["Kowloon Bay"], "categories": ["Merchandising & Purchasing", "Others"], "post_time": "2022-01-11T04:39:36Z", "salary": {"currency": null, "max": null, "min": null, "period": "monthly", "term": null}, "salary_visible": false, "title_keywords": ["senior merchandiser"], "responsibilities": ["collaborate with", "work under pressure", "merchandising", "communication", "internal parties", "planning"], "requirements": {"degrees": [], "majors": [], "languages": ["english", "mandarin"], "language_level": ["fluent"], "hard_skills": ["pc knowledge"], "soft_skills": ["problem solver"], "languages_combined": [{"language": "english", "language_level": ["fluent"]}, {"language": "mandarin", "language_level": ["fluent"]}]}, "experience_required": {"duration": ["at least one year"], "field": ["relevant working experience"]}}, {"job_id": "100003009046108", "location_code": "hk", "company": "Formia Limited", "job_title": "ASSISTANT MERCHANDISING MANAGER", "description": "Your role\n\nUnderstand and set direction to various procurement categories, particularly Office Products & Equipment and Contractor Services. Ensure supply availability, meet quality standards, and deliver best value to the companies\nFormulate and manage strategic relationship with suppliers, monitor and perform periodic review to ensure suppliers\u2019 performance and quality\nEnsure Tender/RFx with relevant bidder lists are properly issued, evaluated, shortlisted, negotiated, accepted and completed in accordance with the then-current purchasing policy and procedures\nWork closely with internal stakeholders to achieve results, advising and influencing when necessary\nResponsible for compliance of standing policy, procedures and certification requirements, and regularly review practices, policies, procedures, and systems in light of emerging best practices\nContribute to purchasing savings plans and provide insights on delivery of outcome within the Group\n\n\nTo succeed in this role\n\n5 years of experience in Purchasing and Supply field with supervisory exposure\nSolid procurement experience in either Office Products & Equipment and Contractor Services in sizable organization\nProven track record in purchasing management\nFamiliarity with Quality System Requirements including ISO\nKnowledge on international trade control, sanction laws and regulations highly preferred\nProven negotiation, influencing skills and the ability to prioritize\nExcellent people skills that enable team work and effective partnership with both internal & external stakeholders\nCandidate with more experience might be considered for the post of Purchasing Manager\n\nIf you have the desire for an exciting and rewarding career, please apply by sending your resume immediately, quoting your present and expected salary by clicking \"Apply Now\".\n\nFor more information on other job opportunities of PCCW/HKT Corporate Functions, please visit our website. (http://www.hkt.com/about-hkt/careers/job-opportunities)", "employment_types": ["Full Time", "Permanent"], "selling_points": ["Merchandiser in gifts & premiums products", "5 days work week, 15 days AL", "Excellent career development"], "locations": ["Lai Chi Kok"], "categories": ["Merchandising & Purchasing", "Handbag", "Sundries", "Others"], "post_time": "2022-01-13T09:38:30Z", "salary": {"currency": null, "max": null, "min": null, "period": "monthly", "term": null}, "salary_visible": false, "title_keywords": ["merchandising manager", "assistant"], "responsibilities": ["regulations", "provide insights", "management", "control", "policies", "review", "monitor", "quality", "procedures", "compliance", "systems", "website", "tender", "plans"], "requirements": {"degrees": [], "majors": [], "languages": [], "language_level": [], "hard_skills": [], "soft_skills": ["negotiation", "responsible", "prioritize"], "languages_combined": []}, "experience_required": {"duration": ["5 years"], "field": ["purchasing", "supervisory", "sizable organization", "procurement"]}}, {"job_id": "100003009050699", "location_code": "hk", "company": "Links International", "job_title": "Assistant Category Manager", "description": "GENERAL DESCRIPTION:\n\nWe are looking for an Assistant Merchandising\u00a0Manager (Assistant Account Manager)\u00a0to work in our operations team driving projects and communication with our global airline customers, brand partners, suppliers as well as multifunctional organization.\n\nOur ideal candidate, who is reporting to the Senior Operations Manager, comes with a detail-oriented mindset, is well organized and demonstrates personal ownership in a proactive and solution oriented working approach. This is combined with a positive outlook, the relentless drive to learn and the openness to effectively collaborate within young and dynamic teams.\n\nIn return, we offer a professional and energetic work environment, competitive compensation programs, comprehensive benefits coverage and much more.\n\n\nESSENTIAL JOB DESCRIPTION:\n\nEffectively liaise and communicate with international airline customers as well as brands, suppliers and logistics providers to further grow our business\nProvide world-class end-to end service to our customers across the areas of customer care, product development, data entry, purchasing, supply planning, production, and quality control\nEffectively manage multifunctional projects including project planning, calculations, products/suppliers sourcing, negotiations and benchmarking as well as artwork & sample development and tender submissions\nCoordinate daily operational activities to ensure order fulfilment through effective production & logistics planning, sales & purchase order creation, invoicing, as well as after sales services\nConstantly review existing workflows and provide improvement recommendations to enhance efficiency, eliminate losses and deliver cost savings \u00a0\nEnsure the key business projects and orders for your region are delivered efficiently and with high quality\nAssist and support ad hoc projects to help the overall progression of the company\n\nJOB REQUIREMENTS:\n\nDegree holder, preferably in Business Administration, Supply Chain, Merchandising or related disciplines\n>7 years working experience in trading industry / merchandising / purchasing is preferable. Candidate will less experience will be consider as Senior Officer\nStrong sense of responsibility and ownership\nFlexible approach, able to work under pressure\u00a0\nFluent command of spoken and written English, Cantonese and Mandarin\u00a0\nExcellent command of computer literacy in Word, Excel and PowerPoint\nA good team player, pro-active, mature, outgoing, and self-motivated\nPositive, Confident and Smart\nImmediate availability is preferred\nWe offer attractive remuneration and benefits including, 5 days work per week (9am-6pm), work from home policy, 15 days annual leave, bonus, medical scheme. Interested parties please send full resume with your availability, present and expected salary, by clicking \"Apply Now\" button.\nPersonal data provided by applicants will be treated strictly in accordance with our personal data policy and for recruitment purposes only.", "employment_types": ["Full Time", "Permanent"], "selling_points": ["Fortune Global 500 Companies", "Convenience Store / Retailing", "2 years contract, subject to renewal"], "locations": ["Not Specified"], "categories": ["Hospitality / F & B", "Food & Beverage", "Others", "Merchandising & Purchasing", "Others"], "post_time": "2022-01-14T11:13:05Z", "salary": {"currency": null, "max": null, "min": null, "period": "monthly", "term": null}, "salary_visible": false, "title_keywords": ["assistant category manager"], "responsibilities": [], "requirements": {"degrees": [], "majors": [], "languages": [], "language_level": [], "hard_skills": [], "soft_skills": [], "languages_combined": []}, "experience_required": {"duration": [], "field": []}}, {"job_id": "100003009051013", "location_code": "hk", "company": "PARKnSHOP", "job_title": "Buyer (Station in Macau)", "description": "Green Power Paper Limited Hong Kong (GPP HK),\u00a0an expert in Retail Window Display and Packaging production. In order to cope with our needs for business growth, we are looking for qualified candidate for the following position.\n\nResponsibilities\n\nTo report to the director and works toward ensuring a smooth business environment with the focus of optimal sales and marketing performance.\nTo work closely with the team to oversee daily business operations\nTo communicate with production support team and factories on capacity planning and order follow up.\nTo liaise with different parties to improve performance and work efficiency\nTo monitor sales orders and supplier relations\nTo attending to any correspondence and emails by customers, clients and contractors\n\nRequirements\n\n\nHigher Diploma or above with minimum 5 years experience in account servicing and project management in packaging and window display production; candidate with less experience will be considered as Project Executive.\nKnowledge of the industry and market trends\nGood project and time management control\nExcellent verbal (English & Putonghua) and written communication skills (English)\nProficiency in Microsoft Office applications\nKnowledge of Photoshop or Accounting is an advantage.\u00a0\u00a0\nAn eye for attention to detail\nAbility to work effectively in a fast-paced environment\nSolid customer service experience is preferable\nImmediately available is highly preferred\n\nWe offer 5-day-work and friendly working environment. Interested candidates please send your full resume and expected salary to us. If you're hard working and dedicated, apply today!\n\nTo apply online please click the Apply button below.", "employment_types": ["Full Time"], "selling_points": [], "locations": ["Others - Macau"], "categories": ["Merchandising & Purchasing", "Others"], "post_time": "2022-01-15T00:47:51Z", "salary": {"currency": null, "max": null, "min": null, "period": null, "term": null}, "salary_visible": false, "title_keywords": [], "responsibilities": ["communicate with", "operations", "monitor", "liaise with", "report", "planning"], "requirements": {"degrees": ["higher diploma or above"], "majors": ["project management"], "languages": ["putonghua", "english"], "language_level": ["excellent"], "hard_skills": ["project management", "photoshop", "microsoft office"], "soft_skills": ["work effectively", "communication skills", "fast-paced environment", "project management", "customer service", "attention to detail", "time management"], "languages_combined": [{"language": "putonghua", "language_level": ["excellent"]}, {"language": "english", "language_level": ["excellent"]}]}, "experience_required": {"duration": ["minimum 5 years"], "field": ["project management", "customer service", "account servicing"]}}, {"job_id": "100003009047827", "location_code": "hk", "company": "Luk Fook Holdings Company Limited", "job_title": "\u63a1\u8cfc\u4e3b\u4efb(\u7d20\u91d1)", "description": "You can enjoy:\n\nComprehensive Medical and Life insurance coverage\nExclusive company pension schemes\nMarriage, Maternity and Paternity Leave\nExclusive shopping discount, Bazaar Sales for our people only\nProfessional training and career advancement opportunities\nResponsibilities:\n\nManage the assigned product category to drive sales and meet margin target\nSource and select new and exclusive products to meet customers' needs\nNegotiate with suppliers to achieve competitive price, deals and terms\nCoordinate with external and internal parties to deliver the best promotion campaigns\nRequirements:\n\nStation in Macau and with Macau citizenship is a must\nUniversity graduate or above\nMinimum 4 years' working experience in retail industry with sourcing and buying experience\nGood command of written and spoken English\nStrong negotiation skill, analytical and numeric ability\nCandidate will less experience will be considered as Assistant Buyer\nAn attractive salary and benefit package will be offered. Interested parties please forward detailed resume stating expected salary to: Human Resources Department, PARKnSHOP (HK) Limited, Watson House, 1-5 Wo Liu Hang Road, Fo Tan, N.T. or email to us.\n\nWe are an equal opportunity employer and welcome applications from all qualified candidates. The information provided will be treated in strict confidence and be used only for consideration of your application for relevant / similar posts within the A.S. Watson Group. All personal data of unsuccessful applicants will be destroyed within 12 months from the date of application.", "employment_types": ["Full Time"], "selling_points": ["\u5354\u52a9\u5206\u6790\u5e02\u5834\u9700\u6c42\u53ca\u8d70\u52e2", "\u5354\u52a9\u90e8\u9580\u54e1\u5de5\u7684\u7ba1\u7406\u53ca\u57f9\u8a13\u5de5\u4f5c", "\u5354\u52a9\u8655\u7406\u63a1\u8cfc\u90e8\u5176\u4ed6\u65e5\u5e38\u4e8b\u5b9c"], "locations": ["Shatin Area"], "categories": ["Merchandising & Purchasing", "Others", "Procurement / Purchasing / Sourcing"], "post_time": "2022-01-14T03:58:13Z", "salary": {"currency": null, "max": null, "min": null, "period": "monthly", "term": null}, "salary_visible": false, "title_keywords": [], "responsibilities": ["customers' needs", "coordinate with", "promotion campaigns", "drive sales", "internal parties"], "requirements": {"degrees": ["university graduate or above"], "majors": [], "languages": ["english"], "language_level": ["good command"], "hard_skills": [], "soft_skills": ["negotiation skill"], "languages_combined": [{"language": "english", "language_level": ["good command"]}]}, "experience_required": {"duration": ["minimum 4 years"], "field": ["retail industry"]}}]