[{"job_id": "100003009056543", "location_code": "hk", "company": "German Pool (Hong Kong) Ltd", "job_title": "Purchasing Officer / Assistant (Ref No. GPHK/AD/00211)", "description": "Responsibilities:\n\nPrepare and follow up purchasing orders, delivery arrangement and inventory control\nLiaise and coordinate with suppliers and factories\nPrepare analytical reports to minimize stock level\nWork closely with different departments to ensure products purchased are in line with the needs of the company\nProvide clerical and administrative support on daily operation of Product Development Department\nAssist in other ad-hoc assignments as required\n\nRequirements:\n\nDiploma or above in purchasing/supply chain or related disciplines\n3-5 year relevant experience, preferable in electronics industry\nGood command in spoken and written Chinese and English, fluency in Mandarin is an advantage\nProficiency in MS Office (Excel, PowerPoint etc.)\nGood communication and interpersonal skills\nDetail-minded, hard-working, independent and self-motivated\nWilling travel to Mainland China\nImmediate available is highly preferred\nBenefits:\n\nAttractive remuneration package\nYear end bonus\nStaff purchase discount\nOn the job training\nGood Career Prospects\nGroup Medical Insurance\nPaid Sick Leave, Marriage Leave, Compassionate Leave\n\n\n\nWe provide friendly and dynamic working environment to the right candidate.\u00a0 Interested parties, please send your full resume with current salary, expected salary and availability to\u00a0us\u00a0or by clicking \u2018Apply Now\u2019.\n\nFor more company details, please visit our website at www.germanpool.com\n\nGerman Pool (Hong Kong) Limited is an equal opportunity employer. It provides equal opportunity to all employees and applicants for employment in accordance with all applicable laws and regulations.\n\n(All information collected will be used for recruitment purpose only.)", "employment_types": ["Full Time", "Permanent"], "selling_points": [], "locations": ["To Kwa Wan"], "categories": ["Admin & HR", "Clerical / Admin Staff", "Merchandising & Purchasing", "Home Appliances", "Procurement / Purchasing / Sourcing"], "post_time": "2022-01-18T04:45:01Z", "salary": {"currency": null, "max": null, "min": null, "period": "monthly", "term": null}, "salary_visible": false, "title_keywords": ["assistant", "purchasing officer"], "responsibilities": ["liaise", "administrative support", "ad-hoc assignments", "coordinate with", "daily operation", "inventory control", "reports"], "requirements": {"degrees": ["diploma or above"], "majors": ["related disciplines"], "languages": ["english", "chinese", "mandarin"], "language_level": ["fluency", "advantage", "good command"], "hard_skills": ["excel", "powerpoint", "ms office"], "soft_skills": ["detail-minded", "self-motivated", "independent", "communication and interpersonal skills", "hard-working"], "languages_combined": [{"language": "english", "language_level": ["advantage", "good command"]}, {"language": "chinese", "language_level": ["fluency", "advantage", "good command"]}, {"language": "mandarin", "language_level": ["fluency", "advantage", "good command"]}]}, "experience_required": {"duration": ["3-5 year"], "field": ["relevant experience"]}}, {"job_id": "100003009054085", "location_code": "hk", "company": "Sodexo (Hong Kong) Limited", "job_title": "Purchasing Officer / Assistant Officer", "description": "Job Duties:\n\nResponsible for food and non-food products and service sourcing\nMonitor and liaise with suppliers to ensure high performance, competitive pricing, on-time delivery and quality service provided to Business Units\nIdentify, monitor and report purchasing savings & compliance\nSupport tender process\nWork closely with authorized suppliers and internal stakeholders\nAd hoc duties as assigned\n\n\u00a0Job Requirements:\u00a0\n\nWith tertiary qualification, vocational higher diploma in supply chain or purchasing and supply management or related discipline\nPreferably with minimum 2 years solid\u00a0experience of supply chain, strategic sourcing or procurement roles\nExperience in facility management and / or project management is a plus\nProven ability to work in a fast-paced environment\nIndependent, self reliant and\u00a0adaptable\nExcellent communication and interpersonal skills are essential\nImmediate available is preferred\n\nWe offer competitive remuneration package to the right candidates. Please apply with detailed resume and salary expectations to the Human Resources Department, Sodexo (Hong Kong) Limited by e-mail to hr.hk@ sodexo.com \u00a0 Please quote PR number on all correspondence.\n\n*Personal data collected is for recruitment purposes only. \u00a0", "employment_types": ["Full Time", "Permanent"], "selling_points": ["Procurement / Supply Management Assistant Officer", "Catalogue management, products/services sourcing", "1-2 years solid experience of procurement"], "locations": ["Yau Tsim Mong Area"], "categories": ["Hospitality / F & B", "Food & Beverage", "Others", "Merchandising & Purchasing", "Procurement / Purchasing / Sourcing"], "post_time": "2022-01-17T08:21:07Z", "salary": {"currency": null, "max": null, "min": null, "period": "monthly", "term": null}, "salary_visible": false, "title_keywords": ["assistant officer", "purchasing officer"], "responsibilities": ["ad hoc duties", "compliance", "quality", "monitor", "tender", "liaise with suppliers", "report"], "requirements": {"degrees": ["diploma"], "majors": [], "languages": [], "language_level": [], "hard_skills": ["project management", "plus"], "soft_skills": ["independent", "fast-paced environment", "adaptable", "project management", "communication and interpersonal skills"], "languages_combined": []}, "experience_required": {"duration": ["minimum 2 years"], "field": ["supply chain", "management", "project management", "procurement"]}}, {"job_id": "100003009050984", "location_code": "hk", "company": "Vocational Training Council", "job_title": "Officer (Supplies)", "description": "Ref. no :\u00a0C/VOU/OFF(SUPP)/11/21-AP2\n\u00a0\nMajor Duties:\n(a)\n\u00a0 \u00a0\u00a0 \u00a0To administer procurement operations including issue and acceptance of purchase orders / tenders, sourcing, contract monitoring, orders / tenders and contract negotiations;\n(b) \u00a0\u00a0 \u00a0To assist and coordinate Supplies team to ensure efficient and effective supplies service deliveries;\n(c)\n\u00a0 \u00a0\u00a0 \u00a0To supervise subordinates for provision of quality, professional procurement and supplies services, including integrity and ethics;\n(d) \u00a0\u00a0 \u00a0To offer professional advice / guidance to users on procurement and supplies matters;\n(e) \u00a0\u00a0 \u00a0To implement procurement policies, and conduct periodic review where necessary;\n(f) \u00a0\u00a0 \u00a0To help maintain operations of computerised procurement and supplies systems effectively;\n(g) \u00a0\u00a0 \u00a0To coordinate stock-taking and supervise the data maintenance of the inventory management system; and\n(h) \u00a0\u00a0 \u00a0To assist in development and implementation of projects as assigned.\n\u00a0\nRequirements:\n(a)\n\u00a0 \u00a0\u00a0 \u00a0A recognised degree preferably in Purchasing and Supply Management, Supply Chain Management, Business Administration or equivalent;\n(b) \u00a0\u00a0 \u00a0At least two years\u2019 relevant work experience, preferably in sizeable or comparable organisations;\n(c) \u00a0\u00a0 \u00a0Proficiency in Microsoft Office Software and computerised accounting / purchasing systems;\n(d) \u00a0\u00a0 \u00a0Good negotiation, problem-solving, time management, interpersonal and communication skills;\n(e) \u00a0\u00a0 \u00a0Good team spirit, be proactive and able to work independently under pressure; and\n(f) \u00a0\u00a0 \u00a0Good command of English and Chinese.\n\u00a0\nNotes:\n(1) \u00a0\u00a0 \u00a0Shortlisted candidates may be required to attend a written test in English.\n(2) \u00a0\u00a0 \u00a0The appointee may be required to perform duties outside normal office hours and in designated places as assigned.\n\nApplication Procedures:\nA completed application form [VTC-1 (Rev. 1/2018)], together with a full curriculum vitae, should be sent to the Human Resources Division, 18/F, VTC Tower, 27 Wood Road, Wanchai, Hong Kong.\u00a0 Please specify on the envelope the reference of the post being applied for.\n\u00a0\nClosing date for application:\u00a07 February 2022\n\n\u00a0Applicants not invited for interview within 10 weeks from the closing date may consider their applications unsuccessful.\n\u00a0\nThe Council reserves the right not to fill the post(s).\n\u00a0\nPersonal data collected will be used for recruitment purposes only. Information on unsuccessful candidates will normally be destroyed 12 months after the completion of the recruitment exercise.", "employment_types": ["Full Time"], "selling_points": ["Assist in development and implementation", "A recognised degree preferably in Purchasing", "At least two years\u2019 relevant work experience"], "locations": ["Not Specified"], "categories": ["Merchandising & Purchasing", "Others", "Procurement / Purchasing / Sourcing"], "post_time": "2022-01-17T06:00:29Z", "salary": {"currency": null, "max": null, "min": null, "period": "monthly", "term": null}, "salary_visible": false, "title_keywords": ["officer"], "responsibilities": ["guidance", "maintenance", "data", "operations", "monitoring", "quality", "review", "systems", "coordinate", "inventory management", "purchase", "procurement policies", "maintain", "implementation of projects"], "requirements": {"degrees": ["degree"], "majors": ["business administration"], "languages": ["english", "chinese"], "language_level": ["good command"], "hard_skills": ["microsoft office software", "problem-solving", "c"], "soft_skills": ["communication skills", "work independently", "team spirit", "proactive", "negotiation", "under pressure", "perform duties", "problem-solving", "time management", "interpersonal"], "languages_combined": [{"language": "english", "language_level": ["good command"]}, {"language": "chinese", "language_level": ["good command"]}]}, "experience_required": {"duration": ["at least two years"], "field": []}}, {"job_id": "100003009056410", "location_code": "hk", "company": "Panasonic Hong Kong Co., Limited", "job_title": "Procurement Coordinator / Officer", "description": "Responsibilities:\n\nTo handle\u00a0RFQ, PO processing and monitoring\nTo\u00a0keep close contact with customers and suppliers for quotation and follow up outstanding PO delivery status\nTo\u00a0maintain PO, invoice files and related purchasing records such as material, price, inventory and delivery records\nTo work with shipping team and support logistics operations with warehouse & forwarders where necessary\nTo assist other ad-hoc projects as assigned\n\n\nRequirements:\n\nForm 7 / DSE graduate or above\n2 years of relevant international trading experiences especially in electrical parts and components\nGood command of written and spoken English and Chinese, knowledge in Japanese is definitely an advantage\nProficient in MS Office\nGood communication skill, well organized and a fast learner\nMore experience will be considered as Procurement Officer\nImmediate available / short notice will be an advantage\n\nRemuneration will be commensurate with qualification and experience. Interested parties, please send your application with detailed resume indicating both existing & expected salary and date of availability to us.\n\nWe are an equal opportunity employer. All information provided by applicants will be treated in strict confidence and used for recruitment purpose only.", "employment_types": ["Full Time", "Permanent"], "selling_points": ["All round procurement exposure", "Attractive package with good career prospect", "Stable MNC in-house environment"], "locations": ["Tsim Sha Tsui"], "categories": ["Transportation & Logistics", "Supply Chain", "Merchandising & Purchasing", "Electronics", "Procurement / Purchasing / Sourcing"], "post_time": "2022-01-18T04:12:13Z", "salary": {"currency": null, "max": null, "min": null, "period": "monthly", "term": null}, "salary_visible": false, "title_keywords": ["officer", "coordinator"], "responsibilities": ["shipping", "invoice", "operations", "inventory", "quotation", "monitoring", "maintain", "logistics", "contact", "ad-hoc projects"], "requirements": {"degrees": ["dse"], "majors": [], "languages": ["japanese", "english", "chinese"], "language_level": ["advantage", "good command"], "hard_skills": ["ms office"], "soft_skills": ["fast learner", "communication skill", "well organized"], "languages_combined": [{"language": "japanese", "language_level": ["advantage", "good command"]}, {"language": "english", "language_level": ["advantage", "good command"]}, {"language": "chinese", "language_level": ["advantage", "good command"]}]}, "experience_required": {"duration": ["2 years"], "field": ["trading", "procurement"]}}, {"job_id": "100003009055070", "location_code": "hk", "company": "A.S. Watson Retail (HK) Limited", "job_title": "Procurement Officer - Retail Store Equipment", "description": "Come and join a Winning Team\n\nWe are Awesome!\n\nWhy Should You Join Us?\n\nAt ASW, we believe in our people, teamwork, and the importance of your personal growth.\u00a0If you are looking for the opportunity to join our award-winning international family with 15,000+ stores across 25 markets in Asia and Europe, the ASW family welcomes you\u2026\u00a0 #BePartofMORE\n\nYou can enjoy:\n\n\nComprehensive Medical and Life insurance coverage, including your spouse and children!\nProfessional training and career advancement opportunities!\nAttractive ACCA and CPA Australia Recognized Employee Partnership for F&A talents!\nExclusive company pension schemes!\u00a0 Marriage, Maternity, and Paternity Leave!\nConvenient office location, less than 5 min. walk from MTR!\nContemporary workplace, free drinks, and chill-out areas!\u00a0 Onsite Clinic and Lactation Room!\nWell-equipped Gym inside our office building, plus fitness and interest class packages!\nFree round-trip lunchtime shuttle bus services to Shatin!\nExclusive shopping discount, Bazaar Sales for our people only!\u00a0\n\nA typical day in this Role:\u00a0\n\n\nSupport in Project implementation including preparing and conducting tenders for special category (but not limited to), system deployment, improving process, developing KPI, driving for tender savings.\nPerform data collection, mining and database development.\nAssist the team to develop/execute savings plan according to the assigned target\nManage the relationship between suppliers and users, and provide supports to enhance suppliers management system\nMonitoring procurement project progress\nDevelop sourcing plan and monitoring market tracking index, to identify drivers to the commodity prices\nAble to communicate with all the related stakeholders\n\nThis job is a good fit for You if:\u00a0\n\nYou have\u00a0experience in managing the tender process\u00a0\nYou have\u00a0good communication and coordination skills and team working spirit\nYou enjoy working with Multi-cultural team & regional team\nWhat we look for:\n\n\nDegree/Diploma holder in Business Administration, Procurement, Supply Chain or related discipline\nAt least 2-3 years\u2019 Procurement or Supply Chain experience, with MNCs or China working experience is highly preferred.\nWith Project Management skillset and able to develop Project Performance Metrics/ Reports\nHands-on e-tender system utilization preferable\nFamiliar with tender process and general purchase contract terms and conditions\nStrong analytical skills with commercial sense and proactive attitude\nInterpersonal and negotiation skills is essential\nExcellent computer proficiency including excel, PowerPoint and access\nGood spoken and written English and Chinese.\nSome travel is required\u00a0\n\nWhat is holding you back?\u00a0\n\nDon\u2019t miss out on this great chance to shape Your life!\u00a0\n\nApply now!\n\nInterested parties please e-mail your full resume in WORD FORMAT with expected salary to our company email (shown in our Company Profile).\nWe are an equal opportunity employer and welcome applications from all qualified candidates. The information provided will be treated in strict confidence and be used only for consideration of your application for relevant / similar posts within the A.S. Watson Group.\nApplicants not hearing from us within 6 weeks from the date of advertisement may consider their applications unsuccessful. All personal data of unsuccessful applicants will be destroyed within 12 months from the date of application.\u00a0", "employment_types": ["Full Time", "Permanent"], "selling_points": ["Prepare tender process", "Identify effective & reliable sourcing strategies", "Enjoy working with Multi-cultural team & regional"], "locations": ["Shatin Area"], "categories": ["Transportation & Logistics", "Supply Chain", "Merchandising & Purchasing", "Procurement / Purchasing / Sourcing", "Sales, CS & Business Devpt", "Wholesale"], "post_time": "2022-01-18T01:09:27Z", "salary": {"currency": null, "max": null, "min": null, "period": "monthly", "term": null}, "salary_visible": false, "title_keywords": ["procurement officer"], "responsibilities": ["communication", "purchase", "database", "plan", "administration", "implementation", "developing", "develop", "project progress", "reports", "tender", "management", "monitoring", "data collection", "tracking", "communicate with", "performance metrics", "project management", "coordination", "insurance"], "requirements": {"degrees": ["diploma holder", "degree"], "majors": ["business administration"], "languages": ["english", "chinese"], "language_level": ["good"], "hard_skills": ["excel", "acca", "plus", "powerpoint", "analytical skills", "chill", "cpa", "project management", "deployment"], "soft_skills": ["coordination skills", "enjoy working", "teamwork", "analytical skills", "communication", "project management", "hands-on", "comprehensive", "negotiation skills", "team working", "proactive", "interpersonal"], "languages_combined": [{"language": "english", "language_level": ["good"]}, {"language": "chinese", "language_level": ["good"]}]}, "experience_required": {"duration": ["at least 2-3 years"], "field": ["supply chain", "procurement"]}}, {"job_id": "100003009053270", "location_code": "hk", "company": "Cathay Pacific Airways Ltd", "job_title": "Assistant Manager Compliance and Change (Procurement)", "description": "Reports to:\u00a0Compliance and Change Manager\nDepartment:\u00a0Procurement & Aircraft Trading (APD)\n\nRole Introduction\nThis position will be responsible\u202fto\u202fsupport the team on procurement transformational initiatives.\n\nKey Responsibilities\n\n\nWork with the Manager to develop and execute communication and content strategies to support the transformation procurement strategy\nProduce reactive and proactive internal communications that support transformation and change on the end to end process and deepen users\u2019 understanding of all relevant and critical information any new initiatives\nPlan, edit and write holistic content on communications channel including our digital employee portal (The Hub), e-newsletters, digital screens, and other offline channels to engage procurement teams in Head office and subsidiaries\nSupport the department on departmental pages on The Hub as the central communications point \u2013 including content creation, improving the user experience\nResponsible for common support channel monitoring and responses on Yammer on procurement processes\nUse data analytics to measure success and improve quality of communication\nDevelop communication plans and drive effective teamwork and collaboration across head office business units and outport teams\nDevelop quality templates and guidelines to nurture procurement best practice\nBuild robust relationships with business units to understand their procurement needs and streamline the source-to-pay (S2P) process by designing efficient procurement mechanisms\nAnalyse purchasing and transaction data to identify category opportunities and to measure utilisation and effectiveness of category taxonomy\nDrive stakeholder satisfaction by identifying value add and continuous improvement opportunities within the procure-to-pay process\nSupport the development of the procurement e-learning module\nManage functionality improvement, automation and digital transformation projects\nServe as a subject matter expert on procurement systems and processes\nRequirements\n\nUniversity graduate\n5+ years of relevant experience in procurement transformation\nStrong planning and organising skills\nExperience with eLearning tools and digital content app an advantage\nStrong communication skills\nAbility to work independently and meet tight deadlines\nNumerate and with good computer skills\nMotivated to deliver accurate and quality work\n\n\n\nApplication Deadline: 22 January 2022\n\nPersonal & Application Information\nCathay Pacific is an Equal Opportunities Employer. Personal data provided by job applicants will be used strictly in accordance with our personal data policy and for recruitment purposes only. Candidates not notified within eight weeks may consider their application unsuccessful. All related information will be kept in our file for up to 24 months. A copy of our Personal Information Collection Statement will be provided upon request by contacting our Data Protection Officer.\n\nPlease note that with effect from 1 December 2021, all employees must be vaccinated in order to access Cathay City and all other Cathay Group Company premises in Hong Kong. Consideration will be given to those who are unable to get vaccinated for valid medical reasons.\n\n\n\nThis position will be responsible\u202fto\u202fsupport the team on procurement transformational initiatives\nThis position will be responsible\u202fto\u202fsupport the team on procurement transformational initiatives\nThis position will be responsible\u202fto\u202fsupport the team on procurement transformational initiatives\nThis position will be responsible\u202fto\u202fsupport the team on procurement transformational initiatives\nThis position will be responsible\u202fto\u202fsupport the team on procurement transformational initiatives", "employment_types": ["Full Time", "Permanent"], "selling_points": ["5+ years experience in procurement transformation", "Support the transformation procurement strategy", "Travel Benefits, 5-day work, Medical Benefits"], "locations": ["Lantau Island"], "categories": ["Transportation & Logistics", "Aviation Services", "Merchandising & Purchasing", "Procurement / Purchasing / Sourcing"], "post_time": "2022-01-17T06:38:30Z", "salary": {"currency": null, "max": null, "min": null, "period": "monthly", "term": null}, "salary_visible": false, "title_keywords": ["assistant manager"], "responsibilities": ["data", "procurement processes", "guidelines", "monitoring", "teams", "user experience", "quality", "develop", "communication", "subject matter expert", "systems", "plan", "designing", "plans", "analyse"], "requirements": {"degrees": ["university graduate"], "majors": [], "languages": [], "language_level": [], "hard_skills": ["computer skills"], "soft_skills": ["communication skills", "work independently", "meet tight deadlines", "responsible", "motivated", "accurate"], "languages_combined": []}, "experience_required": {"duration": ["5+ years"], "field": ["digital content", "relevant experience", "procurement"]}}, {"job_id": "100003009056037", "location_code": "hk", "company": "DFI Retail Group DFI\u96f6\u552e\u96c6\u5718", "job_title": "Assistant Procurement Manager", "description": "The Job\n\nManage retail & store development procurement projects and work with multiple stakeholders across DFI group\nAlign and Implement procurement strategy and lead the negotiation for Banners\nWorks closely with stakeholders to review the scope, issue, proceed and evaluate RFI and RFx and E-Auction via Procurement system to achieve business objectives in terms of both quality, project plan and achieving best value for money\nEstablish compliance supplier evaluation /selection criteria and coordinates supplier due diligence activities\nParticipate in contract negotiation, analyze the technical and commercial scores to achieve business targets within the current market conditions\nResolve product and service-related problems, monitor supplier to follow and comply with Group Quality assurance requirements\nEnsures compliance with legal and regulatory requirements\n\nTo ensure integrity and ethics are sustained throughout the procurement process\n\nThe Person\n\nDegree or equivalent in Procurement and Supply/Business or related discipline\n5 years of procurement experience, in regional office of MNC and multi-market is preferred\nExperience in retail and store development procurement is an advantage\nExperience in dealing end to end procurement process and work independently\nStrong at data capture/analysis/options generating, able to provide solutions\nStrong communication, influencing and negotiation skills\nStrong computer literacy skills with excellent Excel spreadsheet knowledge\nExperience in E-Procurement and Contract system is an advantage\nGood command in Cantonese, Mandarin and English\n\nDFI Retail Group is responsible for ensuring that all personal information collected from each Candidate presented to DFI Retail Group is used for recruitment purposes only and the data collection process is in accordance with all applicable laws and compliant with the Code of Practice on Human Resource Management.\n\nTo find out more about Our Businesses and Our People, please visit our website: https://www.DFIretailgroup.com\n\nWe are an equal opportunity employer. Personal data collected will be kept and handled confidentially by authorised personnel for recruitment purposes only. We will retain the applications of candidates not selected for a period of no more than 24 months. A copy of our Privacy Policy can be accessed by visiting our Company website.\u201d\n\nIssued by The Dairy Farm Company, Limited", "employment_types": ["Full Time"], "selling_points": [], "locations": ["Quarry Bay"], "categories": ["Merchandising & Purchasing", "Procurement / Purchasing / Sourcing"], "post_time": "2022-01-18T03:12:49Z", "salary": {"currency": null, "max": null, "min": null, "period": "monthly", "term": null}, "salary_visible": false, "title_keywords": ["manager", "assistant"], "responsibilities": ["due diligence", "regulatory requirements", "review", "quality", "project plan", "compliance", "monitor", "evaluate", "banners", "evaluation"], "requirements": {"degrees": ["degree"], "majors": ["business"], "languages": ["cantonese", "english", "mandarin"], "language_level": ["good command"], "hard_skills": ["excel", "no", "analysis", "code", "spreadsheet"], "soft_skills": ["work independently", "responsible", "communication", "computer literacy", "negotiation skills"], "languages_combined": [{"language": "cantonese", "language_level": ["good command"]}, {"language": "english", "language_level": ["good command"]}, {"language": "mandarin", "language_level": ["good command"]}]}, "experience_required": {"duration": ["5 years"], "field": ["development", "retail", "procurement"]}}, {"job_id": "100003009054660", "location_code": "hk", "company": "Acton Consulting Limited", "job_title": "(Senior) Buyers / Purchasers - Procurement Operation x 6 openings", "description": "Our client is a sizable company. Due to the rapid growth of the company, they are now looking for talented individuals to join the professional team.\n\nThe Role:\n\nMaintain up-to-date commercial and contractual knowledge of the market place and methods to ensure that best practices are continually developed and utilized within the group\nManage completed Purchasing cycles\nCoordinate Purchase requisitions from business, advise requestor on sourcing channel and execute tactical sourcing as needed.\nMaintain the contract repository (upload and archive contracts as needed)\nReview contract compliance and contracts due for renewal\nSupport complication of procurement operations / performance reports\nThe Job;\n\nDiploma or University graduate or professional qualification in a related discipline\n3+ years' relevant experience in purchasing in ICT or Tech products and service, Common computer software and office supplies\nhands-on experience in Procurement operations experience is essential\nWorking experience in regulatory requirements and procurement policies\nAbility to inspire, and build trust and respect among the stakeholders\nExcellent people skills; including the ability to negotiate and influence internal and external stakeholders\nA team player, assertive yet approachable and decisive\nproficiency in Excel (V-lookup, macros) and PowerPoint Presentation and procurement systems\nwww.ActonCL.com Unit 2302, 23/F, New World Tower 1, 18 Queen's Road Central. Hong Kong\n\nAll information received will be kept in strict confidence and only for employment-related purposes", "employment_types": ["Full Time", "Permanent", "Contract"], "selling_points": ["Purchaser , Buyer", "Procurement operation", "5 days work"], "locations": ["Not Specified"], "categories": ["Merchandising & Purchasing", "Electronics", "Stationery", "Procurement / Purchasing / Sourcing"], "post_time": "2022-01-17T12:50:42Z", "salary": {"currency": null, "max": null, "min": null, "period": "monthly", "term": null}, "salary_visible": false, "title_keywords": [], "responsibilities": ["software", "performance reports", "office supplies", "contracts", "operations", "review", "compliance", "regulatory requirements", "systems", "coordinate", "purchase", "maintain", "procurement policies"], "requirements": {"degrees": ["university graduate", "diploma"], "majors": [], "languages": [], "language_level": [], "hard_skills": ["excel", "powerpoint", "rapid"], "soft_skills": ["confidence", "approachable", "assertive", "hands-on", "decisive", "team player", "presentation"], "languages_combined": []}, "experience_required": {"duration": ["3+ years"], "field": ["purchasing", "tech", "relevant experience", "procurement"]}}, {"job_id": "100003009037193", "location_code": "hk", "company": "Able Engineering Holdings Limited", "job_title": "Procurement Officer", "description": "Higher Diploma or above ;\nAt least 4 years' relevant working experience, with construction industry experience is preferred;\nGood communication and interpersonal skills;\nResponsible, well-organized and self-motivated;\nGood command of written and spoken English and Chinese;\nCandidate with less experience will be considered as Assistant Procurement Officer.\n\nWe offer competitive salary package and career development opportunity to the successful candidate. Interested parties may send your full resume, present and expected salary, available date and contact number by clicking \"Apply Now\"\n\nTo visit our website for more information:\u00a0www.ableeng.com.hk\n\n(As an Equal Opportunities Employer, Able is committed to eliminating discrimination in employment. The vacancy advertised is open to all applicants meeting the basic entry requirement irrespective of their disability, sex, marital status, pregnancy, age, family status, sexual orientation or race etc. Applicants not hearing from us within 6 months may consider their applications unsuccessful. Personal data collected will be used for recruitment related purposes only.)", "employment_types": ["Full Time"], "selling_points": [], "locations": ["Not Specified"], "categories": ["Merchandising & Purchasing", "Others", "Procurement / Purchasing / Sourcing"], "post_time": "2022-01-15T19:11:31Z", "salary": {"currency": null, "max": null, "min": null, "period": "monthly", "term": null}, "salary_visible": false, "title_keywords": ["procurement officer"], "responsibilities": ["communication"], "requirements": {"degrees": ["higher diploma or above"], "majors": [], "languages": ["english", "chinese"], "language_level": ["good command"], "hard_skills": [], "soft_skills": ["self-motivated", "communication and interpersonal skills", "well-organized", "responsible"], "languages_combined": [{"language": "english", "language_level": ["good command"]}, {"language": "chinese", "language_level": ["good command"]}]}, "experience_required": {"duration": ["at least 4 years"], "field": ["procurement", "construction industry", "relevant working experience"]}}, {"job_id": "100003009054861", "location_code": "hk", "company": "Abouthai (Hong Kong) Limited", "job_title": "Category Manager (Convenience Store)", "description": "Responsibilities:\n\nExecute and implement programs per category strategies as defined in budget and strategic planning\nLiaise with Marketing Team for developing an attractive promotional event which follow pre-agreed selling plan\nMonitor daily inventory, set up order forecast and implement daily replenishment to ensure sufficient stock level in stores\nEnsure stable stock level by good promotion plan and SKU management\nNegotiate and work with vendors to build mutually beneficial relationships to ensure long term strategic partnership, leading to lower costs and higher margin\nMonitor & identify of new trends, new brands, merchandising programs and ad-hoc strategies to optimize category growth and performance\nAnalyze market data and campaigns to ensure effectiveness and positive ROI\u00a0\u00a0\u00a0\u00a0\u00a0\u00a0\u00a0\nSupport any ad hoc projects as assigned\n\nRequirements:\n\nDegree holder in Business, Marketing, or other related disciplines\nMinimum 8 years working experience\u00a0in category management or trade marketing from Convenience Store or Supermarkets\nStrong negotiation skills & interpersonal relationships, leadership skill and presentation skill\nGood network and relationship with different kinds of organization and business sector\nResult-oriented, Self-motivated, aggressive, energetic and a good team player\nRegular travel and outdoor activities are expected\nExcellent command in written and spoken English and Chinese (including Cantonese and Mandarin)\nImmediately available is preferable\n\nWe offer 5-days work week, double pay and good career prospect to the right candidates. Interested parties, please send full resume with\u00a0present & expected\u00a0salaries & date availability to HR Department by \u201cApply Now\u201d below.\n\nAll information will be treated in strict confidence and will be used for recruitment related purpose only. Information of unsuccessful applicants will be destroyed upon completion of the recruitment process.", "employment_types": ["Full Time", "Permanent"], "selling_points": ["Category Management", "SKU Management", "Convenience store"], "locations": ["Tsuen Wan Area"], "categories": ["Merchandising & Purchasing", "Others", "Procurement / Purchasing / Sourcing"], "post_time": "2022-01-17T12:00:00Z", "salary": {"currency": null, "max": null, "min": null, "period": "monthly", "term": null}, "salary_visible": false, "title_keywords": ["category manager"], "responsibilities": ["ad-hoc", "management", "strategic planning", "inventory", "budget", "monitor", "developing", "replenishment", "merchandising", "order forecast", "ad hoc projects", "plan", "liaise with", "market data", "costs"], "requirements": {"degrees": ["degree holder"], "majors": ["related disciplines", "business", "marketing"], "languages": ["cantonese", "english", "chinese", "mandarin"], "language_level": ["excellent"], "hard_skills": ["presentation skill"], "soft_skills": ["presentation skill", "self-motivated", "good team player", "negotiation skills", "energetic", "leadership skill", "interpersonal", "result-oriented"], "languages_combined": [{"language": "cantonese", "language_level": ["excellent"]}, {"language": "english", "language_level": ["excellent"]}, {"language": "chinese", "language_level": ["excellent"]}, {"language": "mandarin", "language_level": ["excellent"]}]}, "experience_required": {"duration": ["minimum 8 years"], "field": ["management", "marketing"]}}, {"job_id": "100003009053559", "location_code": "hk", "company": "Cheung Hing Lifting Components (Hong Kong) Limited", "job_title": "Sourcing and Administration Officer", "description": "Responsibilities:\n\nTo source and evaluate suppliers\u2019 abilities, quality and production capacities.\nPreparation of costings and other analytical reports for cost calculation, comparison, control, and other purposes.\nPlace orders and arrange shipment and logistic handling.\nBuild relationships with suppliers while monitoring and driving their performance.\nPrepare Monthly Purchase & Inventory Report and price analysis.\nCommunicate with Sales Department to source and develop new products.\nTake care of office administration.\nPrepare marketing materials and product information.\nAssist in data input into the Accounting database.\nCarry out cost control measure.\nTo support ad-hoc duties as assigned upon request.\n\nRequirements:\n\nForm 7, DSE or above.\nSolid working experience in similar nature is preferred.\nQuick thinking and eager to take up responsibility.\nExcellent negotiation and communication skills.\nClear minded and able to resolve problems independently.\nCan work under pressure with tight deadline schedule.\nCan work independently with can-do spirit\nFluent spoken and written in English, Chinese and Mandarin.\nWorking on one Saturday morning for every month is required.\n\nSalary and Prospect:\n\nYear end bonus will be offered which makes up to totally 14 months salary per year.\n\nAfter completion of 1 year employment with the performance achieved more than 85% of the works assigned, we will offer at least 10% increase of the second year salary.\n\nOnly short listed candidates will be contacted.\u00a0 All personal information will be treated with strict confidence for recruitment purpose only, and will be disposed after six months.", "employment_types": ["Full Time", "Permanent"], "selling_points": ["To source and evaluate suppliers\u2019 abilities", "Form 7, DSE or above", "year end bonus"], "locations": ["Tsim Sha Tsui"], "categories": ["Admin & HR", "Clerical / Admin Staff", "Others", "Merchandising & Purchasing", "Procurement / Purchasing / Sourcing"], "post_time": "2022-01-17T07:09:33Z", "salary": {"currency": null, "max": null, "min": null, "period": "monthly", "term": null}, "salary_visible": false, "title_keywords": ["sourcing and administration officer"], "responsibilities": ["communicate with", "cost", "control", "ad-hoc duties", "office administration", "inventory", "monitoring", "quality", "analysis", "data input", "develop", "evaluate", "purchase", "reports", "database", "cost control", "prepare marketing materials", "report"], "requirements": {"degrees": ["dse"], "majors": [], "languages": ["english", "chinese", "mandarin"], "language_level": ["fluent"], "hard_skills": [], "soft_skills": ["communication skills", "work independently", "independently", "confidence", "negotiation", "clear", "can-do", "work under pressure"], "languages_combined": [{"language": "english", "language_level": ["fluent"]}, {"language": "chinese", "language_level": ["fluent"]}, {"language": "mandarin", "language_level": ["fluent"]}]}, "experience_required": {"duration": [], "field": []}}, {"job_id": "100003009051767", "location_code": "hk", "company": "Champion Global Services Limited", "job_title": "Assistant Group Procurement Officer", "description": "Responsibilities:\n\nAssist in managing the whole procurement process starting from vendor sourcing & selection, pricing & services benchmarking, negotiation, goods & services delivery and market research\nAssist in managing all services contracts and agreements\nLiaise with all relevant parties in relation to project deliverables\nAssist in work coordination and other ad-hoc projects as assigned\n\nRequirements:\n\nHigher Diploma or above in Procurement, Supply Chain or other related disciplines\nAt least 1 year\u2019s purchasing experience, preferably gained from hospitality industry or catering group\nKnowledge in budgeting and costing is an advantage\nGood communication and negotiation skills\nWell-organized and willing to learn\nAble to work under pressure and independently\nProficient in MS Office applications\nGood command of both spoken and written English and Chinese (including Putonghua)\nCandidates with more experience and qualifications will be considered as Group Procurement Officer\n\n\nSalary and benefits will be commensurate with qualifications and experience.\u00a0 Interested parties, please send a full resume with present and expected salary, and date available to The Human Resources Department, 32/F., Great Eagle Centre, 23 Harbour Road, Wanchai, Hong Kong or e-mail to us.\u00a0\u00a0(Please quote the reference no. on the envelope and the covering letter.)\n\nTo know more about us, please visit our website at http://www.greateagle.com.hk\n\nWe are an equal opportunity employer and welcome applications from all qualified candidates.\n\nPersonal data collected will be treated in strict confidence and used only for recruitment-related purpose. Applicants who have not heard from us within four weeks may consider their applications unsuccessful. All personal data will be destroyed after 12 months.", "employment_types": ["Full Time", "Permanent"], "selling_points": ["Group purchasing for hospitality industry", "Food / Non-food Procurement", "Contract and tender management"], "locations": ["Wan Chai"], "categories": ["Hospitality / F & B", "Food & Beverage", "Others", "Merchandising & Purchasing", "Procurement / Purchasing / Sourcing"], "post_time": "2022-01-17T00:58:05Z", "salary": {"currency": null, "max": null, "min": null, "period": "monthly", "term": null}, "salary_visible": false, "title_keywords": ["procurement officer", "assistant"], "responsibilities": ["project deliverables", "contracts", "market research", "coordination", "liaise with", "ad-hoc projects"], "requirements": {"degrees": ["higher diploma or above"], "majors": ["related disciplines"], "languages": ["putonghua", "english", "chinese"], "language_level": ["good command"], "hard_skills": ["ms office"], "soft_skills": ["independently", "willing to learn", "well-organized", "communication", "negotiation skills", "work under pressure"], "languages_combined": [{"language": "putonghua", "language_level": ["good command"]}, {"language": "english", "language_level": ["good command"]}, {"language": "chinese", "language_level": ["good command"]}]}, "experience_required": {"duration": ["at least 1 year"], "field": ["purchasing", "procurement", "hospitality industry"]}}, {"job_id": "100003009053149", "location_code": "hk", "company": "The American Club", "job_title": "Purchasing Manager (5 days work)", "description": "Job Summary:\n\nResponsible for managing and leading the overall Purchasing function by developing and executing the purchasing strategies\nResponsible for improving operational efficiency of current ERP system and of the Purchasing Department\nPerform cost analysis and conduct market price trend analysis to ensure long terms saving and quality improvement\nResponsible for departmental staff development\n\nJob Duties and Responsibilities:\n\nReport to the Finance Director about all matters of purchasing and sourcing\nDirect supervision of a team of Assistant Purchasing Manager and Purchasing Officer\nProcess all purchase request for F&B items, non F&B items, capital expenditure items, consignment items, project related items, etc\nTender process including preparation/analysis/award \u2013 work closely with Finance Director and related Senior Managers\nMaintain a complete record of catalogues and suppliers/vendors contacts\nVendor management process including supplier/vendor selection and creation of all new suppliers/vendors\nPrice and terms negotiation with selected supplier/vendor for the best deal\nPerform \u201cSupplier Quality & Food Safety Evaluation\" by site visit with related department personnel for pre-selected suppliers/vendors\nApprove all pertinent purchasing reports: (a) Monthly/YTD Saving Report, (b) Purchase Order Amendment, (c) Periodic Competitive Price Analysis Reports\nEnsure the delivery of product / service on time and conform to the requirements\nEnsure all the purchasing procedures are carried out in accordance with the Club\u2019s policies and procedures\nStrategic purchases for long term savings and quality improvement\n\nJob Requirements\n\nEducation: Degree Holder in Purchasing & Supply Chain Management or related disciplines\nExperience: At least 5 years\u2019 managerial experience in hospitality or similar industry\n\nWorking location: Tai Tam\n\nWe offer attractive remuneration. Please send full resume by clicking\u00a0Apply Now, by Whatsapp: 9093 7658, or by fax: 3585 1360. For more information please visit our website:\u00a0www.americanclubhk.com\n\nWe are an equal opportunity employer. All information provided by applicants will be used for recruitment related purpose only and handled in strict confidence by authorized personnel only. Only short-listed candidates will be notified. The personal data collected will be destroyed after 3 months.", "employment_types": ["Full Time", "Permanent"], "selling_points": ["Managerial grade benefit", "2 months bonus", "In charge of food/non food purchasing of the Club"], "locations": ["Southern Area"], "categories": ["Hospitality / F & B", "Hospitality / Hotel Services", "Merchandising & Purchasing", "Sundries", "Procurement / Purchasing / Sourcing"], "post_time": "2022-01-17T06:07:59Z", "salary": {"currency": null, "max": null, "min": null, "period": "monthly", "term": null}, "salary_visible": false, "title_keywords": ["purchasing manager"], "responsibilities": ["management", "food safety", "terms negotiation", "analysis reports", "policies", "analysis", "quality", "procedures", "purchase", "maintain", "reports", "tender", "evaluation", "report"], "requirements": {"degrees": ["degree holder"], "majors": ["related disciplines"], "languages": [], "language_level": [], "hard_skills": [], "soft_skills": [], "languages_combined": []}, "experience_required": {"duration": ["at least 5 years"], "field": ["managerial"]}}, {"job_id": "100003009054238", "location_code": "hk", "company": "Swarovski Hong Kong Ltd", "job_title": "Procurement Excellence Manager", "description": "At Swarovski, where innovation meets inspiration, our people desire to explore, experience, and create. We are looking for a Procurement Excellence Manager where you will get a chance to work in a rewarding role within a diverse team that is pushing boundaries. Be part of a truly iconic global brand, learn and grow with us. We\u2019re bold and inventive, revealing astonishing things like no one else can. A world of wonder awaits you.\n\nAbout the job\n\nEnable SCB strategic procurement functions in strategic aspects of category management, supplier and risk management\n\nSupport Head of Procurement Excellence in defining the harmonized ways of working in strategic areas for entire function\n\nDefine the ways of working and framework for Supplier and Risk management using the market best practice approach\n\nSupport and guide on strategy definition within category management, monitor category strategy execution, manage tools for category strategy\n\nRepresent the voice of strategic procurement \u00a0and gather new functional requirements from strategic procurement functions towards tools and processes in given areas\n\nMonitor market procurement trends and best practice solutions available to optimize the ways of working and procurement strategy in given areas\n\nStrong alignment with leadership of procurement functions to support the strategy development\n\nAbout you\n\nWe are looking for a unique and amazing talent, who brings along the following:\n\nUniversity degree/ Education\n\nMinimum 5 years of professional experience in a similar role within an international setting\n\nKnowledge in strategic procurement processes, techniques, and approaches\n\nExperience in supplier and risk management\n\nStrong stakeholder management - ability to work effectively with all levels of the organization\n\nIndependent and strategic mindset\n\nExcellent English proficiency, presentation, and communication skills\n\nInnovative and creative approach whenever possible and can-do attitude\n\nBy applying this job, I understand and accept the principles of personal data protection, please visit the following link to find out more about Data Protection Consent Statement.\u00a0https://www.swarovskigroup.com/S/careers/data_protection_consent_statement.en.html\n\n\n\n\nAbout Swarovski\n\nSwarovski is a Wonderlab where magic and science meet.\n\nSwarovski unifies all parts of its organization under one spellbinding idea and brings forward a wondrous new world of crystal craftsmanship. Founded in 1895 in Austria, the company designs, manufactures and sells the world\u2019s highest quality crystal, genuine gemstones, Swarovski Created Diamonds and zirconia, jewelry, and accessories, as well as crystal objects and home accessories. Together with its sister companies Swarovski Optik (optical devices) and Tyrolit (abrasives), Swarovski Crystal Business forms the Swarovski Group.\n\nA responsible relationship with people and the planet has always been an integral part of Swarovski\u2019s heritage. This manifests today in the company\u2019s well-established sustainability agenda with youth-focused education programs and foundations to promote human empowerment and conserve natural resources to achieve positive social impact.", "employment_types": ["Full Time", "Permanent"], "selling_points": ["Knowledge in strategic procurement processes", "Experience in supplier and risk management", "Strong stakeholder management"], "locations": ["Kowloon City"], "categories": ["Transportation & Logistics", "Supply Chain", "Merchandising & Purchasing", "Procurement / Purchasing / Sourcing"], "post_time": "2022-01-17T08:53:09Z", "salary": {"currency": null, "max": null, "min": null, "period": "monthly", "term": null}, "salary_visible": false, "title_keywords": ["manager"], "responsibilities": ["management", "data", "procurement processes", "monitor", "quality", "communication", "personal data"], "requirements": {"degrees": ["university degree"], "majors": [], "languages": ["english"], "language_level": ["excellent", "proficiency"], "hard_skills": ["no", "html"], "soft_skills": ["work effectively", "communication skills", "independent", "creative", "responsible", "can-do attitude", "focused", "bold", "unique", "genuine", "diverse", "innovative", "leadership", "presentation", "positive"], "languages_combined": [{"language": "english", "language_level": ["proficiency", "excellent"]}]}, "experience_required": {"duration": ["minimum 5 years"], "field": ["risk management"]}}, {"job_id": "100003009055467", "location_code": "hk", "company": "Chandler Macleod Group (HK) Limited", "job_title": "Procurement Operations Support / Buyer (Up to 40K/mth)", "description": "Job Responsibilities\n\nConduct new sourcing requests, contract renewals, contract re-negotiation and transactional tasks of tactical sourcing projects.\nConduct detailed spend analysis and compile spend dashboard\nManage purchase requisitions from business, advise requestor on sourcing channel and execute tactical sourcing as needed.\nManage PO issuance (if needed) and review PO status / follow-up with suppliers\nMaintain the contract repository (upload and archive contracts as needed)\nReview contract compliance and contracts due for renewal\nSupport supplier identification, qualification and onboarding process\nSupport master data management\nSupport complication of procurement operations / performance reports\n\nJob Requirements\n\nUniversity graduate or professional qualification in a related discipline\nAbout 3 years' relevant experience\nProcurement operations experience is essential\nAbility to adapt and learn rapidly to be able to talk the language of the stakeholders\nUnderstanding of regulatory requirements and procurement policies\nAbility to inspire, and build trust and respect among the stakeholders\nExcellent people skills; including the ability to negotiate and influence internal and external stakeholders\nA team player, assertive yet approachable and decisive\nPossess of proficiency in Excel (V-lookup, macros) and PowerPoint Presentation and procurement systems\nImmediately available is highly preferred but not a must", "employment_types": ["Full Time", "Contract"], "selling_points": ["A multinational technology corporation", "Well-rounded procurement exposure", "Immediately available highly preferred"], "locations": ["Not Specified"], "categories": ["Merchandising & Purchasing", "Others", "Procurement / Purchasing / Sourcing"], "post_time": "2022-01-18T02:37:41Z", "salary": {"currency": null, "max": null, "min": null, "period": "monthly", "term": null}, "salary_visible": false, "title_keywords": ["operations"], "responsibilities": ["management", "performance reports", "data", "contracts", "analysis", "review", "compliance", "operations", "purchase", "maintain"], "requirements": {"degrees": ["university graduate"], "majors": [], "languages": [], "language_level": [], "hard_skills": ["excel", "powerpoint"], "soft_skills": ["approachable", "assertive", "decisive", "team player", "presentation"], "languages_combined": []}, "experience_required": {"duration": ["3 years"], "field": ["relevant experience", "procurement"]}}, {"job_id": "100003009053299", "location_code": "hk", "company": "Cathay Pacific Airways Ltd", "job_title": "Assistant Procurement Manager - Strategic Projects & Analysis", "description": "Reports to:\u00a0E-Platform and Strategic Procurement Manager\u00a0\u00a0\nDepartment:\u00a0Procurement & Aircraft Trading (APD)\n\nRole Introduction\n\n\nAs the Assistant Procurement Manager, you will actively contribute and support the formulation and execution of initiatives for optimizing the end-to-end Procurement process. \u00a0You will be working with different stakeholders across the company to optimize the source-to-pay process, enabled by leading cloud-based technology solutions (e.g. Ariba/SAP) and other software vendors. \u00a0In this connection, this person is expected to continuously identify and enable potential suppliers and catalogues to ensure complied purchasing activities conducted across the company.\n\nThis person will also work with an offshore team and various stakeholders across the company in providing all sort of sourcing and procurement activities.\n\nKey Responsibilities\n\nManage the design, implementation and deployment of different strategic projects that will optimize the source-to-pay process\nLiaise with related stakeholders across all phases of implementation, including requirements gathering, design, build, testing, supplier enablement and change management activities\nDrive continuous enhancements to previously implemented Ariba modules. \u00a0In particular, the Guided Buying solution recently launched globally. \u00a0This includes but not limited to:Lead an off-shore team of 5 in carrying out sourcing and procurement activities for all categories across the company, such as vendor sourcing, price &; commercial terms negotiation, cost analysis, vendor selection & evaluation\nsetup of additional catalogs and other compliance enhancements\nconduct regular spend reviews, fit-gap analysis to identify suitable categories/suppliers. \u00a0Thus, carry out sourcing and commercial discussions with identified suppliers\nsupport the supplier enablement efforts, this includes being the escalation point for supplier enablement support in implemented regions and working with the implementation team on supplier enablement strategies for enhancements to be implemented\nWork with internal stakeholders to determine specifications and requirements of assigned sourcing projects\nEnsure the procurement process is in compliance with the internal policies and procedures\nAnalyze spend and finance data to identify trends, patterns and anomalies for escalation to the category managers\n\nRequirements\n\nBachelor\u2019s degree in Procurement, Supply Chain, Business Administration or related disciplines. CIPS qualification is a plus\n3+ years of procurement sourcing, procurement operations and/or project management experience\nIn-depth understanding of end-to-end procurement process\nSolid knowledge / experience in strategic sourcing, commercial & contract management, supplier assessment and selection, and supplier relationship management\nGood stakeholder management and interpersonal skills is essential\nStrong communication, analytical, attentional to details and problem-solving skills required\nFamiliar with e-procurement tools development & operations\nExperience with the e-procurement systems or similar products, including but not limited to SAP, Ariba, Ariba Guided Buying is a plus\nWorking knowledge of P2P process and systems technology will be an advantage\nExperiences of implementation transformational and change projects is preferred\nProficiency and fluency in English\n\n\n\nApplication Deadline: 31 January 2022\n\nPersonal & Application Information\nCathay Pacific is an Equal Opportunities Employer. Personal data provided by job applicants will be used strictly in accordance with our personal data policy and for recruitment purposes only. Candidates not notified within eight weeks may consider their application unsuccessful. All related information will be kept in our file for up to 24 months. A copy of our Personal Information Collection Statement will be provided upon request by contacting our Data Protection Officer.\n\nPlease note that with effect from 1 December 2021, all employees must be vaccinated in order to access Cathay City and all other Cathay Group Company premises in Hong Kong. Consideration will be given to those who are unable to get vaccinated for valid medical reasons.", "employment_types": ["Full Time", "Permanent"], "selling_points": ["3+ years of procurement sourcing", "End-to-end procurement process", "Travel Benefits, 5-day work, Medical Benefits"], "locations": ["Lantau Island"], "categories": ["Transportation & Logistics", "Aviation Services", "Merchandising & Purchasing", "Procurement / Purchasing / Sourcing"], "post_time": "2022-01-17T06:44:24Z", "salary": {"currency": null, "max": null, "min": null, "period": "monthly", "term": null}, "salary_visible": false, "title_keywords": ["manager", "assistant"], "responsibilities": ["change management", "terms negotiation", "data", "policies", "analysis", "compliance", "procedures", "implementation", "design", "testing", "specifications", "evaluation", "liaise with", "cost analysis", "setup"], "requirements": {"degrees": ["degree", "bachelor"], "majors": ["related disciplines", "business administration"], "languages": ["english"], "language_level": ["fluency", "proficiency"], "hard_skills": ["problem-solving skills", "project management", "plus", "sap"], "soft_skills": ["communication", "project management", "problem-solving skills", "interpersonal skills"], "languages_combined": [{"language": "english", "language_level": ["proficiency", "fluency"]}]}, "experience_required": {"duration": ["3+ years"], "field": ["project management", "management", "commercial", "procurement"]}}, {"job_id": "100003009054083", "location_code": "hk", "company": "Vita Green Pharmaceutical (H.K.) Limited", "job_title": "Purchasing & Material Control Manager", "description": "Smart Manufacturing Division\nRef:\u00a0SMD409/21,\u00a04866/JDB/040122\nJob Description\nWho we are looking for:\nCreativity in new ideas and future focus vision.\u00a0\nCollaboration with colleagues and the community at large.\nWork Smart, Play Smart!\nWhat you'll do:\nTo provide industrial consultancy services and implement government-funded and consultancy projects on Industry 4.0 (i4.0), intelligent manufacturing and reindustrialization related smart enabling solutions adoption, such as Digital Lean, Machine Connectivity via IIoT, Human Machine interface (HMI), Smart Data Analytics, Cyber Physical Production System (CPPS), etc.\nTo formulate government project proposals on i4.0 enabling technology development, reindustrialization, manufacturing upgrading and industrial applications.\nTo conduct R&D work in development of i4.0 enabling technology solution such as Blockchain, Industrial Drone, Smart Logistics, Sensor applications\nOrganize and deliver training and marketing activities such as overseas study missions, international conferences, technical seminars, workshops, etc.\nTo travel over GBA on a regular basis for consultancy projects\nYou'll be a good fit if you have/are:\nBachelor Degree from engineering disciplines such as Industrial and System Engineering, Manufacturing Engineering, Data/Computer Science, or equivalent. Candidate with top up master degree on Information and Communication Technology preferred\nAt least two years\u2019 or more relevant experience in manufacturing operations, particularly in the technical area of digital manufacturing knowledge/solutions\nSounds knowledge on i4.0, intelligent manufacturing, reindustrialization, advanced digital tools and enabling technologies for digital manufacturing a definitely advantage\nStrong commitment to task outcome, mature, independent, self-initiated, proactive and good team player\nExcellent analytical, presentation, communication and interpersonal skills\nExcellent command of English, Cantonese and Putonghua\nNote:\nApplicant may be considered for other positions if not matching the requirements of the subject position.\nWhat we offer and What you\u2019ll like here:\nInnovative and energetic culture with smart outfits and sport shoes\nProfessional lab and latest technology to actualize your creative ideas\n5-day work week\u00a0\nPrime location with good public transport network\nMPF Top-up and dental benefit\nMedical benefits from Day-1 with extended coverage to dependent(s)\nProfessional training and career advancement opportunities\nApply now if you\u2019re ready to take the challenge! \u00a0Do not miss this opportunity to join us to Create Value and \u201cMAKE SMART SMARTER\u201d!\u00a0\u00a0\nHKPC will take into consideration both the quantitative and qualitative requirements of the position when selecting the suitable candidates.\u00a0 A competitive salary package commensurate with academic qualifications and experience will be offered.\u00a0\nApplicants are welcome to\u00a0submit application\u00a0at the HKPC e-Recruitment System (careers.hkpc.org) in 1\u00a0week\u00a0from the posting date.\u00a0 Recruitment will continue until the position is filled.\u00a0\u00a0\nPersonal data collected will be used for recruitment purpose only. Candidates not invited for interviews within 6 weeks may consider their applications unsuccessful and the applications will be disposed by HKPC within 12 months.", "employment_types": ["Full Time", "Permanent"], "selling_points": ["Newly created role", "Material Control & Purchasing focus", "Team leader role"], "locations": ["Tai Po Area"], "categories": ["Transportation & Logistics", "Supply Chain", "Manufacturing", "Production Planning / Control", "Merchandising & Purchasing", "Procurement / Purchasing / Sourcing"], "post_time": "2022-01-17T08:20:43Z", "salary": {"currency": null, "max": null, "min": null, "period": "monthly", "term": null}, "salary_visible": false, "title_keywords": ["manager"], "responsibilities": ["ideas", "data", "operations", "communication", "conferences", "logistics"], "requirements": {"degrees": ["degree", "bachelor", "master degree"], "majors": ["system engineering", "manufacturing", "engineering", "computer science"], "languages": ["cantonese", "putonghua", "english"], "language_level": ["excellent"], "hard_skills": ["r&d", "blockchain", "lean", "data analytics", "workshops", "focus"], "soft_skills": ["good team player", "independent", "advanced", "mature", "communication", "communication and interpersonal skills", "work smart", "focus", "proactive", "presentation"], "languages_combined": [{"language": "cantonese", "language_level": ["excellent"]}, {"language": "putonghua", "language_level": ["excellent"]}, {"language": "english", "language_level": ["excellent"]}]}, "experience_required": {"duration": ["at least two years"], "field": ["digital", "manufacturing", "relevant experience"]}}, {"job_id": "100003009053219", "location_code": "hk", "company": "Eternity Commerce Limited", "job_title": "E-Commerce Supply Chain Assistant/Officer (Logistics&Procurement/Sourcing/Merchandising/Purchasing)", "description": "Job Responsibilities:\n\nCollaborate with sales team and warehouse for delivery schedule arrangement and issue delivery note\nAssist in sourcing and purchasing raw materials\nLiaise with suppliers to drive on- time shipment delivery\nHandle order processing, inventory control and coordinate all transportation including ocean and air freight forwarding\nHandle purchase orders and shipping documents. Freight rate checking and transit time analysis\nMonitor supply availability, quality standards, cost & contracts and ensure deliverables are achieved to project site\nAssist in handling product quality issue and quality control\nAd hoc tasks as assigned\n\nRequirement:\n\nHigher Diploma or above, major in Supply Chain Management/Logistics, Mathematics, Science, Business or equivalent\nFresh graduates with passion and willing to learn are welcomed\nGood knowledge of PC and Excel is essential\nGood command of both spoken and written English and Chinese\nSelf-motivated, well organized, able to work independently and strong compliance with ability to meet deadlines\nCandidate with more experience will be consider as Supply Chain Officer\nImmediately available is preferred\u00a0\n\nOur attractive remuneration includes:\n\nMedical Insurance\nDouble Pay\nDiscretionary Bonus\nBirthday Leave\nPaid Sick Leave\nGym Membership\nFive Days Work Week\nFlexible working hours\nEducation Allowance", "employment_types": ["Full Time"], "selling_points": ["Logistics/Procurement/Purchasing/Merchandising", "Fresh Graduates are Welcome", "Young & Energetic Working Environment"], "locations": ["Quarry Bay"], "categories": ["Transportation & Logistics", "Supply Chain", "Merchandising & Purchasing", "Procurement / Purchasing / Sourcing", "E-commerce", "Supply Chain"], "post_time": "2022-01-17T06:27:59Z", "salary": {"currency": null, "max": null, "min": null, "period": "monthly", "term": null}, "salary_visible": false, "title_keywords": ["officer", "merchandising", "supply chain assistant"], "responsibilities": ["collaborate with", "shipping documents", "quality", "product quality issue", "purchase", "contracts", "monitor", "cost", "air freight", "ad hoc tasks", "checking", "delivery schedule", "inventory control", "analysis", "coordinate", "sales team", "order processing", "quality control", "liaise with suppliers"], "requirements": {"degrees": ["higher diploma or above"], "majors": ["mathematics", "business", "science"], "languages": ["english", "chinese"], "language_level": ["good command"], "hard_skills": ["pc", "excel"], "soft_skills": ["flexible", "self-motivated", "work independently", "willing to learn", "well organized", "meet deadlines"], "languages_combined": [{"language": "english", "language_level": ["good command"]}, {"language": "chinese", "language_level": ["good command"]}]}, "experience_required": {"duration": [], "field": ["supply chain"]}}, {"job_id": "100003009056027", "location_code": "hk", "company": "Morgan McKinley", "job_title": "Procurement Manager (Corporate & Marketing), Leading Corp", "description": "A globally reputable company is looking for a Procurement Manager (Corporate & Marketing). With a rapid growing business, they are looking for the right talent to join their business.\n\nResponsibilities:\n\nAs a Procurement Manager (Corporate & Marketing), you will direct report to the Senior Manager. You will be responsible for supporting complex procurement projects across all department / categories. You will be responsible for ensuring all project procurement execution align with internal policy. You will be responsible for leading global procurement strategy and precise vendor selection for all aspects of corporate services. You will be responsible for managing T&Cs negotiation with suppliers. You will be responsible for updating internal procurement policy and procedures. You will be responsible for any ad hoc tasks.\n\nRequirements:\n\nDegree holder in Procurement, Supply Chain, Sourcing, Purchasing, Facilities Management or Business Administration related discipline\nProcurement qualifications will be an advantage\nKnowledge of procurement control and governance\nMinimum of 4 to 5 years working experience in sizeable organizations, highly preferred large size of companies\nWilling to learn and have can-do attitude\nMS office applications (Word, Excel, Power Point)\nThe ability to communicate effectively to all levels of the organization and interface with cross-functional people in the group is essential\nPossesses excellent communication skills with good command in both written and spoken English and Chinese\n\nThis is an excellent opportunity for individuals seeking a Procurement Manager (Corporate & Marketing) role for a large reputable corporation that is able to offer a great package and excellent working environment.\n\nTo apply online, please click the \"Apply\" button below. For a confidential discussion about this role, please contact Candice Yung on +3907 3934", "employment_types": ["Full Time", "Permanent"], "selling_points": ["Reputable Company", "Clear Career Path", "Attractive Bonus"], "locations": ["Not Specified"], "categories": ["Merchandising & Purchasing", "Others", "Procurement / Purchasing / Sourcing", "Others", "Others"], "post_time": "2022-01-18T03:12:03Z", "salary": {"currency": null, "max": null, "min": null, "period": "monthly", "term": null}, "salary_visible": false, "title_keywords": ["manager"], "responsibilities": ["ad hoc tasks", "procedures", "report"], "requirements": {"degrees": ["degree holder"], "majors": ["business administration"], "languages": ["english", "chinese"], "language_level": ["excellent", "good command"], "hard_skills": ["excel", "word", "facilities management", "power point", "ms office"], "soft_skills": ["communication skills", "willing to learn", "can-do attitude"], "languages_combined": [{"language": "english", "language_level": ["excellent", "good command"]}, {"language": "chinese", "language_level": ["excellent", "good command"]}]}, "experience_required": {"duration": ["minimum of 4 to 5 years"], "field": []}}, {"job_id": "100003009052342", "location_code": "hk", "company": "Chinese Pharmaceuticals (HK) Co., Limited", "job_title": "Purchasing clerk / executive", "description": "Responsibilities:\n- Handle purchase orders and follow up with suppliers on delivery schedule;\n- Carry out administrative work and clerical support for the department;\n- Handle other ad hoc project as assigned\n\nRequirements:\n- Higher Diploma or above;\n- 1-2 years of working experience in supplement or beauty is preferred;\n- Detail oriented with good numeric sense and strong negotiation and analytical skills;\n- Able to work under pressure with good multi-tasking skills;\n- Good command of written and spoken English and Chinese;\n- Proficiency in MS Office, including MS Word, MS Excel;\n- Immediate available is highly preferred", "employment_types": ["Full Time"], "selling_points": [], "locations": ["Kwun Tong"], "categories": ["Admin & HR", "Clerical / Admin Staff", "Merchandising & Purchasing", "Others", "Procurement / Purchasing / Sourcing"], "post_time": "2022-01-17T16:20:57Z", "salary": {"currency": null, "max": null, "min": null, "period": "monthly", "term": null}, "salary_visible": false, "title_keywords": ["executive", "purchasing clerk"], "responsibilities": ["ad hoc", "administrative work", "clerical support", "delivery schedule", "purchase"], "requirements": {"degrees": ["higher diploma or above"], "majors": [], "languages": ["english", "chinese"], "language_level": ["good command"], "hard_skills": ["ms word", "ms excel", "ms office", "analytical skills"], "soft_skills": ["negotiation", "detail oriented", "analytical skills", "multi-tasking skills", "work under pressure"], "languages_combined": [{"language": "english", "language_level": ["good command"]}, {"language": "chinese", "language_level": ["good command"]}]}, "experience_required": {"duration": ["1-2 years"], "field": ["beauty"]}}, {"job_id": "100003009056083", "location_code": "hk", "company": "DFI Retail Group DFI\u96f6\u552e\u96c6\u5718", "job_title": "Product Development Manager (OB Food)", "description": "About Us\n\nGrowing our Own Brand sales is a key focus for the DFI Retail Group, and as such we are looking for a passionate Product Development Manager to join our team who wants to help shape the future of our Own Brand ranges. You will be part of a dynamic team, partnering with our key Own Brand suppliers to deliver exciting new products to make Own Brand a bigger part of our supermarket business, offering customers great quality products at great prices!\n\nThe Job\n\nAs an integral part of our Own Brand team, you\u2019ll be responsible for the end to end development of your category including:\n\nDevelop a customer-focused category strategy for our supermarkets across Asia\nComplete competitor reviews to ensure that we are developing ranges that differentiate us in the market\nIdentify and partner with suppliers to develop great tasting products\nWork alongside our technical team to ensure we are delivering safe, legal and great quality products, as well as attending factory trials and first productions\nOur Product Development Managers act quickly to transform ideas into products and then bring products into a reality for our customers. They love the exhilaration of operating with pace and passion and bringing their products to life in our stores\n\nThe Person\n\nDegree holder in Food Science or Science related disciplines\nMinimum 5 years of experience in FMCG purchasing, Product Development, Food Technical or R&D, preferably in Own Brand or with a strong culinary/food science background\nA sound understanding of product development and category management metrics with a strong passion for global industry developments and food trends to deliver customer-driven marketing leading innovation\nCandidates with advanced understanding and knowledge of product formulations, manufacturing, packaging and testing applications, with a basic knowledge of applicable government regulations is highly preferable\nExcellent analytical skills, being highly organized with the ability to prioritize projects and tasks\nOutstanding influencing, negotiation and stakeholder management skills\nExperience in managing a number of suppliers\nGood command of spoken and written Cantonese and English\nExtensive travel to all our markets across North Asia and South East Asia\n\nDFI Retail Group is an equal opportunity employer and responsible for ensuring that all personal information collected from each Candidate presented to DFI Retail Group is used for recruitment purposes only and the personal data will be kept and handled confidentially. We will retain the applications of candidates not selected for a period of no more than 24 months. The data collection process is in accordance with all applicable laws and compliant with the Code of Practice on Human Resource Management.\n\nTo find out more about Our Businesses and Our People, please visit our website: https://www.DFIretailgroup.com\n\n\u00a0\nIssued by The Dairy Farm Company, Limited", "employment_types": ["Full Time"], "selling_points": ["5+ years of experience in FMCG purchasing", "Understanding of product development metrics", "Outstanding stakeholder management skills"], "locations": ["Quarry Bay"], "categories": ["Merchandising & Purchasing", "Procurement / Purchasing / Sourcing"], "post_time": "2022-01-18T03:15:29Z", "salary": {"currency": null, "max": null, "min": null, "period": "monthly", "term": null}, "salary_visible": false, "title_keywords": ["product development manager"], "responsibilities": ["ideas", "quality", "developing", "develop"], "requirements": {"degrees": ["degree holder"], "majors": ["related disciplines", "science", "food science"], "languages": ["cantonese", "english"], "language_level": ["good command"], "hard_skills": ["r&d", "no", "basic", "analytical skills", "code"], "soft_skills": ["organized", "advanced", "negotiation", "passion for", "responsible", "prioritize", "analytical skills", "extensive", "driven"], "languages_combined": [{"language": "cantonese", "language_level": ["good command"]}, {"language": "english", "language_level": ["good command"]}]}, "experience_required": {"duration": ["minimum 5 years"], "field": ["fmcg", "brand", "purchasing", "food", "product development"]}}, {"job_id": "100003009052676", "location_code": "hk", "company": "Canon Engineering Hong Kong Co Ltd", "job_title": "Procurement Clerk", "description": "Responsibilities:\n\nTo manage business account registration\nTo manage master setting for procurement\nTo monitor and manage quotation record\nTo enter and maintain the shipping data\nTo support for procurement data analysis and report\nTo provide the system support for supplier\nTo provide the general clerical support\nAd hoc duties will be assigned\n\nRequirements:\n\nDegree holder in purchasing, logistic management, or related discipline\nAt least 1 - 2 years with relevant experience\nBe precise in handling ( Accuracy & Efficiency of Work)\nIndependently, detail-oriented and rational thinking\nGood communication and interpersonal skill\nGood command of written\u00a0and spoken English, Chinese; Knowledge in Japaness would be an advantage\nProficient in MS Applications such as MS Office (Word, Excel, etc.)\nImmediate availability is preferred.\n\nWe offer 5 days\u2019 work and a competitive remuneration package to the right candidate. Interested candidate, please send your resume with the expected salary through \"Apply Now\"\n\n(Personal data collected will be used for recruitment purposes only)", "employment_types": ["Full Time", "Permanent"], "selling_points": [], "locations": ["Kwai Hing"], "categories": ["Merchandising & Purchasing", "Electronics", "Procurement / Purchasing / Sourcing"], "post_time": "2022-01-17T03:41:13Z", "salary": {"currency": null, "max": null, "min": null, "period": "monthly", "term": null}, "salary_visible": false, "title_keywords": ["procurement clerk"], "responsibilities": ["ad hoc duties", "shipping", "data", "quotation", "monitor", "clerical support", "data analysis", "maintain", "report"], "requirements": {"degrees": ["degree holder"], "majors": [], "languages": ["english", "chinese"], "language_level": ["good command"], "hard_skills": ["excel", "ms applications", "word", "ms office"], "soft_skills": ["independently", "interpersonal skill", "communication", "detail-oriented", "precise"], "languages_combined": [{"language": "english", "language_level": ["good command"]}, {"language": "chinese", "language_level": ["good command"]}]}, "experience_required": {"duration": ["at least 1 - 2 years"], "field": ["relevant experience"]}}, {"job_id": "100003009051731", "location_code": "hk", "company": "Asia Airfreight Terminal Co Ltd", "job_title": "Purchasing Supervisor", "description": "Duties\n\n\nHandle end to end procurement cycle from vendor sourcing, tendering , cost analysis, supplier negotiation to fulfillment\nCommunicate and co-ordinate with internal stakeholders regarding their purchasing needs and feedback to vendors\nTake a proactive role to negotiate with vendors for obtaining the better terms and conditions for the Company\u2019s interest\nEnsure the procurement cycle compliance to the internal policy; capable to work on cost analysis and vendor recommendation and selection\nExpand and consolidate vendor base to support business objectives\n\n\u00a0Requirements\u00a0\n\n\nBachelor Degree in Supply Chain, Business Administration, Procurement or related discipline\nMinimum 4 years\u2019 of experience in procurement or related disciplines with at least 1 year in supervisory level\nExperience in managing tender process and preparation of tender documents will be a plus\nProficiency in MS Office especially Excel, Word, PowerPoint\nGood command of both written and spoken English and Chinese\nProficiency in written English will be an advantage\nAble to work independently and under pressure\nHonest, responsible and self-motivated\nStrong communication, negotiation and analytical skills\n\nWe offer the right incumbent attractive remuneration package including 5-day work week, 13 days annual leave, double pay, performance bonus, medical scheme, life insurance, travel allowance and education subsidy.\n\nInterested parties please send your full resume with reference no., recent and expected salary to: Human Resources Department, Asia Airfreight Terminal Co. Ltd., 10 Chun Ping Road, Hong Kong International Airport, Lantau, Hong Kong OR Fax to 2286 0374 OR Please click \u201cApply Now\u201d to submit your application.\n\nTo know more about AAT, please visit http://www.aat.com.hk\n\nWe are an equal opportunity employer and welcome applications from all qualified candidates. We will not be responsible for any disclosure or the loss of personal data during transmission. All personal data collected will be used for recruitment only. Information of unsuccessful candidates will be destroyed after 3 months from the date of application.", "employment_types": ["Full Time", "Permanent"], "selling_points": ["5-day week, double pay, performance bonus", "Provide procurement services", "Capable to work on cost analysis"], "locations": ["Airport Area"], "categories": ["Admin & HR", "Clerical / Admin Staff", "Merchandising & Purchasing", "Others", "Procurement / Purchasing / Sourcing"], "post_time": "2022-01-16T21:51:15Z", "salary": {"currency": null, "max": null, "min": null, "period": "monthly", "term": null}, "salary_visible": false, "title_keywords": ["supervisor"], "responsibilities": ["co-ordinate with", "fulfillment", "compliance", "tendering", "cost analysis"], "requirements": {"degrees": ["degree", "bachelor"], "majors": ["business administration"], "languages": ["english", "chinese"], "language_level": ["advantage", "proficiency", "good command"], "hard_skills": ["excel", "plus", "word", "powerpoint", "analytical skills", "scheme", "ms office"], "soft_skills": ["work independently", "self-motivated", "under pressure", "negotiation", "responsible", "analytical skills", "communication", "honest"], "languages_combined": [{"language": "english", "language_level": ["proficiency", "advantage", "good command"]}, {"language": "chinese", "language_level": ["proficiency", "good command"]}]}, "experience_required": {"duration": ["minimum 4 years", "at least 1 year"], "field": ["related", "supervisory level", "procurement"]}}, {"job_id": "100003009056635", "location_code": "hk", "company": "Scents Limited", "job_title": "Merchandising Clerk", "description": "Are you interested to join a team of eco-conscious and positive people working hard to make a change in the beauty industry?\u00a0\n\nIf you are independent, proactive, highly motivated, willing to roll up your sleeves to get the job done then we have the perfect opportunity for you!\n\nWe are looking for an awesome full time Merchandising Clerk to work closely with our management, design and merchandiser and\u00a0be fully part of our team to get things done, learn, and grow.\u00a0\n\nJob Duties:\n\n+ Liaise with Beauty packaging factories to develop new products (haircare, perfume)\n+ Source new sustainable materials and suppliers (Alibaba, 1688, TaoBao)\n+ Follow-up on sampling, production, quality control and delivery\n+ Help to negotiate prices and quantities\n+ Coordinate with our Marketing and Design teams on new launches\n\nJob Requirements:\n\n+ 1 - 3 years working experience in Admin, Secretarial, Merchandising, Buying or Sourcing\n+ Positive attitude, detail minded, well organized\n+ Fluent in Spoken and Written of both English and Chinese are a must (Cantonese and Mandarin)\n+ Word, Excel, PowerPoint and Chinese word processing\n+ Experience working in English is a plus\n+ Immediate availability\u00a0is a plus\n\nWe offer :\n\n- A fun working environment,\n- 5-days work,\n- flexible working hours,\n- MPF,\n- 13 month\n- Performance Bonus\n- 12 days annual leave,\n- All hongkong bank Holiday,\n- Free product incentive,\u00a0\n- Staff-Discount\n- A Good salary package to the right candidate.\u00a0\n-\u00a0And a job in a company who truly care about the planet.\n\nIf you wish to learn, grow and you're up for a challenge ...\nPlease send your full resume with expected salary\u00a0and availability via\u00a0the \u201cAPPLY\u201d button\u00a0", "employment_types": ["Full Time", "Permanent"], "selling_points": [], "locations": ["Kwun Tong"], "categories": ["Admin & HR", "Clerical / Admin Staff", "Merchandising & Purchasing", "Procurement / Purchasing / Sourcing", "Sales, CS & Business Devpt", "Sales Administration"], "post_time": "2022-01-18T05:18:28Z", "salary": {"currency": "HKD", "max": 16999, "min": 14000, "period": "monthly", "term": null}, "salary_visible": true, "title_keywords": ["merchandising clerk"], "responsibilities": ["coordinate with", "teams", "design", "develop", "quality control", "liaise with"], "requirements": {"degrees": [], "majors": [], "languages": ["cantonese", "english", "chinese", "mandarin"], "language_level": ["fluent"], "hard_skills": ["excel", "plus", "chinese word processing", "word", "powerpoint"], "soft_skills": ["positive attitude", "well organized"], "languages_combined": [{"language": "cantonese", "language_level": ["fluent"]}, {"language": "english", "language_level": ["fluent"]}, {"language": "chinese", "language_level": ["fluent"]}, {"language": "mandarin", "language_level": ["fluent"]}]}, "experience_required": {"duration": ["1 - 3 years"], "field": ["secretarial", "admin", "merchandising"]}}, {"job_id": "100003008980877", "location_code": "hk", "company": "Shun Lee Building Materials and Sanitary Wares Ltd", "job_title": "Purchasing Manager", "description": "Responsibilities:\n\nDevelop and implement strategic purchasing and materials management plans in line with company objectives and development\nDrive and manage purchasing, product & quality management and logistics functions to ensure smooth day-to-day operations\nFormulate and maintain strategic relationship with the suppliers, and to ensure that the product supply and quality are met with Company\u2019s standards\nForecast and administer inventory to ensure adequate stock level\nTake remedial and/or preventive measures in response to problems that may arise during the procurement process\nOther ad-hoc job duties as assigned\n\nRequirements:\n\nDegree in Materials or Procurement Management or related disciplines\n5 years\u2019 relevant experience\nWilling to take up challenges and strong sense of responsibility\nExperience in the building materials industry will be an advantage\nFluent spoken & writing in English and Putonghua\nGood PC Knowledge\nOccasional travel is required\n\nWe offer 5-day work week, competitive salary, discretionary performance bonus, medical benefits, annual leave, marriage leave, compassionate leave, staff discount and excellent career prospects.\n\nInterested parties please send your application letter and full resume with current / expected salary and availability to Human Resources Department by clicking APPLY NOW.\n\nFor more information about our Company, please visit our website at\u00a0https://shunlee.com.hk\u00a0\u00a0\n\nInformation collected will be treated in strict confidence and only be used for recruitment purpose.", "employment_types": ["Full Time", "Permanent"], "selling_points": [], "locations": ["Lai Chi Kok"], "categories": ["Transportation & Logistics", "Inventory / Warehousing", "Shipping", "Merchandising & Purchasing", "Procurement / Purchasing / Sourcing"], "post_time": "2022-01-16T21:50:05Z", "salary": {"currency": null, "max": null, "min": null, "period": "monthly", "term": null}, "salary_visible": false, "title_keywords": ["purchasing manager"], "responsibilities": ["ad-hoc", "management", "inventory", "quality", "day-to-day operations", "develop", "maintain", "logistics", "forecast", "plans"], "requirements": {"degrees": ["degree"], "majors": ["related disciplines"], "languages": ["putonghua", "english"], "language_level": ["fluent"], "hard_skills": ["pc knowledge"], "soft_skills": ["sense of responsibility"], "languages_combined": [{"language": "putonghua", "language_level": ["fluent"]}, {"language": "english", "language_level": ["fluent"]}]}, "experience_required": {"duration": ["5 years"], "field": ["relevant experience"]}}, {"job_id": "100003009054015", "location_code": "hk", "company": "American Phil Textiles Ltd", "job_title": "Purchasing Clerk / Senior Purchasing Clerk / Assistant Purchasing Supervisor (Garment)", "description": "Purchasing Clerk / Senior Purchasing Clerk /\nAssistant Purchasing Supervisor\n\nResponsibilities:\n\nMaterials sourcing and purchasing\nPrepare and issue purchase orders\nFollow up and monitor the delivery schedules with suppliers and factories to meet production plan\nData input for the daily system operation\u00a0\nPerform clerical support to department\n\n\u00a0Qualifications and Requirements:\n\nForm 5 / DSE or above\u00a0\nAt least 2 years related working experience\nWell organized, detail-minded, initiative, willing to learn and able to work under pressure\nProficient in MS Excel, experience in using ERP system is preferable\nGood command of written and spoken English and Mandarin\nCandidates with more experience will be considered as Senior Purchasing Clerk / Assistant Purchasing Supervisor\nImmediate available\u00a0\n\nWe offer\u00a05-day work, Double Pay\u00a0and\u00a0attractive remuneration packages\u00a0to the right candidate.\u00a0 Interested candidates please e-mail full resume\u00a0with expected salary to\u00a0Personnel Section\u00a0by clicking \"Apply Now\".\n\nAll data supplied will be kept in strict confidence and only for employment related purpose. Those not invited for an interview within 6 weeks may consider their applications unsuccessful and personal data provided will be destroyed", "employment_types": ["Full Time", "Permanent"], "selling_points": ["Garment materials procurement, purchasing orders", "Follow up and monitor the delivery schedules", "5 days work, Medical & Dental Insurance, ERP"], "locations": ["Cheung Sha Wan"], "categories": ["Merchandising & Purchasing", "Woven / Knit", "Textiles", "Procurement / Purchasing / Sourcing"], "post_time": "2022-01-17T09:04:24Z", "salary": {"currency": null, "max": null, "min": null, "period": "monthly", "term": null}, "salary_visible": false, "title_keywords": ["supervisor", "senior purchasing clerk", "purchasing clerk", "assistant"], "responsibilities": ["schedules", "monitor", "data input", "clerical support", "purchase", "plan"], "requirements": {"degrees": ["form 5", "dse"], "majors": [], "languages": ["english", "mandarin"], "language_level": ["good command"], "hard_skills": ["ms excel", "erp system"], "soft_skills": ["detail-minded", "willing to learn", "well organized", "initiative", "work under pressure"], "languages_combined": [{"language": "english", "language_level": ["good command"]}, {"language": "mandarin", "language_level": ["good command"]}]}, "experience_required": {"duration": ["at least 2 years"], "field": ["related", "erp system", "purchasing"]}}, {"job_id": "100003009053278", "location_code": "hk", "company": "Seeds Financial Group", "job_title": "Assistant Sales and Event Manager/ HK$25,000-35,000 plus bonus", "description": "Job Summary:\nAssistant Sales and Event Manager\u00a0 - \u00a0is responsible for providing administrative and coordination to support sales projects and event services team. It also involves day to day tasks of preparing departmental correspondence for sales activities and events servicing.\n\nTo enhance the financial services that our team provides to our clients, this role requires good customer service knowledge, exhibit a professional attitude and be a team player to achieve \u00a0sales and services goals.\n\nResponsibilities:\n\nDelivery quality customer services by providing accurate and sufficient information to clients as well as drafting concise and informative replies when necessary.\nProvide sales activities support, in organizing sales materials, preparing prospect proposal review, merchandise give-away items, \u00a0turnover preparation, answering sales or client enquiries, etc.\nMaintain extensive accounts and client\u2019s data for customer relationship management\nOffice administration and clerical support, including the arrangement of meetings, taking meeting minutes, office supply ordering / pickup and maintenance, management of team roster and leave records, courier deliveries, team cast related preparation and arrangement, organize filing systems and other related tasks.\nKeep up-to-date spending records, trace clients' billings, and prepare financial reports to clients.\nAssist in handling small scale corporate groups, social and internal event\nGenerate related reports for management and operation partners\nBasic Qualifications:\nBachelor degree is required, fresh-graduates are welcomed\nKnowledgeable in customer service industry\nAble to work independently\nLiterate in PC applications including MS Word, Excel, PowerPoint and Chinese typing\nGood communication skills with spoken and written English, Cantonese, and Putonghua", "employment_types": ["Full Time"], "selling_points": ["Monthly Income up to HK$50,000 (including bonus)", "Fresh-graduates are welcomed", "Good team culture"], "locations": ["Causeway Bay"], "categories": ["Sales, CS & Business Devpt", "Customer Service - Supervisor / Officer", "Marketing / Public Relations", "Public Relations - Event Management", "Merchandising & Purchasing", "Procurement / Purchasing / Sourcing"], "post_time": "2022-01-17T06:39:09Z", "salary": {"currency": "HKD", "max": 34999, "min": 25000, "period": "monthly", "term": null}, "salary_visible": true, "title_keywords": ["sales", "assistant", "event manager"], "responsibilities": ["sales activities", "management", "financial reports", "maintenance", "data", "office administration", "billings", "review", "quality", "clerical support", "systems", "customer services", "communication", "customer service", "maintain", "reports", "coordination"], "requirements": {"degrees": ["degree", "bachelor"], "majors": [], "languages": ["cantonese", "putonghua", "english", "chinese"], "language_level": ["good"], "hard_skills": ["small", "excel", "basic", "maintenance", "typing", "powerpoint", "pc applications", "ms word"], "soft_skills": ["communication skills", "work independently", "responsible", "customer service", "coordination", "team player", "accurate", "extensive"], "languages_combined": [{"language": "cantonese", "language_level": ["good"]}, {"language": "putonghua", "language_level": ["good"]}, {"language": "english", "language_level": ["good"]}, {"language": "chinese", "language_level": []}]}, "experience_required": {"duration": [], "field": []}}, {"job_id": "100003009053297", "location_code": "hk", "company": "Loyal Trade Limited", "job_title": "Clerk / Assistant Merchandiser / Merchandiser", "description": "Requirements:\n\n-\u00a0\u00a0\u00a0\u00a0\u00a0\u00a0\u00a0 F.5 / DSE or above education\n\n-\u00a0\u00a0\u00a0\u00a0\u00a0\u00a0\u00a0 1-2 years relevant working experience in Artificial Flowers and Christmas items. (Candidate with less experience will be considered as Clerk or Assistant Merchandiser)\n\n-\u00a0\u00a0\u00a0\u00a0\u00a0\u00a0\u00a0 Fresh graduate will be also considered\n\n-\u00a0\u00a0\u00a0\u00a0\u00a0\u00a0\u00a0 Good command of written and spoken English, Cantonese and Mandarin\n\n-\u00a0\u00a0\u00a0\u00a0\u00a0\u00a0\u00a0 Strong communication, interpersonal and analytical skills\n\n-\u00a0\u00a0\u00a0\u00a0\u00a0\u00a0\u00a0 Proficiency in PC skills\n\n-\u00a0\u00a0\u00a0\u00a0\u00a0\u00a0\u00a0 Require to travel to China periodically\n\n-\u00a0\u00a0\u00a0\u00a0\u00a0\u00a0\u00a0 Immediate available is preferable\n\nWe offer bank holidays and medical allowance etc. to the right candidates.", "employment_types": ["Full Time"], "selling_points": [], "locations": ["Kwai Hing"], "categories": ["Admin & HR", "Clerical / Admin Staff", "Merchandising & Purchasing", "Others", "Procurement / Purchasing / Sourcing"], "post_time": "2022-01-17T06:43:22Z", "salary": {"currency": null, "max": null, "min": null, "period": "monthly", "term": null}, "salary_visible": false, "title_keywords": ["merchandiser", "clerk", "assistant merchandiser"], "responsibilities": ["communication"], "requirements": {"degrees": ["fresh graduate", "dse"], "majors": [], "languages": ["cantonese", "english", "mandarin"], "language_level": ["good command"], "hard_skills": ["pc skills", "analytical skills"], "soft_skills": ["communication", "interpersonal", "analytical skills"], "languages_combined": [{"language": "cantonese", "language_level": ["good command"]}, {"language": "english", "language_level": ["good command"]}, {"language": "mandarin", "language_level": ["good command"]}]}, "experience_required": {"duration": ["1-2 years"], "field": ["relevant working experience"]}}, {"job_id": "100003009055425", "location_code": "hk", "company": "Craigengower Cricket Club", "job_title": "Purchasing Assistant (F & B)", "description": "Job duties and responsibilities\n\nCoordinate all purchasing activities for the F & B dept, including sourcing, ordering, receiving and update the unit cost for all food and non-food items\nAssist in preparing documentation of relevant purchasing activities including price comparisons, supplier audit and record keeping\nRequirement\n\nCertificate in Purchasing Management / Supply Chain or related disciplines is preferable\nGood communication skill\nGood knowledge about the food product and market supplies\nGood command of written and spoken English and Chinese\nGood negotiation skill\n\nAttractive remuneration package will be offered to the right persons. Interested parties are invited to apply with full resume with current and expected salary by clicking \u201cApply Now\u201d or by fax: 28905501\n\nPersonal data collected for recruitment purpose only", "employment_types": ["Full Time"], "selling_points": [], "locations": ["Causeway Bay"], "categories": ["Hospitality / F & B", "Others", "Merchandising & Purchasing", "Procurement / Purchasing / Sourcing"], "post_time": "2022-01-18T02:35:17Z", "salary": {"currency": null, "max": null, "min": null, "period": "monthly", "term": null}, "salary_visible": false, "title_keywords": ["purchasing assistant"], "responsibilities": ["coordinate", "cost", "documentation", "audit"], "requirements": {"degrees": ["certificate"], "majors": ["related disciplines"], "languages": ["english", "chinese"], "language_level": ["good command"], "hard_skills": [], "soft_skills": ["negotiation skill", "communication skill"], "languages_combined": [{"language": "english", "language_level": ["good command"]}, {"language": "chinese", "language_level": ["good command"]}]}, "experience_required": {"duration": [], "field": []}}, {"job_id": "100003009056502", "location_code": "hk", "company": "Orenji Creation Limited", "job_title": "Junior Project Executive / Junior Merchandiser (Merchandising) - Fresh Graduate are welcomed", "description": "Overview:\n\nOrenji Creation Limited is a design, gift and premium company that provides professional one-stop service to international well-known brands in Asia Pacific. To Cope with our rapid expansion, we are now inviting high caliber candidate pursuing to join our team in Hong Kong.\n\nJob Requirement:\n\nDiploma holder or above\n1-2 years or above relevant working experience (Fresh Graduate are also welcomed)\nSolid knowledge of gift & premium industry\nStrong in Product Development\nHardworking, Self-motivated, Independent, Attention to detail, Teamwork spirit\nStrong negotiation skill\nAble to work under pressure and tight deadline\nProficiency in PC skills\nFluent in written and spoken English and Mandarin\nImmediate available preferred\n\nResponsibilities:\n\nTo source factories for quality comparison\nTo coordinate with internal parities and follow up production from product development to delivery\nClosely Monitor the production process\nTo solve problem with the factories to ensure product quality and meet tight schedule\nCoordinate with Lab Test Company, ensure the product meet Client\u2019s product safety standard\nFrequent Travel to PRC is required\n\nInterested parties please send a cover letter stating your expected salary, resume and a full set of your portfolio to us.\n\n*All information will be treated as confidential and used solely for recruitment purposes.\n\nInterested parties, please click Apply Now to submit your full resume.", "employment_types": ["Full Time", "Permanent"], "selling_points": [], "locations": ["Wong Tai Sin Area"], "categories": ["Merchandising & Purchasing", "Sundries", "Others", "Procurement / Purchasing / Sourcing"], "post_time": "2022-01-18T04:47:46Z", "salary": {"currency": null, "max": null, "min": null, "period": "monthly", "term": null}, "salary_visible": false, "title_keywords": ["merchandising", "project executive", "junior merchandiser", "junior"], "responsibilities": ["production process", "monitor", "quality", "coordinate with", "schedule"], "requirements": {"degrees": ["diploma holder", "fresh graduate"], "majors": [], "languages": ["english", "mandarin"], "language_level": ["fluent"], "hard_skills": ["pc skills"], "soft_skills": ["self-motivated", "independent", "teamwork spirit", "attention to detail", "negotiation skill", "hardworking", "work under pressure"], "languages_combined": [{"language": "english", "language_level": ["fluent"]}, {"language": "mandarin", "language_level": ["fluent"]}]}, "experience_required": {"duration": ["1-2 years"], "field": ["relevant working experience"]}}, {"job_id": "100003009054431", "location_code": "hk", "company": "Currys Sourcing Limited", "job_title": "Assistant to Product Manager (Consumer Electronics Products)", "description": "Responsibilities:\n\nSupplier Management \u2013 continuous management and review of supplier base on product, price, supply and quality\nProduct Management \u2013 support Product Manager to manage day-to-day operations\nCritical Path Maintenance and Reporting \u2013 support Product Manager to update and deliver to deadlines. Produce and maintain relevant reporting and summaries to support category.\nBuying Trip Preparation - support Product Manager to effectively prepare for buying trips\n\nRequirements:\n\nDiploma or above\nMature, responsible, strong initiation and attention to details\nAble to handle multi-tasks with tight deadlines and work under pressure\nFamiliar with Microsoft Office, such as Excel, Power point\nExperience in sourcing system is advantageous\n1 year of relevant product experience in sizable company, ideally in a buying office environment in EU for consumer electronics products\nStrong communication skills, team-player mindset\nWilling to learn, change, be curious and self-motivated\nExcellent command of English, Mandarin and Cantonese\n\nWe offer attractive remuneration package including work from home policy, 13-instalment salary, discretionary bonus,\u00a0life, medical, dental and eyecare insurances to the right candidate.\u00a0Interested\u00a0applicants\u00a0please send\u00a0your\u00a0detailed\u00a0resume with current and expected salary and the\u00a0availability to Human Resources Department by clicking \"APPLY NOW\"\u00a0or by post:\n\nHuman Resources Department\nCurrys Sourcing Limited\n31/F, AXA Tower, Landmark East\n100 How Mong Street, Kwun Tong\nKowloon\n\nPersonal Data collected will be used for recruitment purposes only.\u00a0\u00a0Applicants who are not invited within 2 months may consider their application unsuccessful. Personal data of unsuccessful applicants will be retained for a period of up to 6 months from the date of rejecting applicants and will then be destroyed.", "employment_types": ["Full Time", "Permanent"], "selling_points": ["Attractive Remuneration Package", "Comprehensive Wellbeing Programme", "Work-life Balance"], "locations": ["Kwun Tong"], "categories": ["Merchandising & Purchasing", "Electronics", "Home Appliances", "Procurement / Purchasing / Sourcing"], "post_time": "2022-01-17T09:30:37Z", "salary": {"currency": null, "max": null, "min": null, "period": "monthly", "term": null}, "salary_visible": false, "title_keywords": ["product manager", "assistant"], "responsibilities": ["reporting", "management", "maintenance", "review", "day-to-day operations", "quality", "maintain"], "requirements": {"degrees": ["diploma or above"], "majors": [], "languages": ["cantonese", "english", "mandarin"], "language_level": ["excellent"], "hard_skills": ["power point", "excel", "microsoft office"], "soft_skills": ["communication skills", "self-motivated", "multi-tasks", "responsible", "team-player", "willing to learn", "mature", "detailed", "attention to details", "work under pressure"], "languages_combined": [{"language": "cantonese", "language_level": ["excellent"]}, {"language": "english", "language_level": ["excellent"]}, {"language": "mandarin", "language_level": ["excellent"]}]}, "experience_required": {"duration": ["1 year"], "field": []}}, {"job_id": "100003009053130", "location_code": "hk", "company": "Sinopec (Hong Kong) Limited", "job_title": "Senior Retail Operation Officer (5-day work)", "description": "Senior Retail Operation Officer\u00a0\n\nJob Description:\n\nIdentify customers\u2019 needs and formulate appropriate strategies i.e. pricing, placing, promoting etc to drive sales.\nWork closely with store managers to ensure the execution of each strategy.\nGenerate actionable quality and quantitative insights with data and analysis for strategic decision making.\nContinuous report and review on retail priorities and strategic action plans with Management in driving sales performance.\nJob Requirements:\n\nBachelor Degree or above\n3-5 years' retailing industry experience is preferable.\nAnalytical, creative, customer-focused, open to change, well planned and self-motivated.\nGood\u00a0interpersonal and people management skills.\u00a0\nProficient in spoken and written Chinese and English.", "employment_types": ["Full Time", "Permanent"], "selling_points": ["Retail Business Strategic Analysis", "Retail operations, convenience store", "Customer focused and quality driven"], "locations": ["Wan Chai"], "categories": ["Merchandising & Purchasing", "Procurement / Purchasing / Sourcing", "Sales, CS & Business Devpt", "Retail Sales", "Sales - Sales Management"], "post_time": "2022-01-17T06:02:19Z", "salary": {"currency": null, "max": null, "min": null, "period": "monthly", "term": null}, "salary_visible": false, "title_keywords": ["officer", "retail operation"], "responsibilities": ["management", "data", "sales performance", "analysis", "review", "quality", "plans", "drive sales", "report"], "requirements": {"degrees": ["degree or above", "bachelor"], "majors": [], "languages": ["english", "chinese"], "language_level": ["proficient"], "hard_skills": [], "soft_skills": ["self-motivated", "creative", "customer-focused", "interpersonal"], "languages_combined": [{"language": "english", "language_level": ["proficient"]}, {"language": "chinese", "language_level": ["proficient"]}]}, "experience_required": {"duration": ["3-5 years"], "field": []}}, {"job_id": "100003009054639", "location_code": "hk", "company": "Urban Group", "job_title": "Senior Administration Officer / Administration Officer", "description": "Responsibilities:\nAssist in preparing contract to building service contractor\nArrange insurance coverage to various locations\nHandle correspondence independently\u00a0\nHandle general office administrative services\nOther ad-hoc projects as assigned\nRequirements:\nDegree in Business Administration or equivalent is preferable\n3 years working experience preferably gained in sizable company\nKnowledge in insurance and contract administration is an advantage\nGood command of written and spoken English and Chinese\nIndependent, good interpersonal and communication skill\nProficiency in Microsoft Office\nImmediate available is preferable\nCandidates with more experience will be considered as Senior Administration Officer\n\nInterested parties please\u00a0send\u00a0application letter with detailed resume, current and expected salary to\u00a0Group Manager \u2013 Human Capital & Training\u00a0through one of the following means:\n\nMail:\u00a016/F., Chevalier Commercial Centre, 8 Wang Hoi Road, Kowloon Bay, Kowloon, Hong Kong\n\nEmail: Click 'Apply Now'\n\nAll personal data collected will be used for employment-related purposes only.\n", "employment_types": ["Full Time", "Permanent"], "selling_points": [], "locations": ["Kowloon Bay"], "categories": ["Admin & HR", "Clerical / Admin Staff", "Others", "Merchandising & Purchasing", "Procurement / Purchasing / Sourcing"], "post_time": "2022-01-17T10:23:38Z", "salary": {"currency": null, "max": null, "min": null, "period": "monthly", "term": null}, "salary_visible": false, "title_keywords": ["senior administration officer", "administration officer"], "responsibilities": ["ad-hoc projects", "insurance"], "requirements": {"degrees": ["degree"], "majors": ["business administration"], "languages": ["english", "chinese"], "language_level": ["good command"], "hard_skills": ["microsoft office"], "soft_skills": ["communication skill", "independent", "interpersonal"], "languages_combined": [{"language": "english", "language_level": ["good command"]}, {"language": "chinese", "language_level": ["good command"]}]}, "experience_required": {"duration": ["3 years"], "field": ["administration"]}}, {"job_id": "100003009047948", "location_code": "hk", "company": "NewPower Worldwide Limited", "job_title": "Purchasing Representative", "description": "Job Overview\n\nThe Purchasing Representative is a critical member of the NewPower Worldwide Procurement team and is responsible for driving revenue growth through new and existing vendor relationship. Your focus is to increase the vendor base and contribute to our long-term business growth. Responsibilities include researching targeted/strategic vendors, developing relationships with potential new vendors, managing, and growing existing vendor revenue opportunities.\n\nJob Roles & Responsibilities\n\n\nIdentify, qualify new suppliers and vendors.\nMonitors pertinent markets and defines how changes will impact supply and pricing conditions.\nResponsible to retrieve service request enquiries from Sales team and update pricing into the CRM.\nBuild, maintain strong relationship with existing and new suppliers and/or vendors.\n\nJob Requirement(s)\n\n\n\u00a0\u00a0\u00a0\u00a0\u00a0\u00a0\u00a0 Minimum a Diploma in any discipline\n\u00a0\u00a0\u00a0\u00a0\u00a0\u00a0\u00a0 Some years of experience as a Buyer/Sourcing role preferred.\n\u00a0\u00a0\u00a0\u00a0\u00a0\u00a0\u00a0 Candidates with no experience are welcome to apply\n\nPersonality Trait(s)\n\n\u00a0\u00a0\u00a0\u00a0\u00a0\u00a0\u00a0 Possesses a highly energetic, outgoing, and friendly demeanor\n\u00a0\u00a0\u00a0\u00a0\u00a0\u00a0\u00a0 Good negotiation skills\n\u00a0\u00a0\u00a0\u00a0\u00a0\u00a0\u00a0 Good communication and presentation skills, both verbal and written.\n\u00a0\u00a0\u00a0\u00a0\u00a0\u00a0\u00a0 Ability to work in fast-paced environment and under pressure\n\u00a0\u00a0\u00a0\u00a0\u00a0\u00a0\u00a0 Self-motivated and self-directed\n\u00a0\u00a0\u00a0\u00a0\u00a0\u00a0\u00a0 Able to multitask, prioritize and manage time efficiently\n\u00a0\u00a0\u00a0\u00a0\u00a0\u00a0\u00a0 Possesses a positive and can-do attitude\n\u00a0\u00a0\u00a0\u00a0\u00a0\u00a0\u00a0 Ability to work independently and as a team", "employment_types": ["Full Time", "Permanent"], "selling_points": ["Attractive Commission Package", "Good Career Growth and Progression", "Friendly and Positive Work Environment"], "locations": ["Kwai Fong"], "categories": ["Merchandising & Purchasing", "Electronics", "Procurement / Purchasing / Sourcing"], "post_time": "2022-01-17T01:45:38Z", "salary": {"currency": null, "max": null, "min": null, "period": "monthly", "term": null}, "salary_visible": false, "title_keywords": ["representative"], "responsibilities": ["maintain", "sales team"], "requirements": {"degrees": ["diploma"], "majors": [], "languages": [], "language_level": [], "hard_skills": ["no"], "soft_skills": ["outgoing", "self-motivated", "work independently", "under pressure", "can-do attitude", "prioritize", "communication", "multitask", "negotiation skills", "presentation skills", "friendly", "work in fast-paced environment", "energetic", "positive"], "languages_combined": []}, "experience_required": {"duration": [], "field": []}}, {"job_id": "100003009054481", "location_code": "hk", "company": "The Wing On Department Stores (Hong Kong) Limited", "job_title": "Assistant Buyer (Household/Apparel/Fashion)", "description": "Responsibilities:\n\nResponsible for the development of products, e.g. household, fashion, shoes & handbags, children & infants, and execution of merchandise assortment as well as buying plans\nSource and develop commercial opportunities, including sourcing new vendors/suppliers to maintain a unique selling proposition for the company\nMonitor inventory through appropriate stock planning and allocation\nCollaborate closely with internal departments to provide product information for supporting marketing campaigns and in-store activities\nNegotiate with suppliers to achieve competitive prices and terms\n\nRequirements:\n\nDegree or above in Supply Chain Management or Business related discipline\n2 years of buying/merchandising experience in retail industry\nHaving overseas buying experiences and supplier network is highly preferable\nStrong market and business sense\nSelf-motivated and able to work under pressure and tight deadlines\nExcellent negotiation and communication skills\nStrong analytical and problem solving skills, perform multi-tasks and good time management skills\nGood command of spoken and written English and Chinese\nImmediately available is highly preferred\n\nCommensurate remuneration and other fringe benefits will be offered to the right candidate. Interested parties please send your\u00a0full resume\u00a0including\u00a0expected salary\u00a0to Human Resources Division, 3/F, Wing On Godown Building, 1 Wang Kee Street, Kowloon Bay, Kowloon, or by click \"APPLY NOW\" button below.\n\n(Candidates not invited for interview within one month may consider their applications filed for future reference.\u00a0 All information collected will be used for recruitment purpose only and will be destroyed after 6 months.)", "employment_types": ["Full Time", "Permanent"], "selling_points": [], "locations": ["Kowloon Bay"], "categories": ["Merchandising & Purchasing", "Footwear", "Handbag", "Procurement / Purchasing / Sourcing"], "post_time": "2022-01-17T09:43:28Z", "salary": {"currency": null, "max": null, "min": null, "period": "monthly", "term": null}, "salary_visible": false, "title_keywords": ["assistant"], "responsibilities": ["collaborate", "inventory", "monitor", "develop", "maintain", "marketing campaigns", "plans", "stock planning"], "requirements": {"degrees": ["degree or above"], "majors": ["business"], "languages": ["english", "chinese"], "language_level": ["good command"], "hard_skills": ["problem solving skills"], "soft_skills": ["communication skills", "self-motivated", "negotiation", "multi-tasks", "business sense", "time management skills", "analytical and problem solving skills", "work under pressure"], "languages_combined": [{"language": "english", "language_level": ["good command"]}, {"language": "chinese", "language_level": ["good command"]}]}, "experience_required": {"duration": ["2 years"], "field": ["retail industry", "merchandising"]}}, {"job_id": "100003009053510", "location_code": "hk", "company": "Bape Hong Kong Limited", "job_title": "Buying Assistant - Aape", "description": "Accountabilities \u2013 Key Result Areas\n\n\n\nAssist buying team in execute buying activities, stock planning and allocation, and merchandise delivery and reordering situations to meet company business objectives\nPrepare merchandising reports for management review on business performance and inventory turn\nAssist OTB planning, sell through, mark down logistics\nWork closely with production and sourcing team to ensure the smooth flow of merchandise delivery\nWork with marketing and retail teams in regard to speedy response to market dynamics and promotions\n\nExperience / Qualification Requirements\n\n\nDegree holder in Fashion & Textiles or business discipline\nWith 1-2 years of experience in\u00a0buying and merchandising, preferably in the fashion / lifestyle / retail industry\nProactive, sensitive to figures and strong analytical and negotiation skills\nAdequate product sensibility and understanding of competitive retail landscape\nAttention to detail with high level of accuracy\n\nCompetitive remuneration and benefit package will be offered to the right candidate. Please submit your application by clicking \"Apply Now\" below.\n\n\n\nAll data collected is for recruitment purpose only.", "employment_types": ["Full Time"], "selling_points": ["1-2 years of working experience in buying", "Assist OTB planning, sell through, mark down", "Prepare merchandising reports"], "locations": ["Southern Area"], "categories": ["Merchandising & Purchasing", "Textiles", "Others", "Procurement / Purchasing / Sourcing"], "post_time": "2022-01-17T07:04:30Z", "salary": {"currency": null, "max": null, "min": null, "period": "monthly", "term": null}, "salary_visible": false, "title_keywords": ["buying assistant"], "responsibilities": ["data", "inventory", "merchandising", "teams", "otb", "reports", "logistics", "recruitment", "stock planning", "management review", "planning"], "requirements": {"degrees": ["degree holder"], "majors": ["business"], "languages": [], "language_level": [], "hard_skills": [], "soft_skills": ["sensitive to figures", "negotiation skills", "attention to detail", "smooth", "proactive"], "languages_combined": []}, "experience_required": {"duration": ["1-2 years"], "field": ["retail industry", "merchandising"]}}, {"job_id": "100003009054669", "location_code": "hk", "company": "New Age Technology (Asia) Limited", "job_title": "Senior merchandiser / Purchaser", "description": "Responsibilities :\n\nCoordinates orders quotations with vendors and category manager\nGuides suppliers for timely execution of production samples and on-time delivery according to the confirmed delivery date\nCollaborate with internal parties to ensure the timeline detail oriented , flexible minded with self confidence , able to work under pressure and overtime \u00a0\nSupports warehouse in sourcing activities (e.g., sample arrangement and handling delivery)\nNegotiates with suppliers/factories to meet the HQ's cost and quality requirements\nMaintain strong business relationships with suppliers/ factories to ensure continuous suppliers' development\nWork closely with quality assurance team to meet markets quality standards\nMaintain open communication within the team as well as with cross-functional departments\nPerform ad hoc duties\n\nRequirements :\n\n\n\nwith minimum 5 years working experience in the accounting/audit field\nGood communicate skill\nGood in written English and Chinese as well as Putonghua.\nProficient in SAP system. Good command in Word, Excel\nMature, Self-motivated, well organized, Work accurately, with a strong sense of responsibility with good interpersonal skills.", "employment_types": ["Full Time"], "selling_points": [], "locations": ["Tsuen Wan Area"], "categories": ["Merchandising & Purchasing", "Procurement / Purchasing / Sourcing"], "post_time": "2022-01-17T16:21:07Z", "salary": {"currency": null, "max": null, "min": null, "period": null, "term": null}, "salary_visible": false, "title_keywords": ["senior merchandiser"], "responsibilities": ["collaborate with", "ad hoc duties", "cost", "quality", "communication", "maintain", "internal parties", "work under pressure"], "requirements": {"degrees": [], "majors": [], "languages": ["putonghua", "english", "chinese"], "language_level": ["good"], "hard_skills": ["excel", "word", "sap"], "soft_skills": ["self-motivated", "sense of responsibility", "well organized", "mature", "interpersonal skills"], "languages_combined": [{"language": "putonghua", "language_level": ["good"]}, {"language": "english", "language_level": ["good"]}, {"language": "chinese", "language_level": ["good"]}]}, "experience_required": {"duration": ["minimum 5 years"], "field": ["accounting", "audit"]}}, {"job_id": "100003009053159", "location_code": "hk", "company": "", "job_title": "Shipping clerk", "description": "Global companies' (Europe/USA) Hong Kong office\n\nPosition : Shipping clerk\n\nWorking: Tsimshatsui\n\nRequirements :\n\nRelevant experience in food additives, chemicals or pharmaceuticals is advantage\nKnowledge in logistic/shipping system & checking of the export documents are essential. (Preparation of full set shipping documents is NOT required).\nCommunication with Chinese producers in Mandarin is a must\nFluent in spoken English & Mandarin and reading & writing in English are most important.\nFamiliar with Ms Word, Outlook, Excel & Chinese Word Processing\nImmediate available is highly preferable\n\nOffer attractive salary & 5 days work to the right candidate\n\nInterested candidates, please contact us at 62122989 for company details before applying.", "employment_types": ["Full Time"], "selling_points": ["Passion, careful, attentive are essential", "Good working environment", "Immediate available is highly preferable"], "locations": ["Tsim Sha Tsui"], "categories": ["Transportation & Logistics", "Documentary Credit / Bills Processing", "Supply Chain", "Merchandising & Purchasing", "Procurement / Purchasing / Sourcing"], "post_time": "2022-01-17T06:10:06Z", "salary": {"currency": null, "max": null, "min": null, "period": "monthly", "term": null}, "salary_visible": false, "title_keywords": ["shipping clerk"], "responsibilities": ["shipping documents", "communication", "shipping", "checking"], "requirements": {"degrees": [], "majors": [], "languages": ["english", "chinese", "mandarin"], "language_level": ["fluent"], "hard_skills": ["excel", "chinese word processing", "outlook", "ms word"], "soft_skills": ["communication"], "languages_combined": [{"language": "english", "language_level": ["fluent"]}, {"language": "chinese", "language_level": []}, {"language": "mandarin", "language_level": ["fluent"]}]}, "experience_required": {"duration": [], "field": ["food", "relevant experience"]}}, {"job_id": "100003009055309", "location_code": "hk", "company": "Wm Morrison (HK) Limited", "job_title": "Sourcing Assistant", "description": "We are currently seeking a Sourcing Assistant for our buying office in Hong Kong\n\nKey accountabilities:\n\n\nLiaise with suppliers to gather supporting documents for profile setup and make sure all data provided by the suppliers are accurately in line with company standards\nOrganize and maintain supplier database\nSupport Sourcing Executives and buying team to build competitive and commercial product range that reflects the design stories is delivered to the customer with strong availability\nAssist Sourcing Executives on end-to-end merchandising activities from buyer's brief to shipment and organize the buying trip\nPerform ad hoc clerical works, sample handling and administrative support as required\nRequirements:\n\nDiploma or above\nSolid EXCEL skills in specific to the need in sourcing and merchandising\nOrganized, self-motivated and detail-orientated\nAbility to adapt to change\nAble to work under pressure and to meet tight deadlines\nProficient in written and spoken English, Mandarin and Cantonese\nGood communication and analytical skills\nA good team-player and individual contributor\nBenefits:\n\nDouble Pay and Annual Performance Bonus\nMedical and Dental Insurance\n20 days Annual Leave\n\nInterested parties please send full resume with expected salary in MS WORD Format by clicking \u201cAPPLY NOW\u201d.\u00a0\n\nApplications will be treated in strict confidence. Personal data collected will be used for recruitment purpose only.", "employment_types": ["Full Time"], "selling_points": ["1-2 years buying office experience", "Organized, self-motivated and detail-orientated", "Good benefits"], "locations": ["Ngau Tau Kok"], "categories": ["Merchandising & Purchasing", "Procurement / Purchasing / Sourcing"], "post_time": "2022-01-18T02:08:25Z", "salary": {"currency": null, "max": null, "min": null, "period": "monthly", "term": null}, "salary_visible": false, "title_keywords": ["assistant"], "responsibilities": ["liaise with suppliers", "ad hoc", "data", "administrative support", "merchandising", "design", "communication", "maintain", "database", "setup", "work under pressure"], "requirements": {"degrees": ["diploma or above"], "majors": [], "languages": ["cantonese", "english", "mandarin"], "language_level": ["proficient"], "hard_skills": ["make", "excel", "analytical skills"], "soft_skills": ["organized", "self-motivated", "meet tight deadlines", "team-player", "analytical skills", "communication", "work under pressure"], "languages_combined": [{"language": "cantonese", "language_level": ["proficient"]}, {"language": "english", "language_level": ["proficient"]}, {"language": "mandarin", "language_level": ["proficient"]}]}, "experience_required": {"duration": [], "field": []}}, {"job_id": "100003009052687", "location_code": "hk", "company": "CTC Triangle (Hong Kong) Limited", "job_title": "Merchandiser", "description": "CTC Triangle (Hong Kong) Limited operates as a subsidiary of Canadian Tire Corporation Ltd., which is the largest retailer of hardlines in Canada, is now seeking a progressive and enthusiastic individual to fill the following position in our Hong Kong Office.\n\nThe successful candidate will be responsible for sourcing and screening suppliers to find the best match for our operational and financial requirements. The candidate will also negotiate and execute projects and programs based on company objectives. Requirements: \u2022 Degree holder in Business Management or Marketing \u2022 At least 3 years of practical experience in sourcing and merchandising \u2022 Excellent interpersonal and communication skills \u2022 Strong analytical, planning, presentation and negotiation skills \u2022 Good systems skills including Excel and Access \u2022 Self-motivated, independent as well as being able to work as a team \u2022 Ability to work in a time sensitive environment and be results driven \u2022 Proficient in Mandarin and an advanced command of both written and spoken English \u2022 Ability to travel frequently to China We are a growth company offering a competitive compensation package and a superior work environment to the right candidate.", "employment_types": ["Full Time"], "selling_points": ["Merchandiser", "At least 3 years of practical experience", "Degree holder in Business Management or Marketing"], "locations": ["Tsim Sha Tsui"], "categories": ["Merchandising & Purchasing", "Procurement / Purchasing / Sourcing"], "post_time": "2022-01-17T03:42:18Z", "salary": {"currency": null, "max": null, "min": null, "period": "monthly", "term": null}, "salary_visible": false, "title_keywords": ["merchandiser"], "responsibilities": ["management", "systems", "merchandising", "communication", "planning"], "requirements": {"degrees": ["degree holder"], "majors": ["business", "marketing"], "languages": ["english", "mandarin"], "language_level": ["proficient", "excellent", "good"], "hard_skills": ["business management", "excel"], "soft_skills": ["communication skills", "self-motivated", "independent", "advanced", "responsible", "work as a team", "presentation", "driven", "negotiation skills", "enthusiastic", "progressive", "superior", "interpersonal", "sensitive"], "languages_combined": [{"language": "english", "language_level": ["excellent", "good"]}, {"language": "mandarin", "language_level": ["proficient", "excellent", "good"]}]}, "experience_required": {"duration": ["at least 3 years"], "field": ["management", "analytical", "merchandising", "business", "marketing", "team", "planning"]}}, {"job_id": "100003009048739", "location_code": "hk", "company": "Tsit Wing Coffee Co Ltd", "job_title": "Procurement Manager", "description": "Job Responsibilities:\n\nDeveloping and implementing Procurement Policies and Procedures requirement on purchasing function\nManaging the purchasing system in a cost-effective way and making recommendation for improvement\nPerforming the proper material requirement planning to avoid any stock out situation\nDeveloping and selecting qualified vendors to ensure the uninterrupted supply and price competitiveness\nManaging all material suppliers to provide quality products to cope with the operation requirement\nStrong leadership, stakeholder management and change management skills, able to negotiate and persuade others for positive results and communicate effectively across all functions and levels\nExploring reliable contract packers to produce own brand products at affordable prices\nUse a breadth of sourcing and procurement skills and tools including good knowledge of the supplier market\nManaging procurement staff and supervising the whole department effectively and efficiently\nStrong organizational skills, able to work independently and under pressure\nSound business acumen with strong competencies and experience in procurement operation\n\nJob Requirements:\n\nDegree holder in Purchasing, Supply Chain Management or any related disciplines\n10 years relevant experience in food & beverage industries\nStrong Supply Chain Management concept with wide exposure\nProcesses excellent communication skills with good command in both written and spoken English and Chinese\n\nWorking Location: Kwai Chung\n\nStaff Benefits:\u00a0\n\nDiscretionary Bonus\nMedical & Life Insurance\nAnnual Leave\nPayable Sick Leave\nEncourage continuing education and on-job training\nOpen office working environment\nOffer promotion opportunities and long-term career path\n\nWe offer a competitive remuneration package to the right candidate. Interested parties please click \"Apply Now\" to submit your application or by email to\u00a0hr1 @twcoffee.com\n\n(All personal data provided by applicants will be treated in strict confidence and used for employment-related purpose only.)", "employment_types": ["Full Time"], "selling_points": [], "locations": ["Kwai Fong"], "categories": ["Merchandising & Purchasing", "Procurement / Purchasing / Sourcing"], "post_time": "2022-01-14T07:11:13Z", "salary": {"currency": null, "max": null, "min": null, "period": "monthly", "term": null}, "salary_visible": false, "title_keywords": ["manager"], "responsibilities": ["cost", "management", "change management", "supervising", "procedures", "developing", "quality", "procurement policies", "planning"], "requirements": {"degrees": ["degree holder"], "majors": ["related disciplines"], "languages": ["english", "chinese"], "language_level": ["excellent", "good command"], "hard_skills": [], "soft_skills": ["communication skills"], "languages_combined": [{"language": "english", "language_level": ["excellent", "good command"]}, {"language": "chinese", "language_level": ["excellent", "good command"]}]}, "experience_required": {"duration": ["10 years"], "field": ["food", "relevant experience"]}}, {"job_id": "100003009055775", "location_code": "hk", "company": "Dunamis International Company Limited", "job_title": "Purchase Executive", "description": "Duties & Responsibilities\n\n\nLiaise with suppliers, follow-up purchase orders, delivery arrangement and inventory control\nManage and develop the assigned product category to drive sales and meet margin target\nKeeping up with market trends, to assist products category are developed in the correct direction\nClosely monitoring assign product\u2019s category and its market price to make sure we are at our most combative on all across channel included our ecommerce platform\nTo handle PO processing and monitoring\nManage quotations, documents & costing\nTo assist other ad-hoc projects as assigned\n\nExperience & Qualifications\n\n\nDiploma or above\n2-5 year work experience, experienced with trading/ FMCG/ electronics related industry will be an advantage\nGood command in spoken and written Chinese and English\nAdaptable to changes with good communication skills, able to work in a fast-paced environment\nImmediate availability is preferred\n\nWe offer attractive fringe benefits including: 5 days-work week, bank holidays & Attendance Bonus.\n\nOur website: http://www.dunamis.hk", "employment_types": ["Full Time"], "selling_points": ["Diploma or above", "Experienced with trading/ FMCG/ electronics", "Immediate availability is preferred"], "locations": ["Kwun Tong"], "categories": ["Marketing / Public Relations", "Marketing - Direct Marketing", "Merchandising & Purchasing", "Electronics", "Procurement / Purchasing / Sourcing"], "post_time": "2022-01-18T02:56:14Z", "salary": {"currency": null, "max": null, "min": null, "period": "monthly", "term": null}, "salary_visible": false, "title_keywords": ["executive"], "responsibilities": ["monitoring", "develop", "communication", "purchase", "inventory control", "drive sales", "ad-hoc projects", "liaise with suppliers"], "requirements": {"degrees": ["diploma or above"], "majors": [], "languages": ["english", "chinese"], "language_level": ["good command"], "hard_skills": ["make", "processing"], "soft_skills": ["adaptable", "communication skills", "fast-paced environment"], "languages_combined": [{"language": "english", "language_level": ["good command"]}, {"language": "chinese", "language_level": ["good command"]}]}, "experience_required": {"duration": ["2-5 year"], "field": ["related", "fmcg", "trading"]}}, {"job_id": "100003009050335", "location_code": "hk", "company": "PERSOLKELLY Hong Kong Limited", "job_title": "Procurement Operation Officer (Multi-International Company)", "description": "Our client, a cognitive solutions and cloud platform company headquartered in New York with operations in over 175 countries and has played a pivotal role in Hong Kong\u2019s development and transformation.\n\nResponsibilities:\n\nConduct new sourcing requests, contract renewals, contract re-negotiation and transactional tasks of tactical sourcing projects.\nConduct detailed spend analysis and compile spend dashboard\nManage purchase requisitions from business, advise requestor on sourcing channel and execute tactical sourcing as needed.\nManage PO issuance (if needed) and review PO status / follow-up with suppliers\nMaintain the contract repository (upload and archive contracts as needed)\nReview contract compliance and contracts due for renewal\nSupport supplier identification, qualification, and onboarding process\nSupport master data management\nSupport complication of procurement operations/performance reports\nOrganize regular vendor meetings, develop appropriate service level agreements and to lead the discussion in resolving vendor/internal issues when required\nManage ongoing vendor relationships, including conformity to contract performance, resolution of payment disputes, and activity on critical dates (extensions, renewals, price adjustments, etc.)\n\nRequirements:\n\nUniversity graduate or professional qualification in a related discipline\nMinimum 3 years of relevant working experience in the procurement field\nExperience in using procurement systems for operating the source-to-pay process and spend analysis\nExcellent people skills, including the ability to negotiate and influence internal and external stakeholders\nPossess of proficiency in Excel (V-lookup, macros) and PowerPoint Presentation\n\nTo apply for this position, please send your full resume to contract_hk @persolkelly.com in word format indicating the job title.\u00a0\n\nIf you are not contacted by our consultants within 2 weeks, please consider your application unsuccessful. All applications will be treated in strict confidence and used for recruitment purposes only in accordance with PERSOLKELLY Hong Kong Limited's Privacy Notice", "employment_types": ["Full Time"], "selling_points": ["At least 3+ yrs relevant exp in procurement field", "Experience in using procurement systems", "Proficiency in Excel (V-lookup, Macros)"], "locations": ["Central & Western Area"], "categories": ["Merchandising & Purchasing", "Procurement / Purchasing / Sourcing"], "post_time": "2022-01-14T10:08:58Z", "salary": {"currency": null, "max": null, "min": null, "period": "monthly", "term": null}, "salary_visible": false, "title_keywords": ["operation officer"], "responsibilities": ["management", "performance reports", "data", "contracts", "analysis", "review", "compliance", "operations", "develop", "resolution", "purchase", "maintain", "payment"], "requirements": {"degrees": ["university graduate"], "majors": [], "languages": [], "language_level": [], "hard_skills": ["excel", "analysis", "word", "powerpoint"], "soft_skills": ["confidence", "presentation"], "languages_combined": []}, "experience_required": {"duration": ["minimum 3 years"], "field": ["procurement", "relevant working experience"]}}, {"job_id": "100003009049008", "location_code": "hk", "company": "Cathay Pacific Catering Services (H.K.) Limited", "job_title": "Procurement Officer", "description": "Responsibilities\nSource, assess and select products and suppliers in order to achieve the Company target on the cost and quality performance of assigned product categories, as well as the relevant suppliers\nNegotiate with suppliers for best deals\nMaintain and update the purchasing database and records\nPerform source planning, conduct market research and develop a supply market\nInvestigate product and supplier issues and coordinate for solutions\nMeasure and analyze the performance of assigned product categories\nAssist in inter-departmental projects to achieve the Company goals and objectives\nRequirements\nDiploma / higher diploma or above in any discipline\nMinimum 2 years\u2019 working experience, preferably with relevant experience in food purchasing\nCandidate possesses a degree in any discipline with less than 2 years working experience will also be considered\nStrong problem solving, numerical and analytical skills\nGood interpersonal and communication skills\nGood price negotiation and cost control skills\nAble to work under pressure and meet stretching targets\nGood command in both written and spoken English and Chinese.\u00a0 Knowledge in Putonghua would be an advantage\nProficient in Microsoft Office, especially MS Word and Excel\nCandidates with more experience will be considered for the position of Senior Procurement Officer\n\nWe offer a competitive remuneration package and a full range of benefits. Interested parties please send your resume with your current and expected salary to Head of People,11 Catering Road East, Hong Kong International Airport, Lantau, Hong Kong or by clicking the \"Apply Now\" button on or before 10 February 2022.\n\nPersonal data collected will be treated in the strictest confidence and only be used for recruitment-related purposes. Applicants who do not receive notification for an interview within six weeks may consider their application unsuccessful.", "employment_types": ["Full Time", "Permanent"], "selling_points": ["Source, assess and select products/suppliers", "Investigate issues with products/suppliers", "Maintain and upkeep purchasing database & records"], "locations": ["Airport Area"], "categories": ["Merchandising & Purchasing", "Sundries", "Others", "Procurement / Purchasing / Sourcing"], "post_time": "2022-01-14T07:54:18Z", "salary": {"currency": null, "max": null, "min": null, "period": "monthly", "term": null}, "salary_visible": false, "title_keywords": ["procurement officer"], "responsibilities": ["product categories", "cost", "conduct market research", "quality", "develop", "coordinate", "maintain", "database", "planning"], "requirements": {"degrees": ["diploma", "higher diploma or above", "degree"], "majors": [], "languages": ["putonghua", "english", "chinese"], "language_level": ["advantage", "good command"], "hard_skills": ["excel", "microsoft office", "analytical skills", "problem solving", "ms word"], "soft_skills": ["communication skills", "negotiation", "analytical skills", "problem solving", "interpersonal", "work under pressure"], "languages_combined": [{"language": "putonghua", "language_level": ["advantage"]}, {"language": "english", "language_level": ["good command"]}, {"language": "chinese", "language_level": ["good command"]}]}, "experience_required": {"duration": ["2 years", "minimum 2 years"], "field": ["purchasing", "food", "relevant experience", "procurement"]}}, {"job_id": "100003009048599", "location_code": "hk", "company": "Timex Nederland B.V. Sequel Services", "job_title": "Procurement Director", "description": "The Procurement Director will report directly to the Senior Procurement Director in Hong Kong.\u00a0 This position will be responsible for leading a supply chain team of professionals in Hong Kong, responsible for the strategic sourcing development and operational management of all product procurement for the company (watches components commodities).\u00a0\n\nThe main goals are to optimize the total cost of ownership for the company, protect IP, maximize the service from vendors in order to meet key stakeholders business expectations, maintain the required quality and delivery levels and ensure compliance with international norms/ regulations and licensor\u2019s requirements.\n\nResponsibilities:\n\n\nWork with key stakeholders to strategically evolve the network of suppliers and consolidate where appropriate to leverage efficiencies, mitigate risk and simplify \"run the business\" activities and drive cost savings.\u00a0\nContinue the robust gross margin enhancement program through the roll out of continuous improvement initiatives at supply partners, motivating key internal Supply Chain and QA stakeholders and supplementing with external resources to drive meaningful cost reduction projects that have a favorable ROI.\nStrategically lead the cost savings program, providing the commercial team with options and recommendations to drive down unit cost and improve gross margin.\nRelentlessly pursue excellence in service levels. He/She will motivate the Supply Planning, Sourcing and Quality teams to collaborate on optimizing batch sizes, run frequency, risk identification and mitigation, lead time reduction and supply chain simplification to achieve service level targets while decreasing overall investment in working capital.\nFoster a team environment, delegated decision making, creative thinking, and excellence in internal customer service. Be accessible and visible, demonstrating energy, passion and enthusiasm.\nActively participate concurrently in the New Product Innovation program and staged gate deliverables, including idea generation, driving awareness of supply-side capabilities and relevant new product developments, and creating a culture across Operations that embraces the importance of every employee in the New Product Development process to effectively launch new SKUs to drive organic company growth.\nBuilding on the business intelligence and current Oracle/Excel reports, institute a data-driven Supplier Performance Scorecard program to measure firm's key desirable attributes: Quality, Service, Cost containment and Supply Continuity.\u00a0\nFoster and develop long-term supplier relationships to create a cooperative and professional framework, while protecting Timex IP, whereby firm's supply partners desire to share in Timex\u2019s growth and success, and work tirelessly on continuous improvement to reduce cost and waste.\nStay informed of current industry-wide regulatory requirements and emerging trends, and ensure that suppliers to Timex conform to these requirements; monitor gap closure plans to mitigate shortfalls as needed.\u00a0\nDevelop and mentor employees and ensure their readiness for company and personal career growth; ensure programs are developed for enhanced use of Oracle and other supply chain tools.\u00a0 Build an organization so that the balance between tactical and strategic is close to 50/50.\u00a0\nRequirement:\n\nBachelor Degree in Mechanical/Electronic/industrial Engineering or related field is minimum with Master Degree is preferred (Mechanical, Electronic Engineering or MBA)\n10+ years of progression in leadership responsibilities in sourcing and commodity purchasing.\u00a0 Experience in watch industry and China experience is preferred.\u00a0\u00a0\nExperience in managing a high volume, high mix portfolio in similar industries (Fast consumer good) and experience in dealing with electronics, mechanical, plating, electro-mechanical technologies.\u00a0\nDemonstrated purchasing and negotiation expertise with 10+ years of broad experience in commodity analysis and product cycles\u00a0\nFluent verbal, presentation and written skills in English and Chinese.\u00a0 Fluent in Mandarin is preferred.\u00a0\nWe offer 5-day work, medical care plus other fringe benefits to the right candidate.\u00a0 Remuneration package will commensurate with your experience and qualification.\u00a0 Interested parties, please send detailed resume with expected salary to our Human Resources Manager.\u00a0\u00a0\n\n\nAll applications will be treated with strict confidentiality and only shortlisted candidates will be notified.", "employment_types": ["Full Time", "Permanent"], "selling_points": [], "locations": ["Cheung Sha Wan"], "categories": ["Merchandising & Purchasing", "Watch", "Procurement / Purchasing / Sourcing"], "post_time": "2022-01-14T08:33:25Z", "salary": {"currency": null, "max": null, "min": null, "period": "monthly", "term": null}, "salary_visible": false, "title_keywords": ["director"], "responsibilities": ["collaborate", "cost", "data", "operations", "regulatory requirements", "quality", "teams", "monitor", "develop", "customer service", "reports", "plans", "planning"], "requirements": {"degrees": ["degree", "bachelor", "master degree"], "majors": ["engineering"], "languages": ["english", "chinese", "mandarin"], "language_level": ["fluent"], "hard_skills": ["analysis"], "soft_skills": ["presentation", "leadership", "negotiation"], "languages_combined": [{"language": "english", "language_level": []}, {"language": "chinese", "language_level": []}, {"language": "mandarin", "language_level": ["fluent"]}]}, "experience_required": {"duration": ["10+ years"], "field": ["purchasing"]}}, {"job_id": "100003009028244", "location_code": "hk", "company": "Creative China Creations Limited", "job_title": "Sourcing Coordinator/ Merchandiser /Sr. Merchandiser /Product Manager (Consumer Products/ Sundries)", "description": "Job Requirements:\u00a0\n\nMinimum 5 years merchandising or relevant experience in Trading or Manufacturing Company. (Sourcing, Product development experience)\nMotivated, Organized, and able to work efficiently to meet the deadlines of buyers\nEXCELLENT COMMAND IN WRITTEN & SPOKEN ENGLISH, CANTONESE & MANDARIN SKILLS\nAble to communicate with suppliers and overseas customers\nResponsible, willing to learn, exhibit a positive attitude and work overtime\nExcellent knowledge of product cost breakdown and production process.\nProficient in material sourcing and supplier evaluation and management.\nExcellent and successful in price negotiation and problem solving skills\nTravel to China for supplier evaluation, management, follow-up, and inspection.\nProficient in PC applications (Microsoft Word, Excel, Microsoft Office applications).\nAn analytical and strategic thinker who is efficient, organized, and attentive to details and able to motivate staff and work under time deadlines.\nStrong sourcing skills and network of potential suppliers that allows the company to source directly through the most cost efficient and competent factories.\nCommunicate clearly to suppliers, including lead time, capacity allocation, pricing and resource allocation to ensure reliable service, quality and low-cost procurement.\nCoordinate with factories for manufacturing process and ensure on time shipment\nSelf-motivated, detailed oriented, a team player and able to work under pressure.\u00a0\nExperienced to supervise merchandising team, & be a team leader.\nCustomer-oriented, effective interpersonal and communication skills\nAble to work independently or part of a team with overseas customers and vendors\nEffectively manage and review vendor base for optimal sourcing results and possess an extensive sourcing network and excellent relationships with vendors.\nProduct management including product development, product selection, Target Negotiation, placement order, pricing.\nAnalyze the marketplace, customers and competitors to determine the right features to bring to market\u00a0\u00a0\nDaily communications with buyers, laboratories and vendors, following through all samples, testing, production to shipments\nEnsuring an effective merchandising value chain which produces goods in good quality standard and meet tight delivery\nGood sourcing experience for USA and EU markets and are familiar with sourcing Websites such as Alibaba.com, globalsources.com, and other sourcing sites.\nA team leader who exhibits leadership qualities and is able to work under pressure and within time constraints.\nPermanent Hong Kong ID card Holder.\nFlexible working times and willing to work after hours if needed.\n\n\nKey responsibilities:\n\nTake the lead in the end-to-end product sourcing cycle from product development, price negotiation to production of consumer products\nWork with the buyers to understand the product and order requirement\nCommunicate with vendors and factories to ensure on-time delivery and resolve any potential problems\nExecute and review existing internal systems and policies to ensure smooth operations and meeting company standards\n\n\nKey requirements:\n\nDegree/Diploma holder, with at least 5 years of relevant experience\nGood understanding on global Markets\nExcellent command in Cantonese, English and Mandarin\nGood communication and interpersonal skills to work with counterparts\nAble to work independently and meet tight deadlines\nProficient in computer skills and MS Office Applications\n\n\nInterested applicants please send your English application along with cover letter and detailed resume with current and expected salary clearly stated to \u201cApply Now\u201d.\n\nAll Personal data collected will be used for recruitment purpose only.", "employment_types": ["Full Time", "Permanent"], "selling_points": ["double pay and performance bonus", "Good understanding on global markets", "With at least 5 years of relevant experience"], "locations": ["Ngau Tau Kok"], "categories": ["Manufacturing", "Product Development / Management", "Merchandising & Purchasing", "Sundries", "Procurement / Purchasing / Sourcing"], "post_time": "2022-01-17T16:20:53Z", "salary": {"currency": null, "max": null, "min": null, "period": "monthly", "term": null}, "salary_visible": false, "title_keywords": ["merchandiser", "product manager", "coordinator", "sr. merchandiser"], "responsibilities": ["communicate with", "price negotiation", "policies", "review", "communication", "recruitment", "ensure smooth operations", "personal data", "internal systems"], "requirements": {"degrees": [], "majors": [], "languages": ["cantonese", "english", "mandarin"], "language_level": ["excellent"], "hard_skills": ["excel", "microsoft word", "microsoft office", "id", "vendor", "pc applications", "problem solving skills"], "soft_skills": ["work overtime", "team player", "leadership", "work under pressure", "efficient", "customer-oriented", "reliable", "interpersonal", "organized", "communication skills", "work independently", "negotiation", "competent", "willing to learn", "extensive", "flexible", "self-motivated", "detailed oriented", "responsible", "attentive to details", "positive attitude", "motivated", "problem solving skills"], "languages_combined": [{"language": "cantonese", "language_level": ["excellent", "excellent"]}, {"language": "english", "language_level": ["excellent", "excellent"]}, {"language": "mandarin", "language_level": ["excellent", "excellent"]}]}, "experience_required": {"duration": ["minimum 5 years"], "field": ["manufacturing", "merchandising", "relevant experience", "product development", "trading"]}}, {"job_id": "100003009052176", "location_code": "hk", "company": "Champion Global Services Limited", "job_title": "Project Officer \u2013 FF&E and OS&E", "description": "Responsibilities:\n\nAssist in handling and managing FF&E andOS&E projects including but not limited to budget control, project schedule and tender process\nSupport procurement goods & services by obtaining competitive quotes from reliable vendors\nIdentify potential suppliers and manage the relationships with suppliers to support the procurement function\nCoordinate with all relevant parties to ensure timely delivery and installation as per approved and prescribed procedure\nIssue tender, verify and input evaluation and analysis documents\nIssue and track Purchase Orders from issuance, shop drawing, production, QA&QC of goods, deliveries and payment to suppliers.\nHandle ad hoc projects as assigned\n\nRequirements:\n\nDegree or above in Procurement, Supply Chain or other related disciplines\n2 \u2013 3 years\u2019 experience in managing FF&E andOS&E procurement projects; experience gained in hotel industry or sizeable organization is an advantage\nExperience in managing overseas projects is an advantage\nGood knowledge in interior design is an advantage\nWell-organized, independent and able to work under pressure\nGood communication and problem-solving analytical skills\nSelf-motivate, proactive and high integrity with trustworthy personality\nProficient in MS Office applications\nGood command of both spoken and written English and Chinese (including Putonghua)\nCandidates with less experience and qualifications will be considered as Senior Project Officer\n\nSalary and benefits will be commensurate with qualifications and experience.\u00a0 Interested parties, please send a full resume with present and expected salary, and date available to The Human Resources Department, 32/F., Great Eagle Centre, 23 Harbour Road, Wanchai, Hong Kong or e-mail to us.\u00a0\u00a0\u00a0(Please quote the reference no. on the envelope and the covering letter.)\n\nTo know more about us, please visit our website at http://www.greateagle.com.hk\n\nWe are an equal opportunity employer and welcome applications from all qualified candidates.\n\nPersonal data collected will be treated in strict confidence and used only for recruitment-related purpose. Applicants who have not heard from us within four weeks may consider their applications unsuccessful. All personal data will be destroyed after 12 months.", "employment_types": ["Full Time", "Permanent"], "selling_points": ["FF&E and OS&E projects", "Prcourement consultancy services", "Hospitality industry"], "locations": ["Wan Chai"], "categories": ["Hospitality / F & B", "Others", "Merchandising & Purchasing", "Furniture", "Procurement / Purchasing / Sourcing"], "post_time": "2022-01-17T02:21:22Z", "salary": {"currency": null, "max": null, "min": null, "period": "monthly", "term": null}, "salary_visible": false, "title_keywords": ["project officer"], "responsibilities": ["installation", "analysis", "coordinate with", "purchase", "payment", "ad hoc projects", "schedule", "tender", "evaluation", "budget control"], "requirements": {"degrees": ["degree or above"], "majors": ["related disciplines"], "languages": ["putonghua", "english", "chinese"], "language_level": ["good command"], "hard_skills": ["problem-solving", "ms office", "analytical skills"], "soft_skills": ["independent", "trustworthy", "problem-solving", "well-organized", "integrity", "analytical skills", "communication", "proactive", "work under pressure"], "languages_combined": [{"language": "putonghua", "language_level": ["good command"]}, {"language": "english", "language_level": ["good command"]}, {"language": "chinese", "language_level": ["good command"]}]}, "experience_required": {"duration": ["3 years"], "field": ["hotel industry", "procurement"]}}, {"job_id": "100003009050195", "location_code": "hk", "company": "FnF Hong Kong Limited", "job_title": "Assistant Buyer / Assistant Merchandiser", "description": "RESPONSIBILITIES\n\nSpecific responsibilities include but are not restricted to:-\n\nResponsible for merchandise mix and assortment planning in accordance to business objectives\nPlan and execute buying activities of designated product categories for maximizing sales and inventory productivity\nFollow through on delivery, stock allocation, replenishment and consolidation\nAnalyse sales, sell-through performance and share recommendations for achieving quantitative and qualitative goals\nManage e-shop operation including product listings, pricing, UAT and sales supporting tasks\nRegularly conduct market research and consistently strive to buy better in order to upgrade responsible merchandise assortment and department\u2019s sales performance\nPrepare weekly and monthly merchandising reports for management review\nDeliver administration and assistant duties to ensure smooth running of the team\nWork closely with Retail / Visual Merchandising / Marketing teams to ensure smooth operations\n\n\u00a0REQUIREMENTS\n\nDegree holder in Fashion, Textile and Clothing or business-related disciplines with minimum 3-4 years solid merchandising / buying experience in fashion retail company\nStrong knowledge and passion for fashion retail / business\nPositive working attitude, self-motivated and able to work under pressure and fast pace environment\nGood interpersonal, communication and presentation skills\nProficient in MS Office, strong in Excel (e.g. vlookup & pivot table)\nProficiency in both spoken and written English and Chinese\nImmediate available is prefered", "employment_types": ["Full Time", "Permanent"], "selling_points": ["Follow through on delivery, stock allocation", "Replenishment and consolidation", "E-shop operation"], "locations": ["Yau Tsim Mong Area"], "categories": ["Merchandising & Purchasing", "Others", "Procurement / Purchasing / Sourcing", "E-commerce", "Product Management / Business Analyst"], "post_time": "2022-01-14T09:55:30Z", "salary": {"currency": null, "max": null, "min": null, "period": "monthly", "term": null}, "salary_visible": false, "title_keywords": ["assistant merchandiser", "assistant"], "responsibilities": ["inventory", "conduct market research", "merchandising", "planning", "plan", "management review", "administration", "product categories", "sales supporting tasks", "uat", "sales performance", "teams", "reports", "visual", "stock allocation", "manage e-shop", "ensure smooth operations", "product listings", "replenishment", "analyse"], "requirements": {"degrees": ["degree holder"], "majors": ["related disciplines", "business"], "languages": ["english", "chinese"], "language_level": ["proficiency"], "hard_skills": ["excel", "vlookup", "pivot table", "ms office"], "soft_skills": ["self-motivated", "passion for", "communication", "positive working attitude", "presentation skills", "interpersonal", "work under pressure"], "languages_combined": [{"language": "english", "language_level": ["proficiency"]}, {"language": "chinese", "language_level": ["proficiency"]}]}, "experience_required": {"duration": ["minimum 3-4 years"], "field": ["related", "merchandising", "business", "textile", "retail"]}}, {"job_id": "100003009055198", "location_code": "hk", "company": "Tsit Wing Coffee Co Ltd", "job_title": "Shipping clerk", "description": "What awaits you \u2026\n\nResponsible for direct and indirect procurement of products and services to support company\u2019s business\nEnsure that the products or services are of high quality and cost effective aligned with the procurement policies and guidelines in the approval of each purchase including RFQ, PO issue, invoice tracking, filing and log in record in internal system\nBuild and maintain good relationships with key vendors and various stakeholders and explore great opportunities to obtain the best deals from them and ensure products and services are in high quality and delivered on time\nCompare and evaluate offers from vendors and review annual contract with vendors and negotiate contract terms of agreement and pricing\nWork closely with Operations Teams to understand their requirements for potential suppliers\nUpdate vendors/suppliers\u2019 data on regularly base and maintain the up-to-dated list for record and analysis\nMaintain accurate records of purchases, delivery information, benchmarking prices in internal databases\nPrepare reports on purchases including cost analyses\nConduct research on potential new vendors or sub-contractors from local and overseas market\nFactory visit on new potential vendors within or outside Hong Kong\nOnsite visit before and after client events to ensure quality of vendor service is up to standard\nWhat you should bring with you \u2026\n\n\nDiploma or degree in related discipline\nHold relevant certification such as MCIPS or CPSM will be a bonus\nMinimum 3+ years of purchasing management experience in fast paced working environment\nWorking knowledge in Events and Exhibition industry is preferred but not a must\nStrong existing network of high-quality suppliers to Event and Exhibition industry is a bonus\nProven knowledge of vendor sourcing practices (researching, evaluating and liaising with vendors)\nSolid analytical skills, with the ability to create financial reports and conduct cost analyses\nAttention to details with strong commercial awareness and compliance with deadlines\nExcellent interpersonal and negotiation skills\nEffective verbal and written English and Chinese communication skills, ability to speak Mandarin is a bonus\nProficient in MS Word, Excel and PowerPoint\u00a0\nPlease submit your resume together\u00a0with your current and expected salary\u00a0by clicking \"Apply Now\".\u00a0\n\nAll\u00a0applications will be treated in strict confidence and used exclusively for recruitment purposes.\n\nApplicants who are not being contacted within 6-8 weeks may consider their application unsuccessful.", "employment_types": ["Full Time", "Permanent"], "selling_points": [], "locations": ["Kwai Fong"], "categories": ["Transportation & Logistics", "Fulfillment", "Shipping", "Merchandising & Purchasing", "Procurement / Purchasing / Sourcing"], "post_time": "2022-01-18T01:44:58Z", "salary": {"currency": null, "max": null, "min": null, "period": "monthly", "term": null}, "salary_visible": false, "title_keywords": ["shipping clerk"], "responsibilities": ["data", "operations", "quality", "communication", "purchase", "procurement policies", "maintain", "conduct research", "compliance", "teams", "liaising with", "cost", "management", "invoice", "review", "tracking", "financial reports", "guidelines", "analysis", "evaluate", "recruitment", "databases", "prepare reports"], "requirements": {"degrees": ["diploma", "degree"], "majors": [], "languages": ["english", "chinese", "mandarin"], "language_level": [], "hard_skills": ["excel", "analysis", "vendor", "powerpoint", "analytical skills", "databases", "ms word"], "soft_skills": ["communication skills", "confidence", "responsible", "analytical skills", "negotiation skills", "attention to details", "accurate", "interpersonal"], "languages_combined": [{"language": "english", "language_level": []}, {"language": "chinese", "language_level": []}, {"language": "mandarin", "language_level": []}]}, "experience_required": {"duration": ["minimum 3+ years"], "field": ["purchasing", "management"]}}, {"job_id": "100003009051784", "location_code": "hk", "company": "Keysen (LPB) Management Services Limited", "job_title": "Buying Assistant", "description": "OUR COMPANY\u00a0\n\nGROWN UP GROUP (Listed at the Hong Kong Stock Exchange, HKEX: 1842) is one of the world\u2019s leading companies within the bags and luggage industry.\n\nWe manufacture and design for a wide range of international brands, such as Adidas, Samsonite, Wilson and a strong portfolio of licensed and own brands like LEGO, Caterpillar, New Balance and Ellehammer.\n\nWe manufacture at both our own factories and at our numerous partner factories in \u00a0\u00a0Southeast Asia. We serve our customers from our global head office in Hong Kong, our R&D center in Shenzhen, our sales and design offices in Asia, Europe and the USA.\n\n\u00a0\nYOUR ROLE\n\nYou will be a member of our Merchandising Team and report directly to \u00a0 Head of Product Development, Merchandising, Sourcing and Design.\n\nYou have past record of successfully managing a small team.\n\nYou are leading a merchandising team in full merchandising duties from customer inquiry, product development, execute sourcing strategies, production and quality follow up, lab test submission, and handling incident etc., until shipment is completed, so as to ensure proper execution of schedule and timely delivery.\nYou are analyzing costing of products and materials, negotiating with suppliers for better price and target on company\u2019s cost improvement aim.\nYou are maintaining close communication with Brand & Licenses Team and customers\nYou are training the merchandising team on problem solving, product knowledge, merchandising skills and overall abilities\nThe post is based in Shenzhen Office. Frequent travelling is required.\n\n\nYOUR CHARACTER & COMPETENCES\n\nDiploma or above, in fashion, clothing or related discipline will be an advantage\nAt least 8 years of Merchandising experience, preferably in travel goods, garment, apparel, accessories or sports goods, and experience in order follow up and correspondence independently.\nDetailed-minded, flexible and be able to work well under pressure and meet strict deadlines.\nGood problem solving, interpersonal, communication and negotiation skills.\nGood command of both written and spoken English and Chinese, as well as Putonghua.\nAvailable by March 2022.\nWE OFFER YOU\nCompetitive salary\n5-day work week\nMedical insurance\nAnnual leave starting from 14 days\nWork experience with exposure to European markets\nA friendly work environment\n\nYOUR APPLICATION\n\n\u00a0\u00a0\u00a0\u00a0\u00a0 Please send us your application and CV with salary expected today.", "employment_types": ["Full Time", "Permanent"], "selling_points": ["Buying process and merchandise management", "PO analysis", "Beauty store"], "locations": ["Mong Kok"], "categories": ["Beauty Care / Health", "Others", "Marketing / Public Relations", "Marketing - Market Research", "Merchandising & Purchasing", "Procurement / Purchasing / Sourcing"], "post_time": "2022-01-17T01:07:06Z", "salary": {"currency": null, "max": null, "min": null, "period": "monthly", "term": null}, "salary_visible": false, "title_keywords": ["buying assistant"], "responsibilities": ["cost", "maintaining", "quality", "merchandising", "design", "communication", "schedule", "report"], "requirements": {"degrees": ["diploma or above"], "majors": [], "languages": ["putonghua", "english", "chinese"], "language_level": ["good command"], "hard_skills": ["r&d", "small", "problem solving", "exchange"], "soft_skills": ["flexible", "independently", "under pressure", "timely", "communication", "problem solving", "negotiation skills", "interpersonal", "detailed"], "languages_combined": [{"language": "putonghua", "language_level": ["good command"]}, {"language": "english", "language_level": ["good command"]}, {"language": "chinese", "language_level": ["good command"]}]}, "experience_required": {"duration": ["at least 8 years"], "field": ["garment", "merchandising"]}}, {"job_id": "100003009048691", "location_code": "hk", "company": "Cornerstone Technologies Holdings Limited", "job_title": "Senior Procurement Officer", "description": "Job Requirements:\n\nDevelop and implement the Creative China Creations Limited (CCCL) Vendor Quality Management System across the supplier network in China as well as CCCL own facility in Mainland China in conjunction with the product development team at Hong Kong head office.\nFacilitate correspondence on internal Quality Control checks between Hong Kong office (Product Development Team) & CCCL factory in Mainland China as well as 3rd party suppliers\nCommunicate with Hong Kong team members on technical specifications & requirements through the product development process to ensure quality standards for both product functionality, safety and compliance are met.\nEstablish protocols with supplier production teams to develop high-volume and quick- turnaround manufacturing processes and capabilities for new product implementation (NPI)\nConduct quality audits (IQC, IPQC & OQC) for pre- and mass-production at suppliers.\nIntroduce protocols for final goods inspection with supplier QC team and third-party inspectors, and SOPs for in-time reporting and rapid corrective/preventive action plan (CAPA).\nSuggest quality control enhancements for both infrastructure & ERP systems as well as specific consumer products.\nUtilize inspection metrics and quality improvement/control tools (e.g., DOE & FMEA) to drive continuous quality improvement with suppliers.\nLiaise & coordinate 3rd party inspections with various companies such as SGS, Intertek, BV, etc and help establish inspection mandates & protocols to follow.\nMonitor market sale and return data and provide warning alerts to head office for quality risk management.\nLead company initiative to support overseas suppliers to attain C-TPAT validation (Customs \u2013 Trade Partnership against Terrorism - USA) as well as meet other audit or client specific audit standards such as ISO, ETL, UL, CE, BSCI, ICTI standards.\nEXCELLENT COMMAND IN WRITTEN & SPOKEN ENGLISH, CANTONESE & MANDARIN SKILLS\nAble to Travel to China for implementation and monitoring of Quality Control systems.\nCandidates with at least 5 years\u2019 experience is preferred but not a requirement.\nThe ability to work independent or part of a larger team, with the mentality & work ethic of a leader.\nFamiliarity with Quality control systems for consumer products is preferred.\nA team leader who exhibits leadership qualities and is able to work under pressure and within time constraints.\nPermanent Hong Kong ID card Holder.\nFlexible working times and willing to work after hours if needed.\n\n\u00a0Key requirements:\n\nDegree/Diploma holder, with at least 5 years of relevant experience\nGood understanding on US/UK/EU Markets\nExcellent command in Cantonese, English and Mandarin\nGood communication and interpersonal skills to work with counterparts\nAble to work independently and meet tight deadlines\nProficient in computer skills and MS Office Applications\nUnderstand electronic circuitry in component level.\nHands on experience in operating test equipment such as voltmeter, ammeter and oscilloscope\nCoordinate weekly customer complaint meeting.\n\nInterested applicants please send your English application along with cover letter and detailed resume with current and expected salary clearly stated to \u201cApply Now\u201d.\n\nAll Personal data collected will be used for recruitment purpose only.\n", "employment_types": ["Full Time", "Permanent"], "selling_points": ["Material Control, demand planning, suppliers mgt.", "Product sourcing and price negotiation", "3-year exp., preferably in electrical industry"], "locations": ["Wong Tai Sin Area"], "categories": ["Transportation & Logistics", "Supply Chain", "Merchandising & Purchasing", "Electronics", "Procurement / Purchasing / Sourcing"], "post_time": "2022-01-14T07:02:56Z", "salary": {"currency": null, "max": null, "min": null, "period": "monthly", "term": null}, "salary_visible": false, "title_keywords": ["procurement officer"], "responsibilities": ["liaise", "data", "quality", "audit", "communication", "plan", "personal data", "work under pressure", "control", "compliance", "teams", "implementation", "infrastructure", "develop", "monitor", "reporting", "management", "monitoring", "inspection", "specifications", "sops", "audits", "communicate with", "systems", "coordinate", "recruitment", "quality control"], "requirements": {"degrees": ["diploma holder", "degree"], "majors": [], "languages": ["cantonese", "english", "mandarin"], "language_level": ["excellent"], "hard_skills": ["erp systems", "id", "vendor", "c", "computer skills", "rapid", "ms office"], "soft_skills": ["flexible", "work independently", "meet tight deadlines", "independent", "detailed", "communication and interpersonal skills", "hands on", "work ethic", "creative", "leadership", "initiative", "work under pressure"], "languages_combined": [{"language": "cantonese", "language_level": ["excellent", "excellent"]}, {"language": "english", "language_level": ["excellent", "excellent"]}, {"language": "mandarin", "language_level": ["excellent", "excellent"]}]}, "experience_required": {"duration": ["at least 5 years"], "field": ["relevant experience"]}}, {"job_id": "100003009052833", "location_code": "hk", "company": "Panasonic Hong Kong Co., Limited", "job_title": "Officer (Operation Planning)", "description": "Responsibilities\u00a0\n\nResponsible for I/E Document preparation, declaration\nMonitor shipment status and order follow up\nCoordinate with freight forwarders and shipping companies for shipment and transportation arrangement\nAccurate and timely data input of shipment details to order system\nPerform any ad hoc projects as assigned\n\nRequirements\n\nDegree holder in relevant discipline\u00a0\n2 years\u2019 experiences preferably in shipping\nFresh graduates will be considered\nExcellent communication skills with both internal and exteral parties\nGood command of spoken English, Putonghua and Cantonese\nKnowledge of SAP system is preferred\n\nWorking location:\u00a0Kwai Chung\n\n\n\nStaff Benefit\n\nDiscretionary Bonus\nMedical & Life Insurance\nAnnual Leave\nPayable Sick Leave\nEncourage continuing education and on-job training\nOpen office working environment\nOffer promotion opportunities and long-term career path\u00a0\n\nWe offer a competitive remuneration package to the right candidate.\u00a0Interested parties\u00a0please click\u00a0\"Apply Now\"\u00a0to submit your application\u00a0or by email to\u00a0hr1 @twcoffee.com\n\n\u00a0(All personal data provided by applicants will be treated in strict confidence and used for employment-related purpose only.)", "employment_types": ["Full Time", "Permanent"], "selling_points": ["Knowledge in System & Operation Planning", "3 yrs relevant exp. in international trading", "Stable MNC in-house environment"], "locations": ["Tsim Sha Tsui"], "categories": ["Information Technology (IT)", "Product Management / Business Analyst", "Transportation & Logistics", "Supply Chain", "Merchandising & Purchasing", "Procurement / Purchasing / Sourcing"], "post_time": "2022-01-17T04:13:26Z", "salary": {"currency": null, "max": null, "min": null, "period": "monthly", "term": null}, "salary_visible": false, "title_keywords": ["officer"], "responsibilities": ["shipping", "monitor", "data input", "coordinate with", "ad hoc projects"], "requirements": {"degrees": ["degree holder"], "majors": [], "languages": ["cantonese", "putonghua", "english"], "language_level": ["good command"], "hard_skills": ["sap"], "soft_skills": ["communication skills"], "languages_combined": [{"language": "cantonese", "language_level": ["good command"]}, {"language": "putonghua", "language_level": ["good command"]}, {"language": "english", "language_level": ["good command"]}]}, "experience_required": {"duration": ["2 years"], "field": []}}, {"job_id": "100003009040320", "location_code": "hk", "company": "REWE Far East Limited", "job_title": "Project Manager, Packaging", "description": "Responsibilities:\n\nSupport the Buyer in all aspects of the buying process and merchandise management including monitoring stock allocation, warehouse schedules and deliveries, and other logistics administration\nAssist in analyzing market trends, merchandise assortment and sales performance on merchandise categories\nPrepare PO analysis report and weekly ordering report\nLiaise with own purchase brand for PO placement with approved OTB budget weekly\nFollow up on order confirmation, ensure prompt delivery, and manage stock re-allocation\nPerform ad hoc duties as assigned\n\nRequirements:\n\nDegree holder in Business Administration or any related disciplines\n1-2 years of experience in buying counter management in beauty store\nHands-on experience in managing multiple own bought brands is highly preferred\nProactive, detail-oriented, self-motivated and able to work under pressure\nGood communication and interpersonal skills\nProficient in MS Office Applications and Chinese Word Processing\nStrong business sense with passion in beauty industry\nGood command of both written and spoken English and Chinese\n\nSalary and benefits will be commensurate with qualifications and experience.\u00a0 Interested parties, please send a full resume with present and expected salary, and date available to The Human Resources Department, 32/F., Great Eagle Centre, 23 Harbour Road, Wanchai, Hong Kong or e-mail to us.\u00a0(Please quote the reference no. on the envelope and the covering letter.)\n\nTo know more about us, please visit our website at http://www.greateagle.com.hk.\n\nWe are an equal opportunity employer and welcome applications from all qualified candidates.\n\nPersonal data collected will be treated in strict confidence and used only for recruitment-related purpose. Applicants who have not heard from us within four weeks may consider their applications unsuccessful. All personal data will be destroyed after 12 months.", "employment_types": ["Full Time", "Permanent"], "selling_points": ["Packaging, Project management", "EU buying office, Mobile Working, Flex Working Hr", "13th month Bonus, Discretionary Bonus"], "locations": ["Kwun Tong Area"], "categories": ["Transportation & Logistics", "Supply Chain", "Manufacturing", "Printing", "Merchandising & Purchasing", "Procurement / Purchasing / Sourcing"], "post_time": "2022-01-16T21:50:03Z", "salary": {"currency": null, "max": null, "min": null, "period": "monthly", "term": null}, "salary_visible": false, "title_keywords": ["project manager"], "responsibilities": ["ad hoc duties", "management", "schedules", "stock allocation", "sales performance", "monitoring", "analysis report", "budget", "otb", "purchase", "logistics", "liaise with", "report", "administration"], "requirements": {"degrees": ["degree holder"], "majors": ["related disciplines", "business administration"], "languages": ["english", "chinese"], "language_level": ["good command", "proficient"], "hard_skills": ["chinese word processing", "ms office"], "soft_skills": ["self-motivated", "business sense", "passion in", "detail-oriented", "hands-on", "communication and interpersonal skills", "proactive", "work under pressure"], "languages_combined": [{"language": "english", "language_level": ["good command"]}, {"language": "chinese", "language_level": ["good command", "proficient"]}]}, "experience_required": {"duration": ["1-2 years"], "field": ["management", "beauty"]}}, {"job_id": "100003009051136", "location_code": "hk", "company": "RenoPipe Construction (H.K.) Limited", "job_title": "Purchasing Officer", "description": "We are seeking high caliber people like you to join us to fast-track your career with\u00a0Cornerstone Technologies.\n\nResponsibilities:\u00a0\n\nManage and monitor the Material suppliers including demand planning, order processing and forecasting, suppliers' management and logistics arrangement\nResponsible for product sourcing and price negotiation (electronic components and electro-mechanical parts)\nWork closely with\u00a0supplier and monitor\u00a0material\u00a0receiving, kitting, stock ledger accuracy and finish goods delivery\nManage stock level & logistics to ensure on time delivery\nGenerate and maintain effective reports to control Suppliers' production and material plan.\nTravel to PRC is required upon request (after Covid-19)\nPerform other ad hoc tasks assigned by the Management\n\nRequirements:\n\nHigher Diploma or above\nDegree holder in\u00a0Logistics, Procurement, Material control, or related discipline is preferred\nAt least 3 years of relevant experience in Electrical industry / electrical product trading company - Export Trade / Business\nKnowledge in purchasing electrical material and mechanical parts is preferred.\nProficiency in Word, Excel and Chinese word processing\nFamiliar with SAP system is preferred.\nGood command of both written and spoken English and Chinese\nFluency in Putonghua in a PLUS.\nPleasant, mature, proactive, independent, and able to work under pressure\nImmediately available is preferred.\n\nWe offer 5-day work and medical benefits to the successful candidates. Interested parties please send your full CV with current and expected salary in MS Word format to the Human Resources & Administration Manager.\n\nTo know more about us, please visit our website at\u00a0https://www.cstl.com.hk.\n\nWe are an equal opportunity employer and welcome applications from all qualified candidates.\n\nPersonal data collected will be treated in strict confidence and used only for recruitment-related purpose. Applicants who have not heard from us within four weeks may consider their applications unsuccessful. All personal data will be destroyed after 6 months.", "employment_types": ["Full Time"], "selling_points": ["Handle material sourcing & vendor selection", "Keep file of all documents in good order;", "3 years solid purchasing experience"], "locations": ["Ngau Tau Kok"], "categories": ["Building & Construction", "Civil / Structural", "Merchandising & Purchasing", "Procurement / Purchasing / Sourcing"], "post_time": "2022-01-15T03:18:08Z", "salary": {"currency": null, "max": null, "min": null, "period": "monthly", "term": null}, "salary_visible": false, "title_keywords": ["purchasing officer"], "responsibilities": ["management", "price negotiation", "control", "logistics arrangement", "demand planning", "monitor", "ensure on time delivery", "ad hoc tasks", "material receiving", "logistics", "maintain", "order processing", "reports", "plan", "forecasting"], "requirements": {"degrees": ["higher diploma or above", "degree holder"], "majors": [], "languages": ["putonghua", "english", "chinese"], "language_level": ["fluency", "proficiency", "good command"], "hard_skills": ["excel", "plus", "chinese word processing", "sap", "word"], "soft_skills": ["independent", "mature", "pleasant", "proactive", "work under pressure"], "languages_combined": [{"language": "putonghua", "language_level": ["fluency"]}, {"language": "english", "language_level": ["good command"]}, {"language": "chinese", "language_level": ["proficiency", "good command"]}]}, "experience_required": {"duration": ["at least 3 years"], "field": ["business", "relevant experience", "trading"]}}, {"job_id": "100003009048393", "location_code": "hk", "company": "Airport Authority Hong Kong", "job_title": "Assistant Manager, Procurement", "description": "Responsibilities:\n\nPrepare schedule and coordinate Electronic Data Interchange with users, business partners, IT Dept and monitor the overall performance\nPrepare monthly reports and ad-hoc management reports for management analysis purpose\nCoordinate Global Freight Cost and container space issue with GFC Team and Operation team\nSupport improvement projects in system, operation and logistics aspects\nSupport in-house system login management\nPerform in-house training within Division\nPerform other ad-hoc projects as assigned\n\nRequirements:\n\nBachelor Degree or above in Business, Supply Chain Management, Computer Science or related discipline\n3 years relevant experience in international trading\nProficient in MS Office (Word, Excel, PowerPoint)\nGood command of English and Mandarin. Japanese is preferable\nGood analytical skills on reporting\nGood communication skills, well organized\n\nRemuneration will be commensurate with qualification and experience. Interested parties, please send your application with detailed resume indicating both existing & expected salary and date of availability to us.\n\nWe are an equal opportunity employer. All information provided by applicants will be treated in strict confidence and used for recruitment purpose only.", "employment_types": ["Full Time"], "selling_points": ["Procurement of IT hardware, software, telecom etc", "A minimum of 6 years' relevant working experience", "Experience in handling WTO/ GPA tender"], "locations": ["Airport Area"], "categories": ["Merchandising & Purchasing", "Procurement / Purchasing / Sourcing"], "post_time": "2022-01-14T06:27:50Z", "salary": {"currency": null, "max": null, "min": null, "period": "monthly", "term": null}, "salary_visible": false, "title_keywords": ["assistant manager,"], "responsibilities": ["ad-hoc", "management", "cost", "monthly reports", "data", "analysis", "monitor", "coordinate", "management reports", "logistics", "schedule", "ad-hoc projects"], "requirements": {"degrees": ["degree or above", "bachelor"], "majors": ["business", "computer science"], "languages": ["japanese", "english", "mandarin"], "language_level": ["good command"], "hard_skills": ["excel", "word", "powerpoint", "analytical skills", "ms office"], "soft_skills": ["communication skills", "well organized", "analytical skills"], "languages_combined": [{"language": "japanese", "language_level": []}, {"language": "english", "language_level": ["good command"]}, {"language": "mandarin", "language_level": ["good command"]}]}, "experience_required": {"duration": ["3 years"], "field": ["relevant experience", "trading"]}}, {"job_id": "100003009048057", "location_code": "hk", "company": "The Hang Seng University of Hong Kong", "job_title": "Procurement Manager \u2013 Finance Office  (Ref: PM (FO) 2022-01-14)", "description": "Key Responsibilities :\n\nOversee the operations of packaging team.\nEnsure the packaging projects can be structurally organized and prioritize according to the requirements.\nDevelop and establish a project milestone controlling, and report to management.\nCoordinate projects regarding the improvement or revision of the packaging of assortment items.\nLead the vendor performance management program. Analyse supplier performance and communicate the findings and potential risks to the management and the stakeholders.\nInitiate the continuous development, implementation and improvement of daily processes in the packaging department e.g. artwork check, packaging development and packaging optimization.\nDocument packaging processes and create work instructions.\nConduct trainings for internal and external stakeholders on the REWE packaging processes.\nJob Requirements\u00a0:\n\nAt least 5 years of related professional experience, preferably in a purchasing / sourcing office or in the packaging industry.\nGood knowhow of packaging development process.\nWith solid track records in leading packaging re-launch or improvement projects.\nAbility to work in cross-cultural environment and liaise with internal and external stakeholders.\nGood command of written & spoken English and Chinese (Cantonese & Putonghua).\nKnowledge of German is an advantage.\nProficiency in MS Office.\n\nIf you are interested in the position, please submit your full resume with cover letter, current and expected salary and available date via JobsDB.\n\nAll personal information is collected for recruitment purpose only and will be treated in strict confidentiality.", "employment_types": ["Full Time", "Permanent"], "selling_points": [], "locations": ["Not Specified"], "categories": ["Manufacturing", "Manufacturing Management", "Merchandising & Purchasing", "Others", "Procurement / Purchasing / Sourcing"], "post_time": "2022-01-14T11:52:34Z", "salary": {"currency": null, "max": null, "min": null, "period": "monthly", "term": null}, "salary_visible": false, "title_keywords": ["manager"], "responsibilities": ["management", "operations", "implementation", "develop", "coordinate", "analyse", "report"], "requirements": {"degrees": [], "majors": [], "languages": ["german", "cantonese", "english", "putonghua", "chinese"], "language_level": ["advantage", "good command"], "hard_skills": ["ms office"], "soft_skills": ["interested in"], "languages_combined": [{"language": "german", "language_level": ["advantage"]}, {"language": "cantonese", "language_level": ["good command"]}, {"language": "english", "language_level": ["good command"]}, {"language": "putonghua", "language_level": ["good command"]}, {"language": "chinese", "language_level": ["good command"]}]}, "experience_required": {"duration": ["at least 5 years"], "field": ["related", "purchasing"]}}, {"job_id": "100003009055771", "location_code": "hk", "company": "ConnectedGroup Limited", "job_title": "Merchandiser- Food", "description": "Duties\n\nSupport the Operations in matching supply & demand of the project material-wise;\nHandle material sourcing & vendor selection of construction materials;\nProcess quotation comparison / analysis, conduct price negotiation and make recommendation;\nPrepare procurement contract document, purchase order etc;\nManage in-house purchasing system;\nPrepare monthly reports & inventory control, work closely with internal parties to keep track & monitor inventory movement & purchasing needs;\nInvolve in the tendering & planning process;\nAd hoc duties as assigned.\n\n\u00a0Requirements\n\nCertificate in Purchasing & Supply Chain Management or Construction related discipline is preferred;\n3 years solid purchasing experience in construction industry;\nExperience in managing in-house purchasing system;\nGood problem-solving, negotiating, organization, interpersonal & communication skills;\nMature, independent, integrity, proactive, co-operative and positive working attitude;\nA strong team player and able to work under pressure;\nAbility to multi-task & prioritize with minimum supervision;\nProficient in MS Office (Word & Excel)\nGood command of written and spoken English and Chinese.\n\n\n\nInterested parties please send your full resume with date available, present & expected salary by clicking \"Apply Now\".\n\n\nPersonal data will be used for recruitment purpose only.", "employment_types": ["Full Time", "Permanent"], "selling_points": ["Well-established buying office", "Food experience is preferred", "Attractive Remuneration Package"], "locations": ["Not Specified"], "categories": ["Merchandising & Purchasing", "Others", "Procurement / Purchasing / Sourcing"], "post_time": "2022-01-18T02:55:57Z", "salary": {"currency": null, "max": null, "min": null, "period": "monthly", "term": null}, "salary_visible": false, "title_keywords": ["merchandiser"], "responsibilities": ["ad hoc duties", "price negotiation", "make recommendation", "monthly reports", "operations", "analysis", "quotation", "monitor", "inventory", "tendering", "planning process", "purchase", "inventory control", "internal parties"], "requirements": {"degrees": ["certificate"], "majors": [], "languages": ["english", "chinese"], "language_level": ["good command"], "hard_skills": ["excel", "problem-solving", "word", "ms office"], "soft_skills": ["communication skills", "independent", "multi-task", "problem-solving", "integrity", "mature", "prioritize", "positive working attitude", "team player", "proactive", "interpersonal", "work under pressure"], "languages_combined": [{"language": "english", "language_level": ["good command"]}, {"language": "chinese", "language_level": ["good command"]}]}, "experience_required": {"duration": ["3 years"], "field": ["purchasing", "construction industry"]}}, {"job_id": "100003009052394", "location_code": "hk", "company": "Hong Kong Huafa Investment Holdings Limited", "job_title": "International Trade Supervisor \u570b\u969b\u8cbf\u6613\u4e3b\u4efb", "description": "Responsibilities:\n\nProactively work with user departments to analyze and identify business needs, issues, market situation and recommendations\nConduct market research and sourcing activities\nDevelop the most appropriate procurement and contract strategies for the procurement of IT hardware, software, telecom and turnkey projects\nSupervise Senior Officers to ensure effective implementation of procurement strategies for the low to medium value purchases\nImplement the procurement activities which are fully compliant with corporate procurement policy and procedures\nSupport as team member in cross functional team on tender assessment\nLiaise with stakeholders for the preparation of tender and contract documents\nManage the relationship among suppliers and users, and provide support to enhance supplier management system\nSupport initiatives for streamlining procurement process for continuous improvement\n\nRequirements:\n\nBachelor's degree and / or relevant professional qualifications in Procurement, Business Administration or related disciplines with preference to master degree level\nProfessional qualification on procurement is preferred\nA minimum of 6 years' relevant working experience, preferably in public organizations and IT procurement field, with at least 2 years' experience at supervisory level\nGood understanding and experience in handling World Trade Organization (WTO) / Agreement on Government Procurement (GPA) tender would be an advantage\nKnowledge in using ERP system e.g. Oracle Financial/ Procurement System would be an advantage\nProficient in MS Office application\nGood communication and influencing skills\nStrong interpersonal and analysis skills\nProactive, high level of integrity, good team spirit and able to work under pressure\nExcellent spoken and written English and Chinese. Proficiency in Putonghua is an advantage", "employment_types": ["Full Time", "Permanent"], "selling_points": ["Support International Trade Team", "Negotiating trade details", "Maintain good relations with trading partners"], "locations": ["Central"], "categories": ["Banking / Finance", "Dealing & Trading", "Sales, CS & Business Devpt", "Business Development", "Merchandising & Purchasing", "Procurement / Purchasing / Sourcing"], "post_time": "2022-01-17T02:56:21Z", "salary": {"currency": null, "max": null, "min": null, "period": "monthly", "term": null}, "salary_visible": false, "title_keywords": ["supervisor"], "responsibilities": ["provide support", "management", "software", "conduct market research", "procedures", "implementation", "develop", "hardware", "tender", "liaise with"], "requirements": {"degrees": ["degree", "bachelor", "master degree"], "majors": ["related disciplines", "business administration"], "languages": ["putonghua", "english", "chinese"], "language_level": ["advantage", "excellent", "proficiency"], "hard_skills": ["oracle", "professional qualifications", "analysis", "erp system", "ms office"], "soft_skills": ["team spirit", "integrity", "communication", "proactive", "interpersonal", "work under pressure"], "languages_combined": [{"language": "putonghua", "language_level": ["proficiency", "advantage"]}, {"language": "english", "language_level": ["excellent"]}, {"language": "chinese", "language_level": ["excellent"]}]}, "experience_required": {"duration": ["at least 2 years", "minimum of 6 years"], "field": ["procurement", "it", "supervisory level", "relevant working experience"]}}, {"job_id": "100003009049512", "location_code": "hk", "company": "Walters People (HK)", "job_title": "Procurement Specialist (HK$ 35k)", "description": "(Ref: PM (FO) 2022-01-14)\n\nResponsibilities:\nlead the Procurement Team to manage the purchasing functions of the University, outsourced on-campus catering services and business services including general insurance, office supplies and appointed travel agents for business trips;\ndevelop effective procurement and sourcing strategies and formulate cost-saving initiatives;\nformulate, review and implement policies and procedures on procurement for continuous improvement;\nmanage the procurement activities and obtain the best value-for-money options in all aspects of goods and services required for the University\u2019s operation and resolve any contractual disputes;\nliaise with the service providers of on-campus catering outlets on service quality, environment and hygiene, and pricing matters; and\nmanage and regularly review the general insurance arrangement with the appointed insurance broker to ensure adequate coverage for risk mitigation.\n\nApplicants should:\npossess a bachelor\u2019s degree or above in Procurement, Business Administration, or related disciplines, preferably with professional qualifications (e.g. CIPS or equivalent);\nhave at least 10 years\u2019 relevant work experience in sizeable organisations, of which at least 5 years should be at managerial level;\npossess solid experience and knowledge in the procurement process and contract management;\npossess good leadership and interpersonal skills to work effectively with requisition units, suppliers and other teams of the Finance Office;\nhave business acumen, strong communication, presentation and problem-solving skills and be able to perform tasks of great diversity requiring considerable independent analysis and evaluation; and\nhave good command of written and spoken English and Chinese.\nApplicants with work experience in the higher education sector / public sector will be an advantage.\n\n\nSalary will be commensurate with qualifications and experience.\u00a0 Interested applicant should visit this link https://recruit.hsu.edu.hk/ and apply on or before 30 January 2022.\u00a0 The University reserves the right not to fill the position in this exercise.\nApplicants who are not invited to an interview within three months may consider their applications unsuccessful.\u00a0 All information received will be treated in strict confidence, and the data collected will be used for recruitment purposes only.\u00a0 The Personal Information Collection Statement will be provided upon request.\nThe Hang Seng University of Hong Kong, incorporated in Hong Kong with limited liability by guarantee, is an equal opportunity employer.", "employment_types": ["Full Time", "Permanent"], "selling_points": ["Asia based hospitality group", "Central procurement", "Competitive remuneration package"], "locations": ["Not Specified"], "categories": ["Hospitality / F & B", "Hospitality / Hotel Services", "Marketing / Public Relations", "Marketing - Brand / Product Management", "Merchandising & Purchasing", "Procurement / Purchasing / Sourcing"], "post_time": "2022-01-14T08:47:02Z", "salary": {"currency": "HKD", "max": 34999, "min": 30000, "period": "monthly", "term": null}, "salary_visible": true, "title_keywords": ["specialist"], "responsibilities": ["data", "quality", "communication", "evaluation", "liaise with", "administration", "teams", "develop", "cost", "office supplies", "review", "procedures", "hygiene", "policies", "analysis", "contract management", "recruitment", "insurance", "catering"], "requirements": {"degrees": ["degree or above", "bachelor"], "majors": ["related disciplines", "business administration"], "languages": ["english", "chinese"], "language_level": ["good command"], "hard_skills": ["problem-solving skills", "analysis", "acumen", "professional qualifications"], "soft_skills": ["work effectively", "confidence", "independent", "communication", "interpersonal skills", "business acumen", "problem-solving skills", "leadership", "presentation"], "languages_combined": [{"language": "english", "language_level": ["good command"]}, {"language": "chinese", "language_level": ["good command"]}]}, "experience_required": {"duration": ["at least 10 years", "at least 5 years"], "field": ["managerial", "management", "procurement", "education"]}}, {"job_id": "100003009051777", "location_code": "hk", "company": "Citistore (Hong Kong) Limited", "job_title": "Merchandising Assistant", "description": "Our Client is a Well-established buying office, they are looking for a Merchandiser to join their expanding team.\n\nKey Job Responsibilities include:\n\n\n\nResponsible for the whole merchandising process and ensure products meet customers' requirements\nResponsible for order follow-up, sampling, product development, price negotiations, quality control, and shipments, etc.\nWork closely with internal parties to ensure production schedules are aligned with company strategy.\nWork closely with the quality team and ensure products meet QA requirements\nMaintain & update product record to prepare related documents\nMaintain strong business relationships with supplier for product development and production\n\n\nOther requirements include:\n\nTertiary education with a minimum of 2 years experience in merchandising, experience in food and near food items\nExperienced in product and project development, follow up and negotiation\nGood communication skills, self-motivated, proactive, and open-minded\nExcellent in English, Cantonese, and Mandarin, both spoken and written\nTravel if necessary", "employment_types": ["Full Time", "Permanent"], "selling_points": ["Degree holder in related discipline", "Administrative support to merchandising team", "Immediate available is preferred"], "locations": ["Tsuen Wan Area"], "categories": ["Merchandising & Purchasing", "Sundries", "Others", "Procurement / Purchasing / Sourcing"], "post_time": "2022-01-17T01:03:24Z", "salary": {"currency": null, "max": null, "min": null, "period": "monthly", "term": null}, "salary_visible": false, "title_keywords": ["merchandising assistant"], "responsibilities": ["schedules", "related documents", "merchandising", "quality", "maintain", "quality control", "internal parties"], "requirements": {"degrees": [], "majors": [], "languages": ["cantonese", "english", "mandarin"], "language_level": ["excellent"], "hard_skills": [], "soft_skills": ["communication skills", "self-motivated", "negotiation", "open-minded", "proactive"], "languages_combined": [{"language": "cantonese", "language_level": ["excellent"]}, {"language": "english", "language_level": ["excellent"]}, {"language": "mandarin", "language_level": ["excellent"]}]}, "experience_required": {"duration": ["minimum of 2 years"], "field": ["food", "merchandising", "education"]}}, {"job_id": "100003009050816", "location_code": "hk", "company": "Health and Happiness (H&H) Hong Kong Limited", "job_title": "Senior Procurement Specialist (FMCG)", "description": "\u5de5\u4f5c\u8077\u8cac\n\n\u5354\u52a9\u90e8\u9580\u843d\u5be6\u5e74\u5ea6\u71df\u696d\u984d\u3001\u5229\u6f64\u6307\u6a19\u7b49\u7684\u7d93\u71df\u6307\u6a19\n\u8ca0\u8cac\u8cbf\u6613\u5168\u6d41\u7a0b\u64cd\u4f5c\uff0c\u5305\u62ec\u78ba\u5b9a\u8cbf\u6613\u8a73\u60c5\u3001\u8349\u64ec\u8cbf\u6613\u5408\u540c\u3001\u63d0\u4ea4\u5167\u90e8\u5be9\u6279\u3001\u76e3\u7763\u8cbf\u6613\u843d\u5be6\u60c5\u6cc1\u7b49\n\u8207\u8cbf\u6613\u5925\u4f34\u53ca\u5176\u4ed6\u5167\u5916\u90e8\u55ae\u4f4d\u7dad\u6301\u826f\u597d\u7684\u5408\u4f5c\u95dc\u4fc2\n\u8ca0\u8cac\u90e8\u9580\u7684\u6587\u6a94\u7ba1\u7406\u5de5\u4f5c\n\u5b8c\u6210\u4e0a\u7d1a\u4ea4\u8fa6\u7684\u5176\u5b83\u5de5\u4f5c\n\u4efb\u8077\u8cc7\u683c\n\n\u5927\u5b78\u672c\u79d1\u6216\u4ee5\u4e0a\u5b78\u6b77\uff0c\u4fee\u8b80\u570b\u969b\u8cbf\u6613\u3001\u5546\u696d\u3001\u7d93\u6fdf\u6216\u76f8\u95dc\u5c08\u696d\n2\u5e74\u6216\u4ee5\u4e0a\u76f8\u95dc\u5de5\u4f5c\u7d93\u9a57\uff0c\u66fe\u5f9e\u4e8b\u570b\u969b\u8cbf\u6613\u3001\u5927\u5b97\u5546\u54c1\u8cbf\u6613\u3001\u9280\u884c\u7d50\u69cb\u6027\u878d\u8cc7\u5de5\u4f5c\u512a\u5148\uff0c\u5177\u5099\u570b\u6709\u4f01\u696d\uff0f\u4e2d\u8cc7\u4f01\u696d\u5de5\u4f5c\u7d93\u9a57\u8005\u512a\u5148\n\u826f\u597d\u7684\u5546\u696d\u982d\u8166\u548c\u5206\u6790\u80fd\u529b\n\u7cb5\u8a9e\u3001\u666e\u901a\u8a71\u6d41\u5229\uff0c\u826f\u597d\u7684\u4e2d\u82f1\u6587\u8b80\u5beb\u80fd\u529b\n\u6027\u683c\u7a4d\u6975\u4e3b\u52d5\uff0c\u5177\u8cac\u4efb\u5fc3\n\u5177\u5099\u826f\u597d\u7684\u6e9d\u901a\u3001\u8ac7\u5224\u3001\u5354\u8abf\u80fd\u529b\uff0c\u80fd\u5920\u540c\u6642\u8655\u7406\u591a\u9805\u4efb\u52d9\u4e26\u5728\u58d3\u529b\u4e0b\u5de5\u5b8c\u6210\u4f5c\uff0c\u5177\u5099\u826f\u597d\u7684\u8077\u696d\u9053\u5fb7\n\u80fd\u7d14\u719f\u64cd\u4f5cMicrosoft Office\u7b49\u7684\u8fa6\u516c\u8edf\u4ef6\nJob Description\n\nAssist in achieving the KPIs of the department, such as sales turnover, profit and other targets\nSupport the team in trade administration matters, such as negotiating trade details, drafting contracts, applying for internal approval, monitoring and implementation of trade, etc.\nMaintain good relations with trading partners and other related parties\nResponsible in administrative documentation and file management\nComplete other tasks as assigned\nJob Specification\n\nBachelor\u2019s degree in international trade, business, economics or other related fields\n2 years of relevant work experience in international trading, commodity trading and bank structured financing are preferred\nExposure to Chinese state-owned enterprises/ Chinese enterprises would be desirable\nProficient command of Chinese and English\nProactive and responsible character\nExcellent communication, negotiation and coordination skills. Be able to handle multiple tasks at the same time and complete work under pressure. With good professional ethics\nProficient to use Microsoft Office and other office software proficiently\nWe offer attractive remuneration package to the right candidates, including year-end double pay, discretionary bonus, allowances, group medical insurance, annual health check, and etc. Interested parties please apply directly by clicking \u201cApply Now\u201d.", "employment_types": ["Full Time", "Permanent"], "selling_points": ["International Procurement (FMCG)", "Manage Purchase Orders (Adult/Baby Nutrition)", "Excellent Excel & Good Language Skills"], "locations": ["Quarry Bay"], "categories": ["Transportation & Logistics", "Documentary Credit / Bills Processing", "Shipping", "Merchandising & Purchasing", "Procurement / Purchasing / Sourcing"], "post_time": "2022-01-15T03:51:14Z", "salary": {"currency": null, "max": null, "min": null, "period": "monthly", "term": null}, "salary_visible": false, "title_keywords": ["specialist"], "responsibilities": ["year-end", "software", "work under pressure", "contracts", "monitoring", "implementation", "communication", "other tasks", "maintain", "coordination", "documentation", "kpis", "insurance", "file management", "support the team", "administration"], "requirements": {"degrees": ["degree", "bachelor"], "majors": ["economics", "business"], "languages": ["english", "chinese"], "language_level": ["proficient"], "hard_skills": ["documentation", "office software", "microsoft office"], "soft_skills": ["proactive", "negotiation", "responsible", "coordination skills", "communication", "handle multiple tasks", "structured", "work under pressure"], "languages_combined": [{"language": "english", "language_level": ["proficient"]}, {"language": "chinese", "language_level": ["proficient"]}]}, "experience_required": {"duration": ["2 years"], "field": ["financing", "trading"]}}, {"job_id": "100003009055888", "location_code": "hk", "company": "Randstad Hong Kong Limited", "job_title": "Merchandise Assistant - Fresh Grad Welcome", "description": "Our client is one of the Asia based hospitality group, they are now looking for experienced talent to join their central procurement team.\n\nJob responsibilities\n* Carry out wide range of procurement activities and provision of guidance to internal parties for purchasing flow\n* Oversee the entire tendering process, including framework agreement, post-delivery follow up and evaluation on services etc.\n* Facilitate team development and accomplish the new system launching and UAT\n* Manage and maintain a good relationship with vendor, contractors and internal stakeholders\n* Monitoring vendor's performance, make sure on time delivery and ensure product quality\n* Assist to Manager to carry out any procurement related matters\n\n\n\nJob requirements\n* Diploma or above in Supply Chain, Procurement or any related discipline\n* At least 7 years of central procurement experience in sizeable company, especially in hospitality is a plus\n* Strong interpersonal skill, team work and project management skill\n* Proficient in MS Office especially in Excel, e.g. Pivot table, Vlookup\nExcellent command of both written and spoken English", "employment_types": ["Full Time", "Permanent"], "selling_points": ["Fresh Grad Welcome", "US Sourcing Office", "Fortune 500 Company"], "locations": ["Not Specified"], "categories": ["Merchandising & Purchasing", "Others", "Procurement / Purchasing / Sourcing"], "post_time": "2022-01-18T03:03:18Z", "salary": {"currency": "HKD", "max": 19999, "min": 17000, "period": "monthly", "term": null}, "salary_visible": true, "title_keywords": ["assistant"], "responsibilities": ["guidance", "uat", "monitoring", "quality", "tendering", "good relationship", "maintain", "evaluation", "internal parties"], "requirements": {"degrees": ["diploma or above"], "majors": [], "languages": ["english"], "language_level": ["excellent"], "hard_skills": ["excel", "plus", "pivot table", "project management", "vlookup", "ms office"], "soft_skills": ["project management skill", "interpersonal skill"], "languages_combined": [{"language": "english", "language_level": ["excellent"]}]}, "experience_required": {"duration": ["at least 7 years"], "field": ["procurement"]}}, {"job_id": "100003009051455", "location_code": "hk", "company": "Honour Century International Limited", "job_title": "Sales Coordinator", "description": "KEY RESPONSIBILITIES:\n\nContact supplier to consolidate product and promotion information\nHandle price and promotion setup\nPrepare sales report and work out presentation file\nProvide general administrative support to the team\nAssist in ad-hoc duties as per assigned\n\n\u00a0JOB REQUIREMENTS:\n\nBachelor\u2019s Degree holder or above\nAt least 1 year of retail buying experience\nSelf-motivated, energetic, well-organized and able to work under pressure\nGood communication skills and good command of spoken & written English and Chinese\nProficiency in PC knowledge; familiar with Excel & Chinese Word\nImmediate available is highly preferred\n\nAn attractive remuneration package together with fringe benefits will be offered to the right candidate.\u00a0\u00a0Interested parties are invited to send your full resume with current and expected salary\u00a0by clicking \"Apply Now\".\n\nPersonal data collected will be used for recruitment purpose only.", "employment_types": ["Full Time", "Permanent"], "selling_points": [], "locations": ["Kwun Tong"], "categories": ["Merchandising & Purchasing", "Procurement / Purchasing / Sourcing"], "post_time": "2022-01-16T21:50:27Z", "salary": {"currency": null, "max": null, "min": null, "period": "monthly", "term": null}, "salary_visible": false, "title_keywords": ["sales coordinator"], "responsibilities": ["general administrative support", "prepare sales", "contact", "ad-hoc duties", "setup", "report"], "requirements": {"degrees": ["bachelor", "degree holder"], "majors": [], "languages": ["english", "chinese"], "language_level": ["good command", "good"], "hard_skills": ["excel", "pc knowledge", "word"], "soft_skills": ["communication skills", "self-motivated", "well-organized", "energetic", "work under pressure"], "languages_combined": [{"language": "english", "language_level": ["good command", "good"]}, {"language": "chinese", "language_level": ["good command", "good"]}]}, "experience_required": {"duration": ["at least 1 year"], "field": ["retail"]}}, {"job_id": "100003009041176", "location_code": "hk", "company": "Mid Ocean Hong Kong Ltd", "job_title": "Procurement Officer (Promotional Products)", "description": "A bit about us\n\nHealth & Happiness (H&H) Group is a publicly traded company out of Hong Kong, with offices worldwide. Our vision is focused on premium nutrition and lifetime wellness. We have three business segments \u2013 Baby, Adult and Pet Nutrition and Care \u2013 supporting whole-family health and happiness across seven international brands. We care passionately about our customers and community and are looking for similar-minded people to join us!\n\nOn our journey to making a positive difference across the world, you will work with passionate people in an innovative and collaborative organisation as we inspire wellness through #PurposeLedCareers!\n\nAs an equal opportunity employer, we care deeply about creating an inclusive workplace where our team members feel valued, respected, and empowered.\n\nYour role within the team\n\nReporting to Associate Director - Procurement, the incumbent will have to manage Purchase Orders (POs) for global markets.\n\nKey responsibilities include:\n\nPrepare and issue purchase orders to overseas factories as well as managing each order shipment plans from creation to payment.\nEnsure execution of all regular procurement duties and administrative work.\nPrepare all the IC documents.\nManage all product and supplier data setup and updates in system.\nFollow up and analyze purchase order execution & completion.\nCheck supplier shipping documents and prepare related internal documents.\nLiaise with internal parties to make sure all specifications are communicated and received by Supplier.\nRegularly review supplier costing.\nPrepare and analyze supplier KPIs.\nDesired Skills and Experience\n\n\nTo make sure we are setting new starters up for success, we ask that you meet a few criteria relevant to the role to be considered for this opportunity:\n\n\u00a0Bachelor Degree in Supply Chain/Purchasing or equivalent.\n\u00a0At least 2-3 years relevant experience from FMCG industry.\n\u00a0Familiar with international trading\n\u00a0Detail minded, strong analytical and organizational skills\n\u00a0Excellent knowledge of MS Excel, preferably knowledge of Oracle and AX order processing\n\u00a0Good presentation and report writing skills\u00a0\n\u00a0Ability to work in a diversified culture environment.\n\u00a0Fluent in spoken English and Mandarin.\n\nH&H Group believes in the benefits of a diverse and inclusive workplace and aims to reflect the varied cultures within which we exist. We are committed to providing a working environment that is free from discrimination and harassment, creating a safe and inclusive environment for all.\n\nWe encourage applications from people of all ages, nationalities, religions, racial and gender identities, sexual orientations, abilities and cultures, and our hiring decisions will be based on business needs, position requirements, and the qualifications and experience of individuals.\u00a0 If you require support or assistance during the application process, please notify us at the time of application and we will be sure to enable reasonable adjustments where suitable.\n\nIf you have what it takes, please apply via the online portal and we will be in touch soon. We move quickly and may fill the role prior to the application close date, so we suggest you get in touch today!\n\nSalary and benefits will be competitive and commensurate with experience.\u00a0 All personal data collected is for recruitment purposes only.", "employment_types": ["Full Time", "Permanent"], "selling_points": ["Good command in English and Mandarin", "2 years relevant experience", "Salary negotiable ; 5 days working ; double pay"], "locations": ["Lai Chi Kok"], "categories": ["Merchandising & Purchasing", "Sundries", "Others", "Procurement / Purchasing / Sourcing"], "post_time": "2022-01-13T05:33:57Z", "salary": {"currency": null, "max": null, "min": null, "period": "monthly", "term": null}, "salary_visible": false, "title_keywords": ["procurement officer"], "responsibilities": ["shipping documents", "reporting", "administrative work", "data", "review", "purchase", "payment", "specifications", "internal parties", "kpis", "liaise with", "plans", "order processing", "setup", "report"], "requirements": {"degrees": ["degree", "bachelor"], "majors": [], "languages": ["english", "mandarin"], "language_level": ["fluent"], "hard_skills": ["pos", "fmcg industry", "writing skills", "make", "ms excel", "order processing", "oracle"], "soft_skills": ["passionate", "organizational skills", "focused", "collaborative", "writing skills", "organisation", "innovative", "presentation", "positive"], "languages_combined": [{"language": "english", "language_level": ["fluent"]}, {"language": "mandarin", "language_level": ["fluent"]}]}, "experience_required": {"duration": ["at least 2-3 years"], "field": ["fmcg", "relevant experience"]}}, {"job_id": "100003009056200", "location_code": "hk", "company": "ME Job Personnel Limited", "job_title": "Merchandiser & Senior Merchandiser  (Label / Packaging )", "description": "about the company.\n\nOur client is a well-known US Sourcing Office with a fun and dynamic working culture. They have over 300,000 employees over the world and 5,000 stores in their portfolio. With their growing business, they are looking for an Merchandising Assistant for their Home team. Fluency in English is a must. Fresh Grad welcome.\nabout the job.\nMananage the assigned category through precise executive of process\nFollow up orders with suppliers/ factories to ensure on-time delivery\nProvide support in sample handling, prepare the quotation for buyer evaluation\nMaintain strong business partnership with suppliers\nProvide support to team leader\nskills & experiences required.\nUniversity graduate in Merchandising, Business or related discipline\nSmart, motivated and independent\nExcellent communication and interpersonal skills\nGood command of English Cantonese and Mandarin\nabout the package.\n\n5 days work\nMedical and Dental\nDiscretionary Bonus\nFast Track Promotion\nIf you're interested in this role, click 'apply now' or email cecilia.ng@randstad.com.hk to forward an up-to-date copy of your CV, or call Cecilia NG at 2232 3444. If this is not your ideal job but you are looking out, please contact us for a discussion on your career preferences.", "employment_types": ["Full Time"], "selling_points": [], "locations": ["Kwai Tsing Area"], "categories": ["Merchandising & Purchasing", "Sundries", "Others", "Procurement / Purchasing / Sourcing"], "post_time": "2022-01-18T03:32:01Z", "salary": {"currency": null, "max": null, "min": null, "period": "monthly", "term": null}, "salary_visible": false, "title_keywords": ["merchandiser", "senior merchandiser"], "responsibilities": ["follow up orders", "provide support", "quotation", "merchandising", "communication", "business partnership", "maintain", "contact", "evaluation"], "requirements": {"degrees": ["university graduate"], "majors": ["business"], "languages": ["cantonese", "english", "mandarin"], "language_level": ["fluency", "good command"], "hard_skills": ["dynamic", "fun"], "soft_skills": ["independent", "interested in", "dynamic", "motivated", "communication and interpersonal skills", "precise", "ideal"], "languages_combined": [{"language": "cantonese", "language_level": ["good command"]}, {"language": "english", "language_level": ["fluency", "good command"]}, {"language": "mandarin", "language_level": ["good command"]}]}, "experience_required": {"duration": [], "field": []}}, {"job_id": "100003009044548", "location_code": "hk", "company": "Owlsome Limited", "job_title": "Procurement Officer / Assistant", "description": "Requirements\n\nFluent English and Mandarin is a MUST.\nExcellent communication and interpersonal skills.\nPatience and attentive listening.\nProficiency in MS Office, ERP System, Chinese and English typing.\nDegree holder or 2 years merchandising experience is an advantage.\nResponsibilities\n\nManage and follow through merchandising activities (create & review product briefs, price negotiation, project coordination, sample & production delivery/ quality control).\nInventory control & support logistic functions.\nMonitor Sales & Purchase Orders with proper tracking, filing and documentation.", "employment_types": ["Full Time", "Permanent"], "selling_points": [], "locations": ["Admiralty"], "categories": ["Admin & HR", "Personal / Executive Assistant", "Hospitality / F & B", "Food & Beverage", "Merchandising & Purchasing", "Procurement / Purchasing / Sourcing"], "post_time": "2022-01-13T04:32:19Z", "salary": {"currency": null, "max": null, "min": null, "period": "monthly", "term": null}, "salary_visible": false, "title_keywords": ["procurement officer", "assistant"], "responsibilities": ["price negotiation", "project coordination", "review", "merchandising", "monitor", "purchase", "inventory control", "quality control", "documentation", "tracking"], "requirements": {"degrees": ["degree holder"], "majors": [], "languages": ["english", "chinese", "mandarin"], "language_level": ["proficiency", "fluent"], "hard_skills": ["erp system", "typing", "ms office"], "soft_skills": ["attentive", "communication and interpersonal skills", "patience"], "languages_combined": [{"language": "english", "language_level": ["fluent", "proficiency"]}, {"language": "chinese", "language_level": ["proficiency"]}, {"language": "mandarin", "language_level": ["fluent"]}]}, "experience_required": {"duration": ["2 years"], "field": ["merchandising"]}}, {"job_id": "100003009051967", "location_code": "hk", "company": "The Great Eagle Group of Companies", "job_title": "Analyst Programmer / Senior Analyst Programmer", "description": "About Our Client\n\nOur client is a leading apparel and home fashion retailer with over 4,000 store and supports online shopping. Due to business expansion plan, they are looking for a Sourcing Manager for apparel team in Hong Kong office.\n\n\nJob Duties\n\nManage and follow all activities of possible sourcing units, and monitor the workload with different functional teams\nLiaise and work with different functional teams in headquarter, and monitor and communicate with external stakeholders\nDecision making on processes and procedures in merchandising, sourcing and logistics areas\nSupervise and prepare foreign trips of staff with foreign and resident buyers for vendors, buying and fair visit\nRemain in constant contact with external management to obtain information on strategies and development projects, sales data on merchandise and market conditions that impact sourcing decisions\nResearch and analyze the market trend with recommendation, proposals, attend trade shows and coordinate with external buyer to investigate market opportunities and evaluate the best source of products\nHandle all order process activities and resolve problems with manufacturers to ensure the order standards are met\nSpot check and make recommendations on vendor warehouse and factories to ensure the quality and production requirements are met\nReview the potential new vendors and factories to ensure the standards and requirements for Social Compliance and Cargo Security Programs are met\n\nRequirement\n\nDegree holder or above in sourcing and production or related disciplines\nAt least 6 years of experience in buying office or agent to U.S., Canada, or UK markets\nProven relevant experience in woven or sweater is a must\nConcrete experience in continuous improvement projects or related process enhancement ability is preferable\nFluent communication in English and Chinese\nProficient in MS Office and related system is preferable\n\nClick \"Apply Now\" to apply for this position or call Sandy Chan at +852 3180 4951 for a confidential discussion. All information collected will be kept in strict confidence and will be used for recruitment purpose only.", "employment_types": ["Full Time", "Permanent"], "selling_points": ["Hands-on for system implementation", "Support for ERP system", "5 days work, 12AL"], "locations": ["Wan Chai"], "categories": ["Information Technology (IT)", "Application Specialist - Software", "Software Development", "Merchandising & Purchasing", "Procurement / Purchasing / Sourcing"], "post_time": "2022-01-17T01:40:17Z", "salary": {"currency": null, "max": null, "min": null, "period": "monthly", "term": null}, "salary_visible": false, "title_keywords": ["analyst programmer", "senior analyst programmer"], "responsibilities": ["liaise", "communicate with", "management", "make recommendations", "data", "review", "teams", "monitor", "procedures", "merchandising", "coordinate with", "evaluate", "quality", "compliance", "logistics", "contact"], "requirements": {"degrees": ["degree holder"], "majors": ["related disciplines"], "languages": ["english", "chinese"], "language_level": ["fluent"], "hard_skills": ["ms office"], "soft_skills": ["communication", "confidence"], "languages_combined": [{"language": "english", "language_level": ["fluent"]}, {"language": "chinese", "language_level": ["fluent"]}]}, "experience_required": {"duration": ["at least 6 years"], "field": ["related", "relevant experience"]}}, {"job_id": "100003009048952", "location_code": "hk", "company": "Find Asia Limited", "job_title": "Procurement Manager (Electronics)", "description": "Responsibilities:\n\nHands-on for system implementation, development, maintenance, testing, training and enhancement of business application in SDLC\nPerform requirement / feasibility study and analysis and provide technical advice\nWork closely with team and business users to ensure technical compatibility and user satisfaction\nAssist team leader to collaborate with peers for tasks required in various system development tasks if required\nPrepare application support for ERP system\nAssist in preparing project documents and system specifications\nHandle ad hoc assignment as required\n\nRequirements:\n\nDegree holder in Computer Science, Information Technology or related disciplines\nMinimum 3 years\u2019 relevant experience\nSolid experience in ASP.NET / C#, JAVA, report development and MS-SQL\nExperience in ERP, CRM, HR or property management system is an advantage\nHand-on experience in mobile application development is an advantage\nA good team player, independent, self-motivated, able to work independently and under pressure\nGood communication, interpersonal, analytical and problem-solving skill\nGood command of spoken and report writing skill in English and Chinese\nCandidates with more experience will be considered as Senior Analyst Programmer\n\nSalary and benefits will be commensurate with qualifications and experience.\u00a0 Interested parties, please send a full resume with present and expected salary, and date available to The Human Resources Department, 32/F., Great Eagle Centre, 23 Harbour Road, Wanchai, Hong Kong or e-mail to us.\u00a0\u00a0\u00a0(Please quote the reference no. on the envelope and the covering letter.)\n\nTo know more about us, please visit our website at http://www.greateagle.com.hk.\n\nWe are an equal opportunity employer and welcome applications from all qualified candidates.\n\nPersonal data collected will be treated in strict confidence and used only for recruitment-related purpose. Applicants who have not heard from us within four weeks may consider their applications unsuccessful. All personal data will be destroyed after 12 months.", "employment_types": ["Full Time", "Permanent"], "selling_points": ["Japanese electronics components manufacturing", "procurement, purchasing", "5 days, Double Pay, Bonus"], "locations": ["Tsuen Wan Area"], "categories": ["Manufacturing", "Manufacturing Management", "Product Development / Management", "Merchandising & Purchasing", "Procurement / Purchasing / Sourcing"], "post_time": "2022-01-15T03:50:06Z", "salary": {"currency": null, "max": null, "min": null, "period": "monthly", "term": null}, "salary_visible": false, "title_keywords": ["manager"], "responsibilities": ["collaborate with", "maintenance", "analysis", "technical advice", "ad hoc assignment", "implementation", "testing", "project documents", "specifications"], "requirements": {"degrees": ["degree holder"], "majors": ["related disciplines", "computer science", "information technology"], "languages": ["english", "chinese"], "language_level": ["good command"], "hard_skills": ["java", "problem-solving", "erp", "writing skill", "mobile", "ms-sql", "c#"], "soft_skills": ["good team player", "work independently", "under pressure", "independent", "self-motivated", "problem-solving", "writing skill", "communication", "interpersonal"], "languages_combined": [{"language": "english", "language_level": ["good command"]}, {"language": "chinese", "language_level": ["good command"]}]}, "experience_required": {"duration": ["minimum 3 years"], "field": ["hr", "relevant experience", "management", "application development"]}}, {"job_id": "100003009048791", "location_code": "hk", "company": "SAE Magnetics (Hong Kong) Ltd", "job_title": "Buyer", "description": "Our client, a Japanese electronics component company is looking for the candidate with the following details\n\nDuties\n\nUnderstand the needs and the workflow of the procurement processing\u00a0\nProcurement planning, research and analysis of the parts and finished goods production\u00a0\n\nReview the shipment schedule, monitor the delivery and shipment schedule\u00a0\nSupervise and control the production manufacturing, scheduling and operation\u00a0\nPO approval and shipment schedule review\u00a0\nProduct planning, re-modifying and market research to enhancement the product functions fit in different markets\u00a0\n\nRequirements\n\nUniversity graduate and with procurement/ purchasing/ SCM experience\nFluent English and Mandarin\nWith supervision and solid experience in procurement, production planning, good understand of product cycle, delivery processing\nExperience in project Management, processing review, industrial engineering review of production procedure\nGood sense of figure for data analysis\nGood knowledge of ISO 9001, 14001 and with knowledge/ experience working with compliance team\u00a0\nIndependent, persuasive and self-motivated", "employment_types": ["Full Time", "Permanent"], "selling_points": ["Execute and monitor regular purchasing duties", "Working Location: HK Science Park, Shatin", "5-day work; Double Pay; Incentive Bonus; 12-19 AL"], "locations": ["Shatin Area"], "categories": ["Transportation & Logistics", "Supply Chain", "Merchandising & Purchasing", "Electronics", "Procurement / Purchasing / Sourcing"], "post_time": "2022-01-15T03:50:04Z", "salary": {"currency": null, "max": null, "min": null, "period": "monthly", "term": null}, "salary_visible": false, "title_keywords": [], "responsibilities": ["control", "analysis", "review", "monitor", "market research", "scheduling", "schedule", "planning"], "requirements": {"degrees": ["university graduate"], "majors": [], "languages": ["english", "mandarin"], "language_level": ["fluent"], "hard_skills": ["project management", "analysis", "processing"], "soft_skills": ["project management", "self-motivated", "persuasive", "independent"], "languages_combined": [{"language": "english", "language_level": ["fluent"]}, {"language": "mandarin", "language_level": ["fluent"]}]}, "experience_required": {"duration": [], "field": ["engineering", "purchasing", "compliance", "project management", "team", "procurement", "planning"]}}, {"job_id": "100003009051979", "location_code": "hk", "company": "", "job_title": "Assistant Merchandiser", "description": "Responsibility\n- Execute regular purchasing duties, e.g. PO processing, price negotiation, vendor sourcing, etc.;\n- Co-ordinate with other departments and suppliers in the purchasing scope of work;\n- Monitor the service, quality, price, on-time delivery and reliability of the suppliers.\n- Perform other duties as assigned.\n\n\nRequirement\nAcademic Qualification: Bachelor Degree holder or above;\nField of Study: Logistic / Supply Chain Management / Manufacturing / Engineering / Business Administration or other relevant discipline;\nYears of Experience: 1 - 3 years of related working experience;\n*Fresh graduate will also be considered.\n- Knowledgeable and hands-on experience in SAP & MS Office.\n- Effective communication skill with good command of written and spoken English & Chinese.\n\nFringe Benefit\n- Double Pay;\n- Incentive Bonus;\n- 5-days Work;\n- 12-19 days annual leave;\n- Medical, Dental & Life Insurance Scheme.\n\nApplication Method\nInterested parties please click \"APPLY NOW\" or send your application with the title & expected salary to HK Human Resources via Application E-mail.\n\nAll personal data collected will be used for recruitment purpose only. Only short-listed candidates will be contacted for interview.", "employment_types": ["Full Time", "Permanent"], "selling_points": [], "locations": ["Hung Hom"], "categories": ["Merchandising & Purchasing", "Sundries", "Others", "Procurement / Purchasing / Sourcing"], "post_time": "2022-01-17T01:44:45Z", "salary": {"currency": null, "max": null, "min": null, "period": "monthly", "term": null}, "salary_visible": false, "title_keywords": ["assistant merchandiser"], "responsibilities": ["price negotiation", "perform other duties", "co-ordinate with", "quality", "monitor"], "requirements": {"degrees": ["fresh graduate", "bachelor degree holder"], "majors": [], "languages": ["english", "chinese"], "language_level": ["good command"], "hard_skills": ["scheme", "sap", "ms office"], "soft_skills": ["hands-on", "communication skill"], "languages_combined": [{"language": "english", "language_level": ["good command"]}, {"language": "chinese", "language_level": ["good command"]}]}, "experience_required": {"duration": ["1 - 3 years"], "field": ["related"]}}, {"job_id": "100003009047587", "location_code": "hk", "company": "Ocean Park Corporation", "job_title": "Senior Corporate Services Officer - Purchasing (Water World)", "description": "Lauris Walton is exclusively partnering with a fast growing multinational online accessories firm, and we have an opportunity for a Product Assistant based in Hong Kong. This role will play a key role in supporting the product team on the daily organization of files, researching for new suppliers, office administration and operation matters.\n\nKey responsibilities:\n\nProvided administration and operation support to product manager\u00a0 \u00a0\nCommunicate with suppliers on quality control and finding new factories\nPerform quality checks and ensure accuracy of the product\nMaintain database and order management system\nAssist in organizing team building activities in Hong Kong\u00a0\nHandle office expenses and other ad-hoc requests\nRole requirements:\u00a0\n\nFluent in English and Chinese (Cantonese and Mandarin)\nMinimum of 1 year of relevant work experience\nDetail minded, well organized, punctual\nPositive mindset with a can-do attitude\u00a0\nWorking location:\u00a0Central (Prime location, excellent work environment)\u00a0", "employment_types": ["Full Time", "Contract"], "selling_points": ["Handle procurement matters", "Conducting tender/quotation exercises", "Supplier management"], "locations": ["Aberdeen"], "categories": ["Merchandising & Purchasing", "Procurement / Purchasing / Sourcing"], "post_time": "2022-01-14T03:30:53Z", "salary": {"currency": null, "max": null, "min": null, "period": "monthly", "term": null}, "salary_visible": false, "title_keywords": ["senior corporate services officer"], "responsibilities": ["communicate with", "order management", "ad-hoc requests", "expenses", "quality", "maintain", "quality control", "database", "administration"], "requirements": {"degrees": [], "majors": [], "languages": ["cantonese", "english", "chinese", "mandarin"], "language_level": ["fluent"], "hard_skills": [], "soft_skills": ["can-do attitude", "well organized", "positive mindset"], "languages_combined": [{"language": "cantonese", "language_level": []}, {"language": "english", "language_level": ["fluent"]}, {"language": "chinese", "language_level": ["fluent"]}, {"language": "mandarin", "language_level": []}]}, "experience_required": {"duration": ["minimum of 1 year"], "field": []}}, {"job_id": "100003009054787", "location_code": "hk", "company": "Tristate Holdings Limited", "job_title": "Senior Merchandiser / Merchandiser (Woven Garment)", "description": "Responsibilities\n\nHandle day-to-day store enquires\nProcess store orders\nDevelop, implement, and maintain HK Group's related central procurement strategy, policy and procedures on food & beverage items, including but not limited to disposable & other non-food items and service & maintenance\nDrive awareness / compliance to adhere to such policies and procedures, through close collaboration and educating the internal customers and external vendors\nAchieve procurement efficiency while meeting Group\u2019s standard\nUtilize e-platform applications to drive optimum performance, efficiency and effectiveness\n\nRequirements\n\n1-2 years of solid & relevant procurement experience gained from sizable corporations in sourcing / purchasing / supply chain and F&B industry or similar capacity preferable\nFresh graduates will also be considered\nCandidate with more experience will be considered as Procurement Officer\nDiploma holder in Supply Chain Management, Procurement / Purchasing or Business Administration.\u00a0 Past experiences in F&B / Catering Industry will be an advantage\nStrong interpersonal and communication skills, well-organized with strong project management, self-motivated, good quality and working attitude, detailed minded, cost conscientious\nProficient in Microsoft software both in English and Chinese\nGood command of both written & spoken English and Chinese\n\n\n\nWe offer an attractive remuneration package and excellent career prospects to the right candidate.\n\nIf you are interested in joining us, please send your full resume with academic qualifications, work experience, availability, present and expected salary by clicking\u00a0APPLY NOW\u00a0button.\n\nCompass Group Hong Kong is an Equal Opportunities Employer. All applications and enquiries will be handled in the strictest confidence and personal data collected will be used for recruitment purposes only. All the applicant contact details will be kept for 6 months only.\n\nTo find out more about us, you are welcome to visit our website:\u00a0www.compass-hk.com", "employment_types": ["Full Time", "Permanent"], "selling_points": ["Outerwear, men's wear, woven garment", "5 years relevant experience or above", "5-day work, AL 13-20 days, medical, flexible hour"], "locations": ["Kwai Tsing Area"], "categories": ["Merchandising & Purchasing", "Woven / Knit", "Procurement / Purchasing / Sourcing"], "post_time": "2022-01-17T11:04:56Z", "salary": {"currency": null, "max": null, "min": null, "period": "monthly", "term": null}, "salary_visible": false, "title_keywords": ["merchandiser", "senior merchandiser"], "responsibilities": ["maintenance", "policies", "compliance", "procedures", "develop", "maintain"], "requirements": {"degrees": ["diploma holder"], "majors": ["business administration"], "languages": ["english", "chinese"], "language_level": ["good command", "proficient"], "hard_skills": ["project management"], "soft_skills": ["communication skills", "self-motivated", "well-organized", "project management", "conscientious", "interpersonal", "detailed"], "languages_combined": [{"language": "english", "language_level": ["proficient", "good command"]}, {"language": "chinese", "language_level": ["proficient", "good command"]}]}, "experience_required": {"duration": ["1-2 years"], "field": ["purchasing", "supply chain", "f&b", "procurement"]}}, {"job_id": "100003009054081", "location_code": "hk", "company": "TAL Apparel Limited", "job_title": "Merchandising Executive / Merchandiser (Senior)", "description": "Responsibilities\n\n(Long Term Contract)\n\n\nThe incumbent will handle procurement matters for supporting the operations of the Water World and the Ocean Park. Key responsibilities include sourcing, conducting tender/quotation exercises, contract negotiation and preparation, supplier management, performing compliance control of procurement activities and assume any other ad hoc duties as assigned.\n\nRequirements\n\n\u2022 Degree in Purchasing and Supply/ Business/ Logistics Management/ Hotel Management or equivalent\n\u2022 At least 5 years\u2019 relevant working experience in sizable organization, preferably in public body\n\u2022 Well-organized, work independent, self-motivated with good interpersonal skills and good team player\n\u2022 Ability to work on multiple projects and work under pressure\n\u2022 Good command of both spoken and written English and Cantonese\n\nApplications including details of qualifications, working experience, expected salary, contact telephone number and address should be applied via:\u00a0http://careers.oceanpark.com.hk\u00a0--> Job opening --> Full time/ Long-term.\n\nApplicants not contacted within six weeks may consider their application unsuccessful. Personal data collected will be used for recruitment-related purpose only.", "employment_types": ["Full Time", "Permanent"], "selling_points": ["Perform material sourcing & product development", "provide one-stop merchandising services to clients", "3-4 years relevant experience"], "locations": ["Yau Tsim Mong Area"], "categories": ["Merchandising & Purchasing", "Woven / Knit", "Procurement / Purchasing / Sourcing", "Sales, CS & Business Devpt", "Account Servicing"], "post_time": "2022-01-17T08:20:06Z", "salary": {"currency": null, "max": null, "min": null, "period": "monthly", "term": null}, "salary_visible": false, "title_keywords": ["merchandiser", "executive", "merchandising"], "responsibilities": ["ad hoc duties", "management", "control", "operations", "quotation", "compliance", "tender"], "requirements": {"degrees": ["degree"], "majors": ["hotel", "business"], "languages": ["cantonese", "english"], "language_level": ["good command"], "hard_skills": [], "soft_skills": ["good team player", "self-motivated", "independent", "well-organized", "interpersonal skills", "work under pressure"], "languages_combined": [{"language": "cantonese", "language_level": ["good command"]}, {"language": "english", "language_level": ["good command"]}]}, "experience_required": {"duration": ["at least 5 years"], "field": ["sizable organization", "relevant working experience"]}}, {"job_id": "100003009051066", "location_code": "hk", "company": "Aeon Stores (Hong Kong) Co Ltd", "job_title": "Assistant Buyer (Food / Cosmetics) (Ref.: JDB/AB)", "description": "Job Responsibilities :\u00a0\n\n\nFollow up merchandising order from development to production mainly on woven outerwear or men's wear for famous brand\nKeep track on the WIP and coordinating all product approval milestones, such as Fit, PP, Color Management, Submit Tracking, Approval Status, Risk Escalation.\nCoordinate with trims suppliers, fabric mills, other suppliers and factories to ensure on-time delivery on garment materials\u00a0\nDirectly work with overseas clients on development requirements and tackling with problems in production process and quality issues\nRequirements :\u00a0\n\nDiploma or above in Textile & Clothing Institute or related disciplines\n5 years or above relevant experience in merchandising for US/EU/UK Market \u00a0\nExperience in handling Outerwear and exposure of offshore production is an advantage\nWell organized, self-motivated and able to work in a fast paced and challenging environment\nGood team player with positive attitude\nGood communication in Cantonese, Mandarin and English\nProficiency in Microsoft Office\n\nWe offer competitive\u00a0remuneration package includes\u00a05-day work week,\u00a0bank holidays, flexible working hours, meal allowance, medical benefits, annual leave, marriage leave\u00a0to the right candidate.\u00a0 If you are interested, please send in your full resume listing your present, expected salary to Human Resources Department\u00a0:\u00a05/F, 66-72 Lei Muk Road, Kwai Chung, N.T. or by clicking \"Apply Now\"\n\nFor more company information, please visit our web-site at http://www.tristateww.com\n\n( All applications will be treated in strict confidential and we regret that only shortlisted candidates will be contacted )", "employment_types": ["Full Time", "Permanent"], "selling_points": ["Double Pay", "Discretionary Bonus", "Purchasing, negotiation, budget control"], "locations": ["Tsuen Wan Area"], "categories": ["Hospitality / F & B", "Food & Beverage", "Merchandising & Purchasing", "Procurement / Purchasing / Sourcing", "Sales, CS & Business Devpt", "Wholesale"], "post_time": "2022-01-15T01:41:26Z", "salary": {"currency": null, "max": null, "min": null, "period": "monthly", "term": null}, "salary_visible": false, "title_keywords": ["assistant"], "responsibilities": ["management", "production process", "coordinate with", "merchandising", "quality", "tracking"], "requirements": {"degrees": ["diploma or above"], "majors": ["related disciplines"], "languages": ["cantonese", "english", "mandarin"], "language_level": ["good"], "hard_skills": ["web", "microsoft office"], "soft_skills": ["flexible", "good team player", "self-motivated", "well organized", "positive attitude", "communication"], "languages_combined": [{"language": "cantonese", "language_level": ["good"]}, {"language": "english", "language_level": ["good"]}, {"language": "mandarin", "language_level": ["good"]}]}, "experience_required": {"duration": ["5 years"], "field": ["merchandising", "relevant experience"]}}, {"job_id": "100003009054926", "location_code": "hk", "company": "Apass International Hong Kong Company Limited", "job_title": "(Assistant) Merchandising Officer - FMCG / Food", "description": "We are looking for merchandising talents with apparel/garment background joining our TAL family. The incumbent shall provide one-stop merchandising services to designated customers.\n\n\nKey responsibilities\n\nDaily communicate with partnering departments, factories and customers on all merchandising issues\nPerform on-going material sourcing & product development for our customers by working with partnering departments\nProvide sales data for team\u2019s sales offer preparation\nProvide costings for responsible product categories and perform order checking\nPartner with factories\u2019 customer services team to prepare bulk order\nMonitor bulk production and handle quality control to ensure on-time delivery\nProvide after-sales services\nMaintain strong relationship with stakeholders by properly balancing interests of all parties\nImmediately available is highly preferred\nCandidate with less experience will be considered as Senior Executive.\n\nKey requirements\n\nDegree holder preferably in Fashion & Textile\n3-4 years relevant experience in merchandising, preferably in apparel & garment industry\nSound experience on costing preparation ,preferably Outerwear\nSensitive to numbers and good in mathematics\nStrong communication skills with good customer services manner\nGood team player with positive attitude\nAble to work under pressure and meet dead-lines\nGood PC knowledge in Word, Excel and PowerPoint\nExcellent command of English and Chinese (Cantonese and Putonghua)\nWilling to travel\n\nWe offer a 5-day working week, a competitive remuneration package and generous fringe benefits. Excellent on-the-job training and development will also be provided.\n\nTo apply, please send your full resume, including expected salary and availability, to Human Capital Management Department. Only shortlisted applicants will be contacted. All information will be kept in strict confidence and will be used for employment purpose only.", "employment_types": ["Full Time", "Permanent"], "selling_points": ["Established food discributor of many famous brands", "Great exposure-purchase, marketing & merchandising", "Dynamic Japanese culture & utilise language skill"], "locations": ["Others"], "categories": ["Transportation & Logistics", "Shipping", "Marketing / Public Relations", "Marketing - General / Support", "Merchandising & Purchasing", "Procurement / Purchasing / Sourcing"], "post_time": "2022-01-17T14:06:55Z", "salary": {"currency": null, "max": null, "min": null, "period": "monthly", "term": null}, "salary_visible": false, "title_keywords": ["officer", "merchandising", "assistant"], "responsibilities": ["product categories", "daily communicate", "data", "merchandising", "checking", "monitor", "customer services", "maintain", "quality control"], "requirements": {"degrees": ["degree holder"], "majors": [], "languages": ["cantonese", "putonghua", "english", "chinese"], "language_level": ["excellent"], "hard_skills": ["excel", "garment industry", "word", "powerpoint", "pc knowledge"], "soft_skills": ["communication skills", "good team player", "positive attitude", "sensitive to numbers", "work under pressure"], "languages_combined": [{"language": "cantonese", "language_level": ["excellent"]}, {"language": "putonghua", "language_level": ["excellent"]}, {"language": "english", "language_level": ["excellent"]}, {"language": "chinese", "language_level": ["excellent"]}]}, "experience_required": {"duration": ["3-4 years"], "field": ["garment", "merchandising", "relevant experience"]}}, {"job_id": "100003009054154", "location_code": "hk", "company": "aimHigher Consultancy Limited", "job_title": "Coffee Expert/ Master", "description": "Our\u00a0client is a well-established food distributor representing a number of prestigious Japanese FMCG/food brands and having good market share in Hong Kong.\u00a0\nIn line with their business development, they now require a responsible and detail-minded talent to join their team as Merchandising Officer.\u00a0 The caliber with less years of relavant working experiences will be considered as Assistant Merchandising Officer.\n\n\u00a0Responsibilities:\n\nHandle merchandising & sourcing matters, such as purchasing, suppliers, inventory;\nResponsible for logistics/warehouse operation and stock-take operation regularly;\nCoordinate in purchasing operation with Japan or overseas offices;\nHandle shipping cost calculation, quality control on products importing to Hong Kong;\nAssist in marketing events & regular stock operations\n\nRequirements:\n\nTertiary education in buying/purchasing or business relating discipline;\nAt least 5 years working experience in purchasing/product control, especially in Food & Beverage / Retailing industry;\nGood command in spoken English and Cantonese;\nExcellent language literacy (both spoken and written) in Japanese is highly preferable;\nProficient in MS Office, Sage Accpac knowledge an advantage;\nDetailed-minded and good problem solving skills with strong sense of responsibility", "employment_types": ["Full Time"], "selling_points": ["Expanding business", "Coffee lover", "Fun and energetic team"], "locations": ["Not Specified"], "categories": ["Manufacturing", "Product Development / Management", "Merchandising & Purchasing", "Procurement / Purchasing / Sourcing", "Quality Assurance, Control & Testing / ISO"], "post_time": "2022-01-17T08:35:38Z", "salary": {"currency": null, "max": null, "min": null, "period": "monthly", "term": null}, "salary_visible": false, "title_keywords": [], "responsibilities": ["marketing events", "cost", "shipping", "operations", "inventory", "merchandising", "coordinate", "logistics", "quality control"], "requirements": {"degrees": [], "majors": [], "languages": ["cantonese", "japanese", "english"], "language_level": ["excellent", "good command"], "hard_skills": ["accpac", "problem solving skills", "ms office"], "soft_skills": ["problem solving skills", "sense of responsibility", "detailed"], "languages_combined": [{"language": "cantonese", "language_level": ["good command"]}, {"language": "japanese", "language_level": ["excellent"]}, {"language": "english", "language_level": ["good command"]}]}, "experience_required": {"duration": ["at least 5 years"], "field": ["purchasing", "food"]}}, {"job_id": "100003009047068", "location_code": "hk", "company": "PCC Asia Limited", "job_title": "Purchasing Executive", "description": "Join us & Be eCommerce Innovators\n\n\nAre you looking to be part of revolutionizing online shopping behaviour and experience? We are a well-esteemed eCommcere company that operates multiple eCommerce websites internationally. We are now looking for potential talent to help us expand our new business worldwide.\n\nKey Job Responsibilities:\u00a0\n\nResponsible for Korean office purchase order follow up\nPrepare PI and PO, follow up with payment and shipment arrangement\nConsolidate and follow up with Korea Merchandising Team on all orderings from Hong Kong Team\nConsolidation of all Korean purchased goods and prepare paperwork to facilitate the export of goods from Korea\nCommunicate and coordinate with internal or external logistic parties to ensure smooth export process\nPerform other administrative support to Merchandising Team\nOther ad-hoc duties as assigned\n\nDesired Skills and Experience:\u00a0\n\nDiploma of above\u00a0 \u00a0 \u00a0 \u00a0 \u00a0\nMinimum 1-2 years or above working experience in merchandising or logistic experience under trading environment or buying office\nIndependent, well-organized, detailed minded, and able to manage multiple tasks\nGood command of written and spoken English\nImmediate available is highly preferred\n\nWe offer friendly team environment, good career prospect, also attractive remuneration package including commission and discretionary bonus incentive, together with other benefits like five-day work week, flexible working hours, double pay, medical and dental insurance. Interested parties please send full resume with available date, present and expected salary by clicking \u201cApply Now\u201d for an interview.\n\nAll personal data collected will be used for recruitment purpose only.\u00a0", "employment_types": ["Full Time", "Permanent"], "selling_points": [], "locations": ["Kwun Tong"], "categories": ["Transportation & Logistics", "Supply Chain", "Merchandising & Purchasing", "Textiles", "Procurement / Purchasing / Sourcing"], "post_time": "2022-01-14T02:14:26Z", "salary": {"currency": null, "max": null, "min": null, "period": "monthly", "term": null}, "salary_visible": false, "title_keywords": ["purchasing executive"], "responsibilities": ["shipment arrangement", "administrative support", "merchandising", "coordinate with", "purchase", "payment", "ad-hoc duties", "insurance"], "requirements": {"degrees": ["diploma"], "majors": [], "languages": ["english", "korean"], "language_level": ["good command"], "hard_skills": [], "soft_skills": ["flexible", "independent", "responsible", "multiple tasks", "well-organized", "smooth", "friendly", "ad-hoc duties", "detailed"], "languages_combined": [{"language": "english", "language_level": ["good command"]}, {"language": "korean", "language_level": []}]}, "experience_required": {"duration": ["minimum 1-2 years"], "field": ["ecommerce", "merchandising", "trading"]}}, {"job_id": "100003009048047", "location_code": "hk", "company": "Manpower Services (Hong Kong) Limited", "job_title": "Procurement Manager (Asset&Equipment)(Energy Company)(80K-90K)(1M-1.3M)", "description": "Chevalier (HK) Limited is now inviting high calibre persons to apply for this position:\n\n\nResponsibilities\n\nAssist in procurement activities including preparing purchase orders, purchase planning, price negotiation, etc\nMonitor stock inventory and maintain an updated purchasing database and filing system\nWork closely with suppliers and factories for order follow up and delivery schedule\nHandle ad hoc projects assigned by manager\n\n\nRequirements\n\nDegree in Business Administration or related disciplines\nMinimum 1 year relevant working experience in construction and engineering industry\nGood command of spoken and written English and Chinese\nProficient in MS Office applications and Chinese Word Processing\nImmediately available is highly preferred\n\n\nAttractive remuneration package will be offered to the right candidate. Interested parties, please send us your resume with current and expected salary by clicking \"Apply Now\" or mail to:\n\nThe Human Resources Manager, Chevalier Group, 22/F, Chevalier Commercial Centre, 8 Wang Hoi Road, Kowloon Bay, Hong Kong\n\nWe are an equal opportunity employer and welcome applications from all qualified candidates. Personal data collected would be used for recruitment purpose only.", "employment_types": ["Permanent"], "selling_points": ["Good Salary Package", "Excellent Salary Package with Bouns (Extra ORSO)", "Strong Support from Company"], "locations": ["Others"], "categories": ["Merchandising & Purchasing", "Others", "Procurement / Purchasing / Sourcing"], "post_time": "2022-01-14T04:36:20Z", "salary": {"currency": null, "max": null, "min": null, "period": "monthly", "term": null}, "salary_visible": false, "title_keywords": ["manager"], "responsibilities": ["price negotiation", "inventory", "monitor", "delivery schedule", "purchase", "maintain", "ad hoc projects", "database", "planning"], "requirements": {"degrees": ["degree"], "majors": ["related disciplines", "business administration"], "languages": ["english", "chinese"], "language_level": ["good command", "proficient"], "hard_skills": ["chinese word processing", "ms office"], "soft_skills": [], "languages_combined": [{"language": "english", "language_level": ["good command"]}, {"language": "chinese", "language_level": ["good command", "proficient"]}]}, "experience_required": {"duration": ["minimum 1 year"], "field": ["construction", "engineering", "relevant working experience"]}}, {"job_id": "100003009044108", "location_code": "hk", "company": "Classic Fine Foods (Hong Kong) Limited", "job_title": "Procurement and Shipping Officer (5 Months Contract)", "description": "Key Responsibilities:\n\n\nPerform factory inspections.\nPerform on site audits and supplier evaluation based on quality criteria.\nProvide training to suppliers on our quality requirements.\nPerform product evaluation on-site and in office.\nAccompany the production process on-site to ensure REWE quality requirements.\nAttend buying trips with buyers and merchandiser.\nPrepare weekly report on QA/factory audit/project progress.\n\n\nJob Requirements:\n\n\nDiploma or above in related discipline.\nMinimum of 3 years in quality management/quality control in consumer goods or testing laboratory.\nAble to have frequent travel.\nKnowledge of production processes is a plus.\nSelf-driven and solution oriented, and comfortable to work in cross-cultural environment.\nGood assertiveness and communication skills.\nGood command of both written and spoken English and Chinese (Cantonese and Mandarin).\nGood PC knowledge (Microsoft office suite).\n\nIf you are interested in the position, please submit your full resume with cover letter, current and expected salary and available date via JobsDB.\n\nAll\u00a0personal information is collected for recruitment purpose only and will be treated in strict confidentiality.\u00a0\u00a0", "employment_types": ["Temporary", "Contract"], "selling_points": ["Maternity Cover", "5 days working", "Under Procurement & Shipping Team"], "locations": ["Kwai Tsing Area"], "categories": ["Hospitality / F & B", "Food & Beverage", "Transportation & Logistics", "Shipping", "Merchandising & Purchasing", "Procurement / Purchasing / Sourcing"], "post_time": "2022-01-13T03:05:15Z", "salary": {"currency": null, "max": null, "min": null, "period": "monthly", "term": null}, "salary_visible": false, "title_keywords": ["shipping officer"], "responsibilities": ["provide training", "production process", "quality", "audit", "project progress", "evaluation", "audits", "report"], "requirements": {"degrees": ["diploma or above"], "majors": [], "languages": ["cantonese", "english", "chinese", "mandarin"], "language_level": ["good command"], "hard_skills": ["microsoft office suite", "plus", "pc knowledge"], "soft_skills": ["communication skills", "interested in", "driven"], "languages_combined": [{"language": "cantonese", "language_level": ["good command"]}, {"language": "english", "language_level": ["good command"]}, {"language": "chinese", "language_level": ["good command"]}, {"language": "mandarin", "language_level": ["good command"]}]}, "experience_required": {"duration": [], "field": []}}, {"job_id": "100003009047827", "location_code": "hk", "company": "Luk Fook Holdings Company Limited", "job_title": "\u63a1\u8cfc\u4e3b\u4efb(\u7d20\u91d1)", "description": "Responsibilities:\n\nResponsible for performing market research on the up-coming fashion trend;\nAssemble and execute plans for seasonal brand assortment and OTB in order to meet the company\u2019s business objective;\nProducts sourcing and sell-thru analysis;\nLiaise with suppliers on order placing efficiency and ensure appropriate levels of stock of designated product categories are maintained;\nAllocate merchandises and coordinate with shops and warehouse to smooth the stock replenishment issue;\nWork closely with operations, visual merchandising team and other counterparts to maximize sales performance of responsible category;\nCultivate and maintain partnership relationship with suppliers\n\nRequirements:\n\nBachelor\u2019s degree holder\nMin. 4 years\u2019 apparel / footwear buying experience\nSolid experience in branded merchandise buying, store replenishment, merchandise consolidation and product management is a must\nStrong business sense with excellent negotiation, interpersonal, numerical and analytical skills\nFluent in spoken and written English, Chinese and Mandarin\nProficient in MS Excel (Pivot Table, VLookup and other formula functions)\nWilling to travel\nCandidate with less experience will be considered as Assistant Buyer\n\nInterested parties please\u00a0send your resume with current and expected salary\u00a0by clicking\u00a0\"Apply Now\".\n\n\nData collected will be used for recruitment purpose only.\n\nFor company information, please visit our website www.sportshouse.com.hk", "employment_types": ["Full Time"], "selling_points": ["\u5354\u52a9\u5206\u6790\u5e02\u5834\u9700\u6c42\u53ca\u8d70\u52e2", "\u5354\u52a9\u90e8\u9580\u54e1\u5de5\u7684\u7ba1\u7406\u53ca\u57f9\u8a13\u5de5\u4f5c", "\u5354\u52a9\u8655\u7406\u63a1\u8cfc\u90e8\u5176\u4ed6\u65e5\u5e38\u4e8b\u5b9c"], "locations": ["Shatin Area"], "categories": ["Merchandising & Purchasing", "Others", "Procurement / Purchasing / Sourcing"], "post_time": "2022-01-14T03:58:13Z", "salary": {"currency": null, "max": null, "min": null, "period": "monthly", "term": null}, "salary_visible": false, "title_keywords": [], "responsibilities": ["product categories", "stock replenishment", "operations", "analysis", "sales performance", "coordinate with", "market research", "merchandising", "otb", "maintain", "visual", "plans", "liaise with suppliers"], "requirements": {"degrees": ["bachelor", "degree holder"], "majors": [], "languages": ["english", "chinese", "mandarin"], "language_level": ["fluent"], "hard_skills": ["pivot table", "ms excel", "vlookup", "analytical skills"], "soft_skills": ["interpersonal", "negotiation", "analytical skills", "business sense"], "languages_combined": [{"language": "english", "language_level": ["fluent"]}, {"language": "chinese", "language_level": ["fluent"]}, {"language": "mandarin", "language_level": ["fluent"]}]}, "experience_required": {"duration": ["4 years"], "field": ["product management", "consolidation"]}}, {"job_id": "100003009050540", "location_code": "hk", "company": "Sa Sa Dot Com Limited", "job_title": "Senior Product Executive / Product Supervisor (eCommerce Merchandising)", "description": "Assist to the Manager for material sourcing, price negotiation, and supplier development\n2-3 years solid exp\u00a0in purchasing /\u00a0exp in food\u00a0industry would be an advantage\nDiploma or equivalent\nGood connection with food suppliers are preferable\nMature, work independently and hardworking\nLess experience will be considered as Purchasing Assistant\n\nWe offer an attractive remuneration package to the right candidates. \u00a0Interested parties, please send full resume with expected salary to Personnel Department.\n\n(all personal data collected for recruitment purpose only)", "employment_types": ["Full Time"], "selling_points": ["OTB & assortment planning of beauty products", "Buying exp in the eCommerce of PRC, HK & S.E. Asia", "Source new products to enhance product portfolio"], "locations": ["Siu Sai Wan"], "categories": ["Merchandising & Purchasing", "Sundries", "Procurement / Purchasing / Sourcing", "E-commerce", "Marketing - Brand / Product Management"], "post_time": "2022-01-14T10:40:14Z", "salary": {"currency": null, "max": null, "min": null, "period": null, "term": null}, "salary_visible": false, "title_keywords": ["senior product executive", "merchandising", "product supervisor"], "responsibilities": ["price negotiation"], "requirements": {"degrees": ["diploma"], "majors": [], "languages": [], "language_level": [], "hard_skills": [], "soft_skills": ["work independently", "hardworking", "negotiation", "mature"], "languages_combined": []}, "experience_required": {"duration": [], "field": ["purchasing"]}}, {"job_id": "100003009045055", "location_code": "hk", "company": "Kembla (HK) Limited", "job_title": "Assistant Purchasing Officer", "description": "Takara company\n\n\u00a0\n-\u00a0F.5, IVE or Poly Graduate, Over\u00a01years Garment exp.\n\n- Strong High Fashion Item\n- Good English & Mandarin\n- Factory experiences and advantage\n- Good knowledge of Sourcing, sampling and following orders\n- Knowledge of Travel to China\n- MUST Be immediate availbale\n\n\n\n\n\n\nPlease send your application with detailed resume and expected salary to\nhr@takara.hk\u00a0\u00a0\n**Personal data collected will be used for recruitment purpose only**\n", "employment_types": ["Full Time"], "selling_points": [], "locations": ["Wan Chai"], "categories": ["Building & Construction", "Building / Construction / QS", "Merchandising & Purchasing", "Procurement / Purchasing / Sourcing"], "post_time": "2022-01-13T18:55:05Z", "salary": {"currency": null, "max": null, "min": null, "period": "monthly", "term": null}, "salary_visible": false, "title_keywords": ["assistant purchasing officer"], "responsibilities": ["personal data", "recruitment"], "requirements": {"degrees": [], "majors": [], "languages": ["english", "mandarin"], "language_level": ["good"], "hard_skills": [], "soft_skills": ["detailed"], "languages_combined": [{"language": "english", "language_level": ["good"]}, {"language": "mandarin", "language_level": ["good"]}]}, "experience_required": {"duration": [], "field": []}}, {"job_id": "100003009048130", "location_code": "hk", "company": "Chicardo Investment Limited", "job_title": "\u63a1\u8cfc\u6587\u54e1 Purchasing Clerk (\u5c6f\u9580\u5340)", "description": "Join us & Be eCommerce Innovators\nAre you looking to be part of revolutionizing online shopping behaviour and experience? We are a well-esteemed eCommcere company that operates multiple eCommerce websites internationally. We are now looking for potential talent to help us expand our new business worldwide and to manage the merchandising process of beauty products.\n\n\n\nKey Job Responsibilities:\u00a0\n\nResponsible and manage the sourcing activities and vendor management for Korean and Japanese beauty and cosmetics category\nNegotiate and work with vendors in Korea, Japan or other regions to build and maintain mutually beneficial relationships to ensure long term strategic partnership\nMaximize Korean and Japanese beauty brands/products sales performance through continuous effort in identifying new vendors in Korea, Japan or other regions\nDrive and implement business strategies to build the categories for the company\nManage merchandising process from souring, product development to vendor management\nProvide strategic sourcing planning and coordinate within merchandising team and sales team for implementation\nAny ad-hoc tasks as assigned\n\n\u00a0Desired Skills and Experience:\u00a0\n\nMinimum 3 years or above working experience in relevant merchandise category or business development experience under trading environment or buying office\nExperience in Korea and Japan branded beauty products\nGood supplier networks with sound vendor development experience and skillsets will be an advantage\nWell-organized, detailed minded, result oriented and able to manage multiple tasks environment\nAble to work independently and under pressure, as well as cooperate well with team and stakeholders to achieve company goals\nExcellent command of written and spoken English, proficiency in Korean or Japanese will be an advantage\nFrequent oversea travel is needed\n\nWe offer friendly team environment, good career prospect, also attractive remuneration package including discretionary bonus incentive, together with other benefits like five-day work week, flexible working hours, double pay, medical and dental insurance. Interested parties please send full resume with available date, present and expected salary by clicking \u201cApply Now\u201d for an interview.\n\nAll personal data collected will be used for recruitment purpose only.\u00a0", "employment_types": ["Full Time"], "selling_points": [], "locations": ["Tuen Mun Area"], "categories": ["Admin & HR", "Clerical / Admin Staff", "Merchandising & Purchasing", "Procurement / Purchasing / Sourcing"], "post_time": "2022-01-14T05:07:04Z", "salary": {"currency": "HKD", "max": 19999, "min": 14000, "period": "monthly", "term": null}, "salary_visible": true, "title_keywords": ["purchasing clerk"], "responsibilities": ["management", "sales performance", "ad-hoc tasks", "merchandising", "implementation", "coordinate", "maintain", "sales team", "insurance", "planning"], "requirements": {"degrees": [], "majors": [], "languages": ["japanese", "english", "korean"], "language_level": ["advantage", "excellent", "proficiency"], "hard_skills": ["vendor"], "soft_skills": ["flexible", "work independently", "under pressure", "responsible", "multiple tasks", "well-organized", "result oriented", "friendly", "detailed"], "languages_combined": [{"language": "japanese", "language_level": ["excellent"]}, {"language": "english", "language_level": ["advantage", "proficiency", "excellent"]}, {"language": "korean", "language_level": ["excellent"]}]}, "experience_required": {"duration": ["minimum 3 years"], "field": ["ecommerce", "development", "business development", "beauty", "trading"]}}, {"job_id": "100003009048049", "location_code": "hk", "company": "Manpower Services (Hong Kong) Limited", "job_title": "Assistant Procurement Manager (Performance & Excellence)(Energy Company)(60K-70K)(850K-1M)", "description": "Company Description\u00a0\n\nOur client is a fast expanding F&B group with business in cafe and coffee trading. Because of business expansion, they are looking for someone who is enthusiastic about coffee bean and coffee to join and main/enhance the coffee quality.\n\nResponsibilities\u00a0\n\nSourcing coffee beans globally and identify potential supplier\nEnsure the highest standard of coffee bean is purchased and the best coffee is served to customers.\nAct as quality control for the coffee made\nNegotiate with coffee suppliers to ensure the right price is offered\n\nRequirements\u00a0\n\nExperienced in coffee business\nAble to tell the difference of coffee beans, origins and different roast process\nConnection and network with coffee bean supplier is a plus\nStrong in communications with good working attitude\nFluency in Cantonese and English is a must.\n\nInterested parties please send your updated resume in WORD format with current and expected salaries (quoting Employer Ref:)", "employment_types": ["Permanent"], "selling_points": ["Good Salary Package", "Excellent Salary Package with Bouns (Extra ORSO)", "Strong Support from Company"], "locations": ["Others"], "categories": ["Merchandising & Purchasing", "Others", "Procurement / Purchasing / Sourcing"], "post_time": "2022-01-14T04:36:30Z", "salary": {"currency": null, "max": null, "min": null, "period": "monthly", "term": null}, "salary_visible": false, "title_keywords": ["manager", "assistant"], "responsibilities": ["quality control"], "requirements": {"degrees": [], "majors": [], "languages": ["cantonese", "english"], "language_level": ["fluency"], "hard_skills": ["plus"], "soft_skills": ["good working attitude"], "languages_combined": [{"language": "cantonese", "language_level": ["fluency"]}, {"language": "english", "language_level": ["fluency"]}]}, "experience_required": {"duration": [], "field": []}}, {"job_id": "100003009047756", "location_code": "hk", "company": "Kwong Chak Fat Manufactory Limited", "job_title": "Merchandiser / Senior Merchandiser", "description": "Responsibilities:\n\nLead activities in fabric/sample development, costing package coordination, preliminary screening and order tracking;\nWork with vendors to establish costing plans and follow-up on fit/lab dip approval status and ensure vendors meet the product development timeline, price, and bulk quality standards;\nProficiency on doing the costing analysis and evaluate the cost breakdown correctly;\nWith solid experience to deal with offshore vendors and proactively to communicate with them for all sampling development & production follow up;\nIs accountable to follow up on all details on production to achieve on-time delivery targets;\nProactive in price negotiation and sourcing of suppliers to meet requirements;\nDeal with production issues in efficient & proactive manner and having problem solving skillset;\nPerform any ad-hoc tasks/projects as assigned by the superior.\n\n\u00a0Qualifications:\n\nDiploma or Degree in Merchandising or textile-related discipline is an advantage;\nAt least\u00a05 years relevant experience in a merchandising and/or sourcing environment, exposure with\u00a0sportswear is highly preferred;\nExperience in dealing with off-shore factories;\nKnowledge of the U.S. retail market is an advantage;\nProficient in MS office;\nGood communication, analytical and problem solving skills;\nGood command of written and\u00a0spoken English and Chinese, Mandarin preferred;\nWillingness to Travel.\n\nInterested parties, please click the 'APPLY NOW' button for application. All information received will be used for recruitment purposes only.", "employment_types": ["Full Time"], "selling_points": [], "locations": ["Shatin Area"], "categories": ["Manufacturing", "Product Development / Management", "Merchandising & Purchasing", "Others", "Procurement / Purchasing / Sourcing"], "post_time": "2022-01-14T03:53:24Z", "salary": {"currency": null, "max": null, "min": null, "period": "monthly", "term": null}, "salary_visible": false, "title_keywords": ["merchandiser", "senior merchandiser"], "responsibilities": ["communicate with", "order tracking", "cost", "price negotiation", "ad-hoc tasks", "quality", "merchandising", "evaluate", "communication", "coordination", "costing analysis", "plans"], "requirements": {"degrees": ["diploma", "degree", "dip"], "majors": [], "languages": ["english", "chinese", "mandarin"], "language_level": ["good command"], "hard_skills": ["problem solving", "analysis", "problem solving skills", "ms office"], "soft_skills": ["efficient", "negotiation", "accountable", "problem solving", "communication", "analytical and problem solving skills", "coordination", "proactive", "superior"], "languages_combined": [{"language": "english", "language_level": ["good command"]}, {"language": "chinese", "language_level": ["good command"]}, {"language": "mandarin", "language_level": ["good command"]}]}, "experience_required": {"duration": ["at least 5 years"], "field": ["development", "relevant experience", "merchandising"]}}, {"job_id": "100003009048427", "location_code": "hk", "company": "New Yip Fung Food Centre Limited", "job_title": "Purchasing Clerk \u63a1\u8cfc\u6587\u54e1 (\u5c6f\u9580\u5340)", "description": "My client is looking for 6 staffs , it is expected that have working experience in large scale operation environment\u00a0\n\nKey Responsibilities:\n\nConduct new sourcing requests, contract renewals, contract re-negotiation and transactional tasks of tactical sourcing projects.\nConduct detailed spend analysis and compile spend dashboard\nManage purchase requisitions from business, advise requestor on sourcing channel and execute tactical sourcing as needed.\nManage PO issuance (if needed) and review PO status / follow-up with suppliers\nMaintain the contract repository (upload and archive contracts as needed)\nReview contract compliance and contracts due for renewal\nSupport supplier identification, qualification and onboarding process\nSupport master data management\nSupport complication of procurement operations / performance reports\n\nOther requirements:\u00a0\n\nExperience in using procurement systems for operating the source-to-pay process and spend analysis\nAssisting and supporting the Category Manager in carrying out any other relevant duties which may be required\u00a0\nMaintain up-to-date commercial and contractual knowledge of the market place and methods to ensure that best practices are continually developed and utilized within the group\u00a0\nOrganize regular vendor meetings, develop appropriate service level agreements and to lead the discussion in resolving vendor/internal issues when required\u00a0\nManage ongoing vendor relationships, including conformity to contract performance, resolution of payment disputes, and activity on critical dates (extensions, renewals, price adjustments, etc.)\n\n\u00a0Interested Parties, please send in your CV with expected salary and notification.\n\n\n", "employment_types": ["Full Time"], "selling_points": [], "locations": ["Tuen Mun Area"], "categories": ["Merchandising & Purchasing", "Procurement / Purchasing / Sourcing"], "post_time": "2022-01-14T06:36:13Z", "salary": {"currency": null, "max": null, "min": null, "period": "monthly", "term": null}, "salary_visible": false, "title_keywords": ["purchasing clerk"], "responsibilities": ["management", "performance reports", "data", "contracts", "analysis", "review", "compliance", "operations", "purchase", "maintain"], "requirements": {"degrees": [], "majors": [], "languages": [], "language_level": [], "hard_skills": ["analysis", "vendor"], "soft_skills": [], "languages_combined": []}, "experience_required": {"duration": [], "field": ["procurement"]}}, {"job_id": "100003009048203", "location_code": "hk", "company": "Sainsbury's Argos Asia Limited", "job_title": "Assistant Merchandiser - Home", "description": "Responsibilities\n\nResponsible for sourcing and purchasing of building materials for construction sites\nPreparation of Tender, Analysis and Recommendation\nAdministration Works\n\nRequirements\n\nHD in Purchasing / Supply Chain Business or related discipline\n2 years of relevant experience in procurement of building materials would be an advantage\nGood command of English and Chinese\nGood interpersonal skills\nKnowledge in PC (Excel/ Word)\n\nFresh graduate will also be considered.\n\nAttractive salary and fringe benefits will be offered to the successful candidates. Please apply with full resume, available date, present and expected salary and quoting the reference code on the letter & envelope to\u00a0THE HUMAN RESOURCES & TRAINING DEPARTMENT, HIP HING CONSTRUCTION CO., LTD., 11/F., Chevalier Commercial Centre, No. 8 Wang Hoi Road, Kowloon Bay, Hong Kong OR click \"Apply Now\" OR fax to 2530 4360.\n\nCompany Website:\u00a0www.hiphing.com.hk\n\n\nAll personal data collected will be used for recruitment purposes only.\nApplicants who are not invited for an interview within 8 weeks may consider their applications unsuccessful.\nPlease enable the \"Pop-up\" setting of your browser, click\u00a0here\u00a0for steps.", "employment_types": ["Full Time", "Permanent"], "selling_points": [], "locations": ["Ngau Tau Kok"], "categories": ["Merchandising & Purchasing", "Others", "Procurement / Purchasing / Sourcing"], "post_time": "2022-01-14T05:51:41Z", "salary": {"currency": null, "max": null, "min": null, "period": "monthly", "term": null}, "salary_visible": false, "title_keywords": ["assistant merchandiser"], "responsibilities": ["analysis", "tender", "administration"], "requirements": {"degrees": ["fresh graduate"], "majors": [], "languages": ["english", "chinese"], "language_level": ["good command"], "hard_skills": ["pc", "word", "excel"], "soft_skills": ["interpersonal skills"], "languages_combined": [{"language": "english", "language_level": ["good command"]}, {"language": "chinese", "language_level": ["good command"]}]}, "experience_required": {"duration": ["2 years"], "field": ["relevant experience", "procurement"]}}, {"job_id": "100003009046343", "location_code": "hk", "company": "Manpower Services (Hong Kong) Limited", "job_title": "Contract Procurement Coordinator (Up to 18K)", "description": "Responsibilities\nResponsible for OTB, product mix and assortment planning of beauty products, \u00a0accessories for e-commerce in China / HK / South Asia market;\nWork closely with internal departments including buying operation, inventory, and eCommerce teams to ensure proper execution of assortment strategies;\nKeep track the market trend and identify new brands to optimize category growth;\nIdentify potential suppliers to source new products to enhance the product portfolio and fulfill market needs;\nAlign and actualize the overall sourcing strategies for the e-commerce business;\nAnalyze market trends, sales performance.\nRequirements\nDegree holder in Business or related disciplines;\n3-5 years of buying experience in e-commerce / retail industry preferably in Beauty / health food / Personal Care Category;\nHigh degree of business sense with strong analytical skills;\nSelf-motivated, energetic, well-organized and able to work under pressure;\nStrong negotiation and presentation skills;\nA good team player with strong communication and interpersonal skills;\nIndependent, proactive and well-organised;\nGood command of spoken & written English and Chinese.\n\nWe offer\n\n5 - day work week\nMedical Benefits\nAnnual Merit Bonus\nStaff Purchase Discounts\nStaff Recreation Activity\nShuttle Bus Service\nEducation Sponsorship\n\nInterested parties please send a full resume with current and expected salary by clicking APPLY NOW:\n\nPlease visit our corporate website at\u00a0http://corp.sasa.com/en/home\u00a0to know more about us.\n\n(Sa Sa is an Equal Opportunity Employer and all qualified applicants will receive consideration for employment. Personal data collected will be kept confidential and used for recruitment purpose only)", "employment_types": ["Contract"], "selling_points": ["Hands on source-to-pay procurement process", "support stakeholders", "Fresh graduate will also be considered"], "locations": ["Causeway Bay"], "categories": ["Admin & HR", "Clerical / Admin Staff", "Merchandising & Purchasing", "Procurement / Purchasing / Sourcing", "Others", "Student / Fresh Graduate / No Experience"], "post_time": "2022-01-13T10:35:59Z", "salary": {"currency": null, "max": null, "min": null, "period": "monthly", "term": null}, "salary_visible": false, "title_keywords": ["coordinator"], "responsibilities": ["product mix and assortment planning", "sales performance", "inventory", "teams", "otb"], "requirements": {"degrees": ["degree", "degree holder"], "majors": ["related disciplines", "business"], "languages": ["english", "chinese"], "language_level": ["good command"], "hard_skills": ["analytical skills", "e-commerce"], "soft_skills": ["self-motivated", "good team player", "independent", "negotiation", "proactive", "business sense", "well-organized", "analytical skills", "presentation skills", "communication and interpersonal skills", "well-organised", "energetic", "work under pressure"], "languages_combined": [{"language": "english", "language_level": ["good command"]}, {"language": "chinese", "language_level": ["good command"]}]}, "experience_required": {"duration": ["3-5 years"], "field": ["retail industry", "e-commerce", "beauty", "health food", "personal care"]}}, {"job_id": "100003009049412", "location_code": "hk", "company": "Wharf Real Estate Investment Company Limited", "job_title": "Manager \u2013 Cost Audit Department", "description": "Key Responsibilities\n\nProvide daily support to team members throughout the merchandising cycles;\n\nResponsible for gathering and inputting data into the system as well as ensuring order details accuracy before issuing purchase orders to suppliers;\nPerform samples measurement according to company\u2019s quality standard requirements and identify quality issues at an early stage;\nPrepare individual product style and quality requirement packages to Quality Assurance & Quality Control (\u201cQA & QC\u201d) team for inspection;\nProvide general clerical assistance to team members throughout the merchandising cycles from the arrangement of courier, general samples packing to filing;\nProvide other ad-hoc support to the team.\n\nRequirements\n\n\n\nCompletion of higher secondary school or diploma studies ideally with fashion or textile educational background;\nMinimum 2 years\u2019 relevant experience in the garment industry and preferably with knowledge in Woven/Outdoor items;\nAbility to work under pressure and tight deadlines with a proactive and positive attitude;\nGood communication skills, well-organized and attentive to details;\nExperience in order follow up ranged from sample development to bulk production;\nProficiency in MS Excel, Word, and Outlook Express;\nGood command of written and spoken English and Chinese (fluency in Cantonese and Mandarin).\n\nWhat we offer\n\nExcellent development and career growth opportunity;\nMultinational and open-minded work environment;\nCompetitive remuneration and benefits.", "employment_types": ["Full Time", "Permanent"], "selling_points": ["Lead Cost Audit and Expenditure Budget Units", "At least 15 years of proven track record", "Bachelor\u2019s degree or professional qualification"], "locations": ["Tsim Sha Tsui"], "categories": ["Accounting", "Audit", "Others", "Merchandising & Purchasing", "Procurement / Purchasing / Sourcing"], "post_time": "2022-01-15T03:50:24Z", "salary": {"currency": null, "max": null, "min": null, "period": "monthly", "term": null}, "salary_visible": false, "title_keywords": ["manager"], "responsibilities": ["ad-hoc", "data", "quality", "merchandising", "measurement", "inspection", "purchase", "quality control"], "requirements": {"degrees": ["diploma"], "majors": [], "languages": ["cantonese", "english", "chinese", "mandarin"], "language_level": ["fluency", "good command"], "hard_skills": ["garment industry", "ms excel", "outlook", "word"], "soft_skills": ["communication skills", "attentive to details", "well-organized", "positive attitude", "proactive", "work under pressure"], "languages_combined": [{"language": "cantonese", "language_level": ["fluency", "good command"]}, {"language": "english", "language_level": ["fluency", "good command"]}, {"language": "chinese", "language_level": ["fluency", "good command"]}, {"language": "mandarin", "language_level": ["fluency", "good command"]}]}, "experience_required": {"duration": ["minimum 2 years"], "field": ["garment", "development", "relevant experience"]}}, {"job_id": "100003009039176", "location_code": "hk", "company": "Nestle Hong Kong Ltd", "job_title": "Procurement Executive", "description": "Job Duties\n\nOverseas procurement and logistic arrangement\nAssist in inventory control, follow up order and liaison with warehouse to ensure timely delivery and right quality.\nManage suppliers and shipping forwarders relationship\nPerform ad-hoc duties as assigned\n\nRequirements:\n\n\u00a0DSE/Associate degree holder\n\u00a0Good command of spoken and written English and Chinese\n\u00a0Proficient in word, excel and spreadsheet\n\u00a0Good communication skill & logical thinking\n\u00a0Strong sense of responsibility and willing to learn\n\u00a0Self-motivation, ability to work in team and under pressure\n\nBenefits\n\n\u00a0Attractive salary and career path\n\u00a0Performance bonus\n\u00a0Bank holiday, annual leave\n\u00a0Medical benefit (after probation)\n\nInterested parties please send your full resume indicating your expected salary and your availability.", "employment_types": ["Full Time", "Permanent"], "selling_points": ["Manager indirect sourcing", "Formulate sourcing and procurement strategies", "Implement cost/process improvement projects"], "locations": ["Yuen Long"], "categories": ["Merchandising & Purchasing", "Procurement / Purchasing / Sourcing"], "post_time": "2022-01-11T08:56:16Z", "salary": {"currency": null, "max": null, "min": null, "period": "monthly", "term": null}, "salary_visible": false, "title_keywords": ["procurement executive"], "responsibilities": ["shipping", "quality", "logistic arrangement", "inventory control", "ad-hoc duties"], "requirements": {"degrees": ["associate degree", "dse"], "majors": [], "languages": ["english", "chinese"], "language_level": ["good command"], "hard_skills": ["excel", "spreadsheet", "word"], "soft_skills": ["under pressure", "sense of responsibility", "communication skill", "willing to learn", "self-motivation"], "languages_combined": [{"language": "english", "language_level": ["good command"]}, {"language": "chinese", "language_level": ["good command"]}]}, "experience_required": {"duration": [], "field": []}}, {"job_id": "100003009049555", "location_code": "hk", "company": "Migros (Hong Kong) Ltd", "job_title": "Logistics Officer", "description": "Responsibilities:\n\nProvide administrative and clerical support to the Central Procurement Unit\nCoordinate with both Hong Kong and Mainland procurement teams and assist in standardization of procurement process\nLiaise with user departments, suppliers and contractors on tendering process\nManage the purchase and tender database\nMaintain the filing system in timely manner\nPerform other duties as assigned\n\nRequirements:\n\nDiploma holder or above in Business Administration, Purchasing and Supply Management or related disciplines\nAt least 3 years\u2019 relevant experience, solid experience in procurement will be an advantage\nGood organizational and communication skills\nSelf-motivated, meticulous, good team player and able to work under pressure\nProficient in PC skills including MS Office and Chinese Word Processing\nGood command in both written and spoken English and Chinese (including Putonghua)\n\nWe offer competitive remuneration package that commensurate with experience and qualifications. Interested parties are invited to send full resume stating contact telephone number, date available, present and expected salary to our recruitment email address.\n\n(Personal data provided will be used strictly in accordance with the Company's personal data policy which is available upon request.)\u00a0", "employment_types": ["Full Time", "Permanent"], "selling_points": [], "locations": ["Kowloon Bay"], "categories": ["Transportation & Logistics", "Supply Chain", "Merchandising & Purchasing", "Procurement / Purchasing / Sourcing"], "post_time": "2022-01-14T08:52:28Z", "salary": {"currency": null, "max": null, "min": null, "period": "monthly", "term": null}, "salary_visible": false, "title_keywords": ["logistics officer"], "responsibilities": ["perform other duties", "teams", "coordinate with", "tendering", "purchase", "maintain", "administrative and clerical support", "tender", "liaise with", "database"], "requirements": {"degrees": ["diploma holder"], "majors": ["related disciplines", "business administration"], "languages": ["putonghua", "english", "chinese"], "language_level": ["good command", "proficient"], "hard_skills": ["pc skills", "chinese word processing", "ms office"], "soft_skills": ["communication skills", "self-motivated", "meticulous", "good team player", "organizational", "work under pressure"], "languages_combined": [{"language": "putonghua", "language_level": ["good command"]}, {"language": "english", "language_level": ["good command"]}, {"language": "chinese", "language_level": ["good command", "proficient"]}]}, "experience_required": {"duration": ["at least 3 years"], "field": ["relevant experience", "procurement"]}}, {"job_id": "100003009046458", "location_code": "hk", "company": "Hays Hong Kong Limited", "job_title": "Procurement Officer (Contract)", "description": "We are looking for high caliber candidate to join us and work together for the growth\u00a0of both our Company and individual.\n\nWhat will you be doing?\nThis position is responsible for executing and improving end-to-end best practices in Global Sourcing for assigned product categories. This role is accountable for developing and managing vendors, as well as maintaining existing vendor relationships and driving projects to ensure that vendors meet or exceed their contractual obligations by delivering innovative, quality products on time.\n\nRoles & Responsibility:-\n\nSourcing Process Execution and Vendor Management:\nExecute and improve the end-to-end sourcing processes including vendor management, liaison with agents, price negotiation, product development and sample assessment to meet the on-time delivery, quality and commercial KPIs\nSource and develop potential vendors as well as drive a respectful and collaborative vendor relationship with existing vendors to ensure they meet all company\u2019s requirements including value, quality and innovation.\nManage Request for Proposal, category costing bids and product development independently in conjunction with and product development and sourcing teams.\nEnsure smooth arrangement of product development trip, sourcing trip and finalization events\nExecute order management to ensure accuracy of database; Monitor and regular update on project status of assigned product categories\nProvide support in streamlining sourcing process and enhancement of product specification for price negotiation, cost reduction initiatives and high quality of products.\u00a0 Handle cost and commercial terms negotiation with vendors.\n\nAdditional duties as assigned including:-\n\nCollect latest market intelligence for Sourcing Manager to share with management, product development and sourcing teams.\u00a0\nProvide data for Sourcing Manager to conduct cost and supplier performance analysis in order to generate cost saving opportunities.\nTrain new Associate Sourcing Specialists and assist in their ongoing skills development\nOther duties as assigned\nKnowledge, Skills and Abilities requirement:-\nDegree/Associate Degree/Diploma holder in Merchandising/ Business Management or related discipline\nHands-on computer knowledge in MS word, Excel, Outlook, Power Point & Chinese Word Processing\nMinimum 3 years\u2019 relevant working experience\nEnergetic, self-motivated, detail-oriented and independent working style\nGood communication and interpersonal skills\nEager to work in a team in order to achieve best results\nDemonstrate a high sense of initiative, hardworking and responsible\nThe ability to work in a demanding but collegial, team-oriented environment\nGood command of both written and spoken English and Mandarin\nFrequent travel is required; Up to 30% travel\nSolid sourcing experience preferably gained from US buying office/ retailer\nWe offer competitive pay package and attractive fringe benefits including employer voluntary contribution on MPF scheme, Medical Insurance such as out-patient, hospitalization and dental coverage for employee, spouse and dependents. For interested parties, please make your application by stating the current and expected salaries.\n\nPersonal data collected will be used strictly for recruitment purpose only.", "employment_types": ["Full Time", "Contract"], "selling_points": ["development opportunities", "regional exposure", "attractive package"], "locations": ["Tsim Sha Tsui"], "categories": ["Merchandising & Purchasing", "Procurement / Purchasing / Sourcing"], "post_time": "2022-01-13T11:23:50Z", "salary": {"currency": null, "max": null, "min": null, "period": "monthly", "term": null}, "salary_visible": false, "title_keywords": ["procurement officer"], "responsibilities": ["product categories", "management", "price negotiation", "order management", "provide support", "cost", "terms negotiation", "data", "additional duties", "analysis", "other duties", "quality", "teams", "monitor", "develop", "database", "kpis"], "requirements": {"degrees": ["diploma holder", "associate degree", "degree"], "majors": ["business"], "languages": ["english", "chinese", "mandarin"], "language_level": ["good command"], "hard_skills": ["business management", "excel", "chinese word processing", "scheme", "outlook", "power point", "ms word"], "soft_skills": ["self-motivated", "independent", "responsible", "detail-oriented", "hands-on", "communication and interpersonal skills", "patient", "energetic", "initiative", "hardworking"], "languages_combined": [{"language": "english", "language_level": ["good command"]}, {"language": "chinese", "language_level": []}, {"language": "mandarin", "language_level": ["good command"]}]}, "experience_required": {"duration": ["minimum 3 years"], "field": ["relevant working experience"]}}, {"job_id": "100003009051253", "location_code": "hk", "company": "Chantal Supplies Limited", "job_title": "SENIOR MERCHANDISER / MERCHANDISER (HANDBAG PRODUCTION)", "description": "Main tasks & responsibilities:\n\nTo process efficient and effectively the daily inquiries and orders within the given product categories and according to our quality and compliance standards. The tasks involves\u00a0quoting, procurement, monitoring production and logistics. The goal is to increase the\u00a0number orders and service level to our customers.\n\nDuties\n\nProcess inquiries > prioritize and provide good quality replies within the service level agreement\nTake full responsibility from the inquiry stage; order received till shipment.\nKeep track of suppliers\u2019 production plan to ensure on time delivery\nBe result orientated > offer solutions, alternatives: each inquiry and order is a chance.\nHandle complaints and discuss/negotiate solutions with the factories and/or sales.\n\n\u00a0Your experience\n\nOrganized and an eye for detail;\nResult-orientated team-player;\nGood command in English and Mandarin\nMerchandising or procurement experience\nGood command of Excel, Word, PPT and so on for office software.\n\n\u00a0What\u2019s in it for you?\n\nWe offer you a challenging and exciting job in an enthusiastic team and pleasant working environment with a competitive salary, performance bonus, double pay, life insurance, medical insurance, five-day work week and 15 days holidays per year.\n\nAre you a starter? Don\u2019t hesitate to apply!", "employment_types": ["Full Time", "Permanent"], "selling_points": [], "locations": ["Causeway Bay"], "categories": ["Merchandising & Purchasing", "Handbag", "Procurement / Purchasing / Sourcing"], "post_time": "2022-01-15T06:21:39Z", "salary": {"currency": null, "max": null, "min": null, "period": "monthly", "term": null}, "salary_visible": false, "title_keywords": ["merchandiser", "senior merchandiser"], "responsibilities": ["product categories", "software", "monitoring", "compliance", "quality", "ensure on time delivery", "handle complaints", "merchandising", "logistics", "plan", "insurance"], "requirements": {"degrees": [], "majors": [], "languages": ["english", "mandarin"], "language_level": ["good command"], "hard_skills": ["excel", "word", "goal", "service level agreement", "office software"], "soft_skills": ["efficient", "organized", "team-player", "prioritize", "pleasant", "eye for detail", "enthusiastic"], "languages_combined": [{"language": "english", "language_level": ["good command"]}, {"language": "mandarin", "language_level": ["good command"]}]}, "experience_required": {"duration": [], "field": ["merchandising", "procurement"]}}, {"job_id": "100003009047833", "location_code": "hk", "company": "Multiway Industries (H.K.) Limited", "job_title": "Accounting Clerk", "description": "\u4e2d\u5b78\u7a0b\u5ea6\u6216\u4ee5\u4e0a\uff0c\u4e09\u5e74\u6216\u4ee5\u4e0a\u76f8\u95dc\u7d93\u9a57\n\u661f\u671f\u4e00\u81f3\u516d\uff0c9\u6642\u81f36\u6642\uff0c\u6bcf\u9031\u5de5\u4f5c5.5\u5929\uff0c\u9577\u77ed\u9031\nPizza\u9023\u9396\u5e97\u8058\u63a1\u8cfc\u6587\u54e1\n\u4e00\u822c\u63a1\u8cfc\u6587\u54e1\u5de5\u4f5c\uff0c\u8ca0\u8cac\u5b89\u6392\u8a02\u8ca8\u3001\u8ddf\u9032\u63a1\u8cfc\u8a02\u55ae\n\u806f\u7d61\u4f9b\u61c9\u5546\u3001\u5831\u50f9\u3001\u53d6\u8ca8\u677f\u3001\u51fa\u5165\u8ca8\u7d00\u9304\n\u6e9d\u901a\u80fd\u529b\u826f\u597d\uff0c\u80fd\u64cd\u6d41\u5229\u7cb5\u8a9e\n\u61c2\u96fb\u8166 (Excel\u3001Word)\n\u80fd\u7368\u7acb\u8655\u7406\u5de5\u4f5c\uff0c\u6709\u8cac\u4efb\u611f\u00a0\n\n\u6709\u610f\u8acb\u96fb\u90f5 \"Apply Now\" \u912d\u5c0f\u59d0\u00a0\n\n", "employment_types": ["Full Time", "Permanent"], "selling_points": [], "locations": ["Tsuen Wan Area"], "categories": ["Accounting", "Accounting Clerk / Supervisor", "Merchandising & Purchasing", "Procurement / Purchasing / Sourcing", "Others", "Student / Fresh Graduate / No Experience"], "post_time": "2022-01-14T03:59:44Z", "salary": {"currency": "HKD", "max": 13999, "min": 11000, "period": "monthly", "term": null}, "salary_visible": true, "title_keywords": ["accounting clerk"], "responsibilities": [], "requirements": {"degrees": [], "majors": [], "languages": [], "language_level": [], "hard_skills": [], "soft_skills": [], "languages_combined": []}, "experience_required": {"duration": [], "field": []}}, {"job_id": "100003009045086", "location_code": "hk", "company": "Asia Beauty Concepts Limited", "job_title": "Administrative Assistant", "description": "Purpose of this role...\nThe purpose of this role is to ensure the development, management and prioritization of procurement strategies across all the spend categories to deliver sustainable to the assigned Business/Functional Units\n\nA day in the life of...\nProvide support on include but not limited to support RFX activities, contract negotiations and ensure these activities are completed in compliance with company\u2019s policy\nAdvise and liaise with internal stakeholders to determine demand requirements and business needs\nScreen, audit and select suppliers based on risks and commercial assessment and negotiate with suppliers and evaluate their performance regularly\nFormulate sourcing and procurement strategies of assigned categories\nInitiate & Implement cost/process improvement projects.\nEnsure that suppliers provide quality products/services to meet the corporate requirements.\nSupport in completing market research to identify new suppliers to meet specific needs of the business and improve competitiveness\nConduct spend analysis and gather information on supply market, develop supplier profiles and identify potential supplier risk\nInitiate and lead changes to ensure supply & improve for the end-to-end procurement process\nAct as S2P Super User to provide frontline support\nSupport global program deployment include UAT and training stakeholders\nWhat will make you successful...\n\nDegree in Procurement, Supply Chain, Business Administration or related disciplines\nProfessional qualifications of CIPS will be an advantage\nMinimum 4 years of related work experience in sizable organization\nSolid track record in dealing with contract terms\nExperience in managing marketing & sales categories will be an advantage\nExperience in managing tendering process and preparation of tender documents\nProactive, self-motivated with mature business acumen\nStrong analytical and communication skills\nGood interpersonal and influencing skills\nExperience in SAP and Ariba Easybuy will be an advantage\nProficient is both written and spoken English and Chinese, fluent in Mandarin is a plus", "employment_types": ["Full Time", "Permanent"], "selling_points": ["Purchasing, sourcing and admin work", "5 days work week, Birthday Leave, Free Goods", "Fresh graduates will be considered"], "locations": ["Causeway Bay"], "categories": ["Admin & HR", "Clerical / Admin Staff", "Merchandising & Purchasing", "Procurement / Purchasing / Sourcing", "Sales, CS & Business Devpt", "Sales Administration"], "post_time": "2022-01-13T07:07:49Z", "salary": {"currency": null, "max": null, "min": null, "period": "monthly", "term": null}, "salary_visible": false, "title_keywords": ["administrative assistant"], "responsibilities": ["management", "provide support", "cost", "uat", "tender documents", "analysis", "compliance", "quality", "audit", "market research", "develop", "evaluate", "tendering", "communication", "liaise with", "administration"], "requirements": {"degrees": ["degree"], "majors": ["related disciplines", "business administration"], "languages": ["english", "chinese", "mandarin"], "language_level": ["fluent", "proficient"], "hard_skills": ["plus", "sap", "professional qualifications", "analysis", "make", "deployment", "acumen"], "soft_skills": ["communication skills", "self-motivated", "mature", "business acumen", "proactive", "interpersonal"], "languages_combined": [{"language": "english", "language_level": ["fluent", "proficient"]}, {"language": "chinese", "language_level": ["fluent", "proficient"]}, {"language": "mandarin", "language_level": ["fluent", "proficient"]}]}, "experience_required": {"duration": ["minimum 4 years"], "field": ["related", "sizable organization", "marketing"]}}, {"job_id": "100003009044374", "location_code": "hk", "company": "Meijer Trading Limited", "job_title": "Senior Sourcing Specialist for Stationery and Seasonal Crafts", "description": "In a nutshell\n\nProvide support to the department to deliver great product at supermarket price by fulfilling our Global Sourcing Strategy and successfully achieve our targets of the department\n\nWhat I need to do\n\nAssist Merchandiser / Senior Merchandiser on implementing all aspects of the department strategy to deliver all KPIs including shipment and sales participation targets\nUnderstand the use of Periodic Shipment Report in the management of shipment position of the department\nSupport Merchandiser / Senior Merchandiser in the sourcing processes, administrative work and documentations filing, from supplier engagement, supplier set up through to shipment delivery\nLiaise with suppliers on quotation sheets submission and ensuring samples are delivered to our UK colleagues on a timely basis\nSupport the order management process from purchase order to shipment delivery; maintain accurate purchase order records and critical path trackers, monitoring delivery and flagging potential risk on a timely manner\nAssist in the sealing and approval process from order through to delivery with accurate record keeping\nEstablish strong communication with UK & Asia colleagues and suppliers via weekly progress meetings, e-mails, SKYPE and trips, etc.\nAttend weekly progress meetings with cross functional colleagues in Asia, UK colleagues and suppliers to provide a clear visibility of order status\nHave a clear understanding of our operating procedures and be familiar with all necessary systems and our ways-of-working\nUnderstand our business vision and goal and play a positive role in making Sainsbury\u2019s Asia a great place to work\n\nWhat I need to know\n\n1-2 years working experience in Merchandising is preferred but not limited to.\nGood written and spoken English and Chinese (Cantonese & Mandarin)\nGood communication skills\nUniversity degree and above is prefer\nWe offer a competitive package, including a 5 day week, 17 days Annual Leave, double pay,\u00a0performance bonus,\u00a0MPF, a medical scheme, flexible working environment, plenty of work variety and a great team atmosphere. Interested candidates please go to the website below for application.\nhttps://sainsburys.jobs/asia/", "employment_types": ["Full Time"], "selling_points": ["Executing company's sourcing strategy", "Managing vendors and product development", "Stationery and Seasonal Crafts"], "locations": ["Tsim Sha Tsui"], "categories": ["Merchandising & Purchasing", "Procurement / Purchasing / Sourcing"], "post_time": "2022-01-13T03:53:38Z", "salary": {"currency": null, "max": null, "min": null, "period": "monthly", "term": null}, "salary_visible": false, "title_keywords": ["specialist"], "responsibilities": ["provide support", "management", "order management", "administrative work", "mpf", "quotation", "monitoring", "a timely manner", "procedures", "systems", "communication", "merchandising", "purchase", "maintain", "kpis", "liaise with suppliers", "report"], "requirements": {"degrees": ["university degree"], "majors": [], "languages": ["cantonese", "english", "chinese", "mandarin"], "language_level": ["good"], "hard_skills": ["goal", "scheme", "documentations"], "soft_skills": ["flexible", "communication skills", "timely", "communication", "clear", "accurate", "positive"], "languages_combined": [{"language": "cantonese", "language_level": ["good"]}, {"language": "english", "language_level": ["good"]}, {"language": "chinese", "language_level": ["good"]}, {"language": "mandarin", "language_level": ["good"]}]}, "experience_required": {"duration": ["1-2 years"], "field": ["merchandising"]}}, {"job_id": "100003009051145", "location_code": "hk", "company": "Corporate HR Management Consultancy Limited", "job_title": "Buyer (FMCG) / Manager, Asst. Manager, Executive - Sales & Marketing (FMCG)", "description": "Job Duties:\n\nThe scope of your job responsibilities will include but is not limited to the following:\n\nComprehend petty cash management and efficiency analysis to ensure proper cashflow statements;\nMaintain and monitor procurement and supply management in relation to current suppliers, credit term maintenance, and marginal cost evaluations;\nAssist in sourcing items as they relate to all functions of the restaurants including but not limited to food, drink, structural, and miscellaneous goods;\nAssistant accounting and human resource divisions with Owlsome group as needed at the instruction and guidance of the general manager;\nFulfil roster and shift duties across multiple restaurants as needed as the instruction and guidance of the general manager;\nAssist in coordination of activities and guidelines set out by the general manager in relation to marketing, community, or group related activities as it relates to any or all of our restaurant locations;\nWork hand in hand with shop managers in the daily operations of the business to help provide timely information, proper maintenance, and effective leadership as outlined and instructed by the General Manager of Owlsome restaurants;\nIn addition to the duties which this job normally entails, you may from time to time be required to undertake additional or other duties as necessary to meet the needs of the Company\u2019s business;\nActively participate and support\u00a0outside office company-held events occasionally;\nAny company events activities as required.\nInterested candidates please send full resume with expected salary by clicking \u201cApply Now\u201d.\n\n\nOur company is an equal opportunity employer. It provides equal opportunity to all employees and applicants for employment in accordance with all applicable laws and regulations.\n\nPersonal data collected will be treated in the strictest confidence and only be used for recruitment related purpose.", "employment_types": ["Full Time"], "selling_points": [], "locations": ["Not Specified"], "categories": ["Sales, CS & Business Devpt", "Business Development", "Merchandising & Purchasing", "Procurement / Purchasing / Sourcing", "Account Servicing"], "post_time": "2022-01-15T03:28:08Z", "salary": {"currency": null, "max": null, "min": null, "period": "monthly", "term": null}, "salary_visible": false, "title_keywords": ["asst. manager", "manager", "sales", "executive"], "responsibilities": ["guidance", "management", "cost", "maintenance", "other duties", "guidelines", "analysis", "monitor", "daily operations", "maintain", "coordination"], "requirements": {"degrees": [], "majors": [], "languages": [], "language_level": [], "hard_skills": ["analysis", "maintenance"], "soft_skills": ["timely", "leadership", "coordination"], "languages_combined": []}, "experience_required": {"duration": [], "field": []}}, {"job_id": "100003009050590", "location_code": "hk", "company": "Green Delta Limited", "job_title": "Assistant Merchandiser / Merchandiser", "description": "Job Duties:\n\nHands on source-to-pay procurement process with multiple categories focus (mainly in IT & Telcom, Facility Services & Marketing Services), mainly operates in company's in-house group procurement platform.\nProvides full process support with internal stakeholders and external suppliers in order to achieve business targets by implementing sourcing & procurement execution within the group procurement policy and procedures.\u00a0\nEnhance user experience both internal & external by sound project planning & correspondence, as well as timely reactions in addressing queries & problem solving.\nKeep constant collaboration with central Group Procurement team in Hangzhou, as well as other regional teams, to maintain the synergy of category strategies, process improvement, and best practice sharing of overseas procurement operation.\nCollaborates with other functions such as Finance, Legal, HR in maintaining overall process control and mutual key performance metrics.\nExecuting project-based sourcing with guidance of the line manager. Develop local category strategy and expand local supply base.\nData reporting on a regular basis.\n\nRequirements:\n\nBachelor's Degree or above\nWorking experience in procurement or similar scope is an advantage\nFast learning in a very dynamic and fast pace environment\nPatient with sense of customer care, open-minded and willing to pro-actively communicate with others\nProficient in English and Mandarin, other language is a plus\nFamiliar with online procurement tools as well as major IT tools, advanced user of Excel and Power Point, or database tools is a plus\nCandidate with no experiences or fresh graduate will also be considered", "employment_types": ["Full Time", "Permanent"], "selling_points": [], "locations": ["Lai Chi Kok"], "categories": ["Merchandising & Purchasing", "Sundries", "Procurement / Purchasing / Sourcing"], "post_time": "2022-01-15T03:51:12Z", "salary": {"currency": null, "max": null, "min": null, "period": "monthly", "term": null}, "salary_visible": false, "title_keywords": ["merchandiser", "assistant merchandiser"], "responsibilities": ["guidance", "project planning", "control", "reporting", "maintaining", "data", "hr", "procedures", "user experience", "teams", "performance metrics", "develop", "maintain", "executing"], "requirements": {"degrees": ["degree or above", "bachelor", "fresh graduate"], "majors": [], "languages": ["english", "mandarin"], "language_level": ["proficient"], "hard_skills": ["excel", "plus", "no", "dynamic", "power point"], "soft_skills": ["advanced", "open-minded", "dynamic", "learning", "patient"], "languages_combined": [{"language": "english", "language_level": ["proficient"]}, {"language": "mandarin", "language_level": ["proficient"]}]}, "experience_required": {"duration": [], "field": ["procurement"]}}, {"job_id": "100003009044488", "location_code": "hk", "company": "Shiamas Limited", "job_title": "Assistant Merchandiser", "description": "\n\nBrilliant job opportunity with top tier ibank!\n\nYour new company\nOur client is a global leading investment bank with representation in more than 42 markets spreading across Australia, New Zealand, Asia Pacific, Middle East, Europe and America. As they continue on their journey to build a global business and to support their customers, they are committed to attract and retain the best talents.\n\nWe are looking for an experienced professional to join its team in Asia to support the sourcing activities in its China operations.\n\nYour new role\nAs a Procurement Specialist, you will be involved in:\n\nSupport all Sourcing activities for the China business.\nDay-to-day involvement in contractual and commercial matters and issues arising within the China Business. This will include, but not limited to, tender preparation, bid analysis, contract preparation and award, contract negotiation and administration, vendor management and external representation of the sourcing function.\nWorking either autonomously or closely with business partners to develop sourcing strategies and lead commercial negotiations with vendors on a local or regional basis\nCarry out financial risk assessment studies and procedural evaluations aimed at forming an independent assessment on project financial status\n\nWhat you'll need to succeed\nJoin us, if you are/have\n\nBachelors Degree in Business or other related degree program\n5-7 years' experience in strategic sourcing, contract negotiation, etc\nExcellent verbal, written, presentation and interpersonal skills in Mandarin and English\nStrong analytical, writing and critical thinking skills; successful candidate must be able to analyze offers, business cases (including financial reports), processes and present a summary quantifying differences in a clear concise manner\n\nWhat you'll get in return\nThis position offers a highly desired strong career progression and an attractive salary.\n\nWhat you need to do now\n\nIf you're interested in this role, click 'apply now'", "employment_types": ["Full Time"], "selling_points": ["Diploma holder in Purchasing or equivalent", "At least 2 years\u2019 relevant working experience", "Immediate available preferred"], "locations": ["Not Specified"], "categories": ["Merchandising & Purchasing", "Sundries", "Others", "Procurement / Purchasing / Sourcing"], "post_time": "2022-01-13T08:02:48Z", "salary": {"currency": null, "max": null, "min": null, "period": "monthly", "term": null}, "salary_visible": false, "title_keywords": ["assistant merchandiser"], "responsibilities": ["management", "financial reports", "operations", "analysis", "develop", "tender preparation", "administration"], "requirements": {"degrees": ["degree"], "majors": ["business"], "languages": ["english", "mandarin"], "language_level": ["excellent"], "hard_skills": ["analysis", "vendor"], "soft_skills": ["independent", "negotiation", "interested in", "clear", "committed", "interpersonal skills", "presentation"], "languages_combined": [{"language": "english", "language_level": ["excellent"]}, {"language": "mandarin", "language_level": ["excellent"]}]}, "experience_required": {"duration": ["5-7 years"], "field": []}}, {"job_id": "100003009047448", "location_code": "hk", "company": "Dah Chong Hong, Limited", "job_title": "Assistant Trading Officer / Trainee (Fresh Graduate Welcome)", "description": "Responsibilities:\n\nSupply chain and order management\nProject management on product development\nSourcing for new vendors and new products\nActively involve and coordinate with the team on problem solving related to material and component supply; quality and engineering issues, to keep product development schedule and order schedule on time.\nPrice negotiation\nHandle sample approval and delivery processes\nLiaise with vendors, internal departments and oversea customers to ensure timely and accurate response at all time.\nBusiness travel (China or other countries) is required\n\nRequired Qualifications:\n\nAt least 5 years or above merchandising experience in electric appliance\nDegree holder\nProficiency in PC application\nHard working, details minded, well-organized.\nAble to work under pressure and well team oriented\nAvailable to make frequent trips outside office, to mainland China or Overseas are required\nFluent in Chinese and English\n\nWe offer an attractive remuneration package and comprehensive fringe benefits to suitable candidate.\u00a0 Interested parties, please send your application together with a detail resume including availability, present and expected salary,by e-mail via \"Apply now\" . Your interest will be treated in strict confidence and only shortlisted candidates will be notified. All personal data will be treated in strict confidence and collected for recruitment purposes only.", "employment_types": ["Full Time", "Permanent"], "selling_points": [], "locations": ["Kowloon Bay"], "categories": ["Merchandising & Purchasing", "Procurement / Purchasing / Sourcing", "Sales, CS & Business Devpt", "Channel / Distribution", "Others", "Trading"], "post_time": "2022-01-14T03:06:58Z", "salary": {"currency": null, "max": null, "min": null, "period": "monthly", "term": null}, "salary_visible": false, "title_keywords": ["officer", "assistant", "trainee"], "responsibilities": ["order management", "price negotiation", "coordinate with", "quality", "merchandising", "project management", "schedule", "liaise with", "work under pressure"], "requirements": {"degrees": ["degree holder"], "majors": [], "languages": ["english", "chinese"], "language_level": ["fluent"], "hard_skills": ["problem solving", "project management", "make", "pc"], "soft_skills": ["negotiation", "timely", "hard working", "well-organized", "problem solving", "project management", "accurate", "work under pressure"], "languages_combined": [{"language": "english", "language_level": ["fluent"]}, {"language": "chinese", "language_level": ["fluent"]}]}, "experience_required": {"duration": ["at least 5 years"], "field": ["merchandising"]}}]