[{"job_id": "100003009054033", "location_code": "hk", "company": "Creative Concepts Manufacturing Limited", "job_title": "SENIOR MERCHANDISER", "description": "Liaise with overseas clients and factory independently\nHandle Orders from sampling to shipment in appropriate manner .\nAble to handle large quantity orders and Co-ordinate with colleagues in different departments\nTravel to China and Fluent Mandarin + English is a mandatory\nFollowing projects from sample collection to product development is a requirement\nExperience for minimum 5 years\nStrong negotiation, presentation, problem solving skill and able to work under pressure\nMake order status report on daily-weekly basis .\nExperience in Sundries , Novelties , Product Development , kitchen items , General Merchandise is a must .\nAble to source and find product through website and company database in 2 days maximum.\nWork with the sourcing and merchandising team on orders , queries , shipments, Quality Assurance Department.\nProficient in computers and Chinese typing is mandatory ( Excel , Word , PowerPoint , Outlook )\n5 DAY WORKS\u00a0\n\nInterested parties click \"APPLY NOW\" to submit your application.\n\nPersonal data collected will be used for recruitment purpose only.", "employment_types": ["Full Time", "Permanent"], "selling_points": [], "locations": ["Hung Hom"], "categories": ["Manufacturing", "Product Development / Management", "Merchandising & Purchasing", "Sundries", "Procurement / Purchasing / Sourcing"], "post_time": "2022-01-17T08:08:35Z", "salary": {"currency": null, "max": null, "min": null, "period": "monthly", "term": null}, "salary_visible": false, "title_keywords": ["senior merchandiser"], "responsibilities": ["co-ordinate with", "work under pressure", "merchandising", "website", "quality", "database", "liaise with", "report"], "requirements": {"degrees": [], "majors": [], "languages": ["english", "chinese", "mandarin"], "language_level": ["proficient", "fluent"], "hard_skills": ["excel", "word", "typing", "powerpoint", "problem solving", "make", "outlook"], "soft_skills": ["independently", "negotiation", "problem solving skill", "presentation", "work under pressure"], "languages_combined": [{"language": "english", "language_level": []}, {"language": "chinese", "language_level": ["proficient"]}, {"language": "mandarin", "language_level": ["fluent"]}]}, "experience_required": {"duration": ["minimum 5 years"], "field": ["product development"]}}, {"job_id": "100003009055216", "location_code": "hk", "company": "Regent Lane Ltd", "job_title": "Assistant Marketing Manager & Merchandisers & Designers", "description": "At least 3-4 years\u00a0working experience in Stationery, Health & Beauty Products\nForm 6 or above, fluent in English, Putonghua and Cantonese\nGood interpersonal / communication skills\nAble to work independently under pressure, traveling and overtime required\nResponsible and self-motivated", "employment_types": ["Full Time"], "selling_points": ["5 mins to MTR", "Attractive Benefits", "Marketing & Promotion Company"], "locations": ["Ngau Tau Kok"], "categories": ["Design", "Graphics", "Marketing / Public Relations", "Marketing - Brand / Product Management", "Merchandising & Purchasing", "Sundries"], "post_time": "2022-01-18T01:49:08Z", "salary": {"currency": null, "max": null, "min": null, "period": "monthly", "term": null}, "salary_visible": false, "title_keywords": ["assistant marketing manager"], "responsibilities": ["communication", "stationery"], "requirements": {"degrees": [], "majors": [], "languages": ["cantonese", "putonghua", "english"], "language_level": ["fluent"], "hard_skills": [], "soft_skills": ["communication skills", "work independently", "self-motivated", "under pressure", "responsible", "interpersonal"], "languages_combined": [{"language": "cantonese", "language_level": ["fluent"]}, {"language": "putonghua", "language_level": ["fluent"]}, {"language": "english", "language_level": ["fluent"]}]}, "experience_required": {"duration": ["at least 3-4 years"], "field": ["beauty"]}}, {"job_id": "100003009028237", "location_code": "hk", "company": "Creative China Creations Limited", "job_title": "Production & Quality Engineer (Consumer Products & Sundries)", "description": "We are looking for high caliber candidates to fill the following positions:\n\n\u00a0\nAssistant Marketing Manager\n\n\u00a0Job duty:\n\nProvide good account servicing to clients\nExpand company business and explore new business opportunity\nExecute retail redemption programs / exhibition & event activities\nA keen attention to detail and budgetary restraints\nAbility to think strategically and execute tactically\nProvide innovative and collaborative experience for clients, suppliers and business partners\nAble to work under pressure and meet deadlines\n\n\u00a0Requirement:\n\nDegree holder in any disciplines\nMinimum 5 years\u2019 relevant experience in sales and marketing field\nExperience in advertising account service or retail operation is an asset\nEnergetic, self-motivated, presentable, detail-minded and able to work independently\nGood communication, presentation and interpersonal skill\nFluency in spoken & written English, Cantonese and Mandarin\nPC knowledge in MS Excel, Word & PowerPoint and Chinese Processing\n\n(Less experience will be considered as Marketing Executive)\n\nMerchandisers\n\n\u00a0\u00a0Requirement:\n\nTertiary education with min. 3 years solid experience\u00a0\nProficient in manufacturing process, sourcing and quality control, able to handle order independently\nResponsible for order follow up from sample development to delivery, including product presentations and cost analysis\nExperience in licensing products would be an advantage\nFamiliar to the rules of trading in Mainland China would be an advantage\nMature, hard-working, well organized, willing to work under pressure and independently\u00a0\u00a0\n\n(More experience will be considered as Senior Merchandiser)\n\n\u00a0Product / Graphic Designers\u00a0\n\n\u00a0\u00a0Requirement:\n\nDiploma / Degree Holder in Product / Graphic Design or related discipline\nMin. 5 years product design experience\nGood illustration skill is an asset\nCreative, self-initiative, independent, good market and fashion sense\nProficient in PC computer, Photoshop / Illustrator\nAbility to work with cross-functional team\nMature, hard-working, willing to work under pressure and independently\u00a0\n\n\u00a0\u00a0Immediate availability is preferred\n\n\u00a0\u00a0Interested parties, please email your full CV and expected salary\u00a0by clicking APPLY NOW", "employment_types": ["Full Time", "Permanent"], "selling_points": ["Good understanding on global markets", "Able to work independently & meet tight deadlines", "Preferable 5 years of work experience"], "locations": ["Ngau Tau Kok"], "categories": ["Manufacturing", "Product Development / Management", "Merchandising & Purchasing", "Sundries", "Procurement / Purchasing / Sourcing"], "post_time": "2022-01-17T16:20:53Z", "salary": {"currency": null, "max": null, "min": null, "period": "monthly", "term": null}, "salary_visible": false, "title_keywords": ["engineer"], "responsibilities": ["advertising", "graphic design", "presentations", "communication", "product design", "quality control", "cost analysis", "work under pressure"], "requirements": {"degrees": ["diploma", "degree holder"], "majors": ["graphic design", "any disciplines"], "languages": ["cantonese", "english", "chinese", "mandarin"], "language_level": ["fluency"], "hard_skills": ["analysis", "illustration", "word", "powerpoint", "presentations", "illustrator", "ms excel", "pc", "pc knowledge", "processing", "photoshop"], "soft_skills": ["collaborative", "communication", "hard-working", "work under pressure", "detail-minded", "independent", "keen", "mature", "presentable", "self-initiative", "meet deadlines", "creative", "presentation", "work independently", "interpersonal skill", "attention to detail", "think strategically", "energetic", "self-motivated", "independently", "responsible", "well organized", "innovative"], "languages_combined": [{"language": "cantonese", "language_level": ["fluency"]}, {"language": "english", "language_level": ["fluency"]}, {"language": "chinese", "language_level": []}, {"language": "mandarin", "language_level": ["fluency"]}]}, "experience_required": {"duration": ["3 years", "5 years", "minimum 5 years"], "field": ["advertising", "business", "relevant experience", "marketing", "operation", "product design", "retail"]}}, {"job_id": "100003009056200", "location_code": "hk", "company": "ME Job Personnel Limited", "job_title": "Merchandiser & Senior Merchandiser  (Label / Packaging )", "description": "Job Requirements:\n\nDevelop and implement the Creative China Creations Limited (CCCL) Vendor Quality Management System across the supplier network in China as well as CCCL own facility in Mainland China in conjunction with the product development team at Hong Kong head office.\nFacilitate correspondence on internal Quality Control checks between Hong Kong office (Product Development Team) & CCCL factory in Mainland China as well as 3rd party suppliers\nCommunicate with Hong Kong team members on technical specifications & requirements through the product development process to ensure quality standards for both product functionality, safety and compliance are met.\nEstablish protocols with supplier production teams to develop high-volume and quick- turnaround manufacturing processes and capabilities for new product implementation (NPI)\nConduct quality audits (IQC, IPQC & OQC) for pre- and mass-production at suppliers.\nIntroduce protocols for final goods inspection with supplier QC team and third-party inspectors, and SOPs for in-time reporting and rapid corrective/preventive action plan (CAPA).\nSuggest quality control enhancements for both infrastructure & ERP systems as well as specific consumer products.\nUtilize inspection metrics and quality improvement/control tools (e.g., DOE & FMEA) to drive continuous quality improvement with suppliers.\nLiaise & coordinate 3rd party inspections with various companies such as SGS, Intertek, BV, etc and help establish inspection mandates & protocols to follow.\nMonitor market sale and return data and provide warning alerts to head office for quality risk management.\nLead company initiative to support overseas suppliers to attain C-TPAT validation (Customs \u2013 Trade Partnership against Terrorism - USA) as well as meet other audit or client specific audit standards such as ISO, ETL, UL, CE, BSCI, ICTI standards.\nEXCELLENT COMMAND IN WRITTEN & SPOKEN ENGLISH, CANTONESE & MANDARIN SKILLS\nAble to Travel to China for implementation and monitoring of Quality Control systems.\nCandidates with at least 5 years\u2019 experience is preferred but not a requirement.\nThe ability to work independent or part of a larger team, with the mentality & work ethic of a leader.\nFamiliarity with Quality control systems for consumer products is preferred.\nA team leader who exhibits leadership qualities and is able to work under pressure and within time constraints.\nPermanent Hong Kong ID card Holder.\nFlexible working times and willing to work after hours if needed.\n\n\u00a0Key requirements:\n\nDegree/Diploma holder, with at least 5 years of relevant experience\nGood understanding on US/UK/EU Markets\nExcellent command in Cantonese, English and Mandarin\nGood communication and interpersonal skills to work with counterparts\nAble to work independently and meet tight deadlines\nProficient in computer skills and MS Office Applications\nUnderstand electronic circuitry in component level.\nHands on experience in operating test equipment such as voltmeter, ammeter and oscilloscope\nCoordinate weekly customer complaint meeting.\n\nInterested applicants please send your English application along with cover letter and detailed resume with current and expected salary clearly stated to \u201cApply Now\u201d.\n\nAll Personal data collected will be used for recruitment purpose only.\n", "employment_types": ["Full Time"], "selling_points": [], "locations": ["Kwai Tsing Area"], "categories": ["Merchandising & Purchasing", "Sundries", "Others", "Procurement / Purchasing / Sourcing"], "post_time": "2022-01-18T03:32:01Z", "salary": {"currency": null, "max": null, "min": null, "period": "monthly", "term": null}, "salary_visible": false, "title_keywords": ["merchandiser", "senior merchandiser"], "responsibilities": ["liaise", "data", "quality", "audit", "communication", "plan", "personal data", "work under pressure", "control", "compliance", "teams", "implementation", "infrastructure", "develop", "monitor", "reporting", "management", "monitoring", "inspection", "specifications", "sops", "audits", "communicate with", "systems", "coordinate", "recruitment", "quality control"], "requirements": {"degrees": ["diploma holder", "degree"], "majors": [], "languages": ["cantonese", "english", "mandarin"], "language_level": ["excellent"], "hard_skills": ["erp systems", "id", "vendor", "c", "computer skills", "rapid", "ms office"], "soft_skills": ["flexible", "work independently", "meet tight deadlines", "independent", "detailed", "communication and interpersonal skills", "hands on", "work ethic", "creative", "leadership", "initiative", "work under pressure"], "languages_combined": [{"language": "cantonese", "language_level": ["excellent", "excellent"]}, {"language": "english", "language_level": ["excellent", "excellent"]}, {"language": "mandarin", "language_level": ["excellent", "excellent"]}]}, "experience_required": {"duration": ["at least 5 years"], "field": ["relevant experience"]}}, {"job_id": "100003009028244", "location_code": "hk", "company": "Creative China Creations Limited", "job_title": "Sourcing Coordinator/ Merchandiser /Sr. Merchandiser /Product Manager (Consumer Products/ Sundries)", "description": "Three Sizable Non-Garment\u00a0Companies (Two \"USA Buying Office\" & One \"EEC Buying Office\")\u00a0are URGENTLY looking for a suitable candidate for the Merchandising position.\n\nRequirements:\n\nF.5 or above\nAt least 3-5 years experience in\u00a0merchandising which one in\u00a0(Label /Packaging) items\nGood communicate across teams involving multiple partners\nDeliver and succeed in the challenging arena of Hardline\nDetail and a strong sense of pro-activity will also be part of your arsenal\nGood command of written and spoken English and Chinese\nCommunication skills to analyze, projects manage and delivery\n\nSalary : Negotiable\n\nLocation : Kwai Chung\n\nOurclients have offered a comprehensive benefits package to the successful candidate.\n\nInterested parties, please send a detailed resume by clicking \"Apply Now\" or visit our company website find email address (ATTN : Eddy.Tse) Hotline : 27066333.\n\nTo learn more about Me Job Personnel Limited., visit http://www.mejob.com.hk/ .\n\nAll information collected is strictly for recruitment purpose.", "employment_types": ["Full Time", "Permanent"], "selling_points": ["double pay and performance bonus", "Good understanding on global markets", "With at least 5 years of relevant experience"], "locations": ["Ngau Tau Kok"], "categories": ["Manufacturing", "Product Development / Management", "Merchandising & Purchasing", "Sundries", "Procurement / Purchasing / Sourcing"], "post_time": "2022-01-17T16:20:53Z", "salary": {"currency": null, "max": null, "min": null, "period": "monthly", "term": null}, "salary_visible": false, "title_keywords": ["merchandiser", "product manager", "coordinator", "sr. merchandiser"], "responsibilities": ["communication", "teams", "merchandising"], "requirements": {"degrees": [], "majors": [], "languages": ["english", "chinese"], "language_level": ["good command"], "hard_skills": [], "soft_skills": ["communication skills"], "languages_combined": [{"language": "english", "language_level": ["good command"]}, {"language": "chinese", "language_level": ["good command"]}]}, "experience_required": {"duration": ["at least 3-5 years"], "field": ["merchandising"]}}, {"job_id": "100003009051777", "location_code": "hk", "company": "Citistore (Hong Kong) Limited", "job_title": "Merchandising Assistant", "description": "Job Requirements:\u00a0\n\nMinimum 5 years merchandising or relevant experience in Trading or Manufacturing Company. (Sourcing, Product development experience)\nMotivated, Organized, and able to work efficiently to meet the deadlines of buyers\nEXCELLENT COMMAND IN WRITTEN & SPOKEN ENGLISH, CANTONESE & MANDARIN SKILLS\nAble to communicate with suppliers and overseas customers\nResponsible, willing to learn, exhibit a positive attitude and work overtime\nExcellent knowledge of product cost breakdown and production process.\nProficient in material sourcing and supplier evaluation and management.\nExcellent and successful in price negotiation and problem solving skills\nTravel to China for supplier evaluation, management, follow-up, and inspection.\nProficient in PC applications (Microsoft Word, Excel, Microsoft Office applications).\nAn analytical and strategic thinker who is efficient, organized, and attentive to details and able to motivate staff and work under time deadlines.\nStrong sourcing skills and network of potential suppliers that allows the company to source directly through the most cost efficient and competent factories.\nCommunicate clearly to suppliers, including lead time, capacity allocation, pricing and resource allocation to ensure reliable service, quality and low-cost procurement.\nCoordinate with factories for manufacturing process and ensure on time shipment\nSelf-motivated, detailed oriented, a team player and able to work under pressure.\u00a0\nExperienced to supervise merchandising team, & be a team leader.\nCustomer-oriented, effective interpersonal and communication skills\nAble to work independently or part of a team with overseas customers and vendors\nEffectively manage and review vendor base for optimal sourcing results and possess an extensive sourcing network and excellent relationships with vendors.\nProduct management including product development, product selection, Target Negotiation, placement order, pricing.\nAnalyze the marketplace, customers and competitors to determine the right features to bring to market\u00a0\u00a0\nDaily communications with buyers, laboratories and vendors, following through all samples, testing, production to shipments\nEnsuring an effective merchandising value chain which produces goods in good quality standard and meet tight delivery\nGood sourcing experience for USA and EU markets and are familiar with sourcing Websites such as Alibaba.com, globalsources.com, and other sourcing sites.\nA team leader who exhibits leadership qualities and is able to work under pressure and within time constraints.\nPermanent Hong Kong ID card Holder.\nFlexible working times and willing to work after hours if needed.\n\n\nKey responsibilities:\n\nTake the lead in the end-to-end product sourcing cycle from product development, price negotiation to production of consumer products\nWork with the buyers to understand the product and order requirement\nCommunicate with vendors and factories to ensure on-time delivery and resolve any potential problems\nExecute and review existing internal systems and policies to ensure smooth operations and meeting company standards\n\n\nKey requirements:\n\nDegree/Diploma holder, with at least 5 years of relevant experience\nGood understanding on global Markets\nExcellent command in Cantonese, English and Mandarin\nGood communication and interpersonal skills to work with counterparts\nAble to work independently and meet tight deadlines\nProficient in computer skills and MS Office Applications\n\n\nInterested applicants please send your English application along with cover letter and detailed resume with current and expected salary clearly stated to \u201cApply Now\u201d.\n\nAll Personal data collected will be used for recruitment purpose only.", "employment_types": ["Full Time", "Permanent"], "selling_points": ["Degree holder in related discipline", "Administrative support to merchandising team", "Immediate available is preferred"], "locations": ["Tsuen Wan Area"], "categories": ["Merchandising & Purchasing", "Sundries", "Others", "Procurement / Purchasing / Sourcing"], "post_time": "2022-01-17T01:03:24Z", "salary": {"currency": null, "max": null, "min": null, "period": "monthly", "term": null}, "salary_visible": false, "title_keywords": ["merchandising assistant"], "responsibilities": ["communicate with", "price negotiation", "policies", "review", "communication", "recruitment", "ensure smooth operations", "personal data", "internal systems"], "requirements": {"degrees": [], "majors": [], "languages": ["cantonese", "english", "mandarin"], "language_level": ["excellent"], "hard_skills": ["excel", "microsoft word", "microsoft office", "id", "vendor", "pc applications", "problem solving skills"], "soft_skills": ["work overtime", "team player", "leadership", "work under pressure", "efficient", "customer-oriented", "reliable", "interpersonal", "organized", "communication skills", "work independently", "negotiation", "competent", "willing to learn", "extensive", "flexible", "self-motivated", "detailed oriented", "responsible", "attentive to details", "positive attitude", "motivated", "problem solving skills"], "languages_combined": [{"language": "cantonese", "language_level": ["excellent", "excellent"]}, {"language": "english", "language_level": ["excellent", "excellent"]}, {"language": "mandarin", "language_level": ["excellent", "excellent"]}]}, "experience_required": {"duration": ["minimum 5 years"], "field": ["manufacturing", "merchandising", "relevant experience", "product development", "trading"]}}, {"job_id": "100003009041176", "location_code": "hk", "company": "Mid Ocean Hong Kong Ltd", "job_title": "Procurement Officer (Promotional Products)", "description": "Overview:\n\nOrenji Creation Limited is a design, gift and premium company that provides professional one-stop service to international well-known brands in Asia Pacific. To Cope with our rapid expansion, we are now inviting high caliber candidate pursuing to join our team in Hong Kong.\n\nJob Requirement:\n\nDiploma holder or above\n1-2 years or above relevant working experience (Fresh Graduate are also welcomed)\nSolid knowledge of gift & premium industry\nStrong in Product Development\nHardworking, Self-motivated, Independent, Attention to detail, Teamwork spirit\nStrong negotiation skill\nAble to work under pressure and tight deadline\nProficiency in PC skills\nFluent in written and spoken English and Mandarin\nImmediate available preferred\n\nResponsibilities:\n\nTo source factories for quality comparison\nTo coordinate with internal parities and follow up production from product development to delivery\nClosely Monitor the production process\nTo solve problem with the factories to ensure product quality and meet tight schedule\nCoordinate with Lab Test Company, ensure the product meet Client\u2019s product safety standard\nFrequent Travel to PRC is required\n\nInterested parties please send a cover letter stating your expected salary, resume and a full set of your portfolio to us.\n\n*All information will be treated as confidential and used solely for recruitment purposes.\n\nInterested parties, please click Apply Now to submit your full resume.", "employment_types": ["Full Time", "Permanent"], "selling_points": ["Good command in English and Mandarin", "2 years relevant experience", "Salary negotiable ; 5 days working ; double pay"], "locations": ["Lai Chi Kok"], "categories": ["Merchandising & Purchasing", "Sundries", "Others", "Procurement / Purchasing / Sourcing"], "post_time": "2022-01-13T05:33:57Z", "salary": {"currency": null, "max": null, "min": null, "period": "monthly", "term": null}, "salary_visible": false, "title_keywords": ["procurement officer"], "responsibilities": ["production process", "monitor", "quality", "coordinate with", "schedule"], "requirements": {"degrees": ["diploma holder", "fresh graduate"], "majors": [], "languages": ["english", "mandarin"], "language_level": ["fluent"], "hard_skills": ["pc skills"], "soft_skills": ["self-motivated", "independent", "teamwork spirit", "attention to detail", "negotiation skill", "hardworking", "work under pressure"], "languages_combined": [{"language": "english", "language_level": ["fluent"]}, {"language": "mandarin", "language_level": ["fluent"]}]}, "experience_required": {"duration": ["1-2 years"], "field": ["relevant working experience"]}}, {"job_id": "100003009040321", "location_code": "hk", "company": "REWE Far East Limited", "job_title": "Junior Merchandiser", "description": "KEY RESPONSIBILITIES:\n\nContact supplier to consolidate product and promotion information\nHandle price and promotion setup\nPrepare sales report and work out presentation file\nProvide general administrative support to the team\nAssist in ad-hoc duties as per assigned\n\n\u00a0JOB REQUIREMENTS:\n\nBachelor\u2019s Degree holder or above\nAt least 1 year of retail buying experience\nSelf-motivated, energetic, well-organized and able to work under pressure\nGood communication skills and good command of spoken & written English and Chinese\nProficiency in PC knowledge; familiar with Excel & Chinese Word\nImmediate available is highly preferred\n\nAn attractive remuneration package together with fringe benefits will be offered to the right candidate.\u00a0\u00a0Interested parties are invited to send your full resume with current and expected salary\u00a0by clicking \"Apply Now\".\n\nPersonal data collected will be used for recruitment purpose only.", "employment_types": ["Full Time", "Permanent"], "selling_points": ["Seasonal and Decoration items, Merchandising, S&D", "EU buying office, Mobile Working, Flex Working Hr", "13th Month Bonus, Discretionary Bonus"], "locations": ["Kwun Tong Area"], "categories": ["Merchandising & Purchasing", "Sundries", "Others"], "post_time": "2022-01-16T21:50:04Z", "salary": {"currency": null, "max": null, "min": null, "period": "monthly", "term": null}, "salary_visible": false, "title_keywords": ["junior merchandiser"], "responsibilities": ["general administrative support", "prepare sales", "contact", "ad-hoc duties", "setup", "report"], "requirements": {"degrees": ["bachelor", "degree holder"], "majors": [], "languages": ["english", "chinese"], "language_level": ["good command", "good"], "hard_skills": ["excel", "pc knowledge", "word"], "soft_skills": ["communication skills", "self-motivated", "well-organized", "energetic", "work under pressure"], "languages_combined": [{"language": "english", "language_level": ["good command", "good"]}, {"language": "chinese", "language_level": ["good command", "good"]}]}, "experience_required": {"duration": ["at least 1 year"], "field": ["retail"]}}, {"job_id": "100003009051979", "location_code": "hk", "company": "", "job_title": "Assistant Merchandiser", "description": "Key Responsibilities\n\nSupport daily operations in merchandising team to ensure smooth order processing and on-time delivery.\nAssist offer preparation and follow up from order placement until shipment for all purchased products.\nFacilitate effective communication with internal and external stakeholders such as German headquarters, suppliers, quality department and logistics department.\nEnsure order, costing and vendor information are recorded in appointed systems accurately and timely.\nWork closely with Quality Assurance team to meet company\u2019s quality requirements.\n\n\n\nJob Requirements\n\nBachelor\u2019s degree in a business-related subject is preferred but also other proficiencies are welcomed.\nExperience in merchandising positions or in a sourcing office is preferred. Fresh graduates are also welcomed to apply.\nEager to learn more about international trade business and ability to work in cross-cultural teams.\nAttention to details, a positive work attitude, structured, and able to organize multi-task is crucial.\nGood command of both written and spoken English and Chinese (Cantonese and Mandarin) is a must.\nGood computer knowledge (Microsoft office).\nImmediately available is preferable.\nFlexible to have business travel when required.\n\nIf you are interested in the position, please submit your full resume with cover letter, current and expected salary and available date via JobsDB.\n\nAll\u00a0personal information is collected for recruitment purpose only and will be treated in strict confidentiality.\u00a0\u00a0", "employment_types": ["Full Time", "Permanent"], "selling_points": [], "locations": ["Hung Hom"], "categories": ["Merchandising & Purchasing", "Sundries", "Others", "Procurement / Purchasing / Sourcing"], "post_time": "2022-01-17T01:44:45Z", "salary": {"currency": null, "max": null, "min": null, "period": "monthly", "term": null}, "salary_visible": false, "title_keywords": ["assistant merchandiser"], "responsibilities": ["systems", "quality", "merchandising", "communication", "daily operations", "logistics", "order processing"], "requirements": {"degrees": ["degree", "bachelor"], "majors": ["business"], "languages": ["cantonese", "english", "chinese", "mandarin"], "language_level": ["good command"], "hard_skills": ["microsoft office"], "soft_skills": ["flexible", "multi-task", "interested in", "eager to learn", "attention to details", "structured", "positive work attitude"], "languages_combined": [{"language": "cantonese", "language_level": ["good command"]}, {"language": "english", "language_level": ["good command"]}, {"language": "chinese", "language_level": ["good command"]}, {"language": "mandarin", "language_level": ["good command"]}]}, "experience_required": {"duration": [], "field": ["merchandising"]}}, {"job_id": "100003009051683", "location_code": "hk", "company": "Special Happy Limited", "job_title": "Merchandiser / Junior Merchandiser", "description": "A MEDIUM SIZED EXPORT FIRM IN\u00a0HUNG HOM\u00a0REQUIRES:\n\n-\u00a0 F.6\u00a0 or above\u00a0\n- Quotation, Sampling and Orders follow up etc.\n- Handle customers enquire\n- English is required and Mandarin is preferred\n- PC knowledge (Ms office, Email) is required\n- Minimum 2-3 years working experience\n- 5-Day work week\n- Bank Holidays\n\n\u00a0For any enquiries,\u00a0 please \u00a0Call 2303-0343.\u00a0", "employment_types": ["Full Time", "Permanent"], "selling_points": [], "locations": ["Tsuen Wan Area"], "categories": ["Merchandising & Purchasing", "Sundries", "Others", "Others", "Trading"], "post_time": "2022-01-16T21:50:45Z", "salary": {"currency": null, "max": null, "min": null, "period": "monthly", "term": null}, "salary_visible": false, "title_keywords": ["merchandiser", "junior merchandiser"], "responsibilities": ["quotation"], "requirements": {"degrees": [], "majors": [], "languages": ["english", "mandarin"], "language_level": [], "hard_skills": ["pc knowledge", "ms office"], "soft_skills": [], "languages_combined": [{"language": "english", "language_level": []}, {"language": "mandarin", "language_level": []}]}, "experience_required": {"duration": ["minimum 2-3 years"], "field": []}}, {"job_id": "100003009049002", "location_code": "hk", "company": "Newell Rubbermaid Asia Pacific Limited", "job_title": "Senior Sourcing Analyst", "description": "Degree holder or at least 1 year relevant experience\nArrangement of samples, costing and follow up orders\nProactive & independent, aggressive & capable to cooperate with a team\nGood command of English & Mandarin\nAbility to work independently with overseas customers\nTo be responsible, hardworking and willing to work under pressure\nLess experience will consider to assist Merchandisers on paper work\n\n\nInterested parties, please apply by click Apply Now\n\nPersonal data will be used for recruitment purpose only.\n", "employment_types": ["Full Time", "Permanent"], "selling_points": ["Great career advancement", "Attractive Remuneration", "Sourcing function"], "locations": ["Kowloon Bay"], "categories": ["Merchandising & Purchasing", "Sundries"], "post_time": "2022-01-14T07:53:18Z", "salary": {"currency": null, "max": null, "min": null, "period": "monthly", "term": null}, "salary_visible": false, "title_keywords": ["analyst"], "responsibilities": ["follow up orders", "cooperate with", "work under pressure"], "requirements": {"degrees": ["degree holder"], "majors": [], "languages": ["english", "mandarin"], "language_level": ["good command"], "hard_skills": [], "soft_skills": ["work independently", "independent", "capable", "responsible", "proactive", "hardworking", "work under pressure"], "languages_combined": [{"language": "english", "language_level": ["good command"]}, {"language": "mandarin", "language_level": ["good command"]}]}, "experience_required": {"duration": ["at least 1 year"], "field": ["relevant experience"]}}, {"job_id": "100003009047648", "location_code": "hk", "company": "", "job_title": "Senior Merchandiser / Merchandiser (Toy)", "description": "Overview:\nThe Senior Sourcing Analyst, Sourced Finished Goods \u2013 Home Fragrance will be responsible for providing support to strategic procurement activities, including spend analysis, detailed savings analysis, RFI/P/Q development and execution, macro-economic industry analysis, among other things. The Senior Sourcing Analyst will create / maintain significant amounts of information gathering, data consolidation, and data cleansing activities related to the Sourced Finished Good categories of our Home Fragrance business. He/She will assist the Sourcing Director and support category teams with managing all aspects of Sourced Finished Goods supplier relationships that impact product cost, quality and product delivery.\n\nResponsibilities:\n\u2022 Support in development and execution of sourcing strategies for designated commodities or product platforms that encompass the following:\no Productivity \u2013 Develop productivity pipeline to deliver 3% gross productivity annually\no Working capital improvements: payment terms extensions, lead time & inventory reductions\n\u2022 Participative and integral member in new product development teams serving as category sourcing support for NPD initiatives\n\u2022 Supplier and commodity spend management, analysis, and productivity tracking\n\u2022 Partner with internal teams to use sourcing tools to evaluate costs, competitively bid, and negotiate spend.\n\u2022 Create, manage, and support RFI/P/Q and market events execution including post-activity reporting and analysis to meet YOY productivity goal\n\u2022 Navigate seamlessly throughout the organization during data gathering and analysis activities, fostering relationships with partners throughout the business to support data requirements\n\u2022 Develop a deep level of understanding of the data under analysis, focusing on ensuring the right balance of accuracy and completeness with timely delivery of required information.\n\u2022 Research, and evaluate new potential suppliers and technology innovation in support of the Home Fragrance Business\n\nRequirements:\n\u2022 Bachelor's degree in supply chain, engineering, science, mathematics, or related field required\n\u2022 3 - 5 years of relevant sourcing and/or supply chain working experience in Multinational CPG. Preferably in Sourcing of Sourced Finished Goods in home fragrance industry. Experience with sourcing execution of Diffusers, Candles, Scent Plugs, Home Accents, Automotive, packaging, wax, glass, or other key commodities is a plus.\n\u2022 Capable of successfully managing and completing multiple tasks concurrently with cross functional teams and suppliers\n\u2022 Demonstrates effective problem-solving and analytical skills\n\u2022 Demonstrates basic business financial knowledge\n\u2022 Demonstrates expertise in Microsoft Office applications (Outlook, Word, Excel, PowerPoint, SharePoint, Power BI)\n\u2022 Demonstrates ability to manage constructive and cooperative working relationships, often without introduction\n\u2022 Experience leveraging analytical ability to drive and influence business decisions\n\u2022 Relevant ERP experience; preferably in Oracle; Ariba experience is a plus\n\u2022 Occasional travel is required\n\n", "employment_types": ["Full Time", "Permanent"], "selling_points": [], "locations": ["Not Specified"], "categories": ["Merchandising & Purchasing", "Toy", "Sundries"], "post_time": "2022-01-15T01:52:26Z", "salary": {"currency": null, "max": null, "min": null, "period": "monthly", "term": null}, "salary_visible": false, "title_keywords": ["merchandiser", "senior merchandiser"], "responsibilities": ["reporting", "management", "data", "inventory", "analysis", "teams", "develop", "evaluate", "payment", "costs", "tracking"], "requirements": {"degrees": ["degree", "bachelor"], "majors": ["science", "engineering", "mathematics"], "languages": [], "language_level": [], "hard_skills": ["excel", "plus", "bi", "basic", "microsoft office", "problem-solving", "word", "powerpoint", "analytical skills", "erp", "outlook", "oracle"], "soft_skills": ["capable", "multiple tasks", "problem-solving", "cooperative", "analytical skills", "constructive"], "languages_combined": []}, "experience_required": {"duration": ["3 - 5 years"], "field": ["supply chain", "business", "analytical"]}}, {"job_id": "100003009047860", "location_code": "hk", "company": "Michaels Global Sourcing, LLC", "job_title": "Sourcing Specialist", "description": "Job Requirements\n\nCertificate graduate or above\n4-8 years merchandising experience in plastic toys\nAble to handle orders from development to bulk production\nExperience in manufacturing company would be an advantage\nDetail-minded, energetic, well-organized, flexible and efficient\nFamiliar with MS Office such as Word, Excel and Chinese WP\nGood command of spoken & written English and Mandarin\nImmediate available is highly desired\n\nJob Responsibilities\n\nCoordinate with overseas clients, factories and suppliers on order details\nPreform full merchandising duties from development to bulk production\nResponsible for lab test follow up, sample arrangement, costing and sourcing\nAssist in managing order schedules to ensure customers\u2019 requirements can be met\n\nExcellent career opportunities and attractive fringe benefits will be offered to the right candidates. For interested parties please send email to hrdept.ritalam@gmail.com for job enquiries.", "employment_types": ["Full Time", "Permanent"], "selling_points": ["New Headcount!", "Sourcing Process Execution and Vendor Management", "Hardgoods. Largest US Arts & Crafts retailer"], "locations": ["Kowloon Bay"], "categories": ["Merchandising & Purchasing", "Sundries", "Others", "Procurement / Purchasing / Sourcing"], "post_time": "2022-01-14T04:03:39Z", "salary": {"currency": null, "max": null, "min": null, "period": "monthly", "term": null}, "salary_visible": false, "title_keywords": ["specialist"], "responsibilities": ["schedules", "merchandising", "coordinate with"], "requirements": {"degrees": ["certificate"], "majors": [], "languages": ["english", "chinese", "mandarin"], "language_level": ["good command"], "hard_skills": ["excel", "chinese wp", "word", "ms office"], "soft_skills": ["detail-minded", "efficient", "flexible", "well-organized", "energetic"], "languages_combined": [{"language": "english", "language_level": ["good command"]}, {"language": "chinese", "language_level": []}, {"language": "mandarin", "language_level": ["good command"]}]}, "experience_required": {"duration": ["4-8 years"], "field": ["toys", "manufacturing", "merchandising"]}}, {"job_id": "100003009050590", "location_code": "hk", "company": "Green Delta Limited", "job_title": "Assistant Merchandiser / Merchandiser", "description": "Main tasks & responsibilities:\n\nTo process efficient and effectively the daily inquiries and orders within the given product categories and according to our quality and compliance standards. The tasks involves\u00a0quoting, procurement, monitoring production and logistics. The goal is to increase the\u00a0number orders and service level to our customers.\n\nDuties\n\nProcess inquiries > prioritize and provide good quality replies within the service level agreement\nTake full responsibility from the inquiry stage; order received till shipment.\nKeep track of suppliers\u2019 production plan to ensure on time delivery\nBe result orientated > offer solutions, alternatives: each inquiry and order is a chance.\nHandle complaints and discuss/negotiate solutions with the factories and/or sales.\n\n\u00a0Your experience\n\nOrganized and an eye for detail;\nResult-orientated team-player;\nGood command in English and Mandarin\nMerchandising or procurement experience\nGood command of Excel, Word, PPT and so on for office software.\n\n\u00a0What\u2019s in it for you?\n\nWe offer you a challenging and exciting job in an enthusiastic team and pleasant working environment with a competitive salary, performance bonus, double pay, life insurance, medical insurance, five-day work week and 15 days holidays per year.\n\nAre you a starter? Don\u2019t hesitate to apply!", "employment_types": ["Full Time", "Permanent"], "selling_points": [], "locations": ["Lai Chi Kok"], "categories": ["Merchandising & Purchasing", "Sundries", "Procurement / Purchasing / Sourcing"], "post_time": "2022-01-15T03:51:12Z", "salary": {"currency": null, "max": null, "min": null, "period": "monthly", "term": null}, "salary_visible": false, "title_keywords": ["merchandiser", "assistant merchandiser"], "responsibilities": ["product categories", "software", "monitoring", "compliance", "quality", "ensure on time delivery", "handle complaints", "merchandising", "logistics", "plan", "insurance"], "requirements": {"degrees": [], "majors": [], "languages": ["english", "mandarin"], "language_level": ["good command"], "hard_skills": ["excel", "word", "goal", "service level agreement", "office software"], "soft_skills": ["efficient", "organized", "team-player", "prioritize", "pleasant", "eye for detail", "enthusiastic"], "languages_combined": [{"language": "english", "language_level": ["good command"]}, {"language": "mandarin", "language_level": ["good command"]}]}, "experience_required": {"duration": [], "field": ["merchandising", "procurement"]}}, {"job_id": "100003009051223", "location_code": "hk", "company": "Easy Job Centre", "job_title": "Merchandiser / Senior Merchandiser (Sundries / Seasonal / Furniture / Home Appliance)", "description": "We are looking for high caliber candidate to join us and work together for the growth\u00a0of both our Company and individual.\n\nWhat will you be doing?\nThis position is responsible for executing and improving end-to-end best practices in Global Sourcing for assigned product categories. This role is accountable for developing and managing vendors, as well as maintaining existing vendor relationships and driving projects to ensure that vendors meet or exceed their contractual obligations by delivering innovative, quality products on time.\n\nRoles & Responsibility:-\n\nSourcing Process Execution and Vendor Management:\nExecute and improve the end-to-end sourcing processes including vendor management, liaison with agents, price negotiation, product development and sample assessment to meet the on-time delivery, quality and commercial KPIs\nSource and develop potential vendors as well as drive a respectful and collaborative vendor relationship with existing vendors to ensure they meet all company\u2019s requirements including value, quality and innovation.\nManage Request for Proposal, category costing bids and product development independently in conjunction with and product development and sourcing teams.\nEnsure smooth arrangement of product development trip, sourcing trip and finalization events\nExecute order management to ensure accuracy of database; Monitor and regular update on project status of assigned product categories\nProvide support in streamlining sourcing process and enhancement of product specification for price negotiation, cost reduction initiatives and high quality of products.\u00a0 Handle cost and commercial terms negotiation with vendors.\n\nAdditional duties as assigned including:-\n\nCollect latest market intelligence for Sourcing Manager to share with management, product development and sourcing teams.\u00a0\nProvide data for Sourcing Manager to conduct cost and supplier performance analysis in order to generate cost saving opportunities.\nTrain new Associate Sourcing Specialists and assist in their ongoing skills development\nOther duties as assigned\nKnowledge, Skills and Abilities requirement:-\nDegree/Associate Degree/Diploma holder in Merchandising/ Business Management or related discipline\nHands-on computer knowledge in MS word, Excel, Outlook, Power Point & Chinese Word Processing\nMinimum 3 years\u2019 relevant working experience\nEnergetic, self-motivated, detail-oriented and independent working style\nGood communication and interpersonal skills\nEager to work in a team in order to achieve best results\nDemonstrate a high sense of initiative, hardworking and responsible\nThe ability to work in a demanding but collegial, team-oriented environment\nGood command of both written and spoken English and Mandarin\nFrequent travel is required; Up to 30% travel\nSolid sourcing experience preferably gained from US buying office/ retailer\nWe offer competitive pay package and attractive fringe benefits including employer voluntary contribution on MPF scheme, Medical Insurance such as out-patient, hospitalization and dental coverage for employee, spouse and dependents. For interested parties, please make your application by stating the current and expected salaries.\n\nPersonal data collected will be used strictly for recruitment purpose only.", "employment_types": ["Full Time"], "selling_points": [], "locations": ["Yau Tsim Mong Area"], "categories": ["Merchandising & Purchasing", "Furniture", "Home Appliances", "Sundries"], "post_time": "2022-01-15T05:19:56Z", "salary": {"currency": null, "max": null, "min": null, "period": "monthly", "term": null}, "salary_visible": false, "title_keywords": ["merchandiser", "senior merchandiser"], "responsibilities": ["product categories", "management", "price negotiation", "order management", "provide support", "cost", "terms negotiation", "data", "additional duties", "analysis", "other duties", "quality", "teams", "monitor", "develop", "database", "kpis"], "requirements": {"degrees": ["diploma holder", "associate degree", "degree"], "majors": ["business"], "languages": ["english", "chinese", "mandarin"], "language_level": ["good command"], "hard_skills": ["business management", "excel", "chinese word processing", "scheme", "outlook", "power point", "ms word"], "soft_skills": ["self-motivated", "independent", "responsible", "detail-oriented", "hands-on", "communication and interpersonal skills", "patient", "energetic", "initiative", "hardworking"], "languages_combined": [{"language": "english", "language_level": ["good command"]}, {"language": "chinese", "language_level": []}, {"language": "mandarin", "language_level": ["good command"]}]}, "experience_required": {"duration": ["minimum 3 years"], "field": ["relevant working experience"]}}, {"job_id": "100003009050540", "location_code": "hk", "company": "Sa Sa Dot Com Limited", "job_title": "Senior Product Executive / Product Supervisor (eCommerce Merchandising)", "description": "A young and innovative company in General Merchandise (including Houseware and Seasonal\u00a0products\u00a0) looks for a qualified and experienced Assistant Merchandiser / Merchandiser .\n\nOur Head Office is in Hong Kong with additional worldwide offices. We design, manufacture and export to\u00a0major mass market and retailers exporting to over 30 countries worldwide. Major markets include Belgium, France, Germany and USA.\n\nAssistant Merchandiser / Merchandiser\n\nResponsibilities:\n\nYou should be capable of working independently while reporting to our merchandising team in the following areas:\n\nGeneral sourcing duties and sample arrangements\nCreate items in appointed system and coordinate with vendors to obtain all the\u00a0product information, ensure the product information can be recorded accurately in timely basis.\nOrder processing to ensure on-time deliveries and arrange inspection\nIdentifies and escalates any production, quality and delivery issues to Merchandiser\nPrepare inspection reports & shipping documents\nOrganize/accompany trade fair or sourcing trips with buyer\nParticipate in ad-hoc projects as assigned\n\nRequirements:\n\n2 years' relevant working experience, preferable in Houseware or\u00a0seasonal products. \u00a0\nExperience in sourcing is a plus.\nStrong team player with excellent communication and interpersonal skills\nKnowledge of social audit and testing requirements\nAbility to work independently, self-motivated, responsible and willing to learn\nAttention to detail, organizational and multitasking skills, willing to travel\nHigh level of maturity, integrity, trustworthiness.\nProficient in Microsoft Office\nFluency in English and Mandarin is compulsory\u00a0\n\nMore experience will consider as Merchandiser.\n\n\nPlease do not apply if you do not meet the above criteria as your application will NOT be considered. We regret that we shall only contact suitable applicants.\u00a0\u00a0", "employment_types": ["Full Time"], "selling_points": ["OTB & assortment planning of beauty products", "Buying exp in the eCommerce of PRC, HK & S.E. Asia", "Source new products to enhance product portfolio"], "locations": ["Siu Sai Wan"], "categories": ["Merchandising & Purchasing", "Sundries", "Procurement / Purchasing / Sourcing", "E-commerce", "Marketing - Brand / Product Management"], "post_time": "2022-01-14T10:40:14Z", "salary": {"currency": null, "max": null, "min": null, "period": null, "term": null}, "salary_visible": false, "title_keywords": ["senior product executive", "merchandising", "product supervisor"], "responsibilities": ["shipping documents", "reporting", "prepare inspection reports", "delivery issues", "merchandising", "coordinate with", "quality", "inspection", "order processing", "ad-hoc projects"], "requirements": {"degrees": [], "majors": [], "languages": ["english", "mandarin"], "language_level": ["fluency"], "hard_skills": ["plus", "microsoft office"], "soft_skills": ["work independently", "self-motivated", "responsible", "organizational", "willing to learn", "integrity", "communication and interpersonal skills", "attention to detail", "team player"], "languages_combined": [{"language": "english", "language_level": ["fluency"]}, {"language": "mandarin", "language_level": ["fluency"]}]}, "experience_required": {"duration": ["2 years"], "field": ["relevant working experience"]}}, {"job_id": "100003009050533", "location_code": "hk", "company": "TV Products (HK) Limited", "job_title": "Merchandiser", "description": "Responsibilities\nResponsible for OTB, product mix and assortment planning of beauty products, \u00a0accessories for e-commerce in China / HK / South Asia market;\nWork closely with internal departments including buying operation, inventory, and eCommerce teams to ensure proper execution of assortment strategies;\nKeep track the market trend and identify new brands to optimize category growth;\nIdentify potential suppliers to source new products to enhance the product portfolio and fulfill market needs;\nAlign and actualize the overall sourcing strategies for the e-commerce business;\nAnalyze market trends, sales performance.\nRequirements\nDegree holder in Business or related disciplines;\n3-5 years of buying experience in e-commerce / retail industry preferably in Beauty / health food / Personal Care Category;\nHigh degree of business sense with strong analytical skills;\nSelf-motivated, energetic, well-organized and able to work under pressure;\nStrong negotiation and presentation skills;\nA good team player with strong communication and interpersonal skills;\nIndependent, proactive and well-organised;\nGood command of spoken & written English and Chinese.\n\nWe offer\n\n5 - day work week\nMedical Benefits\nAnnual Merit Bonus\nStaff Purchase Discounts\nStaff Recreation Activity\nShuttle Bus Service\nEducation Sponsorship\n\nInterested parties please send a full resume with current and expected salary by clicking APPLY NOW:\n\nPlease visit our corporate website at\u00a0http://corp.sasa.com/en/home\u00a0to know more about us.\n\n(Sa Sa is an Equal Opportunity Employer and all qualified applicants will receive consideration for employment. Personal data collected will be kept confidential and used for recruitment purpose only)", "employment_types": ["Full Time", "Permanent"], "selling_points": ["Five-day week work, Performance bonus", "Near MTR Station", "Sizable and stable trading company"], "locations": ["Tsim Sha Tsui"], "categories": ["Manufacturing", "Product Development / Management", "Merchandising & Purchasing", "Sundries"], "post_time": "2022-01-14T10:38:57Z", "salary": {"currency": null, "max": null, "min": null, "period": "monthly", "term": null}, "salary_visible": false, "title_keywords": ["merchandiser"], "responsibilities": ["product mix and assortment planning", "sales performance", "inventory", "teams", "otb"], "requirements": {"degrees": ["degree", "degree holder"], "majors": ["related disciplines", "business"], "languages": ["english", "chinese"], "language_level": ["good command"], "hard_skills": ["analytical skills", "e-commerce"], "soft_skills": ["self-motivated", "good team player", "independent", "negotiation", "proactive", "business sense", "well-organized", "analytical skills", "presentation skills", "communication and interpersonal skills", "well-organised", "energetic", "work under pressure"], "languages_combined": [{"language": "english", "language_level": ["good command"]}, {"language": "chinese", "language_level": ["good command"]}]}, "experience_required": {"duration": ["3-5 years"], "field": ["retail industry", "e-commerce", "beauty", "health food", "personal care"]}}, {"job_id": "100003009042893", "location_code": "hk", "company": "JS Hometech Co Limited", "job_title": "Assistant Merchandiser / Merchandiser (Korean Speaking)", "description": "Can work and handle project independently\nSupport the Manger in merchandising coordination from development to production\nHandle product development, sample arrangement\nMaintain and update production records and system data\nCoordinate with overseas clients and China factory for orders processing\nAssist other duties and ad hoc duties as required\n\nRequirements\n\nDiploma\u00a0or above\nMin 5 years\u2019 merchandising experience from product development to order finished in household products in overseas market\n\nGood command in written & spoken English, Mandarin & Cantonese\nKnowledge of MS Office\nA good learner\nImmediate available / Short notice is preferred\n\n\u00a0Benefits\n\nFive-day week work\nPerformance bonus\n14 days annual leave\nBank holidays\nMedical Insurance\nInterested parties please apply with full resume and expected salary by email to\u00a0Apply Now", "employment_types": ["Full Time", "Permanent"], "selling_points": ["3 years experience in home appliances", "Korean Speaker", "Project follow up"], "locations": ["Hung Hom"], "categories": ["Manufacturing", "Product Development / Management", "Merchandising & Purchasing", "Home Appliances", "Sundries"], "post_time": "2022-01-12T09:10:05Z", "salary": {"currency": null, "max": null, "min": null, "period": "monthly", "term": null}, "salary_visible": false, "title_keywords": ["merchandiser", "assistant merchandiser"], "responsibilities": ["ad hoc duties", "other duties", "coordinate with", "merchandising", "system data", "maintain", "coordination"], "requirements": {"degrees": ["diploma or above"], "majors": [], "languages": ["cantonese", "english", "mandarin"], "language_level": ["good command"], "hard_skills": ["processing", "ms office"], "soft_skills": ["good learner", "independently", "coordination"], "languages_combined": [{"language": "cantonese", "language_level": ["good command"]}, {"language": "english", "language_level": ["good command"]}, {"language": "mandarin", "language_level": ["good command"]}]}, "experience_required": {"duration": ["min 5 years"], "field": ["product development", "merchandising"]}}, {"job_id": "100003009046108", "location_code": "hk", "company": "Formia Limited", "job_title": "ASSISTANT MERCHANDISING MANAGER", "description": "Sales Coordinator / Assistant Merchandiser \u00d73\nLocation :Kwai Hing/ Kwun Tong,\u00a0Salary : 14-18K ( 5 Days )\u00a0\n\u00a0Requirements:\nDegree/Diploma/ F.5\u00a0or above, 0-3 years or above exp in Assistant Merchandiser or Sales Coordinator or Sales in any products\u00a0\u00a0\nfollow up sales order, data entry, contact suppliers, clients, sourcing for sales Coordinator and Asst. Merch position etc...\u00a0\nPC knowledge, proficient in MS Outlook, Word & Excel and English & Chinese word processing\nGood command in both English and Mandarin\nFresh Graduate also Will be consider\u00a0\nWarehouse Clerk/ Logistic Clerk/ Warehouse Keeper\n(Kwai Chung- Salary : 12-15K)\n\u8077\u8cac:,\n\u4e00\u822c\u6587\u66f8\u5de5\u4f5c\n\u5b89\u6392\u51fa\u8ca8\u53ca\u6536\u8ca8\n\u8ddf\u9032\u8a02\u55ae\n\u5305\u88dd\u8ca8\u7269\u6a19\u7c64\n\u8ddf\u6d77\u5916\u540c\u4e8b\u53ca\u9999\u6e2f\u8239\u52d9\u90e8\u53ca\u63a1\u8cfc\u90e8\u540c\u4e8b\u806f\u7d61\u00a0\n\u8cc7\u683c:\n\n\u4e2d\u5b78\u7a0b\u5ea6\n\u4e00\u5e74\u76f8\u95dc\u5de5\u4f5c\u7d93\u9a57\n\u61c2\u8b80\u5beb\u4e2d\u82f1\u6587\n\u61c2\u96fb\u8166\u53caMicrosoft Office\u64cd\u4f5c\n\u5de5\u4f5c\u6642\u9593\u53ca\u798f\u5229:\n\n\u6bcf\u9031\u5de5\u4f5c\u4e94\u5929\u534a(\u9577\u77ed\u9031)\n\u9280\u884c\u5047\u671f\u3001\u96d9\u7ce7\u3001\u91ab\u7642\u798f\u5229\u3001\u7a7f\u68ad\u5df4\u58eb\u53ca\u63d0\u4f9b\u5728\u8077\u57f9\u8a13\n\u5de5\u4f5c\u5730\u9ede: \u8475\u6d8cATL\u4e09\u865f\u8ca8\u6ac3\u78bc\u982d\u00a0 \u00a0\n*** Personal data will be treated with strict confidential and used for recruitment purpose only.\n\n\nP & A consultant Ltd will not charge any fees from the above-stated job-seeker, your job apply to our company means your acceptance of our terms and conditions.", "employment_types": ["Full Time", "Permanent"], "selling_points": ["Merchandiser in gifts & premiums products", "5 days work week, 15 days AL", "Excellent career development"], "locations": ["Lai Chi Kok"], "categories": ["Merchandising & Purchasing", "Handbag", "Sundries", "Others"], "post_time": "2022-01-13T09:38:30Z", "salary": {"currency": null, "max": null, "min": null, "period": "monthly", "term": null}, "salary_visible": false, "title_keywords": ["merchandising manager", "assistant"], "responsibilities": ["data entry", "follow up sales order", "recruitment", "personal data", "contact suppliers"], "requirements": {"degrees": ["diploma", "degree", "fresh graduate"], "majors": [], "languages": ["english", "chinese", "mandarin"], "language_level": ["good command", "proficient"], "hard_skills": ["excel", "chinese word processing", "word", "outlook", "pc knowledge"], "soft_skills": [], "languages_combined": [{"language": "english", "language_level": ["good command", "proficient"]}, {"language": "chinese", "language_level": ["proficient"]}, {"language": "mandarin", "language_level": ["good command"]}]}, "experience_required": {"duration": [], "field": []}}, {"job_id": "100003009034472", "location_code": "hk", "company": "OBI Group Sourcing Hong Kong Limited", "job_title": "Merchandiser (Hardsgood)", "description": "GENERAL DESCRIPTION:\n\nWe are looking for an Assistant Merchandising\u00a0Manager (Assistant Account Manager)\u00a0to work in our operations team driving projects and communication with our global airline customers, brand partners, suppliers as well as multifunctional organization.\n\nOur ideal candidate, who is reporting to the Senior Operations Manager, comes with a detail-oriented mindset, is well organized and demonstrates personal ownership in a proactive and solution oriented working approach. This is combined with a positive outlook, the relentless drive to learn and the openness to effectively collaborate within young and dynamic teams.\n\nIn return, we offer a professional and energetic work environment, competitive compensation programs, comprehensive benefits coverage and much more.\n\n\nESSENTIAL JOB DESCRIPTION:\n\nEffectively liaise and communicate with international airline customers as well as brands, suppliers and logistics providers to further grow our business\nProvide world-class end-to end service to our customers across the areas of customer care, product development, data entry, purchasing, supply planning, production, and quality control\nEffectively manage multifunctional projects including project planning, calculations, products/suppliers sourcing, negotiations and benchmarking as well as artwork & sample development and tender submissions\nCoordinate daily operational activities to ensure order fulfilment through effective production & logistics planning, sales & purchase order creation, invoicing, as well as after sales services\nConstantly review existing workflows and provide improvement recommendations to enhance efficiency, eliminate losses and deliver cost savings \u00a0\nEnsure the key business projects and orders for your region are delivered efficiently and with high quality\nAssist and support ad hoc projects to help the overall progression of the company\n\nJOB REQUIREMENTS:\n\nDegree holder, preferably in Business Administration, Supply Chain, Merchandising or related disciplines\n>7 years working experience in trading industry / merchandising / purchasing is preferable. Candidate will less experience will be consider as Senior Officer\nStrong sense of responsibility and ownership\nFlexible approach, able to work under pressure\u00a0\nFluent command of spoken and written English, Cantonese and Mandarin\u00a0\nExcellent command of computer literacy in Word, Excel and PowerPoint\nA good team player, pro-active, mature, outgoing, and self-motivated\nPositive, Confident and Smart\nImmediate availability is preferred\nWe offer attractive remuneration and benefits including, 5 days work per week (9am-6pm), work from home policy, 15 days annual leave, bonus, medical scheme. Interested parties please send full resume with your availability, present and expected salary, by clicking \"Apply Now\" button.\nPersonal data provided by applicants will be treated strictly in accordance with our personal data policy and for recruitment purposes only.", "employment_types": ["Full Time", "Permanent"], "selling_points": ["Responsible for product sourcing and development", "Diploma or above with 5 years relevant experience", "AL:18 days+Flex. work hour+13th Month Sal.+Bonus"], "locations": ["Kowloon Bay"], "categories": ["Merchandising & Purchasing", "Electronics", "Home Appliances", "Sundries"], "post_time": "2022-01-10T03:27:55Z", "salary": {"currency": null, "max": null, "min": null, "period": "monthly", "term": null}, "salary_visible": false, "title_keywords": ["merchandiser"], "responsibilities": [], "requirements": {"degrees": [], "majors": [], "languages": [], "language_level": [], "hard_skills": [], "soft_skills": [], "languages_combined": []}, "experience_required": {"duration": [], "field": []}}, {"job_id": "100003009049008", "location_code": "hk", "company": "Cathay Pacific Catering Services (H.K.) Limited", "job_title": "Procurement Officer", "description": "Responsibilities:\n\nBusiness development\n\nResponsible for category sourcing activity, including searching new product and new supplier, quality and price comparison, sample comparison, price negotiation, factory evaluation etc.\nResponsible for project execution with milestone control and good time management\nGuiding and monitoring the order follow up, including working with OTS system to accept order, delivery time control;\nDocument management: Projects document filing and checking.\n\nCustomer and supplier management\n\nCommunicate with Germany headquarter to clarify inquiries and specifications;\nSupply chain management including supplier search, screen and identify potential supplier. Monitor suppliers\u2019 performance\nArrange and implement buying trip independently, including contact with supplier or vendor to arrange schedule, coordinate with supplier and buyer, accompany buying trip, prepare trip report etc.\nSupplier negotiation: price review and control, claim settlement etc.\n\nRequirements:\n\nDiploma or above with 5 years above independent product sourcing working experience in trading company or buying office\nExperience in handling indoor furniture / housing cleaning products is an advantage but not must\n\nStrong negotiation, presentation and problem solving skill\nGood time management and project management skills, can work on a project independently\nStrong communication skills and negotiation skills\nGood command of English and Mandarin\nSound PC knowledge including MS office\n\nWe offer 5 days work, Annual Leave: 18 days, excellent career prospects, competitive remuneration package and fringe benefits to the right candidates. Interested parties please send your full resume (in MS Word or PDF format) with availability, present and expected salary to us.\n\n(Personal data collected is used for recruitment purpose only.)\n\nFor more information, please be welcome to visit our group website: http://www.obisourcing.com/", "employment_types": ["Full Time", "Permanent"], "selling_points": ["Source, assess and select products/suppliers", "Investigate issues with products/suppliers", "Maintain and upkeep purchasing database & records"], "locations": ["Airport Area"], "categories": ["Merchandising & Purchasing", "Sundries", "Others", "Procurement / Purchasing / Sourcing"], "post_time": "2022-01-14T07:54:18Z", "salary": {"currency": null, "max": null, "min": null, "period": "monthly", "term": null}, "salary_visible": false, "title_keywords": ["procurement officer"], "responsibilities": ["communicate with", "document filing", "price negotiation", "management", "control", "monitoring", "quality", "checking", "monitor", "coordinate with", "review", "specifications", "contact", "schedule", "evaluation", "report"], "requirements": {"degrees": ["diploma or above"], "majors": [], "languages": ["english", "mandarin"], "language_level": ["good command"], "hard_skills": ["problem solving", "project management", "pc knowledge", "ms office"], "soft_skills": ["communication skills", "independently", "independent", "negotiation", "project management skills", "negotiation skills", "problem solving skill", "time management", "presentation"], "languages_combined": [{"language": "english", "language_level": ["good command"]}, {"language": "mandarin", "language_level": ["good command"]}]}, "experience_required": {"duration": ["5 years"], "field": ["trading"]}}, {"job_id": "100003009054211", "location_code": "hk", "company": "Eternity Consultants (HK) Ltd", "job_title": "Merchandising Clerk  / Assistant Merchandiser - 5 days works - (Fresh graduate)", "description": "Responsibilities\nSource, assess and select products and suppliers in order to achieve the Company target on the cost and quality performance of assigned product categories, as well as the relevant suppliers\nNegotiate with suppliers for best deals\nMaintain and update the purchasing database and records\nPerform source planning, conduct market research and develop a supply market\nInvestigate product and supplier issues and coordinate for solutions\nMeasure and analyze the performance of assigned product categories\nAssist in inter-departmental projects to achieve the Company goals and objectives\nRequirements\nDiploma / higher diploma or above in any discipline\nMinimum 2 years\u2019 working experience, preferably with relevant experience in food purchasing\nCandidate possesses a degree in any discipline with less than 2 years working experience will also be considered\nStrong problem solving, numerical and analytical skills\nGood interpersonal and communication skills\nGood price negotiation and cost control skills\nAble to work under pressure and meet stretching targets\nGood command in both written and spoken English and Chinese.\u00a0 Knowledge in Putonghua would be an advantage\nProficient in Microsoft Office, especially MS Word and Excel\nCandidates with more experience will be considered for the position of Senior Procurement Officer\n\nWe offer a competitive remuneration package and a full range of benefits. Interested parties please send your resume with your current and expected salary to Head of People,11 Catering Road East, Hong Kong International Airport, Lantau, Hong Kong or by clicking the \"Apply Now\" button on or before 10 February 2022.\n\nPersonal data collected will be treated in the strictest confidence and only be used for recruitment-related purposes. Applicants who do not receive notification for an interview within six weeks may consider their application unsuccessful.", "employment_types": ["Full Time", "Permanent"], "selling_points": ["F.5 or above. 0-2 years exp in merchandising in", "contact with vendor", "Follow up order, sampling. Contact w/ buyer"], "locations": ["Not Specified"], "categories": ["Merchandising & Purchasing", "Woven / Knit", "Handbag", "Sundries"], "post_time": "2022-01-17T08:49:27Z", "salary": {"currency": null, "max": null, "min": null, "period": "monthly", "term": null}, "salary_visible": false, "title_keywords": ["merchandising clerk", "assistant merchandiser"], "responsibilities": ["product categories", "cost", "conduct market research", "quality", "develop", "coordinate", "maintain", "database", "planning"], "requirements": {"degrees": ["diploma", "higher diploma or above", "degree"], "majors": [], "languages": ["putonghua", "english", "chinese"], "language_level": ["advantage", "good command"], "hard_skills": ["excel", "microsoft office", "analytical skills", "problem solving", "ms word"], "soft_skills": ["communication skills", "negotiation", "analytical skills", "problem solving", "interpersonal", "work under pressure"], "languages_combined": [{"language": "putonghua", "language_level": ["advantage"]}, {"language": "english", "language_level": ["good command"]}, {"language": "chinese", "language_level": ["good command"]}]}, "experience_required": {"duration": ["2 years", "minimum 2 years"], "field": ["purchasing", "food", "relevant experience", "procurement"]}}, {"job_id": "100003009044902", "location_code": "hk", "company": "Meiyume (Hong Kong) Limited", "job_title": "Manager - Sourcing", "description": "Buying office\n\nRequirements:\n\nF.5 or above\n1--2 yrs exp in merchandising in Trading\nFollow up order, sampling\nContact with laboratory\nCommunicate with vendor, overseas buyer\nProduct development\n\n\u00a0Many positions are not been posted in media.\u00a0 If you are looking for job in merchandising field, we are welcome you send your resume to us direct.\n\n*Interested parties, please send full resume with current & expected salary & date available in MS WORD FORMAT ONLY to our email address\u00a0or fax to 3527 0634*\n\nFor more jobs, please visit our website: www.hketernity.com\n\n(Personal data submitted are for recruitment purpose only.)\n", "employment_types": ["Full Time"], "selling_points": ["At least 5 years of experience", "Exp in cosmetic packaging,metal,plastic injection", "Knowledge on mechanical assembly and manufacturing"], "locations": ["Lai Chi Kok"], "categories": ["Merchandising & Purchasing", "Home Appliances", "Sundries", "Procurement / Purchasing / Sourcing"], "post_time": "2022-01-13T06:35:31Z", "salary": {"currency": null, "max": null, "min": null, "period": null, "term": null}, "salary_visible": false, "title_keywords": ["manager"], "responsibilities": ["communicate with", "merchandising", "contact"], "requirements": {"degrees": [], "majors": [], "languages": [], "language_level": [], "hard_skills": ["vendor"], "soft_skills": [], "languages_combined": []}, "experience_required": {"duration": [], "field": []}}, {"job_id": "100003009037909", "location_code": "hk", "company": "Taibon Co Ltd", "job_title": "Senior Merchandiser (Gift and Premium)", "description": "Are you a movement maker? Are you seeking new and exciting career opportunities?Here is what you need to know about the job:\n\n\u200b\n\nResponsibilities:\n\nAssist in establishing and enhancing business relationships with customers through provision of quality customer service to maximize business growth\nResponsible for product development and order management to ensure that products meet customers\u2019 quality and budget requirements\nCoordinate and follow up orders and production with vendors, customers, and internal parties to ensure customer satisfaction and on-time delivery\nMaintain strong business relationships with vendors for product development and production\nAssist in supervising junior team members\u2019 merchandising activities in the entire project management to ensure operation efficiency, customer satisfaction and on-time delivery\n\nRequirements:\n\nBachelor's degree in Manufacturing Management or related discipline will be an advantage\nAt least 5 years of solid experience in sourcing.\nKnowledge on mechanical assembly and manufacturing process and cost of mechanical parts for consumer products (plastic injection, metal die casting and sheet metal stamping parts) with multi-factory and cross-country management experience\nWorking experience in consumer products industry will be an advantage\nStrategic leadership skills, strong interpersonal skills, critical thinking, analytic and problem-solving skills\nExcellent communication and presentation skills within the organization and the customer. Suitable candidate should also be a \u201cdriver\u201d for results and strong on execution.\nFluency in Cantonese, Mandarin & English is required to liaise with different stakeholders\nBusiness travels to China/ overseas countries are necessary\n\n#meiyume\n\nIf this sounds like you, Apply Now!\n\n\u200b", "employment_types": ["Full Time"], "selling_points": ["Merchandiser", "Senior Merchandiser", "Gift and premium"], "locations": ["Lai Chi Kok"], "categories": ["Merchandising & Purchasing", "Handbag", "Sundries", "Others"], "post_time": "2022-01-11T04:13:09Z", "salary": {"currency": null, "max": null, "min": null, "period": "monthly", "term": null}, "salary_visible": false, "title_keywords": ["senior merchandiser"], "responsibilities": ["follow up orders", "order management", "supervising", "budget", "quality", "merchandising", "coordinate", "project management", "customer service", "maintain", "internal parties"], "requirements": {"degrees": ["degree", "bachelor"], "majors": ["manufacturing"], "languages": ["cantonese", "english", "mandarin"], "language_level": ["fluency"], "hard_skills": ["problem-solving skills"], "soft_skills": ["leadership skills", "communication", "presentation skills", "interpersonal skills", "problem-solving skills"], "languages_combined": [{"language": "cantonese", "language_level": ["fluency"]}, {"language": "english", "language_level": ["fluency"]}, {"language": "mandarin", "language_level": ["fluency"]}]}, "experience_required": {"duration": ["at least 5 years"], "field": ["management", "manufacturing"]}}, {"job_id": "100003009056004", "location_code": "hk", "company": "Eternity Consultants (HK) Ltd", "job_title": "Coordinator / Sales Executive / Senior Sales Officer  \u2013 Gift / Electronic / Eyewear / Sunglass / Toy", "description": "JOB DUTIES\n\nResponsible for overall merchandising activities from product development to order follow up.\nManage daily communications with internal sales team & factories\nParticipate in price negotiation and cost engineering to meet client\u2019s goal.\nAssist Sales Team for orders and production follow-up\n\nTHE REQUIREMENTS\n\nUniversity degree graduated with good PC skills/English/Mandarin\nExpected to work with high efficiency and under pressure\nMature, self-motivated and\u00a0strong sense of responsibility.\nGood communication and negotiation skills in English & Mandarin\nOccasional travel to China and Oversea may be needed\n\nWe are offering highly competitive package 5 days work, medical benefit, double pay and performance bonus", "employment_types": ["Full Time", "Permanent"], "selling_points": ["Optical / Eyewear, sunglasses, gift, electronic", "medical, 10 al", "Min. 4- 7yrs coordinator in Trading / Factory"], "locations": ["Not Specified"], "categories": ["Merchandising & Purchasing", "PVC", "Sundries", "Sales, CS & Business Devpt", "Account Servicing"], "post_time": "2022-01-18T03:11:00Z", "salary": {"currency": null, "max": null, "min": null, "period": "monthly", "term": null}, "salary_visible": false, "title_keywords": ["senior sales", "officer", "coordinator", "sales executive"], "responsibilities": ["cost", "communications with", "price negotiation", "merchandising", "sales team"], "requirements": {"degrees": ["university degree"], "majors": [], "languages": ["english", "mandarin"], "language_level": ["good"], "hard_skills": ["pc skills"], "soft_skills": ["self-motivated", "under pressure", "sense of responsibility", "mature", "communication", "negotiation skills"], "languages_combined": [{"language": "english", "language_level": ["good", "good"]}, {"language": "mandarin", "language_level": ["good", "good"]}]}, "experience_required": {"duration": [], "field": []}}, {"job_id": "100003009041690", "location_code": "hk", "company": "Orenji Creation Limited", "job_title": "Project Executive / Trainee / Merchandiser (Merchandising) - Fresh Graduate are welcomed", "description": "Duties:\n\nHandle inquiries from customers and sample arrangements\u00a0\u00a0\nPrepare Order as well as updating information records\nCoordinate with suppliers and Buyer\nAny ad hoc tasks required\n\nRequirements:\n\nDiploma or above\nMin.3-7 years coordinator in Trading or factory in Optical or Eyewear or Sunglasses or Toy or consumer electronic\n\nDetail minded, well-organized and eager to learn\nProficiency in spoken & written English and Mandarin\nProficient in MS Word, Excel, PowerPoint\n\n*Interested parties, please Email full resume with current & expected salary & date available in MS WORD FORMAT ONLY to us\u00a0or fax to 3527 0634*\n\nWe are welcome applicants resend resumes to us even you have applied jobs in our company before.\n\nFor more jobs, please visit our website: www.hketernity.com\n\n(Personal data submitted are for recruitment purpose only.)\u00a0", "employment_types": ["Full Time", "Permanent"], "selling_points": [], "locations": ["Wong Tai Sin Area"], "categories": ["Merchandising & Purchasing", "Sundries", "Others", "Procurement / Purchasing / Sourcing"], "post_time": "2022-01-12T06:43:43Z", "salary": {"currency": null, "max": null, "min": null, "period": "monthly", "term": null}, "salary_visible": false, "title_keywords": ["merchandiser", "project executive", "merchandising", "trainee"], "responsibilities": ["ad hoc tasks", "coordinate with", "updating information"], "requirements": {"degrees": ["diploma or above"], "majors": [], "languages": ["english", "mandarin"], "language_level": ["proficiency"], "hard_skills": ["excel", "powerpoint", "ms word"], "soft_skills": ["eager to learn", "well-organized"], "languages_combined": [{"language": "english", "language_level": ["proficiency"]}, {"language": "mandarin", "language_level": ["proficiency"]}]}, "experience_required": {"duration": [], "field": []}}, {"job_id": "100003009050415", "location_code": "hk", "company": "Links International", "job_title": "Hardgoods Merchandiser - Product Developer", "description": "1 Post for Seasonal / Party / Toys / Gift Premium\n1 Post for Fashion Accessories / Bags / Footwear\n1 Post for Household / Kitchenware / Bathroom\n1 Post for Home Appliance / Lighting / Furniture\n1 Post for Consumer Electronics\n\nRequirements\u00a0\u00a0\n\n2-8 years of working experience of product development, sourcing and merchandising\nExtensive knowledge in Toys / Gift Premium / Home Appliance / Household products is a preferable, Sundries items are also consider\nSupplier selection and vendor management, ensuring best buy and good services from suppliers\nSource and review new suppliers\u2019 capabilities to establish long term strategic vendor management program\nWork with Engineering and QA team to ensure product comply with US, European and other countries regulations\nManage sample development and follow up production run for all projects\nPrepare merchandising information and report for project updates ie cost sheets, purchase orders and relevant documents\nCoordinate with QA and/or Technical team on sample process, production orders and delivery status\nWork with factories and internal shipping team to ensure all shipping documents are in plan for on time shipment\nFacilitate order placement process with suppliers\nExcellent communication and interpersonal skills\nGood command of both written and spoken English and Chinese (Putonghua)\nLess experienced candidates will also be considered as Assistant Merchandiser\n\nInterested parties, please send your resume with expected salary by clicking the below \"apply now\" button.\u00a0You can ask click on the website\u00a0www.easyjobhk.com\u00a0for more details about the company", "employment_types": ["Full Time", "Permanent"], "selling_points": ["Toys, textile / bedding sourcing exp", "Sourcing office exp is preferable", "15days AL + 1 day birthday leave"], "locations": ["Kwun Tong Area"], "categories": ["Manufacturing", "Manufacturing Management", "Product Development / Management", "Merchandising & Purchasing", "Sundries"], "post_time": "2022-01-14T10:21:06Z", "salary": {"currency": "HKD", "max": 24999, "min": 20000, "period": "monthly", "term": null}, "salary_visible": true, "title_keywords": ["merchandiser", "product developer"], "responsibilities": ["regulations", "shipping documents", "management", "cost", "shipping", "review", "merchandising", "coordinate with", "project updates", "communication", "purchase", "plan", "report"], "requirements": {"degrees": [], "majors": [], "languages": ["putonghua", "english", "chinese"], "language_level": ["good command"], "hard_skills": ["vendor"], "soft_skills": ["communication and interpersonal skills", "extensive"], "languages_combined": [{"language": "putonghua", "language_level": ["good command"]}, {"language": "english", "language_level": ["good command"]}, {"language": "chinese", "language_level": ["good command"]}]}, "experience_required": {"duration": ["2-8 years"], "field": ["product development", "merchandising"]}}, {"job_id": "100003009045212", "location_code": "hk", "company": "Triple King Co Ltd", "job_title": "Merchandiser and Order Supervisor - Junior Candidates are also welcomed", "description": "Hardgoods Merchandiser - Product Development\n\nOur client is an international supplies retailer, focusing on pet products including food, toys, bedding, etc. They are looking for a Merchandiser to join their organization, responsible for sourcing, product development, and price negotiation process.\n\nJob Description\n\nDevelop and monitor sourcing strategies and procedures, ensure the vendors is fulfilling the sourcing plans\nSource potential suppliers within Asia to support the company's sourcing plans\nCollaborate with different teams to enhance brand identity and product features, keep track of projects' critical paths\nWork closely with UK Headquarter on category & supplier strategies\nUnderstand the product trends and market insight, develop competitive product ranges\nNegotiate and improve price competitiveness, deliver margin gains, improve payment terms and shipment date\nFollow up sourcing processes and help maintain sourcing systems\nTravel to factories /suppliers for buying trips & new product development\nManage any ad hoc projects, frequent travel to PRC\n\nRequirements\n\nDegree holder or above in the relevant discipline\nExperience of working in a sourcing/buying office is preferable\n2 - 5 years solid experience in developing or sourcing toys, textile or bedding products\nStrong negotiation and presentation skills, attention to details\nGood command of both spoken and written English, Cantonese & Mandarin\nWilling to travel to PRC\n\n", "employment_types": ["Full Time"], "selling_points": ["Ability to deal with suppliers", "Ability to take in charge new projects", "Willing to learn and be committed"], "locations": ["Kwun Tong"], "categories": ["Manufacturing", "Product Development / Management", "Merchandising & Purchasing", "Sundries", "Procurement / Purchasing / Sourcing"], "post_time": "2022-01-13T07:26:37Z", "salary": {"currency": "HKD", "max": 19999, "min": 14000, "period": "monthly", "term": null}, "salary_visible": true, "title_keywords": ["merchandiser", "supervisor", "junior"], "responsibilities": ["collaborate with", "systems", "monitor", "procedures", "teams", "develop", "payment", "maintain", "ad hoc projects", "plans"], "requirements": {"degrees": ["degree holder"], "majors": [], "languages": ["cantonese", "english", "mandarin"], "language_level": ["good command"], "hard_skills": [], "soft_skills": ["presentation skills", "negotiation", "attention to details"], "languages_combined": [{"language": "cantonese", "language_level": ["good command"]}, {"language": "english", "language_level": ["good command"]}, {"language": "mandarin", "language_level": ["good command"]}]}, "experience_required": {"duration": ["2 - 5 years"], "field": ["toys", "developing", "textile"]}}, {"job_id": "100003009053149", "location_code": "hk", "company": "The American Club", "job_title": "Purchasing Manager (5 days work)", "description": "Job Summary:\n\nResponsible for managing and leading the overall Purchasing function by developing and executing the purchasing strategies\nResponsible for improving operational efficiency of current ERP system and of the Purchasing Department\nPerform cost analysis and conduct market price trend analysis to ensure long terms saving and quality improvement\nResponsible for departmental staff development\n\nJob Duties and Responsibilities:\n\nReport to the Finance Director about all matters of purchasing and sourcing\nDirect supervision of a team of Assistant Purchasing Manager and Purchasing Officer\nProcess all purchase request for F&B items, non F&B items, capital expenditure items, consignment items, project related items, etc\nTender process including preparation/analysis/award \u2013 work closely with Finance Director and related Senior Managers\nMaintain a complete record of catalogues and suppliers/vendors contacts\nVendor management process including supplier/vendor selection and creation of all new suppliers/vendors\nPrice and terms negotiation with selected supplier/vendor for the best deal\nPerform \u201cSupplier Quality & Food Safety Evaluation\" by site visit with related department personnel for pre-selected suppliers/vendors\nApprove all pertinent purchasing reports: (a) Monthly/YTD Saving Report, (b) Purchase Order Amendment, (c) Periodic Competitive Price Analysis Reports\nEnsure the delivery of product / service on time and conform to the requirements\nEnsure all the purchasing procedures are carried out in accordance with the Club\u2019s policies and procedures\nStrategic purchases for long term savings and quality improvement\n\nJob Requirements\n\nEducation: Degree Holder in Purchasing & Supply Chain Management or related disciplines\nExperience: At least 5 years\u2019 managerial experience in hospitality or similar industry\n\nWorking location: Tai Tam\n\nWe offer attractive remuneration. Please send full resume by clicking\u00a0Apply Now, by Whatsapp: 9093 7658, or by fax: 3585 1360. For more information please visit our website:\u00a0www.americanclubhk.com\n\nWe are an equal opportunity employer. All information provided by applicants will be used for recruitment related purpose only and handled in strict confidence by authorized personnel only. Only short-listed candidates will be notified. The personal data collected will be destroyed after 3 months.", "employment_types": ["Full Time", "Permanent"], "selling_points": ["Managerial grade benefit", "2 months bonus", "In charge of food/non food purchasing of the Club"], "locations": ["Southern Area"], "categories": ["Hospitality / F & B", "Hospitality / Hotel Services", "Merchandising & Purchasing", "Sundries", "Procurement / Purchasing / Sourcing"], "post_time": "2022-01-17T06:07:59Z", "salary": {"currency": null, "max": null, "min": null, "period": "monthly", "term": null}, "salary_visible": false, "title_keywords": ["purchasing manager"], "responsibilities": ["management", "food safety", "terms negotiation", "analysis reports", "policies", "analysis", "quality", "procedures", "purchase", "maintain", "reports", "tender", "evaluation", "report"], "requirements": {"degrees": ["degree holder"], "majors": ["related disciplines"], "languages": [], "language_level": [], "hard_skills": [], "soft_skills": [], "languages_combined": []}, "experience_required": {"duration": ["at least 5 years"], "field": ["managerial"]}}, {"job_id": "100003009056542", "location_code": "hk", "company": "Simple Symbol Ltd", "job_title": "Merchandiser", "description": "At least 3-4 years\u00a0working experience in Stationery, Health & Beauty Products\nForm 6 or above, fluent in English, Putonghua and Cantonese\nGood interpersonal / communication skills\nAble to work independently under pressure, traveling and overtime required\nResponsible and self-motivated", "employment_types": ["Full Time"], "selling_points": [], "locations": ["Hung Hom"], "categories": ["Merchandising & Purchasing", "Stationery", "Sundries"], "post_time": "2022-01-18T04:44:58Z", "salary": {"currency": null, "max": null, "min": null, "period": "monthly", "term": null}, "salary_visible": false, "title_keywords": ["merchandiser"], "responsibilities": ["communication", "stationery"], "requirements": {"degrees": [], "majors": [], "languages": ["cantonese", "putonghua", "english"], "language_level": ["fluent"], "hard_skills": [], "soft_skills": ["communication skills", "work independently", "self-motivated", "under pressure", "responsible", "interpersonal"], "languages_combined": [{"language": "cantonese", "language_level": ["fluent"]}, {"language": "putonghua", "language_level": ["fluent"]}, {"language": "english", "language_level": ["fluent"]}]}, "experience_required": {"duration": ["at least 3-4 years"], "field": ["beauty"]}}, {"job_id": "100003009056502", "location_code": "hk", "company": "Orenji Creation Limited", "job_title": "Junior Project Executive / Junior Merchandiser (Merchandising) - Fresh Graduate are welcomed", "description": "Overview:\n\nOrenji Creation Limited is a design, gift and premium company that provides professional one-stop service to international well-known brands in Asia Pacific. To Cope with our rapid expansion, we are now inviting high caliber candidate pursuing to join our team in Hong Kong.\n\nJob Requirement:\n\nDiploma holder or above\n1-2 years or above relevant working experience (Fresh Graduate are also welcomed)\nSolid knowledge of gift & premium industry\nStrong in Product Development\nHardworking, Self-motivated, Independent, Attention to detail, Teamwork spirit\nStrong negotiation skill\nAble to work under pressure and tight deadline\nProficiency in PC skills\nFluent in written and spoken English and Mandarin\nImmediate available preferred\n\nResponsibilities:\n\nTo source factories for quality comparison\nTo coordinate with internal parities and follow up production from product development to delivery\nClosely Monitor the production process\nTo solve problem with the factories to ensure product quality and meet tight schedule\nCoordinate with Lab Test Company, ensure the product meet Client\u2019s product safety standard\nFrequent Travel to PRC is required\n\nInterested parties please send a cover letter stating your expected salary, resume and a full set of your portfolio to us.\n\n*All information will be treated as confidential and used solely for recruitment purposes.\n\nInterested parties, please click Apply Now to submit your full resume.", "employment_types": ["Full Time", "Permanent"], "selling_points": [], "locations": ["Wong Tai Sin Area"], "categories": ["Merchandising & Purchasing", "Sundries", "Others", "Procurement / Purchasing / Sourcing"], "post_time": "2022-01-18T04:47:46Z", "salary": {"currency": null, "max": null, "min": null, "period": "monthly", "term": null}, "salary_visible": false, "title_keywords": ["merchandising", "project executive", "junior merchandiser", "junior"], "responsibilities": ["production process", "monitor", "quality", "coordinate with", "schedule"], "requirements": {"degrees": ["diploma holder", "fresh graduate"], "majors": [], "languages": ["english", "mandarin"], "language_level": ["fluent"], "hard_skills": ["pc skills"], "soft_skills": ["self-motivated", "independent", "teamwork spirit", "attention to detail", "negotiation skill", "hardworking", "work under pressure"], "languages_combined": [{"language": "english", "language_level": ["fluent"]}, {"language": "mandarin", "language_level": ["fluent"]}]}, "experience_required": {"duration": ["1-2 years"], "field": ["relevant working experience"]}}, {"job_id": "100003009050552", "location_code": "hk", "company": "P & A Consultant Limited", "job_title": "Sales Coordinator/ Assistant Merchandiser/Warehouse & Logistic Clerk /Fresh Graduate (Top Urgent )", "description": "Sales Coordinator / Assistant Merchandiser \u00d73\nLocation :Kwai Hing/ Kwun Tong,\u00a0Salary : 14-18K ( 5 Days )\u00a0\n\u00a0Requirements:\nDegree/Diploma/ F.5\u00a0or above, 0-3 years or above exp in Assistant Merchandiser or Sales Coordinator or Sales in any products\u00a0\u00a0\nfollow up sales order, data entry, contact suppliers, clients, sourcing for sales Coordinator and Asst. Merch position etc...\u00a0\nPC knowledge, proficient in MS Outlook, Word & Excel and English & Chinese word processing\nGood command in both English and Mandarin\nFresh Graduate also Will be consider\u00a0\nWarehouse Clerk/ Logistic Clerk/ Warehouse Keeper\n(Kwai Chung- Salary : 12-15K)\n\u8077\u8cac:,\n\u4e00\u822c\u6587\u66f8\u5de5\u4f5c\n\u5b89\u6392\u51fa\u8ca8\u53ca\u6536\u8ca8\n\u8ddf\u9032\u8a02\u55ae\n\u5305\u88dd\u8ca8\u7269\u6a19\u7c64\n\u8ddf\u6d77\u5916\u540c\u4e8b\u53ca\u9999\u6e2f\u8239\u52d9\u90e8\u53ca\u63a1\u8cfc\u90e8\u540c\u4e8b\u806f\u7d61\u00a0\n\u8cc7\u683c:\n\n\u4e2d\u5b78\u7a0b\u5ea6\n\u4e00\u5e74\u76f8\u95dc\u5de5\u4f5c\u7d93\u9a57\n\u61c2\u8b80\u5beb\u4e2d\u82f1\u6587\n\u61c2\u96fb\u8166\u53caMicrosoft Office\u64cd\u4f5c\n\u5de5\u4f5c\u6642\u9593\u53ca\u798f\u5229:\n\n\u6bcf\u9031\u5de5\u4f5c\u4e94\u5929\u534a(\u9577\u77ed\u9031)\n\u9280\u884c\u5047\u671f\u3001\u96d9\u7ce7\u3001\u91ab\u7642\u798f\u5229\u3001\u7a7f\u68ad\u5df4\u58eb\u53ca\u63d0\u4f9b\u5728\u8077\u57f9\u8a13\n\u5de5\u4f5c\u5730\u9ede: \u8475\u6d8cATL\u4e09\u865f\u8ca8\u6ac3\u78bc\u982d\u00a0 \u00a0\n*** Personal data will be treated with strict confidential and used for recruitment purpose only.\n\n\nP & A consultant Ltd will not charge any fees from the above-stated job-seeker, your job apply to our company means your acceptance of our terms and conditions.", "employment_types": ["Full Time"], "selling_points": [], "locations": ["Kwai Hing"], "categories": ["Transportation & Logistics", "Inventory / Warehousing", "Merchandising & Purchasing", "Sundries", "Sales, CS & Business Devpt", "Sales Administration"], "post_time": "2022-01-15T03:51:11Z", "salary": {"currency": null, "max": null, "min": null, "period": "monthly", "term": null}, "salary_visible": false, "title_keywords": ["sales coordinator", "logistic clerk", "assistant merchandiser"], "responsibilities": ["data entry", "follow up sales order", "recruitment", "personal data", "contact suppliers"], "requirements": {"degrees": ["diploma", "degree", "fresh graduate"], "majors": [], "languages": ["english", "chinese", "mandarin"], "language_level": ["good command", "proficient"], "hard_skills": ["excel", "chinese word processing", "word", "outlook", "pc knowledge"], "soft_skills": [], "languages_combined": [{"language": "english", "language_level": ["good command", "proficient"]}, {"language": "chinese", "language_level": ["proficient"]}, {"language": "mandarin", "language_level": ["good command"]}]}, "experience_required": {"duration": [], "field": []}}, {"job_id": "100003009047857", "location_code": "hk", "company": "Michaels Global Sourcing, LLC", "job_title": "Associate Sourcing Specialist / Assistant Merchandiser", "description": "Responsibilities\nAssist in purchase coordination, prepare business analysis reports & sales forecast;\nAnalyze business trends and consumer insights to deliver brand sales and market share targets;\nAssist in product & category management;\nEnsure inventory levels of various product categories are controlled within reasonable size during both slack and peak seasons;\nCoordinate with internal and external parties to maintain daily operation and maximize business opportunities;\nAssist in ad hoc duties as required by supervisors.\nRequirements\nDegree holder with 1 - 2 years relevant working experience;\nStrong market sense and awareness;\nStrong analytical ability with excellent negotiation and communication skills;\nProactive, detail-minded and able to work independently;\nProficiency in Microsoft applications, particularly in excel applications;\nExcellent spoken and written English and Chinese, proficiency in Mandarin will be an advantage;\nFresh graduate will also be considered.\n\nWe offer\n\n5 - day work week\nMedical Benefits\nAnnual Merit Bonus\nStaff Purchase Discounts\nStaff Recreation Activity\nShuttle Bus Service\nEducation Sponsorship\n\nInterested parties please send a full resume with current and expected salary by clicking APPLY NOW:\n\nPlease visit our corporate website at\u00a0http://corp.sasa.com/en/home\u00a0to know more about us.\n\n(Sa Sa is an Equal Opportunity Employer and all qualified applicants will receive consideration for employment. Personal data collected will be kept confidential and used for recruitment purpose only)", "employment_types": ["Full Time", "Permanent"], "selling_points": ["Sourcing Process Execution and Vendor Management", "Michaels Stores, Largest US Arts & Crafts retailer", "End to end sourcing exposure"], "locations": ["Kowloon Bay"], "categories": ["Merchandising & Purchasing", "Sundries", "Others"], "post_time": "2022-01-14T04:03:38Z", "salary": {"currency": null, "max": null, "min": null, "period": "monthly", "term": null}, "salary_visible": false, "title_keywords": ["specialist", "associate", "assistant merchandiser"], "responsibilities": ["product categories", "ad hoc duties", "management", "consumer insights", "inventory", "internal and external parties", "coordinate with", "daily operation", "business opportunities", "business analysis reports", "purchase", "analyze business trends", "maintain", "forecast", "coordination"], "requirements": {"degrees": ["fresh graduate", "degree holder"], "majors": [], "languages": ["english", "chinese", "mandarin"], "language_level": ["advantage", "excellent", "proficiency"], "hard_skills": ["excel", "microsoft applications"], "soft_skills": ["detail-minded", "communication skills", "work independently", "negotiation", "strong market sense", "proactive"], "languages_combined": [{"language": "english", "language_level": ["advantage", "excellent"]}, {"language": "chinese", "language_level": ["advantage", "excellent"]}, {"language": "mandarin", "language_level": ["proficiency", "advantage", "excellent"]}]}, "experience_required": {"duration": ["1 - 2 years"], "field": ["relevant working experience"]}}, {"job_id": "100003009044488", "location_code": "hk", "company": "Shiamas Limited", "job_title": "Assistant Merchandiser", "description": "We are looking for high caliber candidate to join us and work together for the growth\u00a0of both our Company and individual.\n\nWhat will you be doing?\nThis position is responsible for supporting the execution and improvement of end-to-end best practices in Global Sourcing for assigned product categories.\u00a0\u00a0 This role is accountable for supporting the development and management of vendors, as well as maintaining existing vendor relationships and driving projects to ensure that vendors meet or exceed their contractual obligations by delivering innovative, quality products on time.\n\nRoles & Responsibility:-\n\nAssist the team in Sourcing Process Execution and Vendor Management\nExecute and improve the end-to-end sourcing processes including vendor management, price negotiation, product development and sample assessment to meet the on-time delivery, quality and commercial KPIs\nSource and develop potential vendors as well as drive a respectful and collaborative vendor relationship with existing vendors to ensure they meet all company\u2019s requirements including value, quality and innovation\nLiaise with various parties in sample handling, order management, laboratory testing, packaging artwork creation and approval processes\nSupport on Request for Proposal, category costing bids and product development independently in conjunction with and product development and sourcing teams\nAssists in product development trip, sourcing trip and finalization events to ensure its smooth arrangement\nExecute order management to ensure accuracy of database; Monitor and regular update on project status of assigned product categories\nPerform data entry and provide other administrative support in the team; Support ad hoc assignments and projects if necessary\n\nKnowledge, Skills and Abilities requirement:-\n\nDegree/Associate Degree/Diploma holder in Merchandising/ Business Management or related discipline\nHands-on computer knowledge in MS word, Excel, Outlook, Power Point & Chinese Word Processing\nMinimum 1 years\u2019 relevant working experience\nEnergetic, self-motivated, detail-oriented and independent working style\nGood communication and interpersonal skills\nEager to work in a team in order to achieve best results\nThe ability to work in a demanding but collegial, team-oriented environment\nGood command of both written and spoken English and Mandarin\nFrequent travel is required; Up to 30% travel\nWe offer competitive pay package and attractive fringe benefits including employer voluntary contribution on MPF scheme, Medical Insurance such as out-patient, hospitalization and dental coverage for employee, spouse and dependents. For interested parties, please make your application by stating the current and expected salaries.\n\nPersonal data collected will be used strictly for recruitment purpose only.", "employment_types": ["Full Time"], "selling_points": ["Diploma holder in Purchasing or equivalent", "At least 2 years\u2019 relevant working experience", "Immediate available preferred"], "locations": ["Not Specified"], "categories": ["Merchandising & Purchasing", "Sundries", "Others", "Procurement / Purchasing / Sourcing"], "post_time": "2022-01-13T08:02:48Z", "salary": {"currency": null, "max": null, "min": null, "period": "monthly", "term": null}, "salary_visible": false, "title_keywords": ["assistant merchandiser"], "responsibilities": ["product categories", "management", "price negotiation", "order management", "data entry", "administrative support", "quality", "teams", "monitor", "develop", "testing", "ad hoc assignments", "database", "liaise with", "kpis"], "requirements": {"degrees": ["diploma holder", "associate degree", "degree"], "majors": ["business"], "languages": ["english", "chinese", "mandarin"], "language_level": ["good command"], "hard_skills": ["business management", "excel", "chinese word processing", "scheme", "outlook", "power point", "ms word"], "soft_skills": ["self-motivated", "independent", "detail-oriented", "hands-on", "communication and interpersonal skills", "patient", "energetic"], "languages_combined": [{"language": "english", "language_level": ["good command"]}, {"language": "chinese", "language_level": []}, {"language": "mandarin", "language_level": ["good command"]}]}, "experience_required": {"duration": ["minimum 1 years"], "field": ["relevant working experience"]}}, {"job_id": "100003009044361", "location_code": "hk", "company": "Skyline (Far East) Co., Limited", "job_title": "Merchandiser (Seasonal, Home Decorations & Gifts)", "description": "Job Responsibilities:\n\nTo Assist Merchandising Manager in day-to-day operations\nIssue and follow up purchase orders and arrange delivery\nCheck system PO and supplier invoices and follow up with Accounts Team & Suppliers\nProvide clerical support to the team e.g. data entry, housekeep purchase database and documents\nPrepare regular reports regarding analyzing the sales and suggestion to stock replenishment\nNegotiate with suppliers to achieve competitive prices and terms\nPlan and coordinate sales promotion activities\nPerform other ad hoc duties as assigned\u00a0\n\nJob Requirements:\n\nDiploma holder in Purchasing or equivalent\nPossess with at least 2 years\u2019 relevant working experience in merchandising/supply chain field, preferably retail/accessory business\nDetail-minded, self-motivated, well-organized, good team player\nGood command of both spoken and written English, Cantonese and Mandarin\nProficiency in MS Office applications \u2013 Excel, Word, PowerPoint and Chinese Word Processing (especially at Excel e.g. Pivot Table, vlookup)\nImmediate available preferred\u00a0\n\nWe offer 5-day working week, attractive remuneration package, benefits and good prospect of career opportunities to the right candidate. \u00a0To apply, please email detailed resume with expected salary to", "employment_types": ["Full Time", "Permanent"], "selling_points": [], "locations": ["Hung Hom"], "categories": ["Merchandising & Purchasing", "Sundries", "Procurement / Purchasing / Sourcing", "Sales, CS & Business Devpt", "Account Servicing"], "post_time": "2022-01-13T03:50:16Z", "salary": {"currency": null, "max": null, "min": null, "period": "monthly", "term": null}, "salary_visible": false, "title_keywords": ["merchandiser"], "responsibilities": ["provide clerical support", "ad hoc duties", "stock replenishment", "invoices", "data entry", "day-to-day operations", "merchandising", "plan and coordinate", "purchase", "reports", "database"], "requirements": {"degrees": ["diploma holder"], "majors": [], "languages": ["cantonese", "english", "chinese", "mandarin"], "language_level": ["proficiency", "good command"], "hard_skills": ["excel", "chinese word processing", "pivot table", "word", "powerpoint", "vlookup", "ms office"], "soft_skills": ["detail-minded", "good team player", "self-motivated", "well-organized"], "languages_combined": [{"language": "cantonese", "language_level": ["good command"]}, {"language": "english", "language_level": ["good command"]}, {"language": "chinese", "language_level": ["proficiency"]}, {"language": "mandarin", "language_level": ["good command"]}]}, "experience_required": {"duration": ["at least 2 years"], "field": ["supply chain", "merchandising", "relevant working experience", "business", "retail"]}}, {"job_id": "100003009051390", "location_code": "hk", "company": "Esky Consultancy Limited", "job_title": "Sr Merchandiser / Merchandiser (Garment or Sundries)", "description": "Requirements\n\nF.5 graduated or above\nMinimum 3 years of merchandising and trading experiences is a MUST\nFluent Written and Spoken English and Mandarin\nWell organized, with good interpersonal & communication skill\nIndependent, responsible and willing to learn\nProficiency in on-hand computer skill : MS Excel, Chinese Word processing & Outlook Knowledge\nMature, stable, detail-minded and self-motivated and being a good team player, able to work under pressure\nAble to work in a fast pace environment & overtime\nLess experience will be considered as Assistant Merchandiser\nImmediate available is preferable\n\n\n\nWe offer competitive remuneration package. For Interested parties, please submit your resume by clicking ''Apply Now'' button as below.\u00a0\n\nAll the information provide by applicants will be used for\u00a0recruitment purpose only.\u00a0", "employment_types": ["Full Time", "Permanent"], "selling_points": ["Knit, ,Intimate, Sundries, Hardgoods", "Sizable and stable company", "Five-day week, good salary package"], "locations": ["Lai Chi Kok"], "categories": ["Merchandising & Purchasing", "Woven / Knit", "Sundries", "Procurement / Purchasing / Sourcing"], "post_time": "2022-01-15T13:38:17Z", "salary": {"currency": null, "max": null, "min": null, "period": "monthly", "term": null}, "salary_visible": false, "title_keywords": ["merchandiser"], "responsibilities": ["communication", "merchandising", "work under pressure"], "requirements": {"degrees": [], "majors": [], "languages": ["english", "chinese", "mandarin"], "language_level": ["proficiency", "fluent"], "hard_skills": ["chinese word processing", "ms excel", "computer skill", "outlook"], "soft_skills": ["detail-minded", "self-motivated", "good team player", "independent", "responsible", "communication skill", "well organized", "willing to learn", "mature", "stable", "interpersonal", "work under pressure"], "languages_combined": [{"language": "english", "language_level": ["fluent"]}, {"language": "chinese", "language_level": ["proficiency"]}, {"language": "mandarin", "language_level": ["fluent"]}]}, "experience_required": {"duration": ["minimum 3 years"], "field": ["merchandising", "trading"]}}, {"job_id": "100003009038148", "location_code": "hk", "company": "CASA Collective Limited", "job_title": "Merchandiser (Hardgoods)", "description": "\u00a0 \u00a0 \u00a0 \u00a0 Job Requirement\nHigher Diploma or above\nMin 2 years merchandising exp in INTIMATE or KNIT or SUNDRIES or ELECTRONIC or Hard goods\nGood interpersonal, communication skill\nProficiency in both written and spoken English, Cantonese and Putonghua\nMore experience will be considered as MERCHANDISING MANAGER\n\u00a0\u00a0 \u00a0 \u00a0 \u00a0 \u00a0\u00a0\u00a0Job Duties\nResponsible for product development and order processing\nArrange production schedule and contact to the factory\nGood communication skills with customers and vendors\n\u00a0\u00a0", "employment_types": ["Full Time"], "selling_points": ["Experience in handling relevant categories.", "Experience working in US market is a Must.", "Immediate available is preferable"], "locations": ["Lai Chi Kok"], "categories": ["Merchandising & Purchasing", "Sundries"], "post_time": "2022-01-11T05:37:03Z", "salary": {"currency": null, "max": null, "min": null, "period": "monthly", "term": null}, "salary_visible": false, "title_keywords": ["merchandiser"], "responsibilities": ["communication", "contact", "schedule", "order processing"], "requirements": {"degrees": ["higher diploma or above"], "majors": [], "languages": ["cantonese", "putonghua", "english"], "language_level": ["proficiency"], "hard_skills": [], "soft_skills": ["communication skill", "interpersonal"], "languages_combined": [{"language": "cantonese", "language_level": ["proficiency"]}, {"language": "putonghua", "language_level": ["proficiency"]}, {"language": "english", "language_level": ["proficiency"]}]}, "experience_required": {"duration": [], "field": ["merchandising"]}}, {"job_id": "100003009045210", "location_code": "hk", "company": "Baum-Essex Manufacturing (HK) Ltd", "job_title": "Quality Assurance & Compliance Co-ordinator (5 Days Work)", "description": "Assist Quality Control Manager in various QC assignments including understanding of clients\u2019 product protocols, quality procedures, lab-tests and production schedule along with factory audits;\nQuality control knowledge and experience in consumable items, particularly Ceramic Table Top, Cutlery/Kitchenware, Beach products, Umbrella, Natural Fiber Storage is preferred;\nBe able to read client manuals outline, summarize important points for QA/QC/Merchandising and co-ordination with factories;\nGood organization and project management skills;\nGood command of written and spoken English / Chinese / Mandarin;\nDiploma or Degree Holder preferred;\nWorking experience: minimum 1-2 years.\n\n\n\nInterested parties, please send your resume, expected salary & the earliest available date by clicking \u201cAPPLY NOW\u201d.\n\nPersonal data collected will be used for recruitment purpose only.", "employment_types": ["Full Time", "Permanent"], "selling_points": ["Assist Quality Control Manager in various QC", "Diploma or Degree Holder preferred", "Working experience: minimum 1-2 years."], "locations": ["Not Specified"], "categories": ["Manufacturing", "Product Development / Management", "Merchandising & Purchasing", "Sundries", "Quality Assurance, Control & Testing / ISO"], "post_time": "2022-01-13T08:04:52Z", "salary": {"currency": null, "max": null, "min": null, "period": "monthly", "term": null}, "salary_visible": false, "title_keywords": [], "responsibilities": ["quality", "procedures", "merchandising", "project management", "schedule", "quality control", "audits"], "requirements": {"degrees": ["diploma", "degree holder"], "majors": [], "languages": ["english", "chinese", "mandarin"], "language_level": ["good command"], "hard_skills": ["project management"], "soft_skills": ["project management skills"], "languages_combined": [{"language": "english", "language_level": ["good command"]}, {"language": "chinese", "language_level": ["good command"]}, {"language": "mandarin", "language_level": ["good command"]}]}, "experience_required": {"duration": ["minimum 1-2 years"], "field": ["quality control"]}}, {"job_id": "100003009049961", "location_code": "hk", "company": "P & A Consultant Limited", "job_title": "Asst. Merchandiser/Merchandiser/Sr. Merch/Asst. Merchandising Manager(Toys/Seasonal/Handbag) X10", "description": "Assistant Merchandising Manager/ Sr. Merchandiser/Merchandiser/ Assistant Merchandiser(Toys/ Sundries/ Gift & Premium/ Seasonal/ Gardening/ Plastic/ Home Decoration/ Polyresin/ Metal/ Wooden product/ Electronic Consumer/ Sport products/ Watch/ Handbag)- Urgent X10\u00a0\nSalary : 16-34K,\u00a0Location : Hung Hom/ Lai Chi Kok/ Tsuen Wan/ Kwun Tong ( 5 Days )\u00a0\u00a0\nRequirements\u00a0 :\u00a0\n\nF.5 or above,\u00a0\nAt Least 5-10 years of Merchandiser exp in Toys( Plastic/ Hard/ Wood/ Paper /Board game\u00a0) or Seasonal or Sundries, Gift and premium /\u00a0Electronic Consumer/ Sport\u00a0/ Watch\u00a0Product\nProduct development, sourcing, follow up order & sample\nWork independently\nGood command of English & Mandarin\nCandidate have less exp also will be consider as Assistant Merchandiser\u00a0\nSr. Merchandiser/Merchandiser- Seasonal/Gardening (Urgent)\u00a0\n(Lai Chi Kok) 5 days,\u00a0salary:23-28K\u00a0\nRequirements\u00a0 :\u00a0\n\nDiploma/ Degree holder,\u00a0\nAt Least 5-10 years of Merchandiser exp in Seasonal/ Gardening\u00a0\nstrong Product development/ one man bank\u00a0\nsourcing, follow up order & sample, contact client & mfg\u00a0\nWork independently\nHave Canton Fair exp\u00a0\nGood command of Cantonese, English & Mandarin\nImmediate available is preferred\nCandidates have less exp also will be consider as Merchandiser\u00a0\n\n*** Personal data will be treated with strict confidential and used for recruitment purpose only.\n\n\nP & A consultant Ltd will not charge any fees from the above-stated job-seeker, your job apply to our company means your acceptance of our terms and conditions.", "employment_types": ["Full Time"], "selling_points": [], "locations": ["Lai Chi Kok"], "categories": ["Merchandising & Purchasing", "Handbag", "Toy", "Sundries"], "post_time": "2022-01-15T03:50:45Z", "salary": {"currency": null, "max": null, "min": null, "period": "monthly", "term": null}, "salary_visible": false, "title_keywords": ["merchandiser", "merchandising", "asst. merchandiser"], "responsibilities": ["recruitment", "personal data", "merchandising", "contact"], "requirements": {"degrees": ["diploma", "degree holder"], "majors": [], "languages": ["cantonese", "english", "mandarin"], "language_level": ["good command"], "hard_skills": ["wan", "sr", "x10"], "soft_skills": ["work independently"], "languages_combined": [{"language": "cantonese", "language_level": ["good command"]}, {"language": "english", "language_level": ["good command", "good command"]}, {"language": "mandarin", "language_level": ["good command", "good command"]}]}, "experience_required": {"duration": [], "field": []}}, {"job_id": "100003009044438", "location_code": "hk", "company": "\u59ff\u66fc\u570b\u969b\u6709\u9650\u516c\u53f8", "job_title": "Assistant Merchandiser/ Merchandiser", "description": "Overview:\n\nOrenji Creation Limited is a design, gift and premium company that provides professional one-stop service to international well-known brands in Asia Pacific. To Cope with our rapid expansion, we are now inviting high caliber candidate pursuing to join our team in Hong Kong.\n\nJob Requirement:\n\nDiploma holder or above\n1-2 years or above relevant working experience (Fresh Graduate are also welcomed)\nSolid knowledge of gift & premium industry\nStrong in Product Development\nHardworking, Self-motivated, Independent, Attention to detail, Teamwork spirit\nStrong negotiation skill\nAble to work under pressure and tight deadline\nProficiency in PC skills\nFluent in written and spoken English and Mandarin\nImmediate available preferred\n\nResponsibilities:\n\nTo source factories for quality comparison\nTo coordinate with internal parities and follow up production from product development to delivery\nClosely Monitor the production process\nTo solve problem with the factories to ensure product quality and meet tight schedule\nCoordinate with Lab Test Company, ensure the product meet Client\u2019s product safety standard\nFrequent Travel to PRC is required\n\nInterested parties please send a cover letter stating your expected salary, resume and a full set of your portfolio to us.\n\n*All information will be treated as confidential and used solely for recruitment purposes.\n\nInterested parties, please click Apply Now to submit your full resume.", "employment_types": ["Full Time", "Permanent"], "selling_points": ["3-year experience about manufacturing & merchandis", "Follow-up on sales & production arrangement", "Experience in handling OEM projects is preferable"], "locations": ["Mong Kok"], "categories": ["Merchandising & Purchasing", "Electronics", "Woven / Knit", "Sundries"], "post_time": "2022-01-13T04:04:28Z", "salary": {"currency": null, "max": null, "min": null, "period": "monthly", "term": null}, "salary_visible": false, "title_keywords": ["merchandiser", "assistant merchandiser"], "responsibilities": ["production process", "monitor", "quality", "coordinate with", "schedule"], "requirements": {"degrees": ["diploma holder", "fresh graduate"], "majors": [], "languages": ["english", "mandarin"], "language_level": ["fluent"], "hard_skills": ["pc skills"], "soft_skills": ["self-motivated", "independent", "teamwork spirit", "attention to detail", "negotiation skill", "hardworking", "work under pressure"], "languages_combined": [{"language": "english", "language_level": ["fluent"]}, {"language": "mandarin", "language_level": ["fluent"]}]}, "experience_required": {"duration": ["1-2 years"], "field": ["relevant working experience"]}}, {"job_id": "100003009047347", "location_code": "hk", "company": "DKSH Hong Kong Limited", "job_title": "Assistant, Instore Merchandising, P&G (Workstation at Office)", "description": "Responsibility\n\nResponsible for garment manufacturing & merchandising\nOrder follow up with both factory & customers is required\nHandle ad hoc tasks when required\nRequirement\n\nForm 5 graduate or above\nMinimum 3-year experience about garment manufacturing & merchandising\nExperience in handling OEM projects is preferable\nMinimum 2 years merchandising or trading experience in one of the below areas:\nSundries\nDecoration\nsouvenirs\nDIY Items / Toys\nIP products\nElectronic items / Lighting\nSporting items\nPaper & gift items\nWell organized, hardworking, self-motivated, energetic, and able to work under pressure\nPC knowledge of Excel, Word, and Chinese word processing\nFluent in spoken and written Cantonese, English and Mandarin", "employment_types": ["Full Time", "Permanent"], "selling_points": ["Support instore merchandising", "FMCG merchandising (personal care product)", "P&G products, e.g. Pampers, Oral-B, Whisper, Olay"], "locations": ["Aberdeen"], "categories": ["Marketing / Public Relations", "Marketing - General / Support", "Merchandising & Purchasing", "Home Appliances", "Sundries"], "post_time": "2022-01-14T02:52:29Z", "salary": {"currency": null, "max": null, "min": null, "period": "monthly", "term": null}, "salary_visible": false, "title_keywords": ["merchandising", "assistant"], "responsibilities": ["ad hoc tasks", "merchandising"], "requirements": {"degrees": ["form 5"], "majors": [], "languages": ["cantonese", "english", "chinese", "mandarin"], "language_level": ["fluent"], "hard_skills": ["excel", "chinese word processing", "word", "ip", "pc knowledge"], "soft_skills": ["self-motivated", "well organized", "energetic", "hardworking", "work under pressure"], "languages_combined": [{"language": "cantonese", "language_level": ["fluent"]}, {"language": "english", "language_level": ["fluent"]}, {"language": "chinese", "language_level": []}, {"language": "mandarin", "language_level": ["fluent"]}]}, "experience_required": {"duration": ["minimum 3-year", "minimum 2 years"], "field": ["garment", "manufacturing", "merchandising", "trading"]}}, {"job_id": "100003009035304", "location_code": "hk", "company": "Asian Trade (Hong Kong) Limited", "job_title": "Merchandiser", "description": "Job Responsibilities\n\nSupport instore merchandising for key accounts (e.g. mannings, Watsons, ParknShop, Wellcome) as per company instructed\nProvide report on progress\nEnsure KPIs are achieved\nJob Requirements\n\n1 years\u2019 experience in FMCG merchandising, personal care product is preferred\nExperience in key accounts operations is an advantage\nGood communication, to collaborate with internal/external parties\nAble to work independent, self-motivated with responsibility\nFluency in Chinese and ideally in English, both written and spoken\nProficient in office productivity tools (e.g. Excel, Word and PowerPoint)\nWorking location: Wong Chuk Hang\n\nPlease apply with full particulars, contact number and current/expected salary to Human Resources Department, DKSH Hong Kong Limited, 23rd Floor, Tower A, Southmark, 11 Yip Hing Street, Wong Chuk Hang, Hong Kong or click the APPLY NOW button below. All personal data collected will be used for recruitment purpose only. Candidates will be contacted within 2 weeks if the background and experience are closely relevant to the job requirement.\n\nDrive Growth. Be the Difference. Join DKSH.\n\nDKSH\u2019s strength lies in our great diversity of services, industries, clients, products, regions, and employees from various cultures. We are proud of our people: they are the best in the industry and the reason for our business success. They are passionate, energetic, and purposeful, positively touching millions of lives through the products and services we provide. Join us today if you are ready to \u201cDrive Growth. Be the Difference.\u201d With DKSH, you will experience a world of learning and development, own your career and take business responsibility, and have a positive impact that touches people\u2019s lives.\n\n", "employment_types": ["Full Time"], "selling_points": [], "locations": ["Sheung Wan"], "categories": ["Merchandising & Purchasing", "Sundries"], "post_time": "2022-01-10T07:22:57Z", "salary": {"currency": null, "max": null, "min": null, "period": null, "term": null}, "salary_visible": false, "title_keywords": ["merchandiser"], "responsibilities": ["kpis", "merchandising", "report"], "requirements": {"degrees": [], "majors": [], "languages": ["english", "chinese"], "language_level": ["fluency"], "hard_skills": ["excel", "word", "powerpoint", "reason"], "soft_skills": ["communication", "self-motivated", "independent"], "languages_combined": [{"language": "english", "language_level": []}, {"language": "chinese", "language_level": ["fluency"]}]}, "experience_required": {"duration": ["1 years"], "field": ["personal care", "fmcg", "merchandising"]}}, {"job_id": "100003009046426", "location_code": "hk", "company": "Eternity Consultants (HK) Ltd", "job_title": "Sourcing Manager / Senior Buyer ~ Supermarket (Food and Non-food Products)", "description": "Sheung Wan\n\nMerchandiser\n\nDuties:\n\n-\u00a0\u00a0\u00a0\u00a0\u00a0\u00a0 Responsible for product sourcing, product development and cost analysis\n\n-\u00a0 \u00a0 \u00a0 \u00a0Responsible to manage the samples and couriers for overseas customers\n\n-\u00a0\u00a0\u00a0\u00a0\u00a0\u00a0 Closely monitor and conduct quality control on merchandise and vendors\u2019 production processes in accordance with QC procedures\n\n-\u00a0\u00a0\u00a0\u00a0\u00a0\u00a0 Establishes strong relationship with vendors on strategic level\n\nRequirements:\n\n-\u00a0\u00a0\u00a0\u00a0\u00a0\u00a0 F.6 or above\n\n-\u00a0\u00a0\u00a0\u00a0\u00a0\u00a0 More than 2 years relevant experience\n\n-\u00a0\u00a0\u00a0\u00a0\u00a0\u00a0 Product knowledge for Ceramic/ Glass/ Metal/ Printing items for Europe market is preferred\n\n-\u00a0\u00a0\u00a0\u00a0\u00a0\u00a0 Good command of spoken and written English and Chinese\n\n-\u00a0\u00a0\u00a0\u00a0\u00a0\u00a0 Responsible and hardworking, well-organized and good communication skills\n\n-\u00a0\u00a0\u00a0\u00a0\u00a0\u00a0 Traveling to China is required\n\n-\u00a0\u00a0\u00a0\u00a0\u00a0\u00a0 Immediately available is highly preferred\n\nPackages:\n\n-\u00a0\u00a0\u00a0\u00a0\u00a0\u00a0 Working Hours: 5 days per week\n\n-\u00a0\u00a0\u00a0\u00a0\u00a0\u00a0 Location: Sheung Wan\n\n-\u00a0\u00a0\u00a0\u00a0\u00a0\u00a0 Salary: 18k\n\nInterested parties please send your full resume with expected salary via online application\nPersonal data collected will be used for recruitment purpose only", "employment_types": ["Full Time", "Permanent"], "selling_points": ["Daily buying process from budgeting to launching", "Manage supply chain and logistics functions", "Strong organizational and planning skills"], "locations": ["Not Specified"], "categories": ["Merchandising & Purchasing", "Sundries", "Others", "Procurement / Purchasing / Sourcing"], "post_time": "2022-01-13T11:03:03Z", "salary": {"currency": null, "max": null, "min": null, "period": "monthly", "term": null}, "salary_visible": false, "title_keywords": ["sourcing manager"], "responsibilities": ["cost analysis", "monitor", "conduct quality control", "procedures"], "requirements": {"degrees": [], "majors": [], "languages": ["english", "chinese"], "language_level": ["good command"], "hard_skills": ["wan"], "soft_skills": ["communication skills", "hardworking", "well-organized", "responsible"], "languages_combined": [{"language": "english", "language_level": ["good command"]}, {"language": "chinese", "language_level": ["good command"]}]}, "experience_required": {"duration": ["2 years"], "field": ["relevant experience"]}}, {"job_id": "100003009046583", "location_code": "hk", "company": "Eternity Consultants (HK) Ltd", "job_title": "Sales Manager - Toy - Trading", "description": "A well-established holding company is starting new supermarket business, is URGENTLY seeking for:\n\nSourcing Manager / Senior Buyer ~ Supermarket (Food and Non-food Products)\n\nResponsibilities:\n\nWork closely with Sales & Business Development Team for maximizing top line and minimizing inventory\nStrong at daily / seasonal buying process from budgeting to launching\nStrong at analyze regular buying to spot out the most sellable goods in order to achieve the great sales performance\nManage supply chain and logistics functions for the imported goods / food\n\nRequirements:\n\nDegree of Business Administration or related disciplines\nMinimum 5 years of relevant experience, preferably on the food and non-food products or grocery section / frozen food in supermarket industry\nIdentify and evaluate cost saving opportunities, reliable supplier base and quality vendors\nKeep abreast of concurrent food and non-food statutory regulations as to ensure all the ordered item are comply with safety and regulatory rules\nStrong organizational and planning skills\nLess experience is also considered as \u201cSenior Buyer\u201d\n\n*Interested parties, please send full resume with current & expected salary & date available in MS WORD FORMAT ONLY to email: \u00a0jobs@HKETERNITY. com \u00a0\u00a0\u00a0or fax to 3527 0634\n\nHotline: (852) 3542 5082\n\nFor more jobs, please visit our website: www.hketernity.com\n\nWe are welcome applicants resend resumes to us even you have applied jobs in our company before.\n\n(Personal data submitted are for recruitment purpose only.)\u00a0", "employment_types": ["Full Time", "Permanent"], "selling_points": ["5- 10 in sales & marketing in trading, factory", "Plastic Toys, Soft Toys, Electronic Toys", "5 days, 13 months+bonus, bank, medical"], "locations": ["Not Specified"], "categories": ["Merchandising & Purchasing", "PVC", "Sundries", "Sales, CS & Business Devpt", "Account Servicing"], "post_time": "2022-01-15T03:49:32Z", "salary": {"currency": null, "max": null, "min": null, "period": "monthly", "term": null}, "salary_visible": false, "title_keywords": ["sales manager"], "responsibilities": ["budgeting", "inventory", "sales performance", "logistics"], "requirements": {"degrees": ["degree"], "majors": ["related disciplines", "business administration"], "languages": [], "language_level": [], "hard_skills": [], "soft_skills": ["reliable", "organizational and planning skills"], "languages_combined": []}, "experience_required": {"duration": ["minimum 5 years"], "field": ["food", "relevant experience"]}}, {"job_id": "100003009036095", "location_code": "hk", "company": "PCHI Asia Limited", "job_title": "Merchandiser", "description": "Duties:\n\nOEM project driving and Account servicing\n\nHandle daily enquiries, to solve problems on projects, daily production\n\nVideo conference with buyer\u00a0\nFollow up order, quotations\n\nAttending trade shows, leading for factory/line visits, interpreting customers\u2019 requirements to engineers or production teams.\n\nRequirements:\n\nDegree or above\nMin.5-10 years coordinator in Toys in Trading\u00a0\nDetail minded, well-organized and eager to learn\nProficiency in spoken & written English and Mandarin\nProficient in MS Word, Excel, PowerPoint\n\n*Interested parties, please Email full resume with current & expected salary & date available in MS WORD FORMAT ONLY to us\u00a0or fax to 3527 0634*\n\nWe are welcome applicants resend resumes to us even you have applied jobs in our company before.\n\nFor more jobs, please visit our website: www.hketernity.com\n\n(Personal data submitted are for recruitment purpose only.)\u00a0", "employment_types": ["Full Time"], "selling_points": [], "locations": ["Lai Chi Kok"], "categories": ["Merchandising & Purchasing", "Toy", "Sundries", "Others"], "post_time": "2022-01-10T09:19:57Z", "salary": {"currency": null, "max": null, "min": null, "period": "monthly", "term": null}, "salary_visible": false, "title_keywords": ["merchandiser"], "responsibilities": ["teams"], "requirements": {"degrees": ["degree or above"], "majors": [], "languages": ["english", "mandarin"], "language_level": ["proficiency"], "hard_skills": ["excel", "powerpoint", "ms word"], "soft_skills": ["eager to learn", "well-organized"], "languages_combined": [{"language": "english", "language_level": ["proficiency"]}, {"language": "mandarin", "language_level": ["proficiency"]}]}, "experience_required": {"duration": [], "field": []}}, {"job_id": "100003009037811", "location_code": "hk", "company": "ProCrown Fine Trading Company", "job_title": "Senior Merchandiser - Toy", "description": "We are a global sourcing company and looking for a Sr. Merchandiser/ Merchandiser for hardgoods team, looking after Home D\u00e9cor and household products. This role will be reporting to the Assistant Merchandise Manager and Divisional Merchandise Manager.\n\n\u00a0Key responsibilities include:\n\nWork with AMM / DMM of the whole supply chain from factory sourcing, development till shipment. Proactive on problem precaution and solving.\nWell organization skills, attentive to details and problem solving mindset is prerequisite.\nAble to work independently with factories and customers.\nMonitor suppliers performance to ensure product development and production on right track.\nCoordinate with cross functional teams.\nGood negotiation skills to drive cost saving and costing margin for clients\u2019 continue business growth.\nDevelop a close relationship with existing suppliers and develop new suppliers through personal connections, trade fairs and sourcing trips.\nProduct, payment and business term negotiations with suppliers.\nExperienced in work with foreign design team will be an advantage.\nWilling to travel.\n\nTo succeed in this role, you will have at least 5 years experience in sourcing & merchandising.\n\nRequirements:\n\nTertiary educated\nSelf-motivated and have strong sense of responsibility.\nIndependent and excellent time management in meeting deadline.\nGood communication skills and fluent in English, Mandarin and Cantonese.\nGood computer skills in MS Office including Excel, Power Point and MS TEAM.\nExperience in handling relevant categories.\nExperience working in US market is a Must.\nExperience in handling relevant categories\nExperience working in US market is a Must.\nImmediate available is preferable.", "employment_types": ["Full Time", "Permanent"], "selling_points": [], "locations": ["Not Specified"], "categories": ["Merchandising & Purchasing", "Toy", "Sundries"], "post_time": "2022-01-11T06:13:19Z", "salary": {"currency": null, "max": null, "min": null, "period": "monthly", "term": null}, "salary_visible": false, "title_keywords": ["senior merchandiser"], "responsibilities": ["cost", "teams", "monitor", "coordinate with", "develop", "design", "merchandising", "payment"], "requirements": {"degrees": [], "majors": [], "languages": ["cantonese", "english", "mandarin"], "language_level": ["fluent", "good"], "hard_skills": ["power point", "excel", "computer skills", "ms office"], "soft_skills": ["communication skills", "self-motivated", "independent", "sense of responsibility", "time management"], "languages_combined": [{"language": "cantonese", "language_level": ["fluent", "good"]}, {"language": "english", "language_level": ["fluent", "good"]}, {"language": "mandarin", "language_level": ["fluent", "good"]}]}, "experience_required": {"duration": [], "field": []}}, {"job_id": "100003009037797", "location_code": "hk", "company": "Vaform (HK) Company", "job_title": "Merchandiser \u2013 Home Decoration & Sundries", "description": "Responsibilities and Duties\n\nAssist in the development of appropriate sourcing opportunities by downloading artworks and preparing sample shipments\nMaintains development logs, files, compiles data, creates reports\nAssist Merchandiser in entering approvals comments in PLM\nMonitors the production WIP, testing and inspection and delivery status for all purchase orders to meet delivery goals\nReview pending or failed inspection reports with Merchandiser to take necessary action\nFollows up with factories on production inner samples submission and handle sample shipments\nIdentifies and escalates any production, quality and delivery issues to Merchandiser\nSupport smooth, efficient, and effective buyer/sourcing and design visits by assisting with trip planning and supplier meetings\n\nJob Requirements\n\nUniversity degree or relevant experience\nMinimum 0-3 years\u2019 experience in merchandising, preferably in sourcing/buying offices\nStrong team player with excellent communication and interpersonal skills\nAbility to work independently, self-motivated, responsible and willing to learn\nAttention to detail, organizational and multitasking skills\nProficient in Microsoft Office (Word, Excel, Pivot Tables and VLOOKUP, PowerPoint, and Outlook)\nGood command of both verbal and written English and Chinese including Mandarin", "employment_types": ["Full Time", "Permanent"], "selling_points": [], "locations": ["Not Specified"], "categories": ["Merchandising & Purchasing", "Toy", "Sundries", "Others"], "post_time": "2022-01-11T06:12:32Z", "salary": {"currency": null, "max": null, "min": null, "period": "monthly", "term": null}, "salary_visible": false, "title_keywords": ["merchandiser"], "responsibilities": ["inspection reports", "delivery issues", "data", "comments", "review", "quality", "design", "testing", "inspection", "purchase", "reports", "planning"], "requirements": {"degrees": ["university degree"], "majors": [], "languages": ["english", "chinese", "mandarin"], "language_level": ["good command"], "hard_skills": ["excel", "microsoft office", "word", "powerpoint", "outlook", "vlookup"], "soft_skills": ["work independently", "self-motivated", "responsible", "organizational", "willing to learn", "communication and interpersonal skills", "attention to detail", "team player"], "languages_combined": [{"language": "english", "language_level": ["good command"]}, {"language": "chinese", "language_level": ["good command"]}, {"language": "mandarin", "language_level": ["good command"]}]}, "experience_required": {"duration": ["minimum 0-3 years"], "field": ["merchandising", "relevant experience", "buying offices"]}}, {"job_id": "100003009041937", "location_code": "hk", "company": "J&C Employment Consultant", "job_title": "Merchandiser/ Purchaser \u2013 Office Supplies (18-20K) (JC021)", "description": "Job Requirements\n\nDiploma holder or above\n7-8 years working experience in toys merchandising\nExperience in hard toys and product development is preferred\nIndependent, well-organized, energetic and attention to details\nGood command of spoken & written English, Mandarin is a plus\nConversant with computer skills in MS Word, Excel and Outlook\nImmediate available would be an advantage\n\nJob Responsibilities\n\nHandle sales orders from sample arrangement to bulk production\nWork closely with overseas clients and factories for order follow up\nCoordinate product development process with suppliers and factory\nResponsible for sourcing vendors, costing and price & terms negotiation\nHandle production coordination with factory for delivery arrangement\n\nWe offer excellent fringe benefits and attractive development prospect to the right candidates. Interested parties, please apply with full resume stating expected & last salary and date of available by clicking \u2018Apply Now\u2019", "employment_types": ["Full Time", "Permanent"], "selling_points": ["merchandising / purchasing experience", "office supplies items", "Diploma or above"], "locations": ["Kwai Tsing Area"], "categories": ["Merchandising & Purchasing", "Stationery", "Sundries", "Procurement / Purchasing / Sourcing"], "post_time": "2022-01-12T04:43:17Z", "salary": {"currency": null, "max": null, "min": null, "period": "monthly", "term": null}, "salary_visible": false, "title_keywords": ["merchandiser"], "responsibilities": ["coordinate", "coordination with", "terms negotiation"], "requirements": {"degrees": ["diploma holder"], "majors": [], "languages": ["english", "mandarin"], "language_level": ["good command"], "hard_skills": ["excel", "plus", "computer skills", "outlook", "ms word"], "soft_skills": ["energetic", "independent", "well-organized", "attention to details"], "languages_combined": [{"language": "english", "language_level": ["good command"]}, {"language": "mandarin", "language_level": ["good command"]}]}, "experience_required": {"duration": ["7-8 years"], "field": ["toys", "product development", "merchandising"]}}, {"job_id": "100003009034514", "location_code": "hk", "company": "Twelve NYC Asia Limited", "job_title": "Senior Merchandiser - Sundries", "description": "Job Requirements\n\nDiploma graduate or above\n3-4 years relevant experience in sundries merchandising\nExperience in home decoration would be an advantage\nAble to handle orders from product development to production\nWell-versed in MS Office including Word, Excel and Outlook\nGood command of English and fair in spoken Mandarin\nImmediate available is highly preferred\n\nJob Responsibilities\n\nCoordinate order processing with overseas customers and China factory\nHandle quotation & purchase order follow up and arrange sample delivery\nAssist in sourcing vendors, lab dip follow up and production coordination\nProvide merchandising support from product development to production\n\nWe offer attractive career development prospects and excellent fringe benefits to the right candidates. Interested parties please send full resume with date of available, last and expected salary by clicking \u2018Apply Now\u2019", "employment_types": ["Full Time"], "selling_points": [], "locations": ["Kwun Tong"], "categories": ["Merchandising & Purchasing", "Sundries"], "post_time": "2022-01-10T03:33:29Z", "salary": {"currency": null, "max": null, "min": null, "period": "monthly", "term": null}, "salary_visible": false, "title_keywords": ["senior merchandiser"], "responsibilities": ["quotation", "merchandising", "coordinate", "purchase", "coordination", "order processing"], "requirements": {"degrees": ["diploma"], "majors": [], "languages": ["english", "mandarin"], "language_level": ["good command"], "hard_skills": ["excel", "outlook", "word", "ms office"], "soft_skills": [], "languages_combined": [{"language": "english", "language_level": ["good command"]}, {"language": "mandarin", "language_level": ["good command"]}]}, "experience_required": {"duration": ["3-4 years"], "field": ["merchandising", "relevant experience"]}}, {"job_id": "100003009040030", "location_code": "hk", "company": "Festival Products (HK) Ltd", "job_title": "Merchandiser/ Assistant Merchandiser (5 days work week)", "description": "Job description:\n\n\n\nResponsibilities:\n\nResponsible of developing businesses with Sundries/ Bags/ Accessories / Festival Decoration/ Gift & Premium/ Home Products/ Seasonal Items/\u00a0Plastic / Stationery etc..\nPursue and receive all product specifications from customers and contact with factories to follow up all necessary processes including technical issues\u00a0\nMonitor factory performance in order to ensure product development and production are on right track\nProduction planning, monitoring the factory capacity and production status contact closely with QC / QA related to quality issue from all development samples to bulk productions and to ensure the goods should be correctly, completely, meeting quality standard and delivery on time as requested from customers\nParticipate in ad-hoc projects as assigned\n\nRequirements:\n\nDegree or equivalent\nFrequently travel to China factory is needed\nAt least 10 years\u2019 solid practice in merchandising field in\u00a0SUNDRIES & BAGS\nExpertise of sourcing and production processes is essential, with\u00a0working practice in factory is preferred\nHard working, well organized, proactive team and result-oriented, flexible and be capable to follow up client's requirements independently and effectively\nAttentive to details and problem solving mindset is prerequisite\nSound PC expertise \u2013 Word Processing, Excel and Power Point\n\nFluency in both written and oral English, Cantonese and Mandarin\nMature, responsible, self-motivated and able to work under pressure\n\n\n\nWe offer competitive remuneration package including 5-day work and other benefits to the right candidate", "employment_types": ["Full Time", "Permanent"], "selling_points": [], "locations": ["Kwun Tong"], "categories": ["Merchandising & Purchasing", "Toy", "Sundries", "Procurement / Purchasing / Sourcing"], "post_time": "2022-01-12T00:52:13Z", "salary": {"currency": null, "max": null, "min": null, "period": "monthly", "term": null}, "salary_visible": false, "title_keywords": ["merchandiser", "assistant merchandiser"], "responsibilities": ["monitoring", "monitor", "stationery", "developing", "production planning", "quality", "specifications", "contact", "ad-hoc projects"], "requirements": {"degrees": ["degree"], "majors": [], "languages": ["cantonese", "english", "mandarin"], "language_level": ["fluency"], "hard_skills": ["excel", "word processing", "problem solving", "power point", "pc"], "soft_skills": ["flexible", "oral", "independently", "self-motivated", "capable", "attentive to details", "responsible", "hard working", "well organized", "mature", "problem solving", "proactive", "result-oriented", "work under pressure"], "languages_combined": [{"language": "cantonese", "language_level": ["fluency"]}, {"language": "english", "language_level": ["fluency"]}, {"language": "mandarin", "language_level": ["fluency"]}]}, "experience_required": {"duration": [], "field": []}}, {"job_id": "100003009040217", "location_code": "hk", "company": "", "job_title": "Assistant Merchandiser", "description": "Responsibilities:\n\nSupport Senior Merchandiser and Merchandiser in order process and follow-up with suppliers and factories\nCo-ordinate samples arrangement e.g. receive and unpack samples, prepare for checking, pack and send to buyers, manage storage and clearance etc.\nFinalize artwork and print proof with supervisor\u00a0\nConfirm price labels and carton labels\nRemind supplier about FRI and inline inspection booking\nLiaise with logistics department to monitor vessel bookings and closing date\nSupport general clerical duties\n\nRequirements:\n\nDiploma or above, relevant experience in hardgoods merchandising is an advantage\nExperience of at least 1-2 years as in sourcing / buying office or trading company\nConversant with MS Office, Outlook, Word, Excel and Internet\nFluent in spoken & written English, Cantonese & Mandarin is a must\nSelf-motivated, ability to work in a team and attention to details\nHardworking, good time management and organizational skills\nAbility to handle pressure and willing for routine work\n\nWe offer right candidate with competitive salary, 13th month salary, 5-day work per week, flexible working hours, 15 days annual leave, birthday leave, family leave, education sponsorship, MPF voluntary contribution, medical & dental insurance, business travel insurance.\n\nInterested parties please send us your full resume with last/current and expected salary by clicking \u201cApply Now\u201d\n\nPlease visit our website for more information: https://www.migros.com.hk/\n\nAll data collected will be used for recruitment purpose only.", "employment_types": ["Full Time", "Permanent"], "selling_points": [], "locations": ["Hung Hom"], "categories": ["Merchandising & Purchasing", "Sundries", "Others", "Procurement / Purchasing / Sourcing"], "post_time": "2022-01-12T01:55:09Z", "salary": {"currency": null, "max": null, "min": null, "period": "monthly", "term": null}, "salary_visible": false, "title_keywords": ["assistant merchandiser"], "responsibilities": ["monitor", "checking", "inspection", "logistics", "booking", "liaise with"], "requirements": {"degrees": ["diploma or above"], "majors": [], "languages": ["cantonese", "english", "mandarin"], "language_level": ["fluent"], "hard_skills": ["excel", "outlook", "word", "ms office"], "soft_skills": ["flexible", "organizational skills", "self-motivated", "attention to details", "time management", "hardworking"], "languages_combined": [{"language": "cantonese", "language_level": ["fluent"]}, {"language": "english", "language_level": ["fluent"]}, {"language": "mandarin", "language_level": ["fluent"]}]}, "experience_required": {"duration": ["at least 1-2 years"], "field": ["merchandising", "relevant experience", "trading"]}}, {"job_id": "100003009037317", "location_code": "hk", "company": "METRO Sourcing International Limited", "job_title": "Junior Merchandiser / Merchandiser Assistant (Dinning&Cooking ware / Electrical)", "description": "A MEDIUM SIZED EXPORT FIRM IN\u00a0HUNG HOM\u00a0REQUIRES:\n\n-\u00a0 F.6\u00a0 or above\u00a0\n- Quotation, Sampling and Orders follow up etc.\n- Handle customers enquire\n- English is required and Mandarin is preferred\n- PC knowledge (Ms office, Email) is required\n- Minimum 2-3 years working experience\n- 5-Day work week\n- Bank Holidays\n\n\u00a0For any enquiries,\u00a0 please \u00a0Call 2303-0343.\u00a0", "employment_types": ["Full Time", "Permanent"], "selling_points": ["Exp in merchandising / trading for EU markets", "Resp. for end to end merchandising activities", "MNC, 5-day work, insurance, double pay, bonus"], "locations": ["Kowloon Bay"], "categories": ["Merchandising & Purchasing", "Electronics", "Home Appliances", "Sundries"], "post_time": "2022-01-11T16:01:39Z", "salary": {"currency": null, "max": null, "min": null, "period": "monthly", "term": null}, "salary_visible": false, "title_keywords": ["merchandiser", "junior merchandiser", "assistant"], "responsibilities": ["quotation"], "requirements": {"degrees": [], "majors": [], "languages": ["english", "mandarin"], "language_level": [], "hard_skills": ["pc knowledge", "ms office"], "soft_skills": [], "languages_combined": [{"language": "english", "language_level": []}, {"language": "mandarin", "language_level": []}]}, "experience_required": {"duration": ["minimum 2-3 years"], "field": []}}, {"job_id": "100003009029700", "location_code": "hk", "company": "Creative China Creations Limited", "job_title": "Production & Quality Engineer (Consumer Products & Sundries)", "description": "Role Purpose:\nOur Junior Merchandiser / Merchandiser Assistant are responsible for everyday end to end merchandising activities and support in the global sourcing and chain supply projects.\nWhat you will be handling:\nResponsible for order follow-up, buying trips preparation, sample handling and showroom management\nEngage in merchandising process such as sourcing, product development, article & offer management and supplier management\nWork directly with overseas suppliers and customers to ensure smooth operations\nCoordinate with internal departments e.g. Packaging, Quality Assurance, Logistics and other external service providers to ensure on-time shipment\nMaintain accurate and updated order status and product information in supply chain system\nTalent that we are looking for:\nExperience and knowledge\u00a0in merchandising / trading industry\nGood negotiation skills and problem-solving skills\nOpen minded, right attitude to learn and bring about change\nEnergetic to drive for customer success and excellent service\nStrong sense of ownership and high degree of independence\nPassionate in connecting with people and adopting high level of interpersonal skills\nWilling to travel when needed\nExperience, knowledge and skills required:\nDegree holder in\u00a0Business Administration / Supply Chain Management / International Business or equivalent discipline\nAt least 2 years\u2019 relevant merchandising experience, EU market experience is preferred\nProficient in both spoken and written English and Mandarin\nProficient in MS Office (Excel / Word / PowerPoint / Outlook) applications\nCandidate with less experience will be considered as\u00a0Merchandiser Assistant\nFresh graduates are also welcome\nYou can enjoy:\nDiverse and Inclusive work environment\nFlexi Office Space with flexible working hours and home office option\n5-day work week, 13th month salary & performance bonus\nProfessional training and career advancement opportunities\nTraining Sponsorship for personal professional development\n\n\nJoin us\u00a0and\u00a0apply\u00a0now!\n\n\nPlease send your full resume with available date, present and expected salary to us.\nResume and personal data collected will be kept strictly confidential and used for recruitment purpose only.", "employment_types": ["Full Time", "Permanent"], "selling_points": ["Good understanding on global markets", "Able to work independently & meet tight deadlines", "Preferable 5 years of work experience"], "locations": ["Ngau Tau Kok"], "categories": ["Manufacturing", "Product Development / Management", "Merchandising & Purchasing", "Sundries", "Procurement / Purchasing / Sourcing"], "post_time": "2022-01-10T16:52:34Z", "salary": {"currency": null, "max": null, "min": null, "period": "monthly", "term": null}, "salary_visible": false, "title_keywords": ["engineer"], "responsibilities": ["management", "quality", "merchandising", "coordinate with", "maintain", "logistics", "ensure smooth operations", "recruitment", "personal data", "administration"], "requirements": {"degrees": ["degree", "degree holder"], "majors": ["international business", "business administration"], "languages": ["english", "mandarin"], "language_level": ["proficient"], "hard_skills": ["excel", "word", "powerpoint", "outlook", "problem-solving skills", "ms office"], "soft_skills": ["passionate", "flexible", "responsible", "diverse", "negotiation skills", "energetic", "interpersonal skills", "open minded", "smooth", "problem-solving skills", "accurate"], "languages_combined": [{"language": "english", "language_level": ["proficient"]}, {"language": "mandarin", "language_level": ["proficient"]}]}, "experience_required": {"duration": ["at least 2 years"], "field": ["merchandising", "trading"]}}, {"job_id": "100003009029709", "location_code": "hk", "company": "Creative China Creations Limited", "job_title": "Sourcing Coordinator/ Merchandiser /Sr. Merchandiser /Product Manager (Consumer Products/ Sundries)", "description": "Job Requirements:\n\nDevelop and implement the Creative China Creations Limited (CCCL) Vendor Quality Management System across the supplier network in China as well as CCCL own facility in Mainland China in conjunction with the product development team at Hong Kong head office.\nFacilitate correspondence on internal Quality Control checks between Hong Kong office (Product Development Team) & CCCL factory in Mainland China as well as 3rd party suppliers\nCommunicate with Hong Kong team members on technical specifications & requirements through the product development process to ensure quality standards for both product functionality, safety and compliance are met.\nEstablish protocols with supplier production teams to develop high-volume and quick- turnaround manufacturing processes and capabilities for new product implementation (NPI)\nConduct quality audits (IQC, IPQC & OQC) for pre- and mass-production at suppliers.\nIntroduce protocols for final goods inspection with supplier QC team and third-party inspectors, and SOPs for in-time reporting and rapid corrective/preventive action plan (CAPA).\nSuggest quality control enhancements for both infrastructure & ERP systems as well as specific consumer products.\nUtilize inspection metrics and quality improvement/control tools (e.g., DOE & FMEA) to drive continuous quality improvement with suppliers.\nLiaise & coordinate 3rd party inspections with various companies such as SGS, Intertek, BV, etc and help establish inspection mandates & protocols to follow.\nMonitor market sale and return data and provide warning alerts to head office for quality risk management.\nLead company initiative to support overseas suppliers to attain C-TPAT validation (Customs \u2013 Trade Partnership against Terrorism - USA) as well as meet other audit or client specific audit standards such as ISO, ETL, UL, CE, BSCI, ICTI standards.\nEXCELLENT COMMAND IN WRITTEN & SPOKEN ENGLISH, CANTONESE & MANDARIN SKILLS\nAble to Travel to China for implementation and monitoring of Quality Control systems.\nCandidates with at least 5 years\u2019 experience is preferred but not a requirement.\nThe ability to work independent or part of a larger team, with the mentality & work ethic of a leader.\nFamiliarity with Quality control systems for consumer products is preferred.\nA team leader who exhibits leadership qualities and is able to work under pressure and within time constraints.\nPermanent Hong Kong ID card Holder.\nFlexible working times and willing to work after hours if needed.\n\n\u00a0Key requirements:\n\nDegree/Diploma holder, with at least 5 years of relevant experience\nGood understanding on US/UK/EU Markets\nExcellent command in Cantonese, English and Mandarin\nGood communication and interpersonal skills to work with counterparts\nAble to work independently and meet tight deadlines\nProficient in computer skills and MS Office Applications\nUnderstand electronic circuitry in component level.\nHands on experience in operating test equipment such as voltmeter, ammeter and oscilloscope\nCoordinate weekly customer complaint meeting.\n\nInterested applicants please send your English application along with cover letter and detailed resume with current and expected salary clearly stated to \u201cApply Now\u201d.\n\nAll Personal data collected will be used for recruitment purpose only.\n", "employment_types": ["Full Time", "Permanent"], "selling_points": ["double pay and performance bonus", "Good understanding on global markets", "With at least 5 years of relevant experience"], "locations": ["Ngau Tau Kok"], "categories": ["Manufacturing", "Product Development / Management", "Merchandising & Purchasing", "Sundries", "Procurement / Purchasing / Sourcing"], "post_time": "2022-01-10T16:52:34Z", "salary": {"currency": null, "max": null, "min": null, "period": "monthly", "term": null}, "salary_visible": false, "title_keywords": ["merchandiser", "product manager", "coordinator", "sr. merchandiser"], "responsibilities": ["liaise", "data", "quality", "audit", "communication", "plan", "personal data", "work under pressure", "control", "compliance", "teams", "implementation", "infrastructure", "develop", "monitor", "reporting", "management", "monitoring", "inspection", "specifications", "sops", "audits", "communicate with", "systems", "coordinate", "recruitment", "quality control"], "requirements": {"degrees": ["diploma holder", "degree"], "majors": [], "languages": ["cantonese", "english", "mandarin"], "language_level": ["excellent"], "hard_skills": ["erp systems", "id", "vendor", "c", "computer skills", "rapid", "ms office"], "soft_skills": ["flexible", "work independently", "meet tight deadlines", "independent", "detailed", "communication and interpersonal skills", "hands on", "work ethic", "creative", "leadership", "initiative", "work under pressure"], "languages_combined": [{"language": "cantonese", "language_level": ["excellent", "excellent"]}, {"language": "english", "language_level": ["excellent", "excellent"]}, {"language": "mandarin", "language_level": ["excellent", "excellent"]}]}, "experience_required": {"duration": ["at least 5 years"], "field": ["relevant experience"]}}, {"job_id": "100003009035974", "location_code": "hk", "company": "Wolf 1834, Limited", "job_title": "Senior Merchandiser", "description": "Job Requirements:\u00a0\n\nMinimum 5 years merchandising or relevant experience in Trading or Manufacturing Company. (Sourcing, Product development experience)\nMotivated, Organized, and able to work efficiently to meet the deadlines of buyers\nEXCELLENT COMMAND IN WRITTEN & SPOKEN ENGLISH, CANTONESE & MANDARIN SKILLS\nAble to communicate with suppliers and overseas customers\nResponsible, willing to learn, exhibit a positive attitude and work overtime\nExcellent knowledge of product cost breakdown and production process.\nProficient in material sourcing and supplier evaluation and management.\nExcellent and successful in price negotiation and problem solving skills\nTravel to China for supplier evaluation, management, follow-up, and inspection.\nProficient in PC applications (Microsoft Word, Excel, Microsoft Office applications).\nAn analytical and strategic thinker who is efficient, organized, and attentive to details and able to motivate staff and work under time deadlines.\nStrong sourcing skills and network of potential suppliers that allows the company to source directly through the most cost efficient and competent factories.\nCommunicate clearly to suppliers, including lead time, capacity allocation, pricing and resource allocation to ensure reliable service, quality and low-cost procurement.\nCoordinate with factories for manufacturing process and ensure on time shipment\nSelf-motivated, detailed oriented, a team player and able to work under pressure.\u00a0\nExperienced to supervise merchandising team, & be a team leader.\nCustomer-oriented, effective interpersonal and communication skills\nAble to work independently or part of a team with overseas customers and vendors\nEffectively manage and review vendor base for optimal sourcing results and possess an extensive sourcing network and excellent relationships with vendors.\nProduct management including product development, product selection, Target Negotiation, placement order, pricing.\nAnalyze the marketplace, customers and competitors to determine the right features to bring to market\u00a0\u00a0\nDaily communications with buyers, laboratories and vendors, following through all samples, testing, production to shipments\nEnsuring an effective merchandising value chain which produces goods in good quality standard and meet tight delivery\nGood sourcing experience for USA and EU markets and are familiar with sourcing Websites such as Alibaba.com, globalsources.com, and other sourcing sites.\nA team leader who exhibits leadership qualities and is able to work under pressure and within time constraints.\nPermanent Hong Kong ID card Holder.\nFlexible working times and willing to work after hours if needed.\n\n\nKey responsibilities:\n\nTake the lead in the end-to-end product sourcing cycle from product development, price negotiation to production of consumer products\nWork with the buyers to understand the product and order requirement\nCommunicate with vendors and factories to ensure on-time delivery and resolve any potential problems\nExecute and review existing internal systems and policies to ensure smooth operations and meeting company standards\n\n\nKey requirements:\n\nDegree/Diploma holder, with at least 5 years of relevant experience\nGood understanding on global Markets\nExcellent command in Cantonese, English and Mandarin\nGood communication and interpersonal skills to work with counterparts\nAble to work independently and meet tight deadlines\nProficient in computer skills and MS Office Applications\n\n\nInterested applicants please send your English application along with cover letter and detailed resume with current and expected salary clearly stated to \u201cApply Now\u201d.\n\nAll Personal data collected will be used for recruitment purpose only.", "employment_types": ["Full Time", "Permanent"], "selling_points": ["Double Pay & Performance bonus", "Travel to China often when there is no quarantine", "5-day work"], "locations": ["Lai Chi Kok"], "categories": ["Manufacturing", "Product Development / Management", "Merchandising & Purchasing", "Sundries", "Procurement / Purchasing / Sourcing"], "post_time": "2022-01-10T09:12:31Z", "salary": {"currency": "HKD", "max": 29999, "min": 20000, "period": "monthly", "term": null}, "salary_visible": true, "title_keywords": ["senior merchandiser"], "responsibilities": ["communicate with", "price negotiation", "policies", "review", "communication", "recruitment", "ensure smooth operations", "personal data", "internal systems"], "requirements": {"degrees": [], "majors": [], "languages": ["cantonese", "english", "mandarin"], "language_level": ["excellent"], "hard_skills": ["excel", "microsoft word", "microsoft office", "id", "vendor", "pc applications", "problem solving skills"], "soft_skills": ["work overtime", "team player", "leadership", "work under pressure", "efficient", "customer-oriented", "reliable", "interpersonal", "organized", "communication skills", "work independently", "negotiation", "competent", "willing to learn", "extensive", "flexible", "self-motivated", "detailed oriented", "responsible", "attentive to details", "positive attitude", "motivated", "problem solving skills"], "languages_combined": [{"language": "cantonese", "language_level": ["excellent", "excellent"]}, {"language": "english", "language_level": ["excellent", "excellent"]}, {"language": "mandarin", "language_level": ["excellent", "excellent"]}]}, "experience_required": {"duration": ["minimum 5 years"], "field": ["manufacturing", "merchandising", "relevant experience", "product development", "trading"]}}, {"job_id": "100003009034387", "location_code": "hk", "company": "ALDI Services Asia Limited", "job_title": "Buying Specialist / Buyer (Regional Buy) - Housewares (m/f)", "description": "Job Description\n\n- Job details are as follows:\n\nHandle hard goods including watch winder, jewellery box, small leather goods, watch box, tray and handbags\nLiaise between factories and overseas offices\nTravel to China for sourcing, factory visits, meetings and inspections\nRespond emails daily\nSource materials and factories\nHandle product development\nManage orders and paper work\nConduct pre-production document and meeting with factories\nMonitor factories to assure the quality level\nConduct inline inspection at the factories\nFollow up factory audit\n\n\n-\u00a0Candidate has to have about 5 years of relevant work experience\n\n- Candidate experiences in trading or manufacturing company is required. No experience in hard-lines will not be considered\n\n- Candidate has experience in branded leather goods as an advantage\n\n- Candidate has experience in inspection as an advantage\n\n- Candidate must have high proficiency in English, Mandarin & Cantonese\n\n- Proficient in MS Office is a must\n\n\n- Candidate has to be hardworking, independent, communicative, initiative, detail-minded and responsible\n\n- Candidate has to work with a small team closely", "employment_types": ["Full Time", "Permanent"], "selling_points": ["Reviews the layout of packaging materials", "Prepares international new product proposals", "Reviews the development of the national Buying"], "locations": ["Kwun Tong"], "categories": ["Merchandising & Purchasing", "Sundries", "Others", "Procurement / Purchasing / Sourcing"], "post_time": "2022-01-10T03:17:26Z", "salary": {"currency": null, "max": null, "min": null, "period": "monthly", "term": null}, "salary_visible": false, "title_keywords": ["specialist"], "responsibilities": ["liaise", "monitor", "quality", "audit", "inspection", "pre-production"], "requirements": {"degrees": [], "majors": [], "languages": ["cantonese", "english", "mandarin"], "language_level": ["proficiency"], "hard_skills": ["small", "no", "ms office"], "soft_skills": ["detail-minded", "independent", "responsible", "initiative", "hardworking"], "languages_combined": [{"language": "cantonese", "language_level": ["proficiency"]}, {"language": "english", "language_level": ["proficiency"]}, {"language": "mandarin", "language_level": ["proficiency"]}]}, "experience_required": {"duration": ["5 years"], "field": ["manufacturing", "trading"]}}, {"job_id": "100003009039368", "location_code": "hk", "company": "Page Personnel", "job_title": "Senior Merchandiser - Bags and Accessories", "description": "We invite now high caliber talent to apply for\u00a0Buying Specialist / Buyer (Regional Buy) (m/f)\u00a0to join our rapidly growing sourcing team in Hong Kong. This position supports product development and commercialization with a fast-paced successful team.\n\nResponsibilities\n\n\nPrepares and consolidates all documents required for the smooth international procurement of products in due time (e.g. Item Confirmations, tenders, supplier contracts).\nReviews the layout of packaging materials, user manuals, and assembly instructions in accordance with the international brand style guides and relevant guidelines until final approval.\nCoordinates completely new designs or significant changes with the responsible MB/DIB in advance.\nPrepares product samples for presentation and review to the responsible MB, DIB, DIS/ GDIS.\nReviews the development of the national Buying areas with regard to overlaps and potential new products.\nPrepares international new product proposals for presentation to the national Buying department.\nSupports the MB/ DIB/ DIS in conducting market and competitor analysis.\nEffectively communicates with Sourcing, CR, Admin and Logistics team members to ensure the success of Buying operations.\nPrepares, maintains, and updates the International Category Proposal, timeline, tender schedule and product portfolios for their product area as well as the lists which serve as the basis for various evaluations.\nCommissions in-house testing of product samples and informs the BM, DIB/ DIS of the results\nMaintain and update of new and existing supplier record.\nProvide cover for the team members and supports the training of employees and trainees from other areas\n\n\u00a0Your Profile.\n\nAt least (Non-Degree) Tertiary education required.\nMinimum of 2 years' relevant working experience, preferably gained in sourcing/buying offices, working with consumer products.\nExcellent communication and interpersonal skills, team player.\nGood command of both verbal and written business English and fluency in Mandarin essential.\nAble to work independently, self-motivated, responsible, well-organized and willing to learn.\nAttention to detail and good organizing, coordination and planning skills.\nGeneral knowledge of MS office and Exchange essential.\nHigh level of maturity, integrity, trustworthiness.\n\nKey Benefits of working at ALDI.\n\nMarket leading remuneration package\n\nRewarding, attractive remuneration package.\nGroup Medical Insurance covering dental and maternity* benefits .\n\nWork-life balance\n\nFull time, permanent position, 5-day-work-week.\n20 days of paid Annual Leave.\n\nBeing part of a pleasant, successful, growing business\n\nALDI\u2019s business is expanding, same for the Hong Kong Office with lots of opportunities for growth and development.\nPleasant working atmosphere where proactive communication, teamwork and collaboration is highly valued.\n\nPeople Focused\n\nStructured, comprehensive orientation and on-the-job training.\nALDI empowers our people allowing staff ownership of their areas of responsibilities.\n\nTrust and Integrity\n\nWE DO WHAT WE SAY - \u00a0for us there is no grey area, we have robust business processes, procedures and strong governance in place.\nWe treat our staff members, customers, suppliers and service providers with trust and fairness as business partners.\n\n\u00a0* Maternity benefits only apply for female employees due to local Insurance policy\n\nHow to apply\u00a0\u00a0\n\nIf you are interested in applying for the job, we look forward to receiving your full application in English, including salary expectation and possible starting date. The application should be sent through JobsDB by clicking icon \u00a0\u201cApply Now\u201d or addressed to\u00a0ALDI HR Department, 18/F, Millennium City 6, 392 Kwun Tong Road Kwun Tong, Kowloon, Hong Kong.\n\nALDI is an Equal Opportunity employer. We are dedicated to create an equal opportunity throughout recruitment process and staff employment to build a diverse and inclusive workforce. We oppose all forms of unfair or unlawful discrimination in our selection process.\n\nAll personal data collected will be used for recruitment purposes only and be treated in strictest confidence and highest security level in accordance with Hong Kong Data (Privacy) Ordinance as well as ALDI internal Security Policy.\n\nNo part of this job content including but not limited to company information, logo and job description may be reproduced, presented, uploaded, transmitted, modified or distributed \u00a0in any form or by any means without prior permission of ALDI Services Asia Limited / ALDI Sourcing Asia Limited (\u201cthe Company\u201d). The Company reserves the right to take legal action on any unauthorized reproduction, presentation, upload, transmission, modification or distribution. Only applications submitted directly to the Company in response to this advertisement will be considered and any application received by the Company through unauthorized third party agents or via any other channels will not be considered.\n", "employment_types": ["Full Time", "Permanent"], "selling_points": ["Bags and Accessories", "Competitive package", "Flexible working arrangement"], "locations": ["Not Specified"], "categories": ["Merchandising & Purchasing", "Fabrics", "Handbag", "Sundries"], "post_time": "2022-01-11T09:31:31Z", "salary": {"currency": null, "max": null, "min": null, "period": "monthly", "term": null}, "salary_visible": false, "title_keywords": ["senior merchandiser"], "responsibilities": ["guidelines", "contracts", "analysis", "review", "operations", "testing", "communication", "commercialization", "commissions", "logistics", "schedule", "tender", "maintain", "coordination", "planning"], "requirements": {"degrees": ["degree"], "majors": [], "languages": ["english", "mandarin"], "language_level": ["fluency", "good command"], "hard_skills": ["exchange", "analysis", "ms office"], "soft_skills": ["planning skills", "work independently", "self-motivated", "responsible", "well-organized", "willing to learn", "integrity", "communication and interpersonal skills", "attention to detail", "smooth", "coordination", "team player", "presentation"], "languages_combined": [{"language": "english", "language_level": ["fluency", "good command"]}, {"language": "mandarin", "language_level": ["good command"]}]}, "experience_required": {"duration": ["minimum of 2 years"], "field": ["buying offices", "relevant working experience"]}}, {"job_id": "100003009040482", "location_code": "hk", "company": "Hillman Ross", "job_title": "Sourcing Manager (Houseware)", "description": "Responsibilities:\n\nWork closely with the Sales team to develop product range for corporate customers\nResponsible for supplier sourcing and establish close relationship with major suppliers\nNegotiate competitive product pricing and business terms\nMonitor suppliers\u2019 performance including production schedule, product quality and delivery service\n\nRequirements:\n\nDiploma / Degree holder in Purchasing and Supply Chain Management\n3-4 years merchandising / purchasing experience preferable in office supplies items (such as computer consumables or stationery)\nProficiency in MS Word & Excel\nExcellent sourcing, negotiation, interpersonal & communication skills\nSelf-initiative, able to work independently and under pressure\nGood planning & organizing skills, and detailed minded\nGood command of English & Chinese, Mandarin preferred\nOccasional travel to China required\n\nIf this is a role for you, please apply now by sending your resume (in MS WORD format) with your expected salary to us via our company email\u00a0:\u00a0info @ jncemployment.com\u00a0or click \"APPLY NOW\"\n**Due to the volume of applicants, only shortlisted candidates will be contacted.**\nThe information provided by applicants will be used for employment related purpose only. All applications will be treated in strict confidence and used exclusively for recruitment purposes.", "employment_types": ["Full Time", "Permanent"], "selling_points": ["European Buying Office", "Houseware Products", "Step up candidate will also be considered"], "locations": ["Not Specified"], "categories": ["Merchandising & Purchasing", "Sundries", "Others", "Procurement / Purchasing / Sourcing"], "post_time": "2022-01-12T02:39:35Z", "salary": {"currency": null, "max": null, "min": null, "period": "monthly", "term": null}, "salary_visible": false, "title_keywords": ["sourcing manager"], "responsibilities": ["quality", "monitor", "develop", "sales team", "schedule"], "requirements": {"degrees": ["diploma", "degree holder"], "majors": [], "languages": ["english", "chinese", "mandarin"], "language_level": ["good command"], "hard_skills": ["excel", "ms word"], "soft_skills": ["communication skills", "work independently", "confidence", "under pressure", "negotiation", "self-initiative", "interpersonal", "detailed"], "languages_combined": [{"language": "english", "language_level": ["good command"]}, {"language": "chinese", "language_level": ["good command"]}, {"language": "mandarin", "language_level": ["good command"]}]}, "experience_required": {"duration": ["3-4 years"], "field": ["purchasing", "merchandising"]}}, {"job_id": "100003009035980", "location_code": "hk", "company": "ALDI Services Asia Limited", "job_title": "Merchandiser - General Hardgoods (m/f)", "description": "Excellent opportunity for merchandising experts to work for a leading trading company.\n\nClient Details\n\nOur client is a leading trading company with over hundreds of customers in the globe. With significant business expansion in their local business, they are currently looking to recruit a Senior Merchandiser to support future operations.\n\nDescription\n\nManage end-to-end merchandising project including sourcing, product development, cost control, schedule monitoring, on time delivery and after-sales handling\nMaintain good relationship with suppliers, service providers and customers to ensure smooth operation process and generate business growth\nInitiate operation improvement to optimize business performance, cost savings, working efficiency\nAssist in ad-hoc duties as per assigned\n\nProfile\n\n5 years of experience in merchandising/procurement experience in Bags/Accessories\nStrong analytical skills with numerical sense\nOrganized and detail-oriented individual\nExcellent command in both English and Chinese\n\nJob Offer\n\nMNC Culture\nMedical covered\nCompetitive pay", "employment_types": ["Full Time", "Permanent"], "selling_points": ["Responsible for orders monitoring and follow-up", "Tender submission and shipment documents", "Communicate with Quality, CR, Admin and Logistics"], "locations": ["Kwun Tong"], "categories": ["Merchandising & Purchasing", "Stationery", "Sundries", "Watch"], "post_time": "2022-01-10T08:58:58Z", "salary": {"currency": null, "max": null, "min": null, "period": "monthly", "term": null}, "salary_visible": false, "title_keywords": ["merchandiser"], "responsibilities": ["cost", "operations", "monitoring", "merchandising", "maintain good relationship", "schedule", "cost control", "ad-hoc duties"], "requirements": {"degrees": [], "majors": [], "languages": ["english", "chinese"], "language_level": ["excellent"], "hard_skills": ["analytical skills"], "soft_skills": ["organized", "detail-oriented", "analytical skills", "smooth", "ad-hoc duties"], "languages_combined": [{"language": "english", "language_level": ["excellent"]}, {"language": "chinese", "language_level": ["excellent"]}]}, "experience_required": {"duration": ["5 years"], "field": ["merchandising", "procurement"]}}, {"job_id": "100003009040484", "location_code": "hk", "company": "Hillman Ross", "job_title": "Sourcing Manager (Tabletop)", "description": "We invite now high caliber talent to apply for Merchandiser (m/f)\u00a0to join our rapidly growing sourcing team in Hong Kong. This position supports product development and commercialization with a fast-paced successful team.\n\nResponsibilities.\n\nPerform general sourcing duties as required by the Manager\nPrepare and ensures that all documents related to tender, submission, awarding of contracts and shipments are correct and completed\nFinalize submission comparison documents and identify preferred submission in line with company procedures\nEffectively communicate with Quality, CR, Admin and Logistics team members as well as ALDI International departments/ offices and other internal/external parties on behalf of Manager/ team\nFollow through the production process for all purchased products\nCarry out visits to trade fairs or suppliers in order to manage and develop the supplier pool within the commodity area\nProvides cover for the team members and supports the training of employees and trainees from other areas\n\n\u00a0Your Profile.\n\nAt least (Non-Degree) Tertiary education required.\nMinimum of 2 years' relevant working experience, preferably gained in sourcing/buying offices, working with consumer products.\nExcellent communication and interpersonal skills, team player.\nGood command of both verbal and written business English and fluency in Mandarin essential.\nAble to work independently, self-motivated, responsible, well-organized and willing to learn.\nAttention to detail and good organizing, coordination and planning skills.\nGeneral knowledge of MS office and Exchange essential.\nHigh level of maturity, integrity, trustworthiness.\n\nKey Benefits of working at ALDI.\n\nMarket leading remuneration package\n\nRewarding, attractive remuneration package.\nGroup Medical Insurance covering dental and maternity* benefits .\n\nWork-life balance\n\nFull time, permanent position, 5-day-work-week.\n20 days of paid Annual Leave.\n\nBeing part of a pleasant, successful, growing business\n\nALDI\u2019s business is expanding, same for the Hong Kong Office with lots of opportunities for growth and development.\nPleasant working atmosphere where proactive communication, teamwork and collaboration is highly valued.\n\nPeople Focused\n\nStructured, comprehensive orientation and on-the-job training.\nALDI empowers our people allowing staff ownership of their areas of responsibilities.\n\nTrust and Integrity\n\nWE DO WHAT WE SAY - \u00a0for us there is no grey area, we have robust business processes, procedures and strong governance in place.\nWe treat our staff members, customers, suppliers and service providers with trust and fairness as business partners.\n\n\u00a0* Maternity benefits only apply for female employees due to local Insurance policy\n\nHow to apply\u00a0\u00a0\n\nIf you are interested in applying for the job, we look forward to receiving your full application in English, including salary expectation and possible starting date. The application should be sent through JobsDB by clicking icon \u201cApply Now\u201d or addressed to ALDI HR Department,\u00a018/F, Millennium City 6, 392 Kwun Tong Road, Kwun Tong, Kowloon, Hong Kong.\n\nALDI is an Equal Opportunity employer. We are dedicated to create an equal opportunity throughout recruitment process and staff employment to build a diverse and inclusive workforce. We oppose all forms of unfair or unlawful discrimination in our selection process.\n\nAll personal data collected will be used for recruitment purposes only and be treated in strictest confidence and highest security level in accordance with Hong Kong Data (Privacy) Ordinance as well as ALDI internal Security Policy.\n\nNo part of this job content including but not limited to company information, logo and job description may be reproduced, presented, uploaded, transmitted, modified or distributed \u00a0in any form or by any means without prior permission of ALDI Services Asia Limited / ALDI Sourcing Asia Limited (\u201cthe Company\u201d). The Company reserves the right to take legal action on any unauthorized reproduction, presentation, upload, transmission, modification or distribution. Only applications submitted directly to the Company in response to this advertisement will be considered and any application received by the Company through unauthorized third party agents or via any other channels will not be considered.\n", "employment_types": ["Full Time", "Permanent"], "selling_points": ["Global Sourcing Company", "Tabletop Products", "Experience working in European market is a Must"], "locations": ["Not Specified"], "categories": ["Merchandising & Purchasing", "Sundries", "Others", "Procurement / Purchasing / Sourcing"], "post_time": "2022-01-12T02:39:40Z", "salary": {"currency": null, "max": null, "min": null, "period": "monthly", "term": null}, "salary_visible": false, "title_keywords": ["sourcing manager"], "responsibilities": ["communicate with", "production process", "contracts", "external parties", "procedures", "quality", "develop", "communication", "commercialization", "logistics", "tender", "coordination", "planning"], "requirements": {"degrees": ["degree"], "majors": [], "languages": ["english", "mandarin"], "language_level": ["fluency", "good command"], "hard_skills": ["exchange", "ms office"], "soft_skills": ["planning skills", "work independently", "self-motivated", "responsible", "well-organized", "willing to learn", "integrity", "communication and interpersonal skills", "attention to detail", "coordination", "team player"], "languages_combined": [{"language": "english", "language_level": ["fluency", "good command"]}, {"language": "mandarin", "language_level": ["good command"]}]}, "experience_required": {"duration": ["minimum of 2 years"], "field": ["buying offices", "relevant working experience"]}}, {"job_id": "100003009034484", "location_code": "hk", "company": "The Marketing Store Worldwide (Asia) Ltd", "job_title": "Merchandising Manager", "description": "Role\n\nSourcing Specialist\u00a0\n\nLocation\n\nHong Kong\n\nWho we are\n\nProgram Management\n\nAt ELEVATE, we offer a unique and impactful career journey designed to empower our teams to influence change. Join our team for a truly international experience.\u00a0 With 24+ offices globally (and still growing), you will have exposure to real issues that span the globe. Fasten your seatbelt for an energetic and dynamic experience where you will enable clients to meet the challenge of navigating risk across the value chain.\u00a0 Companies and organizations specifically outsource programs to us in order to leverage our world-class capabilities and reputation for innovation and quality execution, global research and in-depth expertise on the ground in key sourcing markets, and experience in sustainability strategy and shaping community investment initiatives.\n\nJob overview at a glance\n\nThis role supports Sourcing manager for all spend areas in achieving the goal of significant initial cost reductions and regional sourcing and works closely with Sourcing manager in building and vetting supplier list in the region, analyzing\u00a0spend data, and preparing monthly status reports. This role will report to Regional Sourcing Manager in Hong Kong.\n\nWho you are\n\nAre you thrilled by the idea of working in a business that aims tackle the world\u2019s biggest challenges? Do you want to work:\n\non environmental, social and governance issues\nwith an amazing team of like-minded creative thinkers\nin a fast-paced dynamic environment\nfor some of the biggest and most forward-looking brands in the world\n\nResponsibilities\n\nSourcing Activities:\n\nResearch and identify new and potential suppliers\nInspect and evaluate the quality of quotation product according to focused area and internal policy\nPrepare proposals, request quotes, and negotiate purchase terms and conditions\nPerform source planning, conduct market research and develop the supply market\nInvestigate issues with products/suppliers and coordinate for a solution\nPrepare reports and maintain accurate procurement records\nInspect items prior to production to ensure requirements have been met\nSet up lab test and inspection schedule when required\nLiaising with suppliers, sample handling\nDevelop and maintain effective supplier relationships for assigned categories\nMonitor existing supplier performance to define service levels and cope with operation needs\n\nQualifications\n\nUniversity degree, preferably in business, or a related quantitative field\n3+ years of experience in sourcing and supply chain management, preferably in sundry / multicar areas,\nPossess strong skills in Excel or other data management systems\nPossess a passion for finding information on new and innovative trends to relevant industries\nWork independently to prioritize numerous requests simultaneously and manage work schedule with minimum supervision\nCandidate with more experience can be considered as a Senior Sourcing Specialist\nGood communication skills in Mandarin and English both oral and written\nTravel will be required\n\nEqual Opportunity Employer\n\nELEVATE is committed to creating a diverse and inclusive workplace and is proud to be an Equal Opportunity Employer. All qualified applicants will be considered without regard to race, color, religion, gender, gender identity, sexual orientation, national origin, genetics, disability, age, veteran status, or any other status protected by local law. Personal data provided by applicants will be treated as confidential information and will be used exclusively for employment purposes only.\u00a0 Only short-listed candidates will be notified.\u00a0 Applicants who are not invited for an interview may consider their applications filed for future reference.\n\nTo learn more about career opportunities at ELEVATE, please visit our Careers Page here: https://www.elevatelimited.com/careers/\n\nUpdated: Oct 2021", "employment_types": ["Full Time", "Permanent"], "selling_points": ["Supply chain operations", "Experience in toys/premiums/sundries industry", "5-Day work week & Attractive Compensation Package"], "locations": ["Kowloon Bay"], "categories": ["Merchandising & Purchasing", "Textiles", "Toy", "Sundries"], "post_time": "2022-01-10T03:29:26Z", "salary": {"currency": null, "max": null, "min": null, "period": "monthly", "term": null}, "salary_visible": false, "title_keywords": ["merchandising manager"], "responsibilities": [], "requirements": {"degrees": [], "majors": [], "languages": [], "language_level": [], "hard_skills": [], "soft_skills": [], "languages_combined": []}, "experience_required": {"duration": [], "field": []}}, {"job_id": "100003009036152", "location_code": "hk", "company": "Randstad Hong Kong Limited", "job_title": "Senior Merchandiser (Bags, Gift & Premium)", "description": "Role:\n\n(Senior) Consultant, Sustainability Consulting Asia\n\nLocation\n\nHong Kong or Singapore\n\nAbout ELEVATE\n\nWe are looking for a highly motivated and passionate professional to support our growing work helping clients design and implement leading responsible sourcing and strategic sustainability programs. This role will be client-facing and require direct engagement with client Sustainability/ESG, Sourcing and/or Procurement teams.\u00a0\u202f\u00a0\n\nYou\u00a0will work with\u00a0private sector clients, mostly Fortune 500 companies,\u00a0spanning a variety of sectors, including consumer goods, retail, food/agriculture, and electronics. You will\u00a0be\u00a0part of the Asia Pacific consulting team\u00a0and\u00a0will\u00a0work with, and learn from, ELEVATE experts from\u00a0teams\u00a0across the globe.\u00a0\u00a0\n\nWith supply chain sustainability increasingly becoming a focus topic across industries,\u00a0and\u00a0as new\u00a0risks, regulations and expectations\u00a0emerge,\u00a0this is a great opportunity for a sustainability professional to enter a team working with leading brands to directly shape the future of how companies\u00a0can drive impact and positive change throughout their global supply chains.\u00a0\n\nWe are looking for individuals who will\u00a0be motivated by the opportunity to work at the cutting edge of\u00a0corporate sustainability and\u00a0that are\u00a0energized by innovative and challenging environments.\u00a0\n\nJob Description\n\nThe (Senior) Consultant will be instrumental in the delivery of our sustainability consulting plan and in ensuring that we are:\n\nDelivering high quality consulting services as part of a global practice\nSupporting business development across sustainability and supply chain consulting businesses\nContributing to the evolution and scalability of our transformative products\n\nThis is an excellent opportunity for an entrepreneurial individual to join a rapidly growing and successful business that is disrupting traditional approaches to sustainability, social and labor programs and supply chain management.\n\nProjects may\u00a0include:\u00a0Development of responsible sourcing strategies, stakeholder engagement and benchmarking, human rights\u00a0due diligence,\u00a0policy development,\u00a0supporting clients on developing supplier guidelines and new internal processes as well as compiling of country risk assessments or responsible sourcing performance reports.\u00a0\n\nResponsibilities\n\nDeliver consulting engagements through end-to-end project management: Provide full-spectrum leadership and action to ensure the delivery of consulting projects by engaging with clients, project management and delivery in the areas of sustainability consulting and climate management. Deliver presentations and conduct training.\nProvide subject-matter expertise: Ensure consulting projects reflect industry best practice and thought leadership through the application and integration of subject-matter expertise in areas including responsible sourcing, social and labor topics (e.g. worker empowerment, human rights), risk management, and other sustainability topics as relevant/needed\nReporting\u00a0to Associate Director to account for above responsibilities.\nProduct and service development: Contribute to new product and service development across both the sustainability consulting and climate change services, through innovating and enhancing existing products, processes and ways of working to accelerate efficiencies, effectiveness and delivering positive impact projects.\n\nApplicable to Senior Consultants:\n\nBusiness development: Produce consultancy proposals, develop and secure new business opportunities with existing and prospective clients\nGuiding and mentoring team members: Provide guidance to our talented and enthusiastic consultants to build a strong, diverse and high performing team\n\nQualifications\n\nFor this position we consider both Consultant and Senior Consultant level applications based on experience.\n\nThe candidate must have at least 3-5 years (Consultant) or 5-7 years (Senior Consultant) of experience in areas such as responsible sourcing, strategy development, and other social/labor consulting experience and at least basic experience in supply chain/sourcing/manufacturing. The candidate must bring strong English writing and presentation skills, be a great communicator, be passionate about sustainable development and be a self-starter. You need to have a willingness to learn and be challenged. You will have the opportunity to contribute to ELEVATE\u2019s strategic direction as we grow and expand over the next 3-5 years and you will drive the development of ELEVATE various products and services.\n\n3-5 / 5-7+ years professional sustainability / supply chain consulting experience\nExtensive knowledge of the sustainability, supply chain, sourcing environment and trends. Ideally, the candidate brings an understanding of social and labor topics.\nEvidence of successful project delivery to clients (company, government, civil society)\nCommunication, networking and stakeholder engagement skills\nStrong writing skills in English\nStrong mind-set for innovation, product development and responding to market drivers\n\nAdditional requirements for Senior Consultant\n\nBusiness development experience and comfort working toward ambitious growth targets\nEvidence of managing and growing new markets, products and services\nHas and applies emotional intelligence and proven team leadership\n\nCompensation\n\nELEVATE offers a competitive salary and compensation package based on experience and qualifications", "employment_types": ["Full Time", "Permanent"], "selling_points": [], "locations": ["Not Specified"], "categories": ["Merchandising & Purchasing", "Textiles", "Sundries", "Procurement / Purchasing / Sourcing"], "post_time": "2022-01-10T09:29:16Z", "salary": {"currency": null, "max": null, "min": null, "period": "monthly", "term": null}, "salary_visible": false, "title_keywords": ["senior merchandiser"], "responsibilities": ["due diligence", "management", "reporting", "consulting", "performance reports", "guidelines", "business opportunities", "quality", "developing", "presentations", "develop", "communication", "project management", "policy development", "plan", "provide guidance"], "requirements": {"degrees": [], "majors": [], "languages": [], "language_level": [], "hard_skills": [], "soft_skills": ["leadership"], "languages_combined": []}, "experience_required": {"duration": [], "field": ["business development"]}}, {"job_id": "100003009031311", "location_code": "hk", "company": "Redcliff Corporation Limited", "job_title": "Merchandiser / Senior Merchandiser (5 days work/Lai Chi Kwok MTR)", "description": "Role\n\nSourcing Specialist\u00a0\n\nLocation\n\nHong Kong\n\nWho we are\n\nProgram Management\n\nAt ELEVATE, we offer a unique and impactful career journey designed to empower our teams to influence change. Join our team for a truly international experience.\u00a0 With 24+ offices globally (and still growing), you will have exposure to real issues that span the globe. Fasten your seatbelt for an energetic and dynamic experience where you will enable clients to meet the challenge of navigating risk across the value chain.\u00a0 Companies and organizations specifically outsource programs to us in order to leverage our world-class capabilities and reputation for innovation and quality execution, global research and in-depth expertise on the ground in key sourcing markets, and experience in sustainability strategy and shaping community investment initiatives.\n\nJob overview at a glance\n\nThis role supports Sourcing manager for all spend areas in achieving the goal of significant initial cost reductions and regional sourcing and works closely with Sourcing manager in building and vetting supplier list in the region, analyzing\u00a0spend data, and preparing monthly status reports. This role will report to Regional Sourcing Manager in Hong Kong.\n\nWho you are\n\nAre you thrilled by the idea of working in a business that aims tackle the world\u2019s biggest challenges? Do you want to work:\n\non environmental, social and governance issues\nwith an amazing team of like-minded creative thinkers\nin a fast-paced dynamic environment\nfor some of the biggest and most forward-looking brands in the world\n\nResponsibilities\n\nSourcing Activities:\n\nResearch and identify new and potential suppliers\nInspect and evaluate the quality of quotation product according to focused area and internal policy\nPrepare proposals, request quotes, and negotiate purchase terms and conditions\nPerform source planning, conduct market research and develop the supply market\nInvestigate issues with products/suppliers and coordinate for a solution\nPrepare reports and maintain accurate procurement records\nInspect items prior to production to ensure requirements have been met\nSet up lab test and inspection schedule when required\nLiaising with suppliers, sample handling\nDevelop and maintain effective supplier relationships for assigned categories\nMonitor existing supplier performance to define service levels and cope with operation needs\n\nQualifications\n\nUniversity degree, preferably in business, or a related quantitative field\n3+ years of experience in sourcing and supply chain management, preferably in sundry / multicar areas,\nPossess strong skills in Excel or other data management systems\nPossess a passion for finding information on new and innovative trends to relevant industries\nWork independently to prioritize numerous requests simultaneously and manage work schedule with minimum supervision\nCandidate with more experience can be considered as a Senior Sourcing Specialist\nGood communication skills in Mandarin and English both oral and written\nTravel will be required\n\nEqual Opportunity Employer\n\nELEVATE is committed to creating a diverse and inclusive workplace and is proud to be an Equal Opportunity Employer. All qualified applicants will be considered without regard to race, color, religion, gender, gender identity, sexual orientation, national origin, genetics, disability, age, veteran status, or any other status protected by local law. Personal data provided by applicants will be treated as confidential information and will be used exclusively for employment purposes only.\u00a0 Only short-listed candidates will be notified.\u00a0 Applicants who are not invited for an interview may consider their applications filed for future reference.\n\nTo learn more about career opportunities at ELEVATE, please visit our Careers Page here: https://www.elevatelimited.com/careers/\n\nUpdated: Oct 2021", "employment_types": ["Full Time", "Permanent"], "selling_points": [], "locations": ["Lai Chi Kok"], "categories": ["Merchandising & Purchasing", "Furniture", "Sundries", "Others", "Trading"], "post_time": "2022-01-07T09:11:29Z", "salary": {"currency": null, "max": null, "min": null, "period": "monthly", "term": null}, "salary_visible": false, "title_keywords": ["merchandiser", "senior merchandiser"], "responsibilities": [], "requirements": {"degrees": [], "majors": [], "languages": [], "language_level": [], "hard_skills": [], "soft_skills": [], "languages_combined": []}, "experience_required": {"duration": [], "field": []}}, {"job_id": "100003009029371", "location_code": "hk", "company": "A.S. Watson Retail (HK) Limited", "job_title": "Senior Buyer / Buyer, Electrical & Electronics - Personal Care Products", "description": "ELEVATE is seeking an experienced IT Infrastructure and DevOps Lead. This is a vital role in leading ELEVATE\u2019s posture around IT infrastructure / DevOps management. This role will evaluate and establish scalable infrastructure and appropriate controls for ELEVATE\u2019s enterprise applications which will transform the way brands and retailers assess their supply chains and drive improvements.\n\nEssential Duties\n\nManage and oversee multi-region, redundant and performant infrastructure solutions for the breadth of our applications leveraging cloud hosting service providers (e.g. AWS)\nDesign and deliver effective engineering solutions and automated processes to address operational goals centered around hosting, data storage, and application availability.\nPartner with Software Engineering, Quality Assurance (QA), and Technical Operations (TechOps) in an operational capacity to maintain continuous delivery and availability of mission critical systems.\nProfile server, cloud resources, and applications to identify and resolve performance issues.\nInterface directly with Technical Architect and Software Engineering to architect efficient and effective solutions.\nBe responsible for the hardening, resiliency and security of all of our network and infrastructure\nLead and administer the security and usability aspects related to ELEVATE\u2019s Office 365 solution\nHelp with the establishment of enterprise solutions around Active Directory, VPN and centralized management of all client assets (laptops/mobiles) in that context\nBe responsible for the hardening, resiliency and security of all our network and infrastructure\nProactively assess and improve quality of service and implement industry best practices\nBuild and maintain tools for deployment, monitoring and operations\nMonitor and respond to system issue and participate in 24x7 on-call rotation.\nOther duties as assigned\nRequirement and Qualifications\n\nAt least 5 years working experience on IT infrastructure, Information Security such as\u00a0Application\u00a0Security, security architecture and DevOps\nKnowledge of enterprise infrastructure, AD, Group Policy, Office 365, Identity and Access Management, Windows, Linux, VMware, cloud services such as AWS and GCP.\nKnowledge of infrastructure automation through DevOps tools and scripting knowledge\nAble to cover and manage docker/containers, Continuous Integration/Continuous Deployment\nExperience in designing, executing and supporting central IT infrastructure, and Cloud solutions\nStrong understanding of Application Design including web, mobile and backend platforms, DevOps, APIs (JSON/REST/SOAP), Database, Cloud Security, Infra as Code (IaC), TCP/IP, system and network fundamentals.\nExperience with at least one programming language, preferably NodeJS, Bash, Python, Ruby\nExperience with Atlassian suite of tools: JIRA, Confluence, BitBucket\nWorking knowledge of using configuration management systems, such as Chef, Puppet, Salt, DSC, Ansible, Docker, Etckeeper.\nExperience in configuring and administering Amazon Web Services (VPC, EC2, ELB, and RDS, Virtual Networking Topologies, PowerShell/DSC, BASH, PHP, Windows, SQL Server (deployment and monitoring), Linux, RDP, and more)\nExperience implementing and using Continuous Integration and Continuous Delivery concepts and tools such as Github, Jenkins, TeamCity, Octopus, Maven, CodeDeploy or comparable tools.\nUnderstanding of system monitoring and application logging solutions (SumoLogic, New Relic, Nagios, Graphite, Grafana, Logstash, InfluxDB, Solarwinds)\nHolder of professional qualification(s) any of Project Management, Security, Cloud, Linux, MS or Virtualization certifications is advantageous\nGood problem-solving skill for handling system operations issue\nStrong written and oral communication skills including the ability to communicate complex issues to technical and non-technical staff and management.\nGood leadership and communication skills, team player with multi-tasking capabilities and able to meet tight deadline\nHighly motivated team player with excellent analytical, written, verbal communications and presentation skills is required.\u00a0\n\nFor interested candidates, please apply now and send your resume with indication of your latest and expected monthly salary as well as your earliest availability to our Human Resources Department.\n\nInformation provided will be treated in strict confidence and used for employment purpose within the Group only.", "employment_types": ["Full Time", "Permanent"], "selling_points": ["Product Sourcing / Development", "Identify and select vendors", "Market trend analysis"], "locations": ["Shatin Area"], "categories": ["Merchandising & Purchasing", "Electronics", "Home Appliances", "Sundries"], "post_time": "2022-01-07T19:19:55Z", "salary": {"currency": null, "max": null, "min": null, "period": "monthly", "term": null}, "salary_visible": false, "title_keywords": ["personal"], "responsibilities": ["management", "software", "active directory", "data", "other duties", "operations", "infrastructure", "quality", "systems", "design", "monitoring", "monitor", "maintain", "application availability"], "requirements": {"degrees": [], "majors": [], "languages": [], "language_level": [], "hard_skills": ["jenkins", "web", "server", "vmware", "tcp", "problem-solving", "integration", "amazon web services", "office 365", "devops", "ruby", "aws", "ansible", "sql", "python", "linux", "php", "bash", "mobile", "ip", "project management", "deployment", "programming", "powershell", "code"], "soft_skills": ["communication skills", "oral", "problem-solving", "project management", "multi-tasking", "motivated", "presentation skills", "meet tight deadline", "team player", "leadership"], "languages_combined": []}, "experience_required": {"duration": ["at least 5 years"], "field": ["devops", "infrastructure", "sql", "it", "security", "programming"]}}, {"job_id": "100003009022202", "location_code": "hk", "company": "Hillman Ross", "job_title": "Sourcing Manager (Houseware)", "description": "Requirements\n\nDiploma or Certificate graduate\n2-4 years relevant experience in housewares or gift & premium\nPrevious experience in sundries products will also be considered\nPrior exposure in handling USA or EEC customers is highly preferred\nComputer literate in using MS Office such as Word, Excel, Outlook etc\nGood command of spoken & written English, Mandarin is a plus\nImmediate available is a definite advantage\n\nResponsibilities\n\nFollow up quotation, product development and sample arrangement\nWork closely with overseas customers and factory for order details\nResponsible for sourcing materials and updating order status in the system\nCoordinate production schedules to meet quality and delivery requirements\n\nAttractive remuneration package and excellent career prospect will be offered to the successful candidates. For interested parties, please send full resume stating expected and last salary with date of available by clicking \u2018Apply Now\u2019", "employment_types": ["Full Time", "Permanent"], "selling_points": ["European Buying Office", "Houseware Products", "Step up candidate will also be considered"], "locations": ["Not Specified"], "categories": ["Merchandising & Purchasing", "Sundries", "Others", "Procurement / Purchasing / Sourcing"], "post_time": "2022-01-05T05:12:20Z", "salary": {"currency": null, "max": null, "min": null, "period": "monthly", "term": null}, "salary_visible": false, "title_keywords": ["sourcing manager"], "responsibilities": ["coordinate", "schedules", "quotation", "quality"], "requirements": {"degrees": ["certificate", "diploma"], "majors": [], "languages": ["english", "mandarin"], "language_level": ["good command"], "hard_skills": ["excel", "plus", "word", "outlook", "ms office"], "soft_skills": [], "languages_combined": [{"language": "english", "language_level": ["good command"]}, {"language": "mandarin", "language_level": ["good command"]}]}, "experience_required": {"duration": ["2-4 years"], "field": ["relevant experience"]}}, {"job_id": "100003009015142", "location_code": "hk", "company": "ADM Promotions Hong Kong Limited", "job_title": "Merchandiser/Senior Merchandiser - Beauty Accessories/Premium", "description": "Responsibilities:\n\nManage whole processes start from product development, price negotiation, buying trip, ordering and production until the post-delivery\nIndependent handle the sample\u2019s measurement and evaluate the sample\u2019s quality\nEnsure product- and quality-standards\nNegotiate with producers / suppliers\nInformation exchange with headquarter / buyers, suppliers and superior\nSource new suppliers and conduct factory visits\n\nRequirements:\n\nDiploma or above, relevant experience in hardgoods (Seasonal Product, Home Decoration) merchandising is an advantage\nExperience of at least 3-4 years as in sourcing / buying office or trading company\nConversant with MS Office, Outlook, Word, Excel and Internet\nFluent in spoken & written English, Cantonese & Mandarin is a must\nSelf-motivated, ability to work in a team and attention to details\nHardworking, good time management and organizational skills\nAbility to handle pressure and willing for routine work\nWe offer right candidate with competitive salary, 13th month salary, 5-day work per week, flexible working hours, 15 days annual leave, birthday leave, family leave, education sponsorship, MPF voluntary contribution, medical & dental insurance, business travel insurance.\n\nInterested parties please send us your full resume with last/current and expected salary by clicking \u201cApply Now\u201d\n\nPlease visit our website for more information: https://www.migros.com.hk/\n\nAll data collected will be used for recruitment purpose only.", "employment_types": ["Full Time", "Permanent"], "selling_points": [], "locations": ["Hung Hom"], "categories": ["Merchandising & Purchasing", "Sundries", "Procurement / Purchasing / Sourcing"], "post_time": "2022-01-03T05:55:48Z", "salary": {"currency": null, "max": null, "min": null, "period": "monthly", "term": null}, "salary_visible": false, "title_keywords": ["merchandiser", "senior merchandiser"], "responsibilities": ["evaluate", "quality", "price negotiation", "measurement"], "requirements": {"degrees": ["diploma or above"], "majors": [], "languages": ["cantonese", "english", "mandarin"], "language_level": ["fluent"], "hard_skills": ["excel", "outlook", "word", "ms office"], "soft_skills": ["flexible", "organizational skills", "self-motivated", "attention to details", "time management", "hardworking"], "languages_combined": [{"language": "cantonese", "language_level": ["fluent"]}, {"language": "english", "language_level": ["fluent"]}, {"language": "mandarin", "language_level": ["fluent"]}]}, "experience_required": {"duration": ["at least 3-4 years"], "field": ["merchandising", "relevant experience", "trading"]}}, {"job_id": "100003009017868", "location_code": "hk", "company": "ME Job Personnel Limited", "job_title": "Merchandiser & Senior Merchandiser  (Label / Packaging )", "description": "Good experienced in Beauty Accessories/Premium\u00a0\nExperience in order processing from development to production\nExperience in sourcing and product development is a must\nBackground gained from trading or manufacturing\u00a0\nHandle new product development to bulk production\nResponsible for product sourcing, new vendor development, sample arrangement, price negotiation and costing\nWork closely with overseas customers and suppliers for quotation follow up, sample arrangement and order follow up\nRisk mitigation and claim settlement\nEnsure on time delivery in full\nTravelling to China is required\nAssisting and contributing in the company environmental activities", "employment_types": ["Full Time"], "selling_points": [], "locations": ["Kwai Tsing Area"], "categories": ["Merchandising & Purchasing", "Sundries", "Others", "Procurement / Purchasing / Sourcing"], "post_time": "2022-01-04T02:18:57Z", "salary": {"currency": null, "max": null, "min": null, "period": "monthly", "term": null}, "salary_visible": false, "title_keywords": ["merchandiser", "senior merchandiser"], "responsibilities": ["price negotiation", "quotation", "ensure on time delivery", "order processing"], "requirements": {"degrees": [], "majors": [], "languages": [], "language_level": [], "hard_skills": ["vendor", "order processing"], "soft_skills": ["negotiation", "responsible"], "languages_combined": []}, "experience_required": {"duration": [], "field": ["development", "product development", "order processing"]}}, {"job_id": "100003009025285", "location_code": "hk", "company": "Eternity Consultants (HK) Ltd", "job_title": "Asst Merch / Merchandiser / Sr Merch (Party / Stationery / Seasonal / Beauty / Gift / Sundries)", "description": "Three Sizable Non-Garment\u00a0Companies (Two \"USA Buying Office\" & One \"EEC Buying Office\")\u00a0are URGENTLY looking for a suitable candidate for the Merchandising position.\n\nRequirements:\n\nF.5 or above\nAt least 3-5 years experience in\u00a0merchandising which one in\u00a0(Label /Packaging) items\nGood communicate across teams involving multiple partners\nDeliver and succeed in the challenging arena of Hardline\nDetail and a strong sense of pro-activity will also be part of your arsenal\nGood command of written and spoken English and Chinese\nCommunication skills to analyze, projects manage and delivery\n\nSalary : Negotiable\n\nLocation : Kwai Chung\n\nOurclients have offered a comprehensive benefits package to the successful candidate.\n\nInterested parties, please send a detailed resume by clicking \"Apply Now\" or visit our company website find email address (ATTN : Eddy.Tse) Hotline : 27066333.\n\nTo learn more about Me Job Personnel Limited., visit http://www.mejob.com.hk/ .\n\nAll information collected is strictly for recruitment purpose.", "employment_types": ["Full Time", "Permanent"], "selling_points": ["sourcing factory", "orders follow up till production", "good in English and Mandarin"], "locations": ["Not Specified"], "categories": ["Merchandising & Purchasing", "Stationery", "Sundries", "Others"], "post_time": "2022-01-06T04:00:08Z", "salary": {"currency": null, "max": null, "min": null, "period": "monthly", "term": null}, "salary_visible": false, "title_keywords": ["merchandiser"], "responsibilities": ["communication", "teams", "merchandising"], "requirements": {"degrees": [], "majors": [], "languages": ["english", "chinese"], "language_level": ["good command"], "hard_skills": [], "soft_skills": ["communication skills"], "languages_combined": [{"language": "english", "language_level": ["good command"]}, {"language": "chinese", "language_level": ["good command"]}]}, "experience_required": {"duration": ["at least 3-5 years"], "field": ["merchandising"]}}, {"job_id": "100003009015338", "location_code": "hk", "company": "CVH Company Limited", "job_title": "General Clerk", "description": "Our clients are trading company and they are looking for caliber candidates to apply\n\n\nAssistant Merchandiser (Sundries)\nMerchandiser / Senior Merchandiser (Party).\u00a0\u00a0\nMerchandiser / Senior Merchandiser (Seasonal)\nMerchandiser (Stationery)\nMerchandiser / Senior Merchandiser (Beauty)\nMerchandiser (Gift)\n\n\nExperience in Sundries / Party / Stationery / Paper / Seasonal / Beauty / Gift)\nHigher Diploma or above\nOrganized and detail orientated, able to\u00a0follow up and processing the orders from factory to overseas clients\u00a0independently.\nFollow up samples and products from development to shipment.\nSourcing new products.\u00a0\nAble to\u00a0handle and negotiate with suppliers and overseas customers.\nGood written and verbal communication skills in English and Chinese,\u00a0Good PC knowledge is necessary.\u00a0\n\n*Interested parties, please send full resume with current & expected salary & date available in MS WORD FORMAT ONLY to our email merch@HKETERNITY. com\u00a0or fax to 3527 0634*\n\n\u00a0For more jobs, please visit our website:\u00a0www.hketernity.com\n\n\u00a0(Personal data submitted are for recruitment purpose only.)", "employment_types": ["Full Time", "Permanent"], "selling_points": ["General Clerk", "5 Day Work", "Fresh graduate"], "locations": ["Kowloon Bay"], "categories": ["Merchandising & Purchasing", "Sundries"], "post_time": "2022-01-03T06:33:38Z", "salary": {"currency": "HKD", "max": 16999, "min": 11000, "period": "monthly", "term": null}, "salary_visible": true, "title_keywords": ["general clerk"], "responsibilities": ["communication", "stationery"], "requirements": {"degrees": ["higher diploma or above"], "majors": [], "languages": ["english", "chinese"], "language_level": ["good"], "hard_skills": ["pc knowledge", "processing"], "soft_skills": ["communication skills", "organized", "independently", "detail orientated"], "languages_combined": [{"language": "english", "language_level": ["good"]}, {"language": "chinese", "language_level": ["good"]}]}, "experience_required": {"duration": [], "field": ["beauty"]}}, {"job_id": "100003009018557", "location_code": "hk", "company": "Sentinel International Co. Limited", "job_title": "Merchandiser / \u65e5\u8a9e\u8ddf\u55ae (Japanese Toys)", "description": "We are a Trading Company in Kowloon Bay and specialist at Seasonal Decorative items. We are looking for a talent to support the daily operation of the merchandising team.\n\n\u00a0Job Requirements:\n\nHandle and coordinate shipment bookings.\nFiling, data entry and other clerical duties as required\nTo assist in other ad-hoc assignments as required\n\n\u00a0Requirements:\n\nDiploma or above graduate\n0-3 year working experience.\nFresh graduate will also be considered\nProficient in MS Office and Excel; excellent PC knowledge\nStrong in communication & negotiation skills with clients and factories\nIndependent and able to work under pressure\nGood command of English, Mandarin and Chinese\nOur attractive remuneration package includes 5 day-week, 13 months salary.\u00a0Interested parties please email detailed resume with availability, current and expected salary\n\n\nAll personal data collected will be used for recruitment purpose only", "employment_types": ["Full Time"], "selling_points": ["Competitive Salary and Good Career Path", "bonus, medical insurance, banking holiday", "Japanese Speaking request"], "locations": ["Tsuen Wan Area"], "categories": ["Merchandising & Purchasing", "Home Appliances", "Toy", "Sundries"], "post_time": "2022-01-04T03:55:09Z", "salary": {"currency": null, "max": null, "min": null, "period": "monthly", "term": null}, "salary_visible": false, "title_keywords": ["merchandiser"], "responsibilities": ["data entry", "ad-hoc assignments", "merchandising", "daily operation", "coordinate", "communication", "work under pressure"], "requirements": {"degrees": ["fresh graduate", "diploma or above"], "majors": [], "languages": ["english", "chinese", "mandarin"], "language_level": ["good command"], "hard_skills": ["excel", "bookings", "pc knowledge", "ms office"], "soft_skills": ["communication", "negotiation skills", "independent", "work under pressure"], "languages_combined": [{"language": "english", "language_level": ["good command"]}, {"language": "chinese", "language_level": ["good command"]}, {"language": "mandarin", "language_level": ["good command"]}]}, "experience_required": {"duration": ["0-3 year"], "field": []}}, {"job_id": "100003009020790", "location_code": "hk", "company": "Hillman Ross", "job_title": "Sourcing Manager (Tabletop)", "description": "\u00a0Responsibilities\n\nHandle order processing\nAssist in sample handling, order and liaison with Japanese clients as required\nCommunicate and coordinate with vendors, suppliers, Japanese customers, internal parties to ensure the production and shipment are on right track and ship on time.\nExperienced in handling enquiries, orders and projects, to ensure product quality and delivery meeting standards\n\nRequirements\n\nForm 5 / DSE or above\nGood spoken and written Japanese\nGood command of spoken and written English, Cantonese and Mandarin\n1 - 2 years\u2019 solid experience in sundries/toys industry.\nSelf-motivated, with strong sense of commitment and able to work under pressure & overtime\nWell organized, with good interpersonal & communication skill\nTravel to China is required.\n\n* We offer\u00a0competitive package including medical insurance, bank holiday and bonus\u00a0to right candidates. Interested parties please\u00a0apply with full resume and expected salary\u00a0by clicking \u201cAPPLY NOW\u201d or email (hr @ sentinel-toys.com) to us.\n\n* All applications and data collected will be treated in strict confidence and used exclusively for recruitment purposes only .", "employment_types": ["Full Time", "Permanent"], "selling_points": ["Global Sourcing Company", "Tabletop Products", "Experience working in European market is a Must"], "locations": ["Not Specified"], "categories": ["Merchandising & Purchasing", "Sundries", "Others", "Procurement / Purchasing / Sourcing"], "post_time": "2022-01-05T02:01:18Z", "salary": {"currency": null, "max": null, "min": null, "period": "monthly", "term": null}, "salary_visible": false, "title_keywords": ["sourcing manager"], "responsibilities": ["internal parties", "coordinate with", "order processing", "quality"], "requirements": {"degrees": ["form 5", "dse"], "majors": [], "languages": ["cantonese", "japanese", "english", "mandarin"], "language_level": ["good command", "good"], "hard_skills": [], "soft_skills": ["self-motivated", "communication skill", "well organized", "interpersonal", "work under pressure"], "languages_combined": [{"language": "cantonese", "language_level": ["good command"]}, {"language": "japanese", "language_level": ["good"]}, {"language": "english", "language_level": ["good command"]}, {"language": "mandarin", "language_level": ["good command"]}]}, "experience_required": {"duration": ["1 - 2 years"], "field": ["toys"]}}, {"job_id": "100003009017981", "location_code": "hk", "company": "Hamilton Limited", "job_title": "Assistant Procurement Officer (F & B)", "description": "Our client is a European buying office and they are looking for a Sourcing Manager, looking after houseware products including knives, kitchen utensils, cutlery, food storage, general houseware products etc. This role will be an individual contributor, reporting to the Head of Sourcing.\n\nWe are now seeking for Sourcing Manager (Houseware)\n\nRESPONSIBILITIES\n\nWell organization skills of dealing with complex product categories, manage high sku and multi-countries production base.\nWork with head of sourcing, other functional teams and manage the merchandising team for business migration from client's current operation to the company.\nDevelop product and vendor strategies to drive for continue business growth.\nEvaluate the performance of factories and assess the business risk that support clients' business needs.\nSupervise and guide a team of merchandisers and coordinate with cross functional teams to achieve excellent KPI to meet client's expectation.\nStrong and in-depth negotiation skills to drive cost saving and costing margin for clients' continue business growth.\nFull ownership of the whole supply chain from factory sourcing, development till shipment with in-depth technical knowledge, proactive on problem precaution & strong decision maker.\nBudget control and business forecast.\nManage the team to ensure they are up to the company standard\nCollaborate with APAC teams to drive global business\nMotivate the team by sharing knowledge and expertise, ensuring attention to detail and seeking continuous improvements\nDevelop a close relationship with existing suppliers and develop new suppliers through personal connections, trade fairs and sourcing trips\nProduct, payment and business term negotiations with suppliers.\n\nTo succeed in this key role, you will have at least 10 years experience in sourcing\n\nQUALIFICATIONS:\n\nBachelor degree preferred\nSelf-motivated and have strong sense of responsibility.\nPrevious experience in handling household products such as cutlery, kitchen utensils, food storage etc. is a Must\nExcellent people and process management skills\nStrong commercial sense, mature and be able to work independently.\nStrong analytical and interpersonal skills\nIndependent and excellent time management in meeting deadline.\nStrong communication skills and fluent in English, Mandarin and Cantonese\nExperience in handling relevant categories\nPrevious experience working in European market is a Must\nStep up candidate in the capacity of Senior Merchandiser will also be considered\n\nAPPLY FOR THIS JOB\n\nInterested candidate please CLICK apply button to apply online or send your resume in MS word format to Hillman Ross Recruitment Solution Professional\n\nPlease note that only shortlisted candidate will be notified. All information will be treated in strict confidence and solely used for recruitment purposes.", "employment_types": ["Full Time", "Permanent"], "selling_points": ["5 days work/ 12-14 Annual Leave/ Medical Insurance", "Handle purchasing functions (food & non-food)", "Assist in coordination of purchase specification"], "locations": ["Sheung Wan"], "categories": ["Hospitality / F & B", "Food & Beverage", "Merchandising & Purchasing", "Sundries", "Procurement / Purchasing / Sourcing"], "post_time": "2022-01-04T02:38:46Z", "salary": {"currency": null, "max": null, "min": null, "period": "monthly", "term": null}, "salary_visible": false, "title_keywords": ["procurement officer", "assistant"], "responsibilities": ["product categories", "reporting", "cost", "collaborate with", "continuous improvements", "management", "teams", "merchandising", "coordinate with", "develop", "evaluate", "communication", "payment", "support clients", "recruitment", "forecast", "migration", "budget control"], "requirements": {"degrees": ["degree", "bachelor"], "majors": [], "languages": ["cantonese", "english", "mandarin"], "language_level": ["fluent"], "hard_skills": ["vendor", "ms word"], "soft_skills": ["communication skills", "self-motivated", "work independently", "independent", "confidence", "sense of responsibility", "mature", "time management", "negotiation skills", "interpersonal skills", "attention to detail", "organization skills", "proactive"], "languages_combined": [{"language": "cantonese", "language_level": ["fluent"]}, {"language": "english", "language_level": ["fluent"]}, {"language": "mandarin", "language_level": ["fluent"]}]}, "experience_required": {"duration": ["at least 10 years"], "field": ["food"]}}, {"job_id": "100003009016848", "location_code": "hk", "company": "Migros (Hong Kong) Ltd", "job_title": "Assistant Merchandiser - Homecare / Stationery", "description": "Our client is a global sourcing company and they are looking for a Sourcing Manager, looking after tabletop products including ceramic, glassware, plastic drinkware etc. This role will be an individual contributor, reporting to the Director of Sourcing.\n\nWe are now seeking for Sourcing Manager (Tabletop)\n\nRESPONSIBILITIES\n\nWell organization skills of dealing with complex product categories, manage high sku and multi-countries production base.\nWork with head of sourcing, other functional teams and manage the merchandising team for business migration from client's current operation to the company.\nDevelop product and vendor strategies to drive for continue business growth.\nEvaluate the performance of factories and assess the business risk that support clients' business needs.\nSupervise and guide a team of merchandisers and coordinate with cross functional teams to achieve excellent KPI to meet client's expectation.\nStrong and in-depth negotiation skills to drive cost saving and costing margin for clients' continue business growth.\nFull ownership of the whole supply chain from factory sourcing, development till shipment with in-depth technical knowledge, proactive on problem precaution & strong decision maker.\nBudget control and business forecast.\nManage the team to ensure they are up to the company standard\nCollaborate with APAC teams to drive global business\nMotivate the team by sharing knowledge and expertise, ensuring attention to detail and seeking continuous improvements\nDevelop a close relationship with existing suppliers and develop new suppliers through personal connections, trade fairs and sourcing trips\nProduct, payment and business term negotiations with suppliers.\n\nTo succeed in this key role, you will have at least 12 years experience in sourcing with at least 5 years in managerial capacity.\n\nQUALIFICATIONS:\n\nBachelor degree preferred\nSelf-motivated and have strong sense of responsibility.\nSolid product knowledge in ceramic is a MUST\nExcellent people and process management skills\nStrong commercial sense, mature and be able to work independently.\nStrong analytical and interpersonal skills\nIndependent and excellent time management in meeting deadline.\nStrong communication skills and fluent in English, Mandarin and Cantonese\nExperience in handling relevant categories\nPrevious experience working in European market is a Must\n\nAPPLY FOR THIS JOB\n\nInterested candidate please CLICK apply button to apply online or send your resume in MS word format to Hillman Ross Recruitment Solution Professional\n\nPlease note that only shortlisted candidate will be notified. All information will be treated in strict confidence and solely used for recruitment purposes.", "employment_types": ["Full Time", "Permanent"], "selling_points": [], "locations": ["Kowloon Bay"], "categories": ["Merchandising & Purchasing", "Stationery", "Sundries", "Procurement / Purchasing / Sourcing"], "post_time": "2022-01-03T09:57:53Z", "salary": {"currency": null, "max": null, "min": null, "period": "monthly", "term": null}, "salary_visible": false, "title_keywords": ["assistant merchandiser"], "responsibilities": ["product categories", "reporting", "cost", "collaborate with", "continuous improvements", "management", "teams", "merchandising", "coordinate with", "develop", "evaluate", "communication", "payment", "support clients", "recruitment", "forecast", "migration", "budget control"], "requirements": {"degrees": ["degree", "bachelor"], "majors": [], "languages": ["cantonese", "english", "mandarin"], "language_level": ["fluent"], "hard_skills": ["vendor", "ms word"], "soft_skills": ["communication skills", "self-motivated", "work independently", "independent", "confidence", "sense of responsibility", "mature", "time management", "negotiation skills", "interpersonal skills", "attention to detail", "organization skills", "proactive"], "languages_combined": [{"language": "cantonese", "language_level": ["fluent"]}, {"language": "english", "language_level": ["fluent"]}, {"language": "mandarin", "language_level": ["fluent"]}]}, "experience_required": {"duration": ["at least 12 years", "at least 5 years"], "field": ["managerial"]}}, {"job_id": "100003009010871", "location_code": "hk", "company": "ProcureNet Limited", "job_title": "Sourcing Manager / Senior Merchandiser (Immediate start)", "description": "Job Responsibilities:\n\nAssist in Procurement operational functions such as product sourcing and vendor selection of food & non-food items;\nProvide administrative & clerical support to procurement team;\nPrepare documentation of relevant purchasing activities including price comparisons, purchasing order, and market price surveys;\nAssist in the coordination of all product and purchase specifications from business units;\nConduct interviews as required by Procurement Manager with suppliers\u2019 representatives to obtain information, specifications, and quotations and to negotiate to the best advantage of the Group;\nAssist in\u00a0ad hoc projects as assigned.\n\nJob Requirements:\n\nDiploma or above in Purchase and Supply Chain Management or related discipline;\nMin. 1\u00a0year relevant experience in F&B industry;\nProficiency in computer skills;\nSelf-motivated, ability to work under pressure, good team player,\u00a0good communications skills in Chinese & English.\n\nMuch more experienced candidate will be considered for the post of Procurement Officer.\n\nInterested parties please apply with full resume with date of availability and expected salary\u00a0by clicking \"Apply Now\"\n\n(Personal data collected will be kept strictly confidential and to be used for recruitment purposes only.)", "employment_types": ["Full Time", "Permanent"], "selling_points": [], "locations": ["Kwun Tong"], "categories": ["Merchandising & Purchasing", "Sundries", "Others", "Procurement / Purchasing / Sourcing"], "post_time": "2021-12-31T05:16:42Z", "salary": {"currency": null, "max": null, "min": null, "period": "monthly", "term": null}, "salary_visible": false, "title_keywords": ["senior merchandiser", "sourcing manager"], "responsibilities": ["clerical support", "purchase", "specifications", "ad hoc projects", "coordination", "documentation"], "requirements": {"degrees": ["diploma or above"], "majors": [], "languages": ["english", "chinese"], "language_level": ["good"], "hard_skills": ["computer skills"], "soft_skills": ["good team player", "self-motivated", "work under pressure"], "languages_combined": [{"language": "english", "language_level": ["good"]}, {"language": "chinese", "language_level": ["good"]}]}, "experience_required": {"duration": ["1 year"], "field": ["f&b", "relevant experience"]}}, {"job_id": "100003009014478", "location_code": "hk", "company": "", "job_title": "Assistant Merchandiser", "description": "DUTIES AND RESPONSIBILITIES:\n\nProvide customer supports for sales team\nAssit sales in production development\nLiaison with overseas customers for order enquiries, production planning and shipments\nTo ensure customer satisfaction and strengthen customer relationships\nTo coordinate with internal parties and production for timely delivery to customers\nPrepare sales orders to customer using ERP system\n\nRequirements:\n\n1-2 years of relevant working\u00a0experience in sundries industry would be preferred\nWell organized, responsible, energetic and good team player\nConfident with great communication skills\nDetailed minded and able to work independently under pressure\nProficiency in use of MS office software\nGood command of English & Mandarin & Cantonese is a MUST\n\nLocation:\u00a0 Lai Chi Kok\n\nBenefit\n\nBank Holidays\nFive-day Work Week\nDouble Pay\nDiscretionary Performance Bonus\nMedical Coverage\n\nImmediate available will be preferred, candidate with no experience will also be considered. Potential opportunity for promotion further if candidate is interested and competent.\n\nPlease send your resume with expected salary to us\n\nFor company details, please visit http://www.winghingbutton.com\n\nAll information received will be treated strictly confidential and for employment purpose only", "employment_types": ["Full Time", "Permanent"], "selling_points": [], "locations": ["Hung Hom"], "categories": ["Merchandising & Purchasing", "Sundries", "Others", "Procurement / Purchasing / Sourcing"], "post_time": "2022-01-03T03:29:31Z", "salary": {"currency": null, "max": null, "min": null, "period": "monthly", "term": null}, "salary_visible": false, "title_keywords": ["assistant merchandiser"], "responsibilities": ["coordinate with", "prepare sales", "production planning", "sales team", "internal parties"], "requirements": {"degrees": [], "majors": [], "languages": ["cantonese", "english", "mandarin"], "language_level": ["good command"], "hard_skills": ["ms office"], "soft_skills": ["confident", "communication skills", "good team player", "work independently", "under pressure", "responsible", "well organized", "energetic", "detailed"], "languages_combined": [{"language": "cantonese", "language_level": ["good command"]}, {"language": "english", "language_level": ["good command"]}, {"language": "mandarin", "language_level": ["good command"]}]}, "experience_required": {"duration": ["1-2 years"], "field": ["relevant working experience"]}}, {"job_id": "100003009013513", "location_code": "hk", "company": "Job-Hunter Employment Agency", "job_title": "Merchandiser / Senior Merchandiser \u2013 Toy", "description": "A MEDIUM SIZED EXPORT FIRM IN\u00a0HUNG HOM\u00a0REQUIRES:\n\n-\u00a0 F.6\u00a0 or above\u00a0\n- Quotation, Sampling and Orders follow up etc.\n- Handle customers enquire\n- English is required and Mandarin is preferred\n- PC knowledge (Ms office, Email) is required\n- Minimum 2-3 years working experience\n- 5-Day work week\n- Bank Holidays\n\n\u00a0For any enquiries,\u00a0 please \u00a0Call 2303-0343.\u00a0", "employment_types": ["Full Time", "Permanent"], "selling_points": [], "locations": ["Not Specified"], "categories": ["Merchandising & Purchasing", "Toy", "Sundries"], "post_time": "2022-01-03T03:12:08Z", "salary": {"currency": null, "max": null, "min": null, "period": "monthly", "term": null}, "salary_visible": false, "title_keywords": ["merchandiser", "senior merchandiser"], "responsibilities": ["quotation"], "requirements": {"degrees": [], "majors": [], "languages": ["english", "mandarin"], "language_level": [], "hard_skills": ["pc knowledge", "ms office"], "soft_skills": [], "languages_combined": [{"language": "english", "language_level": []}, {"language": "mandarin", "language_level": []}]}, "experience_required": {"duration": ["minimum 2-3 years"], "field": []}}, {"job_id": "100003009017775", "location_code": "hk", "company": "KAS Pty Limited", "job_title": "Production Merchandiser - (Hardgoods)", "description": "About Our Client\n\nA reputable trading and manufacturing company providing a wide selection of toys for worldwide customers.\n\nRequirements\n\nCertificate holder or above\n4 years or above experience in hard toys merchandising\nExperience in order processing with overseas clients and factories\nSelf-motivated, energetic, adaptable with good interpersonal skills\nWell-versed in MS Office including Word, Excel and Outlook\nGood communication of both English and Mandarin\nImmediate available would be an advantage\n\nResponsibilities\n\nHandle order processing from development to bulk production\nHandle daily communications with overseas clients and factories\nResponsible for price & terms negotiation and costing calculation\nCoordinate production schedules with factory for delivery arrangement\n\nInterested parties, please apply with full resume stating date of available, expected and last salary to charmaine@job-hunter.com.hk\nAll personal information will be treated strictly confidential and solely for recruitment purpose.", "employment_types": ["Full Time", "Permanent"], "selling_points": [], "locations": ["Cheung Sha Wan"], "categories": ["Merchandising & Purchasing", "Toy", "Sundries", "Others"], "post_time": "2022-01-04T01:58:01Z", "salary": {"currency": null, "max": null, "min": null, "period": "monthly", "term": null}, "salary_visible": false, "title_keywords": ["merchandiser"], "responsibilities": ["communications with", "terms negotiation", "schedules", "coordinate", "order processing"], "requirements": {"degrees": ["certificate"], "majors": [], "languages": ["english", "mandarin"], "language_level": ["good"], "hard_skills": ["excel", "word", "outlook", "order processing", "ms office"], "soft_skills": ["self-motivated", "adaptable", "communication", "interpersonal skills", "energetic"], "languages_combined": [{"language": "english", "language_level": ["good"]}, {"language": "mandarin", "language_level": ["good"]}]}, "experience_required": {"duration": ["4 years"], "field": ["toys", "merchandising", "order processing"]}}, {"job_id": "100003009013802", "location_code": "hk", "company": "ConnectedGroup Limited", "job_title": "Merchandiser/Senior Merchandiser - Hardline", "description": "Categories:\u00a0Xmas Trim & Wrap, Season Food, Confectionery\n\n\u00a0Responsibilities:\n\nTo provide a quality customer service to the buyer\nTo maintain relationship with supplier\nFollow up order and on time shipment of product\nMonitoring process at different stages of the critical path\nTesting of products to meet QA requirement\nFollow up the QA approval process including product function and safety\nCritical Path Management by DSS system\nMaintain a proper filing system to ensure visibility in all areas and allow other team members be able to handle current work immediately in your absence\nAd. hoc project as assigned by Management\n\nRequirements:\n\n4-5 years solid merchandising experience in\u00a0Hardgoods categories, preferably in buying office environment\nStrong negotiation and interpersonal skill to liaison\u00a0between buyers and\u00a0factories\nTertiary education or equivalent\nProven experience to be able to work with overseas buyers independently\nDemonstrate the ability to work under pressure\nExcellent communication skills both in English and Mandarin\nExcellent computer knowledge\nTravel is required\n\nAll information provided will be treated in strict confidence and used solely for recruitment purpose.", "employment_types": ["Full Time", "Permanent"], "selling_points": ["Well-established sourcing office", "Attractive Remuneration Package", "Responsible for handling hardgoods items"], "locations": ["Not Specified"], "categories": ["Merchandising & Purchasing", "Sundries", "Others", "Procurement / Purchasing / Sourcing"], "post_time": "2022-01-03T02:43:52Z", "salary": {"currency": null, "max": null, "min": null, "period": "monthly", "term": null}, "salary_visible": false, "title_keywords": ["merchandiser", "senior merchandiser"], "responsibilities": ["maintain", "monitoring", "customer service", "quality"], "requirements": {"degrees": [], "majors": [], "languages": ["english", "mandarin"], "language_level": ["excellent"], "hard_skills": [], "soft_skills": ["communication skills", "independently", "confidence", "negotiation", "interpersonal skill", "work under pressure"], "languages_combined": [{"language": "english", "language_level": ["excellent"]}, {"language": "mandarin", "language_level": ["excellent"]}]}, "experience_required": {"duration": ["4-5 years"], "field": ["merchandising"]}}, {"job_id": "100003009008554", "location_code": "hk", "company": "BuyHive Limited", "job_title": "Freelance Merchandiser", "description": "Due to business expansion, we now invite talented and enthusiastic talents to join our growing team. This is an excellent opportunity for proactive and skilled individuals to join our rapidly expanding and friendly team.\u00a0\n\nResponsibilities\n\nLiaise with new and current suppliers to for updated pricings on assigned products\nResearch and source for new suppliers\nRegular update and maintenance of database\u00a0\nPrice negotiation, arrange samples etc.\u00a0\nWork with Sales and Logistics teams to ensure the smooth daily operation\nOther ad hoc tasks/ projects as assigned\u00a0\n\nRequirements\n\nDiploma or above with some\u00a0experience in sourcing/ purchasing/ trading/ export\nKnowledge of medical products such as masks, PPEs, syringes, etc. definite advantage but not a must\nIndependent, hard working, flexible and with westernized mindset\nExcellent communications and negotiation skills\nGood English & Mandarin required\u00a0\nCandidates with less experienced will be considered as Senior Officer / Officer\nImmediately available preferred\n\nWe offer attractive remuneration package and comprehensive benefits to the right candidate.\u00a0Interested parties, please click Apply Now with your updated resume with current and expected salary.\u00a0\n\nDue to the volume of applicants, only shortlisted candidates will be contacted.\u00a0All information provided by applicants will be treated in strict confidentiality and used for recruitment purpose only.\u00a0 We will retain your application for a maximum period of 6 months and may refer it to other vacancies within the Group.", "employment_types": ["Freelance"], "selling_points": ["HKD$1,500 per project", "Work with overseas buyers", "Responsible for creating sourcing reports"], "locations": ["Others"], "categories": ["Merchandising & Purchasing", "Home Appliances", "Sundries", "Others"], "post_time": "2021-12-30T08:18:43Z", "salary": {"currency": null, "max": null, "min": null, "period": "hourly", "term": null}, "salary_visible": false, "title_keywords": ["merchandiser"], "responsibilities": ["price negotiation", "maintenance", "teams", "daily operation", "ad hoc tasks", "logistics", "database", "liaise with"], "requirements": {"degrees": ["diploma or above"], "majors": [], "languages": ["english", "mandarin"], "language_level": ["good"], "hard_skills": [], "soft_skills": ["flexible", "hard working", "independent", "negotiation skills"], "languages_combined": [{"language": "english", "language_level": ["good"]}, {"language": "mandarin", "language_level": ["good"]}]}, "experience_required": {"duration": [], "field": ["purchasing", "trading"]}}, {"job_id": "100003009017309", "location_code": "hk", "company": "Eternity Consultants (HK) Ltd", "job_title": "Merchandiser / Senior Merchandiser - Outdoor Furniture - Europe market", "description": "Our Client is a well-established sourcing office, they are looking for a Merchandiser/Senior merchandiser to join their expanding team.\n\nKey Job Responsibilities include:\n\n\n\nResponsible for the whole merchandising process and ensure products meet customers' requirements\nResponsible for order follow up, sampling, product development, price negotiations, quality control and shipments, etc.\nWork closely with internal parties to ensure production schedules are aligned with company strategy.\nWork closely with quality team and ensure products meet QA requirements\nMaintain & update product record to prepare related documents\nMaintain strong business relationships with supplier for product development and production\n\n\nOther requirements include:\n\nTertiary education with a minimum of 3 years' experience in merchandising, experienced in hardgoods items\nExperienced in product and project development, follow up and negotiation\nGood communication skills, self-motivated, proactive and open-minded\nExcellent in English, Cantonese and Mandarin, both spoken and written\nTravel if necessary", "employment_types": ["Full Time", "Permanent"], "selling_points": ["F.5 or above / DSE graduate.", "4 years in merchandising in camping", "Outdoor furniture, outdoor items"], "locations": ["Not Specified"], "categories": ["Merchandising & Purchasing", "Furniture", "Sundries", "Procurement / Purchasing / Sourcing"], "post_time": "2022-01-03T12:56:39Z", "salary": {"currency": null, "max": null, "min": null, "period": "monthly", "term": null}, "salary_visible": false, "title_keywords": ["merchandiser", "senior merchandiser"], "responsibilities": ["schedules", "related documents", "merchandising", "quality", "maintain", "quality control", "internal parties"], "requirements": {"degrees": [], "majors": [], "languages": ["cantonese", "english", "mandarin"], "language_level": ["excellent"], "hard_skills": [], "soft_skills": ["communication skills", "self-motivated", "negotiation", "open-minded", "proactive"], "languages_combined": [{"language": "cantonese", "language_level": ["excellent"]}, {"language": "english", "language_level": ["excellent"]}, {"language": "mandarin", "language_level": ["excellent"]}]}, "experience_required": {"duration": ["minimum of 3 years"], "field": ["merchandising", "education"]}}, {"job_id": "100003009011202", "location_code": "hk", "company": "Cathay Pacific Catering Services (H.K.) Limited", "job_title": "Assistant Procurement Manager", "description": "Job Position:\u00a0Freelance Sourcing Expert (Flexible Hours/Part-Time) based in HK\n\nAs a BuyHive freelance sourcing expert, you will use your own supplier network to find quality suppliers to recommend to overseas buyers, based upon the buyer\u2019s product and supplier requirements. You will work on a project basis, each project will take 3-5 days to complete, and you can work at night or on weekends -- whenever you\u2019re available!\n\nCompensation:\u00a0HK$1,500 per project\n\nJob Description:\n\nDuties\n\nUnderstand product & supplier requirements of overseas buyers\nContact suppliers in your network, or find & contact new suppliers online, or meet suppliers at sourcing trade shows in your area\nGather required supplier & product information and input into BuyHive\u2019s online system\nSubmit required information before the agreed project deadline\nCommunicate with BuyHive management, participate in training and assist with scheduling, as required\n\nJob Requirements\n\nMust have minimum of 5 years of merchandising experience\nExperience sourcing products in one or more of the following categories:\nProactive approach to work, self-motivated, and excellent team player\nStrong communication and organizational skills\nAbility to meet deadlines and work under pressure\nExperience attending sourcing trade shows in your area\nLanguages: Advanced proficiency in written English and spoken Mandarin Chinese required; intermediate proficiency in spoken English helpful.\n\nArts & Crafts, School & Office\n\nBaby\n\nBeauty & Personal Care\n\nGarden & Outdoor\n\nHealth & Medical\n\nHome Improvement, Tools & Lighting\n\nPackaging\n\nPet Supplies\n\nPPE\n\nSports & Fitness\n\nTravel, Bags & Luggage\n\nCompany Description\n\nBuyHive Ltd. is a Hong Kong-based technology company that is building a network of freelance sourcing experts to help buyers worldwide find and qualify suppliers. Since 2019 we have been helping global retailers, importers, and promotional companies source quality finished products across all consumer product categories. You can learn more about us at: www.thebuyhive.com", "employment_types": ["Full Time", "Permanent"], "selling_points": ["Source, assess and select products/suppliers", "Investigate issues with products/suppliers", "Maintain and upkeep purchasing database & records"], "locations": ["Airport Area"], "categories": ["Merchandising & Purchasing", "Sundries", "Others", "Procurement / Purchasing / Sourcing"], "post_time": "2021-12-31T06:41:19Z", "salary": {"currency": null, "max": null, "min": null, "period": "monthly", "term": null}, "salary_visible": false, "title_keywords": ["manager", "assistant"], "responsibilities": ["communicate with", "management", "scheduling", "contact", "contact suppliers"], "requirements": {"degrees": [], "majors": [], "languages": ["mandarin chinese", "english"], "language_level": ["proficiency", "intermediate"], "hard_skills": [], "soft_skills": ["organizational skills", "self-motivated", "advanced", "communication", "team player", "proactive", "meet deadlines", "work under pressure"], "languages_combined": [{"language": "mandarin chinese", "language_level": ["proficiency"]}, {"language": "english", "language_level": ["proficiency", "proficiency", "intermediate"]}]}, "experience_required": {"duration": ["minimum of 5 years"], "field": ["merchandising"]}}, {"job_id": "100003009008434", "location_code": "hk", "company": "Skyline (Far East) Co., Limited", "job_title": "Merchandiser (Seasonal, Home Decorations & Gifts)", "description": "Responsibilities:\n\nLiaise with overseas customers in order confirmation and handle their daily enquiries.\nCommunicate with China factories and internal parties\nEnsure accurate and on-time production orders, order status reports and delivery time schedule, etc\nCoordinate samples development and delivery on time and prepare for customer presentation\nFollow up the whole merchandising process from product development until production\nPrepare product related documents and reports\nHandle ad hoc assignments as required.\n\nRequirements:\n\nHigh diploma or above in any discipline;\nMinimum 3 years relevant experience in merchandising\u00a0\nWith experience in Camping, Outdoor furniture\nStrong interpersonal and time management skill\nWell-organized, self-motivated, flexible and able to work independently\nGood PC skill (MS Word, Excel, PowerPoint & Chinese WP is essential)\nOccasionally travel to Mainland China is required\nImmediate available is highly preferred.\n\nMany positions are not been posted in media.\u00a0 If you are looking for job in merchandising field, we are welcome you send your resume to us direct.\n\n*Interested parties, please Email full resume with current & expected salary & date available in MS WORD FORMAT ONLY to us\u00a0or fax to 3527 0634*\n\nFor more jobs, please visit our website:\u00a0www.hketernity.com", "employment_types": ["Full Time", "Permanent"], "selling_points": [], "locations": ["Hung Hom"], "categories": ["Merchandising & Purchasing", "Sundries", "Procurement / Purchasing / Sourcing", "Sales, CS & Business Devpt", "Account Servicing"], "post_time": "2021-12-30T08:02:21Z", "salary": {"currency": null, "max": null, "min": null, "period": "monthly", "term": null}, "salary_visible": false, "title_keywords": ["merchandiser"], "responsibilities": ["communicate with", "related documents", "merchandising", "coordinate", "reports", "schedule", "ad hoc assignments", "liaise with", "internal parties"], "requirements": {"degrees": ["high diploma or above"], "majors": [], "languages": ["chinese"], "language_level": ["good"], "hard_skills": ["excel", "chinese wp", "powerpoint", "pc skill", "ms word"], "soft_skills": ["flexible", "self-motivated", "work independently", "well-organized", "time management skill", "interpersonal"], "languages_combined": [{"language": "chinese", "language_level": ["good"]}]}, "experience_required": {"duration": ["minimum 3 years"], "field": ["merchandising", "relevant experience"]}}, {"job_id": "100003009002399", "location_code": "hk", "company": "MUJI (Hong Kong) Company Limited", "job_title": "Assistant Category Manager / Senior Category Planner - Household", "description": "Responsibilities\n\nPlays a leading role within the department and resolves day to day supply problems\nMaintains an effective and efficient supplier base\nSupervise a team and achieve targets set by the Company regarding the cost and quality performance of the assigned categories, as well as the relevant suppliers\nSource, assess and select products/suppliers and negotiate with suppliers for best deals\nMaintain and upkeep the purchasing database and records\nPerform source planning, conduct market research and develop the supply market\nMeasure and analyze the performance of assigned categories\nInvestigate issues with products/suppliers and coordinate for a solution\nWork directly with external customers on menu planning, offer commercially desirable options, sort out procurement issues and lead cross-departmental projects\nIdentify work improvement opportunities and follow through with suitable projects\nRequirements\n\nDiploma / Degree in Purchasing & Supply or related subject\n5 years or above experience in purchasing, including 3 years in supervisory level\nExcellence in problem-solving, analytical skills and numerical ability; Able to lead and coach subordinates\nStrong price negotiation and cost control skills\nGood interpersonal and communication skills\nGood command in both written and spoken English and Chinese. Good in Putonghua would be an advantage\nCandidate with less experience will be considered as Procurement Officer\n\nWe offer a competitive remuneration package and a full range of benefits. Interested parties please send your resume with your current and expected salary to Head of People,11 Catering Road East, Hong Kong International Airport, Lantau, Hong Kong or by clicking the \"Apply Now\" button on or before 30 January 2022.\n\nPersonal data collected will be treated in the strictest confidence and only be used for recruitment-related purposes. Applicants who do not receive notification for an interview within six weeks may consider their application unsuccessful.", "employment_types": ["Full Time", "Permanent"], "selling_points": ["Plan sales & merchandising strategy in household", "Work w/ suppliers in order & delivery arrangement", "Any degree holder, with min. of 6 yrs relevant exp"], "locations": ["Tsim Sha Tsui"], "categories": ["Merchandising & Purchasing", "Furniture", "Sundries", "Procurement / Purchasing / Sourcing"], "post_time": "2021-12-28T05:03:43Z", "salary": {"currency": null, "max": null, "min": null, "period": "monthly", "term": null}, "salary_visible": false, "title_keywords": ["assistant category manager"], "responsibilities": ["achieve targets", "cost", "conduct market research", "quality", "develop", "coordinate", "maintain", "database", "planning"], "requirements": {"degrees": ["diploma", "degree"], "majors": [], "languages": ["putonghua", "english", "chinese"], "language_level": ["advantage", "good command", "good"], "hard_skills": ["problem-solving", "analytical skills"], "soft_skills": ["communication skills", "negotiation", "problem-solving", "analytical skills", "interpersonal"], "languages_combined": [{"language": "putonghua", "language_level": ["good", "advantage"]}, {"language": "english", "language_level": ["good command"]}, {"language": "chinese", "language_level": ["good command"]}]}, "experience_required": {"duration": ["5 years", "3 years"], "field": ["purchasing", "supervisory level", "procurement"]}}, {"job_id": "100003009005786", "location_code": "hk", "company": "West Kowloon Cultural District Authority", "job_title": "Senior Manager, Museum Retail Merchandising (Ref: R2971)", "description": "Job Highlights\n\n\nA Trading company in Kwun Tong\n5 days work\nDouble pay\nLunch offered\nBirthday Leave\n\nJob Description\nResponsibilities\n\n\n-\u00a0\u00a0Follow up seasonal decoration, home decoration and toys products,\n-\u00a0 Prepare quotations, samples\u00a0and orders\u00a0follow up\n-\u00a0 Product development\n-\u00a0 Assist in daily operational activities and provide supports to the merchandising\u00a0team members\n-\u00a0 Routine communication with factories and customers\n-\u00a0 Product sourcing in China or Far East countries\u00a0\n\nRequirements\n\n-\u00a0 Diploma or above\n-\u00a0 Minimum 1\u00a0year related working experience\n-\u00a0 Good in English and Mandarin\n-\u00a0 Proficiency in Illustrator\u00a0or\u00a0Photoshop\u00a0will be an advantage\n-\u00a0 Able to handle multi-tasks and cope with deadlines\n-\u00a0 Strong sense of responsibility, good communication skills and team work\u00a0\n\nInterested parties, please send full resume with current and expected salary via clicking \u2018Apply Now\u2019 for an interview.\n", "employment_types": ["Full Time"], "selling_points": ["Retail merchandising & buying experience sought", "Lifestyle retailers background sought", "Demonstrate strong business acumen sense"], "locations": ["Tsim Sha Tsui"], "categories": ["Manufacturing", "Product Development / Management", "Merchandising & Purchasing", "Stationery", "Sundries"], "post_time": "2021-12-29T04:41:19Z", "salary": {"currency": null, "max": null, "min": null, "period": null, "term": null}, "salary_visible": false, "title_keywords": ["senior manager", "merchandising"], "responsibilities": ["routine communication", "merchandising"], "requirements": {"degrees": ["diploma or above"], "majors": [], "languages": ["english", "mandarin"], "language_level": ["good"], "hard_skills": ["illustrator", "photoshop"], "soft_skills": ["communication skills", "multi-tasks", "sense of responsibility"], "languages_combined": [{"language": "english", "language_level": ["good"]}, {"language": "mandarin", "language_level": ["good"]}]}, "experience_required": {"duration": ["minimum 1 year"], "field": ["related"]}}, {"job_id": "100003009006771", "location_code": "hk", "company": "", "job_title": "Procurement Officer/Manager", "description": "We are a rapid-growing healthcare group based in Hong Kong. We are now looking for an energetic person to join us in this dynamic role.\n\nJob Description\n\nHandle Purchase Requisition and Sales Order administration system\nCoordinate potential suppliers, including negotiation, discussing materials, products and quality standards\nParticipate in negotiations with vendors, including researching prices, products and other data beforehand and coordinating with suppliers to create optimal purchasing contracts\nMaintain computerized database of supply purchase orders, paid invoices, goods delivered, product and raw material quality, current inventory and future order scheduling\nSales & purchase order administratin follow up and handling\nMaintain effective relationship with strategic vendors and customers\n\nJob Requirements\n\nBachelor\u2019s degree or high school diploma in supply management is preferred\nAt least 2 years of working experience in purchasing and/or sales administration/merchandising\nExperience in healthcare industry will be an advantage\nStrong price negotiation and cost control skills\nGood interpersonal and communication skills\nExcellent command in spoken and written English and Chinese (Mandarin and Cantonese)\nMore experience will be considered as Procurement Manager\nImmediately availability is preferred\n(Personal data will be used for recruitment purpose only.\u00a0\u00a0All information received will remain confidential and will be destroyed after 6 months.)\n\nInterested candidates, please contact us at 34279018 for company details before applying.", "employment_types": ["Full Time", "Permanent"], "selling_points": [], "locations": ["Central"], "categories": ["Merchandising & Purchasing", "Sundries", "Procurement / Purchasing / Sourcing", "Sales, CS & Business Devpt", "Sales Administration"], "post_time": "2021-12-29T10:25:27Z", "salary": {"currency": null, "max": null, "min": null, "period": "monthly", "term": null}, "salary_visible": false, "title_keywords": ["procurement officer", "manager"], "responsibilities": ["invoices", "data", "contracts", "inventory", "quality", "coordinate", "scheduling", "purchase", "maintain", "database", "administration"], "requirements": {"degrees": ["high school diploma", "degree", "bachelor"], "majors": [], "languages": ["cantonese", "english", "chinese", "mandarin"], "language_level": ["excellent"], "hard_skills": [], "soft_skills": ["communication skills", "interpersonal", "negotiation"], "languages_combined": [{"language": "cantonese", "language_level": ["excellent"]}, {"language": "english", "language_level": ["excellent"]}, {"language": "chinese", "language_level": ["excellent"]}, {"language": "mandarin", "language_level": ["excellent"]}]}, "experience_required": {"duration": ["at least 2 years"], "field": ["sales administration", "purchasing", "merchandising", "healthcare industry", "procurement"]}}, {"job_id": "100003009009784", "location_code": "hk", "company": "A.S. Watson Retail (HK) Limited", "job_title": "(Senior) Product Development Officer (Watsons Own Brand Personal Care Products)", "description": "\u00a0Come and join a Winning Team\n\n\u00a0We are Awesome !\n\nWhy Should You Join Us?\u00a0\n\nAt ASW, we believe in our people, in teamwork and the importance of your personal growth.\u00a0If you are looking for the opportunity to join our award-winning international family with 16,200+ stores across 28 markets in Asia and Europe, the ASW family welcomes you\u2026\u00a0! \u00a0#BePartofMORE\n\nYou can enjoy:\u00a0 \u00a0\n\nComprehensive Medical and Life insurance coverage, including your spouse and children!\nProfessional training and career advancement opportunities!\nAttractive ACCA and CPA Australia Recognized Employer Program for F&A talents!\nExclusive company pension schemes!\u00a0 Marriage, Maternity and Paternity Leave!\nConvenient office location, less than 5 min. walk from MTR!\nContemporary workplace with Onsite Clinic, Lactation Rooms, free drinks and chill out areas!\nWell-equipped Gym inside our office building, plus fitness and interest class packages!\nFree round-trip lunchtime shuttle bus services to Shatin!\nExclusive shopping discount, Bazaar Sales for our people only!\n\nRole Purpose:\u00a0\n\n\nResponsible for the development of Own Brand product, working in close cooperation with different internal and external parties to drive profitable participation of Own Brands\u00a0mainly in Personal Category in Asia and Eastern Europe.\u00a0\n\nA typical day in this Role:\u00a0\u00a0\n\nTo assist the line manager, in co-operation with Watsons International Own Brand Marketing team and BU Own Brand specialists, to identify a continuous stream of commercially valuable new products.\nTo manage all projects for categories directly responsible for across all key aspects of the development process, from supplier liaison, cost management to post launch.\nTo understand customers\u2019 need and identify product development opportunities of the assigned categories.\nTo collaborate with both internal and external stakeholders to execute of the brand and plans.\nTo provide support of the ad-hoc product development projects and key meeting forums\n\nThis job is a good fit for You if:\u00a0\u00a0\n\nYou have keen interest in product development.\nYou are fond of beauty/skincare/personal care products.\nYou love to connect with people across different departments.\nYou\u00a0have sense of urgency and have good time management.\n\n\u00a0What we look for:\u00a0\u00a0\n\nDegree holder in any discipline.\nMinimum 3 years in FMCG / Beauty (mainly personal care) experience - Ideally Health & Beauty / Retail experience.\nGood Project Management Skills \u2013 capable of timely delivery of several projects.\u00a0\nGood Team player capable of taking on board other perspectives.\nKnowledge of OEM product development, with strong analytical skills.\nSelf motivated with an ability to manage day to day issues independently.\nProficient in both spoken and written English and Chinese.\nTo be a highly organised individual, with great attention to detail and the ability to work pro-actively and flexibly.\n\n\u00a0\u00a0\u00a0What is holding you back?\n\n\u00a0Don\u2019t miss out on this great chance to shape Your life!\n\n\u00a0\u00a0Apply now!\u00a0\n\nInterested parties, please send your resume with current and expected salary package to our Company\u2019s email.\u00a0\u00a0\n\nWe are an equal opportunity employer and welcome applications from all qualified candidates. The information provided will be treated in strict confidence and be used only for consideration of your application for relevant/ similar posts within the A.S. Watson Group.", "employment_types": ["Full Time", "Permanent"], "selling_points": ["Asia and Eastern Europe exposure", "Min. 3 years in Beauty/Skincare products", "Watsons own brand products development"], "locations": ["Shatin Area"], "categories": ["Manufacturing", "Product Development / Management", "Merchandising & Purchasing", "Sundries", "Procurement / Purchasing / Sourcing"], "post_time": "2021-12-31T02:09:18Z", "salary": {"currency": null, "max": null, "min": null, "period": null, "term": null}, "salary_visible": false, "title_keywords": ["officer", "product development", "personal"], "responsibilities": ["collaborate with", "ad-hoc", "cost", "management", "provide support", "internal and external parties", "project management", "plans", "insurance"], "requirements": {"degrees": ["degree holder"], "majors": [], "languages": ["english", "chinese"], "language_level": ["proficient"], "hard_skills": ["acca", "plus", "analytical skills", "chill", "cpa", "project management"], "soft_skills": ["good team player", "independently", "capable", "responsible", "urgency", "keen", "project management skills", "teamwork", "timely", "analytical skills", "self motivated", "comprehensive", "attention to detail", "organised", "time management"], "languages_combined": [{"language": "english", "language_level": ["proficient"]}, {"language": "chinese", "language_level": ["proficient"]}]}, "experience_required": {"duration": ["minimum 3 years"], "field": ["personal care", "fmcg", "beauty", "retail"]}}, {"job_id": "100003001742743", "location_code": "hk", "company": "Simple Symbol Ltd", "job_title": "Merchandiser", "description": "Job description:\n\n\n\nResponsibilities:\n\nResponsible of developing businesses with Sundries/ Bags/ Accessories / Festival Decoration/ Gift & Premium/ Home Products/ Seasonal Items/\u00a0Plastic / Stationery etc..\nPursue and receive all product specifications from customers and contact with factories to follow up all necessary processes including technical issues\u00a0\nMonitor factory performance in order to ensure product development and production are on right track\nProduction planning, monitoring the factory capacity and production status contact closely with QC / QA related to quality issue from all development samples to bulk productions and to ensure the goods should be correctly, completely, meeting quality standard and delivery on time as requested from customers\nParticipate in ad-hoc projects as assigned\n\nRequirements:\n\nDegree or equivalent\nFrequently travel to China factory is needed\nAt least 10 years\u2019 solid practice in merchandising field in\u00a0SUNDRIES & BAGS\nExpertise of sourcing and production processes is essential, with\u00a0working practice in factory is preferred\nHard working, well organized, proactive team and result-oriented, flexible and be capable to follow up client's requirements independently and effectively\nAttentive to details and problem solving mindset is prerequisite\nSound PC expertise \u2013 Word Processing, Excel and Power Point\n\nFluency in both written and oral English, Cantonese and Mandarin\nMature, responsible, self-motivated and able to work under pressure\n\n\n\nWe offer competitive remuneration package including 5-day work and other benefits to the right candidate", "employment_types": ["Full Time"], "selling_points": [], "locations": ["Hung Hom"], "categories": ["Merchandising & Purchasing", "Stationery", "Sundries"], "post_time": "2021-12-29T01:38:19Z", "salary": {"currency": null, "max": null, "min": null, "period": "monthly", "term": null}, "salary_visible": false, "title_keywords": ["merchandiser"], "responsibilities": ["monitoring", "monitor", "stationery", "developing", "production planning", "quality", "specifications", "contact", "ad-hoc projects"], "requirements": {"degrees": ["degree"], "majors": [], "languages": ["cantonese", "english", "mandarin"], "language_level": ["fluency"], "hard_skills": ["excel", "word processing", "problem solving", "power point", "pc"], "soft_skills": ["flexible", "oral", "independently", "self-motivated", "capable", "attentive to details", "responsible", "hard working", "well organized", "mature", "problem solving", "proactive", "result-oriented", "work under pressure"], "languages_combined": [{"language": "cantonese", "language_level": ["fluency"]}, {"language": "english", "language_level": ["fluency"]}, {"language": "mandarin", "language_level": ["fluency"]}]}, "experience_required": {"duration": [], "field": []}}, {"job_id": "100003009001047", "location_code": "hk", "company": "Twelve NYC Asia Limited", "job_title": "Senior Merchandiser - Sundries", "description": "Responsibilities\n\nPlan for sales & merchandising strategies with ordering made to achieve sales and GP objectives\nWork with operations and other departments to execute the plan in an effective manner at all levels\nNegotiate with supplier in regards to ordering & delivery arrangements to have the appropriate stock for the sales plan\nPlan for seasonal buying and OTB amount to maximize sales and GP\nMonitor inventory to ensure appropriate levels for stocks have been maintained with proper remedial act to be execute in case of any problem encountered;\nAssist in other ad hoc project as assigned\n\nRequirements\n\nDegree holder in\u00a0all disciplines\nMinimum 6 years of solid buying & merchandising planning experience of lifestyle products in retail chain environment\nWork experience in retail operation will be an advantage\nSelf-motivated, positive and able to work under pressure\nA fast learner, acute market sense with strong analytical mind and product sense\nExcellent communication and organization skills\nGood command of written and spoken Chinese and English, with knowledge of written and spoken Japanese is an asset\nProficient in MS Office, especially in MS Excel\nWilling to work overtime\nCandidates with less experience will be considered as\u00a0Senior Category Planner\n\nA competitive package and promising career prospect will be offered to the right candidate. Interested parties please send detailed resume with expected salary and availability by clicking \"Apply Now\" to submit your application.\u00a0\n\n\nThe personal data collected will be treated in strict confidence and used for recruitment-related purpose only. Applicants who are not invited for interview within\u00a04 weeks may consider their applications unsuccessful.\u00a0 All personal data of unsuccessful candidates will be destroyed after 6 months.\n\nMUJI (Hong Kong) Company Limited\u00a0is an equal opportunities employer.", "employment_types": ["Full Time"], "selling_points": [], "locations": ["Kwun Tong"], "categories": ["Merchandising & Purchasing", "Sundries"], "post_time": "2021-12-28T01:18:37Z", "salary": {"currency": null, "max": null, "min": null, "period": "monthly", "term": null}, "salary_visible": false, "title_keywords": ["senior merchandiser"], "responsibilities": ["ad hoc", "operations", "inventory", "monitor", "merchandising", "otb", "plan"], "requirements": {"degrees": ["degree holder"], "majors": [], "languages": ["japanese", "english", "chinese"], "language_level": ["good command"], "hard_skills": ["planner", "ms excel", "ms office"], "soft_skills": ["self-motivated", "work overtime", "communication", "analytical mind", "organization skills", "fast learner", "positive", "work under pressure"], "languages_combined": [{"language": "japanese", "language_level": ["good command"]}, {"language": "english", "language_level": ["good command"]}, {"language": "chinese", "language_level": ["good command"]}]}, "experience_required": {"duration": ["minimum 6 years"], "field": ["operation", "retail", "merchandising", "planning"]}}, {"job_id": "100003009007101", "location_code": "hk", "company": "Hillman Ross", "job_title": "Sourcing Manager (Home dcor)", "description": "Reporting to the Head, Museum Retail and Commerce, the role of Senior Manager, Museum Retail Merchandising is key to ensuring the delivery of a truly unique M+ cultural retail experience.\u00a0 Through the creation, purchase and visual merchandising of extraordinary product offerings, the incumbent will deliver an on-brand message to all visitor type to ensure revenue maximization.\n\nYou will be responsible for :\n\nworking closely with the Head, Museum Retail & Commerce, develop and implement the museum\u2019s product development, procurement and retail sales strategy for all retail outlets including online platforms;\nrepresenting the retail merchandising function across the museum, understanding museum programmes and activities and identifying retail sales opportunities;\u00a0\nmanaging overall retail budget, ensuring the allocation, spending and income are within the approved scope and for the best interest of M+;\ndeveloping and maintaining the requisite structures, systems and procedures in order to facilitate the implementation of the agreed strategies;\nleading the team to manage the retail and buying activities, product development, supply chain, ecommerce and business development for the museum, aiming to drive the profitability through agreed strategies;\ndriving the product development process, efficiently procuring and launching new products to align with the collections and activities of the museum;\nensuring that core ranges of merchandise are procured efficiently, maximising sale and profitability and ensuring that they are aligned with the collections and activities of the museum;\nworking with the retail sales manager to ensure the highest level of visual merchandising and window displays are achieved;\ndeveloping sales and promotional programmes that maximizes sales opportunities with exhibitions, museum activities and customer seasonality while maximizing margins and minimizing mark downs to ensure inventory levels are always kept at acceptable levels;\ndeveloping workshop, product launches and other community engagement opportunities as they arise with merchandising strategy;\nmanaging supplier relationships to ensure high service levels and optimum terms and conditions; and\nworking closely with other departments to ensure smooth operations of the team.\nYou should :\npossess a recognised university degree in any disciplines;\nhave at least 10 years of experience with multi-national lifestyle retailers which 5 years at managerial position;\ndemonstrate strong project management skill, business acumen and numerical sense to drive large volume of retail and merchandising function;\npossess strong leadership capability and attributes which aim to deliver the best business result and team management;\npossess strong negotiation, influencing and collaboration skills, able to work with a number of stakeholders to drive result and achieve the targets; and\nhave good communication skills, be proficient in both written and oral English and Chinese.\nFor interested parties, please submit your application with detailed CV on or before 12 January 2022. Applicants are encouraged to submit their applications as soon as possible. The review of applications will continue until post is filled.\n\nData collected will only be used for job application processing. Your data may be accessed by our appointed recruitment consultants who have agreed to keep confidence of all personal data in not less than the standards applicable to us.\n\nApplicants not being invited for interview within 4 weeks from the submission date may assume their applications unsuccessful.\n\nAll related information will be kept up to 24 months and all personal data will be destroyed afterwards.\n\nFor more information\nhttp://www.westkowloon.hk or contact\nMs. Linda Hung at 2200 5481", "employment_types": ["Full Time", "Permanent"], "selling_points": ["UK buying office", "Step up candidate will also be considered", "Lead a team of 2 staff"], "locations": ["Not Specified"], "categories": ["Merchandising & Purchasing", "Sundries", "Others", "Procurement / Purchasing / Sourcing"], "post_time": "2021-12-30T01:31:11Z", "salary": {"currency": null, "max": null, "min": null, "period": "monthly", "term": null}, "salary_visible": false, "title_keywords": ["sourcing manager"], "responsibilities": ["reporting", "management", "maintaining", "inventory", "budget", "merchandising", "developing", "systems", "develop", "procedures", "implementation", "purchase", "workshop", "project management", "ensure smooth operations", "communication", "visual"], "requirements": {"degrees": ["university degree"], "majors": ["any disciplines"], "languages": ["english", "chinese"], "language_level": ["proficient", "good"], "hard_skills": ["project management", "visual merchandising", "acumen"], "soft_skills": ["communication skills", "oral", "negotiation", "responsible", "unique", "smooth", "project management skill", "business acumen", "leadership"], "languages_combined": [{"language": "english", "language_level": ["proficient", "good"]}, {"language": "chinese", "language_level": ["proficient", "good"]}]}, "experience_required": {"duration": ["at least 10 years", "5 years"], "field": ["managerial", "retail", "merchandising"]}}, {"job_id": "100003009006344", "location_code": "hk", "company": "JPC Texson Limited", "job_title": "SALES & MARKETING COORDINATOR / EXECUTIVE (20K-28K) - French fashion accessories trading / mfg", "description": "Our client is a UK buying office and they are looking for a Sourcing Manager, looking after home d\u00e9cor. This role will lead a team of 2 staff, reporting to the Head of Sourcing.\n\nWe are now seeking for Sourcing Manager (Home d\u00e9cor)\n\nRESPONSIBILITIES\n\nWell organization skills of dealing with complex product categories, manage high sku and multi-countries production base.\nWork with head of sourcing, other functional teams and manage the merchandising team for business migration from client's current operation to the company.\nDevelop product and vendor strategies to drive for continue business growth.\nEvaluate the performance of factories and assess the business risk that support clients' business needs.\nSupervise and guide a team of merchandisers and coordinate with cross functional teams to achieve excellent KPI to meet client's expectation.\nStrong and in-depth negotiation skills to drive cost saving and costing margin for clients' continue business growth.\nFull ownership of the whole supply chain from factory sourcing, development till shipment with in-depth technical knowledge, proactive on problem precaution & strong decision maker.\nBudget control and business forecast.\nManage the team to ensure they are up to the company standard\nCollaborate with APAC teams to drive global business\nMotivate the team by sharing knowledge and expertise, ensuring attention to detail and seeking continuous improvements\nDevelop a close relationship with existing suppliers and develop new suppliers through personal connections, trade fairs and sourcing trips\nProduct, payment and business term negotiations with suppliers.\n\nTo succeed in this key role, you will have at least 10 years experience in sourcing\n\nQUALIFICATIONS:\n\nBachelor degree preferred\nSelf-motivated and have strong sense of responsibility.\nPrevious experience in handling home d\u00e9cor OR seasonal is a Must\nExcellent people and process management skills\nStrong commercial sense, mature and be able to work independently.\nStrong analytical and interpersonal skills\nIndependent and excellent time management in meeting deadline.\nStrong communication skills and fluent in English, Mandarin and Cantonese\nExperience in handling relevant categories\nPrevious experience working in European market is a Must\nStep up candidate in the capacity of Senior Merchandiser will also be considered\n\nAPPLY FOR THIS JOB\n\nInterested candidate please CLICK apply button to apply online or send your resume in MS word format to Hillman Ross Recruitment Solution Professional\n\nInterested candidate please CLICK apply button to apply online or send your resume in MS word format to Hillman Ross Recruitment Solution Professional", "employment_types": ["Full Time", "Permanent"], "selling_points": ["Over 3 yr exp in US / EU mkt of consumer goods", "Prf optical/fashion accessories/watch/jewelry exp", "Perform orders & clients follow & coordination"], "locations": ["Hung Hom"], "categories": ["Marketing / Public Relations", "Marketing - Brand / Product Management", "Merchandising & Purchasing", "Sundries", "Sales, CS & Business Devpt", "Account Servicing"], "post_time": "2021-12-29T08:15:24Z", "salary": {"currency": null, "max": null, "min": null, "period": "monthly", "term": null}, "salary_visible": false, "title_keywords": ["marketing coordinator", "executive", "sales"], "responsibilities": ["collaborate with", "merchandising", "communication", "payment", "support clients", "budget control", "product categories", "teams", "develop", "forecast", "migration", "continuous improvements", "reporting", "cost", "management", "coordinate with", "evaluate", "lead a team", "recruitment"], "requirements": {"degrees": ["degree", "bachelor"], "majors": [], "languages": ["cantonese", "english", "mandarin"], "language_level": ["fluent"], "hard_skills": ["vendor", "ms word"], "soft_skills": ["communication skills", "self-motivated", "work independently", "independent", "sense of responsibility", "mature", "time management", "negotiation skills", "interpersonal skills", "attention to detail", "organization skills", "proactive"], "languages_combined": [{"language": "cantonese", "language_level": ["fluent"]}, {"language": "english", "language_level": ["fluent"]}, {"language": "mandarin", "language_level": ["fluent"]}]}, "experience_required": {"duration": ["at least 10 years"], "field": []}}, {"job_id": "100003009005270", "location_code": "hk", "company": "Hillman Ross", "job_title": "Sourcing Manager (Household)", "description": "\n\nTHE COMPANY :\n\n\nFrench owned company\nManufacturer : optical frame and fashion accessories\n\nHong Kong office : trading office\n\nFactories : Dongguan, Vietnam and Cambodia\nOverseas sales offices : France, Italy and USA\nMain market : Europe & US for fashion brands, optical brands and designer brands\nWe are looking for\u00a0\u00a0 SALES & MARKETING COORDINATOR \u2013 with details as follows :\u00a0\u00a0\n\u00a0\nTHE JOB :\n\n\nOver 3 years work experience in consumer goods to EU / US market\nExperience in eyewear / optical frames / fashion accessories / watch / fashion jewellery / lifestyle products is a big plus\n\nExperience in merchandising / order processing / client servicing / sales / marketing or equivalent\n\nProficient in English & Chinese; Mandarin is a plus\n\nExperience in Europe or US markets or brands is highly prefer\n\nManufacturers experience will be a plus\nReport to the Senior Marketing Manager\nProvide professional service to assigned overseas clients or brands from US or Europe\nPerform product development and orders follow up until shipment completed\n\nHandle customers enquiries\nIssue and follow up quotations\nProject development, prototype and delivery follow up\nCoordinate with factories and overseas customers\n5 days work\nWork life balance\n\nFriendly work environment\n\nMore solid experience will be considered as Sales & Marketing Executive (2 posts)\n\n\u00a0\n\u00a0\nTO APPLY for this job or similar jobs :\n\nFor secure and confidential job application, please click the below link to get our email address.\n\u00a0\nhttp://jpc.hk/confidential_apply.htm\n\nWe provide free job hunting services to job seekers.\n\u00a0\nTo speed up our process, please do NOT send us download links.\n\u00a0\nPersonal data provided by job applicants will be used for recruitment purpose only.\n\u00a0\nYour privacy is guaranteed. We will never give out, lease, or sell your personal information.\n\u00a0\nJPC Recruiting Services was established in 1990.\n\u00a0\nhttp://www.facebook.com/pages/JPC-Texson-Ltd/500356593325952\n\n", "employment_types": ["Full Time", "Permanent"], "selling_points": ["European Buying Office", "Houseware Products", "Step up candidate will also be considered"], "locations": ["Not Specified"], "categories": ["Merchandising & Purchasing", "Sundries", "Others", "Procurement / Purchasing / Sourcing"], "post_time": "2021-12-29T03:41:03Z", "salary": {"currency": null, "max": null, "min": null, "period": "monthly", "term": null}, "salary_visible": false, "title_keywords": ["sourcing manager"], "responsibilities": ["coordinate with", "merchandising", "order processing", "report"], "requirements": {"degrees": [], "majors": [], "languages": ["english", "french", "chinese", "mandarin"], "language_level": ["proficient"], "hard_skills": ["plus", "order processing"], "soft_skills": ["friendly"], "languages_combined": [{"language": "english", "language_level": ["proficient"]}, {"language": "french", "language_level": []}, {"language": "chinese", "language_level": ["proficient"]}, {"language": "mandarin", "language_level": []}]}, "experience_required": {"duration": ["3 years"], "field": ["marketing", "merchandising", "order processing"]}}, {"job_id": "100003009000949", "location_code": "hk", "company": "Creative China Creations Limited", "job_title": "Production & Quality Engineer (Consumer Products & Sundries)", "description": "Our client is a European buying office and they are looking for a Sourcing Manager, looking after houseware products. This role will be an individual contributor, reporting to the Head of Sourcing.\n\nWe are now seeking for Sourcing Manager (Household)\n\nRESPONSIBILITIES\n\nWell organization skills of dealing with complex product categories, manage high sku and multi-countries production base.\nWork with head of sourcing, other functional teams and manage the merchandising team for business migration from client's current operation to the company.\nDevelop product and vendor strategies to drive for continue business growth.\nEvaluate the performance of factories and assess the business risk that support clients' business needs.\nSupervise and guide a team of merchandisers and coordinate with cross functional teams to achieve excellent KPI to meet client's expectation.\nStrong and in-depth negotiation skills to drive cost saving and costing margin for clients' continue business growth.\nFull ownership of the whole supply chain from factory sourcing, development till shipment with in-depth technical knowledge, proactive on problem precaution & strong decision maker.\nBudget control and business forecast.\nManage the team to ensure they are up to the company standard\nCollaborate with APAC teams to drive global business\nMotivate the team by sharing knowledge and expertise, ensuring attention to detail and seeking continuous improvements\nDevelop a close relationship with existing suppliers and develop new suppliers through personal connections, trade fairs and sourcing trips\nProduct, payment and business term negotiations with suppliers.\n\nTo succeed in this key role, you will have at least 10 years experience in sourcing\n\nQUALIFICATIONS:\n\nBachelor degree preferred\nSelf-motivated and have strong sense of responsibility.\nPrevious experience in handling household products such as cutlery, kitchen utensils, food storage etc. is a Must\nExcellent people and process management skills\nStrong commercial sense, mature and be able to work independently.\nStrong analytical and interpersonal skills\nIndependent and excellent time management in meeting deadline.\nStrong communication skills and fluent in English, Mandarin and Cantonese\nExperience in handling relevant categories\nPrevious experience working in European market is a Must\nStep up candidate in the capacity of Senior Merchandiser will also be considered\n\nAPPLY FOR THIS JOB\n\nInterested candidate please CLICK apply button to apply online or send your resume in MS word format to Hillman Ross Recruitment Solution Professional\n\nPlease note that only shortlisted candidate will be notified. All information will be treated in strict confidence and solely used for recruitment purposes.", "employment_types": ["Full Time", "Permanent"], "selling_points": ["Good understanding on global markets", "Able to work independently & meet tight deadlines", "Preferable 5 years of work experience"], "locations": ["Ngau Tau Kok"], "categories": ["Manufacturing", "Product Development / Management", "Merchandising & Purchasing", "Sundries", "Procurement / Purchasing / Sourcing"], "post_time": "2021-12-27T16:03:42Z", "salary": {"currency": null, "max": null, "min": null, "period": "monthly", "term": null}, "salary_visible": false, "title_keywords": ["engineer"], "responsibilities": ["product categories", "reporting", "cost", "collaborate with", "continuous improvements", "management", "teams", "merchandising", "coordinate with", "develop", "evaluate", "communication", "payment", "support clients", "recruitment", "forecast", "migration", "budget control"], "requirements": {"degrees": ["degree", "bachelor"], "majors": [], "languages": ["cantonese", "english", "mandarin"], "language_level": ["fluent"], "hard_skills": ["vendor", "ms word"], "soft_skills": ["communication skills", "self-motivated", "work independently", "independent", "confidence", "sense of responsibility", "mature", "time management", "negotiation skills", "interpersonal skills", "attention to detail", "organization skills", "proactive"], "languages_combined": [{"language": "cantonese", "language_level": ["fluent"]}, {"language": "english", "language_level": ["fluent"]}, {"language": "mandarin", "language_level": ["fluent"]}]}, "experience_required": {"duration": ["at least 10 years"], "field": ["food"]}}, {"job_id": "100003009004810", "location_code": "hk", "company": "ProCrown Fine Trading Company", "job_title": "Merchandiser \u2013 Household & Sundries Products", "description": "Job Requirements:\n\nDevelop and implement the Creative China Creations Limited (CCCL) Vendor Quality Management System across the supplier network in China as well as CCCL own facility in Mainland China in conjunction with the product development team at Hong Kong head office.\nFacilitate correspondence on internal Quality Control checks between Hong Kong office (Product Development Team) & CCCL factory in Mainland China as well as 3rd party suppliers\nCommunicate with Hong Kong team members on technical specifications & requirements through the product development process to ensure quality standards for both product functionality, safety and compliance are met.\nEstablish protocols with supplier production teams to develop high-volume and quick- turnaround manufacturing processes and capabilities for new product implementation (NPI)\nConduct quality audits (IQC, IPQC & OQC) for pre- and mass-production at suppliers.\nIntroduce protocols for final goods inspection with supplier QC team and third-party inspectors, and SOPs for in-time reporting and rapid corrective/preventive action plan (CAPA).\nSuggest quality control enhancements for both infrastructure & ERP systems as well as specific consumer products.\nUtilize inspection metrics and quality improvement/control tools (e.g., DOE & FMEA) to drive continuous quality improvement with suppliers.\nLiaise & coordinate 3rd party inspections with various companies such as SGS, Intertek, BV, etc and help establish inspection mandates & protocols to follow.\nMonitor market sale and return data and provide warning alerts to head office for quality risk management.\nLead company initiative to support overseas suppliers to attain C-TPAT validation (Customs \u2013 Trade Partnership against Terrorism - USA) as well as meet other audit or client specific audit standards such as ISO, ETL, UL, CE, BSCI, ICTI standards.\nEXCELLENT COMMAND IN WRITTEN & SPOKEN ENGLISH, CANTONESE & MANDARIN SKILLS\nAble to Travel to China for implementation and monitoring of Quality Control systems.\nCandidates with at least 5 years\u2019 experience is preferred but not a requirement.\nThe ability to work independent or part of a larger team, with the mentality & work ethic of a leader.\nFamiliarity with Quality control systems for consumer products is preferred.\nA team leader who exhibits leadership qualities and is able to work under pressure and within time constraints.\nPermanent Hong Kong ID card Holder.\nFlexible working times and willing to work after hours if needed.\n\n\u00a0Key requirements:\n\nDegree/Diploma holder, with at least 5 years of relevant experience\nGood understanding on US/UK/EU Markets\nExcellent command in Cantonese, English and Mandarin\nGood communication and interpersonal skills to work with counterparts\nAble to work independently and meet tight deadlines\nProficient in computer skills and MS Office Applications\nUnderstand electronic circuitry in component level.\nHands on experience in operating test equipment such as voltmeter, ammeter and oscilloscope\nCoordinate weekly customer complaint meeting.\n\nInterested applicants please send your English application along with cover letter and detailed resume with current and expected salary clearly stated to \u201cApply Now\u201d.\n\nAll Personal data collected will be used for recruitment purpose only.\n", "employment_types": ["Full Time", "Permanent"], "selling_points": [], "locations": ["Not Specified"], "categories": ["Merchandising & Purchasing", "Toy", "Sundries", "Others"], "post_time": "2021-12-29T04:01:15Z", "salary": {"currency": null, "max": null, "min": null, "period": "monthly", "term": null}, "salary_visible": false, "title_keywords": ["merchandiser"], "responsibilities": ["liaise", "data", "quality", "audit", "communication", "plan", "personal data", "work under pressure", "control", "compliance", "teams", "implementation", "infrastructure", "develop", "monitor", "reporting", "management", "monitoring", "inspection", "specifications", "sops", "audits", "communicate with", "systems", "coordinate", "recruitment", "quality control"], "requirements": {"degrees": ["diploma holder", "degree"], "majors": [], "languages": ["cantonese", "english", "mandarin"], "language_level": ["excellent"], "hard_skills": ["erp systems", "id", "vendor", "c", "computer skills", "rapid", "ms office"], "soft_skills": ["flexible", "work independently", "meet tight deadlines", "independent", "detailed", "communication and interpersonal skills", "hands on", "work ethic", "creative", "leadership", "initiative", "work under pressure"], "languages_combined": [{"language": "cantonese", "language_level": ["excellent", "excellent"]}, {"language": "english", "language_level": ["excellent", "excellent"]}, {"language": "mandarin", "language_level": ["excellent", "excellent"]}]}, "experience_required": {"duration": ["at least 5 years"], "field": ["relevant experience"]}}, {"job_id": "100003009007121", "location_code": "hk", "company": "Eternity Consultants (HK) Ltd", "job_title": "Merchandiser / Senior Merchandiser -Toy / Kitchenware / ceramic  / furniture", "description": "Job Requirements\n\nDiploma holder or above\n3 years relevant experience in sundries or household products\nPrevious experience in order follow up, preferably for USA/EEC market\nWell-versed in using MS Office including Word, Excel and Outlook\nAdaptable, detail-minded, energetic with proactive attitude\nGood command of English and fair in spoken Mandarin\nImmediate available will be a great advantage\n\nJob Responsibilities\n\nHandle order coordination and quotation follow up with overseas clients\nAssist in merchandising duties from product development to bulk production\nHandle sample arrangement, sourcing and production follow up with factory\nProvide support on merchandising coordination and ad hoc duties\n\nWe offer excellent fringe benefits and attractive development prospect to the right candidates. Interested parties, please apply with full resume stating expected & last salary and date of available by clicking \u2018Apply Now\u2019", "employment_types": ["Full Time", "Permanent"], "selling_points": ["merchandising in Toys / Gift, Ceramic", "Kitchenware, furniture , sourcing new vendors", "5 days, double pay, bonus, medical"], "locations": ["Not Specified"], "categories": ["Merchandising & Purchasing", "Furniture", "Sundries", "Procurement / Purchasing / Sourcing"], "post_time": "2021-12-30T01:37:02Z", "salary": {"currency": null, "max": null, "min": null, "period": "monthly", "term": null}, "salary_visible": false, "title_keywords": ["merchandiser", "senior merchandiser"], "responsibilities": ["ad hoc duties", "provide support", "quotation", "merchandising", "coordination"], "requirements": {"degrees": ["diploma holder"], "majors": [], "languages": ["english", "mandarin"], "language_level": ["good command"], "hard_skills": ["excel", "outlook", "word", "ms office"], "soft_skills": ["adaptable", "detail-minded", "energetic", "proactive"], "languages_combined": [{"language": "english", "language_level": ["good command"]}, {"language": "mandarin", "language_level": ["good command"]}]}, "experience_required": {"duration": ["3 years"], "field": ["relevant experience"]}}, {"job_id": "100003009004134", "location_code": "hk", "company": "TRI-Come Recruitment Search", "job_title": "Senior Merchandiser/ Merchandiser (Gift & Premium/ Toys/ Beauty items / Sundries )", "description": "- Degree holder\n\n- Minimum 3 years experience in manufacturing firm\n\n- Follow up overseas orders\n\n- Product development coordination\n\n- Fluency in spoken and written Chinese and English\n\n- Good at MS office and Chinese WP\n\nPersonal data collected is for recruitment purpose only.", "employment_types": ["Full Time", "Permanent"], "selling_points": [], "locations": ["Yau Tsim Mong Area"], "categories": ["Merchandising & Purchasing", "Home Appliances", "Toy", "Sundries"], "post_time": "2021-12-29T01:22:17Z", "salary": {"currency": null, "max": null, "min": null, "period": "monthly", "term": null}, "salary_visible": false, "title_keywords": ["merchandiser", "senior merchandiser"], "responsibilities": ["personal data", "recruitment", "coordination"], "requirements": {"degrees": ["degree holder"], "majors": [], "languages": ["english", "chinese"], "language_level": ["fluency", "good"], "hard_skills": ["chinese wp", "ms office"], "soft_skills": ["coordination"], "languages_combined": [{"language": "english", "language_level": ["fluency"]}, {"language": "chinese", "language_level": ["fluency", "good"]}]}, "experience_required": {"duration": ["minimum 3 years"], "field": ["manufacturing"]}}, {"job_id": "100003008989460", "location_code": "hk", "company": "ProcureNet Limited", "job_title": "Sourcing / Purchasing Specialist (Immediate Start)", "description": "\u00a0\u00a0\u00a0 \u00a0 \u00a0 \u00a0 Responsibilities :\n\nStrong communication and negotiation skill to work with both suppliers and buyers\nWork with vendors and material suppliers to source and develop appropriate materials and components.\nCommunicate with appropriate clients, product development team members, supply chain, factory product development staff, raw material vendors and manufacturers to ensure products are developed in keeping with brief specs and goals.\nSupport the Technical and Merchandising team on development issues.\n\n\u00a0 \u00a0 \u00a0 \u00a0\u00a0 Requirements :\n\nAt least 3 to 5 years of related work experience in the\u00a0Gift & Premium/ Toys/ Beauty items/ Sundries\nStrong verbal and written communication skills with an advanced ability to communicate new ideas, concepts and functional expertise within product teams\nGood communication & negotiation skill\nFluency in both written and spoken Cantonese, English and Mandarin.\n\n\u00a0 \u00a0 \u00a0 \u00a0 \u00a0 \u00a0 \u00a0 \u00a0Interested parties please send your resume :\u00a0 \u00a0hr @ tri-come.com.hk\n", "employment_types": ["Full Time", "Permanent"], "selling_points": ["Immediate start", "Good English & Mandarin required", "Fresh graduations will be considered"], "locations": ["Kwun Tong"], "categories": ["Merchandising & Purchasing", "Sundries", "Others", "Procurement / Purchasing / Sourcing"], "post_time": "2021-12-21T03:48:38Z", "salary": {"currency": null, "max": null, "min": null, "period": "monthly", "term": null}, "salary_visible": false, "title_keywords": ["specialist"], "responsibilities": ["communication", "merchandising", "communicate with", "develop"], "requirements": {"degrees": [], "majors": [], "languages": ["cantonese", "english", "mandarin"], "language_level": ["fluency"], "hard_skills": [], "soft_skills": ["communication", "communication skills", "advanced", "negotiation skill"], "languages_combined": [{"language": "cantonese", "language_level": ["fluency"]}, {"language": "english", "language_level": ["fluency"]}, {"language": "mandarin", "language_level": ["fluency"]}]}, "experience_required": {"duration": ["at least 3 to 5 years"], "field": ["related", "beauty", "toys"]}}, {"job_id": "100003009005693", "location_code": "hk", "company": "Gemini Personnel Limited", "job_title": "Sales Coordinator /  Secretary -  (20K, double pay, 14 days Annual Leave, 5-day, TST)", "description": "Due to business expansion, we now invite talented and enthusiastic talents to join our growing team. This is an excellent opportunity for proactive and skilled individuals to join our rapidly expanding and friendly team.\u00a0\n\nResponsibilities\n\nLiaise with new and current suppliers to for updated pricings on assigned products\nResearch and source for new suppliers\nRegular update and maintenance of database\u00a0\nPrice negotiation, arrange samples etc.\u00a0\nWork with Sales and Logistics teams to ensure the smooth daily operation\nOther ad hoc tasks/ projects as assigned\u00a0\n\nRequirements\n\nDiploma or above with some\u00a0experience in sourcing/ purchasing/ trading/ export\nKnowledge of medical products such as masks, PPEs, syringes, etc. definite advantage but not a must\nIndependent, hard working, flexible and with westernized mindset\nExcellent communications and negotiation skills\nGood English & Mandarin required\u00a0\nCandidates with more experienced will be considered as Senior Officer\nImmediately available preferred\n\nWe offer attractive remuneration package and comprehensive benefits to the right candidate.\u00a0Interested parties, please click Apply Now with your updated resume with current and expected salary.\u00a0\n\nDue to the volume of applicants, only shortlisted candidates will be contacted.\u00a0All information provided by applicants will be treated in strict confidentiality and used for recruitment purpose only.\u00a0 We will retain your application for a maximum period of 6 months and may refer it to other vacancies within the Group.", "employment_types": ["Full Time", "Permanent"], "selling_points": ["Sales Coordination, Secretarial experience", "Good language & PC skills", "20 K, 5-day, Double Pay, 14 A/L, TST"], "locations": ["Tsim Sha Tsui"], "categories": ["Admin & HR", "Secretary", "Merchandising & Purchasing", "Sundries", "Procurement / Purchasing / Sourcing"], "post_time": "2021-12-29T04:16:21Z", "salary": {"currency": "HKD", "max": 19999, "min": 17000, "period": "monthly", "term": null}, "salary_visible": true, "title_keywords": ["sales coordinator", "secretary"], "responsibilities": ["price negotiation", "maintenance", "teams", "daily operation", "ad hoc tasks", "logistics", "database", "liaise with"], "requirements": {"degrees": ["diploma or above"], "majors": [], "languages": ["english", "mandarin"], "language_level": ["good"], "hard_skills": [], "soft_skills": ["flexible", "hard working", "independent", "negotiation skills"], "languages_combined": [{"language": "english", "language_level": ["good"]}, {"language": "mandarin", "language_level": ["good"]}]}, "experience_required": {"duration": [], "field": ["purchasing", "trading"]}}, {"job_id": "100003008998137", "location_code": "hk", "company": "CASA Collective Limited", "job_title": "Merchandiser (Hardgoods)", "description": "Responsibilities:\n\nBusiness development\n\nResponsible for category sourcing activity, including searching new product and new supplier, quality and price comparison, sample comparison, price negotiation, factory evaluation etc.\nResponsible for project execution with milestone control and good time management\nGuiding and monitoring the order follow up, including working with OTS system to accept order, delivery time control;\nDocument management: Projects document filing and checking.\n\nCustomer and supplier management\n\nCommunicate with Germany headquarter to clarify inquiries and specifications;\nSupply chain management including supplier search, screen and identify potential supplier. Monitor suppliers\u2019 performance\nArrange and implement buying trip independently, including contact with supplier or vendor to arrange schedule, coordinate with supplier and buyer, accompany buying trip, prepare trip report etc.\nSupplier negotiation: price review and control, claim settlement etc.\n\nRequirements:\n\nDiploma or above with 5 years above independent product sourcing working experience in trading company or buying office\nExperience in handling lighting products and European market is preferred\nStrong negotiation, presentation and problem solving skill\nGood time management and project management skills, can work on a project independently\nStrong communication skills and negotiation skills\nGood command of English and Mandarin\nSound PC knowledge including MS office\n\nWe offer 5 days work, Annual Leave: 18 days, excellent career prospects, competitive remuneration package and fringe benefits to the right candidates. Interested parties please send your full resume (in MS Word or PDF format) with availability, present and expected salary to us.\n\n(Personal data collected is used for recruitment purpose only.)\n\nFor more information, please be welcome to visit our group website: http://www.obisourcing.com/", "employment_types": ["Full Time"], "selling_points": [], "locations": ["Lai Chi Kok"], "categories": ["Merchandising & Purchasing", "Sundries"], "post_time": "2021-12-24T02:40:53Z", "salary": {"currency": null, "max": null, "min": null, "period": "monthly", "term": null}, "salary_visible": false, "title_keywords": ["merchandiser"], "responsibilities": ["communicate with", "document filing", "price negotiation", "management", "control", "monitoring", "quality", "checking", "monitor", "coordinate with", "review", "specifications", "contact", "schedule", "evaluation", "report"], "requirements": {"degrees": ["diploma or above"], "majors": [], "languages": ["english", "mandarin"], "language_level": ["good command"], "hard_skills": ["problem solving", "project management", "pc knowledge", "ms office"], "soft_skills": ["communication skills", "independently", "independent", "negotiation", "project management skills", "negotiation skills", "problem solving skill", "time management", "presentation"], "languages_combined": [{"language": "english", "language_level": ["good command"]}, {"language": "mandarin", "language_level": ["good command"]}]}, "experience_required": {"duration": ["5 years"], "field": ["trading"]}}, {"job_id": "100003009003989", "location_code": "hk", "company": "Eternity Consultants (HK) Ltd", "job_title": "Sales Coordinator / Sales Executive / Officer  - Watch / Jewelry / Optical - Trading", "description": "We are a global sourcing company and looking for a Sr. Merchandiser/ Merchandiser for hardgoods team, looking after Home D\u00e9cor and household products. This role will be reporting to the Assistant Merchandise Manager and Divisional Merchandise Manager.\n\n\u00a0Key responsibilities include:\n\nWork with AMM / DMM of the whole supply chain from factory sourcing, development till shipment. Proactive on problem precaution and solving.\nWell organization skills, attentive to details and problem solving mindset is prerequisite.\nAble to work independently with factories and customers.\nMonitor suppliers performance to ensure product development and production on right track.\nCoordinate with cross functional teams.\nGood negotiation skills to drive cost saving and costing margin for clients\u2019 continue business growth.\nDevelop a close relationship with existing suppliers and develop new suppliers through personal connections, trade fairs and sourcing trips.\nProduct, payment and business term negotiations with suppliers.\nExperienced in work with foreign design team will be an advantage.\nWilling to travel.\n\nTo succeed in this role, you will have at least 5 years experience in sourcing & merchandising.\n\nRequirements:\n\nTertiary educated\nSelf-motivated and have strong sense of responsibility.\nIndependent and excellent time management in meeting deadline.\nGood communication skills and fluent in English, Mandarin and Cantonese.\nGood computer skills in MS Office including Excel, Power Point and MS TEAM.\nExperience in handling relevant categories.\nExperience working in US market is a Must.\nExperience in handling relevant categories\nExperience working in US market is a Must.\nImmediate available is preferable.", "employment_types": ["Full Time", "Permanent"], "selling_points": ["2-3 years Sales & marketing in Trading or factory", "optical or watch or jewelry, Electronic", "business development, meeting with clients"], "locations": ["Not Specified"], "categories": ["Merchandising & Purchasing", "PVC", "Sundries", "Sales, CS & Business Devpt", "Account Servicing"], "post_time": "2021-12-28T14:30:57Z", "salary": {"currency": null, "max": null, "min": null, "period": "monthly", "term": null}, "salary_visible": false, "title_keywords": ["sales coordinator", "officer", "sales executive"], "responsibilities": ["cost", "teams", "monitor", "coordinate with", "develop", "design", "merchandising", "payment"], "requirements": {"degrees": [], "majors": [], "languages": ["cantonese", "english", "mandarin"], "language_level": ["fluent", "good"], "hard_skills": ["power point", "excel", "computer skills", "ms office"], "soft_skills": ["communication skills", "self-motivated", "independent", "sense of responsibility", "time management"], "languages_combined": [{"language": "cantonese", "language_level": ["fluent", "good"]}, {"language": "english", "language_level": ["fluent", "good"]}, {"language": "mandarin", "language_level": ["fluent", "good"]}]}, "experience_required": {"duration": [], "field": []}}, {"job_id": "100003008990063", "location_code": "hk", "company": "Taibon Co Ltd", "job_title": "Senior Merchandiser (Gift and Premium/Plastic Molding)", "description": "Duties:\n\nKey account follow up\nBusiness development\u00a0\nHandle inquiries from customers and sample arrangements\u00a0\u00a0\nMeeting with overseas buyer\nCoordinate with suppliers and Buyer\nAny ad hoc tasks required\nBusiness trip in China / overseas\u00a0\n\nRequirements:\n\nDiploma or above\nMin.3-7years Sales & Marketing in Optical, fine Jewelry , Watch in Trading\n\nDetail minded, well-organized and eager to learn\nProficiency in spoken & written English and Mandarin\nProficient in MS Word, Excel, PowerPoint\n\n\u00a0*Interested parties, please Email full resume with current & expected salary & date available in MS WORD FORMAT ONLY to us\u00a0or fax to 3527 0634*\n\nWe are welcome applicants resend resumes to us even you have applied jobs in our company before.\n\nFor more jobs, please visit our website: www.hketernity.com\n\n(Personal data submitted are for recruitment purpose only.)\u00a0", "employment_types": ["Full Time"], "selling_points": ["Plastic Molding/Toy Manufacturing", "Senior Merchandiser", "Gift and premium"], "locations": ["Lai Chi Kok"], "categories": ["Merchandising & Purchasing", "Handbag", "Sundries", "Others"], "post_time": "2021-12-21T07:29:01Z", "salary": {"currency": null, "max": null, "min": null, "period": "monthly", "term": null}, "salary_visible": false, "title_keywords": ["senior merchandiser"], "responsibilities": ["ad hoc tasks", "coordinate with", "business trip"], "requirements": {"degrees": ["diploma or above"], "majors": [], "languages": ["english", "mandarin"], "language_level": ["proficiency"], "hard_skills": ["excel", "powerpoint", "ms word"], "soft_skills": ["eager to learn", "well-organized"], "languages_combined": [{"language": "english", "language_level": ["proficiency"]}, {"language": "mandarin", "language_level": ["proficiency"]}]}, "experience_required": {"duration": [], "field": []}}]