[{"job_id": "100003009053960", "location_code": "hk", "company": "Lai's Knitters Limited", "job_title": "ASST. MERCHANDISER / MERCHANDISER / SENIOR MERCHANDISER (SWEATERS KNIT)", "description": "Job Description:\n\nCommunicate with oversea customers on day-to-day basis and address corresponding concerns\nUnderstand customers' expectation on their samples and translate the idea to factory technicians\nReview and comment on samples\nKeep track on sample and production status to ensure on-time delivery\nCoordinate neccessary materials for bulk production and sampling\n\n\nJob Requirements:\n\nPolyU, HKDI or CITA graduate in Textile / Clothing or related discipline\u00a0\nMinimum 3 years\u2019 solid experience in sweater merchandising\u00a0\nStrong technical knowledge in sweater knit\nGood sense of styling\u00a0and\u00a0fitting\nGood command in English and Mandarin\nWilling to travel to China\nStrong organizing and analytical skills, energetics and willing to work as a team\n\n\nInterested parties please send your full resume with current and expected salary by email or by fax at 2325 3225\n\n\nPersonal data will be used for recruitment purpose only.", "employment_types": ["Full Time", "Permanent", "Contract"], "selling_points": [], "locations": ["Wong Tai Sin Area"], "categories": ["Manufacturing", "Garment / Textile", "Merchandising & Purchasing", "Sweater"], "post_time": "2022-01-17T07:52:49Z", "salary": {"currency": null, "max": null, "min": null, "period": "monthly", "term": null}, "salary_visible": false, "title_keywords": ["merchandiser", "senior merchandiser", "asst. merchandiser"], "responsibilities": ["communicate with", "review", "coordinate"], "requirements": {"degrees": [], "majors": [], "languages": ["english", "mandarin"], "language_level": ["good command"], "hard_skills": ["analytical skills"], "soft_skills": ["work as a team", "analytical skills"], "languages_combined": [{"language": "english", "language_level": ["good command"]}, {"language": "mandarin", "language_level": ["good command"]}]}, "experience_required": {"duration": ["minimum 3 years"], "field": ["merchandising"]}}, {"job_id": "100003009053941", "location_code": "hk", "company": "Lai's Knitters Limited", "job_title": "FASHIION DESIGNER / KNITWEAR DESIGNER", "description": "Job Description:\n\nManage and develop the in-house collection\nResearch on the fashion and colour trend\nDevelop and design new stitches\nReview and comment on samples\nKeep track on sample and development status to ensure on-time delivery\nCoordinate necessary materials for sampling\nDevelop trend board for presentation\nAd-hoc brand related duties\n\nJob Requirements:\n\nPolyU, HKDI or CITA\u00a0graduate in Fashion Design or related discipline, majoring in knit would be an advantage.\u00a0\nMinimum 3 years\u2019 solid experience in sweater design or merchandising\nStrong technical knowledge in sweater knit\nGood sense of styling\u00a0and\u00a0fitting\nGood command in English and Mandarin\nWilling to travel to China\nStrong organizing and analytical skills, energetics and willing to work as a team\nAmbitious in sweater knit\nFresh graduate will also be considered as Assistant Fashion Designer\n\nInterested parties please send your full resume with current and expected salary by\u00a0fax to 2325 3225 or by email via jobsdb.\n\n\n\n\nPersonal data will be used for recruitment purpose only.", "employment_types": ["Full Time", "Permanent"], "selling_points": [], "locations": ["Kowloon City Area"], "categories": ["Design", "Fashion", "Manufacturing", "Garment / Textile", "Merchandising & Purchasing", "Sweater"], "post_time": "2022-01-17T07:48:37Z", "salary": {"currency": null, "max": null, "min": null, "period": "monthly", "term": null}, "salary_visible": false, "title_keywords": ["designer"], "responsibilities": ["ad-hoc", "review", "design", "develop", "coordinate"], "requirements": {"degrees": ["fresh graduate"], "majors": [], "languages": ["english", "mandarin"], "language_level": ["good command"], "hard_skills": ["analytical skills"], "soft_skills": ["work as a team", "analytical skills"], "languages_combined": [{"language": "english", "language_level": ["good command"]}, {"language": "mandarin", "language_level": ["good command"]}]}, "experience_required": {"duration": ["minimum 3 years"], "field": ["merchandising", "design"]}}, {"job_id": "100003009052246", "location_code": "hk", "company": "Newtimes Development Limited", "job_title": "Senior Merchandiser (Sweater)", "description": "Responsibilities:\n\nAssist the team on full cycle merchandising from product development until shipment delivery\nNegotiate with suppliers to meet customers\u2019 cost and quality requirements\nPrepare presentation for the buying trip including sample styles, price, supplier and factory information\nWork with full merchandising cycle counterparts of design, technical, production, QC and logistics for the order follow up\nPerform other ad hoc duties\u00a0\n\nRequirements:\n\nAt least 5 years' garment trading or buying office experience in sweater\nExperience in USA market is preferable\nPossess knowledge in product development is an advantage\nGood computer knowledge (MS Office and Chinese Word Processing)\nGood command of written & spoken English\nGood negotiation skills and communication skills to liaise with suppliers, buyers and factories\nAble to work independently, a good team player, attentive to details and able to work under pressure\nImmediate available is highly recommended\u00a0\n\nInterested parties please send\u00a0your application\u00a0with\u00a0current salary,\u00a0expected salary and availability\u00a0via \u201cAPPLY NOW\u201d button.\n\n(Collected personal data will be kept strictly confidential and used for recruitment purpose only.)\n", "employment_types": ["Full Time", "Permanent"], "selling_points": ["Immediate available is highly recommended", "5-day work", "Double Pay, Discretionary Bonus, Birthday Leave"], "locations": ["Lai Chi Kok"], "categories": ["Merchandising & Purchasing", "Sweater"], "post_time": "2022-01-17T02:32:55Z", "salary": {"currency": null, "max": null, "min": null, "period": "monthly", "term": null}, "salary_visible": false, "title_keywords": ["senior merchandiser"], "responsibilities": ["ad hoc duties", "cost", "quality", "merchandising", "design", "logistics"], "requirements": {"degrees": [], "majors": [], "languages": ["english", "chinese"], "language_level": ["good command", "good"], "hard_skills": ["chinese word processing", "ms office"], "soft_skills": ["communication skills", "work independently", "good team player", "attentive to details", "negotiation skills", "work under pressure"], "languages_combined": [{"language": "english", "language_level": ["good command", "good"]}, {"language": "chinese", "language_level": ["good"]}]}, "experience_required": {"duration": ["at least 5 years"], "field": ["garment", "trading"]}}, {"job_id": "100003009055409", "location_code": "hk", "company": "initial Fashion Co Limited", "job_title": "Merchandiser (Ladieswear)", "description": "Responsibilities\u00a0\u00a0\nFollow up costing, sample development, bulk production and ensure high quality of output\nWork closely with Design team, Buying team and Vendors to ensure the whole merchandising procedures are in timely manner\nPrepare quotations and details for buy meeting\nAttend fitting session and follow up all designers' fit comments with vendors\nControl cost sheets and conduct negotiation with vendors for getting competitive prices\nManage product development till bulk production in line with buy calendar\nDay to day communication with factories for tracking production & delivery schedule without delay\nRequirements\nDiploma in Fashion, Clothing & Textile or related discipline preferable\nMinimum 3 years' solid experience in Garment items\nStrong fashion sense, detail minded, well organized and strong sense of responsibility\nGood communication, interpersonal and negotiation skills\nGood command of written and spoken English, Mandarin and Cantonese\nProficiency in MS Word, Excel and Chinese Word Processing\nWe are looking for candidates who have forward-looking vision, creative, energetic and strong fashion sense candidate. We offer the good development as well as regional and local career advancement opportunities.\nWe are a Hong Kong-based fashion label, established in 2000. We are now have business presence in Hong Kong, Macau and the Chinese Mainland.\u00a0We create a culture rather than just a piece of clothing.\u00a0 Unlike the usual practices of branding that are normally seen in the consumer goods industry, the branding philosophy in the fashion and lifestyle goods industry is unique and personality based, we bring \u201cThe Unusual Experience\u201d to our customers.\n\n\nInterested parties please send your resume with expected salary to Human Resources Department via email by clicking \"Apply Now\".\nPlease visit our company website at http://www.initialfashion.com for company information.\n\n\nAll information received will be treated in strict confidence and for recruitment purpose only.", "employment_types": ["Full Time", "Permanent"], "selling_points": ["To take initiate to search for new fabric", "Have daily communication with designers & vendor", "Minimum 3 years' relevant experience"], "locations": ["Kwun Tong"], "categories": ["Merchandising & Purchasing", "Sweater", "Woven / Knit", "Others"], "post_time": "2022-01-18T02:29:22Z", "salary": {"currency": null, "max": null, "min": null, "period": "monthly", "term": null}, "salary_visible": false, "title_keywords": ["merchandiser"], "responsibilities": ["control", "cost", "comments", "merchandising", "quality", "design", "procedures", "communication", "delivery schedule", "tracking"], "requirements": {"degrees": ["diploma"], "majors": [], "languages": ["cantonese", "english", "chinese", "mandarin"], "language_level": ["proficiency", "good command"], "hard_skills": ["excel", "chinese word processing", "ms word"], "soft_skills": ["sense of responsibility", "well organized", "communication", "negotiation skills", "energetic", "creative", "interpersonal"], "languages_combined": [{"language": "cantonese", "language_level": ["good command"]}, {"language": "english", "language_level": ["good command"]}, {"language": "chinese", "language_level": ["proficiency"]}, {"language": "mandarin", "language_level": ["good command"]}]}, "experience_required": {"duration": ["minimum 3 years"], "field": ["garment"]}}, {"job_id": "100003009051873", "location_code": "hk", "company": "LAWSGROUP", "job_title": "Senior Merchandiser, Sweater", "description": "Job\u00a0Responsibilities:\n\nAssist the merchandising team to ensure the garment development to production in a timely manner\nLiaise with internal and external parties to ensure the production is on track and the quality is up to customer\u2019s standard\nPerform strategic merchandising plan through various market research, analysis and forecasting to achieve company objective\nEstablish good relationship with existing and new customers\nRetrieve and facilitate problem solution when necessaries\nPerform ad hoc tasks as assigned by immediate superior\n\nJob\u00a0Requirements:\n\nDiploma\u00a0or above in Textile / Clothing or related discipline\nMinimum 3 years relevant working experience (with garment factory background\u00a0is an advantage)\nEnergetic person with strong leadership and enjoy team work\nWith \u201cCan-do\u201d attitude and able to work independently under pressure\nGood command of both written and spoken English and Chinese\nCandidate with less experience will be considered as Merchandiser\nWe\u00a0offer\u00a0attractive remuneration package to the right candidate. Interested parties please click the \"APPLY NOW\" button below and send your application together with a detailed resume including current & expected salary and availability to Human Resources Department.\nCompany website:\u00a0https://www.lawsgroup.com\n(Data collected will be treated in strict confidence and used for recruitment purpose only)", "employment_types": ["Full Time", "Permanent"], "selling_points": ["Dip. in Textile/Clothing or related discipline", "Min. 3 years relevant working experience", "Perform strategic merchandising plan"], "locations": ["Lai Chi Kok"], "categories": ["Manufacturing", "Garment / Textile", "Production Planning / Control", "Merchandising & Purchasing", "Sweater"], "post_time": "2022-01-17T01:25:49Z", "salary": {"currency": null, "max": null, "min": null, "period": "monthly", "term": null}, "salary_visible": false, "title_keywords": ["senior merchandiser"], "responsibilities": ["analysis", "internal and external parties", "a timely manner", "merchandising", "quality", "market research", "good relationship", "ad hoc tasks", "plan", "liaise with", "forecasting"], "requirements": {"degrees": ["diploma or above"], "majors": [], "languages": ["english", "chinese"], "language_level": ["good command"], "hard_skills": [], "soft_skills": ["work independently", "under pressure", "can-do", "energetic", "leadership"], "languages_combined": [{"language": "english", "language_level": ["good command"]}, {"language": "chinese", "language_level": ["good command"]}]}, "experience_required": {"duration": ["minimum 3 years"], "field": ["garment", "relevant working experience"]}}, {"job_id": "100003009043302", "location_code": "hk", "company": "Chamtex Limited", "job_title": "Merchandiser", "description": "Minimum 3 years' merchandising experience in sweater development and\u00a0Production follow up\nTI / Polytechnic graduate is preferable\nGood technical skill in sweater manufacturing and able to handle complicated\u00a0styles in both high fashion sweater and price conscious sweater\nExperience in factory manufacturing is an advantage\nAble to handle customer independently\nGood command of spoken and written English and able to communicate in Mandarin\nMature, self motivated, detail-minded, responsible and able to work under pressure\nWilling to travel to China (Dong Guan) when required\n\nInterested parties please apply with full resume and expected salary to us by clicking APPLY NOW.\u00a0\n\n", "employment_types": ["Full Time", "Permanent"], "selling_points": [], "locations": ["Kwun Tong"], "categories": ["Manufacturing", "Product Development / Management", "Merchandising & Purchasing", "Sweater", "Procurement / Purchasing / Sourcing"], "post_time": "2022-01-12T23:26:18Z", "salary": {"currency": null, "max": null, "min": null, "period": "monthly", "term": null}, "salary_visible": false, "title_keywords": ["merchandiser"], "responsibilities": ["merchandising", "work under pressure"], "requirements": {"degrees": [], "majors": [], "languages": ["english", "mandarin"], "language_level": ["good command"], "hard_skills": [], "soft_skills": ["detail-minded", "independently", "responsible", "mature", "self motivated", "technical skill", "work under pressure"], "languages_combined": [{"language": "english", "language_level": ["good command"]}, {"language": "mandarin", "language_level": ["good command"]}]}, "experience_required": {"duration": ["minimum 3 years"], "field": ["development", "manufacturing", "merchandising"]}}, {"job_id": "100003009051868", "location_code": "hk", "company": "LAWSGROUP", "job_title": "Senior Merchandiser, Cut & Sewn Knit", "description": "Job Responsibilities:\n\nSupervise the merchandising team to ensure the garment development to production in a timely manner\nLiaise with internal and external parties to ensure the production is on track and the quality is up to customer\u2019s standard\nPerform strategic merchandising plan through various market research, analysis and forecasting to achieve company objective\nEstablish good relationship with existing and new customers\nRetrieve and facilitate problem solution when necessaries\nPerform ad hoc tasks as assigned by immediate superior\n\nJob Requirements:\n\nDiploma\u00a0or above in Textile / Clothing or related discipline\nMinimum 3 years relevant working experience (with garment factory background\u00a0is an advantage)\nEnergetic person with strong leadership and enjoy team work\nWith \u201cCan-do\u201d attitude and able to work independently under pressure\nGood command of both written and spoken English and Chinese\nCandidate with less experience will be considered as Merchandiser\nFrequently travel to China is required\nWe\u00a0offer\u00a0attractive remuneration package to the right candidate. Interested parties please click the \"APPLY NOW\" button below and send your application together with a detailed resume including current & expected salary and availability to Human Resources Department.\nCompany website:\u00a0http://www.lawsgroup.com\n(Data collected will be treated in strict confidence and used for recruitment purpose only)", "employment_types": ["Full Time", "Permanent"], "selling_points": ["Perform strategic merchandising plan", "Dip. in Textile/Clothing with 3 yrs relevant exp.", "Frequently travel to China is required"], "locations": ["Lai Chi Kok"], "categories": ["Manufacturing", "Garment / Textile", "Production Planning / Control", "Merchandising & Purchasing", "Sweater"], "post_time": "2022-01-17T01:25:47Z", "salary": {"currency": null, "max": null, "min": null, "period": "monthly", "term": null}, "salary_visible": false, "title_keywords": ["senior merchandiser"], "responsibilities": ["analysis", "internal and external parties", "a timely manner", "merchandising", "quality", "market research", "good relationship", "ad hoc tasks", "plan", "liaise with", "forecasting"], "requirements": {"degrees": ["diploma or above"], "majors": [], "languages": ["english", "chinese"], "language_level": ["good command"], "hard_skills": [], "soft_skills": ["work independently", "under pressure", "can-do", "energetic", "leadership"], "languages_combined": [{"language": "english", "language_level": ["good command"]}, {"language": "chinese", "language_level": ["good command"]}]}, "experience_required": {"duration": ["minimum 3 years"], "field": ["garment", "relevant working experience"]}}, {"job_id": "100003009055698", "location_code": "hk", "company": "KOS International Limited", "job_title": "Planning Manager (Menswear)", "description": "To Lead the planning and buying function, our client is looking for a high calibre to join their team.\n\nResponsibilities\n\nWork with upper management on OTB based on sales goals\nSet assortment plan according to product category and store location\nWork with departments on product Launch and discount\nWork with retail store team for product replenishments\n\nRequirements\n\nBachelor's Degree in merchandising or related disciplines\n5+ years of experience in retail with apparel experience\nGood command in Chinese and English\n\nClick \"Apply Now\" to apply for this position or call Martin Tsang at +852 3180 4971 for a confidential discussion. All information collected will be kept in strict confidence and will be used for recruitment purpose only.", "employment_types": ["Full Time", "Permanent"], "selling_points": ["OTB", "Assortment", "Buying"], "locations": ["Kwai Tsing Area"], "categories": ["Merchandising & Purchasing", "Sweater"], "post_time": "2022-01-18T02:51:47Z", "salary": {"currency": null, "max": null, "min": null, "period": "monthly", "term": null}, "salary_visible": false, "title_keywords": ["manager"], "responsibilities": ["management", "plan", "otb"], "requirements": {"degrees": ["degree", "bachelor"], "majors": ["related disciplines"], "languages": ["english", "chinese"], "language_level": ["good command"], "hard_skills": [], "soft_skills": ["confidence"], "languages_combined": [{"language": "english", "language_level": ["good command"]}, {"language": "chinese", "language_level": ["good command"]}]}, "experience_required": {"duration": ["5+ years"], "field": ["retail"]}}, {"job_id": "100003009049091", "location_code": "hk", "company": "South Asia Knitting Factory Limited", "job_title": "Senior Merchandiser (Sweater) - 5  day work", "description": "Job Duties:\n\nResponsible for the coordination of operating merchandising cycle from sample development, sourcing, costing till production\nLiaise with overseas buyer and PRC factories\n\nJob Requirement:\n\nForm\u00a07 or above with minimum 5 years\u2019 merchandising experience in sweater, experience in factories is an advantage\nFamiliar with USA market is preferable\nWell-organized, detail-minded and good interpersonal skills\nGood command of both written and spoken English, Chinese & Mandarin\nWe provide the high caliber\u00a0with\u00a0attractive salary, good career prospect and benefits package\u00a0including\u00a05 day work,\u00a0\u00a0discretionary bonus,\u00a0education allowance and\u00a0medical scheme.\nInterested parties please send your full resume with your availability, current and expected salary details by \"APPLY\"\n\n(All applications will be treated in strict confidence and data collected will be used for recruitment purposes only)", "employment_types": ["Full Time", "Permanent"], "selling_points": ["Fluent Speaking and Writing English", "Diploma in Fashion / Textile is an advantage", "5 days work"], "locations": ["Kwun Tong Area"], "categories": ["Manufacturing", "Garment / Textile", "Merchandising & Purchasing", "Sweater"], "post_time": "2022-01-14T08:06:45Z", "salary": {"currency": null, "max": null, "min": null, "period": "monthly", "term": null}, "salary_visible": false, "title_keywords": ["senior merchandiser"], "responsibilities": ["liaise with", "merchandising", "coordination"], "requirements": {"degrees": [], "majors": [], "languages": ["english", "chinese", "mandarin"], "language_level": ["good command"], "hard_skills": [], "soft_skills": ["detail-minded", "well-organized", "interpersonal skills"], "languages_combined": [{"language": "english", "language_level": ["good command"]}, {"language": "chinese", "language_level": ["good command"]}, {"language": "mandarin", "language_level": ["good command"]}]}, "experience_required": {"duration": ["minimum 5 years"], "field": ["merchandising"]}}, {"job_id": "100003009045079", "location_code": "hk", "company": "SanMarino (Hong Kong) Co., Limited", "job_title": "Merchandiser (Sweater)", "description": "SanMarino (Hong Kong) Co., Ltd.\nWe are a well-established Japanese apparel company with offices in Tokyo, Paris, Shanghai, Hong Kong. Currently we are looking for great talents to join our team in HK:\n\n\nUniversity graduate preferable\nAt least 3 years working experience in knitwear preferable for high end brands\nProficient in English and Chinese languages (verbal and written)\nGood knitwear technical knowledge\nExcellent interpersonal and communication skills\nSelf-motivated, hardworking, attentive to details\nAble to work under pressure and high capacity of problem-solving skills\nPassion in fashion making\nCandidates with more experience can be considered as Senior Merchandiser\nWe offer 5-day work, medical, attractive remuneration packages(year-end double pay and bonus) and challenging career to the right candidates.\nInterested parties please send your resume with current salary, expected salary and availability via \u201cAPPLY NOW\u201d button.\nPersonal data collected will be treated in strict confidence and will be used for recruitment purposes only.\n", "employment_types": ["Full Time"], "selling_points": [], "locations": ["Lai Chi Kok"], "categories": ["Merchandising & Purchasing", "Sweater"], "post_time": "2022-01-13T07:21:19Z", "salary": {"currency": null, "max": null, "min": null, "period": null, "term": null}, "salary_visible": false, "title_keywords": ["merchandiser"], "responsibilities": ["communication", "work under pressure"], "requirements": {"degrees": ["university graduate"], "majors": [], "languages": ["japanese", "english", "chinese"], "language_level": ["proficient"], "hard_skills": ["problem-solving skills"], "soft_skills": ["communication skills", "self-motivated", "attentive to details", "passion in", "problem-solving skills", "interpersonal", "hardworking", "work under pressure"], "languages_combined": [{"language": "japanese", "language_level": []}, {"language": "english", "language_level": ["proficient"]}, {"language": "chinese", "language_level": ["proficient"]}]}, "experience_required": {"duration": ["at least 3 years"], "field": []}}, {"job_id": "100003009050210", "location_code": "hk", "company": "JFE Consulting Limited", "job_title": "Senior Merchandiser (Sweater / Home Textiles / Digital & Electronic appliance)", "description": "Our client is a global product sourcing company\n\nResponsibilities:\n\nTo develop existing regional sourcing partners and create synergy within business partners\nExperienced in Regional Sourcing (US/EU Markets), Global\u00a0Sourcing experience would be a plus\nMaintain a good relationship with customers to build the business\nPlay teamwork between Merchandising team and Logistics team to ensure a timely delivery\nExcellent communication and coordination skills with different parties\n\nRequirement:\n\nAt least 2 years relevant experience in Merchandising\nKnowledgeable of Sweater OR Home Textiles OR Digital & Electronic appliance\nFamiliar with US, Canada & EU markets and regional sourcing\nExcellent command of spoken and written Cantonese, Mandarin, and English\nLess experience will be considered as\u00a0Merchandiser/ Assistant\u00a0Merchandiser", "employment_types": ["Full Time", "Permanent"], "selling_points": ["5-day work, attractive salary, medical insurance", "Global  sourcing company,5+Merchandising exp", "Sweater/Home Textiles/Digital&Electronic appliance"], "locations": ["Not Specified"], "categories": ["Merchandising & Purchasing", "Electronics", "Sweater", "Textiles"], "post_time": "2022-01-14T09:56:54Z", "salary": {"currency": null, "max": null, "min": null, "period": "monthly", "term": null}, "salary_visible": false, "title_keywords": ["senior merchandiser"], "responsibilities": ["merchandising", "develop", "good relationship", "communication", "maintain", "logistics", "coordination"], "requirements": {"degrees": [], "majors": [], "languages": ["cantonese", "english", "mandarin"], "language_level": ["excellent"], "hard_skills": [], "soft_skills": [], "languages_combined": [{"language": "cantonese", "language_level": ["excellent"]}, {"language": "english", "language_level": ["excellent"]}, {"language": "mandarin", "language_level": ["excellent"]}]}, "experience_required": {"duration": ["at least 2 years"], "field": ["merchandising", "relevant experience"]}}, {"job_id": "100003009046135", "location_code": "hk", "company": "Find Asia Limited", "job_title": "Japanese speaking Assistant Merchandiser/ Merchandiser (Garment)", "description": "About Our Client\u00a0(Japanese\u00a0Manufacturer) &\u00a0Job Description\u00a0\n\nOur client, one of the\u00a0 manufacturing companies,\u00a0is now looking for a Japanese speaking Assistant Merchandiser / Merchandiser\u00a0to join their Team. The job duties are as follows:\n\n\n\nResponsible for clients' orders from product development, sampling, production orders to delivery\nPerform quality inspection at the factory\nWork closely with vendors for issue settlement during production process\nMaintain and update production records and system data\nAssist in any ad hoc projects assigned by supervisor\n\nRequirements:\n\n\u00a0Diploma or above\n1 years relevant experience in garment/ textile industry is highly preferred\nProficiency in spoken and written English, Mandarin and Japanese (JLPT Level 2 or above is a must)\nSound knowledge in PC operations\nGood interpersonal and communication skills, well-organized, patient, self-initiative\nBusiness travel is required (China and Asia Pacific)\nImmediate available is preferred\nCandidates with more relevant experience, esp. in Japanese apparel market will be considered as Merchandiser", "employment_types": ["Full Time", "Permanent"], "selling_points": ["5 days work, double pay, bonus, AL from 14 days", "Medical, Dental, Body Check", "Sizable and stable company"], "locations": ["Yau Tsim Mong Area"], "categories": ["Merchandising & Purchasing", "Fabrics", "Sweater", "Woven / Knit"], "post_time": "2022-01-13T09:43:25Z", "salary": {"currency": null, "max": null, "min": null, "period": "monthly", "term": null}, "salary_visible": false, "title_keywords": ["merchandiser", "assistant merchandiser"], "responsibilities": ["production process", "quality", "system data", "inspection", "maintain", "ad hoc projects"], "requirements": {"degrees": ["diploma or above"], "majors": [], "languages": ["japanese", "english", "mandarin"], "language_level": ["proficiency"], "hard_skills": ["pc operations"], "soft_skills": ["communication skills", "well-organized", "self-initiative", "patient", "interpersonal"], "languages_combined": [{"language": "japanese", "language_level": ["proficiency"]}, {"language": "english", "language_level": ["proficiency"]}, {"language": "mandarin", "language_level": ["proficiency"]}]}, "experience_required": {"duration": ["1 years"], "field": ["garment", "relevant experience", "textile"]}}, {"job_id": "100003009039356", "location_code": "hk", "company": "TRI-Come Recruitment Search", "job_title": "Merchandise Manager/ Senior Merchandiser/ Merchandiser  (Sweater/ Cotton Knit/ Woven/ Lingerie wear)", "description": "Minimum 3 years Merchandising experience in Sweater/ Woven/ Intimate Apparel/ Outerwear/ Sportswear/ Woven/Fine Knit / Casual wear/ Fashion Wear items such as Denim jeans, Functional jacket, Tee shirt, Lingerie wear, Casual & Fashion wear or Toys items.\nEquip with strong product knowledge to work with designers and garment factories to turn out quality products with justifiable value.\nEquip with strong communication and negotiation skill to work with both suppliers and buyers.\n\u00a0\nTextile & Clothing\u00a0Certificate or similar qualification in Technical Institute.\nGood written and spoken English\u00a0/ Mandarin is preferable\nWilling to travelling", "employment_types": ["Full Time", "Permanent"], "selling_points": [], "locations": ["Yau Tsim Mong Area"], "categories": ["Merchandising & Purchasing", "Sweater", "Woven / Knit", "Others"], "post_time": "2022-01-11T09:29:41Z", "salary": {"currency": null, "max": null, "min": null, "period": "monthly", "term": null}, "salary_visible": false, "title_keywords": ["merchandiser", "manager", "senior merchandiser"], "responsibilities": ["communication", "quality", "merchandising"], "requirements": {"degrees": ["certificate"], "majors": [], "languages": ["english", "mandarin"], "language_level": ["good"], "hard_skills": [], "soft_skills": ["communication", "negotiation skill"], "languages_combined": [{"language": "english", "language_level": ["good"]}, {"language": "mandarin", "language_level": ["good"]}]}, "experience_required": {"duration": ["minimum 3 years"], "field": ["toys", "merchandising"]}}, {"job_id": "100003009033181", "location_code": "hk", "company": "Hisso Limited", "job_title": "Merchandiser", "description": "Job Descriptions\n\n\nFollow through the entire merchandising process from Yardage & Trims sourcing, product development, sampling, bulk production to delivery;\nRegular meeting with sales team to identify customer\u2019s needs;\nClosely liaise with design team in product development stage and provide professional advices to improve cost efficiency and to better meet customer\u2019s needs;\nPrepare purchase orders and monitor the overall production schedule;\nCommunicate and coordinate with vendors, suppliers and manufacturers to ensure bulk quality and on-time delivery;\nLook for new suppliers to cope with company\u2019s development;\nFrequently review cost sheets and conduct price negotiations with various parties;\nEnsure data accuracy and maintain records in system.\nAd-hoc projects upon assignment.\n\nRequirements\n\n\nDiploma or above in Fashion, Clothing, Textile, Merchandising\u00a0or other related disciplines;\n5 years of solid experience;\nStrong product knowledge of garment and other fashion accessories;\nProficiency in MS office;\nDetail-minded, independent and able to meet tight schedule;\nStrong negotiation, communication and problem-solving skills;\nGood command of written and spoken English, Mandarin and Cantonese;\nWilling to travel to PRC\u00a0\nInterested candidates, please send your full resume with expected salary to\u00a0us\u00a0for interview.\n", "employment_types": ["Full Time", "Permanent"], "selling_points": ["Local fashion brand", "Dynamic working environment", "5-day work"], "locations": ["Lai Chi Kok"], "categories": ["Merchandising & Purchasing", "Sweater", "Woven / Knit", "Others"], "post_time": "2022-01-08T13:34:16Z", "salary": {"currency": null, "max": null, "min": null, "period": "monthly", "term": null}, "salary_visible": false, "title_keywords": ["merchandiser"], "responsibilities": ["cost", "review", "merchandising", "monitor", "design", "coordinate with", "quality", "ensure data accuracy", "purchase", "maintain", "sales team", "schedule", "liaise with", "ad-hoc projects"], "requirements": {"degrees": ["diploma or above"], "majors": ["related disciplines"], "languages": ["cantonese", "english", "mandarin"], "language_level": ["good command"], "hard_skills": ["problem-solving skills", "ms office"], "soft_skills": ["detail-minded", "independent", "negotiation", "communication", "problem-solving skills"], "languages_combined": [{"language": "cantonese", "language_level": ["good command"]}, {"language": "english", "language_level": ["good command"]}, {"language": "mandarin", "language_level": ["good command"]}]}, "experience_required": {"duration": ["5 years"], "field": []}}, {"job_id": "100003009050964", "location_code": "hk", "company": "Chandler Macleod Group (HK) Limited", "job_title": "Regional Merchandising Director (Luxury retail, RTW)", "description": "Responsibilities:\n\nFormulate merchandising strategies and prepare briefing on sales, sell -thru result, assortment mix and price structure\nManage Merchandising teams\nAnalyse and summarise analytical reports including weekly, monthly and seasonal reviews of the collection performance and relevant KPI\nConsolidate, verify and release country assortment plans and buying plans in line with overall budget objectives\nMonitor open to buy inventory and sales plan\nSupport countries with season end promotion planning in order to maximize sales and margins\n\nRequirements\n\nDegree holder in fashion & clothing or related discipline\nAt least 15 years of experience as Retail Buyer in Men's & Women's RTW\nStrong analytical and communication skills\nStrong computer skills especially in MS Word and Excel\nFluent in English\nWilling to travel", "employment_types": ["Full Time", "Permanent"], "selling_points": ["Market Leader", "Multinational working environment", "Competitive remuneration with multiple benefits"], "locations": ["Not Specified"], "categories": ["Merchandising & Purchasing", "Sweater", "Woven / Knit", "Others"], "post_time": "2022-01-14T12:08:05Z", "salary": {"currency": null, "max": null, "min": null, "period": "monthly", "term": null}, "salary_visible": false, "title_keywords": ["merchandising", "director"], "responsibilities": ["overall budget", "inventory", "teams", "merchandising", "monitor", "planning", "reports", "plan", "plans", "analyse"], "requirements": {"degrees": ["degree holder"], "majors": [], "languages": ["english"], "language_level": ["fluent"], "hard_skills": ["excel", "computer skills", "ms word"], "soft_skills": ["communication skills"], "languages_combined": [{"language": "english", "language_level": ["fluent"]}]}, "experience_required": {"duration": ["at least 15 years"], "field": ["retail"]}}, {"job_id": "100003009025601", "location_code": "hk", "company": "Chamtex Limited", "job_title": "Merchandiser", "description": "\n\nMinimum 3 years' merchandising experience in sweater development and\u00a0Production follow up\nTI / Polytechnic graduate is preferable\nGood technical skill in sweater manufacturing and able to handle complicated\u00a0styles in both high fashion sweater and price conscious sweater\nExperience in factory manufacturing is an advantage\nAble to handle customer independently\nGood command of spoken and written English and able to communicate in Mandarin\nMature, self motivated, detail-minded, responsible and able to work under pressure\nWilling to travel to China (Dong Guan) when required\n\nInterested parties please apply with full resume and expected salary to us by clicking APPLY NOW.\u00a0\n\n", "employment_types": ["Full Time", "Permanent"], "selling_points": [], "locations": ["Kwun Tong"], "categories": ["Manufacturing", "Product Development / Management", "Merchandising & Purchasing", "Sweater", "Procurement / Purchasing / Sourcing"], "post_time": "2022-01-06T16:08:09Z", "salary": {"currency": null, "max": null, "min": null, "period": "monthly", "term": null}, "salary_visible": false, "title_keywords": ["merchandiser"], "responsibilities": ["merchandising", "work under pressure"], "requirements": {"degrees": [], "majors": [], "languages": ["english", "mandarin"], "language_level": ["good command"], "hard_skills": [], "soft_skills": ["detail-minded", "independently", "responsible", "mature", "self motivated", "technical skill", "work under pressure"], "languages_combined": [{"language": "english", "language_level": ["good command"]}, {"language": "mandarin", "language_level": ["good command"]}]}, "experience_required": {"duration": ["minimum 3 years"], "field": ["development", "manufacturing", "merchandising"]}}, {"job_id": "100003009025568", "location_code": "hk", "company": "Win Paradise Limited", "job_title": "ASST MERCH/MERCHANDISER/SR MERCH/MERCH MGR (GARMENT/FABRIC/GARMENT ACC/FASHION ACC/HANDBAG/SUNDRIES)", "description": "F.5/TI\nMin 2 yrs Merchandising/Sales & Marketing/Purchasing experience in either one of below:\n\nWoven / Knit / Sweater / Silk / Denim\u00a0/\u00a0Garment, Casual Wear,\u00a0 Fashion, Underwear, Mould Cup, Bra Bonding, Sleepwear, Babywear, Kidswear, Outerwear, Sportswear, Swimwear, Jeans, Jacket, Suit, Board Shorts, Uniform, Fur, Leatherwear, Costume, Safety Wear Merchandising;\n\n\u00a0\u00a0\u00a0\u00a0\u00a0\u00a0\u00a0\u00a0\u00a0\u00a0\u00a0\u00a0 or\n\nWoven / Knit / Silk / Denim / Washed Fabric Merchandising and Purchasing and Sourcing and Development / Selling / Weaving / Dyeing / Printing;\n\n\u00a0\u00a0\u00a0\u00a0\u00a0\u00a0\u00a0\u00a0\u00a0\u00a0\u00a0\u00a0 or\n\nGarment Accessories / Underwear Accessories / Yarn / Garment Packaging / Embroidery / Logo / Cup Mould / Lace / Woven Label / Interlining / Purchasing and Sourcing and Librarian;\u00a0\n\u00a0\u00a0 or\nFashion Accessories / Cold Weather Items / Soft Accessories-Kids / Handbag / Fashion Bag / Casual Bag / Cosmetic Bag / Backpack / Tools Bag / Luggage / Shoes / Hat / Cap / Gloves / PVC Products / Socks / Home Textile / Bedding / Fine Jewellery / Fashion Jewellery / Baby Products / Infant Textile Products / Beauty Products / Cosmetic / Toiletries / Hair Care Products.\n\u00a0 or\nHard Toys / Soft Toys / Watch / Eyeglasses / Fine Jewellery / Imitation Jewellery / Houseware / Kitchenware / Kitchen Gadget / Home DIY / Dining Ware / Tableware / Ceramic / Sundries / Stationery / Seasonal Items\u00a0/\u00a0Artificial Flower / Art & Craft / Home Decoration /\u00a0Lighter / Gift Items /\u00a0Electrical Appliance / Audio / Electronic Products / Mobile Phone Accessories / Stationery /\u00a0Toiletries / Bath Room Acc / Sanitary Ware / Baby Products / Baby Textile / Make Up Acc / Office Supplies / Furniture\u00a0/\u00a0Bodycare /\u00a0Cosmetic / Beauty Products / Hair Care Products / Lighting / Sports Goods\u00a0/\u00a0Paper Products / Paper Raw Materials / Computer Parts / Tools / Assembly Kit / Steel Product / Outdoor Products / BBQ / Gardening / Bicycle / Pet Accessories / Camping Goods / Outdoor Goods / Canned Foods / Frozen Foods / Snack / Machine / Surf Accessories / Swim Accessories / Hotel Supplies / Bldg Materials / Sanitary Ware / Hotel Supplies / Home Textile / Bedding / Tools / Hardware / Glassware / Drinkware / Candle / Display / Label / Party Goods / PC Accessories / Jewellery Packaging / Jewellery Box / Electric Fan / Heater / Make Up Accessories / Cosmetic / Beauty Acc / Cosmetic Packaging / Metal Parts / Industrial Device / Electrical Device / Battery / Plastic Material / Home Care Products / Elec Alarm / Industrial Safety Products / Marine Equipment / Door & Window Hardware / Window Display Frame / Medical Protective Device / Face Mask / Baby Feed Products / Cake Tool / Pet Accessories / Home Technology / Printing & Packaging / Photoframe / Sports Goods / Glass / Fitness Equipment / Inflatable Swimming Goods / Swimming Acc / PVC Products.\u00a0\n\n\u00a0 or\nPurchaser / Purchasing Officer / Purchasing Manager / Supply Chain Director\u00a0 for\u00a0 Electronic Parts / Mechanical Parts\u00a0/ Watch Parts\u00a0/ Smart Watch / Eyeswear Parts / Handbag Accessories / Backpack Accessories / Shoes Materials / Leather Material\u00a0/ Chemical / Dyeing Stuff / Office Supplies / Office Equipment & Furniture / Toys Parts / Packaging Materials / Building Materials / Marble / Renovation Materials / Tile / Frozen Foods / Canned Foods / Dried Seafoods / Food Packaging / FMCG / Supermarket Commodities / Food Raw Material / F&B / Kitchen Equipment / E&M.\n\nProficient in English/Proficient in\u00a0Mandarin, Japanese/Korean Speaking preferred but not essential.\u00a0\u00a0\u00a0\u00a0\u00a0\u00a0\u00a0\u00a0\u00a0\nWork in HK/China Stay/Cambodia/Vietnam/Offshore Stay.\u00a0\nSalary Range: HK$13K-$60K / Month\n\n*** Please send your detailed resume in \u201cword format\u201d including \" Expected Salary \", \u201cCompany Nature & Product\u201d & \u201cAvailability Date\u201d to our \u201cE-mail Address\u201d shown above or fax to \u201c2780 2672\u201d or by clicking \u201cApply Now\u201d.", "employment_types": ["Full Time", "Permanent"], "selling_points": ["- F.5/Dip in BA/Textile/Garment/other", "- 2-8 yrs relevant Merch/Pur exp.", "- Garment/Fabric/Yarn/Fashn Acc/Toys/Wth/Gift/Sund"], "locations": ["Not Specified"], "categories": ["Merchandising & Purchasing", "Fabrics", "Sweater", "Woven / Knit"], "post_time": "2022-01-09T16:25:41Z", "salary": {"currency": null, "max": null, "min": null, "period": "monthly", "term": null}, "salary_visible": false, "title_keywords": ["merchandiser"], "responsibilities": ["office supplies", "renovation", "merchandising", "stationery", "hardware", "industrial safety", "audio"], "requirements": {"degrees": [], "majors": [], "languages": ["japanese", "english", "mandarin", "korean"], "language_level": ["proficient"], "hard_skills": ["acc", "word", "mobile", "hardware", "make", "pc", "logo"], "soft_skills": ["detailed"], "languages_combined": [{"language": "japanese", "language_level": []}, {"language": "english", "language_level": ["proficient", "proficient"]}, {"language": "mandarin", "language_level": []}, {"language": "korean", "language_level": []}]}, "experience_required": {"duration": [], "field": ["purchasing", "marketing", "merchandising"]}}, {"job_id": "100003009036162", "location_code": "hk", "company": "ALDI Services Asia Limited", "job_title": "Assistant Merchandiser / Merchandiser - Textile (m/f)", "description": "We invite now high caliber talent to apply for Assistant Merchandiser/ Merchandiser (m/f)\u00a0to join our rapidly growing sourcing team in Hong Kong. This position supports product development and commercialization with a fast-paced successful team.\n\nResponsibilities.\n\nPerform general sourcing duties as required by the Manager\nPrepare and ensures that all documents related to tender, submission, awarding of contracts and shipments are correct and completed\nFinalize submission comparison documents and identify preferred submission in line with company procedures\nEffectively communicate with Quality, CR, Admin and Logistics team members as well as ALDI International departments/ offices and other internal/external parties on behalf of Manager/ team\nFollow through the production process for all purchased products\nCarry out visits to trade fairs or suppliers in order to manage and develop the supplier pool within the commodity area\nProvides cover for the team members and supports the training of employees and trainees from other areas\n\n\u00a0Your Profile.\n\nAt least (Non-Degree) Tertiary education required.\nMinimum of 2 years' relevant working experience, preferably gained in sourcing/buying offices, working with consumer products.\nExcellent communication and interpersonal skills, team player.\nGood command of both verbal and written business English and fluency in Mandarin essential.\nAble to work independently, self-motivated, responsible, well-organized and willing to learn.\nAttention to detail and good organizing, coordination and planning skills.\nGeneral knowledge of MS office and Exchange essential.\nHigh level of maturity, integrity, trustworthiness.\n\nKey Benefits of working at ALDI.\n\nMarket leading remuneration package\n\nRewarding, attractive remuneration package.\nGroup Medical Insurance covering dental and maternity* benefits .\n\nWork-life balance\n\nFull time, permanent position, 5-day-work-week.\n20 days of paid Annual Leave.\n\nBeing part of a pleasant, successful, growing business\n\nALDI\u2019s business is expanding, same for the Hong Kong Office with lots of opportunities for growth and development.\nPleasant working atmosphere where proactive communication, teamwork and collaboration is highly valued.\n\nPeople Focused\n\nStructured, comprehensive orientation and on-the-job training.\nALDI empowers our people allowing staff ownership of their areas of responsibilities.\n\nTrust and Integrity\n\nWE DO WHAT WE SAY - \u00a0for us there is no grey area, we have robust business processes, procedures and strong governance in place.\nWe treat our staff members, customers, suppliers and service providers with trust and fairness as business partners.\n\n\u00a0* Maternity benefits only apply for female employees due to local Insurance policy\n\nHow to apply\u00a0\u00a0\n\nIf you are interested in applying for the job, we look forward to receiving your full application in English, including salary expectation and possible starting date. The application should be sent through JobsDB by clicking icon \u201cApply Now\u201d or addressed to ALDI HR Department,\u00a0Unit 2501, Tower 1, The Gateway, Harbour City, TST, Hong Kong.\n\nALDI is an Equal Opportunity employer. We are dedicated to create an equal opportunity throughout recruitment process and staff employment to build a diverse and inclusive workforce. We oppose all forms of unfair or unlawful discrimination in our selection process.\n\nAll personal data collected will be used for recruitment purposes only and be treated in strictest confidence and highest security level in accordance with Hong Kong Data (Privacy) Ordinance as well as ALDI internal Security Policy.\n\nNo part of this job content including but not limited to company information, logo and job description may be reproduced, presented, uploaded, transmitted, modified or distributed \u00a0in any form or by any means without prior permission of ALDI Services Asia Limited / ALDI Sourcing Asia Limited (\u201cthe Company\u201d). The Company reserves the right to take legal action on any unauthorized reproduction, presentation, upload, transmission, modification or distribution. Only applications submitted directly to the Company in response to this advertisement will be considered and any application received by the Company through unauthorized third party agents or via any other channels will not be considered.\n", "employment_types": ["Full Time", "Permanent"], "selling_points": ["Responsible for orders monitoring and follow-up", "Tender submission and shipment documents", "Communicate with Quality, CR, Admin and Logistics"], "locations": ["Kwun Tong"], "categories": ["Merchandising & Purchasing", "Fabrics", "Sweater", "Textiles"], "post_time": "2022-01-10T09:31:31Z", "salary": {"currency": null, "max": null, "min": null, "period": "monthly", "term": null}, "salary_visible": false, "title_keywords": ["merchandiser", "assistant merchandiser"], "responsibilities": ["communicate with", "production process", "contracts", "external parties", "procedures", "quality", "develop", "communication", "commercialization", "logistics", "tender", "coordination", "planning"], "requirements": {"degrees": ["degree"], "majors": [], "languages": ["english", "mandarin"], "language_level": ["fluency", "good command"], "hard_skills": ["exchange", "ms office"], "soft_skills": ["planning skills", "work independently", "self-motivated", "responsible", "well-organized", "willing to learn", "integrity", "communication and interpersonal skills", "attention to detail", "coordination", "team player"], "languages_combined": [{"language": "english", "language_level": ["fluency", "good command"]}, {"language": "mandarin", "language_level": ["good command"]}]}, "experience_required": {"duration": ["minimum of 2 years"], "field": ["buying offices", "relevant working experience"]}}, {"job_id": "100003009035360", "location_code": "hk", "company": "Bape Hong Kong Limited", "job_title": "Assistant Buyer - Aape", "description": "Accountabilities \u2013 Key Result Areas\n\n\n\nPrepare OTB, seasonal and annual buying plans based on a thorough understanding of consumer, market trends and company business objectives\nExecute buying activities, stock planning and allocation, and merchandise delivery and reordering situations\nAnalyze business performance and inventory turn\nWork closely with production and sourcing team to ensure the smooth flow of merchandise delivery\nWork with marketing and retail teams in regard to speedy response to market dynamics and promotions\nExperience / Qualification Requirements\n\n\nDegree holder in Fashion & Textiles or business discipline\nWith at least 1-2 years of experience in\u00a0buying and merchandising, preferably in the fashion / lifestyle / retail industry\nProactive, sensitive to figures and strong analytical and negotiation skills\nExcellent product sensibility and understanding of competitive retail landscape\nAttention to detail with high level of accuracy\n\nCompetitive remuneration and benefit package will be offered to the right candidate. Please submit your application by clicking \"Apply Now\" below.\n\n\n\nAll data collected is for recruitment purpose only.", "employment_types": ["Full Time"], "selling_points": ["1-2 years solid experience in buying", "Prepare OTB, seasonal and annual buying plans", "Strong analytical and negotiation skills"], "locations": ["Southern Area"], "categories": ["Merchandising & Purchasing", "Sweater", "Woven / Knit", "Textiles"], "post_time": "2022-01-10T06:55:56Z", "salary": {"currency": null, "max": null, "min": null, "period": "monthly", "term": null}, "salary_visible": false, "title_keywords": ["assistant"], "responsibilities": ["data", "inventory", "teams", "merchandising", "otb", "recruitment", "plans", "stock planning"], "requirements": {"degrees": ["degree holder"], "majors": ["business"], "languages": [], "language_level": [], "hard_skills": [], "soft_skills": ["sensitive to figures", "negotiation skills", "thorough", "attention to detail", "smooth", "proactive"], "languages_combined": []}, "experience_required": {"duration": ["at least 1-2 years"], "field": ["retail industry", "merchandising"]}}, {"job_id": "100003009035291", "location_code": "hk", "company": "Private Shop Limited", "job_title": "Assistant Buyer/ Buyer", "description": "Job Description\n\nThe incumbent will be responsible for the execution of buying activities and ensure a smooth communication with shops so as to achieve turnover, gross profit and inventory target.\n\nJob Duties and Responsibilities:\n\nPlan and execute all merchandising functions, including merchandise planning and monitoring seasonal OTB and sales\nAnalyse sales performance, sell through and manage markdown during sale period to maximize and maintain planned GP\nDeploy effective merchandise ordering, replenishment and inventory control to achieve sell-through and GP target\nControl designated brands OTB from given sales targets\nAllocate goods accurately to different stores based on demand and store profile, forecast and manage inventory level from store to store\nConduct consolidation to maintain optimal stock/SKUs holding at store level, PO allocation/ replenishment order/ price change/ Shipment schedule and others\nPrepare regular analysis & reports for management review\nConduct regular product training to sales team\nWork closely with Retail operation and Marketing team to maximize sales performance\nRecommend and exploit potential products/brands from market knowledge and data analysis, buy the right products in coherence with the retail chain's positioning\n\nRequirements:\n\nUniversity graduate\nMinimum 2 years' relevant buying experience with knowledge in buying and inventory management of Lingerie/Apparel/ Footwear, Less experience will be considered as assistant buyer\nStrong business sense, attentive to figures and strong analytical skills\nPassionate, Proactive, Good communication and negotiation skills, and able to work under pressure\nProficiency in English and Chinese\nProficient in MS Word, Excel, PowerPoint\n\nWe are equal opportunity employer with good work environment. We offer attractive salary, training opportunity, and\u00a0staff purchase discount. Please send your application with resume and expected salary to HR Department,\u00a0Office Tower 8/F, 807-811, Hutchison Logistics Centre, 18 Container Port Road South, Kwai Chung or send your application by clicking \u201cApply Now\u201d.\n\nAll applications will be treated in strict confidence and all personal data collected will be used for recruitment purposes only.", "employment_types": ["Full Time", "Permanent"], "selling_points": ["5-day work, Competitive Pay and Benefits", "Plan and execute all merchandising functions", "Lingerie/Apparel/ Footwear"], "locations": ["Kwai Tsing Area"], "categories": ["Merchandising & Purchasing", "Footwear", "Sweater", "Procurement / Purchasing / Sourcing"], "post_time": "2022-01-10T06:41:35Z", "salary": {"currency": null, "max": null, "min": null, "period": "monthly", "term": null}, "salary_visible": false, "title_keywords": ["assistant"], "responsibilities": ["inventory", "merchandising", "otb", "communication", "maintain", "planning", "plan", "deploy", "management review", "control", "sales performance", "reports", "schedule", "forecast", "monitoring", "data analysis", "inventory control", "analysis", "replenishment", "sales team", "analyse"], "requirements": {"degrees": ["university graduate"], "majors": [], "languages": ["english", "chinese"], "language_level": ["proficiency"], "hard_skills": ["ms word", "excel", "powerpoint", "analytical skills"], "soft_skills": ["attentive", "passionate", "business sense", "analytical skills", "communication", "negotiation skills", "proactive", "work under pressure"], "languages_combined": [{"language": "english", "language_level": ["proficiency"]}, {"language": "chinese", "language_level": ["proficiency"]}]}, "experience_required": {"duration": ["minimum 2 years"], "field": ["inventory management"]}}, {"job_id": "100003009040156", "location_code": "hk", "company": "ConnectedGroup Limited", "job_title": "PD & Sourcing Director (Sportswear)", "description": "PD & Sourcing Director (Sportswear)\n\nA global lifestyle retailer is now looking to hire a director for PD & sourcing to join their well-established business. Leading a team of over 15, you will be in charge of all sourcing and product development operations for product categories such as knits, sweater, accessories & swimwear, whilst reporting directly to the managing director.\n\nKey responsibilities: -\n\nSourcing & Vendor Management\nSupervise and lead all sourcing and product development operations\nConstant interaction and consultation on vendor capacity, order allocation etc\nObserve and understand in detail the buyer's needs and provide as much support as possible\nAnalyse, evaluate and improve vendor's capabilities and performance\nExpand or consolidate vendor base when appropriate\nPrice negotiation and create detailed cost saving plans and methods\nLead-time negotiation along with regular trouble shooting issues such as deliveries and quality issues\nProduct Development\nWork closely with suppliers on providing available products and new trends, technology\nFrequent communications with buyers and designers on available products on offer and manage all sampling processes\nDrive price negotiations and strive for meeting or exceeding target margins\nCommunications with internal support teams\nAssist in certain quality driven initiatives\nAssist in any quality issues, claims or disputes between buyers/QA with vendors\nMonitor potential quality issues and execute relative solutions to ensure they can be avoided\n\nRequirements: -\n\nBachelor's degree of above in Fashion or related discipline\nSelf-driven, flexible\nMinimum 15 years relevant sourcing experience with at least 5 years director level experience\nExcellent written and verbal Cantonese, Mandarin and English\nStrong product technical knowledge in sportswear, especially in knits is a must\nInternational travel is required and to production sites in Southeast Asia or otherwise\n\nInterested parties please send your CV to Vincent.chow@connectedgroup.com", "employment_types": ["Full Time", "Permanent"], "selling_points": ["sportswear & lifestyle clothing company", "excellent office environment & culture", "great career prospects & opportunities"], "locations": ["Not Specified"], "categories": ["Merchandising & Purchasing", "Sweater", "Woven / Knit", "Textiles"], "post_time": "2022-01-12T01:39:35Z", "salary": {"currency": null, "max": null, "min": null, "period": "monthly", "term": null}, "salary_visible": false, "title_keywords": ["director"], "responsibilities": ["management", "price negotiation", "cost", "communications with", "operations", "quality", "teams", "monitor", "evaluate", "plans", "analyse"], "requirements": {"degrees": ["degree", "bachelor"], "majors": [], "languages": ["cantonese", "english", "mandarin"], "language_level": ["excellent"], "hard_skills": [], "soft_skills": ["flexible", "driven"], "languages_combined": [{"language": "cantonese", "language_level": ["excellent"]}, {"language": "english", "language_level": ["excellent"]}, {"language": "mandarin", "language_level": ["excellent"]}]}, "experience_required": {"duration": ["at least 5 years", "minimum 15 years"], "field": []}}, {"job_id": "100003009031745", "location_code": "hk", "company": "BDM Company Ltd.", "job_title": "Divisional Merchandising Manager / Senior Merchandising Manager (Woven / Knit / Sweater)", "description": "At least\u00a012 years\u2019 apparel merchandising experience, in which\u00a03 -\u00a04 years at the senior managerial\u00a0grade\nStrong\u00a0product knowledge for woven / knit / sweater garments for high fashion\u00a0markets\nExperienced in handling from\u00a0product development, production follow-up till to product delivery\nSolid experience\u00a0in serving\u00a0US / EU customers\nExcellent leadership and problem solving skills\nProficiency in both written and spoken English\nAggressive, presentable and able to work under pressure\nWilling to travel\nCandidates with\u00a0more experience\u00a0are considered for the post of Divisional Merchandising Manager\n\nWe offer attractive remuneration package to the right candidate. \u00a0Interested parties please send your\u00a0detailed CV with expected salary and available date\u00a0to the Human Resources Department by clicking the Apply Now button.\n\nPersonal data collected will be used for recruitment purpose only.", "employment_types": ["Full Time", "Permanent"], "selling_points": ["Min. 12 years\u2019 apparel merchandising experience", "Solid product knowledge for woven / knit / sweater", "Experienced in serving US / EU customers"], "locations": ["Not Specified"], "categories": ["Merchandising & Purchasing", "Sweater", "Woven / Knit"], "post_time": "2022-01-07T09:43:08Z", "salary": {"currency": null, "max": null, "min": null, "period": "monthly", "term": null}, "salary_visible": false, "title_keywords": ["merchandising manager"], "responsibilities": ["merchandising", "work under pressure"], "requirements": {"degrees": [], "majors": [], "languages": ["english"], "language_level": ["proficiency"], "hard_skills": ["problem solving skills"], "soft_skills": ["work under pressure", "problem solving skills", "leadership", "presentable"], "languages_combined": [{"language": "english", "language_level": ["proficiency"]}]}, "experience_required": {"duration": ["at least 12 years", "3 - 4 years"], "field": ["managerial", "merchandising"]}}, {"job_id": "100003009031704", "location_code": "hk", "company": "Gap International Sourcing Ltd", "job_title": "Temporary - Senior Merchandiser (5 Month)", "description": "ABOUT THE ROLE\nThe Senior Merchandiser, Product Development will be responsible for developing the garment samples for the assigned product / style while working closely with the Merchandising teams of the Vendors. As part of product development team s/he will also be providing support in identifying opportunities of cost saving, onboarding new vendors and executing the innovation agenda for the department in the assigned product.\n\nWHAT YOU'LL DO\n\nManages vendor orders and relationships for a sub-category.\nMaintains relationships and negotiation with new and current vendor\nResponsible for product development and order placement in efficient and effective manner\nWorks with Technical, QA and Mill management team to ensure all commercial decision and standards are met\nSupports category team in problem solving, information sharing and counter sourcing to support best placement plan\nManages counter costing; Handling samples; Tracking fit approvals; Tracking lab dips\nPartners with brand Design, R&D and key suppliers to develop innovative and quality product\nPartners with Mill management, QA and technical teams to resolve fabric or quality issues\nResolves issues within a timely manner while working to continuously improve and create internal and external processes and procedures\n\nWHO YOU ARE\n\nMerchandise Sourcing Knowledge \u2013 Experience in sample development and with offshore production exposure; in large-sized buying office or trading company\u00a0\nPlanning & Influencing \u2013 proven experience in plan, prioritize and influence at all levels\nDrive Results - ability to analyze situations and proactively suggest solutions to meet deliverables\nLearning Agility & Experimentation \u2013 demonstrates eagerness to learn and explore new ways of approaching goals\nEffective Communicator & Team Player - proven capability to communicate effectively, verbal and written\nHigh level of proficiency with Microsoft Excel\n\nFor over 50 years, Gap Inc. has done more than sell clothes \u2013 we give back to the community and engage in sustainability and environmental initiatives.\u00a0As our communities react to the global health crisis caused by COVID-19, our focus remains on supporting the health and livelihood of our employees while caring for our customers and communities.\u00a0To read more, visit\u00a0https://corporate.gapinc.com/en-us/news/coronavirus-response.\n\nGap Inc. is an equal-opportunity employer and continues to foster a diverse and inclusive environment. We have received numerous awards for our long-held commitment to equality. This year, we\u2019ve been named as one of the\u00a0Best Places to Work by the Humans Rights Campaign for the fifteenth consecutive year\u00a0and have been included in the\u00a02020 Bloomberg Gender-Equality Index for the\u00a0third year in a row.\u00a0\u00a0\n\nAny personal information collected relating to employment applications will be used for recruitment purposes only.\u00a0", "employment_types": ["Temporary", "Contract"], "selling_points": ["Cross-functions partnership", "Innovative production development", "Development and training opportunities"], "locations": ["Kwun Tong"], "categories": ["Merchandising & Purchasing", "Sweater", "Textiles", "Procurement / Purchasing / Sourcing"], "post_time": "2022-01-07T09:42:38Z", "salary": {"currency": null, "max": null, "min": null, "period": "monthly", "term": null}, "salary_visible": false, "title_keywords": ["senior merchandiser"], "responsibilities": ["management team", "cost", "management", "teams", "merchandising", "developing", "design", "develop", "quality", "a timely manner", "procedures", "executing", "planning", "providing support", "plan", "recruitment", "tracking"], "requirements": {"degrees": [], "majors": [], "languages": [], "language_level": [], "hard_skills": ["r&d", "bloomberg", "react", "gap", "vendor", "microsoft excel", "problem solving", "focus"], "soft_skills": ["efficient", "focus", "negotiation", "responsible", "timely", "prioritize", "problem solving", "ability to analyze", "diverse", "learning", "team player", "communicator", "innovative"], "languages_combined": []}, "experience_required": {"duration": [], "field": ["development", "planning"]}}, {"job_id": "100003009019995", "location_code": "hk", "company": "Contempo Limited", "job_title": "Merchandiser - Sweater", "description": "Responsibilities:\n\nCarry out business development activities and be responsible for the planning and coordination of production and shipment of customer orders so as to achieve customer satisfaction and meet business objectives.\n\n\u00a0Requirements\n\n\nHigher Diploma or above in textile and clothing.\nMinimum 5 years experience in the merchandising role of the sourcing industry.\nStrong knowledge of Sweater products is a must.\nWell understanding the sweater manufacturing process.\nFamiliar with US, Canada & EU markets, and regional sourcing.\nGood command of English and Chinese.\nImmediate availability is preferred.\n\n\nWe offer an attractive remuneration package including a 5-day work week, double pay, performance bonus, group medical insurance, birthday leave, long-service leave, and education allowance.\n\nPlease complete the application by clicking the\u00a0Apply now\u00a0button. You can also attach your CV and Cover Letter with your current and expected salary.\n\nClick here to visit our website\n\n\nOnly short-listed candidates will be notified. Personal Data collected will be kept in the strictest confidence and for recruitment purposes only.", "employment_types": ["Full Time", "Permanent"], "selling_points": ["Min 5 yrs exp in sweater product MR role", "Exp in global sourcing & familiar with US market", "5 days work, Fixed Bonus, Birthday leave"], "locations": ["Kwun Tong"], "categories": ["Merchandising & Purchasing", "Sweater", "Others", "Procurement / Purchasing / Sourcing"], "post_time": "2022-01-04T09:39:25Z", "salary": {"currency": null, "max": null, "min": null, "period": "monthly", "term": null}, "salary_visible": false, "title_keywords": ["merchandiser"], "responsibilities": ["coordination", "planning"], "requirements": {"degrees": ["higher diploma or above"], "majors": [], "languages": ["english", "chinese"], "language_level": ["good command"], "hard_skills": [], "soft_skills": ["confidence"], "languages_combined": [{"language": "english", "language_level": ["good command"]}, {"language": "chinese", "language_level": ["good command"]}]}, "experience_required": {"duration": ["minimum 5 years"], "field": ["merchandising"]}}, {"job_id": "100003009024283", "location_code": "hk", "company": "METRO Sourcing International Limited", "job_title": "Junior Merchandiser / Merchandiser Assistant (Textile / Garment)", "description": "Role Purpose:\nOur Junior Merchandiser / Merchandiser Assistant are responsible for everyday end to end merchandising activities and support in the global sourcing and chain supply projects.\nWhat you will be handling:\nResponsible for order follow-up, buying trips preparation, sample handling and showroom management\nEngage in merchandising process such as sourcing, product development, article & offer management and supplier management\nWork directly with overseas suppliers and customers to ensure smooth operations\nCoordinate with internal departments e.g. Packaging, Quality Assurance, Logistics and other external service providers to ensure on-time shipment\nMaintain accurate and updated order status and product information in supply chain system\nTalent that we are looking for:\nExperience and knowledge\u00a0in\u00a0textile / garment industry\nGood negotiation skills and problem-solving skills\nOpen minded, right attitude to learn and bring about change\nEnergetic to drive for customer success and excellent service\nStrong sense of ownership and high degree of independence\nPassionate in connecting with people and adopting high level of interpersonal skills\nWilling to travel when needed\nExperience, knowledge and skills required:\nDegree holder in\u00a0Textiles / Fashion Merchandising / Business Administration / Supply Chain Management / International Business or equivalent discipline\nAt least 2 years\u2019 relevant merchandising experience, EU market experience is preferred\nProficient in both spoken and written English and Mandarin\nProficient in MS Office (Excel / Word / PowerPoint / Outlook) applications\nCandidate with less experience will be considered as\u00a0Merchandiser Assistant\nFresh graduates are also welcome\nYou can enjoy:\nDiverse and Inclusive work environment\nFlexi Office Space with flexible working hours and home office option\n5-day work week, 13th month salary & performance bonus\nProfessional training and career advancement opportunities\nTraining Sponsorship for personal professional development\n\n\nJoin us\u00a0and\u00a0apply\u00a0now!\n\n\nPlease send your full resume with available date, present and expected salary to us.\nResume and personal data collected will be kept strictly confidential and used for recruitment purpose only.", "employment_types": ["Full Time", "Permanent"], "selling_points": ["Exp in textile / garment merchandising", "Resp. for end to end merchandising activities", "MNC, 5-day work, insurance, double pay, bonus"], "locations": ["Kowloon Bay"], "categories": ["Merchandising & Purchasing", "Sweater", "Woven / Knit", "Textiles"], "post_time": "2022-01-05T20:32:10Z", "salary": {"currency": null, "max": null, "min": null, "period": "monthly", "term": null}, "salary_visible": false, "title_keywords": ["merchandiser", "junior merchandiser", "assistant"], "responsibilities": ["management", "quality", "merchandising", "coordinate with", "maintain", "logistics", "ensure smooth operations", "recruitment", "personal data", "administration"], "requirements": {"degrees": ["degree", "degree holder"], "majors": ["international business", "business administration"], "languages": ["english", "mandarin"], "language_level": ["proficient"], "hard_skills": ["excel", "garment industry", "word", "powerpoint", "outlook", "problem-solving skills", "ms office"], "soft_skills": ["passionate", "flexible", "responsible", "diverse", "negotiation skills", "energetic", "interpersonal skills", "open minded", "smooth", "problem-solving skills", "accurate"], "languages_combined": [{"language": "english", "language_level": ["proficient"]}, {"language": "mandarin", "language_level": ["proficient"]}]}, "experience_required": {"duration": ["at least 2 years"], "field": ["textile", "merchandising", "garment"]}}, {"job_id": "100003009019186", "location_code": "hk", "company": "Gap International Sourcing Ltd", "job_title": "Senior Merchandiser - Sweater", "description": "\nABOUT THE ROLE\nThe Senior Merchandiser, Product Development will be responsible for developing the garment samples for the assigned product / style while working closely with the Merchandising teams of the Vendors. As part of product development team s/he will also be providing support in identifying opportunities of cost saving, onboarding new vendors and executing the innovation agenda for the department in the assigned product.\n\nWHAT YOU'LL DO\n\nDownloads tech pack and BOM\nWorks with vendors for development sampling and initial costs\nManages counter costing; Handling samples; Tracking fit approvals; Tracking lab dips\nFollowing up with vendor on system-updates\nManages wear-test samples and tailoring samples\nEnsures Systems are updated with costs and details\nCoordinates MST legacy ID communications for purchase order\nPartners with brand Design, R&D and key suppliers to develop innovative and quality product\nPartners with Mill management, QA and technical teams to resolve fabric or quality issues\nResolves issues within a timely manner while working to continuously improve and create internal and external processes and procedures\nSupport to coordinate with vendors / mills on T&A based on the provided booking timeline to facilitate capacity planning and migration plan\n\nWHO YOU ARE\n\n\n\u00a0Merchandise Sourcing Knowledge \u2013 Experience in sample development and with offshore production exposure; in large-sized buying office or trading company\nPlanning & Influencing \u2013 proven experience in plan, prioritize and influence at all levels\nDrive Results \u2013 ability to analyze situations and proactively suggest solutions to meet deliverables\n\u00a0Learning Agility & Experimentation \u2013 demonstrates eagerness to learn and explore new ways of approaching goals\nEffective Communicator & Team Player - proven capability to communicate effectively, verbal and written\n\nFor over 50 years, Gap Inc. has done more than sell clothes \u2013 we give back to the community and engage in sustainability and environmental initiatives.\u00a0As our communities react to the global health crisis caused by COVID-19, our focus remains on supporting the health and livelihood of our employees while caring for our customers and communities.\u00a0To read more, visit\u00a0https://corporate.gapinc.com/en-us/news/coronavirus-response.\n\nGap Inc. is an equal-opportunity employer and continues to foster a diverse and inclusive environment. We have received numerous awards for our long-held commitment to equality. This year, we\u2019ve been named as one of the\u00a0Best Places to Work by the Humans Rights Campaign for the fifteenth consecutive year\u00a0and have been included in the\u00a02020 Bloomberg Gender-Equality Index for the\u00a0third year in a row.\u00a0\u00a0\n\nAny personal information collected relating to employment applications will be used for recruitment purposes only.\u00a0", "employment_types": ["Full Time", "Permanent"], "selling_points": ["Partnering with regional teams", "WFH/ Flexible working hour", "Sweater Product Development"], "locations": ["Kwun Tong"], "categories": ["Manufacturing", "Product Development / Management", "Merchandising & Purchasing", "Sweater"], "post_time": "2022-01-04T06:55:22Z", "salary": {"currency": null, "max": null, "min": null, "period": "monthly", "term": null}, "salary_visible": false, "title_keywords": ["senior merchandiser"], "responsibilities": ["merchandising", "quality", "design", "purchase", "plan", "costs", "teams", "developing", "develop", "migration", "cost", "management", "coordinate with", "procedures", "executing", "booking", "providing support", "tracking", "systems", "a timely manner", "recruitment", "planning"], "requirements": {"degrees": [], "majors": [], "languages": [], "language_level": [], "hard_skills": ["r&d", "bloomberg", "react", "id", "gap", "vendor", "focus"], "soft_skills": ["focus", "responsible", "timely", "prioritize", "ability to analyze", "diverse", "learning", "team player", "communicator", "innovative"], "languages_combined": []}, "experience_required": {"duration": [], "field": ["development", "planning"]}}, {"job_id": "100003009025343", "location_code": "hk", "company": "Eternity Consultants (HK) Ltd", "job_title": "Garment Merchandiser (Woven / Knit / Lingerie / Fabric)", "description": "Few jobs opening in Woven/Knit or Lingerie or Fabric industries !!\n\nResponsibilities:\n\nDaily merchandising duties from product development, sampling, production orders to delivery, etc\nLiaise with factory and overseas customer\nIssue PO and work closely with suppliers and factories for materials arrangement\nConduct quality inspection at the factory\n\nRequirements:\n\nDegree holder\u00a0\n3+ years\u2019 relevant experience gained from woven / knit / textiles\u00a0\nProficiency in spoken and written English, Mandarin and Cantonese\nExcellent interpersonal and communication skills, responsible, well-organized, and self-initiative\n\n\n\n\nMany positions are not been posted in media.\u00a0 If you are looking for job in merchandising field, we are welcome you send your resume to us direct.\n\n*Interested parties, please send full resume with current & expected salary & date available in MS WORD FORMAT ONLY to email: \u00a0merch@HKETERNITY. com \u00a0\u00a0\u00a0or fax to 3527 0634\n\nHotline: (852) 3542 5082\n\nFor more jobs, please visit our website: www.hketernity.com\n\nWe are welcome applicants resend resumes to us even you have applied jobs in our company before.\n\n(Personal data submitted are for recruitment purpose only.)", "employment_types": ["Full Time", "Permanent"], "selling_points": ["3years experience in Garment merchandising", "Daily duties: product development, sampling, etc", "Conduct quality inspection, business travel"], "locations": ["Not Specified"], "categories": ["Manufacturing", "Garment / Textile", "Merchandising & Purchasing", "Sweater", "Woven / Knit"], "post_time": "2022-01-06T04:12:06Z", "salary": {"currency": null, "max": null, "min": null, "period": "monthly", "term": null}, "salary_visible": false, "title_keywords": ["merchandiser"], "responsibilities": ["liaise with", "quality", "merchandising", "inspection"], "requirements": {"degrees": ["degree holder"], "majors": [], "languages": ["cantonese", "english", "mandarin"], "language_level": ["proficiency"], "hard_skills": [], "soft_skills": ["communication skills", "responsible", "well-organized", "self-initiative", "interpersonal"], "languages_combined": [{"language": "cantonese", "language_level": ["proficiency"]}, {"language": "english", "language_level": ["proficiency"]}, {"language": "mandarin", "language_level": ["proficiency"]}]}, "experience_required": {"duration": ["3+ years"], "field": ["relevant experience"]}}, {"job_id": "100003009031556", "location_code": "hk", "company": "ConnectedGroup Limited", "job_title": "Merchandising Manager (garment manufacturer)", "description": "Merchandising Manager (garment manufacturer)\n\nMy client is a sizable & renowned manufacturer, who is looking for a Merchandising Manager. Reports to VP, leads small team in HK.\n\nKey responsibilities: -\n\nMerchandising Activities\nSupervise and lead the merchandising operations\nFollow production plans to ensure all orders are shipped on time\nConstant interaction and consultation on vendor capacity, order allocation etc.\nObserve and understand in detail the buyer's needs and provide as much support as possible\nVendor management\nAnalyse, evaluate and improve vendor's capabilities and performance\nExpand or consolidate vendor base when appropriate\nPrice negotiation and create detailed cost saving plans and methods\nLead-time negotiation along with regular trouble shooting issues such as deliveries and quality issues\nCommunications with internal support teams\nAssist in certain quality driven initiatives\nAssist in any quality issues, claims or disputes between buyers/QA with vendors\nMonitor potential quality issues and execute relative solutions to ensure they can be avoided\n\nRequirements: -\n\nDiploma or above in Textiles / Fashion / related discipline\nMinimum 8 years relevant sourcing experience\nExcellent Cantonese, Mandarin and English\nWilling to travel\n\nInterested parties pls send your CV to Angela Tsui angela.tsui@connectedgroup.com for more details.\n\nFor other available opportunities, please visit www.connectedgroup.com", "employment_types": ["Full Time", "Permanent"], "selling_points": ["Sizable & renowned manufacturer", "Leads small team, reports to VP", "Welcome any category"], "locations": ["Not Specified"], "categories": ["Merchandising & Purchasing", "Sweater", "Woven / Knit", "Textiles"], "post_time": "2022-01-07T09:27:51Z", "salary": {"currency": null, "max": null, "min": null, "period": "monthly", "term": null}, "salary_visible": false, "title_keywords": ["merchandising manager"], "responsibilities": ["management", "price negotiation", "cost", "communications with", "operations", "merchandising", "quality", "teams", "monitor", "evaluate", "plans", "analyse"], "requirements": {"degrees": ["diploma or above"], "majors": [], "languages": ["cantonese", "english", "mandarin"], "language_level": ["excellent"], "hard_skills": [], "soft_skills": [], "languages_combined": [{"language": "cantonese", "language_level": ["excellent"]}, {"language": "english", "language_level": ["excellent"]}, {"language": "mandarin", "language_level": ["excellent"]}]}, "experience_required": {"duration": ["minimum 8 years"], "field": []}}, {"job_id": "100003009016205", "location_code": "hk", "company": "BDM Company Ltd.", "job_title": "Merchandising Director (Apparel)", "description": "Job Description\u00a0\n\nProvide leadership and strategic direction to merchandising teams\nEnsure smooth running of the whole merchandising process from customer servicing, product development, supplier sourcing, vendor selection and quality management to product delivery\nMonitor annual and quarterly budgets\nBuild strong alliance and collaboration with internal & external stakeholders\n\nRequirements\n\nHigher Diploma or Degree in Garment, Merchandising or related disciplines is preferable\nMinimum 15 years\u2019 experience in apparel industry, of which\u00a02 -\u00a03 years at the same level\nStrong interpersonal, leadership and strategic planning skills\nMature, flexible, self-motivated and able to work under pressure\nExcellent\u00a0command of English and Mandarin\nWilling to travel\n\nWe offer attractive remuneration package to the right candidate. \u00a0Interested parties please send your\u00a0detailed CV with expected salary and available date\u00a0to the Human Resources Department by clicking the Apply Now button.\n\nPersonal data collected will be used for recruitment purpose only.", "employment_types": ["Full Time", "Permanent"], "selling_points": ["Provide strategic direction to merchandising teams", "Monitor annual and quarterly budgets", "Strong leadership and strategic planning skills"], "locations": ["Not Specified"], "categories": ["Merchandising & Purchasing", "Sweater", "Woven / Knit"], "post_time": "2022-01-03T08:37:06Z", "salary": {"currency": null, "max": null, "min": null, "period": "monthly", "term": null}, "salary_visible": false, "title_keywords": ["merchandising", "director"], "responsibilities": ["budgets", "management", "monitor", "quality", "teams", "merchandising"], "requirements": {"degrees": ["diploma", "degree"], "majors": ["related disciplines"], "languages": ["english", "mandarin"], "language_level": ["excellent"], "hard_skills": [], "soft_skills": ["flexible", "planning skills", "self-motivated", "mature", "leadership", "interpersonal", "work under pressure"], "languages_combined": [{"language": "english", "language_level": ["excellent"]}, {"language": "mandarin", "language_level": ["excellent"]}]}, "experience_required": {"duration": ["2 - 3 years", "minimum 15 years"], "field": []}}, {"job_id": "100003009020533", "location_code": "hk", "company": "KOS International Limited", "job_title": "Vice President - Product Development (High Fashion)", "description": "About our client:\nOur client is a global fashion retailer with a highly successful business around the globe. Due to business expansion in the region, there is a newly created role - Product Development Director in its regional sourcing hub based in Hong Kong.\nAbout your role:\nRationalization of the processes for the collection development at the headquarter in New York, coordinating regional platforms in Asia, in relation to company calendar timings\nImplementation of a structured and comprehensive quality management system to certify the quality of the finished product to the consumer\nDefine vendor strategy and management; as well as material sourcing management.\nNew factory/mill evaluation and on boarding.\nContinuously strive to improve communications internally and with suppliers and other external parties to develop and maintain an atmosphere of cooperation, confidence and trust, and to facilitate the shipping and delivery of sourced products by way of following up on orders and otherwise.\nReview staff development (productivity, performance, set career path)\nDelivery, Claim & Short Shipment review ongoing base\nPeriodically review existing key vendor performance (review KPI via season basis)\nEstablish the timeline and seasonal calendar with head-quarter PD team\nDesign the design process for the brand and monitor, implement and control the whole process in order to achieve the company's plan.\nCommit to creative product design and cost control. Based on the design aspect, carefully consider the cost of production.\n\nRequirement:\n\n\nMinimum of 20 years in apparel sourcing and supply chain, project & change management and leadership training.\nStrong business acumen with proven track record in general management, brand & business development.\nAble to develop and maintain commercial relationship with corporate and regional teams from multi-cultural backgrounds.\nCustomer and result orientated, strong problem solving skills.\nExperience working with premium brands, master and degree holder preferred.\nAbility to analyze and recommend business and organizational needs; manage long term to daily workloads with the team.\nFluent in English is required.\n\nClick \"Apply Now\" to apply for this position or call Jason Li at +852 3180 4962 for a confidential discussion. All information collected will be kept in strict confidence and will be used for recruitment purpose only.", "employment_types": ["Full Time", "Permanent"], "selling_points": ["Newly Created Role", "Leading Global Fashion Retailer", "High End Apparel"], "locations": ["Not Specified"], "categories": ["Merchandising & Purchasing", "Sweater", "Others", "Procurement / Purchasing / Sourcing"], "post_time": "2022-01-04T14:32:13Z", "salary": {"currency": null, "max": null, "min": null, "period": "monthly", "term": null}, "salary_visible": false, "title_keywords": ["vice president", "product development"], "responsibilities": ["shipping", "external parties", "quality", "design", "maintain", "plan", "evaluation", "control", "monitor", "implementation", "teams", "develop", "management", "cost", "change management", "review", "product design", "recruitment", "cost control"], "requirements": {"degrees": ["degree holder", "master"], "majors": [], "languages": ["english"], "language_level": ["fluent"], "hard_skills": ["problem solving skills", "vendor", "acumen"], "soft_skills": ["confidence", "organizational", "ability to analyze", "comprehensive", "structured", "business acumen", "problem solving skills", "creative", "leadership"], "languages_combined": [{"language": "english", "language_level": ["fluent"]}]}, "experience_required": {"duration": [], "field": []}}, {"job_id": "100003009014750", "location_code": "hk", "company": "", "job_title": "Asst Merchandiser / Merchandiser/ Senior Merchandiser (Woven High Fashion)", "description": "Excellent opportunity for sourcing experts to work for a Top Tier Retailer. The chosen candidate will be responsible for product development and order fulfilment to the team.\n\nClient Details\n\nOur client is one of the most reputable companies within the retail industry. With over decades of history, they have been delivering the best products and services to the world. With steady and rapid expansion in business in Hong Kong, they are actively looking for a Senior Merchandiser to join their dynamic company.\n\nDescription\n\nAssist in product development including vendor sourcing, fabric evaluation and sampling\nResponsible for order fulfilment to ensure production and delivery on time\nFormulate order critical path for vendors to follow and identify potential obstacles\nInvolve in negotiation with vendors regarding terms and conditions including delivery date, cost, MOQ, etc.\nAssist in ad-hoc duties as per assigned\n\nProfile\n\n3 years of experience in merchandising childrenswear/ladieswear/sweater in trading company/buying office, preferably with US market knowledge\nKnowledge in PLM and advanced excel skills - Pivot Table, VLOOKUP is a must\nStrong analytical skills with numerical sense\nOrganized and detail-oriented individual\nExcellent command in both English and Chinese\n\nJob Offer\n\nCareer progression\nRegional role\nCompetitive pay\n5-day work", "employment_types": ["Full Time"], "selling_points": [], "locations": ["Not Specified"], "categories": ["Manufacturing", "Garment / Textile", "Merchandising & Purchasing", "Sweater", "Woven / Knit"], "post_time": "2022-01-03T04:05:43Z", "salary": {"currency": null, "max": null, "min": null, "period": "monthly", "term": null}, "salary_visible": false, "title_keywords": ["merchandiser", "senior merchandiser"], "responsibilities": ["cost", "merchandising", "ad-hoc duties", "evaluation"], "requirements": {"degrees": [], "majors": [], "languages": ["english", "chinese"], "language_level": ["excellent"], "hard_skills": ["excel", "pivot table", "vendor", "analytical skills", "dynamic", "rapid", "vlookup"], "soft_skills": ["organized", "advanced", "negotiation", "responsible", "analytical skills", "detail-oriented", "dynamic", "ad-hoc duties"], "languages_combined": [{"language": "english", "language_level": ["excellent"]}, {"language": "chinese", "language_level": ["excellent"]}]}, "experience_required": {"duration": ["3 years"], "field": ["merchandising", "trading"]}}, {"job_id": "100003009017017", "location_code": "hk", "company": "Walters People (HK)", "job_title": "Assistant Merchandiser Officer (1 year contract)", "description": "Germany\u00a0company\n\n\u00a0\n-\u00a0F.5, IVE or Poly Graduate, Over\u00a01years Garment exp.\n\n- Strong High Fashion Item\n- Good English & Mandarin\n- Factory experiences and advantage\n- Good knowledge of Sourcing, sampling and following orders\n- Knowledge of Travel to China\n- MUST Be immediate availbale\n\n\n\n\n\n\nPlease send your application with detailed resume and expected salary to\nhr@takara.hk\u00a0\u00a0\n**Personal data collected will be used for recruitment purpose only**\n", "employment_types": ["Full Time", "Contract"], "selling_points": ["US based fashion company", "Leading designer brand", "Renewable contract"], "locations": ["Not Specified"], "categories": ["Manufacturing", "Garment / Textile", "Merchandising & Purchasing", "Sweater", "Textiles"], "post_time": "2022-01-03T10:21:56Z", "salary": {"currency": "HKD", "max": 24999, "min": 20000, "period": "monthly", "term": null}, "salary_visible": true, "title_keywords": ["officer", "assistant merchandiser"], "responsibilities": ["personal data", "recruitment"], "requirements": {"degrees": [], "majors": [], "languages": ["english", "mandarin"], "language_level": ["good"], "hard_skills": [], "soft_skills": ["detailed"], "languages_combined": [{"language": "english", "language_level": ["good"]}, {"language": "mandarin", "language_level": ["good"]}]}, "experience_required": {"duration": [], "field": []}}, {"job_id": "100003009001463", "location_code": "hk", "company": "Able Choice Personnel Consultancy", "job_title": "Merchandiser / Senior Merchandiser", "description": "Job Responsibilities:\n\n-\u00a0\u00a0\u00a0\u00a0\u00a0\u00a0Responsible for R&D to bulk production order follow up.\n\n-\u00a0\u00a0\u00a0\u00a0\u00a0\u00a0Prepare sales confirmations, factory contracts and sample order\n\nJob Requirements:\n\n-\u00a0\u00a0\u00a0\u00a0\u00a0\u00a0Higher Diploma or Above\n\n-\u00a0 \u00a0 \u00a0 5 years or above solid experience in garment trading, with manufacturing\u00a0experience is preferable\u00a0\n\n-\u00a0\u00a0\u00a0\u00a0\u00a0\u00a0Familiar with MS Office\n\n-\u00a0\u00a0\u00a0\u00a0\u00a0\u00a0Able to work independently and under pressure\n\n-\u00a0\u00a0\u00a0\u00a0\u00a0\u00a0Good command of spoken and written English and fluent in Mandarin\n\n-\u00a0\u00a0\u00a0\u00a0\u00a0 Travels to overseas required\n\n-\u00a0\u00a0\u00a0\u00a0\u00a0 Immediate available is highly preferred\n\n-\u00a0\u00a0\u00a0\u00a0\u00a0 Candidates with less experience will be considered as Assistant Merchandiser.\n\nInterested parties please apply with your full resume with expected salary.", "employment_types": ["Full Time", "Permanent"], "selling_points": ["Form 5 or above", "5 years Woven / Knit garment experience", "Good English must"], "locations": ["Kwun Tong Area"], "categories": ["Merchandising & Purchasing", "Sweater", "Woven / Knit", "Textiles"], "post_time": "2021-12-28T02:28:51Z", "salary": {"currency": null, "max": null, "min": null, "period": "monthly", "term": null}, "salary_visible": false, "title_keywords": ["merchandiser", "senior merchandiser"], "responsibilities": ["contracts", "prepare sales"], "requirements": {"degrees": ["higher diploma or above"], "majors": [], "languages": ["english", "mandarin"], "language_level": ["good command", "fluent"], "hard_skills": ["ms office"], "soft_skills": ["work independently", "under pressure"], "languages_combined": [{"language": "english", "language_level": ["fluent", "good command"]}, {"language": "mandarin", "language_level": ["good command"]}]}, "experience_required": {"duration": ["5 years"], "field": ["garment", "manufacturing", "trading"]}}, {"job_id": "100003009008344", "location_code": "hk", "company": "ConnectedGroup Limited", "job_title": "Costing Analyst - Apparel", "description": "~Form 5 or above\n~5 years Woven / Knit / Sweater garment experience\n~Good English, Cantonese and fair Mandarin\n", "employment_types": ["Full Time", "Permanent"], "selling_points": ["Buying office x 2", "Costing + PD", "26-33k"], "locations": ["Not Specified"], "categories": ["Merchandising & Purchasing", "Sweater", "Woven / Knit", "Textiles"], "post_time": "2021-12-30T07:41:13Z", "salary": {"currency": null, "max": null, "min": null, "period": "monthly", "term": null}, "salary_visible": false, "title_keywords": ["analyst"], "responsibilities": [], "requirements": {"degrees": [], "majors": [], "languages": ["cantonese", "english", "mandarin"], "language_level": [], "hard_skills": [], "soft_skills": [], "languages_combined": [{"language": "cantonese", "language_level": []}, {"language": "english", "language_level": []}, {"language": "mandarin", "language_level": []}]}, "experience_required": {"duration": [], "field": ["garment"]}}, {"job_id": "100003009005912", "location_code": "hk", "company": "Ralph Lauren", "job_title": "Assistant Buyer & Operations", "description": "F.5/TI\nMin 2 yrs Merchandising/Sales & Marketing/Purchasing experience in either one of below:\n\nWoven / Knit / Sweater / Silk / Denim\u00a0/\u00a0Garment, Casual Wear,\u00a0 Fashion, Underwear, Mould Cup, Bra Bonding, Sleepwear, Babywear, Kidswear, Outerwear, Sportswear, Swimwear, Jeans, Jacket, Suit, Board Shorts, Uniform, Fur, Leatherwear, Costume, Safety Wear Merchandising;\n\n\u00a0\u00a0\u00a0\u00a0\u00a0\u00a0\u00a0\u00a0\u00a0\u00a0\u00a0\u00a0 or\n\nWoven / Knit / Silk / Denim / Washed Fabric Merchandising and Purchasing and Sourcing and Development / Selling / Weaving / Dyeing / Printing;\n\n\u00a0\u00a0\u00a0\u00a0\u00a0\u00a0\u00a0\u00a0\u00a0\u00a0\u00a0\u00a0 or\n\nGarment Accessories / Underwear Accessories / Yarn / Garment Packaging / Embroidery / Logo / Cup Mould / Lace / Woven Label / Interlining / Purchasing and Sourcing and Librarian;\u00a0\n\u00a0\u00a0 or\nFashion Accessories / Cold Weather Items / Soft Accessories-Kids / Handbag / Fashion Bag / Casual Bag / Cosmetic Bag / Backpack / Tools Bag / Luggage / Shoes / Hat / Cap / Gloves / PVC Products / Socks / Home Textile / Bedding / Fine Jewellery / Fashion Jewellery / Baby Products / Infant Textile Products / Beauty Products / Cosmetic / Toiletries / Hair Care Products.\n\u00a0 or\nHard Toys / Soft Toys / Watch / Eyeglasses / Fine Jewellery / Imitation Jewellery / Houseware / Kitchenware / Kitchen Gadget / Home DIY / Dining Ware / Tableware / Ceramic / Sundries / Stationery / Seasonal Items\u00a0/\u00a0Artificial Flower / Art & Craft / Home Decoration /\u00a0Lighter / Gift Items /\u00a0Electrical Appliance / Audio / Elec Products / Elec Fan / Heater / Stationery /\u00a0Toiletries / Bath Room Acc / Sanitary Ware / Baby Products / Baby Textile / Make Up Acc / Office Supplies / Furniture\u00a0/\u00a0Bodycare /\u00a0Cosmetic / Beauty Products / Hair Care Products / Lighting / Sports Goods\u00a0/\u00a0Paper Products / Paper Raw Materials / Computer Parts / Tools / Assembly Kit / Steel Product / Outdoor Products / BBQ / Gardening / Bicycle / Pet Accessories / Camping Goods / Outdoor Goods / Canned Foods / Frozen Foods / Snack / Machine / Surf Accessories / Swim Accessories / Hotel Supplies / Bldg Materials / Sanitary Ware / Hotel Supplies / Home Textile / Bedding / Tools / Hardware / Glassware / Drinkware / Candle / Display / Label / Party Goods / PC Accessories / Jewellery Packaging / Jewellery Box / Electric Fan / Heater / Make Up Accessories / Cosmetic / Beauty Acc / Cosmetic Packaging / Metal Parts / Industrial Device / Electrical Device / Battery / Plastic Material / Home Care Products / Elec Alarm / Industrial Safety Products / Marine Equipment / Door & Window Hardware / Window Display Frame / Medical Protective Device / Face Mask / Baby Feed Products / Cake Tool / Pet Accessories / Home Technology / Printing & Packaging / Photoframe / Sports Goods / Glass / Fitness Equipment / Inflatable Swimming Goods / Swimming Acc / PVC Products.\u00a0\n\n\u00a0 or\nPurchaser / Purchasing Officer / Purchasing Manager / Supply Chain Director\u00a0 for\u00a0 Electronic Parts / Mechanical Parts\u00a0/ Watch Parts\u00a0/ Smart Watch / Eyeswear Parts / Handbag Accessories / Backpack Accessories / Shoes Materials / Leather Material\u00a0/ Chemical / Dyeing Stuff / Office Supplies / Office Equipment & Furniture / Toys Parts / Packaging Materials / Building Materials / Marble / Renovation Materials / Tile / Frozen Foods / Canned Foods / Dried Seafoods / Food Packaging / FMCG / Supermarket Commodities / Food Raw Material / F&B / Kitchen Equipment / E&M.\n\nProficient in English/Proficient in\u00a0Mandarin, Japanese/Korean Speaking preferred but not essential.\u00a0\u00a0\u00a0\u00a0\u00a0\u00a0\u00a0\u00a0\u00a0\nWork in HK/China Stay/Cambodia/Vietnam/Offshore Stay.\u00a0\nSalary Range: HK$13K-$60K / Month\n\n*** Please send your detailed resume in \u201cword format\u201d including \" Expected Salary \", \u201cCompany Nature & Product\u201d & \u201cAvailability Date\u201d to our \u201cE-mail Address\u201d shown above or fax to \u201c2780 2672\u201d or by clicking \u201cApply Now\u201d.", "employment_types": ["Full Time", "Permanent"], "selling_points": ["APAC", "Prior experience in Retail Merchandise/Buying", "Fluent in English and Cantonese"], "locations": ["Tsim Sha Tsui"], "categories": ["Merchandising & Purchasing", "Sweater", "Woven / Knit", "Others"], "post_time": "2021-12-29T06:14:07Z", "salary": {"currency": null, "max": null, "min": null, "period": "monthly", "term": null}, "salary_visible": false, "title_keywords": ["operations", "assistant"], "responsibilities": ["office supplies", "renovation", "merchandising", "stationery", "hardware", "industrial safety", "audio"], "requirements": {"degrees": [], "majors": [], "languages": ["japanese", "english", "mandarin", "korean"], "language_level": ["proficient"], "hard_skills": ["acc", "word", "make", "hardware", "pc", "logo"], "soft_skills": ["detailed"], "languages_combined": [{"language": "japanese", "language_level": []}, {"language": "english", "language_level": ["proficient", "proficient"]}, {"language": "mandarin", "language_level": []}, {"language": "korean", "language_level": []}]}, "experience_required": {"duration": [], "field": ["purchasing", "marketing", "merchandising"]}}, {"job_id": "100003008996744", "location_code": "hk", "company": "Page Personnel", "job_title": "Senior Sourcing Specialist - US Market - Sweater/Ladieswear", "description": "COMPANY OVERVIEW\nOur Client, a Japanese garment manufacturer, is looking for a Merchandising Clerk.\n\nJOB RESPONSIBILITIES\n\nSupport the team from product development, sampling, production orders to delivery\nPrepare and handle various documents, e.g. invoices and P/L, etc. independently\nWork with shipping company for the shipment arrangement\nManage goods return, ATA carnet and payment follow up\nEstablish and maintain good rapport with customers and factory\nProvide general support to the team and assist in any ad hoc assignments\n\nJOB REQUIREMENTS\n\nDiploma or above\n1-2yrs working experience in garment / textile industry is an advantage\nGood command of English and Chinese (Cantonese & Mandarin)\nGood in PC operations\nImmediate available is highly preferred\nFresh graduate will also be considered\n\nBENEFITS\n\n5days, Mon-Fri\nDouble pay\nDiscretionary bonus\nMedical & Dental insurance\nAL 15days\nLocation: TST\n\nInterested candidates, please send your detailed resume including:\n\n1) Current and expected salary\n2) Availability\n3) Reason for leaving current company \u3000to\n\ndaisy.leung @jac-recruitment.com, jac.hk @jac-recruitment.com\n\nPersonal data collected will be used for employment-related purposes only. We regret to inform that only shortlisted candidates will be notified.", "employment_types": ["Full Time", "Permanent"], "selling_points": ["End to end merchandising process", "Attractive package", "Excellent career progression"], "locations": ["Not Specified"], "categories": ["Merchandising & Purchasing", "Sweater", "Woven / Knit", "Textiles"], "post_time": "2021-12-23T08:29:56Z", "salary": {"currency": null, "max": null, "min": null, "period": "monthly", "term": null}, "salary_visible": false, "title_keywords": ["specialist"], "responsibilities": ["shipping", "invoices", "shipment arrangement", "payment", "maintain", "ad hoc assignments", "ata carnet", "general support", "support the team"], "requirements": {"degrees": ["fresh graduate", "diploma or above"], "majors": [], "languages": ["cantonese", "english", "chinese", "mandarin"], "language_level": ["good command"], "hard_skills": ["pc operations"], "soft_skills": [], "languages_combined": [{"language": "cantonese", "language_level": ["good command"]}, {"language": "english", "language_level": ["good command"]}, {"language": "chinese", "language_level": ["good command"]}, {"language": "mandarin", "language_level": ["good command"]}]}, "experience_required": {"duration": [], "field": ["garment", "textile"]}}]