[{"job_id": "100003009053510", "location_code": "hk", "company": "Bape Hong Kong Limited", "job_title": "Buying Assistant - Aape", "description": "Accountabilities \u2013 Key Result Areas\n\n\n\nAssist buying team in execute buying activities, stock planning and allocation, and merchandise delivery and reordering situations to meet company business objectives\nPrepare merchandising reports for management review on business performance and inventory turn\nAssist OTB planning, sell through, mark down logistics\nWork closely with production and sourcing team to ensure the smooth flow of merchandise delivery\nWork with marketing and retail teams in regard to speedy response to market dynamics and promotions\n\nExperience / Qualification Requirements\n\n\nDegree holder in Fashion & Textiles or business discipline\nWith 1-2 years of experience in\u00a0buying and merchandising, preferably in the fashion / lifestyle / retail industry\nProactive, sensitive to figures and strong analytical and negotiation skills\nAdequate product sensibility and understanding of competitive retail landscape\nAttention to detail with high level of accuracy\n\nCompetitive remuneration and benefit package will be offered to the right candidate. Please submit your application by clicking \"Apply Now\" below.\n\n\n\nAll data collected is for recruitment purpose only.", "employment_types": ["Full Time"], "selling_points": ["1-2 years of working experience in buying", "Assist OTB planning, sell through, mark down", "Prepare merchandising reports"], "locations": ["Southern Area"], "categories": ["Merchandising & Purchasing", "Textiles", "Others", "Procurement / Purchasing / Sourcing"], "post_time": "2022-01-17T07:04:30Z", "salary": {"currency": null, "max": null, "min": null, "period": "monthly", "term": null}, "salary_visible": false, "title_keywords": ["buying assistant"], "responsibilities": ["data", "inventory", "merchandising", "teams", "otb", "reports", "logistics", "recruitment", "stock planning", "management review", "planning"], "requirements": {"degrees": ["degree holder"], "majors": ["business"], "languages": [], "language_level": [], "hard_skills": [], "soft_skills": ["sensitive to figures", "negotiation skills", "attention to detail", "smooth", "proactive"], "languages_combined": []}, "experience_required": {"duration": ["1-2 years"], "field": ["retail industry", "merchandising"]}}, {"job_id": "100003009054435", "location_code": "hk", "company": "C.F.L. Enterprise Limited", "job_title": "Senior Merchandiser (Sweater)", "description": "Responsibilities & Requirements:\n\nDiploma or above, preferably major in Textile and Clothing\nAt least 5 - 8 year experiences in handling sweater items\nExperiences in US Market will be an advantage\nStrong in yarn sourcing\nMust have experience in product development, costing and production\nAble to work independently and under tight schedule\nProficiency in both spoken and written English\n\n\u00a0We offer 5-day work plus attractive remuneration and fringe benefits to the right candidate.\u00a0 Interested parties please send your resume with current and expected salary and availability by\u00a0clicking \"APPLY NOW\".", "employment_types": ["Full Time"], "selling_points": [], "locations": ["Kowloon Bay"], "categories": ["Merchandising & Purchasing", "Textiles"], "post_time": "2022-01-17T09:33:08Z", "salary": {"currency": null, "max": null, "min": null, "period": "monthly", "term": null}, "salary_visible": false, "title_keywords": ["senior merchandiser"], "responsibilities": [], "requirements": {"degrees": ["diploma or above"], "majors": [], "languages": ["english"], "language_level": ["proficiency"], "hard_skills": [], "soft_skills": ["work independently"], "languages_combined": [{"language": "english", "language_level": ["proficiency"]}]}, "experience_required": {"duration": ["at least 5 - 8 year"], "field": ["product development"]}}, {"job_id": "100003009052252", "location_code": "hk", "company": "ALF Retail Hong Kong Limited", "job_title": "Buying Assistant \u2013 Womenswear & Lingerie (Brand: Marks and Spencer)", "description": "Reporting to the Buyer, the incumbent will be responsible for:\n\nProviding clerical and administrative support to the buying team in an effective and timely manner\nRegular data entries and data maintenance in SAP & UK IRP systems\u00a0\nAssisting in the preparation/collation of weekly management reports\nSeasonal catalogue maintenance\nManaging stock allocation to all retail stores and price maintenance\nHandling administrative duties and responsible for ad hoc projects independently as required\nJob Requirements:\nSecondary educated with a minimum of 1 year working experience\nProficient in both Windows and MS Excel\nAttentive to details, good numerical sense and organisational skills\nSelf-driven, energetic, well-organised and able to play as a good team-player\nFast learner with positive working attitude\nExcellent communication, interpersonal and presentation skills\nSAP experience is an added advantage\nIf you are interested in this role, please send your full resume together with your current and expected salary to us.\u00a0\n\n\n\nApply by\u00a0clicking \"Apply Now\"\n\nThe Human Resources Department: Unit 1806B-10, 18/F, Exchange Tower, 33 Wang Chiu Road, Kowloon Bay, Kowloon, Hong Kong\n\nPersonal information received from applicants will be kept confidential and used for employment-related purposes only.", "employment_types": ["Full Time", "Permanent"], "selling_points": ["Secondary educated or fresh graduates", "Providing clerical and administrative support", "Proficient in both Windows and MS Excel"], "locations": ["Kowloon Bay"], "categories": ["Admin & HR", "Clerical / Admin Staff", "Merchandising & Purchasing", "Textiles", "Sales, CS & Business Devpt", "Wholesale"], "post_time": "2022-01-17T02:34:40Z", "salary": {"currency": null, "max": null, "min": null, "period": "monthly", "term": null}, "salary_visible": false, "title_keywords": ["buying assistant"], "responsibilities": ["reporting", "maintenance", "data", "administrative support", "stock allocation", "systems", "communication", "management reports", "administrative duties", "ad hoc projects", "price maintenance", "catalogue"], "requirements": {"degrees": [], "majors": [], "languages": [], "language_level": [], "hard_skills": ["sap", "maintenance", "management reports", "ms excel", "exchange"], "soft_skills": ["independently", "attentive to details", "responsible", "team-player", "interpersonal", "timely", "interested in", "communication", "positive working attitude", "presentation skills", "organisational skills", "well-organised", "energetic", "fast learner", "driven"], "languages_combined": []}, "experience_required": {"duration": ["minimum of 1 year"], "field": []}}, {"job_id": "100003009054339", "location_code": "hk", "company": "YKK Hong Kong Limited", "job_title": "Associate Planning & Operation Executive", "description": "Job Descriptions:\n\nResponsible for purchasing & operation activities from business contracts, sourcing, price negotiation, orders, shipment;\n\nCollaborate with sales team and liaise with suppliers to drive on time shipment delivery;\nLiaise and support post-contract management activities like handling deliveries discrepancies and monitoring supplier performance;\nHandle full set of shipping I/E documents, liaise with supplier and forwarders for shipment schedule and arrangement;\nPrepare regular reporting and conduct analysis to support business decisions;\nAssist in other ad-hoc assignment as required.\n\nJob Requirements:\n\nDegree holder majoring in Purchasing, Supply Chain Management or other related subjects with at least 2 years related working experience, with background in purchasing field or manufacturing industry will be a plus;\n\nFluent in spoken and written English & Chinese (Cantonese and Mandarin);\nWell versed with PC applications, i.e. MS Word, Excel, PowerPoint & Chinese Word Processing;\nPatient, detailed-mind, willing to learn, able to work under pressure;\nWell-organized with good interpersonal and communication skills;\nCandidates with more experience will be considered as Planning & Operation Executive.\n\nBenefits:\n\n5-day work\u00a0(staggered working hours)\nDouble pay\nDiscretionary bonus\nGroup medical\nOT pay\nStatutory Annual Leave with extra\u00a07 days Company Annual Leave\nBank Holiday\nOther Special Leave i.e. Marriage Leave, etc.\n\nWe offer competitive remuneration and benefits, holidays, stable working environment to the right candidates. Interested parties please click \"Apply Now\" and send your full resume with expected salary in MS Word Format to us (Please quote Position Name & Reference No.)\n\n*All personal data collected will be kept strictly confidential and used for recruitment-related purpose only.", "employment_types": ["Full Time", "Permanent"], "selling_points": ["Degree in Purchasing / Supply Chain Management", "2 years exp.,Good command of English & Chinese", "5-day, 13-mth, discretionary bonus, extra leave"], "locations": ["Tsim Sha Tsui"], "categories": ["Transportation & Logistics", "Shipping", "Supply Chain", "Merchandising & Purchasing", "Textiles"], "post_time": "2022-01-17T09:12:06Z", "salary": {"currency": null, "max": null, "min": null, "period": "monthly", "term": null}, "salary_visible": false, "title_keywords": ["associate", "operation executive"], "responsibilities": ["collaborate with", "liaise", "price negotiation", "shipping", "reporting", "ad-hoc", "contracts", "analysis", "monitoring", "contract management", "support business decisions", "sales team", "schedule", "liaise with", "liaise with suppliers"], "requirements": {"degrees": ["degree holder"], "majors": ["manufacturing"], "languages": ["cantonese", "english", "chinese", "mandarin"], "language_level": ["fluent"], "hard_skills": ["excel", "plus", "chinese word processing", "powerpoint", "pc applications", "ms word"], "soft_skills": ["communication skills", "willing to learn", "well-organized", "detailed", "patient", "interpersonal", "work under pressure"], "languages_combined": [{"language": "cantonese", "language_level": ["fluent"]}, {"language": "english", "language_level": ["fluent"]}, {"language": "chinese", "language_level": ["fluent"]}, {"language": "mandarin", "language_level": ["fluent"]}]}, "experience_required": {"duration": ["at least 2 years"], "field": ["management", "purchasing", "supply chain", "related", "operation", "manufacturing industry", "planning"]}}, {"job_id": "100003009054015", "location_code": "hk", "company": "American Phil Textiles Ltd", "job_title": "Purchasing Clerk / Senior Purchasing Clerk / Assistant Purchasing Supervisor (Garment)", "description": "Purchasing Clerk / Senior Purchasing Clerk /\nAssistant Purchasing Supervisor\n\nResponsibilities:\n\nMaterials sourcing and purchasing\nPrepare and issue purchase orders\nFollow up and monitor the delivery schedules with suppliers and factories to meet production plan\nData input for the daily system operation\u00a0\nPerform clerical support to department\n\n\u00a0Qualifications and Requirements:\n\nForm 5 / DSE or above\u00a0\nAt least 2 years related working experience\nWell organized, detail-minded, initiative, willing to learn and able to work under pressure\nProficient in MS Excel, experience in using ERP system is preferable\nGood command of written and spoken English and Mandarin\nCandidates with more experience will be considered as Senior Purchasing Clerk / Assistant Purchasing Supervisor\nImmediate available\u00a0\n\nWe offer\u00a05-day work, Double Pay\u00a0and\u00a0attractive remuneration packages\u00a0to the right candidate.\u00a0 Interested candidates please e-mail full resume\u00a0with expected salary to\u00a0Personnel Section\u00a0by clicking \"Apply Now\".\n\nAll data supplied will be kept in strict confidence and only for employment related purpose. Those not invited for an interview within 6 weeks may consider their applications unsuccessful and personal data provided will be destroyed", "employment_types": ["Full Time", "Permanent"], "selling_points": ["Garment materials procurement, purchasing orders", "Follow up and monitor the delivery schedules", "5 days work, Medical & Dental Insurance, ERP"], "locations": ["Cheung Sha Wan"], "categories": ["Merchandising & Purchasing", "Woven / Knit", "Textiles", "Procurement / Purchasing / Sourcing"], "post_time": "2022-01-17T09:04:24Z", "salary": {"currency": null, "max": null, "min": null, "period": "monthly", "term": null}, "salary_visible": false, "title_keywords": ["supervisor", "senior purchasing clerk", "purchasing clerk", "assistant"], "responsibilities": ["schedules", "monitor", "data input", "clerical support", "purchase", "plan"], "requirements": {"degrees": ["form 5", "dse"], "majors": [], "languages": ["english", "mandarin"], "language_level": ["good command"], "hard_skills": ["ms excel", "erp system"], "soft_skills": ["detail-minded", "willing to learn", "well organized", "initiative", "work under pressure"], "languages_combined": [{"language": "english", "language_level": ["good command"]}, {"language": "mandarin", "language_level": ["good command"]}]}, "experience_required": {"duration": ["at least 2 years"], "field": ["related", "erp system", "purchasing"]}}, {"job_id": "100003009054158", "location_code": "hk", "company": "AMERICAN EAGLE OUTFITTERS ASIA LTD", "job_title": "Fabric Merchandiser", "description": "Key Responsibilities:\n\n\nResponsible for mill\u2019s management, fabric development and cost control\nAssist Fabric Manager in fabric & wash development\nConduct new fabric development & evaluation, including participate in fabric shows and research new fabrications, techniques and finishes\nCoordinate with US fabric team to align on seasonal development plans\nProvide mills with idea and assistant for new development and ensure mills use correct technique to meet quality requirement\nMaintain daily communication with mills and internal counter parts\nElaborate testing protocol to mills and guide them thru American Eagle quality standard\nEvaluate fabrics and callout potential quality & delivery issue to US fabric team when needed\nManage signed off fabric library, and manage seasonal sample yardages Update and report seasonal adoption rate to manager\nVisit fabric mills to update latest production technology, follow up sample and bulk quality etc\nStay focus at proper mill to provide best cost option\nNegotiate with mill according to HK sourcing & US production cost control guidelines\nDevelop strong connection with US cross functional teams\nOther projects and responsibilities as assigned\n\nRequirements:\n\nDiploma or Degree in Textile Science or related disciplines is preferred\nMinimum 3-year experience of fabric development with proven track record\nTechnical knowledge of yarns, fabrics, dyeing, printing and finish processes is needed\nAbility to facilitate effective communication internally and externally\nFirm understanding of global fabric sourcing, especially mill base in Asia with advance knowledge of raw material, fabric & finishing process or other variables driving cost\nGood communication and organizational skills\n\n\nTo apply, please email your full resume (as an attachment) together with your latest and expected package to us by clicking 'Apply Now'.\n\nAEO is Equal Opportunity Employer. All personal information received from applications will be kept confidential and used for employment-related purpose only.\n", "employment_types": ["Full Time", "Permanent"], "selling_points": ["Work From Home policy", "Friendly and casual culture", "Multi national company"], "locations": ["Kwai Fong"], "categories": ["Merchandising & Purchasing", "Fabrics", "Woven / Knit", "Textiles"], "post_time": "2022-01-17T08:37:04Z", "salary": {"currency": null, "max": null, "min": null, "period": "monthly", "term": null}, "salary_visible": false, "title_keywords": ["fabric merchandiser"], "responsibilities": ["management", "cost", "guidelines", "coordinate with", "quality", "teams", "testing", "communication", "evaluate", "develop", "maintain", "cost control", "evaluation", "plans", "report"], "requirements": {"degrees": ["diploma", "degree"], "majors": ["related disciplines", "science"], "languages": [], "language_level": [], "hard_skills": [], "soft_skills": ["communication", "organizational skills"], "languages_combined": []}, "experience_required": {"duration": ["minimum 3-year"], "field": ["development"]}}, {"job_id": "100003009051872", "location_code": "hk", "company": "LAWSGROUP", "job_title": "Merchandiser / Assistant Merchandiser, Cut & Sewn Knit", "description": "Job Responsibilities:\n\n\nManage and follow up with production line to ensure the product quality\nAssist to analyze quarterly forecast align with merchandising strategies\nLiaise with internal and external customers to keep tracking the product development\nRetrieve and facilitate problem solution when necessaries\nAssist to prepare material for\u00a0price negotiation\n\nJob Requirements:\n\nDiploma\u00a0graduate in Textile / Clothing or related discipline\nMinimum\u00a02 years\u2019 solid experience in\u00a0cut & sewn\u00a0merchandising , preferably in U.S. market\nWith factory background is an advantage\nStrong leadership, energetic & dynamic\nGood command of written and spoken English and Chinese including Putonghua\nWeekly Travel\u00a0to Zhuhai office is required\nCandidate with less experience will be considered as Assistant Merchandiser\n\nWe\u00a0offer\u00a0attractive remuneration package to the right candidate. Interested parties please click the \"APPLY NOW\" button below and send your application together with a detailed resume including current & expected salary and availability to Human Resources Department.\n\nCompany website:\u00a0https://www.lawsgroup.com\n\n(Data collected will be treated in strict confidence and used for recruitment purpose only)", "employment_types": ["Full Time", "Permanent"], "selling_points": ["Min. 2 yrs  exp in cut & sewn merchandising", "Manage and follow up with production line", "Excellent career development exposure"], "locations": ["Others - China"], "categories": ["Manufacturing", "Garment / Textile", "Merchandising & Purchasing", "Woven / Knit", "Textiles"], "post_time": "2022-01-17T01:25:49Z", "salary": {"currency": null, "max": null, "min": null, "period": "monthly", "term": null}, "salary_visible": false, "title_keywords": ["merchandiser", "assistant merchandiser"], "responsibilities": ["internal and external customers", "price negotiation", "merchandising", "quality", "forecast", "liaise with", "tracking"], "requirements": {"degrees": ["diploma"], "majors": [], "languages": ["putonghua", "english", "chinese"], "language_level": ["good command"], "hard_skills": ["dynamic"], "soft_skills": ["dynamic", "energetic", "leadership"], "languages_combined": [{"language": "putonghua", "language_level": ["good command"]}, {"language": "english", "language_level": ["good command"]}, {"language": "chinese", "language_level": ["good command"]}]}, "experience_required": {"duration": ["minimum 2 years"], "field": ["merchandising"]}}, {"job_id": "100003009053945", "location_code": "hk", "company": "MGA Entertainment (H.K.) Ltd", "job_title": "Senior Project Engineer", "description": "Higher diploma or university graduate in textile/merchandising/fashion design/garment\nMinimum 3-5 years\u2019 hands-on experience in\u00a0design, material sourcing and fabric development, preferably with strong project coordination experience\nKnowledge of plastic resin, fabric material, tooling and mechanical design in toys and consumer products is an added advantage\nProficient in written and spoken English\n\nInterested parties with relevant experience and qualification, please send detailed resume and expected salary to HR Department, MGA Entertainment, Suite 301, 3/F., Chinachem Golden Plaza, No. 77 Mody Road, Tsimshatsui, Kowloon or via email.\n\n(All information collected is used for recruitment purpose only)\n", "employment_types": ["Full Time", "Permanent"], "selling_points": [], "locations": ["Tsim Sha Tsui"], "categories": ["Engineering", "Engineering Project Management", "Merchandising & Purchasing", "Fabrics", "Textiles"], "post_time": "2022-01-17T07:48:47Z", "salary": {"currency": null, "max": null, "min": null, "period": "monthly", "term": null}, "salary_visible": false, "title_keywords": ["senior project engineer"], "responsibilities": ["mechanical design", "merchandising", "design", "project coordination"], "requirements": {"degrees": ["university graduate", "diploma"], "majors": ["design"], "languages": ["english"], "language_level": ["proficient"], "hard_skills": [], "soft_skills": ["hands-on", "coordination"], "languages_combined": [{"language": "english", "language_level": ["proficient"]}]}, "experience_required": {"duration": ["minimum 3-5 years"], "field": ["development", "design"]}}, {"job_id": "100003009055316", "location_code": "hk", "company": "Spring Professional (Hong Kong) Limited", "job_title": "Sourcing and Production Lead for a Fashion e-Commerce Platform", "description": "Sourcing and Production Lead for a Fashion e-Commerce Platform\n\nGrate opportunity with a Start-up Fashion Brand\u00a0\nSourcing with Innovative in textile and garment manufacturing\nRemote Working, and Able to be Fully Work from Home\u00a0\n\n\n\nAbout Our Client:\nOur Client is an innovative Fashion e-Commerce Platform and they are looking for experience candidate who can join their Sourcing team to develop a better strategy on their new Supplier on latest product.\u00a0\n\nResponsibilities:\n\nConduct sourcing activities in line with business needs, by recommending, source and e-source commodities suppliers, materials, and manufacturers.\nUtilizes category-based technical knowledge to achieve sourcing objectives at an efficient level, imparting knowledge to cross-functional stakeholders and partners.\nResponsibility for the onboarding process, ensuring all proposed suppliers meet the needs of the business.\nRegulate commodities supplier negotiations, including and not limited to material planning, development and BOM coordination.\nReview supplier audits and conduct on-ground inspections to ensure sustainability and ethical compliance standards are met.\nEnsure all fabrications meet required performance attributes, testing requirements and sustainability requirements.\nSet up sourcing and production calendar with timelines based on targeted launch, supplemented with active tracking and milestones check-in with key stakeholders.\nTrack and manage the pre-production to production schedule, diligently updating to maintain an organized and accurate production schedule\n\nRequirements:\n\nTertiary education / Diploma holder in textiles / garment / business, or related disciplines.\n5+ years of experience in sourcing, production or product development\nExcellent Bilingual Skills\nExperience working with a diverse range of stakeholders or are a natural excellent\nMust have a strong knowledge or interest in raw material process as well as\nNot be afraid to change the plan of execution whenever required\nKnowledge of garment construction, fit, and finishing", "employment_types": ["Full Time"], "selling_points": ["e-Commerce", "Innovative in textile and garment manufacturing", "Remote Working"], "locations": ["Others"], "categories": ["Merchandising & Purchasing", "Textiles"], "post_time": "2022-01-18T02:10:16Z", "salary": {"currency": null, "max": null, "min": null, "period": "monthly", "term": null}, "salary_visible": false, "title_keywords": ["lead"], "responsibilities": ["tracking", "compliance", "review", "testing", "maintain", "schedule", "coordination", "audits", "pre-production", "planning"], "requirements": {"degrees": ["diploma holder"], "majors": ["related disciplines", "business"], "languages": [], "language_level": [], "hard_skills": [], "soft_skills": ["diverse"], "languages_combined": []}, "experience_required": {"duration": ["5+ years"], "field": ["product development"]}}, {"job_id": "100003009049947", "location_code": "hk", "company": "Prym Fashion Asia Pacific Limited", "job_title": "Customer Service Executive", "description": "Job Description\u00a0\n\nResponsible for order follow up, sampling\u00a0and liaise closely with various departments to ensure the smooth completion of the order\nHandle customers' inquiries and complaints\nLiaise closely with the sales department and provide comprehensive support\nPerform ad hoc duties when required\n\nJob Requirement\u00a0\n\nF.5/ DSE or above\n2+ years customer service experience in garment accessories field\u00a0field (especially Plastic / Metal Trims) is absolutely an advantage\nGood command of English & Mandarin\nSelf-motivated with positive working attitude\nMature & responsible, good interpersonal skills\nGood PC Knowledge & communication skill\nImmediately available preferred\n\nWe offer attractive benefit package including\n\n5 days work\nDiscretionary Bonus\nMedical coverage\nHospital Insurance\nGroup Life Assurance\n\nWorking Location:\n\nTai Wai\n\nInterested Parties, Please send full resume with contact telephone number, present and expected salary to the Human Resources Department by \"Apply Now\"\u00a0\n\nAll Personal data collected will be used for recruitment purpose only.", "employment_types": ["Full Time", "Permanent"], "selling_points": [], "locations": ["Shatin Area"], "categories": ["Sales, CS & Business Devpt", "Customer Service - Supervisor / Officer", "Merchandising & Purchasing", "Textiles", "Sales Administration"], "post_time": "2022-01-14T09:29:34Z", "salary": {"currency": null, "max": null, "min": null, "period": "monthly", "term": null}, "salary_visible": false, "title_keywords": ["customer service executive"], "responsibilities": ["liaise", "customers' inquiries", "ad hoc duties"], "requirements": {"degrees": ["dse"], "majors": [], "languages": ["english", "mandarin"], "language_level": ["good command"], "hard_skills": ["pc knowledge"], "soft_skills": ["self-motivated", "responsible", "communication skill", "mature", "positive working attitude", "customer service", "interpersonal skills"], "languages_combined": [{"language": "english", "language_level": ["good command"]}, {"language": "mandarin", "language_level": ["good command"]}]}, "experience_required": {"duration": ["2+ years"], "field": ["garment", "customer service"]}}, {"job_id": "100003009054817", "location_code": "hk", "company": "Victoria\u2019s Secret", "job_title": "Technologist, Raw Materials", "description": "PURPOSE/GENERAL SUMMARY:\n\nSupport the end to end process of all raw material components of lingerie and/or apparel products from development to production including quality assurance, risk assessment to assure final product quality.\n\nPRINCIPAL DUTIES & RESPONSIBILITIES:\n\nSupport sourcing and developments of all raw material components including specification set up, physical performance validation, quality approval, color and print approval for lingerie and/or apparel products to meet the design\u2019s expectation\nMaintain internal systems for record update after raw material approval, lab dips/print development approval and bulk submission approval.\u00a0Data entry/ system input/ simple data drawing with analysis from FlexPLM and shared drive.\nCoordinate with mills to gather information on raw material production lead time and machine capacity for analysis and planning\nApply effective systems of Quality Management and regulatory standards, both internally and with vendors to support the fabric and color development process and assure final product quality\nSupport mills\u2019 evaluation, onboarding and calibration to ensure their capabilities meet the business expectations\nSupport bulk management, e.g. color management, physical performance, quality check and problem solving\nTake control of the submissions with responsibility for the interpretation and communication of all departmental laboratory testing\nFollow the business calendar timeline to assure the operations on track\n\n\n\nREQUIREMENTS:\n\nBachelor\u2019s degree holder of Technical Education in Textile Science or equivalent\n3-5 years of related experience in synthetic fabric, lace and embroidery products, print and color development in related product category(-ies), as well as in quality assurance in textile industry\nGood command of written and spoken English and Chinese\nGood command of computer skills.\u00a0Experience in FlexPLM system is highly preferable\nProactive and willing to learn\n\nCandidates not invited for interview within 8 weeks may consider their applications unsuccessful. All personal information will be treated as confidential and be used for recruitment purposes only.", "employment_types": ["Full Time", "Permanent"], "selling_points": ["Fabric technical development", "Lace/embroidery/intimate experience is a plus", "5 days' work week; flexible work model"], "locations": ["Kowloon Bay"], "categories": ["Manufacturing", "Garment / Textile", "Merchandising & Purchasing", "Fabrics", "Textiles"], "post_time": "2022-01-17T11:21:35Z", "salary": {"currency": null, "max": null, "min": null, "period": "monthly", "term": null}, "salary_visible": false, "title_keywords": [], "responsibilities": ["management", "quality check", "control", "data entry", "data", "operations", "analysis", "systems", "quality", "coordinate with", "design", "testing", "communication", "maintain", "system input", "evaluation", "internal systems", "planning"], "requirements": {"degrees": ["bachelor", "degree holder"], "majors": ["science"], "languages": ["english", "chinese"], "language_level": ["good command"], "hard_skills": ["computer skills"], "soft_skills": ["proactive", "willing to learn"], "languages_combined": [{"language": "english", "language_level": ["good command"]}, {"language": "chinese", "language_level": ["good command"]}]}, "experience_required": {"duration": ["3-5 years"], "field": ["related", "development", "print", "textile", "quality assurance"]}}, {"job_id": "100003009053359", "location_code": "hk", "company": "Pasona Asia Co., Limited", "job_title": "Japanese Speaking Assistant Merchandiser (Multinational Corporation, Welcome Fresh Graduates)", "description": "Our client, a reputable multinational garment firm, is seeking for a Japanese speaking Merchandiser to join their team in Hong Kong.\n\n\u00a0Responsibilities:\n\nHandle clients\u2019 orders from product development, sampling, production orders to delivery\nPerform quality inspection at the factory\nWork closely with vendors for issues settlement during production process\nMaintain and update production records and system data\nAssist in any ad hoc projects assigned by supervisor\n\n\u00a0Requirements:\n\nDiploma or above\n1-2 years\u2019 relevant experience in garment/ textile industry is preferred\nProficiency in spoken and written English and Mandarin. Business level in Japanese (JLPT Level 2 or above)\nSound knowledge in PC operations\nGood interpersonal and communication skills, well-organized, patient, self-initiative\nBusiness travel is required (China and Asia Pacific)\nImmediate available is preferred\nCandidates with more relevant experience, especially in Japanese apparel market, will be considered as Merchandiser\n\n\u00a0**Data collected will be used for recruitment purpose only**\n\u00a0**Interested parties please send resume in \"ENGLISH\" with CURRENT & EXPECTED salary and DATE OF AVAILABILITY or WhatsApp us at 9320 3296 for details**", "employment_types": ["Full Time", "Permanent"], "selling_points": ["Support daily merchandising duties", "Eager to work in fast paced environment", "More experience will be considered as Merchandiser"], "locations": ["Tsim Sha Tsui"], "categories": ["Merchandising & Purchasing", "Fabrics", "Textiles", "Others"], "post_time": "2022-01-17T06:51:05Z", "salary": {"currency": null, "max": null, "min": null, "period": "monthly", "term": null}, "salary_visible": false, "title_keywords": ["assistant merchandiser"], "responsibilities": ["production process", "quality", "system data", "inspection", "maintain", "ad hoc projects"], "requirements": {"degrees": ["diploma or above"], "majors": [], "languages": ["japanese", "english", "mandarin"], "language_level": ["proficiency"], "hard_skills": ["pc operations"], "soft_skills": ["communication skills", "well-organized", "self-initiative", "patient", "interpersonal"], "languages_combined": [{"language": "japanese", "language_level": []}, {"language": "english", "language_level": ["proficiency"]}, {"language": "mandarin", "language_level": ["proficiency"]}]}, "experience_required": {"duration": ["1-2 years"], "field": ["garment", "relevant experience", "textile"]}}, {"job_id": "100003009052626", "location_code": "hk", "company": "Morgan Philips Hong Kong Limited", "job_title": "Senior Merchandiser - Apparel (Woven)", "description": "My client is an US Buying Office with 200+ staff in Hong Kong. As of business expansion, they are now recruiting a Senior Merchandiser to join their team.\u00a0\n\n\n\nJob Duties :\n\n\nManage development to bulk production process\nWork with garment factories to achieve best prices\nWork to ensure a seamless co-ordination with internal colleagues related to development issues\nMonitor suppliers and the production market to update market situation.\nPartner with local and overseas technical teams to ensure Brand requirements are met\nReview tech packs and samples with fit tech to ensure the product requirements are followed\nLiaison with Fabric team to ensure on-time submission of quality and obtain approval\nEnsure clear and timeliness of the communication with all the counterparts\nProvide updated market information to customers in respect of style, fabrics, delivery etc.\nProvide information of competitors\u2019 activities within ability to access the market.\n\nRequirements:\u00a0\n\n\nCollege degree or equivalent work experience\n6-10 years related work experience in sourcing and production\nStrong technical knowledge in woven/knit/sweater\nDetail-oriented, strong planning and coordination skills\nExcellent verbal and written communication skills\u00a0\nAbility to work well within a team environment", "employment_types": ["Full Time", "Permanent"], "selling_points": ["An US Company", "Manage End to End PD to Production Cycle", "Woven & Knit"], "locations": ["Not Specified"], "categories": ["Manufacturing", "Product Development / Management", "Merchandising & Purchasing", "Woven / Knit", "Textiles"], "post_time": "2022-01-17T03:35:46Z", "salary": {"currency": null, "max": null, "min": null, "period": "monthly", "term": null}, "salary_visible": false, "title_keywords": ["senior merchandiser"], "responsibilities": ["market information", "production process", "review", "quality", "monitor", "teams", "communication"], "requirements": {"degrees": ["degree"], "majors": [], "languages": [], "language_level": [], "hard_skills": [], "soft_skills": ["communication skills", "coordination skills", "detail-oriented"], "languages_combined": []}, "experience_required": {"duration": ["6-10 years"], "field": ["related"]}}, {"job_id": "100003009054818", "location_code": "hk", "company": "Victoria\u2019s Secret", "job_title": "Technologist, Raw Materials / Colorist (6 months contract)", "description": "PURPOSE/GENERAL SUMMARY:\n\nSupport the end to end process of all raw material components of lingerie and/or apparel products from development to production including quality assurance, risk assessment to assure final product quality.\n\nPRINCIPAL DUTIES & RESPONSIBILITIES:\n\nSupport sourcing and developments of all raw material components including color and print for lingerie and/or apparel products to meet the design\u2019s expectation\nMaintain internal systems for record update after raw material approval, lab dips/print development approval and bulk submission approval.\u00a0Data entry/ system input/ simple data drawing with analysis from FlexPLM and shared drive.\nSupport bulk management, e.g. color management, physical performance and quality check\nApply effective systems of Quality Management and regulatory standards, both internally and with vendors to support the fabric and color development process and assure final product quality\nCoordinate with mills to gather information on raw material production lead time and machine capacity for analysis and planning\nSupport mills\u2019 evaluation, onboarding and calibration to ensure their capabilities meet the business expectations\nTake control of the submissions with responsibility for the interpretation and communication of all departmental laboratory testing\nFollow the business calendar timeline to assure the operations on track\n\nREQUIREMENTS:\n\nBachelor Degree holder of Technical Education in Textile Science or equivalent\n3-5 years of related experience in fabric, print and color development in related product category(-ies), as well as in quality assurance in textile industry\nGood command of written and spoken English and Chinese\nGood command of computer skills.\u00a0Experience in FlexPLM system is highly preferable\nProactive and willing to learn\n\nCandidates not invited for interview within 8 weeks may consider their applications unsuccessful. All personal information will be treated as confidential and be used for recruitment purposes only.", "employment_types": ["Temporary", "Contract"], "selling_points": ["6 months renewable contract", "fabric development and color approval", "5 days work week; flexible work hours"], "locations": ["Kowloon Bay"], "categories": ["Manufacturing", "Garment / Textile", "Merchandising & Purchasing", "Fabrics", "Textiles"], "post_time": "2022-01-17T11:21:36Z", "salary": {"currency": null, "max": null, "min": null, "period": "monthly", "term": null}, "salary_visible": false, "title_keywords": [], "responsibilities": ["management", "quality check", "control", "data entry", "data", "operations", "analysis", "systems", "quality", "coordinate with", "design", "testing", "communication", "maintain", "system input", "evaluation", "internal systems", "planning"], "requirements": {"degrees": ["bachelor degree holder"], "majors": ["science"], "languages": ["english", "chinese"], "language_level": ["good command"], "hard_skills": ["computer skills"], "soft_skills": ["proactive", "willing to learn"], "languages_combined": [{"language": "english", "language_level": ["good command"]}, {"language": "chinese", "language_level": ["good command"]}]}, "experience_required": {"duration": ["3-5 years"], "field": ["related", "development", "print", "textile", "quality assurance"]}}, {"job_id": "100003009049254", "location_code": "hk", "company": "Pacific Textiles Ltd", "job_title": "MERCHANDISING TRAINEES", "description": "Requirements :\n\nUniversity graduate or above, preferably in Textiles or related discipline, but is not mandatory.\u00a0\n1-year experience in Textiles field and working experience in PRC is definitely advantage. \u00a0Fresh graduates will also be considered.\nWilling to travel\u00a0to our Guangzhou Nansha location for 2-3 days on weekly basis.\nWilling to learn, self-motivated & able to work under pressure\nExcellent written & spoken\u00a0English, Mandarin proficiency is an advantage.\nStrong communication & interpersonal skills are required\nImmediate available is preferable\n\n\u00a0Job Responsibilities :\n\nProviding full support to merchandising team on sample and orders follow-up work\nWorking closely with factories and production team to ensure the quality and on-time delivery\n\n\u00a0We offer :\n\nPre-job and on-job training program\nAttractive remuneration package to the right candidate\nBroader work exposure at GBA\n\nInterested parties please send your full resume with expected salary and availability by clicking \"Apply Now\" .\u00a0Personal date provided by job applicants will be used strictly for recruitment related purpose. Those applications do not receive any response from us in 4 weeks may be considered as unsuccessful and their personal data will be destroyed in one month after the vacancy is filled up.", "employment_types": ["Full Time", "Permanent"], "selling_points": [], "locations": ["Kwai Hing"], "categories": ["Merchandising & Purchasing", "Woven / Knit", "Textiles", "Others", "Student / Fresh Graduate / No Experience"], "post_time": "2022-01-14T08:19:42Z", "salary": {"currency": "HKD", "max": 16999, "min": 14000, "period": "monthly", "term": null}, "salary_visible": true, "title_keywords": ["merchandising"], "responsibilities": ["quality", "merchandising"], "requirements": {"degrees": ["university graduate or above"], "majors": [], "languages": ["english", "mandarin"], "language_level": ["advantage", "excellent", "proficiency"], "hard_skills": [], "soft_skills": ["self-motivated", "willing to learn", "communication", "interpersonal skills", "work under pressure"], "languages_combined": [{"language": "english", "language_level": ["advantage", "excellent"]}, {"language": "mandarin", "language_level": ["proficiency", "excellent"]}]}, "experience_required": {"duration": ["1-year"], "field": []}}, {"job_id": "100003009045103", "location_code": "hk", "company": "Carter\u2019s Global Sourcing Limited", "job_title": "Assistant Merchandising Manager (Cut & Sewn Knits)", "description": "Drive cost negotiation with vendors, obtain the best cost from vendors to meet with due date and company goals\nCosting analyzes and provide cost saving options / suggestions to US\nAssist Senior Merchandising Manager to drive Sourcing Strategies, plan vendor and order allocation according to vendors\u2019 offered capacity, capability and cost analysis\nLead and deliver the assigned projects with punctual data in a timely manner\nPrepare new development for each buying season especially in Cut & Sewn items for baby / kids wear\nLead a small team of Merchandising activities mainly for Cut & Sewn items to achieve price, quality and product safety and deliver goals\nSupervise subordinates on product development, materials sourcing, sampling, order follow up and liaison with suppliers and manufacturers for daily operational issues to ensure on time delivery and quality.\nMaster, review and monitor status flow through data overview and analysis\n\nJob Requirement\n\nUniversity degree, preferably major in Apparel / Textile or related discipline\nAt least 10 years\u2019 work experience, minimum 2 years in a similar management capacity in buying / sourcing offices focused on USA and Canada markets in baby / kids wear\nComplete understanding of design, merchandising, and product development functions and able to lead the team to drive result\nStrong in managing vendor relationship with tight deadlines & challenging environment\nFamiliar with order processing system to leverage data for planning / analysis\nWell-organized, strong analytical and good problem-solving skills\nStrong leadership, interpersonal and negotiation skills\nProficient communication skills including written and spoken English & Mandarin\nStrong PC skills, like MS Excel (Pivot table, vlookup), word and outlook\nIn Carter's, we ensure to reward you with....\n\nComprehensive medical coverage including your spouse and children\n5-day work week and flexible working hours\nVoluntary MPF Scheme and various trainings for both soft and hard skills\nCareer development opportunities, U.S. friendly and open-minded culture\nInterested parties please send your application and resume, stating\u00a0Current, Expected\u00a0Salary\u00a0&\u00a0Availability\u00a0by click to\u00a0APPLY NOW. We offer competitive remuneration package with excellent career prospect to the successful candidate. We regret that only short-listed candidates will be notified. Information collected will be used for recruitment purpose only.", "employment_types": ["Full Time", "Permanent"], "selling_points": ["10+ years experience in Soucing & Merchandisng", "2 years of managerial experience", "Cut & Sewn Knits items for baby / kids wear in US"], "locations": ["Ngau Tau Kok"], "categories": ["Merchandising & Purchasing", "Woven / Knit", "Textiles", "Procurement / Purchasing / Sourcing"], "post_time": "2022-01-13T07:10:15Z", "salary": {"currency": null, "max": null, "min": null, "period": "monthly", "term": null}, "salary_visible": false, "title_keywords": ["merchandising manager", "assistant"], "responsibilities": ["data", "merchandising", "quality", "design", "communication", "plan", "monitor", "cost", "management", "mpf", "review", "career development", "cost analysis", "lead a small team", "analysis", "a timely manner", "ensure on time delivery", "order processing", "planning"], "requirements": {"degrees": ["university degree", "master"], "majors": [], "languages": ["english", "mandarin"], "language_level": ["proficient"], "hard_skills": ["small", "analysis", "pivot table", "vendor", "word", "scheme", "ms excel", "outlook", "order processing", "problem-solving skills", "vlookup", "pc skills"], "soft_skills": ["flexible", "communication skills", "negotiation", "focused", "open-minded", "timely", "well-organized", "negotiation skills", "comprehensive", "friendly", "problem-solving skills", "leadership", "interpersonal"], "languages_combined": [{"language": "english", "language_level": ["proficient"]}, {"language": "mandarin", "language_level": ["proficient"]}]}, "experience_required": {"duration": ["at least 10 years", "minimum 2 years"], "field": ["management"]}}, {"job_id": "100003009043196", "location_code": "hk", "company": "I.T Apparels Limited", "job_title": "Assistant Buyer - Womenwear (REF:JDB-IT-ABM)", "description": "Accountabilities \u2013 Key Result Areas\n\nPrepare OTB, seasonal and annual buying plans based on a thorough understanding of consumer, market trends and company business objectives\nMonitor closely on OTB, control sales and inventory to achieve seasonal sales and profit targets based on the seasonal business plan\nDetermine buying guides and assortment strategy in order to obtain a seasonal target\nOversee inventory costs, sales forecast, gross profit margin to achieve sales and profit targets\nFormulate pricing strategies based on competitive analysis, market reviews, competitor positions, and financials, etc.\nEvaluate ongoing performance and takes actions as appropriate\n\nExperience / Qualification Requirements\n\nDegree holder in Fashion & Textiles or business discipline\nWith at least 1 years of experience in\u00a0buying and merchandising, preferably in the fashion/lifestyle/retail industry\nProactive, sensitive to figures and strong analytical and negotiation skills\nExcellent product sensibility and understanding of competitive retail landscape\nAttention to detail with a high level of accuracy\nHands-on analytical skills in MS Excel and ERP systems in a sizable corporation\n\nCompetitive remuneration and benefits package will be offered to the right candidate. Please submit your application by clicking \"Apply Now\" below.\n\nAll data collected is for recruitment purposes only.\n\nSure you want to know more about our company and brands, simply follow our\n\nWEBSITE at http://www.ithk.com\u00a0 \u00a0 \u00a0 \u00a0 \u00a0 \u00a0 \u00a0 \u00a0 \u00a0 \u00a0 \u00a0 \u00a0 \u00a0 \u00a0 \u00a0 \u00a0 \u00a0 \u00a0 \u00a0 \u00a0 \u00a0 \u00a0 \u00a0 \u00a0 \u00a0 \u00a0 \u00a0 \u00a0 \u00a0 \u00a0 \u00a0 \u00a0 \u00a0 \u00a0\u00a0\nFACEBOOK at\u00a0http://www.facebook.com/I.Ttheofficialpage\u00a0 \u00a0 \u00a0 \u00a0 \u00a0 \u00a0 \u00a0 \u00a0 \u00a0\nINSTAGRAM at http://instagram.com/ithk\u00a0 \u00a0 \u00a0 \u00a0 \u00a0 \u00a0 \u00a0 \u00a0 \u00a0 \u00a0 \u00a0 \u00a0 \u00a0 \u00a0 \u00a0 \u00a0 \u00a0 \u00a0 \u00a0 \u00a0 \u00a0 \u00a0 \u00a0 \u00a0 \u00a0 \u00a0 \u00a0 \u00a0\nWEIBO at\u00a0http://e.weibo.com/ithongkong", "employment_types": ["Full Time"], "selling_points": ["1 years' fashion buying experience", "Budget planning, sales planning and analysis", "Formulate pricing strategies"], "locations": ["Southern Area"], "categories": ["Merchandising & Purchasing", "Textiles", "Others", "Procurement / Purchasing / Sourcing"], "post_time": "2022-01-12T10:11:14Z", "salary": {"currency": null, "max": null, "min": null, "period": "monthly", "term": null}, "salary_visible": false, "title_keywords": ["assistant"], "responsibilities": ["control", "inventory", "analysis", "monitor", "merchandising", "systems", "otb", "evaluate", "forecast", "business plan", "plans", "costs"], "requirements": {"degrees": ["degree holder"], "majors": ["business"], "languages": [], "language_level": [], "hard_skills": ["erp systems", "analysis", "ms excel", "analytical skills"], "soft_skills": ["sensitive to figures", "analytical skills", "negotiation skills", "hands-on", "thorough", "attention to detail", "proactive"], "languages_combined": []}, "experience_required": {"duration": ["at least 1 years"], "field": ["retail industry", "merchandising"]}}, {"job_id": "100003009044452", "location_code": "hk", "company": "Newtimes Development Limited", "job_title": "Merchandiser (Woven's / Knit's wear)", "description": "Essential Duties & Responsibilities\n\nLiaise closely with internal counterparts of design, technical, QC and logistics for orders follow-up.\nExecute the T&A on time to ensure material on delivery to offshore factories for both production and sampling, close monitor bulk order follow up with correct quality and quantity.\nAssist the team superiors in the costing and quotation review.\nResponsible for system data entry, tech pack and BOM download.\nPrepare presentation for the buying trip including sample styles, price, supplier and factory information.\nEnsure that fabric/trims/proto/samples are developed to meet customer\u2019s requirements, adequate quotations are negotiated and obtained to achieve business objectives.\u00a0 Follow up on development.\n\nJob Requirements (Education / Experience / Skill-set)\n\nImmediately available is preferable.\nDiploma or above in Textile / Clothing or related discipline.\nAt least 2- 4 years\u2019 solid experience in the garment trading field.\nExperience in USA or Canada market is highly preferable.\nDetail-minded, strong accuracy with good problem-solving skills and able to meet various deadlines.\nStrong multi-tasking ability.\nA good team player with strong communication skills.\nGood command of both written and spoken English, Chinese including Mandarin.\nProficient in Microsoft Office \u2013 Word, Excel, Powerpoint, Outlook\n\nInterested parties please send your application with\u00a0current salary, expected salary and availability\u00a0via \u201cAPPLY NOW\u201d button.\n\n(Collected personal data will be kept strictly confidential and used for recruitment purpose only.)", "employment_types": ["Full Time", "Permanent"], "selling_points": ["Immediately available preferable", "US Clients served", "Focus on Woven or Knits"], "locations": ["Lai Chi Kok"], "categories": ["Manufacturing", "Garment / Textile", "Merchandising & Purchasing", "Woven / Knit", "Textiles"], "post_time": "2022-01-13T04:08:49Z", "salary": {"currency": null, "max": null, "min": null, "period": "monthly", "term": null}, "salary_visible": false, "title_keywords": ["merchandiser"], "responsibilities": ["liaise", "quotation", "quality", "monitor", "design", "review", "system data", "logistics"], "requirements": {"degrees": ["diploma or above"], "majors": [], "languages": ["english", "chinese", "mandarin"], "language_level": ["good command"], "hard_skills": ["excel", "microsoft office", "word", "powerpoint", "outlook", "problem-solving skills"], "soft_skills": ["detail-minded", "communication skills", "good team player", "multi-tasking", "problem-solving skills"], "languages_combined": [{"language": "english", "language_level": ["good command"]}, {"language": "chinese", "language_level": ["good command"]}, {"language": "mandarin", "language_level": ["good command"]}]}, "experience_required": {"duration": ["at least 2- 4 years"], "field": ["garment", "trading", "education"]}}, {"job_id": "100003009051226", "location_code": "hk", "company": "Easy Job Centre", "job_title": "Trims Merchandiser / Senior Trims Merchandiser (Garment Accessories / Packaging Products) (5 days)", "description": "Responsibilities:\n\nAssist the Purchasing Manager through inventory purchasing and stock control activities, e.g. issue purchase orders and documents follow up.\nKeep the inventory in a healthy level, monitor the replenishment needs and inbound logistics management.\nProcesses purchasing orders, records the purchases and maintains database in the system.\nPlan inventory based on sales trend and ordering lead time, strive for optimizing inventory value for the assigned items.\nPrepare analytical reports to optimize stock level. Monitor the inventory level and prepare stock forecasting.\nHandles incoming cargos including the arrangement of import licenses, daily cargo arrival and weekly cargo in-transit lists.\nCoordinates with freight forwarders and warehouse departments to have cargo delivered.\nWork closely with internal departments such as Customer Service, Sales, Quality, and the Warehouse team to keep track of inventory movement.\nTo keep close contact with vendors and suppliers and follow up outstanding PO. Evaluate and monitor suppliers\u2019 performance to ensure standards and schedules are meet.\nProvides an updated monthly stock list to departments of sales, customer services, management for Hong Kong and overseas offices.\nRequirements:\n\nHigher Diploma or above in Logistics / Supply Chain Management or related disciplines.\nWith 3 years solid working experience in Logistics, Purchasing and Supply Chain Management.\nSelf-motivated and able to work under pressure and tight schedules.\nGood command of both written and spoken Chinese and Mandarin.\nProficiency in MS Office, excellence in Excel.\nCandidate with more experience will be considered as Senior Purchasing Executive.\n\n\nWe offer an attractive remuneration package including 5-days work, medical scheme and bank holidays to the right candidate. If you aspired to an exciting and rewarding career, please send a full resume with the expected salary and available starting date by clicking \u201cAPPLY NOW\u201d to the Human\u00a0Resources Department.\n\nTo know more about us, please visit our website at www.chargeurs-pcc.com\n(Personal data collected will be kept confidential and used for recruitment purposes only.)", "employment_types": ["Full Time"], "selling_points": [], "locations": ["Yau Tsim Mong Area"], "categories": ["Manufacturing", "Garment / Textile", "Merchandising & Purchasing", "Textiles", "Procurement / Purchasing / Sourcing"], "post_time": "2022-01-15T05:19:57Z", "salary": {"currency": null, "max": null, "min": null, "period": "monthly", "term": null}, "salary_visible": false, "title_keywords": ["trims merchandiser", "senior trims merchandiser"], "responsibilities": ["control", "management", "import licenses", "schedules", "inventory", "monitor", "replenishment", "quality", "customer services", "evaluate", "purchase", "customer service", "logistics", "reports", "database", "plan", "contact", "forecasting"], "requirements": {"degrees": ["higher diploma or above"], "majors": ["related disciplines"], "languages": ["chinese", "mandarin"], "language_level": ["good command"], "hard_skills": ["excel", "ms office"], "soft_skills": ["self-motivated", "work under pressure"], "languages_combined": [{"language": "chinese", "language_level": ["good command"]}, {"language": "mandarin", "language_level": ["good command"]}]}, "experience_required": {"duration": ["3 years"], "field": ["purchasing", "supply chain", "management", "logistics"]}}, {"job_id": "100003009041475", "location_code": "hk", "company": "Triumph International Services (APAC) Limited", "job_title": "Assistant Merchandiser", "description": "Support factories and distribution centers in all phases of freight movement\nEnsure full set of compliant commercial documents submitted within the standards defined by vendor compliance program\nDesign and manage reports to ensure stakeholders are informed of status and issues\nHandle inspection request and tradelink declaration inquiry from Hong Kong Customs\nReview calendar and on-time delivery performance with freight forwarders and logistics service providers\nProvide feedback and training to factories & DCs\nIdentify issues and provide solutions / suggestions\n\nJob Requirement\n\nHigher diploma or above, preferably major in Logistics related discipline\n3-5 years\u2019 work experience in logistics-related field, preferably in apparel sourcing office or freight forwarder\nKnowledge of trade requirements in multiple countries\nFamiliarize with global shipping networks and procedures\nStrong communication skills including spoken and written English\nStrong computer skills (MS Word, Excel & Powerpoint\nIn Carter's, we ensure to reward you with....\n\nComprehensive medical coverage including your spouse and children\n5-day work week and flexible working hours\nVoluntary MPF Scheme and various trainings for both soft and hard skills\nCareer development opportunities, U.S. friendly and open-minded culture\nInterested parties please send your application and resume, stating\u00a0Current, Expected Salary\u00a0&\u00a0Availability\u00a0by click to\u00a0APPLY NOW. We offer competitive remuneration package with excellent career prospect to the successful candidate. We regret that only short-listed candidates will be notified. Information collected will be used for recruitment purpose only.", "employment_types": ["Full Time", "Permanent"], "selling_points": ["Follow up samples", "Dealing with purchasing/ suppliers", "Monitoring the data entrie"], "locations": ["Kowloon Bay"], "categories": ["Merchandising & Purchasing", "Textiles"], "post_time": "2022-01-12T04:35:11Z", "salary": {"currency": null, "max": null, "min": null, "period": "monthly", "term": null}, "salary_visible": false, "title_keywords": ["assistant merchandiser"], "responsibilities": ["shipping", "mpf", "compliance", "review", "procedures", "tradelink declaration", "design", "inspection", "provide solutions", "communication", "reports", "logistics", "career development"], "requirements": {"degrees": ["higher diploma or above"], "majors": [], "languages": ["english"], "language_level": [], "hard_skills": ["excel", "vendor", "powerpoint", "scheme", "computer skills", "ms word"], "soft_skills": ["flexible", "communication skills", "open-minded", "comprehensive", "friendly"], "languages_combined": [{"language": "english", "language_level": []}]}, "experience_required": {"duration": ["3-5 years"], "field": ["related", "logistics"]}}, {"job_id": "100003009044627", "location_code": "hk", "company": "Interlux Company Limited", "job_title": "Merchandiser", "description": "Our client is a global product sourcing company\n\nResponsibilities:\n\nTo develop existing regional sourcing partners and create synergy within business partners\nExperienced in Regional Sourcing (US/EU Markets), Global\u00a0Sourcing experience would be a plus\nMaintain a good relationship with customers to build the business\nPlay teamwork between Merchandising team and Logistics team to ensure a timely delivery\nExcellent communication and coordination skills with different parties\n\nRequirement:\n\nAt least 2 years relevant experience in Merchandising\nKnowledgeable of Sweater OR Home Textiles OR Digital & Electronic appliance\nFamiliar with US, Canada & EU markets and regional sourcing\nExcellent command of spoken and written Cantonese, Mandarin, and English\nLess experience will be considered as\u00a0Merchandiser/ Assistant\u00a0Merchandiser", "employment_types": ["Full Time"], "selling_points": ["Merchandiser", "Degree holder in Fashion and Textile", "Development opportunities"], "locations": ["Quarry Bay"], "categories": ["Merchandising & Purchasing", "Textiles"], "post_time": "2022-01-13T04:55:48Z", "salary": {"currency": null, "max": null, "min": null, "period": "monthly", "term": null}, "salary_visible": false, "title_keywords": ["merchandiser"], "responsibilities": ["merchandising", "develop", "good relationship", "communication", "maintain", "logistics", "coordination"], "requirements": {"degrees": [], "majors": [], "languages": ["cantonese", "english", "mandarin"], "language_level": ["excellent"], "hard_skills": [], "soft_skills": [], "languages_combined": [{"language": "cantonese", "language_level": ["excellent"]}, {"language": "english", "language_level": ["excellent"]}, {"language": "mandarin", "language_level": ["excellent"]}]}, "experience_required": {"duration": ["at least 2 years"], "field": ["merchandising", "relevant experience"]}}, {"job_id": "100003009051225", "location_code": "hk", "company": "Easy Job Centre", "job_title": "Fabric Merchandiser / Senior Fabric Merchandiser (5 days)", "description": "Form 5 or above;\n3-5 years working experience in garment accessories / packaging products field;\nTrims orders follow up / co-ordination with client and factory\nWell organized and good team player;\nGood communication & interpersonal skills;\nAble to communicate English and Mandarin\nLess experience candidates will also considered as Assistant Merchandiser\n\n\u00a0Interested parties, please send your resume with expected salary by clicking the below \"apply now\" button.\u00a0You can ask click on the website\u00a0www.easyjobhk.com\u00a0for more details about the company", "employment_types": ["Full Time"], "selling_points": [], "locations": ["Yau Tsim Mong Area"], "categories": ["Manufacturing", "Garment / Textile", "Merchandising & Purchasing", "Fabrics", "Textiles"], "post_time": "2022-01-15T05:19:57Z", "salary": {"currency": null, "max": null, "min": null, "period": "monthly", "term": null}, "salary_visible": false, "title_keywords": ["fabric merchandiser"], "responsibilities": ["communication"], "requirements": {"degrees": ["form 5 or above"], "majors": [], "languages": ["english", "mandarin"], "language_level": [], "hard_skills": [], "soft_skills": ["communication", "good team player", "well organized", "interpersonal skills"], "languages_combined": [{"language": "english", "language_level": []}, {"language": "mandarin", "language_level": []}]}, "experience_required": {"duration": ["3-5 years"], "field": ["garment"]}}, {"job_id": "100003009047068", "location_code": "hk", "company": "PCC Asia Limited", "job_title": "Purchasing Executive", "description": "Reporting to the Buyer, the incumbent will be responsible for:\n\nProviding clerical and administrative support to the buying team in an effective and timely manner\nRegular data entries and data maintenance in SAP & UK Buying tools\nAssisting in the preparation/ collation of weekly management reports\nSeasonal catalogue & price maintenance\nManaging stock allocation to all retail stores\nHandling administrative duties and responsible for ad hoc projects independently as required\nJob Requirements:\nDiploma holder with relevant experience is an added advantage\u00a0\nFresh graduate is also considered\nProficient in both Windows and MS Excel\nAttentive to details, good numerical sense and organisational skills\nSelf-driven, energetic, well-organised and able to play as a good team-player\nFast learner with positive working attitude\nExcellent communication, interpersonal and presentation skills\nSAP experience is an added advantage\n\n\n\nIf you are interested in this role, please send your full resume together with your current and expected salary to us via 'Apply Now'.\u00a0\n\nThe Human Resources Department (Interview Address)\u00a0\n\nUnit 1806B - 10, 18/F, Exchange Tower, 33 Wang Chiu Road, Kowloon Bay, Kowloon\n\nPersonal information received from applicants will be kept confidential and used for employment-related purpose only.", "employment_types": ["Full Time", "Permanent"], "selling_points": [], "locations": ["Kwun Tong"], "categories": ["Transportation & Logistics", "Supply Chain", "Merchandising & Purchasing", "Textiles", "Procurement / Purchasing / Sourcing"], "post_time": "2022-01-14T02:14:26Z", "salary": {"currency": null, "max": null, "min": null, "period": "monthly", "term": null}, "salary_visible": false, "title_keywords": ["purchasing executive"], "responsibilities": ["reporting", "maintenance", "data", "administrative support", "stock allocation", "communication", "management reports", "administrative duties", "ad hoc projects", "price maintenance", "catalogue"], "requirements": {"degrees": ["diploma holder", "fresh graduate"], "majors": [], "languages": [], "language_level": [], "hard_skills": ["sap", "maintenance", "management reports", "ms excel", "exchange"], "soft_skills": ["independently", "attentive to details", "responsible", "team-player", "interpersonal", "timely", "interested in", "communication", "positive working attitude", "presentation skills", "organisational skills", "well-organised", "energetic", "fast learner", "driven"], "languages_combined": []}, "experience_required": {"duration": [], "field": ["relevant experience"]}}, {"job_id": "100003009045724", "location_code": "hk", "company": "Carter\u2019s Global Sourcing Limited", "job_title": "Logistics Coordinator", "description": "Job Duties:\n\n- Follow up orders form\n\n- Sample development\n\n- Costing and production\n\n- Communicate with overseas customers\n\n- China & Bangladesh factories efficiently in daily business\n\nRequirements:\n\n- University graduate in Business/Marketing or related discipline\n\n- At least 5 years of merchandising experience related to garment manufacturing is preferable\n\n- CRM & order follow up\n\n- Event / exhibition organization\n\n- Good at research, presentable\n\n- Good command in spoken and written English & Mandarin\n\n- Computer literacy\n\n- Detail-minded, good business sense and good team player\n\n- Dynamic, out going and mature\n\n- Immediate available is preferred\n\n- Occasional business travel is required\n\n\n- Candidates with less experience will be considered as a position of Marketing Executive", "employment_types": ["Full Time"], "selling_points": ["Logistics", "US Sourcing", "Apparel"], "locations": ["Ngau Tau Kok"], "categories": ["Merchandising & Purchasing", "Textiles"], "post_time": "2022-01-13T08:26:59Z", "salary": {"currency": null, "max": null, "min": null, "period": "monthly", "term": null}, "salary_visible": false, "title_keywords": ["logistics coordinator"], "responsibilities": ["follow up orders", "communicate with"], "requirements": {"degrees": ["university graduate"], "majors": ["business", "marketing"], "languages": ["english", "mandarin"], "language_level": ["good command"], "hard_skills": ["dynamic"], "soft_skills": ["detail-minded", "good team player", "business sense", "mature", "presentable", "computer literacy", "dynamic"], "languages_combined": [{"language": "english", "language_level": ["good command"]}, {"language": "mandarin", "language_level": ["good command"]}]}, "experience_required": {"duration": ["at least 5 years"], "field": ["garment", "manufacturing", "related", "merchandising", "marketing"]}}, {"job_id": "100003009050210", "location_code": "hk", "company": "JFE Consulting Limited", "job_title": "Senior Merchandiser (Sweater / Home Textiles / Digital & Electronic appliance)", "description": "Triumph is one of the world\u2019s largest intimate apparel companies. It enjoys a presence in over 120 countries with the core brands Triumph\u00ae and sloggi\u00ae. Globally, the company serves 40,000 wholesale customers and sells its products in 4,050\u00a0controlled points of sale as well as via several own online shops. The Triumph Group is a member of the Business Social Compliance Initiative (BSCI).\n\nLearn more about Triumph on:\n\nwww.triumph.com\n\nwww.linkedin.com/company/triumph-international/\n\nOur Private Label Department in Hong Kong is looking immediately for a highly motivated\u00a0Assistant Merchandiser\n\nRoles & Responsibilities:\n\nFollow up samples (prototype/ colors/ wear test) with designs/ productions in order to meet with customer deadline.\nDealing with purchasing/ suppliers for on time materials orders to catch up samples deadline\nMonitoring the data entries to ensure the accuracy (items & qty) of order placement\nCommunicate the supplementary info to the customer, such as airway bill no. memo.\u00a0 \u00a0\n\nYour ideal profile:\n\n5 graduate +\nIdeally 1 year experience in Assistant Merchandiser in garment industry (fresh graduate also welcome)\u00a0\u00a0\n\nWe offer an opportunity in a fast paced organization which gives those looking for a challenge the possibility to grow with the company and shape the future.\n\nWe are a family owned company with strong values, operating at a global level with key markets in Germany, Japan and China - where our iconic brands, Sloggi and Triumph, continue to delight our consumers.\n\nTriumph Group is committed to employing a diverse workforce. Qualified applicants will receive consideration without regard to race, color, religion, sex, national origin, age, sexual orientation, gender identity, gender expression, veteran status, or disability.\u00a0\n\nIf you are seeking a great opportunity to develop your career, please send us your application letter and CV in English, diplomas and expected salary range by clicking on Apply.\u00a0", "employment_types": ["Full Time", "Permanent"], "selling_points": ["5-day work, attractive salary, medical insurance", "Global  sourcing company,5+Merchandising exp", "Sweater/Home Textiles/Digital&Electronic appliance"], "locations": ["Not Specified"], "categories": ["Merchandising & Purchasing", "Electronics", "Sweater", "Textiles"], "post_time": "2022-01-14T09:56:54Z", "salary": {"currency": null, "max": null, "min": null, "period": "monthly", "term": null}, "salary_visible": false, "title_keywords": ["senior merchandiser"], "responsibilities": ["memo", "data", "monitoring", "compliance", "develop"], "requirements": {"degrees": ["fresh graduate"], "majors": [], "languages": ["english"], "language_level": [], "hard_skills": ["garment industry", "no"], "soft_skills": ["committed", "diverse", "motivated", "controlled", "initiative", "ideal"], "languages_combined": [{"language": "english", "language_level": []}]}, "experience_required": {"duration": ["1 year"], "field": ["garment"]}}, {"job_id": "100003009035491", "location_code": "hk", "company": "ALF Retail Hong Kong Limited", "job_title": "Buying Assistant \u2013 Childrenswear & Home (Brand: Marks and Spencer)", "description": "This role would be responsible for monitoring the merchandise distribution flow from HQ to APAC, stock allocation by country by store, inventory balance in the region and optimize stock replenishment efficiency.\n\nRoles & Responsibilities:\n\u2022 Responsible for merchandise mix and assortment planning in accordance with respective merchandising strategies\n\u2022 Monitor inventory, delivery and reordering situation to ensure appropriate levels of stock are maintained\n\u2022 Responsible for merchandise allocation and coordination with stores and logistics for stock replenishment issues\n\u2022 Regular feedback on seasonal products quantitatively and qualitatively \u2022 Assist in preparing seasonal markdown assortment and discounts\n\u2022 Assist in product training preparation and competitor research\n\nPosition Requirements:\n\u2022 Minimum of 2 years of experience in merchandising, preferably in Fashion industry\n\u2022 A degree holder in Fashion and Textile or related discipline\n\u2022 Acute business sense with analytical mind and sensitive to figures\n\u2022 Dynamic, self-driven and a team player\n\u2022 High proficiency in MS Excel and PowerPoint", "employment_types": ["Full Time", "Permanent"], "selling_points": ["Fresh graduate is welcomed", "Providing clerical and administrative support", "5-day work week"], "locations": ["Kowloon Bay"], "categories": ["Admin & HR", "Clerical / Admin Staff", "Merchandising & Purchasing", "Textiles", "Others"], "post_time": "2022-01-10T07:25:10Z", "salary": {"currency": null, "max": null, "min": null, "period": "monthly", "term": null}, "salary_visible": false, "title_keywords": ["buying assistant"], "responsibilities": ["stock replenishment", "inventory", "coordination with", "monitor", "merchandising", "logistics", "planning"], "requirements": {"degrees": ["degree holder"], "majors": [], "languages": [], "language_level": [], "hard_skills": ["ms excel", "dynamic", "powerpoint"], "soft_skills": ["business sense", "sensitive to figures", "analytical mind", "dynamic", "team player", "driven"], "languages_combined": []}, "experience_required": {"duration": ["minimum of 2 years"], "field": ["merchandising"]}}, {"job_id": "100003009042388", "location_code": "hk", "company": "Mainland Sewing Headwear Manufacturing Limited", "job_title": "Senior Marketing Executive", "description": "1 Post for Woven Fabric\n1 Post for Knit Fabric\n1 Post for Denim Fabric\n1 Post for Underwear Lace\nF.5 or above\n3-5 years experience in garment/textile industry\nCoordinate and execute the orders with mills in China\nCommunicate with customer and mills factory for development and production\nGood knowledge of Woven Fabric or Knit Fabric or Denim Fabric\n\nGood interpersonal and communication skills\nAble to communicate\u00a0English and Mandarin\nLess experience candidates will also considered as Assistant Merchandiser\n\nInterested parties, please send your resume with expected salary by clicking the below \"apply now\" button.\u00a0You can ask click on the website\u00a0www.easyjobhk.com\u00a0for more details about the company", "employment_types": ["Full Time", "Permanent"], "selling_points": [], "locations": ["Kowloon Bay"], "categories": ["Manufacturing", "Garment / Textile", "Merchandising & Purchasing", "Textiles", "Procurement / Purchasing / Sourcing"], "post_time": "2022-01-12T07:17:00Z", "salary": {"currency": null, "max": null, "min": null, "period": "monthly", "term": null}, "salary_visible": false, "title_keywords": ["senior marketing executive"], "responsibilities": ["coordinate", "communication", "communicate with"], "requirements": {"degrees": [], "majors": [], "languages": ["english", "mandarin"], "language_level": [], "hard_skills": [], "soft_skills": ["communication skills", "interpersonal"], "languages_combined": [{"language": "english", "language_level": []}, {"language": "mandarin", "language_level": []}]}, "experience_required": {"duration": ["3-5 years"], "field": ["garment", "textile"]}}, {"job_id": "100003009036274", "location_code": "hk", "company": "I.T Apparels Limited", "job_title": "Merchandiser (REF:JDB-IT-M)", "description": "Accountabilities \u2013 Key Result Areas\n\nMonitor end to end merchandising process from ordering to product delivery\nHandle order and document, data entry and clerical duties\nFollow up with factories and vendors to ensure the orders are delivered on time and according to quality requirements\n\nExperience / Qualification Requirements\n\nAt least 3-4 years of working experience in Merchandising field\nResponsible and organized, and able to work under tight schedules\nGood communication skills in English and Mandarin\nCandidate with more experience will be consider as Senior Merchandiser\n\nCompetitive remuneration and benefit package will be offered to the right candidate. Please submit your application by clicking \"Apply Now\" below.\n\nAll data collected is for recruitment purpose only.\n\nSure you want to know more about our company and brands, simply follow our\n\nWEBSITE at\u00a0http://www.ithk.com\u00a0 \u00a0 \u00a0 \u00a0 \u00a0 \u00a0 \u00a0 \u00a0 \u00a0 \u00a0 \u00a0 \u00a0 \u00a0 \u00a0 \u00a0 \u00a0 \u00a0 \u00a0 \u00a0 \u00a0 \u00a0 \u00a0 \u00a0 \u00a0 \u00a0 \u00a0 \u00a0 \u00a0 \u00a0 \u00a0 \u00a0 \u00a0 \u00a0 \u00a0\u00a0\n\nFACEBOOK at\u00a0http://www.facebook.com/I.Ttheofficialpage\u00a0 \u00a0 \u00a0 \u00a0 \u00a0 \u00a0 \u00a0 \u00a0 \u00a0 \u00a0 \u00a0 \u00a0 \u00a0 \u00a0\u00a0\n\nINSTAGRAM at\u00a0http://instagram.com/ithk\u00a0 \u00a0 \u00a0 \u00a0 \u00a0 \u00a0 \u00a0 \u00a0 \u00a0 \u00a0 \u00a0 \u00a0 \u00a0 \u00a0 \u00a0 \u00a0 \u00a0 \u00a0 \u00a0 \u00a0 \u00a0 \u00a0 \u00a0 \u00a0 \u00a0 \u00a0 \u00a0 \u00a0\n\n\u00a0WEIBO at\u00a0http://e.weibo.com/ithongkong", "employment_types": ["Full Time"], "selling_points": ["Handle order and document", "Monitor end to end merchandising process", "Data entry and clerical duties"], "locations": ["Not Specified"], "categories": ["Merchandising & Purchasing", "Textiles", "Others", "Procurement / Purchasing / Sourcing"], "post_time": "2022-01-10T09:52:53Z", "salary": {"currency": null, "max": null, "min": null, "period": "monthly", "term": null}, "salary_visible": false, "title_keywords": ["merchandiser"], "responsibilities": ["data entry", "schedules", "data", "merchandising", "monitor", "quality", "website", "communication", "recruitment", "facebook"], "requirements": {"degrees": [], "majors": [], "languages": ["english", "mandarin"], "language_level": ["good"], "hard_skills": ["facebook"], "soft_skills": ["communication skills", "organized", "responsible"], "languages_combined": [{"language": "english", "language_level": ["good"]}, {"language": "mandarin", "language_level": ["good"]}]}, "experience_required": {"duration": ["at least 3-4 years"], "field": ["merchandising"]}}, {"job_id": "100003009039089", "location_code": "hk", "company": "Petsource Asia Limited", "job_title": "Merchandiser - Pets", "description": "Petsource Asia Limited is a fast growing startup aiming to bridge the needs from our customers with our manufacturing partners across Asia. You will expect to have an opened and enjoyable working environment with opportunity to learn and stretch your talent. We welcome you to be part of the journey to build and share the success together.\n\n\nJob Duties:\nResponsible for sourcing, merchandising, sampling, quality, price comparison, price negotiation, shipment coordination, factory evaluation etc.\nResponsible for project execution with milestone control and good time management\nKeep abreast of market trend\nCommunicate with customers to clarify inquiries and specifications\nSupply chain management including supplier search, screen and identify potential supplier. Monitor suppliers\u2019 performance\nOrganize and accompany buying/sourcing trips with customers.\nPerform other ad hoc duties.\u00a0\nKey Requirements:\nDiploma or above with 3 years above independent product sourcing and merchandising experience in trading company or buying office\nExperience in handling pets/toys/clothing products is preferred\nStrong negotiation, presentation, and problem-solving skills\nGood time management and project management skills, can work on a project independently\nSound PC knowledge including MS office\nGood product sourcing knowledge and bargaining technique.\nGood network with factories and suppliers in HK & Mainland China.\nFluency in both written and spoken Cantonese, English and Mandarin.\nHard working, Responsible, detail-oriented, flexible and willing to learn\nWe offer competitive remuneration package including 5 days work week, 13th month salary, discretionary bonus, birthday leave, medical scheme, etc. Interested parties please send your application and resume with availability and expected salary for our review. All personal data collected will be kept in strict confidence and only used for recruitment purpose.", "employment_types": ["Full Time", "Permanent"], "selling_points": [], "locations": ["Ngau Tau Kok"], "categories": ["Merchandising & Purchasing", "Textiles", "Toy", "Others"], "post_time": "2022-01-11T08:39:52Z", "salary": {"currency": null, "max": null, "min": null, "period": "monthly", "term": null}, "salary_visible": false, "title_keywords": ["merchandiser"], "responsibilities": ["communicate with", "ad hoc duties", "price negotiation", "control", "management", "quality", "merchandising", "monitor", "specifications", "coordination", "evaluation"], "requirements": {"degrees": ["diploma or above"], "majors": [], "languages": ["cantonese", "english", "mandarin"], "language_level": ["fluency"], "hard_skills": ["problem-solving skills", "project management", "pc knowledge", "ms office"], "soft_skills": ["flexible", "independently", "independent", "negotiation", "responsible", "project management skills", "hard working", "willing to learn", "detail-oriented", "problem-solving skills", "time management", "presentation"], "languages_combined": [{"language": "cantonese", "language_level": ["fluency"]}, {"language": "english", "language_level": ["fluency"]}, {"language": "mandarin", "language_level": ["fluency"]}]}, "experience_required": {"duration": ["3 years"], "field": ["toys", "merchandising", "trading"]}}, {"job_id": "100003009053138", "location_code": "hk", "company": "Gant Asia Pacific Limited", "job_title": "QA Data Analyst", "description": "Job Descriptions:\n\nPrepare analysis, report and presentation PowerPoint for management review and regional meeting;\u00a0\u00a0\nCoordinate and communicate with Supplier/factories for testing & inspection procedures;\nManage incoming 3rd party inspection reports and work with suppliers on any issues;\nManage due diligence chemical testing;\nSupport Head of QA in TQM development and follow up factory audit CAP filing and review;\nGeneral admin support to QA team, create, maintain and file QA records (Inspection Certificate, Seal sample records, Factory audit reports);\nManage incoming Market Product Claims;\nSupport QA operation and Ad hoc projects\n\nQualifications:\n\n\nDegree in apparel design or related discipline;\u00a0\n2-3 experiences of experience in fashion industry preferred (fresh graduates are also welcome);\u00a0\nGood team player with sound communication skills;\u00a0\nAble to multi-task and work in a fast-paced environment;\nFluent in English\nComputer skills (Windows, Microsoft Office, Illustrator, etc.);\nStrong in data analysis & IT skills i.e. Excel, PowerPoint\n\nInterested parties please apply with detailed resume with current & expected salary.\n\nInterested parties, please submit your job application and specify the product categories you have handled in your job experience.", "employment_types": ["Full Time", "Permanent"], "selling_points": [], "locations": ["Wan Chai"], "categories": ["Merchandising & Purchasing", "Textiles"], "post_time": "2022-01-17T06:03:53Z", "salary": {"currency": null, "max": null, "min": null, "period": "monthly", "term": null}, "salary_visible": false, "title_keywords": ["data analyst"], "responsibilities": ["inspection reports", "audit", "design", "communication", "maintain", "management review", "due diligence", "testing", "reports", "report", "review", "procedures", "inspection", "data analysis", "admin support", "communicate with", "analysis", "coordinate", "ad hoc projects"], "requirements": {"degrees": ["certificate", "degree"], "majors": ["design"], "languages": ["english"], "language_level": ["fluent"], "hard_skills": ["excel", "microsoft office", "analysis", "illustrator", "powerpoint", "computer skills"], "soft_skills": ["communication skills", "good team player", "multi-task", "fast-paced environment", "presentation"], "languages_combined": [{"language": "english", "language_level": ["fluent"]}]}, "experience_required": {"duration": [], "field": []}}, {"job_id": "100003009035675", "location_code": "hk", "company": "Eurofiel Confeccion SA", "job_title": "Swim/Active Wear - Merchandiser", "description": "\u2022 DSE / Form 5 or above, IVE/Polytechnic/Graduate is preferred.\n\u2022 1-3 years relevant experience in fashion industry, experience in accessories is a plus.\n\u2022 Following up sampling, costing, order execution, production and delivery\n\u2022 Pragmatic, detailed and results oriented, along with strong organizational skills and commitment to work.\n\u2022 Motivated, independent, willing to learn with good team playing skills and ability to work under pressure.\n\u2022 PC skills with knowledge in MS Office applications Excel, Word, Power Point.\n\u2022 Fluent in spoken, written in English, Cantonese and Mandarin.\n\u2022 Willing to travel China or oversea\n\nIf you like working in a fast pace, international environment with open atmosphere, join us.\n\nWe offer interesting opportunities in an exciting and challenging industry, 5 days work, attractive package and Medical scheme.\n\nFresh graduate or less experience candidate will also be considered as assistant merchandiser.", "employment_types": ["Full Time", "Permanent"], "selling_points": [], "locations": ["Kowloon Bay"], "categories": ["Merchandising & Purchasing", "Textiles"], "post_time": "2022-01-10T08:07:30Z", "salary": {"currency": null, "max": null, "min": null, "period": "monthly", "term": null}, "salary_visible": false, "title_keywords": ["merchandiser"], "responsibilities": ["work under pressure"], "requirements": {"degrees": ["form 5 or above", "dse"], "majors": [], "languages": ["cantonese", "english", "mandarin"], "language_level": ["fluent"], "hard_skills": ["excel", "plus", "word", "power point", "pc skills", "ms office"], "soft_skills": ["organizational skills", "independent", "work under pressure", "willing to learn", "motivated", "detailed"], "languages_combined": [{"language": "cantonese", "language_level": ["fluent"]}, {"language": "english", "language_level": ["fluent"]}, {"language": "mandarin", "language_level": ["fluent"]}]}, "experience_required": {"duration": ["1-3 years"], "field": ["relevant experience"]}}, {"job_id": "100003009043149", "location_code": "hk", "company": "Vocational Training Council", "job_title": "\u4e09\u7d1a\u6a5f\u68b0\u5de5 (\u670d\u98fe)", "description": "\u9999\u6e2f\u77e5\u5c08\u8a2d\u8a08\u5b78\u9662\u53ca\u9999\u6e2f\u5c08\u696d\u6559\u80b2\u5b78\u9662 (\u674e\u60e0\u5229)\n\u00a0\nDepartment / Section : \u6642\u88dd\u53ca\u5f62\u8c61\u8a2d\u8a08\u5b78\u7cfb\nRef. no : C/HKDI-FID/MEC3/01/22-AP1\n\u00a0\n\u4e3b\u8981\u8077\u8cac\uff1a\n(a) \u00a0\u00a0 \u00a0\u64cd\u4f5c\u3001\u5b89\u88dd\u3001\u6e2c\u8a66\u3001\u4fdd\u990a\u53ca\u7dad\u4fee\u5be6\u9a57\u5ba4\u53ca\u5de5\u5834\u5167\u7684\u76f8\u95dc\u6280\u8853\u5100\u5668\u53ca\u6a5f\u5668\u7b49\u914d\u5099\uff1b\n(b) \u00a0\u00a0 \u00a0\u6e96\u5099\u6559\u5b78\u8f14\u52a9\u7528\u5177\u3001\u6240\u9700\u7684\u7269\u6599\u3001\u5100\u5668\u53ca\u914d\u5099\u4f5c\u8a13\u7df4\u4e4b\u7528\uff1b\n(c) \u00a0\u00a0 \u00a0\u5354\u52a9\u7ba1\u7406\u6709\u95dc\u5668\u6750\u53ca\u7269\u8cc7\u7684\u6536\u767c\u5b58\u53d6\uff0c\u4e26\u6aa2\u67e5\u662f\u5426\u640d\u58de\uff1b\n(d) \u00a0\u00a0 \u00a0\u642c\u904b\u6559\u5b78\u8a2d\u5099\u3001\u5100\u5668\u53ca\u7269\u8cc7\uff0c\u4e26\u4fdd\u6301\u5de5\u5834\u7684\u5b89\u5168\u53ca\u6574\u6f54\uff1b\u53ca\n(e) \u00a0\u00a0 \u00a0\u652f\u63f4\u5b78\u9662\u8209\u8fa6\u4e4b\u6d3b\u52d5\u3001\u5c55\u89bd\u548c\u8868\u6f14\u3002\n\u00a0\n\u5165\u8077\u689d\u4ef6\uff1a\n(a) \u00a0\u00a0 \u00a0(i) \u00a0\u00a0 \u00a0\u5b8c\u6210\u76f8\u95dc\u8a8d\u53ef\u8a13\u7df4\u8ab2\u7a0b (\u5305\u62ec\u5b78\u5f92\u53ca\u6280\u5de5\u8a13\u7df4) ; \u6216\n\u00a0 \u00a0\u00a0 \u00a0(ii) \u00a0\u00a0 \u00a0\u901a\u904e\u6280\u80fd\u6e2c\u8a66\u6216\u76f8\u7b49\u6c34\u5e73\u6e2c\u8a66\uff1b\n(b) \u00a0\u00a0 \u00a0\u5177\u5099\u4e0b\u5217\u6280\u80fd\uff1a\n\u00a0 \u00a0\u00a0 \u00a0(i) \u00a0\u00a0 \u00a0\u68ad\u7e54\u8eca\u9593\u7f1d\u7d09\u6280\u8853\uff1b\n\u00a0 \u00a0\u00a0 \u00a0(ii) \u00a0\u00a0 \u00a0\u68ad\u7e54\u6a5f\u5668\u6e05\u6f54\u3001\u7dad\u4fee\u53ca\u4fdd\u990a\uff1b\u53ca / \u6216\n\u00a0 \u00a0\u00a0 \u00a0(iii) \u00a0\u00a0 \u00a0\u68ad\u7e54\u6280\u8853 (\u5982\u61c9\u7528\u548c\u4fee\u88dc\u7b49)\uff1b\n(c) \u00a0\u00a0 \u00a0\u61c2\u57fa\u672c\u96fb\u8166\u64cd\u4f5c\uff1b\n(d) \u00a0\u00a0 \u00a0\u80fd\u95b1\u8b80\u53ca\u66f8\u5beb\u4e2d\u6587\u548c\u7c21\u55ae\u82f1\u8a9e\uff1b\u53ca\n(e) \u00a0\u00a0 \u00a0\u5177\u5099\u61c2\u5f97\u64cd\u4f5c/\u7dad\u4fee\u4ee5\u4e0b\u6a5f\u5668 / \u5de5\u5177\u7684\u7533\u8acb\u4eba\u53ef\u7372\u512a\u5148\u8003\u616e\uff1a\n\u00a0 \u00a0\u00a0 \u00a0(i) \u00a0\u00a0 \u00a0\u5de5\u696d\u8863\u8eca (\u5e73\u8eca)\uff1b\n\u00a0 \u00a0\u00a0 \u00a0(ii) \u00a0\u00a0 \u00a0\u9212\u9aa8\u8eca\uff1b\n\u00a0 \u00a0\u00a0 \u00a0(iii) \u00a0\u00a0 \u00a0\u6311\u8173\u8eca\uff1b\n\u00a0 \u00a0\u00a0 \u00a0(iv) \u00a0\u00a0 \u00a0\u91d8\u9215\u53ca\u958b\u9215\u9580\u8eca\uff1b\n\u00a0 \u00a0\u00a0 \u00a0(v) \u00a0\u00a0 \u00a0\u9ecf\u6734\u6a5f\uff1b\n\u00a0 \u00a0\u00a0 \u00a0(vi) \u00a0\u00a0 \u00a0\u5047\u7f1d\u8eca\uff1b\n\u00a0 \u00a0\u00a0 \u00a0(vii) \u00a0\u00a0 \u00a0\u57cb\u593e\u8eca\uff1b\n\u00a0 \u00a0\u00a0 \u00a0(viii) \u00a0\u00a0 \u00a0\u519a\u8eca\uff1b\n\u00a0 \u00a0\u00a0 \u00a0(ix) \u00a0\u00a0 \u00a0\u5277\u76ae\u6a5f\uff1b\n\u00a0 \u00a0\u00a0 \u00a0(x) \u00a0\u00a0 \u00a0\u9ad8\u982d\u6a5f\uff1b\n\u00a0 \u00a0\u00a0 \u00a0(xi) \u00a0\u00a0 \u00a0\u4eba\u5b57 / \u4e09\u91dd\u8eca\u3002\n\u00a0 \u00a0\u00a0 \u00a0 \u00a0\u00a0\u00a0 \u00a0\n\u5099\u8a3b\uff1a\n(1) \u00a0\u00a0 \u00a0\u7533\u8acb\u8005\u82e5\u5177\u5169\u5e74\u6216\u4ee5\u4e0a\u76f8\u95dc\u5de5\u4f5c\u7d93\u9a57\uff0c\u6216\u6703\u88ab\u8003\u616e\u70ba\u4e8c\u7d1a\u6a5f\u68b0\u5de5\u3002\n(2)\n\u00a0 \u00a0\u00a0 \u00a0\u8a72\u7a7a\u7f3a\u73fe\u65bc\u9999\u6e2f\u77e5\u5c08\u8a2d\u8a08\u5b78\u9662\u53ca\u9999\u6e2f\u5c08\u696d\u6559\u80b2\u5b78\u9662\uff08\u674e\u60e0\u5229\uff09\uff0c\u70ba\u914d\u5408\u904b\u4f5c\u9700\u8981\uff0c\u53d7\u8058\u8005\u65e5\u5f8c\u53ef\u80fd\u6703\u88ab\u8abf\u6d3e\u81f3\u5176\u4ed6\u5730\u9ede\u5de5\u4f5c\u3002\n(3) \u00a0\u00a0 \u00a0\u8acb\u65bc\u7533\u8acb\u8868\u300c(VII) \u5176\u4ed6\u8cc7\u6599\u300d\u6b04\u5167\u5217\u51fa\u80fd\u64cd\u4f5c\u4e4b\u76f8\u95dc\u6a5f\u5668\u8a2d\u5099\u548c\u6280\u80fd\u3002\n(4) \u00a0\u00a0 \u00a0\u7533\u8acb\u8005\u9700\u8981\u53c3\u52a0\u6280\u80fd\u6e2c\u8a66\u3002\n(5) \u00a0\u00a0 \u00a0\u53d7\u8058\u8005\u53ef\u80fd\u9700\u8981\u8f2a\u73ed\u5de5\u4f5c\uff0c\u5305\u62ec\u591c\u73ed\uff0c\u4e26\u65bc\u661f\u671f\u516d\u3001\u65e5\u53ca\u516c\u773e\u5047\u671f\u5de5\u4f5c\uff0c\u4ea6\u53ef\u80fd\u6703\u5728\u4e0d\u540c\u5de5\u5834\u5167\u5de5\u4f5c\u3002\n\n\u7533\u8acb\u8fa6\u6cd5\uff1a\n\u586b\u59a5\u7684\u7533\u8acb\u8868\u683c [VTC-1 (Rev. 1/2018)] \u9023\u540c\u500b\u4eba\u5c65\u6b77\uff0c\u9808\u5bc4\u56de\u9999\u6e2f\u7063\u4ed4\u6d3b\u905327\u865f\uff0c\u8077\u696d\u8a13\u7df4\u5c40\u5927\u6a1318\u6a13\uff0c\u4eba\u529b\u8cc7\u6e90\u79d1\u3002\u8acb\u5728\u4fe1\u5c01\u9762\u8a3b\u660e\u6240\u7533\u8acb\u7684\u8077\u4f4d\u53ca\u53c3\u8003\u7de8\u865f\u3002\n\u00a0\n\u622a\u6b62\u7533\u8acb\u65e5\u671f\uff1a2022\u5e741\u670825\u65e5\n\u00a0\n\u5982\u5728\u622a\u6b62\u7533\u8acb\u5f8c\u7684\u5341\u661f\u671f\u5167\u672a\u6709\u6536\u5230\u9762\u8a66\u901a\u77e5\uff0c\u5373\u8868\u793a\u9019\u9805\u7533\u8acb\u4e0d\u7372\u63a5\u7d0d\u3002\n\u00a0\n\u672c\u5c40\u4fdd\u7559\u4e0d\u586b\u88dc\u4e0a\u8ff0\u8077\u4f4d\u7684\u6b0a\u5229\u3002\n\u00a0\n\u7533\u8acb\u4eba\u7684\u8cc7\u6599\u53ea\u6703\u7528\u65bc\u6709\u95dc\u672c\u5c40\u7684\u4eba\u4e8b\u62db\u8058\u4e8b\u5b9c\u3002\u5728\u4e00\u822c\u60c5\u6cc1\u4e0b\uff0c\u672a\u7372\u53d6\uf93f\u7533\u8acb\u4eba\u7684\u8cc7\uf9be\u5c07\u65bc\u62db\u8058\u5de5\u4f5c\u5b8c\u6210\u5341\u4e8c\u500b\u6708\u5f8c\u5168\u90e8\u92b7\u6bc0\u3002\n\n", "employment_types": ["Full Time"], "selling_points": ["\u64cd\u4f5c\u3001\u5b89\u88dd\u3001\u6e2c\u8a66\u3001\u4fdd\u990a\u53ca\u7dad\u4fee\u5be6\u9a57\u5ba4\u53ca\u5de5\u5834\u5167\u7684\u76f8\u95dc\u6280\u8853\u5100\u5668\u53ca\u6a5f\u5668\u7b49\u914d\u5099", "\u5b8c\u6210\u76f8\u95dc\u8a8d\u53ef\u8a13\u7df4\u8ab2\u7a0b (\u5305\u62ec\u5b78\u5f92\u53ca\u6280\u5de5\u8a13\u7df4)", "\u7533\u8acb\u8005\u82e5\u5177\u5169\u5e74\u6216\u4ee5\u4e0a\u76f8\u95dc\u5de5\u4f5c\u7d93\u9a57\uff0c\u6216\u6703\u88ab\u8003\u616e\u70ba\u4e8c\u7d1a\u6a5f\u68b0\u5de5"], "locations": ["Not Specified"], "categories": ["Design", "Fashion", "Manufacturing", "Garment / Textile", "Merchandising & Purchasing", "Textiles"], "post_time": "2022-01-12T09:59:55Z", "salary": {"currency": null, "max": null, "min": null, "period": "monthly", "term": null}, "salary_visible": false, "title_keywords": [], "responsibilities": [], "requirements": {"degrees": [], "majors": [], "languages": [], "language_level": [], "hard_skills": ["no", "c"], "soft_skills": [], "languages_combined": []}, "experience_required": {"duration": [], "field": []}}, {"job_id": "100003009046831", "location_code": "hk", "company": "L.L.Bean, Inc.", "job_title": "Senior Fabric Merchandiser (Knit & Sweater) - US buying office", "description": "Job Duties :\n\nWork with US sourcing team on fabric material sourcing, color review and development/ commercialization\nCommunicate with mills/ suppliers on order & production tracking, fabric quality testing and color approval, cost & lead time negotiation and development\nResearch on fabric trend and maintain fabric library\n\nJob Requirements :\n\nF.5 or above;\u00a0 Polytechnic/ IVE graduate in Textile/Clothing studies preferred\u00a0\n8 years relevant experience in fabric sourcing ; preferable in knit and sweater\nPrevious work experience in fabric mill is an advantageous\nDetail oriented with high initiative and strong team spirit\n\nGood command of written and spoken English and Cantonese; Mandarin a plus\nPC knowledge is required (MS-Word, Excel and Outlook e-mail)\nOccasional overseas travelling may be required\nImmediate available is required\n\nWe offer a competitive salary and benefits package: 5-day week; 13-month payment; employee medical, life and disability insurance; discretionary bonus; tuition reimbursement; and merchandise discount.\n\nPlease send your resume (with employment history, expected salary and available date) to L.L. Bean, Inc. - HK, Human Resources Department by clicking \"Apply Now\".\u00a0The information supplied for the purposes of this application will be used only in accordance with L.L. Bean\u2019s data policies.\n", "employment_types": ["Full Time"], "selling_points": [], "locations": ["Ngau Tau Kok"], "categories": ["Manufacturing", "Garment / Textile", "Merchandising & Purchasing", "Woven / Knit", "Textiles"], "post_time": "2022-01-14T01:23:55Z", "salary": {"currency": null, "max": null, "min": null, "period": "monthly", "term": null}, "salary_visible": false, "title_keywords": ["fabric merchandiser"], "responsibilities": ["communicate with", "cost", "review", "quality", "testing", "commercialization", "maintain", "tracking"], "requirements": {"degrees": [], "majors": [], "languages": ["cantonese", "english", "mandarin"], "language_level": ["good command"], "hard_skills": ["ms-word", "plus", "excel", "outlook", "pc knowledge"], "soft_skills": ["detail oriented", "team spirit", "initiative"], "languages_combined": [{"language": "cantonese", "language_level": ["good command"]}, {"language": "english", "language_level": ["good command"]}, {"language": "mandarin", "language_level": []}]}, "experience_required": {"duration": ["8 years"], "field": ["relevant experience"]}}, {"job_id": "100003009038284", "location_code": "hk", "company": "Tchibo Merchandising Hong Kong LP", "job_title": "Merchandiser, Textile (Lingerie & Underwear) (Ref.: MTX001)", "description": "DSE/ Form 7 or above\nMinimum 3 years of relevant experience in merchandising field\nExtensive product knowledge in Lingerie & Underwear\nStrong negotiation skills and able to deal with buyers and overseas factories independently\nPreferably work in buying office or multinational trading company with overseas production\nAttentive to details, well organized, able to meet various deadlines.\nGood command of written & spoken English and Chinese (Cantonese & Putonghua)\nProficiency in MS office, SAP preferable\nOccasional travel to China and South East Asia required\nWe offer attractive remuneration package including 5-day week, double pay, discretionary bonus, medical & dental insurance, travel allowance, etc. Interested parties, please send your CV with expected salary and availability, and by quoting reference number (MTX001) in the subject via \"Apply Now\". Candidates who are not contacted within 8 weeks should consider their application as unsuccessful.\n(The information provided will be used for selection purpose only.)", "employment_types": ["Full Time", "Permanent"], "selling_points": ["Minimum 3 years\u2019 experience in merchandising field", "Extensive product knowledge in Lingerie &Underwear", "European Buying Office, Flexible Working Hours"], "locations": ["Tsim Sha Tsui"], "categories": ["Merchandising & Purchasing", "Textiles", "Others", "Procurement / Purchasing / Sourcing"], "post_time": "2022-01-11T06:26:03Z", "salary": {"currency": null, "max": null, "min": null, "period": "monthly", "term": null}, "salary_visible": false, "title_keywords": ["merchandiser"], "responsibilities": ["merchandising"], "requirements": {"degrees": ["dse"], "majors": [], "languages": ["cantonese", "putonghua", "english", "chinese"], "language_level": ["good command"], "hard_skills": ["sap", "ms office"], "soft_skills": ["independently", "attentive to details", "well organized", "negotiation skills", "extensive"], "languages_combined": [{"language": "cantonese", "language_level": ["good command"]}, {"language": "putonghua", "language_level": ["good command"]}, {"language": "english", "language_level": ["good command"]}, {"language": "chinese", "language_level": ["good command"]}]}, "experience_required": {"duration": ["minimum 3 years"], "field": ["merchandising", "relevant experience"]}}, {"job_id": "100003009035360", "location_code": "hk", "company": "Bape Hong Kong Limited", "job_title": "Assistant Buyer - Aape", "description": "Accountabilities \u2013 Key Result Areas\n\n\n\nPrepare OTB, seasonal and annual buying plans based on a thorough understanding of consumer, market trends and company business objectives\nExecute buying activities, stock planning and allocation, and merchandise delivery and reordering situations\nAnalyze business performance and inventory turn\nWork closely with production and sourcing team to ensure the smooth flow of merchandise delivery\nWork with marketing and retail teams in regard to speedy response to market dynamics and promotions\nExperience / Qualification Requirements\n\n\nDegree holder in Fashion & Textiles or business discipline\nWith at least 1-2 years of experience in\u00a0buying and merchandising, preferably in the fashion / lifestyle / retail industry\nProactive, sensitive to figures and strong analytical and negotiation skills\nExcellent product sensibility and understanding of competitive retail landscape\nAttention to detail with high level of accuracy\n\nCompetitive remuneration and benefit package will be offered to the right candidate. Please submit your application by clicking \"Apply Now\" below.\n\n\n\nAll data collected is for recruitment purpose only.", "employment_types": ["Full Time"], "selling_points": ["1-2 years solid experience in buying", "Prepare OTB, seasonal and annual buying plans", "Strong analytical and negotiation skills"], "locations": ["Southern Area"], "categories": ["Merchandising & Purchasing", "Sweater", "Woven / Knit", "Textiles"], "post_time": "2022-01-10T06:55:56Z", "salary": {"currency": null, "max": null, "min": null, "period": "monthly", "term": null}, "salary_visible": false, "title_keywords": ["assistant"], "responsibilities": ["data", "inventory", "teams", "merchandising", "otb", "recruitment", "plans", "stock planning"], "requirements": {"degrees": ["degree holder"], "majors": ["business"], "languages": [], "language_level": [], "hard_skills": [], "soft_skills": ["sensitive to figures", "negotiation skills", "thorough", "attention to detail", "smooth", "proactive"], "languages_combined": []}, "experience_required": {"duration": ["at least 1-2 years"], "field": ["retail industry", "merchandising"]}}, {"job_id": "100003009040610", "location_code": "hk", "company": "The Swank Shop Ltd", "job_title": "Merchandising Manager - Men's and Ladies'", "description": "Job Descriptions:\n\nDrive, plan and implement buying strategies that will help the Business to achieve its objectives\nFormulates buying strategy, develops buying plan for each season in terms of brand & merchandise mix, category ratio, size ratio and ensures the best brands and merchandise mix are right for the Business Strategy in different locations or sales channel to maximize sales and profit\nProactively source appropriate new and key international designers\nNegotiate favorable terms of contract such as prices, terms of payment and delivery schedule with brands/vendors in order to obtain the highest profit margin within budgeted forecasts\nExecute pre-season and main-season purchases within approved OTB budget\nResponsible for managing the profit and loss, sales growth, gross profit and volume of inventory on hand for the Business\nSet appropriate pricing and markup strategies to meet sell through, sales volume and GP objectives\nKeep abreast of the activity of competitors, customer preferences and buying patterns and recommends changes to buying plan where relevant\nWork closely with Marketing & Communications Department to initiate & develop brand promotion activities\nWork closely with VM Department on designing windows and merchandises display\nOther ad-hoc projects as assigned\nJob Requirements:\n\nDegree or above, related in Fashion/Clothing/Merchandising disciplines is an advantage\nAt least 5 - 7 years buying experience in luxury fashion brands or retail chain for both RTW and Accessories buying for multi brand store. Minimum 1 year managerial experience is a must.\nProven ability to manage multiple projects & experience in merchandising for E-commerce\nFamiliar with buying for luxury fashion retail market &\u00a0mix-and-match techniques\nGood knowledge of both online & physical store retail operations and fabric materials\nExcellent communication, interpersonal & negotiation skills and fashion sense\nGood presentation skill and leadership profile\nStrong numerical and analytical skills\nDetail oriented, tactful, mature and can work under pressure\nGood command of both spoken and written English and Chinese, fluent in Mandarin\nWilling to travel\nWe offer an attractive remuneration package to the right candidate. Interested parties please forward your full resume with\u00a0current and expected salary, by pressing \"Apply Now\"\n\nAll applications will be treated in strict confidence and used exclusively for recruitment purposes. The company will retain the applications for a maximum period of 6 months.\n\n", "employment_types": ["Full Time", "Permanent"], "selling_points": ["5 - 7 years buying experience in luxury fashion", "Strong leadership and strategic planning skills", "Good fashion sense and mix & match techniques"], "locations": ["Tsuen Wan Area"], "categories": ["Merchandising & Purchasing", "Woven / Knit", "Textiles", "Others"], "post_time": "2022-01-12T03:36:32Z", "salary": {"currency": null, "max": null, "min": null, "period": "monthly", "term": null}, "salary_visible": false, "title_keywords": ["merchandising manager"], "responsibilities": ["inventory", "budget", "otb", "delivery schedule", "develop", "payment", "plan", "designing", "ad-hoc projects"], "requirements": {"degrees": ["degree or above"], "majors": [], "languages": ["english", "chinese", "mandarin"], "language_level": ["good command", "fluent"], "hard_skills": ["presentation skill", "analytical skills", "e-commerce"], "soft_skills": ["presentation skill", "detail oriented", "mature", "analytical skills", "communication", "negotiation skills", "tactful", "leadership", "interpersonal", "work under pressure"], "languages_combined": [{"language": "english", "language_level": ["good command"]}, {"language": "chinese", "language_level": ["good command"]}, {"language": "mandarin", "language_level": ["fluent", "good command"]}]}, "experience_required": {"duration": ["minimum 1 year", "at least 5 - 7 years"], "field": ["managerial", "brand", "e-commerce", "merchandising", "retail"]}}, {"job_id": "100003009033612", "location_code": "hk", "company": "C.F.L. Enterprise Limited", "job_title": "Senior Merchandiser (Woven)", "description": "Responsibilities:\n\nLiaison with customers & factories\nMaterials sourcing\nCost analysis & price negotiation with suppliers\nResponsible for\u00a0development follow up, order execution\nEnsure the product development processes are smooth and accurate information transfer to all relevant parties\nLiaison with Fabric, QC & Logistics team\nPerform other ad hoc duties as assigned\n\nRequirements:\n\nDiploma or above, preferably major in Textile and Clothing\nAt least 5 - 8 year experiences in handling woven / functional items\nExperiences in US market will be an advantage\nAble to work independently and under tight schedule\nProficiency in both spoken and written English\nGood computer skill\n\nWe offer 5-day work plus attractive remuneration and fringe benefits to the right candidate.\u00a0 Interested parties please send you resume with expected salary and availability by clicking \u201cAPPLY NOW\u201d.", "employment_types": ["Full Time"], "selling_points": [], "locations": ["Kowloon Bay"], "categories": ["Merchandising & Purchasing", "Textiles"], "post_time": "2022-01-10T01:19:52Z", "salary": {"currency": null, "max": null, "min": null, "period": "monthly", "term": null}, "salary_visible": false, "title_keywords": ["senior merchandiser"], "responsibilities": ["ad hoc duties", "cost analysis", "logistics", "price negotiation"], "requirements": {"degrees": ["diploma or above"], "majors": [], "languages": ["english"], "language_level": ["proficiency"], "hard_skills": ["computer skill"], "soft_skills": ["work independently"], "languages_combined": [{"language": "english", "language_level": ["proficiency"]}]}, "experience_required": {"duration": ["at least 5 - 8 year"], "field": []}}, {"job_id": "100003009036034", "location_code": "hk", "company": "I.T Apparels Limited", "job_title": "Management Trainee - Buying (REF:JDB-IT-MTB)", "description": "Accountabilities \u2013 Key Result Areas\n\nAssist buying team in execute buying activities, stock planning and allocation, and merchandise delivery and reordering situations to meet company business objectives\nPrepare merchandising reports for management review on business performance and inventory turn\nAssist OTB planning, sell through, mark down logistics\nWork with marketing and retail teams in regard to speedy response to market dynamics and promotions\nSupport buyers to prepare seasonal product training material and market research analysis\n\nExperience / Qualification Requirements\n\nDegree holder in Fashion & Textiles or business discipline\nProactive, sensitive to figures and strong analytical and negotiation skills\nAdequate product sensibility and understanding of competitive retail landscape\nAttention to detail with high level of accuracy\nHands on analytical skills in MS Excel and ERP systems in sizable corporation\n\nCompetitive remuneration and benefit package will be offered to the right candidate. Please submit your application by clicking \"Apply Now\" below.\n\nDBcampaignaviation\n\nAll data collected is for recruitment purpose only.\n\nSure you want to know more about our company and brands, simply follow our\n\nWEBSITE at http://www.ithk.com\u00a0 \u00a0 \u00a0 \u00a0 \u00a0 \u00a0 \u00a0 \u00a0 \u00a0 \u00a0 \u00a0 \u00a0 \u00a0 \u00a0 \u00a0 \u00a0 \u00a0 \u00a0 \u00a0 \u00a0 \u00a0 \u00a0 \u00a0 \u00a0 \u00a0 \u00a0 \u00a0 \u00a0 \u00a0 \u00a0 \u00a0 \u00a0 \u00a0 \u00a0\u00a0\n\nFACEBOOK at\u00a0http://www.facebook.com/I.Ttheofficialpage\u00a0 \u00a0 \u00a0 \u00a0 \u00a0 \u00a0 \u00a0 \u00a0 \u00a0 \u00a0 \u00a0 \u00a0 \u00a0 \u00a0\u00a0\n\nINSTAGRAM at http://instagram.com/ithk\u00a0 \u00a0 \u00a0 \u00a0 \u00a0 \u00a0 \u00a0 \u00a0 \u00a0 \u00a0 \u00a0 \u00a0 \u00a0 \u00a0 \u00a0 \u00a0 \u00a0 \u00a0 \u00a0 \u00a0 \u00a0 \u00a0 \u00a0 \u00a0 \u00a0 \u00a0 \u00a0 \u00a0\n\nWEIBO at\u00a0http://e.weibo.com/ithongkong", "employment_types": ["Full Time"], "selling_points": ["Fresh Grad", "Budget planning, sales planning and analysis", "Stock planning and allocation"], "locations": ["Southern Area"], "categories": ["Merchandising & Purchasing", "Textiles", "Others", "Procurement / Purchasing / Sourcing"], "post_time": "2022-01-10T09:09:54Z", "salary": {"currency": null, "max": null, "min": null, "period": "monthly", "term": null}, "salary_visible": false, "title_keywords": ["management trainee"], "responsibilities": ["data", "inventory", "analysis", "merchandising", "teams", "market research", "otb", "systems", "website", "reports", "logistics", "recruitment", "facebook", "stock planning", "management review", "planning"], "requirements": {"degrees": ["degree holder"], "majors": ["business"], "languages": [], "language_level": [], "hard_skills": ["erp systems", "analysis", "analytical skills", "ms excel", "facebook"], "soft_skills": ["sensitive to figures", "analytical skills", "negotiation skills", "hands on", "attention to detail", "proactive"], "languages_combined": []}, "experience_required": {"duration": [], "field": []}}, {"job_id": "100003009041520", "location_code": "hk", "company": "Michael Kors (HK) Limited", "job_title": "Senior Planner / Associate Planning Manager", "description": "SUMMARY:\n\n\nThe objective of this position is to plan and manage inventory allocation in order to maximize sales and margin across both Full Price and Outlet channels within Hong Kong/Macao, and extend regional support to Taiwan/Australia.\u00a0\n\nJOB RESPONSIBILITIES\n\nBe responsible for allocation / replenishment / rebalancing for selected product categories within Hong Kong/Macao and support Taiwan/Australia for regional allocation\nAllocate, replenish, and rebalance inventory by store, according to\n- Seasonal flow, including seasonal launch, floor sets, markdown, and liquidation\n- Product lifecycle and markdown risk (such as core/carryover items vs. fashion newness)\n- Sales performance by store, down to the SKU level\n- Optimal inventory levels by store according to store type, sales performance and store capacity\n- Anticipate peak / slow shopping periods and holidays\n- Anticipate future product (such as reserving and rebalancing) according to store opening plan\nPrioritize key stores and understand product substitutes in limited stock situations\nPrepare inventory for new store openings\nPromotion and markdown management, update relevant system\nDevelop stock clearance plan, organize and coordinate return\nAct as key stakeholder to provide GC Merch team, the insight of HK/Macao business, from merchandising planning point of view\nHandle assortment planning including price and discount setting for Sogo Thankful event and Brand sale\nIssue TN and SO for HK, Macao and Taiwan orders.\u00a0 Coordinate with HK logistics and EU team for Australia orders\nPartner with other team members and functions as needed, for example\n- Partner with logistics to ensure timely execution of allocation / replenishment\n- Communicate with stores on store requests and needs; enforce efficient transfers / returns from stores\n- Work with buyers to understand launching schedule, product needs by store and substitutes in limited stock situations\n- Partner with marketing and VM to support special marketing requests (e.g. store events) and VM (e.g. mannequin looks)\n\u00a0SKILLS and WORK EXPERIENCE\n\nBachelor\u2019s Degree or above\nStrong record of academic and professional performance, with references\n6-8 years\u2019 inventory management experience in the retail industry (experience in APAC management is preferred)\nExtremely sensitive to number; strong data analysis and Excel skills\nEstablish and develop the inventory management team\nHonest, open, and non-hierarchical attitude\nExcellent communication and interpersonal skills\nStrong prioritization and organizational skills\nDriven to execute efficiently and accurately\nProfessional demeanor\nProactive, ambitious, flexible, and entrepreneurial; able to work in a startup environment\nComputer and systems literate\nFluent in English, good Mandarin is a plus\n\nWe offer remuneration package\u00a0commensurate with qualification and experience to the successful candidate.\u00a0 If you would like to apply for this position or find out more, please press 'Apply Now'.\n\n(Data collected will be treated as strict confidential and will be used for recruitment purpose only.)", "employment_types": ["Full Time", "Permanent"], "selling_points": ["At least 6 years\u2019 exp. inventory management", "Computer and systems literate", "Fluent in English, good Mandarin is a plus."], "locations": ["Tsim Sha Tsui"], "categories": ["Merchandising & Purchasing", "Footwear", "Handbag", "Textiles"], "post_time": "2022-01-12T03:59:40Z", "salary": {"currency": null, "max": null, "min": null, "period": "monthly", "term": null}, "salary_visible": false, "title_keywords": ["associate", "manager"], "responsibilities": ["product categories", "communicate with", "management", "sales performance", "inventory", "systems", "merchandising", "replenishment", "coordinate with", "develop", "coordinate", "inventory management", "data analysis", "communication", "logistics", "schedule", "plan", "planning"], "requirements": {"degrees": ["degree or above", "bachelor"], "majors": [], "languages": ["english", "mandarin"], "language_level": ["good", "fluent"], "hard_skills": ["vs", "excel", "analysis", "plus"], "soft_skills": ["efficient", "organizational skills", "flexible", "responsible", "timely", "prioritize", "sensitive to", "communication and interpersonal skills", "honest", "proactive", "driven"], "languages_combined": [{"language": "english", "language_level": ["fluent"]}, {"language": "mandarin", "language_level": ["good", "fluent"]}]}, "experience_required": {"duration": ["6-8 years"], "field": ["inventory management", "management", "retail industry"]}}, {"job_id": "100003009035856", "location_code": "hk", "company": "Newtimes Development Limited", "job_title": "Senior Technician (Garment)", "description": "\u00a0Responsibilities:\nResponsible for samples review and approval process\nEvaluate sample comments and tech packs to fulfill customer requirements\nProvide technical support to merchandisers, customers, and factories\nLiaise with merchandisers and factories to establish correction action plans\nPerform other ad hoc duties\u00a0\nRequirements:\nAt least 5 years' garment trading or buying office experience\u00a0\nExperience in USA market for both Men & Women is preferred\nGood knowledge of woven and knits fabric, knowledge of pattern and grading & quality of thread and stitch type\nGood computer knowledge (MS Office - Word, Excel, Chinese Word Processing)\nGood communication skills to liaise with external parties\u00a0\nAble to work independently, a good team player, attentive to details, and able to work under pressure\nImmediate available is highly preferred\n\nInterested parties please send\u00a0your\u00a0detailed resume\u00a0with\u00a0current and\u00a0expected salary\u00a0via the\u00a0\u201cAPPLY NOW\u201d button.", "employment_types": ["Full Time", "Permanent"], "selling_points": ["5 years' related experience in garment industry", "5-day work, Lai Chi Kok", "Double Pay, Discretionary Bonus, Birthday Leave"], "locations": ["Lai Chi Kok"], "categories": ["Manufacturing", "Garment / Textile", "Merchandising & Purchasing", "Woven / Knit", "Textiles"], "post_time": "2022-01-10T08:34:02Z", "salary": {"currency": null, "max": null, "min": null, "period": "monthly", "term": null}, "salary_visible": false, "title_keywords": ["technician"], "responsibilities": ["ad hoc duties", "technical support", "review", "comments", "evaluate", "liaise with", "plans"], "requirements": {"degrees": [], "majors": [], "languages": ["chinese"], "language_level": ["good"], "hard_skills": ["excel", "chinese word processing", "word", "ms office"], "soft_skills": ["communication skills", "work independently", "good team player", "attentive to details", "work under pressure"], "languages_combined": [{"language": "chinese", "language_level": ["good"]}]}, "experience_required": {"duration": ["at least 5 years"], "field": ["garment", "trading"]}}, {"job_id": "100003009049933", "location_code": "hk", "company": "Sportshouse Limited", "job_title": "Buyer", "description": "Responsibilities:\n\nResponsible for performing market research on the up-coming fashion trend;\nAssemble and execute plans for seasonal brand assortment and OTB in order to meet the company\u2019s business objective;\nProducts sourcing and sell-thru analysis;\nLiaise with suppliers on order placing efficiency and ensure appropriate levels of stock of designated product categories are maintained;\nAllocate merchandises and coordinate with shops and warehouse to smooth the stock replenishment issue;\nWork closely with operations, visual merchandising team and other counterparts to maximize sales performance of responsible category;\nCultivate and maintain partnership relationship with suppliers\n\nRequirements:\n\nBachelor\u2019s degree holder\nMin. 4 years\u2019 apparel / footwear buying experience\nSolid experience in branded merchandise buying, store replenishment, merchandise consolidation and product management is a must\nStrong business sense with excellent negotiation, interpersonal, numerical and analytical skills\nFluent in spoken and written English, Chinese and Mandarin\nProficient in MS Excel (Pivot Table, VLookup and other formula functions)\nWilling to travel\nCandidate with less experience will be considered as Assistant Buyer\n\nInterested parties please\u00a0send your resume with current and expected salary\u00a0by clicking\u00a0\"Apply Now\".\n\n\nData collected will be used for recruitment purpose only.\n\nFor company information, please visit our website www.sportshouse.com.hk", "employment_types": ["Full Time", "Permanent"], "selling_points": ["Responsible for performing market research", "Products sourcing & sell-thru analysis", "Degree holder or above"], "locations": ["Tsuen Wan Area"], "categories": ["Merchandising & Purchasing", "Textiles", "Others", "Procurement / Purchasing / Sourcing"], "post_time": "2022-01-14T09:27:47Z", "salary": {"currency": null, "max": null, "min": null, "period": "monthly", "term": null}, "salary_visible": false, "title_keywords": [], "responsibilities": ["product categories", "stock replenishment", "operations", "analysis", "sales performance", "coordinate with", "market research", "merchandising", "otb", "maintain", "visual", "plans", "liaise with suppliers"], "requirements": {"degrees": ["bachelor", "degree holder"], "majors": [], "languages": ["english", "chinese", "mandarin"], "language_level": ["fluent"], "hard_skills": ["pivot table", "ms excel", "vlookup", "analytical skills"], "soft_skills": ["interpersonal", "negotiation", "analytical skills", "business sense"], "languages_combined": [{"language": "english", "language_level": ["fluent"]}, {"language": "chinese", "language_level": ["fluent"]}, {"language": "mandarin", "language_level": ["fluent"]}]}, "experience_required": {"duration": ["4 years"], "field": ["product management", "consolidation"]}}, {"job_id": "100003009038233", "location_code": "hk", "company": "Majestic City International Limited", "job_title": "Garment Senior Merchandiser (5 days works)", "description": "15 years garment experience in senior level with factory background\nFluent in English & Mandarin\nCan supervise the team independently and work under pressure\n5 days works in LCK area\n\nApply with full resume and expected salary by clicking \"Apply Now\"\n", "employment_types": ["Full Time", "Permanent"], "selling_points": [], "locations": ["Not Specified"], "categories": ["Merchandising & Purchasing", "Textiles", "Others", "Procurement / Purchasing / Sourcing"], "post_time": "2022-01-11T06:16:04Z", "salary": {"currency": null, "max": null, "min": null, "period": "monthly", "term": null}, "salary_visible": false, "title_keywords": ["senior merchandiser"], "responsibilities": ["work under pressure"], "requirements": {"degrees": [], "majors": [], "languages": ["english", "mandarin"], "language_level": ["fluent"], "hard_skills": [], "soft_skills": ["independently", "work under pressure"], "languages_combined": [{"language": "english", "language_level": ["fluent"]}, {"language": "mandarin", "language_level": ["fluent"]}]}, "experience_required": {"duration": ["15 years"], "field": ["garment"]}}, {"job_id": "100003009033614", "location_code": "hk", "company": "C.F.L. Enterprise Limited", "job_title": "Merchandiser - Knit", "description": "Responsibilities:\n\nLiaison with customers & factories from development to shipment\nMaterials sourcing\nCost analysis & price negotiation with suppliers\nResponsible for\u00a0development/production follow up, order execution\nEnsure the product development/production processes are smooth and accurate information transfer to all relevant parties\nLiaison with Fabric, QC & Logistics team\nPerform other ad hoc duties as assigned\n\n\u00a0Requirements:\n\nDiploma or above, preferably major in Textile and Clothing\nAt least 3 - 5 year experiences in handling knit items\nExperiences in US market will be an advantage\nAble to work independently and under tight schedule\nProficiency in both spoken and written English\nGood computer skill", "employment_types": ["Full Time"], "selling_points": [], "locations": ["Kowloon Bay"], "categories": ["Merchandising & Purchasing", "Textiles"], "post_time": "2022-01-10T01:20:14Z", "salary": {"currency": null, "max": null, "min": null, "period": "monthly", "term": null}, "salary_visible": false, "title_keywords": ["merchandiser"], "responsibilities": ["ad hoc duties", "cost analysis", "logistics", "price negotiation"], "requirements": {"degrees": ["diploma or above"], "majors": [], "languages": ["english"], "language_level": ["proficiency"], "hard_skills": ["computer skill"], "soft_skills": ["work independently"], "languages_combined": [{"language": "english", "language_level": ["proficiency"]}]}, "experience_required": {"duration": ["at least 3 - 5 year"], "field": []}}, {"job_id": "100003009029021", "location_code": "hk", "company": "Hong Kong Aosheng Hi-Tech Limited", "job_title": "Shipping Officer/ Clerk", "description": "F.7 or above with at least 5 years of shipping experience\nHands on experience in handling full set of shipping and banking documents independently (I/E & L/C documents, customs clearance, etc.) within a manufacturing field\nMust have solid experience in issuing LC documents\u00a0\nCoordinate with suppliers & factories to ensure prompt delivery of goods\nGood command of English & Mandarin\nMature, independent and able to work under pressure\nImmediate available preferred\nWe offer a competitive salary package and 5 days work to the right applicant.\u00a0 Interested parties please send full resume with current & expected salary and date of availability via email.", "employment_types": ["Full Time"], "selling_points": [], "locations": ["Kwai Hing"], "categories": ["Merchandising & Purchasing", "Textiles"], "post_time": "2022-01-09T07:26:40Z", "salary": {"currency": null, "max": null, "min": null, "period": "monthly", "term": null}, "salary_visible": false, "title_keywords": ["clerk", "shipping officer"], "responsibilities": ["work under pressure", "shipping", "coordinate with", "banking"], "requirements": {"degrees": [], "majors": [], "languages": ["english", "mandarin"], "language_level": ["good command"], "hard_skills": ["c"], "soft_skills": ["independently", "independent", "prompt", "mature", "hands on", "work under pressure"], "languages_combined": [{"language": "english", "language_level": ["good command"]}, {"language": "mandarin", "language_level": ["good command"]}]}, "experience_required": {"duration": ["at least 5 years"], "field": ["banking"]}}, {"job_id": "100003009043702", "location_code": "hk", "company": "C.F.L. Enterprise Limited", "job_title": "Senior Merchandising Manager - Woven", "description": "Responsibilities:\n\nTo follow-up and monitor the whole merchandising flow within the team from sample fitting to bulk production till shipment by in-depth technical knowledge\nStrive to understand customers\u2019 requirement and work closely to provide our best professional service\nTo work closely with supporting team to ensure fitting, washing, and lab-testing etc\nTo source and evaluate factory from the perspective of product, pricing, quality, reliability, compliance to meet the interest of customers\nTo ensure the product quality control\nTo lead the production team and coach them to upgrade product knowledge, merchandising skills and overall effectiveness\u00a0\nWilling to travel to China\n\nRequirements:\n\nHigher Diploma or above, preferably major in Textile and Clothing\nAt least\u00a010 years working experience in merchandising for USA market\nStrong\u00a0garment knowledge for\u00a0woven casual, technical & performance wear\nDetail-minded, able to work independently and under tight schedule\u00a0\nStrong leadership, communication and problem solving skills\nProficiency in both spoken and written English and Mandarin\nGood computer & presentation skills\nSelf-motivated and able to define, plan and implement tasks in a team environment", "employment_types": ["Full Time"], "selling_points": [], "locations": ["Kowloon Bay"], "categories": ["Merchandising & Purchasing", "Textiles"], "post_time": "2022-01-13T01:32:39Z", "salary": {"currency": null, "max": null, "min": null, "period": "monthly", "term": null}, "salary_visible": false, "title_keywords": ["merchandising manager"], "responsibilities": ["compliance", "merchandising", "monitor", "quality", "testing", "evaluate", "quality control"], "requirements": {"degrees": ["higher diploma or above"], "majors": [], "languages": ["english", "mandarin"], "language_level": ["proficiency"], "hard_skills": ["problem solving skills"], "soft_skills": ["detail-minded", "work independently", "self-motivated", "communication", "presentation skills", "problem solving skills", "leadership"], "languages_combined": [{"language": "english", "language_level": ["proficiency"]}, {"language": "mandarin", "language_level": ["proficiency"]}]}, "experience_required": {"duration": ["at least 10 years"], "field": ["merchandising"]}}, {"job_id": "100003009041517", "location_code": "hk", "company": "C.F.L. Enterprise Limited", "job_title": "IT - Technical Support Supervisor", "description": "Responsibilities:\n\nProvide on site/remote support for end users;\nProvide Cloud infrastructure and maintain Microsoft Azure cloud services, Office\u00a0365, SharePoint services and security setup;\u00a0\nMaintain operations of company LAN, WLAN, MPLS, WAN and maintain\u00a0all IT related equipment; firewall and related devices;\nMaintain operation of virtual infrastructure and fine tune resources according to utilization;\nEstablish disaster recovery plan and procedure and carry out regular backup;\nIntroduce IT technologies to the company, carry out product / services; evaluation and cost comparison\nFormulate IT capex and opex budget;\nSupervise subordinates\n\nRequirements:\n\nDegree holder in Computer Science or related disciplines.\n3 years or above working experience in IT technical support or related fields, candidate with less experience will be considered for the post of Technical Support Engineer.\nExperiences in the following technologies are preferred:\nMicrosoft Azure Cloud, Microsoft AD\nNetwork technologies: TCP/IP, MPLS, routing, switch, router, wireless, IP phone, video conference\nFirewall, VPN, end points protection, digital certificates\nVMWare\nDisaster recovery, backup\nGood command of both written and spoken in Chinese, English and Mandarin", "employment_types": ["Full Time"], "selling_points": [], "locations": ["Kowloon Bay"], "categories": ["Merchandising & Purchasing", "Textiles"], "post_time": "2022-01-12T03:59:21Z", "salary": {"currency": null, "max": null, "min": null, "period": "monthly", "term": null}, "salary_visible": false, "title_keywords": ["technical support", "supervisor"], "responsibilities": ["cost", "operations", "infrastructure", "capex", "budget", "opex", "maintain", "plan", "evaluation", "setup"], "requirements": {"degrees": ["degree holder"], "majors": ["related disciplines", "computer science"], "languages": ["english", "chinese", "mandarin"], "language_level": ["good command"], "hard_skills": ["azure", "vmware", "tcp", "switch", "router", "ip", "vpn", "firewall"], "soft_skills": [], "languages_combined": [{"language": "english", "language_level": ["good command"]}, {"language": "chinese", "language_level": ["good command"]}, {"language": "mandarin", "language_level": ["good command"]}]}, "experience_required": {"duration": ["3 years"], "field": ["related", "it technical support"]}}, {"job_id": "100003009036145", "location_code": "hk", "company": "Varner Far East Limited", "job_title": "Garment Technician", "description": "VARNER Group is one of the largest fashion retailers in Scandinavia, consisting of 6 retail concepts, with nearly 11,000 employees and 1,400 stores across 6 countries.\u00a0We have a production office based in Hong Kong and supporting offices in Hangzhou and Beijing. We are now seeking a high caliber\u00a0candidate to fill the Varner Far East Garment Technician position at our Hong Kong office.\n\nThe Garment Technician has a problem-solving role with the aim to communicate with internal stakeholders effectively about a specific matter. The Technician works with a specific product, finds the best practice and instructs effectively on how to proceed.\u00a0 The Technician works closely alongside the Pattern and Measurement\u00a0Department at the HQ, designers, buyers, suppliers, merchandisers and QC team.\u00a0\n\nMajor areas of responsibility:\n\nMeasuring and evaluating samples (development, fit, size-set, pre-production and shipment) before submitting to our HQ.\nUnderstanding garment construction techniques and suitability for bulk production.\nEstablish communication between internal stakeholders and suppliers.\nGuide suppliers to make necessary corrections with clear instructions.\nCollaborate with suppliers to improve understanding of our brands' fitting requirements.\nBeing part of risk analysis of product quality.\nExecuting follow-up and documentation in internal software.\n\nThe position requires frequent travelling in China/Far East region.\u00a0It is estimated that 3-5 days a month will be spent traveling.\u00a0You will be reporting to Varner Far East Production Office Manager.\n\nRequired experience:\n\nStrong technical knowledge in pattern making, garment sewing, construction, fitting and grading.\nPreferably experienced on different product groups.\u00a0Candidates with strong lingerie experience and knowledge will be prioritized.\nLiterate in Microsoft office programs, exposure to PLM, Pattern CAD/CAM system and 3D would be an advantage\nMinimum 3 years working experience at sourcing offices and/or in production.\nHigher Diploma or above in Fashion Design, Fashion Technology, Technical Design, Clothing studies or related disciplines.\n\nPersonality:\n\nResults oriented and efficient\nAbility to work independently\nPro-active and problem solver\nWell organized and good planning abilities\nExcellent communication skills\nHonest, positive and outgoing\n\nLanguage skills: Excellent skills in written and spoken Mandarin and English.\n\nAn attractive package and 5-day work week will be offered to the right candidate.\nWe can offer a position in a dynamic and results driven organization\u00a0built on the following values;\nBusiness Minded, Passion, Make it Easy, Friendship, Happiness, and Responsibility.\n\nInterested parties please apply with full resume, state current and expected salaries and available\u00a0starting date by clicking\u00a0\"Apply Now\".", "employment_types": ["Full Time"], "selling_points": [], "locations": ["Hung Hom"], "categories": ["Manufacturing", "Garment / Textile", "Merchandising & Purchasing", "Woven / Knit", "Textiles"], "post_time": "2022-01-10T16:52:47Z", "salary": {"currency": null, "max": null, "min": null, "period": "monthly", "term": null}, "salary_visible": false, "title_keywords": ["technician"], "responsibilities": ["communicate with", "collaborate with", "reporting", "software", "measurement", "quality", "design", "communication", "executing", "risk analysis", "documentation", "pre-production", "planning"], "requirements": {"degrees": ["higher diploma or above"], "majors": ["related disciplines", "design"], "languages": ["english", "mandarin"], "language_level": ["excellent"], "hard_skills": ["microsoft office", "cad", "problem-solving", "analysis", "make", "dynamic", "documentation"], "soft_skills": ["efficient", "communication skills", "work independently", "outgoing", "problem solver", "problem-solving", "well organized", "communication", "clear", "business minded", "dynamic", "honest", "pro-active", "driven", "positive"], "languages_combined": [{"language": "english", "language_level": ["excellent"]}, {"language": "mandarin", "language_level": ["excellent"]}]}, "experience_required": {"duration": ["minimum 3 years"], "field": []}}, {"job_id": "100003009036152", "location_code": "hk", "company": "Randstad Hong Kong Limited", "job_title": "Senior Merchandiser (Bags, Gift & Premium)", "description": "about the company.\n\nMy client is a multinational sourcing company with over 50 offices across the globe. They focus on provide promotional innovation to a wide range of clients including brands, retailers, department stores and e-commerce companies. Currently they are hiring a Senior Merchandiser to join their highly successful team.\nabout the job.\nHandle daily merchandising activities in costing, product development to production\nResponsible for product innovation and proposing cost saving opportunities\nWork closely with overseas customers and suppliers for quatation follow up, sample arrangement and order follw up\nGood technical knowledge in bags, pouches, backpack, shopping bags etc.\nIdentify, address and resolve any issues in different stages and provide recommendations to facilitate effective business decision making\nEnsure on time delivery of tasks and projects\n\nskills and experience required.\n\nDiploma or above\n5+ years merchandising experience in sourcing & product development\nExperience in bags/ beauty pouches would be an advantage\nOpen minded, flexible, organised and independent\nSelf-motivated, hard-working and able to work under pressure\nGood negotiation skills and problem solving skills\nGood command of English, Cantonese and Mandarin\nWilling to travel\n\nabout the package.\n\n5 days work\nFast Track Promotion\nDouble Pay\nFriendly Working Culture\nMedical\n\nIf you're interested in this role, click 'apply now' or email cecilia.ng@randstad.com.hk to forward an up-to-date copy of your CV, or call Cecilia NG at 2232 3444. If this is not your ideal job but you are looking out, please contact us for a discussion on your career preferences.", "employment_types": ["Full Time", "Permanent"], "selling_points": [], "locations": ["Not Specified"], "categories": ["Merchandising & Purchasing", "Textiles", "Sundries", "Procurement / Purchasing / Sourcing"], "post_time": "2022-01-10T09:29:16Z", "salary": {"currency": null, "max": null, "min": null, "period": "monthly", "term": null}, "salary_visible": false, "title_keywords": ["senior merchandiser"], "responsibilities": ["cost", "ensure on time delivery", "merchandising", "provide recommendations", "contact", "work under pressure"], "requirements": {"degrees": ["diploma or above"], "majors": [], "languages": ["cantonese", "english", "mandarin"], "language_level": ["good command"], "hard_skills": ["focus", "problem solving skills", "e-commerce"], "soft_skills": ["flexible", "self-motivated", "independent", "ideal", "responsible", "work under pressure", "interested in", "negotiation skills", "problem solving skills", "hard-working", "open minded", "friendly", "organised", "focus", "decision making"], "languages_combined": [{"language": "cantonese", "language_level": ["good command"]}, {"language": "english", "language_level": ["good command"]}, {"language": "mandarin", "language_level": ["good command"]}]}, "experience_required": {"duration": ["5+ years"], "field": ["product development", "merchandising", "beauty"]}}, {"job_id": "100003009035400", "location_code": "hk", "company": "Top Grade International Enterprise Limited", "job_title": "Merchandiser - Apparel", "description": "Responsibilities\n\n\u30fbFollow up order with oversea vendors, customers, and internal parties to ensure customer satisfaction and on-time delivery.\n\u30fbCo-ordinate with Team to ensure that all products routinely and consistently meet acceptable standards required by customer/team leader.\n\u30fbArrange sample development, Design sheet translations, production monitoring\n\u30fbAssist in creating and enhancing long-term business relationships with our customers to maximise business growth and opportunities.\n\u30fbAssist in the Product Development process to ensure that products meet customers' quality and budget requirements.\n\u30fbAssist to developing new business opportunities with customers.\n\nRequirements\n\n\u30fbExperience in wholesales Market/ Premium Fashion for Japan Market.\n\u30fbDiploma/ or Above in Merchandising or Textile / Clothing discipline\n\u30fbMerchandiser 2-3 years' relevant experience\n\u30fbOffshore production relevant experience (Example, Bangladesh, Cambodia, Vietnam\u2026\u2026)\n\u30fbInovative, willing to learn, hardworking, well-organized and teamwork spirit required.\n\u30fbAble to work under pressure, excellent communication skills and an eye for details will be appreciated.\n\u30fbWell organized indidvidual, able to manage multiple tasks, strong problem solving skills, able to meet deadlines.\n\u30fbStrong Product and material knowledge with good development skills, and familiar with merchandising and product development and production process.\n\u30fbGood command of written and spoken English , Cantonese and Mandarin Japanese (JLPT Level 2 or above) preferred.\n\n\u00a0Attractive benefits including 5 days work, 13months salary , medical benefit will be offered to the qualified candidate.", "employment_types": ["Full Time"], "selling_points": [], "locations": ["Lai Chi Kok"], "categories": ["Merchandising & Purchasing", "Textiles"], "post_time": "2022-01-10T07:02:31Z", "salary": {"currency": null, "max": null, "min": null, "period": "monthly", "term": null}, "salary_visible": false, "title_keywords": ["merchandiser"], "responsibilities": ["business opportunities", "budget", "monitoring", "quality", "design", "developing", "internal parties"], "requirements": {"degrees": [], "majors": [], "languages": ["cantonese", "japanese", "english", "mandarin"], "language_level": [], "hard_skills": ["problem solving skills"], "soft_skills": ["communication skills", "organized", "multiple tasks", "willing to learn", "well-organized", "teamwork spirit", "problem solving skills", "meet deadlines", "hardworking", "work under pressure"], "languages_combined": [{"language": "cantonese", "language_level": []}, {"language": "japanese", "language_level": []}, {"language": "english", "language_level": []}, {"language": "mandarin", "language_level": []}]}, "experience_required": {"duration": ["2-3 years"], "field": ["relevant experience"]}}, {"job_id": "100003009039122", "location_code": "hk", "company": "ImagineX Management Co Ltd", "job_title": "Part Time Clerk - Merchandising", "description": "Are you a passionate and yet creative talent who can think out of the box to driving the people agenda with a new approach? ImagineX Group is a premier retail, brand management and distribution company. We build luxury, designer and premium contemporary fashion, beauty and lifestyle businesses with an entrepreneurial approach and the passion and flair of a brand owner.\n\n\nWe are now inviting a creative, self-motivated, energetic and talented Part Time Clerk - Merchandising to join us.\u00a0\n\n\nWHAT YOU WILL BE DOING?\n\nAssist and support buyers in all matters relating to buying, operations and promotion initiatives\nProvide clerical support the team\nPerform other ad-hoc projects as assigned\nYOU NEED TO BE\u2026\nBachelor degree or above, undergraduate students are also welcome\u00a0\nStrong analytical and communication skills\nGood knowledge in MS Word, Excel and PowerPoint\nAble to work 3 days per week\nWE OFFER YOU\u2026\n\nFlexible working hour (total 3 working days a week)\nFree shuttle bus services\n\n\nInterested parties please send your Full resume with expected salary to us through \"Apply Now\"\u00a0 or\u00a0WhatsApp 6411 4891\n\nInformation provided will be treated in strict confidence and only be used for recruitment purpose. The Company may refer suitable applicants to other vacancies within the associated Group of companies.\nFor more information of ImagineX Group, please visit our web site at\u00a0http://www.imaginex.com.", "employment_types": ["Part Time"], "selling_points": ["Undergraduates are welcomed", "Able to work 3 days per week", "Free Shuttle Bus"], "locations": ["Southern Area"], "categories": ["Admin & HR", "Clerical / Admin Staff", "Merchandising & Purchasing", "Textiles", "Others"], "post_time": "2022-01-11T08:46:14Z", "salary": {"currency": null, "max": null, "min": null, "period": "hourly", "term": null}, "salary_visible": false, "title_keywords": ["part time clerk", "merchandising"], "responsibilities": ["provide clerical support", "management", "operations", "merchandising", "communication", "ad-hoc projects"], "requirements": {"degrees": ["degree or above", "bachelor"], "majors": [], "languages": [], "language_level": [], "hard_skills": ["excel", "powerpoint", "ms word"], "soft_skills": ["passionate", "communication skills", "self-motivated", "energetic", "creative"], "languages_combined": []}, "experience_required": {"duration": [], "field": []}}, {"job_id": "100003009039382", "location_code": "hk", "company": "CSG International Limited", "job_title": "Merchandiser for the Ski Wear, Functional Jacket & Pants , Padding & Down Proof", "description": "CSG International Limited\u00a0\n\n\u00a0We are a well-established conglomerate with businesses in garment manufacturing and trading of industrial in Hong Kong. We have our own manufacture in China and Myanmar. To cope with our expansion, we are seeking energetic and competent candidate to join us.\n\nManufactory background is a must\nGood command of spoken and written English and Chinese (Mandarin included)\nFrequent travel between China sample room and Hong Kong office\n5-10 years working experience in MEN's\u00a0& WOMAN's wear specially on sport and jacket for Europe markets (eg.\u00a0Ski Wear, Functional Jacket and Pants , Padding and Down Proof)\nKnowledge in material resources\nWell-organized, willing to work and able to work under pressure\nWilling to travel\u00a0\nImmediate available is preferred", "employment_types": ["Full Time"], "selling_points": [], "locations": ["Lai Chi Kok"], "categories": ["Merchandising & Purchasing", "Textiles"], "post_time": "2022-01-11T09:35:36Z", "salary": {"currency": null, "max": null, "min": null, "period": "monthly", "term": null}, "salary_visible": false, "title_keywords": ["merchandiser"], "responsibilities": ["work under pressure"], "requirements": {"degrees": [], "majors": [], "languages": ["english", "chinese", "mandarin"], "language_level": ["good command"], "hard_skills": [], "soft_skills": ["work under pressure", "energetic", "well-organized", "competent"], "languages_combined": [{"language": "english", "language_level": ["good command"]}, {"language": "chinese", "language_level": ["good command"]}, {"language": "mandarin", "language_level": ["good command"]}]}, "experience_required": {"duration": ["5-10 years"], "field": []}}, {"job_id": "100003009034484", "location_code": "hk", "company": "The Marketing Store Worldwide (Asia) Ltd", "job_title": "Merchandising Manager", "description": "PD & Sourcing Director (Sportswear)\n\nA global lifestyle retailer is now looking to hire a director for PD & sourcing to join their well-established business. Leading a team of over 15, you will be in charge of all sourcing and product development operations for product categories such as knits, sweater, accessories & swimwear, whilst reporting directly to the managing director.\n\nKey responsibilities: -\n\nSourcing & Vendor Management\nSupervise and lead all sourcing and product development operations\nConstant interaction and consultation on vendor capacity, order allocation etc\nObserve and understand in detail the buyer's needs and provide as much support as possible\nAnalyse, evaluate and improve vendor's capabilities and performance\nExpand or consolidate vendor base when appropriate\nPrice negotiation and create detailed cost saving plans and methods\nLead-time negotiation along with regular trouble shooting issues such as deliveries and quality issues\nProduct Development\nWork closely with suppliers on providing available products and new trends, technology\nFrequent communications with buyers and designers on available products on offer and manage all sampling processes\nDrive price negotiations and strive for meeting or exceeding target margins\nCommunications with internal support teams\nAssist in certain quality driven initiatives\nAssist in any quality issues, claims or disputes between buyers/QA with vendors\nMonitor potential quality issues and execute relative solutions to ensure they can be avoided\n\nRequirements: -\n\nBachelor's degree of above in Fashion or related discipline\nSelf-driven, flexible\nMinimum 15 years relevant sourcing experience with at least 5 years director level experience\nExcellent written and verbal Cantonese, Mandarin and English\nStrong product technical knowledge in sportswear, especially in knits is a must\nInternational travel is required and to production sites in Southeast Asia or otherwise\n\nInterested parties please send your CV to Vincent.chow@connectedgroup.com", "employment_types": ["Full Time", "Permanent"], "selling_points": ["Supply chain operations", "Experience in toys/premiums/sundries industry", "5-Day work week & Attractive Compensation Package"], "locations": ["Kowloon Bay"], "categories": ["Merchandising & Purchasing", "Textiles", "Toy", "Sundries"], "post_time": "2022-01-10T03:29:26Z", "salary": {"currency": null, "max": null, "min": null, "period": "monthly", "term": null}, "salary_visible": false, "title_keywords": ["merchandising manager"], "responsibilities": ["management", "price negotiation", "cost", "communications with", "operations", "quality", "teams", "monitor", "evaluate", "plans", "analyse"], "requirements": {"degrees": ["degree", "bachelor"], "majors": [], "languages": ["cantonese", "english", "mandarin"], "language_level": ["excellent"], "hard_skills": [], "soft_skills": ["flexible", "driven"], "languages_combined": [{"language": "cantonese", "language_level": ["excellent"]}, {"language": "english", "language_level": ["excellent"]}, {"language": "mandarin", "language_level": ["excellent"]}]}, "experience_required": {"duration": ["at least 5 years", "minimum 15 years"], "field": []}}, {"job_id": "100003009030365", "location_code": "hk", "company": "MGF Sourcing Far East, Limited", "job_title": "Technologist, Fit", "description": "This position is responsible for supporting the development and production in the region. Manages the technical development process and to work with the customer side (technical designers) and regional production team (merchandising team, QA team and vendors), taking responsibility for the technical development of new styles and the application of all quality standards relating to fit and construction.\n\nPRINCIPAL DUTIES & RESPONSIBILITIES:\n\nWork with PD team on the customer new development such as construction, size specification and modification\nDevelop the client-approved block and instruct the sample production factories to use the specified pattern\nReview from product development stage to ensure factories fully understand and will follow the first fit sample\nValidate the sample submission per Time and Action calendar and execute timely\nReview samples per customers\u2019 specification and construction details. Visit factories to troubleshoot and make corrective arrangement Join PP meetings for quality enhancement and urge for TOP samples if necessary\nPrepare and submit monthly report for Brand Leaders for overviewing sample performance\nWork with Brand Leaders to address underperforming factories and set up remedial measures\nFactory visit to measure factory improvement progress and alert merchandising team on relative sample weakness\nJOB SPECIFICATIONS (e.g. Qualification, Job Experience):\n\nCollege degree or equivalent work experience\nMore than 4 years' related work experience in woven/knit manufacturing process in a factory, production management and quality control. Less experience will be considered as Associate Tech.\nA recognized expert with about 6 years of pattern making/grading and machinery limitations\nAble to provide constructive solutions and directions for manufacturer to improve fit and product appearance\nGood analytical skills to solve complex technical problems which have impact to the business\nWe offer 5\u2013day work week, attractive compensation package and comprehensive employee benefits to the right candidate. Interested parties please send your full resume with your existing salary and expected salary by clicking \"Apply Now\".\n\nAll personal information collected will be kept for employment related purposes only", "employment_types": ["Full Time", "Permanent"], "selling_points": ["Quality standards relating to fit and construction", "4+ years\u2019 Woven/Knit Fit Tech exp. for US market", "Double pay & comprehensive benefit scheme"], "locations": ["Kwun Tong"], "categories": ["Manufacturing", "Garment / Textile", "Merchandising & Purchasing", "Fabrics", "Textiles"], "post_time": "2022-01-09T23:42:51Z", "salary": {"currency": null, "max": null, "min": null, "period": "monthly", "term": null}, "salary_visible": false, "title_keywords": [], "responsibilities": ["management", "review", "quality", "merchandising", "develop", "specifications", "troubleshoot", "monthly report", "quality control"], "requirements": {"degrees": ["degree"], "majors": [], "languages": [], "language_level": [], "hard_skills": ["make", "analytical skills"], "soft_skills": ["responsible", "timely", "analytical skills", "troubleshoot", "constructive"], "languages_combined": []}, "experience_required": {"duration": ["4 years"], "field": ["management", "manufacturing", "related", "tech", "quality control"]}}, {"job_id": "100003009034379", "location_code": "hk", "company": "Bluestream Limited", "job_title": "Customer Service Garments", "description": "Job Responsibilities\n\nWork closely with Product Development teams and vendors on price negotiations, sample development and approvals.\nCommunicate and negotiate with factories for samples development, cost analysis, etc. to meet client\u2019s quality, cost requirement and due dates.\nFollow-up and monitor orders to ensure quality control and on-time delivery.\nMonitor production schedule to make sure on \u2013time delivery.\n\nJob Requirements\n\nMinimum 2 years working experience in Customer Service and sourcing. Knowledge in labels and garment items are preferable.\u00a0\nDetail-minded, flexible, self-initiative with excellent interpersonal skills.\nNeed to be able to work under pressure, be very clear-minded to handle multi-tasks and project details.\nAbility to work independently and good problem solving skills.\nProficiency in spoken and written English & Chinese (Cantonese & Mandarin).\nProficiency in MS Office applications including Word, Excel and Vlookup.\nImmediate available is preferable.", "employment_types": ["Full Time"], "selling_points": [], "locations": ["Tuen Mun Area"], "categories": ["Admin & HR", "Clerical / Admin Staff", "Manufacturing", "Garment / Textile", "Merchandising & Purchasing", "Textiles"], "post_time": "2022-01-10T03:16:53Z", "salary": {"currency": null, "max": null, "min": null, "period": "monthly", "term": null}, "salary_visible": false, "title_keywords": ["customer service"], "responsibilities": ["cost", "quality", "teams", "monitor", "schedule", "quality control", "cost analysis", "negotiate with factories"], "requirements": {"degrees": [], "majors": [], "languages": ["cantonese", "english", "chinese", "mandarin"], "language_level": ["proficiency"], "hard_skills": ["excel", "vlookup", "word", "problem solving skills", "ms office"], "soft_skills": ["detail-minded", "flexible", "work independently", "multi-tasks", "clear", "customer service", "self-initiative", "interpersonal skills", "problem solving skills", "work under pressure"], "languages_combined": [{"language": "cantonese", "language_level": ["proficiency"]}, {"language": "english", "language_level": ["proficiency"]}, {"language": "chinese", "language_level": ["proficiency"]}, {"language": "mandarin", "language_level": ["proficiency"]}]}, "experience_required": {"duration": ["minimum 2 years"], "field": ["customer service"]}}, {"job_id": "100003009034268", "location_code": "hk", "company": "Legend Swimwear Factory Ltd", "job_title": "Assistant General Manager \u2013 Merchandising & Central Procurement", "description": "Major roles:\n\nEffectively lead and manage the Merchandising & Purchasing and Central Procurement teams as part of monitoring the critical path from product development to goods delivery;\nReport to the Chief Commercial Officer;\nKeep abreast of the market trend and carry out excellent customer relationship management to meet different markets\u2019 and customers\u2019 changing needs in a competitive approach;\nSet sourcing strategies for relevant countries of origin, in particular China and Vietnam, in support of new and existing product development;\nDevise innovative approach to achieve best pricing;\nDevise best-in-class and continue to improve procurement processes, and provide direction on assessing and monitoring supplier capabilities in the areas of fabric and trims;\nSupport business growth strategies across customer accounts by providing insights and directions on business model based on the company\u2019s strengths and dynamic global market situation.\nSet up sales and sourcing strategies and targets for different sales regions / customers / suppliers and to strive for meeting / exceeding the related KPIs;\nStation in Guangdong province for 4 days per week and in Hong Kong for 1 day per week;\nOccasional overseas travelling required;\n\nRequirements:\n\nBachelor\u2019s degree holder or above in Fashion / Textiles / Clothing or related disciplines, with at least 10 years\u2019 experience at managerial level in the apparel industry;\nA mature leader, independent, pro-active, well-organised, creative, and result-oriented;\nStrong business acumen, analytical, problems solving, and negotiation skills;\nKnowledgeable and experienced in product development, sourcing, and production processes, preferably in the lingerie / swimwear areas, and European / North American experience & exposure, a definite asset;\nStrong interpersonal and communication skills and good command of written and spoken English and Chinese;\nProficient in computer applications, such as MS Office / ERP system\n\nWe offer a competitive compensation package to the right candidate.\u00a0Please apply with full resume including salary expectation and availability by clicking \"Apply Now\".\n\nAll data collected will only be used for recruitment purpose and kept confidential.", "employment_types": ["Full Time"], "selling_points": [], "locations": ["Others - China"], "categories": ["Manufacturing", "Garment / Textile", "Merchandising & Purchasing", "Textiles", "Procurement / Purchasing / Sourcing"], "post_time": "2022-01-10T03:03:32Z", "salary": {"currency": null, "max": null, "min": null, "period": "monthly", "term": null}, "salary_visible": false, "title_keywords": ["assistant general manager", "merchandising"], "responsibilities": ["management", "problems solving", "provide direction", "procurement processes", "monitoring", "teams", "merchandising", "communication", "computer applications", "kpis", "report"], "requirements": {"degrees": ["bachelor", "degree holder"], "majors": ["related disciplines"], "languages": ["english", "chinese"], "language_level": ["good command"], "hard_skills": ["erp system", "dynamic", "ms office", "acumen"], "soft_skills": ["communication skills", "independent", "creative", "interpersonal", "business acumen", "mature", "negotiation skills", "dynamic", "pro-active", "well-organised", "innovative", "result-oriented"], "languages_combined": [{"language": "english", "language_level": ["good command"]}, {"language": "chinese", "language_level": ["good command"]}]}, "experience_required": {"duration": ["at least 10 years"], "field": ["related", "managerial", "product development"]}}, {"job_id": "100003009039654", "location_code": "hk", "company": "Magic Search Limited", "job_title": "Men's Buying Manager (Fashion Group)", "description": "Our client is a renowned fashion brand and and their shops locate in prestigious business area. To cope with their business expansion, they are looking for a\u00a0Men's Buying Manager to join the team.\n\nThe Job :\n\nBuild sales projections from a business perspective for Retail and Merchandising\nDevelop OTB budgets to insure Countries\u2019 budgets and buy plans are executed in accordance to company strategies\nPrepare analysis with insights, regular business reviews to flag risks and opportunities\nSupervise and support planners to ensure merchandise appear in the right store at the right time and in the right quantities and assortment, involving planning stock levels and monitoring sales performance\nSet up OTB procedures for the region so that country heads and buyers are clear of objectives and actions for their buys\nPartner with Merchandising and Retail to lay out action plans for risks and opportunities identified\nBuild planning modules for core & continuative merchandise\nConsolidate weekly/monthly sales analysis for regular working with planners and buyers to understand business\nRecommend price index and gross margins (maximise ROI) for the region and for each country\nAnalyze end of season markdowns and propose markdown strategies based on inventory and sales analysis by countries, by locations to ensure cohesive flow from one season to the next\nAnalyze intended orders and determine whether the orders are coherent to the business objectives\nAnticipate shipments, receipting capacity, display, BOH of each country to minimize congestions, maximize sales opportunities, sell through, and margins by working closely with logistics\nPerform effective inventory control, inventory management best practices\nAd hoc projects as assigned\n\nThe Candidate:\n\nBachelor\u2019s degree with a minimum of 5 - 8 years merchandising/ buying experience in related business or brand\nAn accomplished individual, able to demonstrate excellent people management skills\nMust have fashion or premium product background\nBe a strong communicator, with the gravitas to report to the top level within the business\nDemonstrate proven results in driving sales\nStrong leadership skills with the ability to motivate and develop a team\nExcellent command of both written and spoken English & Mandarin\nImmediate available is preferred\n\n\nAll information provided will be treated in strict confidence and used solely for recruitment purposes. To apply, please quote current and expected salary and send your CV through \" APPLY NOW\"", "employment_types": ["Full Time", "Permanent"], "selling_points": ["Buying Manager", "OTB Planning", "Attractive salary package"], "locations": ["Not Specified"], "categories": ["Merchandising & Purchasing", "Handbag", "Textiles", "Sales, CS & Business Devpt", "Wholesale"], "post_time": "2022-01-11T10:23:25Z", "salary": {"currency": null, "max": null, "min": null, "period": "monthly", "term": null}, "salary_visible": false, "title_keywords": ["buying manager"], "responsibilities": ["inventory", "merchandising", "otb", "inventory management", "plans", "sales performance", "develop", "logistics", "report", "management", "monitoring", "procedures", "inventory control", "gross margins", "budgets", "analysis", "ad hoc projects", "recruitment", "planning"], "requirements": {"degrees": ["degree", "bachelor"], "majors": ["business"], "languages": ["english", "mandarin"], "language_level": ["excellent"], "hard_skills": ["analysis"], "soft_skills": ["confidence", "leadership skills", "coherent", "cohesive", "clear", "communicator"], "languages_combined": [{"language": "english", "language_level": ["excellent"]}, {"language": "mandarin", "language_level": ["excellent"]}]}, "experience_required": {"duration": ["minimum of 5 - 8 years"], "field": ["related", "business", "merchandising", "brand"]}}, {"job_id": "100003009027611", "location_code": "hk", "company": "ALF Retail Hong Kong Limited", "job_title": "Buying Assistant \u2013 Womenswear  (Brand: Marks and Spencer)", "description": "Reporting to the Buyer, the incumbent will be responsible for:\n\nProviding clerical and administrative support to the buying team in an effective and timely manner\nRegular data entries and data maintenance in SAP & UK IRP systems\u00a0\nAssisting in the preparation/collation of weekly management reports\nSeasonal catalogue maintenance\nManaging stock allocation to all retail stores and price maintenance\nHandling administrative duties and responsible for ad hoc projects independently as required\nJob Requirements:\nSecondary educated with a minimum of 1 year working experience/ recent\u00a0graduates will be considered\u00a0\nProficient in both Windows and MS Excel\nAttentive to details, good numerical sense and organizational skills\nSelf-driven, energetic, well-organized and able to play as a good team-player\nFast learner with positive working attitude\nExcellent communication, interpersonal and presentation skills\nSAP experience is an added advantage\nIf you are interested in this role, please send your full resume together with your current and expected salary to us.\u00a0\n\n\n\nApply by\u00a0clicking \"Apply Now\"\n\nHuman Resources Department: Unit 1806B-10, 18/F, Exchange Tower, 33 Wang Chiu Road, Kowloon Bay, Kowloon, Hong Kong\n\n\n\nPersonal information received from applicants will be kept confidential and used for employment-related purposes only.", "employment_types": ["Full Time", "Permanent"], "selling_points": ["Secondary educated or fresh graduates", "Providing clerical and administrative support", "Proficient in both Windows and MS Excel"], "locations": ["Kowloon Bay"], "categories": ["Admin & HR", "Clerical / Admin Staff", "Merchandising & Purchasing", "Textiles", "Sales, CS & Business Devpt", "Others"], "post_time": "2022-01-06T10:37:03Z", "salary": {"currency": null, "max": null, "min": null, "period": "monthly", "term": null}, "salary_visible": false, "title_keywords": ["buying assistant"], "responsibilities": ["reporting", "maintenance", "data", "administrative support", "stock allocation", "systems", "communication", "management reports", "administrative duties", "ad hoc projects", "price maintenance", "catalogue"], "requirements": {"degrees": [], "majors": [], "languages": [], "language_level": [], "hard_skills": ["sap", "maintenance", "management reports", "ms excel", "exchange"], "soft_skills": ["organizational skills", "independently", "attentive to details", "responsible", "team-player", "interpersonal", "timely", "interested in", "well-organized", "communication", "positive working attitude", "presentation skills", "energetic", "fast learner", "driven"], "languages_combined": []}, "experience_required": {"duration": ["minimum of 1 year"], "field": []}}, {"job_id": "100003009030634", "location_code": "hk", "company": "Gap International Sourcing Ltd", "job_title": "Senior Merchandiser  - Knits", "description": "About the role\nThe Senior Merchandiser, Product Development will be responsible for developing the garment samples for the assigned product / style while working closely with the Merchandising teams of the Vendors. As part of product development team s/he will also be providing support in identifying opportunities of cost saving, onboarding new vendors and executing the innovation agenda for the department in the assigned product.\n\nWhat you will do\n\n\nDownloads tech pack and BOM. Works with vendors for development sampling and initial costs.\nManages counter costing; Handling samples; Tracking fit approvals; Tracking lab dips.\nFollowing up with vendor on system-updates. Manages wear-test samples and tailoring samples.\nEnsures Systems are updated with costs and details. Coordinates MST legacy ID communications for purchase order.\nPartners with brand Design, R&D and key suppliers to develop innovative and quality product.\nPartners with Mill management, QA and technical teams to resolve fabric or quality issues.\nResolves issues within a timely manner while working to continuously improve and create internal and external processes and procedures.\nWho you are\n\nMerchandise Sourcing Knowledge \u2013 Experience in sample development and with offshore production exposure; in large-sized buying office or trading company ; handling Plus size products is a must (Please specify Plus size products experience in detail)\nPlanning & Influencing \u2013 proven experience in plan, prioritize and influence at all levels\nDrive Results \u2013 ability to analyze situations and proactively suggest solutions to meet deliverables\nLearning Agility & Experimentation \u2013 demonstrates eagerness to learn and explore new ways of approaching goals\nEffective Communicator & Team Player - proven capability to communicate effectively, verbal and written\n\nFor over 50 years, Gap Inc. has done more than sell clothes \u2013 we give back to the community and engage in sustainability and environmental initiatives.\u00a0As our communities react to the global health crisis caused by COVID-19, our focus remains on supporting the health and livelihood of our employees while caring for our customers and communities.\u00a0To read more, visit\u00a0https://corporate.gapinc.com/en-us/news/coronavirus-response.\n\nGap Inc. is an equal-opportunity employer and continues to foster a diverse and inclusive environment. We have received numerous awards for our long-held commitment to equality. This year, we\u2019ve been named as one of the\u00a0Best Places to Work by the Humans Rights Campaign for the fifteenth consecutive year\u00a0and have been included in the\u00a02020 Bloomberg Gender-Equality Index for the\u00a0third year in a row.\u00a0\u00a0\n\nAny personal information collected relating to employment applications will be used for recruitment purposes only.\u00a0", "employment_types": ["Full Time"], "selling_points": ["Partner with regional teams", "Multicultural and dynamic environment", "WFH and Flexible working hour"], "locations": ["Kwun Tong"], "categories": ["Manufacturing", "Garment / Textile", "Merchandising & Purchasing", "Woven / Knit", "Textiles"], "post_time": "2022-01-07T07:57:26Z", "salary": {"currency": null, "max": null, "min": null, "period": "monthly", "term": null}, "salary_visible": false, "title_keywords": ["senior merchandiser"], "responsibilities": ["management", "systems", "quality", "teams", "design", "develop", "a timely manner", "procedures", "purchase", "costs", "tracking"], "requirements": {"degrees": [], "majors": [], "languages": [], "language_level": [], "hard_skills": ["plus", "bloomberg", "react", "gap", "focus"], "soft_skills": ["focus", "prioritize", "ability to analyze", "diverse", "learning", "team player", "communicator"], "languages_combined": []}, "experience_required": {"duration": [], "field": ["development", "planning"]}}, {"job_id": "100003009016146", "location_code": "hk", "company": "Xiu Xin Knitting Company", "job_title": "Merchandiser", "description": "Requirements :\n\n\u00a0Minimum 5 years merchandising experience in hosiery or/ and garment will be preferable.\nFamiliar with US market will be preferable.\nStrong order and production follow up, quality Inspection.\nSelf-motivated, responsible and can work independently.\nGood in English and Mandarin.\nGood PC knowledge.\nAble to work overtime if needed.\nImmediate available is preferable.\n\n\n\nWe offer :\n\nWe offer 5-days work, bank holiday and an attractive package to the successful candidate.", "employment_types": ["Full Time"], "selling_points": ["Minimum 5 years merchandising experience", "Familiar with US market will be preferable", "Immediate available is preferable"], "locations": ["Shatin Area"], "categories": ["Merchandising & Purchasing", "Woven / Knit", "Textiles", "Others"], "post_time": "2022-01-07T19:19:15Z", "salary": {"currency": null, "max": null, "min": null, "period": "monthly", "term": null}, "salary_visible": false, "title_keywords": ["merchandiser"], "responsibilities": ["quality", "merchandising", "inspection"], "requirements": {"degrees": [], "majors": [], "languages": ["english", "mandarin"], "language_level": ["good"], "hard_skills": ["pc knowledge"], "soft_skills": ["self-motivated", "work overtime", "work independently", "responsible"], "languages_combined": [{"language": "english", "language_level": ["good"]}, {"language": "mandarin", "language_level": ["good"]}]}, "experience_required": {"duration": ["minimum 5 years"], "field": ["garment", "merchandising"]}}, {"job_id": "100003009036632", "location_code": "hk", "company": "Bape Hong Kong Limited", "job_title": "Part Time Clerk", "description": "To assist internal departments for administrative support and related paper work\nWorking hours: Flexible 2-3 days per week\u00a0(Mondays - Fridays, 9:30 - 18:30)\nGood computer knowledge in MS Word, Excel and Chinese Word Processing\nBe responsible, initiative, hard working and well-organized\nImmediately available is preferred\nFresh graduate / undergraduates are welcome to apply\nCompetitive remuneration and benefit package will be offered to the right candidate. Please submit your application by clicking \"Apply Now\" below.\n\n\n\nAll data collected is for recruitment purpose only.", "employment_types": ["Part Time"], "selling_points": ["Fresh graduate / undergraduates are welcome", "Working hours: Flexible 2-3 days per week", "Immediately available is preferred"], "locations": ["Southern Area"], "categories": ["Merchandising & Purchasing", "Textiles", "Others", "Procurement / Purchasing / Sourcing"], "post_time": "2022-01-10T11:29:59Z", "salary": {"currency": null, "max": null, "min": null, "period": "hourly", "term": null}, "salary_visible": false, "title_keywords": ["part time clerk"], "responsibilities": ["recruitment", "data", "administrative support"], "requirements": {"degrees": ["fresh graduate"], "majors": [], "languages": ["chinese"], "language_level": ["good"], "hard_skills": ["excel", "chinese word processing", "ms word"], "soft_skills": ["flexible", "responsible", "hard working", "well-organized", "initiative"], "languages_combined": [{"language": "chinese", "language_level": ["good"]}]}, "experience_required": {"duration": [], "field": []}}, {"job_id": "100003009036272", "location_code": "hk", "company": "I.T Apparels Limited", "job_title": "Assistant Merchandise Planner (REF:JDB-IT-AMP)", "description": "Accountabilities \u2013 Key Result Areas\n\nAssist monitoring of OTB, pre-season and in-season sales forecast, margin, receipts and inventory on a monthly basis.\u00a0\nWork closely with buyers to monitor planned sales, planned gross profit, and planned markdowns\nManage good balance of stock level among stores\nManage mark down during sale period so as to maximize sales and maintain planned gross profit\nEnsure that on-order and committed receipts are delivering on time to support forecasts and sales\nAssist report preparations on sales trends and patterns, stock replenishment and inventory level in weekly cycle\nMonitor periodically the stock level, merchandise allocation plan, logistics flow from ordering to delivery at stores\u00a0\nWork with cross functional team and stores to create transfers and as needed to drive sales.\nTo support ad-hoc assignments or inventory related projects\n\nExperience / Qualification Requirements\n\nDegree holder in business or supply chain related discipline\n2 years working experience in a planning, buying or merchandising function\nHighly sensitive to figures and strong analytical skills\nAttention to detail with high level of accuracy\nGood interpersonal skills and presentation skills\nCandidates with less experience will be considered as Assistant Merchandise Planner\u00a0\n\nCompetitive remuneration and benefit package will be offered to the right candidate. Please submit your application by clicking \"Apply Now\" below.\n\nAll data collected is for recruitment purpose only.\n\nSure you want to know more about our company and brands, simply follow our\n\nWEBSITE at\u00a0http://www.ithk.com\u00a0 \u00a0 \u00a0 \u00a0 \u00a0 \u00a0 \u00a0 \u00a0 \u00a0 \u00a0 \u00a0 \u00a0 \u00a0 \u00a0 \u00a0 \u00a0 \u00a0 \u00a0 \u00a0 \u00a0 \u00a0 \u00a0 \u00a0 \u00a0 \u00a0 \u00a0 \u00a0 \u00a0 \u00a0 \u00a0 \u00a0 \u00a0 \u00a0 \u00a0\u00a0\n\nFACEBOOK at\u00a0http://www.facebook.com/I.Ttheofficialpage\u00a0 \u00a0 \u00a0 \u00a0 \u00a0 \u00a0 \u00a0 \u00a0 \u00a0 \u00a0 \u00a0 \u00a0 \u00a0 \u00a0\u00a0\n\nINSTAGRAM at\u00a0http://instagram.com/ithk\u00a0 \u00a0 \u00a0 \u00a0 \u00a0 \u00a0 \u00a0 \u00a0 \u00a0 \u00a0 \u00a0 \u00a0 \u00a0 \u00a0 \u00a0 \u00a0 \u00a0 \u00a0 \u00a0 \u00a0 \u00a0 \u00a0 \u00a0 \u00a0 \u00a0 \u00a0 \u00a0 \u00a0\n\nWEIBO at\u00a0http://e.weibo.com/ithongkong", "employment_types": ["Full Time", "Permanent"], "selling_points": ["Degree holder in business or supply chain", "2 years working experience", "Assist monitoring of OTB, pre-season"], "locations": ["Southern Area"], "categories": ["Merchandising & Purchasing", "Textiles", "Procurement / Purchasing / Sourcing", "Sales, CS & Business Devpt", "Retail Sales"], "post_time": "2022-01-10T09:52:24Z", "salary": {"currency": null, "max": null, "min": null, "period": "monthly", "term": null}, "salary_visible": false, "title_keywords": ["assistant merchandise"], "responsibilities": ["receipts", "data", "inventory", "merchandising", "website", "otb", "maintain", "plan", "facebook", "stock replenishment", "monitor", "logistics", "forecast", "report", "monitoring", "drive sales", "ad-hoc assignments", "recruitment", "planning"], "requirements": {"degrees": ["degree holder"], "majors": ["business"], "languages": [], "language_level": [], "hard_skills": ["planner", "facebook", "analytical skills"], "soft_skills": ["sensitive to figures", "analytical skills", "committed", "presentation skills", "interpersonal skills", "attention to detail"], "languages_combined": []}, "experience_required": {"duration": ["2 years"], "field": ["merchandising", "planning"]}}, {"job_id": "100003009036162", "location_code": "hk", "company": "ALDI Services Asia Limited", "job_title": "Assistant Merchandiser / Merchandiser - Textile (m/f)", "description": "We invite now high caliber talent to apply for Assistant Merchandiser/ Merchandiser (m/f)\u00a0to join our rapidly growing sourcing team in Hong Kong. This position supports product development and commercialization with a fast-paced successful team.\n\nResponsibilities.\n\nPerform general sourcing duties as required by the Manager\nPrepare and ensures that all documents related to tender, submission, awarding of contracts and shipments are correct and completed\nFinalize submission comparison documents and identify preferred submission in line with company procedures\nEffectively communicate with Quality, CR, Admin and Logistics team members as well as ALDI International departments/ offices and other internal/external parties on behalf of Manager/ team\nFollow through the production process for all purchased products\nCarry out visits to trade fairs or suppliers in order to manage and develop the supplier pool within the commodity area\nProvides cover for the team members and supports the training of employees and trainees from other areas\n\n\u00a0Your Profile.\n\nAt least (Non-Degree) Tertiary education required.\nMinimum of 2 years' relevant working experience, preferably gained in sourcing/buying offices, working with consumer products.\nExcellent communication and interpersonal skills, team player.\nGood command of both verbal and written business English and fluency in Mandarin essential.\nAble to work independently, self-motivated, responsible, well-organized and willing to learn.\nAttention to detail and good organizing, coordination and planning skills.\nGeneral knowledge of MS office and Exchange essential.\nHigh level of maturity, integrity, trustworthiness.\n\nKey Benefits of working at ALDI.\n\nMarket leading remuneration package\n\nRewarding, attractive remuneration package.\nGroup Medical Insurance covering dental and maternity* benefits .\n\nWork-life balance\n\nFull time, permanent position, 5-day-work-week.\n20 days of paid Annual Leave.\n\nBeing part of a pleasant, successful, growing business\n\nALDI\u2019s business is expanding, same for the Hong Kong Office with lots of opportunities for growth and development.\nPleasant working atmosphere where proactive communication, teamwork and collaboration is highly valued.\n\nPeople Focused\n\nStructured, comprehensive orientation and on-the-job training.\nALDI empowers our people allowing staff ownership of their areas of responsibilities.\n\nTrust and Integrity\n\nWE DO WHAT WE SAY - \u00a0for us there is no grey area, we have robust business processes, procedures and strong governance in place.\nWe treat our staff members, customers, suppliers and service providers with trust and fairness as business partners.\n\n\u00a0* Maternity benefits only apply for female employees due to local Insurance policy\n\nHow to apply\u00a0\u00a0\n\nIf you are interested in applying for the job, we look forward to receiving your full application in English, including salary expectation and possible starting date. The application should be sent through JobsDB by clicking icon \u201cApply Now\u201d or addressed to ALDI HR Department,\u00a0Unit 2501, Tower 1, The Gateway, Harbour City, TST, Hong Kong.\n\nALDI is an Equal Opportunity employer. We are dedicated to create an equal opportunity throughout recruitment process and staff employment to build a diverse and inclusive workforce. We oppose all forms of unfair or unlawful discrimination in our selection process.\n\nAll personal data collected will be used for recruitment purposes only and be treated in strictest confidence and highest security level in accordance with Hong Kong Data (Privacy) Ordinance as well as ALDI internal Security Policy.\n\nNo part of this job content including but not limited to company information, logo and job description may be reproduced, presented, uploaded, transmitted, modified or distributed \u00a0in any form or by any means without prior permission of ALDI Services Asia Limited / ALDI Sourcing Asia Limited (\u201cthe Company\u201d). The Company reserves the right to take legal action on any unauthorized reproduction, presentation, upload, transmission, modification or distribution. Only applications submitted directly to the Company in response to this advertisement will be considered and any application received by the Company through unauthorized third party agents or via any other channels will not be considered.\n", "employment_types": ["Full Time", "Permanent"], "selling_points": ["Responsible for orders monitoring and follow-up", "Tender submission and shipment documents", "Communicate with Quality, CR, Admin and Logistics"], "locations": ["Kwun Tong"], "categories": ["Merchandising & Purchasing", "Fabrics", "Sweater", "Textiles"], "post_time": "2022-01-10T09:31:31Z", "salary": {"currency": null, "max": null, "min": null, "period": "monthly", "term": null}, "salary_visible": false, "title_keywords": ["merchandiser", "assistant merchandiser"], "responsibilities": ["communicate with", "production process", "contracts", "external parties", "procedures", "quality", "develop", "communication", "commercialization", "logistics", "tender", "coordination", "planning"], "requirements": {"degrees": ["degree"], "majors": [], "languages": ["english", "mandarin"], "language_level": ["fluency", "good command"], "hard_skills": ["exchange", "ms office"], "soft_skills": ["planning skills", "work independently", "self-motivated", "responsible", "well-organized", "willing to learn", "integrity", "communication and interpersonal skills", "attention to detail", "coordination", "team player"], "languages_combined": [{"language": "english", "language_level": ["fluency", "good command"]}, {"language": "mandarin", "language_level": ["good command"]}]}, "experience_required": {"duration": ["minimum of 2 years"], "field": ["buying offices", "relevant working experience"]}}, {"job_id": "100003009033999", "location_code": "hk", "company": "Alexis Services Limited", "job_title": "Lead - Technical (Textile & Manufacturing)", "description": "Responsibilities\n\nOversee the technology stack, technical and architectural design, and solution of the digital products. Enforcing technical and architectural design guidelines\nLead & manage the technical team internal or / and external resources, mentoring, and enhancing and maintaining a best in class digital development team\nContributes to technical delivery plans and timelines with effective planning skills\nUnderstand and design network infrastructure of on-premises or cloud deployment of applications\nReview the design, implementation and quality of vendor\u2019s deliverables. Ensure they meet the company requirements and development standard\nCommunicate with upstream and downstream system teams for any planned technical deliveries\nActively contributes to technology engineering practice by sharing subject matter expertise from their area of specialism, best practice and learnings\nDevelop and maintain documentation and deliver communication sessions to different stakeholders\nWork collaboratively and effectively in virtual teams across Hong Kong and China\n\nRequirements:\n\nBachelor\u2019s degree in Computer Science, IT or equivalent required\n10 years of Digital Product Development & management experience in B2B/B2C domain\nSolid experience in developing enterprise level of web and mobile applications (iOS/Android) with track record\nProficiency in, at least, one modern programming language and framework such as Java, PHP, Swift/Objective-C, HTML5/CSS, React Native, Kotlin, vue.js/react.js, node.js, etc.\nExperience in DevOps Continuous Integration and Continuous Deployment, Code Analysis and Test Automation\nExperience in designing, developing and deploying solutions using container technologies in Cloud (eg. AWS, Azure, AliCloud)\nExposure to Docker, Kubernetes Container Orchestration is a plus\nExperience in Agile software development with Scrum or other Agile methodologies/frameworks\nExperience in developing 3D solution is an advantage\nExperience and ability to coach, develop, motivate and manage a team\nDemonstrated leadership, relationship management and change management experience and skills gained is a diversified organization\nExcellent communication, interpersonal, planning and organization skills\nExperience in textile and manufacturing industry is an advantage", "employment_types": ["Full Time"], "selling_points": ["Experience in developing 3D solution", "Agile software development with Scrum or Agile", "Oversee technology task, technical & architectural"], "locations": ["Cheung Chau Area"], "categories": ["Design", "Fashion", "Information Technology (IT)", "IT Project Management / Team Lead", "Merchandising & Purchasing", "Textiles"], "post_time": "2022-01-10T02:21:46Z", "salary": {"currency": null, "max": null, "min": null, "period": "monthly", "term": null}, "salary_visible": false, "title_keywords": ["lead"], "responsibilities": ["network infrastructure", "communicate with", "maintaining", "guidelines", "review", "quality", "implementation", "design", "teams", "develop", "communication", "maintain documentation", "plans", "planning"], "requirements": {"degrees": ["degree", "bachelor"], "majors": ["it", "computer science"], "languages": [], "language_level": [], "hard_skills": ["plus", "azure", "agile", "web", "react native", "java", "css", "integration", "kotlin", "devops", "objective-c", "aws", "container", "php", "react", "analysis", "mobile", "deployment", "programming", "swift", "code", "android"], "soft_skills": ["agile", "communication", "organization skills", "leadership", "interpersonal"], "languages_combined": []}, "experience_required": {"duration": ["10 years"], "field": ["management", "devops", "developing", "software development", "textile", "digital", "product development", "manufacturing industry", "team"]}}, {"job_id": "100003009037366", "location_code": "hk", "company": "ConnectedGroup Limited", "job_title": "Merchandising Director - Apparel", "description": "Merchandising Director - Apparel\n\nThis represents an excellent opportunity to work at a leading global fashion & apparel company as their merchandising director. The role will report into the MD directly, leading a team of over 20 and will primarily focus on development (sampling, costing & sourcing). The company is going through rapid expansion as their business strategy has taken them to huge success by making the most of opportunities created by the pandemic.\n\nResponsibilities:\n\nManaging the development process and operations for the BU\nCosting, sampling, material sourcing, technical developments and approvals will be carried out in an efficient and accurate manner\nWorking closely with the PD, design and production teams, ensure that orders are delivered on time with competitive cost and expected requirements and quality\nBe the leader of the BU, manage internal and external stakeholders whilst delivering high performing standards in sample hit rate, margin, delivery and order intake.\nBuild strong partnership with vendors and suppliers and manage their performance to be at a consistently high level\n\nRequirements:\n\nMinimum of 10 years in merchandising / sourcing roles for fashion and apparel companies\nMinimum of 5 years in managerial position\nDegree in fashion/textile preferred\nExperience with US market, particularly in low-priced, mass market sector\nStrong product knowledge in woven and knit\nMust speak and write excellent English and Chinese\nMust be able to live and work in HK (candidates currently in HK preferred)\n\nInterested parties please send your CV to Vincent.chow@connectedgroup.com", "employment_types": ["Full Time", "Permanent"], "selling_points": ["Leading apparel company", "Fast growing business", "Excellent career prospects & opportunities"], "locations": ["Not Specified"], "categories": ["Merchandising & Purchasing", "Woven / Knit", "Textiles"], "post_time": "2022-01-11T02:36:25Z", "salary": {"currency": null, "max": null, "min": null, "period": "monthly", "term": null}, "salary_visible": false, "title_keywords": ["merchandising", "director"], "responsibilities": ["cost", "operations", "teams", "quality", "design"], "requirements": {"degrees": ["degree"], "majors": [], "languages": ["english", "chinese"], "language_level": ["excellent"], "hard_skills": [], "soft_skills": [], "languages_combined": [{"language": "english", "language_level": ["excellent"]}, {"language": "chinese", "language_level": ["excellent"]}]}, "experience_required": {"duration": [], "field": []}}, {"job_id": "100003009031704", "location_code": "hk", "company": "Gap International Sourcing Ltd", "job_title": "Temporary - Senior Merchandiser (5 Month)", "description": "ABOUT THE ROLE\nThe Senior Merchandiser, Product Development will be responsible for developing the garment samples for the assigned product / style while working closely with the Merchandising teams of the Vendors. As part of product development team s/he will also be providing support in identifying opportunities of cost saving, onboarding new vendors and executing the innovation agenda for the department in the assigned product.\n\nWHAT YOU'LL DO\n\nManages vendor orders and relationships for a sub-category.\nMaintains relationships and negotiation with new and current vendor\nResponsible for product development and order placement in efficient and effective manner\nWorks with Technical, QA and Mill management team to ensure all commercial decision and standards are met\nSupports category team in problem solving, information sharing and counter sourcing to support best placement plan\nManages counter costing; Handling samples; Tracking fit approvals; Tracking lab dips\nPartners with brand Design, R&D and key suppliers to develop innovative and quality product\nPartners with Mill management, QA and technical teams to resolve fabric or quality issues\nResolves issues within a timely manner while working to continuously improve and create internal and external processes and procedures\n\nWHO YOU ARE\n\nMerchandise Sourcing Knowledge \u2013 Experience in sample development and with offshore production exposure; in large-sized buying office or trading company\u00a0\nPlanning & Influencing \u2013 proven experience in plan, prioritize and influence at all levels\nDrive Results - ability to analyze situations and proactively suggest solutions to meet deliverables\nLearning Agility & Experimentation \u2013 demonstrates eagerness to learn and explore new ways of approaching goals\nEffective Communicator & Team Player - proven capability to communicate effectively, verbal and written\nHigh level of proficiency with Microsoft Excel\n\nFor over 50 years, Gap Inc. has done more than sell clothes \u2013 we give back to the community and engage in sustainability and environmental initiatives.\u00a0As our communities react to the global health crisis caused by COVID-19, our focus remains on supporting the health and livelihood of our employees while caring for our customers and communities.\u00a0To read more, visit\u00a0https://corporate.gapinc.com/en-us/news/coronavirus-response.\n\nGap Inc. is an equal-opportunity employer and continues to foster a diverse and inclusive environment. We have received numerous awards for our long-held commitment to equality. This year, we\u2019ve been named as one of the\u00a0Best Places to Work by the Humans Rights Campaign for the fifteenth consecutive year\u00a0and have been included in the\u00a02020 Bloomberg Gender-Equality Index for the\u00a0third year in a row.\u00a0\u00a0\n\nAny personal information collected relating to employment applications will be used for recruitment purposes only.\u00a0", "employment_types": ["Temporary", "Contract"], "selling_points": ["Cross-functions partnership", "Innovative production development", "Development and training opportunities"], "locations": ["Kwun Tong"], "categories": ["Merchandising & Purchasing", "Sweater", "Textiles", "Procurement / Purchasing / Sourcing"], "post_time": "2022-01-07T09:42:38Z", "salary": {"currency": null, "max": null, "min": null, "period": "monthly", "term": null}, "salary_visible": false, "title_keywords": ["senior merchandiser"], "responsibilities": ["management team", "cost", "management", "teams", "merchandising", "developing", "design", "develop", "quality", "a timely manner", "procedures", "executing", "planning", "providing support", "plan", "recruitment", "tracking"], "requirements": {"degrees": [], "majors": [], "languages": [], "language_level": [], "hard_skills": ["r&d", "bloomberg", "react", "gap", "vendor", "microsoft excel", "problem solving", "focus"], "soft_skills": ["efficient", "focus", "negotiation", "responsible", "timely", "prioritize", "problem solving", "ability to analyze", "diverse", "learning", "team player", "communicator", "innovative"], "languages_combined": []}, "experience_required": {"duration": [], "field": ["development", "planning"]}}, {"job_id": "100003009026067", "location_code": "hk", "company": "Lululemon HK Limited", "job_title": "Production Analyst (6 Months)", "description": "We prioritize to go through applicants who apply through our career web page and encourage you to apply using the link below:\u00a0https://careers.lululemon.com/en_US/careers/JobDetail/Hong-Kong-Island-Hong-Kong-Production-Analyst-6-Months/16178\n\nWho we are\nlululemon is an innovative performance apparel company for yoga, running, training, and other athletic pursuits. Setting the bar in technical fabrics and functional design, we create transformational products and experiences that support people in moving, growing, connecting, and being well. We owe our success to our innovative product, emphasis on stores, commitment to our people, and the incredible connections we make in every community we're in. As a company, we focus on creating positive change to build a healthier, thriving future. In particular, that includes creating an equitable, inclusive and growth-focused environment for our people.\n\nAbout this team\nThe lululemon Liaison Office (LLO) team is dedicated to ensuring our components are produced of the highest quality, delivered when we need them, and manufactured with partners who share our commitment to elevating the world. Not only do we manage the production of great product, we also build great relationships.\n\n\nA day in the life:\n\nReport and support the Merchandising Manager to manage production from BUY confirmation to shipment\nWork closely with the vendors on lululemon production and logistics policies, processes and IT systems;\nManage production process, which includes WIP, PO change, WWMT and the BUY confirmation to negotiate the best delivery with vendors;\nAnalyze the capacity and capability of vendors to make sure they can deliver the right product and on time, escalate potential issues to support teams;\nFollow up on liability SOP with vendors due to cancellation;\nAble to anticipate high-risk areas and take the lead in resolving any potential or current issues with cross-functional teams to minimize the immediate impact;\nPrepare the Past Due Date and Delay Reason Code report;\nWork closely with our Compliance and Quality teams in ensuring that our social compliance and quality standards are adhered to, and goals are met, and communicate delivery statuses and issues to appropriate SSC counterparts in a timely and concise manner\n\nQualifications:\n\nYour ideal background: Higher Diploma or Bachelor\u2019s degree in Textiles or related fields; 5+ years experience in a similar role within a production environment; good understanding of technical fabrics, garment construction and related machinery.\nYou can analyze work flow and can access bottlenecks; are fluent in Mandarin and English;\nStrong IT skills needed \u2013 you are an MS Excel guru (V Lookup and Pivot Table knowledge essential)! And you love working with a lot of Microsoft Office, Tradestone, GTNexus and FlexPLM!\nMust haves:\n\nAcknowledges the presence of choice in every moment and takes personal responsibility for their life.\nPossesses an entrepreneurial spirit and continuously innovates to achieve great results.\nCommunicates with honesty and kindness, and creates the space for others to do the same.\nLeads with courage, knowing the possibility of greatness is bigger than the fear of failure.\nFosters connection by putting people first and building trusting relationships.\nIntegrates fun and joy as a way of being and working, aka doesn\u2019t take themselves too seriously.\u00a0\nNOTE: Only those applicants under consideration will be contacted. Please accept our utmost appreciation for your interest. lululemon is an Equal Employment Opportunity employer. Employment decisions are based on merit and business needs, and not on race, color, creed, age, sex, gender, sexual orientation, national origin, religion, marital status, medical condition, physical or mental disability, military service, pregnancy, childbirth and related medical conditions or any other classification protected by federal, state or provincial and local laws and ordinances. Reasonable accommodation is available for qualified individuals with disabilities, upon request. This Equal Employment Opportunity policy applies to all practices relating to recruitment and hiring, compensation, benefits, discipline, transfer, termination and all other terms and conditions of employment. While management is primarily responsible for seeing that lululemon equal employment opportunity policies are implemented, you share in the responsibility for assuring that, by your personal actions, the policies are effective.", "employment_types": ["Full Time", "Contract"], "selling_points": ["Good understanding of technical fabrics/garment", "Strong in V Lookup and Pivot Table", "Eager to collaborate and grow with the team"], "locations": ["Tin Hau"], "categories": ["Manufacturing", "Garment / Textile", "Merchandising & Purchasing", "Woven / Knit", "Textiles"], "post_time": "2022-01-06T07:18:13Z", "salary": {"currency": null, "max": null, "min": null, "period": "monthly", "term": null}, "salary_visible": false, "title_keywords": ["analyst"], "responsibilities": [], "requirements": {"degrees": [], "majors": [], "languages": [], "language_level": [], "hard_skills": ["go", "web"], "soft_skills": ["prioritize"], "languages_combined": []}, "experience_required": {"duration": [], "field": []}}, {"job_id": "100003009036163", "location_code": "hk", "company": "ALDI Services Asia Limited", "job_title": "Buying Specialist / Buyer (Regional Buy) - Textile (m/f)", "description": "We invite now high caliber talent to apply for\u00a0Buying Specialist / Buyer (Regional Buy) (m/f)\u00a0to join our rapidly growing sourcing team in Hong Kong. This position supports product development and commercialization with a fast-paced successful team.\n\nResponsibilities\n\n\nPrepares and consolidates all documents required for the smooth international procurement of products in due time (e.g. Item Confirmations, tenders, supplier contracts).\nReviews the layout of packaging materials, user manuals, and assembly instructions in accordance with the international brand style guides and relevant guidelines until final approval.\nCoordinates completely new designs or significant changes with the responsible MB/DIB in advance.\nPrepares product samples for presentation and review to the responsible MB, DIB, DIS/ GDIS.\nReviews the development of the national Buying areas with regard to overlaps and potential new products.\nPrepares international new product proposals for presentation to the national Buying department.\nSupports the MB/ DIB/ DIS in conducting market and competitor analysis.\nEffectively communicates with Sourcing, CR, Admin and Logistics team members to ensure the success of Buying operations.\nPrepares, maintains, and updates the International Category Proposal, timeline, tender schedule and product portfolios for their product area as well as the lists which serve as the basis for various evaluations.\nCommissions in-house testing of product samples and informs the BM, DIB/ DIS of the results\nMaintain and update of new and existing supplier record.\nProvide cover for the team members and supports the training of employees and trainees from other areas\n\n\u00a0Your Profile.\n\nAt least (Non-Degree) Tertiary education required.\nMinimum of 2 years' relevant working experience, preferably gained in sourcing/buying offices, working with consumer products.\nExcellent communication and interpersonal skills, team player.\nGood command of both verbal and written business English and fluency in Mandarin essential.\nAble to work independently, self-motivated, responsible, well-organized and willing to learn.\nAttention to detail and good organizing, coordination and planning skills.\nGeneral knowledge of MS office and Exchange essential.\nHigh level of maturity, integrity, trustworthiness.\n\nKey Benefits of working at ALDI.\n\nMarket leading remuneration package\n\nRewarding, attractive remuneration package.\nGroup Medical Insurance covering dental and maternity* benefits .\n\nWork-life balance\n\nFull time, permanent position, 5-day-work-week.\n20 days of paid Annual Leave.\n\nBeing part of a pleasant, successful, growing business\n\nALDI\u2019s business is expanding, same for the Hong Kong Office with lots of opportunities for growth and development.\nPleasant working atmosphere where proactive communication, teamwork and collaboration is highly valued.\n\nPeople Focused\n\nStructured, comprehensive orientation and on-the-job training.\nALDI empowers our people allowing staff ownership of their areas of responsibilities.\n\nTrust and Integrity\n\nWE DO WHAT WE SAY - \u00a0for us there is no grey area, we have robust business processes, procedures and strong governance in place.\nWe treat our staff members, customers, suppliers and service providers with trust and fairness as business partners.\n\n\u00a0* Maternity benefits only apply for female employees due to local Insurance policy\n\nHow to apply\u00a0\u00a0\n\nIf you are interested in applying for the job, we look forward to receiving your full application in English, including salary expectation and possible starting date. The application should be sent through JobsDB by clicking icon \u00a0\u201cApply Now\u201d or addressed to\u00a0ALDI HR Department, 18/F, Millennium City 6, 392 Kwun Tong Road Kwun Tong, Kowloon, Hong Kong.\n\nALDI is an Equal Opportunity employer. We are dedicated to create an equal opportunity throughout recruitment process and staff employment to build a diverse and inclusive workforce. We oppose all forms of unfair or unlawful discrimination in our selection process.\n\nAll personal data collected will be used for recruitment purposes only and be treated in strictest confidence and highest security level in accordance with Hong Kong Data (Privacy) Ordinance as well as ALDI internal Security Policy.\n\nNo part of this job content including but not limited to company information, logo and job description may be reproduced, presented, uploaded, transmitted, modified or distributed \u00a0in any form or by any means without prior permission of ALDI Services Asia Limited / ALDI Sourcing Asia Limited (\u201cthe Company\u201d). The Company reserves the right to take legal action on any unauthorized reproduction, presentation, upload, transmission, modification or distribution. Only applications submitted directly to the Company in response to this advertisement will be considered and any application received by the Company through unauthorized third party agents or via any other channels will not be considered.\n", "employment_types": ["Full Time", "Permanent"], "selling_points": ["Reviews the layout of packaging materials", "Prepares international new product proposals", "Reviews the development of the national Buying"], "locations": ["Kwun Tong"], "categories": ["Merchandising & Purchasing", "Textiles", "Others", "Procurement / Purchasing / Sourcing"], "post_time": "2022-01-10T09:31:53Z", "salary": {"currency": null, "max": null, "min": null, "period": "monthly", "term": null}, "salary_visible": false, "title_keywords": ["specialist"], "responsibilities": ["guidelines", "contracts", "analysis", "review", "operations", "testing", "communication", "commercialization", "commissions", "logistics", "schedule", "tender", "maintain", "coordination", "planning"], "requirements": {"degrees": ["degree"], "majors": [], "languages": ["english", "mandarin"], "language_level": ["fluency", "good command"], "hard_skills": ["exchange", "analysis", "ms office"], "soft_skills": ["planning skills", "work independently", "self-motivated", "responsible", "well-organized", "willing to learn", "integrity", "communication and interpersonal skills", "attention to detail", "smooth", "coordination", "team player", "presentation"], "languages_combined": [{"language": "english", "language_level": ["fluency", "good command"]}, {"language": "mandarin", "language_level": ["good command"]}]}, "experience_required": {"duration": ["minimum of 2 years"], "field": ["buying offices", "relevant working experience"]}}, {"job_id": "100003009026228", "location_code": "hk", "company": "Triumph International Services (APAC) Limited", "job_title": "Buyer - Sloggi", "description": "sloggi\u00ae brings true comfort to people\u2019s everyday by creating the most wearable, innovative bodywear in the world. Launched in 1979, the brand has long been the best-selling brief brand in Europe and today delivers unrivalled comfort across multi-faceted intimate apparel ranges for both women and men across Europe, Asia, US and Canada.\n\nLearn more about Sloggi on:\n\nwww.sloggi.com\n\nwww.facebook.com/sloggi/\n\nwww.instagram.com/sloggi\n\nwww.linkedin.com/company/sloggi\n\nFor our Merchandising and Buying Department we are searching for a highly motivated\n\n\u00a0\u00a0\u00a0\u00a0\u00a0\u00a0\u00a0\u00a0\u00a0\u00a0\u00a0\u00a0\u00a0\u00a0\u00a0\u00a0\u00a0\u00a0\u00a0\u00a0\u00a0\u00a0\u00a0\u00a0\u00a0\u00a0\u00a0\u00a0\u00a0\u00a0\u00a0\u00a0\u00a0\u00a0\u00a0\u00a0\u00a0\u00a0\u00a0\u00a0\u00a0\u00a0\u00a0\u00a0\u00a0\u00a0\u00a0\u00a0\u00a0\u00a0\u00a0\u00a0\u00a0\u00a0\u00a0\u00a0\u00a0\u00a0\u00a0\u00a0\u00a0\u00a0\u00a0\u00a0\u00a0\u00a0\u00a0\u00a0\u00a0\u00a0\u00a0\u00a0\u00a0\u00a0\u00a0\u00a0\u00a0\u00a0\u00a0\u00a0\u00a0\u00a0\u00a0\u00a0\u00a0\u00a0\u00a0\u00a0\u00a0\u00a0\u00a0\u00a0\u00a0\u00a0\u00a0\u00a0\u00a0\u00a0\u00a0\u00a0\u00a0\u00a0\u00a0\u00a0\u00a0\u00a0\u00a0\u00a0\u00a0\u00a0\u00a0\u00a0\u00a0\u00a0\u00a0\u00a0\u00a0\u00a0\u00a0\u00a0\u00a0\u00a0\u00a0\u00a0\u00a0\u00a0\u00a0\u00a0\u00a0\u00a0\u00a0\u00a0\u00a0Buyer - Sloggi\n\nWhat You\u2019ll do:\n\nBuyer is one of the key members in the merchandising team who will support the head of merchandising to deliver the merchandising strategy and achieve the budget by formulating, conducting and implementing various kinds of analysis and planning (e.g., merchandising plan, buying plan, sell-through, delivery, replenishment, and stock clearance plan). This role will also work closely with the online & offline sales team and marketing team to achieve the sales growth with targeted profitability.\n\nKey accountabilities include:\n\nAssist Head of Merchandising in product mix planning, merchandise selection, pricing, buying plan and assortment plan\nSupport the Head to plan the regular and ad hoc promotional activities to increase sales growth\nFormulate OTB, assortment plan and allocation plan according to the budget and maintain a smooth flow of merchandise delivery\nManage monthly and seasonal buy for regions / stores with effective assortment and pricing strategy\nPrepare various sales, product and inventory performance reports\nMonitor the sell through, stock level, SKU holding and their efficiency, merchandise distribution and replenishment on a timely basis so as to ensure the right stock in right quantity at right place at right time for sales growth and Sloggi brand building\nWork closely with sales and marketing team in development and execution of assortment for buying plans to maximize the sales growth and proper Sloggi brand image\nQuick response to market so as to optimize sales performance\nKeep track the market trends and suitable new products, identify market opportunities, benchmark against competitors, and make necessary recommendations\n\nWhat You\u2019ll bring:\n\nOutsanding COMMUNICATION skills both verbal & written\nDemonstrated BUSINESS acumen\nAdapt easily to DIVERSE audiences and environments\nRESILIENCE in the face of advertsity and stress\nSort thru COMPLEXITY and present in strategic and conclusive way\nAble to PRIORITIZE and work independently with minimal supervision\nAble to work effectively in a TEAM environment.\nCapable of MULTI-TASKING, prioritizing, and managing time efficiently.\nDemonstrate ability to INFLUENCE decisions through experience and analysis\nEffectively plan workload and PRIORITIZE tasks and achieve deadlines.\nAt least 3 years hands-on retail buying experience in underwear, lifestyle, fast-fashion, sportswear\nStrong fashion sense, analytical skills, business acumen and numerical sense\nKnowledge of online retail is advantage\n\nWhat You\u2019ll get:\n\nWe offer an opportunity in a fast paced organization which gives those looking for a challenge the possibility to grow with the company and shape the future.\n\nWe are a family owned company with strong values, operating at a global level with key markets in Germany, Japan and China - where our iconic brands, Sloggi and Triumph, continue to delight our consumers.\n\nSloggi is committed to employing a diverse workforce. Qualified applicants will receive consideration without regard to race, colour, religion, sex, national origin, age, sexual orientation, gender identity, gender expression, veteran status, or disability.\u00a0\n\nIf you are seeking a great opportunity to develop your career, please send us your application letter and CV in English, diplomas and expected salary range by clicking on Apply.", "employment_types": ["Full Time", "Permanent"], "selling_points": ["ands-on retail buying experience", "underwear, lifestyle, fast-fashion, sportswear", "fashion sense, analytical skills, business acumen"], "locations": ["Kowloon Bay"], "categories": ["Manufacturing", "Garment / Textile", "Merchandising & Purchasing", "Textiles"], "post_time": "2022-01-06T07:45:21Z", "salary": {"currency": null, "max": null, "min": null, "period": "monthly", "term": null}, "salary_visible": false, "title_keywords": [], "responsibilities": ["performance reports", "inventory", "budget", "merchandising", "otb", "communication", "maintain", "plan", "plans", "facebook", "ad hoc", "sales performance", "monitor", "develop", "promotional activities", "analysis", "replenishment", "sales team", "planning"], "requirements": {"degrees": [], "majors": [], "languages": ["english"], "language_level": [], "hard_skills": ["analysis", "analytical skills", "make", "facebook", "acumen"], "soft_skills": ["work effectively", "communication skills", "work independently", "capable", "able to prioritize", "timely", "prioritize", "analytical skills", "diverse", "multi-tasking", "motivated", "hands-on", "committed", "smooth", "business acumen", "innovative", "prioritizing"], "languages_combined": [{"language": "english", "language_level": []}]}, "experience_required": {"duration": ["at least 3 years"], "field": ["retail"]}}, {"job_id": "100003009023188", "location_code": "hk", "company": "I.T Apparels Limited", "job_title": "Buyer - BIT Menswear (REF:JDB-IT-SB)", "description": "Accountabilities \u2013 Key Result Areas\n\nPrepare OTB, seasonal and annual buying plans based on a thorough understanding of consumer, market trends and company business objectives\nMonitor closely on OTB, control sales and inventory to achieve seasonal sales and profit targets based on the seasonal business plan\nDetermine buying guides and assortment strategy in order to obtain a seasonal target\nOversee inventory costs, sales forecast, gross profit margin to achieve sales and profit targets\nFormulate pricing strategies based on competitive analysis, market reviews, competitor positions, and financials, etc.\nEvaluate ongoing performance and takes actions as appropriate\n\nExperience / Qualification Requirements\n\nDegree holder in Fashion & Textiles or business discipline\nWith at least 5 years of experience in\u00a0buying and merchandising, preferably in the fashion/lifestyle/retail industry\nProactive, sensitive to figures and strong analytical and negotiation skills\nExcellent product sensibility and understanding of competitive retail landscape\nAttention to detail with a high level of accuracy\nHands-on analytical skills in MS Excel and ERP systems in a sizable corporation\nCandidates with less experience will be considered as Assistant Buyer\n\nCompetitive remuneration and benefits package will be offered to the right candidate. Please submit your application by clicking \"Apply Now\" below.\n\nAll data collected is for recruitment purposes only.\n\nSure you want to know more about our company and brands, simply follow our\n\nWEBSITE at http://www.ithk.com\u00a0 \u00a0 \u00a0 \u00a0 \u00a0 \u00a0 \u00a0 \u00a0 \u00a0 \u00a0 \u00a0 \u00a0 \u00a0 \u00a0 \u00a0 \u00a0 \u00a0 \u00a0 \u00a0 \u00a0 \u00a0 \u00a0 \u00a0 \u00a0 \u00a0 \u00a0 \u00a0 \u00a0 \u00a0 \u00a0 \u00a0 \u00a0 \u00a0 \u00a0\u00a0\nFACEBOOK at\u00a0http://www.facebook.com/I.Ttheofficialpage\u00a0 \u00a0 \u00a0 \u00a0 \u00a0 \u00a0 \u00a0 \u00a0 \u00a0\nINSTAGRAM at http://instagram.com/ithk\u00a0 \u00a0 \u00a0 \u00a0 \u00a0 \u00a0 \u00a0 \u00a0 \u00a0 \u00a0 \u00a0 \u00a0 \u00a0 \u00a0 \u00a0 \u00a0 \u00a0 \u00a0 \u00a0 \u00a0 \u00a0 \u00a0 \u00a0 \u00a0 \u00a0 \u00a0 \u00a0 \u00a0\nWEIBO at\u00a0http://e.weibo.com/ithongkong", "employment_types": ["Full Time"], "selling_points": ["5 years' fashion buying experience", "Budget planning, sales planning and analysis", "Formulate pricing strategies"], "locations": ["Southern Area"], "categories": ["Merchandising & Purchasing", "Textiles", "Others", "Procurement / Purchasing / Sourcing"], "post_time": "2022-01-05T07:44:40Z", "salary": {"currency": null, "max": null, "min": null, "period": "monthly", "term": null}, "salary_visible": false, "title_keywords": [], "responsibilities": ["control", "inventory", "analysis", "monitor", "merchandising", "systems", "otb", "evaluate", "forecast", "business plan", "plans", "costs"], "requirements": {"degrees": ["degree holder"], "majors": ["business"], "languages": [], "language_level": [], "hard_skills": ["erp systems", "analysis", "ms excel", "analytical skills"], "soft_skills": ["sensitive to figures", "analytical skills", "negotiation skills", "hands-on", "thorough", "attention to detail", "proactive"], "languages_combined": []}, "experience_required": {"duration": ["at least 5 years"], "field": ["retail industry", "merchandising"]}}, {"job_id": "100003009032011", "location_code": "hk", "company": "STA Pacific Limited", "job_title": "Merchandising Officer ($14k - $16k \u2013 Japanese Firm)", "description": "Duties:\n\nDaily support Supervisor to run company\u2019s merchandising process, including product sampling, development and orders to delivery\nPrepare & Follow up purchase order (PO) and observe production records\nLiaise with factories and suppliers for materials arrangement and quality inspection\nAdvise various instruction to internal departments about shipment of import & export orders\nHandle ad-hoc projects assigned by Supervisor/Manager\n\nRequirements:\n\nWith 1 year of relevant merchandising experience will be highly preferred\nExperience in merchandising from a big scale manufacturing company will be a plus\nGood command in spoken and written Chinese, English and Japanese\nHolder of JLPT N2 or above\nWork experience in Japan will be an advantage\nHigher Diploma holder of Fashion and Textiles or related discipline will be preferred\nBusiness travel to Asia Pacific might be required after COVID-19 epidemic\nFresh Graduates are welcome to apply\n\nFor the interested parties, please APPLY now or email\u00a0your updated CV at\u00a0career3\u00a0(a) stapacific.com\u00a0", "employment_types": ["Full Time", "Permanent"], "selling_points": ["Global Company with great Office Environment", "Holder of JLPT N2 or above", "Fresh Graduates are welcome to apply"], "locations": ["Tsim Sha Tsui"], "categories": ["Manufacturing", "Garment / Textile", "Merchandising & Purchasing", "Textiles", "Procurement / Purchasing / Sourcing"], "post_time": "2022-01-07T19:21:02Z", "salary": {"currency": null, "max": null, "min": null, "period": "monthly", "term": null}, "salary_visible": false, "title_keywords": ["officer", "merchandising"], "responsibilities": ["quality", "merchandising", "inspection", "purchase", "liaise with", "ad-hoc projects"], "requirements": {"degrees": ["higher diploma holder"], "majors": [], "languages": ["japanese", "english", "chinese"], "language_level": ["good command"], "hard_skills": ["plus"], "soft_skills": [], "languages_combined": [{"language": "japanese", "language_level": ["good command"]}, {"language": "english", "language_level": ["good command"]}, {"language": "chinese", "language_level": ["good command"]}]}, "experience_required": {"duration": ["1 year"], "field": ["manufacturing", "merchandising"]}}, {"job_id": "100003009023764", "location_code": "hk", "company": "Majid Al Futtaim Sourcing Limited", "job_title": "MERCHANDISER \u2013 TEXTILE", "description": "Categories:\n\nFast fashion basics\nShoes, Fashion Bags, Jewelry and accessories\n\nGlobal Buying Office\n\n\u00a0Job Responsibilities:\n\nDaily communicate with suppliers and buyers on order follow up from order placement to shipment\nSample Management: coordinate sample deliver to Head Office when necessary\nMonitor shipment deliveries with supplier\nPrepare reports, system update\nFollow up orders with high diligence and accuracy to ensure excellent service level\nSupport Logistic and supply team chain on shipment arrangement\nVisit factories in South East Asia and China for sample checking and production follow up\nAttend trade fairs to keep up-to-date market trend and source potential suppliers\nAd-hoc job tasks may be required\n\nRequirements:\n\nAt least 1 to 3 years related product development and production follow up experience & knowledge in garments, home linen in trading or buying office will be an advantage\nInitiative, independent, well-organized, responsible and willing to learn\nStrong interpersonal skill, good communication and time management skill with good command of written and spoken English and Mandarin/Chinese\nDetailed-oriented, proactive working attitude\nProficiency in MS Word, Excel and Chinese Word Processing skill\nFresh graduates will also be considered\n\nWe offer 5 day work week, double pay, medical and competitive salary package commensurate with experience and qualification. Candidates not stating their expected salary will not be considered.\n\n\nHow to apply:\n\nIf the above job requirements ideally match your profile, we would like to invite you to email your full resume with your current & expected remuneration and earliest commencement date to recruitment by clicking 'Apply Now'.\n\nWe may not be able to respond to all applications as only shortlisted candidates will be notified.\n\nMajid Al Futtaim Sourcing Limited\u00a0is an equal opportunity employer and welcomes all qualified candidates for job applications. Any personal data and information collected would be kept confidential and used for recruitment purpose only.", "employment_types": ["Full Time", "Permanent"], "selling_points": [], "locations": ["Sheung Wan"], "categories": ["Merchandising & Purchasing", "Woven / Knit", "Textiles", "Procurement / Purchasing / Sourcing"], "post_time": "2022-01-05T20:32:08Z", "salary": {"currency": null, "max": null, "min": null, "period": "monthly", "term": null}, "salary_visible": false, "title_keywords": ["merchandiser"], "responsibilities": ["follow up orders", "ad-hoc", "management", "daily communicate", "shipment arrangement", "system update", "monitor", "checking", "coordinate", "prepare reports"], "requirements": {"degrees": [], "majors": [], "languages": ["english", "chinese", "mandarin"], "language_level": ["proficiency", "good command", "good"], "hard_skills": ["excel", "chinese word processing", "ms word"], "soft_skills": ["independent", "responsible", "willing to learn", "well-organized", "interpersonal skill", "communication", "time management skill", "proactive", "initiative", "detailed"], "languages_combined": [{"language": "english", "language_level": ["good command", "good"]}, {"language": "chinese", "language_level": ["proficiency", "good command", "good"]}, {"language": "mandarin", "language_level": ["good command", "good"]}]}, "experience_required": {"duration": ["at least 1 to 3 years"], "field": ["related", "product development", "trading"]}}, {"job_id": "100003009028213", "location_code": "hk", "company": "Sun Tak International Holdings Limited", "job_title": "Shipping Clerk", "description": "Responsibilities : -\n\n* Independent handle a full set of Import & Export documents\n\n* Support and follow up import and export shipment\n\n* Handle / follow customer instruction\n\n* Monitor the shipment schedule ensure smooth transition of the shipment operation, timely shipment delivery\n\n* Solid experience in dealing and negotiating with forwarders and couriers preferred\n\n\n\nRequirements : -\n\n* Form 5 or above with Pass with English\n\n* At least 1 year working experience in garment / textile manufacturing field an advantage\n\n* Self-motivated, creative and able to work independently\n\n* Computer skills & knowledge of Microsoft office essential\n\n* Good command of written and spoken English & Mandarin\n\n* Immediate available is highly preferable\n\nWe offer an attractive remuneration package as well as good career prospects. \u00a0Interest parties, please send full resume with expected salary to Human Resources Department \u00a0\n\nemail : suntak @suntak.com.\n\nPlease visit our website www.suntak.com for company information.\n\nInformation collected will only be used in connected with recruitment proposes. \u00a0All applications will be treated in strict confidence.", "employment_types": ["Full Time"], "selling_points": ["5-day work week; stable work hours; no travels", "Bank Holiday & Medical Insurance", "1 year working experience"], "locations": ["Kwai Hing"], "categories": ["Transportation & Logistics", "Shipping", "Merchandising & Purchasing", "Textiles", "Procurement / Purchasing / Sourcing"], "post_time": "2022-01-07T01:47:28Z", "salary": {"currency": null, "max": null, "min": null, "period": "monthly", "term": null}, "salary_visible": false, "title_keywords": ["shipping clerk"], "responsibilities": ["monitor", "schedule", "import and export shipment"], "requirements": {"degrees": ["form 5 or above"], "majors": [], "languages": ["english", "mandarin"], "language_level": ["good command"], "hard_skills": ["computer skills", "microsoft office"], "soft_skills": ["self-motivated", "creative", "work independently"], "languages_combined": [{"language": "english", "language_level": ["good command"]}, {"language": "mandarin", "language_level": ["good command"]}]}, "experience_required": {"duration": ["at least 1 year"], "field": ["garment", "manufacturing", "textile"]}}, {"job_id": "100003009025705", "location_code": "hk", "company": "C.F.L. Enterprise Limited", "job_title": "Senior Merchandising Manager - Knit (Intimate/Swimwear)", "description": "Job Description :\n\n\n\nOversee sourcing, development and production in\u00a0Knit (Intimate/Swimwer)category\nFollow-up and monitor the whole merchandising flow within the team from sample fitting to bulk production till shipment by in-depth technical knowledge\nStrive to understand customers\u2019 requirement and provide our best professional service to customers\nWork closely with US offices and supporting team to ensure product quality can meet\u00a0 customers\u2019 requirement\nSource and evaluate factory from the perspective of product, pricing, quality, reliability, compliance to meet the interest of customers\nLead the production team and coach them to upgrade product knowledge,\u00a0merchandising skills and overall effectiveness\nEstablish strategic business development\nEnsures orders are fulfilled per customer\u2019s need and margin expectation\nAccountable for the profit and loss of the own business area\nHas good fashion sense and able to identify business growth opportunities\u00a0\n\n\u00a0Requirements:\n\n15 years or above experience on merchandising/sourcing & production in fashion apparel\nHigher Diploma or above, preferably major in Textile and Clothing\nStrong\u00a0garment knowledge in\u00a0knit\u00a0wear,\u00a0 intimate & swimwear preferable\nFamiliar with\u00a0merchandising/sourcing industry in USA market\nEnjoy working in fast paced environment and strive for continuous improvement\nStrong management skills and analytical ability\nDetail-minded, able to work independently and under tight schedule\u00a0\nStrong leadership, communication, and problem-solving skills\nExcellence in both spoken and written English and Mandarin\nGood computer & presentation skills", "employment_types": ["Full Time"], "selling_points": [], "locations": ["Kowloon Bay"], "categories": ["Merchandising & Purchasing", "Textiles"], "post_time": "2022-01-06T06:16:17Z", "salary": {"currency": null, "max": null, "min": null, "period": "monthly", "term": null}, "salary_visible": false, "title_keywords": ["merchandising manager"], "responsibilities": ["compliance", "merchandising", "monitor", "quality", "evaluate"], "requirements": {"degrees": ["higher diploma or above"], "majors": [], "languages": ["english", "mandarin"], "language_level": [], "hard_skills": ["problem-solving skills"], "soft_skills": ["detail-minded", "work independently", "enjoy working", "communication", "presentation skills", "problem-solving skills", "leadership"], "languages_combined": [{"language": "english", "language_level": []}, {"language": "mandarin", "language_level": []}]}, "experience_required": {"duration": ["15 years"], "field": ["merchandising"]}}, {"job_id": "100003009022754", "location_code": "hk", "company": "Linmark (HK) Limited", "job_title": "Merchandiser (Apparel)", "description": "Merchandiser\n\n\nResponsibilities:\n\nAssist the Merchandise Manager to handle merchandising process from sample development until shipment delivery;\nFamiliar with development and production process;\nAbility to communicate with Customers, vendors and QA independently on development or production schedule;\nPerform other ad-hoc projects as assigned.\n\n\u00a0Requirements:\n\nSolid merchandising experiences in Garment field;\nProficiency in Excel and PowerPoint;\nIndependent and able to work under pressure to meet tight working schedule;\nEnergetic with can-do attitude;\nSufficient communication skills in English and Mandarin;\nOccasional travel is required.\nLess\u00a0experience will be considered as Assistant Merchandiser;\n\nInterested parties please apply with full resume, present / expected salary, and date of availability.\u00a0", "employment_types": ["Full Time"], "selling_points": ["A leading global sourcing and trading house", "Corporate role based in Hong Kong", "Excellent career development opportunity"], "locations": ["Kowloon Bay"], "categories": ["Manufacturing", "Garment / Textile", "Merchandising & Purchasing", "Textiles"], "post_time": "2022-01-05T06:27:16Z", "salary": {"currency": null, "max": null, "min": null, "period": "monthly", "term": null}, "salary_visible": false, "title_keywords": ["merchandiser"], "responsibilities": ["communicate with", "production process", "merchandising", "schedule", "ad-hoc projects"], "requirements": {"degrees": [], "majors": [], "languages": ["english", "mandarin"], "language_level": [], "hard_skills": ["excel", "powerpoint"], "soft_skills": ["communication skills", "independent", "can-do attitude", "energetic", "work under pressure"], "languages_combined": [{"language": "english", "language_level": []}, {"language": "mandarin", "language_level": []}]}, "experience_required": {"duration": [], "field": ["garment", "merchandising"]}}, {"job_id": "100003009018800", "location_code": "hk", "company": "I.T Apparels Limited", "job_title": "Buying Assistant - Beauty (REF:JDB-IT-BA)", "description": "Form 5 graduate or above\nMin 3years experience about garment manufacturing & merchandising.\nOrder follow up with both factory & customers is required\nPC knowledge of Excel, Word and Chinese word processing\nFluent in spoken and written Cantonese, English and Mandarin\nTravelling is required when needed and off-shore manufacturing experience is preferred\nInterested parties, please send full resume by clicking APPLY NOW.", "employment_types": ["Full Time"], "selling_points": ["1-2 years' fashion buying experience", "Budget planning, sales planning and analysis", "Stock planning and allocation"], "locations": ["Southern Area"], "categories": ["Merchandising & Purchasing", "Textiles", "Others", "Procurement / Purchasing / Sourcing"], "post_time": "2022-01-04T04:55:38Z", "salary": {"currency": null, "max": null, "min": null, "period": "monthly", "term": null}, "salary_visible": false, "title_keywords": ["buying assistant"], "responsibilities": ["merchandising"], "requirements": {"degrees": ["form 5"], "majors": [], "languages": ["cantonese", "english", "chinese", "mandarin"], "language_level": ["fluent"], "hard_skills": ["excel", "pc knowledge", "chinese word processing", "word"], "soft_skills": [], "languages_combined": [{"language": "cantonese", "language_level": ["fluent"]}, {"language": "english", "language_level": ["fluent"]}, {"language": "chinese", "language_level": []}, {"language": "mandarin", "language_level": ["fluent"]}]}, "experience_required": {"duration": [], "field": ["garment", "manufacturing", "merchandising"]}}, {"job_id": "100003009028847", "location_code": "hk", "company": "Topfame (HK) Trading Limited", "job_title": "Assistant Merchandiser/ Merchandiser", "description": "Responsibilities:\n\n\nManage programs for top clients related to our services within the global network\nClearly understand program priorities and initiatives.\nCreate and maintain an excellent partnership with the client to understand the client\u2019s challenges, issues and provide outstanding deliverables.\nProactively strategize with\u00a0sales team\u00a0to reduce business risk and maximize potential opportunities.\nPre-empt potential program risks and initiate preventive actions.\nPre-engage related internal stakeholders to deploy program changes in the most effective and efficient way for operationalization.\nAnalyze the complexity of program changes, and determine the most effective tools to best present complicated procedures or processes in the program documentation.\nDesign, develop, and conduct successful program operationalization training for the network.\nHandle Ad Hoc tasks assigned by the line manager or client.\n\nJob Requirements:\n\n\nDegree holder or higher\nMinimum\u00a03 years relevant working experience\nGood command of both written and spoken English, Chinese and Mandarin\nStrong project management, communication and organization skills\nResponsible, patient, customer oriented\nAble to work under pressure and balance several tasks simultaneously\nMust possess strong work ethic and excellent client service skills to ensure effective, responsive client interaction\n\nWe offer competitive salary and benefits to the right candidate.\u00a0 Interested parties please send your application with date of availability, present & expected salary to the\u00a0Human Resources Department,\u00a0Bureau Veritas Hong Kong\u00a0Limited\u00a0by mail\u00a0or\u00a0clicking \u201cAPPLY NOW\u201d.\u00a0\u00a0To\u00a0submit your application by mail, please mark \"Confidential\" and position applied on the envelope.\n\n\u00a0\nOur Benefits:\u00a0\n\n5-day Work Week\u00a0\nPublic Holiday, Annual Leave, Marriage Leave, Maternity Leave & Paternity Leave\nDouble Pay, Discretionary Bonus\nLife & Medical Insurance Benefits\nMandatory Provident Fund Contribution\nEducation & Training Subsidies\nExcellent Training & Career Advancement Opportunities\n\n\u00a0Join us on Linkedin:\u00a0\u00a0https://www.linkedin.com/company/bureau-veritas\u00a0\n\nMail\u00a0\n7/F,\u00a0Harbourside HQ\n8 Lam Chak Street\nKowloon Bay, Kowloon\n\nPersonal data collected will be used for recruitment purposes only.", "employment_types": ["Full Time"], "selling_points": ["Near Lai Chi Kok MTR station", "3yr+ exp about gmt manufacturing  & merchandising", "Travelling is required when needed"], "locations": ["Lai Chi Kok"], "categories": ["Manufacturing", "Garment / Textile", "Merchandising & Purchasing", "Textiles", "Others"], "post_time": "2022-01-07T03:23:40Z", "salary": {"currency": null, "max": null, "min": null, "period": "monthly", "term": null}, "salary_visible": false, "title_keywords": ["merchandiser", "assistant merchandiser"], "responsibilities": ["procedures", "ad hoc tasks", "design", "develop", "maintain", "sales team", "deploy", "documentation"], "requirements": {"degrees": ["degree holder"], "majors": [], "languages": ["english", "chinese", "mandarin"], "language_level": ["good command"], "hard_skills": ["project management"], "soft_skills": ["responsible", "communication", "project management", "work ethic", "organization skills", "patient", "responsive", "work under pressure"], "languages_combined": [{"language": "english", "language_level": ["good command"]}, {"language": "chinese", "language_level": ["good command"]}, {"language": "mandarin", "language_level": ["good command"]}]}, "experience_required": {"duration": ["minimum 3 years"], "field": ["relevant working experience"]}}, {"job_id": "100003009031660", "location_code": "hk", "company": "Bureau Veritas Hong Kong Limited", "job_title": "Manager/ Assistant Manager, Program Management", "description": "Role Purpose:\nOur Junior Merchandiser / Merchandiser Assistant are responsible for everyday end to end merchandising activities and support in the global sourcing and chain supply projects.\nWhat you will be handling:\nResponsible for order follow-up, buying trips preparation, sample handling and showroom management\nEngage in merchandising process such as sourcing, product development, article & offer management and supplier management\nWork directly with overseas suppliers and customers to ensure smooth operations\nCoordinate with internal departments e.g. Packaging, Quality Assurance, Logistics and other external service providers to ensure on-time shipment\nMaintain accurate and updated order status and product information in supply chain system\nTalent that we are looking for:\nExperience and knowledge\u00a0in\u00a0textile / garment industry\nGood negotiation skills and problem-solving skills\nOpen minded, right attitude to learn and bring about change\nEnergetic to drive for customer success and excellent service\nStrong sense of ownership and high degree of independence\nPassionate in connecting with people and adopting high level of interpersonal skills\nWilling to travel when needed\nExperience, knowledge and skills required:\nDegree holder in\u00a0Textiles / Fashion Merchandising / Business Administration / Supply Chain Management / International Business or equivalent discipline\nAt least 2 years\u2019 relevant merchandising experience, EU market experience is preferred\nProficient in both spoken and written English and Mandarin\nProficient in MS Office (Excel / Word / PowerPoint / Outlook) applications\nCandidate with less experience will be considered as\u00a0Merchandiser Assistant\nFresh graduates are also welcome\nYou can enjoy:\nDiverse and Inclusive work environment\nFlexi Office Space with flexible working hours and home office option\n5-day work week, 13th month salary & performance bonus\nProfessional training and career advancement opportunities\nTraining Sponsorship for personal professional development\n\n\nJoin us\u00a0and\u00a0apply\u00a0now!\n\n\nPlease send your full resume with available date, present and expected salary to us.\nResume and personal data collected will be kept strictly confidential and used for recruitment purpose only.", "employment_types": ["Full Time", "Permanent"], "selling_points": ["Global Leader in Testing Industry", "Double Pay, Discretionary Bonus, Medical Insurance", "Minimum 3 years relevant working experience"], "locations": ["Kowloon Bay"], "categories": ["Sciences, Lab, R&D", "Laboratory", "Merchandising & Purchasing", "Textiles", "Sales, CS & Business Devpt", "Account Servicing"], "post_time": "2022-01-07T09:39:02Z", "salary": {"currency": null, "max": null, "min": null, "period": "monthly", "term": null}, "salary_visible": false, "title_keywords": ["manager", "assistant manager,"], "responsibilities": ["management", "quality", "merchandising", "coordinate with", "maintain", "logistics", "ensure smooth operations", "recruitment", "personal data", "administration"], "requirements": {"degrees": ["degree", "degree holder"], "majors": ["international business", "business administration"], "languages": ["english", "mandarin"], "language_level": ["proficient"], "hard_skills": ["excel", "garment industry", "word", "powerpoint", "outlook", "problem-solving skills", "ms office"], "soft_skills": ["passionate", "flexible", "responsible", "diverse", "negotiation skills", "energetic", "interpersonal skills", "open minded", "smooth", "problem-solving skills", "accurate"], "languages_combined": [{"language": "english", "language_level": ["proficient"]}, {"language": "mandarin", "language_level": ["proficient"]}]}, "experience_required": {"duration": ["at least 2 years"], "field": ["textile", "merchandising", "garment"]}}, {"job_id": "100003009024283", "location_code": "hk", "company": "METRO Sourcing International Limited", "job_title": "Junior Merchandiser / Merchandiser Assistant (Textile / Garment)", "description": "Key responsibilities:\n\nPrepare OTB, seasonal and annual buying plans based on a thorough understanding of consumer, market trends and company business objectives\nMonitor closely on OTB, control sales and inventory to achieve seasonal sales and profit targets based on the seasonal business plan\nDetermine buying guides and assortment strategy in order to obtain a seasonal target\nOversee inventory costs, sales forecast, gross profit margin to achieve sales and profit targets\nFormulate pricing strategies based on competitive analysis, market reviews, competitor positions, and financials, etc.\nEvaluate ongoing performance and takes actions as appropriate\n\nQualifications:\n\nDegree holder in Fashion & Textiles or business discipline\nWith at least 5 years of experience in\u00a0buying and merchandising, preferably in the fashion/lifestyle/retail industry\nProactive, sensitive to figures and strong analytical and negotiation skills\nExcellent product sensibility and understanding of competitive retail landscape\nAttention to detail with a high level of accuracy\nHands-on analytical skills in MS Excel and ERP systems in a sizable corporation\nCandidates with less experience will be considered as Buyer\n\nInterested parties please apply below with your resume for a private discussion. All information collected will be kept in strict confidentiality.\u00a0", "employment_types": ["Full Time", "Permanent"], "selling_points": ["Exp in textile / garment merchandising", "Resp. for end to end merchandising activities", "MNC, 5-day work, insurance, double pay, bonus"], "locations": ["Kowloon Bay"], "categories": ["Merchandising & Purchasing", "Sweater", "Woven / Knit", "Textiles"], "post_time": "2022-01-05T20:32:10Z", "salary": {"currency": null, "max": null, "min": null, "period": "monthly", "term": null}, "salary_visible": false, "title_keywords": ["merchandiser", "junior merchandiser", "assistant"], "responsibilities": ["control", "inventory", "analysis", "monitor", "merchandising", "systems", "otb", "evaluate", "forecast", "business plan", "plans", "costs"], "requirements": {"degrees": ["degree holder"], "majors": ["business"], "languages": [], "language_level": [], "hard_skills": ["erp systems", "analysis", "ms excel", "analytical skills"], "soft_skills": ["sensitive to figures", "analytical skills", "negotiation skills", "hands-on", "thorough", "attention to detail", "proactive"], "languages_combined": []}, "experience_required": {"duration": ["at least 5 years"], "field": ["retail industry", "merchandising"]}}, {"job_id": "100003009029476", "location_code": "hk", "company": "Carter\u2019s Global Sourcing Limited", "job_title": "Senior Data Analyst", "description": "Responsibilities:\n\nWork independently and coordinate with teammates to fulfill the targets\nCommunicate company\u2019s core values to the team\nCoordinate with other teams closely\nKnowledge in inventory and warehouse management\nensure optimum inventory level\nimprove inventory turnover rate\nensure correct inventory information\nProduct matrix design and product line expansion\nManage sample books\nMaintenance of products, collections and brands description (include translation from English to Chinese)\nSet schedule of launch of new fabric collections and retirement of old collections\nKeep relationship with existing vendors\nSource reliable vendors and cope with disputes with vendors\nSolid experience in cost control and pricing strategy\nPerform ad hoc. duties as assigned\n\nRequirements:\n\n\n\nAt least 4 - 6 years experience in warehouse and inventory management related position.\nDegree Holder\nDiligent, Accountable, Get tasks done, Continuously improvement, Share and collaboration, Open and honest, Attention to details, Efficiency, Organization and planning, Analytical skills, Proactivity\nLeadership and team player\nProficient computer skills, including Microsoft Office Suite (Excel skill is very important) and ERP systems\nGood written and spoken English and Chinese (will need to communicate with vendors in English and Chinese, and do translation of products and brands introductions/information.)\nSolid knowledge and understanding of supply chain and inventory management\nKnowledge in fabric industry will be an advantage, but not a must. You will get sufficient knowledge from our adequate training as long as you are a person who eagers to learn\nLess experience may consider Assistant Officer\n\n\n\nData collected will be used for recruitment purposes only. Personal data provided by job applicants will be used strictly in accordance with the Personal Data (Privacy) Ordinance.\u00a0", "employment_types": ["Full Time"], "selling_points": ["Power Query, SQL, Tableau, Microsoft BI, Python, R", "Textiles", "Data Analyse"], "locations": ["Ngau Tau Kok"], "categories": ["Merchandising & Purchasing", "Textiles"], "post_time": "2022-01-07T05:22:12Z", "salary": {"currency": null, "max": null, "min": null, "period": "monthly", "term": null}, "salary_visible": false, "title_keywords": ["data analyst"], "responsibilities": ["management", "ad hoc", "maintenance", "inventory", "teams", "coordinate with", "design", "schedule", "cost control"], "requirements": {"degrees": ["degree holder"], "majors": [], "languages": ["english", "chinese"], "language_level": ["good"], "hard_skills": ["erp systems", "excel", "analytical skills", "microsoft office suite", "computer skills", "translation"], "soft_skills": ["diligent", "accountable", "analytical skills", "attention to details", "honest", "team player", "leadership"], "languages_combined": [{"language": "english", "language_level": ["good"]}, {"language": "chinese", "language_level": ["good"]}]}, "experience_required": {"duration": ["at least 4 - 6 years"], "field": ["inventory management", "related"]}}, {"job_id": "100003009023184", "location_code": "hk", "company": "Brown\u2019s", "job_title": "Senior Buyer - Menswear (BR-M)", "description": "Job Responsibilities\n\nAdhere to and drive 4 initiatives for GANT sourcing including: Sustainability, Quality, Speed and Transparency;\nResponsible for monitoring critical path including delivery of trims and fabric to supplier for on-time delivery of salesman samples and bulk to designated customers / markets;\nProvide support new supplier on boarding, development, cost analysis, price negotiation and system updates; Work with supplier on new innovative product options;\nEnsure suppliers are well-adhered with GANT standard and support in new project roll out and supplier training;\nCollaborate with head office and suppliers to eliminate open issues and mitigate risks of delay in both development and bulk;\nManage weekly production risk assessment and work on corrective action plan with suppliers;\nUpdate order status and weekly schedule on delivery process;\nWork with Logistics team for shipment, custom issues and delivery;\nAssist in ad hoc tasks as assigned\n\nJob Requirements\n\nHigh Diploma or above in Textile or related discipline;\n5+ years of relevant working experience in retail brand, preferably gained in buying office or multi-national companies;\nStrong knowledge on specific product category (Home Textile);\nFamiliar with product development procedure and schedule;\nGood system and data management;\nA good team player with sound communication and interpersonal skills;\nAttentive to details and good organization skills;\nGood command of English and Chinese (Mandarin and Cantonese);\nProficiency in Microsoft Word, Excel & PowerPoint, knowledge for PLM system will be of an advantage;\nOccasional travel is required\n\nInterested parties, please submit your job application and specify the product categories you have handled in your job experience.", "employment_types": ["Full Time"], "selling_points": ["5 years' fashion buying experience", "Budget planning, sales planning and analysis", "Formulate pricing strategies"], "locations": ["Southern Area"], "categories": ["Merchandising & Purchasing", "Textiles", "Others", "Procurement / Purchasing / Sourcing"], "post_time": "2022-01-05T07:44:38Z", "salary": {"currency": null, "max": null, "min": null, "period": "monthly", "term": null}, "salary_visible": false, "title_keywords": [], "responsibilities": ["collaborate with", "provide support", "price negotiation", "system updates", "monitoring", "quality", "ad hoc tasks", "logistics", "schedule", "plan", "cost analysis"], "requirements": {"degrees": ["high diploma or above"], "majors": [], "languages": ["cantonese", "english", "chinese", "mandarin"], "language_level": ["good command"], "hard_skills": ["excel", "microsoft word", "data management", "powerpoint"], "soft_skills": ["organization skills", "good team player", "communication and interpersonal skills", "attentive to details"], "languages_combined": [{"language": "cantonese", "language_level": ["good command"]}, {"language": "english", "language_level": ["good command"]}, {"language": "chinese", "language_level": ["good command"]}, {"language": "mandarin", "language_level": ["good command"]}]}, "experience_required": {"duration": ["5+ years"], "field": ["retail", "brand", "relevant working experience"]}}, {"job_id": "100003009022201", "location_code": "hk", "company": "Triumph International Services (APAC) Limited", "job_title": "Senior Sourcing Specialist", "description": "Accountabilities \u2013 Key Result Areas\n\nAssist buying team in execute buying activities, stock planning and allocation, and merchandise delivery and reordering situations to meet company business objectives\nPrepare merchandising reports for management review on business performance and inventory turn\nAssist OTB planning, sell through, mark down logistics\nWork with marketing and retail teams in regard to speedy response to market dynamics and promotions\nSupport buyers to prepare seasonal product training material and market research analysis\n\nExperience / Qualification Requirements\n\nDegree holder in Fashion & Textiles or business discipline\nWith 1-2 years of experience in\u00a0buying and merchandising, preferably in the fashion / lifestyle / retail industry\nProactive, sensitive to figures and strong analytical and negotiation skills\nAdequate product sensibility and understanding of competitive retail landscape\nAttention to detail with high level of accuracy\nHands on analytical skills in MS Excel and ERP systems in sizable corporation\n\nCompetitive remuneration and benefit package will be offered to the right candidate. Please submit your application by clicking \"Apply Now\" below.\n\nDBcampaignaviation\n\nAll data collected is for recruitment purpose only.\n\nSure you want to know more about our company and brands, simply follow our\n\nWEBSITE at http://www.ithk.com\u00a0 \u00a0 \u00a0 \u00a0 \u00a0 \u00a0 \u00a0 \u00a0 \u00a0 \u00a0 \u00a0 \u00a0 \u00a0 \u00a0 \u00a0 \u00a0 \u00a0 \u00a0 \u00a0 \u00a0 \u00a0 \u00a0 \u00a0 \u00a0 \u00a0 \u00a0 \u00a0 \u00a0 \u00a0 \u00a0 \u00a0 \u00a0 \u00a0 \u00a0\u00a0\n\nFACEBOOK at\u00a0http://www.facebook.com/I.Ttheofficialpage\u00a0 \u00a0 \u00a0 \u00a0 \u00a0 \u00a0 \u00a0 \u00a0 \u00a0 \u00a0 \u00a0 \u00a0 \u00a0 \u00a0\u00a0\n\nINSTAGRAM at http://instagram.com/ithk\u00a0 \u00a0 \u00a0 \u00a0 \u00a0 \u00a0 \u00a0 \u00a0 \u00a0 \u00a0 \u00a0 \u00a0 \u00a0 \u00a0 \u00a0 \u00a0 \u00a0 \u00a0 \u00a0 \u00a0 \u00a0 \u00a0 \u00a0 \u00a0 \u00a0 \u00a0 \u00a0 \u00a0\n\nWEIBO at\u00a0http://e.weibo.com/ithongkong", "employment_types": ["Full Time", "Permanent"], "selling_points": ["execute sourcing strategies", "forecast changev", "negotiate to minimize the impact"], "locations": ["Kowloon Bay"], "categories": ["Manufacturing", "Garment / Textile", "Merchandising & Purchasing", "Textiles"], "post_time": "2022-01-05T05:13:43Z", "salary": {"currency": null, "max": null, "min": null, "period": "monthly", "term": null}, "salary_visible": false, "title_keywords": ["specialist"], "responsibilities": ["data", "inventory", "analysis", "merchandising", "teams", "market research", "otb", "systems", "website", "reports", "logistics", "recruitment", "facebook", "stock planning", "management review", "planning"], "requirements": {"degrees": ["degree holder"], "majors": ["business"], "languages": [], "language_level": [], "hard_skills": ["erp systems", "analysis", "analytical skills", "ms excel", "facebook"], "soft_skills": ["sensitive to figures", "analytical skills", "negotiation skills", "hands on", "attention to detail", "proactive"], "languages_combined": []}, "experience_required": {"duration": ["1-2 years"], "field": ["retail industry", "merchandising"]}}, {"job_id": "100003009025983", "location_code": "hk", "company": "Artextile International Company Limited", "job_title": "Assistant Procurement and Product Manager", "description": "Responsibilities : -\n\n* Explore new client bases to achieve sales growth\n\n* To sell and promote products to fit customers\u2019 needs\n\n* To communicate with customers independently and provide timely support and services to customers.\n\n* Handle orders follow-up\n\n* Develop sales strategies to build a proactive long-lasting relationship with clients and maximize sales performances\n\n* Achieve business target\n\nRequirements : -\n\n*\u00a0Minimum Level 2 in 5 New Senior Secondary School Subjects in HKDSE or Form 5 standard or above or Diploma in Textile & Clothing studies or related education background is preferred.\n\n*\u00a0At least 2 years sales experience in garment field is an advantage.\n\n*\u00a0Self-motivated, excellent interpersonal, communication and experience in customer relationship management.\n\n*\u00a0Good command of written and spoken English & Mandarin\n\n* Business travel is required.\n\n*\u00a0Immediate available is highly preferable\n\n(Candidate will less experience will be considered for the post of Sales Representative.)\n\nWe offer an attractive remuneration package as well as good career prospects.\u00a0\n\nInterest parties, please send full resume with expected salary to Human Resources Department\u00a0email : suntak@suntak .com\u00a0.\n\nPlease visit our website www.suntak.com for company information.\n\nInformation collected will only be used in connected with recruitment proposes.\u00a0 All applications will be treated in strict confidence .", "employment_types": ["Full Time", "Permanent"], "selling_points": ["4-6 years\u2019 relevant experience", "Five-day work", "Immediately available is preferred"], "locations": ["Not Specified"], "categories": ["Merchandising & Purchasing", "Fabrics", "Textiles", "Procurement / Purchasing / Sourcing"], "post_time": "2022-01-06T06:58:10Z", "salary": {"currency": null, "max": null, "min": null, "period": "monthly", "term": null}, "salary_visible": false, "title_keywords": ["product manager", "assistant"], "responsibilities": ["communicate with", "promote products", "develop"], "requirements": {"degrees": ["diploma", "form 5", "hkdse"], "majors": [], "languages": ["english", "mandarin"], "language_level": ["good command"], "hard_skills": [], "soft_skills": ["communication", "self-motivated", "interpersonal"], "languages_combined": [{"language": "english", "language_level": ["good command"]}, {"language": "mandarin", "language_level": ["good command"]}]}, "experience_required": {"duration": ["at least 2 years"], "field": ["garment", "management"]}}, {"job_id": "100003009018893", "location_code": "hk", "company": "Gant Asia Pacific Limited", "job_title": "Merchandiser (Home Textile)", "description": "Job Description\n\nManage project plan, budget and calendar\nDevelop and own the data analysis model (via Tableau, Tableau Prep, Excel, SQL, etc)\nManage the SDLC lifecycle\nRecommend and support the introduction of new or improved data analytics and business practices\nProactively proposing technical solutions for solving data analysis issues and enhancing the performance\nLiaise with stakeholders to improve operations via technology\nIdentify and understand the business problem and identify the impact of proposed solutions\nIdentify new technologies and solutions to support the operations, keep abreast of industry trends\nExecute existing data model from data preparation, cleansing, transformation to end result\n\nJob Requirement\n\nDegree or above in Data Analysts / Computer Science / Statistic / Information Management\nAt least 5 years\u2019 Data Analyst experience mainly in apparel / textile field with buying office / MNC exposure\nExcellent skills on Power Query, SQL\nFamiliarize with Tableau / Microsoft BI\nProficiency in Python or R is an advantage\nExceptional communication & presentation skills\nExceptional analytical mindset and numerical sense\nFluent in written and spoken English, Chinese and Mandarin\nLess experience will be considered as\u00a0Data Analyst\n\nJob Benefits\n\n13th month\nGroup Life & Medical Insurance\nFlexible Working Hours\nCareer Development\nIn Carter's, we ensure to reward you with....\n\nComprehensive medical coverage including your spouse and children\n5-day work week and flexible working hours\nVoluntary MPF Scheme and various trainings for both soft and hard skills\nCareer development opportunities, U.S. friendly and open-minded culture\nInterested parties please send your application and resume, stating\u00a0Current, Expected Salary\u00a0&\u00a0Availability\u00a0by click to\u00a0APPLY NOW. We offer competitive remuneration package with excellent career prospect to the successful candidate. We regret that only short-listed candidates will be notified. Information collected will be used for recruitment purpose only.", "employment_types": ["Full Time", "Permanent"], "selling_points": [], "locations": ["Wan Chai"], "categories": ["Merchandising & Purchasing", "Textiles"], "post_time": "2022-01-04T05:55:09Z", "salary": {"currency": null, "max": null, "min": null, "period": "monthly", "term": null}, "salary_visible": false, "title_keywords": ["merchandiser"], "responsibilities": ["data", "operations", "cleansing", "budget", "project plan", "develop", "data analysis", "liaise with"], "requirements": {"degrees": ["degree or above"], "majors": ["computer science"], "languages": ["english", "chinese", "mandarin"], "language_level": ["fluent"], "hard_skills": ["bi", "tableau", "sql", "python", "r"], "soft_skills": ["communication", "presentation skills"], "languages_combined": [{"language": "english", "language_level": ["fluent"]}, {"language": "chinese", "language_level": ["fluent"]}, {"language": "mandarin", "language_level": ["fluent"]}]}, "experience_required": {"duration": ["at least 5 years"], "field": ["textile"]}}, {"job_id": "100003009028357", "location_code": "hk", "company": "Sun Tak International Holdings Limited", "job_title": "Sales Representative / Sales Executive \u2013 (Trims) \u71df\u696d\u4ee3\u8868", "description": "Job Descriptions:\n\nPrepare analysis, report and presentation PowerPoint for management review and regional meeting;\u00a0\u00a0\nCoordinate and communicate with Supplier/factories for testing & inspection procedures;\nManage incoming 3rd party inspection reports and work with suppliers on any issues;\nManage due diligence chemical testing;\nSupport Head of QA in TQM development and follow up factory audit CAP filing and review;\nGeneral admin support to QA team, create, maintain and file QA records (Inspection Certificate, Seal sample records, Factory audit reports);\nManage incoming Market Product Claims;\nSupport QA operation and Ad hoc projects\n\nQualifications:\n\n\nDegree in apparel design or related discipline;\u00a0\n2-3 experiences of experience in fashion industry preferred (fresh graduates are also welcome);\u00a0\nGood team player with sound communication skills;\u00a0\nAble to multi-task and work in a fast-paced environment;\nFluent in English\nComputer skills (Windows, Microsoft Office, Illustrator, etc.);\nStrong in data analysis & IT skills i.e. Excel, PowerPoint\n\nInterested parties please apply with detailed resume with current & expected salary.\n\nInterested parties, please submit your job application and specify the product categories you have handled in your job experience.", "employment_types": ["Full Time"], "selling_points": ["Develop and Maintain customer network", "Achieve sales target and handling sales order", "5 working days & development opportunities"], "locations": ["Kwai Hing"], "categories": ["Sales, CS & Business Devpt", "Business Development", "Merchandising & Purchasing", "Textiles", "Sales Administration"], "post_time": "2022-01-07T02:07:54Z", "salary": {"currency": null, "max": null, "min": null, "period": "monthly", "term": null}, "salary_visible": false, "title_keywords": ["\u71df\u696d\u4ee3\u8868", "sales representative", "sales executive"], "responsibilities": ["inspection reports", "audit", "design", "communication", "maintain", "management review", "due diligence", "testing", "reports", "report", "review", "procedures", "inspection", "data analysis", "admin support", "communicate with", "analysis", "coordinate", "ad hoc projects"], "requirements": {"degrees": ["certificate", "degree"], "majors": ["design"], "languages": ["english"], "language_level": ["fluent"], "hard_skills": ["excel", "microsoft office", "analysis", "illustrator", "powerpoint", "computer skills"], "soft_skills": ["communication skills", "good team player", "multi-task", "fast-paced environment", "presentation"], "languages_combined": [{"language": "english", "language_level": ["fluent"]}]}, "experience_required": {"duration": [], "field": []}}, {"job_id": "100003009019738", "location_code": "hk", "company": "Gant Asia Pacific Limited", "job_title": "QA Coordinator", "description": "Industry Field: Trims Accessories Trading\n\n- Be responsible and work hard\n- Office Duties work\n- Contact with customers via e-mail and phone\n- Follow up the sample order\n- Work with colleagues as teamwork\n- Well communication skills", "employment_types": ["Full Time", "Permanent"], "selling_points": [], "locations": ["Wan Chai"], "categories": ["Merchandising & Purchasing", "Textiles"], "post_time": "2022-01-04T08:34:17Z", "salary": {"currency": null, "max": null, "min": null, "period": "monthly", "term": null}, "salary_visible": false, "title_keywords": ["coordinator"], "responsibilities": ["communication", "contact"], "requirements": {"degrees": [], "majors": [], "languages": [], "language_level": [], "hard_skills": [], "soft_skills": ["communication skills", "teamwork", "responsible"], "languages_combined": []}, "experience_required": {"duration": [], "field": []}}, {"job_id": "100003009024887", "location_code": "hk", "company": "King-Choice Group Limited", "job_title": "Assistant Sales Clerk", "description": "Triumph is one of the world\u2019s largest intimate apparel companies. It enjoys a presence in over 120 countries with the core brands Triumph\u00ae and sloggi\u00ae. Globally, the company serves 40,000 wholesale customers and sells its products in 4,050\u00a0controlled points of sale as well as via several own online shops. The Triumph Group is a member of the Business Social Compliance Initiative (BSCI).\n\nLearn more about Triumph on:\n\nwww.triumph.com\n\nwww.linkedin.com/company/triumph-international/\n\nOur Global Strategic Sourcing Department at Kowloon Bay in Hong Kong is looking immediately for a highly motivated\u00a0Senior Sourcing Specialist\n\nRoles & Responsibilities:\n\nLed by the Head of the department to execute sourcing strategies to support company\u2018s P & L .\nAttend monthly business meetings or calls for the assigned category or region with SNP teams to understand the changes on forecast related to styles with 3rd party suppliers.\nAttend monthly or quarterly call with 3rd party suppliers to communicate the total capapcity for Triumph and discuss the impact from total forecast change and negotiate to minimize the impact.\nVisit to current suppliers if needed to execute product reenineering ,collecting pricing details and attend sourcing shows/exibitions to have better understanding of materials/prices/mills/new innovations\nAttend seasonal meeting or call with PD teams to ensure agreed allocation of product development is being executed smoothly and provide support in cost negotiation or suggestion on change of supplier allocation when needed.\nExecute supplier strategy and proctively evaluate country of origin\u00a0 to optimize for margin , product execution capability ,production capacity\u00a0 and agility.\nExecute long range key /strategic supplier capability and capacity booking and align supplier strategy with cross functional teams ( product development , CQA , compliance etc) to ensure product allocation in line with the\u00a0 capacity built with key/strategic suppliers to leverage power of cost negotiation for overall margin imporvement as well as for imporving operational efficiency and effectiveness\u00a0 related to working with 3PV suppliers .\nFollow process for Expatriation and Repatriation\nExecute value engineering project assigned by analyzing materials and construction of the product for cost negotiation or shift to achieve savings.\nMaintain strong and secure business relationships with key/strategic suppliers while constantly evaluating and assessing risks related to sourcing strategies in ever changing global political and other emergency situations\nBe able to create report or presentation in Microsoft Office document ( Excel, Word, PowerPoint)\u00a0 \u00a0 \u00a0 \u00a0\n\nYour ideal profile:\n\n\u00a05+ years experience in apparel sourcing or related supply chain for retailer/brand or trading company, preferably with deep product knowledge for intimates.Technical skills : costing, material consumption and garment construction; good understanding and execution of garment end to end process\nLanguage Skills: Good command of both written & spoken English, Cantonese and Mandarin is a must\nIT proficiency: MS Office\nOther skills : Negotiation, Co-ordination and ability to align teams and provide clarity, Communication, Analytical and basic project planning experience; strength in follow up\nMobility: Traveling globally is required\n\nWe offer an opportunity in a fast paced organization which gives those looking for a challenge the possibility to grow with the company and shape the future.\n\nWe are a family owned company with strong values, operating at a global level with key markets in Germany, Japan and China - where our iconic brands, Sloggi and Triumph, continue to delight our consumers.\n\nTriumph Group is committed to employing a diverse workforce. Qualified applicants will receive consideration without regard to race, color, religion, sex, national origin, age, sexual orientation, gender identity, gender expression, veteran status, or disability.\u00a0\n\nIf you are seeking a great opportunity to develop your career, please send us your application letter and CV in English, diplomas and expected salary range by clicking on Apply.\u00a0", "employment_types": ["Full Time", "Permanent"], "selling_points": ["minimum 1 year of experience", "Competitive package", "5 Days Work"], "locations": ["Shatin Area"], "categories": ["Manufacturing", "Garment / Textile", "Merchandising & Purchasing", "Textiles", "Others", "Trading"], "post_time": "2022-01-06T02:48:30Z", "salary": {"currency": "HKD", "max": 13999, "min": 11000, "period": "monthly", "term": null}, "salary_visible": true, "title_keywords": ["sales clerk", "assistant"], "responsibilities": ["cost", "provide support", "project planning", "compliance", "teams", "develop", "evaluate", "communication", "maintain", "booking", "forecast", "report"], "requirements": {"degrees": [], "majors": [], "languages": ["cantonese", "english", "mandarin"], "language_level": ["good command"], "hard_skills": ["excel", "basic", "microsoft office", "word", "powerpoint", "ms office"], "soft_skills": ["negotiation", "technical skills", "deep", "communication", "committed", "diverse", "motivated", "controlled", "mobility", "initiative", "presentation", "ideal"], "languages_combined": [{"language": "cantonese", "language_level": ["good command"]}, {"language": "english", "language_level": ["good command"]}, {"language": "mandarin", "language_level": ["good command"]}]}, "experience_required": {"duration": ["5+ years"], "field": ["brand", "analytical", "related", "supply chain", "trading", "planning"]}}, {"job_id": "100003009031556", "location_code": "hk", "company": "ConnectedGroup Limited", "job_title": "Merchandising Manager (garment manufacturer)", "description": "Merchandising Manager (garment manufacturer)\n\nMy client is a sizable & renowned manufacturer, who is looking for a Merchandising Manager. Reports to VP, leads small team in HK.\n\nKey responsibilities: -\n\nMerchandising Activities\nSupervise and lead the merchandising operations\nFollow production plans to ensure all orders are shipped on time\nConstant interaction and consultation on vendor capacity, order allocation etc.\nObserve and understand in detail the buyer's needs and provide as much support as possible\nVendor management\nAnalyse, evaluate and improve vendor's capabilities and performance\nExpand or consolidate vendor base when appropriate\nPrice negotiation and create detailed cost saving plans and methods\nLead-time negotiation along with regular trouble shooting issues such as deliveries and quality issues\nCommunications with internal support teams\nAssist in certain quality driven initiatives\nAssist in any quality issues, claims or disputes between buyers/QA with vendors\nMonitor potential quality issues and execute relative solutions to ensure they can be avoided\n\nRequirements: -\n\nDiploma or above in Textiles / Fashion / related discipline\nMinimum 8 years relevant sourcing experience\nExcellent Cantonese, Mandarin and English\nWilling to travel\n\nInterested parties pls send your CV to Angela Tsui angela.tsui@connectedgroup.com for more details.\n\nFor other available opportunities, please visit www.connectedgroup.com", "employment_types": ["Full Time", "Permanent"], "selling_points": ["Sizable & renowned manufacturer", "Leads small team, reports to VP", "Welcome any category"], "locations": ["Not Specified"], "categories": ["Merchandising & Purchasing", "Sweater", "Woven / Knit", "Textiles"], "post_time": "2022-01-07T09:27:51Z", "salary": {"currency": null, "max": null, "min": null, "period": "monthly", "term": null}, "salary_visible": false, "title_keywords": ["merchandising manager"], "responsibilities": ["management", "price negotiation", "cost", "communications with", "operations", "merchandising", "quality", "teams", "monitor", "evaluate", "plans", "analyse"], "requirements": {"degrees": ["diploma or above"], "majors": [], "languages": ["cantonese", "english", "mandarin"], "language_level": ["excellent"], "hard_skills": [], "soft_skills": [], "languages_combined": [{"language": "cantonese", "language_level": ["excellent"]}, {"language": "english", "language_level": ["excellent"]}, {"language": "mandarin", "language_level": ["excellent"]}]}, "experience_required": {"duration": ["minimum 8 years"], "field": []}}, {"job_id": "100003009019742", "location_code": "hk", "company": "Sung IL International Company Limited", "job_title": "HR & Admin Assistant", "description": "Responsibilities\n\n\n\n1. Provide office administration support for the company\n\n2. Provide secretarial support to the management\n\n3. Handle\u00a0and submit\u00a0motor vehicle license application\u00a0\n\n4. Handle leave applications and recuitment\n\n5. Perform general clerical duties including data entry, filing records\n\n6. Support front desk duty (answering calls, greeting guests, handling courier/mail)\n\nQualification\n\n1. Good command of both written and spoken English, Chinese & Putonghua\n\n2. Well-versed with internet and MS Office and Chinese word processing\n\n3. Self-motivated, responsible, multi-tasked and able to meet tight deadline and work under pressure\n\n4. Good communication and interpersonal skills and well-organized\n\n5. Experience in handling insurance license matter is a definite plus.\n\n6. Immediate availability is preferred", "employment_types": ["Full Time"], "selling_points": [], "locations": ["Kwai Fong"], "categories": ["Manufacturing", "Garment / Textile", "Merchandising & Purchasing", "Fabrics", "Textiles"], "post_time": "2022-01-04T08:35:13Z", "salary": {"currency": null, "max": null, "min": null, "period": "monthly", "term": null}, "salary_visible": false, "title_keywords": ["hr & admin assistant"], "responsibilities": ["management", "office administration support", "data entry", "communication", "secretarial support", "license application", "insurance", "work under pressure"], "requirements": {"degrees": [], "majors": [], "languages": ["putonghua", "english", "chinese"], "language_level": ["good command"], "hard_skills": ["plus", "chinese word processing", "ms office"], "soft_skills": ["self-motivated", "responsible", "well-organized", "multi-tasked", "communication and interpersonal skills", "meet tight deadline", "work under pressure"], "languages_combined": [{"language": "putonghua", "language_level": ["good command"]}, {"language": "english", "language_level": ["good command"]}, {"language": "chinese", "language_level": ["good command"]}]}, "experience_required": {"duration": [], "field": ["insurance"]}}, {"job_id": "100003008838499", "location_code": "hk", "company": "Profits Fund Fashion Manufacturing Ltd", "job_title": "Sales Manager", "description": "Responsibilities:\n\nTo explore/expand new customers and business opportunities to achieve company sales target\nTo perform budget planning and forecast and directing the business development to drive sustainable growth based on market intelligence and data analysis\nTo formulate strategies and identify directions for managing the merchandising operation in order to deliver excellent standards to clients, which return achieving the Company goals to cope with the highly competitive markets\nTo co-ordinate with related departments to ensure reaching the delivery schedule and quality requirements\nPerforming ad hoc duties as assigned\n\nJob Requirement:\n\nDegree holder in merchandising, fashion, textile or related disciplines\nAt least 8 years\u2019 relevant working experience, preferably in sales and business development\nStrong verbal and written communication skills (English and Mandarin) and interpersonal skills\nStrong capability of the cost control and product portfolio management\nProficient in MS Office including Word, Excel and PowerPoint\nDetail-oriented, proactive and able to work independently", "employment_types": ["Full Time"], "selling_points": [], "locations": ["Kwai Fong"], "categories": ["Merchandising & Purchasing", "Textiles"], "post_time": "2022-01-06T02:36:08Z", "salary": {"currency": null, "max": null, "min": null, "period": "monthly", "term": null}, "salary_visible": false, "title_keywords": ["sales manager"], "responsibilities": ["ad hoc duties", "budget planning", "co-ordinate with", "sales target", "business opportunities", "merchandising", "quality", "data analysis", "delivery schedule", "forecast"], "requirements": {"degrees": ["degree holder"], "majors": ["related disciplines"], "languages": ["english", "mandarin"], "language_level": [], "hard_skills": ["excel", "word", "powerpoint", "ms office"], "soft_skills": ["communication skills", "work independently", "detail-oriented", "interpersonal skills", "proactive"], "languages_combined": [{"language": "english", "language_level": []}, {"language": "mandarin", "language_level": []}]}, "experience_required": {"duration": ["at least 8 years"], "field": ["business development", "relevant working experience"]}}, {"job_id": "100003009019645", "location_code": "hk", "company": "Takara Personnel Consultancy", "job_title": "AM/ M/ SM/ Fashion Designer/Multimedia Designer   - Urgent", "description": "AM/ M/ SM/ Fashion Designer/ Multimedia Designer/Purchaser (Garment / Trims trading)\n\nAssistant Merchandiser / Merchandiser (Garment/ Fabric)\u00a0\nSenior Merchandiser (Japanese Speaker)\n\nDesigner / Graphic Designer (Trims/Apparel)\n\nCertificate\u00a0Or above in Fashion, Clothing & Textile or relative discipline\n\nFamiliar with USA, EU\u00a0and Japan Market\u00a0 & Mfg. Background\nGood spoken & written English & Mandarin are must\nMature, stable, well-organized, independent\nWith strong communication & interpersonal skill\nAssists in production development, price negotiation, sample & production follow up\nFresh grad also consider\n\n**Immediate available is highly preferred\n\n\n** Pls write down apply which post number on the mail / resume **\n\n\nPlease send your application with detailed resume and expected salary to\nhr@takara.hk\n\n\n**Personal data collected will be used for recruitment purpose only**\n", "employment_types": ["Full Time", "Permanent"], "selling_points": [], "locations": ["Central & Western Area"], "categories": ["Design", "Fashion", "Multi-media", "Merchandising & Purchasing", "Textiles"], "post_time": "2022-01-04T08:13:03Z", "salary": {"currency": null, "max": null, "min": null, "period": "monthly", "term": null}, "salary_visible": false, "title_keywords": ["fashion designer", "multimedia designer"], "responsibilities": ["communication", "price negotiation", "recruitment", "personal data"], "requirements": {"degrees": ["certificate"], "majors": [], "languages": ["japanese", "english", "mandarin"], "language_level": ["good"], "hard_skills": ["multimedia"], "soft_skills": ["independent", "negotiation", "well-organized", "mature", "interpersonal skill", "communication", "stable", "detailed"], "languages_combined": [{"language": "japanese", "language_level": []}, {"language": "english", "language_level": ["good"]}, {"language": "mandarin", "language_level": ["good"]}]}, "experience_required": {"duration": [], "field": []}}, {"job_id": "100003009020299", "location_code": "hk", "company": "Golden Cedar Elastic Webbing Mfg Co Limited", "job_title": "Assistant Merchandiser (Trims), 5day work/ bank holiday", "description": "Job description:\n\n\nPurchase order issuance and production tracking management\nManage purchase and production timeline with various departments and factories\nEnd-to-end order tracking, inventory management and monitor for timely & efficient delivery schedules\nCoordinate closely between overseas office and factories for production follow-up\nCreate and maintain system master\nTo assist senior management to prepare correspondence\nHandle ad hoc tasks when required\n\nRequirements:\n\nEducation: F.5 graduates or equivalent\nImmediately available is highly preferred\nFluent in written and spoken English and Chinese\nAble to work under a pressure\nGood interpersonal, problem-solving, stability, communication and presentation skills\u00a0\n\nBenefits:\n\n5 days work\ndouble pay\nbirthday leave\nmedical\u00a0allowance\nbank holiday\npromotional opportunities", "employment_types": ["Full Time"], "selling_points": ["Purchase order issuance and production tracking", "5-day week, double pay, promotional opportunities", "Garment Trims"], "locations": ["Kwai Hing"], "categories": ["Merchandising & Purchasing", "Textiles", "Procurement / Purchasing / Sourcing", "Others", "Student / Fresh Graduate / No Experience"], "post_time": "2022-01-04T10:28:24Z", "salary": {"currency": null, "max": null, "min": null, "period": "monthly", "term": null}, "salary_visible": false, "title_keywords": ["assistant merchandiser"], "responsibilities": ["order tracking", "management", "schedules", "monitor", "ad hoc tasks", "inventory management", "coordinate", "purchase", "maintain", "senior management", "tracking"], "requirements": {"degrees": [], "majors": [], "languages": ["english", "chinese"], "language_level": ["fluent"], "hard_skills": ["problem-solving"], "soft_skills": ["communication", "problem-solving", "interpersonal", "presentation skills"], "languages_combined": [{"language": "english", "language_level": ["fluent"]}, {"language": "chinese", "language_level": ["fluent"]}]}, "experience_required": {"duration": [], "field": []}}, {"job_id": "100003009013727", "location_code": "hk", "company": "Clover Global Limited", "job_title": "Senior Merchandiser (Garment/Lingerie)", "description": "Job Duties\n1.\u00a0Responsible for the coordination of daily operational activities in product development and/or order follow up\n2.\u00a0Liaise and communicate with overseas customers, factories in mainland China and offshore areas and internal depts. to ensure product samples and bulk production are met with clients\u2019 requirements\n3.\u00a0Assist in negotiation on price and costing package\n4.\u00a0Diagnose production problems and work with factories / suppliers to present alternatives to both clients and management\n5.\u00a0Monitor order tracking activities to meet quantity, quality, order specification and delivery dates requirements.\n6.\u00a0Perform any other duties as assigned by the superior and/or their designate from time to time\n\u00a0\n\nJob Requirements\n1.\u00a0Diploma or above in Textile & Clothing or related discipline\n2.\u00a0At least 5 years experience in garment merchandising\n3.\u00a0Experience in brassiere/lingerie products is highly preferred\n4.\u00a0Smart, presentable & mature for problem solving\n5.\u00a0Good PC knowledge including Chinese word processing\n6.\u00a0Excellent command of both written and spoken English, able to communicate in Mandarin\n\nWe offer competitive remuneration package including 5-day work, discretionary bonus, medical & group life insurance to the right candidate. Interested parties please send your full resume with current & expected salary via email attention to Human Resources Department\u00a0 by clicking \"APPLY NOW\" to visit our website and select Career.\n\nWe are an equal opportunity employer and welcome applicants from all qualified candidates. Information provided will be treated in strict confidence and only be used for consideration of your application for the relevant or similar post(s) within our Group only. Applicants not having heard from us within 6 weeks from the date of this advertisement may consider their application unsuccessful. All personal data of unsuccessful applications will be destroyed within 6 months.", "employment_types": ["Full Time", "Permanent"], "selling_points": [], "locations": ["Lai Chi Kok"], "categories": ["Merchandising & Purchasing", "Woven / Knit", "Textiles", "Others"], "post_time": "2022-01-03T02:40:13Z", "salary": {"currency": null, "max": null, "min": null, "period": "monthly", "term": null}, "salary_visible": false, "title_keywords": ["senior merchandiser"], "responsibilities": ["liaise", "communicate with", "management", "order tracking", "any other duties", "diagnose", "monitor", "quality", "coordination"], "requirements": {"degrees": ["diploma or above"], "majors": [], "languages": ["english", "chinese", "mandarin"], "language_level": ["excellent", "good"], "hard_skills": ["problem solving", "pc knowledge", "chinese word processing"], "soft_skills": ["problem solving", "mature", "presentable"], "languages_combined": [{"language": "english", "language_level": ["excellent"]}, {"language": "chinese", "language_level": ["good"]}, {"language": "mandarin", "language_level": ["excellent"]}]}, "experience_required": {"duration": ["at least 5 years"], "field": ["garment", "merchandising"]}}, {"job_id": "100003009015776", "location_code": "hk", "company": "Boardriders Asia Sourcing Limited", "job_title": "Global Category Sourcing Manager (Swim)", "description": "Responsibilities:\n\nCategory Sourcing Strategy\nSupplier Matrix Development\nProvide insight on sourcing trend and environment\nIdentification, Commercial Assessment, Onboarding and Development of Suppliers\nCapacity Management with venders\nFollow up samples comment till pre-production\nCosting analysis and management\nTeam supervision, ensuring and monitoring performance & overall tracking activities\nChallenge working possess, investigate, diagnose and give recommendation on problem solving and improvements\nDrive the company strategy, provide guideline and support to the Brands and Region\nMonitor the development calendar, responsible for the sample development, submission and comments according to the schedule and fit for region requirement\nPerformance Management & Communication\nWork closely with internal departments on development and resolve issues\nAd hoc and overall duties required from time to time to ensure effectiveness\nRequirements:\n\nBachelor\u2019s Degree in clothing, textile or related discipline preferred\nSolid working experience in Apparel industry with at least 7 years in managerial position, preferably gained in buying office or multi-national companies\nSubstantial knowledge and solid experience in product development and process improvement is preferable\nAbility to execute project work plans and revise as appropriate to meet changing needs\nDetailed & organized, hardworking and over-time working may needed\nProficient in English & strong preference for Mandarin/Cantonese and or another relevant Asian language\nProficiency in Microsoft Office, Illustrator and Photoshop\nImmediate available is preferred\nAttractive salary and comprehensive benefits will be offered to the right candidate. Interested parties please submit detailed resume with applying position, expected salary, availability and contact details to Human Resources Department via \u201cApply Now\u201d.\n\nPersonal data collected will be kept confidential and used for recruitment purpose only.\n", "employment_types": ["Full Time", "Permanent"], "selling_points": ["Category Sourcing Strategy & Matrix development", "Follow up samples comment till pre-production", "Ensuring & monitoring overall tracking activities"], "locations": ["Kowloon Bay"], "categories": ["Merchandising & Purchasing", "Woven / Knit", "Textiles", "Procurement / Purchasing / Sourcing"], "post_time": "2022-01-04T00:51:58Z", "salary": {"currency": null, "max": null, "min": null, "period": "monthly", "term": null}, "salary_visible": false, "title_keywords": ["sourcing manager"], "responsibilities": ["management", "ad hoc", "monitoring", "diagnose", "monitor", "comments", "communication", "schedule", "costing analysis", "pre-production", "tracking"], "requirements": {"degrees": ["degree", "bachelor"], "majors": [], "languages": ["cantonese", "english", "mandarin"], "language_level": ["proficient"], "hard_skills": ["photoshop", "illustrator", "microsoft office"], "soft_skills": ["organized", "hardworking", "detailed"], "languages_combined": [{"language": "cantonese", "language_level": ["proficient"]}, {"language": "english", "language_level": ["proficient"]}, {"language": "mandarin", "language_level": ["proficient"]}]}, "experience_required": {"duration": ["at least 7 years"], "field": ["managerial", "product development"]}}, {"job_id": "100003009020070", "location_code": "hk", "company": "Komar Sourcing Limited", "job_title": "Assistant Shipping Manager (5-Days work)", "description": "Requirements:\n\n\nUndergraduate or College preferable\nWith knowledge of EDI/Blue Cherry/CPSIA System\u00a0\nFamiliar with the regulations of importing countries for wearing apparel items\nOver 15 years supervisory/managerial level\nWell experience and knowledge in shipping & documentation work-flow for shipment to USA/Middle East/Japan/Australia/Mexico/EU market\nGood command of both written and spoken English, Chinese (including Mandarin)\nGood communication skills and strong sense of responsibility\nGood team-player with excellent interpersonal skills\nProficient in MS office\n\nDuties:\n\nSupervise and guide the team for their daily routine work\nCommunicate with all departments within Komar group including USA/HK/Netherlands/Canada/Sri-Lanka/Bangladesh/China offices on daily basis\nLiaising with all Komar agents/factories about shipping document issues\nCommunicate with Forwarder/Carriers about shipment booking & shipment information issue\nFollow up with EDI service provider about system set up or technical issue\nPerform ad-hoc assignment as requested\u00a0\u00a0\n\nWe offer 5-day work,\u00a0year-end bonus, medical insurance.\n\nInterested parties please send your full resume including current and expected salary by clicking \"Apply Now\".\n\nPersonal data will be used for recruitment purpose only.", "employment_types": ["Full Time", "Permanent"], "selling_points": ["Undergraduate or College preferable", "15 yrs supervisory level & knowledge in apparel", "5 day work week"], "locations": ["Tsuen Wan Area"], "categories": ["Manufacturing", "Garment / Textile", "Transportation & Logistics", "Shipping", "Merchandising & Purchasing", "Textiles"], "post_time": "2022-01-04T09:51:09Z", "salary": {"currency": null, "max": null, "min": null, "period": "monthly", "term": null}, "salary_visible": false, "title_keywords": ["shipping", "manager", "assistant"], "responsibilities": ["communicate with", "ad-hoc", "liaising with", "booking", "shipping document"], "requirements": {"degrees": [], "majors": [], "languages": ["english", "chinese", "mandarin"], "language_level": ["good command"], "hard_skills": ["documentation", "ms office"], "soft_skills": ["team-player", "communication skills", "interpersonal skills", "sense of responsibility"], "languages_combined": [{"language": "english", "language_level": ["good command"]}, {"language": "chinese", "language_level": ["good command"]}, {"language": "mandarin", "language_level": ["good command"]}]}, "experience_required": {"duration": [], "field": []}}, {"job_id": "100003009016709", "location_code": "hk", "company": "HARVEY NICHOLS (HONG KONG) LIMITED", "job_title": "Assistant Buyer (Womenswear)", "description": "Responsibilities:\n\nAssist and support Merchandising Manager\u00a0 in all matters relating to buying, operations, and promotion initiatives;\nRegularly conduct market research; May attend overseas trade fairs with\u00a0Merchandising Manager;\nMonitor sales performance closely and execute stock transfer;\nPerform relevant business analysis in order to develop appropriate action plans to achieve financial targets set by Company;\nWork closely with Operations, Visual Merchandising team, and other counterparts to maximize sales performance of responsible category;\nConduct product training for the sales team. \u00a0\n\nRequirements:\n\nDegree holder preferably in fashion design or merchandising;\nMinimum\u00a02 years\u2019 relevant working experience in high-end fashion;\nStrong fashion sense, detail-oriented with good analytical and reporting skills;\nGood team player with a strong sense of responsibility;\nExcellent command of spoken English & Chinese;\nProficient in MS Word and Excel.\n\nWe offer excellent career prospects, competitive salary and fringe benefits to the right candidate.\u00a0 Please apply in strict confidence by sending personal resume together with salary expected and date available\n\nby e-mail to:\u00a0h r d\u00a0 _ h n @ h a r v e y n i c h o l s . c o m . h k\n\nWe are an equal opportunity employer and welcome applications from all qualified candidates. Personal data provided by job applicants will be used strictly in accordance with our personal data policy and for recruitment purposes only. Candidates not notified within eight weeks may consider their application unsuccessful. All related information will be kept in our file for up to 24 months. A copy of our Personal Information Collection Statement will be provided upon request by contacting our Human Resources Division.\u00a0", "employment_types": ["Full Time", "Permanent"], "selling_points": ["Assistant Buyer", "min 2 years' relevant working experience", "Strong fashion sense, detail-oriented"], "locations": ["Yau Tsim Mong Area"], "categories": ["Merchandising & Purchasing", "Footwear", "Handbag", "Textiles"], "post_time": "2022-01-03T09:40:40Z", "salary": {"currency": null, "max": null, "min": null, "period": "monthly", "term": null}, "salary_visible": false, "title_keywords": ["assistant"], "responsibilities": ["operations", "conduct market research", "sales performance", "merchandising", "monitor", "develop", "sales team", "visual", "business analysis", "plans"], "requirements": {"degrees": ["degree holder"], "majors": ["design"], "languages": ["english", "chinese"], "language_level": ["excellent"], "hard_skills": ["excel", "ms word"], "soft_skills": ["good team player", "sense of responsibility", "detail-oriented"], "languages_combined": [{"language": "english", "language_level": ["excellent"]}, {"language": "chinese", "language_level": ["excellent"]}]}, "experience_required": {"duration": ["minimum 2 years"], "field": ["relevant working experience"]}}, {"job_id": "100003009023189", "location_code": "hk", "company": "I.T Apparels Limited", "job_title": "Merchandise Planner - E-Commerce (REF:JDB-IT-AMP)", "description": "Accountabilities \u2013 Key Result Areas\n\nAssist monitoring of OTB, pre-season and in-season sales forecast, margin, receipts and inventory on a monthly basis.\u00a0\nWork closely with buyers to monitor planned sales, planned gross profit, and planned markdowns\nManage good balance of stock level among stores\nManage mark down during sale period so as to maximize sales and maintain planned gross profit\nEnsure that on-order and committed receipts are delivering on time to support forecasts and sales\nAssist report preparations on sales trends and patterns, stock replenishment and inventory level in weekly cycle\nMonitor periodically the stock level, merchandise allocation plan, logistics flow from ordering to delivery at stores\u00a0\nWork with cross functional team and stores to create transfers and as needed to drive sales.\nTo support ad-hoc assignments or inventory related projects\n\nExperience / Qualification Requirements\n\nDegree holder in business or supply chain related discipline\n3 years working experience in a planning, buying or merchandising function\nHighly sensitive to figures and strong analytical skills\nAttention to detail with high level of accuracy\nGood interpersonal skills and presentation skills\nCandidates with less experience will be considered as Assistant Merchandise Planner\u00a0\n\nCompetitive remuneration and benefit package will be offered to the right candidate. Please submit your application by clicking \"Apply Now\" below.\n\nAll data collected is for recruitment purpose only.\n\nSure you want to know more about our company and brands, simply follow our\n\nWEBSITE at\u00a0http://www.ithk.com\u00a0 \u00a0 \u00a0 \u00a0 \u00a0 \u00a0 \u00a0 \u00a0 \u00a0 \u00a0 \u00a0 \u00a0 \u00a0 \u00a0 \u00a0 \u00a0 \u00a0 \u00a0 \u00a0 \u00a0 \u00a0 \u00a0 \u00a0 \u00a0 \u00a0 \u00a0 \u00a0 \u00a0 \u00a0 \u00a0 \u00a0 \u00a0 \u00a0 \u00a0\u00a0\n\nFACEBOOK at\u00a0http://www.facebook.com/I.Ttheofficialpage\u00a0 \u00a0 \u00a0 \u00a0 \u00a0 \u00a0 \u00a0 \u00a0 \u00a0 \u00a0 \u00a0 \u00a0 \u00a0 \u00a0\u00a0\n\nINSTAGRAM at\u00a0http://instagram.com/ithk\u00a0 \u00a0 \u00a0 \u00a0 \u00a0 \u00a0 \u00a0 \u00a0 \u00a0 \u00a0 \u00a0 \u00a0 \u00a0 \u00a0 \u00a0 \u00a0 \u00a0 \u00a0 \u00a0 \u00a0 \u00a0 \u00a0 \u00a0 \u00a0 \u00a0 \u00a0 \u00a0 \u00a0\n\nWEIBO at\u00a0http://e.weibo.com/ithongkong", "employment_types": ["Full Time", "Permanent"], "selling_points": ["Degree holder in business or supply chain", "3 years working experience", "Assist monitoring of OTB, pre-season"], "locations": ["Southern Area"], "categories": ["Merchandising & Purchasing", "Textiles", "Procurement / Purchasing / Sourcing", "Sales, CS & Business Devpt", "Retail Sales"], "post_time": "2022-01-05T07:44:40Z", "salary": {"currency": null, "max": null, "min": null, "period": "monthly", "term": null}, "salary_visible": false, "title_keywords": [], "responsibilities": ["receipts", "data", "inventory", "merchandising", "website", "otb", "maintain", "plan", "facebook", "stock replenishment", "monitor", "logistics", "forecast", "report", "monitoring", "drive sales", "ad-hoc assignments", "recruitment", "planning"], "requirements": {"degrees": ["degree holder"], "majors": ["business"], "languages": [], "language_level": [], "hard_skills": ["planner", "facebook", "analytical skills"], "soft_skills": ["sensitive to figures", "analytical skills", "committed", "presentation skills", "interpersonal skills", "attention to detail"], "languages_combined": []}, "experience_required": {"duration": ["3 years"], "field": ["merchandising", "planning"]}}, {"job_id": "100003009022635", "location_code": "hk", "company": "ConnectedGroup Limited", "job_title": "Product Compliance Manager (Material & Garment Trims)", "description": "Product Compliance Manager (Material & Garment Trims)\n\nMy client is a multinational manufacturer & distributor based in US, who is looking for a manager to head up the Product Compliance team across HK & China.\n\nDuties:\n\nEstablish, implement, continuously improve SOP across their global business, e.g. root cause investigation, testing arrangement, review legislation, RSL\nWork externally with customers, 3rd party service provider etc. to drive intelligence sharing and benchmark with company process\nMonitor compliance program with updated initiatives, e.g. ZDHC, MRSL, oekotex\n\nRequirements:\n\nPrefer Bachelor's Degree in Chemistry, Environmental Engineering, Environmental Science\nMinimum 8 years' experience in garment / trims industry with related product compliance experience\nProject management mindset\nStrong presentation skills in English\nWilling to travel\n\nPlease send your CV to Angela Tsui from ConnectedGroup (Angela.Tsui@connectedgroup.com) for more details. Email address could be found on LinkedIn as well.\n\nFor more opportunities, please visit www.connectedgroup.com", "employment_types": ["Full Time", "Permanent"], "selling_points": ["Multinational manufacturer & distributor based US", "Head up HK & China team", "Strong presentation skills in English"], "locations": ["Not Specified"], "categories": ["Manufacturing", "Garment / Textile", "Merchandising & Purchasing", "Textiles", "Quality Assurance, Control & Testing / ISO"], "post_time": "2022-01-05T06:00:19Z", "salary": {"currency": null, "max": null, "min": null, "period": "monthly", "term": null}, "salary_visible": false, "title_keywords": ["compliance manager"], "responsibilities": ["compliance", "review", "monitor", "investigation", "testing"], "requirements": {"degrees": ["degree", "bachelor"], "majors": ["environmental science", "chemistry", "environmental engineering"], "languages": ["english"], "language_level": [], "hard_skills": ["project management"], "soft_skills": ["project management", "presentation skills"], "languages_combined": [{"language": "english", "language_level": []}]}, "experience_required": {"duration": ["minimum 8 years"], "field": ["garment", "compliance", "related"]}}, {"job_id": "100003009013729", "location_code": "hk", "company": "D-mop Limited", "job_title": "Assistant Buyer / Buying Assistant", "description": "Responsibilities\n\nAssist for the development of products\u00a0and buying plans.\nExecute administration works related to purchases, deliveries, pricing, returns and promotion\nSupport in preparing sales and inventory reports\nMaintain good working relationship with vendors for business development.\nHandle and monitor ad hoc projects.\n\nRequirements:\n\nDegree/ Diploma holder in fashion or other related disciplines;\n2 years solid buying and OTB calculation experiences in fashion retail industry;\nStrong interest and passionate towards fashion with good sense of fashion market;\nGood command in Both Written and spoken English & Chines;\nProficiency in MS Word, Excel and Powerpoint;\nCandidate with less experience would be considered as Buying Assistant.\n\nWe offer 5-day work, double pay and attractive remuneration package to the successful candidate. Interested parties can send your detail resume and expected salary to\u00a0us.\n\nAll information received will be kept in strict confidence and only for employment purposes.", "employment_types": ["Full Time", "Permanent"], "selling_points": [], "locations": ["Lai Chi Kok"], "categories": ["Merchandising & Purchasing", "Textiles", "Others", "Procurement / Purchasing / Sourcing"], "post_time": "2022-01-03T02:39:16Z", "salary": {"currency": null, "max": null, "min": null, "period": "monthly", "term": null}, "salary_visible": false, "title_keywords": ["buying assistant", "assistant"], "responsibilities": ["inventory", "monitor", "maintain", "reports", "ad hoc projects", "plans", "administration"], "requirements": {"degrees": ["diploma holder", "degree"], "majors": ["related disciplines"], "languages": ["english"], "language_level": ["good command"], "hard_skills": ["excel", "powerpoint", "ms word"], "soft_skills": ["passionate"], "languages_combined": [{"language": "english", "language_level": ["good command"]}]}, "experience_required": {"duration": ["2 years"], "field": ["retail industry"]}}, {"job_id": "100003009023137", "location_code": "hk", "company": "", "job_title": "Operations Manager", "description": "Position: Operations Manager (Hong Kong-based)\n\nJob Overview:\u00a0Responsible for supervising & improving the implementation of our merchandising team across our offices and production countries\n\nResponsibilities and Duties:\n\nProvide leadership & supervise to Merchandising team\u00a0across our offices and production countries\nEnsure smooth running of the whole merchandising process from customer servicing, product development, supplier sourcing, vendor selection and quality management to product delivery\nCommunicate effectively with the team leaders in our management offices regarding any production, quality, testing or compliance related issues, with a focus on steps to improve our procedures or training \u00a0\nKeeping close contact with customers\nMaintaining performance KPI\u2019s and overview reports\nManage the budget for the merchandising team in specific locations to ensure cost efficiency\n\nRequirements:\n\n15+ years of experience in quality and compliance across the Asia-Pacific & South Asian regions, of which at least 5 years in a similar senior role\nBachelor\u2019s degree in textile engineering or related subjects\nExtensive knowledge of the technical aspects of apparel construction & production, as well as fabric and yarn production\nExcellent computer skills, like Excel, Word and PowerPoint\nFluency in English, Cantonese and Mandarin, both verbally and in writing\nInterested candidates, please contact us at 29935253 for company details before applying.", "employment_types": ["Full Time"], "selling_points": ["A leading global sourcing and trading house", "Corporate role based in Hong Kong", "Excellent career development opportunity"], "locations": ["Kowloon Bay"], "categories": ["Manufacturing", "Garment / Textile", "Merchandising & Purchasing", "Textiles"], "post_time": "2022-01-05T07:43:51Z", "salary": {"currency": null, "max": null, "min": null, "period": "monthly", "term": null}, "salary_visible": false, "title_keywords": ["operations manager"], "responsibilities": ["management", "cost", "maintaining", "compliance", "quality", "merchandising", "procedures", "testing", "budget", "team across", "reports", "contact"], "requirements": {"degrees": ["degree", "bachelor"], "majors": ["engineering"], "languages": ["cantonese", "english", "mandarin"], "language_level": ["fluency"], "hard_skills": ["excel", "computer skills", "word", "powerpoint"], "soft_skills": ["extensive"], "languages_combined": [{"language": "cantonese", "language_level": ["fluency"]}, {"language": "english", "language_level": ["fluency"]}, {"language": "mandarin", "language_level": ["fluency"]}]}, "experience_required": {"duration": ["15+ years", "at least 5 years"], "field": ["compliance"]}}, {"job_id": "100003009016181", "location_code": "hk", "company": "adidas Sourcing Limited", "job_title": "Manager Materials Sustainability APP", "description": "Purpose & Overall Relevance for the Organization\n\nSupport and drive sustainability focused materials programs (e.g. development and implementation of traceability related processes, policies and systems/tools) and ensure compliant execution for assigned geography and supply base ensuring adidas objectives are met.\n\nKey Responsibilities\n\nSupport global initiatives for creation of new adidas policies / Standard Operating Procedures (SOPs) and systems/tools (e.g. SMTT 2.0) in collaboration with internal and external parties\nExecute and be business key user for (new) materials traceability systems/tools, coordinate with other key users across the company and proactively provide apparel\u00a0business insights and share local requirements of the assigned geography / supply base\nDrive local implementation of adidas initiatives (e.g. the Sustainable Material Traceability SOP and SMTT 2.0 tool), onboard internal and external stakeholders and provide trainings as well as guidance for related processes or systems/tools\nMonitor and analyse process and user performance for the assigned supply base, proactively identify issues, develop solutions with relevant stakeholders (incl. operations improvement plans, user trainings / communications, system enhancements, etc.) and drive implementation to improve performance\nMonitor supplier data input performance to ensure on time and in full data submission (accountable for related key performance indicators)\nPerform and coordinate onsite audits to secure compliant process execution and required data accuracy in traceability tool is achieved\nDevelop a strong degree of knowledge in materials traceability processes, SOPs, tools/ systems to understand interdependencies to other processes/SOPs/systems in order to ensure alignment with the overall brand strategy and key objectives\nFacilitate best practice exchange and continuous improvement efforts proactively with Apparel Materials (Traceability) Managers in other regions and/or other relevant stakeholders\nSupport and guide all system users on daily operation tasks, solve daily system operation issues\nSupport other sustainability / materials initiatives as appropriate after traceability processes and systems/tools are running smoothly\n\nKey Relationships\n\nApparel Materials Sustainability\nSocial & Environmental Affairs (SEA)\nGarment (T1), and Materials (T2), Upstream (T3) Suppliers\nFootwear / Accessories & Gears Materials Sourcing Teams\nApparel Sourcing Liaison Offices (e.g. Operations, Quality, Planning)\nInformation Technology (IT)\nStrategy & Programs Sourcing / Product Operations\nOther Global Operations functions\nExternal companies (suppliers and Certification Bodies e.g. Control Union)\n\n\n\nKnowledge Skills and Abilities\n\nStrong communication & negotiation skills\nProcess thinking / end-to-end mindset\nStrong knowledge in Materials, Sustainability and Materials Traceability topics (incl. related documentation requirements, systems, etc.)\nGood understanding of supply chain mechanics (from raw materials to garment production) and brands (from sourcing to customer) preferably gained within Apparel industry\nStrong implementation and execution skills (incl. ability to\u00a0create, plan and deliver Presentations, Workshops & Trainings)\nFluent English, verbal and written\nStrong problem solving and analytical skills with ability to\u00a0synthesize complex data\u00a0for reporting purposes\nAbility to work independently or with limited guidance\nAdvanced Microsoft Office skills (Word, Excel, PowerPoint, Outlook, etc.)\n\n\n\nRequisite Education and Experience / Minimum Qualifications\n\nUniversity degree in textile, supply chain management, industrial engineering or similar\nMinimum 5 years working experience, ideally in material sourcing or related field of Apparel\nPrevious work experience in Testing Services Providers an advantage\n1-2 years experience in project management (formal certification e.g. 6 Sigma, PMP an advantage)\nSolid operations expertise or experience in process management & KPI ownership", "employment_types": ["Full Time", "Permanent"], "selling_points": ["Passion in Traceability", "Pioneering in this Industry", "Apparel Materials Sustainability"], "locations": ["Ngau Tau Kok"], "categories": ["Transportation & Logistics", "Supply Chain", "Merchandising & Purchasing", "Textiles", "Procurement / Purchasing / Sourcing"], "post_time": "2022-01-03T08:42:41Z", "salary": {"currency": null, "max": null, "min": null, "period": "monthly", "term": null}, "salary_visible": false, "title_keywords": ["manager"], "responsibilities": ["related documentation", "data", "operations", "internal and external parties", "quality", "communication", "planning", "plan", "plans", "control", "monitor", "implementation", "teams", "develop", "presentations", "testing", "guidance", "reporting", "management", "procedures", "coordinate with", "sops", "audits", "policies", "systems", "daily operation", "data input", "coordinate", "project management", "analyse"], "requirements": {"degrees": ["university degree", "degree"], "majors": ["engineering"], "languages": ["english"], "language_level": ["fluent"], "hard_skills": ["workshops", "excel", "microsoft office", "word", "presentations", "analytical skills", "problem solving", "powerpoint", "project management", "outlook", "documentation", "pmp", "exchange"], "soft_skills": ["work independently", "advanced", "focused", "accountable", "communication", "problem solving and analytical skills", "negotiation skills", "project management"], "languages_combined": [{"language": "english", "language_level": ["fluent"]}]}, "experience_required": {"duration": ["1-2 years", "minimum 5 years"], "field": ["management", "related", "testing", "education", "project management"]}}]