[{"job_id": "100003009047648", "location_code": "hk", "company": "", "job_title": "Senior Merchandiser / Merchandiser (Toy)", "description": "Responsibilities:\u00a0 \u00a0\n\nPrimary customer interface to coordinate customer requirement to lab operations.\nProvide friendly and professional pre-sale and post-sales throughout order transaction.\nHandle sample registration and release of test report.\nHandle customer enquiry on service capacity, quotation, reporting status, report contents and complaints.\nFollow up with customer on missing information and samples.\nProvide regular summary report to customer regarding the lab service.\n\nRequirements:\n\nMinimum 3 years\u2019 relevant experience in laboratory testing company (Candidates with less experience will be considered as Customer Service Executive).\nHighly-organized, able to work independently and capable of working under pressure with multi-task assignments.\nGood command of English and Chinese.\nGood computer skills.\nFamiliar with European regulations/standards is an advantage.\nHaving the experience of component sorting is an advantage.\n\nIMMEDIATELY AVAILABLE is PREFERRED\n\n5 days work (overtime and weekend work required if necessary).\n\n*Interested parties please send your full resume stating date of availability, present and expected salary\u00a0via\u00a0APPLY NOW Button.*", "employment_types": ["Full Time", "Permanent"], "selling_points": [], "locations": ["Not Specified"], "categories": ["Merchandising & Purchasing", "Toy", "Sundries"], "post_time": "2022-01-15T01:52:26Z", "salary": {"currency": null, "max": null, "min": null, "period": "monthly", "term": null}, "salary_visible": false, "title_keywords": ["merchandiser", "senior merchandiser"], "responsibilities": ["reporting", "operations", "quotation", "coordinate", "contents", "report"], "requirements": {"degrees": [], "majors": [], "languages": ["english", "chinese"], "language_level": ["good command"], "hard_skills": ["computer skills"], "soft_skills": ["organized", "work independently", "under pressure", "capable", "multi-task", "customer service"], "languages_combined": [{"language": "english", "language_level": ["good command"]}, {"language": "chinese", "language_level": ["good command"]}]}, "experience_required": {"duration": ["minimum 3 years"], "field": ["laboratory testing", "customer service", "relevant experience"]}}, {"job_id": "100003009053947", "location_code": "hk", "company": "MGA Entertainment (H.K.) Ltd", "job_title": "Assistant Costing Manager", "description": "We are the Asia Pacific Sales branch office for one of the leading toy companies based in Germany.\u00a0\u00a0 We are now looking for a Merchandising and Shipping Executive to join the team.\n\nJob Responsibilities:\n\n-\u00a0\u00a0\u00a0\u00a0\u00a0\u00a0\u00a0\u00a0\u00a0 Coordinate, follow up and process orders from factory to overseas clients independently.\n\n-\u00a0\u00a0\u00a0\u00a0\u00a0\u00a0\u00a0\u00a0\u00a0 Maintain and update order-processing system\n\n-\u00a0\u00a0\u00a0\u00a0\u00a0\u00a0\u00a0\u00a0\u00a0 Handle shipping operation with required documents\n\n-\u00a0\u00a0\u00a0\u00a0\u00a0\u00a0\u00a0\u00a0\u00a0 Frequent communication with both factories and overseas customers\n\n-\u00a0\u00a0\u00a0\u00a0\u00a0\u00a0\u00a0\u00a0\u00a0 Reports generation\n\nRequirements:\n\n-\u00a0\u00a0\u00a0\u00a0\u00a0\u00a0\u00a0\u00a0\u00a0 Degree holder in Business related disciplines with minimum 3 years solid experience in International trading.\u00a0 Toy industry a plus.\n\n-\u00a0\u00a0\u00a0\u00a0\u00a0\u00a0\u00a0\u00a0\u00a0 Fluency in both written and spoken English, Cantonese and Mandarin.\n\n-\u00a0\u00a0\u00a0\u00a0\u00a0\u00a0\u00a0\u00a0\u00a0 Excellent interpersonal and communication skills\n\n-\u00a0\u00a0\u00a0\u00a0\u00a0\u00a0\u00a0\u00a0\u00a0 Open minded to multicultural business\n\n-\u00a0\u00a0\u00a0\u00a0\u00a0\u00a0\u00a0\u00a0\u00a0 Strong analytical skills, detail-minded and able to work in multi-task environment under pressure independently and in a team.\n\n-\u00a0\u00a0\u00a0\u00a0\u00a0\u00a0\u00a0\u00a0\u00a0 Well-versed in MS Office such as Excel, Word and PowerPoint.\n\n-\u00a0\u00a0\u00a0\u00a0\u00a0\u00a0\u00a0\u00a0\u00a0 Occasional travels to China may be required\n\n-\u00a0\u00a0\u00a0\u00a0\u00a0\u00a0\u00a0\u00a0\u00a0 Immediate availability is highly preferred\n\nBenefits and Others:\n\nOur office is located in Tsim Sha Tsui.\u00a0 Attractive remuneration package including 5-day work week, bank holidays, 13-month pay, medical benefits and etc. will be offered to the successful candidate.\n\nInterested parties please send CV with expected salary by clicking APPLY NOW.\n", "employment_types": ["Full Time", "Permanent"], "selling_points": [], "locations": ["Tsim Sha Tsui"], "categories": ["Engineering", "Engineering Project Management", "Merchandising & Purchasing", "Fabrics", "Toy"], "post_time": "2022-01-17T07:49:15Z", "salary": {"currency": null, "max": null, "min": null, "period": "monthly", "term": null}, "salary_visible": false, "title_keywords": ["manager", "assistant"], "responsibilities": ["shipping", "process orders", "coordinate", "communication", "maintain", "reports"], "requirements": {"degrees": ["degree holder"], "majors": ["related disciplines", "business"], "languages": ["cantonese", "english", "mandarin"], "language_level": ["fluency"], "hard_skills": ["excel", "plus", "word", "powerpoint", "analytical skills", "ms office"], "soft_skills": ["detail-minded", "communication skills", "independently", "multi-task", "under pressure", "analytical skills", "open minded", "interpersonal"], "languages_combined": [{"language": "cantonese", "language_level": ["fluency"]}, {"language": "english", "language_level": ["fluency"]}, {"language": "mandarin", "language_level": ["fluency"]}]}, "experience_required": {"duration": ["minimum 3 years"], "field": ["related", "business", "trading"]}}, {"job_id": "100003009050068", "location_code": "hk", "company": "Jaz Toys HK Limited", "job_title": "PROJECT MANAGER \u2013 TOYS", "description": "Diploma or above in engineering disciplines\nMinimum 8 years costing and\u00a0tooling experience in toys field, especially in soft toys and fabric material\nKnowledge of manufacturing processes and product design is an added advantage\nSound computer knowledge, especially in Microsoft software\nGood communication skills in English and Chinese (both written and spoken), Putonghua speaking is an advantage\nLocate the fabric source with product development and reach out for cost\nWork on cost comparison on the fabric source and confirm the fabric supplier with Product Development team\nVerify and negotiate the fabric cost with the fabric vendor and sewn goods on production factory\nProvide internal cost estimate and cost reduction suggestions on the sewn goods\n\nInterested parties with relevant experience and qualification, please send detailed resume and expected salary to HR Department, MGA Entertainment,\u00a0Suite 301, Chinachem Golden Plaza, 77 Mody Road, TST East, Kowloon or via email.\n\n(All information collected is used for recruitment purpose only)", "employment_types": ["Full Time"], "selling_points": ["Degree/diploma in Manufacturing/Mechanical Eng.", "min. 5 years working exp.in consumer toys products", "Able to manage critical milestones of product dev."], "locations": ["Chai Wan"], "categories": ["Merchandising & Purchasing", "Toy"], "post_time": "2022-01-14T09:43:18Z", "salary": {"currency": null, "max": null, "min": null, "period": "monthly", "term": null}, "salary_visible": false, "title_keywords": ["project manager"], "responsibilities": ["communication", "cost", "product design", "software"], "requirements": {"degrees": ["diploma or above"], "majors": ["engineering"], "languages": ["putonghua", "english", "chinese"], "language_level": ["advantage", "good"], "hard_skills": ["vendor"], "soft_skills": ["communication skills"], "languages_combined": [{"language": "putonghua", "language_level": ["advantage", "good"]}, {"language": "english", "language_level": ["advantage", "good"]}, {"language": "chinese", "language_level": ["advantage", "good"]}]}, "experience_required": {"duration": ["minimum 8 years"], "field": ["toys"]}}, {"job_id": "100003009043763", "location_code": "hk", "company": "", "job_title": "MERCHANDIER  - PLUSH TOYS", "description": "Job Description:\n\nThe Project Manager participates in the product development process by coordinating new projects with the US Development department while working directly with the Company\u2019s Project and Design team and Asia vendor base to complete the development.\u00a0 The position requires collaboration to ensure that design, character integrity, quality, safety and target price point issues are coordinated and organized properly, and that products are developed within established timelines.\u00a0\n\n\u00a0\u00a0 \u00a0\n\nThe successful candidate should possess the following requirements:\n\nDegree / diploma in Manufacturing / Mechanical Engineering\nA minimum of 5 years of working experience in consumer toys products\nSolid working experience at a manufacturing site is crucial\nCapability in creating/modifying/finalizing product specifications based on ideation\nAble to manage critical milestones of product development, such as prototyping, testing and production\nResolving technical issues with various involved parties\nGood problem-solving skills and schedule-oriented mind-set is a must\nAbility to interact as a team player\nGood command of spoken and written English, Cantonese/Chinese and Mandarin\nSelf-motivated, with strong sense of commitment and able to manage multiple projects simultaneously\nAbility to work in a fast-paced environment\nExceptional organizational skills and a great attention to detail\n\nDuties:\n\nDevelop new proprietary and licensed products that can be sold in multiple worldwide markets\nReceive specs from US-based Product Developer, interpret/clarify specs and communicate final product specs to vendors\nUnderstand technologies and be able to convert concepts into product features\nOversee product development from ideation to production\nInterpret product art packages and communicate these to our Asia vendor base\nPerform functional testing on different types of samples/products\nIndependently source new suppliers or solution partners\nUnderstanding of USA and EU certification standards is a definite advantage\nStation in China\nMore working experiences will consider for a senior post", "employment_types": ["Full Time"], "selling_points": [], "locations": ["Kowloon Bay"], "categories": ["Merchandising & Purchasing", "Toy"], "post_time": "2022-01-13T01:52:06Z", "salary": {"currency": null, "max": null, "min": null, "period": "monthly", "term": null}, "salary_visible": false, "title_keywords": [], "responsibilities": ["quality", "manage multiple projects", "design", "testing", "develop", "specifications", "schedule"], "requirements": {"degrees": ["diploma", "degree"], "majors": ["manufacturing", "mechanical engineering"], "languages": ["cantonese", "english", "chinese", "mandarin"], "language_level": ["good command"], "hard_skills": ["problem-solving skills", "vendor"], "soft_skills": ["organized", "self-motivated", "organizational skills", "manage multiple projects simultaneously", "independently", "fast-paced environment", "integrity", "attention to detail", "problem-solving skills", "team player"], "languages_combined": [{"language": "cantonese", "language_level": ["good command"]}, {"language": "english", "language_level": ["good command"]}, {"language": "chinese", "language_level": ["good command"]}, {"language": "mandarin", "language_level": ["good command"]}]}, "experience_required": {"duration": ["minimum of 5 years"], "field": ["toys products", "manufacturing"]}}, {"job_id": "100003009048438", "location_code": "hk", "company": "Hillman Ross", "job_title": "Assistant Sourcing Manager (Toys)", "description": "Responsibility\n\n- To sever the customers from USA and Europe\n\n- Flexible to work with our US Office and China Office\n\n- Process the orders from sourcing, quotation, samples delivery etc.\n\nRequiremnets\n\n- F. 5 or above\n\n- At least 3 years experiences in Plush Toys field\n\n- Good communication skill in Cantonese / English / Mandarin\n\n- Good PC skills\n\n- Occasional China Trips needed\n\n- Independent, well organized\n\n\u00a0Interested parties, please contact Ms Cheung at 27561911 before applying.", "employment_types": ["Full Time", "Permanent"], "selling_points": ["European company", "Toys category", "Experience in handling plush is a Must"], "locations": ["Not Specified"], "categories": ["Merchandising & Purchasing", "Toy", "Others", "Procurement / Purchasing / Sourcing"], "post_time": "2022-01-14T06:35:00Z", "salary": {"currency": null, "max": null, "min": null, "period": "monthly", "term": null}, "salary_visible": false, "title_keywords": ["assistant", "sourcing manager"], "responsibilities": ["quotation"], "requirements": {"degrees": [], "majors": [], "languages": ["cantonese", "english", "mandarin"], "language_level": ["good"], "hard_skills": ["pc skills"], "soft_skills": ["communication skill", "independent", "well organized"], "languages_combined": [{"language": "cantonese", "language_level": ["good"]}, {"language": "english", "language_level": ["good"]}, {"language": "mandarin", "language_level": ["good"]}]}, "experience_required": {"duration": ["at least 3 years"], "field": ["toys"]}}, {"job_id": "100003009054342", "location_code": "hk", "company": "MGA Entertainment (H.K.) Ltd", "job_title": "Costing Engineer / Industrial Engineer", "description": "Our client is a European company and they are looking for an Assistant Sourcing Manager to take care of toys category. This person will be an individual contributor, reporting to the Sourcing Manager.\n\nWe are now seeking for Assistant Sourcing Manager (Toys)\n\nRESPONSIBILITIES\n\nWell organization skills of dealing with complex product categories, manage high sku and multi-countries production base.\nDevelop product and vendor strategies to drive for continue business growth.\nWork with the Sourcing Managers to evaluate the performance of factories and assess the business risk that support clients' business needs.\nSupervise and guide a team of merchandisers and coordinate with cross functional teams to achieve excellent KPI to meet client's expectation.\nStrong and in-depth negotiation skills to drive cost saving and costing margin for clients' continue business growth.\nFull ownership of the whole supply chain from factory sourcing, development till shipment with in-depth technical knowledge, proactive on problem precaution & strong decision maker.\nManage the team to ensure they are up to the company standard\nMotivate the team by sharing knowledge and expertise, ensuring attention to detail and seeking continuous improvements\nDevelop a close relationship with existing suppliers and develop new suppliers through personal connections, trade fairs and sourcing trips\nProduct, payment and business term negotiations with suppliers.\n\nTo succeed in this key role, you will have at least 10 years experience in sourcing with at least 6 years in managerial capacity.\n\nQUALIFICATIONS:\n\nTertiary educated\nSelf-motivated and have strong sense of responsibility.\nStrong people and process management skills\nStrong analytical and interpersonal skills\nIndependent and excellent time management in meeting deadline.\nStrong communication skills and fluent in English, Mandarin and Cantonese\nExperience in handling plush is a Must\nExperience working in European market is a MUST\n\nAPPLY FOR THIS JOB\n\nInterested candidate please CLICK apply button to apply online or send your resume in MS word format to Hillman Ross Recruitment Solution Professional\n\nPlease note that only shortlisted candidate will be notified. All information will be treated in strict confidence and solely used for recruitment purposes.", "employment_types": ["Full Time", "Permanent"], "selling_points": [], "locations": ["Tsim Sha Tsui"], "categories": ["Engineering", "Manufacturing & Production", "Manufacturing", "Product Development / Management", "Merchandising & Purchasing", "Toy"], "post_time": "2022-01-17T09:12:34Z", "salary": {"currency": null, "max": null, "min": null, "period": "monthly", "term": null}, "salary_visible": false, "title_keywords": ["engineer"], "responsibilities": ["product categories", "reporting", "cost", "continuous improvements", "management", "coordinate with", "teams", "develop", "evaluate", "communication", "payment", "support clients", "recruitment"], "requirements": {"degrees": [], "majors": [], "languages": ["cantonese", "english", "mandarin"], "language_level": ["fluent"], "hard_skills": ["vendor", "ms word"], "soft_skills": ["communication skills", "self-motivated", "confidence", "independent", "sense of responsibility", "time management", "negotiation skills", "interpersonal skills", "attention to detail", "organization skills", "proactive"], "languages_combined": [{"language": "cantonese", "language_level": ["fluent"]}, {"language": "english", "language_level": ["fluent"]}, {"language": "mandarin", "language_level": ["fluent"]}]}, "experience_required": {"duration": ["at least 10 years", "at least 6 years"], "field": ["managerial"]}}, {"job_id": "100003009041325", "location_code": "hk", "company": "Wowwee Group Limited", "job_title": "Merchandiser", "description": "Diploma or above with minimum 5 years softgoods merchandising experience\nKnowledge of manufacturing processes is an added advantage\nAnalytical and attentive to details with good negotiation and problem solving skills\nSound computer knowledge, especially in Microsoft software\nGood communication skills in English and Chinese (both written and spoken), Putonghua speaking is an advantage\n\nInterested parties with relevant experience and qualification, please send detailed resume and expected salary to HR Department, MGA Entertainment,\u00a0Suite 301, Chinachem Golden Plaza, 77 Mody Road, TST East, Kowloon or via email.", "employment_types": ["Full Time"], "selling_points": ["5 years working experience in Toys field", "Experience in exporting to European & South Americ", "Communicate and closely follow up with both overse"], "locations": ["Tsim Sha Tsui"], "categories": ["Merchandising & Purchasing", "Toy"], "post_time": "2022-01-12T03:44:57Z", "salary": {"currency": null, "max": null, "min": null, "period": "monthly", "term": null}, "salary_visible": false, "title_keywords": ["merchandiser"], "responsibilities": ["communication", "merchandising", "software"], "requirements": {"degrees": ["diploma or above"], "majors": [], "languages": ["putonghua", "english", "chinese"], "language_level": ["advantage", "good"], "hard_skills": ["problem solving skills"], "soft_skills": ["communication skills", "problem solving skills", "negotiation", "attentive to details"], "languages_combined": [{"language": "putonghua", "language_level": ["advantage", "good"]}, {"language": "english", "language_level": ["advantage", "good"]}, {"language": "chinese", "language_level": ["advantage", "good"]}]}, "experience_required": {"duration": ["minimum 5 years"], "field": ["merchandising"]}}, {"job_id": "100003009051108", "location_code": "hk", "company": "Yeko Manufacturing Limited", "job_title": "Plastic injection specialist", "description": "Description:\u00a0\n\n8 years+ solid experience in hard toys injection in manufacturing plants\nStation in Vietnam\nDaily operation, problem solving, quality assurance and good time management\u00a0\nGood communication skills, problem solving and highly responsible", "employment_types": ["Full Time"], "selling_points": ["Plastic injection specialists", "Vietnam stationed", "8 years experience"], "locations": ["Overseas"], "categories": ["Manufacturing", "Manufacturing Management", "Merchandising & Purchasing", "Toy"], "post_time": "2022-01-15T02:26:23Z", "salary": {"currency": null, "max": null, "min": null, "period": "monthly", "term": null}, "salary_visible": false, "title_keywords": ["specialist"], "responsibilities": ["communication", "quality", "management", "daily operation"], "requirements": {"degrees": [], "majors": [], "languages": [], "language_level": [], "hard_skills": ["problem solving"], "soft_skills": ["problem solving", "communication skills", "time management", "responsible"], "languages_combined": []}, "experience_required": {"duration": [], "field": ["toys", "manufacturing"]}}, {"job_id": "100003009050438", "location_code": "hk", "company": "AllRightsReserved Limited", "job_title": "Product Design / Developer (Toy and Figure)", "description": "Responsibilities\n\nTo coordinate with internal designer to support new products development, sourcing, sampling and QC\nTo work closely with suppliers and review product brief and initiate/ensure product schedule effectively\nMonitor and\u00a0communicate\u00a0progress and challenge throughout the production\n\nRequirements\n\nForm 5 graduate or above\nMinimum 4 years relevant working experience\nGood Knowledge of China sourcing is a must\u00a0\nGood Knowledge in Photoshop/ Illustrator & MS Office\u00a0is advance\nWell organised and able to work independently\u00a0\u00a0\nGood command of written and spoken English, Cantonese and Mandarin\nWilling to work overtime and under pressure\nWilling to travel to China and visit factory\nImmediate availability is preferable.\n\nWe offer 5-day work week, medical insurance and attractive remuneration package to qualified candidates.\n\nInterested parties please send resume via email\n\n(Personal data collected will be kept confidential and used for recruitment purpose only)", "employment_types": ["Full Time"], "selling_points": [], "locations": ["Wan Chai"], "categories": ["Manufacturing", "Production Planning / Control", "Merchandising & Purchasing", "Toy"], "post_time": "2022-01-14T10:25:46Z", "salary": {"currency": null, "max": null, "min": null, "period": "monthly", "term": null}, "salary_visible": false, "title_keywords": ["developer"], "responsibilities": ["monitor", "review", "coordinate with", "schedule"], "requirements": {"degrees": ["form 5"], "majors": [], "languages": ["cantonese", "english", "mandarin"], "language_level": ["good command"], "hard_skills": ["ms office", "illustrator", "photoshop"], "soft_skills": ["work independently", "work overtime", "under pressure", "organised"], "languages_combined": [{"language": "cantonese", "language_level": ["good command"]}, {"language": "english", "language_level": ["good command"]}, {"language": "mandarin", "language_level": ["good command"]}]}, "experience_required": {"duration": ["minimum 4 years"], "field": ["relevant working experience"]}}, {"job_id": "100003009047363", "location_code": "hk", "company": "Cosmic Pet HK Limited", "job_title": "Project Coordinator / Assistant Merchandiser \u2013 Pet Products/Children Toys/Plastic Toys", "description": "Responsibilities:\n\nMaintain overall aspects of designs and engineering phase, while keeping the product development costs and timelines to market in focus;\nCollaborate with cross-functioning team including the US office, design team, project team, suppliers, to ensure multiple projects are being executed according to plan or timeline;\nProduct Sourcing and cost analysis;\nCoordinate, monitor the product design and project implementation;\nResponsible for product testing, packing design and package artwork handling.\n\n\u00a0Qualification & Requirements:\n\nDegree or above;\n2-year experiences in Children toys/Pet Products/Plastic items;\nFresh graduate will be considered;\nStrong PC skills and familiar with Project handling;\nKnowledge of manufacturing processes and molding processes will be an advantage;\nSelf-motivated, able to work under pressure, good problem-solving skills;\nGood interpersonal & communication skills;\nProficient in spoken & written English and Mandarin;\nOccasionally travel to overseas and China;", "employment_types": ["Full Time"], "selling_points": ["Product Development, Merchandising, Sourcing", "Pet Products / Hard Toys / Gifts & Premium", "5-day work, Double Pay, Performance Bonus, Medical"], "locations": ["Lai Chi Kok"], "categories": ["Manufacturing", "Product Development / Management", "Merchandising & Purchasing", "Toy"], "post_time": "2022-01-14T02:54:46Z", "salary": {"currency": null, "max": null, "min": null, "period": "monthly", "term": null}, "salary_visible": false, "title_keywords": ["project coordinator", "assistant merchandiser"], "responsibilities": ["collaborate with", "development costs", "monitor", "implementation", "design", "testing", "coordinate", "maintain", "product design", "plan", "multiple projects", "cost analysis"], "requirements": {"degrees": ["degree or above", "fresh graduate"], "majors": [], "languages": ["english", "mandarin"], "language_level": ["proficient"], "hard_skills": ["problem-solving skills", "pc skills"], "soft_skills": ["communication skills", "self-motivated", "problem-solving skills", "interpersonal", "work under pressure"], "languages_combined": [{"language": "english", "language_level": ["proficient"]}, {"language": "mandarin", "language_level": ["proficient"]}]}, "experience_required": {"duration": ["2-year"], "field": ["toys"]}}, {"job_id": "100003009047120", "location_code": "hk", "company": "Longshore Ltd", "job_title": "Senior Merchandiser / Merchandiser - Toys", "description": "Responsibilities:\n\nHandle and Coordinate Plastic & Paper product development cycle (including board games & puzzles) with factory\nResponsible in\u00a0managing suppliers, product development schedule,\u00a0costing comparison & calculation, sourcing material and vendors.\nFollow-up orders with factory, customers and internal parties to ensure customer satisfaction and on-time delivery\nHandle ad-hoc assignments as required\n\nRequirements:\n\nForm 7 or above\n3 years experiences in\u00a0OEM/ODM Plastic & Paper products (Experiences in Board game, Puzzle are preferred)\nStrong with plastic paper development cycle / schedule\u00a0is a definite advantage\nGood in English and good in PC/ERP knowledge\nExcellent communication skills with overseas customers and vendors are essential\nDetail-minded, well-organized, responsible and can work independently\nImmediately available is preferred\n\nAlternate Saturday, Double pay, Medical, Annual leave, Bonus\n\nWe offer attractive remuneration packages and excellent career opportunities. Interested parties please send resume states clearly expected salary by \"Apply Now\"", "employment_types": ["Full Time", "Permanent"], "selling_points": ["Whole merchandising procedure", "Excellent career prospect", "Immediate Available is preferred"], "locations": ["Hung Hom"], "categories": ["Manufacturing", "Product Development / Management", "Merchandising & Purchasing", "Electronics", "Toy"], "post_time": "2022-01-14T02:22:51Z", "salary": {"currency": null, "max": null, "min": null, "period": "monthly", "term": null}, "salary_visible": false, "title_keywords": ["merchandiser", "senior merchandiser"], "responsibilities": ["coordinate", "ad-hoc assignments", "schedule", "internal parties"], "requirements": {"degrees": [], "majors": [], "languages": ["english"], "language_level": ["good"], "hard_skills": ["pc", "erp"], "soft_skills": ["detail-minded", "communication skills", "work independently", "responsible", "well-organized"], "languages_combined": [{"language": "english", "language_level": ["good", "good"]}]}, "experience_required": {"duration": ["3 years"], "field": []}}, {"job_id": "100003009037811", "location_code": "hk", "company": "ProCrown Fine Trading Company", "job_title": "Senior Merchandiser - Toy", "description": "Job Requirements\n\nDiploma holder or above\n7-8 years working experience in toys merchandising\nExperience in hard toys and product development is preferred\nIndependent, well-organized, energetic and attention to details\nGood command of spoken & written English, Mandarin is a plus\nConversant with computer skills in MS Word, Excel and Outlook\nImmediate available would be an advantage\n\nJob Responsibilities\n\nHandle sales orders from sample arrangement to bulk production\nWork closely with overseas clients and factories for order follow up\nCoordinate product development process with suppliers and factory\nResponsible for sourcing vendors, costing and price & terms negotiation\nHandle production coordination with factory for delivery arrangement\n\nWe offer excellent fringe benefits and attractive development prospect to the right candidates. Interested parties, please apply with full resume stating expected & last salary and date of available by clicking \u2018Apply Now\u2019", "employment_types": ["Full Time", "Permanent"], "selling_points": [], "locations": ["Not Specified"], "categories": ["Merchandising & Purchasing", "Toy", "Sundries"], "post_time": "2022-01-11T06:13:19Z", "salary": {"currency": null, "max": null, "min": null, "period": "monthly", "term": null}, "salary_visible": false, "title_keywords": ["senior merchandiser"], "responsibilities": ["coordinate", "coordination with", "terms negotiation"], "requirements": {"degrees": ["diploma holder"], "majors": [], "languages": ["english", "mandarin"], "language_level": ["good command"], "hard_skills": ["excel", "plus", "computer skills", "outlook", "ms word"], "soft_skills": ["energetic", "independent", "well-organized", "attention to details"], "languages_combined": [{"language": "english", "language_level": ["good command"]}, {"language": "mandarin", "language_level": ["good command"]}]}, "experience_required": {"duration": ["7-8 years"], "field": ["toys", "product development", "merchandising"]}}, {"job_id": "100003009049961", "location_code": "hk", "company": "P & A Consultant Limited", "job_title": "Asst. Merchandiser/Merchandiser/Sr. Merch/Asst. Merchandising Manager(Toys/Seasonal/Handbag) X10", "description": "Job Requirement & Responsibilities:\n\nDegree/Diploma Graduates/High School Graduates\nAt least 5 years working experience in Toys field\nExperience in exporting to European & South American markets / retailers in trading companies is highly preferable\nCommunicate and closely follow up with both overseas buyers and factories\nSales oriented and customer focused with good interpersonal and presentation skills\nAggressive, outgoing and detail-minded\nA good team player with the ability to communicate the team\nSelf-motivated, independence, energetic with strong sense of commitment & responsible\nReporting to the Merchandising Manager\nProficient in both written and spoken English, Good in spoken Madarin", "employment_types": ["Full Time"], "selling_points": [], "locations": ["Lai Chi Kok"], "categories": ["Merchandising & Purchasing", "Handbag", "Toy", "Sundries"], "post_time": "2022-01-15T03:50:45Z", "salary": {"currency": null, "max": null, "min": null, "period": "monthly", "term": null}, "salary_visible": false, "title_keywords": ["merchandiser", "merchandising", "asst. merchandiser"], "responsibilities": [], "requirements": {"degrees": ["diploma", "degree", "high school"], "majors": [], "languages": ["english"], "language_level": ["good", "proficient"], "hard_skills": [], "soft_skills": ["outgoing", "detail-minded", "good team player", "self-motivated", "focused", "responsible", "presentation skills", "energetic", "interpersonal"], "languages_combined": [{"language": "english", "language_level": ["proficient", "good"]}]}, "experience_required": {"duration": ["at least 5 years"], "field": ["toys", "trading"]}}, {"job_id": "100003009050422", "location_code": "hk", "company": "Majestic Product Development Ltd.", "job_title": "Assistant Merchandiser/ Merchandiser (No experience candidates are welcome)", "description": "Responsibilities:\n\nMonitor and follow up orders, shipments and testing;\nHandle sample development;\n\nRequirements:\n\nF.7 or above;\nAt least 1-2 years merchandising experience (manufacturing / trading / buying office), and preferable in garment / toys field;\nGood command of English / Mandarin and MS Office software (Excel, Word, PowerPoint & Outlook);\nGood communication skill;\nWell organize, mature, a good team player and fast learner;\nOccasional travel to China;\nImmediate available is highly preferable.\n\n\nWe offer attractive competitive package to right candidates.\n\nAll related information will be used solely for recruitment purpose and will be destroyed upon completion of recruitment process.", "employment_types": ["Full Time", "Permanent"], "selling_points": [], "locations": ["Tsim Sha Tsui"], "categories": ["Manufacturing", "Garment / Textile", "Merchandising & Purchasing", "Toy", "Procurement / Purchasing / Sourcing"], "post_time": "2022-01-14T10:22:52Z", "salary": {"currency": null, "max": null, "min": null, "period": "monthly", "term": null}, "salary_visible": false, "title_keywords": ["merchandiser", "assistant merchandiser"], "responsibilities": ["follow up orders", "monitor", "testing"], "requirements": {"degrees": [], "majors": [], "languages": ["english", "mandarin"], "language_level": ["good command"], "hard_skills": ["excel", "word", "powerpoint", "outlook", "ms office"], "soft_skills": ["good team player", "communication skill", "fast learner", "mature"], "languages_combined": [{"language": "english", "language_level": ["good command"]}, {"language": "mandarin", "language_level": ["good command"]}]}, "experience_required": {"duration": ["at least 1-2 years"], "field": ["garment", "toys", "manufacturing", "merchandising", "trading"]}}, {"job_id": "100003009050413", "location_code": "hk", "company": "Toys\u201cR\u201dUs (Hong Kong) Limited", "job_title": "Buyer Assistant / Associate Buyer - Hong Kong", "description": "Key Responsibilities:\n\n\nSupport the team in day-to-day buying activities and carrying out relevant market research for Hong Kong market\nAssist supervisor in sourcing and buying of merchandises from different vendors\u00a0\nLiaise with other departments to execute the merchandise programs smoothly\nAssist in managing relevant sales plan for the assigned products category to achieve turnover and profitability\nOther ad hoc tasks as assigned\n\nRequirements:\n\nHigher Diploma or above in Business or related discipline\nGood command of spoken and written English, Cantonese and Mandarin\nProficient in MS Word, Excel, Access and Chinese and English Word Processing\nExcellent negotiation and communication skills\nStrong numerical sense and analytical mind\nA good team player, multi-tasking, self-driven, independent, and able to work under pressure and tight deadlines\nFresh graduate will also be considered\nMore experience will be considered as Associate Buyer\nImmediately available is highly preferred\n\n\n\nWe offer 5-day work week and below comprehensive\u00a0salary package\u00a0to the right candidate.\n\nAnnual Leave\nBirthday Leave\nChild Care Leave\nMarriage Leave\nDiscretionary Bonus\nStudy Sponsorship\nMedical Coverage\nLife Insurance\nPlease send your resume stating your\u00a0current/last salary,\u00a0expected salary\u00a0and\u00a0available date\u00a0via \"Apply now\" button.\n\nFor more information, please visit our website at\u00a0www.toysrus.com.hk\u00a0\n(All\u00a0collected\u00a0information will be used for recruitment related purpose only.)\n", "employment_types": ["Full Time", "Permanent"], "selling_points": ["Assist in sourcing and buying of merchandises", "Excellent negotiation & communication skills", "Fresh graduate will also be considered"], "locations": ["Lai Chi Kok"], "categories": ["Merchandising & Purchasing", "Toy"], "post_time": "2022-01-14T10:20:42Z", "salary": {"currency": null, "max": null, "min": null, "period": null, "term": null}, "salary_visible": false, "title_keywords": ["associate", "assistant"], "responsibilities": ["ad hoc tasks", "market research", "plan", "liaise with", "support the team"], "requirements": {"degrees": ["higher diploma or above", "fresh graduate"], "majors": ["business"], "languages": ["cantonese", "english", "chinese", "mandarin"], "language_level": ["good command", "proficient"], "hard_skills": ["chinese and english word processing", "excel", "ms word"], "soft_skills": ["communication skills", "good team player", "independent", "negotiation", "multi-tasking", "analytical mind", "driven", "work under pressure"], "languages_combined": [{"language": "cantonese", "language_level": ["good command"]}, {"language": "english", "language_level": ["good command", "proficient"]}, {"language": "chinese", "language_level": ["proficient"]}, {"language": "mandarin", "language_level": ["good command"]}]}, "experience_required": {"duration": [], "field": []}}, {"job_id": "100003009049896", "location_code": "hk", "company": "Paladone Products Limited", "job_title": "Merchandiser", "description": "We are a UK owned gift and health & beauty company located in TST East. Our office is a convenient 10 minute walk from the TST East or Hung Hom MTR station. We offer an interesting and diverse product range to our international retailers and distributors.\u00a0We are looking to recruit a Merchandiser with experience in managing direct to retail global accounts for mass market.\u00a0\u00a0\n\n\u00a0Role KPIs include:\n\n\n\nEfficiently processing stock/customers POs across your assigned factory base\nBespoke product & packaging development (where required) on your retail accounts\nEfficiently processing POs and managing the critical path end to end\nDriving on time deliveries\nDriving cost downs\nDeveloping & maintaining strong/cooperative relationships with your factory contacts; retail customers and your colleagues across the NPD/Design \u2013 QA/QC \u2013 Shipping teams\nEnsuring efficient processing of all admin functions in relation to retailer set up forms etc.\nAssisting the merchandising team with multiple admin duties across your slow season\n\nIf you are looking for a career move, not just a \u201cjob\u201d \u2013 we are interested in talking to you. You need to be highly motivated, organised and calm under pressure. You must have experience working in a fast-paced environment. You must have a good command (spoken and written) in English, Mandarin and Cantonese. You will have at least 3 years\u2019 experience in a merchandising role. You will be a natural problem-solver and excellent communicator. You must be proficient in Microsoft Excel, Word and Outlook. Experience with an ERP system is highly regarded, but not necessary as full training will be provided.\u00a0 Immediate availability is preferred.\u00a0\n\nFor the right candidate we offer flexible working hours, 13th month salary and discretionary bonus. If you are interested in joining our team, please email your cover letter, CV, expected starting salary, title of the position you are applying for in email subject and available starting date by clicking \u201cApply Now\u201d \u2013 note if you don\u2019t include all just listed, your application will be discarded! Attention to detail is a critical requirement for this role. Previous applicants\u2019 please do NOT apply.", "employment_types": ["Full Time", "Permanent"], "selling_points": [], "locations": ["Tsim Sha Tsui"], "categories": ["Merchandising & Purchasing", "Toy", "Others", "Procurement / Purchasing / Sourcing"], "post_time": "2022-01-14T09:25:29Z", "salary": {"currency": null, "max": null, "min": null, "period": "monthly", "term": null}, "salary_visible": false, "title_keywords": ["merchandiser"], "responsibilities": [], "requirements": {"degrees": [], "majors": [], "languages": [], "language_level": [], "hard_skills": [], "soft_skills": [], "languages_combined": []}, "experience_required": {"duration": [], "field": []}}, {"job_id": "100003009050118", "location_code": "hk", "company": "Jaz Toys HK Limited", "job_title": "Senior Designer (Toy Packaging Development)", "description": "\u00a0 Responsibilities:\n\nFollow up toy product development (Material and Colour)\nFollow up packaging design and development process\nCreate highly competitive, innovative, contemporary packaging (graphics and structure) while providing feedback to internal teams and licensors\nCollaboration with communication with engineers PM and US team\nWork closely with licensor and follow each approval step\nWork closely with external parties, such as Factory, Vendors and Prototype markers..etc\nReport to HK Design Manager\n\n\u00a0Requirements:\n\nDegree or Diploma in Design or related disciplines\n8 years\u2019 relevant experience in the toy industry\nKnowledge of packaging design and development\nProficiency in 2D design Software (Photoshop, Illustrator)\nAbility to work in a fast paced environment and manage multiple projects independently\nTravel to China factory is must\nGood command of written and spoken English\u00a0\u00a0\u00a0\u00a0\u00a0\u00a0\u00a0\nMust speak either Cantonese and Mandarin\n\nAvailability\u00a0\u00a0 :\u00a0\u00a0 Immediate is preferred\n\nInterested parties please send detail resume and profoilo", "employment_types": ["Full Time", "Permanent"], "selling_points": ["Follow up toy product development", "8 years\u2019 relevant experience in the toy industry", "Knowledge of packaging design and development"], "locations": ["Chai Wan"], "categories": ["Design", "Industrial / Product", "Others", "Merchandising & Purchasing", "Toy"], "post_time": "2022-01-14T09:48:25Z", "salary": {"currency": null, "max": null, "min": null, "period": "monthly", "term": null}, "salary_visible": false, "title_keywords": ["senior designer"], "responsibilities": ["graphics", "packaging design", "external parties", "teams", "design", "communication", "report"], "requirements": {"degrees": ["diploma", "degree"], "majors": ["related disciplines", "design"], "languages": ["cantonese", "english", "mandarin"], "language_level": ["good command"], "hard_skills": ["illustrator", "photoshop"], "soft_skills": ["work in a fast paced environment", "independently"], "languages_combined": [{"language": "cantonese", "language_level": []}, {"language": "english", "language_level": ["good command"]}, {"language": "mandarin", "language_level": []}]}, "experience_required": {"duration": ["8 years"], "field": ["relevant experience"]}}, {"job_id": "100003009039915", "location_code": "hk", "company": "Yeko Manufacturing Limited", "job_title": "Injection Manager (Toys)", "description": "Description:\u00a0\n\n10 years+ solid experience in hard toys injection in manufacturing plants\nStation in Vietnam\nDaily operation and control, timeline management and meeting clients' quality standard a must\nGood communication skills, problem solving and highly responsible", "employment_types": ["Full Time"], "selling_points": ["Injection Manager (Toys)", "Vietnam stationed", "10 years experience"], "locations": ["Overseas"], "categories": ["Manufacturing", "Manufacturing Management", "Merchandising & Purchasing", "Toy"], "post_time": "2022-01-11T15:07:38Z", "salary": {"currency": null, "max": null, "min": null, "period": "monthly", "term": null}, "salary_visible": false, "title_keywords": ["manager"], "responsibilities": ["control", "management", "quality", "daily operation", "communication"], "requirements": {"degrees": [], "majors": [], "languages": [], "language_level": [], "hard_skills": ["problem solving"], "soft_skills": ["problem solving", "communication skills", "responsible"], "languages_combined": []}, "experience_required": {"duration": [], "field": ["toys", "manufacturing"]}}, {"job_id": "100003009044955", "location_code": "hk", "company": "Intertek Testing Services H.K. Ltd.", "job_title": "Testing Specialist", "description": "Assistant Merchandising Manager/ Sr. Merchandiser/Merchandiser/ Assistant Merchandiser(Toys/ Sundries/ Gift & Premium/ Seasonal/ Gardening/ Plastic/ Home Decoration/ Polyresin/ Metal/ Wooden product/ Electronic Consumer/ Sport products/ Watch/ Handbag)- Urgent X10\u00a0\nSalary : 16-34K,\u00a0Location : Hung Hom/ Lai Chi Kok/ Tsuen Wan/ Kwun Tong ( 5 Days )\u00a0\u00a0\nRequirements\u00a0 :\u00a0\n\nF.5 or above,\u00a0\nAt Least 5-10 years of Merchandiser exp in Toys( Plastic/ Hard/ Wood/ Paper /Board game\u00a0) or Seasonal or Sundries, Gift and premium /\u00a0Electronic Consumer/ Sport\u00a0/ Watch\u00a0Product\nProduct development, sourcing, follow up order & sample\nWork independently\nGood command of English & Mandarin\nCandidate have less exp also will be consider as Assistant Merchandiser\u00a0\nSr. Merchandiser/Merchandiser- Seasonal/Gardening (Urgent)\u00a0\n(Lai Chi Kok) 5 days,\u00a0salary:23-28K\u00a0\nRequirements\u00a0 :\u00a0\n\nDiploma/ Degree holder,\u00a0\nAt Least 5-10 years of Merchandiser exp in Seasonal/ Gardening\u00a0\nstrong Product development/ one man bank\u00a0\nsourcing, follow up order & sample, contact client & mfg\u00a0\nWork independently\nHave Canton Fair exp\u00a0\nGood command of Cantonese, English & Mandarin\nImmediate available is preferred\nCandidates have less exp also will be consider as Merchandiser\u00a0\n\n*** Personal data will be treated with strict confidential and used for recruitment purpose only.\n\n\nP & A consultant Ltd will not charge any fees from the above-stated job-seeker, your job apply to our company means your acceptance of our terms and conditions.", "employment_types": ["Full Time", "Permanent"], "selling_points": ["Communicate with clients to about testing", "Act as Co-ordinator of internal parties & clients", "Immediate available is highly preferred"], "locations": ["Not Specified"], "categories": ["Sciences, Lab, R&D", "Laboratory", "Merchandising & Purchasing", "Toy", "Manufacturing", "Quality Assurance, Control & Testing / ISO"], "post_time": "2022-01-13T06:43:37Z", "salary": {"currency": null, "max": null, "min": null, "period": null, "term": null}, "salary_visible": false, "title_keywords": ["specialist"], "responsibilities": ["recruitment", "personal data", "merchandising", "contact"], "requirements": {"degrees": ["diploma", "degree holder"], "majors": [], "languages": ["cantonese", "english", "mandarin"], "language_level": ["good command"], "hard_skills": ["wan", "sr", "x10"], "soft_skills": ["work independently"], "languages_combined": [{"language": "cantonese", "language_level": ["good command"]}, {"language": "english", "language_level": ["good command", "good command"]}, {"language": "mandarin", "language_level": ["good command", "good command"]}]}, "experience_required": {"duration": [], "field": []}}, {"job_id": "100003009035824", "location_code": "hk", "company": "Toyzeroplus Limited", "job_title": "Assistant Merchandiser / Merchandiser", "description": "Our purpose is to bring safety, quality and sustainability to life.\u00a0\n\n\nThe Job\n\nStation in client\u2019s office and assist client\u2019s on report approvals\nFollow up e-mail and / or phone calls enquiry which related report approvals\nConsolidate information from clients for the requests on results acceptance\nCommunicate with clients to solve question about testing\nWork with internal staffs to follow up report issues\n\nThe Person\n\nAt least\u00a02 years\u2019 experience\u00a0of\u00a0clients communication in product testing/manufacturing/ mechanical aspect\nWorking experience in commercial testing\u00a0laboratory\u00a0/ in house testing laboratory will be an advantage\nGood command of spoken and written Chinese and English\nIndependent and well-organized\nProficiency in\u00a0Microsoft Office including Word and Excel\nCandidate with less experience will also be considered for the position of Assistant Testing Specialist\n\nInterested parties please forward full resume stating your availability, present and expected salary to The Human Resources Manager, Intertek Testing Services HK Ltd., via ONE of the following channels: (Pls quote ref. no. on all correspondence.)\u00a0\n\nAddress: 2/F Garment Centre, 576 Castle Peak Rd., Kowloon, H.K.\n\nE-mail:\u00a0Please click \"APPLY NOW\"\u00a0\u00a0Fax: 3403 2691\u00a0\n\nWelcome to visit our website http://www.intertek.com for corporate information\u00a0\n\nConfidentiality assured and all applications will be kept solely for recruitment purpose for not more than 6 months.", "employment_types": ["Full Time"], "selling_points": ["Toy industry", "Solid Merchandising Experience", "Good computer knowledge"], "locations": ["Lai Chi Kok"], "categories": ["Merchandising & Purchasing", "Toy"], "post_time": "2022-01-10T16:52:44Z", "salary": {"currency": null, "max": null, "min": null, "period": "monthly", "term": null}, "salary_visible": false, "title_keywords": ["merchandiser", "assistant merchandiser"], "responsibilities": ["communicate with", "testing", "phone calls", "report"], "requirements": {"degrees": [], "majors": [], "languages": ["english", "chinese"], "language_level": ["good command"], "hard_skills": ["excel", "word", "microsoft office"], "soft_skills": ["communication", "independent", "well-organized"], "languages_combined": [{"language": "english", "language_level": ["good command"]}, {"language": "chinese", "language_level": ["good command"]}]}, "experience_required": {"duration": ["at least 2 years"], "field": ["commercial", "manufacturing", "laboratory", "testing"]}}, {"job_id": "100003009045660", "location_code": "hk", "company": "Merchant Ambassador (Holdings) Limited", "job_title": "Merchandiser", "description": "Job Description:\n\n\u00a0Responsibilities:\n\nFollow up orders and samples, coordinate with buyer and vendor Mature, self-motivated, able to work under pressure;\nOrders follow up to ensure on time delivery;\nWork closely and effectively with supporting department including: Production / Marketing / Design & Logistic Team;\nOrganizational skills and detail oriented is a must;\nAssist in ad-hoc assignment as required;\nProactive, out-going and willing to provide problems solving whenever necessary;\nGeneral knowledge of material and toy safety regulations;\nFun, young and joyful working environment.\n\nRequirements:\n\nF. 5 / DSE / Diploma holder or above;\nAt least 2 years\u2019 solid experience in toys industry, more experience will be considered as Merchandiser;\nExcellent communication and negotiation skill. Independent and confident in communication with customers and vendors;\nAble to work under pressure & good at switching priorities;\nSensitive to figures & number, contains China tax knowledges is a plus;\nExcellent command of both written and spoken English, Chinese and Mandarin;\nProficiency in MS Office;\nExperience in ERP system;\nWilling to PRC travel if necessary\n\nTo Apply:\n\nFor more information, please visit\u00a0https://toyzeroplus.com/\u00a0.\nInterested parties please send your application by \u201cApply Now\u201d.\nAll information received will be used for recruitment purpose only and will be kept in strict confidential.", "employment_types": ["Full Time"], "selling_points": [], "locations": ["Wong Tai Sin Area"], "categories": ["Merchandising & Purchasing", "Toy", "Others", "Others", "Trading"], "post_time": "2022-01-13T08:17:40Z", "salary": {"currency": null, "max": null, "min": null, "period": "monthly", "term": null}, "salary_visible": false, "title_keywords": ["merchandiser"], "responsibilities": ["follow up orders", "ad-hoc", "problems solving", "regulations", "coordinate with", "ensure on time delivery", "design", "work under pressure"], "requirements": {"degrees": ["diploma holder", "dse"], "majors": [], "languages": ["english", "chinese", "mandarin"], "language_level": ["excellent"], "hard_skills": ["plus", "erp system", "ms office"], "soft_skills": ["confident", "independent", "sensitive to figures", "communication", "negotiation skill", "work under pressure"], "languages_combined": [{"language": "english", "language_level": ["excellent"]}, {"language": "chinese", "language_level": ["excellent"]}, {"language": "mandarin", "language_level": ["excellent"]}]}, "experience_required": {"duration": ["at least 2 years"], "field": ["toys", "erp system"]}}, {"job_id": "100003009039089", "location_code": "hk", "company": "Petsource Asia Limited", "job_title": "Merchandiser - Pets", "description": "Main responsibilities would be:\n\nFull supervision and handling of our retail clients, mainly consisting of large multinational chain stores.\nMerchandiser role at MA is independent beginning-to-end handling of client\u2019s accounts, from quotes to shipment.\nHandling new enquiries: costing analysis, quote preparations, samples, and supervising OEM developments.\nPreparation of various order documents e.g. P/I, P/O\u2019s, vendor registration documents.\nOverseeing & organizing pre-production scheduling, lab testing issues, artwork development, and factory audit issues. Must have experience in supervising all these tasks.\nHandle full set of shipping and payment documents including L/C.\nSupervising our China based staff and vendors to ensure orders on track.\nDaily communications with customers for ongoing orders and new opportunities.\nStrong experience in merchandising role for international trading company is a must, with strength in all areas from marketing, operations, documents, logistics, payments.\nExperience handling large western retailer accounts, especially for European market, are highly desirable.\nExperience in toys industry/trading is highly desirable.\nEnergetic individual required with great communication skills in English + Cantonese + Mandarin, both verbal and written.\nMust be able to work independently, have strong \u2018multi-tasking\u2019 abilities, resourceful & pro-active.\nStrong computer skills in regular MS Office programs.\nMust be professional, high-calibre, with consistently high performance throughout career.\nImmediately available is required.\n\nPlease include resume, reference letters, and expected salary.\u00a0 Information collected will be solely for recruitment purpose.", "employment_types": ["Full Time", "Permanent"], "selling_points": [], "locations": ["Ngau Tau Kok"], "categories": ["Merchandising & Purchasing", "Textiles", "Toy", "Others"], "post_time": "2022-01-11T08:39:52Z", "salary": {"currency": null, "max": null, "min": null, "period": "monthly", "term": null}, "salary_visible": false, "title_keywords": ["merchandiser"], "responsibilities": ["communications with", "supervising", "shipping", "artwork development", "operations", "merchandising", "audit", "letters", "testing", "communication", "scheduling", "payment", "logistics", "payments", "recruitment", "costing analysis", "pre-production"], "requirements": {"degrees": [], "majors": [], "languages": ["cantonese", "english", "mandarin"], "language_level": [], "hard_skills": ["analysis", "vendor", "c", "computer skills", "ms office"], "soft_skills": ["communication skills", "work independently", "independent", "resourceful", "multi-tasking", "pro-active", "energetic"], "languages_combined": [{"language": "cantonese", "language_level": []}, {"language": "english", "language_level": []}, {"language": "mandarin", "language_level": []}]}, "experience_required": {"duration": [], "field": ["toys", "merchandising", "marketing", "logistics", "trading"]}}, {"job_id": "100003009035389", "location_code": "hk", "company": "HTI Toys HK Limited", "job_title": "Senior Sales Executive/ Sales Executive", "description": "What you\u2019ll be doing?\n\nSourcing and communicate with different suppliers\nCoordinate order follow-up\u00a0\nDocumentation and sample follow up\nVisit trade fairs in China if needed\n\nWho\u00a0are\u00a0we\u00a0looking\u00a0for?\u00a0\n\nForm\u00a05 or above\nMinimum 3 years merchandising or trading experience in one of the below areas:\u00a0\nSundries\nKitchenware / Houseware\u00a0\nDecoration\nTools / DIY Items / Toys\nIndoor and Outdoor Furniture\nElectronic items / Lighting\nSporting items\u00a0\nCandidates with less experience will be considered as Assistant Merchandiser\nAble to coordinate with mainland factories independently & work under pressure\nSelf-motivated, responsible and willing to learn\nProficiency in MS Excel, Word, PowerPoint, Outlook & Chinese word processing\nGood command of both written and\u00a0spoken English, Cantonese & Mandarin\nWilling travel to China if necessary\nYou will have an advantage if you are\nWell organized, mature, detail minded and a good team player\nExperience in European Market\nImmediately available\u00a0\n\nWhy you should consider this opportunity:\nWe offer attractive remuneration package with fringe benefits to right candidates. such as\u00a0\n\n5 days work\nPerformance bonus\nDouble pay\nBank holidays\n10 - 15 days of annual leave\n\nWork location: Kwun Tong ( 5 minutes walk for MTR station)\n\nInterested parties please send your resume with available date and expected salary by clicking\u00a0\"Apply Now\".\n\nNote: The Information will be treated in strict confidence and solely used for recruitment purposes.", "employment_types": ["Full Time"], "selling_points": ["Well-verse in Sales/Order execution in toys trades", "Excellent communication skill & exp in toy fields", "Good at handling buying office tasks"], "locations": ["Ngau Tau Kok"], "categories": ["Manufacturing", "Production Planning / Control", "Merchandising & Purchasing", "Toy", "Sales, CS & Business Devpt", "Sales Administration"], "post_time": "2022-01-10T07:00:02Z", "salary": {"currency": null, "max": null, "min": null, "period": "monthly", "term": null}, "salary_visible": false, "title_keywords": ["senior sales executive", "sales executive"], "responsibilities": ["communicate with", "merchandising", "coordinate with", "coordinate", "documentation", "work under pressure"], "requirements": {"degrees": ["form 5 or above"], "majors": [], "languages": ["cantonese", "english", "chinese", "mandarin"], "language_level": ["proficiency", "good command"], "hard_skills": ["chinese word processing", "word", "powerpoint", "ms excel", "outlook", "documentation"], "soft_skills": ["self-motivated", "independently", "good team player", "responsible", "willing to learn", "well organized", "mature", "work under pressure"], "languages_combined": [{"language": "cantonese", "language_level": ["good command"]}, {"language": "english", "language_level": ["good command"]}, {"language": "chinese", "language_level": ["proficiency"]}, {"language": "mandarin", "language_level": ["good command"]}]}, "experience_required": {"duration": ["minimum 3 years"], "field": ["merchandising", "trading"]}}, {"job_id": "100003009034484", "location_code": "hk", "company": "The Marketing Store Worldwide (Asia) Ltd", "job_title": "Merchandising Manager", "description": "Job Highlights\n\nWell-verse in Sales/Order execution\nExcellent communication skills and interpersonal skill\nGood at handling buying office\nExperience in toy industry\n\nJob Responsibilities\n\nDevelop and maintain relationships with key accounts and their affiliates\nHandle customer orders/customize products to shipment (end to end process)\nSupport Frontline Sales Team to deliver Sales Goal\n\n\n\nJob Requirements\n\nDegree holder in Business, preferrable.\n\nMin. 6 years sales and operation experience in toys industry, 3 yrs in senior position for those applying for Senior SE.\n\nExcellent sales and communication skills\n\nSelf-motivated, good interpersonal skills and able to work under pressure\n\nDetail oriented, excellent communication and analytical skills\n\nExperience in multi-cultural working environment preferrable", "employment_types": ["Full Time", "Permanent"], "selling_points": ["Supply chain operations", "Experience in toys/premiums/sundries industry", "5-Day work week & Attractive Compensation Package"], "locations": ["Kowloon Bay"], "categories": ["Merchandising & Purchasing", "Textiles", "Toy", "Sundries"], "post_time": "2022-01-10T03:29:26Z", "salary": {"currency": null, "max": null, "min": null, "period": "monthly", "term": null}, "salary_visible": false, "title_keywords": ["merchandising manager"], "responsibilities": ["maintain relationships", "sales team", "develop"], "requirements": {"degrees": ["degree holder"], "majors": ["business"], "languages": [], "language_level": [], "hard_skills": ["analytical skills"], "soft_skills": ["communication skills", "self-motivated", "detail oriented", "analytical skills", "communication", "interpersonal skills", "work under pressure"], "languages_combined": []}, "experience_required": {"duration": ["6 years"], "field": ["toys", "operation"]}}, {"job_id": "100003009036095", "location_code": "hk", "company": "PCHI Asia Limited", "job_title": "Merchandiser", "description": "Responsibilities and Duties\n\nAssist in the development of appropriate sourcing opportunities by downloading artworks and preparing sample shipments\nMaintains development logs, files, compiles data, creates reports\nAssist Merchandiser in entering approvals comments in PLM\nMonitors the production WIP, testing and inspection and delivery status for all purchase orders to meet delivery goals\nReview pending or failed inspection reports with Merchandiser to take necessary action\nFollows up with factories on production inner samples submission and handle sample shipments\nIdentifies and escalates any production, quality and delivery issues to Merchandiser\nSupport smooth, efficient, and effective buyer/sourcing and design visits by assisting with trip planning and supplier meetings\n\nJob Requirements\n\nUniversity degree or relevant experience\nMinimum 0-3 years\u2019 experience in merchandising, preferably in sourcing/buying offices\nStrong team player with excellent communication and interpersonal skills\nAbility to work independently, self-motivated, responsible and willing to learn\nAttention to detail, organizational and multitasking skills\nProficient in Microsoft Office (Word, Excel, Pivot Tables and VLOOKUP, PowerPoint, and Outlook)\nGood command of both verbal and written English and Chinese including Mandarin", "employment_types": ["Full Time"], "selling_points": [], "locations": ["Lai Chi Kok"], "categories": ["Merchandising & Purchasing", "Toy", "Sundries", "Others"], "post_time": "2022-01-10T09:19:57Z", "salary": {"currency": null, "max": null, "min": null, "period": "monthly", "term": null}, "salary_visible": false, "title_keywords": ["merchandiser"], "responsibilities": ["inspection reports", "delivery issues", "data", "comments", "review", "quality", "design", "testing", "inspection", "purchase", "reports", "planning"], "requirements": {"degrees": ["university degree"], "majors": [], "languages": ["english", "chinese", "mandarin"], "language_level": ["good command"], "hard_skills": ["excel", "microsoft office", "word", "powerpoint", "outlook", "vlookup"], "soft_skills": ["work independently", "self-motivated", "responsible", "organizational", "willing to learn", "communication and interpersonal skills", "attention to detail", "team player"], "languages_combined": [{"language": "english", "language_level": ["good command"]}, {"language": "chinese", "language_level": ["good command"]}, {"language": "mandarin", "language_level": ["good command"]}]}, "experience_required": {"duration": ["minimum 0-3 years"], "field": ["merchandising", "relevant experience", "buying offices"]}}, {"job_id": "100003009041365", "location_code": "hk", "company": "Intertek Testing Services H.K. Ltd.", "job_title": "\u5ba2\u6236\u670d\u52d9\u6587\u54e1 Client Services Clerk", "description": "Responsibilities:\nResponsible for graphic design, conceptual, product graphic & production of private label packaging.\nCommunicate with customers and handle the implementation of their style guides.\nCollaborate with merchandising & design department, printers, and factories.\nInteract with manufacturers to market new toy ideas or concepts.\nActively create and present design strategy along with concepts to merchants, internal design teams.\nIncorporate feedback and input into design strategy along with design solutions to satisfy business needs.\nProficient in photo shooting\nRequirements:\nMust be willing to take responsibility with excellent organizational skills.\nCapable to work independently under pressure with dedication and integrity as a team player.\nGood command of written and spoken English, Cantonese, and Mandarin.\nComputer literate. Proficient in Adobe Illustrator, Photoshop, InDesign, MS Office, Chinese typing is required.\nEducation:\nBe a holder of accredited certificates, diplomas, degrees obtained in programs of post-secondary and tertiary institutes, or have relevant work experience;\nWe offer a challenging job with good career prospects. Please send full resume with current and expected salary by e-mail via \"Apply Now\"\n\n\nAll information provided will be treated in strict confidence and used for recruitment purpose only.", "employment_types": ["Full Time", "Permanent"], "selling_points": ["Provide administrative support", "Handle sample registration, document review", "F.5 / DSE or above with science discipline"], "locations": ["Lai Chi Kok"], "categories": ["Admin & HR", "Clerical / Admin Staff", "Sales, CS & Business Devpt", "Customer Service - Supervisor / Officer", "Merchandising & Purchasing", "Toy"], "post_time": "2022-01-12T03:48:15Z", "salary": {"currency": null, "max": null, "min": null, "period": null, "term": null}, "salary_visible": false, "title_keywords": ["clerk", "\u5ba2\u6236\u670d\u52d9\u6587\u54e1"], "responsibilities": ["communicate with", "collaborate with", "ideas", "design solutions", "graphic design", "merchandising", "implementation", "design", "teams"], "requirements": {"degrees": [], "majors": [], "languages": ["cantonese", "english", "chinese", "mandarin"], "language_level": ["good command", "proficient"], "hard_skills": ["indesign", "typing", "adobe illustrator", "photoshop", "ms office"], "soft_skills": ["organizational skills", "work independently", "under pressure", "capable", "integrity", "team player"], "languages_combined": [{"language": "cantonese", "language_level": ["good command"]}, {"language": "english", "language_level": ["good command"]}, {"language": "chinese", "language_level": ["proficient"]}, {"language": "mandarin", "language_level": ["good command"]}]}, "experience_required": {"duration": [], "field": []}}, {"job_id": "100003009033732", "location_code": "hk", "company": "Dickie Toys Hong Kong Limited", "job_title": "Graphic Designer", "description": "- Degree holder in Marketing or equivalent;\n\n- At least 3 years experience in handling sales & marketing activities such as product development, prepare quotations, samples follow up and orders processing in toys industry;\n\n- Able to work independently and with good self-initiative;\n\n- Demonstrated analytical and negotiation skills;\n\n- Excellent interpersonal and communication skills;\n\n- Proficient in MS Office applications and Chinese Word Processing;\n\n- Good command of written English and Chinese.\n\nInterested candidates, please contact us at 28595011 for company details before applying.\n\nPersonal data collected will be used for recruitment purpose only.", "employment_types": ["Full Time", "Permanent"], "selling_points": ["Responsible for graphic design, conceptual", "Must be willing to take responsibility", "Capable to work independently under pressure"], "locations": ["Tsim Sha Tsui"], "categories": ["Design", "Graphics", "Industrial / Product", "Merchandising & Purchasing", "Toy"], "post_time": "2022-01-10T02:14:30Z", "salary": {"currency": null, "max": null, "min": null, "period": "monthly", "term": null}, "salary_visible": false, "title_keywords": ["graphic designer"], "responsibilities": ["communication", "sales & marketing activities"], "requirements": {"degrees": ["degree holder"], "majors": ["marketing"], "languages": ["english", "chinese"], "language_level": ["good command", "proficient"], "hard_skills": ["processing", "chinese word processing", "ms office"], "soft_skills": ["communication skills", "work independently", "negotiation skills", "self-initiative", "interpersonal"], "languages_combined": [{"language": "english", "language_level": ["good command"]}, {"language": "chinese", "language_level": ["good command", "proficient"]}]}, "experience_required": {"duration": ["at least 3 years"], "field": ["toys", "product development", "marketing"]}}, {"job_id": "100003009028812", "location_code": "hk", "company": "", "job_title": "Assistant Marketing Manager", "description": "The Marketing Store Worldwide (TMS), a HAVI Company, is a Global Customer Engagement Agency and Sourcing Company, with areas of expertise that include consumer promotions, toys and premiums, shopper marketing, digital platforms and innovation. TMS now ranks among the largest toy manufacturers in the world.\u00a0\n\nOur core focus in Asia is delivering strategic and sustainable, global sourcing and supply chain solutions for McDonald\u2019s Happy Meal. We are operationally based out of Hong Kong but our Asia teams are spread throughout Japan, China, Vietnam, Indonesia, Singapore and Lebanon. We collaborate closely with our colleagues based in the US and Europe.\u00a0\n\nWe are committed to continually challenging the status quo, seeking new and progressive solutions for our clients and our people. We are proud to not only have won awards that recognize this commitment in our work but in 2021 our focus on doing this for our people was rewarded with a Best Companies to work for award!\n\nWhat you\u2019ll bring to the TMS\u00a0 \u00a0 \u00a0 \u00a0\u00a0\n\n\nLead a team of project executive(s), coach the team in project management, problem-solving to meet business goals\nOversee production management with vendors, manage project timeline and track performance\nLead and drive global and local window projects, being the focal point with customer, regional offices, and various functions (Engineering, Costing, QA, Logistics \u2026 etc) to meet client expectation\nManage project planning from concept, development, order taking, production to delivery\nAccountable for assured supply, order fulfilment and on time delivery\nWork proactively to monitor production schedule with vendors, identify risk areas which may impact production/delivery or business performance\nReview the current processes and practices and make recommendations for continuous improvement\n\nSkills and experience we\u2019d like you to have\n\nDegree in Business or Supply Chain Management related discipline\n10 years Merchandising /Supply Chain/ Sourcing experience, with exposure in toys, paper items, stationery, or party items in preference\nPrevious experience in MNCs operations and supply chains is definitely a plus\nPrefer with 5+ years people management experience\nProven record in driving business result and operational performance\nDetail minded, well-organized with good analytical skill and problem-solving skills\nSelf-motivated, able to work independently under pressure, as well as work with teams and stakeholders across different regions (US/EU/AP/LATAM/MEA/AUZ) to achieve company goals\nStrong business ethics and high level of integrity\nGood command of both written and spoken English, Chinese (Cantonese and Mandarin)\nAbility/willingness to work overtime and travel when necessary\n\nWe offer attractive remuneration package to the right candidate. Interested parties please send your full resume with present and expected salary by clicking \"Apply Now\". All personal data will be used for recruitment purpose only.\n\nWe are The Marketing Store and we would love to meet you!\u00a0", "employment_types": ["Full Time", "Permanent"], "selling_points": [], "locations": ["Not Specified"], "categories": ["Manufacturing", "Product Development / Management", "Marketing / Public Relations", "Marketing - General / Support", "Merchandising & Purchasing", "Toy"], "post_time": "2022-01-07T03:15:52Z", "salary": {"currency": null, "max": null, "min": null, "period": "monthly", "term": null}, "salary_visible": false, "title_keywords": ["assistant marketing manager"], "responsibilities": ["collaborate", "manage project planning", "business goals", "management", "make recommendations", "ap", "operations", "review", "teams", "monitor", "merchandising", "stationery", "lead a team", "project management", "logistics", "schedule", "order taking"], "requirements": {"degrees": ["degree"], "majors": ["business"], "languages": ["cantonese", "english", "chinese", "mandarin"], "language_level": ["good command"], "hard_skills": ["ap", "plus", "analytical skill", "focal", "problem-solving", "project management", "make", "problem-solving skills", "focus"], "soft_skills": ["make recommendations", "analytical skill", "self-motivated", "work independently", "under pressure", "problem-solving", "well-organized", "accountable", "integrity", "committed", "project management", "willingness to work", "progressive", "problem-solving skills", "focus"], "languages_combined": [{"language": "cantonese", "language_level": ["good command"]}, {"language": "english", "language_level": ["good command"]}, {"language": "chinese", "language_level": ["good command"]}, {"language": "mandarin", "language_level": ["good command"]}]}, "experience_required": {"duration": ["10 years", "5+ years"], "field": ["toys", "supply chain", "people management", "merchandising"]}}, {"job_id": "100003009056154", "location_code": "hk", "company": "API Lab Testing Limited", "job_title": "Senior Customer Service Executive", "description": "Responsibilities:\u00a0 \u00a0\n\nPrimary customer interface to coordinate customer requirement to lab operations.\nProvide friendly and professional pre-sale and post-sales throughout order transaction.\nHandle sample registration and release of test report.\nHandle customer enquiry on service capacity, quotation, reporting status, report contents and complaints.\nFollow up with customer on missing information and samples.\nProvide regular summary report to customer regarding the lab service.\n\nRequirements:\n\nMinimum 3 years\u2019 relevant experience in laboratory testing company (Candidates with less experience will be considered as Customer Service Executive).\nHighly-organized, able to work independently and capable of working under pressure with multi-task assignments.\nGood command of English and Chinese.\nGood computer skills.\nFamiliar with European regulations/standards is an advantage.\nHaving the experience of component sorting is an advantage.\n\nIMMEDIATELY AVAILABLE is PREFERRED\n\n5 days work (overtime and weekend work required if necessary).\n\n*Interested parties please send your full resume stating date of availability, present and expected salary\u00a0via\u00a0APPLY NOW Button.*", "employment_types": ["Full Time"], "selling_points": ["Customer service", "English and Chinese", "Good computer skills"], "locations": ["Tsuen Wan Area"], "categories": ["Sales, CS & Business Devpt", "Customer Service - Supervisor / Officer", "Merchandising & Purchasing", "Furniture", "Toy"], "post_time": "2022-01-18T03:25:49Z", "salary": {"currency": null, "max": null, "min": null, "period": "monthly", "term": null}, "salary_visible": false, "title_keywords": ["senior customer service executive"], "responsibilities": ["reporting", "operations", "quotation", "coordinate", "contents", "report"], "requirements": {"degrees": [], "majors": [], "languages": ["english", "chinese"], "language_level": ["good command"], "hard_skills": ["computer skills"], "soft_skills": ["organized", "work independently", "under pressure", "capable", "multi-task", "customer service"], "languages_combined": [{"language": "english", "language_level": ["good command"]}, {"language": "chinese", "language_level": ["good command"]}]}, "experience_required": {"duration": ["minimum 3 years"], "field": ["laboratory testing", "customer service", "relevant experience"]}}, {"job_id": "100003009052825", "location_code": "hk", "company": "Tim Toys Ltd", "job_title": "MERCHANDISING and SHIPPING EXECUTIVE", "description": "We are the Asia Pacific Sales branch office for one of the leading toy companies based in Germany.\u00a0\u00a0 We are now looking for a Merchandising and Shipping Executive to join the team.\n\nJob Responsibilities:\n\n-\u00a0\u00a0\u00a0\u00a0\u00a0\u00a0\u00a0\u00a0\u00a0 Coordinate, follow up and process orders from factory to overseas clients independently.\n\n-\u00a0\u00a0\u00a0\u00a0\u00a0\u00a0\u00a0\u00a0\u00a0 Maintain and update order-processing system\n\n-\u00a0\u00a0\u00a0\u00a0\u00a0\u00a0\u00a0\u00a0\u00a0 Handle shipping operation with required documents\n\n-\u00a0\u00a0\u00a0\u00a0\u00a0\u00a0\u00a0\u00a0\u00a0 Frequent communication with both factories and overseas customers\n\n-\u00a0\u00a0\u00a0\u00a0\u00a0\u00a0\u00a0\u00a0\u00a0 Reports generation\n\nRequirements:\n\n-\u00a0\u00a0\u00a0\u00a0\u00a0\u00a0\u00a0\u00a0\u00a0 Degree holder in Business related disciplines with minimum 3 years solid experience in International trading.\u00a0 Toy industry a plus.\n\n-\u00a0\u00a0\u00a0\u00a0\u00a0\u00a0\u00a0\u00a0\u00a0 Fluency in both written and spoken English, Cantonese and Mandarin.\n\n-\u00a0\u00a0\u00a0\u00a0\u00a0\u00a0\u00a0\u00a0\u00a0 Excellent interpersonal and communication skills\n\n-\u00a0\u00a0\u00a0\u00a0\u00a0\u00a0\u00a0\u00a0\u00a0 Open minded to multicultural business\n\n-\u00a0\u00a0\u00a0\u00a0\u00a0\u00a0\u00a0\u00a0\u00a0 Strong analytical skills, detail-minded and able to work in multi-task environment under pressure independently and in a team.\n\n-\u00a0\u00a0\u00a0\u00a0\u00a0\u00a0\u00a0\u00a0\u00a0 Well-versed in MS Office such as Excel, Word and PowerPoint.\n\n-\u00a0\u00a0\u00a0\u00a0\u00a0\u00a0\u00a0\u00a0\u00a0 Occasional travels to China may be required\n\n-\u00a0\u00a0\u00a0\u00a0\u00a0\u00a0\u00a0\u00a0\u00a0 Immediate availability is highly preferred\n\nBenefits and Others:\n\nOur office is located in Tsim Sha Tsui.\u00a0 Attractive remuneration package including 5-day work week, bank holidays, 13-month pay, medical benefits and etc. will be offered to the successful candidate.\n\nInterested parties please send CV with expected salary by clicking APPLY NOW.\n", "employment_types": ["Full Time", "Permanent"], "selling_points": ["5-day work week, 13-month pay, medical benefits", "3 years solid experience in International trading", "Degree holder in Business related disciplines"], "locations": ["Tsim Sha Tsui"], "categories": ["Transportation & Logistics", "Shipping", "Merchandising & Purchasing", "Toy", "Sales, CS & Business Devpt", "Direct Sales"], "post_time": "2022-01-17T04:11:38Z", "salary": {"currency": null, "max": null, "min": null, "period": "monthly", "term": null}, "salary_visible": false, "title_keywords": ["shipping", "merchandising", "executive"], "responsibilities": ["shipping", "process orders", "coordinate", "communication", "maintain", "reports"], "requirements": {"degrees": ["degree holder"], "majors": ["related disciplines", "business"], "languages": ["cantonese", "english", "mandarin"], "language_level": ["fluency"], "hard_skills": ["excel", "plus", "word", "powerpoint", "analytical skills", "ms office"], "soft_skills": ["detail-minded", "communication skills", "independently", "multi-task", "under pressure", "analytical skills", "open minded", "interpersonal"], "languages_combined": [{"language": "cantonese", "language_level": ["fluency"]}, {"language": "english", "language_level": ["fluency"]}, {"language": "mandarin", "language_level": ["fluency"]}]}, "experience_required": {"duration": ["minimum 3 years"], "field": ["related", "business", "trading"]}}, {"job_id": "100003009040030", "location_code": "hk", "company": "Festival Products (HK) Ltd", "job_title": "Merchandiser/ Assistant Merchandiser (5 days work week)", "description": "What you\u2019ll be doing?\n\nSourcing and communicate with different suppliers\nCoordinate order follow-up\u00a0\nDocumentation and sample follow up\nVisit trade fairs in China if needed\n\nWho\u00a0are\u00a0we\u00a0looking\u00a0for?\u00a0\n\nForm\u00a05 or above\nMinimum 3 years merchandising or trading experience in one of the below areas:\u00a0\nSundries\nKitchenware / Houseware\u00a0\nDecoration\nTools / DIY Items / Toys\nIndoor and Outdoor Furniture\nElectronic items / Lighting\nSporting items\u00a0\nCandidates with less experience will be considered as Assistant Merchandiser\nAble to coordinate with mainland factories independently & work under pressure\nSelf-motivated, responsible and willing to learn\nProficiency in MS Excel, Word, PowerPoint, Outlook & Chinese word processing\nGood command of both written and\u00a0spoken English, Cantonese & Mandarin\nWilling travel to China if necessary\nYou will have an advantage if you are\nWell organized, mature, detail minded and a good team player\nExperience in European Market\nImmediately available\u00a0\n\nWhy you should consider this opportunity:\nWe offer attractive remuneration package with fringe benefits to right candidates. such as\u00a0\n\n5 days work\nPerformance bonus\nDouble pay\nBank holidays\n10 - 15 days of annual leave\n\nWork location: Kwun Tong ( 5 minutes walk for MTR station)\n\nInterested parties please send your resume with available date and expected salary by clicking\u00a0\"Apply Now\".\n\nNote: The Information will be treated in strict confidence and solely used for recruitment purposes.", "employment_types": ["Full Time", "Permanent"], "selling_points": [], "locations": ["Kwun Tong"], "categories": ["Merchandising & Purchasing", "Toy", "Sundries", "Procurement / Purchasing / Sourcing"], "post_time": "2022-01-12T00:52:13Z", "salary": {"currency": null, "max": null, "min": null, "period": "monthly", "term": null}, "salary_visible": false, "title_keywords": ["merchandiser", "assistant merchandiser"], "responsibilities": ["communicate with", "merchandising", "coordinate with", "coordinate", "documentation", "work under pressure"], "requirements": {"degrees": ["form 5 or above"], "majors": [], "languages": ["cantonese", "english", "chinese", "mandarin"], "language_level": ["proficiency", "good command"], "hard_skills": ["chinese word processing", "word", "powerpoint", "ms excel", "outlook", "documentation"], "soft_skills": ["self-motivated", "independently", "good team player", "responsible", "willing to learn", "well organized", "mature", "work under pressure"], "languages_combined": [{"language": "cantonese", "language_level": ["good command"]}, {"language": "english", "language_level": ["good command"]}, {"language": "chinese", "language_level": ["proficiency"]}, {"language": "mandarin", "language_level": ["good command"]}]}, "experience_required": {"duration": ["minimum 3 years"], "field": ["merchandising", "trading"]}}, {"job_id": "100003009029407", "location_code": "hk", "company": "Remax All Stars Hong Kong Limited", "job_title": "Senior Sales & Merchandiser", "description": "Responsibilities\n\nReporting directly Senior Merchandiser / Merchandising Manager\nSupport in the everyday operations of Merchandising, including customer accounts development\nProactive in new products development and products selections for individual accounts\nDuties will include Pre and Post Sales support\nQuotations and order follow up until shipment\nCoordinate with customers and internal parties to ensure that products meet customers' quality and on-time delivery\n\n\nRequirements\n\nHigh Diploma or above\nComputer Literate\nProficiency in using MS Word, Excel & Powerpoint\nHigh Command Of English with Good Command Of Mandarin\nMinimum 3 Years Of Experience In A Similar Role\nImmediate available is preferred\n\n\nGENERAL REQUIREMENTS:\n\nIdeal successful candidates will require:\n\nSales & Marketing mindset / skills\nExposure mainly with USA market\nAn outgoing and proactive goal driven attitude\nAble to work under pressure, work overtime in order to meet deadlines during buying trip season\nExcellent interpersonal and communication skills\nOccasional travel to our China facility in Guangzhou if required\nExperiences in supporting major US Drug Store retailers is most advantages\n\nApply Method\n\nInterested parties, please\u00a0click \"APPLY NOW\" to submit your application\u00a0with the details below:\n\nDetailed Resume\nPosition Interested\nExpected Salary\nDate Available\n\n\nAll information received will be kept confidential and for recruitment purposes only.", "employment_types": ["Full Time"], "selling_points": [], "locations": ["Tsim Sha Tsui"], "categories": ["Merchandising & Purchasing", "Toy"], "post_time": "2022-01-07T05:41:45Z", "salary": {"currency": null, "max": null, "min": null, "period": "monthly", "term": null}, "salary_visible": false, "title_keywords": ["merchandiser", "senior sales"], "responsibilities": ["reporting", "operations", "merchandising", "coordinate with", "quality", "internal parties"], "requirements": {"degrees": ["high diploma or above"], "majors": [], "languages": ["english", "mandarin"], "language_level": ["good command"], "hard_skills": ["excel", "goal", "powerpoint", "ms word"], "soft_skills": ["outgoing", "communication skills", "work overtime", "ideal", "interpersonal", "meet deadlines", "proactive", "driven", "work under pressure"], "languages_combined": [{"language": "english", "language_level": ["good command"]}, {"language": "mandarin", "language_level": ["good command"]}]}, "experience_required": {"duration": ["minimum 3 years"], "field": []}}, {"job_id": "100003009031356", "location_code": "hk", "company": "Dandee Hong Kong Holdings Limited", "job_title": "Merchandiser", "description": "Responsibilities:\n\nMaintain overall aspects of designs and engineering phase, while keeping the product development costs and timelines to market in focus;\nCollaborate with cross-functioning team including the US office, design team, project team, suppliers, to ensure multiple projects are being executed according to plan or timeline;\nProduct Sourcing and cost analysis;\nCoordinate, monitor the product design and project implementation;\nResponsible for product testing, packing design and package artwork handling.\n\n\u00a0Qualification & Requirements:\n\nDegree or above;\n2-year experiences in Children toys/Pet Products/Plastic items;\nStrong PC skills and familiar with Project handling;\nKnowledge of manufacturing processes and molding processes will be an advantage;\nSelf-motivated, able to work under pressure, good problem-solving skills;\nGood interpersonal & communication skills;\nProficient in spoken & written English and Mandarin;\nOccasionally travel to overseas and China;\nFresh graduate will be considered.", "employment_types": ["Full Time", "Permanent"], "selling_points": [], "locations": ["Tsim Sha Tsui"], "categories": ["Merchandising & Purchasing", "Toy"], "post_time": "2022-01-07T09:14:25Z", "salary": {"currency": null, "max": null, "min": null, "period": "monthly", "term": null}, "salary_visible": false, "title_keywords": ["merchandiser"], "responsibilities": ["collaborate with", "development costs", "monitor", "implementation", "design", "testing", "coordinate", "maintain", "product design", "plan", "multiple projects", "cost analysis"], "requirements": {"degrees": ["degree or above", "fresh graduate"], "majors": [], "languages": ["english", "mandarin"], "language_level": ["proficient"], "hard_skills": ["problem-solving skills", "pc skills"], "soft_skills": ["communication skills", "self-motivated", "problem-solving skills", "interpersonal", "work under pressure"], "languages_combined": [{"language": "english", "language_level": ["proficient"]}, {"language": "mandarin", "language_level": ["proficient"]}]}, "experience_required": {"duration": ["2-year"], "field": ["toys"]}}, {"job_id": "100003009032006", "location_code": "hk", "company": "Cosmic Pet HK Limited", "job_title": "Project Coordinator / Merchandiser \u2013 Pet Products/Children Toys/Plastic Toys", "description": "Job Responsibilities:\n\nReview and understand customers\u2019 buying guide as well as their online purchasing system in preparation for their order and shipment needs.\nLead the merchandising team to ensure all orders are properly follow through from sampling, quotation to production, testing, inspection, final delivery and payment.\nBased on customer confirmed orders, monitor subordinates in the issue of Purchase Orders to vendors and schedule shipment base on production capacity.\u00a0\nWork with various parties to resolve critical issues arising during order processing, production, quality control and shipment delivery in order to secure on time delivery and consistency of product qualities.\nAttend to customer complaints, coordinate with internal departments on execution of corrective action plans.\nAssist in showroom preparation before and during toy show time. Participate in client meetings and presentations.\nStrengthen and maintain good customer relationship to build company business.\nPrepare periodic customer and sales order reports for management review.\u00a0\nWork with US system team to ensure the operations system can effectively support the order processing flow.\nSupervise and coach team members to maximize their capability as well as job performance and satisfaction. Evaluate subordinate\u2019s performance and provide feedback.\n\nRequired Qualification and Experience:\n\nUniversity degree in business related discipline.\n8 years\u2019 experience with at least 3 years in managerial role in sales administration and merchandising responsibilities with a toy, novelty and/or consumer electronic company or factory.\nFamiliar with US and European customer buying requirements and testing standards.\nGood interpersonal relations, strong supervision, communication and problem solving skill, assertive, high integrity\nDetail oriented, highly organized, reliable, capable of working independently and under pressure, able to meet deadlines with good time management\nGood command of spoken and written English and Chinese including Cantonese and Mandarin\nSound knowledge of ERP and computer applications including Microsoft Word and Excel.\n\nInterested parties, please send full resume with date of availability, current and expected salary.\n\n\u00a0(All application information will be treated strictly confidential and for recruitment purpose only)\u00a0\n\nNote: Only shortlisted applicant will be notified.\n\n\n", "employment_types": ["Full Time"], "selling_points": ["Product Development, Merchandising, Sourcing", "Pet Products / Hard Toys / Gifts & Premium", "5-day work, Double Pay, Performance Bonus, Medical"], "locations": ["Lai Chi Kok"], "categories": ["Manufacturing", "Product Development / Management", "Merchandising & Purchasing", "Toy"], "post_time": "2022-01-07T10:07:04Z", "salary": {"currency": null, "max": null, "min": null, "period": "monthly", "term": null}, "salary_visible": false, "title_keywords": ["merchandiser", "project coordinator"], "responsibilities": ["operations", "quotation", "merchandising", "communication", "payment", "purchase", "maintain", "plans", "management review", "monitor", "presentations", "testing", "reports", "schedule", "computer applications", "sales administration", "management", "customer complaints", "review", "coordinate with", "inspection", "evaluate", "order processing", "quality control"], "requirements": {"degrees": ["university degree"], "majors": ["business"], "languages": ["cantonese", "english", "chinese", "mandarin"], "language_level": ["good command"], "hard_skills": ["excel", "microsoft word", "presentations", "erp", "problem solving", "order processing"], "soft_skills": ["organized", "independently", "under pressure", "capable", "assertive", "detail oriented", "integrity", "communication", "time management", "problem solving skill", "reliable", "meet deadlines", "interpersonal"], "languages_combined": [{"language": "cantonese", "language_level": ["good command"]}, {"language": "english", "language_level": ["good command"]}, {"language": "chinese", "language_level": ["good command"]}, {"language": "mandarin", "language_level": ["good command"]}]}, "experience_required": {"duration": ["at least 3 years", "8 years"], "field": ["sales administration", "managerial", "merchandising"]}}, {"job_id": "100003009022610", "location_code": "hk", "company": "Skyrocket H.K. Limited", "job_title": "Merchandising Manager  - Toys", "description": "Job Requirements\n\nDiploma graduate or above\n3-4 years relevant experience in sundries merchandising\nExperience in home decoration would be an advantage\nAble to handle orders from product development to production\nWell-versed in MS Office including Word, Excel and Outlook\nGood command of English and fair in spoken Mandarin\nImmediate available is highly preferred\n\nJob Responsibilities\n\nCoordinate order processing with overseas customers and China factory\nHandle quotation & purchase order follow up and arrange sample delivery\nAssist in sourcing vendors, lab dip follow up and production coordination\nProvide merchandising support from product development to production\n\nWe offer attractive career development prospects and excellent fringe benefits to the right candidates. Interested parties please send full resume with date of available, last and expected salary by clicking \u2018Apply Now\u2019", "employment_types": ["Full Time"], "selling_points": [], "locations": ["Tsim Sha Tsui"], "categories": ["Merchandising & Purchasing", "Toy"], "post_time": "2022-01-05T05:55:38Z", "salary": {"currency": null, "max": null, "min": null, "period": "monthly", "term": null}, "salary_visible": false, "title_keywords": ["merchandising manager"], "responsibilities": ["quotation", "merchandising", "coordinate", "purchase", "coordination", "order processing"], "requirements": {"degrees": ["diploma"], "majors": [], "languages": ["english", "mandarin"], "language_level": ["good command"], "hard_skills": ["excel", "outlook", "word", "ms office"], "soft_skills": [], "languages_combined": [{"language": "english", "language_level": ["good command"]}, {"language": "mandarin", "language_level": ["good command"]}]}, "experience_required": {"duration": ["3-4 years"], "field": ["merchandising", "relevant experience"]}}, {"job_id": "100003009029319", "location_code": "hk", "company": "IMC Toys Hong Kong Limited", "job_title": "OPERATIONS COORDINATOR (Shipping)", "description": "Company has over 30 years of experience in Develop and Selling toy, the office location is located at TST East.\n\nJob Highlights\u00a0\n\nSenior Sales & Merchandiser\nToy industry\n\nJob Responsibilities\n\nSales and maintain customer relationships\nExpand Local and Oversea Market\nDaily communication with buying office\nSales analysis and suggestions to supervisor\nFollow up closely with customer quality control and delivery\nUnderstanding customer's need and solve customer's questions\nAttend Oversea or Mainland China toy fair event\u00a0\nHandle Marketing Campaign\n\nJob Requirements\n\nUniversity graduates\nMinimum of 5 years working experience in merchandising sales or sourcing\nExperience in the oversea market is preferred\nTrading or Buying Office Background will consider as priority\nFluent\u00a0in English Mandarin is required\u00a0\nFamiliar with Word, Powerpoint and Excel (Vlookup).", "employment_types": ["Full Time", "Permanent"], "selling_points": [], "locations": ["Tsim Sha Tsui"], "categories": ["Merchandising & Purchasing", "Toy", "Procurement / Purchasing / Sourcing"], "post_time": "2022-01-07T04:43:09Z", "salary": {"currency": null, "max": null, "min": null, "period": "monthly", "term": null}, "salary_visible": false, "title_keywords": ["shipping", "operations", "coordinator"], "responsibilities": ["communication", "analysis", "maintain", "quality control"], "requirements": {"degrees": [], "majors": [], "languages": ["english", "mandarin"], "language_level": ["fluent"], "hard_skills": ["excel", "vlookup", "word", "powerpoint"], "soft_skills": [], "languages_combined": [{"language": "english", "language_level": []}, {"language": "mandarin", "language_level": ["fluent"]}]}, "experience_required": {"duration": ["minimum of 5 years"], "field": ["merchandising"]}}, {"job_id": "100003009037797", "location_code": "hk", "company": "Vaform (HK) Company", "job_title": "Merchandiser \u2013 Home Decoration & Sundries", "description": "Our client is a well established international company, a French based group with over 30 years in designing and production of high-end collectible figurines and games, with offices in France, China, Hong Kong and Vietnam. \u00a0They are looking for a Junior Merchandiser to join their team to provide support from product development to manufacturing for sales projects.\n\nOrder follow-up, sample handling and product development\n5 days work week, salary HK$16k-18k\nMedical Insurance, 14 annual leave, bank holiday, professional training\nThe job:\u00a0 \u00a0\nResponsible for order follow-up, sample handling, product development and shipment planning\nWork closely between the product development team and factory in China on sourcing, pricing, sampling and production\nCoordinate with internal production departments and external parties to ensure on-time shipment\u00a0\nLiaison and negotiation with suppliers and buyers\nParticipate in ad-hoc projects as assigned\nThe person:\n\nHigher Diploma or above in Business Administration\n1 year relevant merchandising experience\nFluent in English and Chinese\nProficient in MS Office application in Excel, Word and PowerPoint\nGood communication skills and team player\n\nInterested parties please apply through email and provide latest resume and salary expectation.\nAll information provided will be used for recruitment purposes only\u00a0", "employment_types": ["Full Time", "Permanent"], "selling_points": [], "locations": ["Not Specified"], "categories": ["Merchandising & Purchasing", "Toy", "Sundries", "Others"], "post_time": "2022-01-11T06:12:32Z", "salary": {"currency": null, "max": null, "min": null, "period": "monthly", "term": null}, "salary_visible": false, "title_keywords": ["merchandiser"], "responsibilities": ["ad-hoc projects", "external parties", "coordinate with", "planning"], "requirements": {"degrees": ["higher diploma or above"], "majors": ["business administration"], "languages": ["english", "chinese"], "language_level": ["fluent"], "hard_skills": ["excel", "word", "powerpoint", "ms office"], "soft_skills": ["communication skills", "team player"], "languages_combined": [{"language": "english", "language_level": ["fluent"]}, {"language": "chinese", "language_level": ["fluent"]}]}, "experience_required": {"duration": ["1 year"], "field": ["merchandising"]}}, {"job_id": "100003009021310", "location_code": "hk", "company": "Vaform (HK) Company", "job_title": "Senior Merchandiser (Toys)", "description": "Key Responsibilities:\n\nFacilitate communication meetings with countries' buying team\nLiaise with vendor and internal departments on handling daily product enquiries\nCollect and manage vendor access, responsible for materials' sharing\nAssist in range review and toy fair preparations\nConsolidate sales data from countries and assist in report generation\nRequirements\u00a0:\nBachelor Degree in any discipline\n2-5 years experience in retail buying/ souring, preferably in Toys industry\nExperience working in MNC or regional exposure will be an advantage\nProficient in MS Excel\nExcellent negotiation and communication skills\nStrong problem solving skills\nFlexible, resilient and able to operate independently as well as part of a team\nGood command in spoken and written English, Cantonese and Mandarin\n\nWe offer 5-day work week and below comprehensive\u00a0salary package\u00a0to the right candidate.\n\nAnnual Leave\nBirthday Leave\nChild Care Leave\nMarriage Leave\nDiscretionary Bonus\nStudy Sponsorship\nMedical Coverage\nLife Insurance\nPlease send your resume stating your current/ last salary, expected salary and\u00a0available date via \"Apply now\" button.\n\nFor more information, please visit our website at\u00a0www.toysrusasia.com\n\n(All\u00a0collected\u00a0information will be used for recruitment related purpose only.)", "employment_types": ["Full Time", "Permanent"], "selling_points": [], "locations": ["Not Specified"], "categories": ["Merchandising & Purchasing", "Toy", "Sundries"], "post_time": "2022-01-05T04:34:16Z", "salary": {"currency": null, "max": null, "min": null, "period": "monthly", "term": null}, "salary_visible": false, "title_keywords": ["senior merchandiser"], "responsibilities": ["data", "review", "communication", "liaise with", "report"], "requirements": {"degrees": ["degree", "bachelor"], "majors": [], "languages": ["cantonese", "english", "mandarin"], "language_level": ["good command"], "hard_skills": ["ms excel", "problem solving skills"], "soft_skills": ["flexible", "communication skills", "independently", "negotiation", "problem solving skills"], "languages_combined": [{"language": "cantonese", "language_level": ["good command"]}, {"language": "english", "language_level": ["good command"]}, {"language": "mandarin", "language_level": ["good command"]}]}, "experience_required": {"duration": ["2-5 years"], "field": ["toys", "retail"]}}, {"job_id": "100003009029386", "location_code": "hk", "company": "Lidl Asia Pte. Limited (Hong Kong Branch)", "job_title": "Senior Merchandiser Hardgoods (Toys)", "description": "Job profile: Reporting to the Operations Manager, you will support our Operations Department - Shipping Team to co-ordination all logistic task, liaise with suppliers, inter departments and head quarter to monitor and follow up of shipment and delivery status, handle I/E documents, L/C documents, import and export declaration.\n\n\nRequirements:\nForm 7 or above.\nAt least 2 years of relevant experience in shipping arrangement between HK, China and overseas.\nSolid knowledge on MS Office (Word, Excel), Outlook and PC tools.\nExperience with the Ocean Freight.\nExperience in the toy field or trading company will be a plus.\nExperience working for/with large distributors highly valuable.\nExperienced user of Manufacturing software/ERP systems (SAP).\nFluent in Cantonese, English & Mandarin.\nStrong sense of responsibility, well organized, multi-task oriented, hardworking, and willing to learn.\nExtremely self-motivated.\nSelected candidates will be invited to join our dynamic team (office in TST East), and will be offered an attractive package, including:\nCompetitive salary (conditional year end one month salary & conditional performance bonus).\n5 days work (from 9:30am to 6:30pm).\n15 days annual leave (+1 additional day for each 3-year period max 3 days).\u00a0\nGroup medical and life insurance plan after 6\u00a0months period.\nInterested parties\u00a0please send full resume, and cover letter (specifying availability and expected salary) by clicking \"APPLY NOW\". Data collected will be used for recruitment purposes only.\u00a0 Data collected will be used for recruitment purposes only.", "employment_types": ["Full Time"], "selling_points": ["Wooden toy knowledge is a plus", "Great benefits", "International company"], "locations": ["Tsim Sha Tsui"], "categories": ["Merchandising & Purchasing", "Toy"], "post_time": "2022-01-07T04:57:18Z", "salary": {"currency": null, "max": null, "min": null, "period": "monthly", "term": null}, "salary_visible": false, "title_keywords": ["senior merchandiser"], "responsibilities": ["reporting", "shipping", "software", "operations", "systems", "monitor", "import and export declaration", "plan", "insurance", "liaise with suppliers"], "requirements": {"degrees": [], "majors": [], "languages": ["cantonese", "english", "mandarin"], "language_level": ["fluent"], "hard_skills": ["excel", "plus", "erp systems", "max", "sap", "word", "import and export", "c", "outlook", "dynamic", "pc", "ms office"], "soft_skills": ["self-motivated", "multi-task oriented", "sense of responsibility", "well organized", "willing to learn", "dynamic", "hardworking"], "languages_combined": [{"language": "cantonese", "language_level": ["fluent"]}, {"language": "english", "language_level": ["fluent"]}, {"language": "mandarin", "language_level": ["fluent"]}]}, "experience_required": {"duration": ["at least 2 years"], "field": ["relevant experience", "trading"]}}, {"job_id": "100003009009056", "location_code": "hk", "company": "Webster Personnel Agency Limited", "job_title": "Junior Merchandiser (Toys) - 5 days work", "description": "About the company\n\nOur client is one of the UK\u2019s leading retailers of grocery and non-food products. It has more than 146 years of heritage with 160,000 employees and 1,200 stores in UK. It strives to become the most trusted retailer where customers and colleagues enjoy shopping and working. They build a firm commitment to ethical trading practices by sustainable sourcing. Their sourcing office in HK source best quality products and rightest cost for customers. Upon expansion of their strategic sourcing, they are now looking for a confident and committable Assistant Quality Officer to join their enjoyable and winning team.\n\nJob Description\n\nyou will be the key person to perform the following duties:\n\nEnsure products meet quality, legal and safety requirements and due diligence\nSupport and advise merchandisers to ensure products selected comply with UK/European standards and internal company requirements\nEnsure working practices aligned with UK/HK team, understood and implemented by suppliers and third party inspection and testing companies\nCoordinate with external test laboratories to ensure appropriate testing of products\nPerform factory assessment in relation to Quality and Ethical standards\nManage the Quality Management System to ensure quality deliveries of products and services\nManage and respond to quality assurance issues with related divisions\nReport to management for any product incident investigation\nAccountable for internal process and supplier sourcing improvement projects\n\nWhy you?\n\nAt least 1 year of experience in Quality Assurance /Quality Control from sourcing / buying office / retail / manufacturing background\nWelcome fresh graduates\nDegree holder\nStress-resistant and able to make balanced decisions\nExcellent communication skills\nFluently written and spoken English, Cantonese and Mandarin\n\nHow to Apply?\n\nIf you are looking for career changes, you may send resume to resume @)sixpeoplemap.com , quoting Job Ref#TH-8405. You may also contact us via\u00a0Whatsapp. Action now and share with you friends for referral rewards.", "employment_types": ["Full Time", "Permanent"], "selling_points": [], "locations": ["Cheung Sha Wan"], "categories": ["Manufacturing", "Product Development / Management", "Merchandising & Purchasing", "Toy", "Sales, CS & Business Devpt", "Sales Administration"], "post_time": "2022-01-05T08:28:41Z", "salary": {"currency": null, "max": null, "min": null, "period": "monthly", "term": null}, "salary_visible": false, "title_keywords": ["junior merchandiser"], "responsibilities": ["due diligence", "cost", "management", "quality", "coordinate with", "investigation", "inspection", "testing", "communication", "contact", "quality control", "third party", "report"], "requirements": {"degrees": ["degree holder"], "majors": [], "languages": ["cantonese", "english", "mandarin"], "language_level": [], "hard_skills": ["make", "whatsapp"], "soft_skills": ["confident", "communication skills", "accountable", "ethical"], "languages_combined": [{"language": "cantonese", "language_level": []}, {"language": "english", "language_level": []}, {"language": "mandarin", "language_level": []}]}, "experience_required": {"duration": ["at least 1 year"], "field": ["manufacturing", "retail", "quality control", "quality assurance"]}}, {"job_id": "100003009029195", "location_code": "hk", "company": "Toys\"R\"Us (Asia) Limited", "job_title": "Associate Buyer/ Regional Buyer", "description": "Job Requirements\n\nHigher Diploma / Diploma holder\nA minimum of 7 years merchandising experience in plastic toys\nSolid experience in product development and order arrangement\nExperience in manufacturing company would be a great advantage\nDetail-minded, flexible, well-organized, energetic and efficient\nFamiliar with MS Office such as Word, Excel and Chinese WP\nProficient in communication of English and Putonghua\nImmediate available is highly preferred\n\nJob Responsibilities\n\nMonitor daily merchandising flow from quotation, development to production\nHandle orders arrangement with overseas customers, factories and suppliers\nResponsible for product development, lab testing and production follow up\nHandle price & terms negotiation and costing evaluation for order processing\nWork closely with factory to ensure the completion of production on time\n\nWe offer attractive career development prospects and excellent fringe benefits to the right candidates. Interested parties please send full resume with date of available, last and expected salary by clicking \u2018Apply Now\u2019", "employment_types": ["Full Time", "Permanent"], "selling_points": ["Regional toys buying & sourcing for Asia markets", "Fast paced, dynamic working environment", "Fun, energetic, strong team work"], "locations": ["Lai Chi Kok"], "categories": ["Manufacturing", "Production Planning / Control", "Merchandising & Purchasing", "Toy"], "post_time": "2022-01-07T04:20:07Z", "salary": {"currency": null, "max": null, "min": null, "period": null, "term": null}, "salary_visible": false, "title_keywords": ["associate"], "responsibilities": ["terms negotiation", "quotation", "merchandising", "monitor", "testing", "order processing", "evaluation"], "requirements": {"degrees": ["diploma holder", "diploma"], "majors": [], "languages": ["putonghua", "english", "chinese"], "language_level": ["proficient"], "hard_skills": ["excel", "chinese wp", "word", "ms office"], "soft_skills": ["detail-minded", "flexible", "efficient", "well-organized", "communication", "energetic"], "languages_combined": [{"language": "putonghua", "language_level": ["proficient"]}, {"language": "english", "language_level": ["proficient"]}, {"language": "chinese", "language_level": []}]}, "experience_required": {"duration": ["minimum of 7 years"], "field": ["toys", "product development", "manufacturing", "merchandising"]}}, {"job_id": "100003009031200", "location_code": "hk", "company": "Six People Map", "job_title": "Assistant Quality Officer | UK's leading retailer | Sizable buying office| MNC", "description": "Summary\n\nWe value diversity at Lidl and this includes creating collaborative teams with colleagues with diverse experiences and backgrounds. Continue your career journey and make a difference with us here at Lidl!\n\nWhat will you do?\nWork closely with product sourcing and development teams to ensure the best offers to our customer\u00a0\nConduct product evaluations and benchmarking against relevant market items\u00a0\nNegotiations with supplier and project status responsibility\u00a0\nKeep track of purchase orders\u00a0\nConduct factory inspections and ensure product quality\u00a0\nEnsure on time shipment after production\u00a0\nWork closely with product sourcing and development teams to ensure the best offers to our customer\u00a0\nConduct product evaluations and benchmarking against relevant market items\u00a0\nNegotiations with supplier and project status responsibility\u00a0\nKeep track of purchase orders\u00a0\nConduct factory inspections and ensure product quality\u00a0\nEnsure on time shipment after production\u00a0\nWhat will you need?\nForm 6 or above (HKDSE)/ Form 7 or above (HKALE)\u00a0\nMinimum 3 years of merchandising experience in the European market in relevant category\nFamiliar with the related compliance standard is an advantage\u00a0\nPossess strong project management skills and detail orientated mindset to ensure timely production and delivery schedules are met\u00a0\nHigh degree of work ethics and integrity\u00a0\nMust be self motivated, self organized, responsible, hard working and independent\u00a0\nExperience in liaising with factories and suppliers\u00a0\nGood communication skills in both spoken and written English and Chinese\u00a0\nTravel required\u00a0\nWhat do we offer?\n\nWe are dedicated to fostering a family-friendly culture and work environment and have been a proud member of the Caring Company Scheme since 2014. We are an equal opportunities employer and welcome applications from all candidates with the required skills and experience.\n\n\u00a0\nMarket Leading Remuneration Package:\n\nDouble pay and discretionary bonus\nChoice of MPF provider\nLife Insurance\nMedical Insurance\n\u00a0\n\nSupportive Environment:\n\nRental re-imbursement scheme\nOut-Of-Office leave for important appointments\nIn-house training courses\nTraining sponsorship scheme\nHealth Check\nVision Check\nSupporting your child\u2019s education with advice from a leading education consultant\n\u00a0\n\nWork-Life Balance:\n\n5 day week\nCompetitive Annual Leave\nCharity, Community and Sporting Events\n\nWe are dedicated to fostering a family-friendly culture and work environment and have been a proud member of the Caring Company Scheme since 2014. We are an equal opportunities employer and welcome applications from all candidates with the required skills and experience.\n\n\u00a0\nMarket Leading Remuneration Package:\n\nDouble pay and discretionary bonus\nChoice of MPF provider\nLife Insurance\nMedical Insurance\n\u00a0\n\nSupportive Environment:\n\nRental re-imbursement scheme\nOut-Of-Office leave for important appointments\nIn-house training courses\nTraining sponsorship scheme\nHealth Check\nVision Check\nExceptional maternity and paternity leave\nSupporting your child\u2019s education with advice from a leading education consultant\n\u00a0\n\nWork-Life Balance:\n\n5 day week\nCompetitive Annual Leave\nCharity, Community and Sporting Events", "employment_types": ["Full Time", "Permanent"], "selling_points": ["UK\u2019s leading retailers", "Career Progression Opportunity", "Welcome fresh graduates"], "locations": ["Kwun Tong"], "categories": ["Engineering", "Manufacturing & Production", "Merchandising & Purchasing", "Electronics", "Toy"], "post_time": "2022-01-07T09:02:54Z", "salary": {"currency": null, "max": null, "min": null, "period": "monthly", "term": null}, "salary_visible": false, "title_keywords": ["quality officer", "assistant"], "responsibilities": ["schedules", "compliance", "quality", "teams", "merchandising", "liaising with", "communication", "project management", "purchase"], "requirements": {"degrees": ["degree", "hkdse"], "majors": [], "languages": ["english", "chinese"], "language_level": ["good"], "hard_skills": ["make", "project management"], "soft_skills": ["organized", "communication skills", "independent", "responsible", "project management skills", "timely", "hard working", "integrity", "collaborative", "self motivated", "diverse", "detail orientated"], "languages_combined": [{"language": "english", "language_level": ["good"]}, {"language": "chinese", "language_level": ["good"]}]}, "experience_required": {"duration": ["minimum 3 years"], "field": ["merchandising"]}}, {"job_id": "100003009015947", "location_code": "hk", "company": "", "job_title": "MERCHANDIER  - PLUSH TOYS", "description": "Responsibility\n\n- To sever the customers from USA and Europe\n\n- Flexible to work with our US Office and China Office\n\n- Process the orders from sourcing, quotation, samples delivery etc.\n\nRequiremnets\n\n- F. 5 or above\n\n- At least 3 years experiences in Plush Toys field\n\n- Good communication skill in Cantonese / English / Mandarin\n\n- Good PC skills\n\n- Occasional China Trips needed\n\n- Independent, well organized\n\n\u00a0Interested parties, please contact Ms Cheung at 27561911 before applying.", "employment_types": ["Full Time"], "selling_points": [], "locations": ["Kowloon Bay"], "categories": ["Merchandising & Purchasing", "Toy"], "post_time": "2022-01-03T07:59:06Z", "salary": {"currency": null, "max": null, "min": null, "period": "monthly", "term": null}, "salary_visible": false, "title_keywords": [], "responsibilities": ["quotation"], "requirements": {"degrees": [], "majors": [], "languages": ["cantonese", "english", "mandarin"], "language_level": ["good"], "hard_skills": ["pc skills"], "soft_skills": ["communication skill", "independent", "well organized"], "languages_combined": [{"language": "cantonese", "language_level": ["good"]}, {"language": "english", "language_level": ["good"]}, {"language": "mandarin", "language_level": ["good"]}]}, "experience_required": {"duration": ["at least 3 years"], "field": ["toys"]}}, {"job_id": "100003009030784", "location_code": "hk", "company": "Pets at Home (Asia) Limited", "job_title": "Product Specialist", "description": "The role will be based in Hong Kong with frequent travel throughout PRC.\u00a0 Reporting to Product Manager & Merchandise Manager, responsible for sourcing, product development, and delivering innovative products and ranges from world-class vendors, which will drive sales, profit, and cash advantages for the business.\u00a0\n\nJob Description\n\nDevelop and manage sourcing strategies, ensure the right matrix of suppliers to fulfill company\u2019s global sourcing plans\nSource and develop potential suppliers within the Asia region to support the company\u2019s business plans, and/or drive innovation into the business\nLiaise with UK stakeholders on category & supplier strategies\nMonitor industry trends, develop competitive intelligence, and market insights for category planning\nDrive product knowledge, skills, and competency development based on the continuously evolving market needs\nDevelop and engineer products to optimize value\nCollaborate with cross-functional teams to enhance brand identity and product features & benefit\nNegotiate for the best commercial conditions: improve price competitiveness, deliver margin gains, improve payment terms\nFollow up sourcing processes & maintain accurate and updated data in sourcing systems for all projects\nWork with cross-functional teams to keep track of projects\u2019 critical paths\nTravel to factories /suppliers for buying trips & new product development\nManage any ad hoc projects as directed by the team supervisor\n\nRequirement\n\nDegree holder or above in the relevant discipline\nPrevious experience of working in a global sourcing/buying office/trading office is preferable\n2 - 7 years solid experience in developing\u00a0and/or sourcing\u00a0hard goods, pet products.\nGood command of both spoken and written English, Cantonese & Mandarin\nWilling to travel to PRC\nGood negotiation and presentation skills\nProactive, positive, energetic, and attention to details\nTeam player, Responsible, and able to work independently and with teams\n\nThe Benefits:\u00a0\u00a0\n\nCompetitive salary (13 month\u2019s pay) plus discretionary performance bonus\n15 days annual leaves plus birthday leave\u00a0\u00a0\nGroup medical & dental scheme\n\nSound like the perfect job for you? Let's talk!\u00a0 Drop your resume with current and expected salaries to us.\n\n\n\n(Only short-listed candidates will be contacted.\u00a0 All personal data collected will be treated in strict confidence and used for recruitment only)", "employment_types": ["Full Time", "Permanent"], "selling_points": ["Competitive salary", "15 days annual leaves plus birthday leave", "Group medical & dental scheme"], "locations": ["Kwun Tong"], "categories": ["Merchandising & Purchasing", "Toy", "Sundries", "Procurement / Purchasing / Sourcing"], "post_time": "2022-01-07T11:06:36Z", "salary": {"currency": null, "max": null, "min": null, "period": "monthly", "term": null}, "salary_visible": false, "title_keywords": ["product specialist"], "responsibilities": ["collaborate with", "data", "systems", "monitor", "business plans", "develop", "payment", "maintain", "ad hoc projects", "liaise with", "plans", "cross-functional teams", "planning"], "requirements": {"degrees": ["degree holder"], "majors": [], "languages": ["cantonese", "english", "mandarin"], "language_level": ["good command"], "hard_skills": [], "soft_skills": ["work independently", "proactive", "negotiation", "responsible", "presentation skills", "attention to details", "team player", "energetic", "positive"], "languages_combined": [{"language": "cantonese", "language_level": ["good command"]}, {"language": "english", "language_level": ["good command"]}, {"language": "mandarin", "language_level": ["good command"]}]}, "experience_required": {"duration": ["2 - 7 years"], "field": ["trading", "developing"]}}, {"job_id": "100003009021007", "location_code": "hk", "company": "ConnectedGroup Limited", "job_title": "Sourcing Manager - Toys", "description": "International trading company\nGrowing fast, new headcount\nExcellent culture with the benefit\nReporting to Sourcing Director\n\nResponsibilities:\n\nIdentify and develop sourcing strategies, cost reduction programs, and new vendor development activities\nDefine and implement strategies for optimizing supplier performance, including price, service levels, lead times and product quality\nManaging and developing a vendor/factory base\nResponsible for supplier quality assurance\nMonitor and resolve supply chain, logistics and commercial issues\nEstablish and maintain effective regular KPI reporting to monitor the effectiveness of Supply Chain\n\nRequirements:\n\nMinimum 6 years sourcing experience in toys category\nBachelor's degree\nFluent in Cantonese and English is a Must\nSolid experience in handling toys category is a Must\nAbility to work in a fast pace environment\nPrevious experience in handling plush and figurines is required", "employment_types": ["Full Time", "Permanent"], "selling_points": ["Global Trading Company", "Fast Growth and Flexible Working Culture", "Report to Sourcing Director"], "locations": ["Not Specified"], "categories": ["Merchandising & Purchasing", "Toy", "Others", "Procurement / Purchasing / Sourcing"], "post_time": "2022-01-05T02:52:22Z", "salary": {"currency": "HKD", "max": 54999, "min": 45000, "period": "monthly", "term": null}, "salary_visible": true, "title_keywords": ["sourcing manager"], "responsibilities": ["reporting", "cost", "monitor", "quality", "developing", "develop", "maintain", "logistics"], "requirements": {"degrees": ["degree", "bachelor"], "majors": [], "languages": ["cantonese", "english"], "language_level": ["fluent"], "hard_skills": [], "soft_skills": [], "languages_combined": [{"language": "cantonese", "language_level": ["fluent"]}, {"language": "english", "language_level": ["fluent"]}]}, "experience_required": {"duration": ["minimum 6 years"], "field": ["toys"]}}, {"job_id": "100003009023639", "location_code": "hk", "company": "P & A Consultant Limited", "job_title": "Asst. Merchandiser/Merchandiser/Sr. Merch/Asst. Merchandising Manager(Toys/Seasonal/Handbag)", "description": "Assistant Merchandising Manager/ Sr. Merchandiser/Merchandiser/ Assistant Merchandiser(Toys/ Sundries/ Gift & Premium/ Seasonal/ Plastic/ Home Decoration/ Polyresin/ Metal/ Wooden product/ Electronic Consumer/ Sport products)- Urgent\u00a0\nSalary : 16-30K,\u00a0Location : Hung Hom/ Lai Chi Kok/ Tsuen Wan/ Kwun Tong ( 5 Days )\u00a0\u00a0\nRequirements\u00a0 :\u00a0\n\nF.5 or above,\u00a0\nAt Least 5-10 years of Merchandiser exp in Toys( Plastic/ Hard/ Wood/ Paper /Board game\u00a0) or Seasonal or Sundries, Gift and premium /\u00a0Electronic Consumer/ Sport\u00a0Product\nProduct development, sourcing, follow up order & sample\nWork independently\nGood command of English & Mandarin\nCandidate have less exp also will be consider as Assistant Merchandiser\u00a0\nSr. Merchandiser/ Merchandiser- Handbag( Urgent )\u00a0\n(Kwun Tong) 5 days,\u00a0salary:18-30K\u00a0\nRequirements\u00a0 :\u00a0\n\nDiploma/ Degree holder,\u00a0\nAt Least 3-8 years of Merchandiser exp in Handbag( PVC, Nylon, Leather )\nstrong Product development\nsourcing, follow up order & sample, contact client & mfg\u00a0\nWork independently\nGood command of Cantonese, English & Mandarin\nImmediate available is preferred\nCandidates have less exp also will be consider as Assistant Merchandiser\u00a0\n\n*** Personal data will be treated with strict confidential and used for recruitment purpose only.\n\n\nP & A consultant Ltd will not charge any fees from the above-stated job-seeker, your job apply to our company means your acceptance of our terms and conditions.", "employment_types": ["Full Time"], "selling_points": [], "locations": ["Lai Chi Kok"], "categories": ["Merchandising & Purchasing", "Handbag", "Toy", "Sundries"], "post_time": "2022-01-07T19:19:19Z", "salary": {"currency": null, "max": null, "min": null, "period": "monthly", "term": null}, "salary_visible": false, "title_keywords": ["merchandiser", "merchandising", "asst. merchandiser"], "responsibilities": ["recruitment", "personal data", "merchandising", "contact"], "requirements": {"degrees": ["diploma", "degree holder"], "majors": [], "languages": ["cantonese", "english", "mandarin"], "language_level": ["good command"], "hard_skills": ["wan", "sr"], "soft_skills": ["work independently"], "languages_combined": [{"language": "cantonese", "language_level": ["good command"]}, {"language": "english", "language_level": ["good command", "good command"]}, {"language": "mandarin", "language_level": ["good command", "good command"]}]}, "experience_required": {"duration": [], "field": []}}, {"job_id": "100003009025999", "location_code": "hk", "company": "SGS Hong Kong Limited", "job_title": "Technical Services Executive (Hardlines)", "description": "Key Responsibilities:\n\n\nAssist managers of respective testing laboratory in testing development\nProvide technical support and consultancy to operations / customer services / frontlines / clients\nOrganize and delivering seminar and training (internal and external)\nDevelop new services upon client\u2019s specification or updated requirements\n\nRequirements:\n\n\nHigher diploma or above in Physical / Engineering / Product Testing or related disciplines\nMinimum 2 years\u2019 working experience in hardlines lab\nSound knowledge in international regulations and standards of\u00a0toys / hardlines items (eg. eyewear, food contact product, packaging materials, etc.)\nExcellent communication and interpersonal skills\nExcellent analytical ability, positive attitude and attention to details\nGood command of written and spoken English and Chinese, including Mandarin\n\nAs a caring company, SGS not only offers a competitive remuneration package but also offers staff caring items to the right candidates, including:\n\n\n5-day Work Week\u00a0\u00a0\u00a0\u00a0\u00a0\u00a0\u00a0\u00a0\u00a0\u00a0\u00a0\u00a0\u00a0\u00a0\u00a0\u00a0\u00a0\u00a0\u00a0\u00a0\u00a0\u00a0\u00a0\u00a0\u00a0\u00a0\u00a0\u00a0\u00a0\u00a0\u00a0\u00a0\u00a0\u00a0\u00a0\u00a0\u00a0\u00a0\u00a0\u00a0\u00a0\u00a0\u00a0\u00a0\u00a0\u00a0\u00a0\u00a0\nDouble Pay and Performance Bonus\nDental and Medical Benefits\nAccident Insurance and Life Insurance\nAnnual Leave\nBirthday Leave\nPaid Maternity Leave, Paternity Leave\nCareer Advancement Opportunities\nOn-the-Job Training\u00a0\u00a0\u00a0\u00a0\u00a0\u00a0\u00a0\u00a0\u00a0\u00a0\u00a0\u00a0\u00a0\u00a0\u00a0\u00a0\u00a0\u00a0\u00a0\u00a0\u00a0\u00a0\u00a0\u00a0\u00a0\u00a0\u00a0\u00a0\u00a0\u00a0\u00a0\u00a0\u00a0\u00a0\nEducation and Training Subsidies\nTransportation Subsidies\nShuttle Bus Service\nEmployee Assistance Program (EAP)\nStaff Activities\n\nInterested parties please send your full resume with expected salary and date available by clicking \"Apply Now\".\n(Data received will be kept confidential and used for processing application only.)", "employment_types": ["Full Time", "Permanent"], "selling_points": ["Double Pay Free Shuttle Bus; Birthday Leave", "Physical Test ;Toys", "DSE; Fresh graduate will also consider"], "locations": ["Fanling"], "categories": ["Sciences, Lab, R&D", "Laboratory", "Merchandising & Purchasing", "Toy", "Manufacturing", "Quality Assurance, Control & Testing / ISO"], "post_time": "2022-01-06T07:01:22Z", "salary": {"currency": null, "max": null, "min": null, "period": "monthly", "term": null}, "salary_visible": false, "title_keywords": ["executive"], "responsibilities": ["technical support", "operations", "customer services", "testing", "assist managers", "develop"], "requirements": {"degrees": ["higher diploma or above"], "majors": ["related disciplines", "engineering"], "languages": ["english", "chinese", "mandarin"], "language_level": ["good command"], "hard_skills": [], "soft_skills": ["positive attitude", "communication and interpersonal skills", "attention to details"], "languages_combined": [{"language": "english", "language_level": ["good command"]}, {"language": "chinese", "language_level": ["good command"]}, {"language": "mandarin", "language_level": ["good command"]}]}, "experience_required": {"duration": ["minimum 2 years"], "field": []}}, {"job_id": "100003009023910", "location_code": "hk", "company": "Welly Die Casting International Limited", "job_title": "Sales Executive - Five Days Work", "description": "Responsibilities:\n\nTo support sales and marketing activities\nAble to follow up orders and coordinate with porduction department\nAssist your superior in daily operation\nTo communicate with factory for sampling and production\n\nRequirements:\n\nHigher\u00a0Diploma\u00a0or above with at least 2 years relevant experiences in export sales with toys manufacturing background preferable\nGood command of spoken and written English and Chinese\nIndependent, self-motivated, efficent and welloorganized\nWilling to work under pressure\nPC knowledge is essential (on MS Excel & Words)", "employment_types": ["Full Time"], "selling_points": ["Higher Diploma", "2 years experiences with toys manufacturing", "Willing to work under pressure"], "locations": ["Tsuen Wan Area"], "categories": ["Manufacturing", "Others", "Merchandising & Purchasing", "Toy", "Sales, CS & Business Devpt", "Others"], "post_time": "2022-01-05T10:00:42Z", "salary": {"currency": null, "max": null, "min": null, "period": "monthly", "term": null}, "salary_visible": false, "title_keywords": ["sales executive"], "responsibilities": ["follow up orders", "coordinate with", "communicate with", "daily operation"], "requirements": {"degrees": ["higher diploma or above"], "majors": ["manufacturing"], "languages": ["english", "chinese"], "language_level": ["good command"], "hard_skills": ["pc knowledge", "ms excel", "words"], "soft_skills": ["self-motivated", "independent", "work under pressure"], "languages_combined": [{"language": "english", "language_level": ["good command"]}, {"language": "chinese", "language_level": ["good command"]}]}, "experience_required": {"duration": ["at least 2 years"], "field": ["toys", "manufacturing"]}}, {"job_id": "100003009014425", "location_code": "hk", "company": "Branford Limited", "job_title": "Merchandiser - Mainly US (13th month salary)", "description": "Merchandiser (Mainly US)\n\nBranford Limited is an international children\u2019s toy company and we are currently looking for a talented and motivated Merchandiser to cope with the growth of the company.\n\n\nRequirements:\n\nF. 7 level / HKDSE (Grade 4+ in English or Mathematics) or above\nMinimum 3 years merchandising and production planning experience\nProficient in Microsoft Word and Excel\nAdvanced Excel skills (Lookup, Pivot table)\nWell spoken and written English, fluent Putonghua as well as Cantonese\nSelf-motivated, able to work independently and follow through on required tasks\nDetail Oriented\nGood team player and good interpersonal skills\nStrong sense of responsibility\n\nResponsibilities:\u00a0\n\nWork closely with internal sales team in forecast planning\nMonitor inventory level and replenishment status in a timely basis\nIssue orders and follow up production with suppliers\nHandle customer\u2019s enquiries\nCoordinate with internal logistic team on delivery arrangement\nAssist in general office work and ad hoc tasks as required.\n\n\u00a0Benefits:\n\n5-days work week\n13th month salary\nMedical and detail coverage\n\nPlease feel free to visit our current Web Sites: ogdolls.com, myglittergirls.com, woodzeez.com, terrauniverse.com, mybtoys.com and battatco.com.\n\nPlease apply with full resume and expected salary though applies now.\n\nPersonal data collected will be used for recruitment purpose only.", "employment_types": ["Permanent"], "selling_points": [], "locations": ["Tsim Sha Tsui"], "categories": ["Merchandising & Purchasing", "Electronics", "Toy", "Others"], "post_time": "2022-01-03T03:25:05Z", "salary": {"currency": null, "max": null, "min": null, "period": "monthly", "term": null}, "salary_visible": false, "title_keywords": ["merchandiser"], "responsibilities": ["inventory", "monitor", "replenishment", "coordinate with", "ad hoc tasks", "sales team", "forecast", "planning"], "requirements": {"degrees": ["hkdse"], "majors": ["mathematics"], "languages": ["cantonese", "putonghua", "english"], "language_level": ["fluent"], "hard_skills": ["excel", "pivot table", "microsoft word"], "soft_skills": ["self-motivated", "good team player", "work independently", "advanced", "sense of responsibility", "detail oriented", "interpersonal skills"], "languages_combined": [{"language": "cantonese", "language_level": ["fluent"]}, {"language": "putonghua", "language_level": ["fluent"]}, {"language": "english", "language_level": ["fluent"]}]}, "experience_required": {"duration": ["minimum 3 years"], "field": ["merchandising", "planning"]}}, {"job_id": "100003009017775", "location_code": "hk", "company": "KAS Pty Limited", "job_title": "Production Merchandiser - (Hardgoods)", "description": "Categories:\u00a0Xmas Trim & Wrap, Season Food, Confectionery\n\n\u00a0Responsibilities:\n\nTo provide a quality customer service to the buyer\nTo maintain relationship with supplier\nFollow up order and on time shipment of product\nMonitoring process at different stages of the critical path\nTesting of products to meet QA requirement\nFollow up the QA approval process including product function and safety\nCritical Path Management by DSS system\nMaintain a proper filing system to ensure visibility in all areas and allow other team members be able to handle current work immediately in your absence\nAd. hoc project as assigned by Management\n\nRequirements:\n\n4-5 years solid merchandising experience in\u00a0Hardgoods categories, preferably in buying office environment\nStrong negotiation and interpersonal skill to liaison\u00a0between buyers and\u00a0factories\nTertiary education or equivalent\nProven experience to be able to work with overseas buyers independently\nDemonstrate the ability to work under pressure\nExcellent communication skills both in English and Mandarin\nExcellent computer knowledge\nTravel is required\n\nAll information provided will be treated in strict confidence and used solely for recruitment purpose.", "employment_types": ["Full Time", "Permanent"], "selling_points": [], "locations": ["Cheung Sha Wan"], "categories": ["Merchandising & Purchasing", "Toy", "Sundries", "Others"], "post_time": "2022-01-04T01:58:01Z", "salary": {"currency": null, "max": null, "min": null, "period": "monthly", "term": null}, "salary_visible": false, "title_keywords": ["merchandiser"], "responsibilities": ["maintain", "monitoring", "customer service", "quality"], "requirements": {"degrees": [], "majors": [], "languages": ["english", "mandarin"], "language_level": ["excellent"], "hard_skills": [], "soft_skills": ["communication skills", "independently", "confidence", "negotiation", "interpersonal skill", "work under pressure"], "languages_combined": [{"language": "english", "language_level": ["excellent"]}, {"language": "mandarin", "language_level": ["excellent"]}]}, "experience_required": {"duration": ["4-5 years"], "field": ["merchandising"]}}, {"job_id": "100003009017776", "location_code": "hk", "company": "KAS Pty Limited", "job_title": "Assistant Merchandiser (Toys)", "description": "Responsibilities:\nAssist in merchandising activities including but not limited to:\n\nFollow up the sampling and shipment\nDaily communication with supplier and Mel team\nFollow up testing report\nUpdate the order processing system\nMonitor inspection process including inspection booking, samples and QC files\nFollow up packaging artwork (print proof)\nRequirements:\nForm 7 or above\nAt least 1-2 years working experience, preferably in a buying office environment\nWell organized, responsible, problem solving\nGood communication and interpersonal skills\nGood command of English and Mandarin\nCapability on priority setting\nWell-versed in MS office application\nOccasional travel to China is required\nAll information provided will be treated in strict confidence and used solely for recruitment purpose.", "employment_types": ["Full Time", "Permanent"], "selling_points": [], "locations": ["Cheung Sha Wan"], "categories": ["Merchandising & Purchasing", "Toy", "Others", "Procurement / Purchasing / Sourcing"], "post_time": "2022-01-04T01:58:01Z", "salary": {"currency": null, "max": null, "min": null, "period": "monthly", "term": null}, "salary_visible": false, "title_keywords": ["assistant merchandiser"], "responsibilities": ["merchandising", "monitor", "testing", "communication", "inspection", "booking", "order processing", "report"], "requirements": {"degrees": [], "majors": [], "languages": ["english", "mandarin"], "language_level": ["good command"], "hard_skills": ["problem solving", "ms office"], "soft_skills": ["confidence", "responsible", "well organized", "problem solving", "communication and interpersonal skills"], "languages_combined": [{"language": "english", "language_level": ["good command"]}, {"language": "mandarin", "language_level": ["good command"]}]}, "experience_required": {"duration": ["at least 1-2 years"], "field": []}}, {"job_id": "100003009014475", "location_code": "hk", "company": "Branford Limited", "job_title": "Shipping Clerk (13th month salary)", "description": "Shipping Clerk\n\nBranford Limited is an international children\u2019s toy company and we are currently looking for a talented and motivated Shipping Clerk to cope with the growth of the company.\n\nRequirements:\n\n\u00a0 \u00a0 \u00a0 \u00a0 F. 5 level / HKDSE (Grade 3+ in English or Mathematics) or above\n\u00a0\u00a0\u00a0\u00a0\u00a0\u00a0\u00a0 Minimum 3 years logistic experience\n\u00a0\u00a0\u00a0\u00a0\u00a0\u00a0\u00a0 Handle full set I/E documents and experience in ERP system is an asset\n\u00a0\u00a0\u00a0\u00a0\u00a0\u00a0\u00a0 Proficient in Microsoft Word and Excel\n\u00a0\u00a0\u00a0\u00a0\u00a0\u00a0\u00a0 Good command of English and fluent Putonghua as well as Cantonese\n\u00a0\u00a0\u00a0\u00a0\u00a0\u00a0\u00a0 Self-motivated, able to work independently and follow through on required tasks\n\u00a0\u00a0\u00a0\u00a0\u00a0\u00a0\u00a0 Good team player and good interpersonal skills\n\u00a0\u00a0\u00a0\u00a0\u00a0\u00a0\u00a0 Strong sense of responsibility\n\n\u00a0Responsibilities:\n\n\u00a0 \u00a0 \u00a0 \u00a0 Work closely with internal merchandising team and suppliers\n\u00a0\u00a0\u00a0\u00a0\u00a0\u00a0\u00a0 Coordinate and follow up delivery arrangement with forwarders and suppliers\n\u00a0\u00a0\u00a0\u00a0\u00a0\u00a0\u00a0 Handle booking, export documents and customer payment\n\u00a0\u00a0\u00a0\u00a0\u00a0\u00a0\u00a0 Assist in general office work and ad hoc tasks as required.\n\n\u00a0Benefits:\n\n\u00a0 \u00a0 \u00a0 \u00a05-days work week\n\u00a0 \u00a0 \u00a0 13th month salary\n\u00a0 \u00a0 \u00a0 Medical and detail coverage\n\nPlease feel free to visit our current Web Sites: ogdolls.com, myglittergirls.com, woodzeez.com, terrauniverse.com, mybtoys.com and battatco.com.\n\nPlease apply with full resume and expected salary though applies now.\n\nPersonal data collected will be used for recruitment purpose only.", "employment_types": ["Permanent"], "selling_points": [], "locations": ["Tsim Sha Tsui"], "categories": ["Merchandising & Purchasing", "Electronics", "Toy", "Others", "Trading"], "post_time": "2022-01-03T03:29:05Z", "salary": {"currency": null, "max": null, "min": null, "period": "monthly", "term": null}, "salary_visible": false, "title_keywords": ["shipping clerk"], "responsibilities": ["ad hoc tasks", "merchandising", "coordinate", "payment", "booking"], "requirements": {"degrees": ["hkdse"], "majors": ["mathematics"], "languages": ["cantonese", "putonghua", "english"], "language_level": ["good command", "fluent"], "hard_skills": ["excel", "erp system", "microsoft word"], "soft_skills": ["good team player", "self-motivated", "work independently", "sense of responsibility", "interpersonal skills"], "languages_combined": [{"language": "cantonese", "language_level": ["good command"]}, {"language": "putonghua", "language_level": ["good command"]}, {"language": "english", "language_level": ["fluent", "good command"]}]}, "experience_required": {"duration": ["minimum 3 years"], "field": ["erp system"]}}, {"job_id": "100003009011334", "location_code": "hk", "company": "Q P Group Holdings Limited", "job_title": "Senior Procurement Manager/ Director", "description": "Job functions:\nLead and oversee regional sourcing teams, manage the performance and compliance to policy and procedure;\nManage sourcing team to well collaborate with counterpart across the Group to identify the material, component and product needs;\nFormulate and responsible for departmental goals and strategies that align with company goads\nMonitor the vendor\u2019s performance to ensure the fulfillment of safety, \u00a0quality, pricing, delivery schedules, commercial terms and other requirements \u00a0\nDevelop and maintain the long term partnership with vendors, manage vendor selection and evaluation, and improvement initiatives;\nFormulate and execute the contract management and policy, and effective negotiate prices\nAnalysis and share with the management in regular basis the updated market information and price trend;\nDevelop and drive the strategic programs such as cost saving initiative, continuous improvement projects and monitor the execution and goals achievements;\nProvide quick response and implement effective plans and solutions to meet the emerging needs\nNetworking with target suppliers, and industry practitioners\nPerform ad hoc assignment by management\nRequirements:\nDiploma or above in Procurement, Purchasing, Materials Management, Supply Chain, or related disciplines;\nOver 8 years strategic procurement and sourcing, development of material supplier / sub-contractor, and project management experience preferably gained from multinational or sizeable manufacturing companies with minimum 5 years in managerial position;\nSolid experience in material sourcing of Printing / Paper Products / Toys & Gifts Industry would be an advantage;\nGlobal sourcing experience and strong experience in managing China vendors\nStrong people management skill and influencing skill;\nExcellent analytical, communication & negotiation skills;\nResult-oriented, team player\nGood command of written and spoken English, and Chinese/Mandarin;\nTravel to Asian countries is required\nCandidates with more experience will be considered as\u00a0Procurement\u00a0Director\nApplication:\nPlease send your CV, existing salary & expected salary in WORD format to\u00a0ghr\u00a0 @ qpp.com\nAll personal information collected will be kept for employment related purposes only.", "employment_types": ["Full Time", "Permanent"], "selling_points": ["Lead and oversee regional sourcing teams", "Solid experience in material sourcing of Printing", "Monitor the vendor\u2019s performance"], "locations": ["Not Specified"], "categories": ["Transportation & Logistics", "Supply Chain", "Merchandising & Purchasing", "Toy", "Procurement / Purchasing / Sourcing"], "post_time": "2021-12-31T16:58:02Z", "salary": {"currency": null, "max": null, "min": null, "period": "monthly", "term": null}, "salary_visible": false, "title_keywords": ["manager", "director"], "responsibilities": ["collaborate with", "market information", "schedules", "fulfillment", "quality", "communication", "maintain", "evaluation", "plans", "continuous improvement projects", "ad hoc assignment", "compliance", "monitor", "teams", "develop", "management", "cost", "analysis", "contract management", "project management"], "requirements": {"degrees": ["diploma or above"], "majors": ["related disciplines"], "languages": ["english", "chinese", "mandarin"], "language_level": ["good command"], "hard_skills": ["project management", "analysis", "vendor", "word"], "soft_skills": ["result-oriented", "responsible", "communication", "project management", "negotiation skills", "team player", "initiative"], "languages_combined": [{"language": "english", "language_level": ["good command"]}, {"language": "chinese", "language_level": ["good command"]}, {"language": "mandarin", "language_level": ["good command"]}]}, "experience_required": {"duration": ["8 years", "minimum 5 years"], "field": ["toys", "managerial", "manufacturing", "development", "project management", "procurement"]}}, {"job_id": "100003009012566", "location_code": "hk", "company": "Start Way Limited", "job_title": "Assistant Merchandiser / Merchandiser (5 Days Work)", "description": "Job Highlights\n\n\nA Trading company in Kwun Tong\n5 days work\nDouble pay\nLunch offered\nBirthday Leave\n\nJob Description\nResponsibilities\n\n\n-\u00a0\u00a0Follow up seasonal decoration, home decoration and toys products,\n-\u00a0 Prepare quotations, samples\u00a0and orders\u00a0follow up\n-\u00a0 Product development\n-\u00a0 Assist in daily operational activities and provide supports to the merchandising\u00a0team members\n-\u00a0 Routine communication with factories and customers\n-\u00a0 Product sourcing in China or Far East countries\u00a0\n\nRequirements\n\n-\u00a0 Diploma or above\n-\u00a0 Minimum 1\u00a0year related working experience\n-\u00a0 Good in English and Mandarin\n-\u00a0 Proficiency in Illustrator\u00a0or\u00a0Photoshop\u00a0will be an advantage\n-\u00a0 Able to handle multi-tasks and cope with deadlines\n-\u00a0 Strong sense of responsibility, good communication skills and team work\u00a0\n\nInterested parties, please send full resume with current and expected salary via clicking \u2018Apply Now\u2019 for an interview.\n", "employment_types": ["Full Time", "Permanent"], "selling_points": [], "locations": ["Kwun Tong"], "categories": ["Merchandising & Purchasing", "Toy", "Sundries", "Manufacturing", "Printing"], "post_time": "2022-01-01T03:25:46Z", "salary": {"currency": null, "max": null, "min": null, "period": "monthly", "term": null}, "salary_visible": false, "title_keywords": ["merchandiser", "assistant merchandiser"], "responsibilities": ["routine communication", "merchandising"], "requirements": {"degrees": ["diploma or above"], "majors": [], "languages": ["english", "mandarin"], "language_level": ["good"], "hard_skills": ["illustrator", "photoshop"], "soft_skills": ["communication skills", "multi-tasks", "sense of responsibility"], "languages_combined": [{"language": "english", "language_level": ["good"]}, {"language": "mandarin", "language_level": ["good"]}]}, "experience_required": {"duration": ["minimum 1 year"], "field": ["related"]}}, {"job_id": "100003009006998", "location_code": "hk", "company": "Yee Fung International Limited", "job_title": "Production Manager", "description": "Job\u2019s responsibilities:\nHands-on experience in overseeing and good production management to secure quality and delivery meeting customers' requirements\nLead and manage production planning team and all production workshops\nLean Production improvement and management\nProduction cost budget management\nFacility, Machine, Equipment, Mold and Tools maintenance management\nProblem solving, highly responsible and have good visions\nProduct quality standards and scarp improvement\nEnsure efficient collaboration and co-ordination between relevant departments including procurement, distribution and management\nRequirements:\nMinimum 8 years of experience in toys or shoes manufacturing company\nHigher Diploma Holder or above\nStrong production & material planning plus good analytical mind\nGood organization, planning and leadership skill\nGood command of English, Cantonese and Putonghua\nHands-on PC knowledge in MS Office (Proficiency in MS Excel (pivot table)\nERP / MRP application and evaluation skill is MUST!\nBasic knowledge in molding, sewing, painting and assemble production\nStationed in Dongguan Area\nImmediate availability is an advantage\nPackage Offer:\n6 Working Days per week (Alternative Sat off\uff09\nLabor Holiday\nTravel insurance\nMedical coverage\nMPF\nInterested parties please submit CV and expected salary by email via \"Apply Now\"\n(Personal data collected will be used for recruitment only.)", "employment_types": ["Full Time", "Permanent"], "selling_points": [], "locations": ["Not Specified"], "categories": ["Manufacturing", "Production Planning / Control", "Merchandising & Purchasing", "Toy", "Procurement / Purchasing / Sourcing"], "post_time": "2021-12-29T16:10:56Z", "salary": {"currency": null, "max": null, "min": null, "period": "monthly", "term": null}, "salary_visible": false, "title_keywords": ["production manager"], "responsibilities": ["cost", "management", "maintenance", "budget", "quality", "production planning"], "requirements": {"degrees": ["higher diploma holder"], "majors": [], "languages": ["cantonese", "putonghua", "english"], "language_level": ["good command"], "hard_skills": ["plus", "basic", "pivot table", "erp", "ms excel", "pc knowledge", "ms office"], "soft_skills": ["leadership skill", "analytical mind", "hands-on"], "languages_combined": [{"language": "cantonese", "language_level": ["good command"]}, {"language": "putonghua", "language_level": ["good command"]}, {"language": "english", "language_level": ["good command"]}]}, "experience_required": {"duration": ["minimum 8 years"], "field": ["toys", "manufacturing"]}}, {"job_id": "100003009005354", "location_code": "hk", "company": "Hillman Ross", "job_title": "Assistant Sourcing Manager (Toys)", "description": "Our client is a European company and they are looking for an Assistant Sourcing Manager to take care of toys category. This person will be an individual contributor, reporting to the Sourcing Manager.\n\nWe are now seeking for Assistant Sourcing Manager (Toys)\n\nRESPONSIBILITIES\n\nWell organization skills of dealing with complex product categories, manage high sku and multi-countries production base.\nDevelop product and vendor strategies to drive for continue business growth.\nWork with the Sourcing Managers to evaluate the performance of factories and assess the business risk that support clients' business needs.\nSupervise and guide a team of merchandisers and coordinate with cross functional teams to achieve excellent KPI to meet client's expectation.\nStrong and in-depth negotiation skills to drive cost saving and costing margin for clients' continue business growth.\nFull ownership of the whole supply chain from factory sourcing, development till shipment with in-depth technical knowledge, proactive on problem precaution & strong decision maker.\nManage the team to ensure they are up to the company standard\nMotivate the team by sharing knowledge and expertise, ensuring attention to detail and seeking continuous improvements\nDevelop a close relationship with existing suppliers and develop new suppliers through personal connections, trade fairs and sourcing trips\nProduct, payment and business term negotiations with suppliers.\n\nTo succeed in this key role, you will have at least 10 years experience in sourcing with at least 6 years in managerial capacity.\n\nQUALIFICATIONS:\n\nTertiary educated\nSelf-motivated and have strong sense of responsibility.\nStrong people and process management skills\nStrong analytical and interpersonal skills\nIndependent and excellent time management in meeting deadline.\nStrong communication skills and fluent in English, Mandarin and Cantonese\nExperience in handling plush is a Must\nExperience working in European market is a MUST\n\nAPPLY FOR THIS JOB\n\nInterested candidate please CLICK apply button to apply online or send your resume in MS word format to Hillman Ross Recruitment Solution Professional\n\nPlease note that only shortlisted candidate will be notified. All information will be treated in strict confidence and solely used for recruitment purposes.", "employment_types": ["Full Time", "Permanent"], "selling_points": ["European company", "Toys category", "Experience in handling plush is a Must"], "locations": ["Not Specified"], "categories": ["Merchandising & Purchasing", "Toy", "Others", "Procurement / Purchasing / Sourcing"], "post_time": "2021-12-29T03:47:03Z", "salary": {"currency": null, "max": null, "min": null, "period": "monthly", "term": null}, "salary_visible": false, "title_keywords": ["assistant", "sourcing manager"], "responsibilities": ["product categories", "reporting", "cost", "continuous improvements", "management", "coordinate with", "teams", "develop", "evaluate", "communication", "payment", "support clients", "recruitment"], "requirements": {"degrees": [], "majors": [], "languages": ["cantonese", "english", "mandarin"], "language_level": ["fluent"], "hard_skills": ["vendor", "ms word"], "soft_skills": ["communication skills", "self-motivated", "confidence", "independent", "sense of responsibility", "time management", "negotiation skills", "interpersonal skills", "attention to detail", "organization skills", "proactive"], "languages_combined": [{"language": "cantonese", "language_level": ["fluent"]}, {"language": "english", "language_level": ["fluent"]}, {"language": "mandarin", "language_level": ["fluent"]}]}, "experience_required": {"duration": ["at least 10 years", "at least 6 years"], "field": ["managerial"]}}, {"job_id": "100003009003992", "location_code": "hk", "company": "Jaz Toys HK Limited", "job_title": "MANAGER OF ASIA VENDOR MANAGEMENT", "description": "RESPONSBILITY:\n\n-\u00a0\u00a0\u00a0\u00a0\u00a0\u00a0\u00a0\u00a0\u00a0 Direct report to Head of Asia Vendor Management Team\n\n-\u00a0\u00a0\u00a0\u00a0\u00a0\u00a0\u00a0\u00a0\u00a0 Manage a sub-team to monitor Open Order production status; timely alert the team of outstanding issue and work on solutions to strike the original shipping schedule\n\n-\u00a0\u00a0\u00a0\u00a0\u00a0\u00a0\u00a0\u00a0\u00a0 Work closely with Order Management, Planning and Procurement teams on order issues, forecasting activities, manage and identify capacity and key material needs in coming month, quarter and year.\n\n-\u00a0\u00a0\u00a0\u00a0\u00a0\u00a0\u00a0\u00a0\u00a0 Monitor key material ordering and arrival status to assure material availability meets the scheduled time frame\n\n-\u00a0\u00a0\u00a0\u00a0\u00a0\u00a0\u00a0\u00a0\u00a0 Work closely with internal teams on vendor issues and ensure full complies with Jaz requirements on quality procedure and standard, and adequate capacity and capabilities.\n\n-\u00a0\u00a0\u00a0\u00a0\u00a0\u00a0\u00a0\u00a0\u00a0 Refine and establish tools and methodologies to improve vendor management effectiveness and supplier performance.\n\n-\u00a0\u00a0\u00a0\u00a0\u00a0\u00a0\u00a0\u00a0\u00a0 Manage Vendor relationship and oversight vendor related activities, reports to managements on outstanding issues.\n\nREQUIREMENTS:\n\n-\u00a0\u00a0\u00a0\u00a0\u00a0\u00a0\u00a0\u00a0\u00a0 Bachelor degree holder or above, preferably in Supply Chain management, Industrial Engineering or relevant discipline\n\n-\u00a0\u00a0\u00a0\u00a0\u00a0\u00a0\u00a0\u00a0\u00a0 Minimum 8 years of experience in Demand Planning/ Supply Planning/ Inventory Planning, preferrable in toys or FMCG industries\n\n-\u00a0\u00a0\u00a0\u00a0\u00a0\u00a0\u00a0\u00a0\u00a0 Detail oriented and sensitive to figures, well organized and able to work independently\n\n-\u00a0\u00a0\u00a0\u00a0\u00a0\u00a0\u00a0\u00a0\u00a0 Strong analytical, root cause analysis and problem-solving skills\n\n-\u00a0\u00a0\u00a0\u00a0\u00a0\u00a0\u00a0\u00a0\u00a0 Self-motivated with positive attitude and mindset, willing to confront challenge.\n\n-\u00a0\u00a0\u00a0\u00a0\u00a0\u00a0\u00a0\u00a0\u00a0 High adaptability and ability to work in cross functional environment\n\n-\u00a0\u00a0\u00a0\u00a0\u00a0\u00a0\u00a0\u00a0\u00a0 Familiar with MS Excel and experience in Demand/ Supply planning system is an advantage\n\n-\u00a0\u00a0\u00a0\u00a0\u00a0\u00a0\u00a0\u00a0\u00a0 Proficient in spoken and written Chinese (Cantonese & Mandarin) and English\n\n-\u00a0\u00a0\u00a0\u00a0\u00a0\u00a0\u00a0\u00a0\u00a0 China based in DG area and Frequent travel are required.", "employment_types": ["Full Time"], "selling_points": ["Bachelor degree holder (Supply Chain management)", "Industrial Engineering or relevant discipline", "Demand/Supply/Inventory Planning in toys industry"], "locations": ["Chai Wan"], "categories": ["Merchandising & Purchasing", "Toy"], "post_time": "2021-12-28T14:42:12Z", "salary": {"currency": null, "max": null, "min": null, "period": "monthly", "term": null}, "salary_visible": false, "title_keywords": ["manager"], "responsibilities": ["shipping schedule", "management team", "order management", "management", "monitor", "teams", "quality", "planning", "forecasting activities", "reports", "vendor issues", "report"], "requirements": {"degrees": ["bachelor degree holder"], "majors": ["engineering"], "languages": ["cantonese", "english", "chinese", "mandarin"], "language_level": ["proficient"], "hard_skills": ["supply planning", "demand planning", "analysis", "ms excel", "problem-solving skills"], "soft_skills": ["work independently", "self-motivated", "detail oriented", "sensitive to figures", "well organized", "positive attitude", "adaptability", "problem-solving skills"], "languages_combined": [{"language": "cantonese", "language_level": ["proficient"]}, {"language": "english", "language_level": ["proficient"]}, {"language": "chinese", "language_level": ["proficient"]}, {"language": "mandarin", "language_level": ["proficient"]}]}, "experience_required": {"duration": ["minimum 8 years"], "field": ["toys", "fmcg", "planning"]}}, {"job_id": "100003009003985", "location_code": "hk", "company": "Jaz Toys HK Limited", "job_title": "Order Management Analyst", "description": "Responsibilities & Duties:\n\n-\u00a0\u00a0\u00a0\u00a0\u00a0\u00a0\u00a0\u00a0\u00a0 Direct report to Manager of Order Management\n\n-\u00a0\u00a0\u00a0\u00a0\u00a0\u00a0\u00a0\u00a0\u00a0 Work closely with US Sales/Procurement office for order fulfillment (from factory PO release to Shipment release)\n\n-\u00a0\u00a0\u00a0\u00a0\u00a0\u00a0\u00a0\u00a0\u00a0 Handle daily operation issues & seek direction from Order mgmt. Team, compile reports to monitor the open orders to ensure factories ship all customer order in compliance with Jaz requirements.\n\n-\u00a0\u00a0\u00a0\u00a0\u00a0\u00a0\u00a0\u00a0\u00a0 Communicate with customer\u2019s local office to process order inquiries and work with Logistics on shipment issues\n\n-\u00a0\u00a0\u00a0\u00a0\u00a0\u00a0\u00a0\u00a0\u00a0 Coordinate with Vendor Management team to resolve potential shipment issues to ensure on-time shipment.\n\n-\u00a0\u00a0\u00a0\u00a0\u00a0\u00a0\u00a0\u00a0\u00a0 Manage Factory PO commitment to meet customer request\n\n-\u00a0\u00a0\u00a0\u00a0\u00a0\u00a0\u00a0\u00a0\u00a0 Assure MOL system data integrity\n\n-\u00a0\u00a0\u00a0\u00a0\u00a0\u00a0\u00a0\u00a0\u00a0 Review Open Order Report for any outstanding issues and resolve with vendor and internal teams, alert if any potential order slippage and initiate red flag for the team to work on contingency plan.\n\n-\u00a0\u00a0\u00a0\u00a0\u00a0\u00a0\u00a0\u00a0\u00a0 Assist manager in developing and improving PO process\n\n-\u00a0\u00a0\u00a0\u00a0\u00a0\u00a0\u00a0\u00a0\u00a0 Monitor Global order and FOB order status, identify the possible shipment slippage and escalate to the Manager for direction\n\n\u00a0\nREQUIREMENTS:\n\n-\u00a0\u00a0\u00a0\u00a0\u00a0\u00a0\u00a0\u00a0\u00a0 3-5 years\u2019 experience in Order Administration/Customer Service, preferably from Toys industry\n\n-\u00a0\u00a0\u00a0\u00a0\u00a0\u00a0\u00a0\u00a0\u00a0 Excellent skills in Microsoft Excel, Word, Power point, and Outlook\n\n-\u00a0\u00a0\u00a0\u00a0\u00a0\u00a0\u00a0\u00a0\u00a0 Good communication skills.\u00a0 Proficient in spoken and written Chinese and English\n\n-\u00a0\u00a0\u00a0\u00a0\u00a0\u00a0\u00a0\u00a0\u00a0 Detail minded is preferred", "employment_types": ["Full Time"], "selling_points": ["3-5 years exp.in Order Administration/Customer Ser", "Excellent skills in MS Excel, Word, Power point", "Proficient in spoken and written Chinese & English"], "locations": ["Chai Wan"], "categories": ["Merchandising & Purchasing", "Toy"], "post_time": "2021-12-28T14:27:44Z", "salary": {"currency": null, "max": null, "min": null, "period": "monthly", "term": null}, "salary_visible": false, "title_keywords": ["analyst"], "responsibilities": ["communicate with", "management team", "order management", "compile reports", "compliance", "daily operation", "monitor", "coordinate with", "system data", "review", "teams", "developing", "order fulfillment", "logistics", "plan", "report"], "requirements": {"degrees": [], "majors": [], "languages": ["english", "chinese"], "language_level": ["proficient"], "hard_skills": ["power point", "outlook", "word", "microsoft excel"], "soft_skills": ["communication skills", "customer service"], "languages_combined": [{"language": "english", "language_level": ["proficient"]}, {"language": "chinese", "language_level": ["proficient"]}]}, "experience_required": {"duration": ["3-5 years"], "field": ["toys", "customer service", "administration"]}}, {"job_id": "100003009018557", "location_code": "hk", "company": "Sentinel International Co. Limited", "job_title": "Merchandiser / \u65e5\u8a9e\u8ddf\u55ae (Japanese Toys)", "description": "\u00a0Responsibilities\n\nHandle order processing\nAssist in sample handling, order and liaison with Japanese clients as required\nCommunicate and coordinate with vendors, suppliers, Japanese customers, internal parties to ensure the production and shipment are on right track and ship on time.\nExperienced in handling enquiries, orders and projects, to ensure product quality and delivery meeting standards\n\nRequirements\n\nForm 5 / DSE or above\nGood spoken and written Japanese\nGood command of spoken and written English, Cantonese and Mandarin\n1 - 2 years\u2019 solid experience in sundries/toys industry.\nSelf-motivated, with strong sense of commitment and able to work under pressure & overtime\nWell organized, with good interpersonal & communication skill\nTravel to China is required.\n\n* We offer\u00a0competitive package including medical insurance, bank holiday and bonus\u00a0to right candidates. Interested parties please\u00a0apply with full resume and expected salary\u00a0by clicking \u201cAPPLY NOW\u201d or email (hr @ sentinel-toys.com) to us.\n\n* All applications and data collected will be treated in strict confidence and used exclusively for recruitment purposes only .", "employment_types": ["Full Time"], "selling_points": ["Competitive Salary and Good Career Path", "bonus, medical insurance, banking holiday", "Japanese Speaking request"], "locations": ["Tsuen Wan Area"], "categories": ["Merchandising & Purchasing", "Home Appliances", "Toy", "Sundries"], "post_time": "2022-01-04T03:55:09Z", "salary": {"currency": null, "max": null, "min": null, "period": "monthly", "term": null}, "salary_visible": false, "title_keywords": ["merchandiser"], "responsibilities": ["internal parties", "coordinate with", "order processing", "quality"], "requirements": {"degrees": ["form 5", "dse"], "majors": [], "languages": ["cantonese", "japanese", "english", "mandarin"], "language_level": ["good command", "good"], "hard_skills": [], "soft_skills": ["self-motivated", "communication skill", "well organized", "interpersonal", "work under pressure"], "languages_combined": [{"language": "cantonese", "language_level": ["good command"]}, {"language": "japanese", "language_level": ["good"]}, {"language": "english", "language_level": ["good command"]}, {"language": "mandarin", "language_level": ["good command"]}]}, "experience_required": {"duration": ["1 - 2 years"], "field": ["toys"]}}, {"job_id": "100003009004134", "location_code": "hk", "company": "TRI-Come Recruitment Search", "job_title": "Senior Merchandiser/ Merchandiser (Gift & Premium/ Toys/ Beauty items / Sundries )", "description": "\u00a0\u00a0\u00a0 \u00a0 \u00a0 \u00a0 Responsibilities :\n\nStrong communication and negotiation skill to work with both suppliers and buyers\nWork with vendors and material suppliers to source and develop appropriate materials and components.\nCommunicate with appropriate clients, product development team members, supply chain, factory product development staff, raw material vendors and manufacturers to ensure products are developed in keeping with brief specs and goals.\nSupport the Technical and Merchandising team on development issues.\n\n\u00a0 \u00a0 \u00a0 \u00a0\u00a0 Requirements :\n\nAt least 3 to 5 years of related work experience in the\u00a0Gift & Premium/ Toys/ Beauty items/ Sundries\nStrong verbal and written communication skills with an advanced ability to communicate new ideas, concepts and functional expertise within product teams\nGood communication & negotiation skill\nFluency in both written and spoken Cantonese, English and Mandarin.\n\n\u00a0 \u00a0 \u00a0 \u00a0 \u00a0 \u00a0 \u00a0 \u00a0Interested parties please send your resume :\u00a0 \u00a0hr @ tri-come.com.hk\n", "employment_types": ["Full Time", "Permanent"], "selling_points": [], "locations": ["Yau Tsim Mong Area"], "categories": ["Merchandising & Purchasing", "Home Appliances", "Toy", "Sundries"], "post_time": "2021-12-29T01:22:17Z", "salary": {"currency": null, "max": null, "min": null, "period": "monthly", "term": null}, "salary_visible": false, "title_keywords": ["merchandiser", "senior merchandiser"], "responsibilities": ["communication", "merchandising", "communicate with", "develop"], "requirements": {"degrees": [], "majors": [], "languages": ["cantonese", "english", "mandarin"], "language_level": ["fluency"], "hard_skills": [], "soft_skills": ["communication", "communication skills", "advanced", "negotiation skill"], "languages_combined": [{"language": "cantonese", "language_level": ["fluency"]}, {"language": "english", "language_level": ["fluency"]}, {"language": "mandarin", "language_level": ["fluency"]}]}, "experience_required": {"duration": ["at least 3 to 5 years"], "field": ["related", "beauty", "toys"]}}, {"job_id": "100003009000054", "location_code": "hk", "company": "Q P Printing Ltd", "job_title": "Group Sourcing Manager", "description": "Job functions:\nLead and oversee regional sourcing teams, manage the performance and compliance to policy and procedure;\nManage sourcing team to well collaborate with counterpart across the Group to identify the material, component and product needs;\nFormulate and responsible for departmental goals and strategies that align with company goads\nMonitor the vendor\u2019s performance to ensure the fulfillment of safety, \u00a0quality, pricing, delivery schedules, commercial terms and other requirements \u00a0\nDevelop and maintain the long term partnership with vendors, manage vendor selection and evaluation, and improvement initiatives;\nFormulate and execute the contract management and policy, and effective negotiate prices\nAnalysis and share with the management in regular basis the updated market information and price trend;\nDevelop and drive the strategic programs such as cost saving initiative, continuous improvement projects and monitor the execution and goals achievements;\nProvide quick response and implement effective plans and solutions to meet the emerging needs\nNetworking with target suppliers, and industry practitioners\nPerform ad hoc assignment by management\nRequirements:\nDiploma or above in Procurement, Purchasing, Materials Management, Supply Chain, or related disciplines;\nOver 8 years strategic procurement and sourcing, development of material supplier / sub-contractor, and project management experience preferably gained from multinational or sizeable manufacturing companies with minimum 5 years in managerial position;\nSolid experience in material sourcing of Printing / Paper Products / Toys & Gifts Industry would be an advantage;\nGlobal sourcing experience and strong experience in managing China vendors\nStrong people management skill and influencing skill;\nExcellent analytical, communication & negotiation skills;\nResult-oriented, team player\nGood command of written and spoken English, and Chinese/Mandarin;\nTravel to Asian countries is required\nApplication:\nPlease send your CV, existing salary & expected salary in WORD format to ghr\u00a0 @ qpp.com\nAll personal information collected will be kept for employment related purposes only.", "employment_types": ["Full Time", "Permanent"], "selling_points": ["Lead and oversee regional sourcing teams", "Solid experience in material sourcing of Printing", "Monitor the vendor\u2019s performance"], "locations": ["Not Specified"], "categories": ["Transportation & Logistics", "Supply Chain", "Merchandising & Purchasing", "Toy", "Procurement / Purchasing / Sourcing"], "post_time": "2021-12-24T18:21:59Z", "salary": {"currency": null, "max": null, "min": null, "period": "monthly", "term": null}, "salary_visible": false, "title_keywords": ["sourcing manager"], "responsibilities": ["collaborate with", "market information", "schedules", "fulfillment", "quality", "communication", "maintain", "evaluation", "plans", "continuous improvement projects", "ad hoc assignment", "compliance", "monitor", "teams", "develop", "management", "cost", "analysis", "contract management", "project management"], "requirements": {"degrees": ["diploma or above"], "majors": ["related disciplines"], "languages": ["english", "chinese", "mandarin"], "language_level": ["good command"], "hard_skills": ["project management", "analysis", "vendor", "word"], "soft_skills": ["result-oriented", "responsible", "communication", "project management", "negotiation skills", "team player", "initiative"], "languages_combined": [{"language": "english", "language_level": ["good command"]}, {"language": "chinese", "language_level": ["good command"]}, {"language": "mandarin", "language_level": ["good command"]}]}, "experience_required": {"duration": ["8 years", "minimum 5 years"], "field": ["toys", "managerial", "manufacturing", "development", "project management", "procurement"]}}, {"job_id": "100003008999465", "location_code": "hk", "company": "IMC Toys Hong Kong Limited", "job_title": "OPERATIONS COORDINATOR (Purchasing)", "description": "Job profile: Reporting to the Operations Manager, you will support the Operations Department in the order processing and order co-ordination, performing routine purchase, arrangement of samples, data entries and reporting.\nRequirements:\nForm 6 or above.\nAt least 1 year of relevant experience in purchasing, in toys field will be a plus.\nSolid knowledge on MS Office (Word, Excel), Outlook and PC tools.\nExperienced user of Manufacturing software / ERP systems (SAP).\nFluent in Cantonese, English & Mandarin.\nStrong sense of responsibility, well organized, multi-task oriented, hard working, and willing to learn.\nExtremely self-motivated.\nSelected candidates will be invited to join our dynamic team (office in TST East), and will be offered an attractive package, including:\nCompetitive salary (conditional year end one month salary & conditional performance bonus).\n5 days work (from 9:30am to 6:30pm).\n15 days annual leave (+1 additional day for each 3-year period max 3 days).\u00a0\nGroup medical and life insurance plan after 6\u00a0months period.\nInterested parties\u00a0please send full resume, and cover letter (specifying availability and expected salary) by clicking \"APPLY NOW\". Data collected will be used for recruitment purposes only.\u00a0 Data collected will be used for recruitment purposes only.", "employment_types": ["Full Time", "Permanent"], "selling_points": [], "locations": ["Tsim Sha Tsui"], "categories": ["Merchandising & Purchasing", "Toy", "Procurement / Purchasing / Sourcing"], "post_time": "2021-12-24T07:19:58Z", "salary": {"currency": null, "max": null, "min": null, "period": "monthly", "term": null}, "salary_visible": false, "title_keywords": ["operations", "coordinator"], "responsibilities": ["reporting", "software", "data", "operations", "systems", "purchase", "order processing", "plan", "insurance"], "requirements": {"degrees": [], "majors": [], "languages": ["cantonese", "english", "mandarin"], "language_level": ["fluent"], "hard_skills": ["excel", "plus", "erp systems", "max", "sap", "word", "dynamic", "outlook", "order processing", "pc", "ms office"], "soft_skills": ["self-motivated", "multi-task oriented", "sense of responsibility", "hard working", "willing to learn", "well organized", "dynamic"], "languages_combined": [{"language": "cantonese", "language_level": ["fluent"]}, {"language": "english", "language_level": ["fluent"]}, {"language": "mandarin", "language_level": ["fluent"]}]}, "experience_required": {"duration": ["at least 1 year"], "field": ["purchasing", "relevant experience", "toys"]}}, {"job_id": "100003008994187", "location_code": "hk", "company": "HobbyDigi Limited", "job_title": "Merchandiser | Merchandising Officer (Toys - Retail)", "description": "Job Duties:\n\nAssist in purchase coordination, prepare business analysis reports\nMonitor inventory levels to support overall retail sales plans and merchandising strategies\nDevelop and maintain good long-term relationships with brands / suppliers to optimize business opportunities\nMonitor vendors\u2019 performance and develop new vendors\nRequirements:\n\nKnowledge and understanding of toys and hobby collectibles retail market\nHigher Diploma or above, preferably with 1+ years experience in digital merchandising in domestic toys field. Experience in E-commerce is a plus\nStrong consumer market sense and awareness\nStrong analytical ability with good negotiation and communication skills\nProactive, detail-minded and able to work independently\nProficiency in Microsoft applications, particularly in excel applications\nCandidates with less experience may be considered as Assistant Officer", "employment_types": ["Full Time"], "selling_points": ["Young & Energetic Team Culture", "Sensitive to toys and hobby retail market", "Flat Company Structure"], "locations": ["Lai Chi Kok"], "categories": ["Merchandising & Purchasing", "Toy"], "post_time": "2021-12-22T12:10:04Z", "salary": {"currency": null, "max": null, "min": null, "period": "monthly", "term": null}, "salary_visible": false, "title_keywords": ["merchandiser", "officer", "merchandising"], "responsibilities": ["inventory", "business opportunities", "monitor", "merchandising", "develop", "business analysis reports", "purchase", "maintain", "sales plans", "coordination"], "requirements": {"degrees": ["higher diploma or above"], "majors": [], "languages": [], "language_level": [], "hard_skills": ["excel", "plus", "microsoft applications", "e-commerce"], "soft_skills": ["detail-minded", "communication skills", "work independently", "negotiation", "proactive"], "languages_combined": []}, "experience_required": {"duration": ["1+ years"], "field": ["toys", "digital", "merchandising", "e-commerce"]}}, {"job_id": "100003008938035", "location_code": "hk", "company": "AXA China Region Insurance Company Limited", "job_title": "Business Development Manager (HK or China Division)", "description": "Distinguish Yourself From Others\n\nWe are committed to investing in Hong Kong and, are now building a new distribution channel to market our full range of professional financial services in the territory. To cope with our business plan, we are going to recruit several professional Financial Planning Executives to strengthen our base.\n\nOur edge:\n\nStands out from the market, we built upon a fair and efficient agency management system that enables successful candidates to develop and fast track their career to the unlimited height.\n\n\n\nOur offer:\n\nBasic allowance 25K-60K, Commissions and Bonus schemes\nMedical and Life Insurance, Overseas Travel Rewards, MPF and ORSO etc\nComprehensive and Professional Training Programs\nTransparent and prosperous Career Path\nOn-going Company sponsored marketing initiatives to support Business Growth\n\n\n\nCore Responsibilities\n\nManage Corporate Business Account\nProfessional Financial Services Provision to Clients, including Wealth Management & Portfolio Advices, Investment Planning, Retirement Planning, Risk Management Planning, etc.\nDevelop China market, provide offshore wealth management services for Putonghua speaking clients\nClients base provided\nMonitor the client financial status and propose tailor-made solution to satisfy client needs\nLearn Recruiting & Managing Team\nRecruit HIGH Potential financial planners & build your OWN Professional TEAM\n\n\n\nOur requirements:\n\nHong Kong permanent residents only\nDegree holder & above\n5 years working experience is required\nAggressive, Outgoing and Work Independently\nFluent in Cantonese is a must, Mandarin is advance\nExperience of Business Development in China will be an advantage\n\n\n\nWe offer 5-day working week, excellent career prospects and attractive remuneration package to the right candidates. Interested candidates please send your details with expected salary by clicking 'Apply Now'.\n\nIf you have any queries on this position, please feel free to contact us through phone 2893 0612 or whatsapp 6128 6989. The information provided by applicants will be treated in strict confidence and used solely for recruitment purpose. All applicants' information will be destroyed after 12 months", "employment_types": ["Full Time", "Permanent"], "selling_points": ["Manage Corporate Business Account", "Professional Financial Services Provision", "5 years working experience is required"], "locations": ["Kwun Tong"], "categories": ["Merchandising & Purchasing", "Woven / Knit", "Textiles", "Toy"], "post_time": "2021-12-25T20:27:02Z", "salary": {"currency": null, "max": null, "min": null, "period": "monthly", "term": null}, "salary_visible": false, "title_keywords": ["business development manager"], "responsibilities": ["develop", "management", "monitor", "planning"], "requirements": {"degrees": ["degree holder"], "majors": [], "languages": ["cantonese", "mandarin"], "language_level": ["fluent"], "hard_skills": [], "soft_skills": ["outgoing", "work independently"], "languages_combined": [{"language": "cantonese", "language_level": ["fluent"]}, {"language": "mandarin", "language_level": []}]}, "experience_required": {"duration": ["5 years"], "field": ["business development"]}}, {"job_id": "100003008990125", "location_code": "hk", "company": "Petsource Asia Limited", "job_title": "Merchandiser - Pets", "description": "Petsource Asia Limited is a fast growing startup aiming to bridge the needs from our customers with our manufacturing partners across Asia. You will expect to have an opened and enjoyable working environment with opportunity to learn and stretch your talent. We welcome you to be part of the journey to build and share the success together.\n\n\nJob Duties:\nResponsible for sourcing, merchandising, sampling, quality, price comparison, price negotiation, shipment coordination, factory evaluation etc.\nResponsible for project execution with milestone control and good time management\nKeep abreast of market trend\nCommunicate with customers to clarify inquiries and specifications\nSupply chain management including supplier search, screen and identify potential supplier. Monitor suppliers\u2019 performance\nOrganize and accompany buying/sourcing trips with customers.\nPerform other ad hoc duties.\u00a0\nKey Requirements:\nDiploma or above with 3 years above independent product sourcing and merchandising experience in trading company or buying office\nExperience in handling pets/toys/clothing products is preferred\nStrong negotiation, presentation, and problem-solving skills\nGood time management and project management skills, can work on a project independently\nSound PC knowledge including MS office\nGood product sourcing knowledge and bargaining technique.\nGood network with factories and suppliers in HK & Mainland China.\nFluency in both written and spoken Cantonese, English and Mandarin.\nHard working, Responsible, detail-oriented, flexible and willing to learn\nWe offer competitive remuneration package including 5 days work week, 13th month salary, discretionary bonus, birthday leave, medical scheme, etc. Interested parties please send your application and resume with availability and expected salary for our review. All personal data collected will be kept in strict confidence and only used for recruitment purpose.", "employment_types": ["Full Time", "Permanent"], "selling_points": [], "locations": ["Ngau Tau Kok"], "categories": ["Merchandising & Purchasing", "Textiles", "Toy", "Others"], "post_time": "2021-12-21T07:39:04Z", "salary": {"currency": null, "max": null, "min": null, "period": "monthly", "term": null}, "salary_visible": false, "title_keywords": ["merchandiser"], "responsibilities": ["communicate with", "ad hoc duties", "price negotiation", "control", "management", "quality", "merchandising", "monitor", "specifications", "coordination", "evaluation"], "requirements": {"degrees": ["diploma or above"], "majors": [], "languages": ["cantonese", "english", "mandarin"], "language_level": ["fluency"], "hard_skills": ["problem-solving skills", "project management", "pc knowledge", "ms office"], "soft_skills": ["flexible", "independently", "independent", "negotiation", "responsible", "project management skills", "hard working", "willing to learn", "detail-oriented", "problem-solving skills", "time management", "presentation"], "languages_combined": [{"language": "cantonese", "language_level": ["fluency"]}, {"language": "english", "language_level": ["fluency"]}, {"language": "mandarin", "language_level": ["fluency"]}]}, "experience_required": {"duration": ["3 years"], "field": ["toys", "merchandising", "trading"]}}, {"job_id": "100003008988680", "location_code": "hk", "company": "Yee Fung International Limited", "job_title": "Production Manager", "description": "Job\u2019s responsibilities:\nHands-on experience in overseeing and good production management to secure quality and delivery meeting customers' requirements\nLead and manage production planning team and all production workshops\nLean Production improvement and management\nProduction cost budget management\nFacility, Machine, Equipment, Mold and Tools maintenance management\nProblem solving, highly responsible and have good visions\nProduct quality standards and scarp improvement\nEnsure efficient collaboration and co-ordination between relevant departments including procurement, distribution and management\nRequirements:\nMinimum 8 years of experience in toys or shoes manufacturing company\nHigher Diploma Holder or above\nStrong production & material planning plus good analytical mind\nGood organization, planning and leadership skill\nGood command of English, Cantonese and Putonghua\nHands-on PC knowledge in MS Office (Proficiency in MS Excel (pivot table)\nERP / MRP application and evaluation skill is MUST!\nBasic knowledge in molding, sewing, painting and assemble production\nStationed in Dongguan Area\nImmediate availability is an advantage\nPackage Offer:\n6 Working Days per week (Alternative Sat off\uff09\nLabor Holiday\nTravel insurance\nMedical coverage\nMPF\nInterested parties please submit CV and expected salary by email via \"Apply Now\"\n(Personal data collected will be used for recruitment only.)", "employment_types": ["Full Time", "Permanent"], "selling_points": [], "locations": ["Not Specified"], "categories": ["Manufacturing", "Production Planning / Control", "Merchandising & Purchasing", "Toy", "Procurement / Purchasing / Sourcing"], "post_time": "2021-12-20T16:54:26Z", "salary": {"currency": null, "max": null, "min": null, "period": "monthly", "term": null}, "salary_visible": false, "title_keywords": ["production manager"], "responsibilities": ["cost", "management", "maintenance", "budget", "quality", "production planning"], "requirements": {"degrees": ["higher diploma holder"], "majors": [], "languages": ["cantonese", "putonghua", "english"], "language_level": ["good command"], "hard_skills": ["plus", "basic", "pivot table", "erp", "ms excel", "pc knowledge", "ms office"], "soft_skills": ["leadership skill", "analytical mind", "hands-on"], "languages_combined": [{"language": "cantonese", "language_level": ["good command"]}, {"language": "putonghua", "language_level": ["good command"]}, {"language": "english", "language_level": ["good command"]}]}, "experience_required": {"duration": ["minimum 8 years"], "field": ["toys", "manufacturing"]}}, {"job_id": "100003008988860", "location_code": "hk", "company": "API Lab Testing Limited", "job_title": "Customer Service Executive / Customer Service Coordinator", "description": "Responsibilities:\u00a0\n\nPrimary customer interface to coordinate customer requirement to Lab operations\nProvide friendly and professional pre-sale and post-sales throughout order transactions\nHandle sample registration and release of test report\nHandle customer enquiry on service capacity, quotation, reporting status, report contents and complaints\nFollow up with customers on missing information and samples\nProvide regular summary report to customers regarding the lab service\n\nRequirements:\n\nBachelor graduated (If nil but with relevant experience will also be considered)\n\nMinimum 2 years\u2019 relevant experience in laboratory testing company (Candidates with less experience will be considered as Customer Service Coordinator)\nFRESH GRAD CANDIDATE IS WELCOMED\nHigh-organized, able to work independently and capable of working under pressure with multi-task assignments\nGood command of English and Chinese\nGood computer skills\nFamiliar with European regulations/standard is an advantage\nHaving the experience of component sorting is an advantage\nIMMEDIATELY AVAILABLE is an advantage\nExcellent communication and interpersonal skills\nWell-organised, independent, responsible, multi-tasking\nIMMEDIATELY AVAILABLE is an advantage and kindly provide expected salary when apply\n\n5 days work (overtime and weekend work required if necessary)", "employment_types": ["Full Time"], "selling_points": ["Customer service", "English and Chinese", "Fresh grad"], "locations": ["Tsuen Wan Area"], "categories": ["Sales, CS & Business Devpt", "Customer Service - Supervisor / Officer", "Merchandising & Purchasing", "Furniture", "Toy"], "post_time": "2021-12-21T01:43:18Z", "salary": {"currency": null, "max": null, "min": null, "period": "monthly", "term": null}, "salary_visible": false, "title_keywords": ["customer service executive", "customer service coordinator"], "responsibilities": ["reporting", "operations", "quotation", "transactions", "coordinate", "contents", "report"], "requirements": {"degrees": ["bachelor"], "majors": [], "languages": ["english", "chinese"], "language_level": ["good command"], "hard_skills": ["computer skills"], "soft_skills": ["organized", "work independently", "under pressure", "capable", "multi-task", "independent", "responsible", "multi-tasking", "customer service", "communication and interpersonal skills", "well-organised"], "languages_combined": [{"language": "english", "language_level": ["good command"]}, {"language": "chinese", "language_level": ["good command"]}]}, "experience_required": {"duration": ["minimum 2 years"], "field": ["laboratory testing", "customer service", "relevant experience"]}}, {"job_id": "100003008987037", "location_code": "hk", "company": "", "job_title": "Merchandiser \u2013 Gift & Premium / Sundries", "description": "Job Requirements\n\nCertificate holder or above\n3-4 years merchandising experience in trading or manufacturer\nHands-on experience in sundries product or gift & premium\nWell-organized, energetic, dynamics and sense of responsibilities\nGood command of English and conversational Putonghua\nComputer knowledge in MS Word, Excel, Outlook etc\nImmediate available is highly preferred\n\nJob Responsibilities\n\nHandle orders coordination with overseas customers and factory\nResponsible for orders follow up from development to production\nFollow up purchase order and order schedules for delivery arrangement\nHandle sample development, sourcing and production coordination\n\nExcellent development prospect and attractive fringe benefits will be offered to the right candidates. For interested parties, please send email to larrylai.hr@gmail.com for job enquiries.", "employment_types": ["Full Time", "Permanent"], "selling_points": [], "locations": ["Not Specified"], "categories": ["Merchandising & Purchasing", "Toy", "Sundries", "Others"], "post_time": "2021-12-20T06:30:53Z", "salary": {"currency": null, "max": null, "min": null, "period": "monthly", "term": null}, "salary_visible": false, "title_keywords": ["merchandiser"], "responsibilities": ["schedules", "purchase", "coordination with", "coordination"], "requirements": {"degrees": ["certificate"], "majors": [], "languages": ["putonghua", "english"], "language_level": ["conversational", "good command"], "hard_skills": ["excel", "outlook", "ms word"], "soft_skills": ["hands-on", "energetic", "well-organized", "sense of responsibilities"], "languages_combined": [{"language": "putonghua", "language_level": ["good command"]}, {"language": "english", "language_level": ["conversational", "good command"]}]}, "experience_required": {"duration": ["3-4 years"], "field": ["merchandising", "trading"]}}]