[{"job_id": "100003009048089", "location_code": "hk", "company": "Time Grand Limited", "job_title": "Purchaser", "description": "Placing orders with suppliers or vendors and ensuring that documentation is in order, with terms and conditions being clear;\nMaintaining a filing system in the purchase department and updating appropriate records when required;\n\nJob Requirement:\n\nAt least 3 years of relevant experience in purchase work , \u00a0experience in watch manufacturing field is highly preferred\nIn depth knowledge of Microsoft Excel and Words.\nKnowledge in ERP system is highly preferred\nFair command in both written and spoken English and Cantonese;\nGood time-management, self-motivated, willing to learn and able to work under pressure;\nImmediate available is highly preferable\n\nOur company culture and pattern:\n\n5-day work week,\n13-months Salary, Discretionary Bonus, Annual Leave, Payable Sick Leave,\nEmphasize team work,\nEncourage continuing education and on-job training,\nOpen office working environment,\nOffer\u00a0promotion opportunities and long-term career path\n\nWe offer attractive remuneration package and long-term career prospect to the appointed candidate. Please submit your application enclosing your full resume with current and expected salary in strict confidence to HR & Admin Department by clicking \"Apply Now\" below.\u00a0\n\n(All information provided will be treated in strict confidence and used solely for recruitment purpose.)", "employment_types": ["Full Time", "Permanent"], "selling_points": ["Watch Manufacturing; Microsoft Excel and Words;", "5-day work week; 13-months Salary;", "Knowledge in ERP system is preferred"], "locations": ["Kwai Hing"], "categories": ["Manufacturing", "Others", "Merchandising & Purchasing", "Watch"], "post_time": "2022-01-14T04:46:34Z", "salary": {"currency": null, "max": null, "min": null, "period": "monthly", "term": null}, "salary_visible": false, "title_keywords": [], "responsibilities": ["management", "maintaining", "purchase", "placing orders", "documentation", "work under pressure"], "requirements": {"degrees": [], "majors": [], "languages": ["cantonese", "english"], "language_level": [], "hard_skills": ["documentation", "erp system", "words", "microsoft excel"], "soft_skills": ["clear", "self-motivated", "willing to learn", "work under pressure"], "languages_combined": [{"language": "cantonese", "language_level": []}, {"language": "english", "language_level": []}]}, "experience_required": {"duration": ["at least 3 years"], "field": ["manufacturing", "relevant experience"]}}, {"job_id": "100003009054610", "location_code": "hk", "company": "DFS Hong Kong Limited", "job_title": "Assistant Planning Manager, Watches & Jewellry", "description": "We are seeking a self-motivated and meticulous Assistant Planning Manager to join our well-established team. With guidance from the Planning Manager, you will work on stock forecast, ordering and allocation for one category of product. You will closely monitor the inventory flow to achieve the worldwide gross margin plans, and to maximize sales and profitability in your assigned location.\n\nResponsibilities\n\nSeasonal Sales Planning\n\n\nDevelop worldwide seasonal sales, margin and mix plans for one segment of a category based on strategic direction and financial guidelines\nDevelop location-specific sales ratify with region plans; tie to location profiles and assist plans\nDevelop monthly financial plans at department level for one segment of a category\n\nOrder Placement and Replenishment\n\n\nProvide analysis necessary for the development of the monthly Open-to-Buy based on planning variances to the financial plans\nRecommend quantities to place for fashion orders based on stock projection\nReview and update replenishment forecasts as required based on stock projection\nMonitor Open-To-Buy weekly and make recommendations as appropriate\nCommunicate and follow up with vendors to support merchandise flow requirements\n\nInventory Management\n\n\nSupply the SKU Team with appropriate initialization information to activate distribution\nWork with Distributors to ensure on-order needs matches with location sales needs\nIdentify fast and slow sellers and develop action plan with team\nProvide monthly analysis to report and implement discontinued SKU action plans\nDevelop and recommend markdown strategy and manage markdown budgets\n\nKey Requirements\n\n\nBachelor\u2019s Degree or above\n1-2 years\u2019 experience in merchandising and/or planning with a major retailer\nExperience in the luxury market and international business preferred\nAble to create and maintain sophisticated Excel spreadsheets\nNegotiation experience required\nStrong interpersonal skills and be able to deliver high-level presentations\nProficient in both written and spoken English", "employment_types": ["Full Time", "Permanent"], "selling_points": ["World's Leading Luxury Travel Retailer", "Work Life Balance, Five-day Work Week", "International & Dynamic Working Environment"], "locations": ["Quarry Bay"], "categories": ["Accounting", "Others", "Merchandising & Purchasing", "Handbag", "Watch"], "post_time": "2022-01-17T10:14:11Z", "salary": {"currency": null, "max": null, "min": null, "period": "monthly", "term": null}, "salary_visible": false, "title_keywords": ["manager", "assistant"], "responsibilities": ["make recommendations", "budgets", "open-to-buy", "markdown strategy", "guidelines", "analysis", "review", "monitor", "replenishment", "develop", "inventory management", "report", "plan", "plans", "financial plans", "planning"], "requirements": {"degrees": ["degree or above", "bachelor"], "majors": [], "languages": ["english"], "language_level": ["proficient"], "hard_skills": ["excel", "presentations"], "soft_skills": ["sophisticated", "interpersonal skills", "negotiation"], "languages_combined": [{"language": "english", "language_level": ["proficient"]}]}, "experience_required": {"duration": ["1-2 years"], "field": ["business", "merchandising", "planning"]}}, {"job_id": "100003009048599", "location_code": "hk", "company": "Timex Nederland B.V. Sequel Services", "job_title": "Procurement Director", "description": "The Procurement Director will report directly to the Senior Procurement Director in Hong Kong.\u00a0 This position will be responsible for leading a supply chain team of professionals in Hong Kong, responsible for the strategic sourcing development and operational management of all product procurement for the company (watches components commodities).\u00a0\n\nThe main goals are to optimize the total cost of ownership for the company, protect IP, maximize the service from vendors in order to meet key stakeholders business expectations, maintain the required quality and delivery levels and ensure compliance with international norms/ regulations and licensor\u2019s requirements.\n\nResponsibilities:\n\n\nWork with key stakeholders to strategically evolve the network of suppliers and consolidate where appropriate to leverage efficiencies, mitigate risk and simplify \"run the business\" activities and drive cost savings.\u00a0\nContinue the robust gross margin enhancement program through the roll out of continuous improvement initiatives at supply partners, motivating key internal Supply Chain and QA stakeholders and supplementing with external resources to drive meaningful cost reduction projects that have a favorable ROI.\nStrategically lead the cost savings program, providing the commercial team with options and recommendations to drive down unit cost and improve gross margin.\nRelentlessly pursue excellence in service levels. He/She will motivate the Supply Planning, Sourcing and Quality teams to collaborate on optimizing batch sizes, run frequency, risk identification and mitigation, lead time reduction and supply chain simplification to achieve service level targets while decreasing overall investment in working capital.\nFoster a team environment, delegated decision making, creative thinking, and excellence in internal customer service. Be accessible and visible, demonstrating energy, passion and enthusiasm.\nActively participate concurrently in the New Product Innovation program and staged gate deliverables, including idea generation, driving awareness of supply-side capabilities and relevant new product developments, and creating a culture across Operations that embraces the importance of every employee in the New Product Development process to effectively launch new SKUs to drive organic company growth.\nBuilding on the business intelligence and current Oracle/Excel reports, institute a data-driven Supplier Performance Scorecard program to measure firm's key desirable attributes: Quality, Service, Cost containment and Supply Continuity.\u00a0\nFoster and develop long-term supplier relationships to create a cooperative and professional framework, while protecting Timex IP, whereby firm's supply partners desire to share in Timex\u2019s growth and success, and work tirelessly on continuous improvement to reduce cost and waste.\nStay informed of current industry-wide regulatory requirements and emerging trends, and ensure that suppliers to Timex conform to these requirements; monitor gap closure plans to mitigate shortfalls as needed.\u00a0\nDevelop and mentor employees and ensure their readiness for company and personal career growth; ensure programs are developed for enhanced use of Oracle and other supply chain tools.\u00a0 Build an organization so that the balance between tactical and strategic is close to 50/50.\u00a0\nRequirement:\n\nBachelor Degree in Mechanical/Electronic/industrial Engineering or related field is minimum with Master Degree is preferred (Mechanical, Electronic Engineering or MBA)\n10+ years of progression in leadership responsibilities in sourcing and commodity purchasing.\u00a0 Experience in watch industry and China experience is preferred.\u00a0\u00a0\nExperience in managing a high volume, high mix portfolio in similar industries (Fast consumer good) and experience in dealing with electronics, mechanical, plating, electro-mechanical technologies.\u00a0\nDemonstrated purchasing and negotiation expertise with 10+ years of broad experience in commodity analysis and product cycles\u00a0\nFluent verbal, presentation and written skills in English and Chinese.\u00a0 Fluent in Mandarin is preferred.\u00a0\nWe offer 5-day work, medical care plus other fringe benefits to the right candidate.\u00a0 Remuneration package will commensurate with your experience and qualification.\u00a0 Interested parties, please send detailed resume with expected salary to our Human Resources Manager.\u00a0\u00a0\n\n\nAll applications will be treated with strict confidentiality and only shortlisted candidates will be notified.", "employment_types": ["Full Time", "Permanent"], "selling_points": [], "locations": ["Cheung Sha Wan"], "categories": ["Merchandising & Purchasing", "Watch", "Procurement / Purchasing / Sourcing"], "post_time": "2022-01-14T08:33:25Z", "salary": {"currency": null, "max": null, "min": null, "period": "monthly", "term": null}, "salary_visible": false, "title_keywords": ["director"], "responsibilities": ["collaborate", "cost", "data", "operations", "regulatory requirements", "quality", "teams", "monitor", "develop", "customer service", "reports", "plans", "planning"], "requirements": {"degrees": ["degree", "bachelor", "master degree"], "majors": ["engineering"], "languages": ["english", "chinese", "mandarin"], "language_level": ["fluent"], "hard_skills": ["analysis"], "soft_skills": ["presentation", "leadership", "negotiation"], "languages_combined": [{"language": "english", "language_level": []}, {"language": "chinese", "language_level": []}, {"language": "mandarin", "language_level": ["fluent"]}]}, "experience_required": {"duration": ["10+ years"], "field": ["purchasing"]}}, {"job_id": "100003009039581", "location_code": "hk", "company": "Perfex Limited", "job_title": "Account Executive (WATCH)", "description": "Responsibilities:-\n\nCommunication with clients & vendors\nFollow-up projects & orders\nLook after production schedule\nArrange shipment\n\nRequirements:-\n\n2-3 years experience in watch industry\nGood knowledge on different kind of watch components\nwith Product knowledge of development of watch\nProficient computer skills eg. MS office\u00a0\nKnowing Photoshop Illustrator is a plus\nFluent command in both spoken and written English & Mandarin\nSelf-motivated, well organized, able to work independently\n\nWe provide attractive remuneration with medical insurance\n\nTo have extra leave during Lunar New Year period", "employment_types": ["Full Time"], "selling_points": [], "locations": ["Lai Chi Kok"], "categories": ["Marketing / Public Relations", "Marketing - General / Support", "Merchandising & Purchasing", "Watch", "Sales, CS & Business Devpt", "Account Servicing"], "post_time": "2022-01-11T10:09:29Z", "salary": {"currency": null, "max": null, "min": null, "period": "monthly", "term": null}, "salary_visible": false, "title_keywords": ["account executive"], "responsibilities": ["communication", "schedule"], "requirements": {"degrees": [], "majors": [], "languages": ["english", "mandarin"], "language_level": ["fluent"], "hard_skills": ["plus", "illustrator", "computer skills", "ms office", "photoshop"], "soft_skills": ["self-motivated", "well organized", "work independently"], "languages_combined": [{"language": "english", "language_level": ["fluent"]}, {"language": "mandarin", "language_level": ["fluent"]}]}, "experience_required": {"duration": ["2-3 years"], "field": []}}, {"job_id": "100003009044672", "location_code": "hk", "company": "Fossil (East) Ltd", "job_title": "Order Management Planner - Merchandiser (Jewellery / Watch)", "description": "\n\nTHE COMPANY :\nEuropean owned company\nWatch design, develop & trading company\nWe are composed of engineers and technical experts.\u00a0 We are able to develop new projects and products which fulfill clients\u2019 specifications and international standards.\nWe offer rapid prototyping and salesman samples that clients have just drawn or proposed for ODM and OEM products.\nMain market : US and European watch brands and clients\nWe are looking for\u00a0 SENIOR\u00a0PROJECT COORDINATOR\u00a0\u00a0- with details as follows :\u00a0\nTHE JOB :\u00a0\u00a0\nOver 3 years work experience in watch field\nExperience in project or clients follow up is a plus\nExperience in European or US watch companies or watch brands is a plus\nProficient in English & Chinese; Mandarin is a plus\nReport to the Senior Project Manager\nParticipate in project management for assigned watch brands/projects\u00a0\nCoordinate with clients for project management details\nCollaborate with Design team of the developing product;\nLiaise and negotiate with suppliers regarding structure and possibility of Products;\nEnsure the product schedule on time;\nEnsure the products' structure and appearance match requirements\nMonitor the progress rate of each ongoing project;\nNo trips is required\n5 days work\n13 months salary + performance bonus\nAnnual leave : 14 days\nMedical benefits\nMore solid experience will be considered as\u00a0 Assistant Project Manager (2 posts)\nTO APPLY for this job or similar jobs :\n\u00a0\nFor secure and confidential job application, please click the below link to get our email address.\u00a0\nhttp://jpc.hk/confidential_apply.htm\u00a0\nWe provide free job hunting services to job seekers.\nTo speed up our process, please do NOT send us download links.\nPersonal data provided by job applicants will be used for recruitment purpose only.\nYour privacy is guaranteed. We will never give out, lease, or sell your personal information.\nJPC Recruiting Services was established in 1990.\u00a0\nhttp://www.facebook.com/pages/JPC-Texson-Ltd/500356593325952\n\u00a0", "employment_types": ["Full Time", "Permanent"], "selling_points": ["PO issuance, order tracking, control & management", "Manage purchase and production timeline", "Coordinate with overseas offices and factories"], "locations": ["Tsuen Wan Area"], "categories": ["Manufacturing", "Production Planning / Control", "Merchandising & Purchasing", "Watch", "Others"], "post_time": "2022-01-13T05:15:53Z", "salary": {"currency": null, "max": null, "min": null, "period": "monthly", "term": null}, "salary_visible": false, "title_keywords": ["merchandiser"], "responsibilities": ["specifications", "design", "develop"], "requirements": {"degrees": [], "majors": [], "languages": [], "language_level": [], "hard_skills": [], "soft_skills": [], "languages_combined": []}, "experience_required": {"duration": [], "field": []}}, {"job_id": "100003009044166", "location_code": "hk", "company": "JPC Texson Limited", "job_title": "SENIOR PROJECT COORDINATOR / ASST PROJECT MANAGER (25K-35K) \u2013 Europe watch trading / no trips", "description": "What's the role about?\nPurchase order issuance and production tracking management\nManage purchase and production timeline with various departments and factories\nEnd-to-end order tracking, inventory management and monitor for timely & efficient delivery schedules\nCoordinate closely between overseas office and factories for production follow-up\nCreate and maintain system master\nWhat we are looking for:\n\nTertiary education or above\nRelated experience in watch and jewellery industries is a bonus\nGood in MS Office application, experience in google setting is a advantage\nwell organized, proactive, good interpersonal & communication skills\n\nTogether, we make great things happen. Apply now and be part of our tomorrow.\n\nInterested parties please send us your full resume with contact details, preferably with your current and expected salary.\n\nFossil Group is an Equal Opportunity employer. All qualified applicants will receive consideration of employment without regard to race, disability, gender, religion, family status, marital status, national origin, sexual orientation, veteran status, gender identity or expression or any other basis protected by local, state, or national law. Only short-listed candidates will be notified. All information received will be kept in strict confidence and only for employment-related purpose.", "employment_types": ["Full Time", "Permanent"], "selling_points": ["Over 3 yr work exp in watch trading/mfg/buying off", "Participate in project mgt & clients follow up", "No trips required; report to Senior Project Mgr"], "locations": ["Tsuen Wan Area"], "categories": ["Manufacturing", "Product Development / Management", "Merchandising & Purchasing", "Watch", "Sales, CS & Business Devpt", "Sales Administration"], "post_time": "2022-01-13T03:16:39Z", "salary": {"currency": null, "max": null, "min": null, "period": "monthly", "term": null}, "salary_visible": false, "title_keywords": ["project manager", "senior project coordinator"], "responsibilities": ["order tracking", "management", "schedules", "monitor", "inventory management", "coordinate", "purchase", "maintain", "communication", "tracking"], "requirements": {"degrees": ["master"], "majors": [], "languages": [], "language_level": [], "hard_skills": ["make", "ms office"], "soft_skills": ["efficient", "communication skills", "timely", "well organized", "proactive", "interpersonal"], "languages_combined": []}, "experience_required": {"duration": [], "field": ["related"]}}, {"job_id": "100003009039672", "location_code": "hk", "company": "Perfex Limited", "job_title": "Technician (WATCH)", "description": "Job description:\n\nVerify TDs\nCoordinate with suppliers to ensure they meet the high quality standard of our customers\nWhen face to quality/technical problem, know how to find solution individually\nCommunicate with suppliers, assembly factory and internal dept. to improve the quality of the products\nUpdate all inspection results, analysis and improve the quality standard and system\nMay need to go to China factories for QC (after reversed mainland travel restriction)\n\nRequirement:-\n\nRelevant experience in watch industry (at least 5 years)\nGood knowledge and skill on Watch Structure and Processing\nHave good knowledge of watch case, movement & related component (well understanding of TD)\nKnowing how to assemble is a MUST\nGood command in both spoken English & Mandarin\nWell organized, accurate detail, independent\n\nWe provide attractive remuneration with medical insurance\u00a0\n\nHave extra leave during Lunar New Year period\n\nInterest parties, please send your application and your expected salary to us.\n", "employment_types": ["Full Time", "Permanent"], "selling_points": [], "locations": ["Lai Chi Kok"], "categories": ["Manufacturing", "Production Planning / Control", "Merchandising & Purchasing", "Watch", "Others", "Technician"], "post_time": "2022-01-11T10:39:19Z", "salary": {"currency": null, "max": null, "min": null, "period": "monthly", "term": null}, "salary_visible": false, "title_keywords": ["technician"], "responsibilities": ["communicate with", "analysis", "quality", "coordinate with", "inspection"], "requirements": {"degrees": [], "majors": [], "languages": ["english", "mandarin"], "language_level": ["good command"], "hard_skills": ["processing"], "soft_skills": ["independent", "accurate", "well organized"], "languages_combined": [{"language": "english", "language_level": ["good command"]}, {"language": "mandarin", "language_level": ["good command"]}]}, "experience_required": {"duration": ["at least 5 years"], "field": ["relevant experience"]}}, {"job_id": "100003009040038", "location_code": "hk", "company": "Christian Dior Far East Limited", "job_title": "Merchandising Assistant - Fine Jewelry & Timepieces (1-year contract)", "description": "Responsibilities\n\nUpdate daily / weekly / monthly sales report and analyze the market trend.\nFollow up with Asia Pacific markets stock request and arrange stock rebalancing.\nSupport the team in developing catalogues and selling tools.\nSupport the after sales services for Asia Pacific.\nProvide extensive day-to-day operational and administrative supports to Regional Fine Jewelry & Timepieces team.\nHandle other ad hoc, miscellaneous tasks and projects related to the business.\nRequirement\n\nTertiary education in Business Management, Fashion Merchandising, or related discipline.\nRelevant 2 years working experience in buying & merchandising is an advantage.\nGood interpersonal skill, detail-oriented, willing to learn and able to work under pressure.\nGood command of spoken and written English, Cantonese and Mandarin.\nProficient in MS Office, Excel (pivot table, vlookup, etc.) and PowerPoint.\nImmediate availability preferred\n\nInterested parties please send your full resume and salary expectation to:\u00a0recruit@ hk.christiandior.com.\n\n* All applications will be treated in strict confidence and used only for recruitment purpose. Applicants who are not invited for an interview within 4 weeks may be considered for other suitable positions within the Group over a one year period, after which their personal data will be destroyed.*", "employment_types": ["Full Time", "Temporary", "Contract"], "selling_points": ["Support Regional FJ&T department in projects", "2 years experience in buying & merchandising", "Immediate availability preferred"], "locations": ["Causeway Bay"], "categories": ["Merchandising & Purchasing", "Watch", "Others"], "post_time": "2022-01-12T00:59:11Z", "salary": {"currency": null, "max": null, "min": null, "period": "monthly", "term": null}, "salary_visible": false, "title_keywords": ["merchandising assistant"], "responsibilities": ["ad hoc", "monthly sales report", "support the team", "developing"], "requirements": {"degrees": [], "majors": [], "languages": ["cantonese", "english", "mandarin"], "language_level": ["good command"], "hard_skills": ["business management", "excel", "pivot table", "powerpoint", "vlookup", "ms office"], "soft_skills": ["detail-oriented", "work under pressure", "willing to learn", "interpersonal skill"], "languages_combined": [{"language": "cantonese", "language_level": ["good command"]}, {"language": "english", "language_level": ["good command"]}, {"language": "mandarin", "language_level": ["good command"]}]}, "experience_required": {"duration": ["2 years"], "field": ["merchandising"]}}, {"job_id": "100003009037428", "location_code": "hk", "company": "DFS Hong Kong Limited", "job_title": "Senior Assistant Merchandise Manager, Watches & Jewellery - DFS9112107", "description": "Do you have great commercial plans to optimize sales of our products?\n\nYou will have full merchandising accountabilities for a segment of business, defined by either a brand or by division. You will spearhead sales planning, pricing and merchandise assortment to support the overall category/department strategy. You will also partner closely with the Merchandise Manager for vendor management, cost negotiation and product development.\n\nKey Responsibilities:\n\nDevelop and communicate sales strategy for a segment of a department business\nFormulate an assortment strategy that is consistent with overall business strategy\nWork with the Merchandise Manager to monitor the proper execution of the merchandise strategy at the division and location level\nDrive and execute the brands\u2019 floor space planning and allocation for all key locations\nAssist the Merchandise Manager to determine seasonal transition and promotional strategies\nMonitor sales performance on newly developed products, determine further sales opportunities based on results\nSelect/delete assortments as appropriate\nDeliver sales, gross margin and turnover goals for assigned business segment\nPeople Development\nEncourage and support the development of your team; offer honest and constructive feedback to the team to foster individual development\nDevelop and maintain a formal plan for self-development and career\u00a0\nRequirements:\n\nBachelor\u2019s Degree or above\nMinimum 1 year\u2019s merchandising experience in a buying office\nGreat interpersonal skills to negotiate with internal & external work partners\nStrong communication skills, both oral and written and be comfortable in making high level presentations\nProficient in both written and spoken English", "employment_types": ["Full Time", "Permanent"], "selling_points": ["World's Leading Luxury Travel Retailer", "Work Life Balance, Five-day Work Week", "International & Dynamic Working Environment"], "locations": ["Quarry Bay"], "categories": ["Merchandising & Purchasing", "Watch", "Others", "Procurement / Purchasing / Sourcing"], "post_time": "2022-01-11T02:47:10Z", "salary": {"currency": null, "max": null, "min": null, "period": "monthly", "term": null}, "salary_visible": false, "title_keywords": ["assistant merchandise", "manager"], "responsibilities": ["sales performance", "monitor", "develop", "maintain", "plan", "planning"], "requirements": {"degrees": ["degree or above", "bachelor"], "majors": [], "languages": ["english"], "language_level": ["proficient"], "hard_skills": ["presentations"], "soft_skills": ["communication skills", "oral", "interpersonal skills"], "languages_combined": [{"language": "english", "language_level": ["proficient"]}]}, "experience_required": {"duration": ["minimum 1 year"], "field": ["merchandising"]}}, {"job_id": "100003009035980", "location_code": "hk", "company": "ALDI Services Asia Limited", "job_title": "Merchandiser - General Hardgoods (m/f)", "description": "We invite now high caliber talent to apply for Merchandiser (m/f)\u00a0to join our rapidly growing sourcing team in Hong Kong. This position supports product development and commercialization with a fast-paced successful team.\n\nResponsibilities.\n\nPerform general sourcing duties as required by the Manager\nPrepare and ensures that all documents related to tender, submission, awarding of contracts and shipments are correct and completed\nFinalize submission comparison documents and identify preferred submission in line with company procedures\nEffectively communicate with Quality, CR, Admin and Logistics team members as well as ALDI International departments/ offices and other internal/external parties on behalf of Manager/ team\nFollow through the production process for all purchased products\nCarry out visits to trade fairs or suppliers in order to manage and develop the supplier pool within the commodity area\nProvides cover for the team members and supports the training of employees and trainees from other areas\n\n\u00a0Your Profile.\n\nAt least (Non-Degree) Tertiary education required.\nMinimum of 2 years' relevant working experience, preferably gained in sourcing/buying offices, working with consumer products.\nExcellent communication and interpersonal skills, team player.\nGood command of both verbal and written business English and fluency in Mandarin essential.\nAble to work independently, self-motivated, responsible, well-organized and willing to learn.\nAttention to detail and good organizing, coordination and planning skills.\nGeneral knowledge of MS office and Exchange essential.\nHigh level of maturity, integrity, trustworthiness.\n\nKey Benefits of working at ALDI.\n\nMarket leading remuneration package\n\nRewarding, attractive remuneration package.\nGroup Medical Insurance covering dental and maternity* benefits .\n\nWork-life balance\n\nFull time, permanent position, 5-day-work-week.\n20 days of paid Annual Leave.\n\nBeing part of a pleasant, successful, growing business\n\nALDI\u2019s business is expanding, same for the Hong Kong Office with lots of opportunities for growth and development.\nPleasant working atmosphere where proactive communication, teamwork and collaboration is highly valued.\n\nPeople Focused\n\nStructured, comprehensive orientation and on-the-job training.\nALDI empowers our people allowing staff ownership of their areas of responsibilities.\n\nTrust and Integrity\n\nWE DO WHAT WE SAY - \u00a0for us there is no grey area, we have robust business processes, procedures and strong governance in place.\nWe treat our staff members, customers, suppliers and service providers with trust and fairness as business partners.\n\n\u00a0* Maternity benefits only apply for female employees due to local Insurance policy\n\nHow to apply\u00a0\u00a0\n\nIf you are interested in applying for the job, we look forward to receiving your full application in English, including salary expectation and possible starting date. The application should be sent through JobsDB by clicking icon \u201cApply Now\u201d or addressed to ALDI HR Department,\u00a018/F, Millennium City 6, 392 Kwun Tong Road, Kwun Tong, Kowloon, Hong Kong.\n\nALDI is an Equal Opportunity employer. We are dedicated to create an equal opportunity throughout recruitment process and staff employment to build a diverse and inclusive workforce. We oppose all forms of unfair or unlawful discrimination in our selection process.\n\nAll personal data collected will be used for recruitment purposes only and be treated in strictest confidence and highest security level in accordance with Hong Kong Data (Privacy) Ordinance as well as ALDI internal Security Policy.\n\nNo part of this job content including but not limited to company information, logo and job description may be reproduced, presented, uploaded, transmitted, modified or distributed \u00a0in any form or by any means without prior permission of ALDI Services Asia Limited / ALDI Sourcing Asia Limited (\u201cthe Company\u201d). The Company reserves the right to take legal action on any unauthorized reproduction, presentation, upload, transmission, modification or distribution. Only applications submitted directly to the Company in response to this advertisement will be considered and any application received by the Company through unauthorized third party agents or via any other channels will not be considered.\n", "employment_types": ["Full Time", "Permanent"], "selling_points": ["Responsible for orders monitoring and follow-up", "Tender submission and shipment documents", "Communicate with Quality, CR, Admin and Logistics"], "locations": ["Kwun Tong"], "categories": ["Merchandising & Purchasing", "Stationery", "Sundries", "Watch"], "post_time": "2022-01-10T08:58:58Z", "salary": {"currency": null, "max": null, "min": null, "period": "monthly", "term": null}, "salary_visible": false, "title_keywords": ["merchandiser"], "responsibilities": ["communicate with", "production process", "contracts", "external parties", "procedures", "quality", "develop", "communication", "commercialization", "logistics", "tender", "coordination", "planning"], "requirements": {"degrees": ["degree"], "majors": [], "languages": ["english", "mandarin"], "language_level": ["fluency", "good command"], "hard_skills": ["exchange", "ms office"], "soft_skills": ["planning skills", "work independently", "self-motivated", "responsible", "well-organized", "willing to learn", "integrity", "communication and interpersonal skills", "attention to detail", "coordination", "team player"], "languages_combined": [{"language": "english", "language_level": ["fluency", "good command"]}, {"language": "mandarin", "language_level": ["good command"]}]}, "experience_required": {"duration": ["minimum of 2 years"], "field": ["buying offices", "relevant working experience"]}}, {"job_id": "100003009043941", "location_code": "hk", "company": "International Operations & Services Company (HK) Limited", "job_title": "Category Management Planner, Fashion & WJA APAC", "description": "As a member of our Global Category Management community you will be responsible to\u00a0support\u00a0Brand Management and Promotion processes for the Fashion and WJA Category in Asia\u00a0and acting as the interface to the regional category management activities.\n\nThe position is based in Hong Kong\n\nKey Accountabilities\n\nAssist the Category Manager in preparing and implementing the Commercial Plan for the\u00a0Category\nEnsure implementation of the novelties and promotions program to deliver sales and profit targets\nManaging the\u00a0assortments at global and local level.\nMaintain a strong relationship with local operational teams and external suppliers to drive sales and performance\nAssist with allocating space for brands in new shop developments and layouts in partnership with Global Shop Development\nReview the monthly report on\u00a0assortment performance by vendor, brand and SKU (top brands 80/20), sales and margin\nManage implementation of agreed Promotions with the local operations\nCompile and update information packs for pricing policies, co-ordinate the validation of pricing policies and track PAX profiles for all airports.\nAssist the central team with research about product and market trends\nExperience and Skills\n\nDegree holder in business or related disciplines\n3 - 4 years\u2019 experience within travel retail or fast-paced high volume retail businesses\nGood commercial acumen - ability to analyze business performance and identify new opportunities for sales and margin growth\nExcellent analytical skills - good attention to detail with problem solving skills\nGood interpersonal skills - able to communicate with multiple stakeholders at different levels and influence decision making for the category\nSelf-driven and reliable - able to work independently\nStrong PC skills - Advanced knowledge of Excel and other Microsoft programs. SAP knowledge would be helpful\u00a0 \u00a0 \u00a0 \u00a0 \u00a0 \u00a0 \u00a0 \u00a0 \u00a0\nInterested parties, please send full CV with availability, current and expected salary to us by clicking below button \u201cApply Now\u201d.\n\n\nWe are an equal opportunity employer and welcome applications from all qualified candidates. Personal data collected will be treated in strict confidence and handled confidentially by authorized personnel for recruitment-related purposes only within Dufry Group of companies.\n\u00a0 \u00a0 \u00a0 \u00a0 \u00a0 \u00a0 \u00a0", "employment_types": ["Full Time", "Permanent"], "selling_points": [], "locations": ["Hung Hom"], "categories": ["Merchandising & Purchasing", "Handbag", "Watch", "Procurement / Purchasing / Sourcing"], "post_time": "2022-01-13T02:32:40Z", "salary": {"currency": null, "max": null, "min": null, "period": "monthly", "term": null}, "salary_visible": false, "title_keywords": [], "responsibilities": ["communicate with", "management", "operations", "policies", "review", "teams", "implementation", "maintain", "plan", "monthly report", "drive sales"], "requirements": {"degrees": ["degree holder"], "majors": ["related disciplines", "business"], "languages": [], "language_level": [], "hard_skills": ["excel", "airports", "sap", "vendor", "analytical skills", "problem solving skills", "pc skills", "acumen"], "soft_skills": ["work independently", "advanced", "responsible", "analytical skills", "ability to analyze", "interpersonal skills", "attention to detail", "problem solving skills", "reliable", "driven", "decision making"], "languages_combined": []}, "experience_required": {"duration": ["3 - 4 years"], "field": ["retail"]}}, {"job_id": "100003009023548", "location_code": "hk", "company": "Siu Success (Y.K.Y.) and Company Limited", "job_title": "General Merchandising Manager", "description": "Responsibilities:\n\n\nEnsure the smooth running of the whole product development and merchandising processes of multiple clients, including the timely and strategic execution of client briefs, vendor sourcing, sampling, production, quality control and delivery\nWork flexibly across a range of product categories, including Fashion Accessories, Jewellery and Watches, Electronics (including Smartwatches), Beauty Accessories and Sundries\nManage and coordinate client briefs, working with team members and factories to prepare responses\nAct as liaison between cross-functional departments to ensure effective communications across the organisation to uphold excellence in client service\nBuild/develop and maintain strong relationships with clients through effective project management and delivery and exceeding expectations with innovative solutions\nBuild/develop and maintain strong relationships with suppliers/factories, keeping factory base up-to-date and in line with clients\u2019 current and future needs and objectives\nHands-on resolution of day-to-day operational/supply chain issues and complications; identify, propose and implement workable solutions to existing and potential problems\nPrepare timely submission of up-to-date presentations on global and regional product, design, and industry trends and insights; coordinate with designers to develop seasonal concepts and proposals\nLead or participate in and contribute to in-person/virtual client meetings with excellent presentation skills, preparation, understanding of client needs, and fluency in the use of Microsoft Teams/Zoom and their tools\nPro-actively assist and report to Directors with business development plans with existing and potential clients to achieve growth and profitability targets\nRequirements:\nUniversity graduate, preferably in merchandising, fashion management, or related disciplines\n10 years of relevant hands-on experience in product development, merchandising and sourcing for the Europe/US markets\nBackground in multi-national trading/sourcing companies with client-facing experience and an understanding in manufacturing processes\nFluent in English, Mandarin, and Cantonese\nWorking knowledge in quality control and product regulatory compliance\nResponsible and flexible team player and leader with attention-to-detail and strong inter-personal, communication, organisational and negotiation skills\nAbility to cope with tight deadlines\nTravel is required\n\nExcellent career opportunities for promotion and remuneration for the right applicants. Please email your resume and cover letter with current and expected salary by clicking \"Apply Now\".\n\nWe thank all applicants for their interests, but only shortlisted candidates will be notified. All personal data collected will be treated as strictly confidential and used for recruitment purposes only.", "employment_types": ["Full Time"], "selling_points": [], "locations": ["Lai Chi Kok"], "categories": ["Merchandising & Purchasing", "Electronics", "Watch", "Others"], "post_time": "2022-01-05T09:10:54Z", "salary": {"currency": null, "max": null, "min": null, "period": "monthly", "term": null}, "salary_visible": false, "title_keywords": ["merchandising manager"], "responsibilities": ["product categories", "merchandising", "coordinate with", "presentations", "develop", "coordinate", "project management", "resolution", "maintain", "design", "teams", "quality control", "plans", "report"], "requirements": {"degrees": ["university graduate"], "majors": ["related disciplines"], "languages": ["cantonese", "english", "mandarin"], "language_level": ["fluent"], "hard_skills": [], "soft_skills": ["flexible", "responsible", "inter-personal", "communication", "hands-on", "negotiation skills", "team player", "client-facing"], "languages_combined": [{"language": "cantonese", "language_level": ["fluent"]}, {"language": "english", "language_level": ["fluent"]}, {"language": "mandarin", "language_level": ["fluent"]}]}, "experience_required": {"duration": ["10 years"], "field": ["manufacturing", "merchandising", "product development", "trading", "client-facing"]}}, {"job_id": "100003009028041", "location_code": "hk", "company": "Swissam Products Limited", "job_title": "Purchasing Manager/ Project Purchasing Manager", "description": "Key Areas of Responsibilities:\n\n\n\nManage suppliers and drive their performance improvement, to ensure products supplied to MGI meet the pre-determined standards of compliance, quality, delivery reliability, flexibility, lowest integral cost and financial stability.\nAchieve the assigned supplier\u2019s management improvement of Cost competitiveness, Leadtime reduction, delivery reliability and quality improvement etc., to contribute in achieving company target of sustainable profitable growth.\nEnsure that optimized TCO (cost, quality, availability) are assured in product and business creation, and through their full life cycle.\nDrive early supplier involvement and identify cost drivers to influence design decision making and achieve target cost.\nBe responsible for executing and continuously driving improvement for all key purchasing processes with suppliers, e.g. New product cost management, Annual negotiation, Business review meeting, Supplier scorecard, Supplier improvement program, etc.\nManage risk relating to quality, cost, delivery, supply of purchases and fulfilment of social compliance standard.\nTo manage and strengthen the supplier relationship in a professional, systematic, and ethical way\nCollaborate closely with related functions of FE and global team to optimize the working process in value chain.\n\nSkills and competence required:\n\n\nUniversity degree holder is preferred\nMinimum 5 \u2013 8 years solid purchasing experience, experience in project management is a plus.\nStrong leadership, act with integrity, business acumen and strong negotiation skills\nGood communication, a self-motivated team player with initiative to work under pressure\nGood command of both spoken and written Chinese and English\nHigh competency level in MS Office applications\nSAP software experience is an advantage", "employment_types": ["Full Time", "Permanent", "Temporary"], "selling_points": ["Purchasing", "Sourcing", "Manager"], "locations": ["Tin Hau"], "categories": ["Merchandising & Purchasing", "Watch"], "post_time": "2022-01-07T01:19:41Z", "salary": {"currency": null, "max": null, "min": null, "period": "monthly", "term": null}, "salary_visible": false, "title_keywords": ["purchasing manager"], "responsibilities": ["collaborate", "cost", "management", "compliance", "quality", "review", "design", "executing"], "requirements": {"degrees": ["university degree"], "majors": [], "languages": ["english", "chinese"], "language_level": ["good command"], "hard_skills": ["plus", "sap", "acumen", "project management", "ms office"], "soft_skills": ["self-motivated", "integrity", "communication", "project management", "negotiation skills", "business acumen", "team player", "leadership", "initiative", "work under pressure"], "languages_combined": [{"language": "english", "language_level": ["good command"]}, {"language": "chinese", "language_level": ["good command"]}]}, "experience_required": {"duration": ["8 years"], "field": ["purchasing", "project management"]}}, {"job_id": "100003009022799", "location_code": "hk", "company": "Greenland Watch Ltd", "job_title": "Clerk", "description": "We are a well-established watch manufacturer with automation assembling line in Hong Kong, to cope with our continuous growth, we are seeking high caliber candidate for the above position.\n\n\u00a0Responsibilities:\n\nProvide clerical support to the Sales Team\nResponsible for data entry and processing of the documents timely and accurately\n\nRequirements:\u00a0\n\nForm 5 graduate or above;\n2-3 years of relevant experience is preferable\nProficiency in MS Office applications and Chinese word processing\nGood command in English and Chinese\u00a0\nImmediate availability is highly preferred\n\n\u00a0We Offer:\u00a0\n\n5-day\u00a0work week\n14 days annual leave\nDouble pay\nMedical scheme\n\n", "employment_types": ["Full Time", "Permanent"], "selling_points": [], "locations": ["Hung Hom"], "categories": ["Merchandising & Purchasing", "Watch", "Sales, CS & Business Devpt", "Sales Administration"], "post_time": "2022-01-05T06:35:03Z", "salary": {"currency": null, "max": null, "min": null, "period": "monthly", "term": null}, "salary_visible": false, "title_keywords": ["clerk"], "responsibilities": ["provide clerical support", "sales team", "data entry"], "requirements": {"degrees": ["form 5"], "majors": [], "languages": ["english", "chinese"], "language_level": ["proficiency", "good command"], "hard_skills": ["chinese word processing", "ms office"], "soft_skills": [], "languages_combined": [{"language": "english", "language_level": ["good command"]}, {"language": "chinese", "language_level": ["proficiency", "good command"]}]}, "experience_required": {"duration": ["2-3 years"], "field": ["relevant experience"]}}, {"job_id": "100003009024413", "location_code": "hk", "company": "City Chain Company Limited", "job_title": "Management Trainee (Merchandising)", "description": "Our Merchandising Team recruits a Management Trainee (Merchandising). This is truly a unique opportunity to fast track your career field. We offer an attractive salary package and willing to pay above market for a high calibre candidate.\n\n\u00a0\nTop management exposure and support\n\nThe programme incorporates regular professional corporate training sessions\u00a0and comprehensive on-the-job training. During the training period, you will be led by a Brand Manager, meet with Senior Management to pass through the whole training\nOpportunities to learn from experienced leaders sharing their working\u00a0 experience and practical skills for fieldwork\n\nLet\u2019s Work together\n\n18 months comprehensive programs\nVery attractive remuneration and benefits\nClosely monitor stock level and sell-through and ensure the execution of stock allocation, replenishment, re-order the stock and transfer between shops\nCo-ordinate with regional teams, operations and warehouse team for stock transfer and replenishment\nCo-ordinate with the e-Commerce team about the arrangement of the new products\nPrepare sales reports, sales performance analysis, inventory control analysis and merchandising forecasts\nAnalyze market and competitor data and consumer trends to assist in developing future buying plans\nTo handle any other ad hoc tasks as assigned\nWe are looking for\n\nFresh University graduate in Merchandising, Fashion and Textile, Supply Chain, Business Administration, or related disciplines with a maximum of 2 years of relevant working experience\nCandidates with internship programming experience will be at an advantage\n\nTo be eligible you must be\n\nA capable candidate with energetic, self-motivated with strong communication,\u00a0interpersonal and problem-solving skills\nPositive to challenges and capable to identify solutions to problems\nStrong numerical sense, with analytical, coordination and interpersonal skills\nAbility to work independently and be customer-oriented\nDetailed, proactive, well organized and willing to learn\nProficient in MS Word, Excel, PowerPoint and Chinese Word Processing\u00a0\nGood command of written and spoken English, Mandarin and Cantonese\u00a0\nImmediate availability\n\n\u00a0Join us now:\n\nPlease send\u00a0full resume stating your academic qualifications, career history, availability with current and expected salary\u00a0to: The\u00a0Human Resources Manager\n\n\u00a0On offer is a competitive package\n\nAttractive\u00a0Remuneration\n5 Days Work\nAnnual Leave\nFamily Leave\nMonthly Early Release\u00a0\n\n\n\nBirthday Leave with gifts\nMarriage Leave with red packets\nExamination Leave\nMedical Scheme\nStaff Discount\n\n\n\nWebsite:\u00a0www.citychain.com\n", "employment_types": ["Full Time"], "selling_points": ["Management Trainee Program", "Fresh University", "University graduate in Retail Merchandising"], "locations": ["Wong Tai Sin Area"], "categories": ["Merchandising & Purchasing", "Watch"], "post_time": "2022-01-05T23:54:36Z", "salary": {"currency": null, "max": null, "min": null, "period": null, "term": null}, "salary_visible": false, "title_keywords": ["management trainee", "merchandising"], "responsibilities": ["management", "merchandising"], "requirements": {"degrees": [], "majors": [], "languages": [], "language_level": [], "hard_skills": [], "soft_skills": ["unique"], "languages_combined": []}, "experience_required": {"duration": [], "field": []}}, {"job_id": "100003009013508", "location_code": "hk", "company": "Richemont Asia Pacific Limited - Cartier", "job_title": "Senior Merchandising Executive - Regional High Jewellery, Asia", "description": "POSITION SUMMARY\n\nThis\u00a0position\u00a0is responsible for supporting both Fine Jewellery (FJ) and Fine Watches (FW) merchandising and stock planning related activities in Asia. S/he will focus on event related matters from retro planning, stock coordination, transfer among markets and event sales follow up. S/he will be responsible for maintaining the business dashboard while also being a key user of system tools to support daily sales operation.\n\nReports to Asia High Jewellery Merchandising Director\n\nRESPONSIBILITIES\n\nMerchandising activities\nSupport both FJ and FW merchandising daily operations activities\nFocus on events stock related activities, such as retro-planning and follow through for the whole process\nWork closely with merchandising teams across the market and establish a strong relationship, credibility and trust with them regarding event merchandising strategy\nLiaise, work and follow up closely with markets in terms of stock request and logistic arrangement for event stock support\nPrepare event sales report on fulfillment, hit rate and deliveries\nFollow up on event sold pieces status, i.e. pieces transfer to sold market, new production or pieces with workshop\nAnalyze on event stock performance including both fulfillment and hit rate\nEnsure logistics flows, shipments and processes are optimized during event process and look for continuous improvement in order to shorten the required lead time\nBusiness Dashboard\nDevelop and maintain business dashboard for FJ and FW by Power BI with accuracy\nAdjust and keep upgrading the dashboard according to business needs\nTrack, analyze & effectively communicate on key sales, distribution and inventory performance indicators\nKey user of system tools\nAct as the key user on system tools such as PLAZA and PEGA\nMonitor the accuracy of reservation status in PLAZA\nMaintain event selection in PLAZA during international / inter-regional events\nCollect feedback from the market and share comments with central team for continuous improvement on system tools\n\nRequirements\n\nBachelor\u2019s degree, preferably in Business / Supply Chain with Financial / Statistics / Quantitative Methods / Mathematical background\n5 years prior commercial, management or merchandising experience in MNC\nAdvanced working knowledge of Excel, Power BI, SAP\nExcellent with PowerPoint presentations\nStrong attention to detail and analytical mind-set\nAbility to multi-task, prioritize and meet deadlines under pressure\nNumerically sensitive with commercial retail mindset\nQuick-thinker and can think through complex stock situations\nSensitivity to cultural differences\nAdapt to change\nLanguages:\u00a0English and Chinese", "employment_types": ["Full Time", "Permanent"], "selling_points": ["Regional Exposure", "Great working environment", "Good career progression"], "locations": ["Central"], "categories": ["Merchandising & Purchasing", "Watch", "Others"], "post_time": "2022-01-03T02:25:39Z", "salary": {"currency": null, "max": null, "min": null, "period": "monthly", "term": null}, "salary_visible": false, "title_keywords": ["executive", "merchandising"], "responsibilities": ["liaise", "sales report", "power bi", "fulfillment", "workshop", "merchandising", "teams", "inventory", "logistic arrangement", "develop", "monitor", "daily operations", "maintain", "logistics", "comments", "planning"], "requirements": {"degrees": ["degree", "bachelor"], "majors": ["business", "statistics"], "languages": ["english", "chinese"], "language_level": [], "hard_skills": ["excel", "bi", "sap", "powerpoint", "presentations"], "soft_skills": ["multi-task", "advanced", "under pressure", "sensitivity", "prioritize", "analytical mind", "attention to detail", "sensitive", "meet deadlines"], "languages_combined": [{"language": "english", "language_level": []}, {"language": "chinese", "language_level": []}]}, "experience_required": {"duration": ["5 years"], "field": ["commercial", "management", "merchandising"]}}, {"job_id": "100003009008326", "location_code": "hk", "company": "ConnectedGroup Limited", "job_title": "Purchasing Manager - Watch", "description": "Purchasing Manager - Watch\n\nMy client is a US watch, jewelry & fashion accessories retailer, who is looking for a Purchasing Manager to mainly look after Watch category.\n\nDuties:\n\nDrive purchasing processes with suppliers, e.g. business demand meeting, negotiation, supplier scorecard, supplier improvement program\nDrive sourcing strategy and supplier sourcing\nAchieve the supplier's management improvement of Leadtime reduction, delivery reliability, cost competitiveness and quality improvement etc., to achieve company target of sustainable profitable growth\nDrive early supplier involvement and identify cost drivers to influence design decision making and achieve target cost\nOptimize the organization of purchasing function, sourcing department of Asia value chain, and collaborate closely with PD, Engineering Planning & Quality, Customer Service and Finance departments to ensure smooth cross functional cooperation and effective teamwork\nMonitor supplier and vendor compliance with contractual agreements\nAd-hoc cross-functional projects\n\nRequirements:\n\nBachelor's Degree or above\nMinimum 5 years' experience in purchasing with watch / at least eyewear background\nIndividual contributor\nSAP software knowledge is a plus\nGood command of English\n\nPlease send your CV to Angela Tsui from ConnectedGroup (Angela.Tsui@connectedgroup.com) for more details. Email address could be found on LinkedIn.\n\nFor more opportunities, please visit www.connectedgroup.com", "employment_types": ["Full Time", "Permanent"], "selling_points": ["US watch, jewelry & fashion accessories retailer", "Mainly look after watch category", "Strong excel & detail minded is big plus"], "locations": ["Not Specified"], "categories": ["Merchandising & Purchasing", "Watch", "Procurement / Purchasing / Sourcing"], "post_time": "2021-12-30T07:38:18Z", "salary": {"currency": null, "max": null, "min": null, "period": "monthly", "term": null}, "salary_visible": false, "title_keywords": ["purchasing manager"], "responsibilities": ["collaborate", "ad-hoc", "cost", "management", "compliance", "quality", "monitor", "design", "customer service", "planning"], "requirements": {"degrees": ["degree or above", "bachelor"], "majors": [], "languages": ["english"], "language_level": ["good command"], "hard_skills": ["plus", "sap"], "soft_skills": [], "languages_combined": [{"language": "english", "language_level": ["good command"]}]}, "experience_required": {"duration": ["minimum 5 years"], "field": ["purchasing"]}}, {"job_id": "100003008995243", "location_code": "hk", "company": "Manson Precision Industrial Limited", "job_title": "Watch Designer", "description": "Responsibilities:\n\nResponsible for graphic design of watches and packaging.\nGood sketching and drafting technique.\nBasic knowledge of design techniques, tools and construction.\nCan handle design project independently.\nBe able to cooperate with other teams (e.g. sales & Engineering)\nRequirements:\n\nCertificate/ Diploma in Design or related discipline.\n3 + years of watch design experience.\nProficient in 2D/3D software: Adobe Illustrator, CorelDraw, Microsoft Office, Adobe Photoshop, Rhinoceros and KeyShot or equivalent.\nInnovative and creative.\nSelf-motivated, highly organized and strong conceptual rendering skills and presentation skills of 2D & 3D design.\nGood command of English, Cantonese and Mandarin\nImmediately available is preferred.", "employment_types": ["Full Time", "Permanent"], "selling_points": [], "locations": ["Tsuen Wan Area"], "categories": ["Design", "Fashion", "Graphics", "Merchandising & Purchasing", "Watch"], "post_time": "2021-12-29T01:44:39Z", "salary": {"currency": null, "max": null, "min": null, "period": "monthly", "term": null}, "salary_visible": false, "title_keywords": ["designer"], "responsibilities": ["graphic design", "teams", "cooperate with", "design"], "requirements": {"degrees": ["certificate", "diploma"], "majors": ["design"], "languages": ["cantonese", "english", "mandarin"], "language_level": ["good command"], "hard_skills": ["microsoft office", "3d software", "adobe photoshop", "adobe illustrator"], "soft_skills": ["organized", "self-motivated", "creative", "presentation skills", "innovative"], "languages_combined": [{"language": "cantonese", "language_level": ["good command"]}, {"language": "english", "language_level": ["good command"]}, {"language": "mandarin", "language_level": ["good command"]}]}, "experience_required": {"duration": ["3 + years"], "field": ["design"]}}, {"job_id": "100003009010017", "location_code": "hk", "company": "Fossil (East) Ltd", "job_title": "Business Process Re-Engineering Coordinator (Assistant Business Analyst)", "description": "What\u2019s the role about?\nWork with different internal teams to enhance business operations and digital transformation projects\nPlan, execute and control operation / system improvement projects assigned by manager\nFollow up China accounting & statutory requirements and provide solutions for improvement from both operational and system perspectives\nAssist management decision-making by providing operation data analysis\nAssist for system master data maintenance\nSetup & control proper master data input, revision and operation flows\nPrepare training materials & documents and provide training to user department\nWhat we are looking for:\nDegree or above in Information Systems, Information Management, Computer Science or related discipline\nRelevant experience in business analysis/project management role will be an advantage\nFamiliar with MS Access or Navision (NAV) is a plus\nDetail-minded with good analytical skills\nStrong interpersonal and communication skills\nAble to work under pressure and deadlines\nGood command of both written and spoken English and Mandarin\n\nTogether, we make great things happen. Apply now and be part of our tomorrow.\n\n\nInterested parties please send us your full resume with contact details, preferably with your current and expected salary.\n\nFossil Group is an Equal Opportunity employer. All qualified applicants will receive consideration of employment without regard to race, disability, gender, religion, family status, marital status, national origin, sexual orientation, veteran status, gender identity or \u00a0expression or any other basis protected by local, state, or national law. Only short-listed candidates will be notified. All information received will be kept in strict confidence and only for employment-related purpose.", "employment_types": ["Full Time", "Permanent"], "selling_points": [], "locations": ["Tsuen Wan Area"], "categories": ["Information Technology (IT)", "DBA", "Product Management / Business Analyst", "Merchandising & Purchasing", "Watch"], "post_time": "2021-12-31T02:48:13Z", "salary": {"currency": null, "max": null, "min": null, "period": "monthly", "term": null}, "salary_visible": false, "title_keywords": ["coordinator", "business analyst", "assistant"], "responsibilities": ["provide training", "control", "management", "maintenance", "data", "operations", "systems", "teams", "data input", "provide solutions", "data analysis", "statutory requirements", "project management", "communication", "plan", "business analysis", "setup", "work under pressure"], "requirements": {"degrees": ["degree or above", "master"], "majors": ["computer science"], "languages": ["english", "mandarin"], "language_level": ["good command"], "hard_skills": ["plus", "maintenance", "analysis", "analytical skills", "project management", "make"], "soft_skills": ["detail-minded", "communication skills", "analytical skills", "project management", "interpersonal", "work under pressure"], "languages_combined": [{"language": "english", "language_level": ["good command"]}, {"language": "mandarin", "language_level": ["good command"]}]}, "experience_required": {"duration": [], "field": ["business analysis", "project management", "relevant experience"]}}, {"job_id": "100003009037427", "location_code": "hk", "company": "DFS Hong Kong Limited", "job_title": "Senior Assistant Planning Manager, Watches & Jewellery - DFS91121319", "description": "We are seeking a self-motived Senior Assistant Planning Manager to join our well-established team. With guidance from the Planning Manager, you will quantify the Merchandise Strategy for a segment of the business through development of the seasonal and Brand/Class location sales plans. You will work on stock forecast, ordering and allocation to maximize inventory productivity and gross margin. You will be pipelined as the Associate Planning Manager in your career ladder.\n\nOpen-To-Buy & Inventory Management\n\n\nEnsure monthly accurate and timely completion of segment Open-To-Buy (OTB)\nProvide ongoing feedback and information to team members on sales results, competitive practices, vendor issues, and other specific information which could impact business performance\nIdentify and evaluate sales and gross margin opportunities\nMonitor and forecast segment inventory levels\nEstablish and maintain supply chain pipeline by determining order quantities and placing orders with suppliers\nBuy merchandise for the divisions base on assortment plan, model stock and market trends to achieve optimal sales, profit and inventory performance\nIdentify slow and best sellers in inventory; \u00a0respond to\u00a0 merchandise performance to maximize sales and minimize risks\nEnsures all inventory targets are met, including turnover, currency and style/SKU counts\n\nPeople Development\n\nEncourage and support the development of talents; offer honest and constructive feedback to direct reports and business partners to foster people development\nFocus on self-development to prepare for promotion to Associate Planning Manager\nKey Requirements\n\nBachelor\u2019s Degree preferred\nMinimum of 4 years\u2019 experience in a merchandising or planning function, with financial and analytical exposure\nExperience in the luxury market and international business preferred\nNegotiation experience required\nStrong interpersonal skills and be able to deliver high-level presentations\nFluent in both spoken and written English", "employment_types": ["Full Time", "Permanent"], "selling_points": ["World's Leading Luxury Travel Retailer", "Work Life Balance, Five-day Work Week", "International & Dynamic Working Environment"], "locations": ["Quarry Bay"], "categories": ["Transportation & Logistics", "Inventory / Warehousing", "Merchandising & Purchasing", "Watch", "Procurement / Purchasing / Sourcing"], "post_time": "2022-01-11T02:47:09Z", "salary": {"currency": null, "max": null, "min": null, "period": "monthly", "term": null}, "salary_visible": false, "title_keywords": ["manager", "assistant"], "responsibilities": ["open-to-buy", "inventory", "merchandising", "otb", "inventory management", "maintain", "placing orders", "plan", "monitor", "presentations", "reports", "forecast", "competitive practices", "guidance", "determining order quantities", "buy merchandise", "vendor issues", "sales results", "evaluate", "sales plans", "planning"], "requirements": {"degrees": ["degree", "bachelor"], "majors": [], "languages": ["english"], "language_level": ["fluent"], "hard_skills": ["ladder", "focus", "vendor", "presentations"], "soft_skills": ["negotiation", "timely", "interpersonal skills", "honest", "focus", "accurate", "constructive"], "languages_combined": [{"language": "english", "language_level": ["fluent"]}]}, "experience_required": {"duration": ["minimum of 4 years"], "field": ["analytical", "merchandising", "business", "planning", "financial"]}}, {"job_id": "100003009024414", "location_code": "hk", "company": "City Chain Company Limited", "job_title": "Senior Graphic Designer", "description": "Let\u2019s Work together\n\n\nCreating graphic design, sketches from design concepts and animation for all artworks\nProduct shooting and simple photos retouch\nCreate graphic designs and animation for all artworks such as POSM, company, website, social media platforms, EDMs, Google banner ads, etc.,\nWork with internal parties and vendors for materials output\nAd-hoc projects as assigned\nWe are looking for\n\nHigher Diploma in Design or related disciplines\nMinimum 2 years of working experience in graphic or multimedia design. Those candidates who have retail industry is an advantage\nStrong creativity, Good aesthetic sense and fashion flair, high sensitivity to market trends\nCan handle multi-task and have good time management\nAble to handle projects independently and under pressure\nDetails and open-minded\nResponsible, organized, hardworking and positive good attitude\nProficient in design software and graphics editing software, Illustrator and Photoshop and familiar with MAC\nGood command of written and spoken English, Mandarinand Cantonese\nPortfolio links should be provided in the resume\nImmediate availability is preferred\n\nJoin us now:\n\nPlease send\u00a0full resume stating your academic qualifications, career history, availability with current and expected salary\u00a0to: The\u00a0Human Resources Manager\n\n\u00a0On offer is a competitive package\n\nAttractive\u00a0Remuneration\n5 Days Work\nAnnual Leave\nFamily Leave\nMonthly Early Release\u00a0\n\n\n\nBirthday Leave with gifts\nMarriage Leave with red packets\nExamination Leave\nMedical Scheme\nStaff Discount\n\n\n\nWebsite:\u00a0www.citychain.com\n", "employment_types": ["Full Time"], "selling_points": ["Creating graphic design", "Minimum 2 years of working experience in graphic", "Higher Diploma in Design or related disciplines"], "locations": ["Wong Tai Sin Area"], "categories": ["Merchandising & Purchasing", "Watch"], "post_time": "2022-01-05T23:55:09Z", "salary": {"currency": null, "max": null, "min": null, "period": null, "term": null}, "salary_visible": false, "title_keywords": ["senior graphic designer"], "responsibilities": ["multimedia design", "design concepts", "management", "graphics", "edms", "software", "editing", "graphic design", "social media platforms", "product shooting", "graphic designs", "sketches", "website", "design", "internal parties", "ad-hoc projects", "animation"], "requirements": {"degrees": ["diploma"], "majors": ["related disciplines", "design"], "languages": ["cantonese", "english"], "language_level": ["good command"], "hard_skills": ["simple", "graphics", "illustrator", "scheme", "multimedia", "red", "photoshop"], "soft_skills": ["organized", "independently", "multi-task", "under pressure", "responsible", "sensitivity", "open-minded", "positive", "time management", "hardworking"], "languages_combined": [{"language": "cantonese", "language_level": ["good command"]}, {"language": "english", "language_level": ["good command"]}]}, "experience_required": {"duration": ["minimum 2 years"], "field": ["graphic", "design"]}}]