[{"job_id": "100003009038499", "location_code": "hk", "company": "Estate Agents Authority", "job_title": "ASSISTANT MANAGER (Disciplinary Proceedings) (Ref No.: EAA-2021/24)", "description": "Key Responsibilities\n\nReporting to the Legal Counsel (Disciplinary Proceedings), the incumbent is responsible for the following:\n\nScrutinize and prepare disciplinary cases for submission to the Disciplinary Committee of the Authority\nProvide analysis on evidence to facilitate disposal of disciplinary cases\nPresent cases at disciplinary inquiry hearings conducted by the Disciplinary Committee\nSupervise and coach staff members to carry out the disciplinary proceedings function\nAssist the Section Head in the management of the Disciplinary Proceedings Section\nPerform such other duties as may from time to time be assigned\nRequirements\nA recognized university degree in Law\nAt least 3 years\u2019 relevant experience in prosecution or litigation preferably 2 years of which at supervisory level; or a qualified solicitor / barrister with at least 1 year\u2019s post-qualification experience in litigation practice\nGood command of both written and spoken English and Chinese (Preferably attained Grade \u201cC\u201d or above in English Language (Syllabus B) and Chinese Language in HKCEE, or Level 4 or above in HKDSEE, or equivalent)\nQualified legal practitioner, legal executive in litigation, or court/tribunal prosecutor preferred\nGood written and verbal presentation skill\nTerms of Appointment\nCompetitive remuneration package commensurate with the selected candidate\u2019s qualifications and experience will be offered. The appointee will initially be offered a 3-year contract, subject to renewal upon satisfactory performance and the service needs of the Authority.\nApplication Procedure\u00a0\u00a0\u00a0\u00a0\u00a0\u00a0\u00a0\u00a0\u00a0\u00a0\u00a0\u00a0\u00a0\u00a0\u00a0\u00a0\u00a0\u00a0\u00a0\u00a0\u00a0\u00a0\u00a0\u00a0\u00a0\u00a0\u00a0\u00a0\u00a0\u00a0\u00a0\u00a0\u00a0\u00a0\u00a0\u00a0\u00a0\u00a0\u00a0\nApplications with full resume indicating your current and expected salaries and your public examination results should be sent to: Human Resources Section, Estate Agents Authority, 7/F, E-Trade Plaza, 24 Lee Chung Street, Chaiwan, Hong Kong or email via \"Apply now\" at\u00a0 not later than 31 January 2022. Candidates who have already responded to our previous advertisement of the same post in November 2021 need not re-apply. Please mark \u201cPrivate and Confidential\u201d on the envelope and quote the post applied for and its reference number on the envelope.\nCandidates who are not invited to attend an interview within 6 weeks from the closing date may assume their applications unsuccessful. Applications may be considered for other suitable positions within the Authority. All applications will be treated in strict confidence. Personal data provided in the applications will only be used for recruitment-related purposes. All information on non-shortlisted applicants will be destroyed after 6 months.\n\n\nWE ARE AN EQUAL OPPORTUNITIES EMPLOYER", "employment_types": ["Full Time", "Contract"], "selling_points": ["Scrutinize and prepare disciplinary cases", "Present cases at disciplinary inquiry hearings", "A recognized university degree in Law"], "locations": ["Wan Chai"], "categories": ["Public / Civil", "Civil Services", "Professional Services", "Legal & Compliance"], "post_time": "2022-01-16T21:49:59Z", "salary": {"currency": null, "max": null, "min": null, "period": "monthly", "term": null}, "salary_visible": false, "title_keywords": ["assistant manager"], "responsibilities": ["reporting", "analysis", "management", "other duties"], "requirements": {"degrees": ["university degree"], "majors": ["law"], "languages": ["english", "chinese"], "language_level": ["good command"], "hard_skills": ["presentation skill", "c"], "soft_skills": ["presentation skill", "confidence"], "languages_combined": [{"language": "english", "language_level": ["good command"]}, {"language": "chinese", "language_level": ["good command"]}]}, "experience_required": {"duration": ["at least 3 years", "2 years", "at least 1 year"], "field": ["supervisory level", "post-qualification", "relevant experience"]}}, {"job_id": "100003009042190", "location_code": "hk", "company": "Estate Agents Authority", "job_title": "ADMINISTRATIVE ASSISTANT (Licensing)  (Ref No.: EAA-2022/02)", "description": "Key Responsibilities\nThe incumbent will be posted to the Licensing Section to handle the following:\n\n\nvet and pre-approve license applications\nassist in monitoring the progress of various license applications\nassist in the administrative and logistical arrangement for committee meetings\ncompile statistical reports\nliaise with mainland authorities in relation to the mutual recognition scheme\nsupervise and coach junior / new team members\nRequirements\n\n\nA recognized university degree\nAt least 2 years\u2019 relevant experience; preferably in customer service\nGood command of both written and spoken English and Chinese; fluency in Putonghua is an advantage\nProficiency in software applications (MS Word, Excel, Powerpoint, Access and Chinese word processing)\nGood interpersonal and communication skills\nStrong organizational skills and meticulous\nBe able to work independently and under pressure\nTerms of Appointment\nCompetitive remuneration package commensurate with the selected candidate\u2019s qualifications and experience will be offered. The appointee will initially be offered a 3-year contract, subject to renewal upon satisfactory performance and the service needs of the Authority.\nApplication Procedure\nApplications with full resume indicating your current and expected salaries and your public examination results should be sent to: Human Resources Section, Estate Agents Authority, 7/F, E-Trade Plaza, 24 Lee Chung Street, Chaiwan, Hong Kong or via email by clicking \"Apply Now\"\u00a0not later than\u00a031 January 2022. Please mark \u201cPrivate and Confidential\u201d on the envelope and quote the post applied for and its reference number on the envelope.\nCandidates who are not invited to attend an interview within 6 weeks from the closing date may assume their applications unsuccessful. Applications may be considered for other suitable positions within the Authority. All applications will be treated in strict confidence. Personal data provided in the applications will only be used for recruitment-related purposes. All information on non-shortlisted applicants will be destroyed after 6 months.\u00a0\n\n\nWE ARE AN EQUAL\u00a0OPPORTUNITIES EMPLOYER", "employment_types": ["Full Time", "Contract"], "selling_points": [], "locations": ["Chai Wan"], "categories": ["Admin & HR", "Clerical / Admin Staff", "Public / Civil", "Civil Services", "Sales, CS & Business Devpt", "Customer Service - Supervisor / Officer"], "post_time": "2022-01-16T21:50:00Z", "salary": {"currency": null, "max": null, "min": null, "period": "monthly", "term": null}, "salary_visible": false, "title_keywords": ["administrative assistant"], "responsibilities": ["liaise with", "license applications", "monitoring", "reports"], "requirements": {"degrees": ["university degree"], "majors": [], "languages": ["putonghua", "english", "chinese"], "language_level": ["fluency", "advantage", "proficiency", "good command"], "hard_skills": ["excel", "chinese word processing", "powerpoint", "ms word"], "soft_skills": ["communication skills", "meticulous", "organizational skills", "work independently", "under pressure", "confidence", "customer service", "interpersonal"], "languages_combined": [{"language": "putonghua", "language_level": ["fluency", "advantage"]}, {"language": "english", "language_level": ["good command"]}, {"language": "chinese", "language_level": ["proficiency", "good command"]}]}, "experience_required": {"duration": ["at least 2 years"], "field": ["relevant experience"]}}, {"job_id": "100003009052953", "location_code": "hk", "company": "Roundtable \u5be6\u653f\u5713\u684c", "job_title": "\u7530\u5317\u8fb0\u8b70\u54e1\u8fa6\u4e8b\u8655 - Office of Hon. Michael Tien - Public Affairs Assistant", "description": "Requirements:\n\nHave completed secondary 5 or equivalent\nBe able to communicate effectively in Chinese and English, both in written and spoken forms and\nPreferably be proficient in Urdu (or other NEC languages)\nWith proficiency in Cantonese and / or\u00a0\nWith relevant working experience and knowledge in running programmes for non-ethnic Chinese, publicity and promotional work, receiving the public or event coordination.\nDuties:\n\nTo assist in preparing and conducting group activities and programmes, publicity and promotional work, training and various activities, including but not limited to those for non-ethnic Chinese (NEC).\n\nLocation : Wanchai\n\nSelected candidate will be conducted Sexual Conviction Record Check\n\n\u00a0Interested parties, please send your resume in\u00a0WORD\u00a0format, stating your\u00a0current, expected salary and availability by clicking APPLY NOW.", "employment_types": ["Full Time"], "selling_points": ["Sense of current affairs preferred", "Fun and exciting work environment", "Fresh graduates are welcome"], "locations": ["Admiralty"], "categories": ["Media & Advertising", "Others", "Public / Civil", "Civil Services", "Marketing / Public Relations", "Public Relations - General / Support"], "post_time": "2022-01-17T04:41:24Z", "salary": {"currency": null, "max": null, "min": null, "period": "monthly", "term": null}, "salary_visible": false, "title_keywords": ["assistant"], "responsibilities": [], "requirements": {"degrees": [], "majors": [], "languages": ["urdu", "cantonese", "english", "chinese"], "language_level": ["proficiency", "proficient"], "hard_skills": [], "soft_skills": ["coordination"], "languages_combined": [{"language": "urdu", "language_level": ["proficient"]}, {"language": "cantonese", "language_level": ["proficiency"]}, {"language": "english", "language_level": []}, {"language": "chinese", "language_level": []}]}, "experience_required": {"duration": [], "field": ["relevant working experience"]}}, {"job_id": "100003009042106", "location_code": "hk", "company": "Estate Agents Authority", "job_title": "CLERK   (Ref No.: EAA-2022/03)", "description": "Job Description\n\nBe responsible for day-to-day schedule of the director;\nProvide all-rounded secretarial and administrative support to the director;\nCoordinate and accompany the director to attend meetings, conferences, PR functions and social events; and follow up relevant issues after attending the above events;\nLiaise with different government departments, interest groups and media for the organization;\nAssist in writing and preparing public policy related speeches, papers and submissions for the organization;\nAssist in management of promotional materials and online marketing scheme for the organization;\nAssist in event planning and coordination for the organization.\n\n\nJob Requirements\n\nHigher diploma or above in journalism, public administration, politics or other related disciplines;\n2 years\u2019 experience in handling public policy issues, fresh graduates will also be considered;\nStrong awareness of Hong Kong\u2019s current affairs;\nExperience in media, public relation, and event management is preferable;\nThoughtful, attentive, detail-minded and self-motivated;\nA good team player and able to finish multi tasks within tight deadline;\nGood oral and written skills in both Chinese and English (Cantonese is a must), proficiency in Putonghua is\u00a0advantageous;\nProficiency in using Microsoft Word, Excel, PowerPoint and Chinese word processing; and\nWilling to work overtime and in non-office settings.\nBenefits:\n\n\n14-day annual leave;\n5-day work week, bank holiday;\nContract-end gratuity;\nMedical Benefit (both hospitalization & out-patient);\nCompensation leave arrangement.\n\nInterested parties please send your full resume, current salary and expected salary.\n\nWe are an equal opportunity employer and welcome applications from all qualified candidates. The information provided will be treated in strict confidence and be used only for consideration of your application for relevant / similar posts within the Office of Hon. Michael Tien and Roundtable. Applicants not hearing from us within four weeks from the date of advertisement may consider their applications unsuccessful. We retain the unsuccessful applications for a maximum period of six months.", "employment_types": ["Full Time", "Contract"], "selling_points": [], "locations": ["Chai Wan"], "categories": ["Admin & HR", "Clerical / Admin Staff", "Public / Civil", "Civil Services", "Sales, CS & Business Devpt", "Customer Service - Supervisor / Officer"], "post_time": "2022-01-16T21:50:00Z", "salary": {"currency": null, "max": null, "min": null, "period": "monthly", "term": null}, "salary_visible": false, "title_keywords": ["clerk"], "responsibilities": ["management", "administrative support", "coordinate", "liaise with", "conferences", "promotional materials", "schedule", "coordination", "attend meetings", "planning"], "requirements": {"degrees": ["higher diploma or above"], "majors": ["journalism", "related disciplines", "public administration"], "languages": ["cantonese", "putonghua", "english", "chinese"], "language_level": ["proficiency", "good"], "hard_skills": ["excel", "microsoft word", "chinese word processing", "powerpoint"], "soft_skills": ["attentive", "detail-minded", "good team player", "oral", "self-motivated", "work overtime"], "languages_combined": [{"language": "cantonese", "language_level": ["good"]}, {"language": "putonghua", "language_level": ["proficiency", "good"]}, {"language": "english", "language_level": ["good"]}, {"language": "chinese", "language_level": ["good"]}]}, "experience_required": {"duration": ["2 years"], "field": ["public relation", "management", "media"]}}, {"job_id": "100003009053475", "location_code": "hk", "company": "Jupiter Lee & Co. Certified Public Accountants (Practising)", "job_title": "\u521d\u7d1a\u5be9\u8a08\u54e1", "description": "Key Responsibilities\n\nThe incumbent will be posted to the Licensing Section to handle the following:\n\napplications vetting\nenquiries handling (hotline and face-to-face) and reception support\ndata entry\ncard printing / application forms scanning\nletters drafting\nother general clerical duties\nRequirements\nLevel 2 or above in 5 subjects in the HKDSEE OR 5 passes in the HKCEE, including Chinese Language and English Language (Syllabus B), or equivalent\nAt least 2 years\u2019 clerical working experience\nProficiency in software applications (e.g. MS Word, Excel, PowerPoint and Chinese word processing)\nGood customer service skills\nMeticulous, mature personality and be a team player\n\nTerms of Appointment\n\nCompetitive remuneration package commensurate with the selected candidate\u2019s qualifications and experience will be offered. The appointee will initially be offered a 3-year contract, subject to renewal upon satisfactory performance and the service needs of the Authority.\n\nApplication Procedure\n\nApplications with full resume indicating your current and expected salaries and your public examination results should be sent to: Human Resources Section, Estate Agents Authority, 7/F, E-Trade Plaza, 24 Lee Chung Street, Chaiwan, Hong Kong or via email by clicking \"Apply Now\"\u00a0not later than 31 January 2022. Please mark \u201cPrivate and Confidential\u201d on the envelope and quote the post applied for and its reference number on the envelope.\n\nCandidates who are not invited to attend an interview within 6 weeks from the closing date may assume their applications unsuccessful. Applications may be considered for other suitable positions within the Authority. All applications will be treated in strict confidence. Personal data provided in the applications will only be used for recruitment-related purposes. All information on non-shortlisted applicants will be destroyed after 6 months.\n\n\u00a0 \u00a0 \u00a0 \u00a0 \u00a0 \u00a0 \u00a0 \u00a0 \u00a0 \u00a0 \u00a0 \u00a0 \u00a0 \u00a0 \u00a0 \u00a0 \u00a0 \u00a0\u00a0WE ARE AN EQUAL OPPORTUNITIES EMPLOYER\n", "employment_types": ["Full Time"], "selling_points": [], "locations": ["Central"], "categories": ["Public / Civil", "Civil Services", "Beauty Care / Health", "Others", "Marketing / Public Relations", "Public Relations - General / Support"], "post_time": "2022-01-17T07:02:15Z", "salary": {"currency": null, "max": null, "min": null, "period": "monthly", "term": null}, "salary_visible": false, "title_keywords": [], "responsibilities": ["scanning", "letters", "data entry"], "requirements": {"degrees": [], "majors": [], "languages": ["english", "chinese"], "language_level": [], "hard_skills": ["excel", "chinese word processing", "powerpoint", "ms word"], "soft_skills": ["customer service skills", "meticulous", "confidence", "mature", "team player"], "languages_combined": [{"language": "english", "language_level": []}, {"language": "chinese", "language_level": []}]}, "experience_required": {"duration": ["at least 2 years"], "field": ["clerical"]}}, {"job_id": "100003009044873", "location_code": "hk", "company": "ADECCO", "job_title": "Full-Time Library Project Services Assistant(\u5168\u8077\u5716\u66f8\u9928\u9805\u76ee\u52a9\u7406)", "description": "Library Services Assistant\u00a0(\u4e2d\u592e\u5716\u66f8\u9928\u9805\u76ee\u52a9\u7406)\n\nResponsibilities:\u00a0Responsible for handling borrowed books, readers' inquiries and processing of expired newspapers/journals, micro-film, process and update library materials\u00a0\n\nQualifications:\u00a0Secondary 5 or above, 5 subjects passed in the HKCEE or HKDSE including Chinese & English Level 2 / (Course B) Grade E or equivalent\u00a0 with associate degree or above and have 1 or more year(s) of work experience\u00a0\n\nSkills:\u00a0Good Cantonese, Fair English and Putonghua; Able to read and write Chinese and English, typing work is required\n\nLocation: Hong Kong Central Library\n\nWorking hours:\u00a0Monday to Sunday - 9:30 am to 9:15 pm, 7.8 hours a day,\u00a05 days per week, shift work\n\nSalary:\u00a0$11,500 - $12,500\u00a0per month (including bonus)\u00a0\n\u00a0 \u00a0 \u00a0 \u00a0 \u00a0 \u00a0 \u00a0 \u00a0\n\n(Welcome to the \"Medium and Senior Employment Scheme\" participants, housewives and new arrivals applications)\n\nIf you are interested, please email your resume to us.\u00a0The personal data collected will be kept confidential and used only for recruitment purposes\n\n\u8077\u4f4d\u540d\u7a31\uff1a\u4e2d\u592e\u5716\u66f8\u9928\u52a9\u7406\n\n\u8077\u8cac\uff1a\u00a0\u8ca0\u8cac\u8655\u7406\u501f\u9084\u66f8\u7c4d, \u8b80\u8005\u67e5\u8a62\u53ca\u8655\u7406\u904e\u671f\u7684\u5831\u7d19/\u671f\u520a, \u7e2e\u5fae\u8cc7\u6599, \u5354\u52a9\u8655\u7406\u5716\u66f8\u9928\u8cc7\u6599\u5206\u985e, \u4e0a\u67b6, \u642c\u904b\u53ca\u66f4\u65b0\u8cc7\u6599\u7b49\u5de5\u4f5c\n\n\u8cc7\u6b77\uff1a\u00a0\u4e2d\u4e94\u7a0b\u5ea6, \u826f\u597d\u7cb5\u8a9e, \u4e00\u822c\u82f1\u8a9e\u53ca\u666e\u901a\u8a71; \u61c2\u8b80\u5beb\u4e2d\u6587\u53ca\u82f1\u6587; \u4e2d\u5b78\u6703\u8003\u6216\u6587\u6191\u8a66\u4e94\u79d1\u5408\u683c, \u5305\u62ec\u4e2d\u6587, \u82f1\u6587\u79d1\u9054\u7b2c\u4e8c\u7d1a/(\u8ab2\u7a0b\u4e59)\u9054E\u7d1a\u6216\u540c\u7b49\u5b78\u6b77\u53ca\u5927\u5c08\u5b78\u6b77, \u9700\u5177\u6709\u6700\u5c11\u00a01\u00a0\u5e74\u5de5\u4f5c\u7d93\u9a57:\u61c2\u4e2d,\u82f1\u6587\u6253\u5b57\n\n\u5de5\u4f5c\u5730\u9ede\ufe30\u9999\u6e2f\u4e2d\u592e\u5716\u66f8\u9928\n\n\u5de5\u4f5c\u6642\u9593\ufe30\u661f\u671f\u4e00\u81f3\u65e5 - \u4e0a\u5348 9 \u6642 15 \u5206\u81f3\u4e0b\u5348 9 \u6642 15 \u5206, \u6bcf\u9031\u5de5\u4f5c\u00a05\u00a0\u5929, \u6bcf\u5929\u5de5\u4f5c\u00a07.8\u00a0\u5c0f\u6642\n\n\u85aa\u916c\uff1a$11,500 - $12,500/\u6708 (\u5305\u52e4\u5de5)\n\n\u5408\u9069\u4e4b\u7533\u8acb\u8005\u5c07\u7372\u500b\u5225\u901a\u77e5\u3002\u6240\u6709\u6536\u96c6\u7684\u500b\u4eba\u8cc7\u6599\uff0c\u6211\u5011\u5c07\u4fdd\u5bc6\u8655\u7406\u4e26\u53ea\u4f5c\u62db\u8058\u4e8b\u5b9c\u4e4b\u7528\u3002", "employment_types": ["Full Time", "Part Time"], "selling_points": [], "locations": ["Causeway Bay"], "categories": ["Public / Civil", "Civil Services"], "post_time": "2022-01-13T06:31:25Z", "salary": {"currency": null, "max": null, "min": null, "period": "monthly", "term": null}, "salary_visible": false, "title_keywords": [], "responsibilities": ["personal data", "recruitment"], "requirements": {"degrees": ["degree or above", "hkdse"], "majors": [], "languages": ["cantonese", "putonghua", "english", "chinese"], "language_level": ["good"], "hard_skills": ["processing", "typing", "scheme"], "soft_skills": ["responsible"], "languages_combined": [{"language": "cantonese", "language_level": ["good"]}, {"language": "putonghua", "language_level": ["good"]}, {"language": "english", "language_level": ["good"]}, {"language": "chinese", "language_level": ["good"]}]}, "experience_required": {"duration": [], "field": []}}, {"job_id": "100003009046473", "location_code": "hk", "company": "Nova Management Consultants Ltd", "job_title": "Project Assistant (Support Services)(Govt.) ($14,030) (10 Months)(Sai Kung district)", "description": "\n\u5730\u5340 : \u4e0a\u74b0\n\u8077\u8cac : \u8ca0\u8cac\u5be9\u8a08\u5de5\u4f5c\n\u8cc7\u6b77 : \u5c08\u4e0a\u6559\u80b2\uff1a\u6587\u6191/\u8b49\u66f8; \u826f\u597d\u7cb5\u8a9e; \u826f\u597d\u666e\u901a\u8a71; \u826f\u597d\u82f1\u8a9e; \u61c2\u8b80\u5beb\u4e2d\u6587; \u61c2\u8b80\u5beb\u82f1\u6587; \u61c2Peachtree; \u61c2MYOB; \u4fee\u8b80\u6703\u8a08\u79d1; \u5de5\u4f5c\u52e4\u596e\u3001\u6709\u8cac\u4efb\u611f; \u80fd\u7368\u7acb\u8655\u7406\u4e8b\u52d9\n\u5f85\u9047 : \u85aa\u91d1\u9762\u8b70, \u661f\u671f\u4e00\u81f3\u4e94: \u4e0a\u53489\u664215\u5206\u81f3\u4e0b\u53486\u6642\u53ca\u661f\u671f\u516d: \u4e0a\u53489\u6642\u81f3\u4e0b\u53481\u6642, \u6bcf\u9031\u5de5\u4f5c5\u5929\u81f35\u5929\u534a, \u6bcf\u5929\u5de5\u4f5c 4 - 7.5 \u5c0f\u6642\n\u7533\u8acb\u9808\u77e5 : \u6c42\u8077\u8005\u53ef\u96fb\u90f5(Apply Now)\u5c65\u6b77\u8868\u7d66\u674e\u6dd1\u82b3\u6703\u8a08\u5e2b\u4e8b\u52d9\u6240\u3002\u5982\u8981\u7d22\u53d6\u6536\u96c6\u500b\u4eba\u8cc7\u6599\u8072\u660e, \u8acb\u8207\u674e\u5973\u58eb(Tel:21110870)\u806f\u7d61\u3002\n\n", "employment_types": ["Full Time", "Contract"], "selling_points": ["Degree", "Good Chinese and English word processing skill", "Willing to take up outdoor duties"], "locations": ["Kwun Tong Area"], "categories": ["Public / Civil", "Civil Services"], "post_time": "2022-01-13T11:36:49Z", "salary": {"currency": null, "max": null, "min": null, "period": "monthly", "term": null}, "salary_visible": false, "title_keywords": ["project assistant"], "responsibilities": [], "requirements": {"degrees": [], "majors": [], "languages": [], "language_level": [], "hard_skills": [], "soft_skills": [], "languages_combined": []}, "experience_required": {"duration": [], "field": []}}, {"job_id": "100003009047846", "location_code": "hk", "company": "The Chinese General Chamber of Commerce", "job_title": "Clerk (Administration)", "description": "Working Area: Monkok or Sai Kung\n\nDuties:\n\nTo conduct site inspection and to take sample ride of local public services;\nTo assist in investigation and handling of public complaints;\nTo assist in collection of evidence about contravention of ordinances/ regulations;\nTo make photo, audio and video records during the investigations/inspections;\nTo prepare investigations/ Inspection reports, case referral letters and draft replies for public enquiries and complaints;\nTo carry out data searching, and prepare/ update of document, table, drawings and inventories of information.\nTo assist in signage design in Public transport facilities and publicity material for public transport services;\nTo assist in collection of quantitative data and information;\nTo perform other duties as required.\n\nJob requirements:\n\nHave a recognized university degree;\nGood commend of spoken and written English and Chinese;\nGood Chinese and English word processing skill and computer operating knowledge (including MS Word, MS Excel, MS PowerPoint and preferably computer information systems);\nGood analytical skills;\nGood interpersonal communication skills; and\nWilling to take up outdoor duties", "employment_types": ["Full Time", "Permanent"], "selling_points": [], "locations": ["Central"], "categories": ["Admin & HR", "Clerical / Admin Staff", "Receptionist", "Public / Civil", "Civil Services"], "post_time": "2022-01-14T04:02:18Z", "salary": {"currency": null, "max": null, "min": null, "period": "monthly", "term": null}, "salary_visible": false, "title_keywords": ["clerk"], "responsibilities": ["regulations", "perform other duties", "inspection reports", "data", "letters", "investigation", "site inspection", "drawings", "design", "audio"], "requirements": {"degrees": ["university degree"], "majors": [], "languages": ["english", "chinese"], "language_level": ["good"], "hard_skills": ["chinese and english word processing", "analytical skills", "ms excel", "ms powerpoint", "ms word"], "soft_skills": ["communication skills", "interpersonal", "analytical skills"], "languages_combined": [{"language": "english", "language_level": ["good", "good"]}, {"language": "chinese", "language_level": ["good", "good"]}]}, "experience_required": {"duration": [], "field": []}}, {"job_id": "100003009043191", "location_code": "hk", "company": "EIDEALINK LIMITED", "job_title": "Executive Assistant (multi post) ($27,000 - $31,000)", "description": "Clerk (Administration)\n\nDuties:\n\n-\u00a0\u00a0\u00a0\u00a0\u00a0\u00a0 Handle daily correspondence\n\n-\u00a0\u00a0\u00a0\u00a0\u00a0\u00a0 Provide administrative support to the department\n\n-\u00a0\u00a0\u00a0\u00a0\u00a0\u00a0 Act as substitute receptionist when needed\n\nQualifications:\n\n-\u00a0\u00a0\u00a0\u00a0\u00a0\u00a0 Form 5 or above, with PC knowledge, familiar with Excel& Photoshop preferable\n\n-\u00a0\u00a0\u00a0\u00a0\u00a0\u00a0 Experience in meeting venue set-up with basic technical knowledge of on-line meeting an advantage\n\n-\u00a0\u00a0\u00a0\u00a0\u00a0\u00a0 Fluent in Cantonese, English & Putonghua\n\n-\u00a0\u00a0\u00a0\u00a0\u00a0\u00a0 Good telephone manner with patience & politeness\n\n-\u00a0\u00a0\u00a0\u00a0\u00a0\u00a0 Preferable with at least 1 year relevant experience", "employment_types": ["Full Time"], "selling_points": ["Stable working environment", "Work in Government office", "5 days work"], "locations": ["Central"], "categories": ["Public / Civil", "Civil Services"], "post_time": "2022-01-12T10:08:54Z", "salary": {"currency": null, "max": null, "min": null, "period": "monthly", "term": null}, "salary_visible": false, "title_keywords": ["executive assistant"], "responsibilities": ["provide administrative support", "administration"], "requirements": {"degrees": ["form 5 or above"], "majors": [], "languages": ["cantonese", "putonghua", "english"], "language_level": ["fluent"], "hard_skills": ["excel", "pc knowledge", "basic", "photoshop"], "soft_skills": ["telephone manner", "patience"], "languages_combined": [{"language": "cantonese", "language_level": ["fluent"]}, {"language": "putonghua", "language_level": ["fluent"]}, {"language": "english", "language_level": ["fluent"]}]}, "experience_required": {"duration": ["at least 1 year"], "field": ["relevant experience"]}}, {"job_id": "100003009047957", "location_code": "hk", "company": "The Chinese General Chamber of Commerce", "job_title": "Office Assistant (Administration)", "description": "Job Responsibilities:\n\n\nPost 1 & 2:\n\nTo provide administrative support to personnel registry\n\nAssisting in handling recruitment related matters\n\nAssisting in keeping track of appraisal reports\n\nProviding support in compiling and\u00a0consolidating various returns\u00a0\n\nPost 3:\n\n\nTo provide administrative support to resource management Unit\n\nHandling day-to-day resource management\u00a0matters\n\nAssisting in consolidating briefing materials and folders for seniors\n\nPost 4:\u00a0\n\nHandling day-to-day accounting and financial matters\n\nProviding administrative support in preparing annual estimates & analysis\n\nAssisting in processing payment, including checking transactions and the\u00a0supporting documents\n\nJob Requirements:\n\nBachelor Degree in\u00a0from an accredited institution\nLevel 3 or above in Chinese Language and English Language in HKDSE for HKCEE\nGood oral and written communication skills in both Chinese and English\nGood interpersonal skills and be able to cope with tight work schedules\nAt least one year experience, preferably have experience in financial management or human resource or personnel management or in administration management.\nExperience in Government or public organizations is an advantage\u00a0", "employment_types": ["Full Time", "Permanent"], "selling_points": [], "locations": ["Central"], "categories": ["Admin & HR", "Clerical / Admin Staff", "Receptionist", "Public / Civil", "Civil Services"], "post_time": "2022-01-14T04:23:08Z", "salary": {"currency": null, "max": null, "min": null, "period": "monthly", "term": null}, "salary_visible": false, "title_keywords": ["office assistant"], "responsibilities": ["management", "administrative support", "analysis", "checking", "transactions", "payment", "recruitment", "reports", "providing support", "provide administrative support"], "requirements": {"degrees": ["degree", "bachelor", "hkdse"], "majors": [], "languages": ["english", "chinese"], "language_level": ["good"], "hard_skills": [], "soft_skills": ["communication skills", "oral", "interpersonal skills"], "languages_combined": [{"language": "english", "language_level": ["good"]}, {"language": "chinese", "language_level": ["good"]}]}, "experience_required": {"duration": ["at least one year"], "field": ["administration", "management", "financial"]}}, {"job_id": "100003009037225", "location_code": "hk", "company": "Nova Management Consultants Ltd", "job_title": "Office Executive (Govt.)(Central)(9M)($24373)", "description": "Responsibilities:\n\nTo process applications, change requests and other miscellaneous requests from recipients;\nTo monitor approved applications and arrange for disbursement;\nTo prepare statistical reports, including collating returns on questionnaires;\nTo answer enquiries on the programmes;\nTo assist in general administrative matters; and\nTo carry out any other related duties as assigned by senior officers.\n\nRequirement:\n\nAssociated Degree or above, with Level 2 in 5 subjects, including Chinese and English, in HKDSEE or equivalent;\nAt least two years of full-time post-degree working experience;\nGood command of Cantonese and English and Putonghua; and\nGood communication and interpersonal skills.\n\nInterested parties please email your resume (MS Word format), with expected salary and job reference no. to\u00a0anson.leung@manpowergrc.hk", "employment_types": ["Full Time", "Temporary", "Contract"], "selling_points": ["Degree, preferably in law / computer science", "Good command in both Chinese and English", "Administrative working experience in Govt."], "locations": ["Central"], "categories": ["Public / Civil", "Civil Services"], "post_time": "2022-01-11T02:07:26Z", "salary": {"currency": null, "max": null, "min": null, "period": "monthly", "term": null}, "salary_visible": false, "title_keywords": ["executive"], "responsibilities": ["monitor", "reports"], "requirements": {"degrees": ["degree or above", "degree"], "majors": [], "languages": ["cantonese", "putonghua", "english", "chinese"], "language_level": ["good command"], "hard_skills": [], "soft_skills": ["communication and interpersonal skills"], "languages_combined": [{"language": "cantonese", "language_level": ["good command"]}, {"language": "putonghua", "language_level": ["good command"]}, {"language": "english", "language_level": ["good command"]}, {"language": "chinese", "language_level": []}]}, "experience_required": {"duration": ["at least two years"], "field": []}}, {"job_id": "100003009044206", "location_code": "hk", "company": "Nova Management Consultants Ltd", "job_title": "Project Manager (School)(Govt.) ($37,000) (7 Months) (Lam Tin)", "description": "Office Assistant\n\nDuties:\n\n-\u00a0\u00a0\u00a0\u00a0\u00a0\u00a0 provide tea services for guests and visitors\n\n-\u00a0\u00a0\u00a0\u00a0\u00a0\u00a0 maintain cleanliness and tidiness of pantry and facility area\n\n-\u00a0\u00a0\u00a0\u00a0\u00a0\u00a0 replenish supplies in pantry\n\n-\u00a0\u00a0\u00a0\u00a0\u00a0\u00a0 assist in general office administration works including mail arrangement and\n\ndeliveries\n\nQualifications:\n\n-\u00a0\u00a0\u00a0\u00a0\u00a0\u00a0 From 5 or above\n\n-\u00a0\u00a0\u00a0\u00a0\u00a0\u00a0 Simple spoken English, good command of spoken Cantonese\n\n-\u00a0\u00a0\u00a0\u00a0\u00a0\u00a0 3-4 years of relevant work experience\n\n-\u00a0\u00a0\u00a0\u00a0\u00a0\u00a0 5.5 working days", "employment_types": ["Full Time", "Temporary", "Contract"], "selling_points": ["Bachelor degree in psychology,Master is preferable", "5 years Exps in project and contract managemt", "CRE Level 2 in Chinese and English"], "locations": ["Kwun Tong Area"], "categories": ["Public / Civil", "Civil Services"], "post_time": "2022-01-13T03:24:00Z", "salary": {"currency": null, "max": null, "min": null, "period": "monthly", "term": null}, "salary_visible": false, "title_keywords": ["project manager"], "responsibilities": ["office administration", "maintain"], "requirements": {"degrees": [], "majors": [], "languages": ["cantonese", "english"], "language_level": ["good command"], "hard_skills": ["simple", "tea"], "soft_skills": [], "languages_combined": [{"language": "cantonese", "language_level": ["good command"]}, {"language": "english", "language_level": ["good command"]}]}, "experience_required": {"duration": ["3-4 years"], "field": []}}, {"job_id": "100003009052104", "location_code": "hk", "company": "Haven of Hope Christian Service", "job_title": "\u5168\u8077\u8a3a\u6240\u52a9\u8b77 (\u7de8\u865f\uff1aPHS/CA/JDB)", "description": "Duties:\n\n\nTo assist Seniors in Cargo Ships Safety (CSS) Section in administering the Integrated Fleet Information System (iFIS) and Combined System Development for the Enhancement of iFIS and Ships and Seafarers Registration System (SSRS) for the Marine Department (MD)\n\nTo assist seniors in handling administrative work for the issuance and filing of Minimum Safe Manning Certificates (MSMC), Declaration of Maritime Labour Compliance Part I (DMLC Part I) and Wreck Removal Certificates (WRC);\n\nTo assist seniors in handling administrative work for issuing and filing exemptions / dispensations for Hong Kong-registered cargo ships and prepare the monthly and quarterly reports on exemption/dispensation issued;\nTo assist seniors in extracting information and documents such as certificates, survey reports and audit reports issued by Recognized Organizations (ROs) for scrutinising and verifying by assigned surveyors; and then assist to prepare the reports on performance of ROs, including preparation of relevant statistics, which will be published in the MD\u2019s website;\nTo assist seniors in screening Port State Control (PSC) Checklist for all HK Ships before entering USA or Australia ports;\nTo be the Electronic Recordkeeping System (ERKS) coordinator in the CSS Section; and\nTo carry out any other duties as assigned by seniors.\n\n.\n\nRequirements:\n\nBachelor's degree, preferably in law / computer science related studies, from a Hong Kong university, or equivalent; and\nMet the language proficiency requirements of Level 2 or above in Chinese Language and English Language in HKDSEE or HKCEE, or equivalent. Priority will be given to candidates with good command in both Chinese Language and English Language; and\nChinese word-processing speed of 20 words per minute and English word-processing speed of 30 words per minute and knowledge in the application of common business software, especially Microsoft Excel; and\nPrior administrative working experience in Government Bureaux / Departments will be an advantage.", "employment_types": ["Full Time"], "selling_points": [], "locations": ["Tseung Kwan O"], "categories": ["Public / Civil", "Civil Services", "Medical Services", "Nursing", "Others"], "post_time": "2022-01-17T02:05:56Z", "salary": {"currency": null, "max": null, "min": null, "period": "monthly", "term": null}, "salary_visible": false, "title_keywords": ["\u5168\u8077\u8a3a\u6240\u52a9\u8b77"], "responsibilities": ["any other duties", "control", "administrative work", "compliance", "website", "audit", "reports"], "requirements": {"degrees": ["degree", "bachelor"], "majors": ["computer science", "law"], "languages": ["english", "chinese"], "language_level": ["proficiency", "good command"], "hard_skills": ["chinese word-processing", "words", "processing", "word", "microsoft excel", "business software"], "soft_skills": [], "languages_combined": [{"language": "english", "language_level": ["proficiency", "good command"]}, {"language": "chinese", "language_level": ["proficiency", "good command"]}]}, "experience_required": {"duration": [], "field": ["administrative"]}}, {"job_id": "100003009049666", "location_code": "hk", "company": "W M Lee & Co", "job_title": "\u521d\u7d1a\u6838\u6578\u898b\u7fd2\u54e1", "description": "Applications are invited for appointment as\u00a0Post-doctoral Fellow (PDF)/Assistant Research Officer (ARO) in the School of Public Health\u00a0(Ref.: 509156), to commence as soon as possible for one year, with the possibility of renewal subject to satisfactory performance.\n\nApplicants should possess a doctoral degree by research or equivalent in public health, social sciences, or related disciplines, with at least one year's experience in community-based research, public health research or population sciences research. They should have knowledge of community health promotion, and/or experience in the application of Information and Communication Technology (ICT) in research. They should also have the ability to work independently as well as in a multidisciplinary team; the ability to collaborate with external parties including academics, social service groups and politicians; and excellent written and verbal communication skills.\n\nThe appointee will work for the Jockey Club SMART Family-Link Project, with the aim to promote family well-being by leveraging ICT for innovative family services.\u00a0 He/She will coordinate research design; liaise with community parties and institutions; plan, develop and conduct community-based interventions and training programmes for local social service practitioners and professionals; facilitate the collection of big data; oversee data collection and management; write scientific publications and reports; supervise research staff members; and perform other duties as assigned. Those who have responded to the previous advertisement (Ref.: 498698) need not re-apply.\n\nA highly competitive salary commensurate with qualifications and experience will be offered, in addition to annual leave and medical benefits.\u00a0\n\nThe University only accepts online application for the above post.\u00a0Applicants should apply online and upload an up-to-date C.V.\u00a0 Review of applications will start on December 21, 2021 and continue until\u00a0February 28, 2022, or until the post is filled, whichever is earlier.\n\nAdvertised:Dec 7, 2021 (HK Time)\nApplications close:Feb 28, 2022 (HK Time)\n\n\u6709\u610f\u7533\u8acb\u8005\u8acb \u6309 APPLY NOW\u7533\u8acb\n\n", "employment_types": ["Full Time"], "selling_points": [], "locations": ["Tsuen Wan Area"], "categories": ["Public / Civil", "Civil Services", "Social Services - Community / Non-profit Organization", "Others"], "post_time": "2022-01-14T09:02:43Z", "salary": {"currency": null, "max": null, "min": null, "period": "monthly", "term": null}, "salary_visible": false, "title_keywords": [], "responsibilities": ["collaborate with", "management", "perform other duties", "external parties", "big data", "design", "develop", "communication", "coordinate", "reports", "plan", "data collection", "liaise with"], "requirements": {"degrees": ["degree"], "majors": ["related disciplines", "public health", "social sciences"], "languages": [], "language_level": [], "hard_skills": [], "soft_skills": ["communication", "communication skills", "work independently", "innovative"], "languages_combined": []}, "experience_required": {"duration": ["at least one year"], "field": ["related", "research"]}}, {"job_id": "100003009042450", "location_code": "hk", "company": "Manpower Services (Hong Kong) Limited", "job_title": "Senior Administrative Assistant (9 months, 15-16K)", "description": "Job Duties:\n\nAssist in the overall planning, implementation and evaluation of the project\nLiaise , establish and reinforce working partnerships with stakeholder include Dh services, non \u2013government organist ion, tertiary institution and others to ensure effective and efficient cooperation in developing, implementing and timely delivery of quality works for the project\nTranscribe teaching materials of basic life skills training programme in the Std HS of the DH into education materials for wider general public groups and to plan and implement dissemination of these materials for wider through relevant channels including websites and other social media\nPlan, organize, monitor process and co-ordinate various of the Project, including production of creative visual-art effects and audio \u2013visual programmes , printing education materials etc. for the project\nDevelop a new website and web content that are appealing to adolescents by transcribing, packaging and re-designing teaching and health education material of Basic Life Skills Training and Topical Programmes in the Std HS of the DH into multi-media formats, including production of infographic, motion graphics, e-magazines and video , to promulgate the key messages in the Campaign\nArrange meeting with various stakeholders and provide secretariat support during the process\n\u00a0Assist in planning , organizing and conducting related surveys, studies and evaluation\nProvide general administrative and logistic support, e.g procurement, contract management etc.\nPerform ad hoc task\n\nJob Requriements:\n\nHaving a Bachelor degree with honours in the field of psychology and preferable to have a master or above degree in a theoretical or an applied field of psychology\nHaving at least 5 years of post-qualification experience, preferably in project and contract management\nHaving 3 years of post-qualification experience relating to implementation of health education programme at schools or school students service setting\nHaving recent 3 year of networking with NGOs working closely with local secondary school\nFluent in spoken and written English: Grade C or above in Use of English of the HKAL or English of the GCE A Level) or overall band 6.5 or above in the same setting in the Academic Module of IELTS within the 2 years or CRE Use of English in Level 2\nFluent in spoken and written Chinese : Grade C or above in Chinese Language and Culture or Chinese language and Literature of the HKALE or CRE Use of Chinese in Level 2\nGood Team player processing good communication and interpersonal skills\nHaving proficient computer Skill(MS Office)", "employment_types": ["Contract"], "selling_points": ["At least 2 years working experience", "Government Project", "Strong interpersonal and communication skills"], "locations": ["Wan Chai"], "categories": ["Admin & HR", "Administration / Operation Manager", "Clerical / Admin Staff", "Public / Civil", "Civil Services"], "post_time": "2022-01-12T07:35:41Z", "salary": {"currency": null, "max": null, "min": null, "period": "monthly", "term": null}, "salary_visible": false, "title_keywords": ["senior administrative", "assistant"], "responsibilities": ["liaise", "quality", "website", "plan", "designing", "evaluation", "ad hoc", "monitor", "developing", "implementation", "develop", "motion graphics", "visual", "audio", "social media", "logistic support", "teaching materials", "contract management", "planning"], "requirements": {"degrees": ["degree", "bachelor", "master"], "majors": ["psychology"], "languages": ["english", "chinese"], "language_level": ["fluent"], "hard_skills": ["c", "processing"], "soft_skills": ["good team player", "communication and interpersonal skills"], "languages_combined": [{"language": "english", "language_level": ["fluent"]}, {"language": "chinese", "language_level": ["fluent"]}]}, "experience_required": {"duration": ["3 years", "at least 5 years"], "field": ["management", "post-qualification", "education"]}}, {"job_id": "100003009047337", "location_code": "hk", "company": "Playright Children's Play Association", "job_title": "Play Officer (Centre Operation)", "description": "\u6301\u8a8d\u53ef\u4e2d\u91ab\u6216\u897f\u91ab\u914d\u85e5\u6587\u6191\u6216\u4e2d\u4e94\u7a0b\u5ea6\uff0c\u7565\u61c2\u64cd\u4f5c\u96fb\u8166\u3001\u5177\u4e2d\u3001\u897f\u85e5\u914d\u5291/\u85e5\u623f\u5de5\u4f5c\u8005\u7d93\u9a57\u512a\u5148\n\u8ca0\u8cac\u8a3a\u6240\u767b\u8a18\u3001\u4e2d/\u897f\u85e5\u914d\u767c\u5de5\u4f5c\uff0c\u4e26\u6309\u9700\u8981\u652f\u63f4\u767b\u8a18\u8655\u670d\u52d9\n\u5354\u52a9\u91ab\u751f/\u7259\u91ab\u9032\u884c\u6aa2\u67e5\u6cbb\u7642\u7b49\uff0c\u6709\u6a5f\u6703\u6d3e\u99d0\u4e2d\u91ab\u3001\u897f\u91ab\u6216\u7259\u79d1\u670d\u52d9\u5de5\u4f5c\n\u5c07\u8ecd\u6fb3\u5de5\u4f5c\uff0c\u6bcf\u661f\u671f\u5de5\u4f5c45\u5c0f\u6642\n\n\u6709\u610f\u8005\u8acb\u65bc\u4e8c\u96f6\u4e8c\u4e8c\u5e74\u4e8c\u6708\u4e94\u65e5\u524d\u89aa\u7e55\u5c65\u6b77\u53ca\u671f\u671b\u5f85\u9047\uff08\u8acb\u65bc\u4fe1\u5c01\u9762\u53ca\u4fe1\u5167\u8a3b\u660e\u7533\u8acb\u8077\u4f4d\u7de8\u865f\uff09\u5bc4\u65b0\u754c\u5c07\u8ecd\u6fb3\u9748\u5be6\u8def\u4e03\u865f\u57fa\u7763\u6559\u9748\u5be6\u5354\u6703\u4eba\u529b\u8cc7\u6e90\u90e8\u6536\uff0c\u6216\u96fb\u90f5\u81f3Apply Now\uff0c\u6216\u767c\u9001\u81f3Whatsapp\u865f\u78bc6507 8148\uff08\u6a19\u984c\u8acb\u8a3b\u660e\u8077\u4f4d\u7de8\u865f\uff09\u3002\u5982\u4e00\u500b\u6708\u5167\u672a\u7372\u901a\u77e5\u7d04\u898b\uff0c\u5247\u4f5c\u843d\u9078\u8ad6\u3002\n\n\u67e5\u8a62\u71b1\u7dda\uff1a2703 3227 (\u96fb\u8a71)\uff1b6507 8148(Whatsapp)\u3002\n\n\u6709\u95dc\u672c\u6703\u8a73\u60c5\uff0c\u8acb\u700f\u89bd\u7db2\u9801http://www.hohcs.org.hk\n\n(\u53ef\u80fd\u7372\u8058\u4eba\u58eb\uff08\u5982\u5f9e\u4e8b\u8207\u5152\u7ae5\u6216\u7cbe\u795e\u4e0a\u7121\u884c\u70ba\u80fd\u529b\u4eba\u58eb\u6709\u95dc\u5de5\u4f5c\u8077\u4f4d\uff09\u9808\u65bc\u5165\u8077\u524d\u9032\u884c\uff0f\u63d0\u4ea4\u6027\u7f6a\u884c\u5b9a\u7f6a\u7d00\u9304\u67e5\u6838\u3002\u7533\u8acb\u4eba\u6240\u63d0\u4f9b\u7684\u8cc7\u6599\u5c07\u4e88\u4fdd\u5bc6\u53ca\u4f5c\u62db\u8058\u6709\u95dc\u8077\u4f4d\u7528\u9014)\n\n\u672a\u7d93\u672c\u5354\u6703\u66f8\u9762\u540c\u610f\uff0c\u4ee5\u4e0a\u62db\u8058\u5ee3\u544a\u5168\u90e8\u6216\u90e8\u5206\u5167\u5bb9\u5747\u4e0d\u5f97\u8907\u88fd\u81f3\u5176\u4ed6\u62db\u8058\u7db2\u7ad9\u3002", "employment_types": ["Full Time", "Contract"], "selling_points": [], "locations": ["Tai Po Area"], "categories": ["Public / Civil", "Civil Services", "Social Services - Community / Non-profit Organization"], "post_time": "2022-01-14T02:52:14Z", "salary": {"currency": null, "max": null, "min": null, "period": "monthly", "term": null}, "salary_visible": false, "title_keywords": ["officer"], "responsibilities": [], "requirements": {"degrees": [], "majors": [], "languages": [], "language_level": [], "hard_skills": [], "soft_skills": [], "languages_combined": []}, "experience_required": {"duration": [], "field": []}}, {"job_id": "100003009048332", "location_code": "hk", "company": "ADECCO", "job_title": "\u535a\u7269\u9928\u5834\u5730\u5927\u4f7f (\u300c\u6cb9\u8857\u5be6\u73fe\u300d\u85dd\u8853\u7a7a\u9593)", "description": "\n\u8077\u8cac :Performing audit, tax, accounting jobs under senior's supervision, work in Mainland China occasionally (\u6bcf\u5e74\u4e00\u6b21\u76e4\u9ede\u5de5\u4f5c) (\u90f5\u5bc4:\u8343\u7063\u9752\u5c71\u9053264-298\u865f\u5357\u8c50\u4e2d\u5fc31913-15\u5ba4)(proficiency in MYOB and other accounting software pref,willing to learn)\n\n\u8cc7\u6b77 :\u4e2d\u516d\u7a0b\u5ea6; 2\u5e74\u7d93\u9a57; \u826f\u597d\u7cb5\u8a9e; \u4e00\u822c\u666e\u901a\u8a71; \u4e00\u822c\u82f1\u8a9e; \u61c2\u8b80\u5beb\u4e2d\u6587; \u61c2\u8b80\u5beb\u82f1\u6587; \u61c2MS Word; \u61c2MS Excel; Self motivated at work, able to work under pressure, willing to work OT in peak season\n\n\u5f85\u9047 :\u6bcf\u6708$12,000 - $18,000, \u6709\u5e74\u7d42\u734e\u91d1(2 yrs or above working exp in accounting section of commercial company), \u4e00\u81f3\u4e94: \u4e0a\u53489\u6642\u81f3\u4e0b\u53485\u6642\u534a\u53ca\u516d: \u4e0a\u53489\u6642\u81f3\u4e0b\u53481\u6642, \u6bcf\u9031\u5de5\u4f5c5-5\u5929\u534a (accounting graduate/with LCC Advanced cert), Saturday off on non peak season only\n\n\u7533\u8acb\u9808\u77e5 :\u50b3\u771f(24158382)/\u96fb\u90f5(Apply Now)/\u90f5\u5bc4\u5c65\u6b77\u8868\u7d66\u674e\u5049\u660e\u6703\u8a08\u5e2b\u884c\u3002\u5982\u8981\u7d22\u53d6\u6536\u96c6\u500b\u4eba\u8cc7\u6599\u8072\u660e, \u8acb\u8207\u6881\u5c0f\u59d0(Fax/Email/Post)\u806f\u7d61\u3002\n\n", "employment_types": ["Contract"], "selling_points": [], "locations": ["North Point"], "categories": ["Public / Civil", "Civil Services"], "post_time": "2022-01-14T06:18:08Z", "salary": {"currency": null, "max": null, "min": null, "period": "hourly", "term": null}, "salary_visible": false, "title_keywords": [], "responsibilities": ["tax", "audit", "software", "work under pressure"], "requirements": {"degrees": [], "majors": [], "languages": [], "language_level": [], "hard_skills": ["excel", "accounting software", "word", "lcc", "myob"], "soft_skills": ["self motivated", "willing to learn", "advanced", "work under pressure"], "languages_combined": []}, "experience_required": {"duration": [], "field": []}}, {"job_id": "100003009045545", "location_code": "hk", "company": "The University of Hong Kong", "job_title": "Post-doctoral Fellow (PDF) / Assistant Research Officer  (ARO) ( 509156)", "description": "Play Officer (Centre Operation)\nPlayright Children's Play Association\nTai Po, Tai Wo\n\nJob Description/ Responsibilities\n\n\nTo assist supervisor in delivering, support and promoting children's play by creating high-quality child-centered indoor free play opportunities for all children.\nTo contribute to the maintenance and improvement of the center operating system.\nTo assist the supervisor to oversee the daily center operation.\nTo supervise the supporting staff for sure the quality center service delivery.\n\nRequirements\n\n\nDegree holder in any discipline.\nAt least one-year working experiences\nBe able to build good relationships with key stakeholders, such as parents, contractors and community organizations\nBe a good team player, independent, self-motivated, positive thinking, possess good interpersonal skills, and able to handle challenges\nMature, energetic, creative, and highly motivated\nHave a passion for working with children through play\nWork on weekends/public holidays are occasionally required\n\n\u00a0------------------------------------------------------------------------------------------------------------------------\u00a0\n* Prospective employee is requested to undergo Sexual Conviction Record Check on voluntary basis *\u00a0\n\n* Internal Play Training will be arranged*\u00a0\n\n*Play Worker Qualification is required (The Association will offer the Play Worker training if the candidate do not have such qualification)*\n\nAll personal data will be used for recruitment purpose only.\u00a0\u00a0Unsuccessful applications will be destroyed upon completion of the recruitment exercise.\u00a0", "employment_types": ["Full Time"], "selling_points": [], "locations": ["Pok Fu Lam"], "categories": ["Public / Civil", "Civil Services", "Sciences, Lab, R&D", "Research & Development (R&D)", "Social Services - Community / Non-profit Organization"], "post_time": "2022-01-13T08:03:23Z", "salary": {"currency": null, "max": null, "min": null, "period": "monthly", "term": null}, "salary_visible": false, "title_keywords": ["research officer", "assistant"], "responsibilities": ["service delivery", "quality", "maintenance"], "requirements": {"degrees": ["degree holder"], "majors": [], "languages": [], "language_level": [], "hard_skills": [], "soft_skills": ["good team player", "self-motivated", "independent", "creative", "passion for", "positive thinking", "mature", "motivated", "interpersonal skills", "energetic"], "languages_combined": []}, "experience_required": {"duration": [], "field": []}}, {"job_id": "100003009042473", "location_code": "hk", "company": "Roundtable \u5be6\u653f\u5713\u684c", "job_title": "\u7530\u5317\u8fb0\u8b70\u54e1\u8fa6\u4e8b\u8655 Office of Hon. Michael Tien - Public Affairs Manager", "description": "\u5de5\u4f5c\u8077\u8cac\uff1a\n\n\u00a0- \u78ba\u4fdd\u5c55\u54c1\u5b89\u5168\uff1b\n\n\u00a0- \u6aa2\u67e5\u53ca\u7dad\u8b77\u85dd\u8853\u54c1\u548c\u8a2d\u5099\u72c0\u6cc1\uff1b\n\n\u00a0- \u5354\u52a9\u986f\u793a\u8a2d\u5099\u7684\u65e5\u5e38\u64cd\u4f5c\uff1b\n\n\u00a0- \u88dc\u5145\u548c\u5206\u767c\u5ba3\u50b3\u6750\u6599\uff1b\n\n\u00a0- \u5411\u516c\u773e\u4ecb\u7d39\u5c55\u89bd\u4e26\u56de\u7b54\u516c\u773e\u8a62\u554f\uff1b\n\n\u00a0- \u8655\u7406\u4e00\u822c\u67e5\u8a62\u53ca\u5728\u5834\u5730\u5354\u52a9\u4eba\u6d41\u7ba1\u5236\uff1b\n\n\u00a0- \u9032\u884c\u5c0e\u8cde\u4e26\u5354\u52a9\u5834\u5730\u7279\u5225\u7bc0\u76ee\uff1b\n\n\u00a0- \u9032\u884c\u8a2a\u5ba2\u8abf\u67e5\uff1b\n\n\u00a0- \u78ba\u4fdd\u5165\u5834\u4eba\u4ed5\u901a\u904e\u9ad4\u6eab\u6aa2\u6e2c\u548c\u57f7\u884cCap.599G\u548cCap.599I\u7684\u8981\u6c42\uff1b\n\n\u00a0- \u5fc5\u8981\u6642\u63d0\u4f9b\u904b\u71df\u4e0a\u548c\u884c\u653f\u4e0a\u652f\u6301\uff0c\u4ee5\u53ca\uff1b\n\n\u00a0- \u6839\u64da\u9700\u8981\u57f7\u884c\u5176\u4ed6\u8077\u8cac\n\n\u5de5\u4f5c\u5730\u9ede\uff1a\u5317\u89d2\u6cb9\u885712\u865f\u300c\u6cb9\u8857\u5be6\u73fe\u300d(Oi!)\n\n\u5de5\u4f5c\u671f\uff1a2022\u5e742\u6708\u81f32023\u5e742\u6708\n\n\u5de5\u4f5c\u6642\u9593\uff1a\u661f\u671f\u4e00\u81f3\u661f\u671f\u65e5\uff0c\u6bcf\u9031\u5de5\u4f5c5\u5929, \u6bcf\u5929\u5de5\u4f5c10\u5c0f\u6642\u9023\u98ef\u9418(\u6709\u85aa),\u00a0\u6642\u9593\u6700\u65e9\u7531\u65e9\u4e0a10:00\u81f3\u665a\u4e0a20:00, \u8f2a\u73ed\u8f2a\u4f11, \u9808\u65bc\u516c\u773e\u5047\u671f\u7576\u503c\n\n\u8981\u6c42\uff1a\n\n- \u4e2d\u4e94(\u6216\u4ee5\u4e0a)\u5b78\u6b77\n\n- \u9999\u6e2f\u4e2d\u5b78\u6703\u8003\u6216\u9999\u6e2f\u4e2d\u5b78\u6587\u6191\u8a66\u4e2d\uff0c\u82f1\u5169\u79d1\u5408\u683c\u6216\u540c\u7b49\u5b78\u6b77\n\n\u00a0- \u6709\u85dd\u8853\u76f8\u95dc\u5de5\u4f5c\u5834\u6240\u8b1b\u89e3\u54e1/\u5927\u4f7f/\u5ba2\u670d/\u5834\u5730\u904b\u71df/\u6a13\u5b87\u7ba1\u7406\u5de5\u4f5c\u7d93\u9a57\u8005\u512a\u5148\uff1b\n\n\u00a0- \u64cd\u6d41\u5229\u7684\u7cb5\u8a9e\uff0c\u826f\u597d\u7684\u82f1\u8a9e\u548c\u666e\u901a\u8a71\uff1b\n\n\u00a0- \u6709\u8208\u8da3\u5354\u52a9\u63a8\u5ee3\u7576\u4ee3\u85dd\u8853\uff1b\n\n\u00a0- \u5fc5\u9808\u9075\u5b88\u653f\u5e9c\u767c\u5e03\u7684\u6700\u65b0 COVID-19 \u6aa2\u6e2c\u548c\u75ab\u82d7\u63a5\u7a2e\u898f\u5b9a\n\n\u85aa\u916c\uff1a$70/hr", "employment_types": ["Full Time"], "selling_points": ["Sense of current affairs", "Fun and exciting work environment", "Good team player"], "locations": ["Central"], "categories": ["Public / Civil", "Civil Services", "Marketing / Public Relations", "Public Relations - General / Support", "Social Services - Community / Non-profit Organization"], "post_time": "2022-01-12T07:43:46Z", "salary": {"currency": null, "max": null, "min": null, "period": "monthly", "term": null}, "salary_visible": false, "title_keywords": ["manager"], "responsibilities": ["hr"], "requirements": {"degrees": [], "majors": [], "languages": [], "language_level": [], "hard_skills": [], "soft_skills": [], "languages_combined": []}, "experience_required": {"duration": [], "field": []}}, {"job_id": "100003009049374", "location_code": "hk", "company": "HGC Global Communications Limited", "job_title": "Technical Officer / Senior Technical Officer (Fixed Network)", "description": "Public Affairs Manager\n\n\nJob Description\n\n\n\nProvide support and suggestions to the organization on overall management, public policy, political and social affairs;\nCoordinate and accompany the director to attend meetings, conferences, PR functions and social events; and follow up relevant issues after attending the above events;\nWrite and prepare public policy related speeches, papers and submissions for the organization;\nLiaise with different government departments, interest groups and media for the organization;\nPlan events for the organization;\nManage promotional materials and online marketing scheme;\nCoordinate promotion campaign for the director and community offices.\n\nJob Requirements\n\n\nA recognized university degree in journalism, public administration, politics or other related disciplines;\nAt least 4-6 years\u2019 experience in handling public policy issues;\nStrong awareness of Hong Kong\u2019s current affairs;\nExperience in media, public relation, and event management is preferable;\nThoughtful, attentive, detail-minded and self-motivated;\nA good team player and able to finish multi tasks within tight deadline;\nExcellent oral and written skills in both Chinese and English (Cantonese is a must), proficiency in Putonghua is\u00a0advantageous;\nProficiency in using Microsoft Word, Excel, PowerPoint and Chinese word processing; and\nWilling to work overtime and in non-office settings.\n\nBenefits:\n\n\n14-day annual leave;\n5-day work week, bank holiday;\nContract-end gratuity;\nMedical Benefit (both hospitalization & out-patient);\n\nInterested parties please send your full resume, current salary and expected salary.\n\n\nWe are an equal opportunity employer and welcome applications from all qualified candidates. The information provided will be treated in strict confidence and be used only for consideration of your application for relevant / similar posts within the Office of Hon. Michael Tien and Roundtable. Applicants not hearing from us within four weeks from the date of advertisement may consider their applications unsuccessful. We retain the unsuccessful applications for a maximum period of six months.", "employment_types": ["Full Time", "Permanent"], "selling_points": ["Diploma holder in IT or related discipline", "2-3 years relevant working experience", "To conduct site measurement & inspection"], "locations": ["Tsing Yi"], "categories": ["Public / Civil", "Civil Services", "Engineering", "Engineering Project Management", "Telecommunication / Wireless / Radio"], "post_time": "2022-01-14T08:31:46Z", "salary": {"currency": null, "max": null, "min": null, "period": "monthly", "term": null}, "salary_visible": false, "title_keywords": ["technical officer", "senior technical officer"], "responsibilities": ["provide support", "management", "coordinate", "liaise with", "conferences", "promotional materials", "plan", "attend meetings"], "requirements": {"degrees": ["university degree"], "majors": ["journalism", "related disciplines", "public administration"], "languages": ["cantonese", "putonghua", "english", "chinese"], "language_level": ["excellent", "proficiency"], "hard_skills": ["excel", "microsoft word", "chinese word processing", "powerpoint"], "soft_skills": ["attentive", "detail-minded", "good team player", "oral", "self-motivated", "work overtime"], "languages_combined": [{"language": "cantonese", "language_level": ["excellent"]}, {"language": "putonghua", "language_level": ["proficiency", "excellent"]}, {"language": "english", "language_level": ["excellent"]}, {"language": "chinese", "language_level": ["excellent"]}]}, "experience_required": {"duration": ["at least 4-6 years"], "field": ["public relation", "management", "media"]}}, {"job_id": "100003009035888", "location_code": "hk", "company": "Innovis Building Supplies Company Limited", "job_title": "Sales Co-ordinator / Sales Administration Clerk", "description": "Job Responsibilities:\n\nTo conduct site measurement & inspection of external cable network to various target of planning building / area;\nTo liaise with internal and external parties such as contractor, engineers and technical staff for necessary planning and fitting out project;\nConduct site measurement and inspection of external cable network for planning and proposal of building / area;\nProvide management services to monitor the work progress of the contractor for work implementation;\nPrepare site drawing , site proposal, as-built drawings and update on system;\nPrepare planning and proposal for major project and to liaise concerned internal and external parties for necessary implementation.\n\nJob Requirements:\n\nDiploma holder in IT or related discipline;\n2-3 years relevant working experience;\nHands on experience in MS Office Applications ;\nHolder of driving license will be an advantage;\nGood analytical, PC / device trouble shooting, and problem solving skills;\nGood interpersonal skill and a good team player;\nMature, dynamic, work independent and self-motivated;\nGood spoken and written English and Cantonese, Mandarin a plus.\n\nWe offer competitive salary package and career development opportunity. Free company coach is provided.\u00a0 Interested parties, please quote our reference number and apply with full resume, present and expected salary, by clicking \u201cAPPLY NOW\u201d.\u00a0\n\nWe are an equal opportunity employer and welcome applications from all qualified candidates. Information provided will be treated in strict confidence and only be used for consideration of your application for the relevant post within HGC Global Communications Limited. Personal data provided by job applicants will be used strictly according to our Personal Information Collection Statement, a copy of which will be available upon written request. Information of unsuccessful candidates will be destroyed within six months.", "employment_types": ["Full Time"], "selling_points": [], "locations": ["Kwun Tong"], "categories": ["Public / Civil", "Civil Services", "Building & Construction", "Civil / Structural", "Sales, CS & Business Devpt", "Sales Administration"], "post_time": "2022-01-10T08:40:35Z", "salary": {"currency": null, "max": null, "min": null, "period": "monthly", "term": null}, "salary_visible": false, "title_keywords": ["clerk", "sales"], "responsibilities": ["liaise", "management", "internal and external parties", "measurement", "monitor", "implementation", "inspection", "drawings", "liaise with", "planning"], "requirements": {"degrees": ["diploma holder"], "majors": ["it"], "languages": ["cantonese", "english", "mandarin"], "language_level": ["good"], "hard_skills": ["plus", "dynamic", "pc", "problem solving skills", "ms office"], "soft_skills": ["good team player", "self-motivated", "independent", "mature", "interpersonal skill", "hands on", "dynamic", "problem solving skills"], "languages_combined": [{"language": "cantonese", "language_level": ["good"]}, {"language": "english", "language_level": ["good"]}, {"language": "mandarin", "language_level": ["good"]}]}, "experience_required": {"duration": ["2-3 years"], "field": ["relevant working experience"]}}, {"job_id": "100003009044473", "location_code": "hk", "company": "Zhong Lun Law Firm LLP", "job_title": "Capital Markets Paralegal", "description": "Job Highlights:\u00a0\n\nHandle sales orders, reports, inventory control and account receivable\nProvide admin and customer services\u2019 support\n\nJob Description:\u00a0 \u00a0 \u00a0 \u00a0 \u00a0 \u00a0 \u00a0 \u00a0 \u00a0 \u00a0 \u00a0 \u00a0 \u00a0 \u00a0 \u00a0 \u00a0 \u00a0 \u00a0 \u00a0 \u00a0 \u00a0 \u00a0 \u00a0 \u00a0 \u00a0 \u00a0 \u00a0\n\nFollow up sales inquiries / sales leads\nResponsible for handling PO from customers and PO processing to vendor\nPrepare quotations / project costing and delivery documents\nProvide clerical and administrative support\nKeep track of sales orders and follow up delivery with suppliers\nHandle enquiries\u00a0phone\u00a0call, data entry and document filing\nPrepare various\u00a0sales related reports\u00a0\u00a0\nAssist in ad-hoc projects as assigned by supervisor\nOutdoor work is necessary", "employment_types": ["Full Time", "Permanent"], "selling_points": ["Minimum 2 years\u2019 HK IPO experience in a law firm", "Bilingual (Chinese and English) drafting skills", "Able to work independently"], "locations": ["Central"], "categories": ["Public / Civil", "Civil Services", "Professional Services", "Legal & Compliance"], "post_time": "2022-01-13T04:13:23Z", "salary": {"currency": null, "max": null, "min": null, "period": "monthly", "term": null}, "salary_visible": false, "title_keywords": ["paralegal"], "responsibilities": ["document filing", "outdoor work", "administrative support", "data entry", "customer services", "handle enquiries", "inventory control", "reports", "ad-hoc projects"], "requirements": {"degrees": [], "majors": [], "languages": [], "language_level": [], "hard_skills": ["processing", "vendor"], "soft_skills": ["responsible"], "languages_combined": []}, "experience_required": {"duration": [], "field": []}}, {"job_id": "100003009040776", "location_code": "hk", "company": "Po Leung Kuk", "job_title": "\u670d\u52d9\u7d93\u7406 (\u5b89\u8001/\u5eb7\u5fa9) SM-SSD-ADM (\u9285\u947c\u7063)", "description": "\u00a0Position offers:\n\n5-day week\ngenerous holidays\nfriendly environment\n\nRequirements:\n\nMinimum\u00a02 year HK IPO experience in a law firm, and experience in prospectus drafting is a plus.\u00a0\u00a0\nStrong self-motivation and ability to handle matters independently\nBilingual (Chinese and English) drafting skills are essential.\nFluent verbal Putonghua is a must.\nTravelling may be required..\nCandidate with a Law degree would be an asset\n\u00a0\u00a0", "employment_types": ["Full Time"], "selling_points": [], "locations": ["Not Specified"], "categories": ["Public / Civil", "Civil Services", "Social Services - Community / Non-profit Organization", "Others"], "post_time": "2022-01-12T03:04:06Z", "salary": {"currency": null, "max": null, "min": null, "period": "monthly", "term": null}, "salary_visible": false, "title_keywords": [], "responsibilities": [], "requirements": {"degrees": ["degree"], "majors": ["law"], "languages": ["putonghua", "english", "chinese"], "language_level": ["fluent"], "hard_skills": ["plus"], "soft_skills": ["self-motivation", "friendly", "independently"], "languages_combined": [{"language": "putonghua", "language_level": ["fluent"]}, {"language": "english", "language_level": []}, {"language": "chinese", "language_level": []}]}, "experience_required": {"duration": ["minimum 2 year"], "field": []}}, {"job_id": "100003009041023", "location_code": "hk", "company": "Kwan On Construction Company Limited", "job_title": "\u6587\u54e1 Clerk", "description": "\n\u4fdd\u826f\u5c40\u5275\u7acb\u65bc1878\u5e74,\u6211\u5011\u672c\u8457\u4ee5\u4eba\u70ba\u672c\u7684\u4fe1\u5ff5,\u79c9\u627f \u300c\u4fdd\u8d64\u5b89\u826f\u3001\u6276\u5eb7\u80b2\u9577\u300d \u7684\u5b97\u65e8,\u806f\u7e6b\u53ca\u5584\u7528\u793e\u6703\u8cc7\u6e90,\u70ba\u5e02\u6c11\u63d0\u4f9b\u591a\u5143\u5316\u7684\u512a\u8cea\u793e\u6703\u670d\u52d9,\u5305\u62ec\u5bb6\u5ead\u670d\u52d9\u3001\u5e7c\u5152\u670d\u52d9\u3001\u5152\u7ae5\u53ca\u9752\u5c11\u5e74\u670d\u52d9\u3001\u5eb7\u5fa9\u670d\u52d9\u3001\u5b89\u8001\u670d\u52d9\u3001\u91ab\u7642\u53ca\u7d9c\u5408\u5065\u5eb7\u670d\u52d9,\u6bcf\u5e74\u670d\u52d9\u4eba\u6578\u8d85\u904e100,000\u4eba\u3002\n\nPo Leung Kuk is established since 1878, adhering to the \u201cpeople-oriented\u201d philosophy and the mission of \u201cprotecting the young and the innocent, aiding the needy and nurturing the talents\u201d, Connect with and make good use of social resources to provide citizens with diversified high-quality social services, including integrated family services, child care services, children and youth services, rehabilitation services, elderly services, medical and comprehensive health services, with more than 100,000 people served each year.\n\n\u5b89\u8001\u670d\u52d9\n\n\u5165\u8077\u8981\u6c42\n\n\u5b78\u4f4d\u8a3b\u518a\u793e\u5de5/\u8b77\u58eb/\u6cbb\u7642\u5e2b,\u4e03\u5e74\u7763\u5c0e\u5b89\u8001/\u5eb7\u5fa9\u670d\u52d9\u7d93\u9a57,\u7372\u8058\u8005\u6703\u7372\u5206\u914d\u7ba1\u7406\u5b89\u8001\u53ca/\u6216\u5eb7\u5fa9\u670d\u52d9\u7684\u55ae\u4f4d, \u4e26\u56e0\u61c9\u670d\u52d9\u53ca\u767c\u5c55\u9700\u8981\u9032\u884c\u8077\u4f4d\u8f2a\u8abf\u3002\n\n\u4e3b\u8981\u8077\u8cac\n\n\u8ca0\u8cac\u5b89\u8001/\u5eb7\u5fa9\u670d\u52d9\u55ae\u4f4d\u7684\u7763\u5c0e\u53ca\u767c\u5c55, \u76e3\u63a7\u5c6c\u4e0b\u670d\u52d9\u55ae\u4f4d\u8ca1\u52d9\u9810\u7b97\u53ca\u904b\u4f5c,\u7d71\u7c4c\u8de8\u55ae\u4f4d\u670d\u52d9\u53ca\u6d3b\u52d5\u8a08\u5283\u7b49\u5de5\u4f5c\u3002\n\n\u9285\u947c\u7063 [email redacted, apply via Company website] 2277 8151\n\n\u622a\u6b62\u7533\u8acb\u65e5\u671f : 2022/1/28\n\n\u61c9\u5fb5\u8005\u8acb\u5099\u8a73\u7d30\u5c65\u6b77\u4e26\u8a3b\u660e\u7533\u8acb\u8077\u4f4d\u53ca\u7de8\u865f\u3001\u73fe\u8077\u85aa\u91d1\u3001\u8981\u6c42\u5f85\u9047\u53ca\u65e5\u9593\u806f\u7d61\u96fb\u8a71,\u6309\u201dAPPLY NOW\u201d\u5373\u6642\u7533\u8acb\u8077\u4f4d\u3002\n\n\u56e0\u61c9\u300c\u6027\u7f6a\u884c\u5b9a\u7f6a\u7d00\u9304\u67e5\u6838\u300d\u6a5f\u5236\u7d93\u5df2\u5be6\u65bd,\u90e8\u5206\u6e96\u50f1\u54e1\u5165\u8077\u524d\u9808\u9032\u884c\u6027\u7f6a\u884c\u5b9a\u7f6a\u7d00\u9304\u67e5\u6838\u3002\u4e00\u5207\u7533\u8acb\u8cc7\u6599\u7d55\u5c0d\u4fdd\u5bc6\u53ca\u53ea\u7528\u4f5c\u62db\u8058\u6709\u95dc\u8077\u4f4d\u7528\u9014\u3002\u82e5\u516d\u661f\u671f\u5167\u672a\u7372\u901a\u77e5,\u5373\u4ee3\u8868\u5176\u7533\u8acb\u672a\u7372\u8003\u616e,\u800c\u7533\u8acb\u4eba\u4e4b\u500b\u4eba\u8cc7\u6599\u4ea6\u5c07\u5728\u5b8c\u6210\u62db\u8058\u7a0b\u5e8f\u5f8c\u516d\u500b\u6708\u92b7\u6bc0\u3002\u6709\u95dc\u4fdd\u826f\u5c40\u8cc7\u6599\u53ef\u53c3\u95b1\u672c\u5c40\u7db2\u7ad9http://www.poleungkuk.org.hk\u3002\n\nPlease state the applied position and reference number in your application, send your full resume together with the current and expected salary, contact phone number by clicking \u201cAPPLY NOW\u201d.\n\nIn response to the implementation of the \"Sexual Conviction Record Check\" mechanism, some prospective employee is required to conduct a sexual conviction record check before entering employment. Applicants who are not contacted within 6 weeks may consider their application unsuccessful and all unsuccessful applications will be destroyed upon completion with six month of the recruitment exercise. For more information about Po Leung Kuk, please visit: http://www.poleungkuk.org.hk.\n\nFull-time\n\n", "employment_types": ["Full Time"], "selling_points": [], "locations": ["Sai Ying Pun"], "categories": ["Public / Civil", "Civil Services", "Building & Construction", "Civil / Structural"], "post_time": "2022-01-12T03:20:45Z", "salary": {"currency": null, "max": null, "min": null, "period": "monthly", "term": null}, "salary_visible": false, "title_keywords": ["clerk", "\u6587\u54e1"], "responsibilities": ["rehabilitation", "quality", "implementation", "recruitment", "contact", "company website"], "requirements": {"degrees": [], "majors": [], "languages": [], "language_level": [], "hard_skills": ["make"], "soft_skills": ["comprehensive", "people-oriented"], "languages_combined": []}, "experience_required": {"duration": [], "field": []}}, {"job_id": "100003009041290", "location_code": "hk", "company": "Big Grains Limited", "job_title": "\u521d\u7d1a\u9eb5\u5305\u5e2b(\u8343\u7063/\u7063\u4ed4/\u4f50\u6566)", "description": "\u8077\u8cac :\u4e00\u822c\u6587\u66f8\u5de5\u4f5c\uff0c\u5305\u62ec\u6587\u4ef6\u5b58\u6a94\u3001\u8cc7\u6599\u8f38\u5165\u7b49\uff0c\u5305\u62ec\u8907\u5370\u7b49\n\u8cc7\u6b77 :\u4e2d\u4e94\u7a0b\u5ea6; 1\u5e74\u7d93\u9a57; \u826f\u597d\u7cb5\u8a9e; \u4e00\u822c\u82f1\u8a9e; \u61c2\u8b80\u5beb\u4e2d\u6587; \u61c2\u8b80\u5beb\u82f1\u6587; \u61c2\u4e2d\u82f1\u6587\u96fb\u8166\u64cd\u4f5c; \u61c2\u4e2d\u6587\u6253\u5b57\n\u5f85\u9047 :\u6bcf\u6708$13,000\u6216\u4ee5\u4e0a (\u8996\u4e4e\u5de5\u4f5c\u7d93\u9a57\u800c\u5b9a), \u6709\u751f\u65e5\u5047, \u661f\u671f\u4e00\u81f3\u4e94: \u4e0a\u53488\u6642\u534a\u81f3\u4e0b\u53485\u6642\u534a\u53ca\u661f\u671f\u516d: \u4e0a\u53488\u6642\u534a\u81f3\u4e2d\u534812\u6642, \u6bcf\u9031\u5de5\u4f5c5\u5929\u534a, \u6bcf\u5929\u5de5\u4f5c 9 \u5c0f\u6642\n\n", "employment_types": ["Full Time"], "selling_points": [], "locations": ["Tsuen Wan Area"], "categories": ["Public / Civil", "Civil Services", "Social Services - Community / Non-profit Organization", "Others"], "post_time": "2022-01-12T03:42:24Z", "salary": {"currency": null, "max": null, "min": null, "period": "monthly", "term": null}, "salary_visible": false, "title_keywords": [], "responsibilities": [], "requirements": {"degrees": [], "majors": [], "languages": [], "language_level": [], "hard_skills": [], "soft_skills": [], "languages_combined": []}, "experience_required": {"duration": [], "field": []}}, {"job_id": "100003009041283", "location_code": "hk", "company": "Big Grains Limited", "job_title": "\u521d\u7d1a\u897f\u9905\u751c\u9ede\u5e2b", "description": "\n\u8077\u8cac :\u5354\u52a9\u88fd\u4f5c\u50b3\u7d71\u6cd5\u5f0f\u53ca\u65e5\u5f0f\u9eb5\u5305, \u6e96\u5099\u6750\u6599, \u7dad\u6301\u5eda\u623f\u74b0\u5883\u885b\u751f\n\n\u8cc7\u6b77 :\u4e2d\u4e09\u7a0b\u5ea6; \u826f\u597d\u7cb5\u8a9e\u512a\u5148; \u4e00\u822c\u666e\u901a\u8a71; \u4e00\u822c\u82f1\u8a9e; \u7565\u61c2\u8b80\u5beb\u4e2d\u6587; \u7565\u61c2\u8b80\u5beb\u82f1\u6587\n\n\u5f85\u9047 :\u6bcf\u6708$14,000 - $15,000, \u6709\u8d85\u6642\u5de5\u4f5c\u6d25\u8cbc, \u52e4\u5de5\u734e\u91d1, \u5728\u8077\u57f9\u8a13\u53ca\u914c\u60c5\u6027\u82b1\u7d05, \u4e0a\u53487\u6642\u81f3\u4e0b\u53484\u6642\u534a, \u6bcf\u9031\u5de5\u4f5c5\u5929\u81f36\u5929,\u8f2a\u4f11, \u6bcf\u5929\u5de5\u4f5c 9.5 \u5c0f\u6642\n\n\u7533\u8acb\u9808\u77e5 :\u6c42\u8077\u8005\u53ef\u81f4\u96fb90103105\u8207\u54c1\u7a40\u6709\u9650\u516c\u53f8\u937e\u5c0f\u59d0\u806f\u7d61\u3002\n\n", "employment_types": ["Full Time"], "selling_points": [], "locations": ["Shatin Area"], "categories": ["Public / Civil", "Civil Services", "Social Services - Community / Non-profit Organization", "Others"], "post_time": "2022-01-12T03:41:46Z", "salary": {"currency": null, "max": null, "min": null, "period": "monthly", "term": null}, "salary_visible": false, "title_keywords": [], "responsibilities": [], "requirements": {"degrees": [], "majors": [], "languages": [], "language_level": [], "hard_skills": [], "soft_skills": [], "languages_combined": []}, "experience_required": {"duration": [], "field": []}}, {"job_id": "100003009035876", "location_code": "hk", "company": "St. James' Settlement", "job_title": "\u793e\u6703\u5de5\u4f5c\u8005(SW III) (\u5408\u7d04)\u3008\u7de8\u865f:CHA/115021\u3009", "description": "\n\u8077\u8cac :\u88fd\u4f5c\u6cd5\u5f0f\u751c\u54c1, \u8ca0\u8cac\u5eda\u623f\u6e96\u5099\u5de5\u4f5c, \u7814\u767c\u751c\u9ede\u6b3e\u5f0f, \u5354\u52a9\u5206\u90e8\u4e3b\u7ba1\u76e3\u63a7\u5eda\u623f\u51fa\u54c1, \u78ba\u4fdd\u885b\u751f\u53ca\u7522\u54c1\u751f\u7522\u9054\u6a19\u6e96\n\n\u8cc7\u6b77 :\u4e2d\u4e09\u7a0b\u5ea6; 1\u5e74\u7d93\u9a57; \u826f\u597d\u7cb5\u8a9e\u512a\u5148; \u4e00\u822c\u666e\u901a\u8a71; \u4e00\u822c\u82f1\u8a9e; \u61c2\u8b80\u5beb\u4e2d\u6587; \u7565\u61c2\u8b80\u5beb\u82f1\u6587\n\n\u5f85\u9047 :\u6bcf\u6708$13,000 - $14,500, \u6709\u8d85\u6642\u5de5\u4f5c\u6d25\u8cbc, \u52e4\u5de5\u734e\u91d1, \u5e74\u504710\u5929, \u751f\u65e5\u50471\u5929, \u914c\u60c5\u6027\u82b1\u7d05\u53ca\u54e1\u5de5\u8cfc\u7269\u512a\u60e0, \u4e0a\u53487\u6642\u81f3\u4e0b\u53485\u6642, \u6bcf\u9031\u5de5\u4f5c5\u5929\u81f36\u5929,\u8f2a\u4f11, \u6bcf\u5929\u5de5\u4f5c 9 - 10 \u5c0f\u6642\n\n\u7533\u8acb\u9808\u77e5 :\u6c42\u8077\u8005\u53ef\u81f4\u96fb90103105\u8207\u54c1\u7a40\u6709\u9650\u516c\u53f8\u937e\u5c0f\u59d0\u806f\u7d61\u3002\n\n", "employment_types": ["Full Time"], "selling_points": [], "locations": ["Not Specified"], "categories": ["Public / Civil", "Civil Services", "Utilities", "Others"], "post_time": "2022-01-10T08:38:07Z", "salary": {"currency": null, "max": null, "min": null, "period": "monthly", "term": null}, "salary_visible": false, "title_keywords": [], "responsibilities": [], "requirements": {"degrees": [], "majors": [], "languages": [], "language_level": [], "hard_skills": [], "soft_skills": [], "languages_combined": []}, "experience_required": {"duration": [], "field": []}}, {"job_id": "100003009033415", "location_code": "hk", "company": "Helping Hand", "job_title": "\u4fdd\u5065\u54e1 Health Worker (Ref: HW)", "description": "\u5730\u5340 :\u77f3\u7864\u5c3e,\u8475\u6d8c\n\n\n\u8077\u8cac :\u77ed\u671f\u98df\u7269\u63f4\u52a9\u7533\u8acb\u5be9\u6279\u53ca\u7763\u5c0e\u524d\u7dda\u540c\u4e8b;\u7368\u7acb\u8ca0\u8cac\u500b\u6848\u5de5\u4f5c\u3001\u7c4c\u8fa6\u5c0f\u7d44\u53ca\u6d3b\u52d5\uff1b\u5efa\u7acb\u5354\u8abf\u7fa9\u5de5\u7db2\u7d61 (1\u5e74\u5408\u7d04\uff0c\u6309\u5e74\u53ef\u7e8c)(\u96fb\u90f5:[via APPLY NOW])\n\u8cc7\u6b77 :\u5c08\u4e0a\u6559\u80b2\uff1a\u6587\u6191/\u8b49\u66f8; \u6703\u8003\u4e94\u79d1\u5408\u683c; \u826f\u597d\u7cb5\u8a9e; \u4e00\u822c\u82f1\u8a9e; \u61c2\u8b80\u5beb\u4e2d\u6587; \u61c2\u8b80\u5beb\u82f1\u6587; \u6301\u8a8d\u53ef\u793e\u6703\u5de5\u4f5c\u6587\u6191\u6216\u4ee5\u4e0a\uff0c\u8a3b\u518a\u793e\u5de5; \u4e2d\u5b78\u6703\u8003\u4e94\u79d1\u5408\u683c\uff0c\u5305\u4e2d\u570b\u8a9e\u6587\u53ca\u82f1\u6587(\u8ab2\u7a0b\u4e59)E\u7d1a\u4ee5\u4e0a\u6216\u7b49\u540c\n\u5f85\u9047 :\u6bcf\u6708$23,210, \u4e0a\u53489\u6642\u81f3\u4e0b\u53486\u6642\u53ca\u4e0a\u53489\u6642\u81f3\u4e0b\u53481\u6642, \u6bcf\u9031\u5de5\u4f5c5\u5929\u81f35\u5929\u534a(44\u5c0f\u6642),\u8f2a\u4f11\n\u7533\u8acb\u9808\u77e5 :\u6c42\u8077\u8005\u53ef\u96fb\u90f5\u5c65\u6b77\u8868\u7d66\u8056\u96c5\u5404\u798f\u7fa4\u6703\u3002\u5982\u8981\u7d22\u53d6\u6536\u96c6\u500b\u4eba\u8cc7\u6599\u8072\u660e, \u8acb\u8207\u984f\u5c0f\u59d0(T:25962746)\u806f\u7d61\u3002", "employment_types": ["Full Time"], "selling_points": [], "locations": ["Not Specified"], "categories": ["Public / Civil", "Civil Services", "Medical Services", "Others", "Social Services - Community / Non-profit Organization"], "post_time": "2022-01-10T05:06:12Z", "salary": {"currency": null, "max": null, "min": null, "period": "monthly", "term": null}, "salary_visible": false, "title_keywords": ["\u4fdd\u5065\u54e1"], "responsibilities": [], "requirements": {"degrees": [], "majors": [], "languages": [], "language_level": [], "hard_skills": [], "soft_skills": [], "languages_combined": []}, "experience_required": {"duration": [], "field": []}}, {"job_id": "100003009053261", "location_code": "hk", "company": "AA Choice Personnel Consultancy Limited", "job_title": "Non-Ethnic Chinese Activity Coordinator - Urdu or NEC Speaking (5 days)", "description": "Requirements:\n\nHave completed secondary 5 or equivalent\nBe able to communicate effectively in Chinese and English, both in written and spoken forms and\nPreferably be proficient in Urdu (or other NEC languages)\nWith proficiency in Cantonese and / or\u00a0\nWith relevant working experience and knowledge in running programmes for non-ethnic Chinese, publicity and promotional work, receiving the public or event coordination.\nDuties:\n\nTo assist in preparing and conducting group activities and programmes, publicity and promotional work, training and various activities, including but not limited to those for non-ethnic Chinese (NEC).\n\nLocation : Wanchai\n\nSelected candidate will be conducted Sexual Conviction Record Check\n\n\u00a0Interested parties, please send your resume in\u00a0WORD\u00a0format, stating your\u00a0current, expected salary and availability by clicking APPLY NOW.", "employment_types": ["Full Time", "Contract"], "selling_points": ["Urdu or other NEC languages", "Able to communicate in Chinese and English", "Government Contract, fresh graduate welcome"], "locations": ["Wan Chai"], "categories": ["Admin & HR", "Clerical / Admin Staff", "Public / Civil", "Civil Services", "Marketing / Public Relations", "Marketing - General / Support"], "post_time": "2022-01-17T06:36:20Z", "salary": {"currency": null, "max": null, "min": null, "period": "monthly", "term": null}, "salary_visible": false, "title_keywords": ["coordinator"], "responsibilities": [], "requirements": {"degrees": [], "majors": [], "languages": ["urdu", "cantonese", "english", "chinese"], "language_level": ["proficiency", "proficient"], "hard_skills": [], "soft_skills": ["coordination"], "languages_combined": [{"language": "urdu", "language_level": ["proficient"]}, {"language": "cantonese", "language_level": ["proficiency"]}, {"language": "english", "language_level": []}, {"language": "chinese", "language_level": []}]}, "experience_required": {"duration": [], "field": ["relevant working experience"]}}, {"job_id": "100003009035447", "location_code": "hk", "company": "Nova Management Consultants Ltd", "job_title": "Temporary clerk \u6587\u54e1  ($13224)(Wan Chai)(2-3M) (\u8f03\u591a\u5916\u51fa\u5de5\u4f5c) (\u653f\u5e9c\u90e8\u9580) (\u53ef\u7e8c\u7d04)", "description": "Duties:\n\n1.Perform outdoor work (visiting local retailer outlet and conduct test purchases when necessary);\n\n2. Conduct background search (e.g. company search, business registration search) to support investigation work;\n\n3. Maintain the record of the monthly market surveillance, prepare the sample for sending to related department and assist in monitoring the testing result;\n\n4. Maintain the record of website monitoring data, prepare and file the follow-up document; and\n\n5. Perform general clerical duties for CMD\n\n.\n\n\u8077\u8cac:\n\n1) \u8f03\u591a\u5916\u51fa\u5de5\u4f5c\u7684\u6642\u9593, \u8ca0\u8cac\u5e6b\u90e8\u9580\u8cfc\u8cb7\u6240\u9700\u7528\u54c1, \u904b\u9001\u7269\u54c1\u5230\u5176\u4ed6\u653f\u5e9c\u90e8\u9580\u7b49\n\n2) \u53ca\u4e00\u822c\u8fa6\u516c\u5ba4\u7684\u5de5\u4f5c\n\n.\n\nRequirement(s):\n\n1.F.5, Have 5 subjects at Grade E/Level 2 or above in Hong Kong Diploma of Secondary Education Examination or in Hon Kong Certificate Of Education Examination, including Chinese Language and English Language (Syllabus B before 2007) are preferably, or equivalent:\n\n2.Possess basic computer knowledge, including MS Word and Excel;\n\n3.Have good typing and communication skills in both English and Chinese; and\n\n4.Permanent resident of the Hong Kong Special Administrative Region\n\n(Fresh graduate are welcome)\n.\n\n\u8981\u6c42:\n\n1) \u9700\u559c\u6b61\u5916\u51fa\u5de5\u4f5c\u7684\u4eba\u58eb\n\n2) \u4e2d\u4e94\u7a0b\u5ea6\n\n3) \u80fd\u4e2d\u6587\u6253\u5b57\u53ca\u82f1\u6587\u6253\u5b57\n\n\u6b61\u8fce\u7562\u696d\u751f", "employment_types": ["Full Time", "Temporary", "Contract"], "selling_points": ["F.5", "Require Outdoor Work", "Immediate available preferred"], "locations": ["Wan Chai"], "categories": ["Public / Civil", "Civil Services"], "post_time": "2022-01-10T07:12:38Z", "salary": {"currency": null, "max": null, "min": null, "period": "monthly", "term": null}, "salary_visible": false, "title_keywords": ["temporary clerk", "\u6587\u54e1"], "responsibilities": ["outdoor work", "data", "monitoring", "website", "investigation", "testing", "maintain", "company search"], "requirements": {"degrees": ["certificate", "diploma", "secondary education", "fresh graduate"], "majors": [], "languages": ["english", "chinese"], "language_level": ["good"], "hard_skills": ["excel", "basic", "typing", "ms word"], "soft_skills": ["communication skills"], "languages_combined": [{"language": "english", "language_level": ["good"]}, {"language": "chinese", "language_level": ["good"]}]}, "experience_required": {"duration": [], "field": []}}, {"job_id": "100003009010369", "location_code": "hk", "company": "Haven of Hope Christian Service", "job_title": "\u5065\u5eb7\u670d\u52d9\u54e1 - \u5bb6\u5c45\u4e0a\u9580\u670d\u52d9 (\u7de8\u865f: EHCCS/HSW/L)", "description": "\u5730\u5340 :\u89c0\u5858,\u5c07\u8ecd\u6fb3,\u9ec3\u5927\u4ed9,\u897f\u8ca2\n\u884c\u696d :\u798f\u5229\u6a5f\u69cb\n\u8077\u8cac :\u8ca0\u8cac\u670d\u52d9\u5bb6\u5c45\u4e4b\u9577\u8005\u53ca\u9577\u671f\u75c5\u60a3\u8005\u7684\u65e5\u5e38\u8b77\u7406\u7167\u9867\u5de5\u4f5c\uff0c\u5305\u62ec\u6c90\u6d74\u3001\u5fa9\u5eb7\u8a13\u7df4\u3001\u5982\u5ec1\u3001\u9001\u98ef\u3001\u966a\u4f34\u3001\u5bb6\u5c45\u6e05\u6f54\u53ca\u966a\u8a3a\u7b49\n\u8cc7\u6b77 :\u5c0f\u516d\u7a0b\u5ea6; 1\u5e74\u7d93\u9a57; \u826f\u597d\u7cb5\u8a9e; \u61c2\u8b80\u5beb\u4e2d\u6587; \u5177\u4e00\u5e74\u6216\u4ee5\u4e0a\u76f8\u95dc\u8a13\u7df4\u53ca\u5de5\u4f5c\u7d93\u9a57\uff0c\u5177\u5de5\u4f5c\u71b1\u8aa0\u3001\u6709\u8010\u5fc3\u53ca\u6709\u611b\u5fc3\n\u5f85\u9047 :\u6bcf\u6708$17,120, \u6709\u5e74\u504712\u5929, \u751f\u65e5\u50471\u5929 \u53ca\u91ab\u7642\u798f\u5229, \u661f\u671f\u4e00\u81f3\u516d: \u4e0a\u53488\u6642\u534a\u81f3\u4e0b\u53486\u6642\u534a, \u6bcf\u9031\u5de5\u4f5c6\u5929, \u6bcf\u5929\u5de5\u4f5c 8 \u5c0f\u6642\n\u7533\u8acb\u9808\u77e5 :\u6c42\u8077\u8005\u53ef\u6309 APPLY NOW\u7533\u8acb", "employment_types": ["Full Time"], "selling_points": ["\u8ca0\u8cac\u670d\u52d9\u5bb6\u5c45\u4e4b\u9577\u8005\u53ca\u9577\u671f\u75c5\u60a3\u8005\u7684\u65e5\u5e38\u8b77\u7406\u7167\u9867", "\u5c0f\u516d\u7a0b\u5ea6; 1\u5e74\u7d93\u9a57", "\u5177\u4e00\u5e74\u6216\u4ee5\u4e0a\u76f8\u95dc\u8a13\u7df4\u53ca\u5de5\u4f5c\u7d93\u9a57"], "locations": ["Not Specified"], "categories": ["Public / Civil", "Civil Services", "Medical Services", "Others", "Social Services - Community / Non-profit Organization"], "post_time": "2021-12-31T03:40:42Z", "salary": {"currency": null, "max": null, "min": null, "period": "monthly", "term": null}, "salary_visible": false, "title_keywords": ["\u5065\u5eb7\u670d\u52d9\u54e1"], "responsibilities": [], "requirements": {"degrees": [], "majors": [], "languages": [], "language_level": [], "hard_skills": [], "soft_skills": [], "languages_combined": []}, "experience_required": {"duration": [], "field": []}}, {"job_id": "100003009010449", "location_code": "hk", "company": "Haven of Hope Christian Service", "job_title": "\u9ad8\u7d1a\u5065\u5eb7\u670d\u52d9\u54e1-\u5fa9\u5eb7\u9662\u820d (\u7de8\u865f: RSD/SHSW/L)", "description": "\u5730\u5340 :\u79c0\u8302\u576a,\u5c07\u8ecd\u6fb3,\u897f\u8ca2\n\u8077\u8cac :\u8ca0\u8cac\u70ba\u667a\u969c\u6216\u80a2\u9ad4\u50b7\u6b98\u4eba\u58eb\u63d0\u4f9b\u8b77\u7406\u670d\u52d9\n\u8cc7\u6b77 :\u4e2d\u4e94\u7a0b\u5ea6; 1\u5e74\u7d93\u9a57; \u826f\u597d\u7cb5\u8a9e; \u4e00\u822c\u82f1\u8a9e; \u61c2\u8b80\u5beb\u4e2d\u6587; \u61c2\u8b80\u5beb\u82f1\u6587; \u6301\u6709\u5b89\u8001\u9662\u4fdd\u5065\u54e1\u8a3b\u518a\u8b49; \u6301\u6709\u6b98\u75be\u4eba\u58eb\u9662\u820d\u4fdd\u5065\u54e1\u8a3b\u518a\u8b49; \u5177\u4e00\u5e74\u6216\u4ee5\u4e0a\u4fdd\u5065\u54e1\u5de5\u4f5c\u7d93\u9a57, \u66fe\u4fee\u8b80\u4fdd\u5065\u54e1\u7d71\u4e00\u8a13\u7df4\u8ab2\u7a0b\u6216\u6b98\u75be\u4eba\u58eb\u9662\u820d\u4fdd\u5065\u54e1\u8ab2\u7a0b, \u4e26\u5df2\u8a3b\u518a\u6210\u70ba\u4fdd\u5065\u54e1\n\u5f85\u9047 :\u6bcf\u6708$18,795, \u6709\u5e74\u504712\u5929, \u751f\u65e5\u50471\u5929\u53ca\u91ab\u7642\u798f\u5229, 24\u5c0f\u6642\u8f2a\u73ed, \u6bcf\u9031\u5de5\u4f5c5\u5929\u81f36\u5929,\u8f2a\u4f11, \u6bcf\u5929\u5de5\u4f5c 7 - 8 \u5c0f\u6642\n\u7533\u8acb\u9808\u77e5 :\u6c42\u8077\u8005\u53ef\u6309 APPLY NOW\u7533\u8acb", "employment_types": ["Full Time"], "selling_points": ["\u8ca0\u8cac\u70ba\u667a\u969c\u6216\u80a2\u9ad4\u50b7\u6b98\u4eba\u58eb\u63d0\u4f9b\u8b77\u7406\u670d\u52d9", "\u4e2d\u4e94\u7a0b\u5ea6; 1\u5e74\u7d93\u9a57", "\u826f\u597d\u7cb5\u8a9e"], "locations": ["Not Specified"], "categories": ["Public / Civil", "Civil Services", "Medical Services", "Others", "Social Services - Community / Non-profit Organization"], "post_time": "2021-12-31T03:50:32Z", "salary": {"currency": null, "max": null, "min": null, "period": "monthly", "term": null}, "salary_visible": false, "title_keywords": [], "responsibilities": [], "requirements": {"degrees": [], "majors": [], "languages": [], "language_level": [], "hard_skills": [], "soft_skills": [], "languages_combined": []}, "experience_required": {"duration": [], "field": []}}, {"job_id": "100003009010401", "location_code": "hk", "company": "Haven of Hope Christian Service", "job_title": "\u5065\u5eb7\u670d\u52d9\u54e1-\u5fa9\u5eb7\u9662\u820d (\u7de8\u865f: RSD&CASD/HSW/L)", "description": "\u8077\u8cac :\u8ca0\u8cac\u7167\u9867\u9662\u820d\u80a2\u9ad4\u50b7\u6b98\u4eba\u58eb\u65e5\u5e38\u8d77\u5c45\u751f\u6d3b, \u5305\u62ec\u6c90\u6d74\u3001\u5982\u5ec1\u53ca\u966a\u8a3a\u7b49\n\u8cc7\u6b77 :\u5c0f\u516d\u7a0b\u5ea6; 1\u5e74\u7d93\u9a57; \u826f\u597d\u7cb5\u8a9e; \u4e00\u822c\u82f1\u8a9e; \u61c2\u8b80\u5beb\u4e2d\u6587; \u61c2\u8b80\u5beb\u82f1\u6587; \u5177\u4e00\u5e74\u6216\u4ee5\u4e0a\u76f8\u95dc\u8a13\u7df4\u53ca\u5de5\u4f5c\u7d93\u9a57; \u5de5\u4f5c\u5bcc\u71b1\u8aa0, \u5177\u8010\u5fc3\u53ca\u6709\u611b\u5fc3\n\u5f85\u9047 :\u6bcf\u6708$18,235, \u6709\u5e74\u504712\u5929, \u751f\u65e5\u50471\u5929\u53ca\u91ab\u7642\u798f\u5229, 24\u5c0f\u6642\u8f2a\u73ed, \u6bcf\u9031\u5de5\u4f5c5\u5929\u81f36\u5929,\u8f2a\u4f11, \u6bcf\u5929\u5de5\u4f5c 7 - 8 \u5c0f\u6642\n\u7533\u8acb\u9808\u77e5 :\u6c42\u8077\u8005\u53ef\u6309 APPLY NOW\u7533\u8acb", "employment_types": ["Full Time"], "selling_points": ["\u8ca0\u8cac\u7167\u9867\u9662\u820d\u80a2\u9ad4\u50b7\u6b98\u4eba\u58eb\u65e5\u5e38\u8d77\u5c45\u751f\u6d3b", "\u5c0f\u516d\u7a0b\u5ea6; 1\u5e74\u7d93\u9a57", "\u826f\u597d\u7cb5\u8a9e"], "locations": ["Tseung Kwan O"], "categories": ["Public / Civil", "Civil Services", "Social Services - Community / Non-profit Organization", "Others"], "post_time": "2021-12-31T03:42:20Z", "salary": {"currency": null, "max": null, "min": null, "period": "monthly", "term": null}, "salary_visible": false, "title_keywords": ["\u5065\u5eb7\u670d\u52d9\u54e1"], "responsibilities": [], "requirements": {"degrees": [], "majors": [], "languages": [], "language_level": [], "hard_skills": [], "soft_skills": [], "languages_combined": []}, "experience_required": {"duration": [], "field": []}}, {"job_id": "100003009013573", "location_code": "hk", "company": "Grow Up Photo", "job_title": "\u521d\u7d1a\u651d\u5f71\u5e2b", "description": "\n\u8077\u8cac :\u8655\u7406\u5f71\u6a13\u65e5\u5e38\u904b\u4f5c\uff0c\u4f8b\u5982\uff1a\u5e97\u8216\u6574\u7406\uff0c\u5f71\u76f8\u53ca\u57f7\u76f8\uff0c\u9700\u8981\u5916\u51fa\u5de5\u4f5c\n\n\u8cc7\u6b77 :\u4e2d\u4e94\u7a0b\u5ea6; 1\u5e74\u7d93\u9a57; \u826f\u597d\u7cb5\u8a9e; \u4e00\u822c\u666e\u901a\u8a71; \u4e00\u822c\u82f1\u8a9e; \u61c2\u8b80\u5beb\u4e2d\u6587; \u61c2\u95b1\u8b80\u82f1\u6587; \u6709\u8cac\u4efb\u611f\uff0c\u91cd\u8996\u5718\u968a\u5408\u4f5c\uff0c\u6709\u826f\u597d\u6e9d\u901a\u6280\u5de7\uff0c\u5c0d\u5c0f\u670b\u53cb\u6709\u8010\u6027\u53ca\u611b\u5fc3\uff0c\u6709\u62cd\u651d\u5c0f\u670b\u53cb\u7d93\u9a57\u512a\u5148\n\n\u5f85\u9047 :\u6bcf\u6708$11,000 - $13,000, \u6709\u52e4\u5de5\u734e\u91d1, \u82b1\u7d05, \u4f63\u91d1, \u5728\u8077\u57f9\u8a13 \u53ca\u6649\u5347\u6a5f\u6703, \u661f\u671f\u4e00\u81f3\u516d: \u4e0a\u53489\u6642\u81f3\u4e0b\u53486\u6642, \u6bcf\u9031\u5de5\u4f5c6\u5929, \u6bcf\u5929\u5de5\u4f5c 9 \u5c0f\u6642\n\n\u7533\u8acb\u9808\u77e5 :\u6c42\u8077\u8005\u53ef\u96fb\u90f5(Apply Now)\u5c65\u6b77\u8868\u7d66GROW UP PHOTO\u3002\u5982\u8981\u7d22\u53d6\u6536\u96c6\u500b\u4eba\u8cc7\u6599\u8072\u660e, \u8acb\u8207\u9678\u5973\u58eb(Email)\u806f\u7d61\u3002\n\n", "employment_types": ["Full Time"], "selling_points": [], "locations": ["Ngau Tau Kok"], "categories": ["Public / Civil", "Civil Services", "Social Services - Community / Non-profit Organization", "Others"], "post_time": "2022-01-03T02:30:21Z", "salary": {"currency": null, "max": null, "min": null, "period": "monthly", "term": null}, "salary_visible": false, "title_keywords": [], "responsibilities": [], "requirements": {"degrees": [], "majors": [], "languages": [], "language_level": [], "hard_skills": [], "soft_skills": [], "languages_combined": []}, "experience_required": {"duration": [], "field": []}}, {"job_id": "100003009001503", "location_code": "hk", "company": "Serco Group (HK) Limited", "job_title": "Building Maintenance Officer", "description": "Job Responsibilities\n\nResponsible for all building maintenance activities including internal fabric maintenance redecoration of Building.\nResponsible for supervisory checks on all civil, structural, cleansing and general building maintenance works in accordance with the required standards.\nLiaise and co-ordinate with internal and external parties on day-to-day maintenance of Building Tunnel Structures.\nResponsible for the health and safety aspects of the operational environment.\n\nJob Requirement\n\n\n\nHolder of Diploma / Certificate in related discipline.\nMinimum 3 years of post-qualification work experience in building service.\nMinimum 1 year of supervisory experience.\n\nWe offer an attractive remuneration package and excellent career development opportunities to the right candidate. Please send detailed resume with your availability, present and expected salary to Ms. Lee:\nBy email: Sara.lee @ serco-ap.com\nBy phone / Whatsapp: 9857 2126\n\n(Data collected will be treated as strictly confidential and used for recruitment propose only)", "employment_types": ["Full Time"], "selling_points": ["Building Maintenance Works", "Minimum 1year supervisory experience", "Able to work independent and lead a team"], "locations": ["Sheung Shui"], "categories": ["Public / Civil", "Civil Services", "Building & Construction", "Building / Construction / QS", "Civil / Structural"], "post_time": "2021-12-28T02:32:07Z", "salary": {"currency": null, "max": null, "min": null, "period": "monthly", "term": null}, "salary_visible": false, "title_keywords": ["maintenance officer"], "responsibilities": ["liaise", "maintenance", "co-ordinate with", "cleansing", "internal and external parties"], "requirements": {"degrees": ["certificate", "diploma"], "majors": [], "languages": [], "language_level": [], "hard_skills": [], "soft_skills": [], "languages_combined": []}, "experience_required": {"duration": ["minimum 1 year", "minimum 3 years"], "field": ["post-qualification", "supervisory experience"]}}, {"job_id": "100003009014327", "location_code": "hk", "company": "Insport Garments Manufactory Company Limited", "job_title": "\u521d\u7d1a\u63a1\u8cfc\u54e1", "description": "\n\u8077\u8cac :\u4e00\u822c\u8ddf\u55ae\u53ca\u63a1\u8cfc\u5de5\u4f5c,includes handling orders from sample development to bulk delivery; work with local/overseas clients and vendors; handle customer inquiries including trims and fabrics sourcing, sample arrangement, product development & price quotation\n\n\u8cc7\u6b77 :\u4e2d\u516d\u7a0b\u5ea6; 2\u5e74\u7d93\u9a57; \u826f\u597d\u7cb5\u8a9e\u512a\u5148; \u826f\u597d\u666e\u901a\u8a71\u512a\u5148; \u826f\u597d\u82f1\u8a9e\u512a\u5148; \u61c2\u8b80\u5beb\u4e2d\u6587; \u61c2\u8b80\u5beb\u82f1\u6587; \u61c2Microsoft Office; \u61c2MS Word; \u61c2MS Outlook; \u61c2MS Excel; \u61c2\u5009\u9821/\u901f\u6210\u8f38\u5165\u6cd5; (Immediately available pref.)\n\n\u5f85\u9047 :\u6bcf\u6708$13,000 - $15,000, \u6709\u96d9\u7ce7, \u5e74\u504714\u5929, \u914c\u60c5\u6027\u82b1\u7d05 \u53ca\u9032\u4fee\u6d25\u8cbc, \u661f\u671f\u4e00\u81f3\u4e94: \u4e0a\u53489\u6642\u534a\u81f3\u4e0b\u53486\u6642\u534a, \u6bcf\u9031\u5de5\u4f5c5\u5929, \u6bcf\u5929\u5de5\u4f5c 9 \u5c0f\u6642\n\n\u7533\u8acb\u9808\u77e5 :\u6c42\u8077\u8005\u53ef\u96fb\u90f5(Apply Now)\u5c65\u6b77\u8868\u7d66\u82f1\u58eb\u535a\u88fd\u8863\u5ee0\u6709\u9650\u516c\u53f8\u3002\u5982\u8981\u7d22\u53d6\u6536\u96c6\u500b\u4eba\u8cc7\u6599\u8072\u660e, \u8acb\u8207\u8521\u5c0f\u59d0(Email)\u806f\u7d61\u3002\n\n", "employment_types": ["Full Time"], "selling_points": [], "locations": ["Kwun Tong Area"], "categories": ["Public / Civil", "Civil Services", "Social Services - Community / Non-profit Organization", "Others"], "post_time": "2022-01-03T03:17:09Z", "salary": {"currency": null, "max": null, "min": null, "period": "monthly", "term": null}, "salary_visible": false, "title_keywords": [], "responsibilities": ["quotation", "customer inquiries"], "requirements": {"degrees": [], "majors": [], "languages": [], "language_level": [], "hard_skills": ["excel", "outlook", "word"], "soft_skills": [], "languages_combined": []}, "experience_required": {"duration": [], "field": []}}, {"job_id": "100003008997574", "location_code": "hk", "company": "Estate Agents Authority", "job_title": "OFFICER (Examination) (Ref No.: EAA-2021/19)", "description": "Key Responsibilities\n\nThe incumbent will be posted to the Legal Services & Examination Section to handle the following:\n\nassist in the setting and developing of questions for qualifying examinations\nco-ordinate the administration of qualifying examinations with the appointed service provider\nassist with the preparation of examination-related documentation, reports and statistics\nfollow up with incidents that involve examination irregularities and breaches of examination regulations\nhandle enquiries on qualifying examinations and related matters\nperform such other duties as may from time to time be assigned\nRequirements\nA recognized university degree, preferably in law\nAt least 2 years\u2019 relevant working experience in law firms and preferably in property related practice\nLegal executive without a recognized university degree but with at least 6 years of solid experience in property related practice will be considered\nPrevious examination officer experience is an added advantage\nGood command of both written and spoken English and Chinese (Preferably attained Grade \u201cC\u201d or above in English Language (Syllabus B) and Chinese Language in HKCEE, or Level 4 or above in HKDSEE, or equivalent)\nGood communication skills\nMeticulous and a strong team player\nTerms of Appointment\nCompetitive remuneration package commensurate with the selected candidate\u2019s qualifications and experience will be offered. The appointee will initially be offered a 3-year contract, subject to renewal upon satisfactory performance and the service needs of the Authority.\nApplication Procedure\nApplications with full resume indicating your current and expected salaries and your public examination results should be sent to: Human Resources Section, Estate Agents Authority, 7/F, E-Trade Plaza, 24 Lee Chung Street, Chaiwan, Hong Kong or via email by clicking \"Apply Now\" not later than 31 December 2021. Candidates who have already responded to our previous advertisement of the same post in November 2021 need not re-apply. Please mark \u201cPrivate and Confidential\u201d on the envelope and quote the post applied for and its reference number on the envelope.\nCandidates who are not invited to attend an interview within 6 weeks from the closing date may assume their applications unsuccessful. Applications may be considered for other suitable positions within the Authority. All applications will be treated in strict confidence. Personal data provided in the applications will only be used for recruitment-related purposes. All information on non-shortlisted applicants will be destroyed after 6 months.\n\n\n\u00a0\u00a0\u00a0\u00a0\u00a0\u00a0\u00a0\u00a0\u00a0\u00a0\u00a0\u00a0\u00a0\u00a0\u00a0\u00a0\u00a0\u00a0\u00a0\u00a0\u00a0\u00a0\u00a0\u00a0\u00a0\u00a0\u00a0\u00a0\u00a0\u00a0\u00a0\u00a0\u00a0\u00a0\u00a0\u00a0\u00a0 WE ARE AN EQUAL\u00a0OPPORTUNITIES EMPLOYER\n", "employment_types": ["Full Time", "Contract"], "selling_points": [], "locations": ["Chai Wan"], "categories": ["Public / Civil", "Civil Services", "Professional Services", "Legal & Compliance"], "post_time": "2021-12-23T20:10:22Z", "salary": {"currency": null, "max": null, "min": null, "period": "monthly", "term": null}, "salary_visible": false, "title_keywords": ["officer"], "responsibilities": ["regulations", "irregularities", "related documentation", "other duties", "developing", "handle enquiries", "reports", "administration"], "requirements": {"degrees": ["university degree"], "majors": ["law"], "languages": ["english", "chinese"], "language_level": ["good command"], "hard_skills": ["c"], "soft_skills": ["communication skills", "team player", "confidence", "meticulous"], "languages_combined": [{"language": "english", "language_level": ["good command"]}, {"language": "chinese", "language_level": ["good command"]}]}, "experience_required": {"duration": ["at least 2 years", "at least 6 years"], "field": ["related", "relevant working experience", "legal"]}}, {"job_id": "100003008999771", "location_code": "hk", "company": "EIDEALINK LIMITED", "job_title": "Assistant Manager", "description": "Job Responsibilities:\n\nTo support in developing creative ideas and concepts for producing multimedia and online publicity materials, and to research, create, edit and proofread such materials.\nTo record video messages for various occasions and to conduct photo and/or video shooting of events and to edit the photos and footage to produce multimedia or online publicity materials.\nTo assist in maintaining and updating Youtube channel and any other social media.\nTo provide support to the publicity of\u00a0 projects and prepare speeches and powerpoint/video presentations, etc.\nTo assist in maintaining and updating websites\nTo perform other duties as assigned by senior officers.\n\nJob Requirements:\n\nBachelor Degree Holder preferably in creative media or multimedia design, or equivalent\n1 year of relevant experience in creative media or digital advertising\nWell versed with video shooting and editing, multimedia design and / or creating content for social media. Experience in Government will be an advantage\nGood knowledge of equipment and computer software including Word, Excel, Powerpoint, Chinese word-processing, Photoshop, Adobe, etc\nGood command in both written and spoken English & Chinese\nBe able to work independently and possess good interpersonal skills.", "employment_types": ["Full Time"], "selling_points": ["5 days work", "Government department", "1 year experience"], "locations": ["Wan Chai"], "categories": ["Public / Civil", "Civil Services"], "post_time": "2021-12-24T08:46:06Z", "salary": {"currency": "HKD", "max": 34999, "min": 30000, "period": "monthly", "term": null}, "salary_visible": true, "title_keywords": ["assistant manager"], "responsibilities": ["social media", "creative ideas", "provide support", "perform other duties", "maintaining", "developing", "presentations", "video shooting"], "requirements": {"degrees": ["bachelor degree holder"], "majors": ["multimedia design", "creative media"], "languages": ["english", "chinese"], "language_level": ["good command", "good"], "hard_skills": ["excel", "chinese word-processing", "word", "powerpoint", "adobe", "multimedia", "photoshop"], "soft_skills": ["work independently", "creative", "interpersonal skills"], "languages_combined": [{"language": "english", "language_level": ["good command", "good"]}, {"language": "chinese", "language_level": ["good command", "good", "good"]}]}, "experience_required": {"duration": ["1 year"], "field": ["digital", "advertising", "relevant experience", "media"]}}, {"job_id": "100003009013499", "location_code": "hk", "company": "Reliance Engineering (HK) Company Limited", "job_title": "\u521d\u7d1a/\u96fb\u5668\u6280\u5de5", "description": "\n\u8077\u8cac :\u4e00\u822c\u96fb\u529b\u5b89\u88dd, \u7dad\u4fee,\u92ea\u8a2d\u96fb\u8def, \u71c8\u5589, \u68b3\u831c, \u96fb\u69fd, \u63a3\u6ac3, \u96fb\u529b\u7cfb\u7d71\u6aa2\u67e5(WR2)\n\n\u8cc7\u6b77 :\u6c92\u6709\u5b78\u6b77\u8981\u6c42; 2\u5e74\u7d93\u9a57; \u826f\u597d\u7cb5\u8a9e; \u4e00\u822c\u82f1\u8a9e; \u61c2\u8b80\u5beb\u4e2d\u6587; \u7565\u61c2\u8b80\u5beb\u82f1\u6587; \u6301\u6709\u5e73\u5b89\u54ad; \u6301\u6709\u5efa\u9020\u696d\u5de5\u4eba\u8a3b\u518a\u8b49; \u5de5\u4f5c\u4e3b\u52d5\u52e4\u596e, \u9858\u610f\u5b78\u7fd2, \u8981\u6709\u8cac\u4efb\u611f, \u670d\u5f9e\u4e0a\u53f8\u5de5\u4f5c\u5b89\u6392, \u5b88\u6642\n\n\u5f85\u9047 :\u6bcf\u65e5$600.00 - $900.00(\u8996\u4e4e\u7d93\u9a57\u800c\u5b9a), \u6709\u914c\u60c5\u6027\u82b1\u7d05 \u53ca\u8d85\u6642\u5de5\u4f5c\u6d25\u8cbc, \u661f\u671f\u4e00\u81f3\u516d: \u4e0a\u53489\u6642\u81f3\u4e0b\u53486\u6642, \u6bcf\u9031\u5de5\u4f5c6\u5929, \u6bcf\u5929\u5de5\u4f5c 8 \u5c0f\u6642\n\n\u7533\u8acb\u9808\u77e5 :\u6c42\u8077\u8005\u53ef\u81f4\u96fb21561166\u8207\u97cb\u5229\u8fc5\u5de5\u7a0b(\u9999\u6e2f)\u6709\u9650\u516c\u53f8\u5289\u5c0f\u59d0\u806f\u7d61\u3002\n\n", "employment_types": ["Full Time"], "selling_points": [], "locations": ["Not Specified"], "categories": ["Public / Civil", "Civil Services", "Social Services - Community / Non-profit Organization", "Others"], "post_time": "2022-01-03T02:25:14Z", "salary": {"currency": null, "max": null, "min": null, "period": "hourly", "term": null}, "salary_visible": false, "title_keywords": [], "responsibilities": [], "requirements": {"degrees": [], "majors": [], "languages": [], "language_level": [], "hard_skills": [], "soft_skills": [], "languages_combined": []}, "experience_required": {"duration": [], "field": []}}, {"job_id": "100003008997572", "location_code": "hk", "company": "Estate Agents Authority", "job_title": "ADMINISTRATIVE ASSISTANT (Professional Development) (Ref No.: EAA-2021/21)", "description": "Key Responsibilities\n\nThe incumbent will be posted to the Professional Development Section to handle the following:\n\nassist in administering the Continuing Professional Development (CPD) Scheme of the estate agency trade, including arranging logistics of CPD activities, hosting CPD seminars, booking venues, preparing presentation and promotional materials, preparing reports, editing videos, etc\nupdate the CPD section of the Authority's website and the web-based learning platform\nhandle enquiries on the CPD Scheme and related matters\nsupervise supporting staff\nperform such other duties as and when assigned\n\nRequirements\n\nA recognized university degree\nAt least 2 years\u2019 relevant working experience\nProficiency in software applications (MS Word, Excel, Powerpoint, and Chinese word processing)\nFamiliarize with video editing software such as Adobe Premiere Pro\nGood interpersonal and communication skills\nStrong organizational skills and meticulous\nBe able to work independently and self-motivated\nGood command of both written and spoken English and Chinese, and proficiency in Putonghua (Preferably attained Grade \u201cC\u201d or above in English Language (Syllabus B) and Chinese Language in HKCEE, or Level 4 or above in HKDSEE, or equivalent)\n\nTerms of Appointment\n\nCompetitive remuneration package commensurate with the selected candidate\u2019s qualifications and experience will be offered. The appointee will initially be offered a 3-year contract, subject to renewal upon satisfactory performance and the service needs of the Authority.\n\nApplication Procedure\n\nApplications with full resume indicating your current and expected salaries and your public examination results should be sent to: Human Resources Section, Estate Agents Authority, 7/F, E-Trade Plaza, 24 Lee Chung Street, Chaiwan, Hong Kong or via email by clicking \"Apply Now\"\u00a0not later than 31 December 2021. Candidates who have already responded to our previous advertisement of the same post in November 2021 need not re-apply. Please mark \u201cPrivate and Confidential\u201d on the envelope and quote the post applied for and its reference number on the envelope.\n\nCandidates who are not invited to attend an interview within 6 weeks from the closing date may assume their applications unsuccessful. Applications may be considered for other suitable positions within the Authority. All applications will be treated in strict confidence. Personal data provided in the applications will only be used for recruitment-related purposes. All information on non-shortlisted applicants will be destroyed after 6 months.\n\n\nWE ARE AN EQUAL\u00a0OPPORTUNITIES EMPLOYER", "employment_types": ["Full Time", "Contract"], "selling_points": [], "locations": ["Chai Wan"], "categories": ["Admin & HR", "Clerical / Admin Staff", "Public / Civil", "Civil Services", "Training & Development"], "post_time": "2021-12-23T20:10:21Z", "salary": {"currency": null, "max": null, "min": null, "period": "monthly", "term": null}, "salary_visible": false, "title_keywords": ["administrative assistant"], "responsibilities": ["other duties", "website", "handle enquiries", "promotional materials", "logistics", "booking", "preparing reports", "editing"], "requirements": {"degrees": ["university degree"], "majors": [], "languages": ["putonghua", "english", "chinese"], "language_level": ["proficiency", "good command"], "hard_skills": ["excel", "chinese word processing", "powerpoint", "adobe premiere pro", "video editing", "c", "ms word"], "soft_skills": ["communication skills", "work independently", "meticulous", "organizational skills", "self-motivated", "confidence", "interpersonal"], "languages_combined": [{"language": "putonghua", "language_level": ["proficiency", "good command"]}, {"language": "english", "language_level": ["good command"]}, {"language": "chinese", "language_level": ["good command"]}]}, "experience_required": {"duration": ["at least 2 years"], "field": ["relevant working experience"]}}, {"job_id": "100003008997575", "location_code": "hk", "company": "Estate Agents Authority", "job_title": "ADMINISTRATIVE ASSISTANT (Data Analysis) (Ref No.: EAA-2021/20)", "description": "Key Responsibilities\nThe incumbent will be posted to the IT & Data Analysis Section to handle the following:\ncompile monthly statistical reports for various sections\nprovide support for data entry, management, extraction and analyses\nassist in conducting research on subjects as advised by endusers\nsupport the Data Analysis Team in daily operational and administrative matters\u00a0\u00a0\nRequirements\nA recognized university degree, preferably in Statistics / Mathematics or relevant discipline\nAt least 2 years\u2019 relevant working experience; in research support an advantage\nNumerically sensitive, meticulous and be a team player\nProficiency in application of Access, Visio, SQL, Python, VBA and statistical software SPSS / SAS\nGood command of Chinese and English\nTerms of Appointment\nCompetitive remuneration package commensurate with the selected candidate\u2019s qualifications and experience will be offered. The appointee will initially be offered a 3-year contract, subject to renewal upon satisfactory performance and the service needs of the Authority.\nApplication Procedure\nApplications with full resume indicating your current and expected salaries and your public examination results should be sent to: Human Resources Section, Estate Agents Authority, 7/F, E-Trade Plaza, 24 Lee Chung Street, Chaiwan, Hong Kong or via email by clicking \"Apply Now\"\u00a0not later than 31 December 2021. Candidates who have already responded to our previous advertisement of the same post in November 2021 need not re-apply. Please mark \u201cPrivate and Confidential\u201d on the envelope and quote the post applied for and its reference number on the envelope.\nCandidates who are not invited to attend an interview within 6 weeks from the closing date may assume their applications unsuccessful. Applications may be considered for other suitable positions within the Authority. All applications will be treated in strict confidence. Personal data provided in the applications will only be used for recruitment-related purposes. All information on non-shortlisted applicants will be destroyed after 6 months.\n\n\nWE ARE AN EQUAL\u00a0OPPORTUNITIES EMPLOYER\n\n\n", "employment_types": ["Full Time", "Contract"], "selling_points": [], "locations": ["Chai Wan"], "categories": ["Public / Civil", "Civil Services", "Information Technology (IT)", "DBA", "Sciences, Lab, R&D", "Research & Development (R&D)"], "post_time": "2021-12-23T20:10:23Z", "salary": {"currency": null, "max": null, "min": null, "period": "monthly", "term": null}, "salary_visible": false, "title_keywords": ["administrative assistant"], "responsibilities": ["provide support", "management", "data entry", "data analysis", "reports"], "requirements": {"degrees": ["university degree"], "majors": ["mathematics", "statistics"], "languages": ["english", "chinese"], "language_level": ["good command"], "hard_skills": ["sql", "vba", "sas", "python"], "soft_skills": ["meticulous", "team player", "confidence", "sensitive"], "languages_combined": [{"language": "english", "language_level": ["good command"]}, {"language": "chinese", "language_level": ["good command"]}]}, "experience_required": {"duration": ["at least 2 years"], "field": ["relevant working experience"]}}, {"job_id": "100003008993879", "location_code": "hk", "company": "Harbridge Partners Limited", "job_title": "Legal Counsel (VP/ SVP etc. dependent on experience)", "description": "Title: Legal Counsel (VP/ SVP etc. dependent on experience)\n\nLocation: Hong Kong, Central\n\nClient Background:\n\nOur client is one of the leading APAC funds houses with an enviable track record in mainland China, HK and international investments.\nWith an AUM in excess of XXX USD Billions, this is an instantly recognizable brand and name.\n\n\u00a0\nJob Description/ Requirements:\n\nThis is a role within the Legal Department.\n\n1. Bachelor\u2019s degree or above, with major in law and related fields;\n\n2. Those who are qualified to practice law in Hong Kong or China; with ideally 3 years PQE.\n\n3. Familiar with the rules of HK listed companies, the SFC rules on direct investment and the rules and regulations of the China Securities Regulatory Commission (CSRC);\n\n4. Good written and typing skills in simplified/ traditional Chinese and English;\n\n5. Complete other projects or tasks assigned by the senior management of the company.\n\n6. Responsible for revising and improving the company's legal management system and policies.\n\n7. Complete other projects and tasks assigned by senior management as may be required by the company.\n\n\nRequirements, Skills and Experiencee:\n\n1. Must have a bachelor\u2019s degree or above in law.\n2. Have 2 to 3 years PQE or similar qualifications is highly preferred but not essential. Must be able to practice law in HK or Mainland China.\n3. Can read, write, and speak Mandarin and English with strong Chinese typing skills.\n4. IANG, HK Permanent or dependents residence is required as no work visa will be sponsored\n\n\nRemuneration/ Benefits:\n\nThe group is well known for offering exceptional fringe benefits which are commensurate of the top funds houses, financial services firms, and banking institutions, with benefits that includes free lunches, drinks, fruits and snacks, medical insurance, and allowances and discretionary personal and performance related bonuses.\n\nHarbridge Partners Limited\nEmployment Agency Licence:\u00a0 65522", "employment_types": ["Full Time", "Permanent"], "selling_points": ["2 to 3 years PQE Lawyer,qualified in HK or China", "Top fund house for direct investment projects", "PE or buy side funds investment,law firm,contracts"], "locations": ["Central & Western Area"], "categories": ["Banking / Finance", "Others", "Public / Civil", "Civil Services", "Professional Services", "Legal & Compliance"], "post_time": "2021-12-22T09:39:12Z", "salary": {"currency": null, "max": null, "min": null, "period": null, "term": null}, "salary_visible": false, "title_keywords": ["legal counsel"], "responsibilities": [], "requirements": {"degrees": ["degree or above", "bachelor"], "majors": ["law"], "languages": ["english", "chinese", "mandarin"], "language_level": ["good"], "hard_skills": ["no", "typing", "sfc rules"], "soft_skills": ["responsible"], "languages_combined": [{"language": "english", "language_level": ["good"]}, {"language": "chinese", "language_level": ["good"]}, {"language": "mandarin", "language_level": []}]}, "experience_required": {"duration": [], "field": []}}, {"job_id": "100003008999988", "location_code": "hk", "company": "C & H Engineering Company Limited", "job_title": "Assistant Project Manager / Site Agent", "description": "Responsibilities:\n\n\u00a0\u00a0\u00a0\u00a0\u00a0\u00a0\u00a0\u00a0 Supervise and monitor the site progress and subcontractors performance;\n\u00a0\u00a0\u00a0\u00a0\u00a0\u00a0\u00a0\u00a0 Assist Project Manager for day-to-day operation, prepare method statement and shop drawings;\n\u00a0\u00a0\u00a0\u00a0\u00a0\u00a0\u00a0\u00a0 Attend weekly, monthly meets with main contractors;\n\u00a0\u00a0\u00a0\u00a0\u00a0\u00a0\u00a0\u00a0 Handle and resolve site constrain and site problem.\n\n\u00a0Requirements - Qualification:\n\n\u00a0\u00a0\u00a0\u00a0\u00a0\u00a0\u00a0\u00a0 Higher Diploma / Degree holder or above in Civil Engineering disciplines;\n\u00a0\u00a0\u00a0\u00a0\u00a0\u00a0\u00a0\u00a0 Minimum 7 years of civil works site experience;\n\u00a0\u00a0\u00a0\u00a0\u00a0\u00a0\u00a0\u00a0 Holder of Valid green card;\n\u00a0\u00a0\u00a0\u00a0\u00a0\u00a0\u00a0\u00a0 Proficiency in Microsoft Office, Microsoft Project and Chinese word processing;\n\u00a0\u00a0\u00a0\u00a0\u00a0\u00a0\u00a0\u00a0 Good command of both written and spoken English and Chinese.\n\u00a0\u00a0\u00a0\u00a0\u00a0\u00a0\u00a0\u00a0 Candidates with less experiences will be considered as Project Engineer.\n\u00a0 \u00a0 \u00a0 \u00a0 \u00a0Alternative Saturday off per month at once.\u00a0\n\u00a0 \u00a0 \u00a0 \u00a0 \u00a0Location:\u00a0\u00a0Kowloon / New Territories\n\n\n", "employment_types": ["Full Time"], "selling_points": [], "locations": ["Tseung Kwan O"], "categories": ["Public / Civil", "Civil Services", "Engineering", "Engineering Project Management"], "post_time": "2021-12-24T09:29:05Z", "salary": {"currency": "HKD", "max": 69999, "min": 25000, "period": "monthly", "term": null}, "salary_visible": true, "title_keywords": ["assistant project manager", "site agent"], "responsibilities": ["monitor", "day-to-day operation", "drawings"], "requirements": {"degrees": ["diploma", "degree holder"], "majors": ["civil engineering"], "languages": ["english", "chinese"], "language_level": ["proficiency", "good command"], "hard_skills": ["microsoft office", "microsoft project", "chinese word processing", "green card"], "soft_skills": [], "languages_combined": [{"language": "english", "language_level": ["good command"]}, {"language": "chinese", "language_level": ["proficiency", "good command"]}]}, "experience_required": {"duration": ["minimum 7 years"], "field": []}}, {"job_id": "100003008993573", "location_code": "hk", "company": "Jobs Board", "job_title": "Government Assistant Inspector (Civil Engineering / Building Studies) $34k+", "description": "You will be assigned to work in our client's workplace for providing the following services:\n\nResponsibilities:\n(i)\u00a0To manage and supervise Works Supervisor Support;\n(ii) To supervise the contractor's\u00a0pedestrian and road improvement schemes initiated by Energizing Kowloon East Office;\n(iii)To carry out site audit checking and measurement on contractor\u2019s works;\n(iv) To\u00a0keep records and report progress and prepare relevant returns;\n(v) To\u00a0apply for the excavation permit for the site works; and\n(vI) To perform any other duties assigned by Seniors.\n\nRequirements:\n(i)\u00a0obtained a Diploma or Higher Certificate in Civil Engineering or Building Studies or other construction/building-related subjects from a Hong Kong polytechnic university / polytechnic, the Hong Kong Institute of Vocational Education or a technical institute / technical college, or equivalent;\n\n(ii)\n\nhave 5 years' relevant experience; or\nhave 3 years' relevant experience, one of which should be at Works Supervisor I level; or\nhave 3 years' relevant post-qualification experience; and\n(iii) Level 2 or Grade E above in English Language and Chinese Language in HKDSE or HKCEE,or equivalent.", "employment_types": ["Full Time", "Contract"], "selling_points": [], "locations": ["Kowloon Bay"], "categories": ["Public / Civil", "Civil Services", "Building & Construction", "Building / Construction / QS", "Civil / Structural"], "post_time": "2021-12-22T08:25:29Z", "salary": {"currency": null, "max": null, "min": null, "period": "monthly", "term": null}, "salary_visible": false, "title_keywords": ["assistant"], "responsibilities": ["any other duties", "measurement", "checking", "audit", "report"], "requirements": {"degrees": ["diploma", "higher certificate", "hkdse"], "majors": ["building studies", "civil engineering"], "languages": ["english", "chinese"], "language_level": [], "hard_skills": [], "soft_skills": [], "languages_combined": [{"language": "english", "language_level": []}, {"language": "chinese", "language_level": []}]}, "experience_required": {"duration": ["5 years", "3 years"], "field": ["post-qualification", "relevant experience"]}}, {"job_id": "100003008998759", "location_code": "hk", "company": "Pok Oi Hospital", "job_title": "\u670d\u52d9\u4e3b\u4efb(\u793e\u5de5)(\u7de8\u865f\uff1aDESSP/SS)", "description": "\u6301\u793e\u6703\u5de5\u4f5c\u6587\u6191\u6216\u4ee5\u4e0a\u7a0b\u5ea6\uff0c\u9808\u70ba\u8a3b\u518a\u793e\u5de5\n\u51772\u5e74\u6216\u4ee5\u4e0a\u9577\u8005\u670d\u52d9\u53ca\u884c\u653f\u5de5\u4f5c\u7d93\u9a57\n\u6709\u8cac\u4efb\u611f\u3001\u826f\u597d\u4eba\u969b\u95dc\u4fc2\u3001\u7368\u7acb\u3001\u71b1\u8aa0\u53ca\u4e3b\u52d5\n\u4e2d\u3001\u82f1\u6587\u66f8\u5beb\u80fd\u529b\u4f73\uff0c\u64cd\u6d41\u5229\u5ee3\u6771\u8a71\u53ca\u82f1\u8a9e\n\u7ba1\u7406\u9577\u8005\u65e5\u9593\u8b77\u7406\u4e2d\u5fc3\uff0c\u8ca0\u8cac\u6574\u9ad4\u7b56\u5283\u53ca\u71df\u904b\u5de5\u4f5c\n\u6df1\u6c34\u57d7\u5340\n\u622a\u6b62\u65e5\u671f\uff1a2022\u5e741\u67085\u65e5\n\n\u4e0a\u8ff0\u8077\u4f4d\u4ee5\u5408\u7d04\u5236\u8058\u8acb\uff0c\u6709\u610f\u8005\u8acb\u89aa\u7e55\u5c65\u6b77\u53ca\u5217\u660e\u8981\u6c42\u5f85\u9047\u5bc4\u5143\u6717\u51f9\u982d\u535a\u611b\u91ab\u9662\u8cfd\u99ac\u6703\u8b77\u7406\u5b89\u8001\u9662\u5927\u6a13\u8463\u4e8b\u5c40\u4eba\u529b\u8cc7\u6e90\u90e8\u6536\u6216\u50b3\u771f\u81f324789624\u6216\u96fb\u90f5\u81f3\"APPLY NOW\"(\u8acb\u8a3b\u660e\u7533\u8acb\u8077\u4f4d\u53ca\u7de8\u865f)\u3002\n\n\nWhatsApp / WeChat\uff1a6061 0873\n\n\u672c\u9662\u7db2\u7ad9\uff1awww.pokoi.org.hk\n\n\n\n\u5982\u670d\u52d9\u5c0d\u8c61\u5305\u62ec\u5152\u7ae5\uff0c\u672c\u9662\u8981\u6c42\u6e96\u50f1\u54e1\u5165\u8077\u524d\u9032\u884c\u6027\u7f6a\u884c\u5b9a\u7f6a\u7d00\u9304\u67e5\u6838\n\n\u7533\u8acb\u4eba\u6240\u63d0\u4f9b\u7684\u8cc7\u6599\u5c07\u4e88\u4fdd\u5bc6\u53ca\u53ea\u4f5c\u62db\u8058\u6709\u95dc\u8077\u4f4d\u7528\u9014\n\n\u672c\u9662\u662f\u5e73\u7b49\u6a5f\u6703\u50f1\u4e3b\n", "employment_types": ["Full Time", "Contract"], "selling_points": ["\u6301\u793e\u6703\u5de5\u4f5c\u6587\u6191\u6216\u4ee5\u4e0a\u7a0b\u5ea6\uff0c\u9808\u70ba\u8a3b\u518a\u793e\u5de5", "\u51772\u5e74\u6216\u4ee5\u4e0a\u9577\u8005\u670d\u52d9\u53ca\u884c\u653f\u5de5\u4f5c\u7d93\u9a57", "\u7ba1\u7406\u9577\u8005\u65e5\u9593\u8b77\u7406\u4e2d\u5fc3\uff0c\u8ca0\u8cac\u6574\u9ad4\u7b56\u5283\u53ca\u71df\u904b\u5de5\u4f5c"], "locations": ["Sham Shui Po Area"], "categories": ["Public / Civil", "Civil Services", "Social Services - Community / Non-profit Organization", "Others"], "post_time": "2021-12-24T04:13:44Z", "salary": {"currency": null, "max": null, "min": null, "period": "monthly", "term": null}, "salary_visible": false, "title_keywords": [], "responsibilities": [], "requirements": {"degrees": [], "majors": [], "languages": [], "language_level": [], "hard_skills": ["whatsapp"], "soft_skills": [], "languages_combined": []}, "experience_required": {"duration": [], "field": []}}, {"job_id": "100003008989979", "location_code": "hk", "company": "EIDEALINK LIMITED", "job_title": "Building Management Officer", "description": "Job Responsibilities:\n\nTo assist Manager to ensure proper maintenance of building and liaise with other department & contractors in carrying out maintenance and repair works.\nTo assist Manager in supervising and monitoring the performance of security guard services\nSuggest improvements to the building and the facilities.\u00a0\nTo monitor security system included fire alarm, walkie-talkie & CCTV.\nTo ensure proper management of the basement carpark\nTo perform any other duties assigned by senior officers.\n\nJob Requirements:\n\nBachelor Degree Holder\nAt least 3 years of relevant experience in venue management, facility management, museums or international conference and exhibition centers.\nKnowledge in MS Word, Excel, PowerPoint and Chinese character input\nGood command in both written and spoken English & Chinese\nBe able to work independently and possess good interpersonal skills.", "employment_types": ["Full Time"], "selling_points": ["5 days work", "work in Government Department", "Stable work environment"], "locations": ["Tsim Sha Tsui"], "categories": ["Public / Civil", "Civil Services"], "post_time": "2021-12-21T08:00:18Z", "salary": {"currency": "HKD", "max": 34999, "min": 30000, "period": "monthly", "term": null}, "salary_visible": true, "title_keywords": ["building management officer"], "responsibilities": ["any other duties", "management", "supervising", "maintenance", "monitoring", "monitor", "repair", "suggest improvements", "liaise with"], "requirements": {"degrees": ["bachelor degree holder"], "majors": [], "languages": ["english", "chinese"], "language_level": ["good command"], "hard_skills": ["excel", "powerpoint", "ms word"], "soft_skills": ["work independently", "interpersonal skills"], "languages_combined": [{"language": "english", "language_level": ["good command"]}, {"language": "chinese", "language_level": ["good command"]}]}, "experience_required": {"duration": ["at least 3 years"], "field": ["management", "relevant experience"]}}, {"job_id": "100003009002926", "location_code": "hk", "company": "AXA Hong Kong", "job_title": "Assistant Manager, Special Investigation Unit", "description": "To support P&C Claims Team to enhance and grow existing Fraud detection and prevention capabilities\nTo share and embed best practices, refine anti-fraud policies and methodologies and work with AXA Stakeholders, relevant external bodies and competitors to develop a more mature Anti-Fraud strategy\nProvides technical direction to external investigators on complex and SIU investigations\nAdhere to the AXA Group's and any local regulatory fraud monitoring policy and report fraud to appropriate authorities as and when required\nConsistently reviews and re-evaluates rules-based selection based on changing market trends\nDevelop key metrics, governance, process, vendor management and training programs to educate and inform the Claims Team to continue professionalizing their fraud detection and prevention capabilities in-house\nPerform ad hoc projects or any other duties as assigned from time to time\nThorough knowledge of claims management processes and procedures\nMulti-line experience preferred. Experience in handling complex claims and suspected insurance fraud investigations\nStrong investigative background with experience in handling investigations into bodily Injury related claims\nUnderstanding of local Insurance Laws\nStrong computer skills using Word, Excel, Power Point and Outlook. Ability to learn new software operating systems\nAnalytical and interpretive skill\nAbility to manage multiple projects and set priorities \u00b7 Ability to work in a team environment", "employment_types": ["Full Time", "Permanent"], "selling_points": [], "locations": ["Not Specified"], "categories": ["Public / Civil", "Civil Services", "Insurance", "Claims Officer"], "post_time": "2021-12-28T07:37:54Z", "salary": {"currency": null, "max": null, "min": null, "period": "monthly", "term": null}, "salary_visible": false, "title_keywords": ["assistant manager,"], "responsibilities": ["any other duties", "management", "software", "policies", "monitoring", "procedures", "manage multiple projects", "develop", "ad hoc projects", "insurance", "operating systems", "report"], "requirements": {"degrees": [], "majors": [], "languages": [], "language_level": [], "hard_skills": ["anti-fraud", "excel", "inform", "vendor", "word", "computer skills", "outlook", "power point"], "soft_skills": ["thorough", "mature"], "languages_combined": []}, "experience_required": {"duration": [], "field": ["related", "insurance"]}}, {"job_id": "100003009005537", "location_code": "hk", "company": "KONG LEE INDUSTRIES (INT'L) CO., LTD.", "job_title": "\u521d\u7d1a\u73a9\u5177\u8a2d\u8a08\u5e2b", "description": "\n\u8077\u8cac :\u5354\u52a9\u7d93\u7406\u4e00\u5207\u5de5\u7a0b\u4e8b\u52d9,\u8207\u5ee0\u8ddf\u9032\u5de5\u7a0b\u4e8b\u5b9c,\u7e6a\u5716,\u9700\u8981\u6642\u5f80\u5167\u5730(\u6cb3\u6e90)\u5de5\u4f5c\n\n\u8cc7\u6b77 :\u4e2d\u4e94\u7a0b\u5ea6; \u826f\u597d\u7cb5\u8a9e\u512a\u5148; \u4e00\u822c\u666e\u901a\u8a71\u512a\u5148; \u4e00\u822c\u82f1\u8a9e\u512a\u5148; \u61c2\u8b80\u5beb\u4e2d\u6587; \u61c2\u8b80\u5beb\u82f1\u6587; \u61c2MS Excel; \u61c2AutoCAD\n\n\u5f85\u9047 :\u6bcf\u6708$17,000, \u6709\u5e74\u7d42\u96d9\u7ce7, \u9280\u884c\u5047\u671f, \u91ab\u7642\u4fdd\u96aa \u53ca\u5728\u8077\u57f9\u8a13, \u661f\u671f\u4e00\u81f3\u4e94: \u4e0a\u53488\u6642\u534a\u81f3\u4e0b\u53486\u6642\u53ca\u661f\u671f\u516d: \u4e0a\u53488\u6642\u534a\u81f3\u4e0b\u53481\u6642, \u6bcf\u9031\u5de5\u4f5c5\u5929\u534a, \u6bcf\u5929\u5de5\u4f5c 8 \u5c0f\u6642\n\n\u7533\u8acb\u9808\u77e5 :\u6c42\u8077\u8005\u53ef\u96fb\u90f5(Apply Now)\u5c65\u6b77\u8868\u7d66\u6e2f\u5229\u5be6\u696d(\u570b\u969b)\u6709\u9650\u516c\u53f8\u3002\u5982\u8981\u7d22\u53d6\u6536\u96c6\u500b\u4eba\u8cc7\u6599\u8072\u660e, \u8acb\u8207\u9673\u5c0f\u59d0(Email)\u806f\u7d61\u3002\n\n", "employment_types": ["Full Time"], "selling_points": [], "locations": ["Tuen Mun Area"], "categories": ["Public / Civil", "Civil Services", "Social Services - Community / Non-profit Organization", "Others"], "post_time": "2021-12-29T04:00:50Z", "salary": {"currency": null, "max": null, "min": null, "period": "monthly", "term": null}, "salary_visible": false, "title_keywords": [], "responsibilities": [], "requirements": {"degrees": [], "majors": [], "languages": [], "language_level": [], "hard_skills": ["excel"], "soft_skills": [], "languages_combined": []}, "experience_required": {"duration": [], "field": []}}, {"job_id": "100003009005544", "location_code": "hk", "company": "Divine Food Service Limited", "job_title": "\u521d\u7d1a\u86cb\u7cd5\u5e2b\u5085", "description": "\n\u8077\u8cac :\u8ca0\u8cac\u897f\u9905\u88fd\u4f5c\u53ca\u8a2d\u8a08\uff0c\u5354\u52a9\u5eda\u623f\u65e5\u5e38\u4e4b\u904b\u4f5c\u7b49\u7b49\n\n\u8cc7\u6b77 :\u6c92\u6709\u5b78\u6b77\u8981\u6c42; 2\u5e74\u7d93\u9a57; \u826f\u597d\u7cb5\u8a9e; \u7565\u61c2\u8b80\u5beb\u4e2d\u6587\n\n\u5f85\u9047 :\u6bcf\u6708$18,000 - $19,000, \u6709\u5a5a\u50473\u5929, \u6bcf\u6708\u52e4\u5de5\u734e\u91d1$500, \u914c\u60c5\u6027\u82b1\u7d05, \u6649\u5347\u6a5f\u6703 \u53ca\u54e1\u5de5\u8cfc\u7269\u512a\u60e0, \u4e0a\u53487\u6642\u534a\u81f3\u4e0b\u53485\u6642\u534a, \u6bcf\u9031\u5de5\u4f5c6\u5929,\u8f2a\u4f11, \u6bcf\u5929\u5de5\u4f5c 10 \u5c0f\u6642\n\n\u7533\u8acb\u9808\u77e5 :\u6c42\u8077\u8005\u53ef\u81f4\u96fb23898698 / 96029826 \u8207\u9d3b\u81b3\u6709\u9650\u516c\u53f8\u984f\u5148\u751f\u806f\u7d61\u3002\n\n", "employment_types": ["Full Time"], "selling_points": [], "locations": ["Kwun Tong"], "categories": ["Public / Civil", "Civil Services", "Social Services - Community / Non-profit Organization", "Others"], "post_time": "2021-12-29T04:01:43Z", "salary": {"currency": null, "max": null, "min": null, "period": "monthly", "term": null}, "salary_visible": false, "title_keywords": [], "responsibilities": [], "requirements": {"degrees": [], "majors": [], "languages": [], "language_level": [], "hard_skills": [], "soft_skills": [], "languages_combined": []}, "experience_required": {"duration": [], "field": []}}, {"job_id": "100003008993342", "location_code": "hk", "company": "U-Tech Engineering Co Ltd", "job_title": "Foreman (Geotechnical) (18-month Contract)", "description": "The Role:\n\nSupervise the sequence of excavation and installation of temporary works;\nCheck the depth of excavation and the quality of retrieved material at the founding stratum;\nEnsure quality of work, safety and timely completion of projects in a cost-effective manner.\nThe Person:\n\nHigher Diploma / Higher Certificate in civil/ structural/ geotechnical engineering;\nMinimum 10-year relevant experience in construction work project;\nExperienced in project management.\n\nApplication with full details stating current and expected salary to: APPLY NOW\u00a0\nPlease quote the reference number (UT/GS/JDB05/21) in\u00a0your application.\n(All personal data provided will be treated in strict confidence and used for recruitment purposes only.)", "employment_types": ["Full Time", "Contract"], "selling_points": ["Supervise sequence of excavation & installation", "Well-experienced in project management", "10-years experience in construction work project"], "locations": ["Fanling"], "categories": ["Public / Civil", "Civil Services", "Engineering", "Mechanical", "Others"], "post_time": "2021-12-22T07:39:56Z", "salary": {"currency": null, "max": null, "min": null, "period": "monthly", "term": null}, "salary_visible": false, "title_keywords": ["foreman"], "responsibilities": ["installation", "cost", "quality", "project management", "recruitment", "personal data"], "requirements": {"degrees": ["diploma", "higher certificate"], "majors": ["engineering"], "languages": [], "language_level": [], "hard_skills": ["project management"], "soft_skills": ["project management", "timely", "confidence"], "languages_combined": []}, "experience_required": {"duration": ["minimum 10-year"], "field": ["relevant experience", "construction"]}}, {"job_id": "100003008986533", "location_code": "hk", "company": "Nova Management Consultants Ltd", "job_title": "Temporary clerk \u6587\u54e1  ($13224)(Wan Chai/Kwun Tong)(2-3M) (\u9700\u8981\u5916\u51fa\u5de5\u4f5c) (\u653f\u5e9c\u90e8\u9580) (\u53ef\u7e8c\u7d04)", "description": "Duties(Wan Chai/Kwun Tong):\n\n1.Perform outdoor work (visiting local retailer outlet and conduct test purchases when necessary);\n\n2. Conduct background search (e.g. company search, business registration search) to support investigation work;\n\n3. Maintain the record of the monthly market surveillance, prepare the sample for sending to related department and assist in monitoring the testing result;\n\n4. Maintain the record of website monitoring data, prepare and file the follow-up document; and\n\n5. Perform general clerical duties.\n\n.\n\n\u8077\u8cac:\n\n1) \u8f03\u591a\u5916\u51fa\u5de5\u4f5c\u7684\u6642\u9593, \u8ca0\u8cac\u5e6b\u90e8\u9580\u8cfc\u8cb7\u6240\u9700\u7528\u54c1, \u904b\u9001\u7269\u54c1\u5230\u5176\u4ed6\u653f\u5e9c\u90e8\u9580\u7b49\n\u00a0 (\u7063\u4ed4\u8f03\u591a\u5916\u51fa\u5de5\u4f5c,\u89c0\u5858\u8f03\u5c11\u5916\u51fa\u5de5\u4f5c)\n\n2) \u53ca\u4e00\u822c\u8fa6\u516c\u5ba4\u7684\u5de5\u4f5c\n\n.\n\nRequirement(s)(Wan Chai/Kwun Tong):\n\n1.F.5, Have 5 subjects at Grade E/Level 2 or above in Hong Kong Diploma of Secondary Education Examination or in Hon Kong Certificate Of Education Examination, including Chinese Language and English Language (Syllabus B before 2007) are preferably, or equivalent:\n\n2.Possess basic computer knowledge, including MS Word and Excel;\n\n3.Have good typing and communication skills in both English and Chinese; and\n\n4.Permanent resident of the Hong Kong Special Administrative Region\n\n(Fresh graduate are welcome)\n.\n\n\u8981\u6c42:\n\n1) \u9700\u559c\u6b61\u5916\u51fa\u5de5\u4f5c\u7684\u4eba\u58eb\n\n2) \u4e2d\u5b78\u6703\u8003\u6216\u4e2d\u5b78\u6587\u6191\u8a66\u5305\u62ec\u4e2d\u6587\u53ca\u82f1\u6587\u4ee5\u5167 5 \u79d1\u5408\u683c/ F.5(\u512a\u5148)\n\n3) \u80fd\u4e2d\u6587\u6253\u5b57\u53ca\u82f1\u6587\u6253\u5b57\n\n\n\n\u5408\u7d04\u5b8c\u7d50\u65e5\u671f:\u7063\u4ed4:3\u6708\n\u00a0 \u00a0 \u00a0 \u00a0 \u00a0 \u00a0 \u00a0 \u00a0 \u00a0 \u00a0 \u00a0 \u00a0 \u00a0\u89c0\u5858:4\u6708\u4e2d\n\n\u53ef\u7e8c\u7d04\u81f32022\u5e745/6\u6708\n\n\u6b61\u8fce\u7562\u696d\u751f", "employment_types": ["Full Time", "Temporary", "Contract"], "selling_points": ["\u4e2d\u4e94", "\u4e2d\u82f1\u4e94\u79d1\u5408\u683c\u512a\u5148", "\u9700\u8981\u5916\u51fa\u5de5\u4f5c(\u4e94\u5929\u5de5\u4f5c)"], "locations": ["Wan Chai"], "categories": ["Admin & HR", "Clerical / Admin Staff", "Public / Civil", "Civil Services"], "post_time": "2021-12-20T03:25:24Z", "salary": {"currency": null, "max": null, "min": null, "period": "monthly", "term": null}, "salary_visible": false, "title_keywords": ["temporary clerk", "\u6587\u54e1"], "responsibilities": ["outdoor work", "data", "monitoring", "website", "investigation", "testing", "communication", "maintain", "company search"], "requirements": {"degrees": ["certificate", "diploma", "secondary education", "fresh graduate"], "majors": [], "languages": ["english", "chinese"], "language_level": ["good"], "hard_skills": ["excel", "basic", "typing", "ms word"], "soft_skills": ["communication skills"], "languages_combined": [{"language": "english", "language_level": ["good"]}, {"language": "chinese", "language_level": ["good"]}]}, "experience_required": {"duration": [], "field": []}}, {"job_id": "100003009001820", "location_code": "hk", "company": "Kallimount Capital (HK) Limited", "job_title": "\u521d\u7d1a\u6a5f\u68b0\u64cd\u4f5c\u54e1(\u751f\u7522\u90e8)**", "description": "\n\u8077\u8cac :\u5354\u52a9\u64cd\u4f5c\u53ca\u8abf\u6821\u81ea\u52d5\u5316\u53e3\u7f69\u6a5f (\u7121\u9700\u6a5f\u68b0\u77e5\u8b58\u64cd\u4f5c\u80cc\u666f)\n\n\u8cc7\u6b77 :\u6c92\u6709\u5b78\u6b77\u8981\u6c42; \u826f\u597d\u7cb5\u8a9e; \u61c2\u8b80\u5beb\u4e2d\u6587; \u52e4\u596e, \u9858\u610f\u5b78\u7fd2, \u5de5\u4f5c\u4e3b\u52d5\u7a4d\u6975\u512a\u5148\n\n\u5f85\u9047 :\u6bcf\u6708$12,000 - $15,000, \u6709\u5e74\u50478\u5929, \u9280\u884c\u5047\u671f, \u914c\u60c5\u6027\u82b1\u7d05, \u54e1\u5de5\u8cfc\u7269\u512a\u60e0 \u53ca\u8d85\u6642\u5de5\u4f5c\u6d25\u8cbc, \u661f\u671f\u4e00\u81f3\u516d: \u4e0a\u53489\u6642\u81f3\u4e0b\u53486\u6642, \u6bcf\u9031\u5de5\u4f5c6\u5929, \u6bcf\u5929\u5de5\u4f5c 9 \u5c0f\u6642, 1\u5c0f\u6642\u7528\u81b3\u6642\u9593, \u56e0\u61c9\u516c\u53f8\u5de5\u4f5c\u60c5\u6cc1\u53ef\u80fd\u6709\u9700\u8981\u8d85\u6642\u5de5\u4f5c\n\n\u7533\u8acb\u9808\u77e5 :\u6c42\u8077\u8005\u53ef\u81f4\u96fb31690986\u8207\u7ffa\u76df\u8cc7\u672c\uff08\u9999\u6e2f\uff09\u6709\u9650\u516c\u53f8\u9673\u5c0f\u59d0\u806f\u7d61\u3002\n\n", "employment_types": ["Full Time"], "selling_points": [], "locations": ["Kwun Tong"], "categories": ["Public / Civil", "Civil Services", "Social Services - Community / Non-profit Organization", "Others"], "post_time": "2021-12-28T03:06:22Z", "salary": {"currency": null, "max": null, "min": null, "period": "monthly", "term": null}, "salary_visible": false, "title_keywords": [], "responsibilities": [], "requirements": {"degrees": [], "majors": [], "languages": [], "language_level": [], "hard_skills": [], "soft_skills": [], "languages_combined": []}, "experience_required": {"duration": [], "field": []}}, {"job_id": "100003008989785", "location_code": "hk", "company": "Serco Group (HK) Limited", "job_title": "\u5927\u5ec8\u7dad\u4fee\u6280\u8853\u54e1 Technician (BLD)", "description": "\u8077\u8cac\n\n\u00a0\u00a0\u00a0\u00a0\u00a0\u00a0\u00a0 \u8ca0\u8cac\u6aa2\u67e5\u53ca\u7dad\u4fee\u5927\u5ec8\u8a2d\u65bd\u3001\u7cfb\u7d71\u7b49\u5de5\u4f5c\n\n\u5de5\u4f5c\u8981\u6c42\n\n\u00a0\u4e94\u5e74\u6216\u4ee5\u4e0a\u76f8\u95dc\u7dad\u4fee\u4fdd\u990a\u7d93\u9a57;\n\n\u00a0\u00a0\u00a0\u00a0\u00a0\u00a0\u00a0\u00a0\u00a0\u00a0\u00a0\u00a0\u00a0\u00a0 \u00a0\u00a0 \u6216\n\n\u00a0\u00a0\u00a0\u00a0\u00a0\u00a0\u00a0\u00a0\u00a0\u00a0\u00a0\u00a0\u00a0 \u6301\u6709\u96fb\u6a5f / \u68b0\u6a5f/\u5c4b\u5b87\u8a2d\u5099\u7b49\u76f8\u95dc\u6587\u6191 / \u5b78\u6b77\u53ca\n\u00a0 \u00a0 \u00a0 \u00a0 \u00a0 \u00a0 \u00a0 \u7562\u696d\u5f8c1 \u5e74\u6216\u4ee5\u4e0a\u76f8\u95dc\u7dad\u4fee\u4fdd\u990a\u7d93\u9a57;\n\n\u00a0\u00a0\u00a0\u00a0\u00a0\u00a0\u00a0 \u53ef\u5373\u6642\u4e0a\u73ed\u8005\u512a\u5148\u8003\u616e\n\n\u5982\u6709\u4efb\u4f55\u67e5\u8a62\uff0c\u6b61\u8fce\u81f4\u96fb 9857 2126 \u6216\u96fb\u90f5\u4f60\u7684\u5c65\u6b77\u8868\uff0c\u8981\u6c42\u5f85\u9047\u53ca\u6700\u5f8c\u85aa\u916c\u5230 sara.lee @serco-ap.com\u806f\u7d61\u4eba\u4e8b\u90e8\u674e\u5c0f\u59d0\uff0c\u8b1d\u8b1d\u3002\n\n(\u6240\u6709\u63d0\u4ea4\u4e4b\u500b\u4eba\u8cc7\u6599\u6587\u4ef6\u5c07\u53ea\u6703\u7528\u4f5c\u62db\u8058\u7528\u9014\u4f7f\u7528)", "employment_types": ["Full Time"], "selling_points": ["\u4e2d\u9ad8\u9f61\u5c31\u696d\u8a08\u5283", "\u5728\u8077\u57f9\u8a13\u53ca\u6d25\u8cbc", "\u8ca0\u8cac\u6aa2\u67e5\u53ca\u7dad\u4fee\u5927\u5ec8\u8a2d\u65bd"], "locations": ["Sheung Shui"], "categories": ["Public / Civil", "Civil Services", "Property / Real Estate", "Others", "Others", "Technician"], "post_time": "2021-12-21T06:12:24Z", "salary": {"currency": null, "max": null, "min": null, "period": "monthly", "term": null}, "salary_visible": false, "title_keywords": ["technician", "\u5927\u5ec8\u7dad\u4fee\u6280\u8853\u54e1"], "responsibilities": ["ap"], "requirements": {"degrees": [], "majors": [], "languages": [], "language_level": [], "hard_skills": ["ap"], "soft_skills": [], "languages_combined": []}, "experience_required": {"duration": [], "field": []}}, {"job_id": "100003008989212", "location_code": "hk", "company": "Playright Children's Play Association", "job_title": "Play Officer (Playscope)", "description": "Play Officer (Playscope)\u00a0\n\nResponsibilities\u00a0\n\n\n\nTo assist in deliver, support and promote children's play by creating high quality child-centred indoor free play opportunity for all children.\u00a0\u00a0\nTo contribute to the creation, maintenance and improvement of the child- friendly and safe play environments.\nTo assist in the service planning work, including play setting, programmes design and promotion plan\nTo undertake related courses to enhance or increase personal knowledge and understanding of play and playwork practice.\nTo be responsible for the daily operations of the play services\nAssist in ad hoc play projects as assigned\u00a0\u00a0\u00a0\n\n\u00a0Requirements\u00a0\n\n\n\nDegree holder in any discipline.\u00a0\u00a0\nAt least two-year working experiences\nPlaywork Qualification is required(The Association will offer the Playwork training if the candidate do not have such qualification)\nBe able to build good relationships with children and their parents and carers.\nBe a good team player, independent, self-motivated, positive thinking, possess good interpersonal skills and able to handle challenges\nMature, energetic, creative and highly motivated\nHave a passion for working with children through play\nWork on weekends/public holidays are occasionally required\n\n\u00a0--------------------------------------------------------------------------------------------------------------------------\u00a0\n* Prospective employee is requested to undergo Sexual Conviction Record Check on voluntary basis *\u00a0\n\n* Internal Play Training will be arranged*\u00a0\n\n*Play Worker Qualification is required (The Association will offer the Play Worker training if the candidate do not have such qualification)*\n\nAll personal data will be used for recruitment purpose only.\u00a0\u00a0Unsuccessful applications will be destroyed upon completion of the recruitment exercise.\u00a0", "employment_types": ["Full Time", "Contract"], "selling_points": [], "locations": ["Tai Po Area"], "categories": ["Public / Civil", "Civil Services", "Social Services - Community / Non-profit Organization"], "post_time": "2021-12-21T02:59:25Z", "salary": {"currency": null, "max": null, "min": null, "period": "monthly", "term": null}, "salary_visible": false, "title_keywords": ["officer"], "responsibilities": ["ad hoc", "maintenance", "quality", "design", "daily operations", "plan", "planning"], "requirements": {"degrees": ["degree holder"], "majors": [], "languages": [], "language_level": [], "hard_skills": [], "soft_skills": ["good team player", "self-motivated", "independent", "creative", "passion for", "positive thinking", "mature", "motivated", "interpersonal skills", "energetic"], "languages_combined": []}, "experience_required": {"duration": [], "field": []}}, {"job_id": "100003008987952", "location_code": "hk", "company": "The Chinese General Chamber of Commerce", "job_title": "Clerk / Assistant (Members\u2019 Affairs Dept)", "description": "Clerk / Assistant (Members' Affairs Dept)\n\nDuties\n\n-\u00a0\u00a0Assist in members\u2019 recruitment and related tasks\n\n-\u00a0 Serve the Chamber\u2019s Committee\n\n-\u00a0 Provide support to the Chamber\u2019s activities\n\n-\u00a0 Assist in any ad-hoc tasks assigned\n\nQualifications:\n\n-\u00a0\u00a0 Tertiary educated\n\n-\u00a0\u00a0 Minimum 2 years working experience\n\n-\u00a0\u00a0\u00a0 Fluent in Cantonese, English & Putonghua\n\n-\u00a0\u00a0\u00a0 Polite and patient with enquiries\n\n-\u00a0\u00a0\u00a0 Proficiency in computer applications\n\n\n-\u00a0\u00a0 Self-motivated, hard-working, good communication skills and have team spirit", "employment_types": ["Full Time", "Permanent"], "selling_points": [], "locations": ["Central"], "categories": ["Admin & HR", "Clerical / Admin Staff", "Personal / Executive Assistant", "Public / Civil", "Civil Services"], "post_time": "2021-12-20T08:40:29Z", "salary": {"currency": null, "max": null, "min": null, "period": "monthly", "term": null}, "salary_visible": false, "title_keywords": ["clerk", "assistant"], "responsibilities": ["provide support", "ad-hoc tasks", "communication", "recruitment", "computer applications"], "requirements": {"degrees": [], "majors": [], "languages": ["cantonese", "putonghua", "english"], "language_level": ["fluent"], "hard_skills": [], "soft_skills": ["communication skills", "self-motivated", "team spirit", "polite", "hard-working", "patient"], "languages_combined": [{"language": "cantonese", "language_level": ["fluent"]}, {"language": "putonghua", "language_level": ["fluent"]}, {"language": "english", "language_level": ["fluent"]}]}, "experience_required": {"duration": ["minimum 2 years"], "field": []}}, {"job_id": "100003008992942", "location_code": "hk", "company": "Po Leung Kuk", "job_title": "\u798f\u5229\u5de5\u4f5c\u54e1WW3 (\u89c0\u5858)", "description": "\n\u00a0 \u5b89\u8001\u670d\u52d9\n\n\u5165\u8077\u8981\u6c42\n\u4e2d\u4e94\u6216\u4ee5\u4e0a\u7a0b\u5ea6\uff0c\u9999\u6e2f\u4e2d\u5b78\u6703\u8003/\u9999\u6e2f\u4e2d\u5b78\u6587\u61915\u79d1\u5408\u683c(\u5305\u62ec\u4e2d\u3001\u82f1\u6587)\u53ca\u5177\u9ad4\u9069\u80fd\u6559\u7df4\u724c\u512a\u5148\u8003\u616e\u3002\n\u4e3b\u8981\u8077\u8cac\n\u2022 \u8ca0\u8cac\u4e2d\u5fc3\u5ba3\u50b3\u3001\u63a8\u884c\u6d3b\u52d5\u3001\u904b\u52d5\u73ed\u7d44\u3001\u884c\u653f\u53ca\u6703\u8a08\u7b49\u5de5\u4f5c\u3002\n\u89c0\u5858 [via\u00a0 Apply Now ] 2796 1129\n\n\u622a\u6b62\u7533\u8acb\u65e5\u671f : 2022/1/7\n\n", "employment_types": ["Full Time"], "selling_points": [], "locations": ["Kwun Tong"], "categories": ["Professional Services", "Business Analysis / Data Analysis", "Public / Civil", "Civil Services", "Social Services - Community / Non-profit Organization"], "post_time": "2021-12-22T06:37:34Z", "salary": {"currency": null, "max": null, "min": null, "period": "monthly", "term": null}, "salary_visible": false, "title_keywords": [], "responsibilities": [], "requirements": {"degrees": [], "majors": [], "languages": [], "language_level": [], "hard_skills": [], "soft_skills": [], "languages_combined": []}, "experience_required": {"duration": [], "field": []}}, {"job_id": "100003008995841", "location_code": "hk", "company": "Stanford Swim School", "job_title": "\u517c\u8077\u521d\u7d1a\u6e38\u6cf3\u6559\u7df4/ \u6e38\u6cf3\u6559\u7df4**", "description": "\n\u8077\u8cac :\u65bc\u5c0f\u5b78, \u4e2d\u5b78\u6216\u570b\u969b\u5b78\u6821\u6cf3\u6c60\u8ca0\u8cac\u6559\u6388\u6e38\u6cf3\u6cf3\u73ed/ \u5354\u52a9\u6559\u7df4\u6559\u6388\u6e38\u6cf3\u73ed (\u61c2\u6700\u5c11\u5169\u7a2e\u6cf3\u5f0f, \u6301\u6709\u6548\u6559\u7df4\u8b49\u66f8\u6216\u6709\u76f8\u95dc\u7d93\u9a57\u512a\u5148)\n\n\u8cc7\u6b77 :\u4e2d\u4e09\u7a0b\u5ea6; 1\u5e74\u7d93\u9a57; \u826f\u597d\u7cb5\u8a9e; \u4e00\u822c\u666e\u901a\u8a71; \u4e00\u822c\u82f1\u8a9e; \u61c2\u8b80\u5beb\u4e2d\u6587; \u4e0a\u73ed\u5b88\u6642\u3001\u6709\u611b\u5fc3\u53ca\u8cac\u4efb\u611f\n\n\u5f85\u9047 :\u6bcf\u5c0f\u6642$75.00 - $150.00, \u6709\u5728\u8077\u57f9\u8a13, \u4e0a\u53489\u6642\u81f3\u4e0b\u53486\u6642, \u6bcf\u9031\u5de5\u4f5c4\u5929,\u8f2a\u4f11, \u6bcf\u5929\u5de5\u4f5c 6 \u5c0f\u6642\n\n\u7533\u8acb\u9808\u77e5 :\u6c42\u8077\u8005\u53ef\u81f4\u96fb35683676\u8207\u53f2\u4e39\u798f\u6e38\u6cf3\u5b78\u6821\u4eba\u529b\u8cc7\u6e90\u90e8\u806f\u7d61\u3002\n\n", "employment_types": ["Part Time"], "selling_points": [], "locations": ["Not Specified"], "categories": ["Public / Civil", "Civil Services", "Social Services - Community / Non-profit Organization", "Others"], "post_time": "2021-12-23T04:59:46Z", "salary": {"currency": null, "max": null, "min": null, "period": "hourly", "term": null}, "salary_visible": false, "title_keywords": [], "responsibilities": [], "requirements": {"degrees": [], "majors": [], "languages": [], "language_level": [], "hard_skills": [], "soft_skills": [], "languages_combined": []}, "experience_required": {"duration": [], "field": []}}, {"job_id": "100003008996112", "location_code": "hk", "company": "Glory International Limited", "job_title": "\u521d\u7d1a\u91d1\u5c6c\u68da\u67b6\u6280\u5de5", "description": "\n\u8077\u8cac :\u8ca0\u8cac\u4e00\u822c\u91d1\u5c6c\u68da\u67b6\u6280\u5de5\u5de5\u4f5c\n\n\u8cc7\u6b77 :\u6c92\u6709\u5b78\u6b77\u8981\u6c42; \u826f\u597d\u7cb5\u8a9e\u512a\u5148; \u61c2\u95b1\u8b80\u4e2d\u6587\n\n\u5f85\u9047 :\u6bcf\u6708$16,000 - $18,000, \u6709\u751f\u65e5\u5047, \u914c\u60c5\u6027\u82b1\u7d05, \u91ab\u7642\u4fdd\u96aa \u53ca\u63d0\u4f9b\u63a5\u9001\u5b89\u6392, \u661f\u671f\u4e00\u81f3\u516d: \u4e0a\u53488\u6642\u534a\u81f3\u4e0b\u53486\u6642, \u6bcf\u9031\u5de5\u4f5c6\u5929, \u6bcf\u5929\u5de5\u4f5c 9 - 9.5 \u5c0f\u6642\n\n\u7533\u8acb\u9808\u77e5 :\u6c42\u8077\u8005\u53ef\u81f4\u96fb62234016\u8207\u9ad8\u529b\u96c5(\u570b\u969b)\u6709\u9650\u516c\u53f8\u6731\u5148\u751f\u806f\u7d61\u3002\n\n", "employment_types": ["Full Time"], "selling_points": [], "locations": ["Yuen Long"], "categories": ["Public / Civil", "Civil Services", "Social Services - Community / Non-profit Organization", "Others"], "post_time": "2021-12-23T05:32:00Z", "salary": {"currency": null, "max": null, "min": null, "period": "monthly", "term": null}, "salary_visible": false, "title_keywords": ["\u521d\u7d1a\u91d1\u5c6c\u68da\u67b6\u6280\u5de5"], "responsibilities": [], "requirements": {"degrees": [], "majors": [], "languages": [], "language_level": [], "hard_skills": [], "soft_skills": [], "languages_combined": []}, "experience_required": {"duration": [], "field": []}}, {"job_id": "100003008992628", "location_code": "hk", "company": "Trendy Group International Holdings Limited", "job_title": "\u521d\u7d1a\u5370\u7ae0\u751f\u7522\u54e1", "description": "\n\u8077\u8cac :\u8ca0\u8cac\u751f\u7522\u539f\u5b50\u5370\u3001\u66ec\u7248\u3001\u5305\u88dd\n\n\u8cc7\u6b77 :\u4e2d\u4e09\u7a0b\u5ea6; \u826f\u597d\u7cb5\u8a9e; \u61c2\u95b1\u8b80\u4e2d\u6587\n\n\u5f85\u9047 :\u6bcf\u6708$13,500 - $14,500, \u6709\u6bcf\u6708\u52e4\u5de5\u734e\u91d1$500, \u5e74\u504710\u5929, \u9280\u884c\u5047\u671f, \u6bcf\u6708\u81b3\u98df\u6d25\u8cbc$1000 \u53ca\u8d85\u6642\u5de5\u4f5c\u6d25\u8cbc, \u661f\u671f\u4e00\u81f3\u4e94: \u4e0b\u53482\u6642\u81f3\u51cc\u66680\u6642, \u6bcf\u9031\u5de5\u4f5c5\u5929, \u6bcf\u5929\u5de5\u4f5c 10 \u5c0f\u6642\n\n\u7533\u8acb\u9808\u77e5 :\u6c42\u8077\u8005\u53ef\u50b3\u771f(25493235)\u6216\u96fb\u90f5(Apply Now)\u5c65\u6b77\u8868\u7d66\u842c\u5716\u516c\u53f8\u3002\u5982\u8981\u7d22\u53d6\u6536\u96c6\u500b\u4eba\u8cc7\u6599\u8072\u660e, \u8acb\u8207\u5433\u5148\u751f(Tel:25497876)\u806f\u7d61\u3002\n\n", "employment_types": ["Full Time"], "selling_points": [], "locations": ["Aberdeen"], "categories": ["Public / Civil", "Civil Services", "Social Services - Community / Non-profit Organization", "Others"], "post_time": "2021-12-22T05:29:15Z", "salary": {"currency": null, "max": null, "min": null, "period": "monthly", "term": null}, "salary_visible": false, "title_keywords": [], "responsibilities": [], "requirements": {"degrees": [], "majors": [], "languages": [], "language_level": [], "hard_skills": [], "soft_skills": [], "languages_combined": []}, "experience_required": {"duration": [], "field": []}}, {"job_id": "100003008991920", "location_code": "hk", "company": "I. T. H. K. Limited", "job_title": "\u521d\u7d1a\u88fd\u9905\u5e2b", "description": "\n\u8077\u8cac :\u8ca0\u8cac\u7cd5\u9905\u88fd\u4f5c(\u6709\u6069\u6064\u5047\u3001\u4ecb\u7d39\u4eba\u734e\u91d1\u3001\u7bc0\u65e5\u7279\u522b\u596c\u91d1\u3001\u8d85\u6642\u5de5\u4f5c\u6d25\u8cbc\u3001\u54e1\u5de5\u751f\u65e5\u514d\u8cbb\u86cb\u7cd5)\n\n\u8cc7\u6b77 :\u6c92\u6709\u5b78\u6b77\u8981\u6c42; 1\u5e74\u7d93\u9a57; \u826f\u597d\u7cb5\u8a9e\u512a\u5148; \u61c2\u8b80\u5beb\u4e2d\u6587; \u7565\u61c2\u8b80\u5beb\u82f1\u6587; \u61c2\u9020\u897f\u9905/\u9eb5\u5305; \u5de5\u4f5c\u614b\u5ea6\u8a8d\u771f\uff0c\u6709\u4e0a\u9032\u5fc3\uff0c\u826f\u597d\u5718\u9ad4\u5408\u4f5c\u7cbe\u795e\n\n\u5f85\u9047 :\u6bcf\u6708$14,000,\u6709\u54e1\u5de5\u8cfc\u7269\u512a\u60e0,\u5728\u8077\u57f9\u8a13,\u91ab\u7642\u4fdd\u96aa,\u6649\u5347\u6a5f\u6703,\u914c\u60c5\u82b1\u7d05,\u65b0\u4eba\u734e,\u5e74\u504710\u5929,\u751f\u65e5\u5047,\u5a5a\u5047,\u8d85\u6642\u5de5\u4f5c\u6d25\u8cbc, \u4e0a\u53488\u6642\u81f3\u4e0b\u53486\u6642\u6216\u4e2d\u534812\u6642\u81f3\u4e0b\u534810\u6642, \u6bcf\u9031\u5de5\u4f5c5\u5929\u81f36\u5929,\u8f2a\u73ed,\u8f2a\u4f11, \u6bcf\u5929\u5de5\u4f5c 10 \u5c0f\u6642,\u6bcf\u67086\u5929\u4f8b\u5047\n\n\u7533\u8acb\u9808\u77e5 :\u6c42\u8077\u8005\u53ef\u81f4\u96fb37651016\u8207I. T. H. K. LIMITED\u90ed\u5c0f\u59d0\u806f\u7d61\u3002\n\n", "employment_types": ["Full Time"], "selling_points": [], "locations": ["Tsuen Wan Area"], "categories": ["Public / Civil", "Civil Services", "Social Services - Community / Non-profit Organization", "Others"], "post_time": "2021-12-22T04:07:04Z", "salary": {"currency": null, "max": null, "min": null, "period": "monthly", "term": null}, "salary_visible": false, "title_keywords": [], "responsibilities": [], "requirements": {"degrees": [], "majors": [], "languages": [], "language_level": [], "hard_skills": [], "soft_skills": [], "languages_combined": []}, "experience_required": {"duration": [], "field": []}}, {"job_id": "100003008992147", "location_code": "hk", "company": "Big Grains Limited", "job_title": "\u521d\u7d1a\u897f\u9905\u751c\u9ede\u5e2b", "description": "\n\u8077\u8cac :\u88fd\u4f5c\u6cd5\u5f0f\u751c\u54c1, \u8ca0\u8cac\u5eda\u623f\u6e96\u5099\u5de5\u4f5c, \u7814\u767c\u751c\u9ede\u6b3e\u5f0f, \u5354\u52a9\u5206\u90e8\u4e3b\u7ba1\u76e3\u63a7\u5eda\u623f\u51fa\u54c1, \u78ba\u4fdd\u885b\u751f\u53ca\u7522\u54c1\u751f\u7522\u9054\u6a19\u6e96\n\n\u8cc7\u6b77 :\u4e2d\u4e09\u7a0b\u5ea6; 1\u5e74\u7d93\u9a57; \u826f\u597d\u7cb5\u8a9e\u512a\u5148; \u4e00\u822c\u666e\u901a\u8a71; \u4e00\u822c\u82f1\u8a9e; \u61c2\u8b80\u5beb\u4e2d\u6587; \u7565\u61c2\u8b80\u5beb\u82f1\u6587\n\n\u5f85\u9047 :\u6bcf\u6708$13,000 - $14,500, \u6709\u52e4\u5de5\u734e\u91d1, \u5e74\u504710\u5929, \u751f\u65e5\u50471\u5929, \u914c\u60c5\u6027\u82b1\u7d05, \u54e1\u5de5\u8cfc\u7269\u512a\u60e0 \u53ca\u8d85\u6642\u5de5\u4f5c\u6d25\u8cbc, \u4e0a\u53487\u6642\u81f3\u4e0b\u53485\u6642, \u6bcf\u9031\u5de5\u4f5c5\u5929\u81f36\u5929, \u8f2a\u73ed, \u8f2a\u4f11, \u6bcf\u5929\u5de5\u4f5c 9 - 10 \u5c0f\u6642\n\n\u7533\u8acb\u9808\u77e5 :\u6c42\u8077\u8005\u53ef\u81f4\u96fb90103105\u8207\u54c1\u7a40\u6709\u9650\u516c\u53f8\u937e\u5c0f\u59d0\u806f\u7d61\u3002\n\n", "employment_types": ["Full Time"], "selling_points": [], "locations": ["Shatin Area"], "categories": ["Public / Civil", "Civil Services", "Social Services - Community / Non-profit Organization", "Others"], "post_time": "2021-12-22T04:25:42Z", "salary": {"currency": null, "max": null, "min": null, "period": "monthly", "term": null}, "salary_visible": false, "title_keywords": [], "responsibilities": [], "requirements": {"degrees": [], "majors": [], "languages": [], "language_level": [], "hard_skills": [], "soft_skills": [], "languages_combined": []}, "experience_required": {"duration": [], "field": []}}]