[{"job_id": "100003009043693", "location_code": "hk", "company": "Hong Kong Institute of Technology", "job_title": "Assistant Campus Counsellor", "description": "Assistant Campus Counsellor\n\n\n\n\u00a0 \u00a0 \u00a0 \u00a0 Duties:\u00a0\n\n\nTo provide guidance and counselling services to students\n\nTo organize youth development programs\nTo nurture student spiritual health and growth\n\n\n\n\u00a0 \u00a0\u00a0 \u00a0 Requirements:\n\nHigher Diploma in relevant discipline\n\nPreferably with counselling and spiritual counselling training\n\n\n\nApplication\n\nPlease submit application (application form can be downloaded from our website http://www.hkit.edu.hk/en/career.php) to the HR Department, HKIT by email.\n\n(Information provided will be treated in strict confidence and only be used for recruitment purposes.)", "employment_types": ["Full Time"], "selling_points": [], "locations": ["Lai Chi Kok"], "categories": ["Admin & HR", "Administration / Operation Manager", "Public / Civil", "Counseling", "Education", "Others"], "post_time": "2022-01-13T01:31:01Z", "salary": {"currency": null, "max": null, "min": null, "period": "monthly", "term": null}, "salary_visible": false, "title_keywords": ["assistant"], "responsibilities": ["provide guidance", "development programs"], "requirements": {"degrees": ["diploma"], "majors": [], "languages": [], "language_level": [], "hard_skills": ["php"], "soft_skills": ["confidence"], "languages_combined": []}, "experience_required": {"duration": [], "field": []}}, {"job_id": "100003009034927", "location_code": "hk", "company": "Be Priceless Limited", "job_title": "Counselor/ Educator for Be Priceless for summer onwards (English and Chinese/Urdu/Nepali//Bahasa)", "description": "Role: Counselor/ Educator for Be Priceless, an educational non-profit organization that strengthens disadvantaged children\u2019s well-being and safety.\n\nSeeking candidate with a passion to empower and serve disadvantaged communities and has extensive experience in teaching and school counseling or social work, as well as service to vulnerable children. Short term contract for school summer break 2022.\u00a0\n\n\nJob Highlight:\n\nOpportunity to drive the development of an educational program that serves disadvantaged children and youth during 2022 summer break\nDrive the coordination and collaboration with diverse professionals, community members, child and youth in empowering ways\nBe part of an innovative and dynamic team of multisectoral professionals and community members.\nEmpowering, positive, collaborative organizational culture\n\n\u00a0Key Jobs Responsibilities\n\nCoordinate and implement the Be Priceless educational program (which builds capacity for growth, well-being and safety of children), including creation of content, teaching, evaluation and keep improving the SEED courses.\nManage the educational and well-being program development. This includes facilitating collaboration of volunteers, consultant and staff from diverse backgrounds and expertise.\nFoster stakeholder\u2019s engagement and collaboration\u2013 including children, youth, caregivers, multi-disciplinary professionals, schools, non-profit organization.\n\nJob Requirement:\n\nPassionate and dedicated in promoting child and youth well-being and protection.\nAt least 3 years of relevant experience in education and counselling role in reputable organization/School.\nDegree in education, psychology, social work or related field\nExperienced in creating educational program for children of 5-17 years old that promotes social-emotional learning, well-being, safety and inclusion.\u00a0\nExperienced in developing and implementing e-learning educational programs.\nExperienced in team, project and resource management\nAdaptive, flexible and collaborative\nStrong ethical and professional standard - including accountability, transparency.\nStrong collaboration, coordination and problem solving skills.\nStrong communication, productivity, organization and time management skills.\nSocial media management proficiency\nProfessional level\u00a0written and spoken English\u00a0\nAdditional professional level written and spoken 1 of the following languages is required: Chinese, Nepali, Urdu, Hindi, Tagalog, or Bahasa.\nUndergoing regular background checks (including\u00a0Sexual\u00a0Conviction Record\u00a0Check\u00a0(SCRC)\u00a0 and previous employment checks) and abiding to code of conduct including for child safeguarding-protection are an absolute requirements. We have continuous and rigorous monitoring of issues of concerns safety of children and other vulnerable individuals. We will investigate/ report where appropriate.\n\nLogistics:\u00a0Full-time contract base, candidate must be in Hong Kong\nDuration: Summer program and beyond, to be extended to long-term contract if performance is outstanding\nSalary: based on experience\u00a0\n\nPlease apply with\u00a0your full resume, cover letter, time availability. and expected salary.", "employment_types": ["Full Time", "Contract"], "selling_points": ["Educator, School Counselor, Non-profit", "Empower disadvantaged children, well-being, safety", "competitive salary"], "locations": ["Central"], "categories": ["Public / Civil", "Counseling", "Education", "Teacher", "Social Services - Community / Non-profit Organization"], "post_time": "2022-01-13T18:54:45Z", "salary": {"currency": null, "max": null, "min": null, "period": "monthly", "term": null}, "salary_visible": false, "title_keywords": [], "responsibilities": ["coordinate", "evaluation"], "requirements": {"degrees": ["degree"], "majors": ["social work", "psychology"], "languages": ["english", "urdu", "hindi", "tagalog", "nepali", "chinese"], "language_level": [], "hard_skills": ["code", "problem solving skills"], "soft_skills": ["passionate", "flexible", "accountability", "time management skills", "collaborative", "communication", "learning", "ethical", "coordination", "problem solving skills"], "languages_combined": [{"language": "english", "language_level": []}, {"language": "urdu", "language_level": []}, {"language": "hindi", "language_level": []}, {"language": "tagalog", "language_level": []}, {"language": "nepali", "language_level": []}, {"language": "chinese", "language_level": []}]}, "experience_required": {"duration": ["at least 3 years"], "field": ["relevant experience", "education"]}}, {"job_id": "100003009047497", "location_code": "hk", "company": "The University of Hong Kong", "job_title": "Research Assistant I/II (several posts) (Ref.: 511380)", "description": "Work type:\u00a0Full-time\nDepartment:\u00a0Department of Psychiatry (21500)\nCategories:\u00a0Research Support Staff\n\nResearch Assistant I/II (several posts) in the Department of Psychiatry\u00a0(Ref.: 511380) (to commence as soon as possible on a one-year temporary basis or two-year fixed-term basis, with the possibility of renewal subject to satisfactory performance)\n\nThis is an exciting opportunity for the appointee to join the multidisciplinary PSI team based at the Department of Psychiatry, University of Hong Kong. The PSI team, made up of enthusiastic and highly motivated researchers and clinicians, is internationally renowned for its\u00a0contribution towards clinical research in psychiatry and mental disorders. The Team\u2019s research provides significant insight and acts as an important informer for front-line mental health services.\n\nApplicants should possess a Bachelor\u2019s degree in psychology, social sciences,\u00a0or other healthcare-related disciplines. They should have an excellent command of written and spoken English and Chinese, the willingness to learn new skills, a strong commitment to high quality research, good organizational, communication, and interpersonal skills, and the ability to prioritize work and maintain a high level of effectiveness. The team is looking for an individual with high calibre to take part in clinical research projects with diverse interests, such as interventions and outcome measures of early psychotic disorders, or large-scale youth mental health assessments and services.\u00a0\n\nThe appointee will work closely with professional researchers and clinicians\u00a0to deliver and evaluate community assessments. He/She will also provide protocol-based interventions and\u00a0support to people with mental health difficulties.\u00a0 This position would be ideal for someone wanting to gain in research and interventions that target early onset mental disorders, and to be equipped with substantial clinical skills at the same time.\u00a0 Those who have responded to the previous advertisement (Ref.: 508724) need not re-apply.\n\nA highly competitive salary commensurate with qualifications and experience will be offered, in addition to annual leave and medical benefits. The appointment on fixed terms will attract a contract-end gratuity and University contribution to a retirement benefits scheme totalling up to 10% of basic salary.\n\nThe University only accepts online applications for the above posts. Applicants should apply online and upload an up-to-date C.V.\u00a0 Review of applications will start as soon as possible and continue until\u00a0February 28, 2022, or until the posts are filled, whichever is earlier.\n\nAdvertised:Dec 29, 2021 (HK Time)\nApplications close:Feb 28, 2022 (HK Time)", "employment_types": ["Full Time"], "selling_points": [], "locations": ["Not Specified"], "categories": ["Public / Civil", "Counseling", "Education", "Others", "Medical Services", "Others"], "post_time": "2022-01-14T03:20:24Z", "salary": {"currency": null, "max": null, "min": null, "period": "monthly", "term": null}, "salary_visible": false, "title_keywords": ["research assistant"], "responsibilities": ["research projects", "quality", "communication", "evaluate", "research support", "maintain"], "requirements": {"degrees": ["degree", "bachelor"], "majors": ["related disciplines", "psychology", "social sciences"], "languages": ["english", "chinese"], "language_level": ["excellent", "good"], "hard_skills": [], "soft_skills": ["organizational", "prioritize", "communication", "diverse", "motivated", "interpersonal skills", "enthusiastic", "ideal"], "languages_combined": [{"language": "english", "language_level": ["excellent", "good"]}, {"language": "chinese", "language_level": ["excellent", "good"]}]}, "experience_required": {"duration": [], "field": []}}, {"job_id": "100003009038436", "location_code": "hk", "company": "Global Associates", "job_title": "Life Coach", "description": "Bilingual (Cantonese and English) family seeks to recruit a friendly, caring and dynamic Life Coach to provide guidance on social, academic and athletic challenges for a teenager.\n\nThe position can be a full-time or part-time arrangement.\n\nHighlights\n\nProvide full range of at-home support for a teenager\nProvide guidance, tutoring and counseling related to academic, social, sports and extracurricular activities\nProvide advice and support on parenting\n\nRequirements\n\nUniversity / diploma education in Secondary Education, Social Work, Counselling, Speech Therapy or related disciplines\nFluency in English required\nExperience in working with teenager in numerous capacities related to educational, social and extracurricular activities essential\nPrevious experience as teachers, social workers, social work assistant, student counselor, speech therapists, are desirable\nExperience in supporting students with Special Educational Needs (SEN) desirable.\nCurrent professional registration IS NOT a requirement\n\nIf you are interested, please send\u00a0\u00a0dan.luk @globalassociates.com and cv\u00a0@globalassociates.com your full resume along with a cover letter outlining your skills, personal interests and experience as well as how they may contribute to the position.\u00a0 Please also indicate your current and expected salary levels.\n\nOnly shortlisted candidates will be contacted for next-stage interviews", "employment_types": ["Full Time", "Part Time"], "selling_points": ["Life Coach for Teenager (FT/PT)", "Experienced in education, social work, counseling", "Hong Kong Island location; flexible hours"], "locations": ["Causeway Bay"], "categories": ["Public / Civil", "Counseling", "Education", "Tutor / Instructor", "Social Services - Community / Non-profit Organization"], "post_time": "2022-01-11T07:07:46Z", "salary": {"currency": null, "max": null, "min": null, "period": "monthly", "term": null}, "salary_visible": false, "title_keywords": [], "responsibilities": ["provide guidance", "provide advice"], "requirements": {"degrees": ["diploma", "secondary education"], "majors": ["social work", "related disciplines"], "languages": ["cantonese", "english"], "language_level": ["fluency"], "hard_skills": ["dynamic"], "soft_skills": ["dynamic", "friendly"], "languages_combined": [{"language": "cantonese", "language_level": []}, {"language": "english", "language_level": ["fluency"]}]}, "experience_required": {"duration": [], "field": ["related"]}}, {"job_id": "100003009045411", "location_code": "hk", "company": "The University of Hong Kong", "job_title": "Post-doctoral Fellow in Elderly Mental Health( 509090)", "description": "Categories:\u00a0Academic-related Staff\n\nApplications are invited for appointment as\u00a0Post-doctoral Fellow in Elderly Mental Health in the Department of Social Work and Social Administration\u00a0(Ref.: 509090), to commence as soon as possible for one to two years, with the possibility of renewal subject to satisfactory performance and funding availability.\n\nApplicants should possess a Ph.D. degree in Social Work, Psychology, Psychiatry, Mental Health or other related disciplines. They should also have excellent written and spoken skills in English and Chinese (including Cantonese), communication skills and an understanding of local NGO operations. Previous research experience in conducting Randomized Controlled Trial (RCT) and/or intervention studies and a good track record of publications are highly preferred. He/She will assist the implementation of the Jockey Club JoyAge Project. Details of the Project could be found at\u00a0https://jcjoyage.hk/.\n\nA highly competitive salary commensurate with qualifications and experience will be offered, in addition to annual leave and medical benefits.\n\nThe University only accepts online applications for the above post. Applicants should apply online and upload an up-to-date CV, a covering letter stating their research background, and the contact information of three referees. Review of applications will start as soon as possible and continue until\u00a0January 31, 2022, or until the post is filled, whichever is earlier.\n\nAdvertised:Dec 7, 2021 (HK Time)\nApplications close:Jan 31, 2022 (HK Time)\n\n\u6709\u610f\u7533\u8acb\u8005\u8acb \u6309 APPLY NOW\u7533\u8acb\n\n", "employment_types": ["Full Time"], "selling_points": [], "locations": ["Pok Fu Lam"], "categories": ["Public / Civil", "Counseling", "Sciences, Lab, R&D", "Research & Development (R&D)", "Social Services - Community / Non-profit Organization"], "post_time": "2022-01-13T07:48:10Z", "salary": {"currency": null, "max": null, "min": null, "period": "monthly", "term": null}, "salary_visible": false, "title_keywords": [], "responsibilities": ["communication", "operations", "implementation", "administration"], "requirements": {"degrees": ["degree"], "majors": ["social work", "psychology", "related disciplines"], "languages": ["cantonese", "english", "chinese"], "language_level": ["excellent"], "hard_skills": [], "soft_skills": ["controlled", "communication skills"], "languages_combined": [{"language": "cantonese", "language_level": ["excellent"]}, {"language": "english", "language_level": ["excellent"]}, {"language": "chinese", "language_level": ["excellent"]}]}, "experience_required": {"duration": [], "field": ["research"]}}, {"job_id": "100003008218191", "location_code": "hk", "company": "Haven of Hope Christian Service", "job_title": "\u793e\u5de5 (\u7de8\u865f : CSE/SW/JDB)", "description": "\u8077\u8cac\uff1a\n\n\u8ca0\u8cac\u5b78\u751f\u4e8b\u52d9\uff0c\u5305\u62ec\u8077\u6daf\u767c\u5c55\u3001\u5b78\u751f\u7d44\u7e54\u53ca\u8f14\u5c0e\u7b49\uff1b\n\u7c4c\u5283\u53ca\u5e36\u9818\u5167\u5730\u8207\u6d77\u5916\u4e4b\u4ea4\u6d41\u6d3b\u52d5\uff1b\n\u64b0\u5beb\u5c0d\u5916\u7684\u8cc7\u52a9\u5efa\u8b70\u66f8\uff1b\n\u8655\u7406\u65e5\u5e38\u884c\u653f\u5de5\u4f5c\u3002\u00a0\n\n\u8981\u6c42\uff1a\n\n\u4e3b\u4fee\u8f14\u5c0e\u3001\u793e\u6703\u5de5\u4f5c\u6216\u793e\u6703\u79d1\u5b78\u5b78\u58eb\u5b78\u4f4d\uff0c\u8a3b\u518a\u793e\u5de5\u5c07\u7372\u512a\u5148\u8003\u616e\uff1b\n\u6700\u5c11\u4e09\u5e74\u76f8\u95dc\u6216\u9752\u5e74\u5de5\u4f5c\u7d93\u9a57\uff1b\n\u5177\u5927\u5b78\u6216\u5c08\u4e0a\u9662\u6821\u5de5\u4f5c\u7d93\u9a57\u3001\u8abf\u7814\u53ca\u53ca\u7c4c\u7d44\u5b78\u751f\u7d44\u7e54\u8005\u512a\u5148\u8003\u616e\uff1b\n\u826f\u597d\u4e2d\u82f1\u6587\u66f8\u5beb\u6280\u5de7\uff1b\n\u4e3b\u52d5\u3001\u80fd\u7368\u7acb\u8655\u4e8b\u3001\u5177\u826f\u597d\u6e9d\u901a\u53ca\u4eba\u969b\u6280\u5de7\uff1b\n\u7d93\u9a57\u8f03\u591a\u8005\uff0c\u6703\u8003\u616e\u70ba\u9ad8\u7d1a\u5b78\u751f\u767c\u5c55\u4e3b\u4efb\u3002\u00a0\n\n\u6211\u5011\u81f4\u529b\u62db\u8058\u53ca\u633d\u7559\u4eba\u624d\uff0c\u63d0\u4f9b\u5b78\u7fd2\u53ca\u767c\u5c55\u6a5f\u6703\uff0c\u5f37\u7a4d\u91d1\u50f1\u4e3b\u81ea\u9858\u6027\u4f9b\u6b3e\uff0c\u4e26\u5728\u9069\u5207\u7684\u60c5\u6cc1\u4e0b\u4f5c\u51fa\u9748\u6d3b\u7684\u5de5\u4f5c\u5b89\u6392\u3002\u00a0\n\n\u61c9\u5fb5\u8005\u8acb\u96fb\u90f5\u6c42\u8077\u4fe1\u53ca\u5c65\u6b77\uff0c\u4e26\u8acb\u5217\u660e\u73fe\u8077\u3001\u8981\u6c42\u85aa\u916c\u5f85\u9047\u53ca\u5230\u8077\u65e5\u671f\u00a0(\u8cc7\u6599\u4e0d\u9f4a\u5168\u53ef\u81f4\u7533\u8acb\u4e0d\u4e88\u8003\u616e)\u3002\u8acb\u65bc\u96fb\u90f5\u4e3b\u65e8\u8a3b\u660e\u7533\u8acb\u7684\u8077\u4f4d\u53ca\u53c3\u8003\u7de8\u865f\u3002\u00a0\n\n\u00a0\u6c42\u8077\u8005\u63d0\u4f9b\u7684\u500b\u4eba\u8cc7\u6599\uff0c\u53ea\u6703\u4f5c\u6709\u95dc\u62db\u8058\u7528\u9014\n\n\u6211\u5011\u662f\u5e73\u7b49\u6a5f\u6703\u50f1\u4e3b", "employment_types": ["Full Time"], "selling_points": [], "locations": ["Not Specified"], "categories": ["Public / Civil", "Counseling", "Social Services - Community / Non-profit Organization", "Others"], "post_time": "2022-01-17T01:59:47Z", "salary": {"currency": null, "max": null, "min": null, "period": "monthly", "term": null}, "salary_visible": false, "title_keywords": ["\u793e\u5de5"], "responsibilities": [], "requirements": {"degrees": [], "majors": [], "languages": [], "language_level": [], "hard_skills": [], "soft_skills": [], "languages_combined": []}, "experience_required": {"duration": [], "field": []}}, {"job_id": "100003009046268", "location_code": "hk", "company": "Hong Kong Sheng Kung Hui Welfare Council Limited", "job_title": "\u793e\u6703\u5de5\u4f5c\u54e1 Social Worker (Ref: LMIS/SWA/20220114-1)", "description": "\u6301\u6709\u9999\u6e2f\u8a8d\u53ef\u793e\u6703\u5de5\u4f5c\u6587\u6191\u6216\u4ee5\u4e0a\uff0c\u4e26\u5df2\u767b\u8a18\u6210\u70ba\u8a3b\u518a\u793e\u5de5\n\u6027\u683c\u6210\u719f\uff0c\u4e3b\u52d5\uff0c\u80fd\u7368\u7acb\u5de5\u4f5c\uff0c\u6709\u8cac\u4efb\u5fc3\uff0c\u5584\u65bc\u8de8\u5c08\u696d\u5408\u4f5c\n\u70ba\u96e2\u9662\u652f\u63f4\u8a08\u5283\u525b\u51fa\u9662\u7684\u9ad4\u5f31\u9577\u8005\u63d0\u4f9b\u500b\u6848\u7ba1\u7406\u3001\u5bb6\u8a2a\u3001\u60c5\u7dd2\u652f\u63f4\u53ca\u8b77\u8001\u8005\u652f\u63f4\u7b49\u670d\u52d9\uff1b\u5177\u5169\u5e74\u6216\u4ee5\u4e0a\u793e\u6703\u5de5\u4f5c\u7d93\u9a57\n\u5de5\u4f5c\u5730\u9ede\uff1a\u6771\u4e5d\u9f8d\u3001\u5c07\u8ecd\u6fb3\u53ca\u897f\u8ca2\n\n\u6709\u610f\u8005\u8acb\u65bc\u4e8c\u96f6\u4e8c\u4e8c\u5e74\u4e8c\u6708\u4e94\u65e5\u524d\u89aa\u7e55\u5c65\u6b77\u53ca\u671f\u671b\u5f85\u9047\uff08\u8acb\u65bc\u4fe1\u5c01\u9762\u53ca\u4fe1\u5167\u8a3b\u660e\u7533\u8acb\u8077\u4f4d\u7de8\u865f\uff09\u5bc4\u65b0\u754c\u5c07\u8ecd\u6fb3\u9748\u5be6\u8def\u4e03\u865f\u57fa\u7763\u6559\u9748\u5be6\u5354\u6703\u4eba\u529b\u8cc7\u6e90\u90e8\u6536\uff0c\u6216\u96fb\u90f5\u81f3 \"Apply Now\"\uff0c\u6216\u767c\u9001\u81f3Whatsapp\u865f\u78bc6507 8148\uff08\u6a19\u984c\u8acb\u8a3b\u660e\u8077\u4f4d\u7de8\u865f\uff09\u3002\u5982\u4e00\u500b\u6708\u5167\u672a\u7372\u901a\u77e5\u7d04\u898b\uff0c\u5247\u4f5c\u843d\u9078\u8ad6\u3002\n\n\u67e5\u8a62\u71b1\u7dda\uff1a2703 3238 (\u96fb\u8a71)\uff1b6507 8148(Whatsapp)\u3002\n\n\u6709\u95dc\u672c\u6703\u8a73\u60c5\uff0c\u8acb\u700f\u89bd\u7db2\u9801http://www.hohcs.org.hk\n\n(\u53ef\u80fd\u7372\u8058\u4eba\u58eb\uff08\u5982\u5f9e\u4e8b\u8207\u5152\u7ae5\u6216\u7cbe\u795e\u4e0a\u7121\u884c\u70ba\u80fd\u529b\u4eba\u58eb\u6709\u95dc\u5de5\u4f5c\u8077\u4f4d\uff09\u9808\u65bc\u5165\u8077\u524d\u9032\u884c\uff0f\u63d0\u4ea4\u6027\u7f6a\u884c\u5b9a\u7f6a\u7d00\u9304\u67e5\u6838\u3002\u7533\u8acb\u4eba\u6240\u63d0\u4f9b\u7684\u8cc7\u6599\u5c07\u4e88\u4fdd\u5bc6\u53ca\u4f5c\u62db\u8058\u6709\u95dc\u8077\u4f4d\u7528\u9014)\u00a0\n\n\u672a\u7d93\u672c\u5354\u6703\u66f8\u9762\u540c\u610f\uff0c\u4ee5\u4e0a\u62db\u8058\u5ee3\u544a\u5168\u90e8\u6216\u90e8\u5206\u5167\u5bb9\u5747\u4e0d\u5f97\u8907\u88fd\u81f3\u5176\u4ed6\u62db\u8058\u7db2\u7ad9\u3002", "employment_types": ["Full Time", "Contract"], "selling_points": [], "locations": ["To Kwa Wan"], "categories": ["Public / Civil", "Counseling", "Social Services - Community / Non-profit Organization"], "post_time": "2022-01-13T18:55:13Z", "salary": {"currency": null, "max": null, "min": null, "period": "monthly", "term": null}, "salary_visible": false, "title_keywords": ["social worker"], "responsibilities": [], "requirements": {"degrees": [], "majors": [], "languages": [], "language_level": [], "hard_skills": [], "soft_skills": [], "languages_combined": []}, "experience_required": {"duration": [], "field": []}}, {"job_id": "100003009032693", "location_code": "hk", "company": "\u9999\u6e2f\u5c08\u696d\u9032\u4fee\u5b78\u6821", "job_title": "\u5b78\u751f\u767c\u5c55\u4e3b\u4efb / \u9ad8\u7d1a\u5b78\u751f\u767c\u5c55\u4e3b\u4efb", "description": "\u8981\u6c42\n\n\u6301\u8a8d\u53ef\u793e\u6703\u5de5\u4f5c\u6587\u6191\u6216\u4ee5\u4e0a\u5b78\u6b77\uff0c\u5fc5\u9808\u70ba\u8a3b\u518a\u793e\u5de5\n\u61c2\u651d\u5f71\u3001\u651d\u9304\u53ca\u77ed\u7247\u88fd\u4f5c\n\u5177\u5b89\u8001\u670d\u52d9\u3001\u7db2\u7d61\u5de5\u4f5c\u3001\u7b56\u5283\u5c0f\u7d44\u53ca\u6d3b\u52d5\u7d93\u9a57\u8005\u512a\u5148\u3002\n\u8077\u8cac\n\n\u8ca0\u8cac\u70ba\u4e2d\u98a8\u60a3\u8005\u53ca\u5176\u5bb6\u5c6c\u63d0\u4f9b\u652f\u63f4\u670d\u52d9\uff0c\u8209\u8fa6\u8de8\u5340\u5927\u578b\u4e2d\u98a8\u9632\u6cbb\u8b1b\u5ea7\u53ca\u5de5\u4f5c\u574a\u3001\u7d44\u7e54\u9577\u8005\u5065\u5eb7\u5927\u4f7f\u53ca\u8a08\u5283\u5ba3\u50b3\u7b49\u5de5\u4f5c\u3002\n\n\n\u6b64\u8077\u4f4d\u5c6c\u300c\u9805\u76ee\u70ba\u672c\u300d(project based)\u6027\u8cea\u3002\n\n\n\u00a0\n\u5168\u8077\u54e1\u5de5\u53ef\u4eab\u6709\u4ee5\u4e0b\u5b8c\u5584\u798f\u5229\uff1a\n\u6309\u4e0d\u540c\u8077\u7cfb\u53ef\u4eab\u6709\u6709\u85aa\u5e74\u504717\u5929\u3001\u516c\u773e\u5047\u671f17\u5929\u3001\u5a5a\u5047\u3001\u5206\u5a29\u5047\u3001\u6069\u6064\u5047\u3001\u4f8d\u7522\u5047\u3001\u8d85\u6642\u5de5\u4f5c\u88dc\u5047\u3001\u514d\u8cbb\u9ad4\u6aa2\u3001\u91ab\u7642\u4fdd\u96aa\u3001\u4eba\u58fd\u4fdd\u96aa\u3001\u91ab\u7642\u512a\u60e0\u3001\u50f1\u4e3b\u5f37\u7a4d\u91d1\u4f9b\u6b3e\u6309\u5e74\u8cc7\u6700\u9ad8\u53ef\u905e\u589e\u81f315%\u3001\u5728\u8077\u57f9\u8a13\u53ca\u826f\u597d\u6649\u5347\u968e\u68af\u7b49\u3002\n\n\n\u6709\u610f\u8005\u8acb\u5177\u5c65\u6b77\u5bc4(\u4fe1\u5c01\u9762\u53ca\u4fe1\u5167\u8acb\u8a3b\u660e\u8077\u4f4d\u7de8\u865f)\uff1a\u4e5d\u9f8d\u571f\u74dc\u7063\u9ad8\u5c71\u9053111\u865f\u6a02\u6c11\u65b0\u6751H\u5ea7\u5730\u4e0b \u2013 \u9999\u6e2f\u8056\u516c\u6703\u6a02\u6c11\u90ed\u9cf3\u8ed2\u7d9c\u5408\u670d\u52d9\u4e2d\u5fc3 - \u55ae\u4f4d\u4e3b\u4efb\u6536\u6216\u6309\"Apply\u00a0Now\"\u3002\n\u7533\u8acb\u4eba\u4e4b\u7be9\u9078\u5c07\u6703\u5373\u6642\u9032\u884c\u76f4\u81f3\u4e8c\u96f6\u4e8c\u4e8c\u5e74\u4e00\u6708\u4e8c\u5341\u516b\u65e5\u6216\u6709\u95dc\u8077\u4f4d\u7f3a\u5df2\u88ab\u586b\u88dc\u70ba\u6b62\u3002\n\n\u00a0\u4e00\u5207\u7533\u8acb\u8cc7\u6599\u7d55\u5c0d\u4fdd\u5bc6\u53ca\u53ea\u7528\u4f5c\u62db\u8058\u6709\u95dc\u8077\u4f4d\u3002\u5982\u65bc\u5ee3\u544a\u520a\u767b\u5f8c\u516d\u500b\u6708\u5167\u4ecd\u672a\u7372\u672c\u6703\u56de\u8986\uff0c\u5373\u5176\u7533\u8acb\u672a\u7372\u8003\u616e\uff0c\u800c\u7533\u8acb\u4eba\u4e4b\u500b\u4eba\u8cc7\u6599\u4ea6\u5c07\u5728\u5b8c\u6210\u62db\u8058\u7a0b\u5e8f\u5f8c\u92b7\u6bc0\u3002", "employment_types": ["Full Time", "Temporary"], "selling_points": ["Student Development", "Counselling", "5-day work"], "locations": ["Shatin Area"], "categories": ["Public / Civil", "Counseling", "Social Services - Community / Non-profit Organization"], "post_time": "2022-01-07T14:51:54Z", "salary": {"currency": null, "max": null, "min": null, "period": "monthly", "term": null}, "salary_visible": false, "title_keywords": [], "responsibilities": [], "requirements": {"degrees": [], "majors": [], "languages": [], "language_level": [], "hard_skills": [], "soft_skills": [], "languages_combined": []}, "experience_required": {"duration": [], "field": []}}, {"job_id": "100003009043666", "location_code": "hk", "company": "Hong Kong Sheng Kung Hui Welfare Council Limited", "job_title": "\u793e\u6703\u5de5\u4f5c\u54e1 Social Worker (YCDE/SWA/20211126-3)", "description": "\u689d\u4ef6\ufe30\n\n\u6301\u8a8d\u53ef\u793e\u6703\u5de5\u4f5c\u6587\u6191\u6216\u4ee5\u4e0a\u5b78\u6b77\uff0c\u5fc5\u9808\u70ba\u8a3b\u518a\u793e\u5de5\n\u5177\u9577\u8005\u670d\u52d9\u5de5\u4f5c\u7d93\u9a57\u8005\u512a\u5148\n\n\u8077\u8cac\ufe30\n\n\u8ca0\u8cac\u63d0\u4f9b\u8f14\u5c0e\u3001\u793e\u4ea4\u5fc3\u7406\u670d\u52d9\u3001\u8a8d\u77e5\u969c\u7919\u75c7\u652f\u63f4\uff0c\u767c\u5c55\u53ca\u7d71\u7c4c\u8b77\u8001\u8005\u53ca\u7fa9\u5de5\u670d\u52d9\uff0c\u4e26\u5354\u52a9\u4e2d\u5fc3\u65e5\u5e38\u904b\u4f5c\u3002\n\n\n\n\u5168\u8077\u54e1\u5de5\u53ef\u4eab\u6709\u4ee5\u4e0b\u5b8c\u5584\u798f\u5229\uff1a\n\u53ef\u4eab\u6709\u6709\u85aa\u5e74\u504717\u5929\u3001\u516c\u773e\u5047\u671f17\u5929\u3001\u5a5a\u5047\u3001\u5206\u5a29\u5047\u3001\u6069\u6064\u5047\u3001\u4f8d\u7522\u5047\u3001\u8d85\u6642\u5de5\u4f5c\u88dc\u5047\u3001\u514d\u8cbb\u9ad4\u6aa2\u3001\u91ab\u7642\u4fdd\u96aa\u3001\u4eba\u58fd\u4fdd\u96aa\u3001\u91ab\u7642\u512a\u60e0\u3001\u50f1\u4e3b\u5f37\u7a4d\u91d1\u4f9b\u6b3e\u6309\u5e74\u8cc7\u6700\u9ad8\u53ef\u905e\u589e\u81f315%\u3001\u5728\u8077\u57f9\u8a13\u53ca\u826f\u597d\u6649\u5347\u968e\u68af\u7b49\u3002\n\n\n\u6709\u610f\u8005\u8acb\u5177\u5c65\u6b77\u53ca\u5217\u660e\u671f\u671b\u85aa\u916c\u5bc4\ufe30\u706b\u70ad\u99ff\u6d0b\u90a8\u99ff\u723e\u6a13\u5730\u4e0b1\u865f\u5ba4\u00a0\u2013 \u9999\u6e2f\u8056\u516c\u6703\u6069\u99ff\u9577\u8005\u65e5\u9593\u8b77\u7406\u4e2d\u5fc3\u4e2d\u5fc3\u4e3b\u4efb\u6536\u6216\u6309\"Apply Now\"\u3002\u7533\u8acb\u4eba\u4e4b\u7be9\u9078\u5c07\u6703\u5373\u6642\u9032\u884c\u76f4\u81f3\u4e8c\u96f6\u4e8c\u4e8c\u5e74\u4e00\u6708\u4e8c\u5341\u516b\u65e5\u6216\u6709\u95dc\u8077\u4f4d\u7a7a\u7f3a\u5df2\u88ab\u586b\u88dc\u70ba\u6b62\u3002\n\n\n\u4e00\u5207\u7533\u8acb\u8cc7\u6599\u7d55\u5c0d\u4fdd\u5bc6\u53ca\u53ea\u7528\u4f5c\u62db\u8058\u6709\u95dc\u8077\u4f4d\u3002\u5982\u65bc\u5ee3\u544a\u520a\u767b\u5f8c\u516d\u500b\u6708\u5167\u4ecd\u672a\u7372\u672c\u6703\u56de\u8986\uff0c\u5373\u5176\u7533\u8acb\u672a\u7372\u8003\u616e\uff0c\u800c\u7533\u8acb\u4eba\u4e4b\u500b\u4eba\u8cc7\u6599\u4ea6\u5c07\u5728\u5b8c\u6210\u62db\u8058\u7a0b\u5e8f\u5f8c\u92b7\u6bc0\u3002\u5982\u6b32\u53c3\u8003\u5354\u6703\u8cc7\u6599\uff0c\u8acb\u767b\u5165\u7db2\u5740\ufe30http://www.skhwc.org.hk", "employment_types": ["Full Time", "Contract"], "selling_points": [], "locations": ["Shatin Area"], "categories": ["Public / Civil", "Counseling", "Social Services - Community / Non-profit Organization"], "post_time": "2022-01-13T18:54:53Z", "salary": {"currency": null, "max": null, "min": null, "period": "monthly", "term": null}, "salary_visible": false, "title_keywords": ["social worker"], "responsibilities": [], "requirements": {"degrees": [], "majors": [], "languages": [], "language_level": [], "hard_skills": [], "soft_skills": [], "languages_combined": []}, "experience_required": {"duration": [], "field": []}}, {"job_id": "100003009020248", "location_code": "hk", "company": "The Independent Schools Foundation Academy Ltd", "job_title": "Guidance Counselor (Ref:LST/GC/20220104_jdb)", "description": "The appointee will report to the Director of Learning Support and will work within a multi-disciplinary Learning Support Team (LST). The appointee is expected to provide school-based counseling support for students on individual as well as group basis, work closely with parents and teachers, implement student well-being programs, collaborate with different teaching and pastoral teams whenever appropriate to ensure students\u2019 diverse needs are met holistically.\u00a0 \u00a0\n\nThe ideal candidate will satisfy the following requirements:\n\nBachelor\u2019s degree in Psychology/Counseling/Social Work or other relevant discipline; Master\u2019s degree preferred;\nAt least 4 years of relevant counseling experience in working with children and adolescents;\nExperience in implementing social and emotional learning or student well-being programs at school;\nExperience in bilingual school setting preferred;\nProficiency in English and Mandarin (both written and verbal) with strong communication skills; and\nExcellent interpersonal skills, case work and group work skills.\n\nThe ISF Foundation, Academy & Pre-School are committed to ensuring safety and well-being of our students. We hold high standards of recruitment practices with specific attention to child protection. \u00a0All applicants must be willing to undergo relevant background checks and screenings. \u00a0\n\nFree Shuttle Bus travelling to and from The ISF Academy will be provided.\n\nApplication Deadline: 21 January 2022\n\nRemuneration will commensurate with qualifications and experience. We will offer an attractive benefits package including medical, life insurance, and opportunities for professional development and continuing education to the right candidate. Please submit your application by completing the Application Form, Reference Check Statement which could be downloaded from our website: www.isf.edu.hk together with full Curriculum Vitae and Covering Letter. Please quote with our \u201cRef: no.\u201d by email via \"Apply Now\". \u00a0\n\nPersonal data is collected for employment purposes only.", "employment_types": ["Full Time", "Permanent"], "selling_points": ["Medical and life insurances", "Provide school-based counseling support", "Bachelor\u2019s degree in Psychology/Counseling/Social"], "locations": ["Pok Fu Lam"], "categories": ["Public / Civil", "Counseling", "Education", "Others", "Social Services - Community / Non-profit Organization"], "post_time": "2022-01-04T10:18:39Z", "salary": {"currency": null, "max": null, "min": null, "period": "monthly", "term": null}, "salary_visible": false, "title_keywords": [], "responsibilities": ["collaborate with", "teams", "website", "background checks", "communication", "recruitment", "personal data", "insurance", "report"], "requirements": {"degrees": ["degree", "bachelor", "master"], "majors": ["social work", "psychology"], "languages": ["english", "mandarin"], "language_level": ["proficiency"], "hard_skills": ["no"], "soft_skills": ["communication skills", "diverse", "committed", "learning", "interpersonal skills", "ideal"], "languages_combined": [{"language": "english", "language_level": ["proficiency"]}, {"language": "mandarin", "language_level": ["proficiency"]}]}, "experience_required": {"duration": ["at least 4 years"], "field": []}}, {"job_id": "100003009029120", "location_code": "hk", "company": "Hong Kong Sheng Kung Hui Welfare Council Limited", "job_title": "\u793e\u6703\u5de5\u4f5c\u54e1 / \u8f14\u5c0e\u54e1 Social Worker / Counsellor\u3014\u7de8\u865f\uff1aLTLEC/ASWO/20211224-2\u3015", "description": "'Hungry to make a difference? Then foodpanda may be the place for you!'\n\nAt foodpanda, we\u2019re on a mission to redefine customers\u2019 food and shopping experience as a multifaceted online platform across the 14 countries we operate in. We\u2019re all about bringing on the smartest and brightest minds as we continue to grow in a fast-moving and agile environment, and hiring those who can thrive in an energetic and hardworking start-up culture. We strive to become everybody\u2019s most loved delivery platform, however, this won't happen without some really awesome people!\n\nWe are looking for a highly-driven and motivated\u00a0Associate Public Affairs Manager\u00a0to join our fun, professional and dedicated Public Affairs Department based here in Hong Kong. Wait no longer and join us if you want to make a direct and visible impact and contribute to large-scale success!\u00a0\u00a0\n\nWhat will you do?\n\nSupport Senior Public Affairs Manager on projects encompassing External Parties Liaison, Government and Industry Relations, Crisis Management, Internal and External Inquiries, and ad hoc projects\nPrepare meeting documents for external meetings and internal records\nDevelop and maintain good relationships with relevant stakeholders and help advocate, negotiate, and defend the company\u2019s positions\nAssist senior manager in engaging local, international, and foreign key regulators, officials, and representatives\nProvide public affairs recommendations for business developments and operations\u00a0\nMonitor competitors\u2019 activities in relevant areas\nHave the opportunities to lead and initiate your own projects\n\nWhat do you need to be?\n\nHungry to make a difference, Hungry to learn\nMinimum 3 years' experience in public affairs, public policies or stakeholder relations, ideally with a focus on eCommerce\nBachelor's degree in a related field (public affairs, law, political science, public administration, public relations or related areas)\nProficient knowledge of the legislative processes\nExcellent communications skills (both oral and written) in English and Cantonese\u00a0\nAttention to detail and accuracy\nStrong interpersonal skills and a troubleshooting-oriented mindset that enables working with a multicultural group of professionals\nPrevious experience working for or engaging with industry associations, regulatory agencies or relevant public agencies is highly desirable.\nDeep interest and experience in public engagement strategy and implementation\nExperience in stakeholder management and planning and ability to collaborate with senior stakeholders across multiple sites / global locations\n\nWhat We Offer\n\nA dynamic, fast paced environment\nA vibrant and international team with diverse background\nSteep learning curve in e-commerce & entrepreneurship\nLearning & development programs and skills trainings\u00a0\nFlexible working hours and agile company with a flat hierarchical structure\nMonthly staff allowance and corporate discounts including at restaurants, gyms and many more\nAgile office environment with a fully-stocked beverage fridge and self-serve beer\u00a0", "employment_types": ["Full Time", "Contract"], "selling_points": [], "locations": ["To Kwa Wan"], "categories": ["Public / Civil", "Counseling", "Social Services - Community / Non-profit Organization"], "post_time": "2022-01-07T04:00:30Z", "salary": {"currency": null, "max": null, "min": null, "period": "monthly", "term": null}, "salary_visible": false, "title_keywords": ["social worker"], "responsibilities": ["collaborate with", "management", "operations", "policies", "external parties", "monitor", "troubleshooting", "implementation", "develop", "maintain", "ad hoc projects", "planning", "crisis management", "administration"], "requirements": {"degrees": ["degree", "bachelor"], "majors": ["science", "public administration", "law"], "languages": ["cantonese", "english"], "language_level": ["excellent"], "hard_skills": ["no", "agile", "fun", "make", "focus"], "soft_skills": ["oral", "agile", "deep", "troubleshooting", "motivated", "interpersonal skills", "multifaceted", "attention to detail", "focus", "energetic", "driven", "hardworking"], "languages_combined": [{"language": "cantonese", "language_level": ["excellent"]}, {"language": "english", "language_level": ["excellent"]}]}, "experience_required": {"duration": ["minimum 3 years"], "field": ["ecommerce", "food", "management", "planning"]}}, {"job_id": "100003009028915", "location_code": "hk", "company": "Hong Kong Sheng Kung Hui Welfare Council Limited", "job_title": "\u793e\u6703\u5de5\u4f5c\u54e1 Social Worker (Ref: TCIS/ASWO/20211203-2)", "description": "\u689d\u4ef6\ufe30\n\n\u6301\u8a8d\u53ef\u793e\u6703\u5de5\u4f5c\u5b78\u4f4d\u6216\u4ee5\u4e0a\u5b78\u6b77\uff0c\u5fc5\u9808\u70ba\u8a3b\u518a\u793e\u5de5\uff0f\u6301\u8a8d\u53ef\u5fc3\u7406\u5b78\u6216\u6559\u80b2\u5b78\u4f4d\u6216\u540c\u7b49\u5b78\u6b77\n\n\u5177\u4e00\u5e74\u6216\u4ee5\u4e0a\u652f\u63f4\u81ea\u9589\u75c7\u8b5c\u7cfb\u4e2d\u5c0f\u5b78\u751f\u3001\u5bb6\u9577\u53ca\u5b78\u6821\u4e4b\u76f8\u95dc\u5de5\u4f5c\u7d93\u9a57\n\n\u8077\u8cac\ufe30\u00a0\n\n\u8ca0\u8cac\u63d0\u4f9b\u5230\u6821\u6216\u4ee5\u8996\u50cf\u5f62\u5f0f\u652f\u63f4\u81ea\u9589\u75c7\u8b5c\u7cfb\u4e4b\u5c0f\u5b78\u81f3\u4e2d\u5b78\u5b78\u751f\u3001\u5bb6\u9577\u53ca\u6559\u5e2b\u4e4b\u5c0f\u7d44\u8a13\u7df4\u3001\u8aee\u8a62\u53ca\u8b1b\u5ea7\uff0c\u8a2d\u8a08\u8a13\u7df4\u5167\u5bb9\u53ca\u63a8\u884c\u670d\u52d9\uff0c\u4e26\u8ca0\u8cac\u652f\u63f4\u4e2d\u5fc3\u904b\u4f5c\u53ca\u5728\u4e2d\u5fc3\u63d0\u4f9b\u8207\u7279\u6b8a\u5b78\u7fd2\u9700\u8981\u4e4b\u76f8\u95dc\u8a13\u7df4\u3002\n\n\u6b64\u8077\u4f4d\u5c6c\u300c\u9805\u76ee\u70ba\u672c\u300d(project based)\u6027\u8cea\u3002\n\n\u6709\u610f\u8005\u8acb\u5177\u5c65\u6b77\u5bc4\ufe30\u4e5d\u9f8d\u99ac\u982d\u6d8c\u9053139\u865f\u8056\u4e09\u4e00\u767d\u666e\u7406\u4e2d\u5fc33\u6a13\u2013 \u611b\u3002\u5bb6\u5ead\u8cfd\u99ac\u6703\u6210\u9577\u4e2d\u5fc3\u670d\u52d9\u7e3d\u76e3\u6536\u6216\u6309\"Apply Now\"\u3002\u7533\u8acb\u4eba\u4e4b\u7be9\u9078\u5c07\u6703\u5373\u6642\u9032\u884c\u76f4\u81f3\u4e8c\u96f6\u4e8c\u4e8c\u5e74\u4e00\u6708\u4e8c\u5341\u4e00\u65e5\u6216\u6709\u95dc\u8077\u4f4d\u7a7a\u7f3a\u5df2\u88ab\u586b\u88dc\u70ba\u6b62\u3002\u4e00\u5207\u7533\u8acb\u8cc7\u6599\u7d55\u5c0d\u4fdd\u5bc6\u53ca\u53ea\u7528\u4f5c\u62db\u8058\u6709\u95dc\u8077\u4f4d\u3002\n\n\n\u5982\u65bc\u5ee3\u544a\u520a\u767b\u5f8c\u516d\u500b\u6708\u5167\u4ecd\u672a\u7372\u672c\u6703\u56de\u8986\uff0c\u5373\u5176\u7533\u8acb\u672a\u7372\u8003\u616e\uff0c\u800c\u7533\u8acb\u4eba\u4e4b\u500b\u4eba\u8cc7\u6599\u4ea6\u5c07\u5728\u5b8c\u6210\u62db\u8058\u7a0b\u5e8f\u5f8c\u92b7\u6bc0\u3002\u5982\u6b32\u53c3\u8003\u5354\u6703\u8cc7\u6599\uff0c\u8acb\u767b\u5165\u7db2\u5740\ufe30http://www.skhwc.org.hk", "employment_types": ["Full Time", "Contract"], "selling_points": [], "locations": ["Tung Chung"], "categories": ["Public / Civil", "Counseling", "Social Services - Community / Non-profit Organization"], "post_time": "2022-01-07T03:34:10Z", "salary": {"currency": null, "max": null, "min": null, "period": "monthly", "term": null}, "salary_visible": false, "title_keywords": ["social worker"], "responsibilities": [], "requirements": {"degrees": [], "majors": [], "languages": [], "language_level": [], "hard_skills": [], "soft_skills": [], "languages_combined": []}, "experience_required": {"duration": [], "field": []}}, {"job_id": "100003009028870", "location_code": "hk", "company": "Hong Kong Sheng Kung Hui Welfare Council Limited", "job_title": "\u793e\u6703\u5de5\u4f5c\u54e1 Social Worker (Ref: TCIS/ASWO/20211112-2)", "description": "\u689d\u4ef6\uff1a\n\n\u6301\u8a8d\u53ef\u793e\u6703\u5de5\u4f5c\u5b78\u4f4d\u6216\u540c\u7b49\u5b78\u6b77\uff0c\u5fc5\u9808\u70ba\u8a3b\u518a\u793e\u5de5\n\u5c0d\u500b\u6848\u670d\u52d9\u6709\u8208\u8da3\n\u5177\u500b\u6848\u670d\u52d9\u7d93\u9a57\u8005\u512a\u5148\n\u719f\u6089\u4e2d\u82f1\u6587\u96fb\u8166\u6587\u66f8\u8655\u7406\n\u80fd\u64cd\u6d41\u5229\u5ee3\u6771\u8a71\u3001\u666e\u901a\u8a71\u53ca\u82f1\u8a9e\n\n\u8077\u8cac\uff1a\n\n\n\u8ca0\u8cac\u7b56\u5283\u53ca\u5f15\u5165\u8cc7\u8a0a\u79d1\u6280\u4ee5\u63a8\u5c55\u5bb6\u5ead\u670d\u52d9\uff0c\u4e26\u63d0\u4f9b\u5bb6\u5ead\u500b\u6848\u670d\u52d9\u3001\u63a8\u884c\u76f8\u95dc\u6d3b\u52d5\u53ca\u652f\u63f4\u4e2d\u5fc3\u670d\u52d9\u767c\u5c55\n\n\u6b64\u8077\u4f4d\u5c6c\u300c\u9805\u76ee\u70ba\u672c\u300d(project based)\u6027\u8cea\u3002\n\n\n\n\u5168\u8077\u54e1\u5de5\u53ef\u4eab\u6709\u4ee5\u4e0b\u5b8c\u5584\u798f\u5229\uff1a\n\u6709\u85aa\u5e74\u504720\u5929\u3001\u516c\u773e\u5047\u671f 17 \u5929\u3001\u5a5a\u5047\u3001\u5206\u5a29\u5047\u3001\u6069\u6064\u5047\u3001\u4f8d\u7522\u5047\u3001\u8d85\u6642\u5de5\u4f5c\u88dc\u5047\u3001\u514d\u8cbb\u9ad4\u6aa2\u3001\u91ab\u7642\u4fdd\u96aa\u3001\u4eba\u58fd\u4fdd\u96aa\u3001\u91ab\u7642\u512a\u60e0\u3001\u50f1\u4e3b\u5f37\u7a4d\u91d1\u4f9b\u6b3e\u6309\u5e74\u8cc7\u6700\u9ad8\u53ef\u905e\u589e\u81f3 15%\u3001\u5728\u8077\u57f9\u8a13\u53ca\u826f\u597d\u6649\u5347\u968e\u68af\u7b49\u3002\n\n\n\n\u6709\u610f\u8005\u8acb\u5177\u5c65\u6b77\u5bc4(\u4fe1\u5c01\u9762\u53ca\u4fe1\u5167\u8acb\u8a3b\u660e\u8077\u4f4d\u7de8\u865f)\ufe30\u9999\u6e2f\u5927\u5dbc\u5c71\u6771\u6d8c\u5bcc\u6771\u5ee3\u58342\u6a13 \u2013 \u9999\u6e2f\u8056\u516c\u6703\u6771\u6d8c\u7d9c\u5408\u670d\u52d9\u7763\u5c0e\u4e3b\u4efb\u6536\u6216\u6309\"Apply Now\"\u3002\u7533\u8acb\u4eba\u4e4b\u7be9\u9078\u5c07\u6703\u5373\u6642\u9032\u884c\u76f4\u81f3\u4e8c\u96f6\u4e8c\u4e8c\u5e74\u4e00\u6708\u4e8c\u5341\u4e00\u65e5\u6216\u6709\u95dc\u8077\u4f4d\u7a7a\u7f3a\u5df2\u88ab\u586b\u88dc\u70ba\u6b62\u3002\n\n\n\u4e00\u5207\u7533\u8acb\u8cc7\u6599\u7d55\u5c0d\u4fdd\u5bc6\u53ca\u53ea\u7528\u4f5c\u62db\u8058\u6709\u95dc\u8077\u4f4d\u3002\u5982\u65bc\u5ee3\u544a\u520a\u767b\u5f8c\u516d\u500b\u6708\u5167\u4ecd\u672a\u7372\u672c\u6703\u56de\u8986\uff0c\u5373\u5176\u7533\u8acb\u672a\u7372\u8003\u616e\uff0c\u800c\u7533\u8acb\u4eba\u4e4b\u500b\u4eba\u8cc7\u6599\u4ea6\u5c07\u5728\u5b8c\u6210\u62db\u8058\u7a0b\u5e8f\u5f8c\u92b7\u6bc0\u3002\u5982\u6b32\u53c3\u8003\u5354\u6703\u8cc7\u6599\uff0c\u8acb\u767b\u5165\u7db2\u5740\ufe30http://www.skhwc.org.hk", "employment_types": ["Full Time", "Contract"], "selling_points": [], "locations": ["Tung Chung"], "categories": ["Public / Civil", "Counseling", "Social Services - Community / Non-profit Organization"], "post_time": "2022-01-07T03:26:28Z", "salary": {"currency": null, "max": null, "min": null, "period": "monthly", "term": null}, "salary_visible": false, "title_keywords": ["social worker"], "responsibilities": [], "requirements": {"degrees": [], "majors": [], "languages": [], "language_level": [], "hard_skills": [], "soft_skills": [], "languages_combined": []}, "experience_required": {"duration": [], "field": []}}, {"job_id": "100003009024090", "location_code": "hk", "company": "Delivery Hero Food Hong Kong Limited", "job_title": "Associate Public Affairs Manager", "description": "\u689d\u4ef6\uff1a\n\n\u6301\u8a8d\u53ef\u793e\u6703\u5de5\u4f5c\u5b78\u4f4d\u6216\u540c\u7b49\u5b78\u6b77\uff0c\u5fc5\u9808\u70ba\u8a3b\u518a\u793e\u5de5\n\u5c0d\u63d0\u4f9b\u5bb6\u5ead\u751f\u6d3b\u6559\u80b2\u3001\u500b\u6848\u670d\u52d9\u6709\u8208\u8da3\n\u5177\u5bb6\u9577\u6d3b\u52d5\u53ca\u500b\u6848\u670d\u52d9\u7d93\u9a57\u8005\u512a\u5148\n\u5177\u4e8c\u5e74\u6216\u4ee5\u4e0a\u76f8\u95dc\u5de5\u4f5c\u7d93\u9a57\u512a\u5148\n\u719f\u6089\u4e2d\u82f1\u6587\u96fb\u8166\u6587\u66f8\u8655\u7406\n\u80fd\u64cd\u6d41\u5229\u5ee3\u6771\u8a71\u3001\u666e\u901a\u8a71\u53ca\u82f1\u8a9e\n\n\u8077\u8cac\uff1a\n\n\n\u8ca0\u8cac\u70ba\u4e2d\u897f\u5357\u5340\u53ca\u96e2\u5cf6\u5340\u63d0\u4f9b\u6559\u80b2\u6216\u63a8\u5ee3\u6d3b\u52d5\uff0c\u5982\u8b1b\u5ea7\u3001\u5c0f\u7d44\u3001\u5bb6\u5ead\u6d3b\u52d5\u7b49\uff0c\u4ee5\u52a0\u5f37\u5bb6\u5ead\u529f\u80fd\u3001\u978f\u56fa\u5bb6\u5ead\u95dc\u4fc2\uff0c\u4e26\u63d0\u4f9b\u5bb6\u5ead\u500b\u6848\u670d\u52d9\uff0c\u53e6\u8981\u5354\u52a9\u7b56\u5283\u3001\u63a8\u884c\u6d3b\u52d5\u53ca\u652f\u63f4\u4e2d\u5fc3\u670d\u52d9\u63a8\u5c55\u3002\u9808\u8f2a\u73ed\u5de5\u4f5c\u3002\n\n\n\n\u5168\u8077\u54e1\u5de5\u53ef\u4eab\u6709\u4ee5\u4e0b\u5b8c\u5584\u798f\u5229\uff1a\n\u6709\u85aa\u5e74\u504720\u5929\u3001\u516c\u773e\u5047\u671f 17 \u5929\u3001\u5a5a\u5047\u3001\u5206\u5a29\u5047\u3001\u6069\u6064\u5047\u3001\u4f8d\u7522\u5047\u3001\u8d85\u6642\u5de5\u4f5c\u88dc\u5047\u3001\u514d\u8cbb\u9ad4\u6aa2\u3001\u91ab\u7642\u4fdd\u96aa\u3001\u4eba\u58fd\u4fdd\u96aa\u3001\u91ab\u7642\u512a\u60e0\u3001\u50f1\u4e3b\u5f37\u7a4d\u91d1\u4f9b\u6b3e\u6309\u5e74\u8cc7\u6700\u9ad8\u53ef\u905e\u589e\u81f3 15%\u3001\u5728\u8077\u57f9\u8a13\u53ca\u826f\u597d\u6649\u5347\u968e\u68af\u7b49\u3002\n\n\n\n\u6709\u610f\u8005\u8acb\u5177\u5c65\u6b77\u5bc4(\u4fe1\u5c01\u9762\u53ca\u4fe1\u5167\u8acb\u8a3b\u660e\u8077\u4f4d\u7de8\u865f)\ufe30\u9999\u6e2f\u5927\u5dbc\u5c71\u6771\u6d8c\u5bcc\u6771\u5ee3\u58342\u6a13 \u2013 \u9999\u6e2f\u8056\u516c\u6703\u6771\u6d8c\u7d9c\u5408\u670d\u52d9\u7763\u5c0e\u4e3b\u4efb\u6536\u6216\u6309\"Apply Now\"\u3002\u7533\u8acb\u4eba\u4e4b\u7be9\u9078\u5c07\u6703\u5373\u6642\u9032\u884c\u76f4\u81f3\u4e8c\u96f6\u4e8c\u4e8c\u5e74\u4e00\u6708\u4e8c\u5341\u4e00\u65e5\u6216\u6709\u95dc\u8077\u4f4d\u7a7a\u7f3a\u5df2\u88ab\u586b\u88dc\u70ba\u6b62\u3002\n\n\n\u4e00\u5207\u7533\u8acb\u8cc7\u6599\u7d55\u5c0d\u4fdd\u5bc6\u53ca\u53ea\u7528\u4f5c\u62db\u8058\u6709\u95dc\u8077\u4f4d\u3002\u5982\u65bc\u5ee3\u544a\u520a\u767b\u5f8c\u516d\u500b\u6708\u5167\u4ecd\u672a\u7372\u672c\u6703\u56de\u8986\uff0c\u5373\u5176\u7533\u8acb\u672a\u7372\u8003\u616e\uff0c\u800c\u7533\u8acb\u4eba\u4e4b\u500b\u4eba\u8cc7\u6599\u4ea6\u5c07\u5728\u5b8c\u6210\u62db\u8058\u7a0b\u5e8f\u5f8c\u92b7\u6bc0\u3002\u5982\u6b32\u53c3\u8003\u5354\u6703\u8cc7\u6599\uff0c\u8acb\u767b\u5165\u7db2\u5740\ufe30http://www.skhwc.org.hk", "employment_types": ["Full Time", "Permanent"], "selling_points": ["Corporate Public Affairs", "Fast Growing Top Minded eCommerce Company", "Flexible and Dynamic Work Environment"], "locations": ["Sheung Wan"], "categories": ["Public / Civil", "Counseling"], "post_time": "2022-01-05T10:38:12Z", "salary": {"currency": null, "max": null, "min": null, "period": "monthly", "term": null}, "salary_visible": false, "title_keywords": ["associate", "manager"], "responsibilities": [], "requirements": {"degrees": [], "majors": [], "languages": [], "language_level": [], "hard_skills": [], "soft_skills": [], "languages_combined": []}, "experience_required": {"duration": [], "field": []}}, {"job_id": "100003009028935", "location_code": "hk", "company": "Hong Kong Sheng Kung Hui Welfare Council Limited", "job_title": "\u793e\u6703\u5de5\u4f5c\u54e1 Social Worker (Ref: TCIS/ASWO-1/20211210-2)", "description": "KEY AREAS OF ACCOUNTABILITY:\n\n1) Project management\n\nDevelop, plan, and execute parenting and mental health programme activities or events and dissemination works, including producing publication materials, organizing workshops, program enrollment, venue set-up and client management\nCoordinate and liaise with related external parties including programme facilitators, schools, community groups, corporates and other key stakeholders\nCollect activity data, monitor progress against both programmatic and budgetary targets and support conduct of evaluations to ensure programme improvement and quality\nProvide input for development of domestic program strategy and project monitoring and evaluation tools and process\nSupport on a variety of other projects or activities as requested, including but not limited to Save the Children Hong Kong direct service programmes and new initiatives\n2) Administration support\n\nSupport in coordinating maintenance of centre facilities and equipment\nReceive and direct visitors and clients\nPerform general clerical duties including photocopying, fax and mailing, managing filling system & project database\nProvide operational and administrative support to related research and campaigns, including documentary and data entry\nProduce accurate and timely reports\n\n3) Assist in other program activities or organizational projects as needed\n\n\nQUALIFICATIONS\u00a0AND EXPERIENCE\n\nUniversity graduate preferably major in Early Childhood Education, Social Science, Special Education, Counselling or related disciplines\nAt least 3 years\u2019 experience in teaching children\nExperiences in working with parents and psychosocial support projects are preferred\nStrong presentation skills and inter-personal communication skills\nAbility to work independently and with a team\nWilling to engage with different types of individual and community groups\nComputer skills and communications technologies, basic knowledge on graphic design and website operation is a plus (Microsoft Office, Zoom, Adobe, Photoshop and AI etc.)\nKeen interest and commitment to the best interest of children\nHigh degree of self-motivation and strong sense of responsibility\nExcellent proficiency in written and oral English and Cantonese\n\nThis is a full-time position on a 2-year fixed term contract with potential for renewal/extension of appointment which will be subject to organizational needs and job performance.\n\nDon\u2019t miss the opportunity to have career success and fulfilment while you deliver change for children to attain the right to survival, protection, development and participation.\n\nWe need to keep children safe so our selection process, which includes background checks, reflects our commitment to the protection of children from abuse. Candidates at the final stage of recruitment process may be requested to undergo Sexual Conviction Record Check by the Hong Kong Police. If you refuse to undergo the check, we have the right not to consider your application.\n\nInterested parties please send full resume, including your current & expect salary and date of availability by clicking \"Apply Now\".\n\nPersonal data collected will be used for recruitment purpose only.\n\n", "employment_types": ["Full Time", "Contract"], "selling_points": [], "locations": ["Tung Chung"], "categories": ["Public / Civil", "Counseling", "Social Services - Community / Non-profit Organization"], "post_time": "2022-01-07T03:37:30Z", "salary": {"currency": null, "max": null, "min": null, "period": "monthly", "term": null}, "salary_visible": false, "title_keywords": ["social worker"], "responsibilities": ["monitor progress", "data", "external parties", "quality", "communication", "timely reports", "website operation", "plan", "evaluation", "liaise with", "database", "administration", "support projects", "data entry", "develop", "publication", "enrollment", "management", "administrative support", "monitoring", "background checks", "recruitment process", "maintenance", "graphic design", "coordinate", "project management"], "requirements": {"degrees": ["university graduate", "degree"], "majors": ["related disciplines", "science", "early childhood education"], "languages": ["cantonese", "english"], "language_level": ["excellent", "proficiency"], "hard_skills": ["plus", "basic", "maintenance", "microsoft office", "ai", "project management", "safe", "adobe", "computer skills", "workshops", "photoshop"], "soft_skills": ["communication skills", "work independently", "oral", "accountability", "inter-personal", "sense of responsibility", "organizational", "timely", "keen", "project management", "presentation skills", "self-motivation", "accurate"], "languages_combined": [{"language": "cantonese", "language_level": ["excellent", "proficiency"]}, {"language": "english", "language_level": ["excellent", "proficiency"]}]}, "experience_required": {"duration": ["at least 3 years"], "field": ["teaching"]}}, {"job_id": "100003009016877", "location_code": "hk", "company": "Save the Children Hong Kong Limited", "job_title": "Domestic Program Officer - Fixed Term Contract", "description": "\u689d\u4ef6\uff1a\n\n\u6301\u8a8d\u53ef\u793e\u6703\u5de5\u4f5c\u5b78\u4f4d\u6216\u540c\u7b49\u5b78\u6b77\uff0c\u5fc5\u9808\u70ba\u8a3b\u518a\u793e\u5de5\n\u5177\u99d0\u6821\u6216\u9752\u5c11\u5e74\u670d\u52d9\u76f8\u95dc\u7d93\u9a57\u3001\u8655\u7406\u7279\u6b8a\u5b78\u7fd2\u9700\u8981\u5b78\u751f\u76f8\u95dc\u6280\u80fd\u8005\u512a\u5148\n\u719f\u6089\u4e2d\u82f1\u6587\u96fb\u8166\u6587\u66f8\u8655\u7406\n\n\u8077\u8cac\uff1a\n\n\n\u8ca0\u8cac\u4e2d\u5b78\u99d0\u6821\u670d\u52d9\uff0c\u4ee5\u500b\u6848\u3001\u5c0f\u7d44\u53ca\u6d3b\u52d5\u6a21\u5f0f\u4ecb\u5165\uff0c\u652f\u63f4\u5b78\u6821\u5b78\u751f\u53ca\u5bb6\u9577\u5de5\u4f5c\uff0c\u4e26\u652f\u63f4\u4e2d\u5fc3\u9752\u5c11\u5e74\u76f8\u95dc\u670d\u52d9\u3002\n\n\u5168\u8077\u54e1\u5de5\u53ef\u4eab\u6709\u4ee5\u4e0b\u5b8c\u5584\u798f\u5229\uff1a\n\u6709\u85aa\u5e74\u504720\u5929\u3001\u516c\u773e\u5047\u671f 17 \u5929\u3001\u5a5a\u5047\u3001\u5206\u5a29\u5047\u3001\u6069\u6064\u5047\u3001\u4f8d\u7522\u5047\u3001\u8d85\u6642\u5de5\u4f5c\u88dc\u5047\u3001\u514d\u8cbb\u9ad4\u6aa2\u3001\u91ab\u7642\u4fdd\u96aa\u3001\u4eba\u58fd\u4fdd\u96aa\u3001\u91ab\u7642\u512a\u60e0\u3001\u50f1\u4e3b\u5f37\u7a4d\u91d1\u4f9b\u6b3e\u6309\u5e74\u8cc7\u6700\u9ad8\u53ef\u905e\u589e\u81f3 15%\u3001\u5728\u8077\u57f9\u8a13\u53ca\u826f\u597d\u6649\u5347\u968e\u68af\u7b49\u3002\n\n\u6709\u610f\u8005\u8acb\u5177\u5c65\u6b77(\u4fe1\u5c01\u9762\u53ca\u4fe1\u5167\u8acb\u8a3b\u660e\u8077\u4f4d\u7de8\u865f)\u5bc4\ufe30\u9999\u6e2f\u5927\u5dbc\u5c71\u6771\u6d8c\u5bcc\u6771\u5ee3\u58342\u6a13 \u2013 \u9999\u6e2f\u8056\u516c\u6703\u6771\u6d8c\u7d9c\u5408\u670d\u52d9\u7763\u5c0e\u4e3b\u4efb\u6536\u6216\u6309\"Apply Now\"\u3002\u7533\u8acb\u4eba\u4e4b\u7be9\u9078\u5c07\u6703\u5373\u6642\u9032\u884c\u76f4\u81f3\u4e8c\u96f6\u4e8c\u4e8c\u5e74\u4e00\u6708\u4e8c\u5341\u4e00\u65e5\u6216\u6709\u95dc\u8077\u4f4d\u7a7a\u7f3a\u5df2\u88ab\u586b\u88dc\u70ba\u6b62\u3002\uff08\u203b\u5165\u8077\u85aa\u916c\u4e43\u6309\u5b78\u6b77\u53ca\u5de5\u4f5c\u7d93\u9a57\u800c\u8a02\u3002\uff09\n\n\n\u4e00\u5207\u7533\u8acb\u8cc7\u6599\u7d55\u5c0d\u4fdd\u5bc6\u53ca\u53ea\u7528\u4f5c\u62db\u8058\u6709\u95dc\u8077\u4f4d\u3002\u5982\u65bc\u5ee3\u544a\u520a\u767b\u5f8c\u516d\u500b\u6708\u5167\u4ecd\u672a\u7372\u672c\u6703\u56de\u8986\uff0c\u5373\u5176\u7533\u8acb\u672a\u7372\u8003\u616e\uff0c\u800c\u7533\u8acb\u4eba\u4e4b\u500b\u4eba\u8cc7\u6599\u4ea6\u5c07\u5728\u5b8c\u6210\u62db\u8058\u7a0b\u5e8f\u5f8c\u92b7\u6bc0\u3002\u5982\u6b32\u53c3\u8003\u5354\u6703\u8cc7\u6599\uff0c\u8acb\u767b\u5165\u7db2\u5740\ufe30http://www.skhwc.org.hk", "employment_types": ["Full Time", "Contract"], "selling_points": ["Plan, develop and organize domestic programs", "Support coordination of programs centre", "Exp. in working with Children is highly preferred"], "locations": ["Sai Wan"], "categories": ["Public / Civil", "Counseling", "Education", "Teacher", "Social Services - Community / Non-profit Organization"], "post_time": "2022-01-03T10:01:18Z", "salary": {"currency": null, "max": null, "min": null, "period": "monthly", "term": null}, "salary_visible": false, "title_keywords": ["officer"], "responsibilities": [], "requirements": {"degrees": [], "majors": [], "languages": [], "language_level": [], "hard_skills": [], "soft_skills": [], "languages_combined": []}, "experience_required": {"duration": [], "field": []}}, {"job_id": "100003009016639", "location_code": "hk", "company": "The Society for the Aid and Rehabilitation of Drug Abusers", "job_title": "\u793e\u6703\u5de5\u4f5c\u52a9\u7406 (Social Work Assistant)", "description": "\u8077\u4f4d\u7de8\u865f\uff1a(247) in ADM 525/01 VI (DB)\n\n\u4e3b\u8981\u8077\u8cac\n\u53d7\u8058\u4eba\u9700\u65bc\u672c\u6703\u6212\u6bd2\u5eb7\u5fa9\u9662\u6216\u670d\u52d9\u4e2d\u5fc3\u5de5\u4f5c\uff0c\u8ca0\u8cac\u70ba\u6212\u6bd2\u5eb7\u5fa9\u4eba\u58eb\u63d0\u4f9b\u5fc3\u7406\u8f14\u5c0e\u548c\u6709\u95dc\u7684\u5eb7\u5fa9\u670d \u52d9\u3002\n\n\u8cc7\u6b77\n\u7533\u8acb\u4eba\u9808\u70ba\u8a8d\u53ef\u793e\u6703\u5de5\u4f5c\u5b78\u4f4d\u6216\u4ee5\u4e0a\u5b78\u6b77\u7684\u8a3b\u518a\u793e\u5de5\uff0c\u4e26\u65bc\u9999\u6e2f\u4e2d\u5b78\u6703\u8003\u4e2d\u8003\u7372\u4e94\u79d1\u5408\u683c\u4e4b\u6210\u7e3e\u3001 \u65bc\u9999\u6e2f\u4e2d\u5b78\u6587\u6191\u8003\u8a66\u8003\u7372\u4e94\u79d1\u7b2c 2 \u7d1a\u6216\u4ee5\u4e0a\u6210\u7e3e\uff08\u5305\u62ec\u4e2d\u6587\u53ca\u82f1\u6587\u79d1\uff09\u6216\u5177\u540c\u7b49\u5b78\u6b77\u3002\u6709\u8cac\u4efb\u611f\u3001 \u7d30\u5fc3\u3001\u4e3b\u52d5\u53ca\u7368\u7acb\u8655\u4e8b\uff0c\u6709\u793e\u4f01\u53ca\u8a2d\u8a08\u601d\u7dad\u7d93\u9a57 (Design Thinking) \u66f4\u4f73\u3002\n\n\u5f85\u9047\n\u6708\u85aa\u6e2f\u5e63$28,780 \u6216\u4ee5\u4e0a\uff0c\u5e74\u5047 14 \u5929\u3002\n\n\u7533\u8acb\u624b\u7e8c\n1. \u586b\u5beb\u7db2\u4e0a\u8868\u683c\u7533\u8acb\u3002\n2. \u5230\u672c\u6703\u7db2\u9801 www.sarda.org.hk \u4e0b\u8f09\u8077\u4f4d\u7533\u8acb\u8868\u683c\uff0c\u586b\u59a5\u5f8c\u5bc4\u7063\u4ed4\u8ed2\u5c3c\u8a69\u9053 15 \u865f\u6eab\u838e\u516c\u7235\u793e\u6703 \u670d\u52d9\u5927\u5ec8 3 \u6a13\u884c\u653f\u7e3d\u4e3b\u4efb\u6536\u3002 (\u4e4b\u524d\u5df2\u7533\u8acb\u6b64\u8077\u4f4d\u7684\u4eba\u58eb\u7121\u9808\u518d\u7533\u8acb\u3002\u672c\u6703\u4fdd\u7559\u4e0d\u586b\u88dc\u4e0a\u8ff0\u8077\u4f4d\u7684\u6b0a\u5229\u3002)\n\n\u622a\u6b62\u65e5\u671f\uff1a2022 \u5e74 1 \u6708 16 \u65e5", "employment_types": ["Full Time"], "selling_points": [], "locations": ["Wan Chai"], "categories": ["Public / Civil", "Counseling", "Social Services - Community / Non-profit Organization"], "post_time": "2022-01-03T09:32:46Z", "salary": {"currency": null, "max": null, "min": null, "period": "monthly", "term": null}, "salary_visible": false, "title_keywords": ["assistant"], "responsibilities": ["design"], "requirements": {"degrees": [], "majors": [], "languages": [], "language_level": [], "hard_skills": [], "soft_skills": [], "languages_combined": []}, "experience_required": {"duration": [], "field": []}}, {"job_id": "100003009016730", "location_code": "hk", "company": "The Society for the Aid and Rehabilitation of Drug Abusers", "job_title": "\u52a9\u7406\u793e\u6703\u5de5\u4f5c\u4e3b\u4efb (ASWO)", "description": "\u8077\u4f4d\u7de8\u865f\uff1a(246) in ADM 525/01 VI (DB)\n\n\u4e3b\u8981\u8077\u8cac\n\u53d7\u8058\u4eba\u9700\u65bc\u672c\u6703\u7684\u793e\u6703\u670d\u52d9\u4e2d\u5fc3\u4ee5\u53ca\u672c\u6703\u8f44\u4e0b\u7684\u6212\u6bd2\u9662\u6240\uff08\u4e3b\u8981\u70ba\u77f3\u9f13\u6d32\u5eb7\u5fa9\u9662\uff09\u53ca\u5176\u4ed6\u5916\u5c55 \u5730\u9ede\u5de5\u4f5c\uff0c\u8ca0\u8cac\u7d71\u7c4c\u8a08\u5283\u6d3b\u52d5\u5305\u62ec\u63d0\u4f9b\u500b\u6848\u3001\u5c0f\u7d44\u3001\u5916\u5c55\u53ca\u652f\u63f4\u6027\u670d\u52d9\u4e88\u672c\u5730\u4eba\u58eb\uff0c\u8207\u793e\u5340\u4eba\u58eb\u5efa \u7acb\u5408\u4f5c\u95dc\u4fc2\u4ee5\u53ca\u64b0\u5beb\u7533\u8acb\u57fa\u91d1\u7684\u5efa\u8b70\u66f8\u7b49\u3002\u53d7\u8058\u4eba\u9700\u65bc\u665a\u9593\u6216\u9031\u672b\u8f2a\u73ed\u7576\u503c\u3002\n\n\u8cc7\u6b77\n\u7533\u8acb\u4eba\u9808\u70ba\u8a8d\u53ef\u793e\u6703\u5de5\u4f5c\u6587\u6191\u6216\u4ee5\u4e0a\u5b78\u6b77\u7684\u8a3b\u518a\u793e\u5de5\u3002\u719f\u6089\u52d5\u6a5f\u5f0f\u8a2a\u8ac7\u6cd5\uff08Motivational Interviewing\uff09 \u5c07\u7372\u512a\u5148\u8003\u616e\u3002\u6b64\u5916\uff0c\u61c9\u5fb5\u4eba\u4ea6\u9700\u5177\u6709\u826f\u597d\u4eba\u969b\u6e9d\u901a\u6280\u5de7\uff0c\u80fd\u7368\u7acb\u5de5\u4f5c\u53ca\u6709\u826f\u597d\u82f1\u6587\u66f8\u5beb\u80fd\u529b\u3002\u5982 \u80fd\u5373\u6642\u4e0a\u73ed\u8005\u66f4\u4f73\u3002 \u5f85\u9047 \u6708\u85aa\u6e2f\u5e63$20,035 \u6216\u4ee5\u4e0a\uff0c\u5e74\u5047 14 \u5929\u3002\n\n\u7533\u8acb\u624b\u7e8c\n1. \u586b\u5beb\u7db2\u4e0a\u8868\u683c\u7533\u8acb\u3002\n2. \u5230\u672c\u6703\u7db2\u9801 www.sarda.org.hk \u4e0b\u8f09\u8077\u4f4d\u7533\u8acb\u8868\u683c\uff0c\u586b\u59a5\u5f8c\u5bc4\u7063\u4ed4\u8ed2\u5c3c\u8a69\u9053 15 \u865f\u6eab\u838e\u516c\u7235\u793e\u6703 \u670d\u52d9\u5927\u5ec8 3 \u6a13\u884c\u653f\u7e3d\u4e3b\u4efb\u6536\u3002\n\n(\u4e4b\u524d\u5df2\u7533\u8acb\u6b64\u8077\u4f4d\u7684\u4eba\u58eb\u7121\u9808\u518d\u7533\u8acb\u3002\u672c\u6703\u4fdd\u7559\u4e0d\u586b\u88dc\u4e0a\u8ff0\u8077\u4f4d\u7684\u6b0a\u5229\u3002)\n\n\u622a\u6b62\u65e5\u671f\uff1a2022 \u5e74 1 \u6708 16 \u65e5", "employment_types": ["Full Time"], "selling_points": [], "locations": ["Shatin Area"], "categories": ["Public / Civil", "Counseling", "Social Services - Community / Non-profit Organization"], "post_time": "2022-01-03T09:43:40Z", "salary": {"currency": null, "max": null, "min": null, "period": "monthly", "term": null}, "salary_visible": false, "title_keywords": [], "responsibilities": [], "requirements": {"degrees": [], "majors": [], "languages": [], "language_level": [], "hard_skills": [], "soft_skills": [], "languages_combined": []}, "experience_required": {"duration": [], "field": []}}, {"job_id": "100003009012742", "location_code": "hk", "company": "Be Priceless Limited", "job_title": "Educator for Be Priceless (English and Chinese/Urdu/Nepali/Hindi/Tagalog/Bahasa)", "description": "Role: Educator for Be Priceless, an educational non-profit organization that strengthens disadvantaged children\u2019s well-being and safety.\n\nSeeking candidate with a passion to empower and serve disadvantaged communities and has extensive experience in teaching and school counseling or social work, as well as service to vulnerable children.\n\n\nJob Highlight:\n\nOpportunity to drive the development of an educational program that serves disadvantaged children and youth.\nDrive the coordination and collaboration with diverse professionals, community members, child and youth in empowering ways\nBe part of an innovative and dynamic team of multisectoral professionals and community members.\nEmpowering, positive, collaborative organizational culture\n\n\u00a0Key Jobs Responsibilities\n\nCoordinate and implement the Be Priceless educational program (which builds capacity for growth, well-being and safety of children), including creation of content, teaching, evaluation and keep improving the SEED courses.\nManage the educational and well-being program development. This includes facilitating collaboration of volunteers, consultant and staff from diverse backgrounds and expertise.\nFoster stakeholder\u2019s engagement and collaboration\u2013 including children, youth, caregivers, multi-disciplinary professionals, schools, non-profit organization.\n\nJob Requirement:\n\nPassionate and dedicated in promoting child and youth well-being and protection.\nAt least 3 years of relevant experience in education and counselling role in reputable organization.\nDegree in education, psychology, social work or related field\nExperienced in creating educational program for children of 5-17 years old that promotes social-emotional learning, well-being, safety and inclusion.\u00a0\nExperienced in developing and implementing e-learning educational programs.\nExperienced in team, project and resource management\nAdaptive, flexible and collaborative\nStrong ethical and professional standard - including accountability, transparency.\nStrong collaboration, coordination and problem solving skills.\nStrong communication, productivity, organization and time management skills.\nSocial media management proficiency\nProfessional level\u00a0written and spoken English\u00a0\nAdditional professional level written and spoken 1 of the following languages is required: Chinese, Nepali, Urdu, Hindi, Tagalog, or Bahasa.\nUndergoing regular background checks (including\u00a0Sexual\u00a0Conviction Record\u00a0Check\u00a0(SCRC)\u00a0 and previous employment checks) and abiding to code of conduct including for child safeguarding-protection are an absolute requirements. We have continuous and rigorous monitoring of issues of concerns safety of children and other vulnerable individuals. We will investigate/ report where appropriate.\n\nLogistics:\u00a0Full-time, candidate must be in Hong Kong\nDuration: 3 month probation, to be extended to long-term contract if performance is satisfactory.\nSalary: based on experience\u00a0\n\nPlease apply with\u00a0your full resume, cover letter, time availability. and expected salary.", "employment_types": ["Full Time"], "selling_points": ["Educator, Counselor, Non-profit organization", "Empower disadvantaged children, well-being, safety", "competitive salary"], "locations": ["Central"], "categories": ["Public / Civil", "Counseling", "Education", "Teacher", "Social Services - Community / Non-profit Organization"], "post_time": "2022-01-02T02:21:38Z", "salary": {"currency": null, "max": null, "min": null, "period": "monthly", "term": null}, "salary_visible": false, "title_keywords": [], "responsibilities": ["coordinate", "evaluation"], "requirements": {"degrees": ["degree"], "majors": ["social work", "psychology"], "languages": ["english", "urdu", "hindi", "tagalog", "nepali", "chinese"], "language_level": [], "hard_skills": ["code", "problem solving skills"], "soft_skills": ["passionate", "flexible", "accountability", "time management skills", "collaborative", "communication", "learning", "ethical", "coordination", "problem solving skills"], "languages_combined": [{"language": "english", "language_level": []}, {"language": "urdu", "language_level": []}, {"language": "hindi", "language_level": []}, {"language": "tagalog", "language_level": []}, {"language": "nepali", "language_level": []}, {"language": "chinese", "language_level": []}]}, "experience_required": {"duration": ["at least 3 years"], "field": ["relevant experience", "education"]}}, {"job_id": "100003009014159", "location_code": "hk", "company": "The Child Development Centre", "job_title": "SEN Pre-school Teacher / Special Child Care Worker/ ECE Teacher/QKT Teacher/ Register Teacher", "description": "SEN Pre-school Teacher (Ref. SENT) / Special Child Care Worker (Ref. SCCW)/ ECE/QKT Teacher/ Register\u00a0Teacher\n\nResponsibilities:\n\nConsistently provide an excellent standard of teaching for young children with a wide\u00a0variety of abilities.\n\u00a0Assess both formally and informally and devise individual learning plans.\n\u00a0Create interesting and engaging teaching plans.\n\u00a0Work closely with parents within the classroom.\n\u00a0Be part of a multidisciplinary team, lead and contribute to meetings both with staff\u00a0and parents.\nThe ability to write reports in both English and Chinese will be an advantage.\nDemonstrate professional knowledge of early childhood development.\nPlan interesting and engaging lessons for a variety of classes for children aged between birth and six years old.\nSet appropriate developmental goals and devise activities to meet those goals.\nMaintain up to date, organised records and reports regarding children\u2019s learning.\nMaintain up to date, organised lesson plans.\nDevelop positive relationships with parents.\nSupervise classroom assistants and/or volunteers.\nCreate organised and tidy classrooms with interesting visual and sensory materials.\nBe a contributing member of a multi-disciplinary team\n\nRequirements:\n\nA recognised relevant\u00a0degree in SEN teaching or Special Child Care Work\nFurther qualifications in the area of special needs desirable.\nA minimum of two years Special Child Care Worker experience with pre-school or\u00a0school-aged children is desirable.\nExperienced in teaching children with autism, PMLD, CLD and those who need\u00a0behavioural and sensory support.\nFamiliar with AACs, PECS, and Makaton.\nFluent Cantonese and English, written and spoken, Mandarin an advantage.\nExcellent communication skills.\nA strong work ethic with a positive attitude.\nExcellent observation and assessment skills.\nHong Kong permanent resident status is desirable.\nBe able to work under pressure and be flexible.\nMust be able to work Saturdays.\nJob Package/Benefits:\n\nPaid professional development opportunities.\nMedical and dental benefits.\nFive-day working week (may include Saturday and or early evening).\nFriendly working environment.\n\nPlease submit your application letter and full resume with availability, current and expected salary directly by clicking \"Apply Now\"\u00a0Please quote the post you are applying for in the subject line of the email.\u00a0\n\nCandidates not invited for an interview within two months may consider their applications unsuccessful.\u00a0 We are an equal opportunity employer.\u00a0 All information received will be kept in strict confidence and used only for employment-related purposes.", "employment_types": ["Full Time"], "selling_points": [], "locations": ["Wan Chai"], "categories": ["Public / Civil", "Counseling", "Education", "Teacher", "Social Services - Community / Non-profit Organization"], "post_time": "2022-01-03T03:05:52Z", "salary": {"currency": null, "max": null, "min": null, "period": "monthly", "term": null}, "salary_visible": false, "title_keywords": ["teacher"], "responsibilities": ["develop", "maintain", "reports", "plan", "visual", "plans"], "requirements": {"degrees": ["degree"], "majors": [], "languages": ["cantonese", "english", "mandarin"], "language_level": ["advantage", "fluent"], "hard_skills": [], "soft_skills": ["flexible", "communication skills", "positive attitude", "work ethic", "work under pressure"], "languages_combined": [{"language": "cantonese", "language_level": ["fluent"]}, {"language": "english", "language_level": ["fluent"]}, {"language": "mandarin", "language_level": ["advantage"]}]}, "experience_required": {"duration": ["minimum of two years"], "field": []}}, {"job_id": "100003009005340", "location_code": "hk", "company": "The Hong Kong Federation of Trade Unions", "job_title": "\u52de\u5de5\u670d\u52d9\u4e2d\u5fc3 \u5e79\u4e8b Labour Services Centre Officer (Ref: CSD/210701)", "description": "\u8077\u8cac\uff1a\n\n\u89e3\u7b54\u52de\u5de5\u6cd5\u4f8b\u7684\u67e5\u8a62\n\u5354\u52a9\u6c42\u52a9\u7684\u5de5\u53cb\u5230\u52de\u5de5\u8655\u53ca\u52de\u8cc7\u5be9\u88c1\u8655\u7b49\u9032\u884c\u52de\u8cc7\u7cfe\u7d1b\u53ca\u5de5\u50b7\u7684\u7533\u7d22\n\u5ba3\u50b3\u53ca\u63a8\u5ee3\u52de\u5de5\u6b0a\u76ca\n\u9808\u5354\u52a9\u5de5\u6703\u8ddf\u9032\u5927\u578b\u52de\u8cc7\u7cfe\u7d1b\u4e8b\u4ef6\n\u652f\u63f4\u90e8\u9580\u7684\u65e5\u5e38\u4e8b\u52d9\uff0c\u4ee5\u53ca\u5354\u52a9\u59d4\u54e1\u6703\u63a8\u884c\u6d3b\u52d5\u548c\u653f\u7b56\u5021\u8b70\n\n\u8981\u6c42\uff1a\n\n\u5927\u5b78\u7562\u696d\u6216\u4ee5\u4e0a\u7a0b\u5ea6\uff0c\u4e3b\u4fee\u793e\u6703\u79d1\u5b78\u3001\u8f14\u5c0e\u3001\u5fc3\u7406\u5b78\u70ba\u4f73\n\u5177\u4e00\u5e74\u6216\u4ee5\u4e0a\u76f8\u95dc\u5de5\u4f5c\u7d93\u9a57\uff0c\u6709\u500b\u6848\u8f14\u5c0e\u670d\u52d9\u7d93\u9a57\u512a\u5148\n\u719f\u6089\u96fb\u8166\u6587\u66f8\u64cd\u4f5c\uff0c\u61c2\u55ae\u5f35\u6d77\u5831\u88fd\u4f5c\u53ca\u62cd\u7247\u526a\u7247\u66f4\u4f73\n\u5177\u826f\u597d\u7684\u4e2d\u82f1\u6587\u66f8\u5beb\u548c\u8868\u9054\u80fd\u529b\uff08\u5305\u62ec\u666e\u901a\u8a71\uff09\n\u6210\u719f\u4e3b\u52d5\uff0c\u5584\u65bc\u8207\u4eba\u6e9d\u901a\u548c\u5354\u8abf\uff0c\u7d30\u5fc3\u76e1\u8cac\uff0c\u5177\u65b0\u805e\u89f8\u89ba\u53ca\u826f\u597d\u670d\u52d9\u614b\u5ea6\n\n\u6709\u610f\u8005\u8acb\u628a\u500b\u4eba\u5c65\u6b77\u3001\u5b78\u6b77\u526f\u672c\u53ca\u8981\u6c42\u5f85\u9047\u5bc4\u300c\u4e5d\u9f8d\u571f\u74dc\u7063\u99ac\u5751\u6d8c\u905312\u865f3\u6a13\u300d\u5de5\u806f\u6703\u79d8\u66f8\u8655\u4eba\u529b\u8cc7\u6e90\u90e8\u6536\uff0c\u6216\u96fb\u90f5\u81f3 \"Apply Now\"\u3002\u8acb\u65bc\u4fe1\u5c01\u9762\u6216\u96fb\u90f5\u4e3b\u65e8\u8a3b\u660e\u61c9\u5fb5\u7684\u8077\u4f4d\u548c\u7de8\u865f\u3002\n\n(\u7533\u8acb\u4eba\u6240\u63d0\u4f9b\u7684\u8cc7\u6599\u5c07\u4e88\u4ee5\u4fdd\u5bc6\uff0c\u4e26\u53ea\u4f5c\u62db\u8058\u7528\u9014\u3002)", "employment_types": ["Full Time"], "selling_points": [], "locations": ["To Kwa Wan"], "categories": ["Admin & HR", "Others", "Public / Civil", "Counseling", "Social Services - Community / Non-profit Organization"], "post_time": "2021-12-29T03:45:51Z", "salary": {"currency": null, "max": null, "min": null, "period": "monthly", "term": null}, "salary_visible": false, "title_keywords": ["officer", "\u5e79\u4e8b"], "responsibilities": [], "requirements": {"degrees": [], "majors": [], "languages": [], "language_level": [], "hard_skills": [], "soft_skills": [], "languages_combined": []}, "experience_required": {"duration": [], "field": []}}, {"job_id": "100003009016528", "location_code": "hk", "company": "The Society for the Aid and Rehabilitation of Drug Abusers", "job_title": "\u968a\u9577-\u975e\u83ef\u88d4\u4eba\u58eb\u5916\u5c55\u670d\u52d9 (ASWO/Team Leader) \u2013 EM Project 2.0", "description": "\u6301\u793e\u6703\u5de5\u4f5c\u6587\u6191/\u793e\u6703\u5de5\u4f5c\u526f\u5b78\u58eb\u6216\u4ee5\u4e0a\u5b78\u6b77\uff0c\u9808\u70ba\u8a3b\u518a\u793e\u5de5\uff0c\u975e\u8a3b\u518a\u793e\u5de5\uff0c\u53ef\u7533\u8acb\u70ba\u9805\u76ee\u4e3b\u4efb\n\u9808\u5177\u5099\u81f3\u5c11\u5169\u5e74\u793e\u5340\u670d\u52d9\u7d93\u9a57\n\u6709\u9752\u5c11\u5e74/\u9577\u8005\u670d\u52d9\u5de5\u4f5c\u7d93\u9a57\u512a\u5148\n\u826f\u597d\u6e9d\u901a\u80fd\u529b\u3001\u4e3b\u52d5\u3001\u6210\u719f\u3001\u6709\u5de5\u4f5c\u71b1\u8aa0\n\u5929\u6c34\u570d\u5340\n\u622a\u6b62\u65e5\u671f\uff1a2022\u5e741\u670812\u65e5\n\n\n\u4e0a\u8ff0\u8077\u4f4d\u4ee5\u5408\u7d04\u5236\u8058\u8acb\uff0c\u6709\u610f\u8005\u8acb\u89aa\u7e55\u5c65\u6b77\u53ca\u5217\u660e\u8981\u6c42\u5f85\u9047\u5bc4\u5143\u6717\u51f9\u982d\u535a\u611b\u91ab\u9662\u8cfd\u99ac\u6703\u8b77\u7406\u5b89\u8001\u9662\u5927\u6a13\u8463\u4e8b\u5c40\u4eba\u529b\u8cc7\u6e90\u90e8\u6536\u6216\u50b3\u771f\u81f324789624\u6216\u96fb\u90f5\u81f3 \"Apply Now\" (\u8acb\u8a3b\u660e\u7533\u8acb\u8077\u4f4d\u53ca\u7de8\u865f)\u3002\n\nWhatsApp /\u00a0 WeChat\uff1a6061 0873\n\n\u672c\u9662\u7db2\u7ad9\uff1awww.pokoi.org.hk\n\u5982\u670d\u52d9\u5c0d\u8c61\u5305\u62ec\u5152\u7ae5\uff0c\u672c\u9662\u8981\u6c42\u6e96\u50f1\u54e1\u5165\u8077\u524d\u9032\u884c\u6027\u7f6a\u884c\u5b9a\u7f6a\u7d00\u9304\u67e5\u6838\n\u7533\u8acb\u4eba\u6240\u63d0\u4f9b\u7684\u8cc7\u6599\u5c07\u4e88\u4fdd\u5bc6\u53ca\u53ea\u4f5c\u62db\u8058\u6709\u95dc\u8077\u4f4d\u7528\u9014\n\u672c\u9662\u662f\u5e73\u7b49\u6a5f\u6703\u50f1\u4e3b", "employment_types": ["Full Time"], "selling_points": [], "locations": ["Sham Shui Po"], "categories": ["Public / Civil", "Counseling", "Management", "General Management", "Social Services - Community / Non-profit Organization"], "post_time": "2022-01-03T09:18:12Z", "salary": {"currency": null, "max": null, "min": null, "period": "monthly", "term": null}, "salary_visible": false, "title_keywords": ["team leader"], "responsibilities": [], "requirements": {"degrees": [], "majors": [], "languages": [], "language_level": [], "hard_skills": ["whatsapp"], "soft_skills": [], "languages_combined": []}, "experience_required": {"duration": [], "field": []}}, {"job_id": "100003009010473", "location_code": "hk", "company": "Pok Oi Hospital", "job_title": "\u670d\u52d9\u4e3b\u4efb(\u793e\u5de5)/\u9805\u76ee\u4e3b\u4efb(\u7de8\u865f\uff1aWYAYC/SS/PJO)", "description": "\u8077\u4f4d\u7de8\u865f\uff1a(245) in ADM 525/01 VI (DB)\n\n\u9019\u662f\u4e00\u9805\u5916\u5c55\u6559\u80b2\u670d\u52d9\u8a08\u5283\uff0c\u70ba\u672c\u5730\u975e\u83ef\u88d4\u7684\u5438\u6bd2\u4eba\u58eb\u53ca\u5176\u5bb6\u4eba\u63d0\u4f9b\u5354\u52a9\u3002\u6b64\u8077\u4f4d\u5408\u7d04\u671f\u81f32023\u5e747\u670831\u65e5\u3002\n\n\u4e3b\u8981\u8077\u8cac\n\u63a5\u89f8\u672c\u5730\u975e\u83ef\u88d4\u4eba\u58eb\uff0c\u8b58\u5225\u96b1\u853d\u6feb\u85e5\u7d44\u7fa4\u3001\u9ad8\u5371\u6feb\u85e5\u4eba\u58eb\u53ca\u5176\u5bb6\u5c6c\uff0c\u70ba\u4ed6\u5011\u63d0\u4f9b\u5371\u6a5f\u4ecb\u5165\u53ca\u8f49\u4ecb\u3001\u500b\u6848\u5de5\u4f5c\u3001\u8209\u8fa6\u6d3b\u52d5\u7b49\uff1b\u5efa\u7acb\u5730\u5340\u7d44\u7e54\u53ca\u5b78\u6821\u806f\u7e6b\uff0c\u8209\u8fa6\u5de5\u4f5c\u574a/\u8b1b\u5ea7\uff1b\u9700\u8f2a\u73ed\u665a\u4e0a\u3001\u9031\u672b\u3001\u516c\u773e\u5047\u671f\u5916\u51fa\u5de5\u4f5c\u3002\u9808\u8ca0\u8cac\u8655\u7406\u8ca1\u653f\u3001\u7d71\u8a08\u6578\u64da\u53ca\u64b0\u5beb\u8a08\u5283\u5831\u544a\u7b49\u3002\n\n\u8cc7\u6b77 \u6301\u8a8d\u53ef\u793e\u6703\u5de5\u4f5c\u5b78\u4f4d\u6216\u4ee5\u4e0a\u5b78\u6b77\u7684\u8a3b\u518a\u793e\u5de5\uff0c\u9999\u6e2f\u4e2d\u5b78\u6703\u8003\u4e94\u79d1\u5408\u683c\u6216\u9999\u6e2f\u4e2d\u5b78\u6587\u6191\u8003\u8a66\u4e94\u79d1\u8003\u7372\u7b2c2\u7d1a\u6216\u540c\u7b49\u6216\u4ee5\u4e0a\u6210\u7e3e\uff0c\u5305\u62ec\u4e2d\u3001\u82f1\u6587\u79d1\u3002\u6700\u5c115\u5e74\u6216\u4ee5\u4e0a\u8a3b\u518a\u793e\u5de5\u5de5\u4f5c\u7d93\u9a57\u3002\u5177\u6709\u95dc\u6212\u6bd2\u6216\u6210\u766e\u670d\u52d9\u7d93\u9a57\u3001\u7ba1\u7406\u548c\u57f7\u884c\u6709\u6642\u9650\u9805\u76ee(time limited projects)\u53ca\u66fe\u8207\u975e\u83ef\u88d4\u4eba\u58eb\u5de5\u4f5c\u7d93\u9a57\u8005\u5c07\u7372\u512a\u5148\u8003\u616e\u3002\n\n\u5f85\u9047\n\u9996\u5e74\u6708\u85aa$40,524\uff0c\u5e74\u504714\u5929\u3002\n\n\u7533\u8acb\u624b\u7e8c\n1. \u586b\u5beb\u7db2\u4e0a\u8868\u683c\u7533\u8acb\u3002\n2. \u5230\u672c\u6703\u7db2\u9801 www.sarda.org.hk \u4e0b\u8f09\u8077\u4f4d\u7533\u8acb\u8868\u683c\uff0c\u586b\u59a5\u5f8c\u5bc4\u7063\u4ed4\u8ed2\u5c3c\u8a69\u905315\u865f\u6eab\u838e\u516c\u7235\u793e\u6703\u670d\u52d9\u5927\u5ec83\u6a13\u884c\u653f\u7e3d\u4e3b\u4efb\u6536\u3002\n\n(\u4e4b\u524d\u5df2\u7533\u8acb\u6b64\u8077\u4f4d\u7684\u4eba\u58eb\u7121\u9808\u518d\u7533\u8acb\u3002\u672c\u6703\u4fdd\u7559\u4e0d\u586b\u88dc\u4e0a\u8ff0\u8077\u4f4d\u7684\u6b0a\u5229\u3002)\n\n", "employment_types": ["Full Time", "Permanent"], "selling_points": ["\u6301\u793e\u6703\u5de5\u4f5c\u6587\u6191/\u793e\u6703\u5de5\u4f5c\u526f\u5b78\u58eb\u6216\u4ee5\u4e0a\u5b78\u6b77", "\u9808\u5177\u5099\u81f3\u5c11\u5169\u5e74\u793e\u5340\u670d\u52d9\u7d93\u9a57", "\u6709\u9752\u5c11\u5e74/\u9577\u8005\u670d\u52d9\u5de5\u4f5c\u7d93\u9a57\u512a\u5148"], "locations": ["Tin Shui Wai"], "categories": ["Public / Civil", "Counseling", "Social Services - Community / Non-profit Organization", "Others"], "post_time": "2021-12-31T03:52:39Z", "salary": {"currency": null, "max": null, "min": null, "period": "monthly", "term": null}, "salary_visible": false, "title_keywords": [], "responsibilities": [], "requirements": {"degrees": [], "majors": [], "languages": [], "language_level": [], "hard_skills": [], "soft_skills": [], "languages_combined": []}, "experience_required": {"duration": [], "field": []}}, {"job_id": "100003009013288", "location_code": "hk", "company": "Haven of Hope Christian Service", "job_title": "\u793e\u5de5 (\u7de8\u865f : EHCCS/SW/JDB)", "description": "\u6301\u6709\u9999\u6e2f\u8a8d\u53ef\u793e\u6703\u5de5\u4f5c\u6587\u6191\u6216\u4ee5\u4e0a\uff0c\u4e26\u5df2\u767b\u8a18\u6210\u70ba\u8a3b\u518a\u793e\u5de5\n\u6027\u683c\u6210\u719f\uff0c\u4e3b\u52d5\uff0c\u80fd\u7368\u7acb\u5de5\u4f5c\uff0c\u6709\u8cac\u4efb\u5fc3\uff0c\u5584\u65bc\u8de8\u5c08\u696d\u5408\u4f5c\n\u8ca0\u8cac\u5bb6\u5c45\u9ad4\u5f31\u9577\u8005\u500b\u6848\u7ba1\u7406\u3001\u63d0\u4f9b\u8f14\u5c0e\u60c5\u7dd2\u652f\u63f4\u3001\u5bb6\u8a2a\u3001\u8b77\u8001\u8005\u652f\u63f4\u53ca\u5e36\u9818\u9577\u8005\u6d3b\u52d5\u7b49\n\u5177\u4e00\u5e74\u6216\u4ee5\u4e0a\u9577\u8005\u793e\u5340\u670d\u52d9\u5de5\u4f5c\u7d93\u9a57 ;\u00a0\u5177\u9577\u8005\u793e\u5340\u670d\u52d9\u5be6\u7fd2\u7d93\u9a57\u4e4b\u7562\u696d\u751f\u4e5f\u53ef\u7533\u8acb\n\u5de5\u4f5c\u5730\u9ede\uff1a\u6771\u4e5d\u9f8d\u3001\u5c07\u8ecd\u6fb3\u53ca\u897f\u8ca2\n\n\n\n\u6709\u610f\u8005\u8acb\u65bc\u4e8c\u96f6\u4e8c\u4e00\u5e74\u4e00\u6708\u4e8c\u5341\u4e8c\u65e5\u524d\u89aa\u7e55\u5c65\u6b77\u53ca\u671f\u671b\u5f85\u9047\uff08\u8acb\u65bc\u4fe1\u5c01\u9762\u53ca\u4fe1\u5167\u8a3b\u660e\u7533\u8acb\u8077\u4f4d\u7de8\u865f\uff09\u5bc4\u65b0\u754c\u5c07\u8ecd\u6fb3\u9748\u5be6\u8def\u4e03\u865f\u57fa\u7763\u6559\u9748\u5be6\u5354\u6703\u4eba\u529b\u8cc7\u6e90\u90e8\u6536\uff0c\u6216\u96fb\u90f5\u81f3\"Apply Now\"\uff0c\u6216\u767c\u9001\u81f3Whatsapp\u865f\u78bc6507 8148\uff08\u6a19\u984c\u8acb\u8a3b\u660e\u8077\u4f4d\u7de8\u865f\uff09\u3002\u5982\u4e00\u500b\u6708\u5167\u672a\u7372\u901a\u77e5\u7d04\u898b\uff0c\u5247\u4f5c\u843d\u9078\u8ad6\u3002\n\n\u67e5\u8a62\u71b1\u7dda\uff1a2703 3227 (\u96fb\u8a71)\uff1b6507 8148(Whatsapp)\u3002\n\n\u6709\u95dc\u672c\u6703\u8a73\u60c5\uff0c\u8acb\u700f\u89bd\u7db2\u9801http://www.hohcs.org.hk\n\n(\u53ef\u80fd\u7372\u8058\u4eba\u58eb\uff08\u5982\u5f9e\u4e8b\u8207\u5152\u7ae5\u6216\u7cbe\u795e\u4e0a\u7121\u884c\u70ba\u80fd\u529b\u4eba\u58eb\u6709\u95dc\u5de5\u4f5c\u8077\u4f4d\uff09\u9808\u65bc\u5165\u8077\u524d\u9032\u884c\uff0f\u63d0\u4ea4\u6027\u7f6a\u884c\u5b9a\u7f6a\u7d00\u9304\u67e5\u6838\u3002\u7533\u8acb\u4eba\u6240\u63d0\u4f9b\u7684\u8cc7\u6599\u5c07\u4e88\u4fdd\u5bc6\u53ca\u4f5c\u62db\u8058\u6709\u95dc\u8077\u4f4d\u7528\u9014)\n\n\u672a\u7d93\u672c\u5354\u6703\u66f8\u9762\u540c\u610f\uff0c\u4ee5\u4e0a\u62db\u8058\u5ee3\u544a\u5168\u90e8\u6216\u90e8\u5206\u5167\u5bb9\u5747\u4e0d\u5f97\u8907\u88fd\u81f3\u5176\u4ed6\u62db\u8058\u7db2\u7ad9\u3002", "employment_types": ["Full Time"], "selling_points": [], "locations": ["Not Specified"], "categories": ["Public / Civil", "Counseling", "Social Services - Community / Non-profit Organization", "Others"], "post_time": "2022-01-03T01:59:04Z", "salary": {"currency": null, "max": null, "min": null, "period": "monthly", "term": null}, "salary_visible": false, "title_keywords": ["\u793e\u5de5"], "responsibilities": [], "requirements": {"degrees": [], "majors": [], "languages": [], "language_level": [], "hard_skills": [], "soft_skills": [], "languages_combined": []}, "experience_required": {"duration": [], "field": []}}, {"job_id": "100003008989296", "location_code": "hk", "company": "The Hong Kong Polytechnic University", "job_title": "Associate Counsellor", "description": "STUDENT AFFAIRS OFFICE\nAssociate Counsellor (Ref. 21122012-JCS)\nDuties\nThe appointee will be required to:\n(a)\u00a0\u00a0 \u00a0provide counselling services to students individually and in groups;\n(b)\u00a0\u00a0 \u00a0handle cases in crisis situations under supervision;\n(c)\u00a0\u00a0 \u00a0design and conduct developmental programmes and university-wide events / campaigns for the promotion of psychological, physical and spiritual wellness of students;\n(d)\u00a0\u00a0 \u00a0work closely with academic faculties / departments in enhancing students\u2019 holistic development;\n(e)\u00a0\u00a0 \u00a0conduct training for staff on campus and in student halls on issues concerning students\u2019 psycho-social well-being and enhance their skills in handling students\u2019 problems;\n(f)\u00a0\u00a0 \u00a0liaise with academic staff, family members and external agencies on matters relating to students\u2019 well-being; and\n(g)\u00a0\u00a0 \u00a0perform any other duties as assigned by the Dean of Students or his/her delegates.\nThe appointee may be required to work irregular hours.\nQualifications\nApplicants should have:\n(a)\u00a0\u00a0 \u00a0a recognised degree in Counselling, Psychology, Social Work or a relevant discipline;\n(b)\u00a0\u00a0 \u00a0at least five years\u2019 relevant experience in counselling, preferably in educational setting and/or mental health setting;\n(c)\u00a0\u00a0 \u00a0the ability to demonstrate good skills in case management, interpersonal relationship and team work;\n(d)\u00a0\u00a0 \u00a0an excellent command of both written and spoken English and Chinese, with fluency in Putonghua being highly preferred; and\n(e)\u00a0\u00a0 \u00a0good servicing attitude.\nShortlisted candidates will be invited to sit for a written test.\nRemuneration and Conditions of Service\nA highly competitive remuneration package will be offered.\u00a0 Appointment will be on a one-year gratuity-bearing contract.\u00a0 Applicants should state their current and expected salary in the application.\nApplication\nPlease send a completed application form by post to Human Resources Office, 13/F, Li Ka Shing Tower, The Hong Kong Polytechnic University, Hung Hom, Kowloon, Hong Kong or via email by clicking \"Apply Now\".\u00a0 Application forms can be downloaded from https://www.polyu.edu.hk/hro/careers/guidelines_and_forms/forms.\u00a0 If a separate curriculum vitae is to be provided, please still complete the application form which will help speed up the recruitment process.\u00a0 The closing date for application is Monday, 3 January 2022.\u00a0 Applicants who are not invited to an interview within two months from the closing date should consider their applications unsuccessful.\u00a0 The University\u2019s Personal Information Collection Statement for recruitment can be found at https://www.polyu.edu.hk/hro/careers/guidelines_and_forms/pics_for_recruitment.\nPolyU is an equal opportunity employer committed to diversity and inclusivity.\u00a0 All qualified applicants will receive consideration for employment without regard to gender, ethnicity, nationality, family status or physical or mental disabilities.", "employment_types": ["Full Time"], "selling_points": [], "locations": ["Not Specified"], "categories": ["Public / Civil", "Counseling", "Social Services - Community / Non-profit Organization", "Others"], "post_time": "2021-12-21T03:14:40Z", "salary": {"currency": null, "max": null, "min": null, "period": null, "term": null}, "salary_visible": false, "title_keywords": ["associate"], "responsibilities": ["any other duties", "management", "design", "recruitment", "liaise with", "recruitment process"], "requirements": {"degrees": ["degree"], "majors": ["social work", "psychology"], "languages": ["putonghua", "english", "chinese"], "language_level": ["fluency", "excellent"], "hard_skills": ["c"], "soft_skills": ["committed", "interpersonal"], "languages_combined": [{"language": "putonghua", "language_level": ["fluency", "excellent"]}, {"language": "english", "language_level": ["excellent"]}, {"language": "chinese", "language_level": ["excellent"]}]}, "experience_required": {"duration": ["at least five years"], "field": ["relevant experience"]}}, {"job_id": "100003008998057", "location_code": "hk", "company": "Pok Oi Hospital", "job_title": "\u670d\u52d9\u4e3b\u4efb(\u7de8\u865f\uff1aFMI/CIIF/SS)", "description": "\u6301\u793e\u6703\u5de5\u4f5c\u6587\u6191/\u793e\u6703\u5de5\u4f5c\u526f\u5b78\u58eb\u6216\u4ee5\u4e0a\u5b78\u6b77\uff0c\u9808\u70ba\u8a3b\u518a\u793e\u5de5\n\u9808\u5177\u5099\u81f3\u5c11\u5169\u5e74\u793e\u5340\u670d\u52d9\u7d93\u9a57\n\u6709\u9577\u8005\u670d\u52d9\u5de5\u4f5c\u7d93\u9a57\u512a\u5148\n\u826f\u597d\u6e9d\u901a\u80fd\u529b\u3001\u4e3b\u52d5\u8207\u5730\u5340\u6301\u4efd\u8005\u806f\u7e6b\u53ca\u5efa\u7acb\u95dc\u4fc2\n\u5c6f\u9580\u5340\n\u622a\u6b62\u65e5\u671f\uff1a2022\u5e741\u67085\u65e5\n\n\n\u4e0a\u8ff0\u8077\u4f4d\u4ee5\u5408\u7d04\u5236\u8058\u8acb\uff0c\u6709\u610f\u8005\u8acb\u89aa\u7e55\u5c65\u6b77\u53ca\u5217\u660e\u8981\u6c42\u5f85\u9047\u5bc4\u5143\u6717\u51f9\u982d\u535a\u611b\u91ab\u9662\u8cfd\u99ac\u6703\u8b77\u7406\u5b89\u8001\u9662\u5927\u6a13\u8463\u4e8b\u5c40\u4eba\u529b\u8cc7\u6e90\u90e8\u6536\u6216\u50b3\u771f\u81f324789624\u6216\u96fb\u90f5\u81f3 \"Apply Now\" (\u8acb\u8a3b\u660e\u7533\u8acb\u8077\u4f4d\u53ca\u7de8\u865f)\u3002\n\nWhatsApp /\u00a0 WeChat\uff1a6061 0873\n\n\u672c\u9662\u7db2\u7ad9\uff1awww.pokoi.org.hk\n\u5982\u670d\u52d9\u5c0d\u8c61\u5305\u62ec\u5152\u7ae5\uff0c\u672c\u9662\u8981\u6c42\u6e96\u50f1\u54e1\u5165\u8077\u524d\u9032\u884c\u6027\u7f6a\u884c\u5b9a\u7f6a\u7d00\u9304\u67e5\u6838\n\u7533\u8acb\u4eba\u6240\u63d0\u4f9b\u7684\u8cc7\u6599\u5c07\u4e88\u4fdd\u5bc6\u53ca\u53ea\u4f5c\u62db\u8058\u6709\u95dc\u8077\u4f4d\u7528\u9014\n\u672c\u9662\u662f\u5e73\u7b49\u6a5f\u6703\u50f1\u4e3b\n", "employment_types": ["Full Time", "Permanent"], "selling_points": ["\u6301\u793e\u6703\u5de5\u4f5c\u6587\u6191/\u793e\u6703\u5de5\u4f5c\u526f\u5b78\u58eb\u6216\u4ee5\u4e0a\u5b78\u6b77\uff0c\u9808\u70ba\u8a3b\u518a\u793e\u5de5", "\u9808\u5177\u5099\u81f3\u5c11\u5169\u5e74\u793e\u5340\u670d\u52d9\u7d93\u9a57", "\u6709\u9577\u8005\u670d\u52d9\u5de5\u4f5c\u7d93\u9a57\u512a\u5148"], "locations": ["Tuen Mun Area"], "categories": ["Public / Civil", "Counseling", "Social Services - Community / Non-profit Organization", "Others"], "post_time": "2021-12-24T02:29:53Z", "salary": {"currency": null, "max": null, "min": null, "period": "monthly", "term": null}, "salary_visible": false, "title_keywords": [], "responsibilities": [], "requirements": {"degrees": [], "majors": [], "languages": [], "language_level": [], "hard_skills": ["whatsapp"], "soft_skills": [], "languages_combined": []}, "experience_required": {"duration": [], "field": []}}, {"job_id": "100003008989240", "location_code": "hk", "company": "The Hong Kong Polytechnic University", "job_title": "Student Guidance Officer (two posts)", "description": "STUDENT AFFAIRS OFFICE\nStudent Guidance Officer (two posts) (Ref. 21122013-JCS)\nDuties\nThe appointees will be required to:\n(a)\u00a0\u00a0 \u00a0provide support in planning and organising programmes and activities for enhancing students\u2019 all-round development;\n(b)\u00a0\u00a0 \u00a0assist in supporting students in their developmental agenda, e.g. providing guidance to students experiencing transient anxiety in the new learning environment;\n(c)\u00a0\u00a0 \u00a0coach and supervise student leaders / mentors / helpers to enable them to support and help fellow students in various developmental activities;\n(d)\u00a0\u00a0 \u00a0administer student surveys or evaluation of programmes / services including data collection, compilation of statistical reports and report writing;\n(e)\u00a0\u00a0 \u00a0supervise supporting staff on aspects related to programme implementation; and\n(f)\u00a0\u00a0 \u00a0perform any other duties as assigned by the Dean of Students or his/her delegates.\nThe appointees may be required to work irregular hours.\nQualifications\nApplicants should have:\n(a)\u00a0\u00a0 \u00a0a recognised degree, preferably in Social Work, Psychology, Education or other relevant discipline;\n(b)\u00a0\u00a0 \u00a0some relevant experience, preferably in working with university students;\n(c)\u00a0\u00a0 \u00a0a good command of both written and spoken English and Chinese, with fluency in Putonghua being an advantage;\n(d)\u00a0\u00a0 \u00a0good computer literacy;\n(e)\u00a0\u00a0 \u00a0good servicing attitude; and\n(f)\u00a0\u00a0 \u00a0excellent interpersonal and communication skills.\nShortlisted candidates will be invited to sit for a written test.\nRemuneration and Conditions of Service\nA highly competitive remuneration package will be offered.\u00a0 Appointment will be on a one-year gratuity-bearing contract.\u00a0 Applicants should state their current and expected salary in the application.\nApplication\nPlease send a completed application form by post to Human Resources Office, 13/F, Li Ka Shing Tower, The Hong Kong Polytechnic University, Hung Hom, Kowloon, Hong Kong or via email by clicking \"Apply Now\".\u00a0 Application forms can be downloaded from https://www.polyu.edu.hk/hro/careers/guidelines_and_forms/forms.\u00a0 If a separate curriculum vitae is to be provided, please still complete the application form which will help speed up the recruitment process.\u00a0 The closing date for application is Monday, 3 January 2022.\u00a0 Applicants who are not invited to an interview within two months from the closing date should consider their applications unsuccessful.\u00a0 The University\u2019s Personal Information Collection Statement for recruitment can be found at https://www.polyu.edu.hk/hro/careers/guidelines_and_forms/pics_for_recruitment.\nPolyU is an equal opportunity employer committed to diversity and inclusivity.\u00a0 All qualified applicants will receive consideration for employment without regard to gender, ethnicity, nationality, family status or physical or mental disabilities.", "employment_types": ["Full Time"], "selling_points": [], "locations": ["Not Specified"], "categories": ["Public / Civil", "Counseling", "Education", "Others", "Marketing / Public Relations", "Public Relations - Event Management"], "post_time": "2021-12-21T03:03:31Z", "salary": {"currency": null, "max": null, "min": null, "period": null, "term": null}, "salary_visible": false, "title_keywords": ["officer"], "responsibilities": ["guidance", "provide support", "any other duties", "communication", "reports", "programme implementation", "data collection", "evaluation", "recruitment", "report", "recruitment process", "planning"], "requirements": {"degrees": ["degree"], "majors": ["social work", "psychology"], "languages": ["putonghua", "english", "chinese"], "language_level": ["fluency", "advantage", "good command"], "hard_skills": ["c"], "soft_skills": ["communication skills", "computer literacy", "committed", "learning", "interpersonal"], "languages_combined": [{"language": "putonghua", "language_level": ["fluency", "advantage", "good command"]}, {"language": "english", "language_level": ["advantage", "good command"]}, {"language": "chinese", "language_level": ["advantage", "good command"]}]}, "experience_required": {"duration": [], "field": ["relevant experience"]}}, {"job_id": "100003008991325", "location_code": "hk", "company": "The University of Hong Kong", "job_title": "Social Work Officer (at the rank of Student Advising Officer) (several posts)", "description": "Social Work Officer (at the rank of Student Advising Officer) (several posts) in the LKS Faculty of Medicine (Ref.: 511317)\u00a0(to commence as soon as possible, on a two-year fixed-term basis with contract-end gratuity and University contribution to a retirement benefits scheme, totalling up to 10% of basic salary, with the possibility of renewal)\n\nApplicants should possess\u00a0a recognised degree or equivalent in Social Work from a local university, and be registered with the Hong Kong Social Workers Registration Board. They should have at least 2 years\u2019 relevant experience in healthcare or a NGO-related \ufb01eld, preferably with experience working with cancer patients and their caregivers. They should also have good counselling skills, knowledge of and interest in digital health intervention, excellent command of written and spoken English and Chinese, strong communication and interpersonal skills, analytical thinking, empathy, and commitment to patient care.\n\nThe appointees will join the HKU Jockey Club Institute of Cancer Care (HKU JCICC) team to develop evidence-based supportive cancer care services. They will be responsible for (i) providing counselling service for cancer patients and their caregivers; (ii) developing digital health intervention/education for cancer patients and their caregivers; (iii) driving the team\u2019s social media work by designing overall strategies and creating public education materials; (iv) planning and conducting patient groups; (v) delivering large-scale education programmes; and (vi) conducting research in relevant areas. Irregular working hours will be required occasionally.\n\nA highly competitive salary commensurate with qualifications and experience will be offered, in addition to annual leave and medical benefits.\n\nThe University only accepts online application for the above posts. Applicants should apply online at the University\u2019s careers site (https://jobs.hku.hk) and upload an up-to-date C.V.\u00a0Review of applications will start from January 4, 2022 and continue until\u00a0January 20, 2022, or until the posts are filled, whichever is earlier.\n\nThe University is an equal opportunities employer and\nis committed to equality, ethics, inclusivity, diversity and transparency", "employment_types": ["Contract"], "selling_points": ["a recognised degree or equivalent in Social Work", "2 years\u2019 relevant experience in healthcare", "annual leave and medical benefits"], "locations": ["Pok Fu Lam"], "categories": ["Public / Civil", "Counseling"], "post_time": "2021-12-22T03:16:50Z", "salary": {"currency": null, "max": null, "min": null, "period": "monthly", "term": null}, "salary_visible": false, "title_keywords": ["officer"], "responsibilities": ["social media", "developing", "develop", "communication", "designing", "planning"], "requirements": {"degrees": ["degree"], "majors": ["social work"], "languages": ["english", "chinese"], "language_level": ["excellent", "good"], "hard_skills": ["basic", "scheme"], "soft_skills": ["supportive", "responsible", "communication and interpersonal skills", "patient", "empathy"], "languages_combined": [{"language": "english", "language_level": ["excellent", "good"]}, {"language": "chinese", "language_level": ["excellent", "good"]}]}, "experience_required": {"duration": ["at least 2 years"], "field": ["related", "healthcare", "relevant experience"]}}, {"job_id": "100003008995680", "location_code": "hk", "company": "Manpower Services (Hong Kong) Limited", "job_title": "Head of Consultant (Fund Management) (HKD 70K - 75K)", "description": "A well known funding association is now looking for the following talents with relevant knowledge and experience to join their team.\n\nHead of Consultant - Fund Management (HKD 70K - 75K)\n\nRequirements:\n\n- Al least 10 years of experience in environmental engineering/ waste management/ recycling management\n- Degree or above in Waste/ Environmental management/ E&M Engineering or any related subject\n- Strong to lead a team (not less than 10 people), strong knowledge in waste management policies, recycling technologies\n- Preferred experience in government funding scheme, programme and consultancy service\u00a0\n- Strong in presentation, planning & analysis, good command in English & Chinese\u00a0\n- Hong Kong ID holder\n\nInterested parties, please send a full resume with expected salary to martin.chan@manpowergrc.mo\n\n(All information collected will be treated in strict confidence and used solely for recruitment purpose)\u00a0", "employment_types": ["Permanent"], "selling_points": ["Min 10 years in waste/ environmental management", "Degree in Environmental/ Chemical/ E&M Engineering", "Hong Kong ID Holder ONLY"], "locations": ["Kowloon City Area"], "categories": ["Banking / Finance", "Project Finance", "Fund Management", "Public / Civil", "Counseling"], "post_time": "2021-12-23T04:35:56Z", "salary": {"currency": null, "max": null, "min": null, "period": "monthly", "term": null}, "salary_visible": false, "title_keywords": ["consultant"], "responsibilities": ["management", "policies", "analysis", "lead a team", "planning"], "requirements": {"degrees": ["degree or above"], "majors": ["engineering"], "languages": ["english", "chinese"], "language_level": ["good command"], "hard_skills": ["id", "analysis", "scheme"], "soft_skills": ["presentation"], "languages_combined": [{"language": "english", "language_level": ["good command"]}, {"language": "chinese", "language_level": ["good command"]}]}, "experience_required": {"duration": ["least 10 years"], "field": ["management", "environmental", "engineering", "team"]}}]