[{"job_id": "100003009046839", "location_code": "hk", "company": "Employees Retraining Board", "job_title": "Executive (Ref: E-1/22)", "description": "Major Responsibilities:\n\nTo perform general executive duties.\n\nEntry Requirements:\n\nA recognised university degree with a minimum of 3 years' post-degree working experience;\nstrong intellectual, analytical, organisational and interpersonal skills; and\ngood command of written and spoken English and Chinese, and good PC skills.\nApplicants may be considered for other related positions should suitable vacancies arise.\n\nRemuneration and Terms:\n\nERB is an equal opportunity employer. We offer competitive packages commensurate with qualifications and experience. In addition to 5-day week, we provide various leave, retirement protection, medical, dental and life insurance coverage.\n\nApplication Method:\n\nApplication should be made by completing the ERB Job Application Form available from the ERB website (http://www.erb.org). \u00a0It should be forwarded together with an application letter and detailed resume either by clicking \"Apply Now\"\u00a0or by post to HRA Section, Employees Retraining Board, 3/F to 6/F, 10 Siu Sai Wan Road, Chai Wan, Hong Kong.\nThe position applied for, with reference number, should be stated on the envelope or at the subject title of the email. \u00a0Applications without a completed ERB Job Application Form may not be considered.\nThe deadline for application is 31\u00a0January 2022.\nShortlisted applicants may be required to sit for a written test.\nPersonal data collected are for recruitment purpose only. \u00a0Personal data of unsuccessful candidates will be destroyed soon after selection, and definitely within 6 months.", "employment_types": ["Full Time", "Permanent"], "selling_points": [], "locations": ["Siu Sai Wan"], "categories": ["Admin & HR", "Clerical / Admin Staff", "Others", "Public / Civil", "Others"], "post_time": "2022-01-18T02:42:20Z", "salary": {"currency": null, "max": null, "min": null, "period": "monthly", "term": null}, "salary_visible": false, "title_keywords": ["executive"], "responsibilities": [], "requirements": {"degrees": ["university degree", "degree"], "majors": [], "languages": ["english", "chinese"], "language_level": ["good command", "good"], "hard_skills": ["pc skills"], "soft_skills": ["interpersonal skills"], "languages_combined": [{"language": "english", "language_level": ["good", "good command"]}, {"language": "chinese", "language_level": ["good", "good command"]}]}, "experience_required": {"duration": ["minimum of 3 years"], "field": []}}, {"job_id": "100003009054240", "location_code": "hk", "company": "The Vine Church Limited", "job_title": "Volunteer & Connections Coordinator", "description": "This is a full-time position which reports to Ministry Life Pastor.\n\nRecruit and train new volunteers;\nArrange rostering and keep scheduling of volunteers;\nCoordinate, develop and mobilize volunteers for both Welcome and Connect Team and Hosts and Counting team;\nDevelop onboarding process for new volunteers. Match volunteers to opportunities that suit their skill sets and ensuring they understand their responsibilities and receive the proper training;\nAppoint and train team leaders for volunteer teams;\nEstablish a Sundays Volunteer Core Team and provide pastoral care for volunteers;\nAssist Ministry Life Pastor to provide a wider Vine volunteer strategy & communication plan. Coordinate volunteers\u2019 connection points and opportunities regularly;\nMaintain a database of Newcomers and keep track of the connection points;\nBe the point person coordinating \u201cfirst contacts\u201d for new first time guests;\nCollaborate with Services Team to coordinate Newcomers Sunday Lunches & Forward Together;\nPartner with Community Groups team to oversee connect hub;\nParticipate fully in Pastoral Team and Ministry Life Team\u2019s activities including meetings, intercession meetings and devotions.\n\nJob Requirement\n\nExperience in volunteering and recruitment.\nWorking knowledge of databases management.\nAble to communicate effectively with diverse people.\nExcellent organization and team coordination skills.\nGood command of written and spoken English and Chinese.\nPleasant and outgoing.\n\nHow to apply\n\nInterested parties please send application with full CV with your current and expected salary by clicking \"Apply Now\".\n\nPersonal data provided by job applicants will be strictly used for recruitment purpose.", "employment_types": ["Full Time"], "selling_points": [], "locations": ["Wan Chai"], "categories": ["Admin & HR", "Clerical / Admin Staff", "Public / Civil", "Social Services - Community / Non-profit Organization", "Others"], "post_time": "2022-01-17T08:55:11Z", "salary": {"currency": null, "max": null, "min": null, "period": "monthly", "term": null}, "salary_visible": false, "title_keywords": ["coordinator"], "responsibilities": ["collaborate with", "management", "teams", "develop", "coordinate", "scheduling", "communication", "maintain", "reports", "recruitment", "plan", "database", "databases", "coordination"], "requirements": {"degrees": [], "majors": [], "languages": ["english", "chinese"], "language_level": ["good command"], "hard_skills": ["databases"], "soft_skills": ["outgoing", "coordination skills", "pleasant", "communication", "diverse"], "languages_combined": [{"language": "english", "language_level": ["good command"]}, {"language": "chinese", "language_level": ["good command"]}]}, "experience_required": {"duration": [], "field": ["recruitment"]}}, {"job_id": "100003009047782", "location_code": "hk", "company": "Tung Wah Group of Hospitals", "job_title": "\u5eb6\u52d9\u54e1(\u6e05\u6f54)(\u8077\u4f4d\u7de8\u865f\uff1aA3/GA(C)/BCAD/JOBS)", "description": "\u5de5\u4f5c\u5730\u9ede\uff1a\u4e0a\u74b0\n\u8077\u8cac\uff1a\n\u8ca0\u8cac\u884c\u653f\u5927\u6a13\u7684\u6e05\u6f54\u53ca\u8336\u6c34\u5de5\u4f5c\u3001\u6587\u4ef6\u7684\u50b3\u9001\u3001\u7c21\u55ae\u7684\u6587\u66f8\u53ca\u4e00\u822c\u5eb6\u52d9\u5de5\u4f5c\u3002\n\u7406\u60f3\u7684\u7533\u8acb\u8005\u61c9\u5177\u5099\uff1a\n\u5b8c\u6210\u5c0f\u5b78\u7a0b\u5ea6\uff0c\u80fd\u95b2\u8b80\u7c21\u55ae\u4e2d\u82f1\u6587\uff0c\u64cd\u6d41\u5229\u7cb5\u8a9e\u3002\u5177\u76f8\u95dc\u5de5\u4f5c\u7d93\u9a57\u8005\u5c07\u7372\u512a\u5148\u8003\u616e\u3002\n\u85aa\u916c\u53ca\u8058\u7528\u689d\u4ef6\uff1a\n\u7372\u9078\u7684\u7533\u8acb\u4eba\u5c07\u4ee5\u5408\u7d04\u689d\u6b3e\u53d7\u8058\u3002\u6709\u95dc\u85aa\u91d1\u6703\u6309\u5e74\u5c31\u54e1\u5de5\u7684\u8868\u73fe\u53ca\u6771\u83ef\u898f\u5b9a\u800c\u5411\u4e0a/\u4e0b\u8abf\u6574\u6216\u51cd\u7d50\u3002\u54e1\u5de5\u798f\u5229\u5305\u62ec\u6709\u85aa\u5047\u671f\u3001\u9032\u4fee\u6d25\u8cbc\u3001\u91ab\u7642\u53ca\u7259\u9f52\u4fdd\u5065\u3002\u4efb\u8077\u8005\u5c07\u6309\u4e94\u5929\u5de5\u4f5c\u5468\u5b89\u6392\u4e0a\u73ed\uff0c\u60df\u4ecd\u9808\u8996\u4e4e\u90e8\u9580\u904b\u4f5c\u53ca\u670d\u52d9\u9700\u8981\u800c\u5b9a\u3002\n\u7533\u8acb\u7a0b\u5e8f\uff1a\n\u8acb\u5c07\u500b\u4eba\u5c65\u6b77\u6216\u586b\u59a5\u7533\u8acb\u8868\u683c<\u8868\u865f\uff1aF601(n)>(\u53ef\u89aa\u81e8\u7d22\u53d6\u6216\u5f9e\u672c\u9662\u7684\u7db2\u9801http://www.tungwah.org.hk\u4e0b\u8f09)\u4e26\u5217\u660e\u73fe\u6642\u53ca\u8981\u6c42\u85aa\u916c\u5f85\u9047\uff0c\u65bc\u4e8c\uff10\u4e8c\u4e8c\u5e74\u4e8c\u6708\u5341\u56db\u65e5\u524d\u5bc4\u9999\u6e2f\u4e0a\u74b0\u666e\u4ec1\u8857\u5341\u4e8c\u865f\u6771\u83ef\u4e09\u9662\u9ec3\u9cf3\u7fce\u7d00\u5ff5\u5927\u6a13\u56db\u6a13\u4eba\u529b\u8cc7\u6e90\u79d1\u4e3b\u7ba1\u6536\uff0c\u4fe1\u5167\u53ca\u4fe1\u5c01\u9762\u8acb\u8a3b\u660e\u7533\u8acb\u7684\u8077\u4f4d\u53ca\u8077\u4f4d\u7de8\u865f\u3002\u6771\u83ef\u4e09\u9662\u4e0d\u6703\u63a5\u6536\u90f5\u8cc7\u4e0d\u8db3\u7684\u4fe1\u4ef6\u3002\u70ba\u78ba\u4fdd\u90f5\u905e\u7121\u8aa4\uff0c\u8acb\u5728\u6295\u5bc4\u90f5\u4ef6\u6642\u652f\u4ed8\u8db3\u984d\u90f5\u8cc7\u53ca\u8a3b\u660e\u56de\u90f5\u5730\u5740\u3002\u6771\u83ef\u4e09\u9662\u5728\u4f7f\u7528\u6c42\u8077\u8005\u63d0\u4f9b\u7684\u500b\u4eba\u8cc7\u6599\u6642\uff0c\u53ea\u6703\u5c07\u8cc7\u6599\u4f5c\u6709\u95dc\u62db\u8058\u7528\u9014\uff0c\u4e26\u6703\u56b4\u683c\u9075\u5b88\u9662\u65b9\u500b\u4eba\u8cc7\u6599\u653f\u7b56\u7684\u898f\u5b9a\u3002\u51e1\u65bc\u4e8c\uff10\u4e8c\u4e8c\u5e74\u4e94\u6708\u4e09\u5341\u4e00\u65e5\u524d\u672a\u7372\u7d04\u898b\u8005\uff0c\u53ef\u4f5c\u843d\u9078\u8ad6\u3002\n\u6211\u5011\u662f\u5e73\u7b49\u6a5f\u6703\u50f1\u4e3b", "employment_types": ["Full Time", "Contract"], "selling_points": [], "locations": ["Sheung Wan"], "categories": ["Admin & HR", "Others", "Public / Civil", "Social Services - Community / Non-profit Organization", "Others"], "post_time": "2022-01-17T08:55:07Z", "salary": {"currency": null, "max": null, "min": null, "period": "monthly", "term": null}, "salary_visible": false, "title_keywords": [], "responsibilities": [], "requirements": {"degrees": [], "majors": [], "languages": [], "language_level": [], "hard_skills": [], "soft_skills": [], "languages_combined": []}, "experience_required": {"duration": [], "field": []}}, {"job_id": "100003009054059", "location_code": "hk", "company": "Hong Kong Baptist University", "job_title": "\u5ba2\u6236\u670d\u52d9\u4e3b\u7ba1 / \u5ba2\u6236\u670d\u52d9\u52a9\u7406 (\u4e2d\u91ab\u85e5\u8a3a\u6240) (PR0334/20-21)", "description": "\u4e2d \u91ab \u85e5 \u5b78 \u9662 \u81e8 \u5e8a \u90e8\n\n\u5ba2\u6236\u670d\u52d9\u4e3b\u7ba1 / \u5ba2\u6236\u670d\u52d9\u52a9\u7406 (\u4e2d\u91ab\u85e5\u8a3a\u6240) (PR0334/20-21)\n\n\u8077\u8cac\u5305\u62ec\u8a3a\u6240\u5de5\u4f5c\u5982\u767b\u8a18\u3001\u63a5\u5f85\u3001\u8f38\u5165\u8655\u65b9\u3001\u6536\u8cbb\u3001\u8655\u7406\u75c5\u4eba\u8a18\u9304\u3001\u8f14\u52a9\u5354\u8abf\u898b\u7fd2\u5b78\u54e1\u3001\u5354\u52a9\u8655\u7406\u8a3a\u6240\u5167\u90e8\u4e00\u822c\u4e8b\u52d9\u53ca\u6587\u66f8\u5de5\u4f5c\u7b49\u3002\u5ba2\u6236\u670d\u52d9\u4e3b\u7ba1\u9700\u540c\u6642\u5354\u52a9\u90e8\u9580\u7763\u5c0e\u5ba2\u6236\u670d\u52d9\u52a9\u7406\u7684\u65e5\u5e38\u5de5\u4f5c\u3001\u6301\u7e8c\u63d0\u5347\u8a3a\u6240\u9867\u5ba2\u670d\u52d9\u8cea\u7d20\u53ca\u53c3\u8207\u57f9\u8a13\u5de5\u4f5c\u7b49\u3002\n\n\u5ba2\u6236\u670d\u52d9\u4e3b\u7ba1\uff1a\u9808\u5b8c\u6210\u4e2d\u5b78\u8ab2\u7a0b\uff0c\u5982\u6709\u5c08\u4e0a\u5b78\u6b77\u8005\u66f4\u4f73\uff1b\u53e6\u9700\u5177\u6709\u6700\u5c11\u4e09\u5e74\u4e2d\u3001\u897f\u91ab\u85e5\u8a3a\u6240\u6216\u5176\u4ed6\u63a5\u5f85\u53ca\u9867\u5ba2\u670d\u52d9\u5de5\u4f5c\u6216\u7ba1\u7406\u7d93\u9a57\uff1b\u719f\u8b58\u96fb\u8166\u64cd\u4f5c\uff0c\u53ca\u64cd\u6d41\u5229\u7cb5\u8a9e\u3001\u666e\u901a\u8a71\u548c\u82f1\u8a9e\u3002\u66fe\u63a5\u53d7\u8b77\u7406\u6216\u4e2d\u85e5\u57f9\u8a13\u66f4\u4f73\u3002\n\n\u5ba2\u6236\u670d\u52d9\u52a9\u7406\uff1a\u9808\u5b8c\u6210\u4e2d\u5b78\u8ab2\u7a0b\uff0c\u53ca\u5177\u6709\u6700\u5c11\u4e00\u5e74\u4e2d\u3001\u897f\u91ab\u85e5\u8a3a\u6240\u6216\u5176\u4ed6\u63a5\u5f85\u53ca\u9867\u5ba2\u670d\u52d9\u5de5\u4f5c\u7d93\u9a57\uff1b\u719f\u8b58\u96fb\u8166\u64cd\u4f5c\uff1b\u53ca\u64cd\u6d41\u5229\u7cb5\u8a9e\u548c\u666e\u901a\u8a71\uff0c\u61c2\u7c21\u55ae\u82f1\u8a9e\u3002\u66fe\u63a5\u53d7\u8b77\u7406\u6216\u4e2d\u85e5\u57f9\u8a13\u66f4\u4f73\u3002\n\n\u5de5\u4f5c\u6642\u9593\u53ca\u5730\u9ede\uff1a\u9031\u4e00\u81f3\u9031\u516d\u5de5\u4f5c\u4e94\u5929\uff0c\u6bcf\u661f\u671f\u8f2a\u4f11\u65e5\u4e0d\u56fa\u5b9a\uff0c\u7531\u81e8\u5e8a\u90e8\u5b89\u6392\u3002\u5730\u9ede\u70ba\u81e8\u5e8a\u90e8\u8f44\u4e0b\u5404\u4e2d\u91ab\u85e5\u8a3a\u6240\uff0c\u6309\u5de5\u4f5c\u9700\u8981\u800c\u5b9a\u3002\n\n\u85aa\u916c\u53ca\u8077\u7d1a\u5c07\u6309\u8cc7\u6b77\u53ca\u6709\u95dc\u5de5\u4f5c\u7d93\u9a57\u800c\u5b9a\u3002\n\n\u66fe\u905e\u4ea4\u7533\u8acb\u6587\u4ef6\u8005\u7121\u9700\u518d\u6b21\u7533\u8acb\u3002\n\n\u7533\u8acb\u7a0b\u5e8f\uff1a\n\n\u7533\u8acb\u4eba\u53ef\u900f\u904e\u9999\u6e2f\u6d78\u6703\u5927\u5b78\u7db2\u4e0a\u6c42\u8077\u7cfb\u7d71(jobs.hkbu.edu.hk)\u905e\u4ea4\u7533\u8acb\u3002\u5982\u622a\u6b62\u7533\u8acb\u65e5\u671f\u5f8c8\u661f\u671f\u5167\u672a\u7372\u9762\u8a66\u901a\u77e5\u5247\u4f5c\u843d\u9078\u8ad6\u3002\u6709\u95dc\u5927\u5b78\u300c\u6536\u96c6\u500b\u4eba\u8cc7\u6599\u8072\u660e\u300d\u7684\u8cc7\u6599\u53ef\u700f\u89bdhttp://hro.hkbu.edu.hk/pics\u3002\u5927\u5b78\u4fdd\u7559\u6b0a\u5229\u53d6\u6d88\u62db\u8058\u4ee5\u4e0a\u6240\u520a\u767b\u7684\u8077\u4f4d\uff0c\u800c\u8058\u7528\u689d\u6b3e\u6703\u6309\u8058\u7528\u6642\u4e4b\u60c5\u6cc1\u800c\u5b9a\u3002\n\n\u622a\u6b62\u65e5\u671f\uff1a2022\u5e741\u670829\u65e5", "employment_types": ["Full Time"], "selling_points": ["\u9808\u5b8c\u6210\u4e2d\u5b78\u8ab2\u7a0b", "\u8a3a\u6240\u5de5\u4f5c\u5982\u767b\u8a18\u3001\u63a5\u5f85\u3001\u8f38\u5165\u8655\u65b9\u3001\u6536\u8cbb\u3001\u8655\u7406\u75c5\u4eba\u8a18\u9304\u3001\u8f14\u52a9\u5354\u8abf\u898b\u7fd2\u5b78\u54e1\u3001\u5354\u52a9\u8655\u7406\u8a3a\u6240\u5167\u90e8\u4e00\u822c\u4e8b\u52d9\u53ca\u6587\u66f8", "\u63a5\u5f85\u53ca\u9867\u5ba2\u670d\u52d9\u5de5\u4f5c\u7d93\u9a57"], "locations": ["Kowloon City"], "categories": ["Education", "Others", "Medical Services", "Others", "Public / Civil", "Others"], "post_time": "2022-01-17T08:15:47Z", "salary": {"currency": null, "max": null, "min": null, "period": "monthly", "term": null}, "salary_visible": false, "title_keywords": ["\u5ba2\u6236\u670d\u52d9\u52a9\u7406"], "responsibilities": [], "requirements": {"degrees": [], "majors": [], "languages": [], "language_level": [], "hard_skills": [], "soft_skills": [], "languages_combined": []}, "experience_required": {"duration": [], "field": []}}, {"job_id": "100003009053374", "location_code": "hk", "company": "Yuen Long Town Hall Management Committee Limited", "job_title": "\u5408\u7d04\u6d3b\u52d5\u52a9\u7406(\u9577\u8005\u670d\u52d9)", "description": "\n\u8077\u8cac :\u5354\u52a9\u9577\u8005\u9130\u820d\u4e2d\u5fc3\u63a8\u884c\u6d3b\u52d5\u3001\u63a5\u5f85\u8655\u53ca\u4e00\u822c\u6587\u66f8\u5de5\u4f5c\u7b49 (\u4e00\u5e74\u5408\u7d04\uff0c\u7d04\u6eff\u56e0\u61c9\u8868\u73fe\u7e8c\u8058)\n\n\u8cc7\u6b77 :\u4e2d\u516d\u7a0b\u5ea6; 1\u5e74\u7d93\u9a57; \u826f\u597d\u7cb5\u8a9e; \u4e00\u822c\u666e\u901a\u8a71; \u826f\u597d\u82f1\u8a9e\u512a\u5148; \u61c2\u8b80\u5beb\u4e2d\u6587; \u61c2\u8b80\u5beb\u82f1\u6587; \u5177\u6709\u4e00\u822c\u4e92\u806f\u7db2\u77e5\u8b58; \u61c2\u82f1\u6587\u6253\u5b57; \u61c2\u4e2d\u82f1\u6587\u96fb\u8166\u64cd\u4f5c; \u61c2\u4e2d\u6587\u6253\u5b57; \u9700\u61c2\u4f7f\u7528\u4e00\u822c\u793e\u4ea4\u5a92\u9ad4\u53ca\u96fb\u8166;\u5f85\u4eba\u6709\u79ae\u3001\u6709\u8010\u5fc3\n\n\u5f85\u9047 :\u6bcf\u6708$10,000, \u6709\u5e74\u504721\u5929, \u661f\u671f\u4e00\u81f3\u4e94: \u4e0a\u53488\u6642\u534a\u81f3\u4e0b\u53485\u6642\u53ca\u661f\u671f\u516d: \u4e0a\u53488\u6642\u81f3\u4e2d\u534812\u6642, \u6bcf\u9031\u5de5\u4f5c5\u5929\u81f35\u5929\u534a, \u661f\u671f\u516d\u9577\u77ed\u9031, \u6bcf\u9031\u5de5\u4f5c44\u5c0f\u6642\n\n\u7533\u8acb\u9808\u77e5 :\u6c42\u8077\u8005\u53ef\u96fb\u90f5(Apply Now)\u5c65\u6b77\u8868\u7d66\u5143\u6717\u5927\u6703\u5802\u7ba1\u7406\u59d4\u54e1\u6703\u6709\u9650\u516c\u53f8\u3002\u5982\u8981\u7d22\u53d6\u6536\u96c6\u500b\u4eba\u8cc7\u6599\u8072\u660e, \u8acb\u8207\u5468\u5c0f\u59d0(Email)\u806f\u7d61\u3002\n\n", "employment_types": ["Contract"], "selling_points": [], "locations": ["Yuen Long"], "categories": ["Admin & HR", "Administration / Operation Manager", "Others", "Junior Executive", "Public / Civil", "Others"], "post_time": "2022-01-17T06:53:02Z", "salary": {"currency": null, "max": null, "min": null, "period": "monthly", "term": null}, "salary_visible": false, "title_keywords": [], "responsibilities": [], "requirements": {"degrees": [], "majors": [], "languages": [], "language_level": [], "hard_skills": [], "soft_skills": [], "languages_combined": []}, "experience_required": {"duration": [], "field": []}}, {"job_id": "100003009051859", "location_code": "hk", "company": "Construction Industry Council", "job_title": "Assistant Officer / Assistant - Registration Services", "description": "The applicant must possess\na recognised degree;\na minimum of 1 year's post-qualification experience;\nproactive and customer-oriented;\ngood sense of responsibility and be a pleasant team player;\nproficiency in Cangjie and / or Sucheng input method; and\ngood command of both written and spoken English and Chinese (including Putonghua).\n(Applicants who do not possess the required qualifications and / or experience may be considered for Assistant \u2013 Registration Services.)\n\nDuties include\nto vet the registration scheme applications in accordance to the Policies and Procedures as well as service pledge;\nto provide registration services and application services to other CIC service offerings in CIC Service Centres located at Kowloon Bay and Nam Cheong or other CIC premises;\nto perform data entry and data analysis work;\nto handle enquiries and complaints according to service pledge;\nto maintain the IT System and update the scheme website and publicity materials;\nto support events and other administrative duties of the Registration Services; and\nto carry out any other duties as assigned from time to time by the Executive Director.\n\nApplications\nThe position is on a renewable fixed-term contract (subject to performance and operational needs) for a period of 2 years.\nPlease click the below \u201cApply Online\u201d to complete the application form and upload the updated curriculum vitae, the results of English and Chinese Language obtained in public examinations, current and expected salary together with a covering letter stating one\u2019s suitability for the job on or before 31 January 2022.\nFor further details on CIC please refer to website:\u00a0http://www.cic.hk.", "employment_types": ["Full Time", "Contract"], "selling_points": ["a recognised degree", "a minimum of 1 year's post-qualification work exp.", "to vet the registration scheme applications"], "locations": ["Not Specified"], "categories": ["Admin & HR", "Clerical / Admin Staff", "Personal / Executive Assistant", "Public / Civil", "Others"], "post_time": "2022-01-17T01:23:55Z", "salary": {"currency": null, "max": null, "min": null, "period": null, "term": null}, "salary_visible": false, "title_keywords": ["assistant officer", "assistant"], "responsibilities": ["any other duties", "data entry", "policies", "procedures", "handle enquiries and complaints", "website", "data analysis", "maintain", "administrative duties"], "requirements": {"degrees": ["degree"], "majors": [], "languages": ["putonghua", "english", "chinese"], "language_level": ["good command"], "hard_skills": ["analysis", "scheme"], "soft_skills": ["sense of responsibility", "pleasant", "customer-oriented", "team player", "proactive"], "languages_combined": [{"language": "putonghua", "language_level": ["good command"]}, {"language": "english", "language_level": ["good command"]}, {"language": "chinese", "language_level": ["good command"]}]}, "experience_required": {"duration": ["minimum of 1 year"], "field": ["post-qualification"]}}, {"job_id": "100003009053808", "location_code": "hk", "company": "Grateful Life Experience Centre Limited", "job_title": "\u5bb6\u52d9\u52a9\u7406 (\u517c\u8077)**", "description": "\n\u8077\u8cac :\u4e00\u822c\u5bb6\u52d9\u52a9\u7406\u5de5\u4f5c\uff0c\u4e00\u822c\u5bb6\u5c45\u6e05\u6f54\n\n\u8cc7\u6b77 :\u4e2d\u4e09\u7a0b\u5ea6; 1\u5e74\u7d93\u9a57; \u826f\u597d\u7cb5\u8a9e; \u7565\u61c2\u8b80\u5beb\u4e2d\u6587; \u61c2\u95b1\u8b80\u82f1\u6587; \u61c2\u7167\u9867\u9577\u8005; \u5b8c\u6210\u5bb6\u52d9\u52a9\u7406\u8a13\u7df4\u8ab2\u7a0b; \u8cb7\u9938\u53ca\u9810\u5099\u5348\u98ef; \u8cb7\u9938\u53ca\u9810\u5099\u665a\u98ef; \u5177\u6709\u5bb6\u52d9\u52a9\u7406\u8b49\u66f8\uff0f\u76f8\u95dc\u5de5\u4f5c\u7d93\u9a57\u512a\u5148\n\n\u5f85\u9047 :\u6bcf\u5c0f\u6642$70.00 - $90.00, \u6709\u4ea4\u901a\u6d25\u8cbc, \u661f\u671f\u4e00\u81f3\u516d: \u4e0a\u53489\u6642\u81f3\u4e0b\u53486\u6642, \u6bcf\u9031\u5de5\u4f5c2\u5929\u81f36\u5929,\u8f2a\u73ed, \u6bcf\u5929\u5de5\u4f5c 2 - 4 \u5c0f\u6642\n\n\u7533\u8acb\u9808\u77e5 :\u6c42\u8077\u8005\u53ef\u96fb\u90f5(Apply Now)\u5c65\u6b77\u8868\u7d66\u6069\u6a02\u5065\u5eb7\u751f\u6d3b\u9ad4\u9a57\u9928\u6709\u9650\u516c\u53f8\u3002\u5982\u8981\u7d22\u53d6\u6536\u96c6\u500b\u4eba\u8cc7\u6599\u8072\u660e, \u8acb\u8207\u9ec3\u5c0f\u59d0(Email)\u806f\u7d61\u3002\n\n", "employment_types": ["Part Time"], "selling_points": [], "locations": ["Not Specified"], "categories": ["Admin & HR", "Administration / Operation Manager", "Others", "Junior Executive", "Public / Civil", "Others"], "post_time": "2022-01-17T07:33:04Z", "salary": {"currency": null, "max": null, "min": null, "period": "hourly", "term": null}, "salary_visible": false, "title_keywords": [], "responsibilities": [], "requirements": {"degrees": [], "majors": [], "languages": [], "language_level": [], "hard_skills": [], "soft_skills": [], "languages_combined": []}, "experience_required": {"duration": [], "field": []}}, {"job_id": "100003009053536", "location_code": "hk", "company": "Million Yield Properties Limited", "job_title": "\u5206\u884c\u806f\u7d61\u52a9\u7406", "description": "\n\u8077\u8cac :\u63a5\u807d\u96fb\u8a71, \u806f\u7d61\u5ba2\u6236, \u66f4\u65b0\u5206\u884c\u9580\u9762\u53ca\u50b3\u55ae\u8cc7\u6599\n\n\u8cc7\u6b77 :\u4e2d\u4e09\u7a0b\u5ea6; \u826f\u597d\u7cb5\u8a9e; \u4e00\u822c\u666e\u901a\u8a71; \u4e00\u822c\u82f1\u8a9e; \u61c2\u8b80\u5beb\u4e2d\u6587; \u61c2\u95b1\u8b80\u82f1\u6587\n\n\u5f85\u9047 :\u5e95\u85aa\u9023\u52e4\u5de5\u53ca\u5176\u4ed6\u6d25\u8cbc\u6bcf\u6708$5,850, \u6709\u5728\u8077\u57f9\u8a13 \u53ca\u5176\u4ed6\u6d25\u8cbc/\u798f\u5229, \u4e0a\u534810\u6642\u534a\u81f3\u4e0b\u53485\u6642\u534a\u6216\u4e2d\u534812\u6642\u81f3\u4e0b\u53487\u6642\u6216\u4e0b\u53482\u6642\u534a\u81f3\u4e0b\u53489\u6642, \u6bcf\u9031\u5de5\u4f5c6\u5929,\u8f2a\u73ed,\u8f2a\u4f11, \u6bcf\u5929\u5de5\u4f5c 6 \u5c0f\u6642\n\n\u7533\u8acb\u9808\u77e5 :\u6c42\u8077\u8005\u53ef\u81f4\u96fb66001200\u8207\u842c\u6021\u7f6e\u696d\u6709\u9650\u516c\u53f8\u65b9\u5c0f\u59d0\u806f\u7d61\u3002\n\n", "employment_types": ["Full Time"], "selling_points": [], "locations": ["Tuen Mun Area"], "categories": ["Admin & HR", "Administration / Operation Manager", "Others", "Junior Executive", "Public / Civil", "Others"], "post_time": "2022-01-17T07:07:19Z", "salary": {"currency": null, "max": null, "min": null, "period": "monthly", "term": null}, "salary_visible": false, "title_keywords": [], "responsibilities": [], "requirements": {"degrees": [], "majors": [], "languages": [], "language_level": [], "hard_skills": [], "soft_skills": [], "languages_combined": []}, "experience_required": {"duration": [], "field": []}}, {"job_id": "100003009053926", "location_code": "hk", "company": "YOJE Prudent Personnel Consultant Agency", "job_title": "Museum Assistant (Science/Chemistry/Engg/Biology/Conservation) - Fresh Graduates", "description": "- University graduate in Science, Chemistry, Biology, Technology, Engineering, Maths, Conservation or equivalent\n(Fresh graduates are welcome)\n- Good English and Chinese\n- Common Recruitment Examination English Level 2, Chinese Level 1 or DSE English 5, Chinese 4 or equivalent\u00a0\n- to assist in planning, coordination, liaison of education program, events\n- update social media & website\n\nInterested parties please send full resume with expected salary in MS WORD format to us by clicking \"APPLY NOW\"\nInformation collected will be used for recruitment purposes only", "employment_types": ["Full Time", "Permanent"], "selling_points": ["Science, Technology, Engineering, Maths, Chemistry", "Common Recruitment Exam English 2, Chinese 1", "Museum Assistant, support,  Biology, Conservation"], "locations": ["Not Specified"], "categories": ["Admin & HR", "Clerical / Admin Staff", "Public / Civil", "Social Services - Community / Non-profit Organization", "Others"], "post_time": "2022-01-17T07:53:13Z", "salary": {"currency": null, "max": null, "min": null, "period": "monthly", "term": null}, "salary_visible": false, "title_keywords": ["assistant"], "responsibilities": ["social media", "website", "recruitment", "coordination", "planning"], "requirements": {"degrees": ["university graduate", "dse"], "majors": ["science", "biology", "chemistry", "engineering"], "languages": ["english", "chinese"], "language_level": ["good"], "hard_skills": [], "soft_skills": ["coordination"], "languages_combined": [{"language": "english", "language_level": ["good"]}, {"language": "chinese", "language_level": ["good"]}]}, "experience_required": {"duration": [], "field": []}}, {"job_id": "100003009053425", "location_code": "hk", "company": "Hong Kong Cement Company Limited", "job_title": "Sailor", "description": "\nResponsibilities:\n\u2022 \u8ca0\u8cac\u6c34\u6ce5\u904b\u8f38\uff0c\u78bc\u982d\u5378\u8239\uff0c\u99c1\u8239\u57fa\u672c\u62cb\u7e9c\u3001\u7d81\u6a01\uff0c\u8239\u52d9\u57fa\u672c\u6aa2\u4fee\u3002\nRequirements :\n\u2022 No requirement on academic qualification;\n3 Year(s) Experience Required; Fluent Cantonese ;\n\u2022 Fair Putonghua preferred; Able to read & write Chinese ;\n\u2022 Shipboard Cargo Handling Basic Training Course Certificate; \u5177\u6c34\u6ce5\u8e89\u8239\u5de5\u4f5c\u7d93\u9a57\u512a\u5148\nEmployment Terms:$18,000 - $23,000 per month, with Double Pay, Meal Allowance, Bonus, Transport Allowance and Year-end Bonus, 8:00AM-5:00PM, 6 working days per week, on shift, shift holiday, 8 working hours per day, \u914d\u5408\u5927\u8239\u5230\u6e2f\u6642\u9593\u57f7\u884c\u8239\u52d9\u5de5\u4f5c\n\n", "employment_types": ["Full Time"], "selling_points": [], "locations": ["Tsing Yi"], "categories": ["Public / Civil", "Social Services - Community / Non-profit Organization", "Others"], "post_time": "2022-01-17T06:58:21Z", "salary": {"currency": null, "max": null, "min": null, "period": "monthly", "term": null}, "salary_visible": false, "title_keywords": [], "responsibilities": [], "requirements": {"degrees": ["certificate"], "majors": [], "languages": ["cantonese", "putonghua", "chinese"], "language_level": ["fluent"], "hard_skills": ["no", "basic"], "soft_skills": [], "languages_combined": [{"language": "cantonese", "language_level": ["fluent"]}, {"language": "putonghua", "language_level": []}, {"language": "chinese", "language_level": []}]}, "experience_required": {"duration": [], "field": []}}, {"job_id": "100003009056749", "location_code": "hk", "company": "The Lok Sin Tong Benevolent Society, Kowloon", "job_title": "Procurement Assistant (NGO)", "description": "Responsibilities:\n\n\nHandle supplier registration and managing performance of suppliers;\nInvitations to tender, compilation of tender documents, tender assessment, contract award to delivery of goods and services;\nAssist in consolidation of meeting document & reports;\nAssist in liaising with internal users;\nHandle ad hoc tasks and any other duties as assigned by Management;\u00a0\n5-day work per week, bank Holiday.\u00a0\n\n\u00a0Requirements:\n\nF.5/DSE graduate or above;\n1-2 years purchasing experience;\nGood command of spoken & written English & Cantonese;\nProficiency in MS Word and Excel;\u00a0\nFresh graduate is welcome;\u00a0\nImmediate available is preferable.\n\nInterested parties please send\u00a0full resume with available date, present and expected salary by clicking \"Apply Now\" for application.\n\nPersonal data collected will be used for recruitment purpose only.\u00a0", "employment_types": ["Full Time", "Permanent"], "selling_points": [], "locations": ["Kowloon City"], "categories": ["Merchandising & Purchasing", "Procurement / Purchasing / Sourcing", "Public / Civil", "Social Services - Community / Non-profit Organization", "Others"], "post_time": "2022-01-18T06:11:28Z", "salary": {"currency": null, "max": null, "min": null, "period": "monthly", "term": null}, "salary_visible": false, "title_keywords": ["procurement assistant"], "responsibilities": ["any other duties", "management", "tender documents", "ad hoc tasks", "liaising with", "reports", "tender"], "requirements": {"degrees": ["fresh graduate", "dse"], "majors": [], "languages": ["cantonese", "english"], "language_level": ["good command"], "hard_skills": ["excel", "ms word"], "soft_skills": [], "languages_combined": [{"language": "cantonese", "language_level": ["good command"]}, {"language": "english", "language_level": ["good command"]}]}, "experience_required": {"duration": ["1-2 years"], "field": ["purchasing"]}}, {"job_id": "100003009053911", "location_code": "hk", "company": "Strive Medical Services Limited", "job_title": "\u897f\u91ab\u5c08\u79d1\u8a3a\u6240\u52a9\u8b77", "description": "\n\u8077\u8cac :\u8ca0\u8cac\u767b\u8a18, \u5354\u52a9\u91ab\u751f\u8a3a\u75c7, \u914d\u85e5, \u6e05\u6f54\u53ca\u6d88\u6bd2\u624b\u8853\u5100\u5668, \u89e3\u7b54\u75c5\u4eba\u67e5\u8a62, \u5354\u52a9\u8a3a\u6240\u65e5\u5e38\u904b\u4f5c\n\n\u8cc7\u6b77 :\u4e2d\u4e94\u7a0b\u5ea6; 1\u5e74\u7d93\u9a57; \u826f\u597d\u7cb5\u8a9e; \u4e00\u822c\u666e\u901a\u8a71; \u4e00\u822c\u82f1\u8a9e; \u61c2\u8b80\u5beb\u4e2d\u6587; \u61c2\u8b80\u5beb\u82f1\u6587\n\n\u5f85\u9047 :\u6bcf\u6708$18,000 - $20,000, \u6709\u8d85\u6642\u5de5\u4f5c\u88dc\u5047, \u96d9\u7ce7, \u9280\u884c\u5047\u671f, \u82b1\u7d05, \u54e1\u5de5\u8cfc\u7269\u512a\u60e0, \u5728\u8077\u57f9\u8a13 \u53ca\u5e74\u7d42\u734e\u91d1, \u661f\u671f\u4e00,\u56db,\u4e94,\u516d: \u4e0a\u53489\u6642\u81f3\u4e0b\u53487\u6642,\u4e09:\u4e0a\u53489\u6642\u81f3\u4e0b\u53481\u6642,\u53ca\u65e5:\u4e0a\u53489\u6642\u534a\u81f3\u4e0b\u53486\u6642\u534a,\u6bcf\u9031\u5de5\u4f5c5\u5929\u534a,\u6bcf\u5929\u5de5\u4f5c9\u5c0f\u6642\n\n\u7533\u8acb\u9808\u77e5 :\u6c42\u8077\u8005\u53ef\u96fb\u90f5(Apply Now)\u5c65\u6b77\u8868\u7d66\u884c\u5065\u91ab\u7642\u670d\u52d9\u6709\u9650\u516c\u53f8\u3002\u5982\u8981\u7d22\u53d6\u6536\u96c6\u500b\u4eba\u8cc7\u6599\u8072\u660e, \u8acb\u8207\u9673\u5973\u58eb(Email)\u806f\u7d61\u3002\n\n", "employment_types": ["Full Time"], "selling_points": [], "locations": ["Central"], "categories": ["Medical Services", "Nursing", "Others", "Public / Civil", "Others"], "post_time": "2022-01-17T07:44:58Z", "salary": {"currency": null, "max": null, "min": null, "period": "monthly", "term": null}, "salary_visible": false, "title_keywords": [], "responsibilities": [], "requirements": {"degrees": [], "majors": [], "languages": [], "language_level": [], "hard_skills": [], "soft_skills": [], "languages_combined": []}, "experience_required": {"duration": [], "field": []}}, {"job_id": "100003009053467", "location_code": "hk", "company": "The Wing Fat Printing (Hong Kong) Limited", "job_title": "Page Make-up Worker", "description": "\nResponsibilities:\n\u8ca0\u8cac\u88fd\u4f5c\u6392\u7248\u3001\u8a2d\u8a08 (\u5177\u5370\u5237\u88fd\u4f5c\u76f8\u95dc\u5de5\u4f5c\u7d93\u9a57,\u5177\u8a2d\u8a08\u5c08\u696d\u7d93\u9a57\u512a\u5148)\nRequirements :\nPost-secondary (Diploma/Certificate);\n1 Year(s) Experience Required; Fluent Cantonese ;\n\u2022 Fair Putonghua ; Able to read & write Chinese ;\n\u2022 Able to read & write simple English ;\n\u2022 \u719f\u7df4\u64cd\u4f5cAI\u3001PS\u3001PDF\u3001InDesign\u7b49\u5716\u5f62\u88fd\u4f5c\u6392\u7248\u8edf\u4ef6,\u719f\u6089\u6d77\u5fb7\u5821CTP\u88fd\u7248\u3001\u51fa\u7248\u7cfb\u7d71\u53ca\u64cd\u4f5c\n\n", "employment_types": ["Full Time"], "selling_points": [], "locations": ["Wong Tai Sin Area"], "categories": ["Public / Civil", "Social Services - Community / Non-profit Organization", "Others"], "post_time": "2022-01-17T07:01:18Z", "salary": {"currency": null, "max": null, "min": null, "period": "monthly", "term": null}, "salary_visible": false, "title_keywords": [], "responsibilities": [], "requirements": {"degrees": ["certificate", "diploma"], "majors": [], "languages": ["cantonese", "putonghua", "english", "chinese"], "language_level": ["fluent"], "hard_skills": ["simple"], "soft_skills": [], "languages_combined": [{"language": "cantonese", "language_level": ["fluent"]}, {"language": "putonghua", "language_level": []}, {"language": "english", "language_level": []}, {"language": "chinese", "language_level": []}]}, "experience_required": {"duration": [], "field": []}}, {"job_id": "100003009051901", "location_code": "hk", "company": "Senior Citizen Home Safety Association", "job_title": "Assistant Manager, Workshop & Training", "description": "Responsibilities:\n\nSupervise a small team\nDevelop and arrange different in-house training programs/workshops for our users and external participants in according to their needs\nLiaise with various stakeholders, such as private or public companies, schools, tutors, and vendors\nManage active aging services and carer support services, reach out target service recipients in the community through diversified trainings and programs\nPrepare reports, budget, operation plans and analysis for services development\n\nQualifications:\n\nMore than 5yrs experience with at least 2 years in supervisory level\nHigher Diploma / Associate degree holder or above in Social Work or related disciplines\nConduct training experience and/or with medical background is in advantage\nPrevious working experience in NGO setting is an asset but not a must\nWell organized, active, good interpersonal skills and manner\nGood command of written & spoken English and Chinese\n\nInterested parties please send your full CV with expected salary, date available and contact number via clicking \"Apply Now\"\u00a0(please state the position applied)\n\nInformation provided will only be used for the purpose of recruitment and selection within the Association and treated in strictly confidential. Only short-listed candidates will be contacted.", "employment_types": ["Full Time", "Permanent"], "selling_points": [], "locations": ["Kowloon City Area"], "categories": ["Admin & HR", "Training & Development", "Public / Civil", "Social Services - Community / Non-profit Organization", "Others"], "post_time": "2022-01-17T01:28:54Z", "salary": {"currency": null, "max": null, "min": null, "period": "monthly", "term": null}, "salary_visible": false, "title_keywords": ["assistant manager,"], "responsibilities": ["prepare reports", "analysis", "support services", "budget", "develop", "liaise with", "plans"], "requirements": {"degrees": ["associate degree", "diploma"], "majors": ["social work", "related disciplines"], "languages": ["english", "chinese"], "language_level": ["good command"], "hard_skills": ["small", "workshops", "analysis"], "soft_skills": ["active", "well organized", "interpersonal skills"], "languages_combined": [{"language": "english", "language_level": ["good command"]}, {"language": "chinese", "language_level": ["good command"]}]}, "experience_required": {"duration": ["at least 2 years"], "field": ["supervisory level", "training", "medical"]}}, {"job_id": "100003009053560", "location_code": "hk", "company": "Hong Kong Community Network Limited", "job_title": "\u9805\u76ee\u5e79\u4e8b", "description": "\n\u8077\u8cac :\u8ca0\u8cac\u63a8\u884c\u5404\u9805\u5c0f\u7d44\u3001\u670d\u52d9\u53ca\u6d3b\u52d5\n\n\u8cc7\u6b77 :\u5c08\u4e0a\u6559\u80b2\uff1a\u6587\u6191/\u8b49\u66f8; 1\u5e74\u7d93\u9a57; \u826f\u597d\u7cb5\u8a9e; \u4e00\u822c\u666e\u901a\u8a71; \u4e00\u822c\u82f1\u8a9e; \u61c2\u8b80\u5beb\u4e2d\u6587; \u61c2\u8b80\u5beb\u82f1\u6587; \u5177\u5ba3\u50b3\u6216\u7c4c\u5283\u77ed\u671f\u5e02\u96c6/\u5c55\u89bd\u6d3b\u52d5\u7d93\u9a57\u512a\u5148\n\n\u5f85\u9047 :\u6bcf\u6708$17,000 - $19,000, \u661f\u671f\u4e00\u81f3\u516d: \u4e0a\u534810\u6642\u81f3\u4e0b\u53486\u6642, \u6bcf\u9031\u5de5\u4f5c5\u5929\u81f36\u5929, \u6bcf\u5929\u5de5\u4f5c 8 \u5c0f\u6642\n\n\u7533\u8acb\u9808\u77e5 :\u6c42\u8077\u8005\u53ef\u96fb\u90f5(Apply Now)\u5c65\u6b77\u8868\u7d66\u9999\u6e2f\u793e\u5340\u7db2\u7d61\u6709\u9650\u516c\u53f8\u3002\u5982\u8981\u7d22\u53d6\u6536\u96c6\u500b\u4eba\u8cc7\u6599\u8072\u660e, \u8acb\u8207\u66fe\u5148\u751f(Email)\u806f\u7d61\u3002\n\n", "employment_types": ["Full Time"], "selling_points": [], "locations": ["Shatin Area"], "categories": ["Public / Civil", "Social Services - Community / Non-profit Organization", "Others", "Others", "Others"], "post_time": "2022-01-17T07:09:50Z", "salary": {"currency": null, "max": null, "min": null, "period": "monthly", "term": null}, "salary_visible": false, "title_keywords": [], "responsibilities": [], "requirements": {"degrees": [], "majors": [], "languages": [], "language_level": [], "hard_skills": [], "soft_skills": [], "languages_combined": []}, "experience_required": {"duration": [], "field": []}}, {"job_id": "100003009049662", "location_code": "hk", "company": "New Life Psychiatric Rehabilitation Association", "job_title": "Executive Officer (Ref: SES \u2013 EO)", "description": "Responsibilities:\n\nTo prepare all kinds of documents including proposals, reports, memos, financial documents and analysis, etc.;\nTo update and compile various data and statistics;\nTo be responsible for logistic management of service projects and to ensure smooth operation to meet contract requirements and quality standards;\nTo liaise with government departments or organizations on matters relating to service, contracts and job orders;\nTo liaise and coordinate with internal and external parties;\nTo be responsible for the office management and administrative duties of the unit; and\nTo perform other duties as required by the supervisor.\n\nRequirements:\n\nDegree holder with 3 years or above experience in administration;\nKnowledge and experience in ISO9001, ISO22000 or Employees Retraining Scheme is an advantage;\nHighly resourceful team player with excellent interpersonal and communication skills;\nProactive, organized and be able to juggle multiple projects;\nResponsible, detailed-minded with a \u201ccan-do\" attitude; and\nGood command of spoken and written English and Chinese.\n\nApplicants are invited to forward a cover letter and a resume to the Human Resources Department by post at New Life Psychiatric Rehabilitation Association, 332 Nam Cheong Street, Kowloon, or by fax at 3552 5398, or by clicking \"Apply Now\".\n\nPersonal data provided by applicants will strictly be used for recruitment purpose.\u00a0\nNew Life Psychiatric Rehabilitation Association is an equal opportunity employer.\nProspective employees are requested to undergo Sexual Conviction Record Check.", "employment_types": ["Full Time"], "selling_points": ["To assist in service project administration", "Employees Retraining Scheme", "ISO9001 & ISO22000"], "locations": ["Wong Tai Sin Area"], "categories": ["Admin & HR", "Clerical / Admin Staff", "Public / Civil", "Social Services - Community / Non-profit Organization", "Others"], "post_time": "2022-01-14T09:02:05Z", "salary": {"currency": null, "max": null, "min": null, "period": "monthly", "term": null}, "salary_visible": false, "title_keywords": ["executive officer"], "responsibilities": ["liaise", "management", "perform other duties", "data", "contracts", "analysis", "internal and external parties", "quality", "coordinate with", "reports", "administrative duties", "liaise with"], "requirements": {"degrees": ["degree holder"], "majors": [], "languages": ["english", "chinese"], "language_level": ["good command"], "hard_skills": ["scheme"], "soft_skills": ["communication skills", "organized", "resourceful", "responsible", "can-do", "team player", "proactive", "interpersonal", "detailed"], "languages_combined": [{"language": "english", "language_level": ["good command"]}, {"language": "chinese", "language_level": ["good command"]}]}, "experience_required": {"duration": ["3 years"], "field": ["administration"]}}, {"job_id": "100003009049683", "location_code": "hk", "company": "Essence Technology Limited", "job_title": "\u52a9\u7406\u5c4b\u5b87\u8a2d\u5099\u5de5\u7a0b\u5e2b", "description": "\n\u8077\u8cac :\u5354\u52a9\u4e0a\u53f8\u6e96\u5099\u5de5\u7a0b\u6587\u4ef6, \u8ddf\u9032\u5de5\u7a0b\u9032\u5ea6, \u8207\u5ba2\u6236\u53ca\u5206\u5224\u5546\u6e9d\u901a\u806f\u7d61.\n\n\u8cc7\u6b77 :\u4e2d\u4e03\u7a0b\u5ea6; 2\u5e74\u7d93\u9a57; \u826f\u597d\u7cb5\u8a9e; \u826f\u597d\u82f1\u8a9e; \u61c2\u8b80\u5beb\u4e2d\u6587; \u61c2\u8b80\u5beb\u82f1\u6587; \u61c2Microsoft Office; \u61c2MS Outlook; \u61c2AutoCAD; \u5177\u6c34\u5589\u6216\u6d88\u9632\u51b7\u6c23\u5de5\u7a0b\u516c\u53f8\u7d93\u9a57\u512a\u5148\n\n\u5f85\u9047 :\u6bcf\u6708$15,000 - $17,000, \u6709\u9280\u884c\u5047\u671f, \u734e\u52f5\u6027\u82b1\u7d05, \u6bcf\u6708\u52e4\u5de5\u734e\u91d1$500 \u53ca\u6bcf\u6708\u624b\u63d0\u96fb\u8a71\u6d25\u8cbc$300, \u661f\u671f\u4e00\u81f3\u4e94: \u4e0a\u53489\u6642\u81f3\u4e0b\u53486\u6642\u53ca\u661f\u671f\u516d: \u4e0a\u53489\u6642\u81f3\u4e0b\u53481\u6642, \u6bcf\u9031\u5de5\u4f5c5\u5929\u534a, \u6bcf\u5929\u5de5\u4f5c 8 \u5c0f\u6642\n\n\u7533\u8acb\u9808\u77e5 :\u6c42\u8077\u8005\u53ef\u96fb\u90f5(Apply Now)\u5c65\u6b77\u8868\u7d66\u6021\u4fe1\u6c34\u5229(\u79d1\u6280)\u6709\u9650\u516c\u53f8\u3002\u5982\u8981\u7d22\u53d6\u6536\u96c6\u500b\u4eba\u8cc7\u6599\u8072\u660e, \u8acb\u8207\u4f59\u5c0f\u59d0(Email)\u806f\u7d61\u3002\n\n", "employment_types": ["Full Time"], "selling_points": [], "locations": ["Not Specified"], "categories": ["Admin & HR", "Administration / Operation Manager", "Others", "Junior Executive", "Public / Civil", "Others"], "post_time": "2022-01-14T09:04:54Z", "salary": {"currency": null, "max": null, "min": null, "period": "monthly", "term": null}, "salary_visible": false, "title_keywords": [], "responsibilities": [], "requirements": {"degrees": [], "majors": [], "languages": [], "language_level": [], "hard_skills": ["outlook"], "soft_skills": [], "languages_combined": []}, "experience_required": {"duration": [], "field": []}}, {"job_id": "100003009052789", "location_code": "hk", "company": "Hong Kong Sheng Kung Hui Welfare Council Limited", "job_title": "\u793e\u6703\u5de5\u4f5c\u54e1 Social Worker", "description": "\u8cc7\u6b77\ufe30\n\n\u6301\u8a8d\u53ef\u793e\u6703\u5de5\u4f5c\u5b78\u4f4d\u6216\u540c\u7b49\u5b78\u6b77\uff0c\u5fc5\u9808\u70ba\u8a3b\u518a\u793e\u5de5\n\u7372\u4e2d\u5b78\u6703\u8003\u4e2d\u6587\u53ca\u82f1\u6587(\u8ab2\u7a0b\u4e59)\u5408\u683c\u6216\u4e2d\u5b78\u6587\u6191\u8003\u8a66\u540c\u7b49\u7b49\u7d1a\n\u51775\u5e74\u76f8\u95dc\u5de5\u4f5c\u7d93\u9a57\n\n\u8077\u8cac\ufe30\n\n\u8ca0\u8cac\u63d0\u4f9b\u54a8\u8a62\u53ca\u8207\u793e\u4ea4\u5fc3\u7406\u76f8\u95dc\u4e4b\u652f\u63f4\u670d\u52d9\n\u5efa\u7acb\u5730\u5340\u5354\u8abf\u7db2\u7d61\uff0c\u63a8\u884c\u53ca\u63a8\u5ee3\u300c\u5730\u5340\u70ba\u672c\u300d\u4e4b\u57fa\u5c64\u91ab\u7642\u670d\u52d9\n\u63a8\u52d5\u793e\u5340\u53c3\u8207\uff0c\u7ba1\u7406\u3001\u7d71\u7c4c\u53ca\u5e36\u9818\u5404\u985e\u8207\u5065\u5eb7\u670d\u52d9\u76f8\u95dc\u4e4b\u5c0f\u7d44\u3001\u6d3b\u52d5\u53ca\u8a08\u5283\u7b49\n\n\n\u6b64\u8077\u4f4d\u5c6c\u300c\u9805\u76ee\u70ba\u672c\u300d(project based)\u6027\u8cea\u3002\n\n\u6709\u610f\u7533\u8acb\u4e0a\u8ff0\u8077\u4f4d\u8005\u8acb\u5177\u51fd\u4e26\u9644\u8a73\u7d30\u5c65\u6b77\uff0c\u73fe\u6642\u85aa\u916c\u53ca\u671f\u671b\u85aa\u916c\u7b49\u8cc7\u6599\uff0c\u5bc4\u9999\u6e2f\u7b72\u7b95\u7063\u8208\u6c11\u885768\u865f\u6d77\u5929\u5ee3\u58345\u6a13 -\u00a0\u9999\u6e2f\u8056\u516c\u6703\u798f\u5229\u5354\u6703\u6709\u9650\u516c\u53f8\u4eba\u529b\u8cc7\u6e90\u90e8\u6536\u6216\u6309\"Apply Now\"\uff0c\u4fe1\u5c01\u53ca\u96fb\u90f5\u8acb\u8a3b\u660e\u7533\u8acb\u7de8\u865f\u3002\u4e00\u5207\u7533\u8acb\u8cc7\u6599\u7d55\u5c0d\u4fdd\u5bc6\u53ca\u53ea\u7528\u4f5c\u62db\u8058\u6709\u95dc\u8077\u4f4d\u3002\u5982\u7533\u8acb\u8005\u5728\u622a\u6b62\u65e5\u671f\u5f8c\u516b\u661f\u671f\u5167\u4ecd\u672a\u7372\u96fb\u8a71\u7d04\u898b\u8005\uff0c\u5176\u7533\u8acb\u53ef\u4f5c\u843d\u9078\u8ad6\uff0c\u6055\u4e0d\u53e6\u51fd\u901a\u77e5\uff0c\u672c\u798f\u5229\u5354\u6703\u5c07\u4fdd\u5b58\u7533\u8acb\u6587\u4ef6\u4e0d\u8d85\u904e\u516d\u500b\u6708\u3002", "employment_types": ["Full Time"], "selling_points": [], "locations": ["Wong Tai Sin Area"], "categories": ["Medical Services", "Others", "Public / Civil", "Social Services - Community / Non-profit Organization", "Others"], "post_time": "2022-01-17T04:04:45Z", "salary": {"currency": null, "max": null, "min": null, "period": "monthly", "term": null}, "salary_visible": false, "title_keywords": ["social worker"], "responsibilities": [], "requirements": {"degrees": [], "majors": [], "languages": [], "language_level": [], "hard_skills": [], "soft_skills": [], "languages_combined": []}, "experience_required": {"duration": [], "field": []}}, {"job_id": "100003009048556", "location_code": "hk", "company": "Plus 8 Consulting Limited", "job_title": "\u52a9\u7406\u5efa\u7bc9\u5e2b", "description": "\n\u8077\u8cac :\u69cb\u601d\u5efa\u7bc9\u8a2d\u8a08\u4e26\u4f5c\u51fa\u63d0\u6848\uff0c\u628a\u63e1\u570b\u5167\u5efa\u7bc9\u8a2d\u8a08\u884c\u696d\u6d41\u884c\u8da8\u52e2\uff0c\u70ba\u5ba2\u6236\u63d0\u4f9b\u5c08\u696d\u610f\u898b\uff0c\u91dd\u5c0d\u6027\u70ba\u570b\u5167\u5ba2\u6236\u9032\u884c\u65b9\u6848\u8a2d\u8a08\n\n\u8cc7\u6b77 :\u5c08\u4e0a\u6559\u80b2\uff1a\u5b78\u58eb\u5b78\u4f4d; 1\u5e74\u7d93\u9a57; \u4e00\u822c\u7cb5\u8a9e; \u826f\u597d\u666e\u901a\u8a71; \u826f\u597d\u82f1\u8a9e; \u61c2\u8b80\u5beb\u4e2d\u6587; \u61c2\u8b80\u5beb\u82f1\u6587; \u61c2SketchUp; \u61c2Microsoft Office; \u61c2AutoCAD; \u6301\u6709\u5efa\u7bc9\u8a2d\u8a08/\u57ce\u5e02\u8a2d\u8a08\u5b78\u58eb\u5b78\u6b77; \u61c2Rhino, Adobe Suite\n\n\u5f85\u9047 :\u6bcf\u6708$15,000 - $25,000 (\u8996\u4e4e\u5b78\u6b77\u53ca\u7d93\u9a57\u800c\u5b9a), \u6709\u5e74\u504712\u5929, \u661f\u671f\u4e00\u81f3\u4e94: \u4e0a\u53489\u6642\u534a\u81f3\u4e0b\u53486\u6642\u534a, \u6bcf\u9031\u5de5\u4f5c5\u5929, \u6bcf\u5929\u5de5\u4f5c 8 \u5c0f\u6642\n\n\u7533\u8acb\u9808\u77e5 :\u6c42\u8077\u8005\u53ef\u96fb\u90f5(Apply Now)\u5c65\u6b77\u8868\u7d66\u7e31\u6a6b\u884c\u54a8\u8a62\u9867\u554f\u6709\u9650\u516c\u53f8\u3002\u5982\u8981\u7d22\u53d6\u6536\u96c6\u500b\u4eba\u8cc7\u6599\u8072\u660e, \u8acb\u8207\u5f35\u5c0f\u59d0(Email)\u806f\u7d61\u3002\n\n", "employment_types": ["Full Time"], "selling_points": [], "locations": ["Wong Tai Sin Area"], "categories": ["Admin & HR", "Administration / Operation Manager", "Others", "Junior Executive", "Public / Civil", "Others"], "post_time": "2022-01-14T06:47:42Z", "salary": {"currency": null, "max": null, "min": null, "period": "monthly", "term": null}, "salary_visible": false, "title_keywords": [], "responsibilities": [], "requirements": {"degrees": [], "majors": [], "languages": [], "language_level": [], "hard_skills": ["adobe"], "soft_skills": [], "languages_combined": []}, "experience_required": {"duration": [], "field": []}}, {"job_id": "100003009046369", "location_code": "hk", "company": "", "job_title": "Company Driver / Family Driver", "description": "Responsibilities:\n\n\n\u00a0\u00a0\u00a0\u00a0\u00a0\u00a0\u00a0\u00a0 Driving duties for Executive Directors and families;\n\u00a0\u00a0\u00a0\u00a0\u00a0\u00a0\u00a0\u00a0 Follow up on car maintenance and ensure safety and cleanliness of the car;\n\u00a0\u00a0\u00a0\u00a0\u00a0\u00a0\u00a0\u00a0 Follow up on HK car licenses application / renewal;\n\u00a0\u00a0\u00a0\u00a0\u00a0\u00a0\u00a0\u00a0 Working hours: 7 am to 7 pm, 6 days a week\n\nRequirements:\n\n\n\nAt\u00a0least 5-8\u00a0years driving experience in serving directors / guests\nFamiliar with traffic conditions, regulations and roads in HK\nWilling to work overtime and on holidays;\nStrong sense of road safety and positive driving records;\nResponsible, punctual, polite and tidy\n\nBenefits:\n\nAttractive salary package with OT allowance, meal allowance, mobile allowance\nMedical Insurance, Dental Insurance, Life Insurance\nPerformance bonus\n\nIf you have interest for this position, you can contact us by 31966253 for more company details.", "employment_types": ["Full Time", "Permanent"], "selling_points": ["At least 5 years driving experience", "Positive driving records", "Immediate available is highly preferred"], "locations": ["Central"], "categories": ["Admin & HR", "Others", "Transportation & Logistics", "Private Transportation", "Public / Civil", "Others"], "post_time": "2022-01-13T10:46:05Z", "salary": {"currency": null, "max": null, "min": null, "period": "monthly", "term": null}, "salary_visible": false, "title_keywords": ["driver"], "responsibilities": ["maintenance"], "requirements": {"degrees": [], "majors": [], "languages": [], "language_level": [], "hard_skills": [], "soft_skills": ["work overtime", "polite", "positive", "responsible"], "languages_combined": []}, "experience_required": {"duration": ["at least 5-8 years"], "field": []}}, {"job_id": "100003009049826", "location_code": "hk", "company": "Benny Kong & Tsai \u6c5f\u70b3\u6ed4\u5f8b\u5e2b\u4e8b\u52d9\u6240", "job_title": "\u53f8\u6a5f\u517c\u8fa6\u516c\u5ba4\u52a9\u7406", "description": "\n\u8077\u8cac :\u8ca0\u8cac\u53f8\u6a5f\u53ca\u8fa6\u516c\u5ba4\u52a9\u7406\u5de5\u4f5c; \u65bc\u5927\u57d4\u53d6\u8eca\n\n\u8cc7\u6b77 :\u4e2d\u4e03\u7a0b\u5ea6; 3\u5e74\u7d93\u9a57; \u826f\u597d\u7cb5\u8a9e; \u826f\u597d\u666e\u901a\u8a71; \u826f\u597d\u82f1\u8a9e; \u61c2\u8b80\u5beb\u4e2d\u6587; \u61c2\u8b80\u5beb\u82f1\u6587; \u6301\u6709\u79c1\u5bb6\u8eca\u99d5\u99db\u57f7\u7167\n\n\u5f85\u9047 :\u6bcf\u6708$19,000, \u6709\u9280\u884c\u5047\u671f, \u661f\u671f\u4e00\u81f3\u4e94: \u4e0a\u53488\u6642\u534a\u81f3\u4e0b\u53488\u6642\u534a, \u6bcf\u9031\u5de5\u4f5c5\u5929\n\n\u7533\u8acb\u9808\u77e5 :\u6c42\u8077\u8005\u53ef\u96fb\u90f5(Apply Now)\u5c65\u6b77\u8868\u7d66\u6c5f\u70b3\u6ed4\u5f8b\u5e2b\u4e8b\u52d9\u6240\u3002\u5982\u8981\u7d22\u53d6\u6536\u96c6\u500b\u4eba\u8cc7\u6599\u8072\u660e, \u8acb\u8207\u5340 \u5c0f\u59d0(Email)\u806f\u7d61\u3002\n\n", "employment_types": ["Full Time"], "selling_points": [], "locations": ["Tai Po Area"], "categories": ["Admin & HR", "Administration / Operation Manager", "Others", "Junior Executive", "Public / Civil", "Others"], "post_time": "2022-01-14T09:17:42Z", "salary": {"currency": null, "max": null, "min": null, "period": "monthly", "term": null}, "salary_visible": false, "title_keywords": [], "responsibilities": [], "requirements": {"degrees": [], "majors": [], "languages": [], "language_level": [], "hard_skills": [], "soft_skills": [], "languages_combined": []}, "experience_required": {"duration": [], "field": []}}, {"job_id": "100003009051399", "location_code": "hk", "company": "Insurance Authority", "job_title": "Part-time Consultant in Health Insurance", "description": "Reporting to the Executive Director - Non-life Business, the incumbent will assume the following:\n\nKey Responsibilities\n\nOffer subject matter expertise support as well as training on health insurance to case officers in the prudential supervision of health insurers\nProvide insights on key market topics, emerging issues and future trends in the changing health insurance environment\nUndertake analysis of health insurance related topics and provide such other relevant support and services to the IA as may be required by the Authority from time to time\n\nRequirements\n\nGood knowledge of the health insurance market in Hong Kong, the competitive environment as well as the value chain in the healthcare segment in Hong Kong market\nSolid understanding of the key value drivers and performance metrics in health insurance\nRelevant professional knowledge in health insurance products, pricing, underwriting governance, claims and management of network of medical service providers\nExperience in health insurance product review, underwriting and claims audit and internal peer review\n\nRemark: This is a purposeful role and is ideal for newly retired health insurance professional seeking to contribute to the wellbeing and professional development of the Hong Kong health insurance market.\n\nRemuneration Package\nA competitive remuneration package commensurate with the successful candidate\u2019s experience and qualifications on a 1-year contract will be offered.\n\nApplication\nReview of the applications will start as soon as possible and continue until the post is filled. Interested applicants may send a letter of application quoting the reference number in the heading, together with a full resume stating current and expected salaries by clicking \"Apply Now\".\n\nThe Insurance Authority is an equal opportunities employer. Applicants not invited for an interview within 2 months from the submission date may assume their applications unsuccessful. Applications may be considered for other suitable positions within IA. All applications will be handled in strict confidence and the information collected will only be used for recruitment purposes. All information on non-shortlisted applicants will be destroyed after 6 months from the submission of their applications.\n", "employment_types": ["Part Time"], "selling_points": [], "locations": ["Southern Area"], "categories": ["Insurance", "Others", "Public / Civil", "Others"], "post_time": "2022-01-15T14:24:26Z", "salary": {"currency": null, "max": null, "min": null, "period": "monthly", "term": null}, "salary_visible": false, "title_keywords": ["consultant"], "responsibilities": ["provide insights", "analysis", "insurance"], "requirements": {"degrees": [], "majors": [], "languages": [], "language_level": [], "hard_skills": [], "soft_skills": ["confidence", "ideal", "purposeful"], "languages_combined": []}, "experience_required": {"duration": ["1-year"], "field": ["underwriting", "insurance", "audit"]}}, {"job_id": "100003009044077", "location_code": "hk", "company": "The Vine Church Limited", "job_title": "Justice & Missions Associate", "description": "This is a full-time position with the Justice & Missions team at The Vine and reports to the Justice & Missions Pastor. The candidate will work in the team responsible for developing and leading initiatives that engage and equip The Vine in its justice advocacy and Missions programs.\n\nThis position requires the ability to operate in strategy development, relationship management, event management, and administrative responsibilities. The successful candidate will be able to take initiative and responsibility for key projects and manage ongoing responsibilities.\n\nJob Description\n\nThe primary role and responsibilities of the Justice & Missions Associate are as follows:\n\nContribute to the development of a strategy that furthers The Vine\u2019s justice profile, advocacy efforts, social justice footprint, and theological framework that will be used across Vine ministries and our local community;\nDesign initiatives that build awareness and mobilise the congregation to practically engage with social and spiritual issues that align with The Vine\u2019s area of focus and the work of our partners;\nProduce the flagship Justice Conference Asia (JCA) and other justice-related events that reflect the vision, core values and standards of the Justice Conference;\nAssist Justice and Missions Pastor and JCA leadership team in developing strategies to expand the impact of The Justice Conference (TJC) in Asia;\nPeriodically assist Justice and Missions Pastor to research on justice topics facing Hong Kong;\nAssist in planning and organising mission events and oversee local and international missions\u2019 trips;\nDevelop and grow relationships with external stakeholders and partners (churches, NGOs, influencers);\nRecruit and build relationships with volunteers from The Vine;\nGeneral administration duties include leading meetings, capturing action steps, managing internal processes, and completing documentation and reporting.\n\nJob Requirement\n\nStrong sense of justice and a passion for social justice issues in Hong Kong and SE Asia;\nKnowledge across a range of social, economic, and spiritual developmental issues;\nA passion and desire to see every individual flourish spiritually, personally, socially, materially;\nPublic speaking experience would be beneficial;\nStrong organizational and administration skills, including effective time management;\nInternational experience and cross-cultural skills are preferred;\nGood command of English (written and spoken). Cantonese is highly desired.\n\nHow to apply\n\nInterested parties please send application with full CV with your current and expected salary by clicking \"Apply Now\".\n\nPersonal data provided by job applicants will be strictly used for recruitment purpose.", "employment_types": ["Full Time"], "selling_points": [], "locations": ["Wan Chai"], "categories": ["Admin & HR", "Clerical / Admin Staff", "Public / Civil", "Social Services - Community / Non-profit Organization", "Others"], "post_time": "2022-01-13T02:59:49Z", "salary": {"currency": null, "max": null, "min": null, "period": "monthly", "term": null}, "salary_visible": false, "title_keywords": ["associate"], "responsibilities": ["reporting", "developing", "design", "develop", "planning", "documentation", "administration"], "requirements": {"degrees": [], "majors": [], "languages": ["cantonese", "english"], "language_level": ["good command"], "hard_skills": [], "soft_skills": ["organizational", "administration skills", "time management", "passion for"], "languages_combined": [{"language": "cantonese", "language_level": []}, {"language": "english", "language_level": ["good command"]}]}, "experience_required": {"duration": [], "field": []}}, {"job_id": "100003009048966", "location_code": "hk", "company": "Yan Oi Tong Ltd", "job_title": "\u52a9\u7406\u670d\u52d9\u4e3b\u4efb (\u8077\u4f4d\u7de8\u865f:ITB&C/AIC1205/220114)", "description": "\u6301\u76f8\u95dc\u5b78\u58eb\u5b78\u4f4d\uff0c2\u5e74\u6216\u4ee5\u4e0a\u7ba1\u7406\u7d9c\u5408\u5bb6\u5c45\u670d\u52d9\u55ae\u4f4d\u7d93\u9a57\u512a\u5148\n\u5177\u7167\u9867\u9577\u8005\u7d93\u9a57\u53ca\u61c2\u5f97\u96fb\u8166\u6587\u66f8\u64cd\u4f5c\n\u5de5\u4f5c\u52e4\u596e\uff0c\u7d30\u5fc3\u6709\u8010\u6027\n\u7ba1\u7406\u7de8\u6392\u5bb6\u5c45\u7167\u9867\u670d\u52d9\u7684\u5de5\u4f5c\n\u7763\u5c0e\u524d\u7dda\u54e1\u5de5\n\u5354\u52a9\u4e2d\u5fc3\u90e8\u4efd\u884c\u653f\u5de5\u4f5c\n\u5c6f\u9580\u5340\u5de5\u4f5c\uff0c\u9700\u5047\u65e5\u8f2a\u503c(\u65e5\u9593\u5de5\u4f5c)\n\n\u6709\u610f\u8005\u8acb\u5c07\u5c65\u6b77\u3001\u8981\u6c42\u5f85\u9047\u3001\u53ef\u5230\u8077\u65e5\u671f\u53ca\u806f\u7d61\u96fb\u8a71\uff08\u5fc5\u9808\u8a3b\u660e\u8077\u4f4d\u7de8\u865f\uff09\u90f5\u5bc4\u5f80\u5c6f\u9580\u555f\u6c11\u5f9118\u865f\u4ec1\u611b\u5802\u8cfd\u99ac\u6703\u793e\u5340\u53ca\u9ad4\u80b2\u4e2d\u5fc37\u6a13\u4eba\u529b\u8cc7\u6e90\u90e8\u6536\u6216\u6309Apply Now\u61c9\u5fb5\u3002\n\n\n\n\u6709\u95dc\u5176\u4ed6\u8077\u4f4d\u7a7a\u7f3a\uff0c\u6b61\u8fce\u700f\u89bd\u672c\u5802\u7db2\u9801www.yot.org.hk\n\n*\u7533\u8acb\u4eba\u6240\u63d0\u4f9b\u7684\u8cc7\u6599\u5c07\u4e88\u4ee5\u4fdd\u5bc6\u53ca\u53ea\u4f5c\u62db\u8058\u6709\u95dc\u8077\u4f4d\u7528\u9014*", "employment_types": ["Full Time", "Contract"], "selling_points": ["\u6301\u76f8\u95dc\u5b78\u58eb\u5b78\u4f4d\uff0c2\u5e74\u6216\u4ee5\u4e0a\u7ba1\u7406\u7d9c\u5408\u5bb6\u5c45\u670d\u52d9\u55ae\u4f4d\u7d93\u9a57\u512a\u5148", "\u7ba1\u7406\u7de8\u6392\u5bb6\u5c45\u7167\u9867\u670d\u52d9\u7684\u5de5\u4f5c", "\u5c6f\u9580\u5340\u5de5\u4f5c\uff0c\u9700\u5047\u65e5\u8f2a\u503c(\u65e5\u9593\u5de5\u4f5c)"], "locations": ["Tuen Mun Area"], "categories": ["Admin & HR", "Clerical / Admin Staff", "Public / Civil", "Social Services - Community / Non-profit Organization", "Others"], "post_time": "2022-01-14T07:48:47Z", "salary": {"currency": null, "max": null, "min": null, "period": "monthly", "term": null}, "salary_visible": false, "title_keywords": [], "responsibilities": [], "requirements": {"degrees": [], "majors": [], "languages": [], "language_level": [], "hard_skills": [], "soft_skills": [], "languages_combined": []}, "experience_required": {"duration": [], "field": []}}, {"job_id": "100003009052167", "location_code": "hk", "company": "Haven of Hope Christian Service", "job_title": "\u52a9\u7406\u5fa9\u5eb7\u670d\u52d9\u54e1 (\u7de8\u865f : EHCCS/ARSW/JDB)", "description": "\u4e2d\u4e09\u6216\u4ee5\u4e0a\u7a0b\u5ea6\uff0c\u7121\u9808\u8f2a\u73ed\n\u5354\u52a9\u6cbb\u7642\u5e2b\u70ba\u9577\u8005\u9032\u884c\u5bb6\u5c45\u5fa9\u5eb7\u904b\u52d5(\u53d6\u9304\u5f8c\u6703\u6709\u9069\u7576\u57f9\u8a13)\uff1b\u53ca\u5354\u52a9\u9577\u8005\u5728\u4e2d\u5fc3\u9032\u884c\u5fa9\u5eb7\u6d3b\u52d5\n\u6301\u6709\u76f8\u95dc\u8077\u696d\u6cbb\u7642\u6216\u7269\u7406\u6cbb\u7642\u52a9\u7406\u8b49\u66f8\n\u6709\u611b\u5fc3\u3001\u6709\u8cac\u4efb\u611f\uff0c\u5177\u5099\u826f\u597d\u7684\u6e9d\u901a\u80fd\u529b\uff0c\u6027\u683c\u4e3b\u52d5\uff0c\u80fd\u7368\u7acb\u8655\u4e8b\n\u5de5\u4f5c\u5730\u9ede\uff1a\u6771\u4e5d\u9f8d\u3001\u5c07\u8ecd\u6fb3\u53ca\u897f\u8ca2\n\n\u6709\u610f\u8005\u8acb\u65bc\u4e8c\u96f6\u4e8c\u4e8c\u5e74\u4e8c\u6708\u4e94\u65e5\u524d\u89aa\u7e55\u5c65\u6b77\u53ca\u671f\u671b\u5f85\u9047\uff08\u8acb\u65bc\u4fe1\u5c01\u9762\u53ca\u4fe1\u5167\u8a3b\u660e\u7533\u8acb\u8077\u4f4d\u7de8\u865f\uff09\u5bc4\u65b0\u754c\u5c07\u8ecd\u6fb3\u9748\u5be6\u8def\u4e03\u865f\u57fa\u7763\u6559\u9748\u5be6\u5354\u6703\u4eba\u529b\u8cc7\u6e90\u90e8\u6536\uff0c\u6216\u96fb\u90f5\u81f3Apply Now\uff0c\u6216\u767c\u9001\u81f3Whatsapp\u865f\u78bc6507 8148\uff08\u6a19\u984c\u8acb\u8a3b\u660e\u8077\u4f4d\u7de8\u865f\uff09\u3002\u5982\u4e00\u500b\u6708\u5167\u672a\u7372\u901a\u77e5\u7d04\u898b\uff0c\u5247\u4f5c\u843d\u9078\u8ad6\u3002\n\n\u67e5\u8a62\u71b1\u7dda\uff1a2703 3227 (\u96fb\u8a71)\uff1b6507 8148(Whatsapp)\u3002\n\n\u6709\u95dc\u672c\u6703\u8a73\u60c5\uff0c\u8acb\u700f\u89bd\u7db2\u9801http://www.hohcs.org.hk\n\n(\u53ef\u80fd\u7372\u8058\u4eba\u58eb\uff08\u5982\u5f9e\u4e8b\u8207\u5152\u7ae5\u6216\u7cbe\u795e\u4e0a\u7121\u884c\u70ba\u80fd\u529b\u4eba\u58eb\u6709\u95dc\u5de5\u4f5c\u8077\u4f4d\uff09\u9808\u65bc\u5165\u8077\u524d\u9032\u884c\uff0f\u63d0\u4ea4\u6027\u7f6a\u884c\u5b9a\u7f6a\u7d00\u9304\u67e5\u6838\u3002\u7533\u8acb\u4eba\u6240\u63d0\u4f9b\u7684\u8cc7\u6599\u5c07\u4e88\u4fdd\u5bc6\u53ca\u4f5c\u62db\u8058\u6709\u95dc\u8077\u4f4d\u7528\u9014)\n\n\u672a\u7d93\u672c\u5354\u6703\u66f8\u9762\u540c\u610f\uff0c\u4ee5\u4e0a\u62db\u8058\u5ee3\u544a\u5168\u90e8\u6216\u90e8\u5206\u5167\u5bb9\u5747\u4e0d\u5f97\u8907\u88fd\u81f3\u5176\u4ed6\u62db\u8058\u7db2\u7ad9\u3002", "employment_types": ["Full Time"], "selling_points": [], "locations": ["Not Specified"], "categories": ["Medical Services", "Nursing", "Others", "Public / Civil", "Others"], "post_time": "2022-01-17T02:19:41Z", "salary": {"currency": null, "max": null, "min": null, "period": "monthly", "term": null}, "salary_visible": false, "title_keywords": [], "responsibilities": [], "requirements": {"degrees": [], "majors": [], "languages": [], "language_level": [], "hard_skills": [], "soft_skills": [], "languages_combined": []}, "experience_required": {"duration": [], "field": []}}, {"job_id": "100003009037452", "location_code": "hk", "company": "Legislative Council Secretariat", "job_title": "Clerical Assistant \u6587\u66f8\u4e8b\u52d9\u52a9\u7406", "description": "Main duties\nThe main duties of a Clerical Assistant include:\n(a) processing incoming documents;\n(b) undertaking Chinese and English word processing;\n(c) arranging filing;\n(d) receiving visitors;\n(e) handling telephone calls received through the enquiry hotline;\n(f)\u00a0 replacing outdated copies of laws and regulations; and\n(g) providing other clerical support.\n\nEntry requirements\nCandidates should:\n(a) preferably have completed Secondary 5, or equivalent;\n(b)\u00a0have obtained (i) Level 2 or above in Chinese Language and English Language in the Hong Kong Diploma of Secondary Education Examination, or equivalent; or (ii) Level 2/Grade E or above in Chinese Language and English Language (\u201cSyllabus B\u201d before 2007) in the Hong Kong Certificate of Education Examination, or equivalent;\n(c)\u00a0preferably have three years\u2019 relevant work experience;\n(d)\u00a0have attained an English word processing speed at 40 w.p.m. or above and Chinese word processing speed at 20 w.p.m. or above;\n(e)\u00a0have knowledge of common computer applications;\n(f)\u00a0 have good knowledge of written and spoken Chinese and English; and\n(g)\u00a0possess initiative, and be self-motivated and responsible.\u00a0\n\nThe Secretariat may devise further criteria to shortlist applicants. Shortlisted applicants may be required to attend a skill test consisting of a typing speed test and a document formatting test.\n\nRemuneration\nThe starting salary is $13,735 per month, increasing by nine annual increments to $24,070.\u00a0 There is also a monthly cash allowance for the rank of Clerical Assistant (the current rate is $310 per month).\u00a0 The successful candidate will be appointed on three-year agreement terms subject to renewal upon satisfactory completion of service, at which the appointee will be eligible for an end-of-agreement gratuity.\u00a0 The gratuity, when added to the employer\u2019s contribution to a Mandatory Provident Fund Scheme, is equal to 10% of the total basic salary drawn during the agreement period.\u00a0 Fringe benefits include paid leave as well as medical and dental benefits.\u00a0\n\nApplication\nApplications should be sent directly to Human Resources Office, Legislative Council Secretariat, Legislative Council Complex, 1 Legislative Council Road, Central, Hong Kong on or before 31 January 2022.Note\u00a0 The position applied for should be indicated on the envelope, and an email address should also be provided in your application.\u00a0 Shortlisted applicants will be notified by email or by phone.\u00a0 All personal data provided will be treated in strict confidence.\u00a0 Applicants not invited for interview or skill test within eight weeks from the closing date may assume their applications unsuccessful.\n(A standard application form may be downloaded from the LegCo Website (http://www.legco.gov.hk))\n\nAs an Equal Opportunities Employer, The Legislative Council Commission is committed to ensuring that there is no discrimination in employment with the Secretariat.\u00a0 The post advertised is open to all applicants meeting the basic entry requirements irrespective of their disability, sex, marital status, pregnancy, age, family status, sexual orientation and race.\u00a0 For more information on our policy on employment of persons with disabilities, please visit the LegCo Website.\n\nNote Please note that the Secretariat has not authorized any employment agencies or third-party organizations to receive applications on behalf of the Secretariat.\u00a0\n\n\u4e3b\u8981\u8077\u8cac\u00a0\n\u6587\u66f8\u4e8b\u52d9\u52a9\u7406\u7684\u4e3b\u8981\u8077\u8cac\u5305\u62ec\uff1a\u00a0\n(a) \u8655\u7406\u4f86\u4ef6\uff1b\n(b) \u57f7\u884c\u4e2d\u82f1\u6587\u6587\u66f8\u8655\u7406\u5de5\u4f5c\uff1b\n(c) \u8655\u7406\u6587\u4ef6\u5b58\u6a94\uff1b\n(d) \u63a5\u5f85\u8a2a\u5ba2\uff1b\n(e) \u63a5\u807d\u67e5\u8a62\u71b1\u7dda\uff1b\n(f)\u00a0 \u66f4\u63db\u6cd5\u4f8b\u53ca\u898f\u4f8b\u65b0\u820a\u7248\u672c\uff1b\u53ca\n(g) \u4f5c\u51fa\u5176\u4ed6\u6587\u66f8\u4e8b\u52d9\u652f\u63f4\u3002\n\n\u5165\u8077\u689d\u4ef6\u00a0\n\u61c9\u5fb5\u8005\u61c9\uff1a\u00a0\n(a)\u00a0\u4fee\u7562\u4e2d\u4e94\u8f03\u4f73\uff0c\u6216\u5177\u5099\u540c\u7b49\u5b78\u6b77\uff1b\n(b) (i)\u5728\u9999\u6e2f\u4e2d\u5b78\u6587\u6191\u8003\u8a66\u4e2d\u570b\u8a9e\u6587\u79d1\u53ca\u82f1\u570b\u8a9e\u6587\u79d1\u53d6\u5f97\u7b2c2\u7b49\u7d1a\u6216\u4ee5\u4e0a\u6210\u7e3e\uff0c\u6216\u5177\u5099\u540c\u7b49\u5b78\u6b77\uff1b\u6216(ii)\u5728\u9999\u6e2f\u4e2d\u5b78\u6703\u8003\u4e2d\u570b\u8a9e\u6587\u79d1\u53ca\u82f1\u570b\u8a9e\u6587\u79d1\uff082007\u5e74\u524d\u7684\u201c\u8ab2\u7a0b\u4e59\u201d\uff09\u53d6\u5f97\u7b2c2\u7b49\u7d1a\uff08\u53732007\u5e74\u524d\u7684\u201cE\u7d1a\u201d\uff09\u6216\u4ee5\u4e0a\u6210\u7e3e\uff0c\u6216\u5177\u5099\u540c\u7b49\u5b78\u6b77\uff1b\n(c) \u5177\u50993\u5e74\u76f8\u95dc\u5de5\u4f5c\u7d93\u9a57\u8f03\u4f73\uff1b\n(d) \u82f1\u6587\u6587\u66f8\u8655\u7406\u901f\u5ea6\u9054\u6bcf\u5206\u941840\u5b57\u6216\u4ee5\u4e0a\u53ca\u4e2d\u6587\u6587\u66f8\u8655\u7406\u901f\u5ea6\u9054\u6bcf\u5206\u941820\u5b57\u6216\u4ee5\u4e0a\uff1b\n(e) \u5177\u5099\u4e00\u822c\u96fb\u8166\u61c9\u7528\u77e5\u8b58\uff1b\n(f)\u00a0 \u4e2d\u3001\u82f1\u6587\u8b1b\u5beb\u80fd\u529b\u826f\u597d\uff1b\u53ca\n(g) \u8655\u4e8b\u4e3b\u52d5\u7a4d\u6975\u53ca\u5177\u81ea\u767c\u6027\u548c\u8cac\u4efb\u611f\u3002\n\n\u79d8\u66f8\u8655\u53ef\u5236\u8a02\u9032\u4e00\u6b65\u7684\u6e96\u5247\uff0c\u4ee5\u9078\u51fa\u521d\u6b65\u5165\u9078\u7684\u7533\u8acb\u4eba\u3002\u521d\u6b65\u5165\u9078\u7684\u7533\u8acb\u4eba\u6216\u9808\u53c3\u52a0\u6280\u80fd\u6e2c\u8a66\uff0c\u5305\u62ec\u6253\u5b57\u901f\u5ea6\u6e2c\u8a66\u53ca\u7de8\u6392\u6587\u4ef6\u683c\u5f0f\u6e2c\u8a66\u3002\n\n\u85aa\u916c\u00a0\n\u5165\u8077\u85aa\u916c\u70ba\u6bcf\u670813,735\u5143\uff0c\u4e26\u63099\u500b\u6309\u5e74\u589e\u85aa\u984d\u589e\u81f324,070\u5143\uff0c\u53e6\u6709\u70ba\u6587\u66f8\u4e8b\u52d9\u52a9\u7406\u8077\u7d1a\u800c\u8a2d\u7684\u6bcf\u6708\u73fe\u91d1\u6d25\u8cbc(\u73fe\u6642\u7684\u6d25\u8cbc\u984d\u70ba\u6bcf\u6708310\u5143)\u3002\u6210\u529f\u53d7\u8058\u4eba\u58eb\u6703\u6309\u5408\u7d04\u689d\u6b3e\u53d7\u8058\uff0c\u70ba\u671f3\u5e74\uff0c\u5018\u5b8c\u6210\u670d\u52d9\u671f\u800c\u5de5\u4f5c\u8868\u73fe\u826f\u597d\uff0c\u53ef\u7372\u7e8c\u7d04\uff0c\u4e26\u6703\u7372\u5f97\u4e00\u7b46\u7d04\u6eff\u916c\u91d1\uff0c\u5176\u6b3e\u984d\u52a0\u4e0a\u50f1\u4e3b\u5728\u5f37\u5236\u6027\u516c\u7a4d\u91d1\u8a08\u5283\u4e0b\u6240\u4f5c\u7684\u4f9b\u6b3e\uff0c\u76f8\u7b49\u65bc\u5408\u7d04\u671f\u5167\u6240\u5f97\u5e95\u85aa\u7e3d\u984d\u768410%\u3002\u9644\u5e36\u798f\u5229\u5305\u62ec\u6709\u85aa\u5047\u671f\u3001\u91ab\u7642\u53ca\u7259\u79d1\u798f\u5229\u3002\n\n\u7533\u8acb\u00a0\n\u8acb\u65bc2022\u5e741\u670831\u65e5\u6216\u8a72\u65e5\u524d\uff0c\u5c07\u7533\u8acb\u76f4\u63a5\u5bc4\u9054\u9999\u6e2f\u4e2d\u5340\u7acb\u6cd5\u6703\u90531\u865f\u7acb\u6cd5\u6703\u7d9c\u5408\u5927\u6a13\u7acb\u6cd5\u6703\u79d8\u66f8\u8655\u4eba\u529b\u8cc7\u6e90\u7d44\u3002\u8a3b\u7533\u8acb\u4eba\u61c9\u5728\u4fe1\u5c01\u9762\u8a3b\u660e\u7533\u8acb\u8077\u4f4d\u7684\u540d\u7a31\uff0c\u4e26\u5728\u7533\u8acb\u6587\u4ef6\u4e2d\u63d0\u4f9b\u96fb\u90f5\u5730\u5740\u3002\u79d8\u66f8\u8655\u5c07\u4ee5\u96fb\u90f5\u6216\u96fb\u8a71\u65b9\u5f0f\u901a\u77e5\u521d\u6b65\u5165\u9078\u7684\u7533\u8acb\u4eba\u3002\u7533\u8acb\u4eba\u63d0\u4f9b\u7684\u6240\u6709\u500b\u4eba\u8cc7\u6599\u5747\u6703\u56b4\u52a0\u4fdd\u5bc6\u3002\u7533\u8acb\u4eba\u5982\u65bc\u622a\u6b62\u65e5\u671f\u5f8c8\u661f\u671f\u5167\u672a\u7372\u9080\u53c3\u52a0\u9762\u8a66\u6216\u6280\u80fd\u6e2c\u8a66\uff0c\u53ef\u7576\u4f5c\u5176\u7533\u8acb\u4e0d\u6210\u529f\u3002\n(\u6a19\u6e96\u7533\u8acb\u8868\u683c\u53ef\u65bc\u7acb\u6cd5\u6703\u7db2\u7ad9(http://www.legco.gov.hk)\u4e0b\u8f09)\n\n\u7acb\u6cd5\u6703\u884c\u653f\u7ba1\u7406\u59d4\u54e1\u6703\u70ba\u5e73\u7b49\u6a5f\u6703\u50f1\u4e3b\uff0c\u81f4\u529b\u78ba\u4fdd\u79d8\u66f8\u8655\u6c92\u6709\u5c31\u696d\u65b9\u9762\u7684\u6b67\u8996\u3002\u6240\u6709\u7b26\u5408\u57fa\u672c\u5165\u8077\u689d\u4ef6\u7684\u4eba\u58eb\uff0c\u4e0d\u8ad6\u5176\u6b98\u75be\u3001\u6027\u5225\u3001\u5a5a\u59fb\u72c0\u6cc1\u3001\u61f7\u5b55\u8207\u5426\u3001\u5e74\u9f61\u3001\u5bb6\u5ead\u5d17\u4f4d\u3001\u6027\u50be\u5411\u53ca\u7a2e\u65cf\uff0c\u5747\u53ef\u7533\u8acb\u6b64\u8077\u4f4d\u3002\u6709\u95dc\u62db\u8058\u6b98\u75be\u4eba\u58eb\u7684\u653f\u7b56\uff0c\u8acb\u700f\u89bd\u7acb\u6cd5\u6703\u7db2\u7ad9\u3002\n\n\u8a3b\u00a0 \u8acb\u6ce8\u610f\uff0c\u79d8\u66f8\u8655\u4e26\u7121\u6388\u6b0a\u4efb\u4f55\u8077\u696d\u4ecb\u7d39\u6240\u6216\u7b2c\u4e09\u65b9\u6a5f\u69cb\u4ee3\u8868\u672c\u8655\u63a5\u6536\u7533\u8acb\u3002", "employment_types": ["Full Time", "Contract"], "selling_points": [], "locations": ["Admiralty"], "categories": ["Admin & HR", "Clerical / Admin Staff", "Others", "Public / Civil", "Others"], "post_time": "2022-01-14T03:11:40Z", "salary": {"currency": null, "max": null, "min": null, "period": "monthly", "term": null}, "salary_visible": false, "title_keywords": ["clerical assistant"], "responsibilities": ["regulations", "replacing", "clerical support"], "requirements": {"degrees": ["certificate", "diploma", "secondary education"], "majors": [], "languages": ["english", "chinese"], "language_level": ["good"], "hard_skills": ["chinese word processing", "basic", "scheme", "word processing", "typing", "c"], "soft_skills": ["self-motivated", "initiative", "responsible"], "languages_combined": [{"language": "english", "language_level": ["good"]}, {"language": "chinese", "language_level": ["good"]}]}, "experience_required": {"duration": ["three years"], "field": []}}, {"job_id": "100003009045072", "location_code": "hk", "company": "Office of the Privacy Commissioner for Personal Data", "job_title": "Legal Counsel", "description": "***Applications via Apply Now will NOT be considered.\u00a0 Please follow the application procedures mentioned below***\n\nRequirements\n\na) A\u00a0good Bachelor\u2019s Degree from a recognised university in Hong Kong or a university in a common law jurisdiction;\nb)\u00a0A Level 2 result in the Use of English paper and a Level 2 result in the Use of Chinese paper in the Common Recruitment Examination, or preferably Grade \u201cB\u201d or above in Use of English in the Hong Kong Advanced Level Examination (HKALE), or Grade \u201c5*\u201d or above in English Language in the Hong Kong Diploma of Secondary Education Examination (HKDSE), or equivalent, or a minimum overall band score of 7.5 in the International English Language Testing System (IELTS) with the Writing Sub-test score not lower than 7; good command of written and spoken Chinese, preferably Grade \u201cB\u201d or above in Chinese Language in the Hong Kong Certificate of Education Examination (HKCEE), or Grade \u201c5*\u201d or above in HKDSE, or\u00a0 equivalent;\nc)\u00a0Solicitor or barrister admitted to practice in Hong Kong; and\nd)\u00a0A minimum of 5 years of post-qualification experience, of which at least 3 years are in criminal practice.\u00a0 Candidates with less experience may be considered for the post of Assistant Legal Counsel and a remuneration package commensurate with that position.\n\nExpectations\na)\u00a0A broadly based practising and advocacy experience, including that of prosecution, advising on the implementation of statutory functions and exercise of statutory powers by a law enforcement agency or regulatory authority;\nb)\u00a0Proven capability in advocacy in court and providing legal advice in respect of legislative and regulatory review / reform and legislative amendments;\nc)\u00a0\u00a0Strong analytical ability to make independent judgement;\nd)\u00a0\u00a0Positive, diligent and self-motivated with good inter-personal skills; and\ne)\u00a0\u00a0Excellent presentational skills in both written and oral English and Chinese.\nMajor Duties\na)\u00a0To handle criminal proceedings and prosecute offences (including appearing in court hearings) in respect of contraventions of the PD(P)O in Magistrates\u2019 Court;\nb)\u00a0\u00a0To provide advisory support on investigation and enforcement matters;\nc)\u00a0To liaise and work with external parties to assist with the conduct of criminal investigations and prosecutions;\nd)\u00a0To provide legal advice on proposed legislative amendments of the PD(P)O, the implementation and enforcement of the provisions of the PD(P)O; and\ne)\u00a0To vet and provide legal advice on responses to media enquiries, public enquiries and the handling of complaints and data breach incidents.\n\nRemuneration Package\nThe successful candidate will be rewarded with commensurate remuneration package with monthly salary ranging from $74,515 to $110,170. \u00a0He or she will be appointed on 2 years\u2019 contract terms. In addition to 5-day week, we provide annual leave, medical and dental insurance benefits, cash allowance and a gratuity on satisfactory completion of the contract which, when added to the employer\u2019s contribution to a Mandatory Provident Fund scheme, is up to 15% of the total basic salary for the contract period.\n***Applications via Apply Now will NOT be considered.\u00a0Please follow the application procedures mentioned below***\nPoints to Note\nClose of Applications:\n\n4 February 2022 (Friday)\nApplication Procedures:\n\nInterested candidates may apply in confidence by 1) providing a detailed resume, 2) completing the job application form\u00a0available on PCPD\u2019s website\u00a0(https://www.pcpd.org.hk/english/about_pcpd/career/career.html), and 3) providing a cover letter in English or Chinese, stating the candidate's suitability for the job, all of\u00a0which\u00a0should be sent to the Human Resources Section of the PCPD by email (please go to our website for the email address).\nApplications without all prescribed documents will not be considered.\nApplicants who do not hear from us within six weeks from the date of the close of applications should consider their applications unsuccessful.\u00a0 All applications will be treated in strict confidence.\u00a0 Personal data provided will be used for recruitment purpose only and in accordance with the Code of Practice on Human Resource Management issued by the PCPD, which can be downloaded from the PCPD's website.\u00a0 In accordance with our data retention policy, the personal data of unsuccessful candidates collected for this recruitment exercise will be kept for 12 months from its completion and thereafter the data will be destroyed.\nFor enquiries, please call Ms Wan at 3423 6657.\n\n\nThe PCPD is an Equal Opportunity Employer\nhttp://www.pcpd.org.hk/\u00a0 \u00a0", "employment_types": ["Full Time", "Contract"], "selling_points": ["Solicitor or barrister admitted to practice in HK", "Post-qualification experience in criminal practice", "Proven capability in advocacy in court"], "locations": ["Wan Chai"], "categories": ["Professional Services", "Legal & Compliance", "Public / Civil", "Others"], "post_time": "2022-01-13T08:46:01Z", "salary": {"currency": "HKD", "max": 119999, "min": 70000, "period": "monthly", "term": null}, "salary_visible": true, "title_keywords": ["legal counsel"], "responsibilities": ["liaise", "data", "external parties", "procedures", "implementation", "investigation", "insurance"], "requirements": {"degrees": ["secondary education", "certificate", "bachelor", "diploma", "degree", "hkdse"], "majors": ["law"], "languages": ["english", "chinese"], "language_level": ["excellent", "good command"], "hard_skills": ["make", "c"], "soft_skills": ["self-motivated", "oral", "independent", "advanced", "diligent", "inter-personal skills", "positive"], "languages_combined": [{"language": "english", "language_level": ["excellent"]}, {"language": "chinese", "language_level": ["excellent", "good command"]}]}, "experience_required": {"duration": ["at least 3 years", "minimum of 5 years"], "field": ["agency", "post-qualification", "legal"]}}, {"job_id": "100003009049666", "location_code": "hk", "company": "W M Lee & Co", "job_title": "\u521d\u7d1a\u6838\u6578\u898b\u7fd2\u54e1", "description": "\n\u8077\u8cac :Performing audit, tax, accounting jobs under senior's supervision, work in Mainland China occasionally (\u6bcf\u5e74\u4e00\u6b21\u76e4\u9ede\u5de5\u4f5c) (\u90f5\u5bc4:\u8343\u7063\u9752\u5c71\u9053264-298\u865f\u5357\u8c50\u4e2d\u5fc31913-15\u5ba4)(proficiency in MYOB and other accounting software pref,willing to learn)\n\n\u8cc7\u6b77 :\u4e2d\u516d\u7a0b\u5ea6; 2\u5e74\u7d93\u9a57; \u826f\u597d\u7cb5\u8a9e; \u4e00\u822c\u666e\u901a\u8a71; \u4e00\u822c\u82f1\u8a9e; \u61c2\u8b80\u5beb\u4e2d\u6587; \u61c2\u8b80\u5beb\u82f1\u6587; \u61c2MS Word; \u61c2MS Excel; Self motivated at work, able to work under pressure, willing to work OT in peak season\n\n\u5f85\u9047 :\u6bcf\u6708$12,000 - $18,000, \u6709\u5e74\u7d42\u734e\u91d1(2 yrs or above working exp in accounting section of commercial company), \u4e00\u81f3\u4e94: \u4e0a\u53489\u6642\u81f3\u4e0b\u53485\u6642\u534a\u53ca\u516d: \u4e0a\u53489\u6642\u81f3\u4e0b\u53481\u6642, \u6bcf\u9031\u5de5\u4f5c5-5\u5929\u534a (accounting graduate/with LCC Advanced cert), Saturday off on non peak season only\n\n\u7533\u8acb\u9808\u77e5 :\u50b3\u771f(24158382)/\u96fb\u90f5(Apply Now)/\u90f5\u5bc4\u5c65\u6b77\u8868\u7d66\u674e\u5049\u660e\u6703\u8a08\u5e2b\u884c\u3002\u5982\u8981\u7d22\u53d6\u6536\u96c6\u500b\u4eba\u8cc7\u6599\u8072\u660e, \u8acb\u8207\u6881\u5c0f\u59d0(Fax/Email/Post)\u806f\u7d61\u3002\n\n", "employment_types": ["Full Time"], "selling_points": [], "locations": ["Tsuen Wan Area"], "categories": ["Public / Civil", "Civil Services", "Social Services - Community / Non-profit Organization", "Others"], "post_time": "2022-01-14T09:02:43Z", "salary": {"currency": null, "max": null, "min": null, "period": "monthly", "term": null}, "salary_visible": false, "title_keywords": [], "responsibilities": ["tax", "audit", "software", "work under pressure"], "requirements": {"degrees": [], "majors": [], "languages": [], "language_level": [], "hard_skills": ["excel", "accounting software", "word", "lcc", "myob"], "soft_skills": ["self motivated", "willing to learn", "advanced", "work under pressure"], "languages_combined": []}, "experience_required": {"duration": [], "field": []}}, {"job_id": "100003009047913", "location_code": "hk", "company": "Hong Kong Adventist Hospital - Stubbs Road", "job_title": "\u6e05\u6f54 (\u5168\u8077) \u7ba1\u4e8b\u90e8", "description": "\u672c\u9662\u73fe\u62db\u8058\u670d\u52d9\u52a9\u7406\uff0c\u8cc7\u6b77\u53ca\u8077\u8cac\u5982\u4e0b\uff1a\n\n\u5c0f\u5b78\u7a0b\u5ea6\u3002\n\u80fd\u64cd\u4e00\u822c\u7cb5\u8a9e\u3001\u61c2\u95b1\u8b80\u4e2d\u6587\u3002\n\u80fd\u61c9\u4ed8\u9ad4\u529b\u52de\u52d5\u4e4b\u5de5\u4f5c\u3001\u5f85\u4eba\u6709\u79ae\u3002\n\u57f7\u884c\u7531\u4e0a\u53f8\u6240\u59d4\u6d3e\u4e4b\u8077\u52d9\u3002\n\u8ca0\u8cac\u4e00\u822c\u6e05\u6f54\u5de5\u4f5c\u3002\n\u9700\u8f2a\u73ed\u5de5\u4f5c\uff0c\u4e0a\u53488\u6642\u81f3-\u4e0b\u53484\u6642\u534a\u6216;\u4e0b\u53482\u6642\u534a\u81f3-\u4e0b\u534811\u6642\u6216;\u4e0b\u534811\u6642\u81f3-\u4e0a\u53487\u6642\u534a\n\n\u798f\u5229\u5305\u62ec\u81b3\u98df\u6d25\u8cbc\u3001\u914c\u60c5\u6027\u5e74\u7d42\u82b1\u7d05\u3001\u91ab\u7642\u53ca\u7259\u79d1\u798f\u5229\u3001\u5341\u4e09\u5929\u5e74\u5047\u3001\u5341\u4e03\u5929\u516c\u773e\u5047\u671f\uff0c\u4e0b\u5348\u73ed\u53ca\u665a\u73ed\u6d25\u8cbc\u7b49\u3002\n\n\u6709\u610f\u61c9\u5fb5\u8005\uff0c\u8acb\u5c07\u500b\u4eba\u5c65\u6b77\u53ca\u8981\u6c42\u85aa\u916c\u9023\u540c\u7533\u8acb\u8077\u4f4d\u540d\u7a31\uff0c\u90f5\u5bc4\u3001\u96fb\u90f5\u6216\u50b3\u771f\u81f3\u4eba\u529b\u8cc7\u6e90\u90e8\u3002\n\n\u90f5\u5bc4\uff1a\u00a0\u00a0\u00a0\u00a0\u00a0\u00a0\u00a0 \u9999\u6e2f\u6e2f\u5b89\u91ab\u9662\u53f8\u5f92\u62d4\u905340\u865f\u4eba\u529b\u8cc7\u6e90\u90e8\u6536\n\u96fb\u90f5\uff1a\u00a0 \u00a0 \u00a0 \u00a0\"Apply Now\"\n\u50b3\u771f\uff1a\u00a0\u00a0\u00a0\u00a0\u00a0\u00a0\u00a0 3651 8865\n\n\u5982\u5728\u63d0\u4ea4\u7533\u8acb\u5f8c\u7684\u56db\u661f\u671f\u5167\u672a\u6709\u6536\u5230\u9762\u8a66\u901a\u77e5\uff0c\u5373\u8868\u793a\u9019\u9805\u7533\u8acb\u4e0d\u7372\u63a5\u7d0d\u3002\u7533\u8acb\u4eba\u7684\u8cc7\u6599\u53ea\u6703\u7528\u65bc\u6709\u95dc\u672c\u9662\u7684\u4eba\u4e8b\u62db\u8058\u4e8b\u5b9c\u53ca\u5c07\u6703\u5728\u516d\u500b\u6708\u5167\u92b7\u6bc0\u3002", "employment_types": ["Full Time", "Permanent"], "selling_points": [], "locations": ["Tai Koo"], "categories": ["Admin & HR", "Others", "Medical Services", "Others", "Public / Civil", "Others"], "post_time": "2022-01-14T04:14:23Z", "salary": {"currency": null, "max": null, "min": null, "period": "monthly", "term": null}, "salary_visible": false, "title_keywords": [], "responsibilities": [], "requirements": {"degrees": [], "majors": [], "languages": [], "language_level": [], "hard_skills": [], "soft_skills": [], "languages_combined": []}, "experience_required": {"duration": [], "field": []}}, {"job_id": "100003009042449", "location_code": "hk", "company": "Construction Industry Council", "job_title": "Assistant Officer \u2013 Industry Development", "description": "The applicant must possess\na recognised degree; construction-related discipline is preferred;\na minimum of 1 years' post-qualification experience;\ndetailed-minded, proactive character and good sense of responsibility;\ngood communication and interpersonal skills; be a pleasant team player;\nproficiency in Microsoft application software (including Word, Excel and Powerpoint, etc.), Chinese word processing is a must; and\ngood command of both spoken and written English and Chinese.\n(Applicants who do not possess the required qualifications and / or experience may be\u00a0considered for other positions within the organisation.)\n\nDuties include\nto vet the funding applications and keep track the execution status;\nto vet the disbursement requests raised by successful applicants according to service pledge;\nto provide support to the marketing and promotional activities of the department;\nto arrange administrative support to the department;\nto handle enquiries;\nto conduct site inspections in construction sites and successful applicants' premises; and\nto carry out any other duties as assigned from time to time by the Executive Director.\nApplications\nThe position is on a renewable fixed-term contract (subject to performance and operational needs) for a period of 2 years. \u00a0\nPlease click the below \u201cApply Online\u201d to complete the application form and upload the updated curriculum vitae, the results of English and Chinese Language obtained in public examinations, current and expected salary together with a covering letter stating one\u2019s suitability for the job on or before\u00a026 January\u00a02022.\nFor further details on CIC please refer to website:\u00a0http://www.cic.hk.", "employment_types": ["Full Time", "Contract"], "selling_points": ["a recognised degree (construction-related)", "a minimum of 1 years' post-qualification work exp.", "vet the funding applications & update the status"], "locations": ["Not Specified"], "categories": ["Admin & HR", "Clerical / Admin Staff", "Marketing / Public Relations", "Marketing - General / Support", "Public / Civil", "Others"], "post_time": "2022-01-12T07:34:58Z", "salary": {"currency": null, "max": null, "min": null, "period": null, "term": null}, "salary_visible": false, "title_keywords": ["assistant officer"], "responsibilities": ["any other duties", "provide support", "software", "administrative support", "website", "communication", "handle enquiries", "promotional activities", "site inspections"], "requirements": {"degrees": ["degree"], "majors": [], "languages": ["english", "chinese"], "language_level": ["good command"], "hard_skills": ["excel", "chinese word processing", "word", "powerpoint"], "soft_skills": ["sense of responsibility", "pleasant", "communication and interpersonal skills", "organisation", "team player", "proactive", "detailed"], "languages_combined": [{"language": "english", "language_level": ["good command"]}, {"language": "chinese", "language_level": ["good command"]}]}, "experience_required": {"duration": ["minimum of 1 years"], "field": ["post-qualification"]}}, {"job_id": "100003009048264", "location_code": "hk", "company": "Q P Group Holdings Limited", "job_title": "Environmental Protection Officer/ Manager", "description": "Responsibilities:\n\nTo assist in developing work and programmes to accomplish the objectives, to foster the continuous local community support and facilitate the smooth implementation of various urban renewal initiatives\nTo establish liaison network and build rapport with different stakeholders affected by the Authority\u2019s redevelopment projects\nTo coordinate work programmes and action plans, including preparing publication for stakeholder communication, and assist in executing the programmes and plans\nTo monitor closely the development of local political dynamics as well as to provide feedback of views and suggestions of the local community for strategy and planning considerations\nTo assist in preparing for District Council meetings, and to attend them as required\nTo assist in training the community development team members and other front-line staff members for community engagement skills and knowledge\n\nRequirements:\n\nDegree holder in public administration, communication or related fields\nMinimum 8 years\u2019 full-time experience in community engagement or district administration\nWork experience related to urban renewal, housing policies or political parties is an advantage\nProven track record in implementing community engagement or public consultation programmes\nOutgoing, self-motivated and innovative in approaching problems and challenges at work\nFluent oral and written communication skills in English and Chinese, as well as fluent Putonghua\n\nFor more information on the work of the URA, please visit the website at http://www.ura.org.hk.\n\nFull resume with present and expected salaries should be submitted via online application (please click this website address: https://careers.ura.org.hk/).\n\nClosing date for application: 27 January 2022.\u00a0All applications will be treated in the strictest confidence and information provided will be used for the consideration of applications.\u00a0 Applicants not invited for interview within four weeks from the closing date may consider their applications unsuccessful.\n\nPersonal data provided by job applicants will be treated in strict confidence and used strictly in accordance with our \u201cPersonal Information Collection Statement Pertaining to Recruitment\u201d for recruitment purpose only.\u00a0 A copy of the Statement is available on our website and obtainable on request.\u00a0 Applicants may be considered for other suitable positions in the Authority and all personal data of unsuccessful applicants will be retained for a maximum of two years.", "employment_types": ["Full Time", "Permanent"], "selling_points": ["5 years\u2019 experience in environmental compliance", "Familiar with ISO GHG Emission", "Frequent travel is required"], "locations": ["Others - China"], "categories": ["Sciences, Lab, R&D", "Energy / Natural Resources / Oil & Gas", "Environmental Science / Waste Management", "Public / Civil", "Others"], "post_time": "2022-01-15T03:49:53Z", "salary": {"currency": null, "max": null, "min": null, "period": "monthly", "term": null}, "salary_visible": false, "title_keywords": ["officer", "manager"], "responsibilities": ["monitor", "implementation", "developing", "coordinate", "communication", "executing", "plans", "publication", "planning"], "requirements": {"degrees": ["degree holder"], "majors": ["public administration"], "languages": ["putonghua", "english", "chinese"], "language_level": ["fluent"], "hard_skills": [], "soft_skills": ["outgoing", "communication skills", "oral", "self-motivated", "confidence", "communication", "innovative"], "languages_combined": [{"language": "putonghua", "language_level": ["fluent"]}, {"language": "english", "language_level": ["fluent"]}, {"language": "chinese", "language_level": ["fluent"]}]}, "experience_required": {"duration": ["minimum 8 years"], "field": ["related", "administration"]}}, {"job_id": "100003009042415", "location_code": "hk", "company": "Lindy Williams", "job_title": "Government Funding Project Officer (Funding Programme / CS / KYC / Vetting / banking)", "description": "Job Highlight\n\n5 years\u2019 experience in environmental compliance\nFamiliar with ISO9001/ISO45001/ISO14001/ISO14064 GHG Emission\n\nJob Responsibilities:\n\nDevelop and implement the Group\u2019s environmental compliance; strategies and plan to achieve our sustainability goals.\nTo build and drive environmental compliance mindset of employees\u2019 behavior to achieve green environment in factories.\nSet up road map and lead the environmental protection team on sustainability of green manufacturing.\nDeploy and implement the environmental policies and guidelines, set up KPI indicators and control mechanism in line with international standards and statutory requirements.\nProvide guidance to the environmental management of factories and organize regular meetings in reviewing the progress of compliance.\nMonitor environmental safety implementation issues, oversee improvement progress on corrective action plans and communicate with relevant internal / external parties for the results achieved. Organize regular meetings about environmental matters.\nTrack and evaluate wastes discharge mechanism effectiveness, identify alternatives to drive reduction of discharge of chemical waste and GHG, to eliminate any potential environmental hazards and pollution.\nLead and Facilitate factories on 3rd party certification on relevant accreditation of environmental compliance scheme in accordance with statutory requirements / regulations and international standards.\nPrevent, reduce or eliminate hazards that may affect the health of employees.\nSet up crisis management policies and procedures, and site crisis management team to analyze and mitigate risks and strengthen the capability of all sites to deal with crisis.\nOrganize social and environmental engagement events both within and outside the group.\nPrepare the group Environmental report required by the listing rule of the Hong Kong stock Exchange.\n\nRequirements:\n\nUniversity degree or above in environment.\nAt least 5 years\u2019 experience in environmental compliance and health and safety work experience in sizable manufacturing enterprises.\nFamiliar with the statutory requirements and international on safety and environmental protection as well as related measurement and production processes.\nFamiliar with standards and audit requirements of ISO9001/ISO45001/ISO14001/ISO14064 or other related systems.\nStrong leadership and management skills required.\nSound project management, analytical and problem solving skills.\nProactive and tactful in communication.\nProficiency in computer software, and in both spoken and written English and Chinese, including Mandarin.\nFrequent travel to support overseas operation is required.\nCandidate with more experience will be considered as\u00a0Environmental Protection Manager\u00a0\n\nApplication:\n\nPlease send your CV, recent salary & expected salary in word file to hkghr @ qpp.com\n\n*** All personal information collected will be kept for employment related purposes only ***", "employment_types": ["Contract"], "selling_points": ["Government Funding Programme", "Program Management, Customer Service", "Vetting, Program Monitoring, KYC, Bank"], "locations": ["Others"], "categories": ["Public / Civil", "Others"], "post_time": "2022-01-12T07:23:30Z", "salary": {"currency": null, "max": null, "min": null, "period": "monthly", "term": null}, "salary_visible": false, "title_keywords": ["project officer"], "responsibilities": ["regulations", "external parties", "statutory requirements", "plan", "deploy", "plans", "listing", "control", "compliance", "monitor", "implementation", "develop", "crisis management", "report", "management", "procedures", "provide guidance", "communicate with", "guidelines", "policies", "evaluate"], "requirements": {"degrees": ["degree or above"], "majors": [], "languages": ["english", "chinese", "mandarin"], "language_level": ["proficiency"], "hard_skills": ["project management", "problem solving skills", "word"], "soft_skills": ["communication", "project management", "analytical and problem solving skills", "tactful", "proactive", "leadership"], "languages_combined": [{"language": "english", "language_level": ["proficiency"]}, {"language": "chinese", "language_level": ["proficiency"]}, {"language": "mandarin", "language_level": ["proficiency"]}]}, "experience_required": {"duration": ["at least 5 years"], "field": ["manufacturing", "compliance", "environmental"]}}, {"job_id": "100003009047665", "location_code": "hk", "company": "The University of Hong Kong", "job_title": "Research Assistant I/II (Ref.: 511352)", "description": "Our client is a multi-disciplinary organisation and is inviting a number of Contract Project Officers.\n\nLocation: Kowloon Tong\n\nContract period: asap - 6 months (under agency payroll with basic benefits, with gratuity bonus depends on performance)\n\nHighlight:\n1.\u00a0\u00a0CS Team\n2.\u00a0 Programme Management Team\u00a0\n\nPost 1. Project Officer (Customer Services) - 6-month Contract\n\nJob Duties:\n\n\u00b7\u00a0\u00a0\u00a0\u00a0\u00a0\u00a0\u00a0\u00a0\u00a0To handle telephone and email enquiries from the public in relation to a large-scale Government funding programme;\n\n\u00b7\u00a0\u00a0\u00a0\u00a0\u00a0\u00a0\u00a0\u00a0\u00a0To perform daily operations of quality hotline and customer service;\n\n\u00b7\u00a0\u00a0\u00a0\u00a0\u00a0\u00a0\u00a0\u00a0\u00a0To receive complaints from the public and compile complaint logs;\n\n\u00b7\u00a0\u00a0\u00a0\u00a0\u00a0\u00a0\u00a0\u00a0\u00a0To provide support for ad-hoc projects as assigned by management.\n\nJob Requirements:\n\n\u00b7\u00a0\u00a0\u00a0\u00a0\u00a0\u00a0\u00a0\u00a0\u00a0A recognized degree, or equivalent;\n\n\u00b7\u00a0\u00a0\u00a0\u00a0\u00a0\u00a0\u00a0\u00a0\u00a0At least two years of relevant experience in handling hotline enquiries and complaints, preferably gained from sizable or public organizations;\n\n\u00b7\u00a0\u00a0\u00a0\u00a0\u00a0\u00a0\u00a0\u00a0\u00a0Proficient in PC applications including Excel, Word and Chinese word processing;\n\n\u00b7\u00a0\u00a0\u00a0\u00a0\u00a0\u00a0\u00a0\u00a0\u00a0Good command of written and spoken English and Chinese;\n\n\u00b7\u00a0\u00a0\u00a0\u00a0\u00a0\u00a0\u00a0\u00a0\u00a0Good communication, interpersonal, organization and problem-solving skills; and\n\n\u00b7\u00a0\u00a0\u00a0\u00a0\u00a0\u00a0\u00a0\u00a0\u00a0Customer-oriented, flexible and able to work independently as well as under pressure.\n\nPost 2. Project Officer (Programme Management) - 6-month Contract\n\nJob Duties:\n\n\u00b7\u00a0\u00a0\u00a0\u00a0\u00a0\u00a0\u00a0\u00a0\u00a0Assist in assessment of the funding applications and perform initial check of final reports from the grantees and prepare relevant documents required for funding disbursement;\n\n\u00b7\u00a0\u00a0\u00a0\u00a0\u00a0\u00a0\u00a0\u00a0\u00a0Support project work and on-site checking of funded projects, liaise with applicants and arrange meetings.\n\nJob Requirements:\n\n\u00b7\u00a0\u00a0\u00a0\u00a0\u00a0\u00a0\u00a0\u00a0\u00a0Degree holder in Business, Engineering, Science subject or related discipline.\n\n\u00b7\u00a0\u00a0\u00a0\u00a0\u00a0\u00a0\u00a0\u00a0\u00a02 years\u2019 full time administrative / customer service experience is preferred.\n\n\u00b7\u00a0\u00a0\u00a0\u00a0\u00a0\u00a0\u00a0\u00a0\u00a0Good command of English and Cantonese.\n\nAll information collected will be kept in strict confidence and will be used for recruitment purpose only.\n\nPlease submit the application with your resume with your availability & expected salary if you are interested.\n\nWhatsapp No. Ms RM +852 5285 3022\n\nFor more jobs, please visit our website: www.williams-asia.com\n\n(Personal data submitted are for recruitment purpose only.)\n", "employment_types": ["Full Time"], "selling_points": ["possess a Bachelor's degree or above", "assist in a community project", "manage research database"], "locations": ["Not Specified"], "categories": ["Professional Services", "Business Analysis / Data Analysis", "Education", "Others", "Public / Civil", "Others"], "post_time": "2022-01-14T03:41:08Z", "salary": {"currency": null, "max": null, "min": null, "period": "monthly", "term": null}, "salary_visible": false, "title_keywords": ["research assistant"], "responsibilities": [], "requirements": {"degrees": [], "majors": [], "languages": [], "language_level": [], "hard_skills": [], "soft_skills": [], "languages_combined": []}, "experience_required": {"duration": [], "field": []}}, {"job_id": "100003009046830", "location_code": "hk", "company": "Hyatt Centric Victoria Harbour Hong Kong", "job_title": "Steward Attendant / Team Leader / Steward Attendant - Stewarding (\u7ba1\u4e8b\u6e05\u6f54\u54e1\uff0f\u7ba1\u4e8b\u90e8\u9818\u73ed / \u5783\u573e\u8655\u7406\u5c08\u54e1)", "description": "Work type:\u00a0Full-time\nDepartment:\u00a0Department of Ophthalmology (22300)\nCategories:\u00a0Research Support Staff\n\nResearch Assistant I/II in the Department of Ophthalmology\u00a0(Ref.: 511352)\u00a0(to commence as soon as possible for one year, with the possibility of renewal subject to satisfactory performance)\n\nApplicants should possess a Bachelor's degree or above, preferably in public health, biomedical science or related disciplines, with relevant work experience.\u00a0 They should have a good command of written and spoken English and Chinese (including fluent Cantonese), good interpersonal skills, and knowledge of basic statistics. \u00a0They should be organized, responsible, detail-minded, self-motivated, and able to work independently as well as in a team.\u00a0 Experience in conducting interviews and using SPSS and Microsoft Access is preferred.\u00a0 A keen research interest in epidemiology would be an advantage.\u00a0 The appointee will mainly assist in a community project in the Southern District of Hong Kong Island.\u00a0 He/She will manage research database for a\u00a0large epidemiology study, conduct interviews, analyse data, and perform other duties as assigned.\u00a0 Irregular working hours may be required occasionally.\u00a0 Shortlisted candidates will be invited to an interview. Those who have responded to the previous advertisement (Ref.: 508905) need not re-apply.\n\nA highly competitive salary commensurate with qualifications and experience will be offered, in addition to annual leave and medical benefits.\n\nThe University only accepts online application for the above post.\u00a0 Applicants should apply online and upload an up-to-date C.V[via APPLY NOW].\u00a0 Review of applications will start as soon as possible and continue until\u00a0January 28, 2022, or until the post is filled, whichever is earlier.\n\nAdvertised:Dec 23, 2021 (HK Time)\nApplications close:Jan 28, 2022 (HK Time)", "employment_types": ["Full Time"], "selling_points": [], "locations": ["North Point"], "categories": ["Beauty Care / Health", "Others", "Hospitality / F & B", "Others", "Public / Civil", "Others"], "post_time": "2022-01-14T01:23:49Z", "salary": {"currency": null, "max": null, "min": null, "period": "monthly", "term": null}, "salary_visible": false, "title_keywords": ["team leader"], "responsibilities": ["perform other duties", "data", "conducting interviews", "research support", "database", "analyse"], "requirements": {"degrees": ["degree or above", "bachelor"], "majors": ["biomedical science", "related disciplines", "public health"], "languages": ["cantonese", "english", "chinese"], "language_level": ["good", "good command", "fluent", "basic"], "hard_skills": ["basic"], "soft_skills": ["detail-minded", "organized", "self-motivated", "work independently", "responsible", "keen", "interpersonal skills"], "languages_combined": [{"language": "cantonese", "language_level": ["fluent", "good", "good command", "basic"]}, {"language": "english", "language_level": ["good", "good command", "basic"]}, {"language": "chinese", "language_level": ["good", "good command", "basic"]}]}, "experience_required": {"duration": [], "field": ["related"]}}, {"job_id": "100003009044375", "location_code": "hk", "company": "Yan Oi Tong Ltd", "job_title": "\u6587\u54e1 (\u8077\u4f4d\u7de8\u865f: JCTC/CLK0105&0106/220113)", "description": "Responsibilities:\n\n\nResponsible for the coordination of the ESG Reporting at Business Unit level (across Hong Kong and Mainland centres)\nDevelop and deliver trainings to ensure the compliance of ESG Reporting requirement and improve the data quality\nManage and keep track of the Company\u2019s environmental performance and target settings\nArrange sustainability related audits, follow-up and ensure the records are maintained and updated\nSupport the implementation of Company\u2019s corporate responsibility policy and the related sustainable operation processes\nSupport the execution of defined sustainability projects and initiatives\nPerform other duties as assigned\n\nRequirements:\n\nDegree holder in Social Responsibility, Sustainability and Compliance, Applied and Pure Sciences or related disciplines\nAt least 2 years of relevant experience, experience with social and environmental compliance standards such as ISO 14001, ISO 45001 etc., will be an advantage\nSelf-motivated, detail-minded, independent and proactive; Team player in a cross-cultural working environment\nProficiency in Microsoft Office, especially in Excel (including pivot tables and VBA Excel)\nGood command of both written and spoken English and Chinese (Cantonese and Mandarin)\n\nWe offer competitive remuneration package that commensurate with experience and qualifications.\u00a0 Interested parties are invited to send full resume stating contact telephone number, date available, present and expected salary to our recruitment email address.\n\n\n(Personal data provided will be used strictly in accordance with the Company's personal data policy which is available upon request.)", "employment_types": ["Full Time", "Contract"], "selling_points": ["\u4e2d\u4e94\u6216DSE\u4ee5\u4e0a\u7a0b\u5ea6", "\u5177\u4e2d\u3001\u82f1\u6587\u8b80\u5beb\u80fd\u529b", "5\u5929\u5de5\u4f5c\uff0c12\u5929\u5e74\u5047\uff0c\u5c6f\u9580\u5340\u5de5\u4f5c"], "locations": ["Tuen Mun Area"], "categories": ["Admin & HR", "Clerical / Admin Staff", "Public / Civil", "Social Services - Community / Non-profit Organization", "Others"], "post_time": "2022-01-13T03:54:08Z", "salary": {"currency": null, "max": null, "min": null, "period": "monthly", "term": null}, "salary_visible": false, "title_keywords": ["\u6587\u54e1"], "responsibilities": ["reporting", "perform other duties", "data", "compliance", "quality", "implementation", "develop", "coordination", "audits"], "requirements": {"degrees": ["degree holder"], "majors": ["related disciplines"], "languages": ["cantonese", "english", "chinese", "mandarin"], "language_level": ["good command"], "hard_skills": ["excel", "vba", "pure", "microsoft office"], "soft_skills": ["detail-minded", "self-motivated", "independent", "team player", "proactive"], "languages_combined": [{"language": "cantonese", "language_level": ["good command"]}, {"language": "english", "language_level": ["good command"]}, {"language": "chinese", "language_level": ["good command"]}, {"language": "mandarin", "language_level": ["good command"]}]}, "experience_required": {"duration": ["at least 2 years"], "field": ["environmental", "compliance", "relevant experience"]}}, {"job_id": "100003009040299", "location_code": "hk", "company": "Construction Industry Council", "job_title": "Assistant - Project", "description": "\u5177\u4e2d\u4e94\u6216DSE\u4ee5\u4e0a\u7a0b\u5ea6\n\u5177\u4e2d\u3001\u82f1\u6587\u8b80\u5beb\u80fd\u529b\n\u719f\u6089\u96fb\u8166\u64cd\u4f5c\n\u5177\u6587\u66f8\u53ca\u6703\u8a08\u5de5\u4f5c\u7d93\u9a57\u512a\u5148\n\u5c6f\u9580\u5340\u5de5\u4f5c", "employment_types": ["Full Time", "Contract"], "selling_points": ["a recognised diploma or certificate", "a minimum of 2 years\u2019 post-qualification work exp.", "to assist the daily operations & handling audit"], "locations": ["Not Specified"], "categories": ["Admin & HR", "Clerical / Admin Staff", "Personal / Executive Assistant", "Public / Civil", "Others"], "post_time": "2022-01-12T02:12:08Z", "salary": {"currency": null, "max": null, "min": null, "period": null, "term": null}, "salary_visible": false, "title_keywords": ["assistant"], "responsibilities": [], "requirements": {"degrees": [], "majors": [], "languages": [], "language_level": [], "hard_skills": [], "soft_skills": [], "languages_combined": []}, "experience_required": {"duration": [], "field": []}}, {"job_id": "100003009052140", "location_code": "hk", "company": "Haven of Hope Christian Service", "job_title": "\u6d3b\u52d5\u7d71\u7c4c\u54e1 / \u6d3b\u52d5\u5de5\u4f5c\u54e1 (\u7de8\u865f : DECS/PW/JDB)", "description": "The applicant must possess\na recognised diploma or certificate;\na minimum of 2 years\u2019 post-qualification work experience;\nexcellent interpersonal, communication and presentation skills;\nproactive character, customer-oriented mindset and good sense of responsibility;\nproficiency in Microsoft application software (including Word, Excel and PowerPoint, etc.) and Chinese word processing is a must; and\ngood command of both written and spoken English and Chinese.\n(Applicants who do not possess the required qualifications and / or experience may be considered for other positions within the organisation.)\n\nDuties include\nto assist in the daily operations of the assigned department including but not limited to handling compliance checks and audits of the Anti-epidemic Fund, checking and verifying the submitted data/information with the relevant applicants and their MPF trustee(s), updating applicants\u2019 status and answering enquiries;\nto support the administration and logistics of compliance checks and audits of the Anti-epidemic Fund, including checking on compliance status of the successful applicants based on relevant records maintained by the relevant MPF trustee(s) and with reference to supplementary records submitted by the applicants, and liaison and co-ordination with the CIC\u2019s implementation agency on the related work;\nto assist in the recovery actions of clawback and charges demanded from non-compliant applicants, including the retrieval of case details/records and preparation\u00a0 for documents for onward action by Government departments including but not limited to Development Bureau and Department of Justice;\nto assist in preparing regular and ad hoc analysis reports as required;\nto perform general administration duties include handling documents and mails, data entry and retrieval, filing etc.; and\nto carry out any other duties as assigned from time to time by the Executive Director.\nApplications\nThe position is on a time-limited fixed-term contract subject to operational needs.\nPlease click the below \u201cApply Online\u201d to complete the application form and upload the updated curriculum vitae, the results of English and Chinese Language obtained in public examinations, current and expected salary together with a covering letter stating one\u2019s suitability for the job on or before\u00a026 January 2022.\nFor further details on CIC please refer to website: http://www.cic.hk.", "employment_types": ["Full Time"], "selling_points": [], "locations": ["Not Specified"], "categories": ["Marketing / Public Relations", "Public Relations - Event Management", "Public / Civil", "Social Services - Community / Non-profit Organization", "Others"], "post_time": "2022-01-17T02:14:38Z", "salary": {"currency": null, "max": null, "min": null, "period": "monthly", "term": null}, "salary_visible": false, "title_keywords": ["\u6d3b\u52d5\u7d71\u7c4c\u54e1", "\u6d3b\u52d5\u5de5\u4f5c\u54e1"], "responsibilities": ["any other duties", "ad hoc", "software", "mpf", "data", "analysis reports", "data entry", "handling documents", "compliance", "checking", "implementation", "website", "communication", "daily operations", "logistics", "audits", "administration"], "requirements": {"degrees": ["certificate", "diploma"], "majors": [], "languages": ["english", "chinese"], "language_level": ["good command"], "hard_skills": ["excel", "chinese word processing", "analysis", "word", "powerpoint"], "soft_skills": ["sense of responsibility", "communication", "presentation skills", "customer-oriented", "organisation", "proactive", "interpersonal"], "languages_combined": [{"language": "english", "language_level": ["good command"]}, {"language": "chinese", "language_level": ["good command"]}]}, "experience_required": {"duration": ["minimum of 2 years"], "field": ["post-qualification"]}}, {"job_id": "100003009045270", "location_code": "hk", "company": "ADI Limited", "job_title": "Resident Landscape Architect for a Large Scale Public Open Space/Public Works Project", "description": "\u9999\u6e2f\u4e2d\u5b78\u6587\u6191\u8003\u8a66\u6216\u9999\u6e2f\u4e2d\u5b78\u6703\u8003\u4e94\u79d1\u8003\u7372\u7b2c2\u7d1a\uff0f\u9054\u6a19\u6216\u4ee5\u4e0a\uff08\u5305\u62ec\u4e2d\u3001\u82f1\u6587\u79d1(\u8ab2\u7a0b\u4e59)\uff09\n\u8ca0\u8cac\u7c4c\u8fa6\u53ca\u63a8\u884c\u9577\u8005\u4e2d\u5fc3\u6d3b\u52d5\u53ca\u5e36\u9818\u5c0f\u7d44\n\u9700\u5916\u52e4\u5de5\u4f5c\uff0c\u4f8b\u5982\u8857\u7ad9\u3001\u63a2\u8a2a\u9577\u8005\n\u5177\u9577\u8005\u670d\u52d9\u7d93\u9a57\u6216\u7fa9\u5de5\u7d93\u9a57\u8005\u512a\u5148\u8003\u616e\n\n\u6709\u610f\u8005\u8acb\u65bc\u4e8c\u96f6\u4e8c\u4e8c\u5e74\u4e8c\u6708\u4e94\u65e5\u524d\u89aa\u7e55\u5c65\u6b77\u53ca\u671f\u671b\u5f85\u9047\uff08\u8acb\u65bc\u4fe1\u5c01\u9762\u53ca\u4fe1\u5167\u8a3b\u660e\u7533\u8acb\u8077\u4f4d\u7de8\u865f\uff09\u5bc4\u65b0\u754c\u5c07\u8ecd\u6fb3\u9748\u5be6\u8def\u4e03\u865f\u57fa\u7763\u6559\u9748\u5be6\u5354\u6703\u4eba\u529b\u8cc7\u6e90\u90e8\u6536\uff0c\u6216\u96fb\u90f5\u81f3Apply Now\uff0c\u6216\u767c\u9001\u81f3Whatsapp\u865f\u78bc6507 8148\uff08\u6a19\u984c\u8acb\u8a3b\u660e\u8077\u4f4d\u7de8\u865f\uff09\u3002\u5982\u4e00\u500b\u6708\u5167\u672a\u7372\u901a\u77e5\u7d04\u898b\uff0c\u5247\u4f5c\u843d\u9078\u8ad6\u3002\n\u67e5\u8a62\u71b1\u7dda\uff1a2703 3227 (\u96fb\u8a71)\uff1b6507 8148 (Whatsapp)\u3002\n\u6709\u95dc\u672c\u6703\u8a73\u60c5\uff0c\u8acb\u700f\u89bd\u7db2\u9801http://www.hohcs.org.hk\n\n(\u53ef\u80fd\u7372\u8058\u4eba\u58eb\uff08\u5982\u5f9e\u4e8b\u8207\u5152\u7ae5\u6216\u7cbe\u795e\u4e0a\u7121\u884c\u70ba\u80fd\u529b\u4eba\u58eb\u6709\u95dc\u5de5\u4f5c\u8077\u4f4d\uff09\u9808\u65bc\u5165\u8077\u524d\u9032\u884c\uff0f\u63d0\u4ea4\u6027\u7f6a\u884c\u5b9a\u7f6a\u7d00\u9304\u67e5\u6838\u3002\u7533\u8acb\u4eba\u6240\u63d0\u4f9b\u7684\u8cc7\u6599\u5c07\u4e88\u4fdd\u5bc6\u53ca\u4f5c\u62db\u8058\u6709\u95dc\u8077\u4f4d\u7528\u9014)\n\n\u672a\u7d93\u672c\u5354\u6703\u66f8\u9762\u540c\u610f\uff0c\u4ee5\u4e0a\u62db\u8058\u5ee3\u544a\u5168\u90e8\u6216\u90e8\u5206\u5167\u5bb9\u5747\u4e0d\u5f97\u8907\u88fd\u81f3\u5176\u4ed6\u62db\u8058\u7db2\u7ad9\u3002", "employment_types": ["Full Time"], "selling_points": [], "locations": ["Not Specified"], "categories": ["Public / Civil", "Social Services - Community / Non-profit Organization", "Others"], "post_time": "2022-01-13T07:31:45Z", "salary": {"currency": null, "max": null, "min": null, "period": "monthly", "term": null}, "salary_visible": false, "title_keywords": [], "responsibilities": [], "requirements": {"degrees": [], "majors": [], "languages": [], "language_level": [], "hard_skills": ["whatsapp"], "soft_skills": [], "languages_combined": []}, "experience_required": {"duration": [], "field": []}}, {"job_id": "100003009036862", "location_code": "hk", "company": "Insurance Authority", "job_title": "Executive Assistant (Team Support)", "description": "\nQualification & Entry Requirements::\ni)\u00a0 \u00a0 \u00a0Applicant should posses Professional Membership of the Hong Kong Institute of Landscape Architects (HKILA) and/or be a Registered Landscape Architect (R.L.A.) in Hong Kong as defined under the Landscape Architect Registration Ordinance (Cap. 516); and\nii)\u00a0 \u00a0 Shall have a minimum 5 years relevant site experience.\niii)\u00a0 \u00a0The Resident Landscape Architect shall be full-time engaged on Site starting immediately to end of October 2023 or any extension as necessary.\n\u00a0\nDuties and responsibilities\nThe duties and responsibilities of the Resident Landscape Architect shall include, but not limited to, the followings:\n1.\u00a0 \u00a0 \u00a0 \u00a0 \u00a0 \u00a0to coordinate with and report to the Supervising Officer or his representatives all aspects of the Landscape Architectural Works on a daily basis;\n2.\u00a0 \u00a0 \u00a0 \u00a0 \u00a0 \u00a0to watch and inspect, to test and examine materials used and workmanship employed in the Landscape Architectural Works, to ensure that they are complying with the Employer\u2019s Requirements (ER), specifications, drawings and construction procedure with the assistance of the site supervisory staff;\n3.\u00a0 \u00a0 \u00a0 \u00a0 \u00a0 \u00a0to identify defective materials and workmanship in the Landscape Architectural Works not complying with the ER, specifications, drawings and construction procedure, and to coordinate appropriate tests on the defective Landscape Architectural Works with the assistance of the site supervisory staff;\n4.\u00a0 \u00a0 \u00a0 \u00a0 \u00a0 \u00a0to communicate among the Designers, the Contracted Party, the Supervising Officer and his Representative, site supervisory staff and the Specialist Contractors on the Landscape Architectural Works;\n5.\u00a0 \u00a0 \u00a0 \u00a0 \u00a0 \u00a0to resolve on site Landscape Architectural Works difficulties arising from unforeseen circumstances to allow the landscape architectural works to progress with minimum disruption, and in case of action involving variations to design, consult the Supervising Officer or his representatives;\n6.\u00a0 \u00a0 \u00a0 \u00a0 \u00a0 \u00a0to report to the Supervising Officer or his representatives any matters of unusual aspect for direction;\n7.\u00a0 \u00a0 \u00a0 \u00a0 \u00a0 \u00a0to report to the Supervising Officer and his Representative immediately any issues that affect time and quality of the works that need their special attention together with any remedial solution proposed;\n8.\u00a0 \u00a0 \u00a0 \u00a0 \u00a0 \u00a0to monitoring and reporting of the performance of the Specialist Contractor for landscape work,\n9.\u00a0 \u00a0 \u00a0 \u00a0 \u00a0 \u00a0to maintain the site record on the Landscape Architectural Works and to coordinate the checking of the Landscape Architectural Works including but not limited to tree preservation, tree transplanting work, plant procurement and tree risk assessment works with the assistance of site supervisory staff;\n10.\u00a0 \u00a0 \u00a0 \u00a0 to monitor the implementation of landscape and visual mitigation measures to ensure compliance with the recommendations of the approved EIA Report;\n11.\u00a0 \u00a0 \u00a0 \u00a0 to monitor the progress and to produce timely information in advance of construction to avoid delay;\n12.\u00a0 \u00a0 \u00a0 \u00a0 to coordinate the Hard and Soft Landscape works requirements in connection to building services and deal with the consequential changes to the Landscape Architectural design and to produce sketch plans and working drawings;\n13.\u00a0 \u00a0 \u00a0 \u00a0 to submit for approval any Landscape Architectural details, in particular any temporary work as required in the Contract;\n14.\u00a0 \u00a0 \u00a0 \u00a0 to attend regular and ad hoc meetings;\n15.\u00a0 \u00a0 \u00a0 \u00a0 to assist the Supervising Officer or his representatives in the investigation and to prepare report on the acceptable or otherwise the use of materials; and\n16.\u00a0 \u00a0 \u00a0 \u00a0 to prepare design, estimate and specification in collaboration with allied disciplines.\n17.\u00a0 \u00a0 \u00a0 \u00a0 to undertake any other duties in connection with site construction activities.\nPlease submit CV to H.R. Dept., ADI Ltd, 10/F Bangkok Bank Building, 18 Bonham Strand West, Sheung Wan or e-mail:\u00a0 [via\u00a0 Apply Now ]\n\u00a0\nFor more information on ADI, please visit our website at www.adi-group.com.hk\n\u00a0\n(Personal data collected will be used for recruitment purpose only.)\n\n", "employment_types": ["Full Time", "Permanent"], "selling_points": [], "locations": ["Southern Area"], "categories": ["Admin & HR", "Clerical / Admin Staff", "Public / Civil", "Others"], "post_time": "2022-01-10T16:52:24Z", "salary": {"currency": null, "max": null, "min": null, "period": "monthly", "term": null}, "salary_visible": false, "title_keywords": ["executive assistant"], "responsibilities": ["any other duties", "supervising", "quality", "website", "design", "drawings", "maintain", "plans", "personal data", "ad hoc", "monitor", "implementation", "visual", "report", "reporting", "prepare report", "monitoring", "coordinate with", "checking", "investigation", "specifications", "ensure compliance", "coordinate", "recruitment"], "requirements": {"degrees": [], "majors": [], "languages": [], "language_level": [], "hard_skills": ["r"], "soft_skills": [], "languages_combined": []}, "experience_required": {"duration": ["minimum 5 years"], "field": []}}, {"job_id": "100003009038361", "location_code": "hk", "company": "Construction Industry Council", "job_title": "Senior Officer \u2013 Mainland Liaison Services", "description": "\n\u8077\u8cac :\u8ca0\u8cac\u767b\u8a18,\u63a5\u5f85,\u8ddf\u75c7,\u914d\u85e5\u53ca\u4e00\u822c\u8a3a\u6240\u8077\u52d9\n\n\u8cc7\u6b77 :\u5c08\u4e0a\u6559\u80b2\uff1a\u6587\u6191/\u8b49\u66f8; \u826f\u597d\u7cb5\u8a9e; \u826f\u597d\u666e\u901a\u8a71; \u826f\u597d\u82f1\u8a9e; \u61c2\u8b80\u5beb\u4e2d\u6587; \u61c2\u8b80\u5beb\u82f1\u6587; \u61c2\u4e2d\u6587\u6253\u5b57; \u5177\u6709\u57fa\u672c\u96fb\u8166\u64cd\u4f5c\u77e5\u8b58; \u5b88\u6642,\u6709\u79ae\u8c8c,\u505a\u4e8b\u7d30\u5fc3,\u5177\u826f\u597d\u5ba2\u6236\u670d\u52d9\u614b\u5ea6\n\n\u5f85\u9047 :\u6bcf\u5c0f\u6642$80.00, \u4e00\u81f3\u4e94: \u4e0a\u53489\u6642\u534a\u81f3\u4e0b\u53486\u6642\u534a\u6216\u4e0a\u534810\u6642\u81f3\u4e0b\u53487\u6642, \u661f\u671f\u516d: \u4e0a\u53489\u6642\u534a\u81f3\u4e0b\u53482\u6642\u6216\u4e0a\u534810\u6642\u81f3\u4e0b\u53482\u6642, \u6bcf\u9031\u5de5\u4f5c1-4\u5929\n\n\u7533\u8acb\u9808\u77e5 :\u6c42\u8077\u8005\u53ef\u96fb\u90f5(Apply Now)\u5c65\u6b77\u8868\u7d66\u5eb7\u532f\u5c08\u79d1\u91ab\u7642\u4e2d\u5fc3\u3002\u5982\u8981\u7d22\u53d6\u6536\u96c6\u500b\u4eba\u8cc7\u6599\u8072\u660e, \u8acb\u8207\u9ec3\u5c0f\u59d0(Email)\u806f\u7d61\u3002\n\n", "employment_types": ["Full Time", "Contract"], "selling_points": ["a recognised degree, preferably in business or mkt", "a minimum 5 years\u2019 post-qualification working exp.", "building & maintaining network among HK & Mainland"], "locations": ["Not Specified"], "categories": ["Admin & HR", "Clerical / Admin Staff", "Marketing / Public Relations", "Public Relations - General / Support", "Public / Civil", "Others"], "post_time": "2022-01-11T06:40:02Z", "salary": {"currency": null, "max": null, "min": null, "period": null, "term": null}, "salary_visible": false, "title_keywords": ["senior officer"], "responsibilities": [], "requirements": {"degrees": [], "majors": [], "languages": [], "language_level": [], "hard_skills": [], "soft_skills": [], "languages_combined": []}, "experience_required": {"duration": [], "field": []}}, {"job_id": "100003009051400", "location_code": "hk", "company": "Insurance Authority", "job_title": "Manager (Non-life Business)", "description": "The applicant must possess\na recognised degree, preferably in business studies or marketing;\n5 years\u2019 post-qualification working experience, preferably with a statutory body or a sizable organisation, in any of the following areas: business development, event organisation, public/corporate relations or stakeholder engagement;\nknowledge and proven track record in dealing with Mainland counterparts, preferably with focus in the Greater Bay Area;\nunderstanding of construction operations, its supply chain and key stakeholders would be a distinct advantage;\nexcellent command of both written and spoken English and Chinese. Must be fluent in Putonghua;\nstrong interpersonal and communication skills; and\na proactive, resourceful, sociable, outgoing character and can work independently under pressure.\n(Applicants who do not possess the required qualifications and / or experience may be considered for other positions within the organisation.)\n\nDuties include\nbuilding and maintaining network among Hong Kong and Mainland construction related companies, institutions, associations, practitioners and government officials;\nliaising with industry stakeholders and understand their aspirations and needs for development in the Greater Bay Area;\nformulating and implementing corresponding support initiatives;\norganising events, visits and study tours to facilitate exchange of knowledge with Mainland counterparts and explore business opportunities for industry stakeholders;\nfrequent travel to and / or be stationed in the Mainland;\nhandling internal administrative tasks; and\ncarrying out any other duties as assigned from time to time by the Executive Director.\nApplications\nThe position is on a renewable fixed-term contract (subject to performance and operational needs) for a period of 2 years. \u00a0\nPlease click the below \u201cApply Online\u201d to complete the application form and upload the updated curriculum vitae, the results of English and Chinese Language obtained in public examinations, current and expected salary together with a covering letter stating one\u2019s suitability for the job on or before\u00a025 January\u00a02022.\nFor further details on CIC please refer to website:\u00a0http://www.cic.hk.", "employment_types": ["Full Time", "Permanent"], "selling_points": [], "locations": ["Southern Area"], "categories": ["Accounting", "Others", "Insurance", "Others", "Public / Civil", "Others"], "post_time": "2022-01-15T14:24:49Z", "salary": {"currency": null, "max": null, "min": null, "period": "monthly", "term": null}, "salary_visible": false, "title_keywords": ["manager"], "responsibilities": ["any other duties", "maintaining", "operations", "business opportunities", "liaising with", "website", "communication", "administrative tasks"], "requirements": {"degrees": ["degree"], "majors": ["business", "marketing"], "languages": ["putonghua", "english", "chinese"], "language_level": ["excellent", "fluent"], "hard_skills": ["focus", "exchange"], "soft_skills": ["outgoing", "communication skills", "work independently", "under pressure", "resourceful", "sociable", "organisation", "focus", "proactive", "interpersonal"], "languages_combined": [{"language": "putonghua", "language_level": ["fluent"]}, {"language": "english", "language_level": ["excellent"]}, {"language": "chinese", "language_level": ["excellent"]}]}, "experience_required": {"duration": ["5 years"], "field": ["business development", "post-qualification"]}}, {"job_id": "100003009043644", "location_code": "hk", "company": "Hong Kong Sheng Kung Hui Welfare Council Limited", "job_title": "\u884c\u653f\u52a9\u7406  Administration Assistant \u3014\u7de8\u865f\uff1aCAC/AA/20220107-2\u3015", "description": "Reporting to the Senior Manager (Non-life Business), the incumbent will undertake the following:\n\nKey Responsibilities\n\nPerform prudential supervision of authorized non-life insurers\nParticipate in conducting inspection and monitoring non-life insurers' compliance with regulatory requirements\nSupport initiatives to promote the non-life insurance market of Hong Kong\nOther duties as assigned by senior management to facilitate the administration of the statutory functions of IA\u00a0\n\nRequirements\n\nA Bachelor\u2019s degree in accounting, finance, economics, statistics, actuarial science or related disciplines. Qualified CPA or actuary is recommended\nMinimum 5 years' solid work experience\nKnowledge of the local regulatory requirements, insurance products, industry practices and market dynamics relating to the insurance business.\nWork experience in a local or overseas insurance regulatory agency or non-life actuarial practices is preferred\nStrong problem-solving, analytical, interpersonal and communication skills, and able to work in a team in a collaborative environment\nAble to work independently and under pressure\nStrong command of both written and spoken English and Chinese. Proficiency in Putonghua will be an advantage\u00a0\n\nRemuneration Package\nA competitive remuneration package commensurate with the successful candidate\u2019s experience and qualifications will be offered.\n\nApplication\nReview of the applications will start as soon as possible and continue until the posts are filled. Interested applicants may send a letter of application quoting the reference number in the heading, together with a full resume stating public examination and university academic results as well as current and expected salaries by clicking \"Apply Now\".\n\nThe Insurance Authority is an equal opportunities employer. Applicants not invited for an interview within 2 months from the submission date may assume their applications unsuccessful. Applications may be considered for other suitable positions within IA. All applications will be handled in strict confidence and the information collected will only be used for recruitment purposes. All information on non-shortlisted applicants will be destroyed after 6 months from the submission of their applications.", "employment_types": ["Full Time", "Contract"], "selling_points": [], "locations": ["Shatin Area"], "categories": ["Admin & HR", "Clerical / Admin Staff", "Public / Civil", "Social Services - Community / Non-profit Organization", "Others"], "post_time": "2022-01-13T18:54:53Z", "salary": {"currency": null, "max": null, "min": null, "period": "monthly", "term": null}, "salary_visible": false, "title_keywords": ["administration assistant", "\u884c\u653f\u52a9\u7406"], "responsibilities": ["other duties", "regulatory requirements", "compliance", "monitoring", "inspection", "senior management", "insurance", "administration"], "requirements": {"degrees": ["degree", "bachelor"], "majors": ["actuarial science", "finance", "economics", "statistics", "related disciplines", "accounting"], "languages": ["putonghua", "english", "chinese"], "language_level": ["advantage", "proficiency"], "hard_skills": ["cpa", "problem-solving"], "soft_skills": ["communication skills", "work independently", "confidence", "under pressure", "problem-solving", "collaborative", "interpersonal"], "languages_combined": [{"language": "putonghua", "language_level": ["proficiency", "advantage"]}, {"language": "english", "language_level": []}, {"language": "chinese", "language_level": []}]}, "experience_required": {"duration": ["minimum 5 years"], "field": ["agency", "insurance"]}}, {"job_id": "100003009046115", "location_code": "hk", "company": "Hong Kong Sheng Kung Hui Welfare Council Limited", "job_title": "\u5bbf\u820d\u5c0e\u5e2b Hostel Instructor \u4e2d\u5ea6\u667a\u969c\u4eba\u58eb\u5bbf\u820d (Ref: PGR/HI-HMMH/20210910-16)", "description": "\u8981\u6c42\ufe30\n\n\u5927\u5c08\u7a0b\u5ea6\u6216\u4ee5\u4e0a\n\u4e2d\u5b78\u6703\u8003\u4e94\u79d1\u5408\u683c(\u5305\u62ec\u4e2d\u6587\u53ca\u82f1\u6587(\u8ab2\u7a0b\u4e59))\u6216\u4ee5\u4e0a\u6210\u7e3e\uff0c\u6216\u4e2d\u5b78\u6587\u6191\u8003\u8a66\u4e94\u79d1\u8003\u7372\u7b2c2\u7d1a\u6216\u540c\u7b49\u7b49\u7d1a\n\u5177\u4e09\u5e74\u6216\u4ee5\u4e0a\u76f8\u95dc\u5de5\u4f5c\u7d93\u9a57\u53ca\u826f\u597d\u6e9d\u901a\u6280\u5de7\n\u719f\u6089\u4e2d\u82f1\u6587\u96fb\u8166\u6587\u66f8\u8655\u7406\n\u8077\u8cac\ufe30\n\n\u8ca0\u8cac\u5354\u52a9\u652f\u63f4\u670d\u52d9\u5718\u968a\u4e4b\u884c\u653f\u6587\u66f8\u3001\u4eba\u529b\u8cc7\u6e90\u53ca\u8ca1\u52d9\u7b49\u5de5\u4f5c\u3002\n\u4e94\u5929\u5de5\u4f5c\u8f2a\u4f11\n\n\u5168\u8077\u54e1\u5de5\u53ef\u4eab\u6709\u4ee5\u4e0b\u5b8c\u5584\u798f\u5229\uff1a\n\n\u53ef\u4eab\u6709\u6709\u85aa\u5e74\u504714\u5929\u3001\u516c\u773e\u5047\u671f17\u5929\u3001\u5a5a\u5047\u3001\u5206\u5a29\u5047\u3001\u6069\u6064\u5047\u3001\u4f8d\u7522\u5047\u3001\u8d85\u6642\u5de5\u4f5c\u88dc\u5047\u3001\u514d\u8cbb\u9ad4\u6aa2\u3001\u91ab\u7642\u4fdd\u96aa\u3001\u4eba\u58fd\u4fdd\u96aa\u3001\u91ab\u7642\u512a\u60e0\u3001\u50f1\u4e3b\u5f37\u7a4d\u91d1\u4f9b\u6b3e\u6309\u5e74\u8cc7\u6700\u9ad8\u53ef\u905e\u589e\u81f315%\u3001\u5728\u8077\u57f9\u8a13\u53ca\u826f\u597d\u6649\u5347\u968e\u68af\u7b49\u3002\n\n\u6709\u610f\u8005\u8acb\u5177\u5c65\u6b77\u5bc4(\u4fe1\u5c01\u9762\u53ca\u4fe1\u5167\u8acb\u8a3b\u660e\u8077\u4f4d\u7de8\u865f)\ufe30\u65b0\u754c\u6c99\u7530\u5713\u6d32\u89d2\u8def13A \u2013\u00a0\u9999\u6e2f\u8056\u516c\u6703\u5f35\u570b\u4eae\u4f09\u5137\u5b89\u8001\u670d\u52d9\u5927\u6a13\u7763\u5c0e\u4e3b\u4efb\u6536\u6216\u6309\"Apply Now\"\u3002\u7533\u8acb\u4eba\u4e4b\u7be9\u9078\u5c07\u6703\u5373\u6642\u9032\u884c\u76f4\u81f3\u4e8c\u96f6\u4e8c\u4e8c\u5e74\u4e00\u6708\u4e8c\u5341\u516b\u65e5\u6216\u6709\u95dc\u8077\u4f4d\u7a7a\u7f3a\u5df2\u88ab\u586b\u88dc\u70ba\u6b62\u3002\uff08\u203b\u5165\u8077\u85aa\u916c\u4e43\u6309\u5b78\u6b77\u53ca\u5de5\u4f5c\u7d93\u9a57\u800c\u8a02\u3002\uff09\n\n\n\u4e00\u5207\u7533\u8acb\u8cc7\u6599\u7d55\u5c0d\u4fdd\u5bc6\u53ca\u53ea\u7528\u4f5c\u62db\u8058\u6709\u95dc\u8077\u4f4d\u3002\u5982\u65bc\u5ee3\u544a\u520a\u767b\u5f8c\u516d\u500b\u6708\u5167\u4ecd\u672a\u7372\u672c\u6703\u56de\u8986\uff0c\u5373\u5176\u7533\u8acb\u672a\u7372\u8003\u616e\uff0c\u800c\u7533\u8acb\u4eba\u4e4b\u500b\u4eba\u8cc7\u6599\u4ea6\u5c07\u5728\u5b8c\u6210\u62db\u8058\u7a0b\u5e8f\u5f8c\u92b7\u6bc0\u3002\u5982\u6b32\u53c3\u8003\u5354\u6703\u8cc7\u6599\uff0c\u8acb\u767b\u5165\u7db2\u5740\ufe30http://www.skhwc.org.hk\n\n\n\n", "employment_types": ["Full Time", "Contract"], "selling_points": [], "locations": ["Tuen Mun Area"], "categories": ["Public / Civil", "Social Services - Community / Non-profit Organization", "Others"], "post_time": "2022-01-13T18:55:12Z", "salary": {"currency": null, "max": null, "min": null, "period": "monthly", "term": null}, "salary_visible": false, "title_keywords": ["\u5bbf\u820d\u5c0e\u5e2b", "hostel instructor"], "responsibilities": [], "requirements": {"degrees": [], "majors": [], "languages": [], "language_level": [], "hard_skills": [], "soft_skills": [], "languages_combined": []}, "experience_required": {"duration": [], "field": []}}, {"job_id": "100003009045603", "location_code": "hk", "company": "Temptation Taste Confectionery Limited", "job_title": "\u5e97\u52d9\u52a9\u7406(\u99ac\u978d\u5c71\u5206\u5e97)", "description": "\u689d\u4ef6\n\n\u4e2d\u5b78\u6703\u8003\u4e2d\u6587\u53ca\u82f1\u6587 (\u8ab2\u7a0b\u4e59) \u5408\u683c\u6216\u4e2d\u5b78\u6587\u6191\u8003\u8a66\u540c\u7b49\u7b49\u7d1a\n\u719f\u6089\u4e2d\u82f1\u6587\u96fb\u8166\u6587\u66f8\u8655\u7406\n\u5177\u5fa9\u5eb7\u670d\u52d9\u53ca\u7763\u5c0e\u524d\u7dda\u54e1\u5de5\u7d93\u9a57\u8005\u512a\u5148\n\n\u8077\u8cac\n\n\u8ca0\u8cac\u65bc\u4e2d\u5ea6\u667a\u969c\u4eba\u58eb\u670d\u52d9\u55ae\u4f4d\u8a08\u5283\u53ca\u5e36\u9818\u6d3b\u52d5\uff0c\u4e26\u5354\u52a9\u57f7\u884c\u500b\u6848\u767c\u5c55\u8a08\u5283\u7b49\u5de5\u4f5c\uff0c\u9808\u8f2a\u73ed\u5de5\u4f5c\n\n\n\u5168\u8077\u54e1\u5de5\u53ef\u4eab\u6709\u4ee5\u4e0b\u5b8c\u5584\u798f\u5229\uff1a\n\u6709\u85aa\u5e74\u5047 17 \u5929\u3001\u516c\u773e\u5047\u671f 17 \u5929\u3001\u5a5a\u5047\u3001\u5206\u5a29\u5047\u3001\u6069\u6064\u5047\u3001\u4f8d\u7522\u5047\u3001\u8d85\u6642\u5de5\u4f5c\u88dc\u5047\u3001\u514d\u8cbb\u9ad4\u6aa2\u3001\u91ab\u7642\u4fdd\u96aa\u3001\u4eba\u58fd\u4fdd\u96aa\u3001\u91ab\u7642\u512a\u60e0\u3001\u50f1\u4e3b\u5f37\u7a4d\u91d1\u4f9b\u6b3e\u6309\u5e74\u8cc7\u6700\u9ad8\u53ef\u905e\u589e\u81f3 15%\u3001\u5728\u8077\u57f9\u8a13\u53ca\u826f\u597d\u6649\u5347\u968e\u68af\u7b49\u3002\n\n\u6709\u610f\u8005\u8acb\u5177\u5c65\u6b77\u53ca\u5217\u660e\u671f\u671b\u85aa\u916c\u5bc4\ufe30\u65b0\u754c\u5c6f\u9580\u9707\u5bf0\u8def82\u865f\u00a0\u2013\u00a0\u5eb7\u6069\u5712\u4eba\u529b\u8cc7\u6e90\u53ca\u884c\u653f\u7d93\u7406\u6536\u6216\u6309\"Apply Now\"\u3002\u7533\u8acb\u4eba\u4e4b\u7be9\u9078\u5c07\u6703\u5373\u6642\u9032\u884c\u76f4\u81f3\u4e8c\u96f6\u4e8c\u4e8c\u5e74\u4e00\u6708\u4e8c\u5341\u516b\u65e5\u6216\u6709\u95dc\u8077\u4f4d\u7a7a\u7f3a\u5df2\u88ab\u586b\u88dc\u70ba\u6b62\u3002\n\n\u4e00\u5207\u7533\u8acb\u8cc7\u6599\u7d55\u5c0d\u4fdd\u5bc6\u53ca\u53ea\u7528\u4f5c\u62db\u8058\u6709\u95dc\u8077\u4f4d\u3002\u5982\u7533\u8acb\u8005\u5728\u622a\u6b62\u65e5\u671f\u5f8c\u516b\u661f\u671f\u5167\u4ecd\u672a\u7372\u96fb\u8a71\u7d04\u898b\u8005\uff0c\u5176\u7533\u8acb\u53ef\u4f5c\u843d\u9078\u8ad6\uff0c\u6055\u4e0d\u53e6\u51fd\u901a\u77e5\uff0c\u672c\u798f\u5229\u5354\u6703\u5c07\u4fdd\u5b58\u7533\u8acb\u6587\u4ef6\u4e0d\u8d85\u904e\u516d\u500b\u6708\u3002\u5982\u6b32\u53c3\u8003\u5354\u6703\u8cc7\u6599\uff0c\u8acb\u767b\u5165\u7db2\u5740 :\u00a0http://www.skhwc.org.hk", "employment_types": ["Full Time"], "selling_points": [], "locations": ["Not Specified"], "categories": ["Admin & HR", "Administration / Operation Manager", "Others", "Junior Executive", "Public / Civil", "Others"], "post_time": "2022-01-13T08:11:12Z", "salary": {"currency": null, "max": null, "min": null, "period": "monthly", "term": null}, "salary_visible": false, "title_keywords": [], "responsibilities": [], "requirements": {"degrees": [], "majors": [], "languages": [], "language_level": [], "hard_skills": [], "soft_skills": [], "languages_combined": []}, "experience_required": {"duration": [], "field": []}}, {"job_id": "100003009051328", "location_code": "hk", "company": "Insurance Authority", "job_title": "Manager (Long Term Business)", "description": "\n\u8077\u8cac :\u8ca0\u8cac\u5e97\u8216\u65e5\u5e38\u5de5\u4f5c, \u63a8\u5ee3\u53ca\u92b7\u552e\u96f6\u98df\u53ca\u6dbc\u679c, \u6536\u9280, \u6536\u8ca8, \u8ca8\u54c1\u4e0a\u67b6\u7b49\n\n\u8cc7\u6b77 :\u4e2d\u4e00\u7a0b\u5ea6; 1\u5e74\u7d93\u9a57; \u4e00\u822c\u7cb5\u8a9e; \u61c2\u8b80\u5beb\u4e2d\u6587; \u5c0d\u5de5\u4f5c\u6709\u71b1\u8aa0, \u6709\u79ae, \u6709\u8cac\u4efb\u5fc3\n\n\u5f85\u9047 :\u6bcf\u6708$13,500 - $15,500,\u6709\u52e4\u5de5\u734e\u91d1,\u751f\u65e5\u5047,\u54e1\u5de5\u8cfc\u7269\u512a\u60e0,\u65b0\u4eba\u734e,\u6649\u5347\u6a5f\u6703,\u71df\u696d\u734e\u91d1\u53ca\u6bcf\u6708\u5168\u52e4\u4eab\u6709\u984d\u5916\u5047\u671f1\u5929, \u4e0a\u534811\u6642\u81f3\u4e0b\u53489\u6642\u534a, \u6bcf\u9031\u5de5\u4f5c5\u5929\u81f36\u5929,\u8f2a\u73ed,\u8f2a\u4f11, \u6bcf\u5929\u5de5\u4f5c 8.5 \u5c0f\u6642, \u7528\u81b3\u6642\u959360\u5206\u9418\n\n\u7533\u8acb\u9808\u77e5 :\u6c42\u8077\u8005\u53ef\u81f4\u96fb39563729\u8207\u5473\u4e4b\u8a98\u60d1\u6709\u9650\u516c\u53f8\u674e\u5c0f\u59d0\u806f\u7d61\u3002\n\n", "employment_types": ["Full Time", "Permanent"], "selling_points": [], "locations": ["Southern Area"], "categories": ["Accounting", "Audit", "Insurance", "Actuarial", "Public / Civil", "Others"], "post_time": "2022-01-15T09:05:38Z", "salary": {"currency": null, "max": null, "min": null, "period": "monthly", "term": null}, "salary_visible": false, "title_keywords": ["manager"], "responsibilities": [], "requirements": {"degrees": [], "majors": [], "languages": [], "language_level": [], "hard_skills": [], "soft_skills": [], "languages_combined": []}, "experience_required": {"duration": [], "field": []}}, {"job_id": "100003009040562", "location_code": "hk", "company": "The Hong Kong Anti-Cancer Society", "job_title": "Social Worker (Cancer Survivorship Care Project)", "description": "Reporting to the Senior Manager (Long Term Business), the incumbent will assume the following:\n\nKey Responsibilities\n\nPerform prudential supervision of authorized life insurers\u00a0\nParticipate in conducting inspection and monitoring life insurers' compliance with regulatory requirements\nPerform other duties as assigned by senior management to facilitate the administration of the statutory functions of IA\nRequirements\n\nA Bachelor\u2019s degree or professional qualification in actuarial science, finance, accounting\u00a0or related disciplines. Qualified actuary is recommended\nMinimum 5 years\u2019 relevant experience in insurance, finance, accounting or regulatory\u00a0fields. Working experience in actuarial practices is preferable\nStrong analytical, interpersonal and communication skills\nGood command of English and Chinese\n\nRemuneration Package\nA competitive remuneration package commensurate with the successful candidate\u2019s experience and qualifications will be offered.\n\nApplication\nReview of the applications will start as soon as possible and continue until 28\u00a0January 2022, or until the post is filled. Interested applicants may send a letter of application quoting the reference number, together with a full resume stating current and expected salaries by clicking \"Apply Now\".\n\nThe Insurance Authority is an equal opportunities employer. Applicants not invited for an interview within 2 months from the closing date may assume their applications unsuccessful. Applications may be considered for other suitable positions within IA. All applications will be handled in strict confidence and the information collected will only be used for recruitment purposes. All information on non-shortlisted applicants will be destroyed after 6 months from the close of applications.", "employment_types": ["Full Time"], "selling_points": [], "locations": ["Not Specified"], "categories": ["Public / Civil", "Social Services - Community / Non-profit Organization", "Others"], "post_time": "2022-01-12T02:46:56Z", "salary": {"currency": null, "max": null, "min": null, "period": "monthly", "term": null}, "salary_visible": false, "title_keywords": ["social worker"], "responsibilities": ["perform other duties", "regulatory requirements", "compliance", "monitoring", "inspection", "senior management", "administration"], "requirements": {"degrees": ["degree", "bachelor"], "majors": ["related disciplines", "finance", "accounting", "actuarial science"], "languages": ["english", "chinese"], "language_level": ["good command"], "hard_skills": [], "soft_skills": ["communication skills", "confidence", "interpersonal"], "languages_combined": [{"language": "english", "language_level": ["good command"]}, {"language": "chinese", "language_level": ["good command"]}]}, "experience_required": {"duration": ["minimum 5 years"], "field": ["finance", "insurance", "relevant experience", "accounting"]}}, {"job_id": "100003009045365", "location_code": "hk", "company": "People Service Centre Limited", "job_title": "\u793e\u6703\u5de5\u4f5c\u54e1 (2 \u540d)", "description": "\nThe Project is funded by The Hong Kong Jockey Club Charities Trust.\n\nResponsibilities:\nManage a caseload according to the standard mode of service delivery in the cancer survivorship care programme\nCarry out assessment for survivors and caregivers and devise plan of intervention and support based on the patients\u2019 personal needs and mobilise resources to aid their coping\nCarry out telephone counselling and outreach/face-to-face visits (home, hospital, centre, etc.) to survivors and caregivers to strengthen self-management skills, alleviate emotional distress and rebuild confidence\nCarry out life review with the patients/families to reflect on their contribution to family, friends or society\nRun and facilitate Integrated Body-Mind-Spirit/wellness/self-empowerment programmes for patients and caregivers\nOrganise and run local support meetings and family outings\nRefer for professional consultation or tangible services whenever appropriate or mobilise other community resources in support of the survivorship\nEndeavour to fulfil their last wish, e.g. a family album, lunch with family or to witness the wedding ceremony of their beloved son/daughter. At the appropriate opportunity, will discuss the funeral arrangement to give peace of mind to patient and family\nDocument all contacts/communications with patients and caregivers\nCoach and supervise Programme Assistant and volunteers\nCarry out duties as assigned by the Project Director or the Project Manager\n\nRequirement s :\nRegistered Social Worker by the Hong Kong Social Workers Registration Board\nExperience in working with cancer patients will be an advantage\nProficiency in both spoken and written English and Chinese Benefits:\n10% of total basic salary as contract-end gratuity\n14-18 days Annual Leave\nBirthday Leave\nPublic Holidays\nMaternity Leave\nPaternity Leave\nCompassionate Leave\nMedical Benefit\nMPF\nOn-job Training\nFree Shuttle Bus Service\nFree meal provided\nLong Service Award Successful candidates will be offered a renewable contract term appointment upon completion of contract with satisfactory performance. Interested parties, MUST download the application form at www.hkacs.org.hk and submit with full resume to the Chief Executive Officer, The Hong Kong Anti-Cancer Society, 30 Nam Long Shan Road, Wong Chuk Hang, Hong Kong or by email to [our mailbox through Apply Now] or by fax to 3921 3822 .\n\n(All personal information provided will be used for recruitment purpose only, candidates not being contacted within 3 months are deemed not suitable. Personal information of candidates will be destroyed after the recruitment process.)\n\n", "employment_types": ["Full Time"], "selling_points": [], "locations": ["Sham Shui Po"], "categories": ["Public / Civil", "Social Services - Community / Non-profit Organization", "Others"], "post_time": "2022-01-13T07:42:04Z", "salary": {"currency": null, "max": null, "min": null, "period": "monthly", "term": null}, "salary_visible": false, "title_keywords": [], "responsibilities": ["service delivery", "management", "communications with", "review", "plan"], "requirements": {"degrees": [], "majors": [], "languages": [], "language_level": [], "hard_skills": [], "soft_skills": [], "languages_combined": []}, "experience_required": {"duration": [], "field": []}}, {"job_id": "100003009041923", "location_code": "hk", "company": "Caritas - Hong Kong", "job_title": "Social Worker (ASWO)(Application Code:NYC/CCASWO003)", "description": "\n\u00a0 \u4e3b\u8981\u8077\u8cac\uff1a\n\u2022 \u4ee5\u793e\u5340\u5de5\u4f5c\u624b\u6cd5\u63a8\u52d5\u5730\u5340\u7d44\u7e54\u5de5\u4f5c\uff1b\n\u2022 \u670d\u52d9\u5c0d\u8c61\u70ba\u57fa\u5c64\u5bb6\u9577\u53ca\u5152\u7ae5\u3001\u9577\u8005\uff1b\n\u2022 \u8209\u8fa6\u793e\u5340\u6216\u7dda\u4e0a\u6d3b\u52d5\u4ee5\u5efa\u7acb\u793e\u5340\u7db2\u7d61\uff0c\u9023\u7d50\u5408\u4f5c\u5718\u9ad4\uff1b\n\u61c9\u5fb5\u8cc7\u6b77\u53ca\u8981\u6c42\uff1a\n\u2022 \u793e\u5de5\u526f\u5b78\u4f4d\u6216\u4ee5\u4e0a\uff0c\u4e00\u5e74\u793e\u5340\u5de5\u4f5c\u7d93\u9a57\uff1b\n\u2022 \u5177\u826f\u597d\u6e9d\u901a\u548c\u4eba\u969b\u95dc\u4fc2\u6280\u5de7\uff0c\u64c5\u65bc\u8207\u4e0d\u540c\u55ae\u4f4d\u5354\u4f5c\uff1b\n\u2022 \u6709\u793e\u5340\u5de5\u4f5c\u53ca\u5c45\u6c11\u7d44\u7e54\u7d93\u9a57\u512a\u5148\u3002\n\u4e3b\u8981\u8fa6\u516c\u5ba4\u65bc\u6df1\u6c34\u57d7\u6216\u571f\u74dc\u7063\uff0c\u9700\u8981\u8de8\u5340\u57df\u5de5\u4f5c\uff0c\u665a\u9593\u53ca\u5916\u51fa\u5de5\u4f5c\u3002\u4e94\u5929\u5de5\u4f5c\uff0c14 \u5929\u5e74\u5047\u3002\n\n", "employment_types": ["Contract"], "selling_points": [], "locations": ["Not Specified"], "categories": ["Public / Civil", "Social Services - Community / Non-profit Organization", "Others"], "post_time": "2022-01-12T04:41:31Z", "salary": {"currency": null, "max": null, "min": null, "period": "monthly", "term": null}, "salary_visible": false, "title_keywords": ["social worker"], "responsibilities": [], "requirements": {"degrees": [], "majors": [], "languages": [], "language_level": [], "hard_skills": [], "soft_skills": [], "languages_combined": []}, "experience_required": {"duration": [], "field": []}}, {"job_id": "100003009046134", "location_code": "hk", "company": "Hong Kong Sheng Kung Hui Welfare Council Limited", "job_title": "\u5bbf\u820d\u5c0e\u5e2b Hostel Instructor \u56b4\u91cd\u667a\u969c\u4eba\u58eb\u5bbf\u820d\u3014\u7de8\u865f\uff1aPGR/HI-HSMH/20200110-92\u3015", "description": "\u689d\u4ef6\n\n\u4e2d\u5b78\u6703\u8003\u4e2d\u6587\u53ca\u82f1\u6587 (\u8ab2\u7a0b\u4e59) \u5408\u683c\u6216\u4e2d\u5b78\u6587\u6191\u8003\u8a66\u540c\u7b49\u7b49\u7d1a\n\u719f\u6089\u4e2d\u82f1\u6587\u96fb\u8166\u6587\u66f8\u8655\u7406\n\u5177\u5fa9\u5eb7\u670d\u52d9\u53ca\u7763\u5c0e\u524d\u7dda\u54e1\u5de5\u7d93\u9a57\u8005\u512a\u5148\n\n\u8077\u8cac\n\n\u8ca0\u8cac\u65bc\u56b4\u91cd\u667a\u969c\u4eba\u58eb\u5bbf\u820d\u8a08\u5283\u53ca\u5e36\u9818\u6d3b\u52d5\uff0c\u4e26\u5354\u52a9\u57f7\u884c\u500b\u6848\u767c\u5c55\u8a08\u5283\u7b49\u5de5\u4f5c\uff0c\u9808\u8f2a\u73ed\u5de5\u4f5c\n\n\n\u5168\u8077\u54e1\u5de5\u53ef\u4eab\u6709\u4ee5\u4e0b\u5b8c\u5584\u798f\u5229\uff1a\n\u6709\u85aa\u5e74\u5047 17 \u5929\u3001\u516c\u773e\u5047\u671f 17 \u5929\u3001\u5a5a\u5047\u3001\u5206\u5a29\u5047\u3001\u6069\u6064\u5047\u3001\u4f8d\u7522\u5047\u3001\u8d85\u6642\u5de5\u4f5c\u88dc\u5047\u3001\u514d\u8cbb\u9ad4\u6aa2\u3001\u91ab\u7642\u4fdd\u96aa\u3001\u4eba\u58fd\u4fdd\u96aa\u3001\u91ab\u7642\u512a\u60e0\u3001\u50f1\u4e3b\u5f37\u7a4d\u91d1\u4f9b\u6b3e\u6309\u5e74\u8cc7\u6700\u9ad8\u53ef\u905e\u589e\u81f3 15%\u3001\u5728\u8077\u57f9\u8a13\u53ca\u826f\u597d\u6649\u5347\u968e\u68af\u7b49\u3002\n\n\u6709\u610f\u8005\u8acb\u5177\u5c65\u6b77\u53ca\u5217\u660e\u671f\u671b\u85aa\u916c\u5bc4\ufe30\u65b0\u754c\u5c6f\u9580\u9707\u5bf0\u8def82\u865f\u00a0\u2013\u00a0\u5eb7\u6069\u5712\u4eba\u529b\u8cc7\u6e90\u53ca\u884c\u653f\u7d93\u7406\u6536\u6216\u6309\"Apply Now\"\u3002\u7533\u8acb\u4eba\u4e4b\u7be9\u9078\u5c07\u6703\u5373\u6642\u9032\u884c\u76f4\u81f3\u4e8c\u96f6\u4e8c\u4e8c\u5e74\u4e00\u6708\u4e8c\u5341\u516b\u65e5\u6216\u6709\u95dc\u8077\u4f4d\u7a7a\u7f3a\u5df2\u88ab\u586b\u88dc\u70ba\u6b62\u3002\n\n\u4e00\u5207\u7533\u8acb\u8cc7\u6599\u7d55\u5c0d\u4fdd\u5bc6\u53ca\u53ea\u7528\u4f5c\u62db\u8058\u6709\u95dc\u8077\u4f4d\u3002\u5982\u7533\u8acb\u8005\u5728\u622a\u6b62\u65e5\u671f\u5f8c\u516b\u661f\u671f\u5167\u4ecd\u672a\u7372\u96fb\u8a71\u7d04\u898b\u8005\uff0c\u5176\u7533\u8acb\u53ef\u4f5c\u843d\u9078\u8ad6\uff0c\u6055\u4e0d\u53e6\u51fd\u901a\u77e5\uff0c\u672c\u798f\u5229\u5354\u6703\u5c07\u4fdd\u5b58\u7533\u8acb\u6587\u4ef6\u4e0d\u8d85\u904e\u516d\u500b\u6708\u3002\u5982\u6b32\u53c3\u8003\u5354\u6703\u8cc7\u6599\uff0c\u8acb\u767b\u5165\u7db2\u5740 :\u00a0http://www.skhwc.org.hk", "employment_types": ["Full Time", "Contract"], "selling_points": [], "locations": ["Tuen Mun Area"], "categories": ["Public / Civil", "Social Services - Community / Non-profit Organization", "Others"], "post_time": "2022-01-13T18:55:12Z", "salary": {"currency": null, "max": null, "min": null, "period": "monthly", "term": null}, "salary_visible": false, "title_keywords": ["\u5bbf\u820d\u5c0e\u5e2b", "hostel instructor"], "responsibilities": [], "requirements": {"degrees": [], "majors": [], "languages": [], "language_level": [], "hard_skills": [], "soft_skills": [], "languages_combined": []}, "experience_required": {"duration": [], "field": []}}, {"job_id": "100003009046164", "location_code": "hk", "company": "Hong Kong Sheng Kung Hui Welfare Council Limited", "job_title": "\u7a0b\u5e8f\u52a9\u7406 (\u534a\u8077) Part-time Programme Worker\u3014\u7de8\u865f\uff1aICCMW/PTPW/20211210-6\u3015", "description": "\u689d\u4ef6\ufe30\n\nDSE\uff0f\u4e2d\u4e94\u7a0b\u5ea6\u6216\u4ee5\u4e0a\uff0f\u6216\u5177\u540c\u7b49\u5b78\u6b77\n\u719f\u6089\u4e2d\u82f1\u6587\u96fb\u8166\u6587\u66f8\u8655\u7406\n\u5c0d\u6703\u8a08\u5de5\u4f5c\u6709\u8a8d\u8b58\n\u5177\u5169\u5e74\u4ee5\u4e0a\u5b89\u8001\u670d\u52d9\u6216\u9662\u820d\u7d93\u9a57\u512a\u5148\n\u5177\u6587\u66f8\u5de5\u4f5c\u53ca\u63a8\u884c\u6d3b\u52d5\u7d93\u9a57\u8005\u512a\u5148\n\n\u8077\u8cac\ufe30\n\n\u8ca0\u8cac\u5354\u52a9\u8209\u8fa6\u53ca\u63a8\u884c\u5c0f\u7d44\u6d3b\u52d5\uff0c\u4e26\u5354\u52a9\u4e2d\u5fc3\u4e00\u822c\u6587\u66f8\u53ca\u65e5\u5e38\u904b\u4f5c\u7b49\u76f8\u95dc\u5de5\u4f5c\u3002\n\n\n\n\u6709\u610f\u8005\u8acb\u5177\u5c65\u6b77(\u4fe1\u5c01\u9762\u53ca\u4fe1\u5167\u8acb\u8a3b\u660e\u8077\u4f4d\u7de8\u865f)\u5bc4\ufe30\u65b0\u754c\u5c6f\u9580\u9707\u5bf0\u8def82\u865f \u2013 \u5eb7\u6069\u5712\u4eba\u529b\u8cc7\u6e90\u53ca\u884c\u653f\u7d93\u7406\u6536\u6216\u6309\"Apply Now\"\u3002\u7533\u8acb\u4eba\u4e4b\u7be9\u9078\u5c07\u6703\u5373\u6642\u9032\u884c\u76f4\u81f3\u4e8c\u96f6\u4e8c\u4e8c\u5e74\u4e00\u6708\u4e8c\u5341\u516b\u65e5\u6216\u6709\u95dc\u8077\u4f4d\u7a7a\u7f3a\u5df2\u88ab\u586b\u88dc\u70ba\u6b62\u3002\u00a0\n\n\n\u4e00\u5207\u7533\u8acb\u8cc7\u6599\u7d55\u5c0d\u4fdd\u5bc6\u53ca\u53ea\u7528\u4f5c\u62db\u8058\u6709\u95dc\u8077\u4f4d\u3002\u5982\u7533\u8acb\u8005\u5728\u622a\u6b62\u65e5\u671f\u5f8c\u516b\u661f\u671f\u5167\u4ecd\u672a\u7372\u96fb\u8a71\u7d04\u898b\u8005\uff0c\u5176\u7533\u8acb\u53ef\u4f5c\u843d\u9078\u8ad6\uff0c\u6055\u4e0d\u53e6\u51fd\u901a\u77e5\uff0c\u672c\u798f\u5229\u5354\u6703\u5c07\u4fdd\u5b58\u7533\u8acb\u6587\u4ef6\u4e0d\u8d85\u904e\u516d\u500b\u6708\u3002\u5982\u6b32\u53c3\u8003\u5354\u6703\u8cc7\u6599\uff0c\u8acb\u767b\u5165\u7db2\u5740:\u00a0http://www.skhwc.org.hk", "employment_types": ["Full Time", "Contract"], "selling_points": [], "locations": ["Tuen Mun Area"], "categories": ["Public / Civil", "Social Services - Community / Non-profit Organization", "Others"], "post_time": "2022-01-13T18:55:13Z", "salary": {"currency": null, "max": null, "min": null, "period": "monthly", "term": null}, "salary_visible": false, "title_keywords": [], "responsibilities": [], "requirements": {"degrees": [], "majors": [], "languages": [], "language_level": [], "hard_skills": [], "soft_skills": [], "languages_combined": []}, "experience_required": {"duration": [], "field": []}}, {"job_id": "100003009044593", "location_code": "hk", "company": "Yan Oi Tong Ltd", "job_title": "\u793e\u6703\u5de5\u4f5c\u5e79\u4e8bI (\u8077\u4f4d\u7de8\u865f: DECC/SWI0104/220113)", "description": "\n\u8077\u8cac :\u8ca0\u8cac\u807d\u529b\u4e2d\u5fc3\u4e00\u822c\u65e5\u5e38\u904b\u4f5c,\u5982\u63a5\u96fb\u8a71,\u63a5\u5f85\u5ba2\u4eba,\u8cc7\u6599\u8f38\u5165,\u89e3\u7b54\u5ba2\u4eba\u67e5\u8a62\n\n\u8cc7\u6b77 :\u5c0f\u4e94\u7a0b\u5ea6; \u826f\u597d\u7cb5\u8a9e; \u4e00\u822c\u666e\u901a\u8a71; \u4e00\u822c\u82f1\u8a9e; \u61c2\u8b80\u5beb\u4e2d\u6587; \u7565\u61c2\u8b80\u5beb\u82f1\u6587; \u61c2MS Word; \u61c2MS Excel; \u61c2\u4e2d\u82f1\u6587\u96fb\u8166\u64cd\u4f5c; \u61c2\u5009\u9821/\u901f\u6210\u8f38\u5165\u6cd5; \u5177\u96f6\u552e\u53ca\u8a3a\u6240\u63a5\u5f85\u7d93\u9a57\u512a\u5148, \u6709\u8010\u6027,\u6709\u79ae\u8c8c,\u4e3b\u52d5\n\n\u5f85\u9047 :\u6bcf\u6708$8,500, \u6709\u9280\u884c\u5047\u671f, \u661f\u671f\u4e00\u81f3\u516d: \u4e0a\u53489\u6642\u81f3\u4e0b\u53486\u6642, \u6bcf\u9031\u5de5\u4f5c6\u5929, \u6bcf\u5929\u5de5\u4f5c 8 \u5c0f\u6642, 1\u5c0f\u6642\u5348\u81b3\u6642\u9593\n\n\u7533\u8acb\u9808\u77e5 :\u6c42\u8077\u8005\u53ef\u50b3\u771f(27350840)\u6216\u96fb\u90f5(Apply Now)\u5c65\u6b77\u8868\u7d66\u8c9d\u723e\u901a\u807d\u529b\u4e2d\u5fc3\u3002\u5982\u8981\u7d22\u53d6\u6536\u96c6\u500b\u4eba\u8cc7\u6599\u8072\u660e, \u8acb\u8207\u9673\u5148\u751f(Email)\u806f\u7d61\u3002\n\n", "employment_types": ["Full Time", "Contract"], "selling_points": ["\u6301\u653f\u5e9c\u8a8d\u53ef\u793e\u6703\u5de5\u4f5c\u5b78\u4f4d\u6216\u4ee5\u4e0a\u5b78\u6b77\u4e4b\u8a3b\u518a\u793e\u5de5", "\u4e09\u5e74\u6216\u4ee5\u4e0a\u9577\u8005\u670d\u52d9\u7d93\u9a57", "5\u5929\u5de5\u4f5c\uff0c\u6bcf\u9031\u5de5\u4f5c44\u5c0f\u6642"], "locations": ["Tuen Mun Area"], "categories": ["Public / Civil", "Social Services - Community / Non-profit Organization", "Others"], "post_time": "2022-01-13T04:44:30Z", "salary": {"currency": null, "max": null, "min": null, "period": "monthly", "term": null}, "salary_visible": false, "title_keywords": [], "responsibilities": [], "requirements": {"degrees": [], "majors": [], "languages": [], "language_level": [], "hard_skills": ["excel", "word"], "soft_skills": [], "languages_combined": []}, "experience_required": {"duration": [], "field": []}}, {"job_id": "100003009038956", "location_code": "hk", "company": "BELTONE HEARING CENTRE LIMITED", "job_title": "\u807d\u529b\u4e2d\u5fc3\u52a9\u7406", "description": "\n\u8077\u8cac :\u5de1\u67e5\u5bbf\u820d\u74b0\u5883\u5b89\u5168\uff0c\u5354\u52a9\u7167\u9867\u5bbf\u751f\uff0c\u5982\u63db\u7247\u3001\u5982\u5ec1\u3001\u68b3\u6d17\u7b49 (\u90f5\u5bc4\u5730\u5740: \u9999\u6e2f\u8584\u6276\u6797\u9053131\u865f)\n\n\u8cc7\u6b77 :\u5c0f\u516d\u7a0b\u5ea6; \u4e00\u822c\u7cb5\u8a9e; \u7565\u61c2\u8b80\u5beb\u4e2d\u6587; \u5177\u7167\u9867\u50b7\u6b98\u4eba\u58eb\u53ca\u9662\u820d\u670d\u52d9\u7d93\u9a57\u512a\u5148;\u6709\u611b\u5fc3, \u8010\u6027\u548c\u8cac\u4efb\u611f,\u80fd\u7368\u7acb\u5de5\u4f5c\n\n\u5f85\u9047 :\u6bcf\u6708$14,620 - $17,870(\u8996\u4e4e\u5de5\u4f5c\u7d93\u9a57\u800c\u5b9a), \u4e0b\u534810\u6642\u81f3\u4e0a\u53489\u6642\u534a, \u6bcf\u9031\u5de5\u4f5c5\u5929(48\u5c0f\u6642), \u8f2a\u73ed, \u8f2a\u4f11\n\n\u7533\u8acb\u9808\u77e5 :\u6c42\u8077\u8005\u53ef\u96fb\u90f5(Apply Now)/\u50b3\u771f(28728418)/\u90f5\u5bc4\u5c65\u6b77\u8868\u7d66\u5fc3\u5149\u6069\u671b\u5b78\u6821\u3002\u5982\u8981\u7d22\u53d6\u6536\u96c6\u500b\u4eba\u8cc7\u6599\u8072\u660e, \u8acb\u8207\u937e\u5973\u58eb(Email/Fax/Post)\u806f\u7d61\u3002\n\n", "employment_types": ["Full Time"], "selling_points": [], "locations": ["Tsim Sha Tsui"], "categories": ["Admin & HR", "Administration / Operation Manager", "Others", "Junior Executive", "Public / Civil", "Others"], "post_time": "2022-01-11T08:13:05Z", "salary": {"currency": null, "max": null, "min": null, "period": "monthly", "term": null}, "salary_visible": false, "title_keywords": [], "responsibilities": [], "requirements": {"degrees": [], "majors": [], "languages": [], "language_level": [], "hard_skills": [], "soft_skills": [], "languages_combined": []}, "experience_required": {"duration": [], "field": []}}, {"job_id": "100003009045464", "location_code": "hk", "company": "Ebenezer New Hope School", "job_title": "\u5bbf\u820d\u90e8\u7167\u9867\u5de5\u4f5c\u54e1", "description": "\n\u8077\u8cac :\u5354\u52a9\u793e\u5de5\u7c4c\u8fa6\u63d0\u6607\u9752\u5e74\u4eba\u8eab\u5fc3\u9748\u5065\u5eb7\u7684\u5c0f\u7d44\u53ca\u6d3b\u52d5, \u63a8\u5ee3\u7cbe\u795e\u5065\u5eb7\u6559\u80b2; \u900f\u904e\u81ea\u8eab\u751f\u547d\u6545\u4e8b\u5206\u4eab\uff0c\u652f\u63f4\u53ca\u95dc\u9867\u53d7\u60c5\u7dd2\u56f0\u64fe\u7684\u9752\u5e74\u4eba; \u8655\u7406\u4e2d\u5fc3\u65e5\u5e38\u904b\u4f5c\u53ca\u7576\u503c; \u8655\u7406\u7531\u7763\u5c0e\u6307\u6d3e\u7684\u5176\u4ed6\u5de5\u4f5c\uff08\u4e00\u5e74\u76f8\u95dc\u5de5\u4f5c\u7d93\u9a57\u512a\u5148; \u5c0d\u7cbe\u795e\u5065\u5eb7\u6709\u76f8\u95dc\u8a8d\u8b58\u6216\u7d93\u6b77\u512a\u5148\uff09\n\n\u8cc7\u6b77 :\u4e2d\u4e94\u7a0b\u5ea6; \u6703\u8003\u4e94\u79d1\u5408\u683c; \u826f\u597d\u7cb5\u8a9e; \u61c2\u8b80\u5beb\u4e2d\u6587; \u61c2\u8b80\u5beb\u82f1\u6587; \u61c2\u96fb\u8166\u6587\u66f8\u8655\u7406; \u61c2MS Word; \u61c2MS PowerPoint; \u61c2MS Excel; \u6703\u8003/\u6587\u6191\u8a66\u4e2d\u82f1\u6578\u5408\u683c; \u5de5\u4f5c\u4e3b\u52d5\u3001\u6709\u8cac\u4efb\u611f\u3001\u9858\u610f\u63a5\u53d7\u6311\u6230\u3001\u826f\u597d\u7d44\u7e54\u53ca\u6e9d\u901a\u6280\u5de7; \u638c\u63e1\u9752\u5c11\u5e74\u6f6e\u6d41\u6587\u5316\u3001\u719f\u6089\u624b\u5de5\u85dd\u8853\u6216\u5176\u4ed6\u8208\u8da3\u6280\u80fd\n\n\u5f85\u9047 :\u6bcf\u6708$12,915 - $14,600, \u661f\u671f\u4e00\u81f3\u516d: \u4e0a\u53489\u6642\u534a\u81f3\u4e0b\u53486\u664220\u5206\u6216\u661f\u671f\u4e00\u81f3\u516d: \u4e0b\u53481\u664210\u5206\u81f3\u4e0b\u534810\u6642, \u6bcf\u9031\u5de5\u4f5c5\u5929,\u8f2a\u73ed, \u6bcf\u9031\u5de5\u4f5c44\u5c0f\u6642\n\n\u7533\u8acb\u9808\u77e5 :\u6c42\u8077\u8005\u53ef\u96fb\u90f5(Apply Now)\u5c65\u6b77\u8868\u7d66\u9999\u6e2f\u5c0f\u7ae5\u7fa4\u76ca\u6703\u3002\u5982\u8981\u7d22\u53d6\u6536\u96c6\u500b\u4eba\u8cc7\u6599\u8072\u660e, \u8acb\u8207\u6797\u5c0f\u59d0(Email)\u806f\u7d61\u3002\n\n", "employment_types": ["Full Time"], "selling_points": [], "locations": ["Pok Fu Lam"], "categories": ["Public / Civil", "Social Services - Community / Non-profit Organization", "Others", "Others", "Others"], "post_time": "2022-01-13T07:54:40Z", "salary": {"currency": null, "max": null, "min": null, "period": "monthly", "term": null}, "salary_visible": false, "title_keywords": [], "responsibilities": [], "requirements": {"degrees": [], "majors": [], "languages": [], "language_level": [], "hard_skills": ["excel", "word", "powerpoint"], "soft_skills": [], "languages_combined": []}, "experience_required": {"duration": [], "field": []}}, {"job_id": "100003009041797", "location_code": "hk", "company": "The Boys' and Girls' Clubs Association of Hong Kong", "job_title": "\u9752\u5e74\u670b\u8f29\u5de5\u4f5c\u54e1", "description": "\u8077\u8cac Principal Duties:\n\n\u00b7 \u5916\u52e4\u5de5\u4f5c,\u66ff\u5ba2\u6236\u8655\u7406\u87f2\u5bb3\u3001\u9664\u9709\u3001\u6d88\u6bd2\u53ca\u9664\u7532\u919b\u554f\u984c / Outdoor work, provide pest control services and the mould or Disinfection service to our clients\n\n\u9808\u6301\u6709\u8f15\u578b\u8ca8\u8eca\u99d5\u99db\u57f7\u7167 / Holding HK light good vehicle driving license\n\n\u8981\u6c42Requirements:\n\n\u00b7 \u5de5\u4f5c\u6642\u9593 : \u661f\u671f\u4e00\u81f3\u516d / Available to work Monday - Saturdays\n\n\u00b7 \u591c\u73ed: 16:00-02:00 / Night shift: 16:00 -02:00\n\n\u00b7 \u5de5\u4f5c\u5730\u9ede:\u904d\u4f48\u9999\u6e2f\u3001\u4e5d\u9f8d\u3001\u65b0\u754c / Work location: HK, KLN, NT\n\n\u00b7 \u826f\u597d\u6e9d\u901a\u6280\u5de7 / Great communication skills\n\n\u00b7 \u826f\u597d\u7cb5\u8a9e,\u61c2\u8b80\u5beb\u4e2d\u6587, \u7c21\u55ae\u82f1\u8a9e / Fluency in written and spoken Cantonese, fair in English\n\n\u00b7 \u7121\u9700\u7d93\u9a57, \u6b61\u8fce\u7562\u696d\u4eba\u58eb\u53ca\u5973\u58eb\u7533\u8acb / Fresh graduates and Females welcome to apply\n\n\u512a\u539a\u85aa\u916c\u798f\u5229: *Benefits: *\n\n\u00b7\u00a0\u6708\u5165\u53ef\u9054HK$22,000/\u6708 /\u00a0Monthly salary package up to HK$22,000\n\n\u00b7 \u65b0\u4eba\u734e$10,000 / Sign-On Bonus $10,000\n\n\u00b7 \u8868\u73fe\u734e\u91d1 Performance Bonus\n\n\u00b7 \u512a\u539a\u6d25\u8cbc, \u6fc0\u52f5\u734e\u91d1 / Attractive allowance, service leads incentive opportunity\n\n\u00b7 \u52a0\u73ed\u6d25\u8cbc / Paid overtime\n\n\u00b7 12\u5929\u5e74\u5047 / 12 Days Annual Leave\n\n\u00b7 17\u5929\u516c\u773e\u5047\u671f / Public Holidays (17 Days)\n\n\u00b7 \u91ab\u7642\u4fdd\u969c (\u5305\u62ec\u4e2d\u897f\u91ab\u9580\u8a3a\u53ca\u4f4f\u9662\u4fdd\u969c) / Medical insurance (Outpatient , Chinese Herbalist & Acupuncture and In-hospital services)\n\n\u00b7 \u7259\u79d1\u91ab\u7642 / Dental insurance\n\n\u00b7 \u9ad4\u6aa2\u8a08\u5283 / Annual medical check up\n\n\u00b7 \u96d9\u7ce7 / 13 months\u2019 salary\n\n\u00b7 \u5c08\u696d\u57f9\u8a13\u53ca\u826f\u597d\u6649\u5347\u6a5f\u6703 / Offer learning & development and Training program, excellent promotion opportunities, staff recognition awards\n\n\u6709\u610f\u8005\u53ef\u81f4\u96fb2954 6111/ whatsapp 9142 6529\u5b89\u6392\u7d04\u898b\n\nIf anyone wants to shape the future together with us, please contact the HRD via WhatsApp 9142 6529 / Hotline\u00a02954 6111\n\n*******************************************\n\n\u9999\u6e2f\u80fd\u591a\u6f54\u5de1\u8ff4\u62db\u8058\u8eca \u2013 \u5373\u5834\u9762\u8a66, \u7121\u9808\u9810\u7d04\n\n\u65e5\u671f: 1\u670812\u65e5 (\u661f\u671f\u4e09)\n\n\u6642\u9593: 10:00am - 6:00pm\n\n\u5730\u9ede: \u6df1\u6c34\u57d7\u9ec3\u91d1\u5546\u5834\u9580\u5916\n\n\u5de5\u4f5c\u985e\u578b: \u5168\u8077, \u9577\u5de5\n\n\u85aa\u916c: \u6700\u591a\u6bcf\u6708 $22,000.00\n\n\u6642\u9593:\n\n\u591c\u73ed\n\n\u9060\u7a0b\u5de5\u4f5c:\n\n\u5426", "employment_types": ["Full Time"], "selling_points": [], "locations": ["Lai Chi Kok"], "categories": ["Public / Civil", "Social Services - Community / Non-profit Organization", "Others"], "post_time": "2022-01-12T04:23:53Z", "salary": {"currency": null, "max": null, "min": null, "period": "monthly", "term": null}, "salary_visible": false, "title_keywords": [], "responsibilities": ["outdoor work", "control"], "requirements": {"degrees": [], "majors": [], "languages": [], "language_level": [], "hard_skills": [], "soft_skills": [], "languages_combined": []}, "experience_required": {"duration": [], "field": []}}, {"job_id": "100003009043903", "location_code": "hk", "company": "Rentokil Initial Hong Kong Ltd", "job_title": "\u591c\u73ed\u53f8\u6a5f\u6ec5\u87f2\u6280\u8853\u54e1, \u6708\u5165\u53ef\u9054$20K / PC Technician Driver(Night shift) - Salary up to $20K", "description": "\n\u8077\u8cac :\u4e00\u822c\u8a3a\u6240\u52a9\u7406\u5de5\u4f5c, \u8ca0\u8cac\u8a3a\u6240\u65e5\u5e38\u904b\u4f5c\uff0c\u5982\u9810\u7d04\u3001\u767b\u8a18\u53ca\u8655\u7406\u67e5\u8a62, \u914d\u85e5, \u5354\u52a9\u91ab\u751f\u8a3a\u6cbb, \u4e00\u822c\u8a3a\u6240\u6e05\u6f54\n\n\u8cc7\u6b77 :\u4e2d\u4e94\u7a0b\u5ea6; 1\u5e74\u7d93\u9a57; \u826f\u597d\u7cb5\u8a9e; \u4e00\u822c\u666e\u901a\u8a71; \u4e00\u822c\u82f1\u8a9e; \u61c2\u8b80\u5beb\u4e2d\u6587; \u61c2\u8b80\u5beb\u82f1\u6587; \u61c2\u4e2d\u82f1\u6587\u96fb\u8166\u64cd\u4f5c\n\n\u5f85\u9047 :\u6bcf\u6708$13,000 - $15,000, \u6709\u52e4\u5de5\u734e\u91d1, \u9280\u884c\u5047\u671f \u53ca\u5e74\u7d42\u734e\u91d1, \u661f\u671f\u4e00\u81f3\u4e94: \u4e0a\u53489\u6642\u534a\u81f3\u4e0b\u53487\u6642\u53ca\u661f\u671f\u516d: \u4e0a\u53489\u6642\u534a\u81f3\u4e0b\u53482\u6642, \u6bcf\u9031\u5de5\u4f5c5\u5929\u534a\n\n\u7533\u8acb\u9808\u77e5 :\u6c42\u8077\u8005\u53ef\u96fb\u90f5(Apply Now)\u5c65\u6b77\u8868\u7d66\u5efa\u6021(\u9999\u6e2f)\u6709\u9650\u516c\u53f8\u3002\u5982\u8981\u7d22\u53d6\u6536\u96c6\u500b\u4eba\u8cc7\u6599\u8072\u660e, \u8acb\u8207\u9ec3\u5973\u58eb(Email)\u806f\u7d61\u3002\n\n", "employment_types": ["Full Time"], "selling_points": ["\u5916\u52e4\u5de5\u4f5c /  Outdoor work", "\u9808\u6301\u6709\u8f15\u578b\u8ca8\u8eca\u99d5\u99db\u57f7\u7167 / Light good vehicle driving license", "\u7121\u9700\u7d93\u9a57 / Everyone is welcome to apply"], "locations": ["Not Specified"], "categories": ["Others", "Technician", "Public / Civil", "Utilities", "Others"], "post_time": "2022-01-13T02:24:08Z", "salary": {"currency": null, "max": null, "min": null, "period": "monthly", "term": null}, "salary_visible": false, "title_keywords": ["technician"], "responsibilities": [], "requirements": {"degrees": [], "majors": [], "languages": [], "language_level": [], "hard_skills": [], "soft_skills": [], "languages_combined": []}, "experience_required": {"duration": [], "field": []}}, {"job_id": "100003009038880", "location_code": "hk", "company": "JOY ORTHO COMPANY LIMITED", "job_title": "\u8a3a\u6240\u52a9\u7406(\u9aa8\u79d1)", "description": "\n\u2022 \u9999\u6e2f\u4e2d\u5b78\u6703\u8003\u6216\u9999\u6e2f\u4e2d\u5b78\u6587\u6191\u8003\u8a662\u79d1\u5408\u683c\u6216\u4ee5\u4e0a\u6216\u540c\u7b49\u5b78\u6b77\n\u2022 \u5df2\u8a3b\u518a\u70ba\u5e7c\u5152\u5de5\u4f5c\u54e1\uff0c\u4e26\u6301\u6709\u8a8d\u53ef\u5e7c\u5152\u5de5\u4f5c\u4e3b\u7ba1\u8cc7\u6b77\n\u5df2\u6301\u6709\u8a8d\u53ef\u7279\u6b8a\u6559\u80b2\u8a3c\u66f8(\u63a5\u53d7\u7279\u6b8a\u5e7c\u5152\u5de5\u4f5c\u54e1\u5728\u8077\u8a13\u7df4)\u8005\uff0c\u53ef\u984d\u5916\u7372\u767c\u6d25\u8cbc\n\u2022 \u5b9c\u51775\u5e74\u6216\u4ee5\u4e0a\u7279\u6b8a\u5e7c\u5152\u5de5\u4f5c\u54e1\u5de5\u4f5c\u7d93\u9a57\uff1b\u9808\u8f2a\u73ed\n\u2022 \u5354\u52a9\u7ba1\u7406\u5bbf\u820d\u904b\u4f5c\uff1b\u5177\u9662\u820d\u53ca\u884c\u653f\u7ba1\u7406\u5de5\u4f5c\u7d93\u9a57\u512a\u5148\u8003\u616e\n\u5165\u8077\u85aa\u916c\u6309\u76f8\u95dc\u5de5\u4f5c\u7d93\u9a57\u800c\u5b9a\uff1b\u6708\u85aa\u53ef\u9054$40,515\n\u2022 \u53e6\u6bcf\u6708\u6709\u85aa\u91d1\u6d25\u8cbc\n\u2022 \u5de5\u4f5c\u5730\u5340\uff1a\u8343\u7063\n\u622a\u6b62\u65e5\u671f\uff1a2022\u5e741\u670814\u65e5\n\n", "employment_types": ["Full Time"], "selling_points": [], "locations": ["Tsim Sha Tsui"], "categories": ["Admin & HR", "Administration / Operation Manager", "Others", "Junior Executive", "Public / Civil", "Others"], "post_time": "2022-01-11T08:02:12Z", "salary": {"currency": null, "max": null, "min": null, "period": "monthly", "term": null}, "salary_visible": false, "title_keywords": [], "responsibilities": [], "requirements": {"degrees": [], "majors": [], "languages": [], "language_level": [], "hard_skills": [], "soft_skills": [], "languages_combined": []}, "experience_required": {"duration": [], "field": []}}, {"job_id": "100003009041846", "location_code": "hk", "company": "Yan Chai Hospital Social Services Department", "job_title": "\u9ad8\u7d1a\u7279\u6b8a\u5e7c\u5152\u5de5\u4f5c\u54e1", "description": "\nYouth & Community Service\nSocial Worker (ASWO) (Application Code:NYC/CCASWO003)\nContract Period: 1-year full-time\nRequirement: Registered social worker with a degree or above in Social Work or equivalent; attained Level 2 / have Grade E or above in five subjects (including Chinese and English) in HKDSE / HKCEE; at least 2 cumulative years of experience in providing social work services for students in secondary schools, including 1 year in providing support service to Non-Chinese Speaking (NCS) students in secondary school; able to speak and write fluent English and Chinese\nDuties: Render service to NCS students in exploring different careers and connect their career exploration and pathway with their studies at school; strengthen teachers of the participating schools in organizing life planning education activities for NCS students; organize a school-based training session for the parents of NCS students on the life planning education for NCS students\nWorking hours: 39 net hours per week (Outreaching work and shift duty on Saturdays and Sundays are required)\nWorking Location: Territory-wide\nSalary: $33,350 (MPS Pt.16, commensurate with working experience)\nApplication letter quoting the job reference code with resume and contact telephone number should be sent to 1/F 256A Prince Edward Road West Kowloon or email to\u00a0 Apply Now before 18 January 2022.\n(Successful candidates must consent to undergoing the sexual conviction record check. The personal data of applicants will be used strictly and exclusively for recruitment-related purpose)\u00a0\n\n", "employment_types": ["Full Time"], "selling_points": [], "locations": ["Tsuen Wan Area"], "categories": ["Public / Civil", "Social Services - Community / Non-profit Organization", "Others"], "post_time": "2022-01-12T04:28:52Z", "salary": {"currency": null, "max": null, "min": null, "period": "monthly", "term": null}, "salary_visible": false, "title_keywords": [], "responsibilities": ["recruitment", "contact", "providing support", "personal data", "planning"], "requirements": {"degrees": ["degree or above", "hkdse"], "majors": ["social work"], "languages": ["english", "chinese"], "language_level": ["fluent"], "hard_skills": ["code"], "soft_skills": [], "languages_combined": [{"language": "english", "language_level": ["fluent"]}, {"language": "chinese", "language_level": ["fluent"]}]}, "experience_required": {"duration": ["1 year"], "field": []}}, {"job_id": "100003009038960", "location_code": "hk", "company": "BEST INNOVATION LIMITED", "job_title": "\u5de5\u7a0b\u5e2b/\u5de5\u7a0b\u5e2b\u52a9\u7406", "description": "\n\u8077\u8cac :\u8ca0\u8cac\u898f\u5283\u3001\u76e3\u5bdf\u53ca\u8ddf\u9032\u5de5\u7a0b\u9032\u5ea6;\u8207\u8a2d\u8a08\u5718\u968a\u6e9d\u901a\u4e26\u95b1\u89bd\u53ca\u88fd\u4f5c\u65bd\u5de5\u5716;\u8207\u5e2b\u5085\u5354\u8abf\u65bd\u5de5\u9805\u76ee;\u78ba\u4fdd\u5de5\u7a0b\u5982\u671f\u9032\u5c55\u3001\u65bd\u5de5\u9805\u76ee\u7121\u8aa4\u3001\u89e3\u6c7a\u5de5\u5730\u554f\u984c\u53ca\u7dad\u6301\u5de5\u5730\u5b89\u5168\n\n\u8cc7\u6b77 :\u5c08\u4e0a\u6559\u80b2\uff1a\u6587\u6191/\u8b49\u66f8; 2\u5e74\u7d93\u9a57; \u4e00\u822c\u7cb5\u8a9e; \u4e00\u822c\u666e\u901a\u8a71; \u4e00\u822c\u82f1\u8a9e; \u61c2\u8b80\u5beb\u4e2d\u6587; \u61c2\u8b80\u5beb\u82f1\u6587; \u61c2Microsoft Office; \u5177\u6709\u57fa\u672c\u96fb\u8166\u64cd\u4f5c\u77e5\u8b58\n\n\u5f85\u9047 :\u6bcf\u6708$15,000 - $23,000, \u6709\u9280\u884c\u5047\u671f, \u661f\u671f\u4e00\u81f3\u4e94: \u4e0a\u53489\u6642\u81f3\u4e0b\u53486\u6642\u53ca\u661f\u671f\u516d: \u4e0a\u53489\u6642\u81f3\u4e2d\u534812\u6642, \u6bcf\u9031\u5de5\u4f5c5\u5929\u534a, \u6bcf\u5929\u5de5\u4f5c 8 \u5c0f\u6642\n\n\u7533\u8acb\u9808\u77e5 :\u6c42\u8077\u8005\u53ef\u96fb\u90f5(Apply Now)\u5c65\u6b77\u8868\u7d66\u4f73\u85dd\u5275\u610f\u6709\u9650\u516c\u53f8\u3002\u5982\u8981\u7d22\u53d6\u6536\u96c6\u500b\u4eba\u8cc7\u6599\u8072\u660e, \u8acb\u8207\u738b\u5c0f\u59d0(Email)\u806f\u7d61\u3002\n\n", "employment_types": ["Full Time"], "selling_points": [], "locations": ["Shatin Area"], "categories": ["Admin & HR", "Administration / Operation Manager", "Others", "Junior Executive", "Public / Civil", "Others"], "post_time": "2022-01-11T08:13:45Z", "salary": {"currency": null, "max": null, "min": null, "period": "monthly", "term": null}, "salary_visible": false, "title_keywords": [], "responsibilities": [], "requirements": {"degrees": [], "majors": [], "languages": [], "language_level": [], "hard_skills": [], "soft_skills": [], "languages_combined": []}, "experience_required": {"duration": [], "field": []}}, {"job_id": "100003009041466", "location_code": "hk", "company": "Wright Life Pharmaceutical Limited", "job_title": "\u751f\u7522\u90e8\u52a9\u7406", "description": "\n\u8077\u8cac :\u8655\u7406\u751f\u7522\u90e8\u9580\u65e5\u5e38\u6587\u66f8\u53ca\u751f\u7522\u8a18\u9304; \u8207\u6709\u95dc\u90e8\u9580\u6e9d\u901a\u6709\u95dc\u9001\u8ca8\u53ca\u6536\u767c\u539f\u6750\u6599\n\n\u8cc7\u6b77 :\u5c08\u4e0a\u6559\u80b2\uff1a\u6587\u6191/\u8b49\u66f8; 2\u5e74\u7d93\u9a57; \u4e00\u822c\u7cb5\u8a9e; \u4e00\u822c\u82f1\u8a9e; \u61c2\u8b80\u5beb\u4e2d\u6587; \u7565\u61c2\u8b80\u5beb\u82f1\u6587; \u5177\u6709\u57fa\u672c\u96fb\u8166\u64cd\u4f5c\u77e5\u8b58; \u5177\u85e5\u5ee0/\u98df\u54c1\u5ee0\u7d93\u9a57\u512a\u5148\n\n\u5f85\u9047 :\u6bcf\u6708$13,000 - $16,000, \u6709\u8d85\u6642\u5de5\u4f5c\u6d25\u8cbc, \u96d9\u7ce7, \u9280\u884c\u5047\u671f, \u91ab\u7642\u798f\u5229 \u53ca\u54e1\u5de5\u8cfc\u7269\u512a\u60e0, \u661f\u671f\u4e00\u81f3\u4e94: \u4e0a\u53488\u6642\u81f3\u4e0b\u53486\u6642, \u6bcf\u9031\u5de5\u4f5c5\u5929, \u6bcf\u5929\u5de5\u4f5c 9 \u5c0f\u6642\n\n\u7533\u8acb\u9808\u77e5 :\u6c42\u8077\u8005\u53ef\u96fb\u90f5(Apply Now)\u5c65\u6b77\u8868\u7d66\u840a\u7279\u7dad\u5065\u85e5\u5ee0\u6709\u9650\u516c\u53f8\u3002\u5982\u8981\u7d22\u53d6\u6536\u96c6\u500b\u4eba\u8cc7\u6599\u8072\u660e, \u8acb\u8207\u5f35\u5c0f\u59d0(Email)\u806f\u7d61\u3002\n\n", "employment_types": ["Full Time"], "selling_points": [], "locations": ["Tsuen Wan Area"], "categories": ["Admin & HR", "Administration / Operation Manager", "Others", "Junior Executive", "Public / Civil", "Others"], "post_time": "2022-01-12T03:55:23Z", "salary": {"currency": null, "max": null, "min": null, "period": "monthly", "term": null}, "salary_visible": false, "title_keywords": [], "responsibilities": [], "requirements": {"degrees": [], "majors": [], "languages": [], "language_level": [], "hard_skills": [], "soft_skills": [], "languages_combined": []}, "experience_required": {"duration": [], "field": []}}, {"job_id": "100003009046672", "location_code": "hk", "company": "Insurance Authority", "job_title": "Manager (Long Term Business \u2013 Group-wide Supervision)", "description": "Reporting to the Senior Manager (Group-wide Supervision (GWS)), the incumbent will assume the following:\n\nKey Responsibilities\n\nAssist in the prudential supervision of major insurance groups, with focus on conducting reviews and risk assessments as part of the GWS supervisory framework\u00a0\nParticipate in the preparations for supervisory colleges and crisis management group meetings\nLiaise and co-ordinate with local and overseas insurance regulators and other financial regulators on prudential supervision of life insurers, and in performing group-wide supervision of major insurance groups\nKeep abreast of developments in the insurance industry, financial and capital markets that may impact on major insurance groups operating in Asia\nOther duties as assigned by senior management to facilitate the administration of the statutory functions of IA\n\nRequirements\n\nA Bachelor\u2019s degree in actuarial science, accounting, finance or related disciplines\nA professional qualification such as qualified actuary, CPA or financial risk manager\nMinimum 5 years\u2019 relevant experience in financial services\nStrong analytical and financial analysis skills\nStrong command of written and spoken English\n\nRemuneration Package\n\nA competitive remuneration package commensurate with the successful candidate\u2019s experience and qualifications will be offered.\u00a0\n\nApplication\n\nReview of the applications will start as soon as possible and continue until 21 January 2022, or until the post is filled. Interested applicants may send a letter of application quoting the reference number, together with a full resume stating current and expected salaries by clicking \"Apply Now\".\n\n\nThe Insurance Authority is an equal opportunities employer. Applicants not invited for an interview within 2 months from the closing date may assume their applications unsuccessful. Applications may be considered for other suitable positions within IA. All applications will be handled in strict confidence and the information collected will only be used for recruitment purposes. All information on non-shortlisted applicants will be destroyed after 6 months from the close of applications.\u00a0", "employment_types": ["Full Time", "Permanent"], "selling_points": [], "locations": ["Southern Area"], "categories": ["Insurance", "Actuarial", "Public / Civil", "Others", "Banking / Finance", "Risk Management"], "post_time": "2022-01-13T18:54:14Z", "salary": {"currency": null, "max": null, "min": null, "period": "monthly", "term": null}, "salary_visible": false, "title_keywords": ["manager"], "responsibilities": ["liaise", "other duties", "co-ordinate with", "senior management", "insurance", "crisis management", "administration"], "requirements": {"degrees": ["degree", "bachelor"], "majors": ["related disciplines", "finance", "accounting", "actuarial science"], "languages": ["english"], "language_level": [], "hard_skills": ["financial analysis", "cpa", "financial risk manager"], "soft_skills": ["confidence"], "languages_combined": [{"language": "english", "language_level": []}]}, "experience_required": {"duration": ["minimum 5 years"], "field": ["financial services", "relevant experience"]}}, {"job_id": "100003009041765", "location_code": "hk", "company": "Kowloon Cricket Club", "job_title": "\u52a9\u7406\u9152\u5427\u90e8\u9577**", "description": "\n\u8077\u8cac :\u65bc\u82f1\u5f0f\u9152\u5427\u5167\u5de5\u4f5c, \u70ba\u6703\u54e1\u53ca\u5176\u5ba2\u4eba\u63d0\u4f9b\u9910\u98f2\u670d\u52d9\n\n\u8cc7\u6b77 :\u6c92\u6709\u5b78\u6b77\u8981\u6c42; 3\u5e74\u7d93\u9a57; \u4e00\u822c\u7cb5\u8a9e; \u4e00\u822c\u82f1\u8a9e; \u7565\u61c2\u8b80\u5beb\u4e2d\u6587; \u7565\u61c2\u8b80\u5beb\u82f1\u6587\n\n\u5f85\u9047 :\u6bcf\u6708$18,000, \u6709\u5e74\u504712\u5929, \u914c\u60c5\u6027\u82b1\u7d05, \u7259\u79d1\u798f\u5229, \u91ab\u7642\u4fdd\u96aa \u53ca\u4f9b\u81b3\u98df, \u4e0b\u53483\u6642\u81f3\u51cc\u666812\u6642\u6216\u4e0b\u53481\u6642\u81f3\u4e0b\u534810\u6642, \u6bcf\u9031\u5de5\u4f5c6\u5929,\u8f2a\u4f11, \u6bcf\u5929\u5de5\u4f5c 9 \u5c0f\u6642, 1\u5c0f\u6642\u7528\u81b3\u6642\u9593; \u53e6\u6bcf\u6708\u4e00\u5929\u984d\u5916\u4f11\u606f\u65e5\n\n\u7533\u8acb\u9808\u77e5 :\u6c42\u8077\u8005\u53ef\u50b3\u771f(26772667)\u6216\u96fb\u90f5(Apply Now)\u5c65\u6b77\u8868\u7d66KLN CRICKET CLUB\u3002\u5982\u8981\u7d22\u53d6\u6536\u96c6\u500b\u4eba\u8cc7\u6599\u8072\u660e, \u8acb\u8207\u912d\u5c0f\u59d0(Tel:34737133)\u806f\u7d61\u3002\n\n", "employment_types": ["Full Time"], "selling_points": [], "locations": ["Yau Tsim Mong Area"], "categories": ["Admin & HR", "Administration / Operation Manager", "Others", "Junior Executive", "Public / Civil", "Others"], "post_time": "2022-01-12T04:20:36Z", "salary": {"currency": null, "max": null, "min": null, "period": "monthly", "term": null}, "salary_visible": false, "title_keywords": [], "responsibilities": [], "requirements": {"degrees": [], "majors": [], "languages": [], "language_level": [], "hard_skills": [], "soft_skills": [], "languages_combined": []}, "experience_required": {"duration": [], "field": []}}, {"job_id": "100003009041363", "location_code": "hk", "company": "Deutsche Bank AG, Hong Kong Branch", "job_title": "Wealth Management - Equity Product Specialist , Director", "description": "\nPosition Overview\n\nDetails of the Division and Team:\nDeutsche Banks Wealth Management business is one of the largest wealth managers worldwide. We offer our clients a broad range of traditional and alternative investment solutions, as well as comprehensive advice on all aspects of Wealth Management. As a trusted partner of wealthy individuals and entrepreneurs, family offices and foundations, we create lasting value for clients. We specialize in developing bespoke solutions for our clients around the world, for instance wealth planning across successive generations and international borders, asset management with individual risk management, loans and deposits. All this is possible thanks to our global network, our many years of experience and our close collaboration with the Corporate Bank, Investment Bank and DWS. We aim to become a highly competitive global wealth manager by combining financial strength and stability with trustworthy partnership and forward-thinking in order to build sustainable and beneficial client relationships. As a growth business for Deutsche Bank, we contribute towards building a more balanced, less capital intense and stable business model for the bank. The Investment Manager is a primary point of contact for clients to access the entire suite of investment capabilities, insights and solutions offered by Deutsche Bank Wealth Management. This is achieved by working in close partnership with the Relationship Manager in the day-to-day planning and servicing for the client. The individual leverages the insight and expertise of the Deutsche Bank Wealth Management Chief Investment Office and the global and regional investment committees to provide advice around long-term thematic investment opportunities, short-term tactical trades and asset allocation. The Investment Manager employs a wide range of asset classes and capabilities, leveraging the knowledge from dedicate product specialists, to address clients needs holistically, including lending and financing, deposits, discretionary and advisory portfolio management solutions, capital markets, private markets, alternative investments and wealth planning. Investment Manager will have accountability for total investment AUM, revenue, asset retention and contribution towards business mix goals\nWhat we will offer you:\nA healthy, engaged and well-supported workforce is better equipped to do their best work and, more importantly, enjoy their lives inside and outside the workplace. That's why we are committed to providing an environment with your development and wellbeing at its center.\nYou can expect:\n\n\u2022 Competitive Salary and non-contributory pension\n\n\u2022 25 days annual leave plus generous number of public holidays\n\n\u2022 Life Assurance and Private Healthcare for you and your family\n\n\u2022 A range of flexible benefits including retail discounts, gym benefits, wellbeing incentives\n\n\u2022 The opportunity to support a wide ranging CSR program plus take volunteering leave days\n\nYour key responsibilities:\n\n\u2022 DB IPB Capital Markets Department in Asia is seeking a high caliber professional to join the team as Equity Product & Solutions Specialist, based in Hong Kong.\n\n\u2022 Provide professional advices and sales coverage in CM Equity business to IPB clients\n\nResponsible for delivering Equity business revenue targets (both team target and individual target) and increasing wallet shares from existing clients\n\n\u2022 Able to lead investment discussions in one-on-one meetings & group meetings and able to host clients seminars & events to drive the thematic product campaigns\n\n\u2022 Partner up with the Relationship Manager and Investment Manager to cover IPB clients as strategic advisor\n\n\u2022 Support the Relationship Managers in their new client acquisition efforts through participation in prospecting, client pitches and showcasing Deutsche Bank Wealth Management capabilities\n\n\u2022 Monitor clients asset allocation across investments and provide ideas for rebalancing across product spectrum based on CIO view\n\n\u2022 Proactively seek to manage and control risks while maximizing financial returns in line with regulations\n\n\u2022 Act within professional, legal and ethical boundaries and guidelines, observing all internal and external compliance regulations and code of ethics and conduct flagging and managing reputational risks and conflicts issues\n\n\u2022 Teamwork and Cooperation across the Bank required\n\n\u2022 Mentor and coach junior team members\n\nYour skills and experience:\n\n\u2022 10 or more years of relevant investment experience\n\n\u2022 Superior investment acumen with a strong understanding of Equity asset class across stocks, Index / ETF and derivatives\n\n\u2022 Proven experience in Equity investment advisory and sales, with good understanding of private clients and U/HNW clients' needs\n\n\u2022 Superior analytical skills as well as being detail-oriented on both strategy and execution\n\n\u2022 Excellent client-facing advisory & sales skills with proven track-record\n\n\u2022 Bachelor or above Degree holder, preferably in Finance, Economics or related discipline\n\n\u2022 Excellent presentation and communication skills in English\n\n\u2022 Relevant local licenses and qualifications\n\n\u2022 Self-motivated and passionate about Private Banking business in Asia\n\n\u2022 CPWP and CFA holder preferred\n\nHow we'll support you:\n\n\u2022 Flexible working to assist you balance your personal priorities\n\n\u2022 Coaching and support from experts in your team\n\n\u2022 A culture of continuous learning to aid progression\n\n\u2022 A range of flexible benefits that you can tailor to suit your needs\n\n\u2022 Training and development to help you excel in your career\n\nAbout us and our teams:\nDeutsche Bank is the leading German bank with strong European roots and a global network. to see what we do.\nDeutsche Bank & Diversity\nOur values define the working environment we strive to create - diverse, supportive and welcoming of different views. We embrace a culture reflecting a variety of perspectives, insights and backgrounds to drive innovation. We build talented and diverse teams to drive business results and encourage our people to develop to their full potential. Talk to us about flexible work arrangements and other initiatives we offer.\nWe promote good working relationships and encourage high standards of conduct and work performance. We welcome applications from talented people from all cultures, countries, races, genders, sexual orientations, disabilities, beliefs and generations and are committed to providing a working environment free from harassment, discrimination and retaliation.\n\nClick to find out more about diversity and inclusion at Deutsche Bank.\n\n", "employment_types": ["Full Time"], "selling_points": [], "locations": ["Not Specified"], "categories": ["Public / Civil", "Social Services - Community / Non-profit Organization", "Others"], "post_time": "2022-01-12T03:48:20Z", "salary": {"currency": null, "max": null, "min": null, "period": "monthly", "term": null}, "salary_visible": false, "title_keywords": ["wealth management", "product specialist", "director"], "responsibilities": ["management", "developing", "planning", "provide advice", "contact", "asset management"], "requirements": {"degrees": [], "majors": [], "languages": [], "language_level": [], "hard_skills": ["plus"], "soft_skills": ["accountability", "trustworthy", "committed", "comprehensive", "stable"], "languages_combined": []}, "experience_required": {"duration": [], "field": ["investment bank"]}}, {"job_id": "100003009040930", "location_code": "hk", "company": "Po Leung Kuk", "job_title": "\u793e\u6703\u5de5\u4f5c\u54e1SW5/6-PHH (\u8475\u6d8c)", "description": "\n\u5eb7\u5fa9\u670d\u52d9\n\u5165\u8077\u8981\u6c42\n\u2022 \u8a3b\u518a\u793e\u5de5\uff0c\u6301\u8a8d\u53ef\u793e\u6703\u5de5\u4f5c\u5b78\u58eb\u5b78\u4f4d\u6216\u4ee5\u4e0a\u5b78\u6b77\u3002\n\u4e3b\u8981\u8077\u8cac\n\u2022 \u8ca0\u8cac\u70ba\u5f31\u667a\u4eba\u58eb\u63d0\u4f9b\u500b\u6848\u8f14\u5c0e\u3001\u8a13\u7df4\u3001\u5bb6\u5c6c\u5de5\u4f5c\u53ca\u670d\u52d9\u63a8\u5ee3\uff0c\u5354\u8abf\u4f7f\u7528\u8005\u7684\u5c08\u696d\u6cbb\u7642\u9700\u8981\uff0c\u5354\u52a9\u90e8\u4efd\u5bbf\u820d\u4eba\u4e8b\u3001\u884c\u653f\u3001\u8ca1\u52d9\u7b49\u7ba1\u7406\u7b49\u5de5\u4f5c\u3002\n\u4e0a\u73ed\u6a21\u5f0f\n\u2022 \u9700\u8f2a\u503c\u3002\n\u8475\u6d8c [via\u00a0 Apply Now ] 3980 9688\n\u622a\u6b62\u7533\u8acb\u65e5\u671f : 2022/1/28\n\n", "employment_types": ["Full Time"], "selling_points": [], "locations": ["Kwai Tsing Area"], "categories": ["Public / Civil", "Social Services - Community / Non-profit Organization", "Others"], "post_time": "2022-01-12T03:14:24Z", "salary": {"currency": null, "max": null, "min": null, "period": "monthly", "term": null}, "salary_visible": false, "title_keywords": [], "responsibilities": [], "requirements": {"degrees": [], "majors": [], "languages": [], "language_level": [], "hard_skills": [], "soft_skills": [], "languages_combined": []}, "experience_required": {"duration": [], "field": []}}, {"job_id": "100003009040804", "location_code": "hk", "company": "The Boys' and Girls' Clubs Association of Hong Kong", "job_title": "\u793e\u6703\u5de5\u4f5c\u54e1 - \u9752\u5c11\u5e74\u7d9c\u5408\u670d\u52d9\u4e2d\u5fc3", "description": "\n\u8077\u8cac\uff1a\n\u2022 \u8ca0\u8cac\u5152\u7ae5\u3001\u9752\u5c11\u5e74\u53ca\u5bb6\u9577\u5de5\u4f5c\n\u2022 \u914d\u5408\u6a5f\u69cb\u7684\u670d\u52d9\u7b56\u7565\uff0c\u8207\u53ca\u4e2d\u5fc3\u7684\u5e74\u5ea6\u670d\u52d9\u8a08\u5283\uff0c\u63a8\u52d5\u53ca\u652f\u63f4\u5404\u9805\u7126\u9ede\u670d\u52d9\uff0c\u7576\u4e2d\u5305\u62ec\uff1a\u57f9\u80b2\u5152\u7ae5\u53ca\u9752\u5c11\u5e74\u7684\u5168\u4eba\u767c\u5c55\u3001\u95dc\u9867\u7cbe\u795e\u5065\u5eb7\u53ca\u60c5\u7dd2\u7684\u9700\u8981\u3001\u4fc3\u9032\u5bb6\u5ead\u95dc\u4fc2\u53ca\u529f\u80fd\u7684\u6d3b\u52d5\u3001\u63a8\u5c55\u91ce\u5916\u53ca\u6236\u5916\u6d3b\u52d5\u5de5\u4f5c\u3001\u7fa9\u5de5\u767c\u5c55\u53ca\u793e\u6703\u53c3\u8207\u5de5\u4f5c\u7b49\n\u2022 \u8655\u7406\u7531\u7763\u5c0e\u6307\u6d3e\u7684\u5176\u4ed6\u5de5\u4f5c\n\u2022 \u5de5\u4f5c\u5730\u9ede: \u6e2f\u4e5d\u65b0\u754c\n\u8981\u6c42\uff1a\n\u2022 \u6301\u8a8d\u53ef\u793e\u6703\u5de5\u4f5c\u6587\u6191\u3001\u9ad8\u7d1a\u6587\u6191\u3001\u526f\u5b78\u58eb\u6216\u4ee5\u4e0a\u7a0b\u5ea6\u4e4b\u8a3b\u518a\u793e\u5de5\n\u9999\u6e2f\u4e2d\u5b78\u6587\u6191\u8003\u8a66\u4e94\u79d1\u5305\u62ec\u4e2d\u6587\u3001\u82f1\u6587\u3001\u6578\u5b78\u3001\u901a\u8b58\u9054\u4e8c\u7d1a\u6216\u9999\u6e2f\u4e2d\u5b78\u6703\u8003\u4e94\u79d1\u5408\u683c\u5305\u62ec\u4e2d\u6587\u3001\u82f1\u6587(2007\u5e74\u524d\u4e4b\"\u8ab2\u7a0b\u4e59\")\u3001\u6578\u5b78\u6216\u5177\u540c\u7b49\u5b78\u6b77\n\u2022 \u5177\u826f\u597d\u4e2d\u82f1\u6587\u6703\u8a71\u53ca\u66f8\u5beb\u80fd\u529b\u3001\u6e9d\u901a\u80fd\u529b\u96fb\u8166\u6587\u66f8\u61c9\u7528\u64cd\u4f5c\n\u2022 \u5177\u5099\u7d44\u7e54\u9752\u5c11\u5e74\u904b\u52d5\u5718\u968a\u53ca\u91ce\u5916\u6d3b\u52d5\u670d\u52d9\u7d93\u9a57\u3001\u7de8\u7a0b\u7d93\u9a57\u3001\u91ce\u5916\u6d3b\u52d5\u3001\u5152\u7ae5\u53ca\u9752\u5c11\u5e74\u670d\u52d9\u5de5\u4f5c\u3001\u6b77\u5947\u3001\u6578\u78bc\u5275\u610f\u3001SEN\u6216\u76f8\u95dc\u5de5\u4f5c\u7d93\u9a57\u512a\u5148\u8003\u616e\n\n", "employment_types": ["Full Time"], "selling_points": [], "locations": ["Not Specified"], "categories": ["Public / Civil", "Social Services - Community / Non-profit Organization", "Others"], "post_time": "2022-01-12T03:06:02Z", "salary": {"currency": null, "max": null, "min": null, "period": "monthly", "term": null}, "salary_visible": false, "title_keywords": [], "responsibilities": [], "requirements": {"degrees": [], "majors": [], "languages": [], "language_level": [], "hard_skills": [], "soft_skills": [], "languages_combined": []}, "experience_required": {"duration": [], "field": []}}, {"job_id": "100003009033749", "location_code": "hk", "company": "Hong Kong Family Welfare Society", "job_title": "\u793e\u5340\u5de5\u4f5c\u54e1I", "description": "\u8ca0\u8cac\u5b89\u6392\u5bb6\u5c45\u7167\u9867\u670d\u52d9\u3001\u7ba1\u7406\u3001\u7763\u5c0e\u3001\u7c4c\u8fa6\u6d3b\u52d5\u53ca\u8655\u7406\u884c\u653f\u53ca\u6587\u66f8\u5de5\u4f5c\u7b49\n\u4e2d\u5b78\u6703\u8003\u4e94\u79d1\u5408\u683c(\u5305\u62ec\u4e2d\u3001\u82f1\u3001\u6578)\uff1b\u6216\u4e2d\u5b78\u6587\u6191\u8003\u8a66\u4e94\u79d1\u6210\u7e3e\u90542\u7d1a\u6216\u4ee5\u4e0a(\u5305\u62ec\u4e2d\u3001\u82f1\u3001\u6578)\u6216\u540c\u7b49\u5b78\u6b77\n\u80fd\u7368\u7acb\u5de5\u4f5c\u3001\u5177\u61c9\u8b8a\u80fd\u529b\u53ca\u826f\u597d\u6e9d\u901a\u6280\u5de7\n\u5c0d\u9577\u8005\u670d\u52d9\u6709\u71b1\u8aa0\n\u5177\u793e\u6703\u670d\u52d9\u6a5f\u69cb\u7d93\u9a57\u6216\u670d\u52d9\u9577\u8005\u7d93\u9a57\u512a\u5148\n\u5165\u8077\u85aa\u916c\u8d77\u9ede\u70ba$19,225.- (\u8996\u4e4e\u5de5\u4f5c\u7d93\u9a57\u800c\u5b9a)\n\u5de5\u4f5c\u5730\u9ede\uff1a\u89c0\u5858 / \u6df1\u6c34\u57d7 / \u5c07\u8ecd\u6fb3\n\n\u7533\u8acb\u8fa6\u6cd5\uff1a \u8acb\u5c07\u5c65\u6b77\u8868\u90f5\u5bc4\u81f3\u4ee5\u4e0b\u5730\u5740\u6216\u96fb\u90f5\u81f3[via CTgoodjobs\u00a0Apply Now\u00a0]\uff0c\u8acb\u8a3b\u660e\u85aa\u91d1\u8981\u6c42\u53ca\u8077\u4f4d\n\n\u90f5\u5bc4\u5730\u5740\uff1a \u4e5d\u9f8d\u9806\u5b89\u90a8\u5b89\u9038\u6a13\u5730\u4e0b1-4\u53ca9-12\u865f", "employment_types": ["Full Time"], "selling_points": [], "locations": ["Not Specified"], "categories": ["Public / Civil", "Social Services - Community / Non-profit Organization", "Others"], "post_time": "2022-01-10T01:45:24Z", "salary": {"currency": null, "max": null, "min": null, "period": "monthly", "term": null}, "salary_visible": false, "title_keywords": [], "responsibilities": [], "requirements": {"degrees": [], "majors": [], "languages": [], "language_level": [], "hard_skills": [], "soft_skills": [], "languages_combined": []}, "experience_required": {"duration": [], "field": []}}, {"job_id": "100003009044142", "location_code": "hk", "company": "Yan Oi Tong Ltd", "job_title": "\u7e3d\u4e3b\u4efb (\u8077\u4f4d\u7de8\u865f: STFAST-WS/CS0103/220113)", "description": "\u6301\u653f\u5e9c\u8a8d\u53ef\u793e\u6703\u5de5\u4f5c\u5b78\u4f4d\u6216\u4ee5\u4e0a\u5b78\u6b77\u4e4b\u8a3b\u518a\u793e\u5de5\uff1b\n\u4e09\u5e74\u6216\u4ee5\u4e0a\u9577\u8005\u670d\u52d9\u7d93\u9a57\uff0c\u6301\u793e\u6703\u798f\u5229\u7f72\u9577\u671f\u8b77\u7406\u670d\u52d9\u7d71\u4e00\u8a55\u4f30\u54e1\u8cc7\u683c/ \u5177\u500b\u6848\u7ba1\u7406\u7d93\u9a57/\u6216\u57fa\u91d1\u7533\u8acb\u7d93\u9a57\u512a\u5148\u8003\u616e\uff1b\n\u8ca0\u8cac\u7b56\u5283\u53ca\u63a8\u884c\u8b77\u8001\u8005\u652f\u63f4\u670d\u52d9\uff0c\u70ba\u8a8d\u77e5\u969c\u7919\u75c7\u60a3\u8005\u53ca\u5176\u8b77\u8001\u8005\u63d0\u4f9b\u652f\u63f4\u53ca\u8f14\u5c0e\u670d\u52d9\uff1b\n\u70ba\u9577\u8005\u5730\u5340\u4e2d\u5fc3\u4e4b\u9577\u8005\u63d0\u4f9b\u500b\u6848\u8f14\u5c0e\u5de5\u4f5c\uff0c\u5b9a\u671f\u4f5c\u51fa\u6aa2\u8a0e\u53ca\u63d0\u4f9b\u9069\u6642\u7684\u8f49\u4ecb\u670d\u52d9\uff1b\n\u6210\u719f\u4e3b\u52d5\u3001\u5177\u8cac\u4efb\u611f\u3001\u7368\u7acb\u8655\u4e8b\u80fd\u529b\u3001\u826f\u597d\u6e9d\u901a\u6280\u5de7\u53ca\u4eba\u969b\u95dc\u4fc2\uff1b\n5\u5929\u5de5\u4f5c\uff0c\u6bcf\u9031\u5de5\u4f5c44\u5c0f\u6642\n\u5c6f\u9580\u5340\u9577\u8005\u5730\u5340\u4e2d\u5fc3\u5de5\u4f5c", "employment_types": ["Full Time", "Contract"], "selling_points": ["\u793e\u5de5\u5b78\u4f4d\u6216\u4ee5\u4e0a\u4e4b\u8a3b\u518a\u793e\u5de5", "\u5177\u50998\u5e74\u6216\u4ee5\u4e0a\u76f8\u95dc\u5de5\u4f5c\u7d93\u9a57\uff0c\u7576\u4e2d\u5305\u62ec\u793e\u5340\uff0f\u5bb6\u5ead\u652f\u63f4\u670d\u52d9\u53ca\u7ba1\u7406\u7d93\u9a57", "\u7ba1\u7406\u53ca\u63a8\u884c\u77ed\u671f\u98df\u7269\u652f\u63f4\u8a08\u5283"], "locations": ["Wong Tai Sin Area"], "categories": ["Public / Civil", "Social Services - Community / Non-profit Organization", "Others"], "post_time": "2022-01-13T03:12:21Z", "salary": {"currency": null, "max": null, "min": null, "period": "monthly", "term": null}, "salary_visible": false, "title_keywords": [], "responsibilities": [], "requirements": {"degrees": [], "majors": [], "languages": [], "language_level": [], "hard_skills": [], "soft_skills": [], "languages_combined": []}, "experience_required": {"duration": [], "field": []}}, {"job_id": "100003009040874", "location_code": "hk", "company": "Evangelical Lutheran Church Social Service - Hong Kong", "job_title": "\u793e\u6703\u5de5\u4f5c\u54e1Social Woker(\u8077\u4f4d\u7de8\u865f\uff1aSWII-SCC-HCS)", "description": "\u8077\u4f4d\u8981\u6c42:\n\n\n\u8a3b\u518a\u793e\u5de5\uff1b\n\u793e\u5de5\u5b78\u4f4d\u6216\u4ee5\u4e0a\uff1b\n\u5177\u50998\u5e74\u6216\u4ee5\u4e0a\u76f8\u95dc\u5de5\u4f5c\u7d93\u9a57\uff0c\u7576\u4e2d\u5305\u62ec\u793e\u5340\uff0f\u5bb6\u5ead\u652f\u63f4\u670d\u52d9\u53ca\u7ba1\u7406\u7d93\u9a57\uff1b\n\u5177\u4e2d\u82f1\u6587\u66f8\u5beb\u80fd\u529b\u53ca\u719f\u6089\u96fb\u8166\u64cd\u4f5c\uff1b\n\u5177\u6210\u719f\u3001\u826f\u597d\u7684\u6e9d\u901a\u6280\u5de7\uff0c\u80fd\u6709\u6548\u767c\u63ee\u5718\u968a\u5408\u4f5c\u7cbe\u795e\n\u4e3b\u8981\u8077\u8cac:\n\n\u7ba1\u7406\u53ca\u63a8\u884c\u77ed\u671f\u98df\u7269\u652f\u63f4\u8a08\u5283\uff1b\n\u7763\u5c0e\u53ca\u652f\u63f4\u5718\u968a\n\u7b56\u5283\u55ae\u4f4d\u767c\u5c55\u53ca\u958b\u62d3\u670d\u52d9\n\u76e3\u5bdf\u55ae\u4f4d\u884c\u653f\u53ca\u6574\u9ad4\u904b\u4f5c\n\u5de5\u4f5c\u5b89\u6392:\n\n\u6bcf\u9031\u5de5\u4f5c5\u5929\uff0c\u5982\u6709\u9700\u8981\uff0c\u9808\u5728\u5047\u65e5\u6216\u4e0d\u5b9a\u6642\u5de5\u4f5c\n\u9ec3\u5927\u4ed9\u5340\u5de5\u4f5c\n\n\n\n\u6709\u610f\u8005\u8acb\u5c07\u5c65\u6b77\u3001\u8981\u6c42\u5f85\u9047\u3001\u53ef\u5230\u8077\u65e5\u671f\u53ca\u806f\u7d61\u96fb\u8a71\uff08\u5fc5\u9808\u8a3b\u660e\u8077\u4f4d\u7de8\u865f\uff09\u90f5\u5bc4\u5f80\u5c6f\u9580\u555f\u6c11\u5f9118\u865f\u4ec1\u611b\u5802\u8cfd\u99ac\u6703\u793e\u5340\u53ca\u9ad4\u80b2\u4e2d\u5fc37\u6a13\u4eba\u529b\u8cc7\u6e90\u90e8\u6536\u6216\u6309Apply Now\u61c9\u5fb5\u3002\n\n*\u7533\u8acb\u4eba\u6240\u63d0\u4f9b\u7684\u8cc7\u6599\u5c07\u4e88\u4ee5\u4fdd\u5bc6\u53ca\u53ea\u4f5c\u62db\u8058\u6709\u95dc\u8077\u4f4d\u7528\u9014*", "employment_types": ["Full Time"], "selling_points": [], "locations": ["Shatin Area"], "categories": ["Public / Civil", "Social Services - Community / Non-profit Organization", "Others"], "post_time": "2022-01-12T03:10:39Z", "salary": {"currency": null, "max": null, "min": null, "period": "monthly", "term": null}, "salary_visible": false, "title_keywords": [], "responsibilities": [], "requirements": {"degrees": [], "majors": [], "languages": [], "language_level": [], "hard_skills": [], "soft_skills": [], "languages_combined": []}, "experience_required": {"duration": [], "field": []}}, {"job_id": "100003009038762", "location_code": "hk", "company": "EDigital Marketing Agency Hong Kong", "job_title": "Web developer (1 Year Exp /Fresh grad welcome)", "description": "\n\u2022 \u65bc\u6c99\u7530\u8b77\u8001\u574a\u2014\u6539\u5584\u5bb6\u5c45\u53ca\u793e\u5340\u7167\u9867\u670d\u52d9\u5de5\u4f5c\n\u9808\u5177\u672c\u6e2f\u793e\u5de5\u6587\u6191\u6216\u4ee5\u4e0a\u7684\u8a3b\u518a\u793e\u5de5\uff0c\u5177\u5b89\u8001\u3001\u5fa9\u5eb7\u3001\u7cbe\u795e\u5065\u5eb7\u3001\u8b77\u8001\u670d\u52d9\u7d93\u9a57\u3001\u6709\u5c08\u9805\u6280\u80fd(e.g.\u8cc7\u8a0a\u79d1\u6280\u6216\u5176\u4ed6) \u53ef\u7372\u512a\u5148\u8003\u616e\n\u2022 \u4e3b\u8981\u8ca0\u8cac\u5bb6\u5c45\u7167\u9867\u670d\u52d9\u9ad4\u5f31\u9577\u8005\u500b\u6848\u7ba1\u7406\u3001\u8f14\u5c0e\u670d\u52d9\u3001\u4e0d\u5b9a\u671f\u5e36\u9818\u9ad4\u5f31\u9577\u8005\u5c0f\u7d44\u5de5\u4f5c\u53ca\u6236\u5916\u6d3b\u52d5\u3001\u5354\u52a9\u670d\u52d9\u4e3b\u4efb\u8655\u7406\u884c\u653f\u4e8b\u52d9\n\n", "employment_types": ["Full Time"], "selling_points": [], "locations": ["Not Specified"], "categories": ["Public / Civil", "Social Services - Community / Non-profit Organization", "Others"], "post_time": "2022-01-11T07:45:55Z", "salary": {"currency": null, "max": null, "min": null, "period": "monthly", "term": null}, "salary_visible": false, "title_keywords": ["developer"], "responsibilities": [], "requirements": {"degrees": [], "majors": [], "languages": [], "language_level": [], "hard_skills": [], "soft_skills": [], "languages_combined": []}, "experience_required": {"duration": [], "field": []}}, {"job_id": "100003009040627", "location_code": "hk", "company": "OCS Hong Kong Co Ltd", "job_title": "\u517c\u8077\u5408\u7d04\u8fa6\u516c\u5ba4\u52a9\u7406**", "description": "\nFounded in 2019, EDigital Hong Kong is a startup digital marketing agency serving SMB to listed Companies in Hong Kong.\nThe company provides a comprehensive range of services in the digital marketing ecosystem, including SEO| SEM | Social Media Management | Website Construction | Video Shooting | CRM | eDM.\nPlease visit our website https://www.edigital.com.hk for details\nResponsibilities:\n\u2022 Building Web user-interface & front end deliverable\n\u2022 Provide operational support to existing digital properties\n\u2022 Build reusable code and libraries for future use and ensure the technical feasibility of UI/UX designs\nRequirements:\n1 years experience in the development and implementation of web application (Fresh Graduated will also be considered)\n\u2022 Higher Diploma or Bachelor Degree Holder in Computer Science, Information Technology or related discipline\n\u2022 Able to bring the designer\u2019s concept to life with HTML5 | CSS3 | PHP | Javascript | JSON | MySQL | Restful API |;|\u2022 Able to bring the designer\u2019s concept to life with HTML5 | CSS3 | PHP | Javascript | JSON | MySQL | Restful API |;|\u2022 Able to bring the designer\u2019s concept to life with HTML5 | CSS3 | PHP | Javascript | JSON | MySQL | Restful API |;|\u2022 Able to bring the designer\u2019s concept to life with HTML5 | CSS3 | PHP | Javascript | JSON | MySQL | Restful API |;|\u2022 Able to bring the designer\u2019s concept to life with HTML5 | CSS3 | PHP | Javascript | JSON | MySQL | Restful API |;|\u2022 Able to bring the designer\u2019s concept to life with HTML5 | CSS3 | PHP | Javascript | JSON | MySQL | Restful API |;|\u2022 Able to bring the designer\u2019s concept to life with HTML5 | CSS3 | PHP | Javascript | JSON | MySQL | Restful API |;|\u2022 Able to bring the designer\u2019s concept to life with HTML5 | CSS3 | PHP | Javascript | JSON | MySQL | Restful API |;\nExperience with responsive web design\u2022 Able to bring the designer\u2019s concept to life with HTML5 | CSS3 | PHP | Javascript | JSON | MySQL | Restful API |;\nKnowledge of Content Management Systems (e.g. WordPress or Magento) is a bonus\n\u2022 Good analytical skills\n\u2022 Good Reading Skills in both English and Chinese\nPackage includes:\n\u2022 5-Day Work / Week\n\u2022 8 Hours Work Per Day\n\u2022 Flexible Working Hour\n\u2022 OT Allowance\n\u2022 12-Day Annual Leave\n\u2022 Bank Holiday\n\u2022 Birthday Leave\nJob Types: Full-time, Permanent\nSalary: $10,000.00 - $13,000.00 per month\nBenefits:\n\u2022 Gym membership\n\u2022 Opportunities for promotion\n\u2022 Work from home\nSchedule:\n\u2022 Day shift\nWork Remotely:\n\u2022 Yes\n\n", "employment_types": ["Part Time"], "selling_points": [], "locations": ["To Kwa Wan"], "categories": ["Admin & HR", "Administration / Operation Manager", "Others", "Junior Executive", "Public / Civil", "Others"], "post_time": "2022-01-12T02:53:23Z", "salary": {"currency": null, "max": null, "min": null, "period": "hourly", "term": null}, "salary_visible": false, "title_keywords": [], "responsibilities": ["operational support", "ui"], "requirements": {"degrees": ["diploma", "bachelor degree holder"], "majors": ["computer science", "information technology"], "languages": ["english", "chinese"], "language_level": ["good"], "hard_skills": ["restful api", "web", "php", "analytical skills", "wordpress", "javascript"], "soft_skills": ["flexible", "responsive", "analytical skills"], "languages_combined": [{"language": "english", "language_level": ["good"]}, {"language": "chinese", "language_level": ["good"]}]}, "experience_required": {"duration": ["1 years"], "field": ["development", "designer"]}}, {"job_id": "100003009041837", "location_code": "hk", "company": "Hong Kong S.K.H. Lady MacLehose Centre", "job_title": "\u9ad8\u7d1a\u6d3b\u52d5\u5de5\u4f5c\u54e1", "description": "\n\u8077\u8cac :\u8ca0\u8cac\u5730\u8216\u53ca3\u6a13\u8fa6\u516c\u5ba4\u8207\u6e05\u6f54\u76f8\u95dc\u7684\u5de5\u4f5c (1\u5e74\u5408\u7d04, \u53ef\u7e8c\u7d04)\n\n\u8cc7\u6b77 :\u6c92\u6709\u5b78\u6b77\u8981\u6c42; \u826f\u597d\u7cb5\u8a9e\u512a\u5148; \u7565\u61c2\u8b80\u5beb\u4e2d\u6587\n\n\u5f85\u9047 :\u6bcf\u5c0f\u6642$58.00, \u661f\u671f\u4e00\u81f3\u516d: \u4e0a\u53487\u6642\u81f3\u4e0a\u534810\u6642, \u6bcf\u9031\u5de5\u4f5c5\u5929\u81f36\u5929, \u6bcf\u5929\u5de5\u4f5c 3 \u5c0f\u6642\n\n\u7533\u8acb\u9808\u77e5 :\u6c42\u8077\u8005\u53ef\u81f4\u96fb26272235\u8207\u9999\u5cf6\u6d77\u5916\u65b0\u805e\u6709\u9650\u516c\u53f8\u891a\u5148\u751f\u806f\u7d61\u3002\n\n", "employment_types": ["Full Time"], "selling_points": [], "locations": ["Not Specified"], "categories": ["Marketing / Public Relations", "Public Relations - General / Support", "Public / Civil", "Social Services - Community / Non-profit Organization", "Others"], "post_time": "2022-01-12T04:28:18Z", "salary": {"currency": null, "max": null, "min": null, "period": "monthly", "term": null}, "salary_visible": false, "title_keywords": [], "responsibilities": [], "requirements": {"degrees": [], "majors": [], "languages": [], "language_level": [], "hard_skills": [], "soft_skills": [], "languages_combined": []}, "experience_required": {"duration": [], "field": []}}, {"job_id": "100003009040745", "location_code": "hk", "company": "The Boys' and Girls' Clubs Association of Hong Kong", "job_title": "\u793e\u6703\u5de5\u4f5c\u54e1 - \u5152\u7ae5\u4e2d\u5fc3", "description": "\n\u8077\u4f4d\u7de8\u865f\uff1aGC\uff0dBOC\uff0dSAW\n\u5354\u52a9\u63a8\u884c\u4e00\u9805\u793e\u5340\u670d\u52d9\u8a08\u5283\uff0c\u63a8\u52d5\u8475\u9752\u5340\u57fa\u5c64\u5bb6\u5ead\u53ca\u7167\u9867\u8005\u5efa\u7acb\u4e92\u52a9\u652f\u63f4\u7db2\u7d61\u3002\u4e3b\u8981\u5de5\u4f5c\u5305\u62ec\u5354\u52a9\u63a8\u884c\u8a08\u5283\u5167\u5404\u9805\u5c0f\u7d44\u53ca\u6d3b\u52d5\u3001\u8a08\u5283\u5ba3\u50b3\u53ca\u4e2d\u5fc3\u670d\u52d9\u7576\u503c\u5de5\u4f5c\u3002\u5927\u5c08\u6216\u4ee5\u4e0a\u7a0b\u5ea6\uff0c\u5c0d\u670d\u52d9\u57fa\u5c64\u793e\u7fa4\u5177\u71b1\u8aa0\uff0c\u6027\u683c\u4e3b\u52d5\u7a4d\u6975\uff0c\u5177\u826f\u597d\u57f7\u884c\u3001\u6e9d\u901a\u53ca\u5718\u968a\u5408\u4f5c\u80fd\u529b\uff0c\u5177\u76f8\u95dc\u5de5\u4f5c\u7d93\u9a57\u512a\u5148\u3002\u6bcf\u9031\u5de5\u4f5c44\u5c0f\u6642\uff0c\u9700\u8f2a\u73ed\u3002\u53d7\u50f1\u8005\u9700\u63d0\u4ea4\u6027\u7f6a\u884c\u67e5\u6838\u3002\n\n", "employment_types": ["Full Time"], "selling_points": [], "locations": ["Quarry Bay"], "categories": ["Public / Civil", "Social Services - Community / Non-profit Organization", "Others"], "post_time": "2022-01-12T03:01:15Z", "salary": {"currency": null, "max": null, "min": null, "period": "monthly", "term": null}, "salary_visible": false, "title_keywords": [], "responsibilities": [], "requirements": {"degrees": [], "majors": [], "languages": [], "language_level": [], "hard_skills": [], "soft_skills": [], "languages_combined": []}, "experience_required": {"duration": [], "field": []}}, {"job_id": "100003009041532", "location_code": "hk", "company": "Agoda International (Hong Kong) Limited", "job_title": "Senior Manager/Associate Director \u2013 Supply Optimization and Commercialization (Bangkok)", "description": "\n\u8077\u8cac\uff1a\n\u2022 \u8ca0\u8cac\u4e2d\u5fc3\u8a17\u7ba1\u670d\u52d9\n\u2022 \u63a8\u5c55\u5152\u7ae5/\u5bb6\u9577\u5c0f\u7d44\u3001\u6d3b\u52d5\u53ca\u5730\u5340\u5927\u578b\u6d3b\u52d5\n\u2022 \u5354\u52a9\u4e2d\u5fc3\u65e5\u5e38\u904b\u4f5c\n\u2022 \u8655\u7406\u7531\u7763\u5c0e\u6307\u6d3e\u7684\u5176\u4ed6\u5de5\u4f5c\n\u2022 \u5de5\u4f5c\u5730\u9ede:\u9c02\u9b5a\u6d8c\n\u8981\u6c42\uff1a\n\u2022 \u6301\u8a8d\u53ef\u793e\u6703\u5de5\u4f5c\u6587\u6191\u3001\u9ad8\u7d1a\u6587\u6191\u3001\u526f\u5b78\u58eb\u6216\u4ee5\u4e0a\u7a0b\u5ea6\u4e4b\u8a3b\u518a\u793e\u5de5\n\u9999\u6e2f\u4e2d\u5b78\u6587\u6191\u8003\u8a66\u4e94\u79d1\u5305\u62ec\u4e2d\u6587\u3001\u82f1\u6587\u3001\u6578\u5b78\u3001\u901a\u8b58\u9054\u4e8c\u7d1a\u6216\u9999\u6e2f\u4e2d\u5b78\u6703\u8003\u4e94\u79d1\u5408\u683c\u5305\u62ec\u4e2d\u6587\u3001\u82f1\u6587(2007\u5e74\u524d\u4e4b\"\u8ab2\u7a0b\u4e59\")\u3001\u6578\u5b78\u6216\u5177\u540c\u7b49\u5b78\u6b77\n\u2022 \u5177\u826f\u597d\u4e2d\u82f1\u6587\u6703\u8a71\u53ca\u66f8\u5beb\u80fd\u529b\u3001\u6e9d\u901a\u80fd\u529b\u96fb\u8166\u6587\u66f8\u61c9\u7528\u64cd\u4f5c\n\u2022 \u5177SEN\u53ca\u5152\u7ae5\u5de5\u4f5c\u7d93\u9a57\u512a\u5148\u8003\u616e\n\n", "employment_types": ["Full Time"], "selling_points": [], "locations": ["Not Specified"], "categories": ["Public / Civil", "Social Services - Community / Non-profit Organization", "Others"], "post_time": "2022-01-12T04:00:38Z", "salary": {"currency": null, "max": null, "min": null, "period": "monthly", "term": null}, "salary_visible": false, "title_keywords": ["senior manager", "associate director"], "responsibilities": [], "requirements": {"degrees": [], "majors": [], "languages": [], "language_level": [], "hard_skills": [], "soft_skills": [], "languages_combined": []}, "experience_required": {"duration": [], "field": []}}, {"job_id": "100003009040461", "location_code": "hk", "company": "The Boys' and Girls' Clubs Association of Hong Kong", "job_title": "(\u5168\u8077/\u517c\u8077)\u66ff\u5047\u7279\u6b8a\u5e7c\u5152\u5de5\u4f5c\u54e1 - \u300c\u6a02\u822a\u300d\u5152\u7ae5\u65e9\u671f\u767c\u5c55\u4e2d\u5fc3(\u6771\u6d8c)", "description": "\nAbout Agoda\n\nAgoda is an online travel booking platform for accommodations, flights, and more. We build and deploy cutting-edge technology that connects travelers with more than 2.5 million accommodations globally. Based in Asia and part of Booking Holdings, our 4,000+ employees representing 90+ nationalities foster a work environment rich in diversity, creativity, and collaboration. We innovate through a culture of experimentation and ownership,\u202fenhancing the ability for our customers to experience the world.\n\nGet to Know our Team:\n\nThe Supply Optimization and Commercialization (SOCs) team sits within the Product Supply team at Agoda. We work closely with the sales department (Partner Services) to identify and optimize growth opportunities on accommodations supply for the company and to set up experiments to measure and implement changes. The projects SOCs team works on directly impact Agoda\u2019s bottom line and have long lasting structural impact to the business. We cover a range of topics including organizational efficiency, sales and product optimization, go to market strategies as well as new innovation and products. We collaborate with multiple departments and produce highly visible results backed up by experimentation and data. Utilizing powerful tools and possessing an end-to-end view of how Agoda works, the SOCs offers a team of learning and experience that will push you (and Agoda) into new territory.\n\nThe Opportunity:\n\nSenior Managers/Associate Directors in Agoda\u2019s Supply Optimization and Commercialization (SOC) team will lead a team of junior managers to own or manage both a region as well as a vertical business area for Agoda\u2019s supply. They are responsible for analyzing data and market insights to identify growth opportunities for Agoda\u2019s supply and new ideas as well as identify and execute localized experiments, product improvements and business optimization..\n\nSenior Managers/Associate Directors will be tasked to develop a deep understanding on a vertical or region to identify growth opportunities for Agoda. Parts of the responsibility includes scanning the competitive landscape, spot trends and technical developments and ideate, plan and execute, experiments or improvements as needed. A Manager should be analytical and data driven enough to support identifying, presenting and ultimately implementing go to market strategies as part of commercializing recommendations. They should also understand various ecommerce and business metrics and concepts i.e. \u2013 conversion, ROI, etc.\n\nIn summary , Senior Manager/Associate Directors can expect to work on the cutting edge of technology, data, digital marketing, algorithmic decision-making and consumer psychology \u2013 all at a scale that very few ecommerce companies in the world today can offer.\n\nIn this Role, you\u2019ll get to:\n\u2022 Manage a high performing team\n\u2022 Work together to identify, and implement projects to improve Agoda\u2019s supply either through a market view, a business vertical view or both\n\u2022 Leverage data to analyze, identify and support recommendations for growth\n\u2022 Presenting proposals including go to market strategies to senior management and C-suite for implementation\n\u2022 Support global supply initiatives, including developing infrastructure\nWhat you\u2019ll Need to Succeed:\n\u2022 7-10 years of experience in Strategy and consulting, or Business development\n\u2022 Past success in leading, coaching and developing teams\n\u2022 Proven ability to leverage analytics and quantitative methods to break down problems and come up with recommendations\n\u2022 Entrepreneurial and not afraid to be hands-on on the work\n\u2022 Experience working in a fast-paced and high growth environment\n\u2022 Enthusiasm to develop engineered processes and technologies and to apply innovative solutions to make organizational improvements while encouraging creative thinking and innovation\nExcellent communication skills (both verbal and written in English) with ability to work well across multiple stakeholders\n\u2022 Bachelor\u2019s degree in Computer Science, Statistics, Economics, Mathematics a plus\nIt\u2019s Great if you have:\n\u2022 Ability to write in SQL a plus, or willingness to learn\n#CNSL #STRA #ANLS #4 #London #Berlin #KualaLumpur #Jakarta #Taipei #HongKong #Amsterdam\n\nEqual Opportunity Employer\n\nAt Agoda, we pride ourselves on being a company represented by people of all different backgrounds and orientations. We prioritize attracting diverse talent and cultivating an inclusive environment that encourages collaboration and innovation. Employment at Agoda is based solely on a person\u2019s merit and qualifications. We are committed to providing equal employment opportunity regardless of sex, age, race, color, national origin, religion, marital status, pregnancy, sexual orientation, gender identity, disability, citizenship, veteran or military status, and other legally protected characteristics.\n\nWe will keep your application on file so that we can consider you for future vacancies and you can always ask to have your details removed from the file. For more details please read our privacy policy .\n\nTo all recruitment agencies: Agoda does not accept third party resumes. Please do not send resumes to our jobs alias, Agoda employees or any other organization location. Agoda is not responsible for any fees related to unsolicited resumes.\n\n", "employment_types": ["Part Time"], "selling_points": [], "locations": ["Tung Chung"], "categories": ["Public / Civil", "Social Services - Community / Non-profit Organization", "Others"], "post_time": "2022-01-12T02:38:14Z", "salary": {"currency": null, "max": null, "min": null, "period": "hourly", "term": null}, "salary_visible": false, "title_keywords": [], "responsibilities": ["collaborate with", "ideas", "consulting", "data", "communication", "commercialization", "plan", "deploy", "senior management", "scanning", "infrastructure", "teams", "implementation", "developing", "develop", "digital marketing", "booking", "third party", "lead a team", "recruitment"], "requirements": {"degrees": ["degree", "bachelor"], "majors": ["mathematics", "economics", "statistics", "computer science"], "languages": ["english"], "language_level": ["excellent"], "hard_skills": ["plus", "sql", "make", "c", "go"], "soft_skills": ["communication skills", "creative", "responsible", "cutting-edge", "organizational", "deep", "prioritize", "diverse", "hands-on", "learning", "committed", "innovative", "driven"], "languages_combined": [{"language": "english", "language_level": ["excellent"]}]}, "experience_required": {"duration": ["7-10 years"], "field": ["business development", "consulting", "team"]}}, {"job_id": "100003009038042", "location_code": "hk", "company": "Links International", "job_title": "Museum Researcher", "description": "\n\u8077\u8cac\uff1a\n\u2022 \u8ca0\u8cac\u70baSCCC\u7684\u7279\u6b8a\u9700\u8981\u5e7c\u5152\u63d0\u4f9b\u8a55\u4f30\u3001\u5c0f\u7d44\u8a13\u7df4\u53ca\u64ec\u5b9a\u500b\u5225\u6559\u5b78\u8a08\u5283\n\u2022 \u5b89\u6392\u53ca\u7de8\u5b9a\u8ab2\u7a0b\u53ca\u8a13\u7df4\u5167\u5bb9\n\u2022 \u70ba\u4e2d\u5fc3\u5c0f\u7d44\u670d\u52d9\u63d0\u4f9b\u5c08\u696d\u8ab2\u5802\u652f\u63f4\u3001\u88fd\u4f5c\u6559\u6750\u53ca\u53c3\u8207\u5bb6\u9577\u5de5\u4f5c\n\u2022 \u9700\u8207\u5176\u4ed6\u5c08\u696d\u5171\u540c\u5408\u4f5c\u63a8\u884c\u8a13\u7df4\n\u2022 \u8655\u7406\u7531\u7763\u5c0e\u6307\u6d3e\u7684\u5176\u4ed6\u5de5\u4f5c\n\u2022 \u4e94\u5929\u5de5\u4f5c\u53ca\u4eab\u6709\u6d25\u8cbc\n\u2022 \u5de5\u4f5c\u5730\u9ede:\u6771\u6d8c\u6eff\u6771\u90a8\n\u8981\u6c42\uff1a\n\u9999\u6e2f\u4e2d\u5b78\u6587\u6191\u8003\u8a66\u4e94\u79d1\u5305\u62ec\u4e2d\u6587\u3001\u82f1\u6587\u3001\u6578\u5b78\u3001\u901a\u8b58\u9054\u4e8c\u7d1a\u6216\u9999\u6e2f\u4e2d\u5b78\u6703\u8003\u4e94\u79d1\u5408\u683c\u5305\u62ec\u4e2d\u6587\u3001\u82f1\u6587(2007\u5e74\u524d\u4e4b\"\u8ab2\u7a0b\u4e59\")\u3001\u6578\u5b78\u6216\u5177\u540c\u7b49\u5b78\u6b77\n\u2022 \u6301\u8a8d\u53ef\u8a3b\u518a\u5e7c\u5152\u5de5\u4f5c\u54e1\u8b49\u66f8\n\u2022 \u6301\u8a8d\u53ef\u7279\u6b8a\u5e7c\u5152\u5de5\u4f5c\u54e1\u8b49\u66f8\u512a\u5148\u8003\u616e\n\u2022 \u5177\u7279\u6b8a\u5e7c\u5152\u670d\u52d9\u7d93\u9a57\u8005\u512a\u5148\u8003\u616e\n\n", "employment_types": ["Full Time", "Contract"], "selling_points": ["conduct thematic research on museum exhibit", "conduct field study and prepare research reports", "major in History or Anthropology"], "locations": ["Tsuen Wan Area"], "categories": ["Education", "Lecturer / Professor", "Others", "Student / Fresh Graduate / No Experience", "Public / Civil", "Others"], "post_time": "2022-01-11T04:42:26Z", "salary": {"currency": "HKD", "max": 16999, "min": 14000, "period": "monthly", "term": null}, "salary_visible": true, "title_keywords": ["researcher"], "responsibilities": [], "requirements": {"degrees": [], "majors": [], "languages": [], "language_level": [], "hard_skills": [], "soft_skills": [], "languages_combined": []}, "experience_required": {"duration": [], "field": []}}, {"job_id": "100003009040155", "location_code": "hk", "company": "Baptist Oi Kwan Social Service", "job_title": "\u4e8c\u7d1a\u8077\u696d\u6cbb\u7642\u5e2b (\u7cbe\u795e\u5065\u5eb7\u7d9c\u5408\u670d\u52d9)", "description": "\u8077\u4f4d\u7de8\u865f\uff1a359\n\n\u70ba\u7cbe\u795e\u5fa9\u5143\u4eba\u58eb\u820d\u53cb\u63d0\u4f9b\u7368\u7acb\u751f\u6d3b\u80fd\u529b\u3001\u8a8d\u77e5\u53ca\u8077\u696d\u80fd\u529b\u8a55\u4f30\uff0c\u63d0\u4f9b\u500b\u5225\u3001\u5c0f\u7d44\u8077\u696d\u6cbb\u7642\u8a13\u7df4\u548c\u5c31\u696d\u652f\u63f4\uff1b\u767c\u5c55\u8077\u696d\u6cbb\u7642\u5728\u5bbf\u820d\u7684\u5404\u9805\u670d\u52d9\uff0c\u63d0\u4f9b\u54e1\u5de5\u5728\u8077\u57f9\u8a13\uff1b\u5354\u52a9\u8655\u7406\u4e2d\u5fc3\u884c\u653f\u5de5\u4f5c\u3002\n\n\u8a3b\u518a\u8077\u696d\u6cbb\u7642\u5e2b\uff1b\u51771\u5e74\u7cbe\u795e\u5065\u5eb7\u670d\u52d9\u81e8\u5e8a\u7d93\u9a57\u512a\u5148\uff1b\u8655\u4e8b\u7368\u7acb\u3001\u6210\u719f\u53ca\u5177\u826f\u597d\u6e9d\u901a\u80fd\u529b\uff1b\u89c0\u5858\u5340\u3002\n\nEnquiries\n\n\u7533\u8acb\u65b9\u6cd5\uff1a\n\u6709\u95dc\u8077\u4f4d\u7684\u8077\u8cac\u3001\u5165\u8077\u8981\u6c42\u53ca\u7533\u8acb\u65b9\u6cd5\uff0c\u8acb\u700f\u89bd\u672c\u8655\u7db2\u7ad9 https://bokss.org.hk/recruitment\n\n\u7533\u8acb\u4eba\u6240\u63d0\u4f9b\u7684\u8cc7\u6599\u5c07\u4e88\u4fdd\u5bc6\u53ca\u53ea\u4f5c\u62db\u8058\u6709\u95dc\u8077\u4f4d\u7528\u9014", "employment_types": ["Full Time"], "selling_points": [], "locations": ["Kwun Tong Area"], "categories": ["Medical Services", "Therapist", "Public / Civil", "Social Services - Community / Non-profit Organization", "Others"], "post_time": "2022-01-12T01:38:57Z", "salary": {"currency": null, "max": null, "min": null, "period": "monthly", "term": null}, "salary_visible": false, "title_keywords": [], "responsibilities": ["recruitment"], "requirements": {"degrees": [], "majors": [], "languages": [], "language_level": [], "hard_skills": [], "soft_skills": [], "languages_combined": []}, "experience_required": {"duration": [], "field": []}}, {"job_id": "100003009040706", "location_code": "hk", "company": "Yan Chai Hospital Social Services Department", "job_title": "\u7279\u6b8a\u5e7c\u5152\u5de5\u4f5c\u54e1", "description": "\n\u2022 \u9999\u6e2f\u4e2d\u5b78\u6703\u8003\u6216\u9999\u6e2f\u4e2d\u5b78\u6587\u6191\u8003\u8a662\u79d1\u5408\u683c\u6216\u4ee5\u4e0a\u6216\u540c\u7b49\u5b78\u6b77\n\u2022 \u5df2\u8a3b\u518a\u70ba\u5e7c\u5152\u5de5\u4f5c\u54e1\n\u5982\u5df2\u6301\u6709\u8a8d\u53ef\u7279\u6b8a\u6559\u80b2\u8a3c\u66f8(\u63a5\u53d7\u7279\u6b8a\u5e7c\u5152\u5de5\u4f5c\u54e1\u5728\u8077\u8a13\u7df4)\u8005\uff0c\u53ef\u984d\u5916\u7372\u767c\u6d25\u8cbc\n\u2022 \u5177\u4e00\u5e74\u6216\u4ee5\u4e0a\u7279\u6b8a\u5e7c\u5152\u5de5\u4f5c\u7d93\u9a57\u5c24\u4f73\n\u2022 \u8ca0\u8cac\u500b\u6848\u8f14\u5c0e\u3001\u5c0f\u7d44\u8a13\u7df4\u7de8\u5beb\u53ca\u8a2d\u8a08\u6559\u6750\u7b49\n\u5165\u8077\u85aa\u916c\u6309\u76f8\u95dc\u5de5\u4f5c\u7d93\u9a57\u800c\u5b9a\uff0c\u6708\u85aa\u53ef\u9054$35,040\uff1b\u53e6\u6bcf\u6708\u6709\u85aa\u91d1\u6d25\u8cbc\n\u2022 \u5de5\u4f5c\u5730\u5340\uff1a\u8343\u7063\n\u622a\u6b62\u65e5\u671f\uff1a2022\u5e741\u670814\u65e5\n\n", "employment_types": ["Full Time"], "selling_points": [], "locations": ["Tsuen Wan Area"], "categories": ["Public / Civil", "Social Services - Community / Non-profit Organization", "Others"], "post_time": "2022-01-12T02:58:31Z", "salary": {"currency": null, "max": null, "min": null, "period": "monthly", "term": null}, "salary_visible": false, "title_keywords": [], "responsibilities": [], "requirements": {"degrees": [], "majors": [], "languages": [], "language_level": [], "hard_skills": [], "soft_skills": [], "languages_combined": []}, "experience_required": {"duration": [], "field": []}}, {"job_id": "100003009040267", "location_code": "hk", "company": "Hays", "job_title": "Company Secretarial Officer, Listed, 33k", "description": "Entry level role for company secretary with in-house listing rules compliance experience!\n\nYour new company\nOur client is a main board Hong Kong listed company which operates through segments of business in finance and property investments.\n\nYour new role\n\nAssist in handling full spectrum of company secretarial duties for the listed group and subsidiaries\nPrepare announcements, circulars, annual and interim reports and HKEx filings\nUpdate and maintain statutory record\nParticipate in ad hoc projects when required\n\n\nWhat you'll need to succeed\n\n5+ years of company secretarial experience gained from Hong Kong listed companies\nGood command in both English and Chinese\nImmediately available\n\n\nWhat you'll get in return\nYou will be working in a business which provides you with great exposure in terms of handling transactions and listing rules related matters. You will be working in a team that is friendly and helpful.\n\nWhat you need to do now\nIf you're interested in this role, click 'apply now' or for further information and a confidential discussion on this role or to find out about more opportunities in the in-house legal space, please contact Natalie Kwok at Hays on +852 2230 7948 or email natalie.kwok@hays.com.hk", "employment_types": ["Full Time", "Permanent"], "selling_points": ["Instantly recognisable brand", "Stable business", "Flexible working arrangement"], "locations": ["Not Specified"], "categories": ["Professional Services", "Company Secretary", "Property / Real Estate", "Property Management", "Public / Civil", "Others"], "post_time": "2022-01-12T02:03:37Z", "salary": {"currency": "HKD", "max": 34999, "min": 25000, "period": "monthly", "term": null}, "salary_visible": true, "title_keywords": ["company secretarial officer"], "responsibilities": ["compliance", "transactions", "maintain", "ad hoc projects", "reports", "contact", "listing"], "requirements": {"degrees": [], "majors": [], "languages": ["english", "chinese"], "language_level": ["good command"], "hard_skills": [], "soft_skills": ["interested in", "friendly"], "languages_combined": [{"language": "english", "language_level": ["good command"]}, {"language": "chinese", "language_level": ["good command"]}]}, "experience_required": {"duration": ["5+ years"], "field": ["secretarial", "compliance"]}}, {"job_id": "100003009040790", "location_code": "hk", "company": "Hong Kong Children and Youth Services", "job_title": "\u793e\u6703\u5de5\u4f5c\u54e1 (\u7d05\u8932\u5b50\u9752\u5e74\u6210\u9577\u53ca\u898f\u5283\u8a08\u5283)", "description": "\n\u5165\u8077\u8981\u6c42\uff1a\u8a3b\u518a\u793e\u5de5\uff0c\u6301\u6709\u8a8d\u53ef\u4e4b\u793e\u6703\u5de5\u4f5c\u5b78\u4f4d\u6216\u4ee5\u4e0a\u5b78\u6b77\uff0c\u5177\u63a8\u884c\u5065\u5eb7\u6821\u5712\u8a08\u5283\u3001\u9752\u5e74\u751f\u6daf\u898f\u5283\u8a08\u5283\u3001\u7279\u6b8a\u5b78\u7fd2\u9700\u8981\u670d\u52d9\u7684\u76f8\u95dc\u7d93\u9a57\u512a\u5148\u3002\n\n\u8077\u8cac\uff1a \u8ca0\u8cac\u63a8\u884c\u5065\u5eb7\u6821\u5712\u8a08\u5283\u3001\u9752\u5e74\u751f\u6daf\u898f\u5283\u8a08\u5283\u53ca\u767c\u5c55\u7279\u6b8a\u5b78\u7fd2\u9700\u8981\u670d\u52d9\u3002\n\n\u5de5\u4f5c\u5730\u9ede\uff1a\u5927\u57d4\u5340\n\n", "employment_types": ["Full Time"], "selling_points": [], "locations": ["Tai Po Area"], "categories": ["Public / Civil", "Social Services - Community / Non-profit Organization", "Others"], "post_time": "2022-01-12T03:05:00Z", "salary": {"currency": null, "max": null, "min": null, "period": "monthly", "term": null}, "salary_visible": false, "title_keywords": [], "responsibilities": [], "requirements": {"degrees": [], "majors": [], "languages": [], "language_level": [], "hard_skills": [], "soft_skills": [], "languages_combined": []}, "experience_required": {"duration": [], "field": []}}, {"job_id": "100003009038609", "location_code": "hk", "company": "Innovation Engineering Company", "job_title": "\u6a13\u5b87\u63a7\u5236\u7cfb\u7d71\u52a9\u7406\u5de5\u7a0b\u5e2b", "description": "\n\u8077\u8cac :\u8ca0\u8cac\u8ddf\u9032\u516c\u71df/\u5927\u578b\u6a5f\u69cb\u5de5\u7a0b\u9805\u76ee\uff0c\u65e5\u5e38\u7cfb\u7d71\u4fdd\u990a\u53ca\u76f8\u95dc\u6587\u4ef6\u8655\u7406\n\n\u8cc7\u6b77 :\u5c08\u4e0a\u6559\u80b2\uff1a\u6587\u6191/\u8b49\u66f8; \u826f\u597d\u7cb5\u8a9e; \u4e00\u822c\u666e\u901a\u8a71; \u826f\u597d\u82f1\u8a9e; \u61c2\u95b1\u8b80\u4e2d\u6587; \u61c2\u95b1\u8b80\u82f1\u6587; \u61c2\u8996\u7a97\u64cd\u4f5c; \u61c2MS Excel; \u61c2AutoCAD\n\n\u5f85\u9047 :\u6bcf\u6708$12,000 - $18,000, \u6709\u96d9\u7ce7, \u661f\u671f\u4e00\u81f3\u516d: \u4e0a\u53489\u6642\u534a\u81f3\u4e0b\u53486\u6642, \u6bcf\u9031\u5de5\u4f5c5\u5929\u81f36\u5929, \u6bcf\u5929\u5de5\u4f5c 7 - 8 \u5c0f\u6642\n\n\u7533\u8acb\u9808\u77e5 :\u6c42\u8077\u8005\u53ef\u96fb\u90f5(Apply Now)\u5c65\u6b77\u8868\u7d66\u5275\u65b0\u5de5\u7a0b\u516c\u53f8\u3002\u5982\u8981\u7d22\u53d6\u6536\u96c6\u500b\u4eba\u8cc7\u6599\u8072\u660e, \u8acb\u8207\u674e\u5148\u751f(Email)\u806f\u7d61\u3002\n\n", "employment_types": ["Full Time"], "selling_points": [], "locations": ["Not Specified"], "categories": ["Admin & HR", "Administration / Operation Manager", "Others", "Junior Executive", "Public / Civil", "Others"], "post_time": "2022-01-11T07:30:58Z", "salary": {"currency": null, "max": null, "min": null, "period": "monthly", "term": null}, "salary_visible": false, "title_keywords": [], "responsibilities": [], "requirements": {"degrees": [], "majors": [], "languages": [], "language_level": [], "hard_skills": ["excel"], "soft_skills": [], "languages_combined": []}, "experience_required": {"duration": [], "field": []}}, {"job_id": "100003009041444", "location_code": "hk", "company": "One Fresh Limited", "job_title": "\u4e2d\u592e\u5eda\u623f\u751f\u7522\u52a9\u7406**", "description": "\n\u8077\u8cac :\u4e00\u822c\u4e2d\u592e\u5eda\u623f\u5de5\u4f5c, \u9810\u5099\u98df\u6750\u5305\u88dd\u5de5\u4f5c, \u8ca0\u8cac\u70f9\u8abf, \u6e05\u6d17\u7528\u5177\u53ca\u6e05\u6f54\u5eda\u623f\n\n\u8cc7\u6b77 :\u6c92\u6709\u5b78\u6b77\u8981\u6c42; 6\u500b\u6708\u7d93\u9a57; \u826f\u597d\u7cb5\u8a9e; \u4e00\u822c\u666e\u901a\u8a71; \u7565\u61c2\u8b80\u5beb\u4e2d\u6587\n\n\u5f85\u9047 :\u6bcf\u6708$13,000 - $15,000, \u6709\u54e1\u5de5\u8cfc\u7269\u512a\u60e0 \u53ca\u6649\u5347\u6a5f\u6703, \u4e00\u81f3\u4e94:9:00AM-6:00PM/1:00PM-10:00PM,\u516d: 9:00AM-1:00PM/9:00AM-6:00PM/1:00PM-10:00PM,\u6bcf\u9031\u5de5\u4f5c5\u5929\u81f36\u5929,\u8f2a\u73ed,\u8f2a\u4f11\n\n\u7533\u8acb\u9808\u77e5 :\u6c42\u8077\u8005\u53ef\u81f4\u96fb35635450\u8207ONE FRESH LIMITED\u9ec3\u5c0f\u59d0\u806f\u7d61\u3002\n\n", "employment_types": ["Full Time"], "selling_points": [], "locations": ["Kwai Fong"], "categories": ["Admin & HR", "Administration / Operation Manager", "Others", "Junior Executive", "Public / Civil", "Others"], "post_time": "2022-01-12T03:53:49Z", "salary": {"currency": null, "max": null, "min": null, "period": "monthly", "term": null}, "salary_visible": false, "title_keywords": [], "responsibilities": [], "requirements": {"degrees": [], "majors": [], "languages": [], "language_level": [], "hard_skills": [], "soft_skills": [], "languages_combined": []}, "experience_required": {"duration": [], "field": []}}, {"job_id": "100003009040967", "location_code": "hk", "company": "Hong Kong Kanekyu Co Limited", "job_title": "\u98df\u54c1\u5de5\u5834\u751f\u7522\u52a9\u7406", "description": "\n\u8077\u8cac :\u8ca0\u8cac\u98df\u54c1\u5de5\u5834\u751f\u7522\u6ce1\u83dc, \u8c46\u8150, \u5305\u88dd\u8ca8\u54c1\u7b49, \u98df\u54c1\u751f\u7522\u5de5\u4f5c(\u5de5\u4f5c\u671f\u9593\u516c\u53f8\u6703\u63d0\u4f9b\u624b\u5957\uff0c\u6c34\u978b\uff0c\u570d\u88d9)\n\n\u8cc7\u6b77 :\u4e2d\u4e09\u7a0b\u5ea6; 2\u5e74\u7d93\u9a57; \u826f\u597d\u7cb5\u8a9e; \u61c2\u95b1\u8b80\u4e2d\u6587\n\n\u5f85\u9047 :\u6bcf\u6708$10,000, \u6709\u91ab\u7642\u798f\u5229, \u81b3\u98df\u6d25\u8cbc, \u8d85\u6642\u5de5\u4f5c\u6d25\u8cbc \u53ca\u4ea4\u901a\u6d25\u8cbc, \u661f\u671f\u4e00\u81f3\u4e94: \u4e0a\u53488\u6642\u534a\u81f3\u4e0b\u53485\u6642\u534a\u53ca\u661f\u671f\u516d: \u4e0a\u53488\u6642\u534a\u81f3\u4e2d\u534812\u6642\u534a, \u6bcf\u9031\u5de5\u4f5c5\u5929\u534a, \u6bcf\u5929\u5de5\u4f5c 9 \u5c0f\u6642\n\n\u7533\u8acb\u9808\u77e5 :\u6c42\u8077\u8005\u53ef\u81f4\u96fb91227250\u8207\u9999\u6e2f\u91d1\u4e45\u6709\u9650\u516c\u53f8\u9ec3\u5c0f\u59d0\u806f\u7d61\u3002\n\n", "employment_types": ["Full Time"], "selling_points": [], "locations": ["Tsuen Wan Area"], "categories": ["Admin & HR", "Administration / Operation Manager", "Others", "Junior Executive", "Public / Civil", "Others"], "post_time": "2022-01-12T03:17:20Z", "salary": {"currency": null, "max": null, "min": null, "period": "monthly", "term": null}, "salary_visible": false, "title_keywords": [], "responsibilities": [], "requirements": {"degrees": [], "majors": [], "languages": [], "language_level": [], "hard_skills": [], "soft_skills": [], "languages_combined": []}, "experience_required": {"duration": [], "field": []}}, {"job_id": "100003009040850", "location_code": "hk", "company": "Evangelical Lutheran Church Social Service - Hong Kong", "job_title": "\u793e\u6703\u5de5\u4f5c\u54e1Social Woker(\u8077\u4f4d\u7de8\u865f\uff1aSWII-MOSDECC)", "description": "\n\u2022 \u65bc\u99ac\u978d\u5c71\u9577\u8005\u5730\u5340\u4e2d\u5fc3\u5de5\u4f5c\n\u2022 \u9808\u5177\u672c\u6e2f\u793e\u5de5\u6587\u6191\u6216\u4ee5\u4e0a\u7684\u8a3b\u518a\u793e\u5de5\uff0c\u5177\u9577\u8005\u670d\u52d9\u7d93\u9a57\u53ef\u7372\u512a\u5148\u8003\u616e\n\u2022 \u4e3b\u8981\u8ca0\u8cac\u8f14\u5c0e\u53ca\u5c0f\u7d44\u5de5\u4f5c\u3001\u8ddf\u9032\u9577\u8005\u500b\u6848\u53ca\u8209\u8fa6\u8b77\u8001\u8005\u6d3b\u52d5\uff0c\u4e26\u9700\u652f\u63f4\u9577\u8005\u5730\u5340\u4e2d\u5fc3\u4e4b\u670d\u52d9\u53ca\u4e8b\u5de5\n\u2022 \u6709\u670d\u52d9\u9577\u8005\u5fc3\u5fd7\uff0c\u6027\u683c\u6210\u719f\u3001\u4e3b\u52d5\u3001\u80fd\u7368\u7acb\u8655\u4e8b\u3001\u5177\u826f\u597d\u6e9d\u901a\u53ca\u6587\u7258\u80fd\u529b\u3001\u80fd\u8207\u4e0d\u540c\u5718\u968a\u53ca\u5c08\u696d\u5408\u4f5c\n\n", "employment_types": ["Full Time"], "selling_points": [], "locations": ["Shatin Area"], "categories": ["Public / Civil", "Social Services - Community / Non-profit Organization", "Others"], "post_time": "2022-01-12T03:09:07Z", "salary": {"currency": null, "max": null, "min": null, "period": "monthly", "term": null}, "salary_visible": false, "title_keywords": [], "responsibilities": [], "requirements": {"degrees": [], "majors": [], "languages": [], "language_level": [], "hard_skills": [], "soft_skills": [], "languages_combined": []}, "experience_required": {"duration": [], "field": []}}, {"job_id": "100003008218191", "location_code": "hk", "company": "Haven of Hope Christian Service", "job_title": "\u793e\u5de5 (\u7de8\u865f : CSE/SW/JDB)", "description": "\u6301\u6709\u9999\u6e2f\u8a8d\u53ef\u793e\u6703\u5de5\u4f5c\u6587\u6191\u6216\u4ee5\u4e0a\uff0c\u4e26\u5df2\u767b\u8a18\u6210\u70ba\u8a3b\u518a\u793e\u5de5\n\u6027\u683c\u6210\u719f\uff0c\u4e3b\u52d5\uff0c\u80fd\u7368\u7acb\u5de5\u4f5c\uff0c\u6709\u8cac\u4efb\u5fc3\uff0c\u5584\u65bc\u8de8\u5c08\u696d\u5408\u4f5c\n\u70ba\u96e2\u9662\u652f\u63f4\u8a08\u5283\u525b\u51fa\u9662\u7684\u9ad4\u5f31\u9577\u8005\u63d0\u4f9b\u500b\u6848\u7ba1\u7406\u3001\u5bb6\u8a2a\u3001\u60c5\u7dd2\u652f\u63f4\u53ca\u8b77\u8001\u8005\u652f\u63f4\u7b49\u670d\u52d9\uff1b\u5177\u5169\u5e74\u6216\u4ee5\u4e0a\u793e\u6703\u5de5\u4f5c\u7d93\u9a57\n\u5de5\u4f5c\u5730\u9ede\uff1a\u6771\u4e5d\u9f8d\u3001\u5c07\u8ecd\u6fb3\u53ca\u897f\u8ca2\n\n\u6709\u610f\u8005\u8acb\u65bc\u4e8c\u96f6\u4e8c\u4e8c\u5e74\u4e8c\u6708\u4e94\u65e5\u524d\u89aa\u7e55\u5c65\u6b77\u53ca\u671f\u671b\u5f85\u9047\uff08\u8acb\u65bc\u4fe1\u5c01\u9762\u53ca\u4fe1\u5167\u8a3b\u660e\u7533\u8acb\u8077\u4f4d\u7de8\u865f\uff09\u5bc4\u65b0\u754c\u5c07\u8ecd\u6fb3\u9748\u5be6\u8def\u4e03\u865f\u57fa\u7763\u6559\u9748\u5be6\u5354\u6703\u4eba\u529b\u8cc7\u6e90\u90e8\u6536\uff0c\u6216\u96fb\u90f5\u81f3 \"Apply Now\"\uff0c\u6216\u767c\u9001\u81f3Whatsapp\u865f\u78bc6507 8148\uff08\u6a19\u984c\u8acb\u8a3b\u660e\u8077\u4f4d\u7de8\u865f\uff09\u3002\u5982\u4e00\u500b\u6708\u5167\u672a\u7372\u901a\u77e5\u7d04\u898b\uff0c\u5247\u4f5c\u843d\u9078\u8ad6\u3002\n\n\u67e5\u8a62\u71b1\u7dda\uff1a2703 3238 (\u96fb\u8a71)\uff1b6507 8148(Whatsapp)\u3002\n\n\u6709\u95dc\u672c\u6703\u8a73\u60c5\uff0c\u8acb\u700f\u89bd\u7db2\u9801http://www.hohcs.org.hk\n\n(\u53ef\u80fd\u7372\u8058\u4eba\u58eb\uff08\u5982\u5f9e\u4e8b\u8207\u5152\u7ae5\u6216\u7cbe\u795e\u4e0a\u7121\u884c\u70ba\u80fd\u529b\u4eba\u58eb\u6709\u95dc\u5de5\u4f5c\u8077\u4f4d\uff09\u9808\u65bc\u5165\u8077\u524d\u9032\u884c\uff0f\u63d0\u4ea4\u6027\u7f6a\u884c\u5b9a\u7f6a\u7d00\u9304\u67e5\u6838\u3002\u7533\u8acb\u4eba\u6240\u63d0\u4f9b\u7684\u8cc7\u6599\u5c07\u4e88\u4fdd\u5bc6\u53ca\u4f5c\u62db\u8058\u6709\u95dc\u8077\u4f4d\u7528\u9014)\u00a0\n\n\u672a\u7d93\u672c\u5354\u6703\u66f8\u9762\u540c\u610f\uff0c\u4ee5\u4e0a\u62db\u8058\u5ee3\u544a\u5168\u90e8\u6216\u90e8\u5206\u5167\u5bb9\u5747\u4e0d\u5f97\u8907\u88fd\u81f3\u5176\u4ed6\u62db\u8058\u7db2\u7ad9\u3002", "employment_types": ["Full Time"], "selling_points": [], "locations": ["Not Specified"], "categories": ["Public / Civil", "Counseling", "Social Services - Community / Non-profit Organization", "Others"], "post_time": "2022-01-17T01:59:47Z", "salary": {"currency": null, "max": null, "min": null, "period": "monthly", "term": null}, "salary_visible": false, "title_keywords": ["\u793e\u5de5"], "responsibilities": [], "requirements": {"degrees": [], "majors": [], "languages": [], "language_level": [], "hard_skills": [], "soft_skills": [], "languages_combined": []}, "experience_required": {"duration": [], "field": []}}, {"job_id": "100003009040816", "location_code": "hk", "company": "Po Leung Kuk", "job_title": "\u793e\u6703\u5de5\u4f5c\u54e1(\u99d0\u6821\u793e\u5de5)SW4/5-CCS (\u9577\u6c99\u7063)", "description": "\n\u5e7c\u5152\u670d\u52d9\n\n\u5165\u8077\u8981\u6c42\n\u2022 \u8a3b\u518a\u793e\u5de5\uff0c\u6301\u8a8d\u53ef\u793e\u6703\u5de5\u4f5c\u5b78\u58eb\u5b78\u4f4d\u6216\u4ee5\u4e0a\u5b78\u6b77\u3002\u5177\u5152\u7ae5\u5fa9\u5eb7\u7d93\u9a57\u53ca\u5c0d\u5e7c\u5152\u670d\u52d9\u5177\u71b1\u8aa0\u8005\u512a\u5148\u8003\u616e\u3002\n\u4e3b\u8981\u8077\u8cac\n\u2022 \u8ca0\u8cac\u5e7c\u7a1a\u5712\u99d0\u6821\u5de5\u4f5c\uff0c\u652f\u63f4\u5e7c\u5152\u53ca\u5176\u5bb6\u9577\u5de5\u4f5c\uff0c\u5305\u62ec\u5e7c\u5152\u53ca\u5bb6\u9577\u89aa\u8077\u5c0f\u7d44/\u6d3b\u52d5\uff0c\u500b\u6848\u8f14\u5c0e\u53ca\u76f8\u95dc\u884c\u653f\u7b49\u5de5\u4f5c\u3002\n\u9577\u6c99\u7063 [via\u00a0 Apply Now ] 2277 8424\n\n\u622a\u6b62\u7533\u8acb\u65e5\u671f : 2022/1/28\n\n", "employment_types": ["Full Time"], "selling_points": [], "locations": ["Cheung Sha Wan"], "categories": ["Public / Civil", "Social Services - Community / Non-profit Organization", "Others"], "post_time": "2022-01-12T03:06:57Z", "salary": {"currency": null, "max": null, "min": null, "period": "monthly", "term": null}, "salary_visible": false, "title_keywords": [], "responsibilities": [], "requirements": {"degrees": [], "majors": [], "languages": [], "language_level": [], "hard_skills": [], "soft_skills": [], "languages_combined": []}, "experience_required": {"duration": [], "field": []}}, {"job_id": "100003009011414", "location_code": "hk", "company": "Office of the Privacy Commissioner for Personal Data", "job_title": "Assistant Privacy Commissioner (a directorate post)", "description": "***Applications via Apply Now will NOT be considered.\u00a0 Please follow the application procedures mentioned below***\n\nRequirements\n\na) A\u00a0good Bachelor\u2019s Degree from a recognised university in Hong Kong or a university in a common law jurisdiction;\nb)\u00a0A Level 2 result in the Use of English paper and a Level 2 result in the Use of Chinese paper in the Common Recruitment Examination, or preferably \u00a0Grade \u201cB\u201d or above in Use of English in the Hong Kong Advanced Level Examination (HKALE), or Grade \u201c5*\u201d or above in the Hong Kong Diploma of Secondary Education Examination (HKDSE), or equivalent, or a minimum overall band score of 7.5 in the International English Language Testing System (IELTS) with the Writing Sub-test score not lower than 7; good command of written and spoken Chinese, preferably Grade \u201cB\u201d or above in Chinese Language in the Hong Kong Certificate of Education Examination (HKCEE), or Grade \u201c5*\u201d or above in HKDSE, or equivalent; and\nc)\u00a0Preferably solicitor or barrister admitted to practice in Hong Kong with a minimum of 10 years of post-qualification experience.\u00a0 Prior experience in criminal prosecutions work would be an advantage.\u00a0 Applicants with 8 years to 10 years of post-qualification experience may apply but may be offered appointment at a remuneration package commensurate with the level of experience.\n\nExpectations\n\na) Relevant experience in public administration, professional practice or private sector management at a senior level;\nb)\u00a0Experience related to personal data privacy work; familiarity with technological developments that have implications on personal data privacy would be an advantage;\nc) Proficiency in advocacy and criminal prosecution would be an advantage;\nd)\u00a0Strong analytical ability to make independent judgement with a high level of acumen in social and political issues;\ne)\u00a0Positive, diligent and self-motivated with good inter-personal skills; and\nf)\u00a0Excellent presentational skills in both written and oral English and Chinese.\n\nMajor Duties\n\na)\u00a0To assist the Privacy Commissioner in the discharge of her statutory duties and responsibilities, including the strategic planning and formulation of operational policies and priorities;\nb) To monitor, co-ordinate and supervise the conduct of criminal investigations and the handling of complaints relating to breaches of the requirements of the PD(P)O;\nc)\u00a0To liaise with other law enforcement agencies in seeking expert advice, assistance in operations and cooperation in crime detection and investigations;\nd)\u00a0To monitor, co-ordinate and supervise the provision of advice and undertake\u00a0research projects, surveys and public consultation exercises on major / topical privacy matters; and\ne)\u00a0To represent the PCPD at conferences, meetings and working groups on personal data privacy matters.\n\nRemuneration Package\n\nThe successful candidate will be rewarded with commensurate remuneration package with monthly salary ranging from $150,950 to $165,200.\u00a0 He or she will be appointed on 2 years\u2019 contract terms. \u00a0In addition to a 5-day week, we provide annual leave, medical and dental insurance benefits, cash allowance and a gratuity on satisfactory completion of the contract which, when added to the employer\u2019s contribution to a Mandatory Provident Fund scheme, is up to 15% of the total basic salary for the contract period.\n\n***Applications via Apply Now will NOT be considered.\u00a0Please follow the application procedures mentioned below***\n\nPoints to Note\n\nClose of Applications:\n\n22 January 2022 (Saturday)\n\nApplication Procedures:\n\nInterested candidates may apply in confidence by 1) providing a detailed resume, 2) completing the job application form\u00a0available on PCPD\u2019s website\u00a0(https://www.pcpd.org.hk/english/about_pcpd/career/career.html), and 3) providing a cover letter in English or Chinese, stating the candidate's suitability for the job, all of\u00a0which\u00a0should be sent to the Human Resources Section of the PCPD by email (please go to our website for the email address).\n\nApplications without all prescribed documents will not be considered.\n\nApplicants who do not hear from us within six weeks from the date of the close of applications should consider their applications unsuccessful.\u00a0 All applications will be treated in strict confidence.\u00a0 Personal data provided will be used for recruitment purpose only and in accordance with the Code of Practice on Human Resource Management issued by the PCPD, which can be downloaded from the PCPD's website.\u00a0 In accordance with our data retention policy, the personal data of unsuccessful candidates collected for this recruitment exercise will be kept for 12 months from its completion and thereafter the data will be destroyed.\n\nFor enquiries, please call Ms Wan at 3423 6657.\n\n\n\nThe PCPD is an Equal Opportunity Employer\nhttp://www.pcpd.org.hk/\u00a0 \u00a0", "employment_types": ["Full Time", "Contract"], "selling_points": ["Solicitor or barrister admitted to practice in HK", "10 years of post-qualification experience", "Proficiency in advocacy and criminal prosecution"], "locations": ["Wan Chai"], "categories": ["Professional Services", "Legal & Compliance", "Management", "Top Executives (CEO, CFO, CTO, GM, MD etc.)", "Public / Civil", "Others"], "post_time": "2022-01-10T16:52:33Z", "salary": {"currency": "HKD", "max": null, "min": 120000, "period": "monthly", "term": null}, "salary_visible": true, "title_keywords": ["assistant"], "responsibilities": ["strategic planning", "research projects", "policies", "operations", "monitor", "procedures", "expert advice", "conferences", "liaise with", "personal data", "insurance"], "requirements": {"degrees": ["secondary education", "certificate", "bachelor", "diploma", "degree", "hkdse"], "majors": ["law"], "languages": ["english", "chinese"], "language_level": ["excellent", "good command"], "hard_skills": ["make", "c", "acumen"], "soft_skills": ["self-motivated", "oral", "independent", "advanced", "diligent", "inter-personal skills", "positive"], "languages_combined": [{"language": "english", "language_level": ["excellent"]}, {"language": "chinese", "language_level": ["excellent", "good command"]}]}, "experience_required": {"duration": ["8 years", "minimum of 10 years", "10 years"], "field": ["management", "post-qualification", "related", "relevant experience", "administration"]}}, {"job_id": "100003009043752", "location_code": "hk", "company": "Yan Oi Tong Ltd", "job_title": "\u6559\u80b2\u5fc3\u7406\u5b78\u5bb6(\u517c\u8077) (\u8077\u4f4d\u7de8\u865f: PPI/PT2203/220113)", "description": "\u9808\u6301\u6709\u7531\u672c\u5730\u5927\u5b78\u9812\u6388\u7684\u6559\u80b2\u5fc3\u7406\u78a9\u58eb\u5b78\u4f4d\uff0c\u6216\u540c\u7b49\u5b78\u6b77\n5\u5e74\u4ee5\u4e0a\u5e7c\u5152\u53ca\u5165\u6821\u5de5\u4f5c\u7d93\u9a57\u512a\u5148\n\u4e3b\u8cac\u65bc\u5168\u6e2f\u4e0d\u540c\u5e7c\u7a1a\u5712\uff0c\u63d0\u4f9b\u5230\u6821\u5c08\u696d\u8aee\u8a62\u670d\u52d9\n\u8ca0\u8cac\u5b78\u751f\u8a55\u4f30\uff1b\u63d0\u4f9b\u5e7c\u7a1a\u5712\u793e\u5de5\u53ca\u8001\u5e2b\u5c08\u696d\u8aee\u8a62\u670d\u52d9\u3001\u5bb6\u9577\u6216\u5c08\u696d\u57f9\u8a13\u7b49\n\u80fd\u64cd\u6d41\u5229\u7cb5\u8a9e\u53ca\u82f1\u8a9e\u53ca\u66f8\u5beb\u6d41\u9806\u4e2d\u82f1\u6587\n\u6210\u719f\u3001\u7368\u7acb\u53ca\u826f\u597d\u6e9d\u901a\u6280\u5de7\uff0c\u80fd\u6709\u6548\u767c\u63ee\u5718\u968a\u5408\u4f5c\u7cbe\u795e\n\u6bcf\u6708\u5de5\u4f5c8\u7bc0\uff0c\u6bcf\u7bc02.5\u5c0f\u6642\uff0c\u53ef\u5f48\u6027\u5b89\u6392\u4e0a\u73ed\u6642\u9593", "employment_types": ["Part Time", "Contract"], "selling_points": ["\u9808\u6301\u6709\u7531\u672c\u5730\u5927\u5b78\u9812\u6388\u7684\u6559\u80b2\u5fc3\u7406\u78a9\u58eb\u5b78\u4f4d\uff0c\u6216\u540c\u7b49\u5b78\u6b77", "5\u5e74\u4ee5\u4e0a\u5e7c\u5152\u53ca\u5165\u6821\u5de5\u4f5c\u7d93\u9a57\u512a\u5148", "\u4e3b\u8cac\u65bc\u5168\u6e2f\u4e0d\u540c\u5e7c\u7a1a\u5712\uff0c\u63d0\u4f9b\u5230\u6821\u5c08\u696d\u8aee\u8a62\u670d\u52d9"], "locations": ["Not Specified"], "categories": ["Education", "Others", "Public / Civil", "Social Services - Community / Non-profit Organization", "Others"], "post_time": "2022-01-13T01:50:05Z", "salary": {"currency": null, "max": null, "min": null, "period": "hourly", "term": null}, "salary_visible": false, "title_keywords": [], "responsibilities": [], "requirements": {"degrees": [], "majors": [], "languages": [], "language_level": [], "hard_skills": [], "soft_skills": [], "languages_combined": []}, "experience_required": {"duration": [], "field": []}}, {"job_id": "100003009035141", "location_code": "hk", "company": "Office of Hon Jeffrey Lam, Legislative Council Member", "job_title": "\u8b70\u54e1\u52a9\u7406/Legislative Assistant", "description": "Job Description:\n\n\nAssist in handling legislative work\n\u00a0Write speeches and articles in both English and Chinese\nLiaise and work closely with different parties\nOrganize schedule arrangement\nFollow up on concerns from the business community\nSupport ad hoc duties when given\nJob Requirements:\n\u00a0 \u00a0 \u00a0 \u00a0 \u00a0\u00a0\nDegree holder in Communication, \u00a0Journalism, Translation or other\u00a0related disciplines\u00a0\nGood command of spoken and written\u00a0 English and\u00a0Chinese\nKnowledge of media relations and digital media\nSolid writing, editing and researching skills\n\u00a0Be a team player with good communication and presentation skills, and be able to work independently and flexibly;\u00a0\nAbility to work multi-task & under pressure with tight deadlines\n\nWork locations: Admiralty and Chai Wan\u00a0\n\nShortlisted applicants will be invited for an interview and a written test. Interested parties please email full CV by clicking \u201cAPPLY NOW\u201d.\u00a0 Please clearly state the Expected Salary in your resume.\nAll information provided by applicants will be handled with strictest confidence and will be solely used for the purpose of recruitment.", "employment_types": ["Full Time"], "selling_points": [], "locations": ["Admiralty"], "categories": ["Media & Advertising", "Editorial / Journalism", "Public / Civil", "Others"], "post_time": "2022-01-10T08:47:21Z", "salary": {"currency": null, "max": null, "min": null, "period": "monthly", "term": null}, "salary_visible": false, "title_keywords": ["assistant"], "responsibilities": ["liaise", "schedule", "ad hoc duties"], "requirements": {"degrees": ["degree holder"], "majors": ["journalism", "related disciplines"], "languages": ["english", "chinese"], "language_level": ["good command"], "hard_skills": ["translation"], "soft_skills": ["work independently", "multi-task", "under pressure", "communication", "presentation skills", "team player"], "languages_combined": [{"language": "english", "language_level": ["good command"]}, {"language": "chinese", "language_level": ["good command"]}]}, "experience_required": {"duration": [], "field": []}}, {"job_id": "100003009040940", "location_code": "hk", "company": "Po Leung Kuk", "job_title": "\u793e\u6703\u5de5\u4f5c\u54e1SW6-CSCMYDC (\u5c6f\u9580)", "description": "\n\u5152\u7ae5\u53ca\u9752\u5c11\u5e74\u670d\u52d9\n\u5165\u8077\u8981\u6c42\n\u2022 \u8a3b\u518a\u793e\u5de5\uff0c\u6301\u8a8d\u53ef\u793e\u6703\u5de5\u4f5c\u6587\u6191\u6216\u4ee5\u4e0a\u5b78\u6b77\uff0c\u5177\u5927\u578b\u8a08\u5283\u7ba1\u7406\u53caSTEAM\u7d93\u9a57\u512a\u5148\u8003\u616e\u3002\u4e2d\u3001\u82f1\u6587\u8868\u9054\u53ca\u66f8\u5beb\u80fd\u529b\u826f\u597d\u3002\n\u4e3b\u8981\u8077\u8cac\n\u2022 \u8ca0\u8cac\u5e36\u9818\u5718\u968a\u767c\u5c55\u5152\u7ae5\u670d\u52d9\uff1b\u7d71\u7c4c\u3001\u7b56\u5283\u4e2d\u5fc3\u6d3b\u52d5\u53ca\u73ed\u7d44\uff1b\u8ca0\u8cac\u8655\u7406STEAM\u8a08\u5283\uff0c\u5354\u52a9\u8655\u7406\u4e2d\u5fc3\u884c\u653f\u7b49\u5de5\u4f5c\u3002\n\u4e0a\u73ed\u6a21\u5f0f\n\u2022 \u6bcf\u661f\u671f\u6700\u5c11\u9700\u8f2a\u503c2\u665a\u3002\n\u5c6f\u9580 [via\u00a0 Apply Now ] 3462 6260\n\u622a\u6b62\u7533\u8acb\u65e5\u671f : 2022/1/28\n\n", "employment_types": ["Full Time"], "selling_points": [], "locations": ["Tuen Mun Area"], "categories": ["Public / Civil", "Social Services - Community / Non-profit Organization", "Others"], "post_time": "2022-01-12T03:15:13Z", "salary": {"currency": null, "max": null, "min": null, "period": "monthly", "term": null}, "salary_visible": false, "title_keywords": [], "responsibilities": [], "requirements": {"degrees": [], "majors": [], "languages": [], "language_level": [], "hard_skills": [], "soft_skills": [], "languages_combined": []}, "experience_required": {"duration": [], "field": []}}, {"job_id": "100003009043587", "location_code": "hk", "company": "Insurance Authority", "job_title": "Assistant Manager (GI Actuarial)", "description": "Reporting to the Senior Manager / Manager (GI Actuarial, Policy and Development Division), the incumbent will undertake the following:\n\n\u00a0Key Responsibilities\n\nParticipate in developing the Risk-based Capital solvency regime and the monitoring approaches or analytical indicators for supervisory focus\nAssist in providing GI actuarial technical support and/or peer review across teams and divisions\nKeep abreast of the developments of insurance industry, conduct researches and conduct industry-wide reviews\nAssist in developing legislation, rules and guidelines on insurance supervision\nAssist in liaising with industry and professional bodies on actuarial topics relating to the regulation and development of the insurance industry\nAssist in coordination work in IA\u2019s information technology development projects\nPerform any other duties as assigned by senior management to facilitate the administration of the statutory functions of the IA\n\n\u00a0Requirements\n\n\nA Bachelor\u2019s degree in actuarial science, statistics, finance, insurance, computer science or related field\nPart-qualified actuary with a minimum of 3 years\u2019 relevant experience in GI actuarial practices\nExperience in reserving, underwriting, claims, risk management, data analytics and/or nat cat modelling will be valued\u00a0\nKnowledge of the local regulatory requirements, actuarial practices, insurance products, industry practices and market dynamics of insurance business\nProfessional, strong business acumen, open-minded, and able to work with a team in a collaborative environment\nStrong command of written and spoken English. Chinese language ability is an advantage\n\nRemuneration Package\nA competitive remuneration package commensurate with the successful candidate\u2019s experience and qualifications will be offered.\n\nApplication\nReview of the applications will start as soon as possible and continue until 20January 2022, or until the post is filled. Interested applicants may send a letter of application quoting the reference number in the heading, together with a full resume stating public examination and university academic results as well as current and expected salaries\u00a0by clicking \"Apply Now\".\n\nThe Insurance Authority is an equal opportunities employer. Applicants not invited for an interview within 2 months from the submission date may assume their applications unsuccessful. Applications may be considered for other suitable positions within IA. All applications will be handled in strict confidence and the information collected will only be used for recruitment purposes. All information on non-shortlisted applicants will be destroyed after 6 months from the submission of their applications.", "employment_types": ["Full Time", "Permanent"], "selling_points": [], "locations": ["Southern Area"], "categories": ["Accounting", "Others", "Insurance", "Others", "Public / Civil", "Others"], "post_time": "2022-01-12T23:19:12Z", "salary": {"currency": null, "max": null, "min": null, "period": "monthly", "term": null}, "salary_visible": false, "title_keywords": ["assistant manager"], "responsibilities": ["any other duties", "technical support", "guidelines", "review", "monitoring", "teams", "developing", "liaising with", "coordination", "senior management", "insurance", "administration"], "requirements": {"degrees": ["degree", "bachelor"], "majors": ["actuarial science", "finance", "statistics", "computer science", "insurance"], "languages": ["english", "chinese"], "language_level": ["advantage"], "hard_skills": ["data analytics", "acumen"], "soft_skills": ["business acumen", "open-minded", "confidence", "collaborative"], "languages_combined": [{"language": "english", "language_level": []}, {"language": "chinese", "language_level": ["advantage"]}]}, "experience_required": {"duration": ["minimum of 3 years"], "field": ["underwriting", "risk management", "relevant experience"]}}, {"job_id": "100003009040908", "location_code": "hk", "company": "Aberdeen Kai-Fong Welfare Association Social Service Centre", "job_title": "\u793e\u6703\u5de5\u4f5c\u54e1 (Social Worker)\u3010\u8077\u4f4d\u7de8\u865f\uff1a IDSP-RSW- 1/2022-CT \u3011", "description": "\n\u00a0 \u8077\u8cac\uff1a\n\u2022 \u63d0\u4f9b\u500b\u6848\u7ba1\u7406\u53ca\u793e\u5340\u652f\u63f4\u670d\u52d9\n\u2022 \u63a8\u884c\u7fa9\u5de5\u670d\u52d9\u53ca\u6cbb\u7642\u5c0f\u7d44\n\u2022 \u7763\u5c0e\u53ca\u57f9\u8a13\u7167\u9867\u54e1\n\u8981\u6c42\u53ca\u5f85\u9047\uff1a\u00a0\n\u2022 \u9700\u6301\u6709\u793e\u5de5\u6587\u6191\u53ca\u8a3b\u518a\u793e\u5de5\n\u2022 \u51771-2\u5e74\u670d\u52d9\u9577\u8005\u9577\u671f\u75c5\u60a3\u8005\u7d93\u9a57\u512a\u5148\u8003\u616e\n\u6708\u85aa$22,510\u8d77\n\n", "employment_types": ["Full Time"], "selling_points": [], "locations": ["Aberdeen"], "categories": ["Public / Civil", "Social Services - Community / Non-profit Organization", "Others"], "post_time": "2022-01-12T03:12:43Z", "salary": {"currency": null, "max": null, "min": null, "period": "monthly", "term": null}, "salary_visible": false, "title_keywords": [], "responsibilities": [], "requirements": {"degrees": [], "majors": [], "languages": [], "language_level": [], "hard_skills": [], "soft_skills": [], "languages_combined": []}, "experience_required": {"duration": [], "field": []}}, {"job_id": "100003009041066", "location_code": "hk", "company": "Yang Memorial Methodist Social Service", "job_title": "\u5168\u8077\u5eb7\u5065\u8b77\u7406\u54e1I (\u8077\u4f4d\u7de8\u865f\uff1aYMIHCS/HCW I)", "description": "\n\u8077\u8cac :\u4e3b\u8981\u670d\u52d9\u9577\u8005,\u63d0\u4f9b\u65e5\u9593\u5230\u6236\u670d\u52d9, \u4f8b\u5982\u500b\u4eba\u8b77\u7406\u3001\u5bb6\u5c45\u6e05\u6f54\u3001\u9001\u98ef\u3001\u8b77\u9001\u3001\u91ab\u8b77\u7167\u9867 (1\u5e74\u5408\u7d04) (\u5c65\u6b77\u8868\u8a3b\u660e\u7533\u8acb\u8077\u4f4d\u540d\u7a31/\u7de8\u865f\u53ca\u8981\u6c42\u5f85\u9047, \u5de5\u4f5c\u5730\u9ede:\u4e5d\u9f8d\u897f)\n\n\u8cc7\u6b77 :\u5c0f\u516d\u7a0b\u5ea6; 1\u5e74\u7d93\u9a57; \u826f\u597d\u7cb5\u8a9e; \u61c2\u8b80\u5beb\u4e2d\u6587; \u5b8c\u6210\u8d77\u5c45\u7167\u9867\u54e1\u8ab2\u7a0b; \u6301\u8d77\u5c45\u7167\u9867\u54e1/\u4fdd\u5065\u54e1/\u7269\u7406\u6cbb\u7642\u52a9\u7406/\u8077\u696d\u6cbb\u7642\u52a9\u7406\u8b49\u66f8,\u5177\u826f\u597d\u6e9d\u901a\u6280\u5de7\u3001\u8010\u6027\u3001\u5177\u8cac\u4efb\u611f\u3001\u80fd\u7368\u7acb\u5de5\u4f5c\n\n\u5f85\u9047 :\u6bcf\u6708$15,560\u6216\u4ee5\u4e0a (\u8996\u4e4e\u7d93\u9a57\u53ca\u8cc7\u6b77\u800c\u5b9a), \u4e0a\u53488\u664245\u5206\u81f3\u4e0b\u53486\u6642, \u6bcf\u9031\u5de5\u4f5c5\u5929\u81f36\u5929,\u8f2a\u73ed,\u8f2a\u4f11, \u6bcf\u9031\u5de5\u4f5c45\u5c0f\u6642, \u4e0a\u73ed\u6642\u9593\u6703\u56e0\u670d\u52d9\u9700\u8981\u800c\u4f5c\u51fa\u8abf\u52d5\uff0c\u7121\u9700\u591c\u73ed\u5de5\u4f5c\n\n\u7533\u8acb\u9808\u77e5 :\u6c42\u8077\u8005\u53ef\u96fb\u90f5(Apply Now)\u6216\u90f5\u5bc4(\u4e5d\u9f8d\u7aa9\u6253\u8001\u905354\u865f)\u5c65\u6b77\u8868\u7d66\u5faa\u9053\u885b\u7406\u694a\u9707\u793e\u6703\u670d\u52d9\u8655\u3002\u5982\u8981\u7d22\u53d6\u6536\u96c6\u500b\u4eba\u8cc7\u6599\u8072\u660e, \u8acb\u8207\u5f35\u5c0f\u59d0(Email)\u806f\u7d61\u3002\n\n", "employment_types": ["Full Time"], "selling_points": [], "locations": ["Not Specified"], "categories": ["Medical Services", "Others", "Public / Civil", "Social Services - Community / Non-profit Organization", "Others"], "post_time": "2022-01-12T03:24:34Z", "salary": {"currency": null, "max": null, "min": null, "period": "monthly", "term": null}, "salary_visible": false, "title_keywords": [], "responsibilities": [], "requirements": {"degrees": [], "majors": [], "languages": [], "language_level": [], "hard_skills": [], "soft_skills": [], "languages_combined": []}, "experience_required": {"duration": [], "field": []}}, {"job_id": "100003009040886", "location_code": "hk", "company": "Evangelical Lutheran Church Social Service - Hong Kong", "job_title": "\u793e\u6703\u5de5\u4f5c\u54e1Social Woker(\u8077\u4f4d\u7de8\u865f\uff1aSWI-ISCR)", "description": "\n\u65bc\u6c99\u7530\u5713\u878d\u7d9c\u5408\u670d\u52d9\u4e2d\u5fc3(\u9752\u5c11\u5e74\u81ea\u5f37\u8a08\u5283)\u5de5\u4f5c\n\u2022 \u9808\u5177\u672c\u6e2f\u793e\u5de5\u5b78\u4f4d\u6216\u4ee5\u4e0a\u7684\u8a3b\u518a\u793e\u5de5\uff0c\u5177\u826f\u597d\u9818\u5c0e\u53ca\u884c\u653f\u80fd\u529b\u3001\u8a8d\u8b58\u53f8\u6cd5\u7a0b\u5e8f\u3001\u6700\u5c11\u5169\u5e74\u8655\u7406\u9055\u898f\u9752\u5c11\u5e74\u53ca\u5bb6\u5ead\u8f14\u5c0e\u7d93\u9a57\u3001\u5c0d\u548c\u89e3\u670d\u52d9\u6709\u8a8d\u8b58\u53ef\u7372\u512a\u5148\u8003\u616e\n\u2022 \u4e3b\u8981\u8ca0\u8cac\u70ba\u88ab\u6355\u53ca\u63a5\u53d7\u8b66\u53f8\u8b66\u8aa1\u7684\u9752\u5c11\u5e74\u53ca\u5176\u5bb6\u5ead\u3001\u670b\u8f29\u3001\u9752\u5c11\u5e74\u53d7\u5bb3\u8005\u63d0\u4f9b\u500b\u6848\u8f14\u5c0e\u3001\u7b56\u5283\u53ca\u63a8\u884c\u5c0f\u7d44\u3001\u5927\u578b\u6d3b\u52d5\u3001\u64b0\u5beb\u57fa\u91d1\u7533\u8acb\uff0c\u4e26\u70ba\u6709\u9700\u8981\u4e4b\u500b\u6848\u63d0\u4f9b\u548c\u89e3\u670d\u52d9\n\u2022 \u6709\u8cac\u4efb\u611f\u3001\u826f\u597d\u6e9d\u901a\u80fd\u529b\u3001\u6210\u719f\u3001\u80fd\u7368\u7acb\u5de5\u4f5c\uff0c\u719f\u6089\u96fb\u8166\u64cd\u4f5c\u3001\u826f\u597d\u4e2d\u82f1\u6587\u80fd\u529b\n\n", "employment_types": ["Full Time"], "selling_points": [], "locations": ["Shatin Area"], "categories": ["Public / Civil", "Social Services - Community / Non-profit Organization", "Others"], "post_time": "2022-01-12T03:11:21Z", "salary": {"currency": null, "max": null, "min": null, "period": "monthly", "term": null}, "salary_visible": false, "title_keywords": [], "responsibilities": [], "requirements": {"degrees": [], "majors": [], "languages": [], "language_level": [], "hard_skills": [], "soft_skills": [], "languages_combined": []}, "experience_required": {"duration": [], "field": []}}, {"job_id": "100003009041290", "location_code": "hk", "company": "Big Grains Limited", "job_title": "\u521d\u7d1a\u9eb5\u5305\u5e2b(\u8343\u7063/\u7063\u4ed4/\u4f50\u6566)", "description": "\n\u8077\u8cac :\u5354\u52a9\u88fd\u4f5c\u50b3\u7d71\u6cd5\u5f0f\u53ca\u65e5\u5f0f\u9eb5\u5305, \u6e96\u5099\u6750\u6599, \u7dad\u6301\u5eda\u623f\u74b0\u5883\u885b\u751f\n\n\u8cc7\u6b77 :\u4e2d\u4e09\u7a0b\u5ea6; \u826f\u597d\u7cb5\u8a9e\u512a\u5148; \u4e00\u822c\u666e\u901a\u8a71; \u4e00\u822c\u82f1\u8a9e; \u7565\u61c2\u8b80\u5beb\u4e2d\u6587; \u7565\u61c2\u8b80\u5beb\u82f1\u6587\n\n\u5f85\u9047 :\u6bcf\u6708$14,000 - $15,000, \u6709\u8d85\u6642\u5de5\u4f5c\u6d25\u8cbc, \u52e4\u5de5\u734e\u91d1, \u5728\u8077\u57f9\u8a13\u53ca\u914c\u60c5\u6027\u82b1\u7d05, \u4e0a\u53487\u6642\u81f3\u4e0b\u53484\u6642\u534a, \u6bcf\u9031\u5de5\u4f5c5\u5929\u81f36\u5929,\u8f2a\u4f11, \u6bcf\u5929\u5de5\u4f5c 9.5 \u5c0f\u6642\n\n\u7533\u8acb\u9808\u77e5 :\u6c42\u8077\u8005\u53ef\u81f4\u96fb90103105\u8207\u54c1\u7a40\u6709\u9650\u516c\u53f8\u937e\u5c0f\u59d0\u806f\u7d61\u3002\n\n", "employment_types": ["Full Time"], "selling_points": [], "locations": ["Tsuen Wan Area"], "categories": ["Public / Civil", "Civil Services", "Social Services - Community / Non-profit Organization", "Others"], "post_time": "2022-01-12T03:42:24Z", "salary": {"currency": null, "max": null, "min": null, "period": "monthly", "term": null}, "salary_visible": false, "title_keywords": [], "responsibilities": [], "requirements": {"degrees": [], "majors": [], "languages": [], "language_level": [], "hard_skills": [], "soft_skills": [], "languages_combined": []}, "experience_required": {"duration": [], "field": []}}, {"job_id": "100003009040827", "location_code": "hk", "company": "Evangelical Lutheran Church Social Service - Hong Kong", "job_title": "\u793e\u6703\u5de5\u4f5c\u54e1Social Woker(\u8077\u4f4d\u7de8\u865f\uff1aSWII-ISCR)", "description": "\n\u65bc\u6c99\u7530\u5713\u878d\u7d9c\u5408\u670d\u52d9\u4e2d\u5fc3(\u9752\u5c11\u5e74\u81ea\u5f37\u8a08\u5283)\u5de5\u4f5c\n\u2022 \u9808\u5177\u793e\u6703\u5de5\u4f5c\u6587\u6191\u6216\u4ee5\u4e0a\u4e4b\u8a3b\u518a\u793e\u5de5\uff0c\u5177\u8655\u7406\u9055\u898f\u9752\u5c11\u5e74\u53ca\u5bb6\u5ead\u8f14\u5c0e\u7d93\u9a57\u3001\u8a8d\u8b58\u53f8\u6cd5\u7a0b\u5e8f\u3001\u5c0d\u548c\u89e3\u670d\u52d9\u6709\u8a8d\u8b58\u53ef\u7372\u512a\u5148\u8003\u616e\n\u2022 \u4e3b\u8981\u8ca0\u8cac\u70ba\u88ab\u6355\u53ca\u63a5\u53d7\u8b66\u53f8\u8b66\u8aa1\u7684\u9752\u5c11\u5e74\u53ca\u5176\u5bb6\u5ead\u3001\u670b\u8f29\u7b49\u63d0\u4f9b\u500b\u6848\u8f14\u5c0e\u670d\u52d9\u3001\u6d3b\u52d5\uff0c\u4e26\u70ba\u6709\u9700\u8981\u4e4b\u500b\u6848\u63d0\u4f9b\u548c\u89e3\u670d\u52d9\u3001\u5354\u52a9\u652f\u63f4\u9752\u5c11\u5e74\u53d7\u5bb3\u8005\u670d\u52d9\n\u2022 \u6709\u8cac\u4efb\u611f\u3001\u826f\u597d\u6e9d\u901a\u80fd\u529b\u3001\u6210\u719f\u3001\u80fd\u7368\u7acb\u5de5\u4f5c\uff0c\u719f\u6089\u96fb\u8166\u64cd\u4f5c\u3001\u826f\u597d\u4e2d\u82f1\u6587\u80fd\u529b\n\n", "employment_types": ["Full Time"], "selling_points": [], "locations": ["Shatin Area"], "categories": ["Public / Civil", "Social Services - Community / Non-profit Organization", "Others"], "post_time": "2022-01-12T03:07:44Z", "salary": {"currency": null, "max": null, "min": null, "period": "monthly", "term": null}, "salary_visible": false, "title_keywords": [], "responsibilities": [], "requirements": {"degrees": [], "majors": [], "languages": [], "language_level": [], "hard_skills": [], "soft_skills": [], "languages_combined": []}, "experience_required": {"duration": [], "field": []}}, {"job_id": "100003009040802", "location_code": "hk", "company": "Yang Memorial Methodist Social Service", "job_title": "\u8a00\u8a9e\u6cbb\u7642\u5e2b (\u65b0\u754c\u5340 \u53ca \u4e5d\u9f8d\u5340) (\u5230\u6821\u5b78\u524d\u5eb7\u5fa9\u670d\u52d9)", "description": "\nPost Date: 07 Jan 2022\n\nFunctions: Health Care / Medical\nTypes: Contract\nEducation: Certificate / Diploma\nSalary: -\nLocation: -\nWebsite: http://www.yang.org.hk\n\n\u8077\u4f4d\u7de8\u865f\uff1aOPRS/ST\n\n\u2022 \u6709\u5e7c\u5152\u5fa9\u5eb7\u7d93\u9a57\u8005\u512a\u5148\uff0c\u4ea6\u6b61\u8fce\u61c9\u5c46\u7562\u696d\u751f\u7533\u8acb\n\u2022 \u9700\u6301\u6709\u6709\u6548\u8a00\u8a9e\u6cbb\u7642\u57f7\u696d\u8b49\u66f8\n\u2022 \u8ca0\u8cac\u5230\u6821\u70ba\u6709\u7279\u6b8a\u5b78\u7fd2\u9700\u8981\u5e7c\u5152\u63d0\u4f9b\u8a00\u8a9e\u8a55\u4f30\u53ca\u6cbb\u7642\u3001\u63d0\u4f9b\u5bb6\u9577\u53ca\u6559\u5e2b\u652f\u63f4\u53ca\u5176\u4ed6\u76f8\u95dc\u5de5\u4f5c\n\u2022 \u6bcf\u9031\u5de5\u4f5c 44 \u5c0f\u6642\uff0c\u9700\u9694\u9031\u516d\u5de5\u4f5c\n\n\u4e0a\u8ff0\u8077\u4f4d\u4ee5\u5408\u7d04\u5236\u8058\u8acb\u3002\nEnquiries\n\u6709\u610f\u8005\u8acb\u9644\u5c65\u6b77\u4e26\u8a3b\u660e\u8981\u6c42\u5f85\u9047\u96fb\u90f5\u81f3 Apply Now \u6216\u90f5\u5bc4\u5230\u4e5d\u9f8d\u7aa9\u6253\u8001\u9053 54 \u865f\u884c\u653f\u90e8\u6536 (\u4fe1\u5c01\u9762\u5fc5\u9808\u8a3b\u660e\u7533\u8acb\u8077\u4f4d\u540d\u7a31 / \u7de8\u865f\uff0c\u5408\u5247\u7d04\u898b)\u3002\n\n\u7db2\u5740 : http://www.yang.org.hk\n\n\u7533\u8acb\u4eba\u63d0\u4f9b\u4e4b\u5168\u90e8\u8cc7\u6599\u7d55\u5c0d\u4fdd\u5bc6\u53ca\u50c5\u4f9b\u62db\u8058\u4e4b\u7528\u3002\u53ea\u6709\u5165\u570d\u7684\u7533\u8acb\u8005\u5c07\u88ab\u9080\u8acb\u53c3\u52a0\u9762\u8a66\u3002\u7533\u8acb\u4eba\u5982\u5728\u5169\u500b\u6708\u5167\u672a\u7372\u672c\u6a5f\u69cb\u56de\u8986\uff0c\u8acb\u8996\u4f5c\u8a72\u9805\u7533\u8acb\u4e0d\u88ab\u63a5\u7d0d\uff0c\u672c\u6a5f\u69cb\u53ea\u4fdd\u7559\u7533\u8acb\u4eba\u4e4b\u5168\u90e8\u8cc7\u6599\u6700\u591a\u516d\u500b\u6708\u3002\n\n", "employment_types": ["Full Time"], "selling_points": [], "locations": ["Not Specified"], "categories": ["Medical Services", "Therapist", "Others", "Public / Civil", "Others"], "post_time": "2022-01-12T03:05:57Z", "salary": {"currency": null, "max": null, "min": null, "period": "monthly", "term": null}, "salary_visible": false, "title_keywords": [], "responsibilities": ["website"], "requirements": {"degrees": ["certificate", "diploma"], "majors": [], "languages": [], "language_level": [], "hard_skills": [], "soft_skills": [], "languages_combined": []}, "experience_required": {"duration": [], "field": []}}, {"job_id": "100003009040862", "location_code": "hk", "company": "Evangelical Lutheran Church Social Service - Hong Kong", "job_title": "\u793e\u6703\u5de5\u4f5c\u54e1Social Woker(\u8077\u4f4d\u7de8\u865f\uff1aSWII-RH)", "description": "\n\u2022 \u65bc\u99ac\u978d\u5c71\u6069\u8000\u574a\u5de5\u4f5c\n\u2022 \u9808\u5177\u793e\u6703\u5de5\u4f5c\u6587\u6191\u6216\u4ee5\u4e0a\u4e4b\u8a3b\u518a\u793e\u5de5\uff0c\u5177\u9577\u8005\u500b\u6848\u5de5\u4f5c\u7d93\u9a57\u53ef\u7372\u512a\u5148\u8003\u616e\n\u2022 \u4e3b\u8981\u8ca0\u8cac\u9577\u8005\u5916\u5c55\u5de5\u4f5c\uff0c\u767c\u6398\u6c99\u7530\u53ca\u99ac\u978d\u5c71\u96b1\u853d\u9577\u8005\uff0c\u4ee5\u500b\u6848\u7ba1\u7406\u624b\u6cd5\u63d0\u4f9b\u5354\u52a9\uff0c\u4e26\u4e14\u958b\u62d3\u7fa9\u5de5\u5718\u9ad4\u53ca\u793e\u5340\u5354\u4f5c\uff1b\u4fc3\u9032\u7fa9\u5de5\u8207\u9577\u8005\u9593\u4e4b\u806f\u7e6b\uff0c\u7d71\u7c4c\u6703\u54e1\u670d\u52d9\u53ca\u6d3b\u52d5\u3001\u5354\u52a9\u8209\u884c\u5927\u578b\u8a08\u5283\uff0c\u4e26\u652f\u63f4\u4e2d\u5fc3\u5176\u4ed6\u5de5\u4f5c\n\u2022 \u6027\u683c\u9748\u6d3b\u3001\u4e3b\u52d5\u3001\u6709\u670d\u52d9\u9577\u8005\u5fc3\u5fd7\u53ca\u559c\u6b61\u5c0d\u5916\u806f\u7e6b\u5de5\u4f5c\uff1b\u719f\u6089\u96fb\u8166\u64cd\u4f5c\u53ca\u4e2d\u3001\u82f1\u6587\u8f38\u5165\n\u2022 \u5408\u7d04\u671f\u5169\u5e74\n\n", "employment_types": ["Full Time"], "selling_points": [], "locations": ["Shatin Area"], "categories": ["Public / Civil", "Social Services - Community / Non-profit Organization", "Others"], "post_time": "2022-01-12T03:09:52Z", "salary": {"currency": null, "max": null, "min": null, "period": "monthly", "term": null}, "salary_visible": false, "title_keywords": [], "responsibilities": [], "requirements": {"degrees": [], "majors": [], "languages": [], "language_level": [], "hard_skills": [], "soft_skills": [], "languages_combined": []}, "experience_required": {"duration": [], "field": []}}, {"job_id": "100003009040837", "location_code": "hk", "company": "Evangelical Lutheran Church Social Service - Hong Kong", "job_title": "\u793e\u6703\u5de5\u4f5c\u54e1Social Woker(\u8077\u4f4d\u7de8\u865f\uff1aSWII-KCDSC)", "description": "\n\u2022 \u65bc\u8475\u6d8c\u5730\u5340\u652f\u63f4\u4e2d\u5fc3\u5de5\u4f5c\n\u2022 \u9808\u5177\u793e\u6703\u5de5\u4f5c\u6587\u6191\u6216\u4ee5\u4e0a\u4e4b\u8a3b\u518a\u793e\u5de5\n\u2022 \u4e3b\u8981\u8ca0\u8cac\u7d71\u7c4c\u53ca\u63a8\u884c\u6b98\u75be\u53ca\u667a\u969c\u4eba\u58eb\u65e5\u9593\u8a13\u7df4\u670d\u52d9\u3001\u63d0\u4f9b\u500b\u6848\u7ba1\u7406\u670d\u52d9\u53ca\u8f14\u5c0e\u670d\u52d9\u3001\u63a8\u884c\u5730\u5340\u5354\u4f5c\u53ca\u57fa\u91d1\u9805\u76ee\u3001\u7763\u5c0e\u524d\u7dda\u54e1\u5de5\n\u2022 \u5177\u8cac\u4efb\u611f\u3001\u4e3b\u52d5\u3001\u8b39\u614e\u3001\u826f\u597d\u6e9d\u901a\u53ca\u7d44\u7e54\u80fd\u529b\n\u2022 \u6bcf\u9031\u5de5\u4f5c44\u5c0f\u6642\uff0c\u9031\u672b\u53ca\u516c\u773e\u5047\u671f\u9700\u8f2a\u73ed\u5de5\u4f5c\n\n", "employment_types": ["Full Time"], "selling_points": [], "locations": ["Kwai Tsing Area"], "categories": ["Public / Civil", "Social Services - Community / Non-profit Organization", "Others"], "post_time": "2022-01-12T03:08:28Z", "salary": {"currency": null, "max": null, "min": null, "period": "monthly", "term": null}, "salary_visible": false, "title_keywords": [], "responsibilities": [], "requirements": {"degrees": [], "majors": [], "languages": [], "language_level": [], "hard_skills": [], "soft_skills": [], "languages_combined": []}, "experience_required": {"duration": [], "field": []}}, {"job_id": "100003009039231", "location_code": "hk", "company": "Mandatory Provident Fund Schemes Authority", "job_title": "Inspectors in the Member Claims and Investigation Department", "description": "The Job\n\nTo investigate into complaints and other cases in relation to non-compliance of the Mandatory Provident Fund Schemes Ordinance with respect to member protection;\nTo conduct inspections to detect MPF non-compliance by employers / self-employed persons;\nTo collect evidence to substantiate the cases; initiate prosecution and civil action where appropriate, and serve as prosecution witness;\nTo prepare reports on findings and analyze case results for management\u2019s review;\nTo answer enquiries on MPF issues from employers / employees / self-employed persons;\nTo supervise staff to conduct investigation work and handle civil claims proceedings; and\nTo perform other duties as assigned.\n\nThe Person\n\nA recognized degree, or equivalent;\nAt least four years of relevant experience in pension, law enforcement, customer service, labour relations, public administration or accounting / auditing, preferably gained from the public sector or large organizations;\nProficient in PC applications including Excel, Word and Chinese word processing;\nGood command of written and spoken English and Chinese;\nProficient in Putonghua will be an advantage;\nGood interpersonal, communication, analytical, problem solving, organization and supervisory skills;\nMature, flexible and a good team player; and\nAble to work independently and under pressure.\n\nRemuneration Package\n\nA competitive remuneration and benefits package including a discretionary performance-linked variable pay, annual leave, medical, dental and life insurance coverage, and MPF will be offered. All new appointments will be made on a two-year fixed-term contract initially prior to consideration for appointment on a non-fixed-term basis.\n\nTo Apply\n\nInterested candidates are invited to apply by sending full career details and application letter, quoting the job reference number, with information of current / expected remuneration, availability, to the address below or by clicking the \"Apply Now\":\n\nHuman Resources Department, MPFA\n\nLevel 8, Tower 1, Kowloon Commerce Centre\n\n51 Kwai Cheong Road, Kwai Chung, Hong Kong\n\nThe closing date for application is 25 January 2022\u00a0or postmarked on\u00a025 January 2022. Applicants not invited for interview by the end of March 2022 may assume that their applications are unsuccessful and their applications will not be retained for more than two years.\n\nThe information provided will be kept confidential and only be used for those purposes relating to your application.\u00a0 Please visit our website for the details of the MPFA\u2019s Personal Information Collection Statement for Job Applicants at https://www.mpfa.org.hk/en/mpfa/joining-mpfa/job-vacancies/personal-information-collection-statement.\u00a0 The MPFA is an equal opportunities employer and welcomes applications from all qualified candidates.", "employment_types": ["Full Time", "Contract"], "selling_points": [], "locations": ["Ngau Tau Kok"], "categories": ["Banking / Finance", "Investment", "Professional Services", "Legal & Compliance", "Public / Civil", "Others"], "post_time": "2022-01-11T09:05:55Z", "salary": {"currency": null, "max": null, "min": null, "period": "monthly", "term": null}, "salary_visible": false, "title_keywords": [], "responsibilities": ["management", "perform other duties", "mpf", "review", "compliance", "investigation", "prepare reports"], "requirements": {"degrees": ["degree"], "majors": [], "languages": ["putonghua", "english", "chinese"], "language_level": ["advantage", "good command", "proficient"], "hard_skills": ["excel", "chinese word processing", "word", "pc applications", "problem solving"], "soft_skills": ["flexible", "good team player", "work independently", "under pressure", "mature", "communication", "problem solving", "customer service", "interpersonal"], "languages_combined": [{"language": "putonghua", "language_level": ["proficient", "advantage"]}, {"language": "english", "language_level": ["good command"]}, {"language": "chinese", "language_level": ["good command"]}]}, "experience_required": {"duration": ["at least four years"], "field": ["customer service", "relevant experience", "accounting", "administration"]}}, {"job_id": "100003009040916", "location_code": "hk", "company": "Po Leung Kuk", "job_title": "\u793e\u6703\u5de5\u4f5c\u54e1SW4-SGH (\u7b72\u7b95\u7063\u53ca\u9ec3\u5927\u4ed9\uff1b\u725b\u6c60\u7063\u53ca\u5c07\u8ecd\u6fb3\u3001\u6c99\u7530)", "description": "\n\u7d9c\u5408\u5bb6\u5ead\u670d\u52d9\n\u5165\u8077\u8981\u6c42\n\u2022 \u8a3b\u518a\u793e\u5de5\uff0c\u6301\u8a8d\u53ef\u793e\u6703\u5de5\u4f5c\u5b78\u58eb\u5b78\u4f4d\uff0c\u51773\u5e74\u6216\u4ee5\u4e0a\u5152\u7ae5\u4f4f\u5bbf\u6216\u5bb6\u5ead\u53ca\u5152\u7ae5\u670d\u52d9\u7d93\u9a57\u3002\n\u4e3b\u8981\u8077\u8cac\n\u2022 \u8ca0\u8cac\u7ba1\u74063\u6240\u5152\u7ae5\u4e4b\u5bb6\uff0c\u5305\u62ec\u500b\u6848\u8f14\u5c0e\u53ca\u7ba1\u7406\u3001\u8077\u54e1\u7763\u5c0e\u3001\u5bb6\u820d\u8ca1\u52d9\u53ca\u884c\u653f\u5de5\u4f5c\uff0c\u5c0f\u7d44\u53ca\u6d3b\u52d5\u5b89\u6392\u3002\n\u7b72\u7b95\u7063\u53ca\u9ec3\u5927\u4ed9\uff1b\u725b\u6c60\u7063\u53ca\u5c07\u8ecd\u6fb3\u3001\u6c99\u7530 [via\u00a0 Apply Now ] 2277 8190\n\u622a\u6b62\u7533\u8acb\u65e5\u671f : 2022/1/28\n\n", "employment_types": ["Full Time"], "selling_points": [], "locations": ["Shau Kei Wan"], "categories": ["Public / Civil", "Social Services - Community / Non-profit Organization", "Others"], "post_time": "2022-01-12T03:13:31Z", "salary": {"currency": null, "max": null, "min": null, "period": "monthly", "term": null}, "salary_visible": false, "title_keywords": [], "responsibilities": [], "requirements": {"degrees": [], "majors": [], "languages": [], "language_level": [], "hard_skills": [], "soft_skills": [], "languages_combined": []}, "experience_required": {"duration": [], "field": []}}, {"job_id": "100003009040896", "location_code": "hk", "company": "Aberdeen Kai-Fong Welfare Association Social Service Centre", "job_title": "\u793e\u6703\u5de5\u4f5c\u54e1 (Social Worker)\u3010\u8077\u4f4d\u7de8\u865f\uff1a CC-RSW-1/2022-CT \u3011", "description": "\n\u8077\u8cac\uff1a\n\u2022 \u8ca0\u8cac\u7b56\u5283\u53ca\u63a8\u884c\u9752\u5c11\u5e74/\u57fa\u5c64\u4eba\u58eb\u670d\u52d9\n\u2022 \u7c4c\u7d44\u53ca\u5e36\u9818\u9577\u671f\u7fa9\u5de5/\u6280\u80fd\u5c0f\u7d44\n\u5b78\u6b77\u8981\u6c42\u53ca\u5f85\u9047\uff1a\n\u793e\u5de5\u6587\u6191\u53ca\u8a3b\u518a\u793e\u5de5\uff0c\u6708\u85aa$22,510\u8d77\n\u2022 \u6b61\u8fce\u61c9\u5c46\u7562\u696d\u751f\u7533\u8acb\n\u2022 \u9808\u6bcf\u9031\u7576\u503c\u5169\u665a\uff0c\u81f3\u665a\u4e0a\u5341\u6642\u00a0\n\u54e1\u5de5\u798f\u5229\ufe30\n\u2022 \u6bcf\u9031\u5de5\u4f5c\u4e94\u5929\n\u2022 \u9280\u884c\u5047\n\u2022 \u6709\u85aa\u5e74\u5047\n\u2022 \u9580\u8a3a\u53ca\u4f4f\u9662\u4fdd\u96aa\n\u2022 \u751f\u65e5\u5047\u3001\u5a5a\u5047\u3001\u6baf\u846c\u6069\u6064\u5047\n\n", "employment_types": ["Full Time"], "selling_points": [], "locations": ["Aberdeen"], "categories": ["Public / Civil", "Social Services - Community / Non-profit Organization", "Others"], "post_time": "2022-01-12T03:12:03Z", "salary": {"currency": null, "max": null, "min": null, "period": "monthly", "term": null}, "salary_visible": false, "title_keywords": [], "responsibilities": [], "requirements": {"degrees": [], "majors": [], "languages": [], "language_level": [], "hard_skills": [], "soft_skills": [], "languages_combined": []}, "experience_required": {"duration": [], "field": []}}]