[{"job_id": "100003009052345", "location_code": "hk", "company": "Be Priceless Limited", "job_title": "Office Administration Officer", "description": "Job Highlights\n\nOffice administrator\n\nEmpower disadvantaged children, well-being, safety\n\nNon-profit organization\n\nJob Description\n\nRole:\u00a0Office administrative officer for Be Priceless,\u00a0an educational non-profit organization that strengthens disadvantaged children\u2019s well-being and safety.\n\nSeeking candidate with a passion to empower and serve disadvantaged communities and has prior experience in office administration and secretarial roles. High level of competence, integrity and accountability is required.\n\n\u00a0\n\nJob Highlight:\n\nOpportunity to work with and learn from professional across multiple sectors, including education, psychology and operations.\n\nDrive the coordination and collaboration with diverse professionals, community members, child and youth in empowering ways\n\nBe part of an innovative and dynamic team of multisectoral professionals and community members.\n\nEmpowering, positive, collaborative organizational culture\n\nKey Jobs Responsibilities\n\nPerform general office administrative tasks\n\nSupport technical team with ad hoc and scheduled events, including booking of venues, coordination at events and post event report/data collection.\u00a0\n\nSupport communication with parents and care takers for the SEED course and other courses we run.\u00a0\n\nCoordinate communication between team members and schedule meetings and documentation of meeting notes.\u00a0\n\nPerform general HR functions, including tracking and recording sick leave, annual leave tallies for employees.\u00a0\n\nOther secretarial and office administrative roles, including ad hoc errands, printing, online purchase of material/equipment and other outsourcing activities that the business will require.\u00a0\n\nJob Requirement:\n\nAt least 2 years of relevant experience in office administration role for small to medium size organization.\u00a0\n\nCollege degree.\u00a0\n\nAdaptive, flexible and collaborative\n\nStrong collaboration, coordination and problem solving skills.\n\nStrong communication, productivity, organization and time management skills.\n\nSocial media management proficiency\n\nProfessional level\u00a0written and spoken English\u00a0\n\nProfessional level written and spoken Chinese\n\nUndergoing regular background checks (including\u00a0Sexual\u00a0Conviction Record\u00a0Check\u00a0(SCRC)\u00a0 and previous employment checks) and abiding to code of conduct including for child safeguarding-protection are an absolute requirements. We have continuous and rigorous monitoring of issues of concerns safety of children and other vulnerable individuals. We will investigate/ report where appropriate.\n\nLogistics:\u00a0Full-time, candidate must be in Hong Kong\nDuration: 3 month probation, to be extended to long-term contract if performance is satisfactory.\nSalary:\u00a0based on experience\u00a0\n\nPlease apply with\u00a0your full resume, cover letter, time availability. and expected salary.", "employment_types": ["Full Time"], "selling_points": ["Great work place", "Learn along side professionals", "Competitive salary"], "locations": ["Central"], "categories": ["Admin & HR", "Clerical / Admin Staff", "Public / Civil", "Social Services - Community / Non-profit Organization", "Management", "Management Trainee"], "post_time": "2022-01-17T02:48:44Z", "salary": {"currency": null, "max": null, "min": null, "period": "monthly", "term": null}, "salary_visible": false, "title_keywords": ["administration officer"], "responsibilities": ["tracking", "documentation", "ad hoc", "office administration", "operations", "hr", "communication", "coordinate", "purchase", "booking", "coordination", "data collection", "administrative tasks", "schedule", "report"], "requirements": {"degrees": ["degree"], "majors": [], "languages": ["english", "chinese"], "language_level": [], "hard_skills": ["small", "code", "problem solving skills"], "soft_skills": ["flexible", "time management skills", "collaborative", "communication", "coordination", "problem solving skills"], "languages_combined": [{"language": "english", "language_level": []}, {"language": "chinese", "language_level": []}]}, "experience_required": {"duration": ["at least 2 years"], "field": ["office administration", "relevant experience"]}}, {"job_id": "100003009052032", "location_code": "hk", "company": "Hong Kong Tourism Board", "job_title": "Aspire Management Trainee Programme (July 2022 Intake)", "description": "Do you aspire to help Hong Kong keep and grow its status as an iconic destination? Join our unconventional management trainee programme and help shape the future of our city.\n\nAt the Hong Kong Tourism Board, we take great pride in helping people across the world fall in love with our home. There are many challenges, but we continue in earnest to revitalise and reshape the Hong Kong tourism brand and build sustainable growth for our city\u2019s economy. To achieve our ambition, we are inviting young and passionate talents with a global mindset to join us at this incredible juncture, and work alongside the management team as we lead the way forward.\n\nYou will face a demanding but rewarding career path where you\u2019ll grow both professionally and personally. You will join forces with industry professionals on tasks and projects ranging from strategic planning and data analysis, to marketing and PR, mega-event staging, and the design of digital experiences that will transform the way our city welcomes visitors. To help you advance to become an all-round leader, you will also have an opportunity to take up placements in the supporting functions as well as at our worldwide offices. It\u2019s certainly not an average 9 to 5 role.\n\nWHAT WE OFFER\n\nA 3-year accelerated development path, which allows you to build management capabilities and skills through assignments and postings across different functions.\n2 placements outside of Hong Kong, with at least one in Mainland China.\nAn aspiring programme that equips you with the knowledge and skills necessary for building a long-term, multifaceted career within the organisation.\nAccess to tailored career support through mentoring and blended learning activities.\n\nYOU MUST HAVE\n\nA degree from any discipline with good academic results, noteworthy achievements outside education, and no more than 3 years of working experience.\nA passion for Hong Kong, with aspiration to be an ambassador to promote Hong Kong, and ambition to drive the growth of the Hong Kong tourism industry.\nSound judgement, rationality, and the ability to collaborate in a professional work environment.\nStrong business acumen, with creative and strategic thinking, and analytical skills.\nGlobal mobility with a connection to the broader world, a sense of cultural sensitivities, and the ability to quickly adapt to new roles and projects.\nExcellent command of written and spoken English and Chinese. Proficiency in other languages a plus.\n\nApplication Method\n\nSend a copy of your CV, academic transcripts, and a video no longer than 3 minutes explaining your motivation to work with us and why you\u2019re best suited for the opportunity by clicking \u201cApply Now\u201d. Please include the video link in your CV.\n\nSuccessful applicants will begin their journey with us in July 2022.\n\nApplication Deadline: 31 January 2022\n\nPersonal data provided by job applicants will be used strictly in accordance with our personal data policies, a copy of which will be provided upon request.\u00a0 Applicants may send a request for a copy of the Personal Information Collection Statement pertaining to Job Application.\u00a0 Only shortlisted applicants will be contacted.\u00a0 All Information received will be kept in strict confidence and used only for employment-related purpose.\n\nWe are an equal opportunities employer.", "employment_types": ["Full Time", "Permanent"], "selling_points": ["A 3-year asipiring career development programme", "Opportunity to contribute to HK tourism industry", "Degree holder from any discipline"], "locations": ["Tin Hau"], "categories": ["Public / Civil", "Social Services - Community / Non-profit Organization", "Hospitality / F & B", "Tourism / Travel Agency", "Management", "Management Trainee"], "post_time": "2022-01-17T01:53:11Z", "salary": {"currency": null, "max": null, "min": null, "period": "monthly", "term": null}, "salary_visible": false, "title_keywords": ["management trainee"], "responsibilities": ["management team", "management", "strategic planning", "design", "data analysis"], "requirements": {"degrees": [], "majors": [], "languages": [], "language_level": [], "hard_skills": ["analysis"], "soft_skills": ["passionate", "earnest"], "languages_combined": []}, "experience_required": {"duration": [], "field": ["pr", "design", "data analysis", "marketing", "digital", "planning"]}}, {"job_id": "100003009052344", "location_code": "hk", "company": "Be Priceless Limited", "job_title": "Business Development and Operations Manager for Non-profit Educational Organization", "description": "Be Priceless\u00a0is a non-profit educational organization that aims to empower disadvantaged children and their communities to strengthen well-being and safety. We believe in a more equitable world where no child is left behind.\n\nWe are seeking a passionate candidate to be the Operations Manager who has extensive experienced in business and partnership development, and program management for non-profit organization or education entrepreneurship sector in Hong Kong.\u00a0 \u00a0 \u00a0 \u00a0 \u00a0 \u00a0 \u00a0 \u00a0\n\nBe Priceless is growing well and the Operations Manager will have a key role in driving the development of the programs, resources, as well as partnerships with trusted NGOs, schools, community groups and members.\n\nWe develop in depth evidence and best practice-based educational programs to build capacity, mindsets and practices of children, caregivers and care service providers to promote personal development, well-being (physical, mental and social health) and risk reduction (against violence, exploitation, health risks, disasters, etc).\u00a0\u00a0\n\nWe work by shared leadership and community-wide collaboration to create and deliver an impactful educational program. Our team comes from diverse technical and community backgrounds. For more information, please visit\u00a0www.bepriceless.org\n\nJob Highlight - Opportunities:\n\n\u00b7\u00a0\u00a0\u00a0\u00a0\u00a0Assist the founder with internal processes and monitor the growth of a transformative educational program that empowers and engages an all-of-city approach to strengthening children, youth and families' well-being and safety.\n\n\u00b7\u00a0\u00a0\u00a0\u00a0\u00a0Coordinate and collaborate with dynamic team of multicultural experts from diverse fields, community members, child and youth in empowering ways.\n\n\u00b7\u00a0\u00a0\u00a0\u00a0\u00a0\u00a0Positive, collaborative, nurturing organizational culture\n\nKey Jobs Responsibilities:\n\n\n\n-\u00a0 \u00a0 \u00a0 Direct report to founder\u00a0\n\n\n\u00b7\u00a0\u00a0\u00a0\u00a0\u00a0\u00a0Develop and implement business plans to generate resources and enhance outcomes and impacts.\n\n\u00b7\u00a0\u00a0\u00a0\u00a0\u00a0\u00a0Facilitate pursuit of opportunities for development and funding for Be Priceless by contributing to grant proposal development.\n\n\u00b7\u00a0\u00a0\u00a0\u00a0\u00a0\u00a0Drive and strengthen organization culture, mechanisms and actions for producing impact, collaboration, coordination, communication, accountability, quality control, team and program operations management.\n\n\u00b7\u00a0\u00a0\u00a0\u00a0\u00a0\u00a0Drive and manage all team operations and coordination.\n\n\u00b7\u00a0\u00a0\u00a0\u00a0\u00a0\u00a0Coordinate the planning, development, implementation, assessments and reporting of all educational and other organizational projects\n\n\u00b7\u00a0\u00a0\u00a0\u00a0\u00a0\u00a0Drive the child safeguarding and protection policy, protocol, monitoring and reporting mechanisms.\n\n\u00b7\u00a0\u00a0\u00a0\u00a0\u00a0\u00a0Work with and support the team, including optimizing operational aspects of the program.\n\n\u00b7\u00a0\u00a0\u00a0\u00a0\u00a0\u00a0Lead the initiatives to promote learning, well-being and safety of the team and the stakeholders we serve\n\n\u00b7\u00a0\u00a0\u00a0\u00a0\u00a0\u00a0Drive and strengthen community engagement\n\n\u00b7\u00a0\u00a0\u00a0\u00a0\u00a0\u00a0Develop strong program management to promote nurturing organization culture, effective impact achievement, multisectoral collaboration, accountability, including tools to strengthen the organization structure, process, work and future development;\n\n\u00b7\u00a0\u00a0\u00a0\u00a0\u00a0\u00a0Create and upkeep processes and team management that facilitate internal and external communication and collaborations from online tools, in-person participation, ongoing updates, to team and partners engagement;\u00a0\n\n\u00b7\u00a0\u00a0\u00a0\u00a0\u00a0\u00a0Facilitate and participate educational program planning, development, production, dissemination, evaluation and review.\n\nJob Requirement:\n\no\u00a0\u00a0Strong track record in business development and operation management role in non-profit sector, social entrepreneurship, or educational sector.\u00a0\n\no\u00a0 High level of competence, independence, integrity and accountability required.\n\no\u00a0\u00a0At least 3-5 years of experience in organization operations management.\u00a0\n\no\u00a0\u00a0Strong experience in working with other non-profit, social entrepreneur, or education sectors.\u00a0\n\n\u00b7\u00a0\u00a0\u00a0Passionate and dedicated in promoting child and youth learning, well-being and protection\n\n\u00b7\u00a0\u00a0\u00a0Adaptive, flexible, productive, efficient and collaborative\n\n\u00b7\u00a0\u00a0\u00a0Strong ethical and professional standard - including accountability, transparency.\n\n\u00b7\u00a0\u00a0\u00a0Strong\u00a0communication, leadership,\u00a0collaboration, coordination and problem solving skills.\n\n\u00b7\u00a0\u00a0\u00a0Strong productivity, organization and time management skills.\n\n\u00b7\u00a0\u00a0\u00a0Social media management proficiency\n\n\u00b7\u00a0\u00a0\u00a0Professional level written and spoken English is required\u00a0\n\n\u00b7\u00a0 Professional level written and spoken one or more of the following is required: Chinese, Nepali, Urdu, Hindi, Tagalog, or Bahasa.\n\n\u00b7\u00a0\u00a0\u00a0Regular background checks (including\u00a0Sexual\u00a0Conviction Record\u00a0Check\u00a0(SCRC)\u00a0and previous employment checks) and abiding to code of conduct including for child safeguarding-protection are an absolute requirements. We have continuous and rigorous monitoring of issues of concerns safety of children and other vulnerable individuals. We will investigate/ report where appropriate.\u00a0\u00a0\n\nPreferred experience/ skills:\u00a0\n\nDegree in education, psychology, social work or related field\nData management and analysis\nExperience in developing e-learning or other educational programs\u00a0\n\nLogistics:\u00a0Full-time, candidate must be in Hong Kong\n\nDuration: Long-term contract with 3 month probation.\n\nSalary: \u00a0Based on experience\n\nExpected\u00a0Start Date: immediately\n\nIf you are interested, please apply with\u00a0your full resume with cover letter as the front page, time availability and expected salary.", "employment_types": ["Full Time"], "selling_points": ["Development, Partnerships, Management, Leadership", "competitive salary, empowering, multi-sectoral", "Non-profit, social entrepreneur, education"], "locations": ["Central"], "categories": ["Education", "Others", "Public / Civil", "Social Services - Community / Non-profit Organization", "Management", "Top Executives (CEO, CFO, CTO, GM, MD etc.)"], "post_time": "2022-01-17T02:48:44Z", "salary": {"currency": "HKD", "max": 54999, "min": 45000, "period": "monthly", "term": null}, "salary_visible": true, "title_keywords": ["business development and operations manager"], "responsibilities": ["reporting", "management", "evaluation", "operations", "monitoring", "review", "implementation", "business plans", "develop", "communication", "coordinate", "planning", "coordination", "quality control", "support the team", "report"], "requirements": {"degrees": ["degree"], "majors": ["social work", "psychology"], "languages": ["english", "urdu", "hindi", "tagalog", "nepali", "chinese"], "language_level": [], "hard_skills": ["code", "problem solving skills", "analysis", "data management"], "soft_skills": ["passionate", "flexible", "productive", "efficient", "accountability", "time management skills", "integrity", "collaborative", "communication", "learning", "ethical", "coordination", "problem solving skills", "leadership"], "languages_combined": [{"language": "english", "language_level": []}, {"language": "urdu", "language_level": []}, {"language": "hindi", "language_level": []}, {"language": "tagalog", "language_level": []}, {"language": "nepali", "language_level": []}, {"language": "chinese", "language_level": []}]}, "experience_required": {"duration": ["at least 3-5 years"], "field": ["operations management", "developing", "education"]}}, {"job_id": "100003009054527", "location_code": "hk", "company": "Hong Kong Federation of Education Workers Limited", "job_title": "\u9805\u76ee\u7d71\u7c4c\u4e3b\u4efb(\u5c08\u696d\u767c\u5c55\u90e8)", "description": "\u8077\u8cac\uff1a\n1. \u7d71\u7c4c\u6d3b\u52d5\u3001\u8b1b\u5ea7\u53ca\u5de5\u4f5c\u574a\uff0c\u8ddf\u9032\u76f8\u95dc\u884c\u653f\u53ca\u5ba3\u50b3\u5de5\u4f5c\uff1b\n2. \u5354\u52a9\u8655\u7406\u90e8\u9580\u7684\u884c\u653f\u53ca\u806f\u7d61\u5de5\u4f5c\uff1b\n3. \u652f\u63f4\u5176\u4ed6\u6703\u52d9\u5de5\u4f5c\n\n\u8981\u6c42\uff1a\n1. \u5927\u5c08\u6216\u4ee5\u4e0a\u7a0b\u5ea6\uff1b\n2. \u5177\u5099\u4e94\u5e74\u7d71\u7c4c\u6d3b\u52d5\u6216\u8ab2\u7a0b\u7d93\u9a57\uff0c\u80fd\u7368\u7acb\u8655\u7406\u5de5\u4f5c\uff1b\n3. \u826f\u597d\u4e2d\u82f1\u6587\u5beb\u4f5c\u80fd\u529b\uff1b\u719f\u6089\u96fb\u8166\u64cd\u4f5c\uff1b\n4. \u7d30\u5fc3\u3001\u52e4\u596e\uff0c\u6709\u8cac\u4efb\u611f\u3002\u80fd\u7368\u7acb\u5de5\u4f5c\uff0c\u4e26\u5177\u5718\u968a\u5408\u4f5c\u7cbe\u795e\n\n\u61c9\u5fb5\u8005\u8acb\u89aa\u7e55\u5c65\u6b77\uff0c\u96fb\u90f5\u81f3\u672c\u6703 \uff0c\u6216\u5bc4\u4e5d\u9f8d\u65fa\u89d2\u905333\u865f\u51f1\u9014\u767c\u5c55\u5927\u5ec817\u6a13\u300c\u9999\u6e2f\u6559\u80b2\u5de5\u4f5c\u8005\u806f\u6703\u300d\u79d8\u66f8\u8655\u6536\uff0c\u8acb\u8a3b\u660e\u300c\u5c08\u696d\u767c\u5c55\u90e8\u9805\u76ee\u7d71\u7c4c\u4e3b\u4efb\u300d\u3002", "employment_types": ["Full Time"], "selling_points": [], "locations": ["Mong Kok"], "categories": ["Education", "Others", "Public / Civil", "Social Services - Community / Non-profit Organization"], "post_time": "2022-01-17T09:53:31Z", "salary": {"currency": null, "max": null, "min": null, "period": "monthly", "term": null}, "salary_visible": false, "title_keywords": [], "responsibilities": [], "requirements": {"degrees": [], "majors": [], "languages": [], "language_level": [], "hard_skills": [], "soft_skills": [], "languages_combined": []}, "experience_required": {"duration": [], "field": []}}, {"job_id": "100003009053190", "location_code": "hk", "company": "Hong Kong Institute of Education for Sustainable Development", "job_title": "Assistant Programme Officer/ Programme Officer", "description": "THE JOB\n\nThe Assistant Programme Officer/ Programme Officer will assist in the coordination of different programs / events. His/ Her responsibilities includes the follows:\n\nDevelop training courses within and outside Hong Kong\nConduct research in investigating training needs\nLiaise with different parties in developing and organizing training courses\nAssist in developing training and assessment materials\nPerforming\u00a0other duties as assigned.\n\nTHE REQUIREMENTS\u00a0\n\nApplicants should have a Degree in Marketing/Business/Communication or related\u00a0disciplines with at least 2 years\u2019 relevant post-qualification working experience;\nGood command of written and spoken English and Chinese (including Putonghua)\nStrong communication skills, self-motivated, organized, detail-oriented\nExperience in training/education is an advantage\nCandidate with less experience will be considered as Assistant Programme Officer\nImmediate available is preferred\n\n[Applicants who have responded to the previous advertisements need not re-apply. Their applications are being considered accordingly.]\n\nAPPLICATIONS\n\nPlease click\u00a0\u201cApply Now\u201d\u00a0or you could\u00a0submit your CV\u00a0with indication of position, current and expected salary\u00a0and date of availability\u00a0(application without expected salary will not be considered). Applicants who are not invited for interview within six months may consider their applications unsuccessful. All applications will be treated in the strictest confidence. Data collected will be used for recruitment and other employment-related purposes only.", "employment_types": ["Full Time", "Permanent"], "selling_points": [], "locations": ["Tsim Sha Tsui"], "categories": ["Public / Civil", "Social Services - Community / Non-profit Organization"], "post_time": "2022-01-17T06:22:28Z", "salary": {"currency": null, "max": null, "min": null, "period": "monthly", "term": null}, "salary_visible": false, "title_keywords": ["officer", "assistant"], "responsibilities": ["other duties", "developing", "develop", "coordination", "liaise with", "conduct research"], "requirements": {"degrees": ["degree"], "majors": ["business", "related disciplines", "marketing"], "languages": ["putonghua", "english", "chinese"], "language_level": ["good command"], "hard_skills": [], "soft_skills": ["communication skills", "self-motivated", "organized", "confidence", "detail-oriented", "communication"], "languages_combined": [{"language": "putonghua", "language_level": ["good command"]}, {"language": "english", "language_level": ["good command"]}, {"language": "chinese", "language_level": ["good command"]}]}, "experience_required": {"duration": ["at least 2 years"], "field": ["post-qualification", "training", "related", "education", "business", "marketing"]}}, {"job_id": "100003009053560", "location_code": "hk", "company": "Hong Kong Community Network Limited", "job_title": "\u9805\u76ee\u5e79\u4e8b", "description": "\n\u8077\u8cac :\u8ca0\u8cac\u63a8\u884c\u5404\u9805\u5c0f\u7d44\u3001\u670d\u52d9\u53ca\u6d3b\u52d5\n\n\u8cc7\u6b77 :\u5c08\u4e0a\u6559\u80b2\uff1a\u6587\u6191/\u8b49\u66f8; 1\u5e74\u7d93\u9a57; \u826f\u597d\u7cb5\u8a9e; \u4e00\u822c\u666e\u901a\u8a71; \u4e00\u822c\u82f1\u8a9e; \u61c2\u8b80\u5beb\u4e2d\u6587; \u61c2\u8b80\u5beb\u82f1\u6587; \u5177\u5ba3\u50b3\u6216\u7c4c\u5283\u77ed\u671f\u5e02\u96c6/\u5c55\u89bd\u6d3b\u52d5\u7d93\u9a57\u512a\u5148\n\n\u5f85\u9047 :\u6bcf\u6708$17,000 - $19,000, \u661f\u671f\u4e00\u81f3\u516d: \u4e0a\u534810\u6642\u81f3\u4e0b\u53486\u6642, \u6bcf\u9031\u5de5\u4f5c5\u5929\u81f36\u5929, \u6bcf\u5929\u5de5\u4f5c 8 \u5c0f\u6642\n\n\u7533\u8acb\u9808\u77e5 :\u6c42\u8077\u8005\u53ef\u96fb\u90f5(Apply Now)\u5c65\u6b77\u8868\u7d66\u9999\u6e2f\u793e\u5340\u7db2\u7d61\u6709\u9650\u516c\u53f8\u3002\u5982\u8981\u7d22\u53d6\u6536\u96c6\u500b\u4eba\u8cc7\u6599\u8072\u660e, \u8acb\u8207\u66fe\u5148\u751f(Email)\u806f\u7d61\u3002\n\n", "employment_types": ["Full Time"], "selling_points": [], "locations": ["Shatin Area"], "categories": ["Public / Civil", "Social Services - Community / Non-profit Organization", "Others", "Others", "Others"], "post_time": "2022-01-17T07:09:50Z", "salary": {"currency": null, "max": null, "min": null, "period": "monthly", "term": null}, "salary_visible": false, "title_keywords": [], "responsibilities": [], "requirements": {"degrees": [], "majors": [], "languages": [], "language_level": [], "hard_skills": [], "soft_skills": [], "languages_combined": []}, "experience_required": {"duration": [], "field": []}}, {"job_id": "100003009056098", "location_code": "hk", "company": "The Hong Kong Society for Rehabilitation", "job_title": "Officer (Communication and Resource Development) (Ref: AO (CRD) _HQ_JAN22)", "description": "Assist in planning and implementing communication strategies;\nAssist in organising campaigns and activities to enhance brand image and promote HKSR services;\nManage outreach channels including website, social media channels, eDM;\nWrite and develop corporate materials including press releases, newsletter, leaflets, brochure;\nLiaise with corporate partners and vendors;\nCoordinate various activities including corporate, media, fundraising and volunteering events;\nProvide administrative, logistics and clerical support to the Division;\nHandle any other ad hoc duties as required.\n\nRequirements\n\nDegree holder in Communications/ Marketing or related disciplines;\nMinimum 2 year of relevant experience in a marketing, communications or event management role, NGO experience is preferred;\nProven track record in social media management and event management;\nGood command of written and spoken English and Chinese;\nProficient in computer skills such as Microsoft Word, Excel, PowerPoint and Chinese Word Processing, knowledge of basic graphic design skills is preferred;\nGood marketing sense, knowledge and experience;\nDetail-minded, well organized and possess good interpersonal skills;\nResponsible, good team player and self-motivated;\nWilling to work on irregular work hours and overtime when required;\nImmediate availability is highly preferred.", "employment_types": ["Full Time", "Contract"], "selling_points": [], "locations": ["Kwun Tong Area"], "categories": ["Marketing / Public Relations", "Public Relations - Event Management", "Public Relations - General / Support", "Public / Civil", "Social Services - Community / Non-profit Organization"], "post_time": "2022-01-18T03:17:41Z", "salary": {"currency": null, "max": null, "min": null, "period": "monthly", "term": null}, "salary_visible": false, "title_keywords": ["officer"], "responsibilities": ["ad hoc duties", "social media", "management", "edm", "leaflets", "graphic design", "website", "clerical support", "develop", "communication", "coordinate", "logistics", "liaise with", "planning"], "requirements": {"degrees": ["degree holder"], "majors": ["related disciplines", "marketing", "communications"], "languages": ["english", "chinese"], "language_level": ["good command", "proficient", "basic"], "hard_skills": ["excel", "microsoft word", "chinese word processing", "basic", "powerpoint", "computer skills"], "soft_skills": ["detail-minded", "good team player", "self-motivated", "marketing sense", "responsible", "well organized", "communication", "interpersonal skills"], "languages_combined": [{"language": "english", "language_level": ["good command"]}, {"language": "chinese", "language_level": ["good command", "proficient", "basic"]}]}, "experience_required": {"duration": ["minimum 2 year"], "field": ["management", "marketing", "relevant experience"]}}, {"job_id": "100003009054965", "location_code": "hk", "company": "Good Lab Foundation Limited", "job_title": "Project Manager", "description": "About Good Lab\n\nGood Lab is a non-profit social innovation consultancy in Hong Kong dedicated to inspiring and fostering positive social change through human-centred design and cross-sector collaboration.\n\nAs a think-and-do tank, our mission is to connect different minds and actions to bring innovative ideas to life. We design and implement social innovation projects and training programmes to raise awareness of and tackle some of the most complex social issues faced by our society nowadays, particularly in the areas of community design, youth empowerment, civic participation, service innovation, environmental sustainability, and social venture incubation.\n\nSince 2012, we have been working at the intersection of civil society, NGOs, Government, and businesses to facilitate innovative co-creation leveraging Design Thinking. Putting people first and facilitating dialogues are the DNA of our work, as we believe this is the answer to co-creating a more sustainable and better tomorrow.\n\nWe are now looking for a\u00a0Project Manager\u00a0to lead our growing and exciting array of new projects and partnerships with a focus on\u00a0Youth Empowerment. Read below to find out more about the positions.\n\nAbout The Role \u2013 Project Manager (Youth Empowerment)\n\nWorking within a passionate small team, we are looking for a person who does not only want to sit at a computer all day. The main duties of this role are to manage a portfolio of innovative social programmes to promote youth empowerment and participation, talent development, and incubate new social ventures that will deliver tangible outcomes for our communities in Hong Kong. You will be engaging directly with our partners to design and implement impact-driven programmes targeted at youth from all walks of life, and coordinate dialogues between multiple stakeholders in different communities.\u00a0You will also get to inspire and develop young changemakers by arranging bespoke and engaging workshops, seminars and coaching sessions to build their capacities as caring, community-centred individuals with an entrepreneurial spirit. In addition, there will be opportunities to engage with and advise early-stage social start-ups, help them navigate their growth paths, and support their innovation journeys.\n\nYour Role as Project Manager \u2013 Our Project Leader\n\nLead social innovation projects to facilitate the co-creation of impactful solutions with partners and collaborators for the local communities;\nBuild empathy with stakeholders and lead them through an innovative process of co-creation and mindset change underpinned by Design Thinking;\nAssume project management responsibilities including, for instance, project scoping & planning, engagement planning & execution, budgeting, workshop design & facilitation, event coordination, data analysis, as well as partner & stakeholder management;\nLead and coach small teams of high-performing, passionate social consultants to align priorities, set directions, and collectively achieve purposeful goals in creating social value;\nIdentify pain points and aspirations of stakeholders through research, dialogues and community outreach; co-create grounded solutions to challenges based on analysis, experience, and judgement;\nProduce high-quality deliverables\u2014such as reports, presentations, prototypes and events\u2014to articulate and illustrate insights and recommendations of actionable solutions;\nBuild relationships and instil confidence in project partners and stakeholders as their trusted collaborator and advisor;\nComprehend and keep up-to-date on industry trends of social innovation, leading perspectives and best practices, as well as local and international cases; and\nIdentify partnership opportunities and forge new collaborations to tackle pressing issues in the social and public sectors of Hong Kong.\n\nRequirements\n\nBachelor\u2019s degree or above in social sciences, management, humanities, arts or related disciplines;\nMinimum five (5) years of experience in social and/or innovation project management in a leading position along with external partners and/or community stakeholders;\nExperience in innovation and/or business consulting, user research, community engagement, public administration, service design, social entrepreneurship, youth empowerment or related fields would be a strong advantage;\nStrong analytical and problem-solving competence with a commitment to high-quality service delivery;\nDemonstrate the ability to juggle multiple work priorities, attention to details, and outstanding organisational skills;\nExcellent communications and interpersonal skills with the capacity to motivate and lead with enthusiasm, drive, and effectiveness;\nDemonstrate the ability to collaborate and interact professionally with stakeholders of diverse backgrounds and interests;\nExcellent proficiency in both spoken and written English and Cantonese (Traditional Chinese); fluency in Mandarin would be an advantage;\nExcellent command on MS PowerPoint and Word;\nA motivated team player with the ability to take self-initiatives in a dynamic and collaborative project environment;\nAn outgoing character with a proven track record of partnership development would be an advantage; and\nBe able to work on weekends and flexible hours for specific Good Lab functions when required.Candidates with less experience may be considered for a\u00a0Project Officer\u00a0position.\n\nTo Applicants: please send your\u00a0Cover Letter\u00a0and\u00a0Resume\u00a0with\u00a0current and expected salary\u00a0via \"Apply Now\" button. Application with missing information will not be considered. Only short-listed candidates will be notified. Data collected will be used for recruitment purpose only and personal data of unsuccessful applicants will be destroyed after 12 months.", "employment_types": ["Full Time"], "selling_points": ["Non-profit social innovation consultancy", "Youth empowerment & Community engagement", "Social project management and execution"], "locations": ["Yau Ma Tei"], "categories": ["Public / Civil", "Social Services - Community / Non-profit Organization"], "post_time": "2022-01-17T16:21:11Z", "salary": {"currency": null, "max": null, "min": null, "period": null, "term": null}, "salary_visible": false, "title_keywords": ["project manager"], "responsibilities": ["ideas", "consulting", "data", "budgeting", "quality", "design", "personal data", "administration", "service delivery", "collaborate", "teams", "presentations", "develop", "reports", "management", "workshop", "data analysis", "analysis", "coordinate", "project management", "recruitment", "coordination", "planning"], "requirements": {"degrees": ["degree or above", "bachelor"], "majors": ["related disciplines", "humanities", "social sciences"], "languages": ["cantonese", "english", "chinese", "mandarin"], "language_level": ["fluency", "advantage", "excellent", "proficiency"], "hard_skills": ["small", "analysis", "problem-solving", "word", "presentations", "project management", "dynamic", "workshops", "ms powerpoint", "focus"], "soft_skills": ["collaborative", "articulate", "team player", "focus", "confidence", "problem-solving", "diverse", "interpersonal skills", "passionate", "organisational skills", "dynamic", "attention to details", "driven", "positive", "outgoing", "flexible", "project management", "motivated", "inspiring", "coordination", "innovative", "empathy", "purposeful"], "languages_combined": [{"language": "cantonese", "language_level": ["excellent", "proficiency"]}, {"language": "english", "language_level": ["excellent", "proficiency"]}, {"language": "chinese", "language_level": ["excellent", "proficiency"]}, {"language": "mandarin", "language_level": ["fluency", "advantage"]}]}, "experience_required": {"duration": [], "field": ["research", "consulting", "related", "design", "project management", "business", "administration"]}}, {"job_id": "100003009053553", "location_code": "hk", "company": "Hong Kong Community Network Limited", "job_title": "\u9805\u76ee\u4e3b\u7ba1(\u8a3b\u518a\u793e\u5de5)", "description": "\n\u8077\u8cac :\u8ca0\u8cac\u4e2d\u5fc3\u767c\u5c55\uff0c\u670d\u52d9\uff0c\u7ba1\u7406\uff0c\u8ca1\u52d9\uff0c\u7d71\u8a08\uff0c\u884c\u653f\uff0c\u4eba\u4e8b\uff0c\u7763\u5c0e\uff0c\u5c0d\u5916\u806f\u7d61\u53ca\u5408\u4f5c\u7b49\u4e8b\u52d9\n\n\u8cc7\u6b77 :\u5c08\u4e0a\u6559\u80b2\uff1a\u5b78\u58eb\u5b78\u4f4d; 2\u5e74\u7d93\u9a57; \u826f\u597d\u7cb5\u8a9e; \u4e00\u822c\u666e\u901a\u8a71; \u826f\u597d\u82f1\u8a9e; \u61c2\u8b80\u5beb\u4e2d\u6587; \u61c2\u8b80\u5beb\u82f1\u6587; \u8a3b\u518a\u793e\u5de5; \u5177\u793e\u5340\u670d\u52d9\u7d93\u9a57\u53ca\u958b\u62d3\u65b0\u670d\u52d9\u7684\u76f8\u95dc\u7d93\u9a57\u512a\u5148\n\n\u5f85\u9047 :\u6bcf\u6708$36,000 - $40,000, \u661f\u671f\u4e00\u81f3\u516d: \u4e0a\u534810\u6642\u81f3\u4e0b\u53486\u6642, \u6bcf\u9031\u5de5\u4f5c5\u5929\u81f36\u5929, \u661f\u671f\u516d\u9577\u77ed\u9031\n\n\u7533\u8acb\u9808\u77e5 :\u6c42\u8077\u8005\u53ef\u96fb\u90f5(Apply Now)\u5c65\u6b77\u8868\u7d66\u9999\u6e2f\u793e\u5340\u7db2\u7d61\u6709\u9650\u516c\u53f8\u3002\u5982\u8981\u7d22\u53d6\u6536\u96c6\u500b\u4eba\u8cc7\u6599\u8072\u660e, \u8acb\u8207\u66fe\u5148\u751f(Email)\u806f\u7d61\u3002\n\n", "employment_types": ["Full Time"], "selling_points": [], "locations": ["Kwai Hing"], "categories": ["Public / Civil", "Social Services - Community / Non-profit Organization", "Others", "Others"], "post_time": "2022-01-17T07:09:11Z", "salary": {"currency": null, "max": null, "min": null, "period": "monthly", "term": null}, "salary_visible": false, "title_keywords": [], "responsibilities": [], "requirements": {"degrees": [], "majors": [], "languages": [], "language_level": [], "hard_skills": [], "soft_skills": [], "languages_combined": []}, "experience_required": {"duration": [], "field": []}}, {"job_id": "100003009054934", "location_code": "hk", "company": "Sun Hung Kai Properties Ltd", "job_title": "PUBLIC AFFAIRS MANAGER", "description": "Requirements:\n\n\nUniversity degree or above\nA minimum of 10 years\u2019 experience in public affairs/ community liaison work in statutory bodies or sizable corporations or equivalent\nExcellent interpersonal and communication skills, able to establish working relationships with all levels of people\nAttention to details and can work under tight timeline\nGood command of English and Chinese\n\nResponsibilities:\n\n\nEstablish, strengthen and maintain a close working relationship with the Company\u2019s stakeholders, in particular government officials, political and community leaders, resident groups and key opinion leaders\nReach out to, liaise and engage with the Company\u2019s stakeholders with a view to advancing the Company\u2019s interest in development projects, businesses and operations\nMonitor public affairs developments which may affect or have an impact on the Company\u2019s interest and take appropriate/necessary actions to address the issues\nParticipate in and support the Company\u2019s public affairs and community services and related activities\nAny other duties and projects as assigned by supervisors\n\nGood remuneration and attractive fringe benefits will be offered to the successful applicant. Interested parties please apply with full resume, present and expected salary, available date by clicking \"Apply Now\".\n\nWe are an equal opportunity employer and welcome applications from all qualified candidates. All personal data collected will be used for recruitment purpose only.\u00a0 Applicants not hearing from us within 3 months may consider their applications unsuccessful.\u00a0 All personal data collected will be destroyed within 24 months.", "employment_types": ["Full Time", "Permanent"], "selling_points": ["Exp in public affairs / community liaison work", "Work with the Company\u2019s stakeholders", "Monitor public affairs developments"], "locations": ["Wan Chai"], "categories": ["Marketing / Public Relations", "Marketing - Marketing Communication", "Public Relations - General / Support", "Public / Civil", "Social Services - Community / Non-profit Organization"], "post_time": "2022-01-17T14:24:18Z", "salary": {"currency": null, "max": null, "min": null, "period": null, "term": null}, "salary_visible": false, "title_keywords": ["manager"], "responsibilities": ["liaise", "any other duties", "operations", "monitor", "maintain"], "requirements": {"degrees": ["degree or above"], "majors": [], "languages": ["english", "chinese"], "language_level": ["good command"], "hard_skills": [], "soft_skills": ["communication skills", "interpersonal", "attention to details"], "languages_combined": [{"language": "english", "language_level": ["good command"]}, {"language": "chinese", "language_level": ["good command"]}]}, "experience_required": {"duration": ["minimum of 10 years"], "field": []}}, {"job_id": "100003009053926", "location_code": "hk", "company": "YOJE Prudent Personnel Consultant Agency", "job_title": "Museum Assistant (Science/Chemistry/Engg/Biology/Conservation) - Fresh Graduates", "description": "- University graduate in Science, Chemistry, Biology, Technology, Engineering, Maths, Conservation or equivalent\n(Fresh graduates are welcome)\n- Good English and Chinese\n- Common Recruitment Examination English Level 2, Chinese Level 1 or DSE English 5, Chinese 4 or equivalent\u00a0\n- to assist in planning, coordination, liaison of education program, events\n- update social media & website\n\nInterested parties please send full resume with expected salary in MS WORD format to us by clicking \"APPLY NOW\"\nInformation collected will be used for recruitment purposes only", "employment_types": ["Full Time", "Permanent"], "selling_points": ["Science, Technology, Engineering, Maths, Chemistry", "Common Recruitment Exam English 2, Chinese 1", "Museum Assistant, support,  Biology, Conservation"], "locations": ["Not Specified"], "categories": ["Admin & HR", "Clerical / Admin Staff", "Public / Civil", "Social Services - Community / Non-profit Organization", "Others"], "post_time": "2022-01-17T07:53:13Z", "salary": {"currency": null, "max": null, "min": null, "period": "monthly", "term": null}, "salary_visible": false, "title_keywords": ["assistant"], "responsibilities": ["social media", "website", "recruitment", "coordination", "planning"], "requirements": {"degrees": ["university graduate", "dse"], "majors": ["science", "biology", "chemistry", "engineering"], "languages": ["english", "chinese"], "language_level": ["good"], "hard_skills": [], "soft_skills": ["coordination"], "languages_combined": [{"language": "english", "language_level": ["good"]}, {"language": "chinese", "language_level": ["good"]}]}, "experience_required": {"duration": [], "field": []}}, {"job_id": "100003009053698", "location_code": "hk", "company": "Property Management Services Authority", "job_title": "Administrative Assistant (Licensing) (Temporary) (Ref. No.: PMSA-AA(LIC)-31/21)", "description": "Responsibilities\nReporting to the Officer (Licensing), the appointee will be required to:\nConduct data entry and update information for licence applications;\nScan, maintain and file the application documents;\nProvide clerical support to the licensing application process and produce periodic statistical reports;\nLiaise and follow up with respective applicants on licence application when necessary;\nUndertake ad-hoc tasks as assigned from time to time.\nRequirements\nTertiary education or above in any disciplines;\nA minimum of 1 year relevant experience;\nRelevant work experience and knowledge in processing data and report generation are preferable;\nIndependent and able to work under pressure;\nKnowledge in MS Word and Excel is a must;\nGood command in Chinese and English input; and\nImmediately available is highly preferable.\n*\u00a0Contract Period: Jan \u2013 End of March 2022\n\nTerms of Appointment\nRemuneration will be commensurate with qualifications and experience. A temporary contract will be offered to the successful candidate. The PMSA is an equal opportunity employer and welcomes applications from all qualified candidates.\nApplication Procedure\nInterested applicants may send a full curriculum vitae indicating current and expected salaries to General Manager (Operation and Service), The Property Management Services Authority, Units 806-8, 8/F, Dah Sing Financial Centre, 248 Queen\u2019s Road East, Wan Chai, Hong Kong or by email. Please mark \u201cPRIVATE & CONFIDENTIAL\u201d, the position applied for and the reference number on the envelope.\nThe closing date for application is 31\u00a0January 2022.\u00a0 Recruitment will continue until the position is filled. Applicants not invited for interview within 6 weeks from the date of application may consider their application unsuccessful.\nAll applications will be treated in strict confidence. Personal data provided will only be used for job application processing.", "employment_types": ["Temporary", "Contract"], "selling_points": ["Clerical support to licensing application process", "Tertiary education with 1 year experience", "Immediately available is highly preferable"], "locations": ["Wan Chai"], "categories": ["Admin & HR", "Clerical / Admin Staff", "Public / Civil", "Social Services - Community / Non-profit Organization", "Utilities"], "post_time": "2022-01-17T07:22:05Z", "salary": {"currency": null, "max": null, "min": null, "period": "monthly", "term": null}, "salary_visible": false, "title_keywords": ["administrative assistant"], "responsibilities": ["provide clerical support", "reporting", "liaise", "data entry", "ad-hoc tasks", "application documents", "maintain", "reports"], "requirements": {"degrees": [], "majors": [], "languages": ["english", "chinese"], "language_level": ["good command"], "hard_skills": ["wan", "excel", "processing", "ms word"], "soft_skills": ["confidence", "independent", "work under pressure"], "languages_combined": [{"language": "english", "language_level": ["good command"]}, {"language": "chinese", "language_level": ["good command"]}]}, "experience_required": {"duration": ["minimum of 1 year"], "field": ["relevant experience"]}}, {"job_id": "100003009052174", "location_code": "hk", "company": "The Hong Kong Girl Guides Association", "job_title": "Assistant Project Officer", "description": "Responsibilities:\n\nTo assist the Senior Officer and Executive to develop Golden Guide services for senior / elder women\nTo coordinate, collaborate and liaise with other colleagues, committees, members and volunteers to plan, organize, implement, and evaluate programmes and activities\nTo promote services and activities and increase service outreach via various social media\nTo liaise and collaborate with other colleagues, volunteers, funding organisations and external parties to ensure smooth service operation\nTo perform general administration and office duties and handle enquiries and requests from members and the public\nTo assist Senior Officer and Executive to prepare reports, service and programme statistics, and analyse data as required\nTo work on weekends/public holidays / night as required\n\nRequirements:\n\n5 passes in HKCEE, including English (Syl. B) and Chinese Language OR 5 subjects obtained Level 2 or above in HKDSEE, including English and Chinese\nUniversity graduate\nAt least 2-3 years\u2019 relevant working experience in social welfare sector\nExperience in planning and organizing activities and events in NGOs\nAble to work independently and interested in communicating with elderly people, deal with multiple tasks and work under pressure\nWell-organised and attentive to details\nWell-versed in Microsoft application, power-point, Chinese word processing of \u5009\u9821 or \u901f\u6210\nKnowledge in Photoshop and/or AI is preferable\nGood manner, sociable and cheerful character with strong communication and interpersonal skill\nGuiding experience will be considered an advantage\n\nPlease send r\u00e9sum\u00e9 with your expected salary (a must) by clicking \"Apply Now\" or to Human Resources Department, 8 Gascoigne Road, Kowloon.\u00a0 Please mark \u201cPrivate & Confidential\u201d on the envelope.\n\nProspective employees are required to undergo Sexual Conviction Record Check.\n\u672c\u6703\u5c07\u8981\u6c42\u6e96\u50f1\u54e1\u9032\u884c\u6027\u7f6a\u884c\u5b9a\u7f6a\u7d00\u9304\u67e5\u6838\u3002\n\nPersonal data provided will be used for recruitment purpose only. All personal data of unsuccessful applicants will be destroyed on completion of the recruitment exercise.", "employment_types": ["Full Time", "Permanent"], "selling_points": [], "locations": ["Yau Tsim Mong Area"], "categories": ["Admin & HR", "Clerical / Admin Staff", "Others", "Public / Civil", "Social Services - Community / Non-profit Organization"], "post_time": "2022-01-17T02:21:04Z", "salary": {"currency": null, "max": null, "min": null, "period": "monthly", "term": null}, "salary_visible": false, "title_keywords": ["assistant project officer"], "responsibilities": ["collaborate", "social media", "liaise", "collaborate with", "prepare reports", "data", "external parties", "develop", "coordinate", "evaluate", "handle enquiries", "plan", "analyse", "liaise with", "administration"], "requirements": {"degrees": ["university graduate"], "majors": [], "languages": ["english", "chinese"], "language_level": [], "hard_skills": ["ai", "chinese word processing", "photoshop"], "soft_skills": ["work independently", "cheerful", "attentive to details", "multiple tasks", "interested in", "sociable", "interpersonal skill", "communication", "well-organised", "work under pressure"], "languages_combined": [{"language": "english", "language_level": []}, {"language": "chinese", "language_level": []}]}, "experience_required": {"duration": ["at least 2-3 years"], "field": ["relevant working experience", "planning"]}}, {"job_id": "100003009056351", "location_code": "hk", "company": "Yew Chung College of Early Childhood Education Limited", "job_title": "Senior Manager (Institutional Advancement)", "description": "Position Summary:\n\nThe\u00a0Senior Manager (Institutional Advancement) will be an important member of the Institutional Advancement and Marketing Office (IAMO).\n\nThe Key Responsibilities include:\n\nWork with the senior team members to establish annual financial goals, strategies and work plans;\nBuild relationships with prospects and donors to confirm major-gift giving and referrals. Cultivate and conduct prospect research to identify prospects to build a healthy pipeline and meet annual targets;\nWork with the marketing & communications team to develop supporting materials and proposals;\nWork with the stewardship team to establish donor stewardship plan and ensure the deliverables are met and communicated in a timely manner;\nBuild relationships with associations, corporate networks and other platforms to expand the reach and build prospect pipelines; and\nAny other duties as assigned by the College as appropriate.\n\nRequirements:\n\nApplicants should meet the following requirements:\n\nA Bachelor\u2019s degree in Business/Communications/Marketing or related discipline;\nAt least 8-10 years\u2019 relevant work experience. Experience in the post-secondary education sector will be an asset;\nDeep knowledge of the Hong Kong philanthropic landscape and fundraising principles;\nAccreditation in fundraising will be an advantage;\nStrong track record of the previous fundraising and industry connections are a must;\nExcellent communications and writing skills in English and Chinese (Spoken Cantonese & Putonghua, ability to read & write traditional and simplified Chinese)\nAbility to engage with senior executives\nOrganised and task-oriented to meet deadlines\nMust be self-motivated and proactive; and\nStrong interpersonal skills, able to resolve issues and maintain strong relationships.\nRemarks: Candidates with more experience may be appointed as Head (Institutional Advancement).\n\n\nSalary and Fringe Benefits:\n\nThe appointment will be made on a contract basis, renewable subject to mutual consent.\nRemuneration is competitive and will be based on qualifications and relevant experience.\nThe College offers group medical insurance, staff development support, annual leave and sick leave, and mandatory Provident Fund to the eligible appointee.\n\nApplication Procedure:\n\nApplicants are invited to:\n\nSubmit an application letter with a full Curriculum Vitae, and copies of all graduate transcripts, and the names and contact details of three references.\nSpecify in the application letter the current/latest salary and expected salary.\nSend applications to HR Office, Yew Chung College of Early Childhood Education by clicking \"Apply Now\".\nThe College will review applications immediately and applications will be accepted until the posts are filled.\u00a0 Only shortlisted candidates will be contacted.\n\nImportant notes to Applicants:\n\nAppointees will have to undergo a medical examination.\u00a0 Reimbursement of costs subject to a ceiling is applicable.\nLocal applicants will have to undergo a Sexual Conviction Record Check. Overseas applicants will have to present a police report before the appointment can be confirmed.\nA satisfactory employment reference is required before the appointment can be confirmed.\nThe College also reserves the right to make an appointment by invitation.\n\n\n\nPersonal data collected will be used for recruitment-related purposes only.", "employment_types": ["Full Time", "Contract"], "selling_points": ["Fundraising in educational organisation", "Good communicator", "Job opportunity in Aberdeen"], "locations": ["Aberdeen"], "categories": ["Education", "Others", "Marketing / Public Relations", "Public Relations - Event Management", "Public / Civil", "Social Services - Community / Non-profit Organization"], "post_time": "2022-01-18T04:03:10Z", "salary": {"currency": null, "max": null, "min": null, "period": "monthly", "term": null}, "salary_visible": false, "title_keywords": ["senior manager"], "responsibilities": ["any other duties", "a timely manner", "develop", "plan", "plans"], "requirements": {"degrees": ["degree", "bachelor", "secondary education"], "majors": ["business", "communications", "marketing"], "languages": ["cantonese", "putonghua", "english", "chinese"], "language_level": ["excellent"], "hard_skills": ["writing skills"], "soft_skills": ["self-motivated", "deep", "writing skills", "interpersonal skills", "organised", "meet deadlines", "proactive"], "languages_combined": [{"language": "cantonese", "language_level": ["excellent"]}, {"language": "putonghua", "language_level": ["excellent"]}, {"language": "english", "language_level": ["excellent"]}, {"language": "chinese", "language_level": ["excellent"]}]}, "experience_required": {"duration": ["at least 8-10 years"], "field": ["education"]}}, {"job_id": "100003009054436", "location_code": "hk", "company": "Changing Young Lives Foundation", "job_title": "Development Manager", "description": "The Job:\n\nIn charge of the full spectrum of fundraising and communications duties of the Organization\nFormulate and implement a strategic fundraising and marketing plan and calendar\nDevelop and maintain sustainable relationships with donors and corporate partners\nOversee the daily operation of a small fundraising team\nReport to Executive Director and perform ad hoc duties as assigned\n\nThe Person:\n\nDegree holder in marketing or communications\nMinimum 5 to 8 years of hands-on experience in fundraising and event management\nExperience in executing large-scale charity event a plus\nKnowledge of new media and digital marketing\nFamiliar with design and editing software a definite advantage\nSolid exposure to media relations or corporate affairs\u00a0preferable\nCreative and able to convert ideas into realities\nExcellent command of spoken and written English and Chinese\nProficient in MS Office\nRemarkable presentation and inter-personal skills\nSelf-motivated, good team player, able to work independently and under pressure\nImmediately available highly preferable\n\nCompetitive remuneration will be offered to the right candidate along with a five-day work week and medical insurance. Please send full resume with current and expected salary by clicking \u201cApply Now\u201d. All personal information will only be used for recruitment purpose.", "employment_types": ["Full Time", "Permanent"], "selling_points": [], "locations": ["Sham Shui Po"], "categories": ["Marketing / Public Relations", "Management", "Marketing - Marketing Communication", "Public / Civil", "Social Services - Community / Non-profit Organization"], "post_time": "2022-01-17T09:33:16Z", "salary": {"currency": null, "max": null, "min": null, "period": "monthly", "term": null}, "salary_visible": false, "title_keywords": ["manager"], "responsibilities": ["ad hoc duties", "daily operation", "develop", "marketing plan", "maintain", "report"], "requirements": {"degrees": ["degree holder"], "majors": ["marketing", "communications"], "languages": ["english", "chinese"], "language_level": ["excellent"], "hard_skills": ["plus", "ms office", "charity"], "soft_skills": ["self-motivated", "good team player", "work independently", "under pressure", "inter-personal skills", "hands-on", "creative", "presentation"], "languages_combined": [{"language": "english", "language_level": ["excellent"]}, {"language": "chinese", "language_level": ["excellent"]}]}, "experience_required": {"duration": ["minimum 5 to 8 years"], "field": ["management"]}}, {"job_id": "100003009054240", "location_code": "hk", "company": "The Vine Church Limited", "job_title": "Volunteer & Connections Coordinator", "description": "This is a full-time position which reports to Ministry Life Pastor.\n\nRecruit and train new volunteers;\nArrange rostering and keep scheduling of volunteers;\nCoordinate, develop and mobilize volunteers for both Welcome and Connect Team and Hosts and Counting team;\nDevelop onboarding process for new volunteers. Match volunteers to opportunities that suit their skill sets and ensuring they understand their responsibilities and receive the proper training;\nAppoint and train team leaders for volunteer teams;\nEstablish a Sundays Volunteer Core Team and provide pastoral care for volunteers;\nAssist Ministry Life Pastor to provide a wider Vine volunteer strategy & communication plan. Coordinate volunteers\u2019 connection points and opportunities regularly;\nMaintain a database of Newcomers and keep track of the connection points;\nBe the point person coordinating \u201cfirst contacts\u201d for new first time guests;\nCollaborate with Services Team to coordinate Newcomers Sunday Lunches & Forward Together;\nPartner with Community Groups team to oversee connect hub;\nParticipate fully in Pastoral Team and Ministry Life Team\u2019s activities including meetings, intercession meetings and devotions.\n\nJob Requirement\n\nExperience in volunteering and recruitment.\nWorking knowledge of databases management.\nAble to communicate effectively with diverse people.\nExcellent organization and team coordination skills.\nGood command of written and spoken English and Chinese.\nPleasant and outgoing.\n\nHow to apply\n\nInterested parties please send application with full CV with your current and expected salary by clicking \"Apply Now\".\n\nPersonal data provided by job applicants will be strictly used for recruitment purpose.", "employment_types": ["Full Time"], "selling_points": [], "locations": ["Wan Chai"], "categories": ["Admin & HR", "Clerical / Admin Staff", "Public / Civil", "Social Services - Community / Non-profit Organization", "Others"], "post_time": "2022-01-17T08:55:11Z", "salary": {"currency": null, "max": null, "min": null, "period": "monthly", "term": null}, "salary_visible": false, "title_keywords": ["coordinator"], "responsibilities": ["collaborate with", "management", "teams", "develop", "coordinate", "scheduling", "communication", "maintain", "reports", "recruitment", "plan", "database", "databases", "coordination"], "requirements": {"degrees": [], "majors": [], "languages": ["english", "chinese"], "language_level": ["good command"], "hard_skills": ["databases"], "soft_skills": ["outgoing", "coordination skills", "pleasant", "communication", "diverse"], "languages_combined": [{"language": "english", "language_level": ["good command"]}, {"language": "chinese", "language_level": ["good command"]}]}, "experience_required": {"duration": [], "field": ["recruitment"]}}, {"job_id": "100003009054979", "location_code": "hk", "company": "Tung Wah Group of Hospitals", "job_title": "Senior Assistant Fund-raising Manager (Corporate Marketing and Sponsorship)/ Admin. Headquarters", "description": "[REF: SHRM(P)1/SAFRM(CMS)/JOBS]\n\nLocation: Sheung Wan\n\nRoles and responsibilities:\n\nProvide executive support in formulation of strategy to strengthen/uplift corporate donations and data mining analysis to identify prospective donors as well as competitive edge, better options and market trends in fund-raising activities;\nenhance data warehouse with collection and collation of updated data for planning and development purposes as well as carry out segmentation of donor groups to identify the best tactics for expansion of opportunity and facilitate collaboration with key stakeholders and setting of business priorities;\ndeliver fund-raising promotion activities and strengthen donor communication platform;\nstrategically manage corporate relationship with donors to achieve high satisfaction and retention results;\nidentify prospective donors and opportunities to bring in new source of donation;\nmonitor and initiate system enhancement of the relevant database and draw up users\u2019 specifications based on business needs as required; and\nplan and execute fund-raising activities, and review the related process to meet the corporate objectives.\n\nThe ideal candidate should possess:\n\na recognized degree in business administration, marketing or related subjects, OR other qualifications with substantial exposure to marketing and customer analytics;\nat least Grade D in English Language (Syllabus B) and Chinese Language in the HKCEE or equivalent;\nat least 4 years of execution experience preferably having performed marketing roles in sizable business operations and possession of strong business acumen;\npreferably managerial experience in marketing gained in B2B businesses or fast-moving consumer goods industry. Connection with corporate of expatriate community is an advantage;\nclear understanding of corporate needs/orientation in the charity field with excellent analytical, problem solving and project management skills;\nproficiency in PC applications and sound knowledge in Microsoft Office, particular in Excel;\nproficiency in written and oral English and Chinese, preferably including Putonghua; and\ngood interpersonal and communication skills, flexible mind, independent with strong drive and initiative well organized, details oriented and result driven with strong sense of responsibility.\n\n(Please specify in the application form the HKCEE results and relevant qualifications/working experience you have attained in detail.)\n\nCompensation & employment terms:\n\nThe successful candidate will be appointed on contract terms with a remuneration package which will be commensurate with his/her background and experience.\u00a0 Apart from contributions to the MPF Scheme, other benefits include paid annual leave, medical services, a dental scheme and training sponsorships.\u00a0 The incumbent will normally work under a 5-day week schedule subject to operational needs and exigencies of the service.\n\nApplication:\n\nPlease send your resume and a completed application form <F601(n)> with indication of your current and expected salaries to the Head of Human Resources Division, Tung Wah Group of Hospitals at 4/F., Wong Fung Ling Memorial Building, 12 Po Yan Street, Hong Kong by\u00a024 January\u00a02022.\u00a0\u00a0Application forms are obtainable in person or can be downloaded from http://www.tungwah.org.hk.\u00a0\u00a0The reference code should be marked both in the letter and on the envelope.\u00a0 Underpaid mail items will not be accepted by Tung Wah.\u00a0 For proper delivery of your mail items, please ensure your mail items bear sufficient postage with return address before posting.\u00a0\u00a0Personal data provided by applicants will be used strictly for recruitment purpose only and in accordance with the Tung Wah's personal data policy.\u00a0 Applicants not invited to attend an interview by\u00a030 April 2022 may assume that their applications are unsuccessful.\n\nWE ARE AN EQUAL OPPORTUNITIES EMPLOYER", "employment_types": ["Full Time"], "selling_points": [], "locations": ["Sheung Wan"], "categories": ["Marketing / Public Relations", "Marketing - Marketing Communication", "Public Relations - Event Management", "Public / Civil", "Social Services - Community / Non-profit Organization"], "post_time": "2022-01-17T16:22:42Z", "salary": {"currency": null, "max": null, "min": null, "period": "monthly", "term": null}, "salary_visible": false, "title_keywords": ["admin. headquarters", "manager", "assistant"], "responsibilities": ["administration", "data", "operations", "analysis", "review", "monitor", "executive support", "communication", "project management", "specifications", "database", "plan", "data mining", "planning"], "requirements": {"degrees": ["degree"], "majors": ["marketing", "business administration"], "languages": ["putonghua", "english", "chinese"], "language_level": ["proficiency"], "hard_skills": ["excel", "microsoft office", "data warehouse", "analysis", "charity", "pc applications", "problem solving", "project management", "data mining", "wan", "acumen"], "soft_skills": ["flexible", "communication skills", "oral", "independent", "sense of responsibility", "project management skills", "well organized", "driven", "communication", "problem solving", "clear", "business acumen", "initiative", "interpersonal", "ideal"], "languages_combined": [{"language": "putonghua", "language_level": []}, {"language": "english", "language_level": ["proficiency"]}, {"language": "chinese", "language_level": ["proficiency"]}]}, "experience_required": {"duration": ["at least 4 years"], "field": ["business", "managerial", "fast-moving consumer goods", "marketing"]}}, {"job_id": "100003009052183", "location_code": "hk", "company": "The Hong Kong Girl Guides Association", "job_title": "Assistant Administrative Officer", "description": "To cope with our development, HKGGA is now looking for candidates of high caliber to join us:\n\n\nResponsibilities:\n\n\nProvide administrative and secretarial support, such as writing minutes, letters and reports for Administration Department as well as senior management.\nAnswer telephone enquiries and perform daily routine administration tasks.\nAssist senior executives to organize events and projects as required.\nIrregular working hours in weekends and public holidays is required if necessary.\n\nRequirements:\n\n\n\nBachelor of Arts or equivalent;\nAt least 2 year\u2019s administrative work experience, social service sector or NGOs is highly preferred\nProficient in spoken and written English language\nProficient in Putonghua is preferable\nWell-versed in Microsoft Office and Chinese word processing e.g. \u901f\u6210or\u5009\u9821\nAble to communicate with all levels of people\nMeticulous, patient and work under pressure\nCandidate with more experience will be considered as Administrative Officer\u00a0\n\nPlease send r\u00e9sum\u00e9 with Ref. Code and expected salary by clicking \"Apply Now\" or to Human Resources Department, 8 Gascoigne Road, Kowloon. Please mark \u201cPrivate & Confidential\u201d on the envelope.\n\nProspective employees are required to undergo Sexual Conviction Record Check.\n\u672c\u6703\u5c07\u8981\u6c42\u6e96\u50f1\u54e1\u9032\u884c\u6027\u7f6a\u884c\u5b9a\u7f6a\u7d00\u9304\u67e5\u6838\u3002\n\nPersonal data provided will be used for recruitment purpose only. All personal data of unsuccessful applicants will be destroyed on completion of the recruitment exercise.", "employment_types": ["Full Time", "Permanent"], "selling_points": [], "locations": ["Yau Tsim Mong Area"], "categories": ["Admin & HR", "Clerical / Admin Staff", "Secretary", "Public / Civil", "Social Services - Community / Non-profit Organization"], "post_time": "2022-01-17T02:22:27Z", "salary": {"currency": null, "max": null, "min": null, "period": "monthly", "term": null}, "salary_visible": false, "title_keywords": ["administrative officer", "assistant"], "responsibilities": ["letters", "reports", "secretarial support", "senior management", "administration"], "requirements": {"degrees": ["bachelor"], "majors": [], "languages": ["putonghua", "english", "chinese"], "language_level": ["proficient"], "hard_skills": ["code", "chinese word processing", "microsoft office"], "soft_skills": ["meticulous", "patient", "work under pressure"], "languages_combined": [{"language": "putonghua", "language_level": ["proficient"]}, {"language": "english", "language_level": []}, {"language": "chinese", "language_level": []}]}, "experience_required": {"duration": ["at least 2 year"], "field": ["administrative"]}}, {"job_id": "100003009054192", "location_code": "hk", "company": "Hong Kong Arts Development Council", "job_title": "Office Support Assistant (Job ref: OSA-2206-JDB)", "description": "Main Duties:\n\n\u00a0 Perform all-round reception counter service, answer phone calls and general enquiries;\n\u00a0 Record and distribute incoming and outgoing mails/couriers and e-Fax etc.;\n\u00a0 Handle meeting room bookings and provide logistic support for Council / Committee meetings;\n\u00a0 Record and ensure office stationery supplies and distribution;\n\u00a0 Responsible for record grant applications registrations and distribution;\n\u00a0 Provide departmental administrative and clerical support;\n\u00a0 Other ad-hoc duties assigned by supervisors\n\nRequirements:\n\n\u00a0 F.5 graduate with 5 passes in HKDSE or above; minimum 1-year working experience;\n\u00a0 Pleasant, courteous with good telephone manner and good communication skills in both English and Chinese;\n\u00a0 Proficient in MS Office and Chinese word processing;\n\u00a0 Punctual, work independently and good at multi-tasking;\n\u00a0 Able to work on Saturday/Sunday occasionally;\n\u00a0 Fresh graduates with some working experience may also be considered.\n\nSalary offered will be commensurate with qualifications and experience. Interested parties, please send CV with details on education and work experience, stating salary history and expected salary, and indicating your earliest availability to the Human Resources Department, 10/F, 1063 King\u2019s Road, Quarry Bay, Hong Kong no later than 4 February 2022. Please quote the job reference on the envelope.\n\nApplicants not invited for interview within 16 weeks from the closing date for application may assume that their applications are unsuccessful. Personal data collected will be treated in strictest confidence and will only be used for recruitment purposes. HKADC reserves the right to consider late applications and not to make appointment for the post advertised. We do not accept applications through e-mail or fax.\n\nHKADC is an Equal Opportunities Employer", "employment_types": ["Full Time", "Permanent"], "selling_points": [], "locations": ["Quarry Bay"], "categories": ["Admin & HR", "Clerical / Admin Staff", "Receptionist", "Public / Civil", "Social Services - Community / Non-profit Organization"], "post_time": "2022-01-17T09:17:02Z", "salary": {"currency": null, "max": null, "min": null, "period": "monthly", "term": null}, "salary_visible": false, "title_keywords": ["assistant"], "responsibilities": ["logistic support", "stationery", "administrative and clerical support", "ad-hoc duties", "incoming and outgoing mails", "answer phone calls"], "requirements": {"degrees": ["hkdse"], "majors": [], "languages": ["english", "chinese"], "language_level": ["proficient", "good"], "hard_skills": ["chinese word processing", "ms office"], "soft_skills": ["communication skills", "courteous", "work independently", "pleasant", "multi-tasking", "telephone manner"], "languages_combined": [{"language": "english", "language_level": ["good"]}, {"language": "chinese", "language_level": ["proficient", "good"]}]}, "experience_required": {"duration": ["minimum 1-year"], "field": []}}, {"job_id": "100003009053234", "location_code": "hk", "company": "Playright Children's Play Association", "job_title": "Project Executive", "description": "The service direction of Play Environment is to champion accessible, inclusive, playable and safe play space for all children. The recent focus of the Play Environment Team includes advocating nature play, supporting children participation in play space design, facilitating the transformation of the 170+ public play space in LCSD venues, promoting better planning policies and practices to ensure children\u2019s access to play. All advocacy work has its root in creating a society where children can enjoy their childhood.\n\nChildren prosper in a society that supports play. Local policy makers, government agents, the creative industry and the civil society are rethinking current practices and seeking innovations in providing quality play space. The incumbent will join Play Environment Team to build stakeholders\u2019 capacity in creating child-friendly and playful built environment.\n\nJOB DUTIES & RESPONSIBILITIES:\n\nProvide research support for local play space management and maintenance strategy and development;\nAssist in policy matters in relation to local children\u2019s play development, including drafting discussion papers and strategic planning advice;\nReview existing district plan of Hung Hom, conduct appropriate research and community engagement to inform the development of adventure playground in Hung Hom promenade;\nPerform any ad hoc play environment projects as assigned.\n\nREQUIREMENTS:\n\nRecognized degree or equivalent experience in Urban Design / Urban Studies;\nSelf-motivated, detail-minded with good interpersonal, communication and statistical analysis skills;\nAbility to work autonomously and to collaborate in a small team environment\nAbility to priorities workload and meet deadlines\nSome knowledge and experience in design and construction process and/or public participation practices is an advantage\nHigh-level written and verbal communication skills, fluent in Chinese and English\n\nOTHER BENIFITS\n\n\n\n5-day work week with flexible work hours\nTransportation Allowance\nMedical insurance\nTraining opportunities\n\nInterested candidates please send the cover letter together with full resume indicating the expected salary by clicking \"Apply Now\"\n\n\nAll applications will be treated in strictest confidence.\u00a0 Personal data collected will be used for recruitment purposes only and unsuccessful applications will be destroyed upon completion of the recruitment exercise.\u00a0", "employment_types": ["Full Time"], "selling_points": [], "locations": ["Kwun Tong"], "categories": ["Building & Construction", "Architectural Services", "Marketing / Public Relations", "Public Relations - Copy-writing", "Public / Civil", "Social Services - Community / Non-profit Organization"], "post_time": "2022-01-17T06:30:26Z", "salary": {"currency": null, "max": null, "min": null, "period": "monthly", "term": null}, "salary_visible": false, "title_keywords": ["project executive"], "responsibilities": ["management", "ad hoc", "strategic planning", "maintenance", "review", "research support", "plan"], "requirements": {"degrees": ["degree"], "majors": ["design"], "languages": ["english", "chinese"], "language_level": ["fluent"], "hard_skills": ["small", "statistical analysis"], "soft_skills": ["detail-minded", "communication skills", "self-motivated", "flexible", "communication", "meet deadlines", "interpersonal"], "languages_combined": [{"language": "english", "language_level": ["fluent"]}, {"language": "chinese", "language_level": ["fluent"]}]}, "experience_required": {"duration": [], "field": ["construction", "design"]}}, {"job_id": "100003009055548", "location_code": "hk", "company": "Hong Kong Housing Society", "job_title": "CES - Senior Officer (Elderly Services)", "description": "[Ref: CES-SO(ES)]\n\nThe Job:\n\nAssist in manage the overall operation and administration of the estate-based social support services and Elderly Lounges.\nAssist in service delivery including to enhance the social capital, to deliver counseling and case management, to provide social activities and volunteer services, to provide support to the property management staff, and to visit all tenants in elderly flats and assisted-living flats.\nAssist in coordinating with the Estate Management Offices and Occupational therapists for on-going facility improvement and home modification at respective rental estates.\nAssist in liaising and coordinating with collaborators from planning to implementation of activities, programs and groups to promote home safety, health and social care to meet with various needs of elderly tenants.\nAssist in monitoring site management such as cleaning and maintenance, inventory and procurement, report and statistic, program planning and evaluation.\nHandle daily requests, enquiries and complaints of the elderly tenants and on site coordination between internal and external parties; in case of any emergency, determine prompt action with the contingency plan to ensure safety for the elderly tenants.\nProvide guidance and arrange duties for S4 / O4 to ensure the service quality and standard of estate-based social support services.\nUndertake any other duties as assigned by the direct supervisor deems appropriate.\n\nThe Person:\n\nDiploma holder or above in social work / health science with minimum 3-5 years\u2019 post qualification working experience in recognized welfare organization of elderly service; community services is preferable.\nGood manner, self-motivated and able to work independently.\nSensitive to interpersonal relations with good communication skill.\nGood command of both written and spoken English and Chinese.\nGood PC knowledge and typing skills.\n\nAttractive remuneration package will be offered to suitable candidates. To apply, please submit online application: https://careers.hkhs.com/ or send your application with full resume and reference quoted to Human Resources Manager by fax: 2882 4466.\n\nYou are welcome to visit our website www.hkhs.com to learn more about us.\nApplicants not invited for interview within 8 weeks may consider their applications unsuccessful.\n\nPersonal data provided by job applicants will be used strictly in accordance with the Housing Society\u2019s personal data policies which is available in our website and obtainable upon request. Please refer to the Policy Statement on Employment Related Data under Personal Data (Privacy) Ordinance in our website.", "employment_types": ["Permanent"], "selling_points": ["Administration of the Elderly Lounges", "Deliver counseling and case management", "Diploma holder or above in social work"], "locations": ["Others"], "categories": ["Public / Civil", "Social Services - Community / Non-profit Organization"], "post_time": "2022-01-18T02:42:01Z", "salary": {"currency": null, "max": null, "min": null, "period": "monthly", "term": null}, "salary_visible": false, "title_keywords": ["senior officer"], "responsibilities": ["any other duties", "inventory", "internal and external parties", "quality", "plan", "evaluation", "administration", "service delivery", "implementation", "report", "management", "provide support", "monitoring", "site coordination", "cleaning", "provide guidance", "maintenance", "support services", "site management", "planning"], "requirements": {"degrees": ["diploma holder"], "majors": ["social work", "science"], "languages": ["english", "chinese"], "language_level": ["good command"], "hard_skills": ["pc knowledge", "typing"], "soft_skills": ["self-motivated", "work independently", "communication skill", "sensitive to", "interpersonal"], "languages_combined": [{"language": "english", "language_level": ["good command"]}, {"language": "chinese", "language_level": ["good command"]}]}, "experience_required": {"duration": ["minimum 3-5 years"], "field": []}}, {"job_id": "100003009056442", "location_code": "hk", "company": "Hong Kong Committee for UNICEF", "job_title": "Manager, Fundraising", "description": "Roles & Responsibilities\n\nPlanning\n\n\nProduce annual plans, budgets and KPIs for Individual Giving income generation via one-off and regular giving, as well as cultivation, solicitation.\u00a0 Contribute to overall individual giving strategy and team development.\nRegularly monitor performance and evaluate plans and budgets, taking effective action where necessary and ensure that appropriate reporting, monitoring and evaluation of activities takes place.\n\nSolicitations\n\nIncrease income generated from individual giving fundraising activities towards individual and medium level donor groups\nLead the team to develop and manage donor recruitment campaigns creatively, and\nEstablish an engaging cultivation programs to increase giving levels of existing donors;\nManage a continuous cycle of testing new channels and platforms, based on audience insight\nFoster strategic and tactical relationships with key external agencies, suppliers and stakeholders as required.\n\nTeam Management & Coaching\n\nProvide management and guidance to direct reports, in order to ensure that IG team KPIs and objectives are achieved and that direct reports each have a clear personal development plan.\nEffective line management, professional support and personal development\n\nRequirements\n\nUndergraduate degree holder with at least 12 years of experience, at least 5 years at a supervisory level in fundraising with a focus on individual donors.\nStrong command of both spoken and written Chinese and English\nConsiderable experience of preparing programmes and business plans to recruit, engage, inspire and cultivate donors\nExperience of developing and implementing an individual giving strategy.\u00a0\nKnowledge of budgets and experience of reporting financial performance against targets\nDemonstrable ability to line manage a small team and inspire others to deliver against targets and objectives\nAbility to work across teams and departments in a collaborative manner and to proactively engage colleagues on projects and initiatives\nThe ability to be a proactive self-starter and to use initiative to resolve problems and create solutions to improve results\nResult oriented, flexible, patient, donor/customer centric with excellent interpersonal and communications skills\nProven problem solving and decision making skills with a track record of using good judgment to make decisions that lead to positive outcomes.\n\n\nThe deadline for application is 17 February 2022. If this is an opportunity you would be interested in, please email your application letter and resume with expected salary to us. Candidates who are selected for interview will receive an invitation within 3 weeks from the closing date. (All information provided will only be used for recruitment-related purpose.)", "employment_types": ["Full Time"], "selling_points": [], "locations": ["North Point"], "categories": ["Public / Civil", "Social Services - Community / Non-profit Organization"], "post_time": "2022-01-18T04:19:48Z", "salary": {"currency": null, "max": null, "min": null, "period": "monthly", "term": null}, "salary_visible": false, "title_keywords": ["manager"], "responsibilities": ["budgets", "reporting", "management", "evaluation", "guidance", "monitor performance", "monitoring", "develop", "evaluate", "testing", "recruitment", "reports", "plan", "kpis", "plans", "planning"], "requirements": {"degrees": ["degree holder"], "majors": [], "languages": ["english", "chinese"], "language_level": [], "hard_skills": ["small", "make", "focus", "problem solving"], "soft_skills": ["flexible", "decision making skills", "interpersonal", "interested in", "collaborative", "problem solving", "result oriented", "patient", "focus", "proactive", "initiative", "positive"], "languages_combined": [{"language": "english", "language_level": []}, {"language": "chinese", "language_level": []}]}, "experience_required": {"duration": ["at least 12 years", "at least 5 years"], "field": ["supervisory level", "business", "developing", "financial"]}}, {"job_id": "100003009052810", "location_code": "hk", "company": "\u5065\u5eb7\u7a7a\u6c23\u884c\u52d5", "job_title": "Communications Manager", "description": "Attractiveness\nHaving grown into the most influential non-profit organization on air pollution issue in Hong Kong, joining the team of Clean Air Network provides you with the opportunity to fulfill your passion for the well-being of the city, get exposed to the global discussion on environmental health issue, and participate in one of the most challenging campaigns to clean up the air in Hong Kong.\n\nRoles and Responsibilities:\nTo implement our strategy, the Communications Manager will work with a small, yet highly effective and multi-talented campaign team to co-deliver established campaign goals.\n\nThe role is responsible for developing content strategy and planning across effective channels to meet organisational goals and objective.\n\nThe Communication Manager is primarily responsible for working with the CEO to develop and implement an effective communication plan, with the objectives to strengthen impact communications and organization presence among target audiences.\n\nSpecific areas of duties:\n. Manage strategic and impact communications to support stakeholder management\n. Develop organizational content plan and manage engagement project\n. Develop external and internal reports, manage media relations and website revamp\n\nPreferred Qualifications:\n. Passionate on and have an understanding of global and local environmental issues\n. Bachelor or master\u2019s degree with 3-5 years of work experience on impact / corporate messaging\n. With a strong sense of project management and quality control\u00a0\n. Proficiency in Chinese and English writing\n. Able to analyse, understand and synthesise complex information, and to present these findings in a concise and engaging way\n. Experience in developing communication strategy, development of website/app\n. Experience in project management and media management\n. Able to work in a small team\n\nAbout us\nClean Air Network is a non-profit organization founded in 2009. Our vision is to build a Hong Kong with clean air. To achieve this vision, we are dedicated to driving policy and behavioral change to improve public health by building knowledge, collaborating strategically, and advocating solutions in a collaborative approach.\n\nWithout losing sight on the pollution from regional activities, marine vessels and power plants, our current primary focus is on roadside pollution.\n\nApplication\nInterested candidates please send your CV and cover letter outlining your skills, experience, expected salary and availability to the provided email. We will review and arrange meet-up interview(s) in due course. Thank you.", "employment_types": ["Full Time"], "selling_points": ["Develop impact/corp communication strategy", "Manage engagement projects", "3-5 years working experience"], "locations": ["Sheung Wan"], "categories": ["Public / Civil", "Social Services - Community / Non-profit Organization"], "post_time": "2022-01-17T04:37:32Z", "salary": {"currency": null, "max": null, "min": null, "period": "monthly", "term": null}, "salary_visible": false, "title_keywords": ["manager"], "responsibilities": ["management", "revamp", "developing", "website", "develop", "communication", "environmental issues", "project management", "reports", "plan", "quality control", "analyse", "planning"], "requirements": {"degrees": ["degree", "bachelor", "master"], "majors": [], "languages": ["english", "chinese"], "language_level": ["proficiency"], "hard_skills": ["clean", "project management", "focus", "small"], "soft_skills": ["passionate", "responsible", "passion for", "organizational", "collaborative", "communication", "influential", "project management", "focus"], "languages_combined": [{"language": "english", "language_level": ["proficiency"]}, {"language": "chinese", "language_level": ["proficiency"]}]}, "experience_required": {"duration": ["3-5 years"], "field": ["management", "development", "developing", "project management", "media"]}}, {"job_id": "100003009053341", "location_code": "hk", "company": "United Christian Nethersole Community Health Service", "job_title": "Radiographer I / II - \u653e\u5c04\u6280\u5e2b", "description": "Responsibilities:\n\nOperate X-Ray, DEXA and Mammogram equipment and instruments according to SOPs\nPerform on-going maintenance checks to ensure test results are precise and accurate\nAssist to maintain document system\n\nRequirements:\n\nBSc in Radiography\nHolder of a valid practising certificate issued by HK Radiographers Board\nProficiency in both English and Chinese\nProvide imaging services for patients and handle patients\u2019 enquiries\nGood personal integrity, hardworking, responsible and trustworthy\nGood team player, with good interpersonal and leadership skills\nIndependent, self-motivated and strong sense of responsibility\nFresh graduate will also be considered\n\nStaff Benefits:\n\nRegular Sunday and Public Holidays off\n14 to 18 days\u2019 annual leave entitlement\nMedical benefits to staff and dependent\n\nInterested parties please send full resume with last and expected salary to Human Resources Unit, United Christian Nethersole Community Health Service, L1, KEC Administrative Building, No. 2 Po Ning Lane, Hang Hau, Tseung Kwan O with job reference no. marked on the envelope or by clicking \"Apply Now\"\n\n(Applicants not invited for interview within 4 weeks from the closing date may consider their applications unsuccessful. All personal data collected will be treated in strict confidence and will only be used for recruitment related purpose.)", "employment_types": ["Full Time", "Part Time", "Contract"], "selling_points": [], "locations": ["Not Specified"], "categories": ["Medical Services", "Medical Services Technician", "Others", "Public / Civil", "Social Services - Community / Non-profit Organization"], "post_time": "2022-01-17T06:48:26Z", "salary": {"currency": null, "max": null, "min": null, "period": "monthly", "term": null}, "salary_visible": false, "title_keywords": ["radiographer"], "responsibilities": ["dexa", "maintenance", "maintain", "sops"], "requirements": {"degrees": ["fresh graduate", "certificate", "bsc"], "majors": [], "languages": ["english", "chinese"], "language_level": ["proficiency"], "hard_skills": [], "soft_skills": ["good team player", "self-motivated", "independent", "trustworthy", "responsible", "sense of responsibility", "leadership skills", "integrity", "interpersonal", "hardworking"], "languages_combined": [{"language": "english", "language_level": ["proficiency"]}, {"language": "chinese", "language_level": ["proficiency"]}]}, "experience_required": {"duration": [], "field": []}}, {"job_id": "100003009053214", "location_code": "hk", "company": "Playright Children's Play Association", "job_title": "Hospital Play Specialist", "description": "Job Summary:\nPlayright is a charity which carries out the mission of promoting children play for 30 years as we \u201cValue Children, Value Play\u201d.\n\nHospital\u00a0Play\u00a0Services\nIn Hospital Play, we help sick children and special needs children to cope with being ill and/or being hospitalized to prevent emotional scars.\u00a0 We support families and partners and also conduct researches to strengthen holistic paediatric care.\n\nJob Duties & Responsibilities:\n\nConduct Play, Leisure Activity and Arts activities to establish Hospital Play services to be a sustainable and essential Part of the Health Care System\nEngage and develop Hospital Play in different public hospitals including but not limited to Special Outpatient Clinic (SOPC), Radiology Department, Renal Ward and other wards and departments as required.\nEmbrace the PLAY model for connecting HKCH with other district hospitals to support seamless care to child patients through Play, Leisure, Arts using a child-centred and child friendly way.\nPartner with NGOs & Communities to strengthen comprehensive care to child patients.\u00a0\nContinue to perform the role with best practices and pursue overseas qualifications and local recognition, gain accreditation and acceptance in the medical communities for quality service provision.\u00a0\nWork with different professional bodies and Universities to conduct evidence based research about the service improvement and sustainability of Hospital Play Services\n\nRequirements\n\nDegree holder in either discipline of Psychology, Nursing, Child Care, Social Work or Education, with preference given to Nursing and Social Work.\nRelevant experience in working or playing with children is plus\nExperience in serving special needs children is a plus\nExperience in playing music with children is a plus\nGood command of Chinese and English (oral and written)\nSound interpersonal skills and outgoing character\nWell organized and able to work independently\nEnergetic and good social skills with people\nHave experience in organizing mass programs\nHolder of adult first-aid certificate is a plus\nHave passion for serving children and charity sector\n\nOther Benefits:\n\n5-day work week with flexible work hours\nTransportation Allowance\nMedical insurance\nTraining opportunities\n\n* Prospective employee is requested to undergo Sexual Conviction Record Check on voluntary basis *\n\nWe offer competitive remuneration package that commensurate with experience and qualifications. Interested candidates are invited to send their applications and full resumes, indicating the interested job post, career history, job references, qualifications, present and expected salary, simply click the below \u201cApply Now\u201d Button.\n\nAll personal data will be used for recruitment purpose only.\u00a0 Unsuccessful applications will be destroyed upon completion of the recruitment exercise.", "employment_types": ["Full Time", "Contract"], "selling_points": [], "locations": ["Not Specified"], "categories": ["Medical Services", "Medical Services Technician", "Specialist", "Public / Civil", "Social Services - Community / Non-profit Organization"], "post_time": "2022-01-17T06:27:19Z", "salary": {"currency": null, "max": null, "min": null, "period": "monthly", "term": null}, "salary_visible": false, "title_keywords": ["specialist"], "responsibilities": ["quality", "develop"], "requirements": {"degrees": ["certificate", "degree holder"], "majors": ["social work", "psychology", "nursing"], "languages": ["english", "chinese"], "language_level": ["good command"], "hard_skills": ["plus", "charity"], "soft_skills": ["outgoing", "oral", "work independently", "passion for", "well organized", "interpersonal skills", "energetic"], "languages_combined": [{"language": "english", "language_level": ["good command"]}, {"language": "chinese", "language_level": ["good command"]}]}, "experience_required": {"duration": [], "field": ["relevant experience"]}}, {"job_id": "100003009053425", "location_code": "hk", "company": "Hong Kong Cement Company Limited", "job_title": "Sailor", "description": "\nResponsibilities:\n\u2022 \u8ca0\u8cac\u6c34\u6ce5\u904b\u8f38\uff0c\u78bc\u982d\u5378\u8239\uff0c\u99c1\u8239\u57fa\u672c\u62cb\u7e9c\u3001\u7d81\u6a01\uff0c\u8239\u52d9\u57fa\u672c\u6aa2\u4fee\u3002\nRequirements :\n\u2022 No requirement on academic qualification;\n3 Year(s) Experience Required; Fluent Cantonese ;\n\u2022 Fair Putonghua preferred; Able to read & write Chinese ;\n\u2022 Shipboard Cargo Handling Basic Training Course Certificate; \u5177\u6c34\u6ce5\u8e89\u8239\u5de5\u4f5c\u7d93\u9a57\u512a\u5148\nEmployment Terms:$18,000 - $23,000 per month, with Double Pay, Meal Allowance, Bonus, Transport Allowance and Year-end Bonus, 8:00AM-5:00PM, 6 working days per week, on shift, shift holiday, 8 working hours per day, \u914d\u5408\u5927\u8239\u5230\u6e2f\u6642\u9593\u57f7\u884c\u8239\u52d9\u5de5\u4f5c\n\n", "employment_types": ["Full Time"], "selling_points": [], "locations": ["Tsing Yi"], "categories": ["Public / Civil", "Social Services - Community / Non-profit Organization", "Others"], "post_time": "2022-01-17T06:58:21Z", "salary": {"currency": null, "max": null, "min": null, "period": "monthly", "term": null}, "salary_visible": false, "title_keywords": [], "responsibilities": [], "requirements": {"degrees": ["certificate"], "majors": [], "languages": ["cantonese", "putonghua", "chinese"], "language_level": ["fluent"], "hard_skills": ["no", "basic"], "soft_skills": [], "languages_combined": [{"language": "cantonese", "language_level": ["fluent"]}, {"language": "putonghua", "language_level": []}, {"language": "chinese", "language_level": []}]}, "experience_required": {"duration": [], "field": []}}, {"job_id": "100003009056450", "location_code": "hk", "company": "Hong Kong Committee for UNICEF", "job_title": "Corporate Partnership Manager", "description": "Roles & Responsibilities\n\nDevise and implement effective platforms to acquire new partners; build a community of supporters to enhance results; and engage corporate donors and partners in a journey of experience with UNICEF\u2019s humanitarian and development mission for children.\u00a0\nProactively approach prospects and drive collaborative programmes to mobilise resources from the private sector and foundations.\nInnovate and lead engagement activities for donors, including forums, talks, donor visits and field trips, and build donors\u2019 knowledge of UNICEF\u2019s programmatic initiatives and impact.\nPlan, assess and implement strategies to retain and grow corporate partners\nManage the departmental budget of income and expenditure.\n\n\n\nRequirements\n\nHighly independently to produce results\nA self-motivator and self-learner, able to acquire and build knowledge on the job or through UNICEF\u2019s internal resource or market contact and experience\nHighly skilled in stakeholder engagement, communications and marketing, backed by a strong social and professional network\nExcellent English & Chinese writing skills. Able to write and present proposals effectively\nStrong analytical skills to drive effective results and provide market assessment\nAt least 8 years of experience in business development, sales and marketing, including relevant experiences with corporate donors. Some global exposure is an advantage\nA university degree in business, marketing, social development or related disciplines\n\n\n\nThe deadline for application is 17 February 2022. If this is an opportunity you would be interested in, please email your application letter and resume with expected salary to us. Candidates who are selected for interview will receive an invitation within 3 weeks from the closing date.\u00a0(All information provided will only be used for recruitment-related purpose.)", "employment_types": ["Full Time"], "selling_points": [], "locations": ["North Point"], "categories": ["Public / Civil", "Social Services - Community / Non-profit Organization"], "post_time": "2022-01-18T04:21:51Z", "salary": {"currency": null, "max": null, "min": null, "period": "monthly", "term": null}, "salary_visible": false, "title_keywords": ["manager"], "responsibilities": ["budget", "plan"], "requirements": {"degrees": ["university degree"], "majors": ["related disciplines", "business", "marketing"], "languages": ["english", "chinese"], "language_level": ["excellent"], "hard_skills": ["writing skills", "analytical skills"], "soft_skills": ["interested in", "independently", "writing skills", "analytical skills"], "languages_combined": [{"language": "english", "language_level": ["excellent"]}, {"language": "chinese", "language_level": ["excellent"]}]}, "experience_required": {"duration": ["at least 8 years"], "field": ["business development", "marketing"]}}, {"job_id": "100003009055547", "location_code": "hk", "company": "Hong Kong Housing Society", "job_title": "Community Services Manager", "description": "[Ref : CES-COMSM]\n\nThe Job\n\nTo assist the Manager (ES) in the execution of social support programmes and review the overall operation and administration of the CES Team at respective estate according to the approved business plans and milestones.\nTo coordinate with Estate Offices and Occupational therapists for on-going facility improvement and home modification at respective estate.\nTo liaise and partner with external parties in the collaborative projects/services at respective estate(s), including but not limited to district social service operators, social enterprises, health service providers, hospitals, educational institutes and governmental departments.\nTo provide professional counseling and case management for needy tenants, expertise timely referrals to social services and closely liaise with NGOs for subsequent follow-up action to prevent crisis.\nTo promote neighborhood support through establishing and developing mutual support networks among tenants and mobilise the volunteer teams in rendering community-building activities at respective estate.\nTo manage the operation of responsible CES cum Elderly Lounge in attaining the designated service outputs and outcomes, and conduct regular home visits and/or telephone concern calls to the needy tenants.\nTo coordinate the working groups of district-based collaborative projects and signature events, including but not limited to the service award ceremonies, festive and thematic carnivals, IT system building and configuration, media interviews and renovation projects.\nTo supervise and coach the subordinates to assure the quality of services, and manage the team in effective and efficient manner.\nTo undertake any other duties as assigned by the direct supervisor deems appropriate.\n\nThe Person\n\nMinimum 5 years\u2019 post qualification working experience in recognized welfare organization of elderly service; community services preferable.\nWith administrative and supervisory experience.\nPrevious in-charge-of community health program, elderly care projects preferable.\nGood connection with NGOs, social enterprises and other stakeholders in social services.\nSelf-starter with ability to excel in a changing community environment.\nStrong team player, mature and able to conduct evidence-based study.\nMotivated with strategic mindset in service development.\nExcellent communication, presentation and interpersonal skills.\nGood command of English, Putonghua and Cantonese.\n\nAttractive remuneration package will be offered to suitable candidates. To apply, please submit online application: https://careers.hkhs.com/ or send your application with full resume and reference quoted to Human Resources Manager by fax: 2882 4466.\n\nYou are welcome to visit our website www.hkhs.com to learn more about us.\nApplicants not invited for interview within 8 weeks may consider their applications unsuccessful.\n\nPersonal data provided by job applicants will be used strictly in accordance with the Housing Society\u2019s personal data policies which is available in our website and obtainable upon request. Please refer to the Policy Statement on Employment Related Data under Personal Data (Privacy) Ordinance in our website.", "employment_types": ["Permanent"], "selling_points": ["Execution of social support programmes", "Experience in welfare org. of elderly service", "Previous in-charge-of community health program"], "locations": ["Others"], "categories": ["Public / Civil", "Social Services - Community / Non-profit Organization"], "post_time": "2022-01-18T02:41:56Z", "salary": {"currency": null, "max": null, "min": null, "period": "monthly", "term": null}, "salary_visible": false, "title_keywords": ["community services manager"], "responsibilities": ["liaise", "any other duties", "management", "configuration", "review", "coordinate with", "external parties", "business plans", "developing", "teams", "coordinate", "renovation", "quality", "liaise with", "administration"], "requirements": {"degrees": [], "majors": [], "languages": ["cantonese", "putonghua", "english"], "language_level": ["good command"], "hard_skills": ["excel"], "soft_skills": ["mature", "communication", "motivated", "interpersonal skills", "team player", "presentation"], "languages_combined": [{"language": "cantonese", "language_level": ["good command"]}, {"language": "putonghua", "language_level": ["good command"]}, {"language": "english", "language_level": ["good command"]}]}, "experience_required": {"duration": ["minimum 5 years"], "field": ["administrative", "supervisory experience"]}}, {"job_id": "100003009054405", "location_code": "hk", "company": "St. James' Settlement", "job_title": "Senior Accounting Officer (AO I) (Contract)\u3008Ref: AC/07222\u3009", "description": "Accounting Unit\n\n\n\nRequirement:\n\nlA university degree in Accounting / Finance or related discipline\n\nlWith 5 years of relevant experience, of which 2 years in a supervisory role\n\nlProficiency in Microsoft Office, experience in Crystal report applications is preferred\n\nlProfessional accounting qualification ACCA/HKICPA or equivalent is an advantage but not a must\n\nlStrong communication, interpersonal, analytical and problem solving skills\n\nlPrevious experience gained in NGO is an advantage\n\nJob Duties:\n\nlSupervise and manage a team on daily accounting operations\n\nlEnsure the relevant rules and regulations are adhered by service units and team members\n\nlLiaise with service units and provide advices for financial related issues\n\nlResponsible for monthly accounting closing and financial reporting\n\nlReview monthly management accounts and financial analyses\n\nlLiaise with external auditors, lawyers and bankers when required\n\nlAssist in formulating accounting policies and internal control procedures\n\nlAd-hoc analyses and tasks as required\n\nInterested persons please apply with full resume via APPLY NOW\u00a0on or before 28/1/2022.\n**When recruiting staff for job positions relating to services for child or mentally incapacitated persons, we shall request applicants to undergo the Sexual Conviction Record Check.**\n\n\u300cPersonal data collected will be strictly used for the recruitment exercise only. Unsuccessful applications will be destroyed one year after the closing date.\u300d\n", "employment_types": ["Full Time", "Contract"], "selling_points": ["Degree in Accounting / Finance or related", "5 yrs of relevant exp of which 2 yrs in supervisor", "Proficiency in Microsoft Office, Crystal report"], "locations": ["Wan Chai"], "categories": ["Accounting", "Accounting Clerk / Supervisor", "Public / Civil", "Social Services - Community / Non-profit Organization"], "post_time": "2022-01-17T09:23:34Z", "salary": {"currency": null, "max": null, "min": null, "period": "monthly", "term": null}, "salary_visible": false, "title_keywords": ["senior accounting officer"], "responsibilities": ["regulations", "provide advices", "management", "procedures", "daily accounting operations", "accounting policies", "recruitment", "financial reporting", "personal data", "internal control", "external auditors"], "requirements": {"degrees": ["university degree"], "majors": ["finance", "accounting"], "languages": [], "language_level": [], "hard_skills": ["hkicpa", "acca", "problem solving skills", "microsoft office"], "soft_skills": ["communication", "analytical and problem solving skills", "interpersonal"], "languages_combined": []}, "experience_required": {"duration": ["5 years", "2 years"], "field": ["supervisory", "relevant experience"]}}, {"job_id": "100003009055569", "location_code": "hk", "company": "ConnectedGroup Limited", "job_title": "NGO - Executive Director", "description": "Our client, a not for profit with a deep history and strong brand recognition, is in the search for their Executive Director. The organisation requires meaningful operational oversight and people leadership as well as core fund-raising/communications activity. With significant investment and growth plans in the coming few years, a strategic review and paced transformation is required.\n\nReporting to the Chairperson and the Executive Committee, and leading a team of 180+ employees, the Executive Director will be responsible for:\n\nEstablishing strategic goals, performance targets and execution plans, aligning efforts into their achievement and encompassing fundraising, service delivery and financial management\nCreating and implementing plans for the development of the organization, ensuring vision and mission are achieved\nResponsible for fiscal management: operating within the approved budget, ensuring maximum resource utilization, and maintenance of the organization in a positive financial position\nDeveloping policies and corporate governance protocols\nResponsible for enhancing the organizational brand and image, executing strategic events, managing relationships with partners, donors, and public bodies\nMotivating, nurturing, and developing staff whilst building a sustainable culture in line with the organizational values, as well as ensuring sustained performance\n\nRequirements:\n\nBachelors degree in business administration or similar\nOver 20 years of professional experience, WITH general management experience, directing and overseeing the operation of a service-driven organization with a similar level of complexity\nMust have large scale team management and leadership experience\nStrong public relations, marketing, and fundraising experience\nStrong financial management, problem solving and communication skills\nMUST have genuine interest and passion for animals and nature\n\nInterested parties please click on \"Apply\", kindly note only relevant candidates will be contacted.", "employment_types": ["Full Time", "Permanent"], "selling_points": ["Must have General Management Experience", "Must have large team 180+ mgt experience", "Cantonese and English required"], "locations": ["Not Specified"], "categories": ["Public / Civil", "Social Services - Community / Non-profit Organization"], "post_time": "2022-01-18T02:43:56Z", "salary": {"currency": null, "max": null, "min": null, "period": "monthly", "term": null}, "salary_visible": false, "title_keywords": ["executive director"], "responsibilities": ["service delivery", "reporting", "management", "maintenance", "policies", "review", "budget", "developing", "communication", "executing", "plans", "administration"], "requirements": {"degrees": ["degree"], "majors": ["business administration"], "languages": [], "language_level": [], "hard_skills": ["problem solving", "maintenance"], "soft_skills": ["communication skills", "responsible", "passion for", "organizational", "deep", "problem solving", "organisation", "genuine", "leadership", "driven", "positive"], "languages_combined": []}, "experience_required": {"duration": ["20 years"], "field": ["management", "public relations", "operation", "marketing", "team"]}}, {"job_id": "100003009053467", "location_code": "hk", "company": "The Wing Fat Printing (Hong Kong) Limited", "job_title": "Page Make-up Worker", "description": "\nResponsibilities:\n\u8ca0\u8cac\u88fd\u4f5c\u6392\u7248\u3001\u8a2d\u8a08 (\u5177\u5370\u5237\u88fd\u4f5c\u76f8\u95dc\u5de5\u4f5c\u7d93\u9a57,\u5177\u8a2d\u8a08\u5c08\u696d\u7d93\u9a57\u512a\u5148)\nRequirements :\nPost-secondary (Diploma/Certificate);\n1 Year(s) Experience Required; Fluent Cantonese ;\n\u2022 Fair Putonghua ; Able to read & write Chinese ;\n\u2022 Able to read & write simple English ;\n\u2022 \u719f\u7df4\u64cd\u4f5cAI\u3001PS\u3001PDF\u3001InDesign\u7b49\u5716\u5f62\u88fd\u4f5c\u6392\u7248\u8edf\u4ef6,\u719f\u6089\u6d77\u5fb7\u5821CTP\u88fd\u7248\u3001\u51fa\u7248\u7cfb\u7d71\u53ca\u64cd\u4f5c\n\n", "employment_types": ["Full Time"], "selling_points": [], "locations": ["Wong Tai Sin Area"], "categories": ["Public / Civil", "Social Services - Community / Non-profit Organization", "Others"], "post_time": "2022-01-17T07:01:18Z", "salary": {"currency": null, "max": null, "min": null, "period": "monthly", "term": null}, "salary_visible": false, "title_keywords": [], "responsibilities": [], "requirements": {"degrees": ["certificate", "diploma"], "majors": [], "languages": ["cantonese", "putonghua", "english", "chinese"], "language_level": ["fluent"], "hard_skills": ["simple"], "soft_skills": [], "languages_combined": [{"language": "cantonese", "language_level": ["fluent"]}, {"language": "putonghua", "language_level": []}, {"language": "english", "language_level": []}, {"language": "chinese", "language_level": []}]}, "experience_required": {"duration": [], "field": []}}, {"job_id": "100003009055539", "location_code": "hk", "company": "Hong Kong Housing Society", "job_title": "Assistant Manager (Elderly Services) / Social Worker - Tseung Kwan O", "description": "[Ref: JL-AM(ES)]\n\n\nThe Job\n\nProvide professional counseling to residents and service users in SEN Jolly Place.\nSupervise CSRs and to coordinate the daily operation of the club house include administrative work.\nMake timely referrals to community service centers or related organizations for early treatment and to closely liaise with NGOs for follow up to prevent from further deterioration.\nPartner with nursing staffs / property management to conduct timely home visits or hospital visitations for all residents.\nOrganize and implement programmes, functions and activities for residents, club members and service users during regular intervals and especially on festive dates.\nOrganize health check programmes for the tenants annually.\nAct as a communication bridge between residents and property management staffs.\nCoordinate the concierge service to provide the backup support to frontline staffs to handle tenants and related service users\u2018 enquiries and complaints.\nHolding the tenants meeting once every two months and prepare the agenda and meetings.\nEmergency support and services arrangement for tenants.\n\nThe Person\n\nDegree holder in social work or related healthcare areas.\nA minimum of 5 years of working experiences in elderly services or related sector.\nPossessed management experience and social worker qualification will be an advantage.\nDemonstrate a balance of business acumen and social conscience.\nGood organization, communication and interpersonal skills.\nFluent spoken English, Cantonese and good written English and Chinese.\nGood computer knowledge and skills.\n\nAttractive remuneration package will be offered to suitable candidates. To apply, please submit online application: https://careers.hkhs.com/ or send your application with full resume and reference quoted to Human Resources Manager by fax: 2882 4466.\n\nYou are welcome to visit our website www.hkhs.com to learn more about us.\nApplicants not invited for interview within 8 weeks may consider their applications unsuccessful.\n\nPersonal data provided by job applicants will be used strictly in accordance with the Housing Society\u2019s personal data policies which is available in our website and obtainable upon request. Please refer to the Policy Statement on Employment Related Data under Personal Data (Privacy) Ordinance in our website.", "employment_types": ["Permanent"], "selling_points": ["Provide professional counseling to residents", "5 years of experiences in elderly services sector", "Management exp. and social worker qualification"], "locations": ["Tseung Kwan O"], "categories": ["Public / Civil", "Social Services - Community / Non-profit Organization"], "post_time": "2022-01-18T02:41:21Z", "salary": {"currency": null, "max": null, "min": null, "period": "monthly", "term": null}, "salary_visible": false, "title_keywords": ["social worker", "assistant manager"], "responsibilities": ["management", "administrative work", "daily operation", "coordinate", "communication", "liaise with"], "requirements": {"degrees": ["degree holder"], "majors": ["social work"], "languages": ["cantonese", "english", "chinese"], "language_level": ["good", "fluent"], "hard_skills": ["acumen"], "soft_skills": ["business acumen", "communication and interpersonal skills"], "languages_combined": [{"language": "cantonese", "language_level": ["fluent"]}, {"language": "english", "language_level": ["good", "fluent"]}, {"language": "chinese", "language_level": ["good", "fluent"]}]}, "experience_required": {"duration": ["minimum of 5 years"], "field": ["related", "management"]}}, {"job_id": "100003009056233", "location_code": "hk", "company": "Po Leung Kuk", "job_title": "Assistant Human Resources Manager (Ref: AM-HR)", "description": "Responsibilities:\n\n\nThe successful candidate will be responsible for managing and administering various HR functions, including Manpower Planning, Recruitment and Appointment, Training and Development, C&B and Payroll, Performance Management and Staff Relations, HRIS maintenance, tax & insurance issues etc. As an Assistant HR manager, you will also be required to formulate, draft, review, implement and constantly update HR policies and proceduresin accordance with prevailing requirements and enhance operational efficiency & effectiveness and work on ad hoc tasks when required.\n\nRequirements:\n\nRecognized university degree in HR Management, Business Administration or related discipline;\n\nMinimum 7-8 years\u2019 relevant experience with 3-5 years at supervisory level of sizeable organization;\nFamiliar with Employment Ordinance and other statutory and compliance requirements in Hong Kong;\nFamiliar with HRIS and NGO staff issues including understanding of government funding and relevant requirement will be an advantage;\nExcellent communication in English and Chinese, with analytical, agile and report writing skills;\nProactive and passion for work with excellent interpersonal skills;\nAble to work under pressure, mature and independent;\nImmediate available is preferred;\nCandidates with less managerial experience may be considered as Senior HR Officer.\nAppointment will be on renewable contract terms.\u00a0Please send your full resume with current and expected salary via clicking \"APPLY NOW\"\u00a0or mail to\u00a0Human Resources Department, Po Leung Kuk, 66 Leighton Road, Hong Kong.\u00a0Please quote the reference on the envelope. For more information about Po Leung Kuk, please visit\u00a0http://www.poleungkuk.org.hk.\n\n\nPo Leung Kuk is an equal opportunity employer and welcomes application from all qualified candidates. Information provided relating to employment will be kept confidential and used only for processing applications. Applicants who are not contacted within 6 weeks may consider their application unsuccessful and all unsuccessful applications will be destroyed upon completion of the recruitment exercise.", "employment_types": ["Full Time", "Contract"], "selling_points": [], "locations": ["Causeway Bay"], "categories": ["Admin & HR", "Compensation & Benefits", "HR Supporting Staff", "Public / Civil", "Social Services - Community / Non-profit Organization"], "post_time": "2022-01-18T03:41:26Z", "salary": {"currency": null, "max": null, "min": null, "period": "monthly", "term": null}, "salary_visible": false, "title_keywords": ["hr", "assistant human resources manager"], "responsibilities": ["tax", "management", "maintenance", "policies", "hr", "review", "ad hoc tasks", "recruitment", "insurance", "payroll", "planning"], "requirements": {"degrees": ["university degree"], "majors": ["business administration"], "languages": ["english", "chinese"], "language_level": ["excellent"], "hard_skills": ["processing", "agile", "writing skills"], "soft_skills": ["independent", "agile", "passion for", "writing skills", "mature", "communication", "interpersonal skills", "proactive", "work under pressure"], "languages_combined": [{"language": "english", "language_level": ["excellent"]}, {"language": "chinese", "language_level": ["excellent"]}]}, "experience_required": {"duration": ["minimum 7-8 years", "3-5 years"], "field": ["supervisory level", "hr", "relevant experience", "managerial"]}}, {"job_id": "100003009054380", "location_code": "hk", "company": "St. James' Settlement", "job_title": "Dispenser (Contract)\u3008Ref: PCP/07122\u3009", "description": "Charity Services\n\n\n\nRequirement:\n\nlPossess a Diploma or Certificate in Pharmaceutical Studies or Dispensing Practice\n\nlRelevant experience in drug Dispensing is preferable\n\nlPro-active, strong interest in providing outreach service in Philanthropic Community Pharmacy\n\nlExcellent communication skills\n\nlGood in both written & spoken Chinese & English\n\nJob Duties:\n\nlProvides Dispensing services under the supervision of Registered Pharmacist\n\nlJob related to pharmacy development such as system management, documentation, data analysis etc.\n\nInterested persons please apply with full resume via APPLY NOW\u00a0on or before 31/01/2022.\n**When recruiting staff for job positions relating to services for child or mentally incapacitated persons, we shall request applicants to undergo the Sexual Conviction Record Check.**\n\n\u300cPersonal data collected will be strictly used for the recruitment exercise only. Unsuccessful applications will be destroyed one year after the closing date.\u300d\n\n\n", "employment_types": ["Full Time", "Contract"], "selling_points": ["Dip./Cert in Pharmaceutical Studies or relevant", "Relevant exp in drug Dispensing is preferable", "Good in both written & spoken Chinese & English"], "locations": ["Wan Chai"], "categories": ["Medical Services", "Pharmaceutical", "Public / Civil", "Social Services - Community / Non-profit Organization"], "post_time": "2022-01-17T09:19:01Z", "salary": {"currency": null, "max": null, "min": null, "period": "monthly", "term": null}, "salary_visible": false, "title_keywords": ["dispenser"], "responsibilities": ["management", "data analysis", "recruitment", "documentation", "personal data"], "requirements": {"degrees": ["certificate", "diploma"], "majors": [], "languages": ["english", "chinese"], "language_level": [], "hard_skills": [], "soft_skills": ["communication skills", "active"], "languages_combined": [{"language": "english", "language_level": []}, {"language": "chinese", "language_level": []}]}, "experience_required": {"duration": [], "field": []}}, {"job_id": "100003009050178", "location_code": "hk", "company": "Hong Kong Quality Assurance Agency", "job_title": "Project Officer (18-month contract)", "description": "Responsibilities:\n\n\nAssist to coordinate, monitor, supervise and work with other team members in completing the work within the planning schedule\nMonitor and control project tasks and costs within the approved project tasks and budget\nManage and monitor the preparation of contract documentations, cost plan, estimates, payments and final account\nLiaise, coordinate and communicate with project stakeholders\nProvide admin and logistic support\nRequirements:\n\nDegree holder with 1 year project management and research experience is an added advantage\nFamiliar with MS Word, Excel, PowerPoint and Chinese word processing\nHard working, responsible, independent with good coordination and communication skill\nAnalytical mind, good learning capability, initiative and flexibility\nRemuneration will be commensurate with qualification and working experience.\u00a0 Interested parties please forward your resume with\u00a0photo,\u00a0expected remuneration\u00a0and\u00a0personal particulars\u00a0to the\u00a0Human Resource Office, Hong Kong Quality Assurance Agency, 19th Floor, K Wah Centre, 191 Java Road, North Point, Hong Kong\u00a0OR\u00a0by fax to\u00a0\u00a02202 9190\u00a0OR\u00a0click\u00a0\u201cApply Now\u201d to apply job. Duplicate applications will not be considered.\u00a0\u00a0\n\n\nInformation supplied will be kept in strict confidence and only be used for recruitment related purpose.\u00a0 Applicants not invited for interview within 6 weeks may consider their applications unsuccessful. Application forms and curriculum vitae will be kept for a period of 3 months after completion of the selection process.", "employment_types": ["Full Time", "Contract"], "selling_points": ["Degree holder with 1 yr exp.", "Managing, performing and delivering projects", "Project management experience"], "locations": ["North Point"], "categories": ["Sales, CS & Business Devpt", "Sales - Sales Management", "Public / Civil", "Social Services - Community / Non-profit Organization", "Sales Administration"], "post_time": "2022-01-14T09:54:35Z", "salary": {"currency": null, "max": null, "min": null, "period": "monthly", "term": null}, "salary_visible": false, "title_keywords": ["project officer"], "responsibilities": ["liaise", "communicate with", "control", "cost", "budget", "monitor", "logistic support", "coordinate", "payments", "schedule", "plan", "costs", "planning"], "requirements": {"degrees": ["degree holder"], "majors": ["project management"], "languages": ["chinese"], "language_level": [], "hard_skills": ["excel", "chinese word processing", "powerpoint", "project management", "ms word"], "soft_skills": ["independent", "responsible", "hard working", "communication skill", "project management", "analytical mind", "learning", "coordination", "initiative"], "languages_combined": [{"language": "chinese", "language_level": []}]}, "experience_required": {"duration": ["1 year"], "field": ["project management", "research"]}}, {"job_id": "100003009054978", "location_code": "hk", "company": "Tung Wah Group of Hospitals", "job_title": "Senior Assistant Human Resources Manager (Administration)/ Admin. HQ [REF: SHRM(P)1/SAHRM(A)/JOBS]", "description": "[REF: SHRM(P)1/SAHRM(A)/JOBS]\n\nLocation: Sheung Wan\n\nRoles & responsibilities:\n\nPlan, design, develop and implement staff relations and welfare policies to align with the corporate strategies;\noversee the handling of staff welfare benefits (such as medical/dental treatment, merit awards and etc.), make recommendations for applications of staff welfare schemes/grants and ensure all applications are processed in a timely and proper manner;\nmanage staff awards such as Long Service Awards, Retirement Awards by designing the souvenir(s) and follow up the production and distribution;\nplan and formulate the office yearly plan/budget of the Section for management\u2019s approval;\nconduct review to smoothen the operation procedure of the Section and provide recommendations to optimize the staff welfare benefit schemes/grants;\nconsolidate the regular/annual exercises (i.e. annual report/plan/budget) for the Section and prepare the integrated version for management\u2019s approval;\nlead the Administration Team to maintain a smooth daily office operation for the Section; and\nplan, design and implement staff welfare/relations initiatives as assigned.\n\nThe ideal candidate should possess:\n\na recognized degree or equivalent;\nat least Grade D in English Language (Syllabus B) and Chinese Language in the HKCEE or equivalent;\nat least 4 years of administrative experience preferably in drafting administration policy/staff welfare schemes or project management;\nproficiency in English and Chinese, and preferably in Putonghua;\ncalibre as a good team player with supervisory experience and sound communication skills; and\nability to work independently with initiative and have a strong sense of responsibility.\n\n(Please specify in the application form the HKCEE result and relevant working experience you have attained in detail.)\n\nCompensation & employment terms:\n\nThe successful candidate will initially be offered a 3-year contract with a remuneration package which will be commensurate with his/her background and experience.\u00a0 The continuation of employment and employment terms thereafter will be subject to mutual agreement.\u00a0 Apart from contributions to the MPF Scheme, other benefits include paid annual leave, medical services, a dental scheme and training sponsorships.\u00a0 The incumbent will normally work under a 5-day week schedule subject to operational needs and exigencies of the service.\n\nApplication:\n\nPlease send your resume and a completed application form [F601(n)] with indication of your current and expected salaries to the Head of Human Resources Division, Tung Wah Group of Hospitals at 4/F., Wong Fung Ling Memorial Building, 12 Po Yan Street, Hong Kong by 24 January\u00a02022.\u00a0 The reference code should be marked both in the letter and on the envelope.\u00a0 Application forms are obtainable in person or can be downloaded from http://www.tungwah.org.hk.\u00a0\u00a0Underpaid mail items will not be accepted by Tung Wah.\u00a0 For proper delivery of your mail items, please ensure your mail items bear sufficient postage with return address before posting.\u00a0 Personal data provided by applicants will be used strictly for recruitment purpose only and in accordance with the Tung Wah's personal data policy.\u00a0 Applicants not invited to attend an interview by 30 April 2022 may assume that their applications are unsuccessful.\n\nWE ARE AN EQUAL OPPORTUNITIES EMPLOYER", "employment_types": ["Full Time"], "selling_points": [], "locations": ["Sheung Wan"], "categories": ["Admin & HR", "Compensation & Benefits", "HR Director / Manager", "Public / Civil", "Social Services - Community / Non-profit Organization"], "post_time": "2022-01-17T16:22:42Z", "salary": {"currency": null, "max": null, "min": null, "period": "monthly", "term": null}, "salary_visible": false, "title_keywords": ["admin", "assistant human resources manager"], "responsibilities": ["develop", "policies", "plan", "design"], "requirements": {"degrees": [], "majors": [], "languages": [], "language_level": [], "hard_skills": ["wan"], "soft_skills": [], "languages_combined": []}, "experience_required": {"duration": [], "field": []}}, {"job_id": "100003009052683", "location_code": "hk", "company": "Hong Kong Housing Society", "job_title": "CES - Senior Officer (Elderly Services)", "description": "[Ref: CES-SO(ES)]\n\nThe Job:\n\nAssist in manage the overall operation and administration of the estate-based social support services and Elderly Lounges.\nAssist in service delivery including to enhance the social capital, to deliver counseling and case management, to provide social activities and volunteer services, to provide support to the property management staff, and to visit all tenants in elderly flats and assisted-living flats.\nAssist in coordinating with the Estate Management Offices and Occupational therapists for on-going facility improvement and home modification at respective rental estates.\nAssist in liaising and coordinating with collaborators from planning to implementation of activities, programs and groups to promote home safety, health and social care to meet with various needs of elderly tenants.\nAssist in monitoring site management such as cleaning and maintenance, inventory and procurement, report and statistic, program planning and evaluation.\nHandle daily requests, enquiries and complaints of the elderly tenants and on site coordination between internal and external parties; in case of any emergency, determine prompt action with the contingency plan to ensure safety for the elderly tenants.\nProvide guidance and arrange duties for S4 / O4 to ensure the service quality and standard of estate-based social support services.\nUndertake any other duties as assigned by the direct supervisor deems appropriate.\n\nThe Person:\n\nDiploma holder or above in social work / health science with minimum 3-5 years\u2019 post qualification working experience in recognized welfare organization of elderly service; community services is preferable.\nGood manner, self-motivated and able to work independently.\nSensitive to interpersonal relations with good communication skill.\nGood command of both written and spoken English and Chinese.\nGood PC knowledge and typing skills.\n\nAttractive remuneration package will be offered to suitable candidates. To apply, please submit online application: https://careers.hkhs.com/ or send your application with full resume and reference quoted to Human Resources Manager by fax: 2882 4466.\n\nYou are welcome to visit our website www.hkhs.com to learn more about us.\nApplicants not invited for interview within 8 weeks may consider their applications unsuccessful.\n\nPersonal data provided by job applicants will be used strictly in accordance with the Housing Society\u2019s personal data policies which is available in our website and obtainable upon request. Please refer to the Policy Statement on Employment Related Data under Personal Data (Privacy) Ordinance in our website.", "employment_types": ["Permanent"], "selling_points": ["Administration of the Elderly Lounges", "Deliver counseling and case management", "Diploma holder or above in social work"], "locations": ["Others"], "categories": ["Public / Civil", "Social Services - Community / Non-profit Organization"], "post_time": "2022-01-17T03:41:40Z", "salary": {"currency": null, "max": null, "min": null, "period": "monthly", "term": null}, "salary_visible": false, "title_keywords": ["senior officer"], "responsibilities": ["any other duties", "inventory", "internal and external parties", "quality", "plan", "evaluation", "administration", "service delivery", "implementation", "report", "management", "provide support", "monitoring", "site coordination", "cleaning", "provide guidance", "maintenance", "support services", "site management", "planning"], "requirements": {"degrees": ["diploma holder"], "majors": ["social work", "science"], "languages": ["english", "chinese"], "language_level": ["good command"], "hard_skills": ["pc knowledge", "typing"], "soft_skills": ["self-motivated", "work independently", "communication skill", "sensitive to", "interpersonal"], "languages_combined": [{"language": "english", "language_level": ["good command"]}, {"language": "chinese", "language_level": ["good command"]}]}, "experience_required": {"duration": ["minimum 3-5 years"], "field": []}}, {"job_id": "100003009048384", "location_code": "hk", "company": "Hong Kong Red Cross", "job_title": "Programme Officer (Emergency Health)", "description": "Job Purpose:\n\nThe position is responsible to support the Programme Coordinator (Emergency Health) /PC(EH) on effective implementation of Hong Kong Red Cross Health Emergency Response Unit (HERU) Development Plan, including HERU service promotion, organization of publicity and training events, volunteer management as well as internal system building and administration. Overseas health project management & missions\u2019 coordination will be assigned as required.\n\nKey Responsibilities:\n\nAssist PC(EH) to implement activities of the HERU service including conducting situational analysis, organizing publicity events for professionals, designing promotion campaigns of the HERU service and produce relevant communication materials\nOrganize global and local learning events, online and face-to-face, to build up and maintain competencies of delegates of HERU service for Overseas Missions in emergency situations\nMaintain good relationship with a pool of volunteers from various professions through designing and implementing retention plan and activities\nPromote HERU service through building networks with potential partners and stakeholders including professional bodies, academic organizations, local NGOs and other partners within the Red Cross Movement\nSupport in knowledge management and project management of Overseas Emergency Health (OEH) Team\nSupport in overseas health projects implementation in emergency or non-emergency where required\nUndertake any other duties as assigned by supervisors\n\nRequirements:\n\nUniversity Degree Holder, preferably in communication, development studies, social science and/or any health-related disciplines\nMinimum of 2 years relevant work experience, preferably in humanitarian or social service sector; with 1 year work experience in, Communication, Event Management and/or Health-related disciplines\nGood knowledge on programme management of human and finance resources; good presentation, networking, facilitation and communications skills\nSound experience in volunteer management, events organization and networking\nExperience in building learning pathway, competency management and facilitation of training courses is an asset\nExcellent in both written and spoken English and Chinese (including Putonghua)\nMature, self-motivated, strong sense of responsibility, independent\nAble to work in a multi-disciplinary team and under pressure\nKnowledge of emergency, disaster management or public health is an asset\n\nContract period: 1 year\n\nPlease send application together with full curriculum vitae and expected salary to the Head of Human Resources, Hong Kong Red Cross, 9/F Hong Kong Red Cross Headquarters, 19 Hoi Ting Road, West Kowloon, HK or email by clicking \"APPLY NOW\"\u00a0on or before 30 January 2022.\n\nPersonal data provided by job applicants will be used strictly in accordance with Agency\u2019s data protection policy for recruitment purposes only. Applicants not contacted within 4 weeks may consider their applications unsuccessful and all related information will be kept on our files up to a period of 6 months.", "employment_types": ["Full Time", "Contract"], "selling_points": [], "locations": ["Yau Ma Tei"], "categories": ["Public / Civil", "Social Services - Community / Non-profit Organization"], "post_time": "2022-01-14T06:27:14Z", "salary": {"currency": null, "max": null, "min": null, "period": "monthly", "term": null}, "salary_visible": false, "title_keywords": ["officer"], "responsibilities": ["any other duties", "management", "analysis", "implementation", "maintain good relationship", "communication", "project management", "promotion campaigns", "maintain", "plan", "designing"], "requirements": {"degrees": ["university degree"], "majors": ["related disciplines", "science"], "languages": ["putonghua", "english", "chinese"], "language_level": ["excellent"], "hard_skills": ["red"], "soft_skills": ["self-motivated", "independent", "under pressure", "sense of responsibility", "mature", "communication", "learning", "presentation"], "languages_combined": [{"language": "putonghua", "language_level": []}, {"language": "english", "language_level": ["excellent"]}, {"language": "chinese", "language_level": ["excellent"]}]}, "experience_required": {"duration": ["minimum of 2 years", "1 year"], "field": ["related", "management", "training"]}}, {"job_id": "100003009052299", "location_code": "hk", "company": "Hong Kong Baptist Hospital", "job_title": "Assistant Manager (Supporting Services)", "description": "Degree holder\nMinimum 6 years of post-qualification administrative and supervisory experience, preferably in healthcare industry\nAssist Manager In-charge to manage the daily operation of hospital supporting services e.g. housekeeping service, logistics, linen and uniform management, maintain high professional standards, and responsible for general administration duties\nStrong communication, problem solving and analytical skills\nProficiency in MS Office and data analysis\nExcellent command of written and spoken Chinese and English\nWe offer attractive remuneration package and fringe benefits to the right candidates. Interested parties please apply with full resume and expected salary to Human Resources Department, Hong Kong Baptist Hospital, 18/F, Tower 2, Enterprise Square, 9 Sheung Yuet Road, Kowloon Bay, Kowloon, by email via \"Apply now\"\u00a0 or by fax to 2339 5769 on or before 31 January 2022.\nThe information provided will only be used for recruitment related purposes. All personal information on unsuccessful candidates will be destroyed within 6 months.", "employment_types": ["Full Time", "Permanent"], "selling_points": [], "locations": ["Kowloon City"], "categories": ["Admin & HR", "Administration / Operation Manager", "Medical Services", "Others", "Public / Civil", "Social Services - Community / Non-profit Organization"], "post_time": "2022-01-17T02:46:31Z", "salary": {"currency": null, "max": null, "min": null, "period": "monthly", "term": null}, "salary_visible": false, "title_keywords": ["assistant manager"], "responsibilities": ["management", "housekeeping", "daily operation", "communication", "data analysis", "maintain", "logistics", "administration"], "requirements": {"degrees": ["degree holder"], "majors": [], "languages": ["english", "chinese"], "language_level": ["excellent"], "hard_skills": ["problem solving", "analysis", "ms office", "analytical skills"], "soft_skills": ["communication", "problem solving and analytical skills", "responsible"], "languages_combined": [{"language": "english", "language_level": ["excellent"]}, {"language": "chinese", "language_level": ["excellent"]}]}, "experience_required": {"duration": ["minimum 6 years"], "field": ["healthcare industry", "administrative", "post-qualification", "supervisory experience"]}}, {"job_id": "100003009055534", "location_code": "hk", "company": "Hong Kong Housing Society", "job_title": "Senior Officer (Elderly Services) / Social Worker \u2013 North Point", "description": "[Ref: TTH-SO(ES)]\n\nThe Job:\n\nManage the daily operation in Day Care Center and RCHE, and responsible for planning, organizing and implementing activities.\u00a0\nCollaborate with other colleagues and external units for execution services to customers.\u00a0\nReport the monthly service and financial statistics to supervisor. \u00a0\nAssist to source and contact with local organizations / NGO/ companies for large event programs.\u00a0\nHandle customer requests, enquiries and complaints independently, provide psychosocial support to residents in RCHE and members in DCC.\u00a0\nLiaise with customers and volunteers to ensure smooth service delivery.\u00a0\nCoordinate psychosocial activities and training sessions especially for dementia cases, group activities and mass program in Day Care Centre.\u00a0\nEvaluate the effectiveness of the designed training program.\u00a0\nSupervise HCOII and Personal Care Workers particularly on skills and techniques of leading dementia groups in DCC and RCHE.\u00a0\nAs a mentor leading the new CSR to coordinate activities in DCC and RCHE.\n\nThe Person:\n\nDegree / Associate degree holder in Social Science / Social Work Studies / Counseling.\nRegistered Social Worker is preferable.\nMinimum 3 years solid working experience in recognized welfare organization; elderly service or mental health services preferable.\nGood connection with various service providers and stakeholders in elderly/ mental health services.\nProficient in English, Chinese and Putonghua.\n\nAttractive remuneration package will be offered to suitable candidates. To apply, please submit online application: https://careers.hkhs.com/ or send your application with full resume and reference quoted to Human Resources Manager by fax: 2882 4466.\n\nYou are welcome to visit our website www.hkhs.com to learn more about us.\nApplicants not invited for interview within 8 weeks may consider their applications unsuccessful.\n\nPersonal data provided by job applicants will be used strictly in accordance with the Housing Society\u2019s personal data policies which is available in our website and obtainable upon request. Please refer to the Policy Statement on Employment Related Data under Personal Data (Privacy) Ordinance in our website.", "employment_types": ["Permanent"], "selling_points": ["Manage the daily operation in Day Care Center", "Minimum 3 years solid working experience", "Degree holder in Social Science"], "locations": ["North Point"], "categories": ["Public / Civil", "Social Services - Community / Non-profit Organization"], "post_time": "2022-01-18T02:41:06Z", "salary": {"currency": null, "max": null, "min": null, "period": "monthly", "term": null}, "salary_visible": false, "title_keywords": ["social worker", "senior officer"], "responsibilities": ["collaborate with", "service delivery", "daily operation", "coordinate", "evaluate", "planning", "contact", "customer requests", "liaise with", "report"], "requirements": {"degrees": ["associate degree", "degree"], "majors": ["social work", "science"], "languages": ["putonghua", "english", "chinese"], "language_level": ["proficient"], "hard_skills": [], "soft_skills": [], "languages_combined": [{"language": "putonghua", "language_level": ["proficient"]}, {"language": "english", "language_level": ["proficient"]}, {"language": "chinese", "language_level": ["proficient"]}]}, "experience_required": {"duration": ["minimum 3 years"], "field": []}}, {"job_id": "100003009052654", "location_code": "hk", "company": "Hong Kong Housing Society", "job_title": "Community Services Manager", "description": "[Ref : CES-COMSM]\n\nThe Job\n\nTo assist the Manager (ES) in the execution of social support programmes and review the overall operation and administration of the CES Team at respective estate according to the approved business plans and milestones.\nTo coordinate with Estate Offices and Occupational therapists for on-going facility improvement and home modification at respective estate.\nTo liaise and partner with external parties in the collaborative projects/services at respective estate(s), including but not limited to district social service operators, social enterprises, health service providers, hospitals, educational institutes and governmental departments.\nTo provide professional counseling and case management for needy tenants, expertise timely referrals to social services and closely liaise with NGOs for subsequent follow-up action to prevent crisis.\nTo promote neighborhood support through establishing and developing mutual support networks among tenants and mobilise the volunteer teams in rendering community-building activities at respective estate.\nTo manage the operation of responsible CES cum Elderly Lounge in attaining the designated service outputs and outcomes, and conduct regular home visits and/or telephone concern calls to the needy tenants.\nTo coordinate the working groups of district-based collaborative projects and signature events, including but not limited to the service award ceremonies, festive and thematic carnivals, IT system building and configuration, media interviews and renovation projects.\nTo supervise and coach the subordinates to assure the quality of services, and manage the team in effective and efficient manner.\nTo undertake any other duties as assigned by the direct supervisor deems appropriate.\n\nThe Person\n\nMinimum 5 years\u2019 post qualification working experience in recognized welfare organization of elderly service; community services preferable.\nWith administrative and supervisory experience.\nPrevious in-charge-of community health program, elderly care projects preferable.\nGood connection with NGOs, social enterprises and other stakeholders in social services.\nSelf-starter with ability to excel in a changing community environment.\nStrong team player, mature and able to conduct evidence-based study.\nMotivated with strategic mindset in service development.\nExcellent communication, presentation and interpersonal skills.\nGood command of English, Putonghua and Cantonese.\n\nAttractive remuneration package will be offered to suitable candidates. To apply, please submit online application: https://careers.hkhs.com/ or send your application with full resume and reference quoted to Human Resources Manager by fax: 2882 4466.\n\nYou are welcome to visit our website www.hkhs.com to learn more about us.\nApplicants not invited for interview within 8 weeks may consider their applications unsuccessful.\n\nPersonal data provided by job applicants will be used strictly in accordance with the Housing Society\u2019s personal data policies which is available in our website and obtainable upon request. Please refer to the Policy Statement on Employment Related Data under Personal Data (Privacy) Ordinance in our website.", "employment_types": ["Permanent"], "selling_points": ["Execution of social support programmes", "Experience in welfare org. of elderly service", "Previous in-charge-of community health program"], "locations": ["Others"], "categories": ["Public / Civil", "Social Services - Community / Non-profit Organization"], "post_time": "2022-01-17T03:39:01Z", "salary": {"currency": null, "max": null, "min": null, "period": "monthly", "term": null}, "salary_visible": false, "title_keywords": ["community services manager"], "responsibilities": ["liaise", "any other duties", "management", "configuration", "review", "coordinate with", "external parties", "business plans", "developing", "teams", "coordinate", "renovation", "quality", "liaise with", "administration"], "requirements": {"degrees": [], "majors": [], "languages": ["cantonese", "putonghua", "english"], "language_level": ["good command"], "hard_skills": ["excel"], "soft_skills": ["mature", "communication", "motivated", "interpersonal skills", "team player", "presentation"], "languages_combined": [{"language": "cantonese", "language_level": ["good command"]}, {"language": "putonghua", "language_level": ["good command"]}, {"language": "english", "language_level": ["good command"]}]}, "experience_required": {"duration": ["minimum 5 years"], "field": ["administrative", "supervisory experience"]}}, {"job_id": "100003009051953", "location_code": "hk", "company": "St. James' Settlement", "job_title": "Human Resources Assistant (Contract)\u3008Ref: HR/06122\u3009", "description": "Requirement:\n\nDiploma or above\nHKCEE/HKDSE 5 passes (incl. English Language (Syl. B) and Chinese Language at grade E / Level 2 or above) or equivalent\nHands-on experience and knowledge of HR system is an advantage\nGood command of written & spoken English and Chinese\nProficient in MS Office applications\nGood interpersonal and communication skills\nDetail-minded, high accuracy in work and well-organized\n\nJob Duties:\n\nResponsible for general HR functions\nProvide clerical support as assigned by supervisors\nAssist in other ad hoc projects\n\nInterested persons please apply with full resume via \u201cAPPLY NOW\u201d on or before 28/01/2022.", "employment_types": ["Full Time", "Contract"], "selling_points": ["Diploma or above", "Proficient in MS Office applications", "Detail-minded, high accuracy in work"], "locations": ["Wan Chai"], "categories": ["Admin & HR", "Clerical / Admin Staff", "Public / Civil", "Social Services - Community / Non-profit Organization"], "post_time": "2022-01-17T01:37:31Z", "salary": {"currency": null, "max": null, "min": null, "period": "monthly", "term": null}, "salary_visible": false, "title_keywords": ["hr", "human resources assistant"], "responsibilities": ["provide clerical support", "hr", "ad hoc projects"], "requirements": {"degrees": ["hkdse", "diploma or above"], "majors": [], "languages": ["english", "chinese"], "language_level": ["good command"], "hard_skills": ["ms office"], "soft_skills": ["detail-minded", "communication skills", "well-organized", "hands-on", "interpersonal"], "languages_combined": [{"language": "english", "language_level": ["good command"]}, {"language": "chinese", "language_level": ["good command"]}]}, "experience_required": {"duration": [], "field": ["hr"]}}, {"job_id": "100003009048592", "location_code": "hk", "company": "Greeners Action", "job_title": "Senior Enviornment Project Officer", "description": "To plan, create, implement and review different environmental projects, social campaigns\nTo manage and coordinate environmental campaigns, educational and promotional activities, conduct progress and finical report\nHandle daily operation of the food donation programs including public enquiries, report writing, tender preparation etc.\nCoordinate with internal departments and outside parties for the operations such as vendors, food suppliers, helper / volunteers and logistics of the projects;\nTo research and develop data base, coordinate questionnaire survey and organize researched data. General administrative, office works etc.\nOther relevant duties and ad hoc projects as required by the Company.\n\nRequirements:\n\n5 years or more solid working experience on Project coordination / Environmental protection / Social Policy advocacy.\nAble to plan, create, coordinate environment events and projects, volunteer activities. Worked in Green Group or other Charity are definite advantage;\nCommit to the mission of Greeners Action. Enthusiastic environmental protection. Hard Working.\nWork independently with minimum supervisor, strong initiative, mature, committed to work and have a strong sense of responsibility\nAble to work in community.\nGood oral and written communication skills in both Chinese and English\nGood interpersonal, communication, presentation and public speaking skills;\nProficient in internet, Windows Office (Excel, PowerPoint & Word)\nAble to work in Sat/Sun & Public Holidays\nImmediate available would be an advantage", "employment_types": ["Full Time", "Permanent"], "selling_points": ["Environmental Management", "Plan, implement, review environmental projects", "To manage and coordinate social campaigns"], "locations": ["Kwai Tsing Area"], "categories": ["Media & Advertising", "Editorial / Journalism", "Sciences, Lab, R&D", "Environmental Science / Waste Management", "Public / Civil", "Social Services - Community / Non-profit Organization"], "post_time": "2022-01-14T06:52:06Z", "salary": {"currency": null, "max": null, "min": null, "period": "monthly", "term": null}, "salary_visible": false, "title_keywords": ["project officer"], "responsibilities": ["sat", "questionnaire", "project coordination", "data", "operations", "review", "daily operation", "coordinate with", "develop", "coordinate", "communication", "promotional activities", "logistics", "plan", "tender preparation", "ad hoc projects", "report"], "requirements": {"degrees": [], "majors": [], "languages": ["english", "chinese"], "language_level": ["good"], "hard_skills": ["excel", "word", "powerpoint", "charity"], "soft_skills": ["communication skills", "work independently", "oral", "sense of responsibility", "hard working", "presentation", "mature", "communication", "committed", "coordination", "enthusiastic", "interpersonal", "initiative"], "languages_combined": [{"language": "english", "language_level": ["good"]}, {"language": "chinese", "language_level": ["good"]}]}, "experience_required": {"duration": ["5 years"], "field": ["environmental"]}}, {"job_id": "100003009052140", "location_code": "hk", "company": "Haven of Hope Christian Service", "job_title": "\u6d3b\u52d5\u7d71\u7c4c\u54e1 / \u6d3b\u52d5\u5de5\u4f5c\u54e1 (\u7de8\u865f : DECS/PW/JDB)", "description": "\u9999\u6e2f\u4e2d\u5b78\u6587\u6191\u8003\u8a66\u6216\u9999\u6e2f\u4e2d\u5b78\u6703\u8003\u4e94\u79d1\u8003\u7372\u7b2c2\u7d1a\uff0f\u9054\u6a19\u6216\u4ee5\u4e0a\uff08\u5305\u62ec\u4e2d\u3001\u82f1\u6587\u79d1(\u8ab2\u7a0b\u4e59)\uff09\n\u8ca0\u8cac\u7c4c\u8fa6\u53ca\u63a8\u884c\u9577\u8005\u4e2d\u5fc3\u6d3b\u52d5\u53ca\u5e36\u9818\u5c0f\u7d44\n\u9700\u5916\u52e4\u5de5\u4f5c\uff0c\u4f8b\u5982\u8857\u7ad9\u3001\u63a2\u8a2a\u9577\u8005\n\u5177\u9577\u8005\u670d\u52d9\u7d93\u9a57\u6216\u7fa9\u5de5\u7d93\u9a57\u8005\u512a\u5148\u8003\u616e\n\n\u6709\u610f\u8005\u8acb\u65bc\u4e8c\u96f6\u4e8c\u4e8c\u5e74\u4e8c\u6708\u4e94\u65e5\u524d\u89aa\u7e55\u5c65\u6b77\u53ca\u671f\u671b\u5f85\u9047\uff08\u8acb\u65bc\u4fe1\u5c01\u9762\u53ca\u4fe1\u5167\u8a3b\u660e\u7533\u8acb\u8077\u4f4d\u7de8\u865f\uff09\u5bc4\u65b0\u754c\u5c07\u8ecd\u6fb3\u9748\u5be6\u8def\u4e03\u865f\u57fa\u7763\u6559\u9748\u5be6\u5354\u6703\u4eba\u529b\u8cc7\u6e90\u90e8\u6536\uff0c\u6216\u96fb\u90f5\u81f3Apply Now\uff0c\u6216\u767c\u9001\u81f3Whatsapp\u865f\u78bc6507 8148\uff08\u6a19\u984c\u8acb\u8a3b\u660e\u8077\u4f4d\u7de8\u865f\uff09\u3002\u5982\u4e00\u500b\u6708\u5167\u672a\u7372\u901a\u77e5\u7d04\u898b\uff0c\u5247\u4f5c\u843d\u9078\u8ad6\u3002\n\u67e5\u8a62\u71b1\u7dda\uff1a2703 3227 (\u96fb\u8a71)\uff1b6507 8148 (Whatsapp)\u3002\n\u6709\u95dc\u672c\u6703\u8a73\u60c5\uff0c\u8acb\u700f\u89bd\u7db2\u9801http://www.hohcs.org.hk\n\n(\u53ef\u80fd\u7372\u8058\u4eba\u58eb\uff08\u5982\u5f9e\u4e8b\u8207\u5152\u7ae5\u6216\u7cbe\u795e\u4e0a\u7121\u884c\u70ba\u80fd\u529b\u4eba\u58eb\u6709\u95dc\u5de5\u4f5c\u8077\u4f4d\uff09\u9808\u65bc\u5165\u8077\u524d\u9032\u884c\uff0f\u63d0\u4ea4\u6027\u7f6a\u884c\u5b9a\u7f6a\u7d00\u9304\u67e5\u6838\u3002\u7533\u8acb\u4eba\u6240\u63d0\u4f9b\u7684\u8cc7\u6599\u5c07\u4e88\u4fdd\u5bc6\u53ca\u4f5c\u62db\u8058\u6709\u95dc\u8077\u4f4d\u7528\u9014)\n\n\u672a\u7d93\u672c\u5354\u6703\u66f8\u9762\u540c\u610f\uff0c\u4ee5\u4e0a\u62db\u8058\u5ee3\u544a\u5168\u90e8\u6216\u90e8\u5206\u5167\u5bb9\u5747\u4e0d\u5f97\u8907\u88fd\u81f3\u5176\u4ed6\u62db\u8058\u7db2\u7ad9\u3002", "employment_types": ["Full Time"], "selling_points": [], "locations": ["Not Specified"], "categories": ["Marketing / Public Relations", "Public Relations - Event Management", "Public / Civil", "Social Services - Community / Non-profit Organization", "Others"], "post_time": "2022-01-17T02:14:38Z", "salary": {"currency": null, "max": null, "min": null, "period": "monthly", "term": null}, "salary_visible": false, "title_keywords": ["\u6d3b\u52d5\u7d71\u7c4c\u54e1", "\u6d3b\u52d5\u5de5\u4f5c\u54e1"], "responsibilities": [], "requirements": {"degrees": [], "majors": [], "languages": [], "language_level": [], "hard_skills": ["whatsapp"], "soft_skills": [], "languages_combined": []}, "experience_required": {"duration": [], "field": []}}, {"job_id": "100003009052853", "location_code": "hk", "company": "The Hongkong Electric Co., Ltd.", "job_title": "Community Business Executive / Customer Business Support Executive (Ref: CS-CBD-CBE-JD)", "description": "Responsibilities:\n\nReporting to the Community Business & Engagement Manager or Customer Business Support Manager, the appointees will mainly perform the following responsibilities:\n\n\nTo assist the Managers to implement the Smart Power Care Fund and Smart Power Services by establishing relationship with the NGOs or relevant stakeholders as well as organising engagement and publicity activities\nTo handle the administration work in relation to funding applications, from vetting to issuing the subsidy\nTo carry out tender enquiries for the supply of electrical appliances under the funding scheme\nTo handle Smart Power Services hotline and maintain a database for reporting and auditing purposes\n\nRequirements:\n\n\n\nBachelor Degree in Business Administration, Social Work or related disciplines\nA minimum of 3 years\u2019 relevant work experience, preferably in customer services, stakeholder engagement, community communication or community campaign administration\nGood PC skill and knowledge of MS Office including Powerpoint, Excel and Word. Knowledge of MS SharePoint or data analytics solution an advantage\nGood command of English and Chinese (including Mandarin) languages, both spoken and written\n\nWorking Location: North Point\n\nApplication:\n\nIf you are interested in this position, please send your resume\u00a0(in PDF format)\u00a0with details of qualification, experience, present and expected salary, and contact number to the\u00a0Human Resources Division, The Hongkong Electric Co., Ltd. on or before\u00a031 January 2022\u00a0and quote the reference number in your application. Please also visit our website to know more about our Company http://www.hkelectric.com.\n\nApplicants not invited for interview within\u00a0one month from the closing date may consider their applications unsuccessful. All unsuccessful applications will be kept for\u00a0six months after the date of this advertisement.\n\nWe are an equal opportunity employer.\u00a0 Personal data provided by job applicants will be treated in strictest confidence and used only for recruitment-related purposes in accordance with the laws and ordinance of the HKSAR.", "employment_types": ["Full Time", "Permanent"], "selling_points": ["To assist the Managers to implement the Care Fund", "Bachelor Degree in Business Administration", "A minimum of 3 years\u2019 relevant work experience"], "locations": ["North Point"], "categories": ["Sales, CS & Business Devpt", "Business Development", "Public / Civil", "Social Services - Community / Non-profit Organization", "Sales Administration"], "post_time": "2022-01-17T04:17:02Z", "salary": {"currency": null, "max": null, "min": null, "period": "monthly", "term": null}, "salary_visible": false, "title_keywords": ["business executive", "executive"], "responsibilities": ["reporting", "maintain", "database", "tender", "auditing", "administration"], "requirements": {"degrees": ["degree", "bachelor"], "majors": ["social work", "related disciplines", "business administration"], "languages": ["english", "chinese", "mandarin"], "language_level": ["good command"], "hard_skills": ["excel", "data analytics", "word", "powerpoint", "pc skill", "ms office"], "soft_skills": ["communication", "interested in", "confidence"], "languages_combined": [{"language": "english", "language_level": ["good command"]}, {"language": "chinese", "language_level": ["good command"]}, {"language": "mandarin", "language_level": ["good command"]}]}, "experience_required": {"duration": ["minimum of 3 years"], "field": ["administration", "human resources", "customer services"]}}, {"job_id": "100003009051901", "location_code": "hk", "company": "Senior Citizen Home Safety Association", "job_title": "Assistant Manager, Workshop & Training", "description": "Responsibilities:\n\nSupervise a small team\nDevelop and arrange different in-house training programs/workshops for our users and external participants in according to their needs\nLiaise with various stakeholders, such as private or public companies, schools, tutors, and vendors\nManage active aging services and carer support services, reach out target service recipients in the community through diversified trainings and programs\nPrepare reports, budget, operation plans and analysis for services development\n\nQualifications:\n\nMore than 5yrs experience with at least 2 years in supervisory level\nHigher Diploma / Associate degree holder or above in Social Work or related disciplines\nConduct training experience and/or with medical background is in advantage\nPrevious working experience in NGO setting is an asset but not a must\nWell organized, active, good interpersonal skills and manner\nGood command of written & spoken English and Chinese\n\nInterested parties please send your full CV with expected salary, date available and contact number via clicking \"Apply Now\"\u00a0(please state the position applied)\n\nInformation provided will only be used for the purpose of recruitment and selection within the Association and treated in strictly confidential. Only short-listed candidates will be contacted.", "employment_types": ["Full Time", "Permanent"], "selling_points": [], "locations": ["Kowloon City Area"], "categories": ["Admin & HR", "Training & Development", "Public / Civil", "Social Services - Community / Non-profit Organization", "Others"], "post_time": "2022-01-17T01:28:54Z", "salary": {"currency": null, "max": null, "min": null, "period": "monthly", "term": null}, "salary_visible": false, "title_keywords": ["assistant manager,"], "responsibilities": ["prepare reports", "analysis", "support services", "budget", "develop", "liaise with", "plans"], "requirements": {"degrees": ["associate degree", "diploma"], "majors": ["social work", "related disciplines"], "languages": ["english", "chinese"], "language_level": ["good command"], "hard_skills": ["small", "workshops", "analysis"], "soft_skills": ["active", "well organized", "interpersonal skills"], "languages_combined": [{"language": "english", "language_level": ["good command"]}, {"language": "chinese", "language_level": ["good command"]}]}, "experience_required": {"duration": ["at least 2 years"], "field": ["supervisory level", "training", "medical"]}}, {"job_id": "100003009053643", "location_code": "hk", "company": "Vineberg Property Management Limited", "job_title": "\u5ba2\u6236\u670d\u52d9\u52a9\u7406 (12\u5c0f\u6642) (\u65e9/\u591c\u8f2a\u66f4)**", "description": "\n\u8077\u8cac :\u5c07\u8ecd\u6fb3\u4f4f\u5b85\u5c4b\u82d1\u4e00\u822c\u4fdd\u5b89\u5de5\u4f5c\u3001\u5de1\u908f\u53ca\u8a2a\u5ba2\u767b\u8a18\n\n\u8cc7\u6b77 :\u5c0f\u4e00\u7a0b\u5ea6; \u826f\u597d\u7cb5\u8a9e; \u61c2\u8b80\u5beb\u4e2d\u6587; \u6301\u6709\u4fdd\u5b89\u57f9\u8a13\u8ab2\u7a0b\u8b49\u66f8(QAS); \u6301\u6709\u4fdd\u5b89\u4eba\u54e1\u8a31\u53ef\u8b49\n\n\u5f85\u9047 :\u6bcf\u6708$15,000 - $18,000, \u6709\u6bcf\u6708\u734e\u8cde$1400, \u751f\u65e5\u5047 \u53ca\u91ab\u7642\u798f\u5229, \u4e0a\u53487\u6642\u534a\u81f3\u4e0b\u53487\u6642\u534a\u6216\u4e0b\u53487\u6642\u534a\u81f3\u4e0a\u53487\u6642\u534a, \u6bcf\u9031\u5de5\u4f5c6\u5929,\u8f2a\u73ed,\u8f2a\u4f11, \u6bcf\u5929\u5de5\u4f5c 12 \u5c0f\u6642\n\n\u7533\u8acb\u9808\u77e5 :\u6c42\u8077\u8005\u53ef\u81f4\u96fb22074388\u8207\u842c\u5bf6\u7269\u696d\u7ba1\u7406\u6709\u9650\u516c\u53f8\u7a0b\u5148\u751f\u806f\u7d61\u3002\n\n", "employment_types": ["Full Time"], "selling_points": [], "locations": ["Tseung Kwan O"], "categories": ["Public / Civil", "Social Services - Community / Non-profit Organization", "Others", "Others"], "post_time": "2022-01-17T07:16:55Z", "salary": {"currency": null, "max": null, "min": null, "period": "monthly", "term": null}, "salary_visible": false, "title_keywords": ["\u5ba2\u6236\u670d\u52d9\u52a9\u7406"], "responsibilities": [], "requirements": {"degrees": [], "majors": [], "languages": [], "language_level": [], "hard_skills": [], "soft_skills": [], "languages_combined": []}, "experience_required": {"duration": [], "field": []}}, {"job_id": "100003009052392", "location_code": "hk", "company": "Tung Wah Group of Hospitals", "job_title": "Human Resources Executive Assistant (Human Resources Development) (REF: A3/HREA/HRD/JOBS)", "description": "Location: Sheung Wan\nRoles & responsibilities:\nCollect and collate data/statistics/HR information for various pay trend and base pay structure reviews in relation to the market driven pay system with liaison and communication with different internal and external parties;\ndeliver administration support for various HR functions and activities including staff recruitment and appointment exercises, inputting/checking of Human Resources Information System entries and other assigned job tasks and ad hoc projects;\nupdate and upkeep the proper records of the administration guidelines and pay tables of pay structures of Administration Headquarters and Social Enterprises;\ndeliver administration support for review of the human resources policies;\nprovide support for the marketing activities to promote TWGHs\u2019 employer brand image;\nmanage the operational details of the Staff Performance Management System and e-Appraisal System including the system development, checking of the data input and updating of the relevant forms/guidelines; and\nassist in general office duties as well as handle ad hoc projects.\nThe ideal candidate should possess:\nHigher Diploma/Associate Degree preferably in Human Resources Management;\npreferably experience in remuneration and benefit administration and marketing administration;\nproficiency in MS Excel and good sense of IT knowledge; and\nability to handle graphic design and figurative work.\n(Please specify in the resume or application form the relevant qualifications/working experience you have attained in detail.)\nCompensation & employment terms:\nThe successful candidate will initially be offered a 2-year contract with a remuneration package which will be commensurate with his/her background and experience.\u00a0 The continuation of employment and employment terms thereafter will be subject to mutual agreement.\u00a0 Apart from contributions to the MPF Scheme, other benefits include paid annual leave, medical services, a dental scheme and training sponsorships.\u00a0 The incumbent will normally work under a 5-day week schedule subject to operational needs and exigencies of the service.\nApplication:\nPlease send your resume or a completed application form [F601(n)] with indication of your current and expected salaries to the Head of Human Resources Division, Tung Wah Group of Hospitals at 4/F., Wong Fung Ling Memorial Building, 12 Po Yan Street, Hong Kong by 31 January 2022.\u00a0 Application forms are obtainable in person or can be downloaded from http://www.tungwah.org.hk.\u00a0 \u00a0The reference code should be marked both in the letter and on the envelope. \u00a0Underpaid mail items will not be accepted by Tung\u00a0Wah.\u00a0 For proper delivery of your mail items, please ensure your mail items bear sufficient postage with return address before posting.\u00a0 Personal data provided by applicants will be used strictly for recruitment purpose only and in accordance with the Tung\u00a0Wah\u2019s personal data policy.\u00a0 Applicants not invited to attend an interview by 30\u00a0April 2022 may assume that their applications are unsuccessful.\nWE ARE AN EQUAL OPPORTUNITIES EMPLOYER", "employment_types": ["Full Time", "Contract"], "selling_points": [], "locations": ["Sheung Wan"], "categories": ["Admin & HR", "Clerical / Admin Staff", "Personal / Executive Assistant", "Public / Civil", "Social Services - Community / Non-profit Organization"], "post_time": "2022-01-17T02:56:04Z", "salary": {"currency": null, "max": null, "min": null, "period": "monthly", "term": null}, "salary_visible": false, "title_keywords": ["human resources", "assistant", "human resources executive"], "responsibilities": ["provide support", "management", "data", "guidelines", "policies", "hr", "internal and external parties", "review", "checking", "data input", "graphic design", "communication", "recruitment", "ad hoc projects", "administration"], "requirements": {"degrees": ["associate degree", "diploma"], "majors": [], "languages": [], "language_level": [], "hard_skills": ["ms excel", "wan", "information system", "it knowledge"], "soft_skills": ["communication", "driven", "ideal"], "languages_combined": []}, "experience_required": {"duration": ["2-year"], "field": ["marketing", "administration"]}}, {"job_id": "100003009052631", "location_code": "hk", "company": "Hong Kong Housing Society", "job_title": "Assistant Manager (Elderly Services) / Social Worker - Tseung Kwan O", "description": "[Ref: JL-AM(ES)]\n\n\nThe Job\n\nProvide professional counseling to residents and service users in SEN Jolly Place.\nSupervise CSRs and to coordinate the daily operation of the club house include administrative work.\nMake timely referrals to community service centers or related organizations for early treatment and to closely liaise with NGOs for follow up to prevent from further deterioration.\nPartner with nursing staffs / property management to conduct timely home visits or hospital visitations for all residents.\nOrganize and implement programmes, functions and activities for residents, club members and service users during regular intervals and especially on festive dates.\nOrganize health check programmes for the tenants annually.\nAct as a communication bridge between residents and property management staffs.\nCoordinate the concierge service to provide the backup support to frontline staffs to handle tenants and related service users\u2018 enquiries and complaints.\nHolding the tenants meeting once every two months and prepare the agenda and meetings.\nEmergency support and services arrangement for tenants.\n\nThe Person\n\nDegree holder in social work or related healthcare areas.\nA minimum of 5 years of working experiences in elderly services or related sector.\nPossessed management experience and social worker qualification will be an advantage.\nDemonstrate a balance of business acumen and social conscience.\nGood organization, communication and interpersonal skills.\nFluent spoken English, Cantonese and good written English and Chinese.\nGood computer knowledge and skills.\n\nAttractive remuneration package will be offered to suitable candidates. To apply, please submit online application: https://careers.hkhs.com/ or send your application with full resume and reference quoted to Human Resources Manager by fax: 2882 4466.\n\nYou are welcome to visit our website www.hkhs.com to learn more about us.\nApplicants not invited for interview within 8 weeks may consider their applications unsuccessful.\n\nPersonal data provided by job applicants will be used strictly in accordance with the Housing Society\u2019s personal data policies which is available in our website and obtainable upon request. Please refer to the Policy Statement on Employment Related Data under Personal Data (Privacy) Ordinance in our website.", "employment_types": ["Permanent"], "selling_points": ["Provide professional counseling to residents", "5 years of experiences in elderly services sector", "Management exp. and social worker qualification"], "locations": ["Tseung Kwan O"], "categories": ["Public / Civil", "Social Services - Community / Non-profit Organization"], "post_time": "2022-01-17T03:36:17Z", "salary": {"currency": null, "max": null, "min": null, "period": "monthly", "term": null}, "salary_visible": false, "title_keywords": ["social worker", "assistant manager"], "responsibilities": ["management", "administrative work", "daily operation", "coordinate", "communication", "liaise with"], "requirements": {"degrees": ["degree holder"], "majors": ["social work"], "languages": ["cantonese", "english", "chinese"], "language_level": ["good", "fluent"], "hard_skills": ["acumen"], "soft_skills": ["business acumen", "communication and interpersonal skills"], "languages_combined": [{"language": "cantonese", "language_level": ["fluent"]}, {"language": "english", "language_level": ["good", "fluent"]}, {"language": "chinese", "language_level": ["good", "fluent"]}]}, "experience_required": {"duration": ["minimum of 5 years"], "field": ["related", "management"]}}, {"job_id": "100003009046447", "location_code": "hk", "company": "BlessVision Foundation Limited", "job_title": "Project Officer (marketing & fundraising)", "description": "BlessVision Foundation is a registered charitable organization in HK. We based on Christian values to provide charitable works, life education and humanitarian care. Through media productions, to spread Jesus\u2019 love and support to those are vulnerable from different nationalities. To promote human wellness in body, mind, society and spirit levels.To cope with our continued growth, we are looking for a right candidate to join us.\n\nResponsibilities:\n\n\nProject coordination to initiate collaboration opportunities with different corporate partners/ organizations, to support and liaise with concerned parties and community caring programs.\nTo prepare fundraising proposals, applications, design programs and run campaigns for caring programs/sponsorship support.\nPlan, budget and draft proposal, monitor progress & prepare reports for media and caring projects.\nPrepare and draft educational and promotional materials, e.g. exhibition, movie, leaflet, Facebook / Instagram post, website content etc.\nPerform copywriting of communications and publicity materials including social media content, press invitations, press releases, event speeches, media editorials, websites etc.\nRequirements:\n\n\nTertiary qualifications or above (Journalism / Communications / Marketing / Event management is preferred) with minimum 2 years relevant working experience\nExcellent command of written English and Chinese; fluent in spoken English, Cantonese and Putonghua preferred.\nCheerful personality with excellent interpersonal skills and customer service skills \u2013 able to interact with all different kinds of people\nProficient in online marketing strategies and marketing channels\nProject organizing experience - strong skills on project planning, financing, implementation and evaluation is preferred\nProficient in MS applications, Google-powered business tools (email, calendar, docs), Chinese Word processing, Photoshop etc.\nMultitasking and analytical skills\nCan work under pressure and capable to handle ad-hoc matters\nOut-door work is necessary\nWith caring heart by Jesus\u2019 love\nStrong commitment to the mission, vision and values of BlessVision Foundation\nInterest parties please email your full resume with present & expected salary and state the date of availability.", "employment_types": ["Full Time"], "selling_points": ["Marketing and fundraising strategies", "Project coordination with corporate parties", "With caring heart by Jesus\u2019 love"], "locations": ["Ngau Tau Kok"], "categories": ["Media & Advertising", "Strategic Planning", "Marketing / Public Relations", "Marketing - General / Support", "Public / Civil", "Social Services - Community / Non-profit Organization"], "post_time": "2022-01-14T06:25:46Z", "salary": {"currency": null, "max": null, "min": null, "period": "monthly", "term": null}, "salary_visible": false, "title_keywords": ["project officer"], "responsibilities": ["prepare reports", "project coordination", "monitor progress", "budget", "leaflet", "website", "design", "promotional materials", "social media content", "plan", "liaise with", "facebook"], "requirements": {"degrees": [], "majors": [], "languages": ["cantonese", "putonghua", "english", "chinese"], "language_level": ["proficient", "excellent", "fluent"], "hard_skills": ["chinese word processing", "ms applications", "analytical skills", "photoshop"], "soft_skills": ["customer service skills", "cheerful", "capable", "analytical skills", "interpersonal skills", "work under pressure"], "languages_combined": [{"language": "cantonese", "language_level": ["fluent"]}, {"language": "putonghua", "language_level": ["fluent"]}, {"language": "english", "language_level": ["excellent", "fluent"]}, {"language": "chinese", "language_level": ["proficient", "excellent"]}]}, "experience_required": {"duration": ["minimum 2 years"], "field": ["management", "financing", "relevant working experience", "marketing", "planning"]}}, {"job_id": "100003009052042", "location_code": "hk", "company": "Hong Kong Red Cross", "job_title": "\u8cc7\u6e90\u767c\u5c55\u5927\u4f7f (\u62db\u52df\u300c\u7d05\u5341\u5b57\u4e4b\u53cb\u300d\u6bcf\u6708\u5b9a\u671f\u6350\u6b3e\u8005)", "description": "\u8077\u8cac\uff1a\n\n\u8ca0\u8cac\u65bc\u793e\u5340\u6216\u5546\u5834\u5411\u5e02\u6c11\u8b1b\u89e3\u7d05\u5341\u5b57\u6703\u4e4b\u670d\u52d9\n\u5354\u52a9\u63a8\u5c55\u300c\u7d05\u5341\u5b57\u4e4b\u53cb\u300d\u8a08\u5283\u53ca\u62db\u52df\u6bcf\u6708\u6350\u6b3e\u8005\n\n\u5de5\u4f5c\u8981\u6c42\uff1a\n\n\u6703\u8003/ \u4e2d\u5b78\u6587\u6191\u8a66\u7a0b\u5ea6\u540c\u7b49\u6216\u4ee5\u4e0a\u5b78\u6b77\n\u6709\u6236\u5916\u92b7\u552e\u5de5\u4f5c\u7d93\u9a57\u8005\u512a\u5148\u8003\u616e\n\u6709\u826f\u597d\u6e9d\u901a\u53ca\u8868\u9054\u80fd\u529b\n\u8a8d\u540c\u9999\u6e2f\u7d05\u5341\u5b57\u6703\u4eba\u9053\u670d\u52d9\u7406\u5ff5\uff0c\u5c0d\u670d\u52d9\u793e\u6703\u5145\u6eff\u71b1\u8aa0\n\u4e3b\u52d5\u7a4d\u6975\u3001\u8aa0\u61c7\u6709\u79ae\u53ca\u6709\u8cac\u4efb\u611f\n\u71b1\u611b\u5718\u968a\u5de5\u4f5c\u53ca\u5177\u6b63\u9762\u7684\u5de5\u4f5c\u614b\u5ea6\n\n\u798f\u5229\uff1a\n\n\u6bcf\u9031\u5de5\u4f5c44\u5c0f\u6642 (5\u5929) \uff0c\u516c\u773e\u5047\u671f\u4f11\u606f\n\u8868\u73fe\u734e\u52f5\u91d1\n\u5341\u56db\u5929\u6709\u85aa\u5e74\u5047\u53ca\u95dc\u5fc3\u5047\u4e00\u5929\u3001\u5a5a\u5047\u3001\u4f8d\u7522\u5047\u3001\u6069\u6064\u5047\n\u63d0\u4f9b\u5916\u5c55\u6d25\u8cbc\u3001\u91ab\u7642\u6d25\u8cbc\u3001\u9032\u4fee\u6d25\u8cbc\n\u5728\u8077\u57f9\u8a13\u53ca\u826f\u597d\u6649\u5347\u6a5f\u6703\n\n\u7533\u8acb\u8fa6\u6cd5\uff1a\u8acb\u5c07\u5c65\u6b77\u53ca\u53ef\u5230\u8077\u65e5\u671f\u65bc2022\u5e741\u670830\u65e5\u6216\u4e4b\u524d\u5bc4\u9999\u6e2f\u897f\u4e5d\u9f8d\u6d77\u5ead\u905319\u865f9\u6a13\u9999\u6e2f\u7d05\u5341\u5b57\u6703\u7e3d\u90e8\u4eba\u529b\u8cc7\u6e90\u4e3b\u7ba1\u6536\uff0c\u6216\u96fb\u90f5\u8acb\u6309\"APPLY NOW\"\u3002(\u4fe1\u5c01\u9762\u8acb\u8a3b\u660e\u7533\u8acb\u8077\u4f4d)\n\n\u7533\u8acb\u8005\u4ea6\u53ef\u900f\u904eWhatsapp 9847 3799\u67e5\u8a62\u3002\n\n\uff08\u7533\u8acb\u4eba\u6240\u63d0\u4f9b\u7684\u8cc7\u6599\u5c07\u4e88\u4ee5\u4fdd\u5bc6\u53ca\u53ea\u4f5c\u6709\u95dc\u62db\u8058\u7528\u9014\uff0c\u4e26\u5c07\u65bc\u8077\u4f4d\u9074\u9078\u5b8c\u7562\u516d\u500b\u6708\u5167\u92b7\u6bc1\uff1b\u7533\u8acb\u4eba\u5982\u65bc\u56db\u500b\u661f\u671f\u5167\u4ecd\u672a\u63a5\u7372\u7d04\u898b\u901a\u77e5\uff0c\u53ef\u8996\u4f5c\u4e0d\u5408\u8ad6\u3002\uff09", "employment_types": ["Full Time", "Contract"], "selling_points": [], "locations": ["Yau Ma Tei"], "categories": ["Public / Civil", "Social Services - Community / Non-profit Organization", "Sales, CS & Business Devpt", "Direct Sales"], "post_time": "2022-01-17T01:55:31Z", "salary": {"currency": null, "max": null, "min": null, "period": "monthly", "term": null}, "salary_visible": false, "title_keywords": ["\u8cc7\u6e90\u767c\u5c55\u5927\u4f7f"], "responsibilities": [], "requirements": {"degrees": [], "majors": [], "languages": [], "language_level": [], "hard_skills": [], "soft_skills": [], "languages_combined": []}, "experience_required": {"duration": [], "field": []}}, {"job_id": "100003009049194", "location_code": "hk", "company": "Urban Renewal Authority", "job_title": "Manager, Community Development (Ref. M(CD))", "description": "Responsibilities:\n\nTo assist in developing work and programmes to accomplish the objectives, to foster the continuous local community support and facilitate the smooth implementation of various urban renewal initiatives\nTo establish liaison network and build rapport with different stakeholders affected by the Authority\u2019s redevelopment projects\nTo coordinate work programmes and action plans, including preparing publication for stakeholder communication, and assist in executing the programmes and plans\nTo monitor closely the development of local political dynamics as well as to provide feedback of views and suggestions of the local community for strategy and planning considerations\nTo assist in preparing for District Council meetings, and to attend them as required\nTo assist in training the community development team members and other front-line staff members for community engagement skills and knowledge\n\nRequirements:\n\nDegree holder in public administration, communication or related fields\nMinimum 8 years\u2019 full-time experience in community engagement or district administration\nWork experience related to urban renewal, housing policies or political parties is an advantage\nProven track record in implementing community engagement or public consultation programmes\nOutgoing, self-motivated and innovative in approaching problems and challenges at work\nFluent oral and written communication skills in English and Chinese, as well as fluent Putonghua\n\nFor more information on the work of the URA, please visit the website at http://www.ura.org.hk.\n\nFull resume with present and expected salaries should be submitted via online application (please click this website address: https://careers.ura.org.hk/).\n\nClosing date for application: 27 January 2022.\u00a0All applications will be treated in the strictest confidence and information provided will be used for the consideration of applications.\u00a0 Applicants not invited for interview within four weeks from the closing date may consider their applications unsuccessful.\n\nPersonal data provided by job applicants will be treated in strict confidence and used strictly in accordance with our \u201cPersonal Information Collection Statement Pertaining to Recruitment\u201d for recruitment purpose only.\u00a0 A copy of the Statement is available on our website and obtainable on request.\u00a0 Applicants may be considered for other suitable positions in the Authority and all personal data of unsuccessful applicants will be retained for a maximum of two years.", "employment_types": ["Full Time"], "selling_points": ["Foster the continuous local community support", "Degree holder in public administration", "Minimum 8 years\u2019 full-time experience"], "locations": ["Not Specified"], "categories": ["Marketing / Public Relations", "Others", "Public / Civil", "Social Services - Community / Non-profit Organization", "Others"], "post_time": "2022-01-14T09:04:26Z", "salary": {"currency": null, "max": null, "min": null, "period": "monthly", "term": null}, "salary_visible": false, "title_keywords": ["manager"], "responsibilities": ["monitor", "implementation", "developing", "coordinate", "communication", "executing", "plans", "publication", "planning"], "requirements": {"degrees": ["degree holder"], "majors": ["public administration"], "languages": ["putonghua", "english", "chinese"], "language_level": ["fluent"], "hard_skills": [], "soft_skills": ["outgoing", "communication skills", "oral", "self-motivated", "confidence", "communication", "innovative"], "languages_combined": [{"language": "putonghua", "language_level": ["fluent"]}, {"language": "english", "language_level": ["fluent"]}, {"language": "chinese", "language_level": ["fluent"]}]}, "experience_required": {"duration": ["minimum 8 years"], "field": ["related", "administration"]}}, {"job_id": "100003009051660", "location_code": "hk", "company": "Tung Wah Group of Hospitals", "job_title": "Human Resources Manager (Appointments Unit I)/ Admin. Headquarters [REF: SHRM(P)1/HRM(AI)/JOBS]", "description": "Location: Sheung Wan\n\nRoles & responsibilities:\n\nLead an appointment unit to manage the corporate human resources matters pertaining to community services in Tung Wah including manpower planning, pay review, recruitment and appointment as well as staff discipline and complaints;\ndevelop and implement human resources policies to meet the corporate objectives and service needs;\nundertake regular review of personnel administration system and procedures as well as assigned ad hoc projects/tasks to cope with changing needs;\nprovide executive support to the secretarial office of the Human Resources Committee; and\nundertake ad hoc projects and other general administrative duties including management of departmental business, supervision of staff and organization of meetings.\n\nThe ideal candidate should possess:\n\nA recognized degree or equivalent, preferably human resources management;\nat least Grade D in English Language (Syllabus B) and Chinese Language in the HKCEE or equivalent;\nat least 4 years\u2019 post-qualification administration experience, preferably human resources management/public administration;\nproficiency in English and Chinese; and\ngood communication and interpersonal skills.\n\n(Please specify in the application form the HKCEE result and relevant working experience you have attained in detail.)\n\nCompensation & employment terms:\n\nThe successful candidate will initially be offered a 3-year contract with a remuneration package which will be commensurate with his/her background and experience.\u00a0 The continuation of employment and employment terms thereafter will be subject to mutual agreement.\u00a0 Apart from contributions to the MPF Scheme, other benefits include paid annual leave, medical services, a dental scheme and training sponsorships.\u00a0 The incumbent will normally work under a 5-day week schedule subject to operational needs and exigencies of the service.\n\nApplication:\n\nPlease send your resume and a completed application form [F601(n)] with indication of your current and expected salaries to the Head of Human Resources Division, Tung Wah Group of Hospitals at 4/F., Wong Fung Ling Memorial Building, 12 Po Yan Street, Hong Kong by 20 January\u00a02022.\u00a0 Application forms are obtainable in person or can be downloaded from http://www.tungwah.org.hk.\u00a0 The reference code should be marked both in the letter and on the envelope.\u00a0\u00a0Underpaid mail items will not be accepted by Tung Wah.\u00a0 For proper delivery of your mail items, please ensure your mail items bear sufficient postage with return address before posting.\u00a0 Personal data provided by applicants will be used strictly for recruitment purpose only and in accordance with the Tung\u00a0Wah\u2019s personal data policy.\u00a0 Applicants not invited to attend an interview by 30 April 2022 may assume that their applications are unsuccessful.\n\nWE ARE AN EQUAL OPPORTUNITIES EMPLOYER", "employment_types": ["Full Time"], "selling_points": [], "locations": ["Sheung Wan"], "categories": ["Admin & HR", "Compensation & Benefits", "Recruitment / Executive Search", "Public / Civil", "Social Services - Community / Non-profit Organization"], "post_time": "2022-01-16T21:50:34Z", "salary": {"currency": null, "max": null, "min": null, "period": "monthly", "term": null}, "salary_visible": false, "title_keywords": ["admin. headquarters", "manager", "human resources"], "responsibilities": ["administration", "management", "policies", "review", "procedures", "executive support", "develop", "regular review", "communication", "recruitment", "ad hoc projects", "administrative duties", "planning"], "requirements": {"degrees": ["degree"], "majors": [], "languages": ["english", "chinese"], "language_level": ["proficiency"], "hard_skills": ["wan"], "soft_skills": ["communication and interpersonal skills", "ideal"], "languages_combined": [{"language": "english", "language_level": ["proficiency"]}, {"language": "chinese", "language_level": ["proficiency"]}]}, "experience_required": {"duration": ["at least 4 years", "3-year"], "field": ["management", "post-qualification", "relevant working experience", "human resources", "administration"]}}, {"job_id": "100003009048589", "location_code": "hk", "company": "Association of Hong Kong Flag-Guards Limited", "job_title": "\u6d3b\u52d5\u7d71\u7c4c\u54e1(Project Coordinator)", "description": "\u8077\u8cac\uff1a\n\n\u7b56\u5283\u53ca\u63a8\u884c\u9752\u5c11\u5e74\u53ca\u89aa\u5b50\u6d3b\u52d5\uff1b\n\u63a8\u5ee3\u5347\u639b\u570b\u65d7\u6587\u5316\u7b49\u570b\u6c11\u6559\u80b2\u6d3b\u52d5\uff1b\n\u57f7\u884c\u57f9\u80b2\u9752\u5c11\u5e74\u6b63\u5411\u50f9\u503c\u7684\u6d3b\u52d5\uff1b\n\u5076\u7136\u8981\u5ba4\u5916\u5de5\u4f5c\uff0c\u80fd\u517c\u4efb\u5347\u65d7\u79ae\u5c0e\u5e2b\u512a\u5148\u8003\u616e\uff1b\n\n\u8cc7\u6b77\uff1a\n\n\n\u8a8d\u540c\u672c\u6703\u5b97\u65e8\uff1b\n\u6a02\u65bc\u63a5\u89f8\u9752\u5c11\u5e74\uff1b\n\u5927\u5c08\u6216\u5927\u5b78\u7a0b\u5ea6\uff1b\n\u80fd\u807d\u8b1b\u8b80\u5beb\u7cb5\u8a9e\u3001\u666e\u901a\u8a71\u53ca\u82f1\u8a9e\uff1b\n\n\u6709\u610f\u61c9\u5fb5\u8077\u4f4d\u8005\uff0c\u8acb\u6309\"Apply Now\"\u63d0\u4ea4\u5c65\u6b77\u8868\u53ca\u671f\u671b\u85aa\u916c\u3002\n\n\u5982\u6709\u67e5\u8a62\uff0c\u53ef\u96fb\u90f5\u81f3\u672c\u6703\u3002", "employment_types": ["Full Time"], "selling_points": ["\u6d3b\u52d5\u7d71\u7c4c\u54e1(Project Coordinator)", "\u8ca0\u8cac\u7d71\u7c4c\u76f8\u95dc\u8ab2\u7a0b\u53ca\u6d3b\u52d5", "\u5982\u6709\u67e5\u8a62\uff0c\u53ef\u96fb\u90f5\u81f3\u672c\u6703\u3002"], "locations": ["Not Specified"], "categories": ["Marketing / Public Relations", "Public Relations - Event Management", "Public / Civil", "Social Services - Community / Non-profit Organization"], "post_time": "2022-01-14T06:51:44Z", "salary": {"currency": null, "max": null, "min": null, "period": "monthly", "term": null}, "salary_visible": false, "title_keywords": ["coordinator"], "responsibilities": [], "requirements": {"degrees": [], "majors": [], "languages": [], "language_level": [], "hard_skills": [], "soft_skills": [], "languages_combined": []}, "experience_required": {"duration": [], "field": []}}, {"job_id": "100003009050199", "location_code": "hk", "company": "Hong Kong Quality Assurance Agency", "job_title": "Senior Marketing Communications Officer/ Marketing Communications Officer", "description": "Responsibilities:\n\nManage the editorial agenda and content development for online and offline publicity materials, such as newsletters, booklet, eDM, leaflets; preparation and production of CSR report\nPrepare speeches, press releases and MC scripts\nFormulate and implement marketing communication strategies\nOrganize PR and marketing communications events and campaigns\nPremium sourcing, production of corporate video and revamp of website\n\nRequirements:\n\nTertiary education or above in Marketing, Communication, Translation, English or related disciplines\nMinimum 3\u00a0years working experience in Marketing or Public Relations\nPractical experience in copy-writing, \u00a0translation, publishing, event management and digital marketing is highly preferred\u00a0\nProactive, organized, detail-minded, able to work under pressure and meet\u00a0tight deadline\nStrong team player with excellent interpersonal and communication skills\nFluent in spoken and written English and Chinese\nProficient in Microsoft Office and Chinese Word Processing\n\nCandidate with more experience will be considered as Senior Marketing Communications Officer\n\n*2-year Contract will be offered to suitable candidate, and is subject to renewal.\u00a0\u00a0\n\nRemuneration will be commensurate with qualification and working experience.\u00a0 Interested parties please forward your resume with photo, expected remuneration and personal particulars to the\u00a0Human Resource Office, Hong Kong Quality Assurance Agency, 19th Floor, K Wah Centre, 191 Java Road, North Point, Hong Kong\u00a0OR\u00a0by fax to\u00a0 2202 9190\u00a0OR\u00a0 \u00a0click\u00a0\u201cApply Now\u201d to apply job.\u00a0 Duplicate applications will not be considered.\u00a0\u00a0\n\n\nInformation supplied will be kept in strict confidence and only be used for recruitment related purpose. Applicants not invited for interview within 6 weeks may consider their applications unsuccessful. Application forms and curriculum vitae will be kept for a period of 3 months after completion of the selection process.", "employment_types": ["Full Time", "Contract"], "selling_points": ["Tertiary education with 3 years experience", "Marketing or Public Relations related experience", "5-day work, Medical & Life Insurance is provided"], "locations": ["North Point"], "categories": ["Marketing / Public Relations", "Marketing - General / Support", "Public Relations - Event Management", "Public / Civil", "Social Services - Community / Non-profit Organization"], "post_time": "2022-01-14T09:55:39Z", "salary": {"currency": null, "max": null, "min": null, "period": "monthly", "term": null}, "salary_visible": false, "title_keywords": ["communications officer", "senior marketing communications officer"], "responsibilities": ["revamp", "edm", "leaflets", "website", "communication", "report"], "requirements": {"degrees": [], "majors": [], "languages": ["english", "chinese"], "language_level": ["proficient", "fluent"], "hard_skills": ["translation", "chinese word processing", "microsoft office"], "soft_skills": ["detail-minded", "organized", "communication skills", "communication", "meet tight deadline", "team player", "proactive", "interpersonal", "work under pressure"], "languages_combined": [{"language": "english", "language_level": ["fluent"]}, {"language": "chinese", "language_level": ["proficient", "fluent"]}]}, "experience_required": {"duration": ["minimum 3 years"], "field": ["management", "public relations", "publishing", "marketing communications", "marketing", "digital marketing", "writing"]}}, {"job_id": "100003009046909", "location_code": "hk", "company": "Yew Chung College of Early Childhood Education Limited", "job_title": "Community Engagement Officer (functional title: Community of Practice Co-ordinator)", "description": "Position Summary\n\nThe College has launched a 38-month project titled \u2018CoolPlay\u2019 (tentative title) which is funded by the Hong Kong Jockey Club Charities Trust. It is the first large-scale project of early STEM education in Hong Kong. In cooperation with YCCECE values and objective, the project's vision is to build up the capacity of schools, families, and community to support young children learning STEM.\n\nTo actualise the CoolPlay Project vision, passionate teachers, parents, and community leaders will form a network called Community of Practice. In the Community of Practice, these passionate stakeholders will share knowledge, collaborate, and provide support to each other. The Community Engagement Officer will be responsible for cultivating this Community of Practice among teachers, parents, and community leaders through various online and offline events.\n\n\u00a0The job holder will perform the following duties:\n\nClosely liaise and coordinate with school contact person, principals and parents\nPlan, facilitate and host community event to promote STEM in the early years\nSupervisor and train student helpers to facilitate with parents\u2019 engagement and community of practice events\nManaging budget related to parents and community of practice events\nCreate network and synergy internally and externally\nOccasionally working during weekends to support school visit\n\n\u00a0Requirements\n\nA Bachelor's degree or above in Event Management, Marketing, Communications, Business, Management, Education, Psychology, Social Sciences, Information Technology or a related field.\nAt least 3 years of proven working experience in event conceptualization and execution\nExperienced in collaborating with project teammates, educators, experts and higher education institution colleagues\nExperience in managing projects in education or non-profit making sectors is a plus\nExcellent written and verbal communication skills in English and Chinese\nStrong working knowledge of Microsoft Office Suite\nSolid organizational skills including attention to detail and multitasking skills\nOutstanding project management knowledge and skills\nBe comfortable working with a team of self-driven professionals who value competence and efficiency\nComfortable working in an emerging project backed by information technology\n\nSalary and Fringe Benefits:\n\nAppointment will be made on contract basis, initially one year and is renewable before the end of the project and subject to mutual consent.\n\nRemuneration is competitive and will be based on qualifications and relevant experience. The College offers group medical insurance, annual leave and sick leave, and Mandatory Provident Fund to eligible appointee.\n\nApplication Procedure:\n\nApplicants are invited to:\n\nSubmit an application letter with a full Curriculum Vitae, and copies of all graduate transcripts, and the names and contact details of three references.\nSpecify in the application letter current/latest salary and expected salary\nSend applications to the Yew Chung College of Early Childhood Education by \"Apply\".\n\nThe College will review applications immediately.\u00a0 Only shortlisted candidates will be contacted.\n\nImportant notes to Applicants:\n\nAppointees will have to undergo a medical examination.\u00a0 Reimbursement of costs subject to a ceiling is applicable.\nLocal applicants will have to undergo a Sexual Conviction Record Check. Overseas applicants will have to present a police report before appointment can be confirmed.\u00a0\nSatisfactory employment reference is required before appointment can be confirmed.\n\nThe College also reserves the right to make an appointment by invitation.\n\nPersonal data collected will be used for recruitment-related purposes only.", "employment_types": ["Full Time", "Contract"], "selling_points": ["Plan community event to promote STEM education", "Supporting development of STEM Education", "Happy and friendly work environment"], "locations": ["Aberdeen"], "categories": ["Marketing / Public Relations", "Marketing - General / Support", "Public Relations - General / Support", "Public / Civil", "Social Services - Community / Non-profit Organization"], "post_time": "2022-01-14T01:41:32Z", "salary": {"currency": null, "max": null, "min": null, "period": "monthly", "term": null}, "salary_visible": false, "title_keywords": ["officer"], "responsibilities": ["collaborate", "liaise", "provide support", "management", "budget", "coordinate with", "communication", "project management", "contact", "plan"], "requirements": {"degrees": ["degree or above", "bachelor"], "majors": ["psychology", "information technology", "business", "marketing", "communications", "social sciences"], "languages": ["english", "chinese"], "language_level": ["excellent"], "hard_skills": ["microsoft office suite", "plus", "project management"], "soft_skills": ["passionate", "communication skills", "organizational skills", "responsible", "project management", "learning", "attention to detail", "driven"], "languages_combined": [{"language": "english", "language_level": ["excellent"]}, {"language": "chinese", "language_level": ["excellent"]}]}, "experience_required": {"duration": ["at least 3 years"], "field": ["education"]}}, {"job_id": "100003009043897", "location_code": "hk", "company": "Hong Kong Sheng Kung Hui Welfare Council Limited", "job_title": "\u52a9\u7406\u8a08\u5283\u4e3b\u4efb Assistant Project Officer (Ref\uff1aMOSS/APO/20211203-2)", "description": "\u689d\u4ef6\ufe30\n\n\u4e2d\u5b78\u6703\u8003\u4e2d\u6587\u53ca\u82f1\u6587(\u8ab2\u7a0b\u4e59)\u5408\u683c\u6216\u4e2d\u5b78\u6587\u6191\u8003\u8a66\u540c\u7b49\u7b49\u7d1a\n\u9808\u638c\u63e1\u4e2d\u82f1\u6587\u96fb\u8166\u6587\u66f8\u8655\u7406\uff0c\u719f\u6089\u8edf\u4ef6(Word\u3001Excel\u53caPowerPoint)\u4e4b\u61c9\u7528\u53ca\u5177\u6587\u4ef6\u6574\u7406\u80fd\u529b\n\u5177\u5169\u5e74\u6216\u4ee5\u4e0a\u5f71\u7247\u62cd\u651d\u526a\u63a5\u3001\u7db2\u4e0a\u8a2d\u8a08\u3001\u7e6a\u5716\u5de5\u4f5c\u7d93\u9a57\u8005\u512a\u5148\n\n\u8077\u8cac\ufe30\n\u8ca0\u8cac\u5354\u52a9\u4e2d\u5fc3\u8655\u7406\u651d\u9304\u5f71\u7247\u3001\u7db2\u9801\u88fd\u4f5c\u53ca\u8ddf\u9032\uff0c\u53ca\u5354\u52a9\u9752\u5e74\u6d3b\u52d5\u7b49\u5de5\u4f5c\u3002\u9700\u5e73\u65e5\u665a\u4e0a\u6216\u661f\u671f\u516d\u3001\u65e5\u7576\u503c\u6216\u5916\u51fa\u5de5\u4f5c\u3002\n\n\n\u6b64\u8077\u4f4d\u540c\u5de5\u6703\u5148\u4ee51\u5e74\u5408\u7d04\u8058\u7528\uff0c\u518d\u7e8c\u8a021\u5e74\u5408\u7d04\uff0c\u5728\u5b8c\u62102\u5e74\u5408\u7d04\u671f\u53ca\u8868\u73fe\u826f\u597d\u8005\uff0c\u6703\u6539\u8058\u70ba\u9577\u671f\u5408\u7d04\u540c\u5de5\u3002\n\n\u5168\u8077\u54e1\u5de5\u53ef\u4eab\u6709\u4ee5\u4e0b\u5b8c\u5584\u798f\u5229\uff1a\n\u53ef\u4eab\u6709\u6709\u85aa\u5e74\u504717\u5929\u3001\u516c\u773e\u5047\u671f17\u5929\u3001\u5a5a\u5047\u3001\u5206\u5a29\u5047\u3001\u6069\u6064\u5047\u3001\u4f8d\u7522\u5047\u3001\u8d85\u6642\u5de5\u4f5c\u88dc\u5047\u3001\u514d\u8cbb\u9ad4\u6aa2\u3001\u91ab\u7642\u4fdd\u96aa\u3001\u4eba\u58fd\u4fdd\u96aa\u3001\u91ab\u7642\u512a\u60e0\u3001\u50f1\u4e3b\u5f37\u7a4d\u91d1\u4f9b\u6b3e\u6309\u5e74\u8cc7\u6700\u9ad8\u53ef\u905e\u589e\u81f315%\u3001\u5728\u8077\u57f9\u8a13\u53ca\u826f\u597d\u6649\u5347\u968e\u68af\u7b49\u3002\n\n\n\u6709\u610f\u8005\u8acb\u5177\u5c65\u6b77\u5bc4(\u4fe1\u5c01\u9762\u53ca\u4fe1\u5167\u8acb\u8a3b\u660e\u8077\u4f4d\u7de8\u865f)\ufe30\u65b0\u754c\u6c99\u7530\u99ac\u978d\u5c71\u8000\u5b89\u90a8\u8000\u548c\u6a13\u5730\u4e0b \u2013 \u9999\u6e2f\u8056\u516c\u6703\u99ac\u978d\u5c71\uff08\u5357\uff09\u9752\u5c11\u5e74\u7d9c\u5408\u670d\u52d9\u4e2d\u5fc3\u7763\u5c0e\u4e3b\u4efb\u6536\u6216\u6309\"Apply Now\"\u3002\u4e00\u5207\u7533\u8acb\u8cc7\u6599\u7d55\u5c0d\u4fdd\u5bc6\u53ca\u53ea\u7528\u4f5c\u62db\u8058\u6709\u95dc\u8077\u4f4d\u3002\u5982\u65bc\u5ee3\u544a\u520a\u767b\u5f8c\u516d\u500b\u6708\u5167\u4ecd\u672a\u7372\u672c\u6703\u56de\u8986\uff0c\u5373\u5176\u7533\u8acb\u672a\u7372\u8003\u616e\uff0c\u800c\u7533\u8acb\u4eba\u4e4b\u500b\u4eba\u8cc7\u6599\u4ea6\u5c07\u5728\u5b8c\u6210\u62db\u8058\u7a0b\u5e8f\u5f8c\u92b7\u6bc0\u3002\u5982\u6b32\u53c3\u8003\u5354\u6703\u8cc7\u6599\uff0c\u8acb\u767b\u5165\u7db2\u5740\ufe30http://www.skhwc.org.hk", "employment_types": ["Full Time", "Contract"], "selling_points": [], "locations": ["Shatin Area"], "categories": ["Admin & HR", "Training & Development", "Public / Civil", "Social Services - Community / Non-profit Organization"], "post_time": "2022-01-13T18:54:54Z", "salary": {"currency": null, "max": null, "min": null, "period": "monthly", "term": null}, "salary_visible": false, "title_keywords": ["assistant project officer"], "responsibilities": [], "requirements": {"degrees": [], "majors": [], "languages": [], "language_level": [], "hard_skills": [], "soft_skills": [], "languages_combined": []}, "experience_required": {"duration": [], "field": []}}, {"job_id": "100003009051849", "location_code": "hk", "company": "St. James' Settlement", "job_title": "\u71df\u904b\u4e3b\u4efb (PO III) (\u5408\u7d04)\u3008\u7de8\u865f:VBH/06022\u3009", "description": "\u793e\u5340\u4e2d\u5fc3\u670d\u52d9\n\n\n\n\u8981\u6c42\ufe30\n\nl\u4e2d\u5b78\u6703\u8003\u4e94\u79d1\u5408\u683c\uff0c\u5305\u62ec\u4e2d\u6587\u3001\u82f1\u6587(\u4e59)\u6216\u7b49\u540c\n\nl\u5ba2\u6236\u670d\u52d9\u6216\u96f6\u552e\u76f8\u95dc\u4e4b\u5de5\u4f5c\u7d93\u9a57\uff0c\u5177\u6700\u5c11\u4e09\u5e74\u9910\u5ef3\u5de5\u4f5c\u7d93\u9a57\u512a\u5148\n\nl\u57fa\u672c\u98df\u7269\u88fd\u4f5c\u77e5\u8b58\uff0c\u4e86\u89e3\u5eda\u623f\u7528\u5177\u4f7f\u7528\u65b9\u6cd5\n\nl\u4e3b\u52d5\u3001\u5177\u8cac\u4efb\u611f\u548c\u826f\u597d\u7684\u5ba2\u6236\u670d\u52d9\u614b\u5ea6\u53ca\u5718\u968a\u7cbe\u795e\n\n\u8077\u8cac\ufe30\n\nl\u7dad\u6301\u53ca\u8655\u7406\u793e\u6703\u4f01\u696d\u65e5\u5e38\u904b\u4f5c\uff0c\u5305\u62ec\u65e5\u5e38\u98df\u7269\u88fd\u4f5c\uff0c\u7db2\u4e0a\u5e73\u53f0\n\nl\u5354\u52a9\u65e5\u5e38\u5e97\u8216\u53ca\u5eda\u623f\u7763\u5c0e\u5de5\u4f5c\uff0c\u4fdd\u6301\u826f\u597d\u98df\u54c1\u8655\u7406\u53ca\u5e97\u8216\u74b0\u5883\u7684\u885b\u751f\n\nl\u7ba1\u7406\u524d\u7dda\u540c\u4e8b\u53ca\u7de8\u6392\u66f4\u8868\n\nl\u7ba1\u7406\u5e97\u8216\u51fa\u5165\u8ca8\u65e5\u5e38\u904b\u4f5c\u53ca\u806f\u7d61\u4f9b\u61c9\u5546\n\n\u00a0\n\u6709\u610f\u8005\u8acb\u65bc31/01/2022\u6216\u4e4b\u524d\u51fd\u9644\u5c65\u6b77\u6309\u4e0bAPPLY\u00a0 \u00a0NOW\u3002\n\n**\u672c\u6703\u5728\u8058\u7528\u50f1\u54e1\u5f9e\u4e8b\u8207\u5152\u7ae5\u6216\u7cbe\u795e\u4e0a\u7121\u884c\u70ba\u80fd\u529b\u4eba\u58eb\u6709\u95dc\u5de5\u4f5c\u7684\u8077\u4f4d\u6642\uff0c\u5c07\u8981\u6c42\u7533\u8acb\u4eba\u9032\u884c\u6027\u7f6a\u884c\u5b9a\u7f6a\u7d00\u9304\u67e5\u6838\u3002**\n\n\u00e9\u7533\u8acb\u4eba\u63d0\u4f9b\u4e4b\u5168\u90e8\u8cc7\u6599\u7d55\u5c0d\u4fdd\u5bc6\u53ca\u53ea\u4f9b\u62db\u8058\u4e4b\u7528\u3002\u5ee3\u544a\u520a\u767b\u5f8c\u4e09\u500b\u6708\u5167\uff0c\u5982\u672a\u7372\u672c\u6703\u56de\u8986\uff0c\u00a0\u8acb\u8996\u4f5c\u8a72\u9805\u7533\u8acb\u4e0d\u88ab\u63a5\u7d0d\uff0c\u672c\u6703\u5c07\u65bc\u4e00\u5e74\u5f8c\u92b7\u6bc0\u7533\u8acb\u4eba\u4e4b\u500b\u4eba\u8cc7\u6599\u3002\u00fb", "employment_types": ["Full Time", "Contract"], "selling_points": ["\u4e2d\u5b78\u6703\u8003\u4e94\u79d1\u5408\u683c\uff0c\u5305\u62ec\u4e2d\u6587\u3001\u82f1\u6587(\u4e59)\u6216\u7b49\u540c", "\u5ba2\u6236\u670d\u52d9\u6216\u96f6\u552e\u76f8\u95dc\u5de5\u4f5c\u7d93\u9a57\uff0c\u5177\u6700\u5c11\u4e09\u5e74\u9910\u5ef3\u5de5\u4f5c\u7d93\u9a57\u512a\u5148", "\u57fa\u672c\u98df\u7269\u88fd\u4f5c\u77e5\u8b58\uff0c\u4e86\u89e3\u5eda\u623f\u7528\u5177\u4f7f\u7528\u65b9\u6cd5"], "locations": ["Wan Chai"], "categories": ["Hospitality / F & B", "Food & Beverage", "Public / Civil", "Social Services - Community / Non-profit Organization"], "post_time": "2022-01-17T01:21:50Z", "salary": {"currency": null, "max": null, "min": null, "period": "monthly", "term": null}, "salary_visible": false, "title_keywords": [], "responsibilities": [], "requirements": {"degrees": [], "majors": [], "languages": [], "language_level": [], "hard_skills": [], "soft_skills": [], "languages_combined": []}, "experience_required": {"duration": [], "field": []}}, {"job_id": "100003009049662", "location_code": "hk", "company": "New Life Psychiatric Rehabilitation Association", "job_title": "Executive Officer (Ref: SES \u2013 EO)", "description": "Responsibilities:\n\nTo prepare all kinds of documents including proposals, reports, memos, financial documents and analysis, etc.;\nTo update and compile various data and statistics;\nTo be responsible for logistic management of service projects and to ensure smooth operation to meet contract requirements and quality standards;\nTo liaise with government departments or organizations on matters relating to service, contracts and job orders;\nTo liaise and coordinate with internal and external parties;\nTo be responsible for the office management and administrative duties of the unit; and\nTo perform other duties as required by the supervisor.\n\nRequirements:\n\nDegree holder with 3 years or above experience in administration;\nKnowledge and experience in ISO9001, ISO22000 or Employees Retraining Scheme is an advantage;\nHighly resourceful team player with excellent interpersonal and communication skills;\nProactive, organized and be able to juggle multiple projects;\nResponsible, detailed-minded with a \u201ccan-do\" attitude; and\nGood command of spoken and written English and Chinese.\n\nApplicants are invited to forward a cover letter and a resume to the Human Resources Department by post at New Life Psychiatric Rehabilitation Association, 332 Nam Cheong Street, Kowloon, or by fax at 3552 5398, or by clicking \"Apply Now\".\n\nPersonal data provided by applicants will strictly be used for recruitment purpose.\u00a0\nNew Life Psychiatric Rehabilitation Association is an equal opportunity employer.\nProspective employees are requested to undergo Sexual Conviction Record Check.", "employment_types": ["Full Time"], "selling_points": ["To assist in service project administration", "Employees Retraining Scheme", "ISO9001 & ISO22000"], "locations": ["Wong Tai Sin Area"], "categories": ["Admin & HR", "Clerical / Admin Staff", "Public / Civil", "Social Services - Community / Non-profit Organization", "Others"], "post_time": "2022-01-14T09:02:05Z", "salary": {"currency": null, "max": null, "min": null, "period": "monthly", "term": null}, "salary_visible": false, "title_keywords": ["executive officer"], "responsibilities": ["liaise", "management", "perform other duties", "data", "contracts", "analysis", "internal and external parties", "quality", "coordinate with", "reports", "administrative duties", "liaise with"], "requirements": {"degrees": ["degree holder"], "majors": [], "languages": ["english", "chinese"], "language_level": ["good command"], "hard_skills": ["scheme"], "soft_skills": ["communication skills", "organized", "resourceful", "responsible", "can-do", "team player", "proactive", "interpersonal", "detailed"], "languages_combined": [{"language": "english", "language_level": ["good command"]}, {"language": "chinese", "language_level": ["good command"]}]}, "experience_required": {"duration": ["3 years"], "field": ["administration"]}}, {"job_id": "100003009048351", "location_code": "hk", "company": "Hong Kong Association of Youth Development Limited", "job_title": "Development and Liaison Officer / Assistant Development and Liaison  Officer  (\u767c\u5c55\u53ca\u806f\u7d61\u5e79\u4e8b/\u52a9\u7406\u767c\u5c55\u53ca\u806f\u7d61\u5e79\u4e8b)", "description": "Roles & Responsibilities:\nAssist the team to co-ordinate and organize youth programs, fundraising and mingling events for the Association from planning, preparation, execution to evaluation\nWork close with youth leaders of us and coordinate enriching activities for the Youth Committee\nLiaise with subordinate 18 district association members, assist to arrange district activities and attend district meetings\nAssist the team to write up funding proposal and design program content\nKeep good rapport with youth members and committee members\nPerform any other duties as assigned by supervisors\nCandidates with less experience may be considered as Assistant Development Officer\nRequirements:\nHigher Diploma or above, preferably in social science disciplines or equivalent\nAt least 2-year relevant working experience with NGOs or public sector\nIndependent worker and able to complete task with minimal supervision\nGood command of spoken and written Chinese, English and Putonghua\n\nExcellent interpersonal and communication skills\nPossessing AI or Photoshop skill set is a plus\nResponsible, detailed-minded, proactive in personality and can be a good team player\nMay work on weekends or in evenings for events/meetings/occasions\nInterested candidates please send your FULL RESUME with DATE OF AVAILABILITY, PRESENT /LATEST and EXPECTED SALARY via \"Apply Now\"\n\nOnly shortlisted candidates will be notified for interview", "employment_types": ["Full Time"], "selling_points": [], "locations": ["Quarry Bay"], "categories": ["Public / Civil", "Social Services - Community / Non-profit Organization"], "post_time": "2022-01-14T06:24:17Z", "salary": {"currency": null, "max": null, "min": null, "period": "monthly", "term": null}, "salary_visible": false, "title_keywords": ["officer", "assistant"], "responsibilities": ["any other duties", "design", "coordinate", "evaluation", "liaise with", "planning"], "requirements": {"degrees": ["higher diploma or above"], "majors": ["science"], "languages": ["putonghua", "english", "chinese"], "language_level": ["good command"], "hard_skills": ["plus", "photoshop", "ai"], "soft_skills": ["communication skills", "good team player", "independent", "responsible", "proactive", "interpersonal", "detailed"], "languages_combined": [{"language": "putonghua", "language_level": ["good command"]}, {"language": "english", "language_level": ["good command"]}, {"language": "chinese", "language_level": ["good command"]}]}, "experience_required": {"duration": ["at least 2-year"], "field": ["relevant working experience"]}}, {"job_id": "100003009049400", "location_code": "hk", "company": "Perrett Laver Limited", "job_title": "Research Associate (5 days)", "description": "Perrett Laver is now seeking to hire a bright, dynamic and ambitious individual to join our fast-growing team in Central Hong Kong as Research Associate.\n\n\n\nThis role draws upon the intellectual skills necessary to grasp a complex brief; the research skills to identify people who are at the highest levels in their professions; the advocacy skills to engage such candidates; the motivation to serve our clients to the best of our abilities; and the capacity to work as part of a core project team and a wider corporate team. You will have a thirst for knowledge, a methodical mind-set that will enable you to carry out a comprehensive and global search of the talent pool, and high attention to detail.\n\n\n\nResearch Associates are expected to manage the research phase of the project including background analysis, identification and securing of candidates, and candidate care. They work closely with and support the Project Management Team and the Consultant(s) in the delivery of projects through to the appointment of a preferred candidate.\n\n\n\nWe are seeking people with the following:\n\nOutstanding verbal and written communication skills in both English and Chinese;\nA Master\u2019s degree or above;\nA strong sense of service and the drive to best support our clients and candidates;\nKnowledge and passion in education and non-profit sector;\nAn intellectually curious mind-set;\nA shared commitment to the mission and values of Perrett Laver;\nSharp and rigorous analytical skills and attention to detail, particularly regarding the assessment of candidates;\nAbility to manage multiple projects and to prioritize workload;\nA willingness to work with flexible hours when needed;\nStrong appreciation and understanding of the importance of punctuality, responsibility and discretion required for this role;\nTenacious, committed and results-oriented;\nEnthusiastic and proactive;\nCollaborative, flexible and able to contribute to the development of a growing team;\nFresh graduates are welcome to apply\n\nDesirable\n\nA Graduate degree;\nFluent in Cantonese and Mandarin;\nExperience working within universities, academic organizations or schools or NGO.\n\nNo previous experience working in executive search is required. Perrett Laver will provide rigorous and systematic training for all new hires.\n\nTo Apply\n\nTo apply, please submit an up-to-date CV and Cover Letter via https://candidates.perrettlaver.com/vacancies/ , quoting reference HKPL/RES.", "employment_types": ["Full Time"], "selling_points": ["Higher Education and Research Leadership", "Senior Executive Recruitment Consultation", "Fresh graduates are welcome to apply"], "locations": ["Central"], "categories": ["Professional Services", "Business Consultancy", "Admin & HR", "Recruitment / Executive Search", "Public / Civil", "Social Services - Community / Non-profit Organization"], "post_time": "2022-01-14T08:35:13Z", "salary": {"currency": null, "max": null, "min": null, "period": "monthly", "term": null}, "salary_visible": false, "title_keywords": ["research associate"], "responsibilities": ["communication", "project management", "analysis", "manage multiple projects"], "requirements": {"degrees": ["degree or above", "degree", "master"], "majors": [], "languages": ["cantonese", "english", "chinese", "mandarin"], "language_level": ["fluent"], "hard_skills": ["no", "analysis", "analytical skills", "project management", "dynamic"], "soft_skills": ["flexible", "communication skills", "research skills", "passion in", "collaborative", "prioritize", "analytical skills", "systematic", "project management", "committed", "comprehensive", "dynamic", "enthusiastic", "attention to detail", "willingness to work", "methodical", "proactive", "tenacious"], "languages_combined": [{"language": "cantonese", "language_level": ["fluent"]}, {"language": "english", "language_level": []}, {"language": "chinese", "language_level": []}, {"language": "mandarin", "language_level": ["fluent"]}]}, "experience_required": {"duration": [], "field": []}}, {"job_id": "100003009052625", "location_code": "hk", "company": "Hong Kong Housing Society", "job_title": "Senior Officer (Elderly Services) / Social Worker \u2013 North Point", "description": "[Ref: TTH-SO(ES)]\n\nThe Job:\n\nManage the daily operation in Day Care Center and RCHE, and responsible for planning, organizing and implementing activities.\u00a0\nCollaborate with other colleagues and external units for execution services to customers.\u00a0\nReport the monthly service and financial statistics to supervisor. \u00a0\nAssist to source and contact with local organizations / NGO/ companies for large event programs.\u00a0\nHandle customer requests, enquiries and complaints independently, provide psychosocial support to residents in RCHE and members in DCC.\u00a0\nLiaise with customers and volunteers to ensure smooth service delivery.\u00a0\nCoordinate psychosocial activities and training sessions especially for dementia cases, group activities and mass program in Day Care Centre.\u00a0\nEvaluate the effectiveness of the designed training program.\u00a0\nSupervise HCOII and Personal Care Workers particularly on skills and techniques of leading dementia groups in DCC and RCHE.\u00a0\nAs a mentor leading the new CSR to coordinate activities in DCC and RCHE.\n\nThe Person:\n\nDegree / Associate degree holder in Social Science / Social Work Studies / Counseling.\nRegistered Social Worker is preferable.\nMinimum 3 years solid working experience in recognized welfare organization; elderly service or mental health services preferable.\nGood connection with various service providers and stakeholders in elderly/ mental health services.\nProficient in English, Chinese and Putonghua.\n\nAttractive remuneration package will be offered to suitable candidates. To apply, please submit online application: https://careers.hkhs.com/ or send your application with full resume and reference quoted to Human Resources Manager by fax: 2882 4466.\n\nYou are welcome to visit our website www.hkhs.com to learn more about us.\nApplicants not invited for interview within 8 weeks may consider their applications unsuccessful.\n\nPersonal data provided by job applicants will be used strictly in accordance with the Housing Society\u2019s personal data policies which is available in our website and obtainable upon request. Please refer to the Policy Statement on Employment Related Data under Personal Data (Privacy) Ordinance in our website.", "employment_types": ["Permanent"], "selling_points": ["Manage the daily operation in Day Care Center", "Minimum 3 years solid working experience", "Degree holder in Social Science"], "locations": ["North Point"], "categories": ["Public / Civil", "Social Services - Community / Non-profit Organization"], "post_time": "2022-01-17T03:35:40Z", "salary": {"currency": null, "max": null, "min": null, "period": "monthly", "term": null}, "salary_visible": false, "title_keywords": ["social worker", "senior officer"], "responsibilities": ["collaborate with", "service delivery", "daily operation", "coordinate", "evaluate", "planning", "contact", "customer requests", "liaise with", "report"], "requirements": {"degrees": ["associate degree", "degree"], "majors": ["social work", "science"], "languages": ["putonghua", "english", "chinese"], "language_level": ["proficient"], "hard_skills": [], "soft_skills": [], "languages_combined": [{"language": "putonghua", "language_level": ["proficient"]}, {"language": "english", "language_level": ["proficient"]}, {"language": "chinese", "language_level": ["proficient"]}]}, "experience_required": {"duration": ["minimum 3 years"], "field": []}}, {"job_id": "100003009045803", "location_code": "hk", "company": "Hong Kong Arts Centre", "job_title": "Officer / Assistant Officer (Communication & Development) (Ref: OCD / AOCD)", "description": "Job Duties:\n(under supervision)\n- To monitor and update school databases / website / social media platforms\n- To assist / coordinate in the production of school publications and printed materials\n- To assist in the planning of digital marketing / student recruitment campaign\n- To provide operational support to the School events such as programme seminars and exhibitions\n- To provide administrative / logistic / editorial support to Communication & Development Team\n\u00a0and perform any other duties as assigned\nRequirements :\n- Degree holder preferably with 1-2 year working experience (Fresh graduate / those with less \u00a0experience will be considered for appointment as Assistant Officer)\n- Detail-oriented, dynamic, open-minded with good command of English and Chinese\n- Proactive, independent and have strong sense of responsibility\n- With an appropriate level of IT skill, preferably with knowledge in design software (eg. Photoshop, InDesign, Canva, etc)\n- Interest in art and art education, knowledge in web design or web editorial work preferred\n- Immediate available is preferred\nThe appointment is basically on full-time on one-year term, and is to be renewed subject to mutual agreements and operational needs.\nInterested parties please apply with your full C.V. and a completed HKAS005 Job Application Form, and send it together with a covering letter indicating your view on art education, your expected salary, and your available date for assuming duty (if applicable) by mail to Human Resources Department, Hong Kong Arts Centre, 8/F, 2 Harbour Road, Wanchai, Hong Kong, or by email. Please quote reference.\nApplication form can be downloaded from Hong Kong Art School website at\u00a0www.hkas.edu.hk\u00a0(https://www.hkas.edu.hk/wp-content/uploads/HKAS005_Job_Application_Form.pdf)\u00a0or picked up directly from the Enrolment Office of the Hong Kong Art School, Room 819, 8/F, Youth Square, 238 Chai Wan Road, Chai Wan, Hong Kong, during office hours.\nThe closing date for application is\u00a025 January 2022.\nOnly shortlisted candidates will be contacted. We are an equal opportunities employer.", "employment_types": ["Full Time", "Contract"], "selling_points": [], "locations": ["Chai Wan"], "categories": ["Admin & HR", "Administration / Operation Manager", "Education", "Others", "Public / Civil", "Social Services - Community / Non-profit Organization"], "post_time": "2022-01-13T08:49:05Z", "salary": {"currency": null, "max": null, "min": null, "period": "monthly", "term": null}, "salary_visible": false, "title_keywords": ["assistant officer", "officer"], "responsibilities": ["any other duties", "operational support", "social media platforms", "monitor", "website", "school events", "coordinate", "communication", "digital marketing", "recruitment", "databases", "planning"], "requirements": {"degrees": ["fresh graduate", "degree holder"], "majors": [], "languages": ["english", "chinese"], "language_level": ["good command"], "hard_skills": ["web design", "web", "indesign", "dynamic", "photoshop"], "soft_skills": ["independent", "sense of responsibility", "open-minded", "detail-oriented", "dynamic", "proactive"], "languages_combined": [{"language": "english", "language_level": ["good command"]}, {"language": "chinese", "language_level": ["good command"]}]}, "experience_required": {"duration": ["1-2 year"], "field": []}}, {"job_id": "100003009048977", "location_code": "hk", "company": "The Lok Sin Tong Benevolent Society, Kowloon", "job_title": "Administrative Assistant (DHCE) \u884c\u653f\u52a9\u7406 (\u5730\u5340\u5eb7\u5065\u7ad9)", "description": "\u5730\u5340\u5eb7\u5065\u7ad9\u670d\u52d9\n\n\u4e5d\u9f8d\u6a02\u5584\u5802\u7372\u5f97\u98df\u7269\u53ca\u885e\u751f\u5c40\u6279\u51fa\u4e5d\u9f8d\u57ce\u5340\u53ca\u6cb9\u5c16\u65fa\u5340\u5730\u5340\u5eb7\u5065\u7ad9\u7684\u71df\u904b\u670d\u52d9\u5408\u7d04\uff0c\u70ba\u671f\u4e09\u5e74\uff0c\u70ba\u5c45\u6c11\u63d0\u4f9b\u5065\u5eb7\u63a8\u5ee3\u548c\u6559\u80b2\u3001\u5065\u5eb7\u98a8\u96aa\u8a55\u4f30\u3001\u6162\u6027\u75be\u75c5\u7ba1\u7406\u7b49\u91cd\u9ede\u57fa\u5c64\u91ab\u7642\u5065\u5eb7\u670d\u52d9\uff0c\u9577\u9060\u5efa\u7acb\u4e00\u500b\u4ee5\u9810\u9632\u70ba\u4e2d\u5fc3\u7684\u57fa\u5c64\u91ab\u7642\u9ad4\u7cfb\u3002\u4e5d\u9f8d\u57ce\u5340\u53ca\u6cb9\u5c16\u65fa\u5340\u5730\u5340\u5eb7\u5065\u7ad9\u65bc 2021 \u5e74 10 \u6708\u555f\u7528\uff0c\u73fe\u8aa0\u9080\u5c0d\u6b64\u670d\u52d9\u6709\u71b1\u8aa0\u53ca\u62b1\u8ca0\u7684\u540c\u5de5\u5171\u540c\u958b\u5c55\u53ca\u7b56\u5283\u5730\u5340\u57fa\u5c64\u91ab\u7642\u670d\u52d9\u3002\u6b61\u8fce\u81f4\u96fb 2272 9870 \u67e5\u8a62\u3002\n\n\u4e3b\u8981\u8077\u8cac\uff1a\n\n\u8ca0\u8cac\u63a5\u5f85\u670d\u52d9\u4f7f\u7528\u8005\uff0c\u6703\u54e1\u767b\u8a18\u548c\u670d\u52d9\u67e5\u8a62\uff1b\n\u652f\u63f4\u884c\u653f\u53ca\u8ca1\u52d9\u5de5\u4f5c\u53ca\u4e2d\u82f1\u6587\u96fb\u8166\u6587\u66f8\u8655\u7406\u3002\n\u5165\u8077\u8981\u6c42\uff1a\n\n\u6301\u8a8d\u53ef\u6587\u6191\u3001\u526f\u5b78\u58eb\u6216\u4ee5\u4e0a\u5b78\u6b77\uff1b\n\u826f\u597d\u4eba\u969b\u95dc\u4fc2\u53ca\u6e9d\u901a\u80fd\u529b\u3001\u5177\u8cac\u4efb\u611f\u3001\u4e3b\u52d5\u53ca\u7d30\u5fc3\uff1b\n\u5177 2 \u5e74\u884c\u653f\u6216\u76f8\u95dc\u5de5\u4f5c\u7d93\u9a57\u3002\n\n\u6709\u610f\u61c9\u5fb5\u8005\u8acb\u5448\u4ea4\u8a73\u7d30\u5c65\u6b77(\u8a3b\u660e\u73fe\u8077\u85aa\u916c\u3001\u671f\u671b\u85aa\u916c\u53ca\u53ef\u5230\u8077\u65e5\u671f)\u96fb\u90f5\u4e88\u6211\u5011\u3002\n(\u7533\u8acb\u4eba\u6240\u63d0\u4f9b\u7684\u8cc7\u6599\u5c07\u4e88\u4fdd\u5bc6\u53ca\u53ea\u4f5c\u62db\u8058\u6709\u95dc\u8077\u4f4d\u7528\u9014)", "employment_types": ["Full Time", "Contract"], "selling_points": [], "locations": ["Kowloon City"], "categories": ["Admin & HR", "Clerical / Admin Staff", "Public / Civil", "Social Services - Community / Non-profit Organization"], "post_time": "2022-01-14T07:49:17Z", "salary": {"currency": null, "max": null, "min": null, "period": "monthly", "term": null}, "salary_visible": false, "title_keywords": ["administrative assistant", "\u884c\u653f\u52a9\u7406"], "responsibilities": [], "requirements": {"degrees": [], "majors": [], "languages": [], "language_level": [], "hard_skills": [], "soft_skills": [], "languages_combined": []}, "experience_required": {"duration": [], "field": []}}, {"job_id": "100003009046159", "location_code": "hk", "company": "Hong Kong General Chamber of Young Entrepreneurs Limited", "job_title": "\u52a9\u7406\u9805\u76ee\u4e3b\u4efb(Assistant Project Officer)", "description": "\u5de5\u4f5c\u5167\u5bb9\uff1a\n\n\u5354\u52a9\u7b56\u5283\u548c\u57f7\u884c\u5546\u6703\u7684\u5275\u696d\u8a08\u5283\u00a0\n\u5354\u52a9\u5546\u6703\u8207\u5927\u7063\u5340\u5404\u5275\u696d\u57fa\u5730\u5354\u8abf\u806f\u7e6b\n\u5354\u52a9\u6536\u96c6\u548c\u5354\u52a9\u6279\u6838\u8a08\u5283\u4e2d\u521d\u5275\u4f01\u696d\u63d0\u4ea4\u7684\u968e\u6bb5\u6027\u5831\u544a\n\u5354\u52a9\u7d44\u7e54\u5546\u6703\u4ea4\u6d41\u6d3b\u52d5\n\u5411\u6703\u54e1\u5ba3\u50b3\u5546\u6703\u7684\u6d3b\u52d5\n\u5546\u6703\u79d8\u66f8\u8655\u7684\u884c\u653f\u5de5\u4f5c\n\u8655\u7406\u7a81\u767c\u6027\u5de5\u4f5c\n\n\u5165\u8077\u8981\u6c42\uff1a\n\n\u6301\u6709\u4efb\u4f55\u5927\u5c08\u5b78\u6b77(\u526f\u5b78\u4f4d\u6216\u4ee5\u4e0a) \u3010\u4f46\u50b3\u64ad\u3001\u516c\u5171\u95dc\u4fc2\u3001\u5e02\u5834\u884c\u92b7\u3001\u5a92\u9ad4\u6216\u76f8\u95dc\u5b78\u79d1\u7562\u696d\u5c07\u512a\u5148\u8003\u616e\u3011\n\u6709\u5546\u6703\u3001\u793e\u5718\u3001NGO\u5de5\u4f5c\u7d93\u9a57\u512a\u5148\u8003\u616e\uff1b\n\u7cbe\u901a\u5fae\u8edf\u8fa6\u516c\u61c9\u7528\u8edf\u9ad4\uff08\u5982Word\u3001Excel\u3001PowerPoint\u7b49\uff09\u548c\u61c2\u4e2d\u6587\u6253\u5b57\n\u61c2\u5f97\u4f7f\u7528Adobe Photoshop \u53ca Illustrator \u5c07\u512a\u5148\u8003\u616e\uff1b\n\u6d41\u5229\u82f1\u8a9e\u3001\u7cb5\u8a9e\u548c\u666e\u901a\u8a71\n\u7cbe\u901a\u82f1\u8a9e\u548c\u4e2d\u6587\u5beb\u4f5c\n\u826f\u597d\u7684\u4eba\u969b\u4ea4\u5f80\u80fd\u529b\n\u80fd\u7368\u7acb\u5de5\u4f5c\uff0c\u6ce8\u91cd\u7d30\u7bc0\uff0c\u6709\u689d\u4e0d\u7d0a\n\n\u6709\u610f\u7533\u8acb\u8005\u8acb\u5c07\u7533\u8acb\u4fe1\u3001\u500b\u4eba\u5c65\u6b77(\u5217\u660e\u671f\u671b\u85aa\u916c\u53ca\u53ef\u5230\u8077\u65e5\u671f)\uff0c\u65bc2022\u5e742\u670813\u65e5\u524d\u96fb\u90f5\u81f3\u9999\u6e2f\u9752\u5e74\u5275\u696d\u5bb6\u7e3d\u5546\u6703\u79d8\u66f8\u8655\u6536\uff0c\u6216\u6309\u300cApply Now\u300d\u7533\u8acb\u3002\u5982\u4ee5\u96fb\u90f5\u7533\u8acb\uff0c\u96fb\u90f5\u5fc5\u9808\u8a3b\u660e\u7533\u8acb\u8077\u4f4d\u4e4b\u540d\u7a31\u3002\n\n\u95dc\u65bc\u9999\u6e2f\u9752\u5e74\u5275\u696d\u5bb6\u7e3d\u5546\u6703\n\n\u9999\u6e2f\u9752\u5e74\u5275\u696d\u5bb6\u7e3d\u5546\u6703\u662f\u7531\u9999\u6e2f\u9752\u5e74\u5354\u6703\u652f\u6301\u53ca\u63a8\u52d5\u4e0b\u65bc2015\u5e74\u6210\u7acb\u7684\u975e\u725f\n\n\u5229\u6a5f\u69cb\uff0c\u5275\u6703\u8463\u4e8b\u5c40\u6210\u54e1\u5747\u70ba\u300c\u6ed9\u8c50\u9752\u5e74\u5275\u696d\u5927\u734e\u300d\u53ca\u300c\u9999\u6e2f\u9752\u5e74\u5275\u696d\u8a08\u5283\u300d\n\n\u7684\u5f97\u734e\u8005\uff0c\u6703\u54e1\u70ba18\u81f345\u6b72\u7684\u9999\u6e2f\u5275\u696d\u9752\u5e74\uff0c\u64c1\u6709\u8d85\u904e300\u9593\u672c\u5730\u521d\u5275\u4f01\u696d\n\n\u6703\u54e1\u3002\n\n\u5176\u4e3b\u8981\u76ee\u6a19\u662f\uff1a\n\n\u2027\u00a0\u00a0\u00a0 \u70ba\u9752\u5e74\u5275\u696d\u5bb6\u5275\u9020\u4e00\u500b\u66f4\u7dca\u5bc6\u7684\u793e\u7fa4\uff0c \u63d0\u4f9b\u5168\u65b9\u4f4d\u7684\u652f\u63f4\n\n\u2027\u00a0\u00a0\u00a0 \u5efa\u7acb\u4e00\u500b\u6536\u96c6\u3001\u4fc3\u9032\u548c\u5206\u4eab\u9752\u5e74\u5275\u696d\u6587\u5316\u53ca\u8cc7\u8a0a\u5e73\u53f0\n\n\u2027\u00a0\u00a0\u00a0 \u5b9a\u671f\u8207\u653f\u5e9c\u76f8\u95dc\u653f\u7b56\u5c40\u53ca\u5167\u5730\u5546\u52d9\u6a5f\u69cb\u806f\u7e6b\u6e9d\u901a\uff0c\u9032\u884c\u653f\u7b56\u5021\u8b70\u7684\u5de5\u4f5c\n\n\u2027\u00a0\u00a0\u00a0 \u901a\u904e\u8207\u77e5\u540d\u5546\u696d\u9818\u8896\u6703\u9762\u4f86\u4fc3\u9032\u6301\u7e8c\u5b78\u7fd2\n\n\u2027\u00a0\u00a0\u00a0 \u9023\u63a5\u9999\u6e2f\u3001\u5927\u4e2d\u83ef\u5730\u5340\u548c\u6d77\u5916\u7684\u5e74\u8f15\u5275\u696d\u5bb6\uff0c\u4ee5\u52a0\u5f37\u4eba\u8108\u806f\u7e6b\u548c\u5546\u6a5f\n\nJob Descriptions:\n\nAssist in the planning and execution of start-up programme of the Chamber\nCoordinate and liaise with the Greater Bay Area Start-up Bases on behalf of the Chamber\nCollect and approve the milestone reports submitted by the start-ups in the programme\nOrganize social and business networking events\nPromote Chamber\u2019s events to members\nHandle the administrative work of the Chamber\u2019s Secretariat\nPerform ad hoc duties as assigned\n\n\u00a0Requirement:\n\nTertiary education (sub-degree or above) in any disciplines, but communications, public relations, marketing, media or related disciplines is an advantage;\nWorking experience in chambers, associations, and NGOs is an advantage;\nWell versed in Microsoft Office applications (e.g. Word, Excel, PowerPoint, etc.) and Chinese word processing;\nPreferable with basic knowledge of\u00a0Adobe Photoshop and Illustrator;\u00a0\nProficient in spoken English, Cantonese and Mandarin;\u00a0\nProficient in written English and Chinese;\u00a0\nGood interpersonal skills;\u00a0\nBe self-motivated, detail-minded and well-organized.\n\nInterested applicants should send the application letter and personal resume (indicating expected salary and date of employment) to The Hong Kong General Chamber of Young Entrepreneurs Secretariat before February 13, 2022 or click \"Apply Now\" application. If you apply by e-mail, the e-mail must indicate the name of the position you are applying for.\n\nThe Hong Kong General Chamber of Young Entrepreneurs (HKGCYE) is a non-profit organization founded in 2015 by a group of young and enthusiastic entrepreneurs. The founding board members were composed of winners from HSBC Youth Business Award and the Youth Business Hong Kong (YBHK) programme. All members of our chamber are local entrepreneurs age ranging from 18 to 45. The organization now has over 300 Hong Kong registered company members.\n\nOur main objectives:\n- To build a community to support Hong Kong young entrepreneurs\n- To foster entrepreneurship in Hong Kong and build a platform for information sharing\n- Regularly meet with government body and Mainland institutions, to work on policy initiatives for the benefits of Hong Kong Entrepreneurs\n- Schedule seminars with reputable business leaders to foster exchange of ideas and learnings\n- Connect Entrepreneurs from Hong Kong and the Greater Bay Area, to expand business network and opportunities", "employment_types": ["Full Time"], "selling_points": [], "locations": ["Kwun Tong"], "categories": ["Public / Civil", "Social Services - Community / Non-profit Organization"], "post_time": "2022-01-13T09:46:01Z", "salary": {"currency": null, "max": null, "min": null, "period": null, "term": null}, "salary_visible": false, "title_keywords": ["project officer"], "responsibilities": ["ad hoc duties", "administrative work", "coordinate", "reports", "liaise with", "planning"], "requirements": {"degrees": ["degree or above"], "majors": ["related disciplines", "marketing", "any disciplines", "communications"], "languages": ["cantonese", "english", "chinese", "mandarin"], "language_level": ["proficient"], "hard_skills": ["excel", "chinese word processing", "basic", "microsoft office", "adobe photoshop", "word", "powerpoint", "illustrator"], "soft_skills": ["detail-minded", "self-motivated", "well-organized", "interpersonal skills", "enthusiastic"], "languages_combined": [{"language": "cantonese", "language_level": ["proficient"]}, {"language": "english", "language_level": ["proficient", "proficient"]}, {"language": "chinese", "language_level": ["proficient"]}, {"language": "mandarin", "language_level": ["proficient"]}]}, "experience_required": {"duration": [], "field": []}}, {"job_id": "100003009047391", "location_code": "hk", "company": "Christian Family Service Centre", "job_title": "Project Officer (M3-SCGS/SKGS)", "description": "Requirements:\u00a0 \u00a0\n\nA Diploma or above holder in Environmental Science / Education / Communication / Social Science / Marketing or any relevant discipline, preferably with a University Degree and 3 years working experience;\nEnglish Language (Syllabus B) and Chinese Language at Grade E or above in HKCEE/Level 2 in HKDSE;\nSound knowledge of local environmental issues, especially in waste reduction, is preferred;\nExperience in developing and organising public educational programmes, events, demonstrations and/or workshops is preferred;\nFamiliar with photo and graphic editing software, such as Adobe Photoshop and Illustrator, will be an advantage;\nCandidates with lower academic qualification or less experience will be considered for a post at a lower rank.\nJob\u00a0Duties:\n\nTo coordinate the planning, content development, liaison, promotion and implementation of educational mass programmes, events and activities related to environmental protection and waste management;\nTo coordinate the design and production of the publicity and education materials, and the management of social media platforms;\nTo engage and liaise with stakeholders in the communities to facilitate the promotion and implementation of the programmes / events / activities;\nTo supervise junior and part-time staff;\nTo perform other tasks pertaining to the work as assigned.\n\nWorking Hours:\u00a045 hours per week and work on weekend when necessary\u00a0 \u00a0\nWorking Location:\u00a0\u00a0Shatin District and Sai Kung District\u00a0\u00a0\n\nPlease send your application letter quoting our job reference code together with a full resume, available date, last and expected salary by post to the Human Resources Department at 10/F, 3 Tsui Ping Road, Kwun Tong, Kowloon or by email via \"Apply Now\".\nProspective employees who will undertake child or mentally incapacitated persons related work will be requested to undergo the Sexual Conviction Record Check (SCRC).\nApplicants not hearing from us within two months from the date of advertisement may consider their applications fail.\nAll personal data of unsuccessful candidates would be destroyed after 6 months of interview and after 3 months of receiving applications for those without interview.\nPersonal data provided by job applicants will be used for recruitment purpose for different posts in the Agency only.", "employment_types": ["Full Time"], "selling_points": [], "locations": ["Not Specified"], "categories": ["Sciences, Lab, R&D", "Environmental Science / Waste Management", "Marketing / Public Relations", "Public Relations - Event Management", "Public / Civil", "Social Services - Community / Non-profit Organization"], "post_time": "2022-01-14T02:58:22Z", "salary": {"currency": null, "max": null, "min": null, "period": "monthly", "term": null}, "salary_visible": false, "title_keywords": ["project officer"], "responsibilities": ["management", "social media platforms", "implementation", "design", "coordinate", "other tasks", "recruitment", "liaise with", "personal data", "planning"], "requirements": {"degrees": ["university degree", "hkdse", "diploma or above"], "majors": ["science", "environmental science", "marketing"], "languages": ["english", "chinese"], "language_level": [], "hard_skills": ["workshops", "adobe photoshop", "illustrator"], "soft_skills": ["communication"], "languages_combined": [{"language": "english", "language_level": []}, {"language": "chinese", "language_level": []}]}, "experience_required": {"duration": ["3 years"], "field": ["marketing", "environmental", "developing", "education"]}}, {"job_id": "100003009047795", "location_code": "hk", "company": "Tung Wah Group of Hospitals", "job_title": "\u5eb6\u52d9\u54e1(\u5f8c\u52e4)(\u8077\u4f4d\u7de8\u865f\uff1aA3/GA(L)/BCAD/JOBS)", "description": "\u5de5\u4f5c\u5730\u9ede\uff1a\u4e0a\u74b0\n\u8077\u8cac\uff1a\n\u8ca0\u8cac\u884c\u653f\u5927\u6a13\u5404\u90e8\u9580\u7684\u9ad4\u529b\u52de\u52d5\u5de5\u4f5c\u53ca\u642c\u904b\u96dc\u7269\uff1b\u5354\u52a9\u50b3\u905e\u6a13\u5c64\u6587\u4ef6\u53ca\u5916\u51fa\u6536\u9001\u6587\u4ef6\uff1b\u8ca0\u8cac\u6536\u9001\u9322\u7bb1\u53ca\u5354\u52a9\u9ede\u7b97\u9322\u7bb1\u6350\u6b3e\uff1b\u5354\u52a9\u6703\u8b70\u5ba4\u3001\u6176\u5178\u3001\u5100\u5f0f\u53ca\u5176\u4ed6\u5834\u5730\u4f48\u7f6e\uff1b\u5354\u52a9\u8655\u7406\u7c21\u55ae\u97f3\u97ff\u5de5\u4f5c\uff1b\u8ca0\u8cac\u8655\u7406\u8336\u6c34\u53ca\u6e05\u6f54\u5de5\u4f5c\uff1b\u5354\u52a9\u8655\u7406\u7c21\u55ae\u6587\u66f8\u5de5\u4f5c\u53ca\u57f7\u884c\u4e0a\u53f8\u6307\u5b9a\u7684\u5176\u4ed6\u5de5\u4f5c\u3002\n\u7406\u60f3\u7684\u7533\u8acb\u8005\u61c9\u5177\u5099\uff1a\n\u5b8c\u6210\u5c0f\u5b78\u7a0b\u5ea6\uff0c\u80fd\u95b2\u8b80\u7c21\u55ae\u4e2d\u82f1\u6587\uff0c\u64cd\u6d41\u5229\u7cb5\u8a9e\u3002\u5177\u76f8\u95dc\u5de5\u4f5c\u7d93\u9a57\u8005\u5c07\u7372\u512a\u5148\u8003\u616e\u3002\n\u85aa\u916c\u53ca\u8058\u7528\u689d\u4ef6\uff1a\n\u7372\u9078\u7684\u7533\u8acb\u4eba\u5c07\u4ee5\u5408\u7d04\u689d\u6b3e\u53d7\u8058\u3002\u6709\u95dc\u85aa\u91d1\u6703\u6309\u5e74\u5c31\u54e1\u5de5\u7684\u8868\u73fe\u53ca\u6771\u83ef\u898f\u5b9a\u800c\u5411\u4e0a/\u4e0b\u8abf\u6574\u6216\u51cd\u7d50\u3002\u54e1\u5de5\u798f\u5229\u5305\u62ec\u6709\u85aa\u5047\u671f\u3001\u9032\u4fee\u6d25\u8cbc\u3001\u91ab\u7642\u53ca\u7259\u9f52\u4fdd\u5065\u3002\u4efb\u8077\u8005\u5c07\u6309\u4e94\u5929\u5de5\u4f5c\u5468\u5b89\u6392\u4e0a\u73ed\uff0c\u60df\u4ecd\u9808\u8996\u4e4e\u90e8\u9580\u904b\u4f5c\u53ca\u670d\u52d9\u9700\u8981\u800c\u5b9a\u3002\n\u7533\u8acb\u7a0b\u5e8f\uff1a\n\u8acb\u5c07\u500b\u4eba\u5c65\u6b77\u6216\u586b\u59a5\u7533\u8acb\u8868\u683c<\u8868\u865f\uff1aF601(n)>(\u53ef\u89aa\u81e8\u7d22\u53d6\u6216\u5f9e\u672c\u9662\u7684\u7db2\u9801http://www.tungwah.org.hk\u4e0b\u8f09)\u4e26\u5217\u660e\u73fe\u6642\u53ca\u8981\u6c42\u85aa\u916c\u5f85\u9047\uff0c\u65bc\u4e8c\uff10\u4e8c\u4e8c\u5e74\u4e8c\u6708\u5341\u56db\u65e5\u524d\u5bc4\u9999\u6e2f\u4e0a\u74b0\u666e\u4ec1\u8857\u5341\u4e8c\u865f\u6771\u83ef\u4e09\u9662\u9ec3\u9cf3\u7fce\u7d00\u5ff5\u5927\u6a13\u56db\u6a13\u4eba\u529b\u8cc7\u6e90\u79d1\u4e3b\u7ba1\u6536\uff0c\u4fe1\u5167\u53ca\u4fe1\u5c01\u9762\u8acb\u8a3b\u660e\u7533\u8acb\u7684\u8077\u4f4d\u53ca\u8077\u4f4d\u7de8\u865f\u3002\u6771\u83ef\u4e09\u9662\u4e0d\u6703\u63a5\u6536\u90f5\u8cc7\u4e0d\u8db3\u7684\u4fe1\u4ef6\u3002\u70ba\u78ba\u4fdd\u90f5\u905e\u7121\u8aa4\uff0c\u8acb\u5728\u6295\u5bc4\u90f5\u4ef6\u6642\u652f\u4ed8\u8db3\u984d\u90f5\u8cc7\u53ca\u8a3b\u660e\u56de\u90f5\u5730\u5740\u3002\u6771\u83ef\u4e09\u9662\u5728\u4f7f\u7528\u6c42\u8077\u8005\u63d0\u4f9b\u7684\u500b\u4eba\u8cc7\u6599\u6642\uff0c\u53ea\u6703\u5c07\u8cc7\u6599\u4f5c\u6709\u95dc\u62db\u8058\u7528\u9014\uff0c\u4e26\u6703\u56b4\u683c\u9075\u5b88\u9662\u65b9\u500b\u4eba\u8cc7\u6599\u653f\u7b56\u7684\u898f\u5b9a\u3002\u51e1\u65bc\u4e8c\uff10\u4e8c\u4e8c\u5e74\u4e94\u6708\u4e09\u5341\u4e00\u65e5\u524d\u672a\u7372\u7d04\u898b\u8005\uff0c\u53ef\u4f5c\u843d\u9078\u8ad6\u3002\n\u6211\u5011\u662f\u5e73\u7b49\u6a5f\u6703\u50f1\u4e3b", "employment_types": ["Full Time", "Contract"], "selling_points": [], "locations": ["Sheung Wan"], "categories": ["Public / Civil", "Social Services - Community / Non-profit Organization", "Others", "Others"], "post_time": "2022-01-17T08:55:54Z", "salary": {"currency": null, "max": null, "min": null, "period": "monthly", "term": null}, "salary_visible": false, "title_keywords": [], "responsibilities": [], "requirements": {"degrees": [], "majors": [], "languages": [], "language_level": [], "hard_skills": [], "soft_skills": [], "languages_combined": []}, "experience_required": {"duration": [], "field": []}}, {"job_id": "100003009044947", "location_code": "hk", "company": "St. James' Settlement", "job_title": "\u9805\u76ee\u4e3b\u4efb (PO I) (\u5408\u7d04)\u3008\u7de8\u865f:RS/05122\u3009", "description": "\u8981\u6c42\ufe30\n\n\u5e02\u5834\u5b78/\u5546\u696d\u7ba1\u7406\u5b78\u4f4d\u4ee5\u4e0a\u7a0b\u5ea6\uff0c\u4e2d\u5b78\u6703\u8003\u4e94\u79d1\u5408\u683c\uff0c\u5305\u62ec\u4e2d\u3001\u82f1\u6587(\u4e59)\u6216\u7b49\u540c\n\u51772\u5e74\u5546\u696d\u7ba1\u7406 / \u6728\u5de5 / \u5de5\u85dd\u5de5\u4f5c\u7d93\u9a57\u512a\u5148\n\u6027\u683c\u6210\u719f\u3001\u4e3b\u52d5\u3001\u80fd\u7368\u7acb\u8655\u4e8b\n\n\u8077\u8cac\ufe30\n\n\u6307\u5c0e\u5fa9\u5eb7\u4eba\u58eb\u6728\u5de5 / \u5de5\u85dd\u696d\u52d9\n\u5354\u52a9\u958b\u62d3\u53ca\u767c\u5c55\u793e\u6703\u4f01\u696d\n\u5de5\u4f5c\u5730\u9ede\uff1a(\u65e5\u9593\u670d\u52d9)\u6e2f\u5cf6\u5340\n\n\u6709\u610f\u8005\u8acb\u65bc26/01/2022\u6216\u4e4b\u524d\uff0c\u51fd\u9644\u5c65\u6b77\u6309\u201cAPPLY NOW\u201d\uff0c\u6216\u90f5\u5bc4\u81f3\u7063\u4ed4\u5805\u5c3c\u5730\u9053100\u865f13\u6a13\u3002\u8acb\u8a3b\u660e\u8077\u4f4d\u7de8\u865f\u3002", "employment_types": ["Full Time", "Contract"], "selling_points": ["\u5e02\u5834\u5b78/\u5546\u696d\u7ba1\u7406\u5b78\u4f4d\u4ee5\u4e0a\u7a0b\u5ea6\uff0c\u4e2d\u5b78\u6703\u8003\u4e94\u79d1\u5408\u683c\uff0c\u5305\u62ec\u4e2d\u3001\u82f1\u6587(\u4e59)\u6216\u7b49\u540c", "\u51772\u5e74\u5546\u696d\u7ba1\u7406 / \u6728\u5de5 / \u5de5\u85dd\u5de5\u4f5c\u7d93\u9a57\u512a\u5148", "\u6027\u683c\u6210\u719f\u3001\u4e3b\u52d5\u3001\u80fd\u7368\u7acb\u8655\u4e8b"], "locations": ["Wan Chai Area"], "categories": ["Public / Civil", "Social Services - Community / Non-profit Organization"], "post_time": "2022-01-13T06:43:08Z", "salary": {"currency": null, "max": null, "min": null, "period": "monthly", "term": null}, "salary_visible": false, "title_keywords": ["\u9805\u76ee\u4e3b\u4efb"], "responsibilities": [], "requirements": {"degrees": [], "majors": [], "languages": [], "language_level": [], "hard_skills": [], "soft_skills": [], "languages_combined": []}, "experience_required": {"duration": [], "field": []}}, {"job_id": "100003009034927", "location_code": "hk", "company": "Be Priceless Limited", "job_title": "Counselor/ Educator for Be Priceless for summer onwards (English and Chinese/Urdu/Nepali//Bahasa)", "description": "Role: Counselor/ Educator for Be Priceless, an educational non-profit organization that strengthens disadvantaged children\u2019s well-being and safety.\n\nSeeking candidate with a passion to empower and serve disadvantaged communities and has extensive experience in teaching and school counseling or social work, as well as service to vulnerable children. Short term contract for school summer break 2022.\u00a0\n\n\nJob Highlight:\n\nOpportunity to drive the development of an educational program that serves disadvantaged children and youth during 2022 summer break\nDrive the coordination and collaboration with diverse professionals, community members, child and youth in empowering ways\nBe part of an innovative and dynamic team of multisectoral professionals and community members.\nEmpowering, positive, collaborative organizational culture\n\n\u00a0Key Jobs Responsibilities\n\nCoordinate and implement the Be Priceless educational program (which builds capacity for growth, well-being and safety of children), including creation of content, teaching, evaluation and keep improving the SEED courses.\nManage the educational and well-being program development. This includes facilitating collaboration of volunteers, consultant and staff from diverse backgrounds and expertise.\nFoster stakeholder\u2019s engagement and collaboration\u2013 including children, youth, caregivers, multi-disciplinary professionals, schools, non-profit organization.\n\nJob Requirement:\n\nPassionate and dedicated in promoting child and youth well-being and protection.\nAt least 3 years of relevant experience in education and counselling role in reputable organization/School.\nDegree in education, psychology, social work or related field\nExperienced in creating educational program for children of 5-17 years old that promotes social-emotional learning, well-being, safety and inclusion.\u00a0\nExperienced in developing and implementing e-learning educational programs.\nExperienced in team, project and resource management\nAdaptive, flexible and collaborative\nStrong ethical and professional standard - including accountability, transparency.\nStrong collaboration, coordination and problem solving skills.\nStrong communication, productivity, organization and time management skills.\nSocial media management proficiency\nProfessional level\u00a0written and spoken English\u00a0\nAdditional professional level written and spoken 1 of the following languages is required: Chinese, Nepali, Urdu, Hindi, Tagalog, or Bahasa.\nUndergoing regular background checks (including\u00a0Sexual\u00a0Conviction Record\u00a0Check\u00a0(SCRC)\u00a0 and previous employment checks) and abiding to code of conduct including for child safeguarding-protection are an absolute requirements. We have continuous and rigorous monitoring of issues of concerns safety of children and other vulnerable individuals. We will investigate/ report where appropriate.\n\nLogistics:\u00a0Full-time contract base, candidate must be in Hong Kong\nDuration: Summer program and beyond, to be extended to long-term contract if performance is outstanding\nSalary: based on experience\u00a0\n\nPlease apply with\u00a0your full resume, cover letter, time availability. and expected salary.", "employment_types": ["Full Time", "Contract"], "selling_points": ["Educator, School Counselor, Non-profit", "Empower disadvantaged children, well-being, safety", "competitive salary"], "locations": ["Central"], "categories": ["Public / Civil", "Counseling", "Education", "Teacher", "Social Services - Community / Non-profit Organization"], "post_time": "2022-01-13T18:54:45Z", "salary": {"currency": null, "max": null, "min": null, "period": "monthly", "term": null}, "salary_visible": false, "title_keywords": [], "responsibilities": ["coordinate", "evaluation"], "requirements": {"degrees": ["degree"], "majors": ["social work", "psychology"], "languages": ["english", "urdu", "hindi", "tagalog", "nepali", "chinese"], "language_level": [], "hard_skills": ["code", "problem solving skills"], "soft_skills": ["passionate", "flexible", "accountability", "time management skills", "collaborative", "communication", "learning", "ethical", "coordination", "problem solving skills"], "languages_combined": [{"language": "english", "language_level": []}, {"language": "urdu", "language_level": []}, {"language": "hindi", "language_level": []}, {"language": "tagalog", "language_level": []}, {"language": "nepali", "language_level": []}, {"language": "chinese", "language_level": []}]}, "experience_required": {"duration": ["at least 3 years"], "field": ["relevant experience", "education"]}}, {"job_id": "100003009045993", "location_code": "hk", "company": "Hong Kong Sheng Kung Hui Welfare Council Limited", "job_title": "\u884c\u653f\u52a9\u7406 Administration Assistant (Ref: PGR/AA/20211203-7)", "description": "\u689d\u4ef6\ufe30\n\n\u5927\u5c08\u7a0b\u5ea6\u6216\u4ee5\u4e0a\n\u4e2d\u5b78\u6703\u8003\u4e94\u79d1\u5408\u683c(\u5305\u62ec\u4e2d\u6587\u53ca\u82f1\u6587(\u8ab2\u7a0b\u4e59))\u6216\u4ee5\u4e0a\u6216\u4e2d\u5b78\u6587\u6191\u8003\u8a66\u540c\u7b49\u7b49\u7d1a\n\u719f\u6089\u4e2d\u82f1\u6587\u96fb\u8166\u6587\u66f8\u8655\u7406\n\u5177\u4e00\u5e74\u6216\u4e0a\u884c\u653f\u6216\u76f8\u95dc\u5de5\u4f5c\u7d93\u9a57\n\n\u8077\u8cac\ufe30\n\n\u8ca0\u8cac\u6587\u66f8\u5de5\u4f5c\u3001\u6a94\u6848\u53ca\u8cc7\u7522\u7ba1\u7406\u3001\u6578\u5b57\u7d71\u8a08\u3001\u4eba\u529b\u8cc7\u6e90\u53ca\u884c\u653f\u7b49\u76f8\u95dc\u5de5\u4f5c\u3002\n\n\u5168\u8077\u54e1\u5de5\u53ef\u4eab\u6709\u4ee5\u4e0b\u5b8c\u5584\u798f\u5229\uff1a\n\u53ef\u4eab\u6709\u6709\u85aa\u5e74\u504714\u5929\u3001\u516c\u773e\u5047\u671f17\u5929\u3001\u5a5a\u5047\u3001\u5206\u5a29\u5047\u3001\u6069\u6064\u5047\u3001\u4f8d\u7522\u5047\u3001\u8d85\u6642\u5de5\u4f5c\u88dc\u5047\u3001\u514d\u8cbb\u9ad4\u6aa2\u3001\u91ab\u7642\u4fdd\u96aa\u3001\u4eba\u58fd\u4fdd\u96aa\u3001\u91ab\u7642\u512a\u60e0\u3001\u50f1\u4e3b\u5f37\u7a4d\u91d1\u4f9b\u6b3e\u6309\u5e74\u8cc7\u6700\u9ad8\u53ef\u905e\u589e\u81f315%\u3001\u5728\u8077\u57f9\u8a13\u53ca\u826f\u597d\u6649\u5347\u968e\u68af\u7b49\u3002\n\n\u6709\u610f\u8005\u8acb\u5177\u5c65\u6b77\u53ca\u5217\u660e\u671f\u671b\u85aa\u916c\u5bc4\ufe30\u65b0\u754c\u5c6f\u9580\u9707\u5bf0\u8def82\u865f \u2013 \u5eb7\u6069\u5712\u4eba\u529b\u8cc7\u6e90\u53ca\u884c\u653f\u7d93\u7406\u6536\u6216\u6309\"Apply Now\"\u3002\u7533\u8acb\u4eba\u4e4b\u7be9\u9078\u5c07\u6703\u5373\u6642\u9032\u884c\u76f4\u81f3\u4e8c\u96f6\u4e8c\u4e8c\u5e74\u4e00\u6708\u4e8c\u5341\u516b\u65e5\u6216\u6709\u95dc\u8077\u4f4d\u7a7a\u7f3a\u5df2\u88ab\u586b\u88dc\u70ba\u6b62\u3002\n\n\u4e00\u5207\u7533\u8acb\u8cc7\u6599\u7d55\u5c0d\u4fdd\u5bc6\u53ca\u53ea\u7528\u4f5c\u62db\u8058\u6709\u95dc\u8077\u4f4d\u3002\u5982\u7533\u8acb\u8005\u5728\u622a\u6b62\u65e5\u671f\u5f8c\u516b\u661f\u671f\u5167\u4ecd\u672a\u7372\u96fb\u8a71\u7d04\u898b\u8005\uff0c\u5176\u7533\u8acb\u53ef\u4f5c\u843d\u9078\u8ad6\uff0c\u6055\u4e0d\u53e6\u51fd\u901a\u77e5\uff0c\u672c\u798f\u5229\u5354\u6703\u5c07\u4fdd\u5b58\u7533\u8acb\u6587\u4ef6\u4e0d\u8d85\u904e\u516d\u500b\u6708\u3002\u5982\u6b32\u53c3\u8003\u5354\u6703\u8cc7\u6599\uff0c\u8acb\u767b\u5165\u7db2\u5740:\u00a0http://www.skhwc.org.hk", "employment_types": ["Full Time", "Contract"], "selling_points": [], "locations": ["Tuen Mun Area"], "categories": ["Admin & HR", "Clerical / Admin Staff", "Public / Civil", "Social Services - Community / Non-profit Organization"], "post_time": "2022-01-13T18:55:10Z", "salary": {"currency": null, "max": null, "min": null, "period": "monthly", "term": null}, "salary_visible": false, "title_keywords": ["administration assistant", "\u884c\u653f\u52a9\u7406"], "responsibilities": [], "requirements": {"degrees": [], "majors": [], "languages": [], "language_level": [], "hard_skills": [], "soft_skills": [], "languages_combined": []}, "experience_required": {"duration": [], "field": []}}, {"job_id": "100003009056228", "location_code": "hk", "company": "St. James' Settlement", "job_title": "\u793e\u5340\u8b77\u58eb (RN) (\u5408\u7d04)\u3008\u7de8\u865f: ETCMT/07022\u3009", "description": "\u8981\u6c42\ufe30\n\n\u6301\u9999\u6e2f\u8a3b\u518a\u8b77\u58eb\u8b49\u66f8\u53ca\u6709\u6548\u57f7\u696d\u8b49\u66f8\n\u4e2d\u5b78\u6703\u8003\u4e94\u79d1\u5408\u683c\uff0c\u5305\u62ec\u4e2d\u3001\u82f1\u6587(\u4e59)\u6216\u7b49\u540c\n\n\u8077\u8cac\ufe30\n\n\u70ba\u5c45\u5bb6\u9577\u8005\u57f7\u884c\u8b77\u7406\u5de5\u4f5c\n\u5354\u52a9\u7b56\u5283\u53ca\u767c\u5c55\u793e\u5340\u8b77\u7406\u670d\u52d9\u4e26\u63a8\u52d5\u6709\u95dc\u5de5\u4f5c\n\u63d0\u4f9b\u7167\u9867\u54e1\u57f9\u8a13\u53ca\u76e3\u5bdf\u8b77\u7406\u6c34\u5e73\n\u6bcf\u903144\u5c0f\u6642\u5de5\u4f5c\n\u5de5\u4f5c\u5730\u9ede\uff1a\u6771\u5340\n\n\u6709\u610f\u8005\u8acb\u65bc18/02/2022\u6216\u4e4b\u524d\uff0c\u51fd\u9644\u5c65\u6b77\u6309\u00a0\u201cAPPLY NOW\u201d\uff0c\u6216\u90f5\u5bc4\u81f3\u9999\u6e2f\u5317\u89d2\u82f1\u7687\u9053373\u865f\u4e0a\u6f64\u4e2d\u5fc311\u6a13d\u5ba4\u3002", "employment_types": ["Full Time", "Contract"], "selling_points": ["\u6301\u9999\u6e2f\u8a3b\u518a\u8b77\u58eb\u8b49\u66f8\u53ca\u6709\u6548\u57f7\u696d\u8b49\u66f8", "\u4e2d\u5b78\u6703\u8003\u4e94\u79d1\u5408\u683c\uff0c\u5305\u62ec\u4e2d\u3001\u82f1\u6587(\u4e59)\u6216\u7b49\u540c", "\u70ba\u5c45\u5bb6\u9577\u8005\u57f7\u884c\u8b77\u7406\u5de5\u4f5c"], "locations": ["Eastern Area"], "categories": ["Public / Civil", "Social Services - Community / Non-profit Organization"], "post_time": "2022-01-18T03:39:45Z", "salary": {"currency": null, "max": null, "min": null, "period": "monthly", "term": null}, "salary_visible": false, "title_keywords": [], "responsibilities": [], "requirements": {"degrees": [], "majors": [], "languages": [], "language_level": [], "hard_skills": [], "soft_skills": [], "languages_combined": []}, "experience_required": {"duration": [], "field": []}}, {"job_id": "100003009047782", "location_code": "hk", "company": "Tung Wah Group of Hospitals", "job_title": "\u5eb6\u52d9\u54e1(\u6e05\u6f54)(\u8077\u4f4d\u7de8\u865f\uff1aA3/GA(C)/BCAD/JOBS)", "description": "\u5de5\u4f5c\u5730\u9ede\uff1a\u4e0a\u74b0\n\u8077\u8cac\uff1a\n\u8ca0\u8cac\u884c\u653f\u5927\u6a13\u7684\u6e05\u6f54\u53ca\u8336\u6c34\u5de5\u4f5c\u3001\u6587\u4ef6\u7684\u50b3\u9001\u3001\u7c21\u55ae\u7684\u6587\u66f8\u53ca\u4e00\u822c\u5eb6\u52d9\u5de5\u4f5c\u3002\n\u7406\u60f3\u7684\u7533\u8acb\u8005\u61c9\u5177\u5099\uff1a\n\u5b8c\u6210\u5c0f\u5b78\u7a0b\u5ea6\uff0c\u80fd\u95b2\u8b80\u7c21\u55ae\u4e2d\u82f1\u6587\uff0c\u64cd\u6d41\u5229\u7cb5\u8a9e\u3002\u5177\u76f8\u95dc\u5de5\u4f5c\u7d93\u9a57\u8005\u5c07\u7372\u512a\u5148\u8003\u616e\u3002\n\u85aa\u916c\u53ca\u8058\u7528\u689d\u4ef6\uff1a\n\u7372\u9078\u7684\u7533\u8acb\u4eba\u5c07\u4ee5\u5408\u7d04\u689d\u6b3e\u53d7\u8058\u3002\u6709\u95dc\u85aa\u91d1\u6703\u6309\u5e74\u5c31\u54e1\u5de5\u7684\u8868\u73fe\u53ca\u6771\u83ef\u898f\u5b9a\u800c\u5411\u4e0a/\u4e0b\u8abf\u6574\u6216\u51cd\u7d50\u3002\u54e1\u5de5\u798f\u5229\u5305\u62ec\u6709\u85aa\u5047\u671f\u3001\u9032\u4fee\u6d25\u8cbc\u3001\u91ab\u7642\u53ca\u7259\u9f52\u4fdd\u5065\u3002\u4efb\u8077\u8005\u5c07\u6309\u4e94\u5929\u5de5\u4f5c\u5468\u5b89\u6392\u4e0a\u73ed\uff0c\u60df\u4ecd\u9808\u8996\u4e4e\u90e8\u9580\u904b\u4f5c\u53ca\u670d\u52d9\u9700\u8981\u800c\u5b9a\u3002\n\u7533\u8acb\u7a0b\u5e8f\uff1a\n\u8acb\u5c07\u500b\u4eba\u5c65\u6b77\u6216\u586b\u59a5\u7533\u8acb\u8868\u683c<\u8868\u865f\uff1aF601(n)>(\u53ef\u89aa\u81e8\u7d22\u53d6\u6216\u5f9e\u672c\u9662\u7684\u7db2\u9801http://www.tungwah.org.hk\u4e0b\u8f09)\u4e26\u5217\u660e\u73fe\u6642\u53ca\u8981\u6c42\u85aa\u916c\u5f85\u9047\uff0c\u65bc\u4e8c\uff10\u4e8c\u4e8c\u5e74\u4e8c\u6708\u5341\u56db\u65e5\u524d\u5bc4\u9999\u6e2f\u4e0a\u74b0\u666e\u4ec1\u8857\u5341\u4e8c\u865f\u6771\u83ef\u4e09\u9662\u9ec3\u9cf3\u7fce\u7d00\u5ff5\u5927\u6a13\u56db\u6a13\u4eba\u529b\u8cc7\u6e90\u79d1\u4e3b\u7ba1\u6536\uff0c\u4fe1\u5167\u53ca\u4fe1\u5c01\u9762\u8acb\u8a3b\u660e\u7533\u8acb\u7684\u8077\u4f4d\u53ca\u8077\u4f4d\u7de8\u865f\u3002\u6771\u83ef\u4e09\u9662\u4e0d\u6703\u63a5\u6536\u90f5\u8cc7\u4e0d\u8db3\u7684\u4fe1\u4ef6\u3002\u70ba\u78ba\u4fdd\u90f5\u905e\u7121\u8aa4\uff0c\u8acb\u5728\u6295\u5bc4\u90f5\u4ef6\u6642\u652f\u4ed8\u8db3\u984d\u90f5\u8cc7\u53ca\u8a3b\u660e\u56de\u90f5\u5730\u5740\u3002\u6771\u83ef\u4e09\u9662\u5728\u4f7f\u7528\u6c42\u8077\u8005\u63d0\u4f9b\u7684\u500b\u4eba\u8cc7\u6599\u6642\uff0c\u53ea\u6703\u5c07\u8cc7\u6599\u4f5c\u6709\u95dc\u62db\u8058\u7528\u9014\uff0c\u4e26\u6703\u56b4\u683c\u9075\u5b88\u9662\u65b9\u500b\u4eba\u8cc7\u6599\u653f\u7b56\u7684\u898f\u5b9a\u3002\u51e1\u65bc\u4e8c\uff10\u4e8c\u4e8c\u5e74\u4e94\u6708\u4e09\u5341\u4e00\u65e5\u524d\u672a\u7372\u7d04\u898b\u8005\uff0c\u53ef\u4f5c\u843d\u9078\u8ad6\u3002\n\u6211\u5011\u662f\u5e73\u7b49\u6a5f\u6703\u50f1\u4e3b", "employment_types": ["Full Time", "Contract"], "selling_points": [], "locations": ["Sheung Wan"], "categories": ["Admin & HR", "Others", "Public / Civil", "Social Services - Community / Non-profit Organization", "Others"], "post_time": "2022-01-17T08:55:07Z", "salary": {"currency": null, "max": null, "min": null, "period": "monthly", "term": null}, "salary_visible": false, "title_keywords": [], "responsibilities": [], "requirements": {"degrees": [], "majors": [], "languages": [], "language_level": [], "hard_skills": [], "soft_skills": [], "languages_combined": []}, "experience_required": {"duration": [], "field": []}}, {"job_id": "100003009050077", "location_code": "hk", "company": "Yew Chung College of Early Childhood Education Limited", "job_title": "Project Manager", "description": "Position Summary\n\nYCCECE is commissioned to drive a large scale funded project.\u00a0 The Project\u2019s vision is to create and implement a nurturing care model comprises a 0-3 years educate framework, capacity building of practitioners and families, and a digital platform that facilitates home-centre communication. The new model aims to enhance professional practice, infrastructure and overall quality of Child Care Centres in Hong Kong. In addition, the project will cultivate a learning community that encourages and empowers knowledge transfer for sustainable development of holistic nurturing care.\n\nTo actualise this vision, it is crucial to support the operation of various events serving different stakeholders. The job holders will perform the following duties:\n\nEnsure that all project outcomes and outputs are delivered on-time, within scope and within budget;\nDevelop and implement a detailed project plan to monitor and track progress of various project components simultaneously ;\nManage changes to the project scope, project schedule and project costs for the rapid changes in the society;\nActively obtain and coordinate internal resources and third parties/vendors for a smooth implementation of the Project;\nCreate synergy among the Project team and stakeholders (e.g. funder, partnership schools);\nCreate and maintain project documentation, including administrative and budget documents requested by the funder; and\nPerform any other duties as required by the College.\n\nRequirements\n\nThe successful candidate should possess a higher degree, and have teaching and programme leadership or management experience in the education industry.\u00a0\n\nA Bachelor's degree in Social Sciences or Education preferred\nAt least 5 years of proven working experience project management\nExcellent written and verbal communication skills in English and Chinese\nOutstanding project management knowledge and skills, Project Management Professional (PMP) or any equivalent qualifications is a plus\nExperience in managing projects in education or non-profit making sectors is a plus\nProficiency in Microsoft Office and other project management tools (e.g. Trello, Microsoft Planner)\nBe comfortable working with a team of self-driven professionals who value competence and efficiency\n\nSalary and Fringe Benefits:\n\nAppointment will be made on contract basis.\u00a0 Remuneration is competitive and will be based on qualifications and relevant experience. The College offers group medical insurance, annual leave and sick leave, and Mandatory Provident Fund to eligible appointee.\n\nApplication Procedure:\n\nApplicants are invited to:\n\nSubmit an application letter with a full Curriculum Vitae, and copies of all graduate transcripts, and the names and contact details of three references.\nSpecify in the application letter current/latest salary and expected salary\nSend applications to the Yew Chung College of Early Childhood Education by clicking below \"Apply Now\" button.\n\nThe College will review applications immediately.\u00a0 Only shortlisted candidates will be contacted.\n\nImportant notes to Applicants:\n\nAppointees will have to undergo a medical examination.\u00a0 Reimbursement of costs subject to a ceiling is applicable.\nLocal applicants will have to undergo a Sexual Conviction Record Check. Overseas applicants will have to present a police report before appointment can be confirmed.\u00a0\nSatisfactory employment reference is required before appointment can be confirmed.\n\nThe College also reserves the right to make an appointment by invitation.\n\nPersonal data collected will be used for recruitment-related purposes only.", "employment_types": ["Full Time", "Contract"], "selling_points": ["Project for 0-3 years education framework", "Project Management", "Experience in managing projects in education"], "locations": ["Aberdeen"], "categories": ["Admin & HR", "Administration / Operation Manager", "Management", "General Management", "Public / Civil", "Social Services - Community / Non-profit Organization"], "post_time": "2022-01-14T09:44:14Z", "salary": {"currency": null, "max": null, "min": null, "period": "monthly", "term": null}, "salary_visible": false, "title_keywords": ["project manager"], "responsibilities": ["any other duties", "management", "infrastructure", "quality", "budget", "digital platform", "develop", "communication", "project plan", "monitor", "coordinate", "implementation", "schedule", "maintain", "project management", "costs", "project documentation"], "requirements": {"degrees": ["degree", "bachelor"], "majors": ["social sciences"], "languages": ["english", "chinese"], "language_level": ["excellent"], "hard_skills": ["planner", "plus", "project management professional", "microsoft office", "project management", "rapid", "documentation", "pmp"], "soft_skills": ["communication skills", "communication", "project management", "learning", "smooth", "leadership", "driven", "detailed"], "languages_combined": [{"language": "english", "language_level": ["excellent"]}, {"language": "chinese", "language_level": ["excellent"]}]}, "experience_required": {"duration": ["at least 5 years"], "field": ["project management", "management", "teaching", "education"]}}, {"job_id": "100003009052876", "location_code": "hk", "company": "Haven of Hope Christian Service", "job_title": "Deputy Home Manager (Ref : NH/DHM/JDB)", "description": "To assist the Home Manager in managing the operation of the Home as well as implementing the corporate policies\nTo oversee and ensure the clinical operation to be in high quality as well as to drive the continuous development of quality care service for elders\nDegree in Nursing or other disciplines with relevant registration & practicing certificate\nMinimum 5-10 years\u2019 post-registration experience in home setting of which at least 2 years should have involved in management and administration duties\nStrong leadership with serving heart and excellent interpersonal communication skills\nFluency in written and spoken Chinese and English\nAlign with the Vision, Mission and Core Values of the Haven of Hope Christian Service\nMainly work during daytime and working location at Haven of Hope Nursing Home\nPlease send full resume with expected salary and reference no. quoted to Haven of Hope Christian Service, Staff Engagement Department, 7 Haven of Hope Road, Tseung Kwan O, New Territories or via email by clicking \"Apply Now\", or via Whatsapp no. 6507 8148 (with reference no. quoted at the caption) on or before 5 February 2022. Only short-listed candidates will be notified.\nEnquiry: 2703 3227 (Phone); 6507 8148 (Whatsapp).\nFor details about our organization, please visit www.hohcs.org.hk.\nProspective employees are requested to undergo/submit Sexual Conviction Record Check for work relating to children or mentally incapacitated persons before employment. Data collected will be used for recruitment purpose only.\nThis advertisement should not be reproduced, in whole or in part, to other recruitment websites without our prior written permission.", "employment_types": ["Full Time", "Permanent"], "selling_points": [], "locations": ["Tseung Kwan O"], "categories": ["Medical Services", "Nursing", "Others", "Public / Civil", "Social Services - Community / Non-profit Organization"], "post_time": "2022-01-17T04:23:29Z", "salary": {"currency": null, "max": null, "min": null, "period": "monthly", "term": null}, "salary_visible": false, "title_keywords": ["home manager"], "responsibilities": ["management", "data", "policies", "quality", "communication", "recruitment", "administration"], "requirements": {"degrees": ["certificate", "degree"], "majors": ["nursing"], "languages": ["english", "chinese"], "language_level": ["fluency"], "hard_skills": ["hope", "whatsapp", "no"], "soft_skills": ["communication skills", "leadership", "interpersonal"], "languages_combined": [{"language": "english", "language_level": ["fluency"]}, {"language": "chinese", "language_level": ["fluency"]}]}, "experience_required": {"duration": ["at least 2 years", "minimum 5-10 years"], "field": ["management", "administration"]}}, {"job_id": "100003009045995", "location_code": "hk", "company": "Hong Chi Association", "job_title": "Assistant General Secretary (Ref.: AGS/15/01/22/JD)", "description": "The Candidate will:\n\nReport to the General Secretary, assist to formulate / implement the policies of the services projects and initiate new services development. His / her work will include but not limited to: professional leadership, service quality assurance, formulation of professional protocol, staff training and development, liaison with government departments and NGOs, and attending relevant Committees.\n\n\nRequirements:\n\n\nA degree in Social Work / Public Administration or above, preference will be given to candidates with rehabilitation studies\u00a0\nSolid 5 years\u2019 working experiences as senior management (social work officer equivalent or above) in rehabilitation services, experience in working with\u00a0people with intellectual disabilities will be an advantage\nAbility to work in collaboration / as a team with other professions for professional leadership and development\nDedication and commitment to serve the Mission of the Association\nAble to communicate effectively in written / spoken English, Chinese and Putonghua with a wide range of stakeholders including service users, caregivers, board members, government officials, funding bodies as well as the media\n\n\nPlease send the completed Job Application Form (can be downloaded from\u00a0https://www.hongchi.org.hk/uploads/form/App2B_Job_Application_Form(201906).pdf) and mark \u201cConfidential & Ref. No.\u201d to\u00a0Human Resources Office, Pinehill Village, Chung Nga Road, Nam Hang, Tai Po, N.T., Hong Kong\u00a0or by clicking \"Apply Now\".\n\n**Prospective employees are requested to undergo Sexual Conviction Record Check on voluntary basis**\n\u00a0(All data collected will be used for recruitment purposes only.)", "employment_types": ["Full Time", "Contract"], "selling_points": [], "locations": ["Tai Po Area"], "categories": ["Public / Civil", "Social Services - Community / Non-profit Organization", "Management", "Top Executives (CEO, CFO, CTO, GM, MD etc.)"], "post_time": "2022-01-15T01:23:19Z", "salary": {"currency": null, "max": null, "min": null, "period": "monthly", "term": null}, "salary_visible": false, "title_keywords": ["secretary", "assistant"], "responsibilities": ["rehabilitation", "data", "policies", "quality", "recruitment", "report", "senior management", "administration"], "requirements": {"degrees": ["degree"], "majors": ["social work", "public administration"], "languages": ["putonghua", "english", "chinese"], "language_level": [], "hard_skills": ["no"], "soft_skills": ["leadership"], "languages_combined": [{"language": "putonghua", "language_level": []}, {"language": "english", "language_level": []}, {"language": "chinese", "language_level": []}]}, "experience_required": {"duration": ["5 years"], "field": ["management"]}}, {"job_id": "100003009049491", "location_code": "hk", "company": "Perrett Laver Limited", "job_title": "Consultant / Associate Consultant  (5 days)", "description": "Perrett Laver is now seeking to hire a bright, dynamic and ambitious individual to join our fast-growing team in Central Hong Kong as Consultant / Associate Consultant.\n\nThese two roles all draw upon the intellectual skills necessary to grasp a complex brief; the research skills to identify people who are at the highest levels in their professions; the advocacy skills to engage such candidates; the motivation to serve our clients to the best of our abilities; and the capacity to work as part of a core project team and a wider corporate team. You will have a thirst for knowledge, a methodical mind-set that will enable you to carry out a comprehensive and global search of the talent pool, and high attention to detail.\n\nConsultants and Associate Consultants are the key drivers of Perrett Laver. The roles entail a high level of advocacy and sales primarily demonstrated through new business wins, success in pitches and personal performance in service-related interactions. Consultants are the primary contact for all clients and must possess managerial and leadership skills to manage internal project delivery teams. During interactions with both candidates and clients, the Consultant should have the ability to bring a depth of understanding and insight into corporate priorities and individual interactions, as well as building and retaining positive relationships to benefit the company.\n\nWe are seeking people with the following:\n\nOutstanding verbal and written communication skills in both English and Chinese;\nA track-record of winning new business and leading projects to success within annual revenue targets;\nA Master\u2019s degree or above;\nA strong sense of service and the drive to best support our clients and candidates;\nKnowledge and passion in education and non-profit sector ;\nAn intellectually curious mind-set;\nA shared commitment to the mission and values of Perrett Laver;\nSharp and rigorous analytical skills and attention to detail, particularly regarding the assessment of candidates;\nAbility to manage multiple projects and to prioritize workload;\nA willingness to work with flexible hours when needed;\nTenacious, committed and results-oriented;\nEnthusiastic and proactive;\nCollaborative, flexible and able to contribute to the development of a growing team;\nMinimum of 5 years work experience.\nDesirable\n\nA Graduate degree;\nFluent in Cantonese and Mandarin;\nExperience working within universities, academic organizations, schools or NGO.\n\nNo previous experience working in executive search is required. Perrett Laver will provide rigorous and systematic training for all new hires.\n\nTo Apply\n\nTo apply, please submit an up-to-date CV and Cover Letter via https://candidates.perrettlaver.com/vacancies/ , quoting reference HKPL/CON.", "employment_types": ["Full Time"], "selling_points": ["Higher Education and Research Leadership", "Senior Executive Recruitment Consultation", "best support our clients and candidates"], "locations": ["Central"], "categories": ["Professional Services", "Business Consultancy", "Marketing / Public Relations", "Marketing - Marketing Communication", "Public / Civil", "Social Services - Community / Non-profit Organization"], "post_time": "2022-01-14T08:47:50Z", "salary": {"currency": null, "max": null, "min": null, "period": "monthly", "term": null}, "salary_visible": false, "title_keywords": ["associate", "consultant"], "responsibilities": ["communication", "manage multiple projects", "teams", "contact"], "requirements": {"degrees": ["degree or above", "degree", "master"], "majors": [], "languages": ["cantonese", "english", "chinese", "mandarin"], "language_level": ["fluent"], "hard_skills": ["no", "dynamic", "analytical skills"], "soft_skills": ["leadership skills", "collaborative", "comprehensive", "tenacious", "systematic", "committed", "communication skills", "passion in", "prioritize", "analytical skills", "dynamic", "attention to detail", "enthusiastic", "positive", "flexible", "research skills", "willingness to work", "methodical", "proactive"], "languages_combined": [{"language": "cantonese", "language_level": ["fluent"]}, {"language": "english", "language_level": []}, {"language": "chinese", "language_level": []}, {"language": "mandarin", "language_level": ["fluent"]}]}, "experience_required": {"duration": ["minimum of 5 years"], "field": []}}, {"job_id": "100003009048759", "location_code": "hk", "company": "Hong Kong Red Cross", "job_title": "Donor Relationship Executive", "description": "Key Responsibilities:\n\nHandle donation process in a timely manner, including regular and one-off donations through various payment channels\nEnsure donor details are captured in donor database in high accuracy and arrange issuance of receipts\nProvide frontline services to donors, related to donation transactions, information updates, donation receipts, complaints and other kinds of enquiry, through phone, email and mail\nPerform outbound calls, such as donation follow-up and welcome calls, as necessary\nDeliver individual donor communications, including welcome packs, SMS, eDMs, etc\nAssist supervisor to explore new communications channels with donors, e.g. messaging apps\nSupport administrative, filing and inventory management functions of the team\nPerform other ad hoc duties as assigned\n\nRequirements:\n\nDegree holder in any discipline\nCandidates with more experiences who completed of HKCEE/ HKDSE (with minimum five passes, including English and Chinese) equivalent or above will also be considered\nMinimum 2 years\u2019 experience in customer service or general administration field. Experience in CRM system management is preferred\nGood telephone manner and customer service skills\nGood command of both spoken & written English and Chinese (including Putonghua)\nProficient in MS Office, English & Chinese word processing\nSelf-motivated, detail-minded, a team player and able to work under pressure\n\nContract Period: 1 year (renewable)\n\nPlease send application together with full curriculum vitae and expected salary to\u00a0the Head of Human Resources, Hong Kong Red Cross,\u00a09/F Hong Kong Red Cross Headquarters, 19 Hoi Ting Road, West Kowloon, HK\u00a0or email by clicking \"APPLY NOW\" on or before\u00a023 Jan 2022.\n\nPersonal data provided by job applicants will be used strictly in accordance with Agency\u2019s data protection policy for recruitment purposes only. Applicants not contacted within 4 weeks may consider their applications unsuccessful and all related information will be kept on our files up to a period of 6 months.", "employment_types": ["Full Time", "Contract"], "selling_points": [], "locations": ["Yau Ma Tei"], "categories": ["Sales, CS & Business Devpt", "Customer Service - Supervisor / Officer", "Public / Civil", "Social Services - Community / Non-profit Organization"], "post_time": "2022-01-14T07:13:48Z", "salary": {"currency": null, "max": null, "min": null, "period": "monthly", "term": null}, "salary_visible": false, "title_keywords": ["executive"], "responsibilities": ["ad hoc duties", "edms", "receipts", "a timely manner", "transactions", "inventory management", "payment", "database"], "requirements": {"degrees": ["hkdse", "degree holder"], "majors": [], "languages": ["putonghua", "english", "chinese"], "language_level": ["good command", "proficient"], "hard_skills": ["red", "chinese word processing", "ms office"], "soft_skills": ["detail-minded", "customer service skills", "self-motivated", "customer service", "team player", "telephone manner", "work under pressure"], "languages_combined": [{"language": "putonghua", "language_level": ["good command"]}, {"language": "english", "language_level": ["good command", "proficient"]}, {"language": "chinese", "language_level": ["good command", "proficient"]}]}, "experience_required": {"duration": ["minimum 2 years"], "field": ["management", "customer service", "administration"]}}, {"job_id": "100003009043644", "location_code": "hk", "company": "Hong Kong Sheng Kung Hui Welfare Council Limited", "job_title": "\u884c\u653f\u52a9\u7406  Administration Assistant \u3014\u7de8\u865f\uff1aCAC/AA/20220107-2\u3015", "description": "\u8981\u6c42\ufe30\n\n\u5927\u5c08\u7a0b\u5ea6\u6216\u4ee5\u4e0a\n\u4e2d\u5b78\u6703\u8003\u4e94\u79d1\u5408\u683c(\u5305\u62ec\u4e2d\u6587\u53ca\u82f1\u6587(\u8ab2\u7a0b\u4e59))\u6216\u4ee5\u4e0a\u6210\u7e3e\uff0c\u6216\u4e2d\u5b78\u6587\u6191\u8003\u8a66\u4e94\u79d1\u8003\u7372\u7b2c2\u7d1a\u6216\u540c\u7b49\u7b49\u7d1a\n\u5177\u4e09\u5e74\u6216\u4ee5\u4e0a\u76f8\u95dc\u5de5\u4f5c\u7d93\u9a57\u53ca\u826f\u597d\u6e9d\u901a\u6280\u5de7\n\u719f\u6089\u4e2d\u82f1\u6587\u96fb\u8166\u6587\u66f8\u8655\u7406\n\u8077\u8cac\ufe30\n\n\u8ca0\u8cac\u5354\u52a9\u652f\u63f4\u670d\u52d9\u5718\u968a\u4e4b\u884c\u653f\u6587\u66f8\u3001\u4eba\u529b\u8cc7\u6e90\u53ca\u8ca1\u52d9\u7b49\u5de5\u4f5c\u3002\n\u4e94\u5929\u5de5\u4f5c\u8f2a\u4f11\n\n\u5168\u8077\u54e1\u5de5\u53ef\u4eab\u6709\u4ee5\u4e0b\u5b8c\u5584\u798f\u5229\uff1a\n\n\u53ef\u4eab\u6709\u6709\u85aa\u5e74\u504714\u5929\u3001\u516c\u773e\u5047\u671f17\u5929\u3001\u5a5a\u5047\u3001\u5206\u5a29\u5047\u3001\u6069\u6064\u5047\u3001\u4f8d\u7522\u5047\u3001\u8d85\u6642\u5de5\u4f5c\u88dc\u5047\u3001\u514d\u8cbb\u9ad4\u6aa2\u3001\u91ab\u7642\u4fdd\u96aa\u3001\u4eba\u58fd\u4fdd\u96aa\u3001\u91ab\u7642\u512a\u60e0\u3001\u50f1\u4e3b\u5f37\u7a4d\u91d1\u4f9b\u6b3e\u6309\u5e74\u8cc7\u6700\u9ad8\u53ef\u905e\u589e\u81f315%\u3001\u5728\u8077\u57f9\u8a13\u53ca\u826f\u597d\u6649\u5347\u968e\u68af\u7b49\u3002\n\n\u6709\u610f\u8005\u8acb\u5177\u5c65\u6b77\u5bc4(\u4fe1\u5c01\u9762\u53ca\u4fe1\u5167\u8acb\u8a3b\u660e\u8077\u4f4d\u7de8\u865f)\ufe30\u65b0\u754c\u6c99\u7530\u5713\u6d32\u89d2\u8def13A \u2013\u00a0\u9999\u6e2f\u8056\u516c\u6703\u5f35\u570b\u4eae\u4f09\u5137\u5b89\u8001\u670d\u52d9\u5927\u6a13\u7763\u5c0e\u4e3b\u4efb\u6536\u6216\u6309\"Apply Now\"\u3002\u7533\u8acb\u4eba\u4e4b\u7be9\u9078\u5c07\u6703\u5373\u6642\u9032\u884c\u76f4\u81f3\u4e8c\u96f6\u4e8c\u4e8c\u5e74\u4e00\u6708\u4e8c\u5341\u516b\u65e5\u6216\u6709\u95dc\u8077\u4f4d\u7a7a\u7f3a\u5df2\u88ab\u586b\u88dc\u70ba\u6b62\u3002\uff08\u203b\u5165\u8077\u85aa\u916c\u4e43\u6309\u5b78\u6b77\u53ca\u5de5\u4f5c\u7d93\u9a57\u800c\u8a02\u3002\uff09\n\n\n\u4e00\u5207\u7533\u8acb\u8cc7\u6599\u7d55\u5c0d\u4fdd\u5bc6\u53ca\u53ea\u7528\u4f5c\u62db\u8058\u6709\u95dc\u8077\u4f4d\u3002\u5982\u65bc\u5ee3\u544a\u520a\u767b\u5f8c\u516d\u500b\u6708\u5167\u4ecd\u672a\u7372\u672c\u6703\u56de\u8986\uff0c\u5373\u5176\u7533\u8acb\u672a\u7372\u8003\u616e\uff0c\u800c\u7533\u8acb\u4eba\u4e4b\u500b\u4eba\u8cc7\u6599\u4ea6\u5c07\u5728\u5b8c\u6210\u62db\u8058\u7a0b\u5e8f\u5f8c\u92b7\u6bc0\u3002\u5982\u6b32\u53c3\u8003\u5354\u6703\u8cc7\u6599\uff0c\u8acb\u767b\u5165\u7db2\u5740\ufe30http://www.skhwc.org.hk\n\n\n\n", "employment_types": ["Full Time", "Contract"], "selling_points": [], "locations": ["Shatin Area"], "categories": ["Admin & HR", "Clerical / Admin Staff", "Public / Civil", "Social Services - Community / Non-profit Organization", "Others"], "post_time": "2022-01-13T18:54:53Z", "salary": {"currency": null, "max": null, "min": null, "period": "monthly", "term": null}, "salary_visible": false, "title_keywords": ["administration assistant", "\u884c\u653f\u52a9\u7406"], "responsibilities": [], "requirements": {"degrees": [], "majors": [], "languages": [], "language_level": [], "hard_skills": [], "soft_skills": [], "languages_combined": []}, "experience_required": {"duration": [], "field": []}}, {"job_id": "100003009049137", "location_code": "hk", "company": "Hong Kong Red Cross", "job_title": "Assistant Resource Development Manager", "description": "Job Purpose:\n\nThe core purpose of this role is to support the Resource Development Manager to plan and execute marketing and fundraising campaigns or donation scheme. Moreover, s/he will assist the Manager in fundraising campaign strategy development to achieve the team\u2019s one-off fundraising goal.\n\nKey Responsibilities:\n\nAssist the Manager to create new ideas, plan and implement the one-off fundraising campaigns (including Pass-It-On Campaign, silent disaster, legacy giving, Flag Day, etc.) in order to achieve the team\u2019s one-off fundraising goal from corporate and individual donors.\nAssist direct mail and email programs, processes and materials to insure effective and on-time results.\nAssist the manager to maintain strong corporate relations by effective communications via the individual conversation and corporate communication materials.\nExplore to expand individual donor database.\nWork closely with internal and external parties including but not limited to the HKRC service/ management departments, graphic designers, advertising/ PR/ digital marketing agencies, contractors, printing houses and media, etc. to ensure the smooth implementation of the projects.\nEvaluate the effectiveness of fundraising campaigns with report analysis and to explore/ propose improvement plans for continuity and new fundraising tools.\nIdentify and coordinate with potential partners to enhance the effectiveness of the fundraising campaigns.\nAssist to monitor the financial status of the research programs and fundraising campaigns.\n\nRequirements:\n\nBachelor degree in related discipline, preferable in marketing, business or communications.\nMinimum 2 years relevant working experience, preferable in marketing or fundraising.\nGood knowledge and practical skills in marketing, developing corporate and individual one-off fundraising campaigns, strong digital marketing experience is preferred.\nExperience in account servicing, promotional materials/ publication copywriting and production, online and offline promotions, acquisition & conversion programs\nSensitive to global and market trends and horizon scanning\nExcellent command of English and Chinese, both written and oral (including Putonghua).\nProficient in PC skills, including MS Word, Excel, PowerPoint and Chinese word processing.\nCreative and good team player with excellent interpersonal communication skills.\nSelf-motivated with strong sense of responsibility, detail-minded and able to work under pressure with good multitasking skills\n\nContract Period:\u00a02 years\n\nPlease send application together with full curriculum vitae and expected salary to\u00a0the Head of Human Resources, Hong Kong Red Cross,\u00a09/F Hong Kong Red Cross Headquarters, 19 Hoi Ting Road, West Kowloon, HK\u00a0or email by clicking \"APPLY NOW\"\u00a0on or before 30 January 2022.\n\nPersonal data provided by job applicants will be used strictly in accordance with Agency\u2019s data protection policy for recruitment purposes only. Applicants not contacted within 4 weeks may consider their applications unsuccessful and all related information will be kept on our files up to a period of 6 months.", "employment_types": ["Full Time", "Contract"], "selling_points": [], "locations": ["Yau Ma Tei"], "categories": ["Marketing / Public Relations", "Marketing - Marketing Communication", "Public / Civil", "Social Services - Community / Non-profit Organization"], "post_time": "2022-01-14T08:10:28Z", "salary": {"currency": null, "max": null, "min": null, "period": "monthly", "term": null}, "salary_visible": false, "title_keywords": ["manager", "assistant"], "responsibilities": ["management", "ideas", "advertising", "analysis", "internal and external parties", "coordinate with", "implementation", "monitor", "communication", "evaluate", "maintain", "digital marketing", "plan", "database", "plans", "report"], "requirements": {"degrees": ["degree", "bachelor"], "majors": ["business", "marketing", "communications"], "languages": ["putonghua", "english", "chinese"], "language_level": ["excellent", "proficient"], "hard_skills": ["excel", "chinese word processing", "powerpoint", "red", "pc skills", "ms word"], "soft_skills": ["detail-minded", "communication skills", "good team player", "oral", "self-motivated", "sense of responsibility", "sensitive to", "creative", "interpersonal", "work under pressure"], "languages_combined": [{"language": "putonghua", "language_level": ["excellent"]}, {"language": "english", "language_level": ["excellent"]}, {"language": "chinese", "language_level": ["excellent", "proficient"]}]}, "experience_required": {"duration": ["minimum 2 years"], "field": ["relevant working experience", "account servicing", "developing", "marketing", "digital marketing", "copywriting"]}}, {"job_id": "100003009050860", "location_code": "hk", "company": "The Society for Community Organization Ltd", "job_title": "Temporary Project Manager (Design and Construction) (1-year contract)", "description": "SoCO is a non-profit-making organization motivated by a common dream: \"Let us work hand in hand and shoulder to shoulder to build a caring, equal and just society\". We are now looking for the committed person for the following post of Transitional Housing project:\n\nTemporary Project Manager (Design and Construction) (1-year contract)\n\n(Sham Shui Po / Tsuen Wan / Chai Wan)\n\nDuty\n\n- To provide professional support to organization on project delivery, post-occupancy survey and review to consolidate experience and design feedback for future enhancement of Transitional Housing projects.\n\n- To co-ordinate and communicate with all relevant parties to ensure a clear understanding of project briefs.\n\n- To liaise with lead consultant, sub-consultants, contractors and suppliers as well as internal cross-divisional groups to facilitate activities from inception stage upon completion of the project.\n\n- To provide preliminary advice on alternations and renovations of existing facilities, and construction of new facilities before engagement of consultant.\n\n- To conduct feasibility studies and evaluations to identify possible project strategies and solutions.\n\n- To monitor and control project progress and expenditures against programmes and budgets approved by the Government to ensure the completion of projects on time and within budget.\n\nQualification\n\n- Local chartered professionals of architectural, surveying and engineering discipline\n\n- Minimum of 1 year relevant post-qualification working experience\n\n- Overseeing projects and monitor the budget\n\n- Proven management and leadership skills\n\n- Excellent communication skills in English and Chinese\n\n- Solid experience in Modular Integrated Construction (MiC) projects of residential or hotel will be preferable\n\nPlease send your application with full resume, the post applied and expected salary to our organization at 3/F, 52 Princess Margaret Road, Homantin, Kowloon, Hong Kong or by e-mail.\n\n\nPersonal information collected is for recruitment purpose only and will be treated in strict confidence.\n\nWe are an equal opportunities employer.\n\n[Closing date of application: 13 February 2022]", "employment_types": ["Full Time"], "selling_points": [], "locations": ["Not Specified"], "categories": ["Public / Civil", "Social Services - Community / Non-profit Organization"], "post_time": "2022-01-14T11:36:08Z", "salary": {"currency": null, "max": null, "min": null, "period": "monthly", "term": null}, "salary_visible": false, "title_keywords": ["project manager"], "responsibilities": ["communicate with", "budgets", "control", "management", "review", "monitor", "transitional housing", "design", "project progress", "budget", "communication", "recruitment", "liaise with"], "requirements": {"degrees": [], "majors": [], "languages": ["english", "chinese"], "language_level": ["excellent"], "hard_skills": ["wan"], "soft_skills": ["communication skills", "confidence", "leadership skills", "clear", "committed", "motivated"], "languages_combined": [{"language": "english", "language_level": ["excellent"]}, {"language": "chinese", "language_level": ["excellent"]}]}, "experience_required": {"duration": ["minimum of 1 year"], "field": ["post-qualification", "construction", "design"]}}, {"job_id": "100003009045611", "location_code": "hk", "company": "Wofoo Social Enterprises Limited", "job_title": "Project Executive / Assistant Project Executive", "description": "Responsibilities:\n\nDevise and manage promotional campaigns and projects on Community development\nWork closely with community and welfare NGOs, local shops, volunteers, and schools for a community empowerment project, which aim to enhance the commitment on community work and provide support to the grass-roots families and elderly, as well as to build up the connections between people and community\nAssist in contacting and communicating local NGOs, welfare partners, commercial companies for activities and programs implementation\nAble to develop and complete projects through timely monitoring progress according to priorities and objectives, problem solving, and constantly making appropriate adjustments to plans to reach goals\nPrepare periodic reports, presentation materials, conducting research and drafting correspondence\nMaintain liaison with all levels of administration to coordinate and resolve problems and issues related to administrative matters of internal and external institutions/organizations\nAssist in any ad hoc tasks or projects\n\nRequirements:\n\nHigher Diploma / Associate Degree Holder or above\nWorking experience in event or program management, or related experience in handling funding programs\nRelevant experience preferably in community development would be an advantage\nInterested in serving the local community, including the grass-roots families and elderly\nGood command of written and spoken English and Chinese to meet the demands of project implementation and coordination\nProficient in computer application including MS Word, MS Excel, MS PowerPoint and Chinese word processing; knowledge of Adobe Illustrator would be an advantage\nPossess positive work ethics, strong result orientation, good time management, maturity, resilience and attention to detail and accuracy\nEffective interpersonal skills, and able to work productively with multiple parties\nWilling to work overtime with tight schedule, and occasionally working on Public Holiday is required\n\nInterested parties may apply with resume, stating source of recruitment information, current & expected salary (application without expected salary will not be considered) and availability to:\n\nHuman Resources Department\n\nWofoo Social Enterprises Limited\n\n25/F Wofoo Commercial Building\n\n574-576 Nathan Road\n\nMongkok, Kowloon, Hong Kong\n\nOur website: www.wse.hk\n\n\n\nPersonal data collected will be kept in strict confidence and used for employment-related purpose only.", "employment_types": ["Full Time", "Permanent"], "selling_points": [], "locations": ["Mong Kok"], "categories": ["Marketing / Public Relations", "Marketing - General / Support", "Public Relations - Event Management", "Public / Civil", "Social Services - Community / Non-profit Organization"], "post_time": "2022-01-13T08:11:58Z", "salary": {"currency": null, "max": null, "min": null, "period": "monthly", "term": null}, "salary_visible": false, "title_keywords": ["project executive", "assistant"], "responsibilities": ["provide support", "monitoring", "ad hoc tasks", "implementation", "develop", "coordinate", "maintain", "reports", "plans", "administration"], "requirements": {"degrees": ["associate degree", "diploma"], "majors": [], "languages": ["english", "chinese"], "language_level": ["good command", "proficient"], "hard_skills": ["chinese word processing", "grass", "adobe illustrator", "ms excel", "ms powerpoint", "ms word"], "soft_skills": ["work overtime", "interested in", "interpersonal skills", "coordination", "attention to detail", "time management", "positive"], "languages_combined": [{"language": "english", "language_level": ["good command"]}, {"language": "chinese", "language_level": ["good command", "proficient"]}]}, "experience_required": {"duration": [], "field": ["related", "development", "management", "relevant experience"]}}, {"job_id": "100003009050414", "location_code": "hk", "company": "PURE International (Hong Kong) Ltd", "job_title": "Community Manager", "description": "Cultivate member engagement\n\nServe as a PURE \u201cambassador\u201d for our members \u2013 from welcoming a new member to enhancing the experience along the way\nWork with marketing team to identify activation opportunities at key consumer moments (e.g., members\u2019 events, social events etc.) create unique PURE branded experiences for our member. Own planning and execution of a monthly club calendar for member events and experiences to increase the stickiness factor of the studio\nAnalysis and reporting of member related KPIs (focused on active member base and key member profiles)Collaborate with other departments to create and implement performance marketing promotions, manage project priorities and internal teams for better business outcomes\nActivate the local community & leverage partnerships\n\nDevelop local community relationships and neighborhood partnerships to drive PURE brand awareness and generate leads\nIdentify potential local brand or lifestyle partners who share PURE\u2019s member values, develop crossover partnerships with shared member benefits (e.g., Leisure - PURE Getaway Trip by partnering with Hotels, PURE Urban Retreat, PURE Fashion+, PURE Sleep Matters / Music Matters etc.]\nDeliver member loyalty through unique moments\u00a0\n\nLeverage data/insights to develop and identify our key member profiles, and further tailor products, services, and marketing programs to drive member satisfaction\nIdentify opportunities and execute regular cadence of special moments for our most valuable members\nRequirements:\n\nOutgoing, service oriented, puts the consumer experience at the center of their objectives\nPassion for the PURE brand and Yoga, member profile and behaviors, ability to leverage this knowledge into creating compelling member experiences\nLoves to test, learn, and create new consumer experience ideas with a continuous drive for improvement\nAbility to combine data and consumer knowledge to drive communications and enhanced member service, experience in developing / delivering premium brand-enhancing consumer facing communication\nKnowledgeable & active on relevant local social platforms.\u00a0 Ability to drive engagement with our key consumers on social media\nExperience with / has connections to local community (lifestyle, F&B, brands, etc)\nAt least 7 years\u2019 experience on Project management / ownership of collaborative cross-functional planning calendar, including budget\nUnderstands KPI planning and business success measures\nFluent spoken and written English and Cantonese are required\nWe provide excellent career opportunities, full training and support programme, attractive remuneration and a fun working environment. For further enquiry, please call 3691 3804 or whatsapp/Line/WeChat to 6792 4467.\n\n", "employment_types": ["Full Time", "Permanent"], "selling_points": ["Develop community relationships & partnership", "Experience with connections to local community", "Ability to drive engagement on social media"], "locations": ["Central"], "categories": ["Sales, CS & Business Devpt", "Customer Service - Manager", "Marketing / Public Relations", "Marketing - Marketing Communication", "Public / Civil", "Social Services - Community / Non-profit Organization"], "post_time": "2022-01-14T10:21:05Z", "salary": {"currency": null, "max": null, "min": null, "period": "monthly", "term": null}, "salary_visible": false, "title_keywords": ["manager"], "responsibilities": ["reporting", "analysis", "teams", "develop", "marketing promotions", "kpis", "planning"], "requirements": {"degrees": [], "majors": [], "languages": [], "language_level": [], "hard_skills": ["analysis", "pure", "factor"], "soft_skills": ["active", "focused", "unique"], "languages_combined": []}, "experience_required": {"duration": [], "field": ["planning"]}}, {"job_id": "100003009039147", "location_code": "hk", "company": "Hong Kong China Dragon Boat Association", "job_title": "Assistant Manager", "description": "Duties\n\n- Undertake administrative and clerical duties\n- Maintain proper filing and accounting records\n- Provide secretarial support\n- Assist in event organizing and promotion\n- Handle ad hoc tasks assigned\n\nAbout the Post\n\n- This post (Administrative Assistant) is subvented by the Leisure and Cultural Services Department\n- May be required to work on Sundays, and statutory holidays\n- May\u00a0be required to work outdoor\n- 5-day work\n\nQualification\n- Grade E / Level 2 or above in 5 subjects including English (Syllabus B), Chinese and\nMathematics in Hong Kong Certificate of Education Examination or equivalent; or Level\n2 or equivalent or above in 5 subjects including English, Chinese and Mathematics in the\nHong Kong Diploma of Secondary Education Examination\n- Good PC knowledge with Microsoft Word, Excel, Power Point and Chinese input (Cangjie / Quick)\n- Good command of\u00a0spoken and written English and Chinese\n- Immediate available is preferred\n\nSalary\nHK$15,525 per month\n\nApplication\nApply in writing before 27 January 2022 with full resume:\n1.\u00a0Cover letter\u00a0with subject of \"Apply for Assistant Manager\"\n2. Only suitable candidates will be invited to attend written test and interview in early-February 2022.\n\n* Personal data collected will be used for recruitment purposes only. All collected data will be disposed after finishing the recruitment. *\n\n", "employment_types": ["Full Time", "Permanent"], "selling_points": [], "locations": ["Wong Tai Sin Area"], "categories": ["Admin & HR", "Clerical / Admin Staff", "Marketing / Public Relations", "Public Relations - Event Management", "Public / Civil", "Social Services - Community / Non-profit Organization"], "post_time": "2022-01-14T07:26:37Z", "salary": {"currency": null, "max": null, "min": null, "period": "monthly", "term": null}, "salary_visible": false, "title_keywords": ["assistant manager"], "responsibilities": ["data", "ad hoc tasks", "maintain", "recruitment", "secretarial support", "personal data"], "requirements": {"degrees": ["certificate", "diploma", "secondary education"], "majors": ["mathematics"], "languages": ["english", "chinese"], "language_level": ["good command", "good"], "hard_skills": ["chinese input", "excel", "microsoft word", "power point", "pc knowledge"], "soft_skills": [], "languages_combined": [{"language": "english", "language_level": ["good command", "good"]}, {"language": "chinese", "language_level": ["good command", "good", "good"]}]}, "experience_required": {"duration": [], "field": []}}, {"job_id": "100003009050895", "location_code": "hk", "company": "The Society for Community Organization Ltd", "job_title": "Temporary Programme Assistant (1-year contract) (Sham Shui Po)", "description": "SoCO is a non-profit-making organization motivated by a common dream: \"Let us work hand in hand and shoulder to shoulder to build a caring, equal and just society\". We are now looking for the committed person for the following post of Transitional Housing project:\n\nTemporary Programme Assistant (1-year contract) (Sham Shui Po)\n\nDuty: To assist the NGO\u2019s provision of social and community support services to tenants of the project.\n\nQualification: Academic qualification equivalent to or above Diploma level from a local or overseas tertiary educational institution with at least 6 months of working experience in providing social services or related services; ability to work under pressure; good team-work spirit; understand and support the mission of SoCO.\n\nPlease send your application with full resume, the post applied and expected salary to our organization at 3/F, 52 Princess Margaret Road, Homantin, Kowloon, Hong Kong or by e-mail.\n\n\nPersonal information collected is for recruitment purpose only and will be treated in strict confidence.\n\nWe are an equal opportunities employer.\n\n[Closing date of application: 13 February 2022]", "employment_types": ["Full Time"], "selling_points": [], "locations": ["Sham Shui Po Area"], "categories": ["Public / Civil", "Social Services - Community / Non-profit Organization"], "post_time": "2022-01-14T11:41:33Z", "salary": {"currency": null, "max": null, "min": null, "period": "monthly", "term": null}, "salary_visible": false, "title_keywords": ["assistant"], "responsibilities": ["support services", "recruitment", "transitional housing", "work under pressure"], "requirements": {"degrees": ["diploma"], "majors": [], "languages": [], "language_level": [], "hard_skills": [], "soft_skills": ["committed", "motivated", "confidence", "work under pressure"], "languages_combined": []}, "experience_required": {"duration": [], "field": ["related"]}}, {"job_id": "100003009046150", "location_code": "hk", "company": "St. James' Settlement", "job_title": "Project Officer (PO II) (Contract)\u3008Ref: CVPA/05522\u3009", "description": "Requirement:\n\nDegree holder in Language, Translation, Communications or related disciplines with 2 years working experience\nHKCEE 5 passes [incl. English (Syl B) and Chinese at Grade E or above] or equivalent\nExcellent command of written and spoken English and Chinese; experience in editorial work preferred\nDynamic, efficient, independent, responsive and resourceful; good interpersonal and teamwork skills\nDetail minded, organized and passionate in writing; ability to create coherent and consistent content\n\nJob Duties:\n\nCarry out editorial duties for agency annual report, newsletter and other publications\nProvide English and Chinese copywriting for a full range of editing, proofreading and translating various publications\nPrepare marketing collaterals to facilitate partnerships and collaborations\nManage social media platforms for service promotion\nImplement various initiatives to achieve the fundraising goals of the agency\n\nInterested persons please apply with full resume via \u201cAPPLY NOW\u201d\u00a0or\u00a0mail to Room 901, 9/F, 85 Stone Nullah Lane, Wanchai, Hong Kong\u00a0on or before 31/01/2022.", "employment_types": ["Full Time", "Contract"], "selling_points": ["Degree holder in Language or related disciplines", "Excellent command of written and spoken English", "experience in editorial work preferred"], "locations": ["Wan Chai"], "categories": ["Public / Civil", "Social Services - Community / Non-profit Organization"], "post_time": "2022-01-13T09:44:57Z", "salary": {"currency": null, "max": null, "min": null, "period": "monthly", "term": null}, "salary_visible": false, "title_keywords": ["project officer"], "responsibilities": ["social media platforms", "marketing collaterals", "proofreading", "editing", "report"], "requirements": {"degrees": ["degree holder"], "majors": ["related disciplines", "communications"], "languages": ["english", "chinese"], "language_level": ["excellent"], "hard_skills": ["translation", "dynamic"], "soft_skills": ["efficient", "organized", "passionate", "independent", "resourceful", "teamwork", "coherent", "dynamic", "responsive", "interpersonal"], "languages_combined": [{"language": "english", "language_level": ["excellent"]}, {"language": "chinese", "language_level": ["excellent"]}]}, "experience_required": {"duration": ["2 years"], "field": ["related", "editorial"]}}, {"job_id": "100003009046795", "location_code": "hk", "company": "Hong Kong Young Women\u2019s Christian Association", "job_title": "Compensation and Benefits Officer", "description": "Key Responsibilities\n\nProvide full spectrum of Payroll and Compensation & Benefits (C&B) administration\u00a0including MPF/ORSO, leave, employee compensation, medical and insurance etc\nPrepare analytics and projections on payroll and benefits costs\nPrepare payroll related data for cost allocation and tracking\nEnsure compliance with the organization Human Resources policies & procedures, and regulations\nAssist the management in the preparation and roll-out of new benefits programs\nA key player to assist in the implementation and roll-out of ERP system on all HR aspects\nAssist in ongoing research into emerging trends, issues and best practices\nPrepare various HR reports and support audit process\n\nRequirements\n\nDegree in Human Resources Management, Business Administration or related disciplines\nMinimum 5 years experience in Human Resources, of which 3 years solid C&B role\nGood command of written and spoken Chinese & English\nHands on with proficiency in MS Excel, Word, and HR system, sound proficiency in ERP on HR modules\nWell versed and keep abreast with HK Employment Ordinance and other related legislation\nResilient, strong sense of responsibility, meticulous, accurate, well-organized, independent and a fast learner\nGood presentation, communication and interpersonal skills\n\nWe offer Paid Holiday (Annual Leave, Public Holiday, Maternity Leave / Paternity Leave, Training Leave), Training Subsidy, Medical Insurance and Subsidy, MPF Employer\u2019s Voluntary Contribution, Staff Discount etc.\u00a0\n\nInterested parties please send full resume with present and expected salary by:\n\nEmail: Click 'Apply Now' button\n\nOnly short-listed candidates will be contacted for interview and all personal data collected will be used for recruitment purposes only.\n\nWe are an equal opportunities employer", "employment_types": ["Full Time", "Permanent"], "selling_points": [], "locations": ["Central"], "categories": ["Admin & HR", "Compensation & Benefits", "HR Supporting Staff", "Public / Civil", "Social Services - Community / Non-profit Organization"], "post_time": "2022-01-14T04:59:57Z", "salary": {"currency": null, "max": null, "min": null, "period": "monthly", "term": null}, "salary_visible": false, "title_keywords": ["officer"], "responsibilities": ["payroll", "mpf", "insurance", "administration"], "requirements": {"degrees": [], "majors": [], "languages": [], "language_level": [], "hard_skills": [], "soft_skills": [], "languages_combined": []}, "experience_required": {"duration": [], "field": []}}, {"job_id": "100003009047319", "location_code": "hk", "company": "Employers' Federation of Hong Kong", "job_title": "Officer - Communications", "description": "Job specifications\n\nTo manage and co-ordinate the production of the Federation's quarterly journal;\nTo manage and co-ordinate the production of the Federation's publications e.g. annual report, newsletter;\nTo manage the website and social media of the Federation;\nTo handle administrative tasks or other ad-hoc duties as assigned.\nRequirements\n\nDiploma holder or above;\n\nOne to two years' relevant job experience will be advantage;\n\nExcellent verbal and written language skills, both in English and Chinese;\n\nGood organisational and communication skills;\n\nSelf-motivated, responsible and have team-spirit;\nAble to work independently and meet deadlines.\nApplication Methods\n\n\u00a0By mail to the Human Resources Division, Employers' Federation of Hong Kong, 1230, 12/F, One Island South, 2 Heung Yip Road, Wong Chuk Hang, Hong Kong.\nApply through JobsDB by clicking the \"APPLY\u00a0NOW\"\u00a0button.\u00a0\nPlease apply with full resume, present and expected salary and date of availability, Please mark \"CONFIDENTIAL\" on the envelope if you will send your application by post.\u00a0\n\n\nThe Federation offers a friendly, small office environment, 5-day work week, attractive salary, MPF and group medical insurance for the right candidate.\u00a0 Please submit your application on or before 13 February 2022.\u00a0\u00a0\n\nAll Personal data collected will be treated in strict confidence and handled confidential by authorised personnel for recruitment-related purpose only.\u00a0 Candidates not notified within 8 weeks may consider their application unsuccessful.\u00a0\nwww.efhk.org.hk\n\n", "employment_types": ["Full Time"], "selling_points": ["Officer, Journal, Publication, Communications", "Possess with relevant experience is beneficial", "Website, Social media, Performance Bonus"], "locations": ["Southern Area"], "categories": ["Media & Advertising", "Editorial / Journalism", "Public / Civil", "Social Services - Community / Non-profit Organization", "Professional Services", "Translation"], "post_time": "2022-01-14T02:49:42Z", "salary": {"currency": null, "max": null, "min": null, "period": "monthly", "term": null}, "salary_visible": false, "title_keywords": ["officer"], "responsibilities": ["social media", "mpf", "website", "communication", "specifications", "recruitment", "ad-hoc duties", "administrative tasks", "personal data", "insurance", "report"], "requirements": {"degrees": ["diploma holder"], "majors": [], "languages": ["english", "chinese"], "language_level": ["excellent"], "hard_skills": ["small"], "soft_skills": ["communication skills", "self-motivated", "work independently", "confidence", "responsible", "friendly", "ad-hoc duties", "meet deadlines"], "languages_combined": [{"language": "english", "language_level": ["excellent"]}, {"language": "chinese", "language_level": ["excellent"]}]}, "experience_required": {"duration": ["one to two years"], "field": []}}, {"job_id": "100003009048184", "location_code": "hk", "company": "Jao Tsung-I Academy", "job_title": "Assistant Operation Officer", "description": "Summary/Objective\u00a0\n\nThe Assistant Operation Officer position assists the Operation Manager in the daily operation of venue bookings and general enquiries.\u00a0\u00a0\n\n\n\nDuties\n\nAssist the Operation Manager in venue booking and liaising with venue users;\nHandle venue users' enquiries;\u00a0\nOn-site support for daily bookings;\nAssist the daily maintenance of web page.\n\nRequirements\n\nOne year working experience, in relevant field is an advantage.\nGood command in both spoken and written English and Chinese.\nProficiency in MS Word, Excel, Chinese Word Processing.\nDetail minded,\u00a0self-motivated and able to work independently and in a team.\nExperience in Web page maintenance is an advantage.\n\n\n\n\nWE ARE AN EQUAL OPPORTUNITY EMPLOYER.\n\nSalary is commensurate with qualifications and experience. Interested parties should send a detailed resume with present & expected salary, together with a covering letter.\n\nAs an NGO we welcome disabled, non-engaged youth, single parents and individuals from low-income families who satisfy the above requirements to apply. All information collected will be used for the purpose of recruitment only.\n", "employment_types": ["Full Time"], "selling_points": [], "locations": ["Lai Chi Kok"], "categories": ["Sales, CS & Business Devpt", "Customer Service - Supervisor / Officer", "Public / Civil", "Social Services - Community / Non-profit Organization"], "post_time": "2022-01-14T06:00:03Z", "salary": {"currency": null, "max": null, "min": null, "period": "monthly", "term": null}, "salary_visible": false, "title_keywords": ["operation officer", "assistant"], "responsibilities": ["liaising with", "booking", "maintenance"], "requirements": {"degrees": [], "majors": [], "languages": ["english", "chinese"], "language_level": ["proficiency", "good command"], "hard_skills": ["excel", "chinese word processing", "maintenance", "web", "ms word"], "soft_skills": ["self-motivated", "work independently"], "languages_combined": [{"language": "english", "language_level": ["good command"]}, {"language": "chinese", "language_level": ["proficiency", "good command"]}]}, "experience_required": {"duration": ["one year"], "field": ["maintenance"]}}, {"job_id": "100003009048347", "location_code": "hk", "company": "ADECCO", "job_title": "Museum Assistant II (Hong Kong Science Museum) 1 Year Contract, Welcome Fresh Graduated student", "description": "Job Duties:\u00a0\n1. To conduct, assist in planning, content development, liaison, promotion and logistics support for various demonstrations, education programmes, laboratory programmes, workshops and online programmes\u00a0organised by the Hong Kong Science Museum.\n\n2. To assist in coordination of programmes with outside parties and monitor such programmes as required\n\n3. To prepare reports for such programmes as required.\n\n4. To assist in updating the contents of thematic websites, designing of publicity videos, and production of educational worksheets.\n\n5. To teach and assist visitors to operate the exhibits properly and to perform operational duties on selected exhibits\n\n6. To work shifts and assist the Duty Exhibition Hall Officer in coordinating with different sections for daily operation of exhibition hall and crowd control\n\n7. To handle enquiries, complaints, ad hoc incidents or emergencies at Museum\n\nContract Period:\n\nFeb 2022 - Dec 2022\n\nService Time: 44 hours per week, 5 days work, 09:30-18:18\n\nSalary: $16,650\n\nRequirements:\u00a0\n\n1. Bachelor degree in Science, Mathematics, Engineering, Technology.\n\n2.\u00a0Good command of both written and spoken Chinese and English, fluency in Putonghua is an advantage.\n\n3. Good knowledge in computer applications, including MS Word, Excel and PowerPoint, and Chinese word processing.\n\n4. Preferably be familiar with photo and video editing software, such as Adobe Photoshop and Final cut Pro.\n\n5. Preferably be experienced in developing and organising demonstrations, workshops or educational programme, early childhood education, museum or laboratory work.", "employment_types": ["Contract"], "selling_points": [], "locations": ["Tsim Sha Tsui"], "categories": ["Public / Civil", "Social Services - Community / Non-profit Organization"], "post_time": "2022-01-14T06:23:28Z", "salary": {"currency": null, "max": null, "min": null, "period": "monthly", "term": null}, "salary_visible": false, "title_keywords": ["assistant"], "responsibilities": ["crowd control", "ad hoc", "monitor", "designing", "daily operation", "handle enquiries", "logistics", "coordination", "contents", "prepare reports", "operational duties", "planning"], "requirements": {"degrees": ["degree", "bachelor"], "majors": ["science", "engineering", "mathematics"], "languages": ["putonghua", "english", "chinese"], "language_level": ["fluency", "advantage", "good command", "good"], "hard_skills": ["final cut pro", "excel", "chinese word processing", "adobe photoshop", "powerpoint", "video editing", "workshops", "ms word"], "soft_skills": [], "languages_combined": [{"language": "putonghua", "language_level": ["fluency", "advantage", "good command", "good"]}, {"language": "english", "language_level": ["advantage", "good command", "good"]}, {"language": "chinese", "language_level": ["advantage", "good command", "good", "good"]}]}, "experience_required": {"duration": [], "field": []}}, {"job_id": "100003009049710", "location_code": "hk", "company": "Playright Children's Play Association", "job_title": "Executive Director", "description": "A. JOB SUMMARY\n\nThe Executive Director is accountable for:\n\nDeveloping and implementing Playright's strategic plan that aligns with its positioning as an active play advocate\nAchieving financial goals of the organisation and ensuring proper financial control\nOverseeing operation of the organisation/services and safeguarding compliance with regulatory requirements\nExpanding pool of supporters for the accomplishment of Playright\u2019s mission\nSupporting the Board of Directors for good governance of the organisation\nDeveloping a solid team that is passionate, accountable, and capable to meet Playright\u2019s strategic goals\n\nB. KEY RESPONSIBILITIES\n\nStrategic & Business Development\n\nBring in global perspectives, research, and best practices, and develop insightful local applications\nWork with the Board in the strategic planning process, and review the strategic plan regularly to ensure that services and programmes are tightly linked to Playright\u2019s mission and vision\nTranslate the strategic plan into responsibilities for senior management, in consideration of the unique professions in play environment, hospital play, and playwork, to follow through, monitor, and implement the plans and use the performance results to inform decisions on strategic planning and resources allocation\nLead service strategies, human resources planning, and pilot new service projects for the sustained growth of Playright\nSupport the Board to carry out its governance functions\n\nFinancial Management & Fundraising\n\nPrepare/review multi-year financial plan for the Board\u2019s discussion and approval of resource allocation, funding plans, and investment objectives in the context of strategic goals\nEnsure timely financial statements/audits for the Board\u2019s regular review\nInitiate and materialise fundraising opportunities, support the Board in fundraising activities, and achieve the financial goals of the organization\n\nOrganisation & Service / Consultancy Programme Operations\n\nWork with the Board to set performance targets for the organisation\nOversee the operations of the organisation, services, and consultancy programme in an effective and efficient manner, and in accordance with high standards and expectations\nMonitor and safeguard compliance with all regulatory and funding requirements\nAssess and monitor potential risks, and ensure mitigation plans are in place\n\nStakeholders\u2019 Engagement\n\nAct as an effective representative of Playright, actively engaging with all internal, external, and international stakeholders. Seek stakeholder feedback to inform strategy and resource allocation\nExpand pool of supporters, funders, and partners, gaining the buy-in needed to accomplish the mission and goals of Playright\nEnsure that impacts of Playright are communicated effectively to stakeholders\n\nPeople Management / Competency Enhancement\n\nLead, manage, and develop high performance teams, and be a role model for Playright\u2019s purpose and value\nCommunicate and enhance the competencies of the different professionals in play, and make connections to maximise the impact for play advocacy\nCultivate a culture of professionalism, trust, commitment, and inclusion in all levels of the organisation\n\nC. PERSONAL ATTRIBUTES\n\nLove of PLAY \u2013 exceptional enthusiasm. Inspirational leadership. Bring new and creative ideas to Playright\nExcellent analytical, negotiation, interpersonal, motivational, and change management skills\nStrong ability to establish credibility and relationships with diverse individuals and groups\nStrong COMMUNICATOR \u2013 sensitivity to internal and external environment of Playright. Strong advocate for Playright externally and Inspirational role model internally\nSolid judgement to make decisions that are aligned with the mission and goals, able to make difficult calls when needed, and manage with transparency, empathy, and respect. Willing to work at execution level when needed\nMindfulness in working in NGOs, but with operational experience to drive system and implementation excellence\n\nD. JOB REQUIREMENTS\n\nDegree in Management or Social Welfare or Health Care or Architecture or related discipline, or other similar qualifications\nSignificant proven record of achievement in a management or strategist position, preferably child-related. Experience in running a self-financed service or social enterprise is an advantage\nSignificant proven record of achievement in effective partnership management\nExcellent verbal and written communication skills in Chinese and English\nComputer literate\n\n\nWe offer an attractive remuneration package and friendly working environment to the right candidate.\u00a0Please send detailed resume to Human Resources Department by clicking \u201cApply Now\u201d button by 31 January 2021.\u00a0For more information about our organization, please visit our website:\u00a0https://www.playright.org.hk/\n\nWe are an equal opportunity employer and welcome applications from all qualified candidates.\u00a0All personal data will be used for recruitment purpose only. Only shortlisted candidates will be contacted. If you have not been contacted within 20 business days of your application, please assume your application has not been shortlisted.", "employment_types": ["Full Time"], "selling_points": [], "locations": ["Chai Wan"], "categories": ["Public / Civil", "Social Services - Community / Non-profit Organization", "Management", "Top Executives (CEO, CFO, CTO, GM, MD etc.)"], "post_time": "2022-01-14T09:08:03Z", "salary": {"currency": null, "max": null, "min": null, "period": "monthly", "term": null}, "salary_visible": false, "title_keywords": ["executive director"], "responsibilities": ["management", "creative ideas", "change management", "strategic planning", "operations", "review", "monitor", "compliance", "financial statements", "develop", "regular review", "teams", "implementation", "plan", "audits", "plans", "senior management", "planning"], "requirements": {"degrees": ["degree"], "majors": ["architecture"], "languages": ["english", "chinese"], "language_level": ["excellent"], "hard_skills": [], "soft_skills": ["communication skills"], "languages_combined": [{"language": "english", "language_level": ["excellent"]}, {"language": "chinese", "language_level": ["excellent"]}]}, "experience_required": {"duration": [], "field": []}}, {"job_id": "100003009052789", "location_code": "hk", "company": "Hong Kong Sheng Kung Hui Welfare Council Limited", "job_title": "\u793e\u6703\u5de5\u4f5c\u54e1 Social Worker", "description": "\u8cc7\u6b77\ufe30\n\n\u6301\u8a8d\u53ef\u793e\u6703\u5de5\u4f5c\u5b78\u4f4d\u6216\u540c\u7b49\u5b78\u6b77\uff0c\u5fc5\u9808\u70ba\u8a3b\u518a\u793e\u5de5\n\u7372\u4e2d\u5b78\u6703\u8003\u4e2d\u6587\u53ca\u82f1\u6587(\u8ab2\u7a0b\u4e59)\u5408\u683c\u6216\u4e2d\u5b78\u6587\u6191\u8003\u8a66\u540c\u7b49\u7b49\u7d1a\n\u51775\u5e74\u76f8\u95dc\u5de5\u4f5c\u7d93\u9a57\n\n\u8077\u8cac\ufe30\n\n\u8ca0\u8cac\u63d0\u4f9b\u54a8\u8a62\u53ca\u8207\u793e\u4ea4\u5fc3\u7406\u76f8\u95dc\u4e4b\u652f\u63f4\u670d\u52d9\n\u5efa\u7acb\u5730\u5340\u5354\u8abf\u7db2\u7d61\uff0c\u63a8\u884c\u53ca\u63a8\u5ee3\u300c\u5730\u5340\u70ba\u672c\u300d\u4e4b\u57fa\u5c64\u91ab\u7642\u670d\u52d9\n\u63a8\u52d5\u793e\u5340\u53c3\u8207\uff0c\u7ba1\u7406\u3001\u7d71\u7c4c\u53ca\u5e36\u9818\u5404\u985e\u8207\u5065\u5eb7\u670d\u52d9\u76f8\u95dc\u4e4b\u5c0f\u7d44\u3001\u6d3b\u52d5\u53ca\u8a08\u5283\u7b49\n\n\n\u6b64\u8077\u4f4d\u5c6c\u300c\u9805\u76ee\u70ba\u672c\u300d(project based)\u6027\u8cea\u3002\n\n\u6709\u610f\u7533\u8acb\u4e0a\u8ff0\u8077\u4f4d\u8005\u8acb\u5177\u51fd\u4e26\u9644\u8a73\u7d30\u5c65\u6b77\uff0c\u73fe\u6642\u85aa\u916c\u53ca\u671f\u671b\u85aa\u916c\u7b49\u8cc7\u6599\uff0c\u5bc4\u9999\u6e2f\u7b72\u7b95\u7063\u8208\u6c11\u885768\u865f\u6d77\u5929\u5ee3\u58345\u6a13 -\u00a0\u9999\u6e2f\u8056\u516c\u6703\u798f\u5229\u5354\u6703\u6709\u9650\u516c\u53f8\u4eba\u529b\u8cc7\u6e90\u90e8\u6536\u6216\u6309\"Apply Now\"\uff0c\u4fe1\u5c01\u53ca\u96fb\u90f5\u8acb\u8a3b\u660e\u7533\u8acb\u7de8\u865f\u3002\u4e00\u5207\u7533\u8acb\u8cc7\u6599\u7d55\u5c0d\u4fdd\u5bc6\u53ca\u53ea\u7528\u4f5c\u62db\u8058\u6709\u95dc\u8077\u4f4d\u3002\u5982\u7533\u8acb\u8005\u5728\u622a\u6b62\u65e5\u671f\u5f8c\u516b\u661f\u671f\u5167\u4ecd\u672a\u7372\u96fb\u8a71\u7d04\u898b\u8005\uff0c\u5176\u7533\u8acb\u53ef\u4f5c\u843d\u9078\u8ad6\uff0c\u6055\u4e0d\u53e6\u51fd\u901a\u77e5\uff0c\u672c\u798f\u5229\u5354\u6703\u5c07\u4fdd\u5b58\u7533\u8acb\u6587\u4ef6\u4e0d\u8d85\u904e\u516d\u500b\u6708\u3002", "employment_types": ["Full Time"], "selling_points": [], "locations": ["Wong Tai Sin Area"], "categories": ["Medical Services", "Others", "Public / Civil", "Social Services - Community / Non-profit Organization", "Others"], "post_time": "2022-01-17T04:04:45Z", "salary": {"currency": null, "max": null, "min": null, "period": "monthly", "term": null}, "salary_visible": false, "title_keywords": ["social worker"], "responsibilities": [], "requirements": {"degrees": [], "majors": [], "languages": [], "language_level": [], "hard_skills": [], "soft_skills": [], "languages_combined": []}, "experience_required": {"duration": [], "field": []}}, {"job_id": "100003009045545", "location_code": "hk", "company": "The University of Hong Kong", "job_title": "Post-doctoral Fellow (PDF) / Assistant Research Officer  (ARO) ( 509156)", "description": "Applications are invited for appointment as\u00a0Post-doctoral Fellow (PDF)/Assistant Research Officer (ARO) in the School of Public Health\u00a0(Ref.: 509156), to commence as soon as possible for one year, with the possibility of renewal subject to satisfactory performance.\n\nApplicants should possess a doctoral degree by research or equivalent in public health, social sciences, or related disciplines, with at least one year's experience in community-based research, public health research or population sciences research. They should have knowledge of community health promotion, and/or experience in the application of Information and Communication Technology (ICT) in research. They should also have the ability to work independently as well as in a multidisciplinary team; the ability to collaborate with external parties including academics, social service groups and politicians; and excellent written and verbal communication skills.\n\nThe appointee will work for the Jockey Club SMART Family-Link Project, with the aim to promote family well-being by leveraging ICT for innovative family services.\u00a0 He/She will coordinate research design; liaise with community parties and institutions; plan, develop and conduct community-based interventions and training programmes for local social service practitioners and professionals; facilitate the collection of big data; oversee data collection and management; write scientific publications and reports; supervise research staff members; and perform other duties as assigned. Those who have responded to the previous advertisement (Ref.: 498698) need not re-apply.\n\nA highly competitive salary commensurate with qualifications and experience will be offered, in addition to annual leave and medical benefits.\u00a0\n\nThe University only accepts online application for the above post.\u00a0Applicants should apply online and upload an up-to-date C.V.\u00a0 Review of applications will start on December 21, 2021 and continue until\u00a0February 28, 2022, or until the post is filled, whichever is earlier.\n\nAdvertised:Dec 7, 2021 (HK Time)\nApplications close:Feb 28, 2022 (HK Time)\n\n\u6709\u610f\u7533\u8acb\u8005\u8acb \u6309 APPLY NOW\u7533\u8acb\n\n", "employment_types": ["Full Time"], "selling_points": [], "locations": ["Pok Fu Lam"], "categories": ["Public / Civil", "Civil Services", "Sciences, Lab, R&D", "Research & Development (R&D)", "Social Services - Community / Non-profit Organization"], "post_time": "2022-01-13T08:03:23Z", "salary": {"currency": null, "max": null, "min": null, "period": "monthly", "term": null}, "salary_visible": false, "title_keywords": ["research officer", "assistant"], "responsibilities": ["collaborate with", "management", "perform other duties", "external parties", "big data", "design", "develop", "communication", "coordinate", "reports", "plan", "data collection", "liaise with"], "requirements": {"degrees": ["degree"], "majors": ["related disciplines", "public health", "social sciences"], "languages": [], "language_level": [], "hard_skills": [], "soft_skills": ["communication", "communication skills", "work independently", "innovative"], "languages_combined": []}, "experience_required": {"duration": ["at least one year"], "field": ["related", "research"]}}, {"job_id": "100003009044892", "location_code": "hk", "company": "Harbour City Estates Ltd", "job_title": "ASSISTANT SUSTAINABILITY OFFICER (CONTRACT)", "description": "Responsibilities:\n\n\nResponsible for the coordination of the ESG Reporting at Business Unit level (across Hong Kong and Mainland centres)\nDevelop and deliver trainings to ensure the compliance of ESG Reporting requirement and improve the data quality\nManage and keep track of the Company\u2019s environmental performance and target settings\nArrange sustainability related audits, follow-up and ensure the records are maintained and updated\nSupport the implementation of Company\u2019s corporate responsibility policy and the related sustainable operation processes\nSupport the execution of defined sustainability projects and initiatives\nPerform other duties as assigned\n\nRequirements:\n\nDegree holder in Social Responsibility, Sustainability and Compliance, Applied and Pure Sciences or related disciplines\nAt least 2 years of relevant experience, experience with social and environmental compliance standards such as ISO 14001, ISO 45001 etc., will be an advantage\nSelf-motivated, detail-minded, independent and proactive; Team player in a cross-cultural working environment\nProficiency in Microsoft Office, especially in Excel (including pivot tables and VBA Excel)\nGood command of both written and spoken English and Chinese (Cantonese and Mandarin)\n\nWe offer competitive remuneration package that commensurate with experience and qualifications.\u00a0 Interested parties are invited to send full resume stating contact telephone number, date available, present and expected salary to our recruitment email address.\n\n\n(Personal data provided will be used strictly in accordance with the Company's personal data policy which is available upon request.)", "employment_types": ["Full Time", "Contract"], "selling_points": ["Responsible for coordination of the ESG Reporting", "Support execution of sustainability projects", "2 years of relevant experience"], "locations": ["Tsim Sha Tsui"], "categories": ["Property / Real Estate", "Property Management", "Public / Civil", "Social Services - Community / Non-profit Organization", "Others"], "post_time": "2022-01-13T06:34:39Z", "salary": {"currency": null, "max": null, "min": null, "period": null, "term": null}, "salary_visible": false, "title_keywords": ["assistant sustainability officer"], "responsibilities": ["reporting", "perform other duties", "data", "compliance", "quality", "implementation", "develop", "coordination", "audits"], "requirements": {"degrees": ["degree holder"], "majors": ["related disciplines"], "languages": ["cantonese", "english", "chinese", "mandarin"], "language_level": ["good command"], "hard_skills": ["excel", "vba", "pure", "microsoft office"], "soft_skills": ["detail-minded", "self-motivated", "independent", "team player", "proactive"], "languages_combined": [{"language": "cantonese", "language_level": ["good command"]}, {"language": "english", "language_level": ["good command"]}, {"language": "chinese", "language_level": ["good command"]}, {"language": "mandarin", "language_level": ["good command"]}]}, "experience_required": {"duration": ["at least 2 years"], "field": ["environmental", "compliance", "relevant experience"]}}, {"job_id": "100003009048895", "location_code": "hk", "company": "Yan Oi Tong Ltd", "job_title": "\u8ab2\u7a0b\u7d71\u7c4cII (\u8077\u4f4d\u7de8\u865f: JCTC/CCII0107/220114)", "description": "\u4e2d\u5b78\u7562\u696d\u6216\u4ee5\u4e0a\u7a0b\u5ea6\n\u5177\u5169\u5e74\u4ee5\u4e0a\u5ba2\u6236\u670d\u52d9\u6216\u57f9\u8a13\u76f8\u95dc\u5de5\u4f5c\u7d93\u9a57\n\u5177\u57fa\u672c\u4e2d\u3001\u82f1\u6587\u8b80\u5beb\u80fd\u529b\uff0c\u719f\u6089\u96fb\u8166\u64cd\u4f5c\n\u8ca0\u8cac\u518d\u57f9\u8a13\u8ab2\u7a0b\u670d\u52d9\n\u5177\u8ab2\u7a0b\u884c\u653f\u53ca\u5c31\u696d\u914d\u5c0d\u5de5\u4f5c\u7d93\u9a57\u8005\u512a\u5148\n\u5c6f\u9580\u6216\u89c0\u5858\u5340\u5de5\u4f5c\n\n\n\n\u6709\u610f\u8005\u8acb\u5c07\u5c65\u6b77\u3001\u8981\u6c42\u5f85\u9047\u3001\u53ef\u5230\u8077\u65e5\u671f\u53ca\u806f\u7d61\u96fb\u8a71\uff08\u5fc5\u9808\u8a3b\u660e\u8077\u4f4d\u7de8\u865f\uff09\u90f5\u5bc4\u5f80\u5c6f\u9580\u555f\u6c11\u5f9118\u865f\u4ec1\u611b\u5802\u8cfd\u99ac\u6703\u793e\u5340\u53ca\u9ad4\u80b2\u4e2d\u5fc37\u6a13\u4eba\u529b\u8cc7\u6e90\u90e8\u6536\u6216\u6309\u00a0Apply Now\u00a0\u61c9\u5fb5\u3002\n\n\n*\u7533\u8acb\u4eba\u6240\u63d0\u4f9b\u7684\u8cc7\u6599\u5c07\u4e88\u4ee5\u4fdd\u5bc6\u53ca\u53ea\u4f5c\u62db\u8058\u6709\u95dc\u8077\u4f4d\u7528\u9014*", "employment_types": ["Full Time", "Contract"], "selling_points": ["\u4e2d\u5b78\u7562\u696d\u6216\u4ee5\u4e0a\u7a0b\u5ea6", "\u5177\u5169\u5e74\u4ee5\u4e0a\u5ba2\u6236\u670d\u52d9\u6216\u57f9\u8a13\u76f8\u95dc\u5de5\u4f5c\u7d93\u9a57", "\u8ca0\u8cac\u518d\u57f9\u8a13\u8ab2\u7a0b\u670d\u52d9"], "locations": ["Tuen Mun Area"], "categories": ["Public / Civil", "Social Services - Community / Non-profit Organization"], "post_time": "2022-01-14T07:38:02Z", "salary": {"currency": null, "max": null, "min": null, "period": "monthly", "term": null}, "salary_visible": false, "title_keywords": [], "responsibilities": [], "requirements": {"degrees": [], "majors": [], "languages": [], "language_level": [], "hard_skills": [], "soft_skills": [], "languages_combined": []}, "experience_required": {"duration": [], "field": []}}, {"job_id": "100003009052888", "location_code": "hk", "company": "Haven of Hope Christian Service", "job_title": "Advanced Practitioner (Nurse) (Ref : NH/APN/JDB)", "description": "Degree in Nursing or Health Care, holder of valid certificate of registration and practicing certificate issued by the Nursing Board of Hong Kong\nTo assist the Home Manager to enhance professional practice/development through clinical teaching/instruction\nTo supervise Floor In Charge and monitor floor operations as well as nursing and personal care services\nStrong leadership with good interpersonal communication skills\nMinimum of 5 years\u2019 post-registration experience in a Nursing Home or a Hospital Geriatric Unit\nMainly work during daytime and working location at Haven of Hope Nursing Home\nPlease send full resume with expected salary and reference no. quoted to Haven of Hope Christian Service, Staff Engagement Department, 7 Haven of Hope Road, Tseung Kwan O, New Territories or via email by clicking \"Apply Now\", or via Whatsapp no. 6507 8148 (with reference no. quoted at the caption) on or before 5 February 2022. Only short-listed candidates will be notified.\nEnquiry: 2703 3227 (Phone); 6507 8148 (Whatsapp).\nFor details about our organization, please visit www.hohcs.org.hk.\nProspective employees are requested to undergo/submit Sexual Conviction Record Check for work relating to children or mentally incapacitated persons before employment. Data collected will be used for recruitment purpose only.\nThis advertisement should not be reproduced, in whole or in part, to other recruitment websites without our prior written permission.", "employment_types": ["Full Time", "Permanent"], "selling_points": [], "locations": ["Tseung Kwan O"], "categories": ["Medical Services", "Nursing", "Others", "Public / Civil", "Social Services - Community / Non-profit Organization"], "post_time": "2022-01-17T04:26:09Z", "salary": {"currency": null, "max": null, "min": null, "period": "monthly", "term": null}, "salary_visible": false, "title_keywords": ["nurse"], "responsibilities": ["data", "operations", "monitor", "communication", "recruitment"], "requirements": {"degrees": ["certificate", "degree"], "majors": ["nursing"], "languages": [], "language_level": [], "hard_skills": ["hope", "whatsapp", "no"], "soft_skills": ["communication skills", "leadership", "interpersonal"], "languages_combined": []}, "experience_required": {"duration": ["minimum of 5 years"], "field": []}}, {"job_id": "100003009050906", "location_code": "hk", "company": "The Society for Community Organization Ltd", "job_title": "Temporary Estate Assistant (1-year contract) (Sham Shui Po)", "description": "SoCO is a non-profit-making organization motivated by a common dream: \"Let us work hand in hand and shoulder to shoulder to build a caring, equal and just society\". We are now looking for the committed person for the following post of Transitional Housing project:\n\nTemporary Estate Assistant (1-year contract) (Sham Shui Po)\n\nDuty: To assist administration works of the project.\n\nQualification: Academic qualification equivalent to or above Diploma level from a local or overseas tertiary educational institution with at least 6 months of working experience; ability to work under pressure; good team-work spirit; understand and support the mission of SoCO.\n\nPlease send your application with full resume, the post applied and expected salary to our organization at 3/F, 52 Princess Margaret Road, Homantin, Kowloon, Hong Kong or by e-mail.\n\n\nPersonal information collected is for recruitment purpose only and will be treated in strict confidence.\n\nWe are an equal opportunities employer.\n\n[Closing date of application: 13 February 2022]", "employment_types": ["Full Time"], "selling_points": [], "locations": ["Sham Shui Po Area"], "categories": ["Public / Civil", "Social Services - Community / Non-profit Organization"], "post_time": "2022-01-14T11:44:03Z", "salary": {"currency": null, "max": null, "min": null, "period": "monthly", "term": null}, "salary_visible": false, "title_keywords": ["assistant"], "responsibilities": ["work under pressure", "recruitment", "transitional housing", "administration"], "requirements": {"degrees": ["diploma"], "majors": [], "languages": [], "language_level": [], "hard_skills": [], "soft_skills": ["committed", "motivated", "confidence", "work under pressure"], "languages_combined": []}, "experience_required": {"duration": [], "field": []}}, {"job_id": "100003009047469", "location_code": "hk", "company": "The University of Hong Kong", "job_title": "Project Assistant (at the rank of Research Assistant I/II) (509157)", "description": "Project Assistant (at the rank of Research Assistant I/II) in the School of Public Health\u00a0(Ref.: 509157) (to commence as soon as possible for 9 months, with the possibility of renewal)\n\nApplicants should possess a Bachelor's degree or above in social work, public administration, or a related discipline. They should have an excellent command of written and spoken English and Chinese (including Cantonese), a strong sense of responsibility, and the ability to work independently and multi-task. They should be sensible and attentive to details. Experience in computation is highly preferred. Those with higher qualifications and/or relevant experience may be considered as Research Assistant I.\n\nThe appointee will assist in the implementation of the Jockey Club SMART Family-Link Project, which aims to promote family well-being by leveraging Information and Communications Technology (ICT) for innovative family service. He/She will liaise with different project stakeholders, assist in programme and training materials development, draft reports, handle day-to-day administrative work, and perform other duties as assigned. Irregular working hours and outdoor work may be required occasionally.\n\nA highly competitive salary commensurate with qualifications and experience will be offered, in addition to annual leave and medical benefits.\n\nThe University only accepts online application for the above post. Applicants should apply online and upload an up-to-date C.V. Review of applications will start on December 23, 2021 and continue until January 31, 2022 (extended to April 30, 2022), or until the post is filled, whichever is earlier.\n\n\u6709\u610f\u7533\u8acb\u8005\u8acb \u6309 APPLY NOW\u7533\u8acb\n\n", "employment_types": ["Full Time"], "selling_points": ["liaise with different project stakeholders", "handle day-to-day administrative work", "perform other duties as assigned"], "locations": ["Pok Fu Lam"], "categories": ["Admin & HR", "Clerical / Admin Staff", "Sciences, Lab, R&D", "Research & Development (R&D)", "Public / Civil", "Social Services - Community / Non-profit Organization"], "post_time": "2022-01-14T03:12:44Z", "salary": {"currency": null, "max": null, "min": null, "period": "monthly", "term": null}, "salary_visible": false, "title_keywords": ["research assistant", "project assistant"], "responsibilities": ["perform other duties", "outdoor work", "administrative work", "implementation", "reports", "liaise with", "administration"], "requirements": {"degrees": ["degree or above", "bachelor"], "majors": ["social work", "public administration"], "languages": ["cantonese", "english", "chinese"], "language_level": ["excellent"], "hard_skills": [], "soft_skills": ["work independently", "multi-task", "attentive to details", "sense of responsibility", "innovative"], "languages_combined": [{"language": "cantonese", "language_level": ["excellent"]}, {"language": "english", "language_level": ["excellent"]}, {"language": "chinese", "language_level": ["excellent"]}]}, "experience_required": {"duration": [], "field": ["research", "relevant experience"]}}, {"job_id": "100003009050924", "location_code": "hk", "company": "The Society for Community Organization Ltd", "job_title": "Temporary Attendant (1-year contract) (Sham Shui Po)", "description": "SoCO is a non-profit-making organization motivated by a common dream: \"Let us work hand in hand and shoulder to shoulder to build a caring, equal and just society\". We are now looking for the committed person for the following post of Transitional Housing project:\n\nTemporary Attendant (1-year contract) (Sham Shui Po)\n\nDuty: To assist frontline operation duties of the project.\n\nQualification: Effectively work in team work in operation and social establishment programme to employ residents of the project; ability to work under pressure; good team-work spirit; understand and support the mission of SoCO.\n\nPlease send your application with full resume, the post applied and expected salary to our organization at 3/F, 52 Princess Margaret Road, Homantin, Kowloon, Hong Kong or by e-mail.\n\n\nPersonal information collected is for recruitment purpose only and will be treated in strict confidence.\n\nWe are an equal opportunities employer.\n\n[Closing date of application: 13 February 2022]", "employment_types": ["Full Time"], "selling_points": [], "locations": ["Sham Shui Po Area"], "categories": ["Public / Civil", "Social Services - Community / Non-profit Organization"], "post_time": "2022-01-14T11:48:30Z", "salary": {"currency": null, "max": null, "min": null, "period": "monthly", "term": null}, "salary_visible": false, "title_keywords": [], "responsibilities": ["recruitment", "transitional housing", "work under pressure"], "requirements": {"degrees": [], "majors": [], "languages": [], "language_level": [], "hard_skills": [], "soft_skills": ["committed", "motivated", "confidence", "work under pressure"], "languages_combined": []}, "experience_required": {"duration": [], "field": []}}, {"job_id": "100003009045987", "location_code": "hk", "company": "Hong Kong Sheng Kung Hui Welfare Council Limited", "job_title": "\u884c\u653f\u4e3b\u4efb Administration Officer\u3014\u7de8\u865f\uff1aPGR/AO/20211022-13\u3015", "description": "\u8981\u6c42\ufe30\n\n\u6301\u672c\u5730\u5927\u5b78\u5b78\u4f4d\u6216\u540c\u7b49\u5b78\u6b77\uff0c\u4e2d\u5b78\u6703\u8003\u4e94\u79d1\u5408\u683c(\u5305\u62ec\u4e2d\u6587\u53ca\u82f1\u6587(\u8ab2\u7a0b\u4e59)\u9054D\u7d1a\u6216\u4ee5\u4e0a)\u6216\u4e2d\u5b78\u6587\u6191\u8003\u8a66\u540c\u7b49\u7b49\u7d1a\n\u5177\u5169\u5e74\u6216\u4ee5\u4e0a\u76f8\u95dc\u5de5\u4f5c\u7d93\u9a57\n\u719f\u6089\u4e2d\u82f1\u6587\u96fb\u8166\u6587\u66f8\u8655\u7406\n\u5177\u7ba1\u7406\u53ca\u5efa\u7acb\u7cfb\u7d71\u3001\u4eba\u529b\u8cc7\u6e90\u7ba1\u7406\u7d93\u9a57\u8005\u512a\u5148\n\u8077\u8cac\ufe30\n\u8ca0\u8cac\u7b56\u5283\u53ca\u7d71\u7c4c\u90e8\u9580\u4e4b\u767c\u5c55\u3001\u904b\u4f5c\u53ca\u884c\u653f\u9805\u76ee\uff0c\u54e1\u5de5\u7763\u5c0e\u53ca\u57f9\u8a13\uff0c\u4e26\u5354\u52a9\u63a1\u8cfc\uff0c\u7ba1\u7406\u8cc7\u7522\uff0c\u8cc7\u6599\u7d71\u8a08\u53ca\u5206\u6790\u3002\n\n\n\n\u5168\u8077\u54e1\u5de5\u53ef\u4eab\u6709\u4ee5\u4e0b\u5b8c\u5584\u798f\u5229\uff1a\n\u53ef\u4eab\u6709\u6709\u85aa\u5e74\u504717\u5929\u3001\u516c\u773e\u5047\u671f17\u5929\u3001\u5a5a\u5047\u3001\u5206\u5a29\u5047\u3001\u6069\u6064\u5047\u3001\u4f8d\u7522\u5047\u3001\u8d85\u6642\u5de5\u4f5c\u88dc\u5047\u3001\u514d\u8cbb\u9ad4\u6aa2\u3001\u91ab\u7642\u4fdd\u96aa\u3001\u4eba\u58fd\u4fdd\u96aa\u3001\u91ab\u7642\u512a\u60e0\u3001\u50f1\u4e3b\u5f37\u7a4d\u91d1\u4f9b\u6b3e\u6309\u5e74\u8cc7\u6700\u9ad8\u53ef\u905e\u589e\u81f315%\u3001\u5728\u8077\u57f9\u8a13\u53ca\u826f\u597d\u6649\u5347\u968e\u68af\u7b49\u3002\n\n\n\n\u6709\u610f\u8005\u8acb\u5177\u5c65\u6b77\u53ca\u5217\u660e\u671f\u671b\u85aa\u916c\u5bc4\ufe30\u65b0\u754c\u5c6f\u9580\u9707\u5bf0\u8def82\u865f\u00a0\u2013\u00a0\u5eb7\u6069\u5712\u4eba\u529b\u8cc7\u6e90\u53ca\u884c\u653f\u7d93\u7406\u6536\u6216\u6309\"Apply Now\"\u3002\u7533\u8acb\u4eba\u4e4b\u7be9\u9078\u5c07\u6703\u5373\u6642\u9032\u884c\u76f4\u81f3\u4e8c\u96f6\u4e8c\u4e8c\u5e74\u4e00\u6708\u4e8c\u5341\u516b\u65e5\u6216\u6709\u95dc\u8077\u4f4d\u7a7a\u7f3a\u5df2\u88ab\u586b\u88dc\u70ba\u6b62\u3002\n\n\u4e00\u5207\u7533\u8acb\u8cc7\u6599\u7d55\u5c0d\u4fdd\u5bc6\u53ca\u53ea\u7528\u4f5c\u62db\u8058\u6709\u95dc\u8077\u4f4d\u3002\u5982\u7533\u8acb\u8005\u5728\u622a\u6b62\u65e5\u671f\u5f8c\u516b\u661f\u671f\u5167\u4ecd\u672a\u7372\u96fb\u8a71\u7d04\u898b\u8005\uff0c\u5176\u7533\u8acb\u53ef\u4f5c\u843d\u9078\u8ad6\uff0c\u6055\u4e0d\u53e6\u51fd\u901a\u77e5\uff0c\u672c\u798f\u5229\u5354\u6703\u5c07\u4fdd\u5b58\u7533\u8acb\u6587\u4ef6\u4e0d\u8d85\u904e\u516d\u500b\u6708\u3002\u5982\u6b32\u53c3\u8003\u5354\u6703\u8cc7\u6599\uff0c\u8acb\u767b\u5165\u7db2\u5740 :\u00a0http://www.skhwc.org.hk", "employment_types": ["Full Time", "Contract"], "selling_points": [], "locations": ["Tuen Mun Area"], "categories": ["Admin & HR", "Clerical / Admin Staff", "Others", "Public / Civil", "Social Services - Community / Non-profit Organization"], "post_time": "2022-01-13T18:55:10Z", "salary": {"currency": null, "max": null, "min": null, "period": "monthly", "term": null}, "salary_visible": false, "title_keywords": ["\u884c\u653f\u4e3b\u4efb"], "responsibilities": [], "requirements": {"degrees": [], "majors": [], "languages": [], "language_level": [], "hard_skills": [], "soft_skills": [], "languages_combined": []}, "experience_required": {"duration": [], "field": []}}, {"job_id": "100003009056258", "location_code": "hk", "company": "St. James' Settlement", "job_title": "\u4e8c\u7d1a\u5bb6\u5c45\u7167\u9867\u54e1 (HCW II) (\u5408\u7d04)\u3008\u7de8\u865f: CC/06222\u3009", "description": "\u8981\u6c42\ufe30\n\n\u5c0f\u516d\u7a0b\u5ea6\u6216\u4ee5\u4e0a\uff0c\u63d0\u4f9b\u5728\u8077\u57f9\u8a13\n\u5177\u76f8\u95dc\u5de5\u4f5c\u7d93\u9a57\u6216\u6301\u8d77\u5c45\u7167\u9867\u8ab2\u7a0b/\u8b77\u7406\u8b49\u66f8\u512a\u5148\n\u6709\u8010\u6027\uff0c\u71b1\u8aa0\u53ca\u826f\u597d\u670d\u52d9\u614b\u5ea6\n\u8077\u8cac\ufe30\n\n\u8ca0\u8cac\u63d0\u4f9b\u670d\u52d9\u4e88\u5c45\u5bb6\u9ad4\u5f31\u9577\u8005\u53ca\u5176\u7167\u9867\u8005\uff0c\u5305\u62ec\uff1a\u5fa9\u5eb7\u904b\u52d5\u3001\u8b77\u7406\u3001\u8a8d\u77e5\u8a13\u7df4\u3001\u500b\u4eba\u7167\u9867\u3001\u9001\u98ef\u3001\u5bb6\u5c45\u6e05\u6f54\u53ca\u966a\u8a3a\u7b49\u5de5\u4f5c\n\u61c9\u5fb5\u6642\uff0c\u8acb\u8a3b\u660e\u9078\u64c7\u7684\u5de5\u4f5c\u5730\u9ede\uff1a\u7063\u4ed4/\u4e2d\u897f\u5340/\u6771\u5340\n\n\n\n\u6709\u610f\u8005\u8acb\u65bc18/02/2022\u6216\u4e4b\u524d\uff0c\u51fd\u9644\u5c65\u6b77\u6309\u201cAPPLY NOW\u201d\uff0c\u6216\u90f5\u5bc4\u81f3\u7063\u4ed4\u77f3\u6c34\u6e20\u885785\u865f3\u6a133\u5ba4 \u8056\u96c5\u5404\u798f\u7fa4\u6703 \u6539\u5584\u5bb6\u5340\u53ca\u793e\u5340\u7167\u9867\u670d\u52d9\uff0c\u6216\u81f4\u96fb28313238\uff0c\u6216\u50b3\u771f\u81f334279206\u3002", "employment_types": ["Full Time", "Contract"], "selling_points": ["\u5177\u76f8\u95dc\u5de5\u4f5c\u7d93\u9a57\u6216\u6301\u8d77\u5c45\u7167\u9867\u8ab2\u7a0b/\u8b77\u7406\u8b49\u66f8\u512a\u5148", "\u6709\u8010\u6027\uff0c\u71b1\u8aa0\u53ca\u826f\u597d\u670d\u52d9\u614b\u5ea6", "\u8ca0\u8cac\u63d0\u4f9b\u670d\u52d9\u4e88\u5c45\u5bb6\u9ad4\u5f31\u9577\u8005\u53ca\u5176\u7167\u9867\u8005"], "locations": ["Central & Western Area"], "categories": ["Public / Civil", "Social Services - Community / Non-profit Organization"], "post_time": "2022-01-18T03:43:37Z", "salary": {"currency": null, "max": null, "min": null, "period": "monthly", "term": null}, "salary_visible": false, "title_keywords": [], "responsibilities": [], "requirements": {"degrees": [], "majors": [], "languages": [], "language_level": [], "hard_skills": [], "soft_skills": [], "languages_combined": []}, "experience_required": {"duration": [], "field": []}}]