[{"job_id": "100003009052697", "location_code": "hk", "company": "EternityX Marketing Technology Limited", "job_title": "Digital Marketing- Senior/ Account Executive", "description": "Job Responsibilities:\n\nExecute all aspects of digital media campaign executions across different channels\nPerform digital media planning, buying across all products and platforms in the market\nPerform fundamental support for pitch, proposal and projects on a local, national and international basis\nProvide in-\u00addepth analysis to get insights using all obtainable analytics tools.\nAssist Senior Account Manager to achieve all campaign objectives through close monitoring and frequent optimisations.\nProvide clients servicing and answer enquires for corporate clients, advertising agencies and resellers at both local and regional level.\nDeliver accurate updates on campaigns to clients on both overall business and daily campaign performance\nBuild strong, long-term client relationships and maintain frequent contact\n\nRequirements:\n\nFresh graduate are also welcomed\nExperience in operating digital advertising platform, (such as\u00a0Facebook, Google, DBM, The Trade Desk...etc) is preferable\nExperience in handling China Related Media platforms (such as\u00a0Baidu, Wechat, Weibo, 360...etc) is preferable\nAble to communicate in Cantonese, English & Mandarin.\nProficient in Chinese language (Simplified & Traditional) and fluent in English.\nStrong interpersonal skills with great attention to details.\nMulti-tasking and able to work under pressure to meet deadlines & business targets.\nPassionate about the Internet and latest online advertising technologies", "employment_types": ["Full Time", "Permanent"], "selling_points": ["Uncapped Quarterly Commission + Performance Bonus", "Opportunity To Work In A Multi-Cultural Team", "Professional Training in China & Global Digi. Mkt"], "locations": ["Sheung Wan"], "categories": ["Media & Advertising", "Account Servicing", "Marketing / Public Relations", "Marketing - General / Support", "Digital Marketing"], "post_time": "2022-01-17T03:44:16Z", "salary": {"currency": null, "max": null, "min": null, "period": "monthly", "term": null}, "salary_visible": false, "title_keywords": ["account executive", "digital marketing"], "responsibilities": ["analytics tools", "advertising", "analysis", "monitoring", "maintain", "contact", "planning"], "requirements": {"degrees": ["fresh graduate"], "majors": [], "languages": ["cantonese", "english", "chinese", "mandarin"], "language_level": ["fluent", "proficient"], "hard_skills": ["facebook", "wechat"], "soft_skills": ["multi-tasking", "interpersonal skills", "attention to details", "meet deadlines", "passionate about", "work under pressure"], "languages_combined": [{"language": "cantonese", "language_level": []}, {"language": "english", "language_level": ["fluent", "proficient"]}, {"language": "chinese", "language_level": ["fluent", "proficient"]}, {"language": "mandarin", "language_level": []}]}, "experience_required": {"duration": [], "field": ["related", "digital", "advertising", "media"]}}, {"job_id": "100003009038978", "location_code": "hk", "company": "Klarity (HK) Limited", "job_title": "Digital Marketing Executive", "description": "Key Responsibilities:\n\nSupport and execute all marketing activities to meet business goals including advertising and promotional activities: traditional, in-store, online, direct, and local marketing activities.\nExecute all web, SEO/SEM, EDM, social media, and advertising campaigns and review execution.\nSet up campaigns and ads to optimize for various KPIs (conversions, awareness, traffic...) across multiple paid channels.\nEffectively optimize targeting and segmentation as well as the allocations of budgets across multiple paid channels in order to generate cost-effective actions and conversions.\nSocial Media initiatives: create social media calendars, post on social media platforms, enhance the reach and optimize.\nUpdate and maintain e-commerce website (shopify / wordpress) and marketplaces.\nLiaise with the design team to share a brief on the campaigns.\nAnalyze and report performance for the website across all the channels.\nConduct post-campaign reporting and analysis to deliver reports on the performance of marketing and e-commerce campaigns. Able to make data-driven recommendations for optimization and to improve effectiveness in all marketing paid channels.\nMonitor competitors' activities and get insights. Stay up to date with digital media technologies and the latest trends\nDrive e-Commerce business growth by analyzing trends/ opportunities, executing, and implementing tactical programs that leverage those trends/ opportunities\nEnhance e-Commerce customer experience. This includes the development of customer retention and loyalty programs.\n\nKey Job Requirements:\n\nAt least 1-2 years of relevant working experience: Experience in a tech, E-commerce, or Startup environment preferred with a proven track record of hands-on experience in marketing campaigns\nln-depth knowledge and hands-on experience across all the digital ecosystems that include, but are not limited to paid media platforms, Google Network, Social Media platforms, and SEO.\nHands-on experience in planning and buying digital media on platforms such as Google Ads (SEM, Shopping Ads, Display, video), Facebook and e-commerce platforms ads.\nHands-on experience setting up, implementing, and optimizing Google Ads, Facebook, and affiliate campaigns.\nHands-on experience/exposure in optimizing landing pages and user funnels.\nHands-on experience with tracking tools and setting up measuring strategies.\nEquipped with the latest trends and best practices in online marketing and measurement.\nKnowledge with A/B and web analytics tools like Google Analytics\nExperience in E-commerce Campaigns\nSocial Media Marketing initiatives\nEmail Marketing campaigns\nStrong interpersonal and communication skills", "employment_types": ["Full Time"], "selling_points": [], "locations": ["Kwun Tong"], "categories": ["Marketing / Public Relations", "Digital Marketing"], "post_time": "2022-01-17T16:20:57Z", "salary": {"currency": null, "max": null, "min": null, "period": null, "term": null}, "salary_visible": false, "title_keywords": ["digital marketing executive"], "responsibilities": ["business goals", "data", "social media platforms", "website", "design", "improve effectiveness", "maintain", "liaise with", "advertising", "monitor", "reports", "kpis", "report", "social media", "cost", "reporting", "seo", "edm", "review", "promotional activities", "executing", "advertising campaigns", "budgets", "analysis", "sem"], "requirements": {"degrees": [], "majors": [], "languages": [], "language_level": [], "hard_skills": ["google analytics", "seo", "e-commerce", "sem", "web analytics", "facebook"], "soft_skills": ["web analytics", "communication skills", "hands-on", "interpersonal"], "languages_combined": []}, "experience_required": {"duration": ["at least 1-2 years"], "field": ["social media", "video", "e-commerce", "tech", "relevant working experience", "marketing", "digital media", "digital", "media", "planning"]}}, {"job_id": "100003009054422", "location_code": "hk", "company": "Bright International Education Limited", "job_title": "Digital Marketing Officer", "description": "Digital Marketing Officer (Branding)\nJob Highlights\n\u00a0Oversee digital mkt for Education field, distribution brands\u00a0\nMultimedia exp with various social media knowhow\n\u00a0passionate in promoting English education trends\n\u00a0Digital Marketing training is provided\u00a0\nJob Description\n\nJob Responsibilities\n\nFormulate digital marketing strategies and plans, including the disciplines of content & paid marketing, including social media, SEO, SEM, website management, advertising, eDM, etc.\nLead integrated digital marketing campaigns from concept to execution\n\u00a0Brainstorm new and creative growth strategies;\nBuild brand awareness and increase engagement by developing and designing strong content strategies across digital channels;\nProofread and initiate creative content to ensure it stays on top of trends in English Education field\nPerform market and digital analysis, report and generate insights to identify opportunity in the market and support impact decisions;\nSet KPIs and implement tracking to evaluate the performance of different digital marketing campaigns through different analytic tools and make recommendations to optimize;\n\u00a0Plan, execute and measure experiments and conversion tests;\nAd hoc assignments as required.\n\nJob Requirements\n\nPassionate in promoting English Education, knowledge in education field is a plus\nBachelor\u2019s degree in Marketing, Multimedia, Communications or related disciplines;\nMinimum of 1 years\u2019 digital marketing experience\nMultimedia experience is preferred;\nDemonstrable experience leading and managing SEO/SEM, marketing database, email, social media and/or display advertising campaigns\nHighly creative with experience in identifying target audiences and devising digital campaigns that engage, inform and motivate\nStrong analytical skills and data-driven thinking\nWell-organized, able to multitasking and cope with fast-paced environment;\nKnowledge of the various marketing operations and consumer experiences;\nFamiliar with Social Media,\nFamiliar with SEO/SEM, Google Ads and other digital channels;\nGood communication and proficient in spoken and written English and Cantonese.\nExperience with A/B and multivariate experiments\nSolid knowledge of website analytics tools (e.g., Google Analytics, NetInsight, Omniture, WebTrends)", "employment_types": ["Full Time"], "selling_points": [], "locations": ["Mong Kok"], "categories": ["Marketing / Public Relations", "Digital Marketing"], "post_time": "2022-01-17T09:29:10Z", "salary": {"currency": null, "max": null, "min": null, "period": "monthly", "term": null}, "salary_visible": false, "title_keywords": ["digital marketing officer"], "responsibilities": ["website", "plan", "designing", "plans", "make recommendations", "digital marketing strategies", "advertising", "creative content", "digital marketing campaigns", "developing", "kpis", "report", "social media", "management", "seo", "edm", "tracking", "analysis", "evaluate", "ad hoc assignments", "sem"], "requirements": {"degrees": ["degree", "bachelor"], "majors": ["related disciplines", "marketing", "communications"], "languages": ["cantonese", "english"], "language_level": ["proficient", "good"], "hard_skills": ["analytics tools", "plus", "inform", "seo", "google analytics", "analytical skills", "multimedia", "sem"], "soft_skills": ["passionate", "fast-paced environment", "well-organized", "analytical skills", "communication", "creative", "driven"], "languages_combined": [{"language": "cantonese", "language_level": ["proficient", "good"]}, {"language": "english", "language_level": ["proficient", "good"]}]}, "experience_required": {"duration": ["minimum of 1 years"], "field": ["social media", "advertising", "marketing", "digital marketing", "database", "digital"]}}, {"job_id": "100003009056155", "location_code": "hk", "company": "\u4fe1\u5c71\u5be6\u696d\u6709\u9650\u516c\u53f8", "job_title": "Digital Marketing Executive", "description": "Job brief\nTo cope with our growth, we are looking for a Digital Marketing Executive to join our team to assist in planning, developing and implementing digital advertising campaigns within budget.\n\nJob Highlights\n2-3 years relevant experience in digital marketing. Able to identify new media / social media partners and market trends proactively.\nImmediate available is highly preferred.\n\nResponsibilities:\n- Assist in planning, developing and implementing digital advertising campaigns within budget and on schedule to achieve target metrics\n- Support the full spectrum of marketing activities\n- Good eye for digital marketing trends and website, e-shop traffic improvement\n- Manage official social media image and performance\n- Propose creative and social media friendly ideas in order to maximize campaign buzz\n- Closely monitor the day-to-day performance of social and online marketing platforms and track effectiveness of marketing campaigns\n- Identify new media / social media partners and market trends proactively\n- Formulate new e-marketing initiatives to generate sales and brand awareness\n- Prepare advertising plans for search, display, video and social media ads\n- Collaborate with internal teams and third-party agencies to create result-driven campaigns and optimize user experience, as well as excellent content production\n- Other ad-hoc projects as assigned\nRequirements\n- Bachelor's degree in marketing or digital marketing or related field\n- 2-3 years relevant experience in digital marketing (agency background is a plus)\n- Strong knowledge of performance/digital marketing (SEO/SEM/Display/Paid Social and etc)\n- Well organized and fast learner\n- High adaptability and flexibility\n- Attention to details and ability to work under tight timeline and multi-task independently\n- Strong ability to focus on customer/market and take initiative\n- Highly driven and results-oriented work ethic with creativity\n- Hands-on experience in digital marketing and/or CRM campaign management using Oracle, Salesforce, Marketo, etc is preferred\n- Experience in China and global marketing is a plus\n- Excellent command of both written and spoken English and Chinese, preferably with proficiency in Putonghua\n- Proficient in MS Office (Word, Excel & Power Point)\n- Immediate available is highly preferred", "employment_types": ["Full Time"], "selling_points": ["Hong Kong Science Park", "Able to identify new media / social media partners", "2-3 years relevant experience"], "locations": ["Shatin Area"], "categories": ["Marketing / Public Relations", "Digital Marketing"], "post_time": "2022-01-18T03:26:28Z", "salary": {"currency": null, "max": null, "min": null, "period": "monthly", "term": null}, "salary_visible": false, "title_keywords": ["digital marketing executive"], "responsibilities": ["collaborate with", "social media", "e-shop", "ideas", "advertising", "budget", "monitor", "developing", "website", "teams", "user experience", "digital marketing", "schedule", "marketing campaigns", "plans", "ad-hoc projects", "advertising campaigns", "planning"], "requirements": {"degrees": ["degree", "bachelor"], "majors": ["marketing", "digital marketing"], "languages": ["putonghua", "english", "chinese"], "language_level": ["excellent", "proficiency"], "hard_skills": ["excel", "plus", "seo", "salesforce", "word", "sem", "power point", "focus", "ms office", "oracle"], "soft_skills": ["independently", "multi-task", "well organized", "driven", "hands-on", "adaptability", "attention to details", "work ethic", "focus", "fast learner", "initiative"], "languages_combined": [{"language": "putonghua", "language_level": ["proficiency", "excellent"]}, {"language": "english", "language_level": ["excellent"]}, {"language": "chinese", "language_level": ["excellent"]}]}, "experience_required": {"duration": ["2-3 years"], "field": ["management", "agency", "marketing", "relevant experience", "digital marketing"]}}, {"job_id": "100003009052851", "location_code": "hk", "company": "VI Group Service Pty Limited", "job_title": "Digital Marketing Executive", "description": "Job Responsibilities:\n\nFormulate and implement content marketing strategy and campaigns to drive online awareness, lead generation and engagement for the various corporate events and public mission initiatives\nDevelop engaging content and assure content excellence for marketing channels including website, blogs and social media platforms\nDevelop and implement social media plans and explore tactics to penetrate brand image to young segment\nDraw traffic to various social media accounts and drive engagement rate and number of fans\nKeep abreast of the latest development, tactics, and policy of various social media channels\nMake use of social media analytics and social listening tools to timely optimize the effectiveness of digital campaigns and engagement effort\nCreate high quality video contents including ideation and script writing to maximize engagement on digital platforms\nWork with designers to produce impactful and attractive visual and design for various public mission initiatives and campaigns\nManage quality assurance for creative and video production output\n\nJob Requirements:\n\nBachelor\u2019s degree or above in Business, Marketing, Communications, Digital Marketing or equivalent\nMinimum five years or above relevant experience in social media marketing, brand management, digital marketing\nTrack records in developing and implementing impactful social media marketing campaigns and promotions (Instagram, Facebook, YouTube)\nExperienced in managing internal/external social media and video production team/KOL/Youtubers\nHighly flexible work style to respond to the dynamic and rapidly changing environment\nWell versed in social media analytics tools, deployment of SEO and website CMS platforms\nCreative, Pro-active, open-minded, and result-oriented\nExcellent interpersonal and communications skills with a strong command in both written and spoken English and Chinese\n\nWe offer attractive remuneration package which includes double pay and discretionary bonus. Interested parties please send your CV indicating your current salary, expected salary and availability to HR Department, by email via \"Apply Now\"\n\n(Personal data collected will be treated in the strictest confidence and will be handled by authorized personnel for recruitment-related purposes only. Applicants who do not hear from us within 3 months may consider their application unsuccessful and their data will be destroyed within 24 months of receipt.)", "employment_types": ["Full Time"], "selling_points": ["Google / Facebook ad manager", "Create engaging content for different social media", "Formulate new e-marketing initiatives"], "locations": ["Tsim Sha Tsui"], "categories": ["Marketing / Public Relations", "Marketing - Brand / Product Management", "Marketing - Market Research", "Digital Marketing"], "post_time": "2022-01-17T04:20:22Z", "salary": {"currency": null, "max": null, "min": null, "period": "monthly", "term": null}, "salary_visible": false, "title_keywords": ["digital marketing executive"], "responsibilities": ["social media", "video production", "social media platforms", "quality", "website", "design", "develop", "visual", "digital campaigns", "contents", "plans"], "requirements": {"degrees": ["degree or above", "bachelor"], "majors": ["business", "digital marketing", "communications", "marketing"], "languages": ["english", "chinese"], "language_level": ["excellent"], "hard_skills": ["analytics tools", "seo", "dynamic", "deployment", "facebook"], "soft_skills": ["flexible", "interpersonal", "open-minded", "dynamic", "pro-active", "creative", "result-oriented"], "languages_combined": [{"language": "english", "language_level": ["excellent"]}, {"language": "chinese", "language_level": ["excellent"]}]}, "experience_required": {"duration": ["minimum five years"], "field": ["social media", "management", "brand", "marketing", "relevant experience", "digital marketing"]}}, {"job_id": "100003009053644", "location_code": "hk", "company": "United Asia Finance Limited", "job_title": "Senior Officer, Digital Marketing", "description": "The Role\n\nThe Social Media Specialist is\u00a0support all social media related projects for the APAC region. The role will report to the Content & Communications Manager. \u00a0\n\nResponsibilities:\n\nCreate, maintain, and implement content calendar for Facebook, Instagram, LinkedIn and YouTube based on feedback from internal departments, industry updates, news & trends and competitor landscape to maximize follower retention and the efficiency of campaign deliverables.\nGenerate high quality content development and create social assets for product launch and social media campaign, identifying content and digital communication material needs across platforms.\nAssist influencer campaign. Co-ordinate shooting and social media instant postings.\nFollow closely and develop analytics social media reports on the trending topics and competitive landscape, keep up with latest digital trends across social media and tech along with competitor analysis.\nWork proactively with in-house designers and co-ordinate with agency to ensure timely deliverables.\n\n\u00a0Requirement:\n\nBachelor\u2019s Degree in Marketing or a related field\nMust be digital and social media savvy\nStrong creative writing skill in English and Chinese\nExperience in planning and creating creative content for social media channels\nExperience in utilizing social media monitoring and social listening tools, e.g., Brandwatch, Sprout Social.\nA great storyteller with consumer mindset on building audience centric content\nPassionate about APAC & China social media marketing best practices & digital trends\n\nOtter Products is an equal employment opportunity employer (EEO).", "employment_types": ["Full Time", "Permanent"], "selling_points": ["Bachelor\u2019s degree or above in Business", "5 years or above relevant experience", "Double pay and Discretionary bonus"], "locations": ["Wan Chai"], "categories": ["Marketing / Public Relations", "Public Relations - General / Support", "Others", "Digital Marketing"], "post_time": "2022-01-17T07:16:57Z", "salary": {"currency": null, "max": null, "min": null, "period": "monthly", "term": null}, "salary_visible": false, "title_keywords": ["senior officer", "digital marketing"], "responsibilities": ["social media", "co-ordinate with", "analysis", "quality", "develop", "communication", "maintain", "reports", "facebook"], "requirements": {"degrees": ["degree", "bachelor"], "majors": ["marketing"], "languages": ["english", "chinese"], "language_level": [], "hard_skills": ["writing skill"], "soft_skills": ["creative", "passionate about", "writing skill"], "languages_combined": [{"language": "english", "language_level": []}, {"language": "chinese", "language_level": []}]}, "experience_required": {"duration": [], "field": ["social media", "planning"]}}, {"job_id": "100003009055938", "location_code": "hk", "company": "OtterBox Hong Kong Limited", "job_title": "Social Media Specialist", "description": "You'll be responsible for...\n\n\nPerform keywords research and analysis\nMonitor and enhance keywords ranking performance to deliver KPIs\nPlan and optimize on-page website content and landing pages\nLead, develop and execute content and technical SEO strategies\nRecommend changes to website architecture, layouts, content and other factors to improve keywords ranking\nConduct technical SEO and backlink audit, and draw insights for improvement\nDevelop and implement link building strategy\nIdentify SEO trend & Implement best practices\n\nIf you are...\n\n\nDegree holder in Marketing/Information Technology/Communications/e-Commerce or related disciplines\nMinimum 2 years working experience in SEO or online marketing or digital agency.\u00a0Candidates with more experience will consider as Senior Digital Marketing Specialist\nExperience in using SEO tools i.e. SEMRush, Ahrefs, Screaming Frog (or similar) is a MUST;\nExperience in using Google tools i.e. Google Analytics, Google Tag Manager, Google Search Console is a MUST;\nExperience in on-site content writing, technical SEO and link building is a MUST\nGood communication and interpersonal skills\nExcellent in Chinese and English written skill\n\nWe offer...\u00a0\n\nFive-days work per week + Bank Holiday\nSeasonal Project Completion Bonus\nEducation Allowance\nMedical Allowance\nSnacks and drinks\nTraining + Good career prospect in growing Digital Marketing Industry\n\nIf this sounds interesting to you, Apply Now!!\u00a0\n\nPlease come with a portfolio that will demonstrate our required fields as mentioned above. Interested parties, please apply with full resume, portfolio, current, and expected salary.\n\nData collected would be used for recruitment purposes only. Applicants who do not hear from us within 8 weeks may consider their application unsuccessful and their data will be destroyed within 24 months of receipt.", "employment_types": ["Full Time", "Permanent"], "selling_points": ["Generate high quality content development", "Create social assets", "Assist influencer campaign"], "locations": ["Hung Hom"], "categories": ["Marketing / Public Relations", "Marketing - Brand / Product Management", "Marketing - Marketing Communication", "Digital Marketing"], "post_time": "2022-01-18T03:06:32Z", "salary": {"currency": null, "max": null, "min": null, "period": "monthly", "term": null}, "salary_visible": false, "title_keywords": ["social media specialist"], "responsibilities": ["seo", "analysis", "monitor", "website", "audit", "develop", "communication", "digital marketing", "plan", "kpis", "architecture"], "requirements": {"degrees": ["degree holder"], "majors": ["e-commerce", "information technology", "related disciplines", "marketing", "communications"], "languages": ["english", "chinese"], "language_level": ["excellent"], "hard_skills": ["google analytics", "analysis", "seo", "e-commerce"], "soft_skills": ["communication and interpersonal skills", "responsible"], "languages_combined": [{"language": "english", "language_level": ["excellent"]}, {"language": "chinese", "language_level": ["excellent"]}]}, "experience_required": {"duration": ["minimum 2 years"], "field": ["agency", "marketing", "digital marketing", "content writing", "digital"]}}, {"job_id": "100003009046512", "location_code": "hk", "company": "Strategic Digital Marketing Company Limited", "job_title": "Digital Marketing Specialist (SEO) (5 days work)", "description": "Job Descriptions\nResponsibilities\n\nServicing a portfolio of clients targeting Hong Kong, Greater China and global markets under the guidance of Account Managers\nManaging holistic digital campaigns covering SEM, SEO, Social Media Marketing, Display Advertising, Video Advertising and more to achieve performance goals\nEnsuring smooth campaign delivery and optimizing results based on data analytics\nWorking closely with Sales Team in campaign delivery and revenue growth\nThe Successful Applicant(s)\n\nResult-oriented challenge taker\nQuick learner - must promptly pick up various advertising platforms and our world-class AI system for campaign optimization and reporting\nIndependent and able to perform well under pressure\nDetail-oriented and organized\nPossessing strategic mindset and strong data analytical skills\nPossessing strong communication and interpersonal skills for building client relationships\nGood command of Chinese, English and Putonghua\nDigital agency background / experience in digital marketing preferred but not a must\nCandidates who are certified with Google Ads are strongly preferred", "employment_types": ["Full Time", "Permanent"], "selling_points": ["2 years experience in SEO", "Friendly and energetic working environment", "Bank Holiday, Birthday Leave & Performance Bonus"], "locations": ["Lai Chi Kok"], "categories": ["Information Technology (IT)", "IT - Webmaster / SEO", "Sales, CS & Business Devpt", "Account Servicing", "Marketing / Public Relations", "Digital Marketing"], "post_time": "2022-01-17T16:21:08Z", "salary": {"currency": null, "max": null, "min": null, "period": "monthly", "term": null}, "salary_visible": false, "title_keywords": ["digital marketing specialist"], "responsibilities": ["guidance", "social media", "reporting", "seo", "advertising", "data", "communication", "sales team", "revenue growth", "sem", "digital campaigns", "digital marketing"], "requirements": {"degrees": [], "majors": [], "languages": ["putonghua", "english", "chinese"], "language_level": ["good command"], "hard_skills": ["seo", "ai", "data analytics", "analytical skills", "sem"], "soft_skills": ["organized", "independent", "quick learner", "detail-oriented", "analytical skills", "communication and interpersonal skills", "smooth", "result-oriented", "perform well under pressure", "world-class"], "languages_combined": [{"language": "putonghua", "language_level": ["good command"]}, {"language": "english", "language_level": ["good command"]}, {"language": "chinese", "language_level": ["good command"]}]}, "experience_required": {"duration": [], "field": ["agency", "digital", "digital marketing"]}}, {"job_id": "100003009053478", "location_code": "hk", "company": "Technik Performance Limited", "job_title": "Digital Marketing Executive (Strong passionate is wanted)", "description": "Responsibilities:\n\nTo plan and execute the marketing and communications strategies across all paid and owned digital touchpoints for all regions\nWork with UX team on customer journey for new digital tools/platforms to ensure the delivery of good customer experience across company\u2019s omni channel ecosystem as a result to grow in traffic and usage\nEnsure to define KPIs and measurement metrics for each activity, closely monitor the results, and prepare regular report for learning and optimization\nManage external agencies to ensure project is completed on brief and on time, content is on brand and deliver with quality\nWork closely with offline marketing team to ensure campaign is well integrated and well-constructed, digital component deliver the right brand tone and manner, plus work with other internal teams to align content direction and deployment\nMaintain well understanding of company values, products and services\nKeep up with the latest digital trends and solutions, maintain and enhance the digital platforms up to the trend and fitting different stakeholder needs\n\nRequirements:\n\nDegree holder with over 5 years of related experience in digital project management. Exposure in luxury or retail sector will be an advantage\nExperience in managing digital user interface project and deadline sensitive\nDetail oriented, strong problem solving and analytical skill with strong sense of work prioritization\nHands-on experience in using website CMS system and Google analytics\nLogical thinker with good marketing sense, understand importance of brand building, able to judge creative that works well with our brand tone and manner. Good understanding of product marketing and storytelling technique, able to create content for digital communication usage beyond pure offline marketing adaptation\nCreative, self-motivated, organized and a committed team player\nGood command of both written and oral presentation in Mandarin, Cantonese and English\nWe offer 5-day-work week with competitive remuneration packages to the right candidate. Interested parties please send your CV with EXPECTED SALARY through the below application procedure.\n\n(Personal data will be used by Chow Sang Sang (CSS) for recruitment only. CSS may refer suitable applications to other vacancies within CSS and its associated companies. We will retain unsuccessful applications for a maximum period of 24 months.)", "employment_types": ["Full Time"], "selling_points": ["Digital marketing strategies", "Advertising and marketing campaign", "Automotive enthusiasts"], "locations": ["Kowloon Bay"], "categories": ["Media & Advertising", "Strategic Planning", "Marketing / Public Relations", "Digital Marketing"], "post_time": "2022-01-17T08:57:56Z", "salary": {"currency": null, "max": null, "min": null, "period": "monthly", "term": null}, "salary_visible": false, "title_keywords": ["digital marketing executive"], "responsibilities": ["monitor", "measurement", "quality", "teams", "maintain", "plan", "kpis", "prepare regular report"], "requirements": {"degrees": ["degree holder"], "majors": ["project management"], "languages": ["cantonese", "english", "mandarin"], "language_level": ["good command"], "hard_skills": ["google analytics", "analytical skill", "pure", "problem solving", "project management"], "soft_skills": ["organized", "self-motivated", "oral", "marketing sense", "detail oriented", "problem solving and analytical skill", "communication", "project management", "hands-on", "committed", "sensitive", "team player", "creative", "presentation"], "languages_combined": [{"language": "cantonese", "language_level": ["good command"]}, {"language": "english", "language_level": ["good command"]}, {"language": "mandarin", "language_level": ["good command"]}]}, "experience_required": {"duration": ["5 years"], "field": ["related", "digital", "project management"]}}, {"job_id": "100003009054417", "location_code": "hk", "company": "Chow Sang Sang Holdings International Limited", "job_title": "Senior Executive - Digital Marketing", "description": "Thinking Group, a sole distributor of Audio products & Smart Gadget products including: Ultimate Ears (UE), JBL/ Harman Kardon, Aftershokz, Ticwatch ....etc. Founded in 1998, its headquarters in HK and branches in Shenzhen & Taiwan. To cope with our continuous expansion, we are seeking qualified candidates to join us.\n\nResponsibilities:\n\n\nManage and update corporate marketing materials (e.g. company website, brochures, newsletter, etc.)\nWorking with social media platform content update and content writing\nFamiliar with shopline\nDevelop, execute and track Social Media platforms promotional campaigns\nMonitor competitors\u2019 marketing campaign and prepare competitive analysis\nComfortable in small business model and fast changing environment\nManage and communicate with KOL\nConducting market analysis to identify the target audience\nAssist in ad-hoc projects and administrative tasks\n\nRequirements:\n\n\nProactive, Self-motivated, independent and result driven\nA minimum of 1-2 years experience with marketing or social media related knowledge\nGood presentation and communication skills (both spoken and written English & Cantonese) liaise with both internal and external parties on developing and producing marketing materials\nGood team player\nKnowledge of Google ads., Copy writing, Social Media\nKnowledge of Ad network (e.g. Google ads, facebook.......)\nFamilar with audio products is an advantage\nFresh graduate are welcome as Marketing assistant\n\nBenefits:\n\n5 Days work\u00a0\nAnnual leave and Sick leave\nBank holiday and Birthday leave\u00a0\nMedical and Dental allowance", "employment_types": ["Full Time", "Permanent"], "selling_points": ["Plan&execute strategies across digital touchpoints", "Work with UX team on customer journey", "Min 5 years exp in digital project management"], "locations": ["Cheung Sha Wan"], "categories": ["Marketing / Public Relations", "Others", "Digital Marketing", "E-commerce", "Marketing - Brand / Product Management"], "post_time": "2022-01-17T09:27:05Z", "salary": {"currency": null, "max": null, "min": null, "period": "monthly", "term": null}, "salary_visible": false, "title_keywords": ["senior executive", "digital marketing"], "responsibilities": ["communicate with", "social media", "analysis", "social media platforms", "monitor", "develop", "market analysis", "marketing materials", "ad-hoc projects", "administrative tasks", "company website"], "requirements": {"degrees": ["fresh graduate"], "majors": ["marketing"], "languages": ["cantonese", "english"], "language_level": ["good"], "hard_skills": ["facebook"], "soft_skills": ["communication skills", "self-motivated", "good team player", "independent", "driven", "proactive", "presentation"], "languages_combined": [{"language": "cantonese", "language_level": ["good"]}, {"language": "english", "language_level": ["good"]}]}, "experience_required": {"duration": ["minimum of 1-2 years"], "field": ["related", "social media", "marketing"]}}, {"job_id": "100003009053883", "location_code": "hk", "company": "Thinking Group Holding Limited", "job_title": "Marketing Executive", "description": "Responsibilities:\n\nResponsible for all online activities including user acquisition, conversion and retention to deliver continuous optimization and growth\nCreate, manage, and analyze Search Engine Marketing and social media across multiple platforms to achieve user acquisition and conversion goals\nCreation & delivery of all paid acquisition campaigns on social media platforms\nTake a data-driven approach to optimism marketing performance\nAnalyze market landscape and consumer insights to identify business opportunity\nHandle and present the performance and ROI of the above digital campaigns\nLiaise with internal and external parties to provide marketing administrative supports\nAny ad-hoc duties as assigned\n\nRequirements:\n\nDegree holder or above in Marketing, Digital Marketing, New Media Communication, Journalism or related disciplines\nMinimum 3 years marketing experience (less experience will be considered for Executive role)\nHands-on experience in Facebook Ad Manager, SEO, SEM, Google Analytics, Adwords planning and content development is a must\nFamiliar with automated email marketing tools preferable\nPossess Google Ads Search Certification, and Ads Display Certification preferable\nProficiency in design software such as Photoshop, AI is a must, video editing is a plus\nAble to handle multi-tasks with strong problem-solving skills with a can-do attitude\nSee themselves as project lead with strong ability of execution\nExcellent communication and interpersonal skills\nExcellent command of Chinese and English writing\n\nInterested parties are invited to send their applications with full resume stating availability date, present and expected salary to us.\n\nPersonal data provided by job applicants will be used strictly in accordance with our personal data policy and for recruitment purposes only.", "employment_types": ["Full Time", "Permanent"], "selling_points": ["1-2 years experience with marketing / social media", "Knowledge of Google ads., Copy writing, Social Med", "Familar with audio products is an advantage"], "locations": ["Kwun Tong"], "categories": ["Marketing / Public Relations", "Marketing - General / Support", "Marketing - Marketing Communication", "Digital Marketing"], "post_time": "2022-01-17T08:51:49Z", "salary": {"currency": null, "max": null, "min": null, "period": "monthly", "term": null}, "salary_visible": false, "title_keywords": ["marketing executive"], "responsibilities": ["social media", "consumer insights", "data", "social media platforms", "internal and external parties", "digital campaigns", "ad-hoc duties", "liaise with"], "requirements": {"degrees": ["degree holder"], "majors": ["journalism", "related disciplines", "marketing", "digital marketing"], "languages": ["english", "chinese"], "language_level": ["excellent"], "hard_skills": ["google analytics", "plus", "seo", "ai", "problem-solving skills", "adwords", "video editing", "sem", "facebook", "photoshop"], "soft_skills": ["multi-tasks", "can-do attitude", "communication", "hands-on", "communication and interpersonal skills", "problem-solving skills"], "languages_combined": [{"language": "english", "language_level": ["excellent"]}, {"language": "chinese", "language_level": ["excellent"]}]}, "experience_required": {"duration": ["minimum 3 years"], "field": ["marketing", "content development", "planning"]}}, {"job_id": "100003009054411", "location_code": "hk", "company": "Royale International Couriers Limited", "job_title": "Digital Marketing Executive/Officer", "description": "Do you think outside the box? Are you a dynamic storyteller who loves beauty products and is\u00a0passionate about digital marketing? You may be the person we are looking for!\n\nThe successful candidate will be responsible for managing the company\u2019s media platforms such as, Facebook, Instagram, Tiktok, Youtube and Naver. You will be able to learn how to use intelligence tool like Hootsuite and OneSignal to manage the platforms better.\n\n\u00a0Roles and responsibilities:\n\nManage campaigns across all social media platforms\u00a0to achieve designated business goals\nResponsible for content\u00a0creation and storytelling on social media channels\u00a0to produce creative, well written, rich and engaging social media content to maximize ROI and increase brand awareness\nDay-to-day tasks includes performance report consolidation, postings on Social Media and app push scheduling\nManage partnership with KOLs, including incentive offering, posting arrangement and payment settlement\n\nRequirements:\n\nExperience in media marketing with 1-2 years relevant experiences\nFresh graduates are also welcome\nBachelor\u2019s degree in communications, marketing or related field\nUnderstanding of APAC markets such as Hong Kong, Australia, New Zealand, Singapore is preferred\nExcellent written and spoken English and\u00a0Traditional Chinese, particularly in creating content for Asian markets\nA passion in digital marketing and beauty e-commerce\nHigh project management skills with attention to detail and ability to multi-task\nA good team player", "employment_types": ["Full Time", "Permanent"], "selling_points": ["Major handling Direct Email Marketing Campaign", "Good at Marketing Database + Automation Technology", "Multi-cultural environment; B2B Email Marketing"], "locations": ["Kowloon Bay"], "categories": ["Marketing / Public Relations", "Marketing - Direct Marketing", "Marketing - Marketing Communication", "Digital Marketing"], "post_time": "2022-01-17T09:26:16Z", "salary": {"currency": null, "max": null, "min": null, "period": "monthly", "term": null}, "salary_visible": false, "title_keywords": ["officer", "digital marketing executive"], "responsibilities": ["social media", "business goals", "social media platforms", "scheduling", "payment", "social media content", "maximize roi", "report"], "requirements": {"degrees": ["degree", "bachelor"], "majors": ["marketing", "communications"], "languages": ["english", "chinese"], "language_level": ["excellent"], "hard_skills": ["project management", "e-commerce"], "soft_skills": ["good team player", "multi-task", "passion in", "project management skills", "attention to detail"], "languages_combined": [{"language": "english", "language_level": ["excellent"]}, {"language": "chinese", "language_level": ["excellent"]}]}, "experience_required": {"duration": ["1-2 years"], "field": ["marketing", "media"]}}, {"job_id": "100003009054442", "location_code": "hk", "company": "E Tag Limited", "job_title": "Senior Digital Marketing Executive", "description": "Job Description\uff1a\nManage different social media platforms\nPlan and create social media content, from written articles to eyecatching graphics\nRegularly post on social media\nEffectively and efficiently engage with followers\nActively research and understand blockchain and cryptocurrency social media trends to incorporate into the company\nPlan strategies to engage and grow followers\nJob Requirements:\n\nDegree in Marketing, Communication or related disciplines\nFluency in written and spoken English and Cantonese is essential\n1+ years of experience in digital marketing, advertising or social media in advance\nKnowledge and experience in e-commerce or FinTech is a plus\nDetail-minded with excellent teamwork, communication and problem solving skills\nSkills in graphic design, photoshop, Canva or AI is a plus\nExcellent interpersonal and communication skills & can effectively work in a team\nCreative, self-motivated with a passion for active engagement in social media", "employment_types": ["Full Time"], "selling_points": ["Create and manage all marketing initiatives", "Conceptualize and formulate marketing campaigns", "At least 5 years relevant working experience"], "locations": ["Tsuen Wan Area"], "categories": ["Marketing / Public Relations", "Marketing - Brand / Product Management", "Marketing - Marketing Communication", "Digital Marketing"], "post_time": "2022-01-17T09:39:51Z", "salary": {"currency": null, "max": null, "min": null, "period": "monthly", "term": null}, "salary_visible": false, "title_keywords": ["senior digital marketing executive"], "responsibilities": ["graphics", "social media", "social media platforms", "social media content", "plan"], "requirements": {"degrees": ["degree"], "majors": ["related disciplines", "marketing"], "languages": ["cantonese", "english"], "language_level": ["fluency"], "hard_skills": ["plus", "ai", "e-commerce", "problem solving skills", "photoshop"], "soft_skills": ["detail-minded", "communication skills", "self-motivated", "active", "passion for", "teamwork", "communication", "problem solving skills", "creative", "interpersonal"], "languages_combined": [{"language": "cantonese", "language_level": ["fluency"]}, {"language": "english", "language_level": ["fluency"]}]}, "experience_required": {"duration": ["1+ years"], "field": ["social media", "advertising", "digital marketing", "e-commerce"]}}, {"job_id": "100003009056262", "location_code": "hk", "company": "Asia Top Loyalty Limited", "job_title": "Digital Marketing & Social Media Executive", "description": "You will be responsible for:\n\nAssist line manager to set digital and eCME platform to help drive diseases medical education and business grows. Work on the action plans to achieve goals on business.\nWork closely with multi-departments to plan & execute digital transformation projects to reach business goals.\nAlign and execute social media plans from planning to execution, in compliant with brand communication goals and guidelines.\nPlan and execute all digital marketing, including SEO/SEM, display advertising, display remarketing and paid media to increase top of funnel lead creation\nResponsible for ATL/ BTL campaign communication strategy design and landing\nSource, identify and build sustainable partnership with social / digital platforms, KOL, associations and brand advocates in a holistic digital marketing management.\nActively track, measure the effectiveness of digital media efficiency, monitor investment ROI towards paid social clients, and take learning for future plan optimization.\nRegularly monitor social media trends, market insights, explore new digital media platform and tools, and competitor information acquirement.\nExecute branding marketing plan and drive brand growth for assigned brands\nSupport on the development of portfolio budgets, brand plans and manage the spending\nImplement the brand building activities. Maintain brand standards with clear brand positioning\nBuilds collaborative relationships with internal stakeholders & external stakeholders to reach digital marketing strategic goals.\n\n\u00a0You should have:\n\nBS/MS degree in marketing or a healthcare science.\nFamiliar or with high interest in digital marketing, understand the love of internet and mobile internet, and have a certain understanding of brand positioning and marketing.\nHave good planning ability, communication and coordination ability, excellent execution ability, strong sense of responsibility and team spirit.\nSelf-motivated, passionate with the ability to work independently and as part of a team\nClose alignments with business analysts and business stakeholder for maximizing content for customers\nKPI-related mindset with excellent transparent value-driven and sustainable processes\nData analytics platforms and good understanding of technical infrastructures in general.\nGood communication skill both English and Mandarin.\nPreferable with at least one year of digital marketing experience of healthcare products\u00a0\u00a0\n\nAll applications received will be used exclusively for recruitment purposes only. Applicants who are not contacted within 8 weeks should consider their application unsuccessful for the position advertised. Data supplied by applicants will be kept for 6 months", "employment_types": ["Full Time"], "selling_points": ["Manage and Operate Social Media Marketing", "Work with our Young, Energetic and Friendly Team!", "Fresh Gradute also welcome"], "locations": ["Kwun Tong"], "categories": ["Marketing / Public Relations", "Digital Marketing"], "post_time": "2022-01-18T03:44:41Z", "salary": {"currency": null, "max": null, "min": null, "period": "monthly", "term": null}, "salary_visible": false, "title_keywords": ["digital marketing", "social media executive"], "responsibilities": ["business goals", "data", "design", "communication", "maintain", "plan", "plans", "advertising", "monitor", "bs", "marketing plan", "social media", "management", "seo", "digital marketing", "budgets", "guidelines", "recruitment", "sem", "coordination", "planning"], "requirements": {"degrees": ["degree"], "majors": ["science", "marketing"], "languages": ["english", "mandarin"], "language_level": ["good"], "hard_skills": ["mobile", "seo", "sem", "data analytics"], "soft_skills": ["passionate", "self-motivated", "team spirit", "work independently", "responsible", "sense of responsibility", "communication skill", "collaborative", "communication", "clear", "learning", "coordination", "driven"], "languages_combined": [{"language": "english", "language_level": ["good"]}, {"language": "mandarin", "language_level": ["good"]}]}, "experience_required": {"duration": ["at least one year"], "field": ["healthcare", "digital marketing"]}}, {"job_id": "100003009054915", "location_code": "hk", "company": "DCH Auriga (Hong Kong) Limited", "job_title": "(Associate) Digital Marketing Manager", "description": "Responsibilities:\n\nDevelop and execute digital campaign, perform SEM / SEO and related social media marketing campaigns\nMonitor online advertisement performance on different social media channels\nAssist to develop creative themes and write ups for both online and offline promotions\u00a0\nProvide detailed ROI analysis of digital marketing programmes\n\nRequirements:\n\nDiploma or above holder in Marketing or related disciplines\n1 year relevant working experience is preferred; fresh graduates will also be considered\nGood command of both written and spoken Chinese and English\nExcellent communication, interpersonal and presentation skills to work with various internal and external stakeholders\nWilling to go extra miles to deliver high quality projects\nAbility to work under pressure and to meet deadlines and tackle multiple tasks at one time\nExperience in digital marketing channels including Facebook, Instagram and Google Adwords is preferred\nGraphic design and video production knowledge is a plus\nImmediately available\u00a0is highly preferred.", "employment_types": ["Full Time"], "selling_points": [], "locations": ["Kwai Fong"], "categories": ["Marketing / Public Relations", "Marketing - Brand / Product Management", "Marketing - Marketing Communication", "Digital Marketing"], "post_time": "2022-01-17T13:49:21Z", "salary": {"currency": null, "max": null, "min": null, "period": "monthly", "term": null}, "salary_visible": false, "title_keywords": ["digital marketing manager", "associate"], "responsibilities": ["social media", "seo", "analysis", "monitor", "develop", "digital marketing", "marketing campaigns", "sem"], "requirements": {"degrees": ["diploma or above"], "majors": ["related disciplines", "marketing"], "languages": ["english", "chinese"], "language_level": ["good command"], "hard_skills": ["facebook", "plus", "go", "adwords"], "soft_skills": ["multiple tasks", "communication", "presentation skills", "meet deadlines", "interpersonal", "work under pressure"], "languages_combined": [{"language": "english", "language_level": ["good command"]}, {"language": "chinese", "language_level": ["good command"]}]}, "experience_required": {"duration": ["1 year"], "field": ["digital marketing", "relevant working experience"]}}, {"job_id": "100003009055196", "location_code": "hk", "company": "NTK Academic Group Limited", "job_title": "Marketing Executive", "description": "Responsibilities:\n\nAssist in supporting and managing the day to day operations of a website / e-commerce business, include CMS, content, SEO, online shop, and customer engagement / support\nSupport marketing cloud operation including customer journey building, automation, email and sms preparation and customer engagement / support\nAssist in planning and implementation of marketing campaigns and promotion activities including but not limited to social media, blogs, KOLs, PR, media\nSupport in data and analytical tasks to run reports, create insights, and optimize marketing campaigns\nSupport in preparing, updating marketing materials (content/visuals), maintain, and drive brand awareness via online and offline marketing\nSupport event planning and operations, including but not limited to material sourcing, vendor coordination, logistics, rsvp\nWork closely with internal and external parties to facilitate smooth implementation and operation of marketing strategies on digital, traditional marketing and event coordination\nHandle other ad hoc projects assigned\n\nRequirements:\n\nDegree holder or above in Communication, Language, Literature, Marketing, Business or related disciplines\n1 - 3 years\u2019 experience in marketing or digital technology, preferable gained in managing external agencies / vendors / recent grads with solid intern experience are welcome\nHands-on experience in online and offline marketing and e-commerce\nWell-organized with ability to prioritize and multi-task\nSelf-motivated, result-oriented and attentive to details\nGood project management, interpersonal skills and communication skills\nGood command of both written and spoken English and Chinese\n\nSalary and benefits will be commensurate with qualifications and experience.\u00a0 Interested parties, please send a full resume with present and expected salary, and date available to The Human Resources Department, 32/F., Great Eagle Centre, 23 Harbour Road, Wan chai, Hong Kong or e-mail to us.\u00a0(Please quote the reference no. on the envelope and the covering letter.)\n\nTo know more about us, please visit our website at http://www.greateagle.com.hk.\n\nWe are an equal opportunity employer and welcome applications from all qualified candidates.\n\nPersonal data collected will be treated in strict confidence and used only for recruitment-related purpose. Applicants who have not heard from us within four weeks may consider their applications unsuccessful. All personal data will be destroyed after 12 months.", "employment_types": ["Full Time", "Permanent"], "selling_points": ["Social Media Management with Creative Mindset", "Marketing and Campaign Analysis (SEO / SEM)", "Nurturing Culture with Great Career Opportunities"], "locations": ["Causeway Bay"], "categories": ["Marketing / Public Relations", "Marketing - General / Support", "Digital Marketing"], "post_time": "2022-01-18T01:44:39Z", "salary": {"currency": null, "max": null, "min": null, "period": "monthly", "term": null}, "salary_visible": false, "title_keywords": ["marketing executive"], "responsibilities": ["social media", "seo", "day to day operations", "marketing strategies", "data", "operations", "internal and external parties", "implementation", "website", "maintain", "reports", "logistics", "marketing campaigns", "coordination", "marketing materials", "ad hoc projects", "planning"], "requirements": {"degrees": ["recent grads", "degree holder"], "majors": ["business", "related disciplines", "marketing"], "languages": ["english", "chinese"], "language_level": ["good command"], "hard_skills": ["project management", "e-commerce"], "soft_skills": ["communication skills", "self-motivated", "multi-task", "attentive to details", "well-organized", "prioritize", "communication", "project management", "hands-on", "interpersonal skills", "result-oriented"], "languages_combined": [{"language": "english", "language_level": ["good command"]}, {"language": "chinese", "language_level": ["good command"]}]}, "experience_required": {"duration": ["1 - 3 years"], "field": ["digital", "marketing", "e-commerce"]}}, {"job_id": "100003009054625", "location_code": "hk", "company": "I.T Apparels Limited", "job_title": "Senior Marketing Officer (REF : JDB-IT-SMO)", "description": "Publicis Groupe:\nMarketing in today\u2019s world is fast evolving.\u00a0Publicis Groupe\u00a0leads the change by offering a one-stop solution, allowing our clients' access to the expertise that sits within our 15-agency network on a daily basis. This is an exciting time to join our agency where you can learn from the best from a broad range of disciplines: advertising, digital, CRM, shopper marketing, PR/events, and social, etc. to empower you to have an intelligent conversation with our clients. At the same time, you are given the opportunity to shine by offering something unique to the team.\n\nJob Description:\nWe are looking for an independent and passionate professional to join our team in Hong Kong. This person will serve as our Associate, joining a group of creative and devoted communications specialists, working on multiple accounts to deliver impactful results to a diverse range of clients.\n\n\"Power of One\" - Part of the 15-agency network under the fully integrated Publicis Groupe, bringing together the best talents from the group\nExcellent office environment - spacious, stylish office with an outdoor terrace for some fresh air\nGood company and team culture\n\nResponsibilities\u00a0\nThe position will equip the right candidate with all of the skills he/she requires to become a well-rounded and experienced digital marketing & communications professional. Of paramount importance, you will be expected to understand the business challenges and environments of the clients you serve. Idea generation, writing, trend analysis, social media operation and third-party coordination will make up a sizeable portion of your daily tasks - as will creating compelling presentations for existing and potential clients. You will manage media and influencer relations as well as coordinate events for your clients.\n\nRequirements\u00a0\u00a0\u00a0\n\nDegree holder in Marketing, PR, Advertising, Journalism, Communications, English or related discipline\nMinimum 1 to 2 years of PR/social experience, preferably with PR or social media content agencies or in a fast-paced environment.\nExperience in developing content for PR/ social campaigns that created online visibility, curiosity and excitement as well as business results\nSound knowledge of the latest online and digital technologies\u00a0\nStrong command of spoken English, Cantonese and Mandarin is mandatory\nExcellent written English and Traditional Chinese\nResponsible, organised, self-motivated and a team player\nFlawless attention to detail\nCandidates with less experience will be considered as Junior Associate\n\nAll information collected will be solely used for recruitment purposes only.", "employment_types": ["Full Time", "Permanent"], "selling_points": ["Digital marketing campaigns", "SEO/SEM, and online advertising campaigns", "Social media"], "locations": ["Southern Area"], "categories": ["Marketing / Public Relations", "Marketing - Marketing Communication", "Public Relations - General / Support", "Digital Marketing"], "post_time": "2022-01-17T10:17:37Z", "salary": {"currency": null, "max": null, "min": null, "period": "monthly", "term": null}, "salary_visible": false, "title_keywords": ["senior marketing officer"], "responsibilities": ["social media", "analysis", "presentations", "coordinate", "digital marketing", "coordination"], "requirements": {"degrees": ["degree holder"], "majors": ["journalism", "marketing", "communications"], "languages": ["cantonese", "english", "chinese", "mandarin"], "language_level": ["excellent"], "hard_skills": [], "soft_skills": ["self-motivated", "responsible", "fast-paced environment", "attention to detail", "organised", "team player"], "languages_combined": [{"language": "cantonese", "language_level": []}, {"language": "english", "language_level": ["excellent"]}, {"language": "chinese", "language_level": ["excellent"]}, {"language": "mandarin", "language_level": []}]}, "experience_required": {"duration": ["minimum 1 to 2 years"], "field": ["social media", "pr", "business", "developing"]}}, {"job_id": "100003009054784", "location_code": "hk", "company": "MANNING SELVAGE & LEE", "job_title": "Associate, PR & Social Media", "description": "JOB ROLE AND RESPONSIBILITIES:\n\nAssist in developing and implementing the ATL/BTL marketing campaigns and retail promotional activities to drive the Inchcape approved used car sales.\nAssist in update and maintaining the Inchcape Approved Used Car website content and social media page.\nWork closely with digital team to accelerate the number of digital enquiries and conversion to sales.\nPrepare marketing materials including advertising, digital, social media, and retail event logistics support.\nCollect market and competitive used car market news and trends to facilitate the promotional activity planning.\nConsolidate reports and monitor expenses as per budget assigned\nAssist in any ad-hoc projects as assigned.\nSKILLS AND EXPERIENCE REQUIRED:\n\nMinimum 2 years of experience in fields of marketing, digital marketing/e-Commerce, or event management. Automotive industry experience is welcomed but not a must.\nDiploma holder or above will be an advantage\nGood communication skills in both written and spoken English and Chinese.\nCreative thinking and passionate, able to drive things happen fast.\nCompetent in MS Word, Excel, PowerPoint & Chinese Word-Processing\nSelf-motivated and able to work independently and under pressure\nDetail-minded and able to multi-task in a fast paced, dynamic culture\n\nPersonal data provided by applicants will be used for recruitment purpose only and will be destroyed after 3 months.\n\n", "employment_types": ["Full Time", "Permanent"], "selling_points": ["Part of fully integrated Publicis Groupe", "Diverse clientele, market leading brands", "Spacious, stylish office with an outdoor terrace"], "locations": ["Kwun Tong"], "categories": ["Marketing / Public Relations", "Marketing - Marketing Communication", "Public Relations - Copy-writing", "Digital Marketing"], "post_time": "2022-01-17T11:04:17Z", "salary": {"currency": null, "max": null, "min": null, "period": "monthly", "term": null}, "salary_visible": false, "title_keywords": ["associate"], "responsibilities": ["budget", "website", "communication", "personal data", "ad-hoc projects", "advertising", "maintaining", "expenses", "monitor", "developing", "logistics", "reports", "marketing campaigns", "social media", "management", "promotional activities", "digital marketing", "prepare marketing materials", "recruitment", "planning"], "requirements": {"degrees": ["diploma holder"], "majors": [], "languages": ["english", "chinese"], "language_level": ["good"], "hard_skills": ["excel", "chinese word-processing", "e-commerce", "powerpoint", "dynamic", "ms word"], "soft_skills": ["passionate", "communication skills", "self-motivated", "work independently", "under pressure", "detail-minded", "multi-task", "competent", "dynamic", "creative"], "languages_combined": [{"language": "english", "language_level": ["good"]}, {"language": "chinese", "language_level": ["good"]}]}, "experience_required": {"duration": ["minimum 2 years"], "field": ["automotive industry", "management", "e-commerce", "marketing", "digital marketing"]}}, {"job_id": "100003009053688", "location_code": "hk", "company": "freeD Group Limited", "job_title": "Senior Executive, Paid Marketing", "description": "Responsibilities:\n\nCreate quality and engaging social media contents for \u653f\u7b56\u2027\u6b63\u5bdfFacebook, YouTube and Instagram\nContribute creative ideas and conduct interviews for video projects\nCollaborate with videographers/editors in production\nAdministrate social media platforms\nDevelop, implement and evaluate digital marketing strategy\nMonitor the social media trend\n\nRequirements:\n\nDegree holder in Journalism, New media, Digital Marketing, Public Policy or relevant disciplines\nMinimum of 2 years of relevant experience\nStrong interest or knowledge in digital content marketing and public affairs\nRelevant media and digital agency experience is an advantage\nKnowledge of editing software and/or online marketing tools is an advantage\nAnchoring or program hosting experience is an advantage\nSelf-motivated and detail-oriented, able to work under pressure and juggle among tasks\nCandidates with more than 5 years' relevant experience will be considered as Senior Officer\nFresh graduates will be considered as Assistant Officer\n\nInterested parties please send:\n\nFull resume;\nCover letter;\nCopies of academic transcripts (including\u00a0public examination results if applicable);\nPresent and expected salary;\nAvailability\n\nBy clicking 'Apply Now' or by post to: Our Hong Kong Foundation Limited, 19/F, Nan Fung Tower, 88 Connaught Road Central, Hong Kong. Applicants who are not invited to an interview within two months from the date of this advertisement should consider their applications unsuccessful.\u00a0\n\nAll information provided by applicants will be handled with strictest confidence and will be solely used for the purpose of recruitment.", "employment_types": ["Full Time", "Permanent"], "selling_points": [], "locations": ["Tsim Sha Tsui"], "categories": ["Marketing / Public Relations", "Digital Marketing"], "post_time": "2022-01-17T07:23:50Z", "salary": {"currency": null, "max": null, "min": null, "period": "monthly", "term": null}, "salary_visible": false, "title_keywords": ["senior executive"], "responsibilities": ["collaborate with", "social media", "creative ideas", "social media platforms", "quality", "monitor", "develop", "evaluate", "digital marketing", "contents"], "requirements": {"degrees": ["degree holder"], "majors": ["journalism", "digital marketing", "public policy"], "languages": [], "language_level": [], "hard_skills": [], "soft_skills": ["work under pressure", "self-motivated", "detail-oriented"], "languages_combined": []}, "experience_required": {"duration": ["5 years", "minimum of 2 years"], "field": ["agency", "digital", "relevant experience", "media"]}}, {"job_id": "100003009055434", "location_code": "hk", "company": "Our Hong Kong Foundation Limited", "job_title": "Officer / Senior officer (Social Media)", "description": "Responsibilities:\u00a0\u00a0\nResponsible and optimization of overseas advertisement channels such as Google, Facebook and Instagram\nSolid experience with social media including blogs, Instagram, Facebook, etc.\nProvide and execute marketing plans including strategy, budget, goals of the project launches\nManager all-rounded marketing and promotion campaigns covering (both online & offline promotions, e-marketing, social media campaign, website updates and consumer experience enhancement)\nOrganize product seeding among celebrities, KOL, media, influencers\nResearch and monitor the strategies of competitors and adjust project plan\nManage brand positioning and product design, online activities planning and promotion for the platforms\n\nRequirements:\n\nDegree or above in Business, Advertising, Marketing, Communications, E-commerce, Project Management, PR or related discipline;\n3 years or above solid experience in marketing / project management\nGood knowledge or experience in HTML, Search Engine Marketing and SEO is an advantage\nKnowledge in\u00a0Google Analytics/ Google Ads/ Facebook Ads Manager tools is a must - Proficient in spoken and written English and Chinese\nEnergetic, self-motivated, detail-oriented, passionate,\u00a0results-oriented and able to work under pressure\nGreat communication and management skills\n\nInterested Candidates,\u00a0please send your\u00a0full resume with your recent photo,\u00a0current & expected salary\u00a0by e-mail to\u00a0hr @moderndentallab.com.\nAll personal data collected will be used for recruitment and employment related purpose only.", "employment_types": ["Full Time", "Permanent"], "selling_points": ["Create quality & engaging content for social media", "Familiar with social media platforms", "Growing platform with development opportunities"], "locations": ["Central & Western Area"], "categories": ["Media & Advertising", "Creative / Design", "Marketing / Public Relations", "Marketing - Marketing Communication", "Digital Marketing"], "post_time": "2022-01-18T02:34:47Z", "salary": {"currency": null, "max": null, "min": null, "period": "monthly", "term": null}, "salary_visible": false, "title_keywords": ["officer", "senior officer"], "responsibilities": ["social media", "marketing plans", "budget", "monitor", "website", "project plan", "promotion campaigns", "product design", "facebook", "planning"], "requirements": {"degrees": ["degree or above"], "majors": ["e-commerce", "project management", "business", "marketing", "communications"], "languages": ["english", "chinese"], "language_level": ["proficient"], "hard_skills": ["google analytics", "seo", "e-commerce", "html", "project management", "facebook"], "soft_skills": ["passionate", "self-motivated", "detail-oriented", "communication", "project management", "energetic", "work under pressure"], "languages_combined": [{"language": "english", "language_level": ["proficient"]}, {"language": "chinese", "language_level": ["proficient"]}]}, "experience_required": {"duration": ["3 years"], "field": ["project management", "marketing"]}}, {"job_id": "100003009055168", "location_code": "hk", "company": "Zenit (Hong Kong) Company Limited", "job_title": "Branding and Marketing Executive / Senior Marketing Executive", "description": "Responsibilities:\n\nManage and create content for various social media platforms (Facebook, Instagram, YouTube), including copywriting, image and video editing;\nMonitor, analyze, and provide insight on social media platform activities;\nHandle various ad hoc duties such as online marketing, develop and maintain social network, etc.\nWork closely with marketing team to develop and execute image visual for advertising materials.\nCooperate with\u00a0team\u00a0members and assisting to keep the office operation.\nKeep up with trends that can be adapted to our online platforms\n\nRequirements :\n\nHigher Diploma or Degree\u00a0holder, preferably in multimedia production, design, multi-media, communication\u00a0or related disciplines.\nA minimum of 1-2 years\u2019 hands-on experience in multimedia and video production, or relevant working experience.\nProficient in photo and video editing software (Photoshop, Premiere Pro) is highly preferred, coupled with basic Illustrator and After Effect skills would be a plus\nOutgoing, creative, well-organized, detail-minded with a strong sense of responsibility, independent and able to work under pressure.\nExperience in web-based and mobile learning courseware development is an advantage.\nDesire to learn new multimedia technology.\nAble to work efficiently and effectively, both independently and as a team member.\nGood command of Chinese, English and Putonghua.", "employment_types": ["Full Time", "Permanent"], "selling_points": ["5 days work", "Double Pay", "Performance Bonus"], "locations": ["Tsuen Wan Area"], "categories": ["Marketing / Public Relations", "Marketing - Brand / Product Management", "Marketing - Marketing Communication", "Digital Marketing"], "post_time": "2022-01-18T01:36:30Z", "salary": {"currency": null, "max": null, "min": null, "period": "monthly", "term": null}, "salary_visible": false, "title_keywords": ["senior marketing executive", "marketing executive"], "responsibilities": ["ad hoc duties", "social media", "advertising", "social media platforms", "monitor", "develop", "video editing", "maintain", "visual", "facebook", "cooperate with"], "requirements": {"degrees": ["diploma", "degree holder"], "majors": ["related disciplines", "design"], "languages": ["putonghua", "english", "chinese"], "language_level": ["good command"], "hard_skills": ["plus", "basic", "web", "illustrator", "video editing", "mobile", "premiere pro", "multimedia", "after effect", "photoshop"], "soft_skills": ["outgoing", "detail-minded", "independently", "independent", "sense of responsibility", "well-organized", "team member", "communication", "hands-on", "learning", "creative", "work under pressure"], "languages_combined": [{"language": "putonghua", "language_level": ["good command"]}, {"language": "english", "language_level": ["good command"]}, {"language": "chinese", "language_level": ["good command"]}]}, "experience_required": {"duration": ["minimum of 1-2 years"], "field": ["video production", "development", "relevant working experience"]}}, {"job_id": "100003009055068", "location_code": "hk", "company": "Oxford University Press (China) Ltd", "job_title": "Marketing Assistant (one-year contract)", "description": "Responsibilities:\u00a0\n\n\nCreate engaging content for different social media platforms and marketing campaigns\nClosely monitor online campaigns and formulate new e-marketing initiatives to generate sales and brand awareness\nMonitor and evaluate campaign performance, assess digital campaign trends, prepare, and handle reporting/data analysis & identify growth opportunities\nHelp grow social media account followers (including Facebook, Instagram, Youtube, Pinterest etc.)\nTranslation and copywriting works for English - Chinese (Traditional)\nOther ad-hoc projects as assigned by management\n\n\u00a0Requirements:\n\nDegree in Marketing, Communication, Journalism, Information Systems or business related discipline\nAbout 2 years\u2019 experience in (digital) marketing\nGood command of Chinese and English copywriting\nGood knowledge of SEO is highly preferred\nExperience with social media, Google Adwords, Google Analytics, email campaigns, facebook Ad Manager is a plus but not essential\nHands-on experience in web CMS is an advantage\nHands-on experience in Illustrator, Photoshop & other graphic and interactive design tools\nKnowledge in photography and video shooting and editing is a plus but not essential\nEnergetic, pro-active, self-motivated and able to work independently\nExcellent communication and interpersonal skills\n\nWe offer attractive remuneration packages to successful candidates:\n\nCompetitive monthly salary commensurate with experience;\nHealth Insurances (Both Medical & Dental);\nFive-day work;\nPaid vacation days;\nIn-house training;\nUnique opportunity for career and self-development.\nIf you are interested in this challenging role, we look forward to discussing this opportunity with you further.\u00a0Interested parties, please submit your application by clicking the apply button.\n\n\nPersonal data collected will be used for recruitment purposes only.\n\n\n\n", "employment_types": ["Full Time", "Contract"], "selling_points": ["Develop school campaigns for teachers", "Assist in below-the-line marketing events/webinar", "Fresh graduates are welcome"], "locations": ["Kowloon Bay"], "categories": ["Marketing / Public Relations", "Public Relations - Event Management", "Public Relations - General / Support", "Digital Marketing"], "post_time": "2022-01-18T01:08:57Z", "salary": {"currency": null, "max": null, "min": null, "period": "monthly", "term": null}, "salary_visible": false, "title_keywords": ["marketing assistant"], "responsibilities": ["reporting", "social media", "management", "social media platforms", "monitor", "evaluate", "data analysis", "marketing campaigns", "facebook", "ad-hoc projects"], "requirements": {"degrees": ["degree"], "majors": ["journalism", "marketing", "business"], "languages": ["english", "chinese"], "language_level": ["good command"], "hard_skills": ["google analytics", "plus", "seo", "web", "adwords", "illustrator", "facebook", "photoshop"], "soft_skills": ["self-motivated", "work independently", "communication", "hands-on", "communication and interpersonal skills", "pro-active", "energetic"], "languages_combined": [{"language": "english", "language_level": ["good command"]}, {"language": "chinese", "language_level": ["good command"]}]}, "experience_required": {"duration": ["2 years"], "field": ["social media", "design", "graphic", "marketing", "digital"]}}, {"job_id": "100003009055135", "location_code": "hk", "company": "Ocean Park Corporation", "job_title": "Contract Social Media Content Creator (Marketing Department)", "description": "Manage marketing activities of a number of brands we currently represent\nLocate collaboration partners to drive create content and drive brand awareness\nFrequent contact with global photography media to build global brand awareness\nPlan and coordinate both online and offline marketing activities with distributors to drive sales\nWork closely with sales team to formulate plans to drive business across distributors\nCommunication with global distributors to understand market changes\nManage social media and provide end customer service and support.\nNurture the user community and identify collaboration brands and parties.\nKeep close track of industry news and competitor movements\nAttend local and overseas events when necessary", "employment_types": ["Temporary", "Contract"], "selling_points": ["Social Media Content Creator", "Marketing", "Digital Marketing"], "locations": ["Aberdeen"], "categories": ["Media & Advertising", "Editorial / Journalism", "Marketing / Public Relations", "Marketing - General / Support", "Digital Marketing"], "post_time": "2022-01-18T01:22:33Z", "salary": {"currency": null, "max": null, "min": null, "period": "monthly", "term": null}, "salary_visible": false, "title_keywords": [], "responsibilities": ["drive sales", "social media", "plan and coordinate", "communication", "customer service", "sales team", "contact", "plans"], "requirements": {"degrees": [], "majors": [], "languages": [], "language_level": [], "hard_skills": [], "soft_skills": ["communication", "customer service"], "languages_combined": []}, "experience_required": {"duration": [], "field": []}}, {"job_id": "100003009053451", "location_code": "hk", "company": "Madcradle Online Limited", "job_title": "(Senior) Account Executive", "description": "Job Responsibilities:\nExecutive and plan both online and offline events for teachers and students including but not limited to event logistics support and preparation;\nPrepare marketing copy for printed and digital campaigns;\nUtilize marketing tools to carry out strategic objectives;\nTrack, analyze and report performance on marketing campaigns;\nProvide clerical support to the Marketing team.\nJob Requirements:\n\nUniversity degree in Business, Marketing, Multimedia or related discipline;\n1-2 years of experience in marketing;\nGood command of both Chinese and English;\nKnowledge of MS Word, Excel & PowerPoint;\nKnowledge of graphics design is a plus;\nGood communications and interpersonal skills;\nGood coordination and planning skills;\nProactive, well organized, able to work independently and a good team player;\nOpen mind to learn new skills;\nFresh graduates are also welcome.\nWe are committed to supporting diversity in our workforce, and ensuring an inclusive environment where all employees can thrive. We seek to employ a workforce representative of the markets that we serve, and encourage applications from people of all ethnic, cultural and social backgrounds.\u00a0\u00a0\nApplications, including curriculum vitae, expected salary and work schedule, should be sent by clicking \u201cAPPLY NOW\u201d.\nPersonal data will be used for recruitment purposes only.\u00a0", "employment_types": ["Full Time", "Permanent"], "selling_points": ["Develop long-term relationship with brands", "Plan & execute business development plans", "Provide strategic marketing & advertising advice"], "locations": ["Kwun Tong"], "categories": ["Media & Advertising", "Account Servicing", "Strategic Planning", "Marketing / Public Relations", "Digital Marketing"], "post_time": "2022-01-17T06:59:54Z", "salary": {"currency": null, "max": null, "min": null, "period": "monthly", "term": null}, "salary_visible": false, "title_keywords": ["account executive"], "responsibilities": ["provide clerical support", "logistics", "digital campaigns", "marketing campaigns", "plan", "report"], "requirements": {"degrees": ["university degree"], "majors": ["business", "marketing"], "languages": ["english", "chinese"], "language_level": ["good command"], "hard_skills": ["graphics", "excel", "plus", "powerpoint", "multimedia", "ms word"], "soft_skills": ["planning skills", "work independently", "good team player", "well organized", "committed", "interpersonal skills", "coordination", "proactive"], "languages_combined": [{"language": "english", "language_level": ["good command"]}, {"language": "chinese", "language_level": ["good command"]}]}, "experience_required": {"duration": ["1-2 years"], "field": ["marketing"]}}, {"job_id": "100003009056428", "location_code": "hk", "company": "Digioo Limited", "job_title": "Digital Trainee / Account Executive", "description": "Job Descriptions\nResponsibilities\n\nServicing a portfolio of clients targeting Hong Kong, Greater China and global markets under the guidance of Account Managers\nManaging holistic digital campaigns covering SEM, SEO, Social Media Marketing, Display Advertising, Video Advertising and more to achieve performance goals\nEnsuring smooth campaign delivery and optimizing results based on data analytics\nWorking closely with Sales Team in campaign delivery and revenue growth\nThe Successful Applicant(s)\n\nResult-oriented challenge taker\nQuick learner - must promptly pick up various advertising platforms and our world-class AI system for campaign optimization and reporting\nIndependent and able to perform well under pressure\nDetail-oriented and organized\nPossessing strategic mindset and strong data analytical skills\nPossessing strong communication and interpersonal skills for building client relationships\nGood command of Chinese, English and Putonghua\nDigital agency background / experience in digital marketing preferred but not a must\nCandidates who are certified with Google Ads are strongly preferred", "employment_types": ["Full Time"], "selling_points": ["Managing holistic digital campaigns", "Ensuring campaign delivery & optimizing results", "Digital agency background / experience"], "locations": ["Mong Kok"], "categories": ["Marketing / Public Relations", "Marketing - Brand / Product Management", "Marketing - Market Research", "Digital Marketing"], "post_time": "2022-01-18T04:16:49Z", "salary": {"currency": null, "max": null, "min": null, "period": "monthly", "term": null}, "salary_visible": false, "title_keywords": ["account executive", "trainee"], "responsibilities": ["guidance", "social media", "reporting", "seo", "advertising", "data", "communication", "sales team", "revenue growth", "sem", "digital campaigns", "digital marketing"], "requirements": {"degrees": [], "majors": [], "languages": ["putonghua", "english", "chinese"], "language_level": ["good command"], "hard_skills": ["seo", "ai", "data analytics", "analytical skills", "sem"], "soft_skills": ["organized", "independent", "quick learner", "detail-oriented", "analytical skills", "communication and interpersonal skills", "smooth", "result-oriented", "perform well under pressure", "world-class"], "languages_combined": [{"language": "putonghua", "language_level": ["good command"]}, {"language": "english", "language_level": ["good command"]}, {"language": "chinese", "language_level": ["good command"]}]}, "experience_required": {"duration": [], "field": ["agency", "digital", "digital marketing"]}}, {"job_id": "100003009054808", "location_code": "hk", "company": "Billion Joy Media HK Limited", "job_title": "Senior Digital and Campaign Marketing Executive", "description": "Responsibilities:\n\nResponsible for all online activities including user acquisition, conversion and retention to deliver continuous optimization and growth\nCreate, manage, and analyze Search Engine Marketing and social media across multiple platforms to achieve user acquisition and conversion goals\nCreation & delivery of all paid acquisition campaigns on social media platforms\nTake a data-driven approach to optimism marketing performance\nAnalyze market landscape and consumer insights to identify business opportunity\nHandle and present the performance and ROI of the above digital campaigns\nLiaise with internal and external parties to provide marketing administrative supports\nAny ad-hoc duties as assigned\n\nRequirements:\n\nDegree holder or above in Marketing, Digital Marketing, New Media Communication, Journalism or related disciplines\nMinimum 3 years marketing experience (less experience will be considered for Executive role)\nHands-on experience in Facebook Ad Manager, SEO, SEM, Google Analytics, Adwords planning and content development is a must\nFamiliar with automated email marketing tools preferable\nPossess Google Ads Search Certification, and Ads Display Certification preferable\nProficiency in design software such as Photoshop, AI is a must, video editing is a plus\nAble to handle multi-tasks with strong problem-solving skills with a can-do attitude\nSee themselves as project lead with strong ability of execution\nExcellent communication and interpersonal skills\nExcellent command of Chinese and English writing\n\nInterested parties are invited to send their applications with full resume stating availability date, present and expected salary to us.\n\nPersonal data provided by job applicants will be used strictly in accordance with our personal data policy and for recruitment purposes only.", "employment_types": ["Full Time", "Permanent"], "selling_points": [], "locations": ["Quarry Bay"], "categories": ["Marketing / Public Relations", "Public Relations - Event Management", "Digital Marketing"], "post_time": "2022-01-17T11:12:35Z", "salary": {"currency": null, "max": null, "min": null, "period": "monthly", "term": null}, "salary_visible": false, "title_keywords": ["marketing executive"], "responsibilities": ["social media", "consumer insights", "data", "social media platforms", "internal and external parties", "digital campaigns", "ad-hoc duties", "liaise with"], "requirements": {"degrees": ["degree holder"], "majors": ["journalism", "related disciplines", "marketing", "digital marketing"], "languages": ["english", "chinese"], "language_level": ["excellent"], "hard_skills": ["google analytics", "plus", "seo", "ai", "problem-solving skills", "adwords", "video editing", "sem", "facebook", "photoshop"], "soft_skills": ["multi-tasks", "can-do attitude", "communication", "hands-on", "communication and interpersonal skills", "problem-solving skills"], "languages_combined": [{"language": "english", "language_level": ["excellent"]}, {"language": "chinese", "language_level": ["excellent"]}]}, "experience_required": {"duration": ["minimum 3 years"], "field": ["marketing", "content development", "planning"]}}, {"job_id": "100003009052072", "location_code": "hk", "company": "Strawberry Cosmetics (Services) Limited", "job_title": "Digital Marketing Executive \u2013 Social Media", "description": "Do you think outside the box? Are you a dynamic storyteller who loves beauty products and is\u00a0passionate about digital marketing? You may be the person we are looking for!\n\nThe successful candidate will be responsible for managing the company\u2019s media platforms such as, Facebook, Instagram, Tiktok, Youtube and Naver. You will be able to learn how to use intelligence tool like Hootsuite and OneSignal to manage the platforms better.\n\n\u00a0Roles and responsibilities:\n\nManage campaigns across all social media platforms\u00a0to achieve designated business goals\nResponsible for content\u00a0creation and storytelling on social media channels\u00a0to produce creative, well written, rich and engaging social media content to maximize ROI and increase brand awareness\nDay-to-day tasks includes performance report consolidation, postings on Social Media and app push scheduling\nManage partnership with KOLs, including incentive offering, posting arrangement and payment settlement\n\nRequirements:\n\nExperience in media marketing with 1-2 years relevant experiences\nFresh graduates are also welcome\nBachelor\u2019s degree in communications, marketing or related field\nUnderstanding of APAC markets such as Hong Kong, Australia, New Zealand, Singapore is preferred\nExcellent written and spoken English and\u00a0Traditional Chinese, particularly in creating content for Asian markets\nA passion in digital marketing and beauty e-commerce\nHigh project management skills with attention to detail and ability to multi-task\nA good team player", "employment_types": ["Full Time", "Permanent"], "selling_points": [], "locations": ["Shau Kei Wan"], "categories": ["Marketing / Public Relations", "Marketing - Direct Marketing", "Marketing - Marketing Communication", "Digital Marketing"], "post_time": "2022-01-17T02:01:58Z", "salary": {"currency": null, "max": null, "min": null, "period": "monthly", "term": null}, "salary_visible": false, "title_keywords": ["digital marketing executive"], "responsibilities": ["social media", "business goals", "social media platforms", "scheduling", "payment", "social media content", "maximize roi", "report"], "requirements": {"degrees": ["degree", "bachelor"], "majors": ["marketing", "communications"], "languages": ["english", "chinese"], "language_level": ["excellent"], "hard_skills": ["project management", "e-commerce"], "soft_skills": ["good team player", "multi-task", "passion in", "project management skills", "attention to detail"], "languages_combined": [{"language": "english", "language_level": ["excellent"]}, {"language": "chinese", "language_level": ["excellent"]}]}, "experience_required": {"duration": ["1-2 years"], "field": ["marketing", "media"]}}, {"job_id": "100003009056376", "location_code": "hk", "company": "Modern Dental Laboratory Company Limited", "job_title": "Project Executive", "description": "Responsibilities:\u00a0\u00a0\nResponsible and optimization of overseas advertisement channels such as Google, Facebook and Instagram\nSolid experience with social media including blogs, Instagram, Facebook, etc.\nProvide and execute marketing plans including strategy, budget, goals of the project launches\nManager all-rounded marketing and promotion campaigns covering (both online & offline promotions, e-marketing, social media campaign, website updates and consumer experience enhancement)\nOrganize product seeding among celebrities, KOL, media, influencers\nResearch and monitor the strategies of competitors and adjust project plan\nManage brand positioning and product design, online activities planning and promotion for the platforms\n\nRequirements:\n\nDegree or above in Business, Advertising, Marketing, Communications, E-commerce, Project Management, PR or related discipline;\n3 years or above solid experience in marketing / project management\nGood knowledge or experience in HTML, Search Engine Marketing and SEO is an advantage\nKnowledge in\u00a0Google Analytics/ Google Ads/ Facebook Ads Manager tools is a must - Proficient in spoken and written English and Chinese\nEnergetic, self-motivated, detail-oriented, passionate,\u00a0results-oriented and able to work under pressure\nGreat communication and management skills\n\nInterested Candidates,\u00a0please send your\u00a0full resume with your recent photo,\u00a0current & expected salary\u00a0by e-mail to\u00a0hr @moderndentallab.com.\nAll personal data collected will be used for recruitment and employment related purpose only.", "employment_types": ["Full Time", "Permanent"], "selling_points": ["Optimization of overseas advertisement channels", "Enjoy Social Media & English copywriting", "Genuine interest in SEO / Digital Marketing"], "locations": ["Lai Chi Kok"], "categories": ["Marketing / Public Relations", "Marketing - General / Support", "Public Relations - Copy-writing", "Digital Marketing"], "post_time": "2022-01-18T04:06:25Z", "salary": {"currency": null, "max": null, "min": null, "period": "monthly", "term": null}, "salary_visible": false, "title_keywords": ["project executive"], "responsibilities": ["social media", "marketing plans", "budget", "monitor", "website", "project plan", "promotion campaigns", "product design", "facebook", "planning"], "requirements": {"degrees": ["degree or above"], "majors": ["e-commerce", "project management", "business", "marketing", "communications"], "languages": ["english", "chinese"], "language_level": ["proficient"], "hard_skills": ["google analytics", "seo", "e-commerce", "html", "project management", "facebook"], "soft_skills": ["passionate", "self-motivated", "detail-oriented", "communication", "project management", "energetic", "work under pressure"], "languages_combined": [{"language": "english", "language_level": ["proficient"]}, {"language": "chinese", "language_level": ["proficient"]}]}, "experience_required": {"duration": ["3 years"], "field": ["project management", "marketing"]}}, {"job_id": "100003009056393", "location_code": "hk", "company": "Hong Kong Live Feed Limited", "job_title": "Digital Content Creator", "description": "Responsibilities:\n\nManage and create content for various social media platforms (Facebook, Instagram, YouTube), including copywriting, image and video editing;\nMonitor, analyze, and provide insight on social media platform activities;\nHandle various ad hoc duties such as online marketing, develop and maintain social network, etc.\nWork closely with marketing team to develop and execute image visual for advertising materials.\nCooperate with\u00a0team\u00a0members and assisting to keep the office operation.\nKeep up with trends that can be adapted to our online platforms\n\nRequirements :\n\nHigher Diploma or Degree\u00a0holder, preferably in multimedia production, design, multi-media, communication\u00a0or related disciplines.\nA minimum of 1-2 years\u2019 hands-on experience in multimedia and video production, or relevant working experience.\nProficient in photo and video editing software (Photoshop, Premiere Pro) is highly preferred, coupled with basic Illustrator and After Effect skills would be a plus\nOutgoing, creative, well-organized, detail-minded with a strong sense of responsibility, independent and able to work under pressure.\nExperience in web-based and mobile learning courseware development is an advantage.\nDesire to learn new multimedia technology.\nAble to work efficiently and effectively, both independently and as a team member.\nGood command of Chinese, English and Putonghua.", "employment_types": ["Full Time"], "selling_points": [], "locations": ["Shatin Area"], "categories": ["Marketing / Public Relations", "Public Relations - Copy-writing", "Media & Advertising", "Photography / Video", "Digital Marketing"], "post_time": "2022-01-18T04:08:46Z", "salary": {"currency": null, "max": null, "min": null, "period": "monthly", "term": null}, "salary_visible": false, "title_keywords": [], "responsibilities": ["ad hoc duties", "social media", "advertising", "social media platforms", "monitor", "develop", "video editing", "maintain", "visual", "facebook", "cooperate with"], "requirements": {"degrees": ["diploma", "degree holder"], "majors": ["related disciplines", "design"], "languages": ["putonghua", "english", "chinese"], "language_level": ["good command"], "hard_skills": ["plus", "basic", "web", "illustrator", "video editing", "mobile", "premiere pro", "multimedia", "after effect", "photoshop"], "soft_skills": ["outgoing", "detail-minded", "independently", "independent", "sense of responsibility", "well-organized", "team member", "communication", "hands-on", "learning", "creative", "work under pressure"], "languages_combined": [{"language": "putonghua", "language_level": ["good command"]}, {"language": "english", "language_level": ["good command"]}, {"language": "chinese", "language_level": ["good command"]}]}, "experience_required": {"duration": ["minimum of 1-2 years"], "field": ["video production", "development", "relevant working experience"]}}, {"job_id": "100003009055357", "location_code": "hk", "company": "S&S Hospitality Limited", "job_title": "Social Media Content Creator", "description": "We are seeking applicants who are enthusiastic, experienced in content creation for the group\u2019s restaurants and bars.\n\nRESPONSIBILITIES\n\n\nMust be self-motivated and able to work independently\nPrepare copy and content calendar for social media posts\nProduce edited photography and short videos\nSet up accounts on social media platforms for new outlets\nResearch latest digital innovations to introduce to company activities\nPresent social media strategic plan and influencer campaign to expand digital reach\nLiaise with marketing team to align brand strategy\nProduce professional social media collaterals with design team\nAnalyze and compile monthly reports on growth tracking, promotion results and guests\u2019 reviews\nManage daily engagement with audiences, respond and react to enquiries and feedback\u00a0\n\nREQUIREMENTS\n\nStrong interpersonal and communication skills\nAble to deliver high quality video, photography\nPost production and editing of video and photography\nExperience in designing brand content for web, desktop and mobile\nCreative thinker, articulate and persuasive\nGood, creative and confident writer, high attention to detail in correct spelling and punctuation\nProficient in Adobe Photoshop, Illustrator, After Effects and Premier Pro\nDegree holder (or similar) in Videography, photography or equivalent experience in the creative or graphic design field\nMinimum 2 years\u2019 experience in managing social media accounts\nAbility to multitask several creative projects\nExcellent creative skills and a great eye for detail\nFluent in English, written and spoken, is essential, Cantonese and Mandarin is an advantage\nCreative, enthusiastic, proactive approach to all social media activities\n\nInterested applicants, please forward your resume together with the expected salary\u00a0by clicking \"Apply Now\"\n\nPersonal information collected is for recruitment purposes only.\u00a0", "employment_types": ["Full Time", "Permanent"], "selling_points": ["Manage social media channels strategies", "Develop campaigns to engage customers", "Create content for social media that drives brand"], "locations": ["Tsim Sha Tsui"], "categories": ["Media & Advertising", "Creative / Design", "Photography / Video", "Marketing / Public Relations", "Digital Marketing"], "post_time": "2022-01-18T02:17:52Z", "salary": {"currency": null, "max": null, "min": null, "period": "monthly", "term": null}, "salary_visible": false, "title_keywords": [], "responsibilities": ["social media", "monthly reports", "social media platforms", "design", "plan", "liaise with", "tracking"], "requirements": {"degrees": ["degree holder"], "majors": ["graphic design"], "languages": ["cantonese", "english", "mandarin"], "language_level": ["advantage", "fluent"], "hard_skills": ["web", "adobe photoshop", "illustrator", "mobile", "after effects"], "soft_skills": ["confident", "communication skills", "proactive", "persuasive", "enthusiastic", "attention to detail", "eye for detail", "articulate", "ability to multitask", "creative", "interpersonal"], "languages_combined": [{"language": "cantonese", "language_level": ["fluent"]}, {"language": "english", "language_level": ["fluent"]}, {"language": "mandarin", "language_level": ["advantage", "fluent"]}]}, "experience_required": {"duration": ["minimum 2 years"], "field": ["graphic design", "social media", "brand"]}}, {"job_id": "100003009050326", "location_code": "hk", "company": "iGoodies Holdings Company Limited", "job_title": "E-commerce & Social Media Officer", "description": "Job Highlights\u00a0\n\nSolid exp in e-Commerce & Social Media 2-3 years\nWork independently for operating an online shop\nKnowledge use of web page, photoshop & AI design marketing materials\n\nJob Description\n\nA newly set up on-line shop is looking for a competent, reliable and agile candidate to fill up a position of E-Commence Officer to manage and boost the sales of our \u00a0e-Commerce platforms including but not limited to our online shops, to design and prepare marketing materials for both the online shops and showroom.\n\nDuties and Responsibilities\n\nFully responsible to operate this\u00a0online shop and showroom independently;\nResponsibilities including but not limited to online sales, marketing and daily\u00a0Operation of this online shop;\nPerform & manage operation of this online shop and on different selling channels and\u00a0 E-Commerce portals;\u00a0\nManage daily operations of online shop including generate & update website content (product listing, data entry, promotions, etc);\nEffective use of SEO, social media and KOLs to promote our products, e.g. through Facebook, Instagram, Google AD, WeChat group and \u5c0f\u7d05\u66f8 etc;\nKnowledge of video shooting, editing and daily video production;\nAnalyze and monitor online shop statistics and daily sales data to optimize\u00a0channel traffic performance and sales;\u00a0\nModify weekly product arrangements and make suggestions to change online shop layouts;\u00a0\nCreate & implement tactical offers to support specific products and target specific market;\nOther ad-hoc assignments.\n\nRequirements\n\nDegree in Journalism & Communication\u00a0or related discipline;\n2+ year relevant experience in E-commerce platform related, (fresh graduated will be considered);\nPossess well-developed design skills and marketing knowledge \u2013 capable to use photoshops, AI for design and preparing marketing materials;\nGood knowledge of SEO, SEM, Goggle analytics and adwords;\nExperience with logistic arrangement and warehouse management is advantage;\nProficient in MS Office (MS Word, Excel, Powerpoint, Outlook);\nCapable to work independently;\nGood command of written and spoken English and Chinese (include Mandarin).\n\nAvailability commencement :\n\nAround February, 2022 (after CNY holiday)\n\nWorking days :\n\n5 days per week\n\nTue\u2013Sat (09:30~18:30); Sun & Mon Rest day", "employment_types": ["Full Time", "Permanent"], "selling_points": [], "locations": ["Kwun Tong"], "categories": ["Media & Advertising", "Photography / Video", "Marketing / Public Relations", "Digital Marketing", "E-commerce", "Marketing - Brand / Product Management"], "post_time": "2022-01-17T09:16:23Z", "salary": {"currency": null, "max": null, "min": null, "period": "monthly", "term": null}, "salary_visible": false, "title_keywords": ["officer"], "responsibilities": ["social media", "seo", "product listing", "boost the sales", "data entry", "video production", "data", "ad-hoc assignments", "daily operation", "e-commerce platforms", "design", "website", "monitor", "video shooting", "facebook", "editing", "manage daily operations", "prepare marketing materials"], "requirements": {"degrees": ["degree"], "majors": ["journalism"], "languages": ["english", "chinese", "mandarin"], "language_level": ["good command"], "hard_skills": ["excel", "seo", "ai", "e-commerce", "adwords", "ms word", "powerpoint", "outlook", "sem", "ms office"], "soft_skills": ["communication", "work independently", "capable"], "languages_combined": [{"language": "english", "language_level": ["good command"]}, {"language": "chinese", "language_level": ["good command"]}, {"language": "mandarin", "language_level": ["good command"]}]}, "experience_required": {"duration": ["2+ year"], "field": ["related", "warehouse management", "relevant experience", "e-commerce"]}}, {"job_id": "100003009052333", "location_code": "hk", "company": "New iMedia Solutions Limited", "job_title": "Digital Performance Executive / Specialist | Digital Advertising | SEM | (Department Expansion)", "description": "To become a digital expertise in our Company, you will enjoy our attractive benefits:\n\nCompetitive remuneration package\nPerformance Bonus\nMedical Insurance\n5-day work per week\nFlexi-working hour\nGeneral Holiday, Annual Leave, Family Care Leave and Anniversary Leave\nCasual wear in office\nFriendly working environment\n\n\u00a0\u00a0The Job\n\nStrong analytical skills to consolidate data from numerous digital advertising platforms, analyze various metrics, and to convert them into strategies and action plans\nCommunicate with client on campaign performance, insight and recommendation\nDemonstrate to clients how digital advertising and web analytics can reach their marketing objectives towards business goal\nAttentive to details, execute and optimize various digital media channels (i.e. Facebook, Google, Yahoo, LinkedIn Programmatics DSP), including but not limited to search engine marketing, display ad, social media marketing, conversion tracking and web analysis.\nCollaborate with internal teams to manage and monitor for search engine marketing and social media campaign, to deliver results and KPIs\nKeep up-to-date with platform knowledge and industry news\nAble to work independently, under pressure and to work on multiple projects with tight schedule\n\n\u00a0The Person\n\nDegree in Business, Marketing, IT or related discipline\u00a0\n2 years' experience in online business incl. Search Engine Marketing, Social Media Marketing, Web Analytic\u00a0and account management; Candidate with less experience may be considered as Executive;\nKnowledge of the Search Engine Marketing in Search engines like Google and Yahoo is preferable\nSolid understanding of the current technologies available for online advertising e,g, Search Engine Marketing, Display Advertising, Social Media Marketing, Programmatics, Website development, etc.\nAttentive to details, good with figures and strong analytical skills\nStrong passion for the Internet/Digital environment, result-oriented, proactive and independent\nAble to work collaboratively across teams as a good team player, with client-centric mindset\nGood command of written, spoken English and Chinese, knowledge of Mandarin is preferable\nAble to work independently, under pressure and to work on multiple projects with tight schedule\n\nCandidate with less experience will be considered as Digital Advertising Executive. Fresh graduates are also welcome if you possess knowledge in digital analytics, ad platforms like Google, Facebook, Bing, etc.\n\nPlease send your application with full resume stating\u00a0your present and expected salary\u00a0to the Company by clicking\u00a0on the\u00a0\"Apply now\".\u00a0Please also quote the\u00a0reference number\u00a0of the applied position in the subject field.", "employment_types": ["Full Time"], "selling_points": ["Flexi-Hour, Monthly Early Friday-off & Incentive", "Young & Energetic Talent with Passion in Digital", "Digital Performance & Strategies"], "locations": ["Kwun Tong"], "categories": ["Media & Advertising", "Account Servicing", "Media Buying", "Marketing / Public Relations", "Digital Marketing"], "post_time": "2022-01-17T02:47:43Z", "salary": {"currency": null, "max": null, "min": null, "period": "monthly", "term": null}, "salary_visible": false, "title_keywords": ["specialist", "performance executive"], "responsibilities": [], "requirements": {"degrees": [], "majors": [], "languages": [], "language_level": [], "hard_skills": [], "soft_skills": [], "languages_combined": []}, "experience_required": {"duration": [], "field": []}}, {"job_id": "100003009053100", "location_code": "hk", "company": "Innity China Co., Limited", "job_title": "Business Development Executive", "description": "Primary Responsibilities\n\nDrive and manage the development of our ad network and enhancement of ad performances to strengthen product offerings and increase market share in the local market.\nCreate and establish strong business relationships with new and existing publisher partners.\nOversee, manage, and resolve campaign performance issues.\nAlign goals and objectives with internal and external stakeholders.\nWork closely with in-house Ad Ops team, design, product teams and local sales team in closing business deals.\u00a0\n\nSpecification and Requirement (Eligibility)\n\nBachelor\u2019s Degree in Marketing and Advertising related field\nMinimum 1 year working experience in digital marketing, advertising, or related field. However, fresh graduates will also be considered.\nIndependent and good communication skill.\nCoordination, prioritization, and relationship building skills are essential\nComfortable with managing multiple projects with deadlines and influencing partners and co-workers at all levels of an organization.\u00a0\nPossess great attitude, passionate, proactive, and innovative\nInitiative and eye for details and can work independently or collaboratively in a team environment\nCandidate who with more working experience will be considered for senior post.", "employment_types": ["Full Time"], "selling_points": ["1+ year working experience in advertising industry", "Independent and good communication skill", "Strong business mindset"], "locations": ["Quarry Bay"], "categories": ["Media & Advertising", "Media Buying", "Sales, CS & Business Devpt", "Business Development", "Marketing / Public Relations", "Digital Marketing"], "post_time": "2022-01-17T07:18:15Z", "salary": {"currency": null, "max": null, "min": null, "period": "monthly", "term": null}, "salary_visible": false, "title_keywords": ["business development executive"], "responsibilities": ["sales team", "teams", "design"], "requirements": {"degrees": ["degree", "bachelor"], "majors": ["marketing"], "languages": [], "language_level": [], "hard_skills": [], "soft_skills": ["passionate", "work independently", "independent", "communication skill", "innovative", "coordination", "proactive", "initiative"], "languages_combined": []}, "experience_required": {"duration": ["minimum 1 year"], "field": ["related", "advertising", "digital marketing"]}}, {"job_id": "100003009053450", "location_code": "hk", "company": "Madcradle Online Limited", "job_title": "(Senior) Digital Performance Specialist", "description": "Job Description\n\n\nMaintain daily operations for the social media advertising campaigns including content creation, posting, ad placing and monitoring;\nClosely monitor and analyze the social media advertising performance and its return of investment;\nFormulate insightful strategies and creative ideas to meet clients\u2019 objectives, ensure successful execution, flow and end-result;\nWork closely with internal teams and clients to deliver outstanding account servicing;\nRegularly generate report and drive analytics and recommendations;\nAssist in preparing document to pitch clients e.g. marketing plan, schedule, budget.\n\nThe Successful Applicant\n\n\nTertiary-educated;\nMinimum 1 year of account servicing and practical experience in social media platforms;\nUnderstanding on social media trends and best practices across the digital and new media sectors;\nFast-learner, passionate in online advertising industry;\nEager to learn, cheerful, detail-oriented and polite;\nGood team player with excellent communications and interpersonal skills;\nProficiency in MS Office applications e.g. Word, Excel etc.;\nGood written and spoken English & Chinese;\nCandidate with more experience will be considered as Senior Digital Performance Specialist.\nWhat's On Offer\n\n\n5-day work\nBank Holidays and other special leave (e.g. Birthday Leave, Family Leave, etc...)\nMedical Insurance\nTeam Building Activities\nDigital Marketing Training will be provided\nFriendly Work Environment\nInterest parties please send your CV with availability, current and expected salary to us.\n**Personal data collected will be used for recruitment purpose only**\n\n\n", "employment_types": ["Full Time", "Permanent"], "selling_points": ["Maintain operations for social media campaigns", "Monitor social media advertising performance", "Report and drive analytics and recommendations"], "locations": ["Kwun Tong"], "categories": ["Media & Advertising", "Account Servicing", "Media Buying", "Marketing / Public Relations", "Digital Marketing"], "post_time": "2022-01-17T06:59:54Z", "salary": {"currency": null, "max": null, "min": null, "period": "monthly", "term": null}, "salary_visible": false, "title_keywords": ["digital performance specialist"], "responsibilities": ["social media", "creative ideas", "advertising", "monitoring", "monitor", "maintain daily operations", "teams", "budget", "social media platforms", "marketing plan", "digital marketing", "schedule", "recruitment", "online advertising", "personal data", "insurance", "advertising campaigns", "report"], "requirements": {"degrees": [], "majors": [], "languages": ["english", "chinese"], "language_level": ["good"], "hard_skills": ["excel", "word", "ms office"], "soft_skills": ["passionate", "good team player", "cheerful", "polite", "detail-oriented", "eager to learn", "interpersonal skills", "friendly", "creative"], "languages_combined": [{"language": "english", "language_level": ["good"]}, {"language": "chinese", "language_level": ["good"]}]}, "experience_required": {"duration": ["minimum 1 year"], "field": ["social media", "account servicing", "digital"]}}, {"job_id": "100003009052753", "location_code": "hk", "company": "Memoriki Limited", "job_title": "Marketing Executive (Digital)", "description": "Responsibilities:\n\nExecute digital ROI driven marketing campaigns among global markets\nProactively monitor and optimize campaigns spending and performance on Facebook, Google Ads, Unity Ads and other digital platforms on a daily basis\nManage social media pages including Facebook, IG, LINE, etc\nMonitor and control marketing budget and campaign timelines\u00a0\nCoordinate with product team to manage daily digital tactics\nCoordinate with internal designer to produce new creatives with innovative ideas and formats\nClosely communicate with advertising partner and manage agency accounts to ensure performance is delivered\nProduce regular data analysis, market trending research and reporting with associated insights\nPerform Ad-hoc duties occasionally\n\n\u00a0Qualifications & Skills\n\nBachelor Degree in Business, Marketing, Advertising, eCommerce or related disciplines\n2 years of digital marketing experience\nFamiliar with digital marketing tools including Facebook ads manager, social media, 3rd party tracking, LTV modeling, SEO and Google Analytics\nStrong in written and spoken English and Chinese\nJapanese speaker or business level of Japanese is a plus\nMobile app or game relevant working experience is a plus\nStrong report and analytical skills is a plus\nPrioritize workload, manage multiple projects and meet deadlines for various and ad-hoc marketing deliverable\nPerform independently but outstanding team player with a strong sense of ownership and accountability\nExcellent communication, collaboration and planning skills\nCandidate with less experience will be considered as Digital Marketing Assistant\nFresh Graduate are welcome\n\nWe offer attractive remuneration and fringe benefits to the right candidates. Please send us the application by clicking the \"Apply Now\" button, together with a detailed resume, stating the current and expected salary.\n\n(All personal data provided by job applicants are used only for recruitment purposes and will be treated strictly confidential. Unsuccessful applications will be properly disposed within 3 months.)", "employment_types": ["Full Time", "Permanent"], "selling_points": ["Happy, fun and harmonious working environment", "5 days work / Flexible working hours", "Monitor and optimize digital advertising campaigns"], "locations": ["Ngau Tau Kok"], "categories": ["Marketing / Public Relations", "Marketing - Brand / Product Management", "Marketing - General / Support", "Digital Marketing"], "post_time": "2022-01-17T03:56:02Z", "salary": {"currency": null, "max": null, "min": null, "period": "monthly", "term": null}, "salary_visible": false, "title_keywords": ["marketing executive"], "responsibilities": ["ad-hoc", "ideas", "budget", "communication", "facebook", "control", "advertising", "mobile app", "monitor", "manage multiple projects", "marketing campaigns", "report", "social media", "reporting", "seo", "coordinate with", "data analysis", "digital marketing", "ad-hoc duties", "tracking", "communicate with", "planning"], "requirements": {"degrees": ["degree", "bachelor", "fresh graduate"], "majors": ["ecommerce", "related disciplines", "business", "marketing"], "languages": ["japanese", "english", "chinese"], "language_level": [], "hard_skills": ["google analytics", "plus", "seo", "analysis", "analytical skills", "mobile", "facebook", "unity"], "soft_skills": ["planning skills", "independently", "accountability", "prioritize", "analytical skills", "communication", "team player", "ad-hoc duties", "meet deadlines", "innovative", "driven"], "languages_combined": [{"language": "japanese", "language_level": []}, {"language": "english", "language_level": []}, {"language": "chinese", "language_level": []}]}, "experience_required": {"duration": ["2 years"], "field": ["digital marketing", "relevant working experience"]}}, {"job_id": "100003009054757", "location_code": "hk", "company": "LABS Group Limited", "job_title": "Social Media and Community Executive/Manager", "description": "Generate and manage unique, engaging and creative content and day-to-day handling of all social media channels such as LinkedIn, Facebook, Twitter, Discord, Instagram, etc, and EDM, adapting content to suit different channels using social media marketing tools to create and maintain the company\u2019s brand\nBuild and maintain relationships with our stakeholders, group companies, partners, customers and other industry professionals\nAssist with the design and execution of social media campaigns\nResearching social media trends and informing management of changes that are relevant to the company\u2019s marketing activities\nAttend networking events or relevant industry\nCoordinate with HR, Marketing, Art, Business Development and Management teams\nImplement strategies to improve employee experience and to build community within our organization\n\nRequirements:\n\nBachelor's degree in business, marketing, journalism, public relations or related field\n2+ year of experience in community marketing / community engagement / community management\nHands on experience in content management and excellent copywriting skills\nYou are responsible and organized\nExperience in online social platforms such as Telegram, Facebook, Twitter, Discord, etc.\nExperience in MailChimp.\nKnowledge in Photoshop or illustrator with basic understanding of graphic design principles.\nProficiency in spoken and written English\nExcellent in communication and interpersonal skills\nAnalytical and multitasking skills\nImmediately available is highly preferred\n\n\u00a0Nice to have:\n\nKnowledge of Cryptocurrency and Blockchain\u00a0\nKnowledge of games, especially blockchain games\u00a0\n\n\u00a0What We Offer:\n\nAttractive remuneration package that includes 5-day work\nPrivilege insurance plan for group medical (covers clinical, hospitalization with supplementary major medical) & dental\nConvenient office location in TsimShaTsui\nWork with the young and energetic team\nOpportunities to participate in blockchain projects\nFree snacks, coffee, and tea\nFestival cash and gifts\nRegular staff activities\n\nPlease send your full resume in English, stating present and expected salary by clicking APPLY NOW.\n\nWe are an equal opportunity employer and welcome applications from all qualified candidates.\u00a0 Personal data collected will be treated in strictest confidence and handled confidentially by authorized personnel for recruitment-related purposes within the Group.", "employment_types": ["Full Time", "Permanent"], "selling_points": ["Knowledge of Cryptocurrency and Blockchain", "Immediately available is highly preferred", "2+ year of experience in community marketing"], "locations": ["Tsim Sha Tsui"], "categories": ["Marketing / Public Relations", "Marketing - Marketing Communication", "Public Relations - Copy-writing", "Digital Marketing"], "post_time": "2022-01-17T10:55:58Z", "salary": {"currency": null, "max": null, "min": null, "period": "monthly", "term": null}, "salary_visible": false, "title_keywords": ["executive", "manager"], "responsibilities": ["maintain relationships", "social media", "management", "management teams", "creative content", "social media campaigns", "edm", "graphic design", "hr", "coordinate with", "design", "communication", "maintain", "facebook"], "requirements": {"degrees": ["degree", "bachelor"], "majors": ["journalism", "business", "marketing"], "languages": ["english"], "language_level": ["proficiency"], "hard_skills": ["blockchain", "basic", "nice", "illustrator", "cryptocurrency", "facebook", "photoshop"], "soft_skills": ["organized", "responsible", "unique", "hands on", "communication and interpersonal skills", "creative"], "languages_combined": [{"language": "english", "language_level": ["proficiency"]}]}, "experience_required": {"duration": ["2+ year"], "field": ["copywriting", "management", "marketing"]}}, {"job_id": "100003009054867", "location_code": "hk", "company": "Strategic Digital Marketing Company Limited", "job_title": "Account Executive (5 days work)", "description": "You'll be responsible for...\n\nDay-to-day project management on search (SEO, Paid Ad) and social media marketing (Facebook, Instagram, LinkedIn) accounts\nServe as key person between client, multi-function teams, internal work counterparts and external parties for service designs and implementation\nAnalyze and evaluate campaign's performance and provide suggestions for improvement\nPrepare pitching proposals\u00a0\nBrainstorm and prepare presentation and reports to clients\nPerform ad-hoc duties as assigned\n\nIf you are...\n\nDegree holder in any\u00a0related\u00a0disciplines (Marketing/ e-Commerce/ Communications or Business);\nWith at least 2 years working experience in Digital Marketing field or related disciplines\nExperienced in search & social media marketing is a must;\nFluency in written and spoken English, Cantonese and Mandarin;\nExcellent communication and interpersonal skills;\nGood in Microsoft Offices (Word, Excel, PowerPoint) and Chinese and English typing;\nKnowledge in Digital Marketing Tools (eg. Google Adwords, Google Analytics, Facebook Ad Manager, etc) is a must;\nTeam leader, highly independent, self-motivated responsive,\u00a0innovative,\u00a0well-organized, presentable with strong analytical skills and business sense;\nWilling to learn and explore new knowledge and technology;\nCandidate with more experience will be considered as Senior Account Executive\n\nWe offer...\u00a0\n\nFive-days work per week + Bank Holiday\nProject Completion Bonus\nEducation Allowance\nMedical Allowance\nSnacks and drinks\nTraining + Good career prospect in growing Digital Marketing Industry\n\nIf this sounds interesting to you, Apply Now!!\u00a0\n\nPlease come with a portfolio that will demonstrate our required fields as mentioned above. Interested parties, please apply with full resume, portfolio, current and expected salary.\n\nData collected would be used for recruitment purposes only. Applicants who do not hear from us within 8 weeks may consider their application unsuccessful and their data will be destroyed within 24 months of receipt.", "employment_types": ["Full Time", "Permanent"], "selling_points": ["Project management for top-tier companies and SME", "Friendly and energetic working environment", "Challenging, an once in a lifetime opportunity!"], "locations": ["Lai Chi Kok"], "categories": ["Information Technology (IT)", "IT - Webmaster / SEO", "Sales, CS & Business Devpt", "Account Servicing", "Marketing / Public Relations", "Digital Marketing"], "post_time": "2022-01-17T16:21:09Z", "salary": {"currency": null, "max": null, "min": null, "period": "monthly", "term": null}, "salary_visible": false, "title_keywords": ["account executive"], "responsibilities": ["social media", "seo", "external parties", "teams", "implementation", "evaluate", "project management", "communication", "reports", "digital marketing", "ad-hoc duties", "facebook"], "requirements": {"degrees": ["degree holder"], "majors": ["e-commerce", "related disciplines", "marketing", "business", "communications"], "languages": ["cantonese", "english", "chinese", "mandarin"], "language_level": ["fluency", "good"], "hard_skills": ["excel", "google analytics", "seo", "e-commerce", "adwords", "word", "powerpoint", "typing", "analytical skills", "project management", "facebook"], "soft_skills": ["highly independent", "self-motivated", "responsible", "business sense", "well-organized", "willing to learn", "presentable", "analytical skills", "project management", "communication and interpersonal skills", "ad-hoc duties", "innovative", "responsive", "presentation"], "languages_combined": [{"language": "cantonese", "language_level": ["fluency"]}, {"language": "english", "language_level": ["fluency", "good"]}, {"language": "chinese", "language_level": ["good"]}, {"language": "mandarin", "language_level": ["fluency"]}]}, "experience_required": {"duration": ["at least 2 years"], "field": ["related", "digital marketing field"]}}, {"job_id": "100003009052556", "location_code": "hk", "company": "AOSource Company Limited", "job_title": "Digital Marketing Manager / Assistant Manager (APAC)   (DM-0117-sh-JDBP)", "description": "Our client is a MNC group,\u00a0 Current they are looking for potential candidate to join their Digital Marketing team in Hong Kong.\n\n\u00a0Responsibilities;\n\nTo drive digital Campaign and program for Global Group Team\u00a0 or APAC team in Hong Kong.\nTo develop and maintain digital strategy for Website and social media.\nDevelop and create digital media strategy for the group.\nTo formulate strategic online for build branding and marketing planning.\nTo measure and report on performance of all marketing advertisement and campaigns.\nTo provide product brand information and business direction with Asia Region.\nExcellent communcation with English is must\u00a0\nIf less experience to be considered as Assistant Manager\u00a0\nRequirements:\n\nDegree or Above in Business / Marketing or related discipline;\n\nAbout 4+ years working experience in Digital Marketing,\u00a0 Asia\u00a0Regional experience is must;\u00a0\nCurrent experience in managing Digital Strategy and Campaign;\nGood experience in dealing with various country business partner;\nExperience in either CRM , Adobe Creative Suite, Google Analystics, Google Ads is a plus;\nGood experience in email marketing/ data analysis and Salesforce Marketing Cloud is plus\nExcellent spoken and written communication skill in English;\nWork independently and good team player;\nLess experience to be considered as Assistant Manager.\nOur client will offer competitive remuneration package and good career prospects to the potential candidate, interested parties please quote ref.no. DM-0117-sh-JDBP and submit your resume to Ms Fung by our email or enquiry with Tel:3428-6121.\n\n\nAll profiles are handled with strictest confidentiality. Shortlisted candidates would be notified", "employment_types": ["Full Time", "Permanent"], "selling_points": ["MNC Group", "Digital Marketing /Asia Region/ Social Media", "Exp.in Google Analytics, Google Ads, CRM etc"], "locations": ["Not Specified"], "categories": ["Marketing / Public Relations", "Management", "Marketing - Brand / Product Management", "Digital Marketing"], "post_time": "2022-01-17T03:24:42Z", "salary": {"currency": null, "max": null, "min": null, "period": "monthly", "term": null}, "salary_visible": false, "title_keywords": ["digital marketing manager", "assistant manager"], "responsibilities": ["social media", "website", "develop", "maintain", "report", "planning"], "requirements": {"degrees": ["degree or above"], "majors": ["business", "marketing"], "languages": ["english"], "language_level": ["excellent"], "hard_skills": ["plus", "analysis", "salesforce", "adobe creative suite"], "soft_skills": ["communication skill", "good team player", "work independently", "creative"], "languages_combined": [{"language": "english", "language_level": ["excellent", "excellent"]}]}, "experience_required": {"duration": ["4+ years"], "field": ["business partner", "data analysis", "marketing", "digital marketing", "digital"]}}, {"job_id": "100003009056102", "location_code": "hk", "company": "Madcradle Online Limited", "job_title": "Assistant Digital Performance Manager", "description": "Job Description\n\n\nDelivering social media campaigns through social media platforms: Facebook, LinkedIn, Twitter, LINE, Wechat etc.;\nPlanning and executing online advertising strategies of various platforms;\nMaintain daily operations for the social media advertising campaigns including content creation, posting, ad placing and monitoring;\nClosely monitor and analyze the social media advertising performance and its return of investment;\nFormulate insightful strategies and creative ideas to meet clients\u2019 objectives, ensure successful execution, flow and end-result;\nMaintain relationship with new and existing customers;\nPerform any ad-hoc duties as assigned.\nThe Successful Applicant\n\n\nBachelor\u2019s degree in Marketing Communication or related;\nMinimum 3 year practical experience in social media platforms, agency experience preferred;\nUnderstanding on social media trends and best practices across the digital and new media sectors;\nAbility to lead and motivate a team to deliver results;\nEager to learn, cheerful, detail-oriented and polite;\nProficiency in MS Office applications e.g. Word, Excel etc.\nmedia sectors;\nGood written and spoken English & Chinese;\nCandidate with more experience will be considered as Digital Performance Manager.\nWhat's On Offer\n\n\n5-day work\nBank Holidays and other special leave (e.g. Birthday Leave, Family Leave, etc...)\nMedical Insurance\nTeam Building Activities\nDigital Marketing Training will be provided\nFriendly Work Environment\nInterest parties please send your CV with availability, current and expected salary to us.\n**Personal data collected will be used for recruitment purpose only**\n\n\n", "employment_types": ["Full Time", "Permanent"], "selling_points": ["Plan & execute Digital Marketing strategies", "Monitor Social Media advertising performance", "5-day week, Competitive Remuneration Package"], "locations": ["Kwun Tong"], "categories": ["Media & Advertising", "Media Buying", "Strategic Planning", "Marketing / Public Relations", "Digital Marketing"], "post_time": "2022-01-18T03:19:04Z", "salary": {"currency": null, "max": null, "min": null, "period": "monthly", "term": null}, "salary_visible": false, "title_keywords": ["manager", "assistant"], "responsibilities": ["social media platforms", "communication", "maintain", "facebook", "personal data", "online advertising", "advertising", "social media campaigns", "maintain daily operations", "monitor", "social media", "monitoring", "executing", "digital marketing", "ad-hoc duties", "advertising campaigns", "creative ideas", "recruitment", "insurance", "planning"], "requirements": {"degrees": ["degree", "bachelor"], "majors": ["marketing"], "languages": ["english", "chinese"], "language_level": ["good"], "hard_skills": ["excel", "word", "wechat", "facebook", "ms office"], "soft_skills": ["cheerful", "polite", "detail-oriented", "communication", "eager to learn", "friendly", "ad-hoc duties", "creative"], "languages_combined": [{"language": "english", "language_level": ["good"]}, {"language": "chinese", "language_level": ["good"]}]}, "experience_required": {"duration": ["minimum 3 year"], "field": ["agency", "social media", "digital"]}}, {"job_id": "100003009052267", "location_code": "hk", "company": "Eagle Partners (International) Co., Limited", "job_title": "Digital Marketing Manager (ecommerce)", "description": "Our client, an established company in baby products/e-commerce is looking for a\u00a0Digital Marketing Manager\u00a0to join their team :-\n\nJob Description\n\nThe Digital Marketing Manager will work within the in-house marketing team and will play a critical role in activating, managing and measuring digital marketing activities for\u00a0B2C online stores and apps in both Hong Kong and overseas. This role will oversee the in-house creation of digital content and management of campaigns and is also responsible for the performance analytics.\n\nJob responsibilities\n\nWork closely with internal stakeholders to develop marketing content and campaigns, such as social media content, copywriting, website ecommerce and app campaigns.\nAssist with development of digital marketing strategies and on brand campaigns to drive revenue via each of our verticals and channel.\nManage and collaborate with digital agencies, freelancers, KOLs and affiliates to improve website commercial performance, PPC and SEO programs to drive key ROI metrics.\nContent generation across digital channels and management of promotional calendars\nCampaign management on social media, email and websites\nAssist with reporting, analytics, dashboards and provide insights for improving digital key metrics\n\nRequirements\n\nSelf motivated, positive attitude and must have digital marketing experience with social media programs, e-commerce and PPC campaigns\nUniversity graduate with 5 years minimum work experience in Digital Marketing in online retail\nDemonstrated experience in content marketing, social media management, ATL/BTL marketing. With forward thinking and openness to new ideas for marketing opportunities\nExcellent written English and Cantonese\nAnalytical mindset and strategic conceptual skill and acute marketing sense with attention to detail\u00a0", "employment_types": ["Full Time"], "selling_points": ["Ecommerce, Online Retail", "Mid-senior level", "Attractive remuneration package"], "locations": ["Sai Ying Pun"], "categories": ["Marketing / Public Relations", "Digital Marketing"], "post_time": "2022-01-17T05:27:33Z", "salary": {"currency": null, "max": null, "min": null, "period": "monthly", "term": null}, "salary_visible": false, "title_keywords": ["digital marketing manager"], "responsibilities": ["collaborate with", "social media", "management", "reporting", "digital marketing strategies", "seo", "provide insights", "website", "develop", "social media content", "digital marketing", "campaign management"], "requirements": {"degrees": ["university graduate"], "majors": ["digital marketing"], "languages": ["cantonese", "english"], "language_level": ["excellent"], "hard_skills": ["e-commerce"], "soft_skills": ["self motivated", "positive attitude", "marketing sense", "attention to detail"], "languages_combined": [{"language": "cantonese", "language_level": ["excellent"]}, {"language": "english", "language_level": ["excellent"]}]}, "experience_required": {"duration": ["5 years"], "field": ["social media", "management", "e-commerce", "marketing", "digital marketing", "retail"]}}, {"job_id": "100003009054551", "location_code": "hk", "company": "Initsoc Limited", "job_title": "Business Development / Sales Executive (Digital Marketing)", "description": "Job Scope:\n\nPromote\u00a0digital marketing service and e-commerce solution\u00a0\nHandle incoming leads and could proactively follow-up potential client\u00a0\nConstant research on the most updated trend in\u00a0digital\u00a0marketing\u00a0\nPrepare sales and promotion materials\u00a0\nOther\u00a0ad-hoc\u00a0sales related activities\u00a0\nRequirements:\u00a0\nMinimum 2 years of relevant sales experiences in digital marketing / media sales /\u00a0online advertising\u00a0\u00a0\nMust be self-motivated, sales-driven, confident and able to work independently\u00a0\nLogical and with sense of beauty in preparing sales and promotion materials\u00a0\nExcellent research, presentation, communication and organizational skills\u00a0\nAble\u00a0to communicate\u00a0effectively\u00a0in\u00a0English and Chinese\u00a0(Cantonese and Mandarin)\u00a0\nBasic knowledge of social media and social ecosystem in China is preferred\u00a0\nProficient with\u00a0Microsoft\u00a0PowerPoint and Excel\u00a0\nIf you are interested in the position, please send us your CV with expected salary to us. All information collected will be used for recruitment purposes only.\u00a0", "employment_types": ["Full Time"], "selling_points": [], "locations": ["Yau Ma Tei"], "categories": ["Marketing / Public Relations", "Digital Marketing"], "post_time": "2022-01-17T09:57:35Z", "salary": {"currency": null, "max": null, "min": null, "period": "monthly", "term": null}, "salary_visible": false, "title_keywords": ["digital marketing", "sales executive"], "responsibilities": ["ad-hoc", "social media", "prepare sales", "communication", "digital marketing", "recruitment", "online advertising"], "requirements": {"degrees": [], "majors": [], "languages": ["cantonese", "english", "chinese", "mandarin"], "language_level": [], "hard_skills": ["excel", "basic", "microsoft powerpoint", "e-commerce"], "soft_skills": ["confident", "organizational skills", "self-motivated", "work independently", "interested in", "driven", "communication", "presentation"], "languages_combined": [{"language": "cantonese", "language_level": []}, {"language": "english", "language_level": []}, {"language": "chinese", "language_level": []}, {"language": "mandarin", "language_level": []}]}, "experience_required": {"duration": ["minimum 2 years"], "field": ["advertising", "digital marketing", "media sales"]}}, {"job_id": "100003009054886", "location_code": "hk", "company": "Vpon HK Limited", "job_title": "Senior Operations Executive (Digital Campaign)", "description": "We thirst for more creative blood to join our growing team!\nWe value employee experience. We encourage Vponers to embrace an agile mindset and adapt to the high-speed business world.\n\nWhen Opportunity Knocks \u2013 Are You Ready to Step Through the Door?\n\nGet ready to meet dynamic business needs and changes in digital advertising, data, and internet industry.\n\n\n\nWhat you will be working on:\n\nMaintain and manage programmatic advertising platforms to ensure smooth campaign execution\nInterpret data, make informed judgments, and suggest insightful implications with excellent and pragmatic decision-making skills relevant to mobile advertising\nWork with cross-functional teams on project management, data analysis, delivery, optimizations for campaign performance and product developments\nCollaborate with colleagues across HK, TW, JP, SG with a good understanding of the region\n\nWhat can make you stand out in a competitive pool:\n\nDegree holder in Marketing, Digital Marketing or a related discipline\n2-year experience in Digital Marketing is preferred\nKnowledge of Google Ads, Facebook Ad and Tencent Ads is preferred\nStrong awareness of digital advertising and strategies\nPossess a can-do attitude, strong organizational skills and be self-motivational\nExcellent communication and project coordination skills\u00a0\nFluency in spoken and written English, Cantonese and Mandarin", "employment_types": ["Full Time", "Permanent"], "selling_points": ["Data Interpretation", "Data Optimizations", "Maintain & manage advertising platforms"], "locations": ["Quarry Bay"], "categories": ["Information Technology (IT)", "Product Management / Business Analyst", "Marketing / Public Relations", "Digital Marketing", "Data Scientist"], "post_time": "2022-01-17T12:37:33Z", "salary": {"currency": null, "max": null, "min": null, "period": "monthly", "term": null}, "salary_visible": false, "title_keywords": ["senior operations", "executive"], "responsibilities": ["collaborate with", "advertising", "project coordination", "data", "data analysis", "project management", "communication", "maintain", "digital marketing", "facebook", "cross-functional teams"], "requirements": {"degrees": ["degree holder"], "majors": ["marketing", "digital marketing"], "languages": ["cantonese", "english", "mandarin"], "language_level": ["fluency"], "hard_skills": ["agile", "analysis", "make", "mobile", "dynamic", "project management", "facebook"], "soft_skills": ["organizational skills", "agile", "coordination skills", "can-do attitude", "communication", "project management", "dynamic", "smooth", "creative"], "languages_combined": [{"language": "cantonese", "language_level": ["fluency"]}, {"language": "english", "language_level": ["fluency"]}, {"language": "mandarin", "language_level": ["fluency"]}]}, "experience_required": {"duration": ["2-year"], "field": ["digital marketing"]}}, {"job_id": "100003009054010", "location_code": "hk", "company": "Thinking Group Holding Limited", "job_title": "Assistant Marketing Manager", "description": "Thinking Group, a sole distributor of Audio products & Smart Gadget products including: Ultimate Ears (UE), JBL/ Harman Kardon, Aftershokz......etc. Founded in 1998, its headquarters in HK and branches in Shenzhen & Taiwan. To cope with our continuous expansion, we are seeking qualified candidates to join us.\n\nResponsibilities:\n\nPlanning, organizing, implementing and evaluating annual marketing plan\nBuild up and maintain relationship with media & network channel\nGuide social media strategy for professional audio products, including strategy for B2B and B2C\u00a0communication\nWork with Product and Sales team to promote products and brands\nEvaluating and optimizing marketing and pricing strategies\nAnalyzing market trends and preparing forecasts\nIncreasing brand awareness and market share\nCoordinating marketing strategies with the sales, financial public rekations, and production departments\nResponsible for media planning, budgeting, event management\nRequirements:\n\n\nDegree holder in Marketing / Communications / Business Administration or related disciplines\n3 years of relevant experience in digital or ecommerce marketing\u00a0\nProven ability to solve problems creatively\nStrong interpersonal skills and extremely resourceful\u00a0\nKnowledge of digital platforms for marketing purposes and Web Analytics tools\nGood command of spoken and written English and Chinese, Putonghua is an advantage\nCreative, responsible, analytical and self-motivated\nBenefits:\n\n5 day work\nBank holiday and Birthday leave\nAnnaul leave and Sick leave\nMedical and Dental allowance", "employment_types": ["Full Time", "Permanent"], "selling_points": ["5 years experience in digital, ecommerce marketing", "Increasing brand awareness and market share", "Responsible for media planning, budgeting, event"], "locations": ["Kwun Tong"], "categories": ["Marketing / Public Relations", "Marketing - Brand / Product Management", "Marketing - Marketing Communication", "Digital Marketing"], "post_time": "2022-01-17T08:53:00Z", "salary": {"currency": null, "max": null, "min": null, "period": "monthly", "term": null}, "salary_visible": false, "title_keywords": ["assistant marketing manager"], "responsibilities": ["social media", "management", "marketing strategies", "budgeting", "communication", "marketing plan", "maintain", "sales team", "promote products", "audio", "planning"], "requirements": {"degrees": ["degree holder"], "majors": ["related disciplines", "marketing", "business administration", "communications"], "languages": ["putonghua", "english", "chinese"], "language_level": ["advantage", "good command"], "hard_skills": ["web analytics"], "soft_skills": ["self-motivated", "resourceful", "responsible", "solve problems", "interpersonal skills", "web analytics", "creative"], "languages_combined": [{"language": "putonghua", "language_level": ["advantage", "good command"]}, {"language": "english", "language_level": ["good command"]}, {"language": "chinese", "language_level": ["good command"]}]}, "experience_required": {"duration": ["3 years"], "field": ["ecommerce", "digital", "marketing", "relevant experience"]}}, {"job_id": "100003009056386", "location_code": "hk", "company": "Spread-it Limited", "job_title": "Account Executive (Micro-influencer)", "description": "Responsibility:\n\nIn-charge of\u00a0the overall operation of micro-influencers campaigns from setting campaign briefs to monitoring campaign results to preparing final reports to the clients\nClosely\u00a0liaising and communicating with clients to make sure their needs are fully\u00a0fulfilled\u00a0\nUnderstands and knows the offerings of Spread-it\nClosely communicating with Spreadians \u00a0(our micro-influencers) to make sure they fulfil the campaigns requirements\nTakes care of clients\u2019 needs and builds relationship with them\n\nRequirements:\u200b\n\n0-2 years of experiences in marketing and advertisement industry\nPassionate in marketing industry\nConversational in cantonese and english. Cantonese is preferred but not necessary\nSelf motivated with positive attitude\nOutgoing and responsible team player\nSense of humor highly encouraged\nStrong interpersonal and communication skills\n\nBenefit:\n\nOpportunity to work at a disruptive startup\nFast paced, fun, and energetic company with west coast inspired startup culture", "employment_types": ["Full Time"], "selling_points": ["0-2 years experience in marketing agencies", "Start up", "happy and fun working environment"], "locations": ["Cheung Sha Wan"], "categories": ["Marketing / Public Relations", "Digital Marketing"], "post_time": "2022-01-18T04:07:49Z", "salary": {"currency": null, "max": null, "min": null, "period": "monthly", "term": null}, "salary_visible": false, "title_keywords": ["account executive"], "responsibilities": ["monitoring", "reports", "communicating with"], "requirements": {"degrees": [], "majors": [], "languages": ["cantonese", "english"], "language_level": ["conversational"], "hard_skills": [], "soft_skills": ["passionate", "outgoing", "communication skills", "responsible", "positive attitude", "self motivated", "team player", "interpersonal"], "languages_combined": [{"language": "cantonese", "language_level": ["conversational"]}, {"language": "english", "language_level": ["conversational"]}]}, "experience_required": {"duration": ["0-2 years"], "field": ["advertisement", "marketing"]}}, {"job_id": "100003009056084", "location_code": "hk", "company": "DFI Retail Group DFI\u96f6\u552e\u96c6\u5718", "job_title": "Senior Financial Services Partnership Executive (yuu)", "description": "The role of the Financial Services Partnerships function is to build and manage relationships with yuu Rewards\u2019 financial services partners participating in the programme and ensure delivery of the agreed value proposition and benefits to the partners.\n\nThe Account Executive is an important position within the organization. This position requires engagement with internal and external stakeholders to realize the agreed objectives and success at key partner/s. A key deliverable of this position is to understand partners\u2019 strategic business and marketing objectives; align them with the programme, ensure seamless integration of the partner into the programme and operationalize customer acquisition and subsequent execution of marketing programmes and other initiatives.\n\nThe Role\n\nSupport:\n\nSupport Senior Partnerships Managers in developing marketing and engagement plans and coordinating activities between yuu rewards and financial services (\u201dFS\u201d) partners\nManage across retail banners and coordinate with retail partnerships team\n\nClient management:\n\nBuild and manage relationships in various perspectives within FS partner organisations to drive partner-based initiatives (including both operational and technical support)\nAct as project management role to ensure full and smooth integration of FS partners into the programme\n\nMarketing & CRM coordination:\n\nDay to day administration of joint marketing and engagement plans with the FS partners to deliver towards the agreed roadmap\nSupport the execution on programme planning to drive CRM journey\nMaintain FS marketing activities across all DF banners \u2013 a key contractual requirement\n\nInsights:\n\nEnsure successful execution of agreed plans with appropriate measurement and reporting mechanisms put in place\nWork with analytics teams to understand trends in partner data\nSupport in delivery of insights and execution of plans arising from insights in key business areas\nAssist Senior Partnerships Managers to identify and realize opportunities to improve FS partner performance in the programme\n\nThe Person\n\nUniversity degree\n3+ years experience in client management roles in a marketing related function\nStrong commercial and communication skills\nA strong team player\nFinancial services experience is ideal, loyalty experience preferred but not essential\nGood PowerPoint, Excel, Word skills\n\nDFI Retail Group is responsible for ensuring that all personal information collected from each Candidate presented to DFI Retail Group is used for recruitment purposes only and the data collection process is in accordance with all applicable laws and compliant with the Code of Practice on Human Resource Management.\n\nTo find out more about Our Businesses and Our People, please visit our website:\u00a0www.DFIretailgroup.com\n\nWe are an equal opportunity employer. Personal data collected will be kept and handled confidentially by authorised personnel for recruitment purposes only. We will retain the applications of candidates not selected for a period of no more than 24 months. A copy of our Privacy Policy can be accessed by visiting our Company website.\n\nIssued by The Dairy Farm Company, Limited", "employment_types": ["Permanent"], "selling_points": ["One of the biggest loyalty program in HK", "Maintain relationships with FS partners", "CRM campaigns and digital marketing"], "locations": ["Tai Koo"], "categories": ["Marketing / Public Relations", "Digital Marketing"], "post_time": "2022-01-18T03:15:34Z", "salary": {"currency": null, "max": null, "min": null, "period": "monthly", "term": null}, "salary_visible": false, "title_keywords": ["executive"], "responsibilities": ["data", "website", "communication", "banners", "maintain", "plans", "personal data", "administration", "measurement", "developing", "teams", "company website", "reporting", "management", "coordinate with", "data collection", "technical support", "project management", "recruitment", "coordination", "planning"], "requirements": {"degrees": ["university degree"], "majors": [], "languages": [], "language_level": [], "hard_skills": ["excel", "no", "word", "powerpoint", "project management", "integration", "code"], "soft_skills": ["communication skills", "responsible", "project management", "coordination", "smooth", "team player", "ideal"], "languages_combined": []}, "experience_required": {"duration": ["3+ years"], "field": ["related", "management", "marketing", "financial services"]}}, {"job_id": "100003009051841", "location_code": "hk", "company": "Stylevana", "job_title": "Digital Marketing Executive (Influencer Marketing) \u2013 Fashion & Beauty", "description": "Join Us and Start your eCommerce Journey\n\nAre you looking to be part of a fast growing eCommerce business focused on bringing world class customer experiences to people across the globe? Join our energetic team as we grow our ideas into reality. We are looking for talent to help continue expand our beauty business, driving brand awareness to interested people.\n\nKey Job Responsibilities:\u00a0\u00a0\n\n\nResponsible for developing strategic influencer marketing strategies to enhance brand awareness\nResponsible for identifying and recruiting new potential KOLs and influencers that align with our company goals and values\nDevelop long-term relationship with KOLs and influencers\nMonitor traffic and marketing KPI as well as ensuring ROAS from KOL marketing, in close collaboration with Business team\nConduct regular ad hoc market search and analysis to keep up with latest market trend and competitor activities in influencer marketing\nPerform other duties as assigned by Management\n\n\u00a0Desired Skills and Experience:\u00a0\u00a0\n\nDegree holder or above in Marketing/ Business/ eCommerce or related disciplines\nMinimum 2-3 years or above working experience in eCommerce, preferably in beauty and fast-fashion industry\nStrong interest in Korean and Asian branded beauty products\nSolid experience in online digital marketing, preferably in social media, influencer marketing and affiliate marketing\nStrong analytical skills to drive marketing results, transforming data to actionable insight and recommendations\nWell-organized, detailed minded and able to manage multiple tasks\nAble to work independently and under pressure, as well as cooperate well with team and stakeholders to achieve company goals\nExcellent command of written and spoken English\nWe offer friendly team environment, good career prospect, also attractive remuneration package, together with other benefits like five-day work week, flexible working hour, double pay, medical and dental insurance. Interested parties please send full resume with available date, present and expected salary by clicking \u201cApply Now\u201d for an interview.\u00a0\n\n\nAll personal data collected will be used for recruitment purpose only.", "employment_types": ["Full Time", "Permanent"], "selling_points": ["eCommerce, preferably in beauty and fast-fashion", "Experience in influencer marketing", "5-day work, Flex working hour, friendly team"], "locations": ["Kwai Hing"], "categories": ["Media & Advertising", "Editorial / Journalism", "Marketing / Public Relations", "Digital Marketing", "E-commerce", "Marketing - Brand / Product Management"], "post_time": "2022-01-17T01:20:53Z", "salary": {"currency": null, "max": null, "min": null, "period": "monthly", "term": null}, "salary_visible": false, "title_keywords": ["digital marketing executive"], "responsibilities": ["social media", "perform other duties", "management", "marketing strategies", "ideas", "ad hoc", "data", "analysis", "monitor", "developing", "develop", "digital marketing", "insurance"], "requirements": {"degrees": ["degree holder"], "majors": ["business", "related disciplines", "ecommerce", "marketing"], "languages": ["english", "korean"], "language_level": ["excellent"], "hard_skills": ["analysis", "analytical skills"], "soft_skills": ["flexible", "work independently", "under pressure", "focused", "responsible", "multiple tasks", "well-organized", "analytical skills", "friendly", "energetic", "detailed"], "languages_combined": [{"language": "english", "language_level": ["excellent"]}, {"language": "korean", "language_level": []}]}, "experience_required": {"duration": ["minimum 2-3 years"], "field": ["ecommerce", "social media", "business", "digital marketing", "beauty", "marketing", "team"]}}, {"job_id": "100003009052663", "location_code": "hk", "company": "Hong Kong Loving Family Limited", "job_title": "Marketing Assistant / Executive", "description": "Job Description\n\nDevelop and implement digital marketing programs which cover website development, SEO, SEM, social media strategy, content strategy for Greater China, Hong Kong\nManage social media properties (Facebook, Instagram, weibo, wechat, Xiaohongshu, Zhihu etc.), including daily monitoring, posting, and content development\nResponsible for different graphic design & artwork adaptation including poster, leaflets, banners etc\nProvide marketing supports to the team\nAny other ad hoc projects assigned by the Management\n\n\nRequirement\n\nDiploma or above in Journalism, Marketing, Communications, or related field\nAt least 1 year of relevant working experience\nA good team player while being able to work independently\nGood communication skills\nGood command of written and spoken Chinese, Mandarin & English\nKnowledge in Adobe Creative Suite. E.g. Adobe Creative Suite, e.g. Photoshop, illustrator, Dreamweaver, etc\nImmediate availability is highly preferred\nFresh graduates are welcome\n\nBenefit\n\nMedical insurance\nDental insurance\nDiscretionary bonus\nAttractive performance bonus\nFriendly and collaborative work environment\n\nWe offer competitive remuneration package and good prospects to the right candidates. Interested parties please send your full resume with expected salary to our email.\n\nFor more details, please visit our official website: https://hkfamily.com.hk/ and click ''Apply Now'' to join us now!\n\n*Data collected will be kept confidential and used solely for recruitment purposes only.", "employment_types": ["Full Time"], "selling_points": [], "locations": ["Shatin Area"], "categories": ["Marketing / Public Relations", "Marketing - Brand / Product Management", "Marketing - Market Research", "Digital Marketing"], "post_time": "2022-01-17T03:39:58Z", "salary": {"currency": null, "max": null, "min": null, "period": "monthly", "term": null}, "salary_visible": false, "title_keywords": ["marketing assistant", "executive"], "responsibilities": ["social media", "management", "seo", "digital marketing programs", "leaflets", "graphic design", "website", "develop", "banners", "ad hoc projects", "sem", "facebook", "daily monitoring"], "requirements": {"degrees": ["diploma or above"], "majors": ["journalism", "marketing", "communications"], "languages": ["english", "chinese", "mandarin"], "language_level": ["good command"], "hard_skills": ["dreamweaver", "illustrator", "adobe creative suite", "photoshop"], "soft_skills": ["communication skills", "good team player", "creative", "work independently"], "languages_combined": [{"language": "english", "language_level": ["good command"]}, {"language": "chinese", "language_level": ["good command"]}, {"language": "mandarin", "language_level": ["good command"]}]}, "experience_required": {"duration": ["at least 1 year"], "field": ["relevant working experience"]}}, {"job_id": "100003009053839", "location_code": "hk", "company": "LifeHub Limited", "job_title": "Marketing Executive / Graphic designer", "description": "Job Description\n\nRoles & Responsibilities\nResponsible for creative concept development and handle all stages of design include but not limited to the following:\n\u2022 Social media visual and feed designs (Facebook, Instagram, eDM, Google ad, etc.)\n\u2022 Online store visual (Web banner, product page, etc)\n\u2022 Sales kit and POP materials\n\u2022 Product retouching and mock-ups\n\u2022 Presentation powerpoint\n\u2022 Printing\nAssisting in all marketing campaigns\nAssisting in all marketing materials in line with marketing plans\nAssisting in website updates\nImplementing promotional campaigns\nSupport clinical team on updating marketing materials, screens etc\nAssisting in handling different marketing promotion materials\nAd hoc projects as assigned by management\n\nSkills & Qualifications\nFluent in English & Chinese\n2-3 years relevant working experience in graphic design\nNeed to be highly organised and attention to detail\nWith passion, creativity and imagination in design\nEager to learn and to participate in marketing projects\nFresh graduates are welcome\n\nPlease send your CV with 3-5 examples of recent artwork job reference.", "employment_types": ["Full Time"], "selling_points": [], "locations": ["Central"], "categories": ["Design", "Graphics", "Marketing / Public Relations", "Marketing - Marketing Communication", "Digital Marketing"], "post_time": "2022-01-17T07:36:17Z", "salary": {"currency": null, "max": null, "min": null, "period": "monthly", "term": null}, "salary_visible": false, "title_keywords": ["graphic designer", "marketing executive"], "responsibilities": ["pop materials", "management", "edm", "marketing plans", "graphic design", "product retouching", "mock-ups", "social media visual and feed designs", "design", "website", "marketing projects", "ad hoc projects", "marketing campaigns", "visual", "marketing materials", "facebook", "sales kit"], "requirements": {"degrees": [], "majors": [], "languages": ["english", "chinese"], "language_level": ["fluent"], "hard_skills": ["powerpoint", "facebook", "web"], "soft_skills": ["responsible", "eager to learn", "attention to detail", "organised", "creative", "presentation"], "languages_combined": [{"language": "english", "language_level": ["fluent"]}, {"language": "chinese", "language_level": ["fluent"]}]}, "experience_required": {"duration": ["2-3 years"], "field": ["graphic design", "relevant working experience"]}}, {"job_id": "100003009053799", "location_code": "hk", "company": "Hysan Development Co Ltd", "job_title": "Assistant Manager, Event & Promotions", "description": "Job Purpose\nTo develop and implement effective marketing plans to generate quality traffic and spending to maximize tenant turnover growth at both local and tourist markets.\n\n\nKey Responsibilities\n\nPlan and execute monthly/festive programs and activities.\nImplement effective and efficient O2O, interactive and digital initiatives, in supporting the overall branding and traffic Effective content curation which matches with the retail leasing portfolio strategy.\nProactively liaise with strategic partners on tactical campaigns to drive new customers and work with tenants on driving special offers and value-added services to shoppers.\nDevelop detail tactics and ensure excellent execution of marketing programs that generate traffic, stimulate shopper spending to maximize tenant turnover growth and support retail portfolio strategy.\nEnsure seamless communication with vendors and internal departments (eg. Leasing and Property Management) which drive excellent execution.\nRegularly assess effectiveness of marketing program.\nCarefully keep track on marketing expenses by program and ensure within plan or latest forecast.\nCollect, compile, analyse and share market intelligence on macro-trends, consumer behaviour and activities of competitive shopping malls.\nConstantly looks for innovation in program execution from promotional tactic to new medium and creative approach.\n\nSkills, Qualifications and Experience Requirements\n\nDegree holder with at least 6 years\u2019 marketing and communications experience\nExperience in shopping malls and/or retail marketing would be a definite advantage.\nGood connection with strategic partners, e.g. Banks, online payment platforms.\nProven track record of 3rd party co-op campaigns on driving new database and sales opportunity to the business\nStrong analytical and problem-solving skills, mature, self-motivated and result-oriented\nStrong communication, interpersonal, project management and data analysis skills.\nSelf-initiative, creative and detail-oriented.\nStrong sense of responsibility and eager to learn.\nGood in both written and spoken English and Chinese.\nWilling to work on weekends and public holidays.\n\nAn attractive remuneration package will be offered to the right candidate. Interested parties please press \"Apply now\".\n\nHysan is an equal opportunity employer.\u00a0 All information collected will be kept in strict confidence and used solely for recruitment related purposes within the Hysan Group Companies.\n\nYou may get to know more about us through www.hysan.com.hk", "employment_types": ["Full Time", "Permanent"], "selling_points": ["Develop and implement effective marketing plans", "Degree holder with 6 years relevant experience", "5-day work, 14-day AL, Dental, Double Pay + Bonus"], "locations": ["Causeway Bay"], "categories": ["Marketing / Public Relations", "Marketing - Market Research", "Others", "Digital Marketing"], "post_time": "2022-01-17T07:31:55Z", "salary": {"currency": null, "max": null, "min": null, "period": "monthly", "term": null}, "salary_visible": false, "title_keywords": ["assistant manager,"], "responsibilities": ["management", "marketing plans", "expenses", "quality", "develop", "communication", "project management", "payment", "data analysis", "plan", "forecast", "liaise with", "database", "analyse"], "requirements": {"degrees": ["degree holder"], "majors": ["marketing", "communications"], "languages": ["english", "chinese"], "language_level": ["good"], "hard_skills": ["problem-solving skills", "macro", "analysis", "project management"], "soft_skills": ["efficient", "self-motivated", "interpersonal", "sense of responsibility", "mature", "detail-oriented", "communication", "project management", "eager to learn", "self-initiative", "problem-solving skills", "creative", "result-oriented"], "languages_combined": [{"language": "english", "language_level": ["good"]}, {"language": "chinese", "language_level": ["good"]}]}, "experience_required": {"duration": ["at least 6 years"], "field": ["marketing", "retail"]}}, {"job_id": "100003009051595", "location_code": "hk", "company": "BallroomBees Limited", "job_title": "Fast growing company looking for a Marketing intern", "description": "Come work at BallroomBees, Hong Kong\u2019s leading Children Dance Program. We are looking to hire an experienced Marketing Intern to help us keep growing. If you're hard-working and dedicated, enthusiastic with excellent communication and design skills, BallroomBees is the place for you.\u00a0\n\nDuties & Responsibilities:\n\nResponsible for marketing related assistance, support, and coordination.\nSupport general administration for classes registration\u00a0\nProvide marketing collateral for classes, events, and media communication \u00a0\nDeliver relevant content and design for social media, website and customer-related communication in English and Chinese, including working with 3rd party providers\nWorking closely with the company\u2019s founder on all external communication\n\n\n\nRequirement:\n\n\u00a0\u00a0\u00a0\u00a0\u00a0\u00a0 Bachelor\u2019s degree holder\n\u00a0\u00a0\u00a0\u00a0\u00a0\u00a0 Excellent communication skills\n\u00a0\u00a0\u00a0\u00a0\u00a0\u00a0 Design experience - Canva or other design software\n\u00a0\u00a0\u00a0\u00a0\u00a0\u00a0 Creative with Good written and verbal communication skills\n\u00a0\u00a0\u00a0\u00a0\u00a0\u00a0 Detail-oriented and highly organized\n\u00a0\u00a0\u00a0\u00a0\u00a0\u00a0 Enthusiastic and a fast learner who takes initiative\n\u00a0\u00a0\u00a0\u00a0\u00a0\u00a0 Knowledge of office applications (inc. Excel and PowerPoint)\n\u00a0\u00a0\u00a0\u00a0\u00a0\u00a0 Willing to work flexible working hours\n\u00a0\u00a0\u00a0\u00a0\u00a0\u00a0 Ability to work in a fast paced and extremely dynamic environment", "employment_types": ["Full Time", "Internship"], "selling_points": [], "locations": ["Central & Western Area"], "categories": ["Marketing / Public Relations", "Digital Marketing"], "post_time": "2022-01-16T13:41:44Z", "salary": {"currency": null, "max": null, "min": null, "period": "monthly", "term": null}, "salary_visible": false, "title_keywords": ["intern"], "responsibilities": ["social media", "website", "design", "communication", "coordination", "administration"], "requirements": {"degrees": ["bachelor", "degree holder"], "majors": [], "languages": [], "language_level": [], "hard_skills": ["excel", "dynamic", "office applications", "powerpoint"], "soft_skills": ["flexible", "organized", "communication skills", "dynamic environment", "detail-oriented", "enthusiastic", "creative", "fast learner", "initiative"], "languages_combined": []}, "experience_required": {"duration": [], "field": ["design"]}}, {"job_id": "100003009052396", "location_code": "hk", "company": "Knight Recruitment Services Limited", "job_title": "Digital Marketing Specialist (HK$28K-$35K x 13m; International Digital Agency; Tsim Sha Tsui)", "description": "Digital Marketing Specialist (HK$28K-$35K x 13m; International Digital Agency; Tsim Sha Tsui)\n\nOur client is a large International Digital Agency, they are currently looking for a\u00a0Digital Marketing Specialist to join their growing team.\n\nKey Responsibilities:\n\nDevelop, optimise and execute digital marketing strategies via social media, instant messengers or any new media platforms etc. to enhance performance of various business divisions\nManage client's online acquisition channels including Instagram, Facebook, LinkedIn, Pinterest, Twitter and YouTube etc.\u00a0\nPrepare media plan, budget summary and execute advertisement campaign with reports\nFamiliarity and know-how on web site development techniques, Content Management Systems (CMS), server responses, end-users\u2019 experience and conversion optimization.\nUtilize all functionalities of implementation tools, which include Google Analytics, Google Adwords, Google Keyword Tool, Keyword ranking tools, SEOmoz tools, Link Research Tools, Webmaster tools etc.\nLiaise with regional SEO/SEM teams, clients and search engines representatives to provide effective solution. \u2022Assist team manager on SEO elements implementation, both semantic and technical level.\n\nRequirements:\n\nUniversity graduate in Digital Marketing, Marketing, Communication or Business related disciplines\n4 years relevant work experience; digital experience in luxury/FMCG field preferred\u00a0\nSolid knowledge of website and marketing analytics tools (e.g. google analytics,\u00a0Google AdWords, Facebook ad manager etc.)\nCreative, flexible, and sensitive to marketing trend\u00a0\nGood analytical skill in resolving problems and multi-tasking\u00a0\nStrong on team work with proactive and collaborative manner\nFluent in both spoken and written English and Chinese (Cantonese/Mandarin)\n\nFor more information, please send your resume complete with cover letter to: yuki.wan@ knightrecruits.com\n\nData collected will be used for recruitment purposes only. Personal data provided by job applicants will be used strictly in accordance with the Personal Data (Privacy) Ordinance. We regret that only the shortlisted candidates will be notified.", "employment_types": ["Full Time", "Permanent"], "selling_points": ["HK$28K-$35K x 13month", "International Digital Agency", "Tsim Sha Tsui, 5 Day"], "locations": ["Tsim Sha Tsui"], "categories": ["Media & Advertising", "Strategic Planning", "Marketing / Public Relations", "Marketing - Direct Marketing", "Digital Marketing"], "post_time": "2022-01-17T02:56:59Z", "salary": {"currency": null, "max": null, "min": null, "period": "monthly", "term": null}, "salary_visible": false, "title_keywords": ["digital marketing specialist"], "responsibilities": ["social media", "management", "digital marketing strategies", "seo", "budget", "systems", "implementation", "teams", "develop", "reports", "plan", "sem", "liaise with", "facebook"], "requirements": {"degrees": ["university graduate"], "majors": ["business", "related disciplines", "marketing", "digital marketing"], "languages": ["cantonese", "english", "chinese", "mandarin"], "language_level": ["fluent"], "hard_skills": ["analytics tools", "google analytics", "analytical skill", "adwords", "facebook"], "soft_skills": ["flexible", "analytical skill", "proactive", "collaborative", "communication", "sensitive to", "multi-tasking", "creative"], "languages_combined": [{"language": "cantonese", "language_level": []}, {"language": "english", "language_level": ["fluent"]}, {"language": "chinese", "language_level": ["fluent"]}, {"language": "mandarin", "language_level": []}]}, "experience_required": {"duration": ["4 years"], "field": ["digital", "fmcg"]}}, {"job_id": "100003009053615", "location_code": "hk", "company": "Fujitsu Hong Kong Limited", "job_title": "Marketing Officer / Senior Marketing Officer", "description": "The Marketing Officer / Senior Marketing Officer direct reports to our Marketing Manager and performs corporate communication and Go-To-Market execution.\nResponsibilities:\n\nThis role will serve 50% corporate communications and 50% Go-To-Market execution\n\u00a050% corporate communications\nAct as contact window to work with region marketing supporting programs and convey corporate messages into local programs\nExecute corporate programs such as virtual summit, flagship event, offsite tour, NPS survey, etc.\nDevelop a thorough understanding of the company direction and strategies into overarching messages\nAssist senior executive in business plan development, executive pitch, speech crafting, storytelling down to ppt creation, etc.\nProvide editorial support in marketing materials such as solution brief, customer stories, digital marketing content, etc.\nBe the brand assets owner and oversee deliverables to ensure brand consistency and coherent messaging\nManage company website content and update by working with global content management unit\n50% Go-To-Market execution\nSupport Marketing Manager to manage and control program funding with expense report\nAssist sales, solution owners and business units to develop programs and demand generation activities such as webinar, customer workshops, solution demo from ideation to execution\nMonitor and prepare activities report, track result and conversion with continuous review and improvement\nManage and guide marketing agency to produce promotion materials and deliverables as needed to ensure effective execution and quality output\nDevelop theme, content with creativity across multiple platforms from F2F to digital\nMonitor market sentiments and update management team and key stakeholders regularly\nSupport Marketing Manager to prepare monthly dashboard and ad-hoc tasks as requested\nRequirements:\n\nDegree in Marketing, Communications or Business Administration\n3-5 years of experience in technology/telecom/B2B marketing\nStrong critical thinking and business mind with good writing skills\nKnowledge in graphic design, hands-on skills in AI/Premiere is an advantage\nAble to work independently and courageous to work with senior executive and express opinions\nInterest in technology, curious in digital world\nPassionate in personal achievement and pursue in quality\nHigh job ownership, detail-minded, dynamic and outgoing\nA good team player with good communication and\u00a0interpersonal skills\nProficient in PC including MS Word, Excel, PowerPoint\nGood communications in English, Mandarin is advantageous\nImmediate available is preferred\nWhat we offer:\n\nA Working Environment with Flexibility and Joy\nWFH and Flexible Working Hours Policy\nFlexible Benefits Program\nTax Effective Program\nCompensation Leave for SH falls on Saturday\nDental and Medical Insurance (including dependents)\nApplication Method:\nAttractive remuneration package will be offered to the right candidate.\u00a0 Please send full resume in Word format with expected salary for application\u00a0via 'Apply Now' Button below or WhatsApp 68995510.\u00a0 Only shortlisted candidates will be contacted.\u00a0 All information provided will be treated in strict confidence and used only for recruitment purposes.", "employment_types": ["Permanent"], "selling_points": [], "locations": ["Kowloon Bay"], "categories": ["Marketing / Public Relations", "Marketing - Marketing Communication", "Digital Marketing"], "post_time": "2022-01-17T07:14:32Z", "salary": {"currency": null, "max": null, "min": null, "period": "monthly", "term": null}, "salary_visible": false, "title_keywords": ["senior marketing officer", "marketing officer"], "responsibilities": ["marketing materials", "management team", "management", "control", "ad-hoc tasks", "review", "monitor", "quality", "develop", "digital marketing", "contact", "business plan", "brand consistency", "company website", "report"], "requirements": {"degrees": ["degree"], "majors": ["marketing", "business administration", "communications"], "languages": ["english", "mandarin"], "language_level": ["good"], "hard_skills": ["excel", "ai", "premiere", "writing skills", "powerpoint", "dynamic", "pc", "ms word"], "soft_skills": ["passionate", "detail-minded", "work independently", "outgoing", "good team player", "writing skills", "hands-on", "dynamic", "communication and interpersonal skills"], "languages_combined": [{"language": "english", "language_level": ["good"]}, {"language": "mandarin", "language_level": ["good"]}]}, "experience_required": {"duration": ["3-5 years"], "field": ["marketing"]}}, {"job_id": "100003009054686", "location_code": "hk", "company": "505 United Limited", "job_title": "Account Executive (E-commerce & Sports Project)", "description": "Job Responsibilities:\n-\u00a0 E-commerce platform daily operation and handling.\u00a0Write, edit and proof-read all copy for e-commerce platform, marketing communication material. Handle new product launch & other ad-hoc projects assignment;\u00a0\n-\u00a0 Sports project planning, coordinating, executing on various marketing campaigns, including events, video production, advertising, public relation and social media.\u00a0To develop and implement marketing activities & prepare presentation materials\n-\u00a0 Social media on\u00a0exploring, researching and creating shareable content in different formats e.g. articles, graphics, videos...etc in social media platforms. Monitor and analyse the performance of marketing campaigns and provide regular report\n-\u00a0 To forge positive relationship with clients.\u00a0To develop and implement growth opportunity in existing and new clients, strong customer development and negotiation skills\n\nRequirements:\n-\u00a0 Sports Lovers,\u00a0self-motivated, proactive and hands-on approach\n-\u00a0 Degree holder or above, proficiency in sports knowledge\n-\u00a0 2 years exp in in PR agency / event / account service experience.\u00a0 More experience will be considered as Senior Account Executive (\u00a0Fresh Graduates are welcome to apply )\n-\u00a0 Creative mindset and familiar with social media and experience in research / media / digital agency is an advantage\n-\u00a0 Attentive to details and able to\u00a0prioritise multiple assignments ; Able to work under pressure & towards deadline\n-\u00a0 A Team Player with\u00a0verbal and written\u00a0communications skills, work within a team and be able to communicate with staff at all levels\n-\u00a0 Proficiency in computer skills such as PowerPoint, Excel, Chinese Word Processing, Photoshop and AI.\u00a0 Photo and Video editing skill is a plus\n-\u00a0 Irregular shift will be required", "employment_types": ["Full Time", "Permanent"], "selling_points": ["E-commerce project for Global famous fashion brand", "Sports Lovers are preferable", "Project,Event & PR work with famous football team"], "locations": ["Mong Kok"], "categories": ["Marketing / Public Relations", "Public Relations - Event Management", "Digital Marketing", "E-commerce", "Marketing - Brand / Product Management"], "post_time": "2022-01-17T10:33:42Z", "salary": {"currency": null, "max": null, "min": null, "period": "monthly", "term": null}, "salary_visible": false, "title_keywords": ["account executive"], "responsibilities": ["graphics", "social media", "project planning", "ad-hoc projects", "advertising", "video production", "social media platforms", "daily operation", "monitor", "develop", "communication", "executing", "marketing campaigns", "report", "e-commerce platform", "analyse"], "requirements": {"degrees": ["degree holder"], "majors": [], "languages": ["chinese"], "language_level": ["proficiency"], "hard_skills": ["excel", "plus", "chinese word processing", "ai", "powerpoint", "video editing", "computer skills", "photoshop"], "soft_skills": ["self-motivated", "attentive to details", "creative mindset", "prioritise", "hands-on", "team player", "proactive", "work under pressure"], "languages_combined": [{"language": "chinese", "language_level": ["proficiency"]}]}, "experience_required": {"duration": ["2 years"], "field": ["social media", "pr", "research", "agency", "digital", "media"]}}, {"job_id": "100003009053053", "location_code": "hk", "company": "\u8a69\u7433\u63a7\u80a1\u96c6\u5718\u6709\u9650\u516c\u53f8", "job_title": "Senior Marketing Executive (5 days work)", "description": "Responsibilities:\n\nResponsibilities the online marketing activities and website contents to capture profitable growth;\nFormulate and implement customized annual promotion plan, ensure to meet the business target and maximize the brand image exposure within the budget;\nPlan and develop the loyalty program, marketing campaigns, CRM initiatives to optimize profitability;\nMonitor business results and campaigns effectiveness;\nKeep track the market trend and competitors promotional and marketing programs/ activities;\u00a0 \u00a0 \u00a0 \u00a0\nPerform ad hoc assignments.\n\nRequirements:\n\n\nBachelor Degree in Marketing or related disciplines;\nMinimum 3 years experience in Beauty centre / reatil is an advantage;\nA good team player with strong communication and interpersonal skills;\nAttention in details with analytical and presentation skills;\nEnergetic, proactive, creative with a good sense in beauty;\nGood command in spoken and written English, Cantonese and Mandarin;\nCandidates with less experience will be considered as Marketing Executive;\nImmediately available is highly preferred\u00a0\n\nWorking Location: Lai Chi Kok\n\nWe offer 5-day work and a competitive\u00a0salary and benefits\u00a0package\u00a0for the right candidate. To apply online please click the 'Apply' button below with your resume, current & expected salary, and availability to us.\n\nPersonal data collected will be treated in strict confidence and be used for recruitment purposes only.", "employment_types": ["Full Time"], "selling_points": ["Experience in beauty industry is an advantage", "Dynamic environment", "Immediate available is preferred"], "locations": ["Lai Chi Kok"], "categories": ["Marketing / Public Relations", "Marketing - Direct Marketing", "Marketing - General / Support", "Digital Marketing"], "post_time": "2022-01-17T05:24:57Z", "salary": {"currency": null, "max": null, "min": null, "period": "monthly", "term": null}, "salary_visible": false, "title_keywords": ["senior marketing executive"], "responsibilities": ["budget", "monitor", "website", "develop", "ad hoc assignments", "plan", "contents", "marketing campaigns"], "requirements": {"degrees": ["degree", "bachelor"], "majors": ["related disciplines", "marketing"], "languages": ["cantonese", "english", "mandarin"], "language_level": ["good command"], "hard_skills": [], "soft_skills": ["good team player", "proactive", "creative", "presentation skills", "communication and interpersonal skills", "energetic"], "languages_combined": [{"language": "cantonese", "language_level": ["good command"]}, {"language": "english", "language_level": ["good command"]}, {"language": "mandarin", "language_level": ["good command"]}]}, "experience_required": {"duration": ["minimum 3 years"], "field": ["marketing", "beauty"]}}, {"job_id": "100003009054798", "location_code": "hk", "company": "New iMedia Solutions Limited", "job_title": "Sr. Account Executive / Account Manager / Senior Account Manager", "description": "To become a digital expertise in our Company, you will enjoy our attractive benefits:\n\nCompetitive remuneration package\nPerformance Bonus\nMedical Insurance\n5-day work per week\nFlexi-working hour\nGeneral Holiday, Annual Leave, Family Care Leave and Anniversary Leave\nCasual wear in office\nFriendly working environment\nThe Job\n\n\nTo sell and market a full range of digital advertising solutions to advertisers/ad agencies;\nCandidates with more China digital marketing background will focus on China marketing solutions, like WeChat, Weibo and Xiaohungshu;\nTo develop a comprehensive media plan, from concept to execution, on multiple digital platforms to meet clients\u2019 business needs;\nTo develop and deliver presentations and proposals to target clients;\nTo identify and recruit new business opportunities;\nTo achieve and exceed sales targets;\n\nThe Person\n\n\nTertiary education in any discipline with 1-2+ years\u2019 work experience;\nKnowledge in Digital Marketing Solution will be an advantage;\nAnalytical sense and detailed oriented;\nStrong initiative, aggressive, result-oriented and willing to take challenges;\nGood telephone manner with positive attitude and customer-oriented;\nGood command of both written and spoken English and Chinese;\nResult oriented, self-motivated individual who is confident and competitive with a strong passion on digital marketing;\nCandidates with more experience in online media will be considered as \u201cAccount Manager or Senior Account Manager\u201d\nPlease send your application with full resume stating your present and expected salary to the Company by clicking on the \"Apply now\". Please also quote the reference number of the applied position in the subject field.", "employment_types": ["Full Time"], "selling_points": ["Attractive performance-based commission", "Prospective career path in digital mktg", "Good interpersonal skill, hard-working"], "locations": ["Kwun Tong"], "categories": ["Media & Advertising", "Account Servicing", "Sales, CS & Business Devpt", "Business Development", "Marketing / Public Relations", "Digital Marketing"], "post_time": "2022-01-17T16:21:09Z", "salary": {"currency": null, "max": null, "min": null, "period": "monthly", "term": null}, "salary_visible": false, "title_keywords": ["senior account manager", "account executive", "account manager"], "responsibilities": [], "requirements": {"degrees": [], "majors": [], "languages": [], "language_level": [], "hard_skills": [], "soft_skills": [], "languages_combined": []}, "experience_required": {"duration": [], "field": []}}, {"job_id": "100003009051275", "location_code": "hk", "company": "Keep With Faith Company", "job_title": "Digital Marketing Executive", "description": "Job Descriptions\n\nManage social media platforms to increase customer engagement and arouse potential customers\u2019 interest\nExecute campaigns and advertisements on marketing platforms such as Google, FB, and IG, and develop strategies to optimize Sales content\nWork closely hand in hand with Sales Department\nProvide sales and administrative support\nAchieve higher levels of business goals to enable your advancement.\n\nBenefits\u00a0\n\nCompetitive remuneration package\nYoung and energetic working environment\nCareer advancement programme sponsorship\nClear career path and fast-track promotion\nMedical benefits and training allowances\n\nRequirements\n\nHigh Diploma or above\nExperience in marketing/sales\nProactive with positive mindset, excellent interpersonal & communication skill\nSolid Management skills is an absolute advantage\nWilling to learn and face challenges\nGood command of written and spoken English and Chinese", "employment_types": ["Full Time", "Permanent"], "selling_points": ["Handle customers enquires", "Manage social media channel feedback and data supp", "Clear career path with attractive bonus"], "locations": ["Not Specified"], "categories": ["Marketing / Public Relations", "Marketing - Direct Marketing", "Others", "Student / Fresh Graduate / No Experience", "Digital Marketing"], "post_time": "2022-01-15T07:02:55Z", "salary": {"currency": null, "max": null, "min": null, "period": "monthly", "term": null}, "salary_visible": false, "title_keywords": ["digital marketing executive"], "responsibilities": ["business goals", "develop strategies", "administrative support", "advertisements", "social media platforms"], "requirements": {"degrees": [], "majors": [], "languages": [], "language_level": [], "hard_skills": [], "soft_skills": [], "languages_combined": []}, "experience_required": {"duration": [], "field": []}}, {"job_id": "100003009054473", "location_code": "hk", "company": "Radica Systems Limited", "job_title": "Business Development Manager/ Senior Business Development Manager", "description": "RADICA was founded in 2000, headquartered in Hong Kong with 2 regional offices at Guangzhou and Shanghai. We develop eMarketing Communication automation solution to support our clients ranging from international luxury brands, Fortune 500 to the publicly listed companies. We focus on growing the value of their customer database by making wise use of data analytics in direct marketing. Over 300 enterprises are using our database marketing platform to deliver millions of Digital Communications to their customers every day.\u00a0\n\n\nJOB SUMMARY:\nThe priority of Business Development Manager\u00a0/ Senior BDM is to assist the Company to acquire new customers; this role is a crucial one for Radica\u2019s business with the ambition to expand or the necessity to diversify its clientele.\u00a0\u00a0\n\n\n\nWHAT YOU'LL DO:\u00a0\u00a0\n\n\u00a0 Work towards weekly and monthly sales targets and KPI\u2019s\n\u00a0 Generate new business leads and follow up on sales opportunities\n\u00a0 Arrange meetings with clients and carry out product demonstrations\n\u00a0 Follow up swiftly on sales inquiries and prepare sales proposal\n\u00a0 Maintain fruitful relationships with clients and address their needs effectively\n\u00a0 Attend industry events and work closely with other teams to develop new business\nWHAT QUALIFICATIONS YOU NEED TO GET:\u00a0\u00a0 \u00a0 \u00a0\n\n\u00a0 University Graduate or above,\n\u00a0 Minimum 3 years of experience in marketing agency/ IT vendor.\u00a0\n\u00a0 Candidates with more experience will be considered for the position of Senior Business Development Manager\n\u00a0 Proven sales track record of bringing in new business and a natural ability to drive sales\n\nWHAT ARE REQUIRED:\u00a0 \u00a0 \u00a0 \u00a0\n\n\u00a0\u00a0Ability to develop good relationships with current and potential clients\n\u00a0\u00a0Excellent teamwork and communication skills\n\u00a0\u00a0Excellent interpersonal skills, with a positive can-do attitude\n\u00a0\u00a0Fluent in Cantonese, English and Mandarin\n\nWHAT YOU WILL LOVE ABOUT US:\n\n\n\nGreat Company Culture.\u00a0Dynamic working environment. Rich gathering and team building\n23 Days Paid Leave\nFlexible working hours. Free snack bar and drinks in office\nEntitle Medical Insurance,\u00a0Health Check-up/ Dental allowance\u00a0\nEntitle training subsidy.\u00a0Take the class, be equipped, get reimbursed\u00a0\n\n~~~~ \u00a0 Data makes our life more meaningful ~~~~\n\n\u00a0Data held by the company relating to employment applications will be kept confidential and used only for processing applications. Applications who are not contacted within 1 month may consider their applications unsuccessful.\n\nAll personal data of unsuccessful applicants will be retained for a maximum period of two years and may refer suitable applicants to other vacancies within the company.", "employment_types": ["Full Time", "Permanent"], "selling_points": ["Competitive Commission Scheme", "Flexible Working Hours and Dynamic Culture", "New Headcount with 23 days Paid Leave"], "locations": ["Lai Chi Kok"], "categories": ["Sales, CS & Business Devpt", "Business Development", "Account Servicing", "Marketing / Public Relations", "Digital Marketing"], "post_time": "2022-01-17T09:42:33Z", "salary": {"currency": null, "max": null, "min": null, "period": "monthly", "term": null}, "salary_visible": false, "title_keywords": ["senior business development manager", "business development manager"], "responsibilities": ["develop new business", "data", "prepare sales", "teams", "develop", "communication", "maintain", "database", "drive sales", "personal data", "insurance", "arrange meetings"], "requirements": {"degrees": ["university graduate or above"], "majors": [], "languages": ["cantonese", "english", "mandarin"], "language_level": ["fluent"], "hard_skills": ["data analytics", "vendor", "dynamic", "focus", "processing"], "soft_skills": ["flexible", "communication skills", "can-do attitude", "teamwork", "communication", "dynamic", "interpersonal skills", "focus", "positive"], "languages_combined": [{"language": "cantonese", "language_level": ["fluent"]}, {"language": "english", "language_level": ["fluent"]}, {"language": "mandarin", "language_level": ["fluent"]}]}, "experience_required": {"duration": ["minimum 3 years"], "field": ["agency", "marketing", "it", "business development"]}}, {"job_id": "100003009056140", "location_code": "hk", "company": "PMQ Management Company Limited", "job_title": "E-commerce Manager / Senior Executive (Contract)", "description": "Responsibilities\n\nFormulate, lead and drive business strategies on digital marketing plan and campaign\nAnalyze market trends, traffic and performance with recommendations to maximize business opportunities and growth\nOffer customized training to facilitate organizations' digital transformation journey and digital up-skilling needs\nWork closely with Tenancy and Business Development Team to enhance services and customer experience\nPerforming other related duties as assigned\n\nRequirements\n\nDegree holder in Business Administration, Marketing or related discipline\nMinimum 5 years of relevant working experience in e-commerce/digital marketing, including at least 3 years in managerial position\nProven experience in use of different social media and online sales platforms\nStrong analytical, communication and interpersonal skills\nA good command of written and spoken English and Chinese\nCandidates with less experience will be considered as Senior Executive\n\nInterested parties please visit our website ( http://www.pmq.org.hk/career ) and send the application to HR Department on or before 7 February 2022. Application\u00a0without\u00a0current and expected salary will not be considered.\n\nPMQ Management Co. Ltd. is an equal opportunity employer and welcome applications from all qualified candidates. Personal data collected will be treated in strictest confidence and for recruitment related purpose only. If we have not contacted you within six weeks of the above date, please consider your application is unsuccessful at this time. All personal data of unsuccessful applicants will be destroyed within six months.", "employment_types": ["Part Time", "Contract"], "selling_points": [], "locations": ["Central"], "categories": ["Marketing / Public Relations", "Digital Marketing"], "post_time": "2022-01-18T03:22:51Z", "salary": {"currency": null, "max": null, "min": null, "period": "monthly", "term": null}, "salary_visible": false, "title_keywords": ["senior executive", "manager"], "responsibilities": ["business opportunities", "digital marketing", "plan"], "requirements": {"degrees": ["degree holder"], "majors": ["marketing", "business administration"], "languages": ["english", "chinese"], "language_level": ["good command"], "hard_skills": ["e-commerce"], "soft_skills": ["communication and interpersonal skills"], "languages_combined": [{"language": "english", "language_level": ["good command"]}, {"language": "chinese", "language_level": ["good command"]}]}, "experience_required": {"duration": ["at least 3 years", "minimum 5 years"], "field": ["online sales", "managerial", "social media", "e-commerce", "relevant working experience", "digital marketing"]}}, {"job_id": "100003009055835", "location_code": "hk", "company": "Ambitious People Group", "job_title": "Business Development Manager (Digital Marketing))", "description": "Business Development Manager (Digital Marketing)\n\nWhat are you going to do as a Business Development Manager?\n\nAs a business development manager, you would be responsible to pitch new clients, provide consultative advice, analyze the business needs, develop strategic solutions and the media plans.\n\nWhat is offered to you as a Business Development Manager?\n\n* Young, energetic, flexible & international workplace\n* Comprehensive medical insurance\n* Competitive base salary + commission\n\nWhat is expected of you?\n\n* 2-5 years digital marketing solutions selling experience\n* Cantonese Native Speaker, Excellent communication skills in English & Mandarin\n* Bachelor's Degree in any discipline\n\nWhere are you going to work?\n\nYou are going to work in an international marketing consultancy with teams. This is a perfect opportunity for young and energetic candidates with a strong sales-driven mind B2B selling experience. If you are interested, apply now. For more information, contact us at cristy.ngan@ambitiouspeople.com", "employment_types": ["Full Time", "Permanent"], "selling_points": ["Digital Marketing", "Business Development", "Account Servicing"], "locations": ["Not Specified"], "categories": ["Sales, CS & Business Devpt", "Business Development", "Marketing / Public Relations", "Marketing - Marketing Communication", "Digital Marketing"], "post_time": "2022-01-18T02:59:48Z", "salary": {"currency": "HKD", "max": 29999, "min": 25000, "period": "monthly", "term": null}, "salary_visible": true, "title_keywords": ["business development manager", "digital marketing"], "responsibilities": ["teams", "develop", "communication", "digital marketing", "contact", "plans", "insurance"], "requirements": {"degrees": ["degree", "bachelor"], "majors": [], "languages": ["cantonese", "english", "mandarin"], "language_level": ["native", "excellent"], "hard_skills": [], "soft_skills": ["flexible", "communication skills", "responsible", "comprehensive", "energetic", "driven"], "languages_combined": [{"language": "cantonese", "language_level": ["native", "excellent"]}, {"language": "english", "language_level": ["native", "excellent"]}, {"language": "mandarin", "language_level": ["native", "excellent"]}]}, "experience_required": {"duration": ["2-5 years"], "field": ["digital marketing"]}}, {"job_id": "100003009055390", "location_code": "hk", "company": "Yew Chung College of Early Childhood Education Limited", "job_title": "Manager (Institutional Advancement and Marketing)", "description": "Position Summary\n\nThe main tasks for the appointee are:\n\nTo assist the Unit Head in driving the overall marketing and communications strategies;\nTo plan the integrated marketing campaigns including events, advertising, digital marketing, school and community outreach, public relations etc to elevate the image of the College and boost student admission;\nTo lead the implementation of the marketing activities and work with different internal or external parties to achieve the goals;\nTo oversee the design and production of advertising and promotional materials, promotional videos/films and digital contents;\nTo generate reports and evaluate the effectiveness of the promotion efforts;\nTo conduct regular research and studies to identify market opportunities and collect feedback from stakeholders;\nTo monitor and lead a small team of marketing and communication;\nTo take up other tasks as assigned by the College\n\nRequirements\n\nApplicants should meet the following requirements:\n\nA Bachelor\u2019s degree in Marketing/Journalism or related discipline\nAt least 5 years of marketing experience in the tertiary education sector or with sales and customer servicing sector. Previous working experience from education sector is preferable.\nExcellent command of English and Chinese (Cantonese and Mandarin)\nExcellent interpersonal and communication skills to interact with different stakeholders and external parties\nA good sense of responsibility and self-motivation\nAble to handle tasks independently with minimum supervision\nAble to adopt a positive attitude to the team\u2019s objectives and maintain collaborative work relationship with team members\nExperience in managing social media platforms and web content is an advantage\nExperience in managing a small team\u00a0\n\nSalary and Fringe Benefits:\n\nInitial appointment will normally be made on a renewable 24-month contract.\n\nRemuneration is competitive and will be based on qualifications and relevant experience. The College offers group medical insurance, staff development support, annual leave and sick leave, and Mandatory Provident Fund to eligible appointee(s).\n\nApplication Procedure:\n\nApplicants are invited to:\n\nSubmit an application letter with a full Curriculum Vitae, and copies of all graduate transcripts, and the names and contact details of three references.\nSpecify in the application letter current/latest salary and expected salary\nSend applications to the Yew Chung College of Early Childhood Education by \"Apply Now\".\nThe College will review applications immediately and applications will be accepted until the posts are filled.\u00a0 Only shortlisted candidates will be contacted.\n\nImportant notes to Applicants:\n\nAppointees will have to undergo a medical examination.\u00a0 Reimbursement of costs subject to a ceiling is applicable.\nLocal applicants will have to undergo a Sexual Conviction Record Check / Overseas applicants will have to present a police report before appointment can be confirmed.\u00a0\n\nThe College also reserves the right to make an appointment by invitation.\n\nPersonal data collected will be used for recruitment-related purposes only.", "employment_types": ["Full Time", "Contract"], "selling_points": ["Marketing and Communications Manager", "Experience in education sector is preferable", "Working location in Aberdeen"], "locations": ["Aberdeen"], "categories": ["Marketing / Public Relations", "Marketing - Brand / Product Management", "Marketing - Marketing Communication", "Digital Marketing"], "post_time": "2022-01-18T02:26:22Z", "salary": {"currency": null, "max": null, "min": null, "period": "monthly", "term": null}, "salary_visible": false, "title_keywords": ["manager"], "responsibilities": ["social media platforms", "maintain"], "requirements": {"degrees": ["degree", "bachelor"], "majors": ["journalism", "marketing"], "languages": ["cantonese", "english", "chinese", "mandarin"], "language_level": ["excellent"], "hard_skills": [], "soft_skills": ["communication skills", "self-motivation", "interpersonal", "sense of responsibility"], "languages_combined": [{"language": "cantonese", "language_level": ["excellent"]}, {"language": "english", "language_level": ["excellent"]}, {"language": "chinese", "language_level": ["excellent"]}, {"language": "mandarin", "language_level": ["excellent"]}]}, "experience_required": {"duration": ["at least 5 years"], "field": ["marketing", "education"]}}, {"job_id": "100003009055171", "location_code": "hk", "company": "NP Solution Limited", "job_title": "Digital Marketing Manager - Hong Kong Listed Company", "description": "Company Profile\nOur client is a well-established Hong Kong Listed Company with multiple businesses across the globe. They are now looking for a Digital Marketing Manager to join their team to cope with the digital advancement.\u00a0\n\n\nJob Responsibilities\n\nPlan and execute marketing content and campaigns, including social media content, copywriting, website ecommerce and app campaigns\nDevelop digital marketing strategies and on brand campaigns to drive revenue\u00a0\nFormulate\u00a0online strategy for build branding and marketing planning\nResponsible for reporting, analytics, dashboards and provide insights for improving digital key metrics\nLiaise with external agencies to optimize go-to-market strategy and sustain growth for across regions\n\nRequirements\n\nBachelor\u2019s Degree in Marketing, Business Management or related fields\nAt least 3-year of relevant experience, especially in Digital Marketing\nPractical experience Google Analytics and comfortable with data visualization tool such as PowerBI\nMotivated self-starter and good project management skill\nProficiency in both spoken and written English and Chinese\n\n\n\n\nAll information provided will be treated in strict confidence and used solely for recruitment purpose.\n\nFor more job opportunities, please visit our website:\u00a0https://npsl.com.hk/\n\n\n\n", "employment_types": ["Full Time"], "selling_points": ["Hong Kong Listed Company", "Dynamic Working Environment", "Competitive Package | Work Life Balance"], "locations": ["Not Specified"], "categories": ["Marketing / Public Relations", "Management", "Marketing - Marketing Communication", "Digital Marketing"], "post_time": "2022-01-18T01:37:11Z", "salary": {"currency": null, "max": null, "min": null, "period": "monthly", "term": null}, "salary_visible": false, "title_keywords": ["digital marketing manager"], "responsibilities": ["reporting", "provide insights", "digital marketing strategies", "website", "develop", "social media content", "plan", "liaise with", "planning"], "requirements": {"degrees": ["degree", "bachelor"], "majors": ["business", "marketing"], "languages": ["english", "chinese"], "language_level": ["proficiency"], "hard_skills": ["business management", "google analytics", "project management", "data visualization"], "soft_skills": ["motivated", "confidence", "project management skill"], "languages_combined": [{"language": "english", "language_level": ["proficiency"]}, {"language": "chinese", "language_level": ["proficiency"]}]}, "experience_required": {"duration": ["at least 3-year"], "field": ["relevant experience", "digital marketing"]}}, {"job_id": "100003009054560", "location_code": "hk", "company": "SampsonStore.com Limited", "job_title": "Video Content Specialist (FMCG - sexual wellness products)", "description": "Do you have a passion in this interesting business arena and to liberate the general view on sexual wellness products? Yet to face the challenge in teasing customers on condoms, personal lubricants and even adult toys in the modern retail trade outlets? A bigger challenge yet, we will work it on a global scale, working in markets including at least Hong Kong, Taiwan, Singapore and the UK. The successful candidate will join our team to develop and enhance our market-focused in the emerging sexual wellness products.\n\nDuties\n\nMarket sexual wellness items - condoms, lubricants and adult toys.\nSpeak on camera to create compelling and engaging videos used for brand-building and social media campaigns.\nResponsible for planning the shoot, shooting, editing, and distributing video via company websites and social media platforms.\nCommunicate with internal teams to combine knowledge into video content and ensure videos meet brand standards/guidelines before being published.\nSuggest and implement YouTube/Podcast channel collaborations to build and reinforce brand image.\nTransform content outlines into intriguing stories and write concise and engaging scripts.\nWork on Hong Kong, Taiwan, Singapore and the UK markets. Regular travelling is required.\nWork with suppliers from Japan, Germany, Malaysia, US and China.\nPerform any ad-hoc duties as required.\n\nRequirements\n\nMust be a Hong Kong resident.\nGood command of English and Putonghua.\nAbility to be comfortable and confident in front of cameras.\nAdvanced knowledge of Adobe Premiere Pro.\nGood working knowledge of After Effects, color grading, and Audition.\nExcellent verbal Cantonese storytelling and communication skills. Fluent in Mandarin or English is a plus.\nExperience in executing multi-camera shoots.\nGood organizational and detail-oriented skills to ensure the quality of deliverables and timely completion.\nExperience with SEO\u00a0is an advantage.\nCreative and thinking out-of-the-box, yet with strong execution ability.\n\nOur working environment\n\nSmall team, close relationship.\nFlexible working hours.\nWork only with the best talent in town. Only sharp applicants with a passion in mind will be invited for an interview.\nWork only for the result, non-commission based, We share success with a year-end performance bonus.\n\nPlease send your CV, expected annual package, your portfolio,\u00a0and the answer of \"What month of the year has 28 days?\"\u00a0for application.", "employment_types": ["Full Time"], "selling_points": ["Sexual wellness products: Sagami, Tenga, Sampson", "Video production from A to Z", "Responsible for HK, TW, SG and UK markets"], "locations": ["Lai Chi Kok"], "categories": ["Design", "Multi-media", "Media & Advertising", "Photography / Video", "Marketing / Public Relations", "Digital Marketing"], "post_time": "2022-01-17T09:59:19Z", "salary": {"currency": null, "max": null, "min": null, "period": "monthly", "term": null}, "salary_visible": false, "title_keywords": ["specialist"], "responsibilities": ["company websites", "communicate with", "social media campaigns", "guidelines", "social media platforms", "teams", "ad-hoc duties", "editing", "planning"], "requirements": {"degrees": [], "majors": [], "languages": ["cantonese", "putonghua", "english", "mandarin"], "language_level": ["excellent", "good command", "fluent"], "hard_skills": ["small", "plus", "seo", "adobe premiere pro", "after effects"], "soft_skills": ["confident", "communication skills", "flexible", "advanced", "passion in", "organizational", "timely", "detail-oriented", "creative"], "languages_combined": [{"language": "cantonese", "language_level": ["excellent"]}, {"language": "putonghua", "language_level": ["good command"]}, {"language": "english", "language_level": ["good command", "fluent"]}, {"language": "mandarin", "language_level": ["fluent"]}]}, "experience_required": {"duration": [], "field": []}}, {"job_id": "100003009055828", "location_code": "hk", "company": "Michael Page", "job_title": "Digital Marketing Manager - FMCG Global Marketing", "description": "Our client is a well-regarded FMCG Brand. They are currently expanding their global business and seeking for a Digital Marketing Manager to join their global marketing team.\n\nClient Details\n\nOur client is a well-regarded FMCG Brand. They are currently expanding their global business and seeking for a Digital Marketing Manager to join their global marketing team. The position is the team leader to plan and implement global digital marketing campaigns and work closely with global team to develop digital marketing frameworks.\n\nDescription\n\nOur client is a well-regarded FMCG Brand. They are currently expanding their global business and seeking for a Digital Marketing Manager to join their global marketing team. The position is the team leader to plan and implement global digital marketing campaigns and work closely with global team to develop digital marketing frameworks.\n\nProfile\n\nThe successful candidate would be an experienced marketing manager for multinational company. Candidate with FMCG, Health and Beauty or pharmaceutical portfolio will be considered first. Our client is looking for a creative and brand thinking person with outstanding leadership skill to join them as a team leader. Public speaking and presentation ability are highly valued to this role. Fluency in English and Cantonese is required. Degree level qualification in marketing, business studies, or other related subjects is preferred.\n\nJob Offer\n\nWork for a global company that provides you with opportunity to expand your career. You will be provided with an attractive salary package and compensation.\n\nTo apply online please click the 'Apply' button below. For a confidential discussion about this role please contact Smania Wu on +852 3412 4858.", "employment_types": ["Full Time", "Permanent"], "selling_points": ["Digital Marketing", "Global Exposure", "Career Growth Opportunities"], "locations": ["Not Specified"], "categories": ["Marketing / Public Relations", "Management", "Marketing - Marketing Communication", "Digital Marketing"], "post_time": "2022-01-18T02:59:27Z", "salary": {"currency": null, "max": null, "min": null, "period": "monthly", "term": null}, "salary_visible": false, "title_keywords": ["digital marketing manager"], "responsibilities": ["digital marketing campaigns", "develop", "digital marketing", "contact", "plan"], "requirements": {"degrees": ["degree"], "majors": ["business", "marketing"], "languages": ["cantonese", "english"], "language_level": ["fluency"], "hard_skills": [], "soft_skills": ["leadership skill", "creative", "presentation"], "languages_combined": [{"language": "cantonese", "language_level": ["fluency"]}, {"language": "english", "language_level": ["fluency"]}]}, "experience_required": {"duration": [], "field": []}}, {"job_id": "100003009055627", "location_code": "hk", "company": "Links International", "job_title": "Marketing Assistant (one year contract)", "description": "Our client is one of the Fortune 500 members and they are currently looking for a contract Marketing Assistant to join their team.\n\nResponsibilities\n\n\nProduce regular reports on redemption, fraud, third party loyalty program and so on\nCoordinate among different stakeholders, including team members, vendors, partners to assist loyalty operation\nCollaborate with Customer Service team to deal with customer complaints\nSupport online project UAT\nExamine payment reports from retailers and payment vendors\nDeal with payment disputes cases\n\nRequirements\n\n\nBachelor degree holder in Marketing, Business or other related disciplines\n1-2 years related working experiences\nMS and digital savvy\nGreat communication skills in both written and verbal Chinese and English\nDetail-oriented, organized and independent team player who can multi-task", "employment_types": ["Full Time", "Permanent"], "selling_points": ["Fortune 500 companies", "Jan-Dec 2022", "Subject to renew"], "locations": ["Not Specified"], "categories": ["Marketing / Public Relations", "Digital Marketing"], "post_time": "2022-01-18T02:48:41Z", "salary": {"currency": null, "max": null, "min": null, "period": "monthly", "term": null}, "salary_visible": false, "title_keywords": ["marketing assistant"], "responsibilities": ["collaborate with", "uat", "customer complaints", "coordinate", "payment", "customer service", "reports", "third party"], "requirements": {"degrees": ["bachelor degree holder"], "majors": ["business", "related disciplines", "marketing"], "languages": ["english", "chinese"], "language_level": [], "hard_skills": [], "soft_skills": ["organized", "communication skills", "independent", "multi-task", "detail-oriented", "team player"], "languages_combined": [{"language": "english", "language_level": []}, {"language": "chinese", "language_level": []}]}, "experience_required": {"duration": ["1-2 years"], "field": ["related"]}}, {"job_id": "100003009050051", "location_code": "hk", "company": "Kingmaker Limited", "job_title": "Digital Marketing Specialist", "description": "About Peeba\n\nPeeba is a wholesale marketplace that makes discovering and buying wholesale from exciting brands from around the world easy and risk-free. We\u2019re backed by multiple prominent venture capital funds in the world and we are seeking an analytical and responsible Digital Marketing Specialist to join our growing organization.\u00a0\n\nSince our product launch in June 2020, we have partnered up with over 1,300 unique brands with over 50,000 products to bring them into Asian retail stores, and developed machine learning algorithms to connect retailers with brands that we guarantee will sell.\u00a0\n\nDiscover an exciting career opportunity at a rapidly growing rocket ship startup that will give you the environment and the freedom to excel. Join us on our mission to become the intelligent operating system that powers the future of commerce, and transform the way local retailers buy for their stores.\u00a0About this role\n\nAs a Digital Marketing Specialist, you will be collaborating closely with marketing, design and sales teams to bring Peeba\u2019s long term vision to life.\n\nWhat you\u2019ll do\n\nManage the company\u2019s social media channels such as Facebook and Instagram on a daily basis\n\nFormulate and execute effective digital and social media marketing strategies and actionable plan for achieving business objectives and goals\n\nTrack, analyze, report and optimize the digital marketing matrix and performance on a regular basis\n\nBuild and own organic and paid growth strategy, from concept to completion\n\nClosely monitor digital, social and e-marketing campaigns to generate traffic, engagement and conversion\n\nQualifications\n\n\n\n\n3+ years\u2019 experience in digital marketing, and/or growth marketing, performance marketing\n\nHands-on Experience with social media, Facebook Ad Manager, Google Analytics, SEO, Google Adwords, email campaigns and other analytic tools\n\nCommunity management on Facebook, Instagram, Linkedin\n\nStrong written and verbal communication skills with the ability to compile and present cohesive reports with clear action items and insights\n\nProject management skills with the ability to work independently and cross-collaboratively in a fast-paced environment\n\nStatistical approach in data-driven decision making\n\nEnergetic, pro-active, and self-motivated\u00a0\n\nBachelor Degree or equivalent\n\nExperience in working at a high-growth startup is a plus\n\nImmediate available or short notice period preferred", "employment_types": ["Full Time"], "selling_points": ["Digital Maketing", "Hyper growth startup environment", "Excellent development opportunities"], "locations": ["Kwun Tong"], "categories": ["Marketing / Public Relations", "Digital Marketing"], "post_time": "2022-01-14T09:41:36Z", "salary": {"currency": null, "max": null, "min": null, "period": "monthly", "term": null}, "salary_visible": false, "title_keywords": ["digital marketing specialist"], "responsibilities": ["social media", "management", "marketing strategies", "seo", "data", "teams", "monitor", "design", "communication", "project management", "digital marketing", "reports", "plan", "marketing campaigns", "facebook", "report"], "requirements": {"degrees": ["degree", "bachelor"], "majors": [], "languages": [], "language_level": [], "hard_skills": ["excel", "google analytics", "plus", "seo", "adwords", "project management", "facebook", "venture capital"], "soft_skills": ["communication skills", "work independently", "self-motivated", "responsible", "fast-paced environment", "project management skills", "unique", "cohesive", "clear", "hands-on", "learning", "pro-active", "energetic", "driven", "decision making"], "languages_combined": []}, "experience_required": {"duration": ["3+ years"], "field": ["social media", "marketing", "digital marketing"]}}, {"job_id": "100003009056416", "location_code": "hk", "company": "Quality People Resources Limited", "job_title": "Part-time Marketing Assistant (Internship)", "description": "The Role\n\nReporting to Head of Marketing, this exciting role sits within the Marketing Department at SEEK Asia. The primary focus of the role is to be responsible for taking ownership and initiative in jobseeker and/or employer engagement strategies planning and implementation. This position plays an integral part in the success of our team\u2019s long-term vision, and represents a brand-new opportunity. We are looking for someone with a proven ability to adapt to a changing environment, and be a change champion, with the role evolving over time, as we progress through our technological & operational transformation.\n\nKey Responsibilities:\n\n\u00b7 Assist to launching and optimizing jobseeker and employer marketing campaigns.\n\n\u00b7 Assist to compile presentation decks and reports on campaign design, data tracking, and deliver other miscellaneous marketing tasks, including but not limited to ongoing acquisition, loyalty and engagement tasks.\n\n\u00b7 Effective Chinese and English copywriting skills to develop both online/ offline collaterals, and sale kits.\n\n\u00b7 As owner of CRM automation daily operations, work with brand owners to deliver regular and ad-hoc eDM and other automated communication to members.\n\n\u00b7 With creative mindset, business acumen and strong consumer centric insights, work with content team and agency to fine tuning social and articles content that engage users and convert business results.\n\n\u00b7 Able to work with sale team, regional and cross-functional teams.\n\n\u00b7 With knowledge of effective multi-channel strategies & tools for brands, such as CRM, eDM, Social, Partnership, Mobile etc to drive online traffic, jobseeker/ employer engagement and conversions.\n\nQualifications\nSo, what we are looking for?\n\nThe successful candidate will have:\n\n\u00b7 University degree holder.\n\n\u00b7 Minimum 2 years' experience preferably in e-commence, internet media or advertising agency, CRM related areas (Salesforce experience is highly preferred) and/or analytics, with a proven track record in driving brand awareness, considerations and conversions through effective strategy.\n\n\u00b7 You are a true believer of quality and always looking for opportunities to sharpen your marketing planning and analysis skills. With your high commercial acumen, you hope to deliver great value of business partnering support to both internal and external stakeholders.\n\n\u00b7 You are deeply passionate about technology and eager to learn new things.\n\n\u00b7 You are an extraordinary team player. You are responsible, supportive and collaborative. You say \u201cwe\u201d more than \u201cI\u201d. While engaging in discussions, you actively listen and bring valuable thoughts or opinions to the table when the \u201cEureka\u201d moment strikes!\n\n\u00b7 To you, the thought of bringing productivity to the next level sparks joy. You are someone who constantly puts on different thinking hats to find ways in improving existing processes, automating mundane tasks and shaping practices for the better.", "employment_types": ["Full Time", "Part Time", "Permanent", "Temporary", "Contract", "Internship", "Freelance"], "selling_points": [], "locations": ["Yau Ma Tei"], "categories": ["Admin & HR", "HR Supporting Staff", "Marketing / Public Relations", "Marketing - Direct Marketing", "Digital Marketing"], "post_time": "2022-01-18T04:14:16Z", "salary": {"currency": "HKD", "max": 369, "min": 240, "period": "hourly", "term": null}, "salary_visible": true, "title_keywords": ["marketing assistant", "internship"], "responsibilities": ["ad-hoc", "reporting", "tracking", "advertising", "data", "edm", "analysis", "quality", "implementation", "design", "develop", "communication", "daily operations", "reports", "marketing campaigns", "cross-functional teams", "planning"], "requirements": {"degrees": ["university degree"], "majors": [], "languages": ["english", "chinese"], "language_level": [], "hard_skills": ["hope", "salesforce", "analysis", "mobile", "focus", "joy", "acumen"], "soft_skills": ["supportive", "responsible", "creative mindset", "collaborative", "communication", "eager to learn", "team player", "consumer centric", "business acumen", "focus", "initiative", "presentation", "passionate about"], "languages_combined": [{"language": "english", "language_level": []}, {"language": "chinese", "language_level": []}]}, "experience_required": {"duration": ["minimum 2 years"], "field": ["related", "brand", "media", "advertising agency"]}}, {"job_id": "100003009051844", "location_code": "hk", "company": "Stylevana", "job_title": "eCommerce Assistant / Executive - Fashion & Beauty", "description": "Responsibilities:\n\n\nTo manage digital marketing platforms to drive traffic and conversion\nTo promote company product and services to potential customer through B2B phone calls\nTo coordinate with innovative team for marketing events and campaigns and assist in copy-writing\nTo handle inquiries from customer via email, phone, WhatsApp\nTo assist in ad hoc projects as assigned\n\n\n\nRequirements:\n\n\nMinimum to work 1.5 days per week\nDSE / higher diploma / degree holders are all welcomed\nExperience in PR / Marketing / Telesales would be a privilege\nGood command in written and spoken English and Cantonese\nResponsible and detail-minded\n\n\n\nInterested parties, please submit your application by clicking \u201cApply Now\u201d or through \"Joboffer\" app;\nOr simply WhatsApp 92886650 (https://wa.me/message/M24M4MRDAA34E1).", "employment_types": ["Full Time", "Permanent"], "selling_points": ["eCom - Asian Fashion & Beauty", "daily eCom operations & monitor mkting channels", "5-day work, Double Pay, friendly team"], "locations": ["Kwai Hing"], "categories": ["Marketing / Public Relations", "Digital Marketing", "E-commerce", "Business Development", "Marketing - Brand / Product Management"], "post_time": "2022-01-17T01:20:54Z", "salary": {"currency": null, "max": null, "min": null, "period": "monthly", "term": null}, "salary_visible": false, "title_keywords": ["executive", "assistant"], "responsibilities": ["marketing events", "coordinate with", "ad hoc projects", "digital marketing", "phone calls"], "requirements": {"degrees": ["diploma", "degree", "dse"], "majors": [], "languages": ["cantonese", "english"], "language_level": ["good command"], "hard_skills": [], "soft_skills": ["detail-minded", "responsible"], "languages_combined": [{"language": "cantonese", "language_level": ["good command"]}, {"language": "english", "language_level": ["good command"]}]}, "experience_required": {"duration": [], "field": ["pr", "marketing", "telesales"]}}, {"job_id": "100003009049287", "location_code": "hk", "company": "SEEK Asia (JobsDB)", "job_title": "Senior Marketing Executive (1 year contract)", "description": "Join us & Be eCommerce Innovators\nAre you looking to be part of revolutionizing online shopping behaviour and experience? We are a well-esteemed eCommerce company that operates multiple eCommerce websites internationally. We are now looking for potential talent to help us expand our new beauty and fashion business worldwide and to build brand awareness and sales revenue.\n\nKey Job Responsibilities:\u00a0\n\nResponsible for daily eCommerce operations include managing website, banner update, promotion rules update, website content update etc.\nResponsible for update reporting on weekly basis to monitor sales performance of marketing channels and program, including newsletter, affiliate marketing, CRM etc.\nEnsure website efficient operation and consumer experience on website content in good UX basis\nAssist other ad hoc projects and operations of website and other online activities in eCommerce backend system\nAssist in website enhancements and resolving any website issues on timely basis\nWork closely with different function units including eCommerce Business, Digital Marketing and Merchandizing to ensure smooth consumer experiences on website\nPerform other duties as assigned by Supervisor and Manager\u00a0\n\n\u00a0Desired Skills and Experience:\u00a0\n\nDiploma or above in Marketing/ Business/ eCommerce or related disciplines\nExperience in any eCommerce backend system is an advantage\nWell-organized, detailed minded and able to manage multiple tasks\nAble to work independently and under pressure, as well as cooperate well with team and stakeholders to achieve company goals\nExcellent command of written and spoken English, Cantonese\nFresh graduate is welcome\n\nWe offer a friendly team environment, good career prospect. We also offer attractive remuneration package including discretionary bonus incentive. We also offer other benefits such as five-day work week, flexible working hours, double pay, medical and dental insurance. Interested parties please send full resume with available date, present and expected salary to our email or clicking \u201cApply Now\u201d for an interview.\n\nAll personal data collected will be used for recruitment purpose only.\u00a0", "employment_types": ["Full Time", "Contract"], "selling_points": ["Our motto: Improving Lives through Better Careers", "Company Values: We Care, We Aim High, We Deliver", "Customized Career Development Opportunities"], "locations": ["Quarry Bay"], "categories": ["Marketing / Public Relations", "Marketing - General / Support", "Marketing - Marketing Communication", "Digital Marketing"], "post_time": "2022-01-14T08:22:57Z", "salary": {"currency": null, "max": null, "min": null, "period": "monthly", "term": null}, "salary_visible": false, "title_keywords": ["senior marketing executive"], "responsibilities": ["reporting", "perform other duties", "operations", "sales performance", "monitor", "website", "ad hoc projects", "operations of website", "digital marketing"], "requirements": {"degrees": ["fresh graduate", "diploma or above"], "majors": ["business", "related disciplines", "ecommerce", "marketing"], "languages": ["cantonese", "english"], "language_level": ["excellent"], "hard_skills": ["merchandizing"], "soft_skills": ["efficient", "work independently", "under pressure", "responsible", "multiple tasks", "timely", "well-organized", "smooth", "detailed"], "languages_combined": [{"language": "cantonese", "language_level": ["excellent"]}, {"language": "english", "language_level": ["excellent"]}]}, "experience_required": {"duration": [], "field": ["ecommerce", "operation", "digital marketing", "business"]}}, {"job_id": "100003009049943", "location_code": "hk", "company": "Hina Technology Co., Limited", "job_title": "Digital Executive /Specialist", "description": "Job Responsibilities:\n\nThis role will serve one of the regional clients in HiNA. This regional client is a listed company group, which also holds a leading role in the industry. Client is currently operating in Hong Kong, Singapore, Malaysia and other countries in SEA market. This role will have opportunities to work in both branding and performance campaigns in web and app, which provides extensive exposure in different media channels.\n\nWork in a team to plan cross-channel paid media campaigns.\nManage digital campaigns across different paid media channels such as Google Ads, Facebook Ads and Apple Search Ads.\nMonitor and analyze campaign performance and derive insights for optimization.\nPrepare performance review presentations and reports.\nCommunicate and deliver findings to client with actionable recommendations to clients.\nWork with Account Manager to provide professional advice.\nServe as one of the main contacts of client support and contribute to the development of media strategies.\n\nJob Requirements:\n\nUniversity degree in business, marketing, advertising, communications, or a related field.\n1-3 years of hands-on experience in digital channels as SEM and Google Ads. Agency background is preferred.\nRelevant certifications of Google Ads.\nWell organized and have strong quantitative/analytical skills.\nEffective communication and problem-solving skills.\nWilling to work in start-up environment.\nPassionate in Digital Marketing.\nFluent in English and Cantonese.\nProficiency in Word, Excel and PowerPoint.\n\nWe offer 5 days work and attractive compensation package to suitable candidates. Interested parties, please send your full resume including your present & expected salary\u00a0", "employment_types": ["Full Time", "Permanent"], "selling_points": ["Expert in Google Ads and performance channels", "Meal, traffic and communication allowance", "Great Exposure and Career Development"], "locations": ["Causeway Bay"], "categories": ["Media & Advertising", "Account Servicing", "Sales, CS & Business Devpt", "Account Servicing", "Marketing / Public Relations", "Digital Marketing"], "post_time": "2022-01-15T19:11:39Z", "salary": {"currency": null, "max": null, "min": null, "period": "monthly", "term": null}, "salary_visible": false, "title_keywords": ["specialist", "digital executive"], "responsibilities": ["review", "monitor", "presentations", "media channels", "reports", "digital campaigns", "plan", "facebook"], "requirements": {"degrees": ["university degree"], "majors": ["business", "communications", "marketing"], "languages": ["cantonese", "english"], "language_level": ["fluent"], "hard_skills": ["excel", "word", "powerpoint", "analytical skills", "sem", "problem-solving skills"], "soft_skills": ["passionate", "well organized", "analytical skills", "communication", "hands-on", "problem-solving skills"], "languages_combined": [{"language": "cantonese", "language_level": ["fluent"]}, {"language": "english", "language_level": ["fluent"]}]}, "experience_required": {"duration": ["1-3 years"], "field": ["digital"]}}, {"job_id": "100003009055892", "location_code": "hk", "company": "Michael Page", "job_title": "APAC Marketing Manager - Luxury Retailer", "description": "Our client is a luxury retailer with worldwide presence. They are currently growing their global business and they are looking for an APAC Marketing Manager to join their dynamic team.\n\nClient Details\n\nOur client is a luxury retailer with worldwide presence. They are currently growing their global business and they are looking for an APAC Marketing Manager to join their dynamic team.\n\nDescription\n\nOur client is a luxury watches brand with worldwide presence. They are currently growing their global business and they are looking for an APAC Marketing Manager to join their dynamic team. The position is the key driver to develop marketing strategy and campaign, work closely with external parties and internal global PR team.\n\nProfile\n\nThe successful candidate would be an experienced marketing manager from luxury industry (brands or retailers) or other e-commerce platforms. Candidate with luxury goods portfolio will be considered first. Our client is looking for someone who has strong presentation skills and hands on experience of marketing plan implementation. Fluency in English and Cantonese is required. Degree level qualification in marketing, media studies, or other related subjects is preferred.\n\nJob Offer\n\nWork for a global company that provides you with opportunity to expand your career. You will be provided with an attractive salary package and compensation.\n\nTo apply online please click the 'Apply' button below. For a confidential discussion about this role please contact Smania Wu on +852 3412 4858.", "employment_types": ["Full Time", "Permanent"], "selling_points": ["Luxury Retailer", "Regional Exposure", "International Working Environment"], "locations": ["Not Specified"], "categories": ["Marketing / Public Relations", "Marketing - Brand / Product Management", "Marketing - Marketing Communication", "Digital Marketing"], "post_time": "2022-01-18T03:03:28Z", "salary": {"currency": null, "max": null, "min": null, "period": "monthly", "term": null}, "salary_visible": false, "title_keywords": ["marketing manager"], "responsibilities": ["external parties", "e-commerce platforms", "implementation", "develop", "marketing plan", "contact"], "requirements": {"degrees": ["degree"], "majors": ["marketing"], "languages": ["cantonese", "english"], "language_level": ["fluency"], "hard_skills": ["dynamic", "e-commerce", "luxury industry"], "soft_skills": ["presentation skills", "dynamic", "hands on"], "languages_combined": [{"language": "cantonese", "language_level": ["fluency"]}, {"language": "english", "language_level": ["fluency"]}]}, "experience_required": {"duration": [], "field": ["marketing"]}}, {"job_id": "100003009055561", "location_code": "hk", "company": "Chandler Macleod Group (HK) Limited", "job_title": "Senior/ Marketing Executive (Financial Services)", "description": "Responsibilities:\n\n\n\n\nResponsible for all marketing related issue, not limited to liaising and coordinating with external parties for the preparation and delivery of marketing communication materials, marketing events or other related marketing activities\nDesign and execute production and publication of marketing collaterals (e.g. brochure, face sheet, website, video, presentations) from sketch\nManage all the marketing & public relations activities including e-marketing, seminars organization and other award and sponsorship programs\nMaintain on-going content and platform maintenance of company website, campaign minisite and social media platforms\nAssist Marketing Manager to drive and implement strategic PR campaigns for brand positioning and enhancing brand image and awareness\nAssist in any ad-hoc tasks or duties as requested\n\nRequirements:\n\n\n\n\nDegree holder in marketing/communications or business-related discipline\nMinimum 1 years of relevant working experience, preferably in professional services provider/financial services\nKnowledge of SEO, social media (Linkedln, Wechat etc) and analytics reporting\nGood project management skills, with attention to detail and quality\nStrong customer and results oriented, with ability to interact effectively at all levels with sensitivity\nSelf-starter and able to prioritize workloads effectively, able to work independently as well as be a team player\nProficient with MS office, Excel and PowerPoint\nGood command of both spoken and written Chinese and English", "employment_types": ["Full Time", "Permanent"], "selling_points": ["Multinational Working Environment", "Genuine Development Opportunity", "A Growing Business"], "locations": ["Not Specified"], "categories": ["Marketing / Public Relations", "Marketing - Direct Marketing", "Marketing - General / Support", "Digital Marketing"], "post_time": "2022-01-18T02:43:21Z", "salary": {"currency": null, "max": null, "min": null, "period": "monthly", "term": null}, "salary_visible": false, "title_keywords": ["marketing executive"], "responsibilities": ["marketing events", "maintenance", "ad-hoc tasks", "external parties", "marketing collaterals", "website", "design", "presentations", "communication", "social media platforms", "maintain", "company website", "publication"], "requirements": {"degrees": ["degree holder"], "majors": ["business", "marketing", "communications"], "languages": ["english", "chinese"], "language_level": ["good command"], "hard_skills": ["excel", "seo", "powerpoint", "wechat", "project management", "ms office"], "soft_skills": ["work independently", "able to prioritize", "project management skills", "sensitivity", "attention to detail", "team player"], "languages_combined": [{"language": "english", "language_level": ["good command"]}, {"language": "chinese", "language_level": ["good command"]}]}, "experience_required": {"duration": ["minimum 1 years"], "field": ["financial services", "relevant working experience"]}}, {"job_id": "100003009052852", "location_code": "hk", "company": "Global Technology Integrator Ltd", "job_title": "E-commerce Executive", "description": "Accountabilities \u2013 Key Result Areas\n\nHandle and manage the daily operations of the company\u2019s E-Commerce platform including but not limited to preparing eDM, content management, product listing, pricing, promotion, inventory update, customer service and order related issues\nDrive sales, define and implement online sales strategy and traffic optimization\nWork closely with various internal and external parties, including agency, marketing, graphic designers, system development team etc\nLiaise with internal and external parties for regular promotions\n\nExperience / Qualification Requirements\n\nDegree in Marketing or related disciplines\n2 years or above relevant experience in E-Commerce\nMicrosoft Office, Good knowledge of website analytics tools, e.g. Google Analytics\nGood command of both spoken and written Cantonese and English\nAbility to work in a fast paced environment, multi task and works well under pressure\nYou may visit www.gcr.com.hk for our company details", "employment_types": ["Full Time"], "selling_points": ["Degree in Marketing or related disciplines", "2 years E-commerce experience", "5 days 9:00-5:30"], "locations": ["Ngau Tau Kok"], "categories": ["Marketing / Public Relations", "Digital Marketing", "E-commerce", "Business Development", "Marketing - Brand / Product Management"], "post_time": "2022-01-17T04:16:51Z", "salary": {"currency": null, "max": null, "min": null, "period": "monthly", "term": null}, "salary_visible": false, "title_keywords": ["executive"], "responsibilities": ["analytics tools", "management", "product listing", "edm", "inventory", "internal and external parties", "website", "daily operations", "customer service", "liaise with", "drive sales", "e-commerce platform"], "requirements": {"degrees": ["degree"], "majors": ["related disciplines", "marketing"], "languages": ["cantonese", "english"], "language_level": ["good command"], "hard_skills": ["microsoft office", "analytics tools", "google analytics", "e-commerce"], "soft_skills": ["work in a fast paced environment", "customer service", "under pressure"], "languages_combined": [{"language": "cantonese", "language_level": ["good command"]}, {"language": "english", "language_level": ["good command"]}]}, "experience_required": {"duration": ["2 years"], "field": ["relevant experience", "e-commerce"]}}, {"job_id": "100003009055045", "location_code": "hk", "company": "The Hong Kong Jockey Club", "job_title": "Assistant Public Affairs Manager  Ref : APAM(C)", "description": "The Department\nThe Public Affairs (Corporate and Charities Communications) Department provides a full range of corporate and charities communications functions to the Club including the formulation of communication strategy, issue management, non-racing media relations; corporate and charity information and overall publicity; as well as organisation of PR programmes and projects.\u00a0\nThe Job\nYou will:\nenhance relationship with media and maximise positive publicity of the Club\u2019s strategic charities communications through proactive media pitching, especially with digital media\nsupport the department in planning and implementing public affairs and publicity programmes\norganise press briefings and prepare press materials and related collaterals\nsupport the department in managing issues\nAbout You\nYou should have:\nuniversity degree in a related discipline or relevant qualification equivalent to minimum of 7 years' experience in public affairs\nself motivation, strong communication and social skills\nhigh level of proficiency in written and spoken English and Chinese\nstrong media network and experience in digital and social media an advantage\nTerms of Employment\nThe level of appointment will be commensurate with qualification and experience.\u00a0 A contract employment will be offered to the successful candidate. Contract renewal will be subject to mutual agreement between the Club and the individual.\n\n\nHow to Apply\nPlease send your resume, complete with expected salary and job reference by clicking the Apply Now button or to:\nFax: 2576-1987\nMail: The Human Resources Department, The Hong Kong Jockey Club, 1 Sports Road, Happy Valley, Hong Kong\nWe are an equal opportunity employer. Personal data provided by job applicants will be used strictly in accordance with the Club's notice to employees and prospective employees relating to the Personal Data (Privacy) Ordinance. A copy of which will be provided immediately upon request.", "employment_types": ["Full Time", "Contract"], "selling_points": ["Minimum of 7 years' experience in public affairs", "Self motivation, strong communication", "University degree in a related discipline"], "locations": ["Causeway Bay"], "categories": ["Marketing / Public Relations", "Marketing - Marketing Communication", "Digital Marketing"], "post_time": "2022-01-18T00:51:23Z", "salary": {"currency": null, "max": null, "min": null, "period": null, "term": null}, "salary_visible": false, "title_keywords": ["manager", "assistant"], "responsibilities": ["social media", "management", "communication", "personal data", "planning"], "requirements": {"degrees": ["university degree"], "majors": [], "languages": ["english", "chinese"], "language_level": ["proficiency"], "hard_skills": ["briefings", "charity"], "soft_skills": ["communication", "proactive", "positive", "organisation"], "languages_combined": [{"language": "english", "language_level": ["proficiency"]}, {"language": "chinese", "language_level": ["proficiency"]}]}, "experience_required": {"duration": ["minimum of 7 years"], "field": ["related", "digital", "social media", "media"]}}, {"job_id": "100003009055577", "location_code": "hk", "company": "ConnectedGroup Limited", "job_title": "Senior Digital Marketing Manager (Global B2B)", "description": "Our client is a HK headquartered International Group that is one of the leaders in the risk management solutions field (Testing, Inspection and Certification Services) field. This is a key position in the corporate team with a global scope, reporting directly into the CMO to design and lead all group digital marketing and communication initiatives.\n\nThis role will be responsible for the following,\n\nLook after group digital marketing and communication initiatives with global coverage\nManage the brand P&L from budget management, digital marketing (website maintenance, social media) to marketing program execution and overall marketing communications\nLead and implement overall digital marketing strategy and business development of brand to ensure long term growth and sustainable customer value\nAnalyse competitive landscape including pricing, product positioning, communications, etc. to support go-to-market approach and support new product development\n\nSuccessful calibre shall possess,\n\nBachelor degree with at least 8 years of solid working experience, of which at least 5 years of corporate branding and digital marketing experience within B2B industries is mandatory\nOver 3 years' consumer marketing experience within sizable global consumers product companies\nMust have prior global experience working in Europe and/or the US\nStrong understanding and experience in Asia and Hong Kong\nExperienced in conducting market studies and analytics; familiar in dealing with multiple internal and external stakeholders including marketing agencies and press\nExcellent dedication to work with can-do attitude; strategic yet hands-on\nHighly agile, open-minded, able to perform under stress and enjoy working in a fast-paced and multicultural environment with limited resources\nStrong business acumen, excellent communication (listening and verbal), presentation, interpersonal, problem solving, multi-priorities management skills\nNative in English, fluency in French is preferable\n\nInterested individuals can click apply now and send updated resume (in WORD format) to Yumi Cheng for further information.\n\nFor a more comprehensive list of current opportunities, please visit www.connectedgroup.com\n\n#StayConnected\n\n#ConnectedGroup", "employment_types": ["Full Time", "Permanent"], "selling_points": ["5+ years B2B digital marketing experience", "Global exp working in Europe/US region", "Strategic,edicated, passionate about B2B business"], "locations": ["Not Specified"], "categories": ["Marketing / Public Relations", "Digital Marketing"], "post_time": "2022-01-18T02:45:12Z", "salary": {"currency": null, "max": null, "min": null, "period": "monthly", "term": null}, "salary_visible": false, "title_keywords": ["senior digital marketing manager"], "responsibilities": ["reporting", "management", "social media", "budget", "website maintenance", "design", "inspection", "testing", "communication", "p&l", "digital marketing", "analyse"], "requirements": {"degrees": ["degree", "bachelor"], "majors": ["digital marketing"], "languages": ["english", "french"], "language_level": ["fluency", "native"], "hard_skills": ["agile", "maintenance", "word", "problem solving", "budget management", "go", "acumen"], "soft_skills": ["agile", "responsible", "can-do attitude", "open-minded", "enjoy working", "communication", "problem solving", "hands-on", "comprehensive", "business acumen", "interpersonal", "presentation"], "languages_combined": [{"language": "english", "language_level": ["native"]}, {"language": "french", "language_level": ["fluency"]}]}, "experience_required": {"duration": ["at least 8 years", "at least 5 years", "3 years"], "field": ["marketing", "digital marketing"]}}, {"job_id": "100003009044365", "location_code": "hk", "company": "Adaka & Company", "job_title": "Senior Marketing Executive (5 days work)", "description": "Responsibilities\n\nCreate, execute and coordinate marketing program materials, communications, graphics, brand website maintenance, digital/social media strategy and events/exhibitions;\nExecute social media marketing ad strategies on Instagram, Facebook, LinkedIn, Pinterest Twitter and YouTube;\nManage and maintain website content using HTML or other web content management interface;\nPrepare media plan, budget summary and execute advertisement campaign with reports;\nReport on the performance of different paid media platform and provide campaign insights to assess campaign effectiveness and identify optimization opportunities;\nCoordinate with Design, PR and Communications and other functional teams to ensure brand consistency and smoothness operations;\nOther ad hoc tasks as assigned.\n\n\u00a0Requirements\n\nDegree holder in marketing or related disciplines;\u00a0\n3 years or above experiences in digital marketing;\nKnowledge in Google Adwords / Facebook AD manager is an advantage;\nKnowledge of Photoshop or AI is an advantage;\nGood communication in spoken and written English and Chinese and Mandarin;\nImmediate available is preferred.", "employment_types": ["Full Time", "Permanent"], "selling_points": ["5 days work, birthday leave, free goods", "Cosmetic, skin care & hair care products", "Marketing & PR"], "locations": ["Kowloon Bay"], "categories": ["Marketing / Public Relations", "Marketing - Brand / Product Management", "Marketing - Marketing Communication", "Digital Marketing"], "post_time": "2022-01-16T21:50:20Z", "salary": {"currency": null, "max": null, "min": null, "period": "monthly", "term": null}, "salary_visible": false, "title_keywords": ["senior marketing executive"], "responsibilities": ["graphics", "social media", "management", "operations", "budget", "coordinate with", "website maintenance", "website", "design", "coordinate", "teams", "ad hoc tasks", "maintain", "reports", "plan", "facebook", "brand consistency", "report"], "requirements": {"degrees": ["degree holder"], "majors": ["related disciplines", "marketing"], "languages": ["english", "chinese", "mandarin"], "language_level": ["good"], "hard_skills": ["ai", "adwords", "facebook", "photoshop"], "soft_skills": ["communication"], "languages_combined": [{"language": "english", "language_level": ["good"]}, {"language": "chinese", "language_level": ["good"]}, {"language": "mandarin", "language_level": ["good"]}]}, "experience_required": {"duration": ["3 years"], "field": ["digital marketing"]}}, {"job_id": "100003009054279", "location_code": "hk", "company": "Sunny Side Up (Never) Limited", "job_title": "SALES & MARKETING MANAGER", "description": "This position will be reporting to Chief Transformation Officer PR Asia, as part of the Regional Transformation Office that is being setup. It will also have a dotted line reporting to A&P Effectiveness Director in the Global Business Development team.\n\nJob Purpose:\u00a0\nPernod Ricard is reinforcing its Transformation team in the context of the deployment of Key Digital Programs (KDPs) in the Group and by fostering the digital enablement of teams and digital culture within Pernod Ricard. Specifically, to lead the engagement and drive the delivery roadmap of the KDP Matrix, Pernod Ricard Asia is setting up within its Regional Transformation team a Centre of Excellence (COE) for Marketing Effectiveness, and is looking for a Associate Director, Marketing Effectiveness that will play a key role in this endeavour by being part of the Regional Transformation Team, and by collaborating strongly with the Marketing Effectiveness KDP team, and the PR Asia Marketing, Business Development and Finance teams in delivering business objectives.\u00a0\n\nJob Duties and Responsibilities\nYou will be the expert of Marketing Mix Modelling (MMM), supporting the definition of the regional MATRIX deployment roadmap, managed by HQ Transformation and KDP teams. He/she will then be in charge of supporting the markets during the deployment of the KDP managed from HQ.\nPost-deployment, he/she will be responsible, in close coordination with the Region\u2019s Marketing, Business Development and Finance departments for working with markets and challenging them on the construction of our A&P Effectiveness (leveraging MATRIX) and sharing their expertise in MMM to the Pernod Ricard community.\n\nYou \u00a0will coordinate, enable and support MATRIX deployment and value steering across the region:\n\nRecommending markets for deployment.\nDefining, securing and allocating resources.\nMeasure skill level and ensuring upskilling across the organisation\nReviewing local constraints impact.\nDriving the deployment.\nMonitoring value delivery (budget vs. actual).\u00a0\n\nYou will also foster best practices and insights generation by providing cross market expertise. Over the medium term, the objective is to internalize the skills and competences leveraged through external resources, in order to create an in-house Marketing Efficiency COE, able to fully support markets in the Region. \u00a0\n\nAs the Associate Director, Marketing Effectiveness, you will\n1.\u00a0\u00a0 \u00a0Support MATRIX tool deployment in the Region\n\nCo-design regional roadmap with HQ Transformation and KDP teams, supporting assessment of data availability and maturity of marketing efficiency of markets\nProvide early support during deployment on data collection, simulation providing early upskilling\u00a0\n\n2.\u00a0\u00a0 \u00a0Support MATRIX tool adoption and value delivery in market.\n\nEnsure best use of the tool and full coherence of scenarios proposed with context and execution planned.\nSupport model improvement through highest data quality (incl. with specific workarounds). Monitor roll-out of Extract tool through the region.\nEnsure that there is a clear change plan in place during the key handover period from the KDP team to the local market team. \u00a0\n\n3.\u00a0\u00a0 \u00a0Drive marketing effectiveness improvement through formalization & adoption of best practices.\n\nBe a support for internal teams to analyse results and marketing insights after the handover period (from the KDP team to the internal team).\u00a0\nCooperate with Marketing Department to challenge markets investment scenarios recommended plans, identify best practices and roll them out through the region.\n\n4.\u00a0\u00a0 \u00a0Lead upskilling effort & support implementation of new ways of working with external partners, with a view to internalise those partners skills and expertise, within a PR Asia Marketing Effectiveness COE.\n\u00a0\nYour scope including:\u00a0\n\nInternal stakeholders: Markets (NB: Japan, South Korea), HQ Marketing Effectiveness Manager (KDP Manager), PR Asia Marketing, Business Development and Finance departments, KDP Deployment lead, local market PMO, Data teams etc\u2026\nKey External stakeholders: Consulting companies and freelancers supporting MATRIX deployment.\nJob scope: 100% international.\n\nWe are looking for: A candidate who is able to drive change. Has excellent leadership skills with experience collaborating with cross-functional teams. Has the ability and seniority to challenge KDP teams in the development. Pragmatic and capable to solve complex issues. Positive/can do mindset and solution-oriented. Ability to work with cross-cultural teams.\n\nA candidate expertise in marketing efficiency in terms of planning and execution. Marketing Mix Modeling experience a big plus. Understanding of data science / data modelling. Expert in business stakes understanding. Good knowledge of financial methods and tools. Understands data and software. Understands principles of advanced modeling techniques.\n\nYou will have: \u00a0\n\n10+ years professional experience.\nStrong experience in a leading data and insight consulting firm, with strong customer relationship with FMCG clients.\nExperience in FMCG, ideally Food & Beverage with similar type of Marketing activation and Route to Market.\nExperience in a global/regional role, to understand various market specificities and to have the agility to work with multicultural teams.\n50% travel\u00a0\n\n\n\nJob Posting End Date:\n\nTarget Hire Date:\n\n2022-03-15-07:00\n\nTarget End Date:", "employment_types": ["Full Time"], "selling_points": ["Degree holder in marketing", "3 yrs exp. in digital marketing", "Knowledge in Google Adwords/Facebook AD manager"], "locations": ["Kwun Tong"], "categories": ["Marketing / Public Relations", "Marketing - Brand / Product Management", "Marketing - General / Support", "Digital Marketing"], "post_time": "2022-01-17T09:19:05Z", "salary": {"currency": null, "max": null, "min": null, "period": "monthly", "term": null}, "salary_visible": false, "title_keywords": ["sales & marketing manager"], "responsibilities": ["software", "consulting", "data", "coordination with", "budget", "quality", "design", "planning", "plan", "plans", "cooperate with", "teams", "monitor", "implementation", "setup", "reporting", "monitoring", "data collection", "cross-functional teams", "coordinate", "analyse"], "requirements": {"degrees": [], "majors": [], "languages": [], "language_level": [], "hard_skills": ["vs", "plus", "deployment"], "soft_skills": ["capable", "responsible", "advanced", "leadership skills", "clear", "coordination", "organisation", "positive"], "languages_combined": []}, "experience_required": {"duration": ["10+ years"], "field": ["food", "marketing", "consulting", "fmcg"]}}, {"job_id": "100003009055843", "location_code": "hk", "company": "Pernod Ricard Hong Kong Ltd - Regional", "job_title": "Associate Director, Marketing Effectiveness", "description": "Responsibilities:\n\n\n\nTo provide English and Chinese copy writing for a full range of editing, proofreading and translating various marketing collaterals including user manual, brochure, press release, print advertisement, corporate, etc.\nCoordinating, implementing and managing various marketing campaigns including Advertising, PR, Event, Print and Joint Promotion.\nLiaising closely with internal teams including Design, Sales, Promotion and Purchasing, to ensure effective communication and to progress all marketing campaigns at each stage, from information gathering to concepts, from copy writing to production\n\nRequirements:\n\n\n\nDegree Holder in Languages, Communications, Journalism, Marketing or Public Relations\nAt least 2 years' solid experience in writing position Strong interest in social media industry\nPassionate, detailed mind, proactive/ outgoing, self & team motivated and willing to take responsibilities\nCreative, willing to take up challenge", "employment_types": ["Full Time"], "selling_points": ["Regional Transformation team in Pernod Ricard", "Foster digital enablement & digital culture", "FMCG; MNC; Wine & Spirit Industry"], "locations": ["Tsim Sha Tsui"], "categories": ["Accounting", "Consulting", "Marketing / Public Relations", "Marketing - Brand / Product Management", "Digital Marketing"], "post_time": "2022-01-18T03:00:13Z", "salary": {"currency": null, "max": null, "min": null, "period": "monthly", "term": null}, "salary_visible": false, "title_keywords": ["associate director"], "responsibilities": ["advertising", "marketing collaterals", "teams", "design", "communication", "proofreading", "marketing campaigns", "editing"], "requirements": {"degrees": ["degree holder"], "majors": ["journalism", "marketing", "communications"], "languages": [], "language_level": [], "hard_skills": [], "soft_skills": ["passionate", "outgoing", "proactive", "creative", "motivated", "detailed mind"], "languages_combined": []}, "experience_required": {"duration": ["at least 2 years"], "field": ["social media", "writing"]}}, {"job_id": "100003009055562", "location_code": "hk", "company": "Chandler Macleod Group (HK) Limited", "job_title": "Copywriter (Professional Service/ Beauty/ Retail)", "description": "\n\u8077\u8cac :\u8ca0\u8cac\u92b7\u552e\u8ca8\u54c1(\u9bae\u82b1)\n\n\u8cc7\u6b77 :\u4e2d\u4e09\u7a0b\u5ea6; \u826f\u597d\u7cb5\u8a9e\u512a\u5148; \u826f\u597d\u666e\u901a\u8a71\u512a\u5148; \u826f\u597d\u82f1\u8a9e\u512a\u5148; \u61c2\u95b1\u8b80\u4e2d\u6587\n\n\u5f85\u9047 :\u6bcf\u5c0f\u6642$50.00 - $80.00, \u4e0a\u53489\u6642\u81f3\u4e0b\u534811\u6642, \u6bcf\u9031\u5de5\u4f5c5\u5929\u81f36\u5929,\u8f2a\u4f11, \u6bcf\u5929\u5de5\u4f5c 5 - 6 \u5c0f\u6642\n\n\u7533\u8acb\u9808\u77e5 :\u6c42\u8077\u8005\u53ef\u81f4\u96fb56143678\u8207\u570b\u4ed5\u5ee3\u544a\u50b3\u5a92\u6709\u9650\u516c\u53f8\u90ed\u5c0f\u59d0\u806f\u7d61\u3002\n\n", "employment_types": ["Full Time", "Permanent"], "selling_points": ["Multinational Working Environment", "Genuine Development Opportunity", "A Growing Business"], "locations": ["Not Specified"], "categories": ["Marketing / Public Relations", "Marketing - Marketing Communication", "Public Relations - Copy-writing", "Digital Marketing"], "post_time": "2022-01-18T02:43:26Z", "salary": {"currency": null, "max": null, "min": null, "period": "monthly", "term": null}, "salary_visible": false, "title_keywords": ["copywriter"], "responsibilities": [], "requirements": {"degrees": [], "majors": [], "languages": [], "language_level": [], "hard_skills": [], "soft_skills": [], "languages_combined": []}, "experience_required": {"duration": [], "field": []}}, {"job_id": "100003009053798", "location_code": "hk", "company": "IMY Media Limited", "job_title": "\u5e74\u5bb5\u92b7\u552e\u54e1", "description": "\n\u8077\u8cac :\u8ca0\u8cac\u7368\u7acb\u8655\u7406\u96f6\u552e,\u6279\u767c\u9867\u5ba2\u4e4b\u8a02\u55ae,\u5831\u50f9\u53ca\u51fa\u8ca8,\u8ddf\u9032\u9867\u5ba2\u67e5\u8a62,\u5354\u52a9\u63d0\u4f9b\u512a\u8cea\u7684\u7db2\u4e0a\u8cfc\u7269\u9ad4\u9a57,\u96fb\u8166\u8cc7\u6599\u8f38\u5165\n\n\u8cc7\u6b77 :\u4e2d\u4e09\u7a0b\u5ea6; 3\u5e74\u7d93\u9a57; \u4e00\u822c\u7cb5\u8a9e; \u4e00\u822c\u666e\u901a\u8a71; \u4e00\u822c\u82f1\u8a9e; \u61c2\u8b80\u5beb\u4e2d\u6587; \u61c2\u8b80\u5beb\u82f1\u6587; \u61c2\u96fb\u8166\u6587\u66f8\u8655\u7406; \u61c2MS Word; \u61c2MS Excel; \u719f\u6089\u793e\u4ea4\u5e73\u53f0\u7ba1\u7406,\u5177\u7db2\u4e0a\u8cfc\u7269\u5e73\u53f0\u5de5\u4f5c\u7d93\u9a57\u512a\u5148,\u5177\u7db2\u5e97\u92b7\u552e\u53ca\u71df\u904b\u7d93\u9a57\n\n\u5f85\u9047 :\u6bcf\u6708$13,000 - $17,000, \u661f\u671f\u4e00\u81f3\u4e94: \u4e0a\u53489\u6642\u81f3\u4e0b\u53486\u6642, \u6bcf\u9031\u5de5\u4f5c5\u5929\n\n\u7533\u8acb\u9808\u77e5 :\u6c42\u8077\u8005\u53ef\u96fb\u90f5(Apply Now)\u5c65\u6b77\u8868\u7d66\u5fa1\u6bbf\u5802\u85e5\u599d\u6709\u9650\u516c\u53f8\u3002\u5982\u8981\u7d22\u53d6\u6536\u96c6\u500b\u4eba\u8cc7\u6599\u8072\u660e, \u8acb\u8207\u6797\u5148\u751f(Email)\u806f\u7d61\u3002\n\n", "employment_types": ["Part Time"], "selling_points": [], "locations": ["Tin Hau"], "categories": ["Sales, CS & Business Devpt", "Others", "Direct Sales", "Marketing / Public Relations", "Digital Marketing"], "post_time": "2022-01-17T07:32:11Z", "salary": {"currency": null, "max": null, "min": null, "period": "hourly", "term": null}, "salary_visible": false, "title_keywords": [], "responsibilities": [], "requirements": {"degrees": [], "majors": [], "languages": [], "language_level": [], "hard_skills": ["excel", "word"], "soft_skills": [], "languages_combined": []}, "experience_required": {"duration": [], "field": []}}, {"job_id": "100003009053611", "location_code": "hk", "company": "Gotendo Beauty and Healthcare Group Limited", "job_title": "\u7db2\u5e97\u696d\u52d9\u71df\u904b\u4e3b\u4efb", "description": "RADICA was founded in 2000, headquartered in Hong Kong with 2 regional offices at Guangzhou and Shanghai. We develop eMarketing Communication automation solutions to our clients ranging from international luxury brands, Fortune 500 to the publicly listed companies. We focus on growing the value of their customer database by making wise use of data analytics in direct marketing. Over 300 enterprises are using our database marketing platform to deliver millions of Digital Communications to their customers every day.\u00a0\n\n\n\u00a0WHAT YOU'LL DO:\u00a0\u00a0\n\nTo lead a team of account executives and designers, developing content marketing, analyzing multi-channels\u2019 effectiveness, and maximizing clients\u2019 customer lifecycle value, ensure high quality of project deliverables for clients\nTo develop CRM & e-marketing consulting proposals & presentation to clients\nTo plan & design Marketing automation journey with the proposal preparation, implementation planning\u00a0& periodical review\nAchieve client's KPIs through the application of creativity, data insight and applicable marketing technology.\nManage account\u2019 P&L to ensure the delivery is executed on time and on budget\nProactively perform regular eMarketing benchmarking research, monitor digital marketing & CRM trends, develop new service scope is a good plus\nProvide on-the-job training and coaching to team members\n\nWHAT QUALIFICATIONS YOU NEED TO GET:\u00a0 \u00a0 \u00a0\u00a0\n\n\u00a0Degree in Business Administration, Marketing or related disciplines\n\u00a0Minimum 7 years of experience in digital marketing, data analysis and project management\nHands-on experience & proven track records in digital and multi-channel e-marketing projects\nStrong knowledge of database management, data analysis, segmentation & marketing automation which drives positive results\nExcellent leadership and people management skills\nStrong business sense, communication & organizational skill\nGood command of both written Chinese and English\nDetail-minded and self-motivated with strong communication, interpersonal and analytical skills\nSometimes travel to China is expected after pandemic\nMore experienced candidate may consider as Account Director\n\nWHAT YOU WILL LOVE ABOUT US:\u00a0\n\nGreat Company Culture. Dynamic working environment\n23 Days Paid Leave\nFlexible working hours. Free snack bar and drinks in office\nEntitle Medical Insurance, Health Check-up/ Dental allowance\nEntitle training subsidy. Take the class, be equipped, get reimbursed\n\n\n\n\n\n~~~~ \u00a0 Data makes our life more meaningful ~~~~\n\nData held by the company relating to employment applications will be kept confidential and used only for processing applications. Applications who are not contacted within 1 month may consider their applications unsuccessful.\n\nAll personal data of unsuccessful applicants will be retained for a maximum period of two years and may refer suitable applicants to other vacancies within the company.", "employment_types": ["Full Time"], "selling_points": [], "locations": ["Kwun Tong"], "categories": ["Beauty Care / Health", "Others", "Sales, CS & Business Devpt", "Retail Sales", "Marketing / Public Relations", "Digital Marketing"], "post_time": "2022-01-17T07:14:35Z", "salary": {"currency": null, "max": null, "min": null, "period": "monthly", "term": null}, "salary_visible": false, "title_keywords": [], "responsibilities": ["consulting", "data", "budget", "quality", "design", "communication", "database", "plan", "personal data", "administration", "monitor", "developing", "implementation", "develop", "p&l", "kpis", "management", "review", "marketing projects", "data analysis", "digital marketing", "project deliverables", "lead a team", "project management", "insurance", "planning"], "requirements": {"degrees": ["degree"], "majors": ["related disciplines", "marketing", "business administration"], "languages": ["english", "chinese"], "language_level": ["good command"], "hard_skills": ["plus", "data analytics", "analysis", "analytical skills", "project management", "dynamic", "focus", "processing"], "soft_skills": ["detail-minded", "flexible", "self-motivated", "organizational skill", "business sense", "analytical skills", "communication", "project management", "hands-on", "dynamic", "focus", "interpersonal", "leadership", "presentation", "positive"], "languages_combined": [{"language": "english", "language_level": ["good command"]}, {"language": "chinese", "language_level": ["good command"]}]}, "experience_required": {"duration": ["minimum 7 years"], "field": ["data analysis", "project management", "marketing", "digital marketing", "digital"]}}, {"job_id": "100003009054474", "location_code": "hk", "company": "Radica Systems Limited", "job_title": "Associate Account Director", "description": "Responsibilities:\n\nExecute graphic design tasks, includes a full range of different collaterals both printed and digital\nLiaise with external parties e.g. printers, agencies, vendors and external designers\nAssist in photo and video shooting and retouch\nConstantly keep an eye on collaterals in shops and restaurants to ensure the appropriateness of content and design, good in quality, initiate replacement where needed\nAssist in English and Chinese translations and copy writing (marketing collaterals and social media)\n\n\n\nRequirements:\n\n\nDiploma / Degree holder in Graphic Design or related disciplines\nMinimum 2-year relevant working experience in Graphic Design, preferably in F&B / restaurant / retail / hospitality industry\nSound technical knowledge in design needs\nSkillful at photography and videography is preferred but not mandatory\nFluent in both spoken and written English, Chinese and Mandarin\nProficient in Photoshop / Illustrator & MS Office applications including Word, Excel, PowerPoint and Chinese Processing\n\nCompetitive remuneration package will be offered to the right candidate. Interested parties please click\u00a0\"Apply Now\"\u00a0or send full resume with expected salary by email to\u00a0 recruitoffice@ fairwood.com.hk\u00a0or 2) direct mail to HR Manager, 2/F TRP Commercial Centre, 18 Tanner Road, North Point, Hong Kong.\n\n(Data collected will be used for recruitment purpose only)", "employment_types": ["Full Time", "Permanent"], "selling_points": ["Expertise in Database Marketing & automation", "Dynamic and flexible working environment", "Team Leader and regional exposure"], "locations": ["Lai Chi Kok"], "categories": ["Media & Advertising", "Account Servicing", "Marketing / Public Relations", "Marketing - Direct Marketing", "Digital Marketing"], "post_time": "2022-01-17T09:42:34Z", "salary": {"currency": null, "max": null, "min": null, "period": "monthly", "term": null}, "salary_visible": false, "title_keywords": ["associate", "account director"], "responsibilities": ["social media", "graphic design", "external parties", "quality", "marketing collaterals", "design", "video shooting", "liaise with"], "requirements": {"degrees": ["diploma", "degree holder"], "majors": ["related disciplines", "graphic design"], "languages": ["english", "chinese", "mandarin"], "language_level": ["proficient", "fluent"], "hard_skills": ["excel", "illustrator", "word", "powerpoint", "photoshop", "processing", "ms office"], "soft_skills": [], "languages_combined": [{"language": "english", "language_level": ["fluent"]}, {"language": "chinese", "language_level": ["proficient", "fluent"]}, {"language": "mandarin", "language_level": ["fluent"]}]}, "experience_required": {"duration": ["minimum 2-year"], "field": ["graphic design", "restaurant", "relevant working experience", "hospitality industry", "f&b", "retail"]}}, {"job_id": "100003009054126", "location_code": "hk", "company": "Fairwood Fast Food Ltd", "job_title": "Graphic Designer, Specialty Restaurant", "description": "REQUIREMENTS\n\nDiploma or above in marketing, communications or related disciplines\n2-3 years relevant experience, preferably in retail or digital marketing\nFamiliar with social media networks with online copywriting experience\nStrong knowledge in Google Ads and Google Analytics\nGood communication and presentation skill in English and Chinese\nProficient PC skills (e.g. MS office, Word, Excel, PowerPoint and Chinese Word Processing)\n\nRESPONSIBILITIES:\n\nResponsible for developing the marketing plan and strategy; compiling and monitoring the annual promotion and marketing budget plan;\n\nAssist the Operation team in formulating in-store marketing and promotional activities to drive sales & traffic;\nAlign with the company strategy and objectives, initiate and implement relevant social media platforms such as Website, Facebook & Instagram, etc;\nWork closely with various parties for planning and executing marketing campaigns, including organizing events, preparing sales materials, advertising and communication tools;\nDevelop monthly report and monitor the sales performance of marketing activities;\nExplore joint promotion opportunity with other parties;\nCarry out ad-hoc tasks as assigned by management.\n\nWe offer competitive package including 5-day work, public holiday & medical scheme together with career growth opportunities. Interested parties, please send full resume and expected salary and recent portfolio to Personnel & Administration Department.", "employment_types": ["Full Time", "Permanent"], "selling_points": ["Collateral design in printed and digital", "English/Chinese translation & copywriting", "Diploma holder with min 2-year relevant experience"], "locations": ["North Point"], "categories": ["Design", "Graphics", "Hospitality / F & B", "Food & Beverage", "Marketing / Public Relations", "Digital Marketing"], "post_time": "2022-01-17T08:29:20Z", "salary": {"currency": null, "max": null, "min": null, "period": "monthly", "term": null}, "salary_visible": false, "title_keywords": ["graphic designer"], "responsibilities": ["budget", "social media platforms", "website", "plan", "monthly report", "facebook", "advertising", "sales performance", "monitor", "developing", "develop", "marketing plan", "marketing campaigns", "management", "monitoring", "promotional activities", "executing", "drive sales", "ad-hoc tasks", "communication tools", "planning"], "requirements": {"degrees": ["diploma or above"], "majors": ["related disciplines", "marketing", "communications"], "languages": ["english", "chinese"], "language_level": ["good"], "hard_skills": ["presentation skill", "google analytics", "excel", "chinese word processing", "word", "powerpoint", "pc skills", "ms office"], "soft_skills": ["communication", "presentation skill"], "languages_combined": [{"language": "english", "language_level": ["good"]}, {"language": "chinese", "language_level": ["good"]}]}, "experience_required": {"duration": ["2-3 years"], "field": ["social media", "relevant experience", "digital marketing", "copywriting", "retail"]}}, {"job_id": "100003009052015", "location_code": "hk", "company": "A-Fontane Company Limited", "job_title": "Assistant Marketing Manager/ Marketing Executive", "description": "Assistant Manager/Senior Officer\u2013 Customer Relationship Management (CRM)\nBased at our Hong Kong headquarters, you will be a team member to interact and work closely with a professional team delegated for the assigned distinguished jewellery brands.\nIf you have the right attitudes and aspirations of develop yourself in luxury retail will receive our investment in your career.\n\u00a0The Job\nCreate and develop\u00a0CRM Strategy and unique customer journey to enable seamless engagement\nImplement membership program to drive sales and enhance customer loyalty through interactive activities and unique experiences\nManage and analyze customer database for formulating, driving and delivering creative CRM events and promotion plans\nStudy and conduct analysis for pre and post campaign, members' behavior and create customer life-cycle recommendation models to drive cross-selling\nCollaborate with internal team & external agency to ensure excellent execution of overall CRM promotion\nImplement and support O2O Strategies to develop customer communications via omni-channels, including shop level, website, mobile App, eDM, SMS as well as internal and external platforms\nThe Person\nDegree holder in Marketing or Communications with minimum 3 years experience in CRM field from luxury industry is a plus\nStrong communications skills with entrepreneurial spirit\nCreative, energetic, dynamic and pro-active\nDetail oriented, analytical and sensitive to numbers\nGood connections with local agencies and vendors\nAttractive remuneration package will be offered to the right candidate. Please email full resume with current and expected salary to us\nPersonal data collected will be used for recruitment purposes only and will be treated in strict confidence.\u00a0 Applicants not invited for interview within 16 weeks may consider their applications unsuccessful and all information submitted will be destroyed.\n\u00a0", "employment_types": ["Full Time"], "selling_points": [], "locations": ["Tsuen Wan Area"], "categories": ["Marketing / Public Relations", "Marketing - Brand / Product Management", "Marketing - Marketing Communication", "Digital Marketing"], "post_time": "2022-01-17T01:50:51Z", "salary": {"currency": null, "max": null, "min": null, "period": "monthly", "term": null}, "salary_visible": false, "title_keywords": ["assistant marketing manager", "marketing executive"], "responsibilities": ["collaborate with", "mobile app", "edm", "analysis", "website", "develop", "plans", "database", "drive sales"], "requirements": {"degrees": ["degree holder"], "majors": ["marketing", "communications"], "languages": [], "language_level": [], "hard_skills": ["plus", "luxury industry", "dynamic"], "soft_skills": ["confidence", "creative", "detail oriented", "dynamic", "pro-active", "sensitive to numbers", "energetic"], "languages_combined": []}, "experience_required": {"duration": ["minimum 3 years"], "field": ["marketing"]}}, {"job_id": "100003009051525", "location_code": "hk", "company": "Ma Belle Jewellery Co Ltd", "job_title": "Assistant Manager/Senior Officer \u2013 Customer Relationship Management (CRM)", "description": "The Job:\n\nWork closely with Products and Solutions Marketing Team to drive the leads of the specific products and solutions\nCoordinate with vendors for the design and production of corporate collaterals, promotional materials and advertisement such as brochure, leaflet, flyer, website, video, social media post etc.\nLiaise with agencies to implement corporate and lead generation events and webinars\nPlan and execute digital marketing campaigns and drip campaigns through the marketing automation platform\nPerform ad-hoc duties as assigned\nThe Person:\n\nBachelor\u2019s Degree in Marketing, Business Administration or related discipline\u3000\nMinimum 4 years of relevant experience in B2B marketing communications, preferably in IT industry\nExperience in Digital Marketing is a must\nSound knowledge in Production, Event Management, Marketing Automation and Digital Analytics is an advantage\u3000\nSelf-motivated, able to work independently and handle multi-tasks\u3000\nExcellent English and Chinese in both written and verbal communications\nWe offer 5-day work, attractive remuneration and benefits package to the right candidate.\n\nInterested parties please forward your full resume (in Microsoft Word or PDF format) with current and expect salary to the\u00a0Human Resources & Facilities Services, Ricoh Hong Kong Limited, by clicking \"Apply Now\".\nInformation provided will be treated in strict confidence and only be used for recruitment related purposes. All personal data of unsuccessful candidates will be destroyed on completion of the recruitment exercise.", "employment_types": ["Full Time", "Permanent"], "selling_points": ["Create & Develop CRM Strategy, Data Analyze", "Plan and Enhance Membership Program", "Customer Recruitment and Re-Activation"], "locations": ["Tin Hau"], "categories": ["Marketing / Public Relations", "Marketing - Brand / Product Management", "Marketing - Marketing Communication", "Digital Marketing"], "post_time": "2022-01-16T08:05:51Z", "salary": {"currency": null, "max": null, "min": null, "period": null, "term": null}, "salary_visible": false, "title_keywords": ["assistant manager", "senior officer"], "responsibilities": ["social media", "digital marketing campaigns", "leaflet", "coordinate with", "website", "design", "promotional materials", "plan", "ad-hoc duties", "liaise with"], "requirements": {"degrees": ["degree", "bachelor"], "majors": ["marketing", "business administration"], "languages": ["english", "chinese"], "language_level": ["excellent"], "hard_skills": [], "soft_skills": ["self-motivated", "work independently", "multi-tasks"], "languages_combined": [{"language": "english", "language_level": ["excellent"]}, {"language": "chinese", "language_level": ["excellent"]}]}, "experience_required": {"duration": ["minimum 4 years"], "field": ["marketing communications", "it", "relevant experience", "digital marketing"]}}, {"job_id": "100003009049815", "location_code": "hk", "company": "SmarTone Telecommunications Limited", "job_title": "Senior Executive, Digital Marketing", "description": "\u7db2\u4e0a\u516c\u53f8\u8aa0\u8058:\u00a0\n\nAdministrative & Marketing Clerk\u884c\u653f\u6587\u54e1(full-time)\n\n\u00a0\u8077\u8cac\uff1a\n\n\u4e00\u822c\u6587\u66f8\u5de5\u4f5c\n\u5354\u52a9\u65e5\u5e38\u904b\u4f5c\uff0c\u63d0\u4f9b\u826f\u597d\u5ba2\u6236\u670d\u52d9\n\u8010\u5fc3\u89e3\u7b54\u67e5\u8a62\n\u5354\u52a9\u5e02\u5834\u71df\u92b7 / \u7db2\u4e0a\u71df\u92b7\n\u00a0\u8077\u4f4d\u8981\u6c42:\n\n\u5927\u5c08\u7a0b\u5ea6\n\u6709\u5ba2\u670d\u7d93\u9a57\u512a\u5148\n\u5e02\u5834\u71df\u92b7\u6216\u7db2\u4e0a\u5ba3\u50b3\u7d93\u9a57\u512a\u5148\n\u719f\u6089\u4e2d\u3001\u82f1\u6587\u96fb\u8166\u64cd\u4f5c (Word, Excel\u53ca\u4e2d\u82f1\u6587\u6253\u5b57)\n\u826f\u597d\u4e2d\u82f1\u6587\u5beb\u4f5c\n2\u5e74\u4ee5\u4e0a\u5de5\u4f5c\u7d93\u9a57\u512a\u5148\n\u57fa\u7763\u5f92\u512a\u5148(\u8acb\u8a3b\u660e)\n\n\u5168\u8077\u5de5\u4f5c\u5730\u5340: \u65b0\u84b2\u5d17\n\n\u6b61\u8fce\u6709\u610f\u61c9\u5fb5\u8005\u4e0a\u8f09CV(\u8a3b\u660e\u671f\u671b\u85aa\u916c)\n\n\n\u6240\u6536\u96c6\u7684\u500b\u4eba\u8cc7\u6599\u7d55\u5c0d\u4fdd\u5bc6\u53ca\u53ea\u4f5c\u62db\u8058\u7528\u9014", "employment_types": ["Full Time", "Permanent"], "selling_points": ["Plan and execute digital marketing campaign", "Manage acquisition related strategy", "5- 6 years\u2019 experience in digital marketing"], "locations": ["Ngau Tau Kok"], "categories": ["Marketing / Public Relations", "Marketing - Brand / Product Management", "Marketing - General / Support", "Digital Marketing"], "post_time": "2022-01-14T09:16:40Z", "salary": {"currency": null, "max": null, "min": null, "period": "monthly", "term": null}, "salary_visible": false, "title_keywords": ["senior executive", "digital marketing"], "responsibilities": [], "requirements": {"degrees": [], "majors": [], "languages": [], "language_level": [], "hard_skills": ["word"], "soft_skills": [], "languages_combined": []}, "experience_required": {"duration": [], "field": []}}, {"job_id": "100003009052170", "location_code": "hk", "company": "Faith Christian Limited", "job_title": "Administrative & Marketing Clerk\u884c\u653f\u6587\u54e1(Full-time)", "description": "\nJob Responsibilities\n\nTake the ownership of the marketing plan development, and create effective promotion strategies to drive interest and new leads in various channel\nManage the tactical execution of marketing campaigns, including sales offer, online/offline communication, digital content creation, video production, etc.\nLead the team to formulate extra sales channel for promotion, including joint promotion, loyalty program, MGM, KOL, etc\nOversee the implementation and budget of digital channel, including SEO/SEM, social media, etc\nUnderstand key marketing performance metrics and tracking tools to provide insights on channel strategies, forecast and competitor analysis\nIdentify the potential area based on CRM and sales analysis, in order to optimize the customer experience on every touchpoint\n\n\u00a0Job Requirement\n\nDegree holder in Business or Marketing or related disciplines\nOver 3 years Digital Marketing experience and proven experience within Social Media\nAt least 3 years work experience in beauty/skincare industry\nFamiliar with Performance Marketing like SEO / SEM, Web Analytics and Facebook ad.\nExperience in building Digital teams, KPI\u2019s processes\nStrong understanding for up-to-date marketing activities across the market\nExcellent planning and project management skills\nCreative, energetic, good interpersonal and communication skills\nExcellent command in English, Cantonese and Mandarin\nCandidate with less experienced will be considered as Assistant Marketing Manager", "employment_types": ["Full Time"], "selling_points": ["San Po Kong", "admin, customer service, digital marketing", "5 days work"], "locations": ["Kowloon City Area"], "categories": ["Admin & HR", "Clerical / Admin Staff", "Sales, CS & Business Devpt", "Customer Service - Supervisor / Officer", "Marketing / Public Relations", "Digital Marketing"], "post_time": "2022-01-17T02:19:52Z", "salary": {"currency": null, "max": null, "min": null, "period": "monthly", "term": null}, "salary_visible": false, "title_keywords": [], "responsibilities": ["social media", "provide insights", "seo", "video production", "analysis", "budget", "implementation", "performance metrics", "communication", "marketing plan", "marketing campaigns", "sem", "forecast", "tracking"], "requirements": {"degrees": ["degree holder"], "majors": ["related disciplines", "business", "marketing"], "languages": ["cantonese", "english", "mandarin"], "language_level": ["excellent"], "hard_skills": ["seo", "project management", "sem", "web analytics", "facebook"], "soft_skills": ["communication skills", "creative", "project management skills", "web analytics", "energetic", "interpersonal"], "languages_combined": [{"language": "cantonese", "language_level": ["excellent"]}, {"language": "english", "language_level": ["excellent"]}, {"language": "mandarin", "language_level": ["excellent"]}]}, "experience_required": {"duration": ["3 years", "at least 3 years"], "field": ["social media", "digital marketing", "beauty", "digital"]}}, {"job_id": "100003009050115", "location_code": "hk", "company": "Swisso Beauty Expert", "job_title": "Marketing Manager / Director", "description": "about the company.\n\nOur client is a MNC insurance company based in Hong Kong, who is currently looking for an Project Manager/Assistant to cater with the team's expansion and different projects\n\nabout the job.\n\nYou will be focusing mainly in tasks below:\n\nResponsible for web application & e-Commerce platform implementation and enhancement to drive the sales\nResponsible for overall project management and resource planning\nDevelop business process flow and performance review to improve customer operational efficiency\nEvaluate current business model and operation workflow\nOrganise and conduct UAT\nskills & experiences required.\nDegree Holder in Business, Computer Science, IT or equivalent\nMin 3 years of related project management experience, with web application exposure\nPrevious experience in insurance industry is preferred, but not a must\nA good team player with good analytical and interpersonal skills, able to work under pressure and independently\nOpen-minded, attention to detail and self-disciplined\nExcellent communication skill with good command of written and spoken Cantonese and English\n\nInterested parties, please click \"Apply Now\" or contact Cheryl Lau at cheryl.lau@randstad.com.hk", "employment_types": ["Full Time"], "selling_points": [], "locations": ["Tsim Sha Tsui"], "categories": ["Beauty Care / Health", "Others", "Marketing / Public Relations", "Marketing - Brand / Product Management", "Digital Marketing"], "post_time": "2022-01-16T21:50:24Z", "salary": {"currency": null, "max": null, "min": null, "period": "monthly", "term": null}, "salary_visible": false, "title_keywords": ["marketing manager", "director"], "responsibilities": ["uat", "work under pressure", "review", "implementation", "develop", "evaluate", "project management", "communication", "business process", "e-commerce platform", "insurance", "planning"], "requirements": {"degrees": ["degree holder"], "majors": ["business", "it", "computer science"], "languages": ["cantonese", "english"], "language_level": ["excellent", "good command"], "hard_skills": ["project management", "web", "e-commerce"], "soft_skills": ["good team player", "independently", "responsible", "open-minded", "communication skill", "project management", "interpersonal skills", "attention to detail", "work under pressure"], "languages_combined": [{"language": "cantonese", "language_level": ["excellent", "good command"]}, {"language": "english", "language_level": ["excellent", "good command"]}]}, "experience_required": {"duration": ["min 3 years"], "field": ["related", "project management", "insurance industry"]}}, {"job_id": "100003009055824", "location_code": "hk", "company": "Randstad Hong Kong Limited", "job_title": "Project Manager/ Assistant Project Manager (Insurance)", "description": "Excellent opportunity for candidates who have experience in English / Chinese copywriting and strong user experience mindset to support the launch of new digital features and products.\n\nClient Details\n\nOur client is a leading bank providing personal & corporate financial management service. With their experiences and sophisticated business, our client has strong client base and great reputation in the industry. To corporate with their growth for their digital product, our client is looking for a high-calibre candidate to join them and support their newly launched digital features and products.\n\nDescription\n\nDevelop clear and customer-centric copy that promote digital products and new features including both long and short form\nUnderstand the digital journeys in order to produce an effective user experience\nEnsure all content presents an accurate overview of brand and is aligned to brand guidelines/tone\nWork closely with internal team to identify opportunities and create human-centred copy-writing experience\n\nProfile\n\nDegree in Marketing / Communication/ Journalism / Language / Related discipline\n3+ years working experience in copy-writing\nStrong communication and written skills in English or Chinese (both Traditional and Simplified)\nExperience in financial services industry is a plus\nPositive attitude, hands-on and can-do mentality\n\nJob Offer\n\nLarge audience based\nGreat career prospect\nReputable brand", "employment_types": ["Full Time", "Permanent"], "selling_points": ["MNC insurance company based in Hong Kong", "Web application & e-Commerce platform", "Young and energetic team environment"], "locations": ["Not Specified"], "categories": ["Information Technology (IT)", "IT Project Management / Team Lead", "Marketing / Public Relations", "Digital Marketing", "E-commerce", "Product Management / Business Analyst"], "post_time": "2022-01-18T02:59:17Z", "salary": {"currency": "HKD", "max": 44999, "min": 30000, "period": "monthly", "term": null}, "salary_visible": true, "title_keywords": ["project manager", "assistant project manager"], "responsibilities": ["management", "user experience", "develop", "communication", "client base", "brand guidelines"], "requirements": {"degrees": ["degree"], "majors": ["journalism", "marketing"], "languages": ["english", "chinese"], "language_level": ["excellent"], "hard_skills": ["plus"], "soft_skills": ["sophisticated", "positive attitude", "communication", "clear", "hands-on", "can-do", "accurate"], "languages_combined": [{"language": "english", "language_level": ["excellent"]}, {"language": "chinese", "language_level": ["excellent"]}]}, "experience_required": {"duration": ["3+ years"], "field": ["business", "writing", "copywriting", "digital", "financial services industry", "team"]}}, {"job_id": "100003009055640", "location_code": "hk", "company": "Page Personnel", "job_title": "Digital Copywriter - Financial Services (Chinese/English)", "description": "Key\u00a0Responsibilities:\n\nFormulate and implement digital marketing strategy to grow customer base and drive global business\nConduct market research and business analysis for a variety of telecommunication products and solutions with an aim to capture market opportunities and customer needs\nConduct Lead Generation programs leveraging both digital and traditional marketing platforms to achieve business objectives\nWork closely with multi-disciplinary teams to boost marketing program results\u00a0\nPerform other duties as assigned by the management\n\n\u00a0Requirements:\n\nDegree holder in Marketing/Business Administration/Data Analytics or related discipline with at least 3 years\u2019 work experience gained from the telecommunications, IT, consultancy or other services industries with track record in digital marketing\nA good understanding of the global telecommunications market and products/solutions\nExperience in developing sales incentive program is definitely an advantage\nExcellent communication, interpersonal and organization skills\nStrong analytical and problem solving skills with good business acumen.\u00a0 Results-oriented, self-motivated and able to cope with a fast pace, dynamic and global operated business environment\nHighly proficient in MS Office including PowerPoint, Excel, Word (including Chinese word processing) and other related applications\nExcellent command of both spoken and written English and Chinese.\u00a0 Fluent Mandarin is an advantage\nQualified candidate with more relevant work experience would be considered as Assistant Product Marketing Manager\n\nWe offer 5 days work, competitive salary package and attractive career development opportunities to the right candidate.\u00a0\n\nInterested parties please email your full resume with your current & expected salary to us.\n\nApplicants not invited for interview within 3 months may assume their applications unsuccessful.\u00a0\n\nIf you are interested in other job opportunities, please check with below career website.\n\nPersonal data collected would be used for recruitment purpose only.\n\n\n\n", "employment_types": ["Full Time", "Contract"], "selling_points": ["Support new launch digital features", "Immediately available", "Competitive salary range"], "locations": ["Not Specified"], "categories": ["Marketing / Public Relations", "Public Relations - Copy-writing", "Others", "Digital Marketing"], "post_time": "2022-01-18T02:49:22Z", "salary": {"currency": null, "max": null, "min": null, "period": "monthly", "term": null}, "salary_visible": false, "title_keywords": ["copywriter"], "responsibilities": ["perform other duties", "management", "conduct market research", "teams", "digital marketing", "business analysis"], "requirements": {"degrees": ["degree holder"], "majors": ["marketing", "business administration", "it", "digital marketing"], "languages": ["english", "chinese", "mandarin"], "language_level": ["advantage", "fluent", "excellent", "proficient"], "hard_skills": ["excel", "chinese word processing", "data analytics", "word", "acumen", "powerpoint", "dynamic", "problem solving skills", "ms office"], "soft_skills": ["self-motivated", "business environment", "organization skills", "communication", "analytical and problem solving skills", "dynamic", "business acumen", "interpersonal"], "languages_combined": [{"language": "english", "language_level": ["excellent"]}, {"language": "chinese", "language_level": ["excellent", "proficient"]}, {"language": "mandarin", "language_level": ["fluent", "advantage"]}]}, "experience_required": {"duration": ["at least 3 years"], "field": ["business administration", "related", "developing", "marketing", "it", "digital marketing", "telecommunications"]}}, {"job_id": "100003009051630", "location_code": "hk", "company": "China Telecom Global Limited", "job_title": "Senior Product Marketing Executive/ Assistant Product Marketing Manager", "description": "Background: My client is one of the most reputable financial services in Hong Kong and they are now growing out their Digital team. Therefore, seeking for an experienced Digital Manager to join them.\u00a0\n\nDuties:\u00a0\nDevelop digital channel operation strategy, channel operation management model, and operation plan for Mobile APP and website\nManage operations and maintenance of digital owned channels and channels where digital is the strategic partner to promote and improve channel efficiency\nMobile APP Release, Monitoring and Account management\nCo-create channel operation reporting mechanism with stakeholders (e.g. business owner, product manager, marketing and IT) and report to management on regular basis\nInvolve in project life cycle for Mobile APP and website projects including user requirement preparation, review of User Acceptance Test cases and results, preparing customer communication and internal training\nWork with IT and other stakeholders to explore new solutions to increase the efficiency of the digital communication channels\nCollaborate with product owners to provide suggestions for operation optimization and digital product iteration and platform positioning based on data and user behavior insight\nMonitor the usage of digital services and stay updated with the market trend\nRequirements:\u00a0\n\nUniversity graduate in Information System, Marketing or related business study\nExperienced in financial industry Mobile APP operation and planning, product portfolio management, or related roles\nGood understanding of different digital channels such as financial industry official website, WeChat, Facebook, IG and user behaviors onto the channels.\nFamiliar with UI/UX, gathering analytics, and developing strategy and tactics for digital channel operation\nKnowledge and understanding of digital platform and infrastructure\u00a0\nAttention to details, self-initiative and result-oriented\nGood interpersonal skills communicating with both technical and non-technical partners across multiple functions to reach business goals.\nFluent in Chinese and English\nCandidate with more experience can be considered as Senior Manager, Digital Channel\nCandidates who are interested in this position, please apply directly by submitting your latest CV including current and expecting salary. Please note that only shortlisted candidates will be notified.\u00a0", "employment_types": ["Full Time", "Permanent"], "selling_points": ["Degree holder in Marketing/Business Administration", "Formulate and implement digital marketing strategy", "Competitive salary package"], "locations": ["Wan Chai"], "categories": ["Marketing / Public Relations", "Marketing - Brand / Product Management", "Marketing - Market Research", "Digital Marketing"], "post_time": "2022-01-16T15:45:55Z", "salary": {"currency": null, "max": null, "min": null, "period": "monthly", "term": null}, "salary_visible": false, "title_keywords": ["product marketing manager", "assistant", "marketing executive"], "responsibilities": ["collaborate with", "reporting", "management", "user requirement", "mobile app", "maintenance", "data", "operations", "monitoring", "review", "website", "monitor", "develop", "communication", "operation plan", "report"], "requirements": {"degrees": ["university graduate"], "majors": ["business", "marketing"], "languages": ["english", "chinese"], "language_level": ["fluent"], "hard_skills": ["mobile", "facebook", "information system", "wechat"], "soft_skills": ["interested in", "self-initiative", "interpersonal skills", "attention to details", "result-oriented"], "languages_combined": [{"language": "english", "language_level": ["fluent"]}, {"language": "chinese", "language_level": ["fluent"]}]}, "experience_required": {"duration": [], "field": ["digital"]}}, {"job_id": "100003009056429", "location_code": "hk", "company": "Wellesley Associates Limited", "job_title": "Manager/Senior Manager, Digital Channel - IT/Digital Mobile Marketing/Banking - Perm - 750-850K pa", "description": "Requirements:\n\n\nBachelor\u2019s degree preferably in communications / marketing or related disciplines\nMinimum 10 years' solid experience in mall promotions / marketing in property developers\nProven English and Chinese proficiency\nGood in digital marketing and media relations with strong market sense\nExcellent interpersonal and leadership skills\nAble to meet tight deadlines and work in a fast-paced and pressurized environment\nWilling to work long hours and during holidays occasionally\n\nResponsibilities:\n\n\nPlan and oversee promotion and advertising activities of shopping malls\nDevelop overall marketing strategy of shopping malls\nPlan and implement digital marketing campaigns\nLiaise and maintain good relationship with tenants and agencies in promoting shopping malls\nWork with internal stakeholders to support group loyalty program\n\nGood remuneration and attractive fringe benefits will be offered to the successful applicant. Interested parties please apply with full resume, present and expected salary, available date by clicking \"Apply Now\".\n\nWe are an equal opportunity employer and welcome applications from all qualified candidates. All personal data collected will be used for recruitment purpose only.\u00a0 Applicants not hearing from us within 3 months may consider their applications unsuccessful.\u00a0 All personal data collected will be destroyed within 24 months.", "employment_types": ["Full Time"], "selling_points": ["Digital Channel/IT/Banking/ Marketing UXUI", "Inhouse Perm Financial Services", "Mobile App"], "locations": ["Not Specified"], "categories": ["Information Technology (IT)", "IT Management", "Marketing / Public Relations", "Digital Marketing", "UI/UX Designer"], "post_time": "2022-01-18T04:17:12Z", "salary": {"currency": null, "max": null, "min": null, "period": "monthly", "term": null}, "salary_visible": false, "title_keywords": ["senior manager", "manager"], "responsibilities": ["liaise", "advertising", "digital marketing campaigns", "develop", "maintain good relationship", "plan"], "requirements": {"degrees": ["degree", "bachelor"], "majors": ["related disciplines", "marketing", "communications"], "languages": ["english", "chinese"], "language_level": ["proficiency"], "hard_skills": [], "soft_skills": ["strong market sense", "leadership skills", "interpersonal", "meet tight deadlines"], "languages_combined": [{"language": "english", "language_level": ["proficiency"]}, {"language": "chinese", "language_level": ["proficiency"]}]}, "experience_required": {"duration": ["minimum 10 years"], "field": ["property developers", "marketing"]}}, {"job_id": "100003009054939", "location_code": "hk", "company": "Sun Hung Kai Properties Ltd", "job_title": "SENIOR PROMOTIONS MANAGER \u2013 SHOPPING MALL", "description": "Job Nature:\u00a0\u00a0\n\nResponsible for daily management of CS Content for social media platform\nProduce content video included writing script, web-articles and social-media contents\nWork close with content partnership and keep daily publish schedule run smooth\nHandling clients project, various ad hoc projects under tight schedule independently\nWork closely with internal parties and sales team\nGenerate regular content reports /\u00a0 CS reports for performance analysis\n\nCharacters / Qualifications:\n\n\nBachelor degree holder, preferably in journalism\nOver 1 years experience on lifestyle / sports reporting or editing\nStrong digital and online knowledge\nGood understanding of social Media environment and multi media industries\nGood communication skill\nHave good connections with KOLs and Sports pages\n\nWe offer competitive salary and benefits package( 5 days work, 14 days AL up, birthday leave, medical & dental insurance) with great opportunity for career development to the successful candidate.\n\nPlease send your detailed resume and expected salary to our Human Resources Department by clicking \"Apply Now\" (please put position applied on subject line).", "employment_types": ["Full Time", "Permanent"], "selling_points": ["Plan & oversee promotion activities of malls", "Develop marketing strategy of malls", "Implement digital marketing campaigns"], "locations": ["Wan Chai"], "categories": ["Marketing / Public Relations", "Marketing - Marketing Communication", "Public Relations - Event Management", "Digital Marketing"], "post_time": "2022-01-17T14:29:22Z", "salary": {"currency": null, "max": null, "min": null, "period": null, "term": null}, "salary_visible": false, "title_keywords": ["manager"], "responsibilities": ["social media", "management", "reporting", "analysis", "communication", "ad hoc projects", "schedule", "sales team", "contents", "reports", "career development", "editing", "insurance", "internal parties"], "requirements": {"degrees": ["bachelor degree holder"], "majors": ["journalism"], "languages": [], "language_level": [], "hard_skills": ["analysis", "web"], "soft_skills": ["independently", "responsible", "communication skill", "smooth", "detailed"], "languages_combined": []}, "experience_required": {"duration": ["1 years"], "field": ["editing"]}}, {"job_id": "100003009052275", "location_code": "hk", "company": "New Media Group Publishing Limited", "job_title": "Project Editor (Sports Trend \u904b\u52d5\u6f6e\u6d41\uff09", "description": "Duties\nExecute both online Buzz Level monitoring among global markets\nClosely and pro-actively monitor and optimize digital campaigns efficiency on daily basis\nMonitor and control marketing campaign timelines\nCoordinate with online content team to manage daily digital tactics\nShare with internal parties to produce new creatives with innovative ideas and formats\nAssist Marketing Manager to formulate execute marketing planning, budget allocation and marketing tools development\nProduce regular data analysis, market trending research and reporting with associated insights\nRequirements\nBachelor Degree in Business, Marketing, Advertising, eCommerce or related disciplines\n2 years of digital marketing experience\nFamiliar with digital marketing tools including Facebook ads manager, social media, 3rd party tracking, SEM, SEO and Google Analytics\nStrong in written and spoken English and Chinese\nMobile app or game relevant working experience is a plus\nPrioritize workload, manage multiple projects and meet deadlines for various and ad-hoc marketing deliverable\nOutstanding team player and positive attitude, with a strong sense of ownership and accountability\nExcellent communication, collaboration and planning skills\nCandidate with more experience will be considered as Senior Digital Marketing Executive\nAttractive remuneration package and excellent prospect will be offered to the right candidate.\u00a0 Please send application with our reference no., detailed resume, present and expected salary to Human Resources Manager, BIG BIG CHANNEL Limited, 8/F, Main Block, TVB City, 77 Chun Choi Street, Tseung Kwan O Industrial Estate, Tseung Kwan O, Kowloon or fax to 2335-9751 or by clicking \u201cApply Now\u201d.\nAll information provided will be used for recruitment purpose only.\u00a0 All personal data of unsuccessful candidates will be destroyed.", "employment_types": ["Full Time", "Permanent"], "selling_points": ["Handling clients project, Strong digital knowledge", "Have good connections with KOLs and Sports pages", "Great development opportunity, competitive package"], "locations": ["Kwun Tong"], "categories": ["Media & Advertising", "Others", "Editorial / Journalism", "Marketing / Public Relations", "Digital Marketing"], "post_time": "2022-01-17T02:37:40Z", "salary": {"currency": null, "max": null, "min": null, "period": null, "term": null}, "salary_visible": false, "title_keywords": ["editor"], "responsibilities": ["reporting", "control", "ideas", "monitoring", "monitor", "coordinate with", "budget", "data analysis", "digital campaigns", "internal parties", "planning"], "requirements": {"degrees": ["degree", "bachelor"], "majors": ["ecommerce", "related disciplines", "business", "marketing"], "languages": ["english", "chinese"], "language_level": [], "hard_skills": ["google analytics", "plus", "no", "seo", "mobile", "sem", "facebook"], "soft_skills": ["planning skills", "accountability", "prioritize", "positive attitude", "communication", "team player", "meet deadlines", "detailed"], "languages_combined": [{"language": "english", "language_level": []}, {"language": "chinese", "language_level": []}]}, "experience_required": {"duration": ["2 years"], "field": ["digital marketing", "relevant working experience"]}}, {"job_id": "100003009044862", "location_code": "hk", "company": "Big Big Channel Limited", "job_title": "DIGITAL MARKETING EXECUTIVE", "description": "\u5c08\u696d\u7406\u8ca1\u9867\u554f\u00a0/\u00a0\u7406\u8ca1\u7b56\u5283\u7d93\u7406\n\n\u4ee5\u7279\u5feb\u9014\u5f91\u6210\u70ba\u4e00\u4f4d\u9ad8\u7aef\u5c08\u696d\u7406\u8ca1\u7b56\u5283\u5e2b\u53ca\u5e74\u9752\u4f01\u696d\u5bb6\uff0c\u4f60\u6e96\u5099\u597d\u672a\uff1f\n\n\u4f60\u662f\u5426\u63a5\u53d7\u904e\u9ad8\u7b49\u6559\u80b2(Higher Diploma, Associate Degree, Degree) ?\u00a0\n\u662f\u5426\u6168\u5606\u73fe\u6642\u85aa\u916c\u5341\u5e74\u5982\u4e00\u65e5?\u00a0\u751a\u81f3\u6bd4\u5e02\u50f9\u4f4e?\n\n\u4f60\u5e0c\u671b\u4e00\u4e16\u505a\u6253\u5de5\u4ed4\u5e6b\u516c\u53f8\u7528\u6642\u9593\u63db\u53d6\u6536\u5165?\u00a0\n\u9084\u662f\u9760\u81ea\u5df1\u6253\u62fc\u4e00\u5206\u8015\u8018\uff0e\u4e00\u5206\u6536\u7a6b\u63d0\u5347\u81ea\u6211\u50f9\u503c,\u00a0\u5f9e\u6b64\u4eab\u53d7\u5de5\u4f5c,\u00a0\u4eab\u53d7\u751f\u6d3b?\u00a0\n\n\u6210\u70ba\u7406\u8ca1\u7b56\u5283\u5e2b,\u00a0\u5169\u5e74\u53ef\u5e74\u85aa\u8d85\u904e100\u842c\u4ee5\u4e0a,\u00a0\u66f4\u53ef\u4ee4\u5de5\u4f5c\u751f\u6d3b\u5e73\u8861\n\n\u6211\u5011\u975e\u5e38\u6b61\u8fce\u9858\u610f\u5b78\u7fd2\uff0c\u7a4d\u6975\uff0c\u80af\u62fc\u640f\u7684\u5404\u4f4d\u52a0\u5165\u6211\u5011\u5718\u968a\u3002\n\u6211\u5011\u63d0\u4f9b\u5168\u65b9\u4f4d\u8077\u696d\u57f9\u8a13\u5305\u62ec\u7406\u8ca1\u7b56\u5283\uff0c\u8cc7\u7522\u7ba1\u7406\uff0c\u9000\u4f11\u65b9\u6848\uff0c\u57fa\u91d1\u6295\u8cc7\uff0c\u5152\u7ae5\u6559\u80b2\u57fa\u91d1\u7b49\u57f9\u80b2\u5091\u51fa\u5c08\u696d\u7406\u8ca1\u9867\u554f\u53ca\u5718\u968a\u9818\u8896\uff08\u9752\u5e74\u4f01\u696d\u5bb6\uff09\n\u00a0\n\n\u4e3b\u8981\u5de5\u4f5c\u5185\u5bb9\uff1a\n\n\u30fb\u5e6b\u5ba2\u6236\u5206\u6790\u8ca1\u52d9\u9700\u6c42\uff0c\u4e26\u63d0\u4f9b\u5404\u7a2e\u7406\u8ca1\u8a08\u5283\u5efa\u8b70\n\u30fb\u70ba\u5ba2\u6236\u63d0\u4f9b\u6709\u95dc\u8cc7\u7522\u914d\u7f6e\u53ca\u8cc7\u7522\u7ba1\u7406\u7684\u5c08\u696d\u5efa\u8b70\n\u30fb\u70ba\u5ba2\u6236\u7ba1\u7406\u6709\u95dc\u8ca1\u5bcc\u7d2f\u7a4d\uff0c\u6295\u8cc7\u8a08\u5283\uff0c\u9000\u4f11\u8a08\u5283\u53ca\u500b\u4eba\u98a8\u96aa\u7ba1\u7406\u8a08\u5283\n\u30fb\u70ba\u500b\u4eba\u6216\u4f01\u696d\u5ba2\u6236\u63d0\u4f9b\u5f37\u7a4d\u91d1\u670d\u52d9\n\n\u798f\u5229\u53ca\u5f85\u9047\uff1a\n\n\u30fb\u6708\u85aa\uff08\u81f3\u5c11\uff09HK22,000.00\u00a0+\u00a0\u7121\u4e0a\u9650\u4f63\u91d1 + \u5b63\u5ea6\u82b1\u7d05\u53ca\u5e74\u7d42\u82b1\u7d05\n\u30fb\u5f48\u6027\u5de5\u4f5c\u6642\u9593\n\u30fb\u8077\u524d\u53ca\u5728\u8077\u6301\u7e8c\u57f9\u8a13\uff1a\u724c\u7167\u8ab2\u7a0b\u53ca\u8003\u8a66\uff0c\u7522\u54c1\u8cc7\u8a0a\u4ecb\u7d39\uff0c\u4e2d\u4ecb\u4eba\u5b88\u5247\uff0c\u4e8b\u696d\u767c\u5c55\u8ab2\u7a0b\u53ca\u5c08\u696d\u5718\u968a\u6559\u6388\u4eba\u969b\u6e9d\u901a\u6280\u5de7\u7b49\u7b49\n\u30fb\u5718\u9ad4\u91ab\u7642\n\u30fb\u5feb\u901f\u6649\u5347\u6a5f\u6703, 1 \u5e74\u6649\u5347\u7d93\u7406\u8a08\u5283\n\u30fb\u5408\u8cc7\u683c\u8005\u7372\u9080\u51fa\u5e2d\u516c\u53f8\u5b89\u6392\u4e4b\u6d77\u5916\u8c6a\u83ef\u65c5\u904a\u734e\u8cde\n\n\u5165\u8077\u8981\u6c42\uff1a\n\n\u30fb\u6301\u9ad8\u7d1a\u6587\u6191\uff0c\u526f\u5b78\u58eb\uff0c\u5927\u5b78\u6216\u4ee5\u4e0a\u5b78\u6b77\uff0c\u6b61\u8fce\u61c9\u5c46\u7562\u696d\u751f\u6216\u7b26\u5408\u7559\u6e2f/\u56de\u6e2f\u5c31\u696d\u5b89\u6392\u7684\u975e\u672c\u5730\u7562\u696d\u751f(IANG)\n\u30fb\u6301\u6709\u9999\u6e2f\u6c38\u4e45\u5c45\u6c11\u8eab\u4efd\u8b49\n\u30fb\u597d\u5b78\u3001\u6709\u8cac\u4efb\u5fc3\u3001\u4e0a\u9032\u3001\u559c\u6b61\u8207\u5225\u4eba\u6e9d\u901a\n\u30fb\u6e34\u671b\u62d3\u5c55\u500b\u4eba\u4e8b\u696d\n\n\u00a0\u5fc3\u52d5\u4e0d\u5982\u884c\u52d5\n\u5982\u4f60\u5c0d\u6b64\u5de5\u4f5c\u6709\u8208\u8da3\u6216\u4efb\u4f55\u7591\u554f\uff0c\u8acb\u7acb\u5373\u9ede\u64ca\u00a0APPLY NOW\n***\u6240\u6709\u6c42\u8077\u8cc7\u6599\u53ea\u7528\u4f5c\u62db\u8058\u7528\u9014***\n", "employment_types": ["Full Time", "Permanent"], "selling_points": [], "locations": ["Not Specified"], "categories": ["Marketing / Public Relations", "Others", "Digital Marketing", "E-commerce", "Business Development"], "post_time": "2022-01-13T06:28:31Z", "salary": {"currency": null, "max": null, "min": null, "period": "monthly", "term": null}, "salary_visible": false, "title_keywords": ["digital marketing executive"], "responsibilities": [], "requirements": {"degrees": ["associate degree", "diploma", "degree"], "majors": [], "languages": [], "language_level": [], "hard_skills": [], "soft_skills": [], "languages_combined": []}, "experience_required": {"duration": [], "field": []}}, {"job_id": "100003009053194", "location_code": "hk", "company": "AXA China Region Insurance Company Limited", "job_title": "AXA \u5b89\u76db \u5c08\u696d\u7406\u8ca1\u9867\u554f / \u7406\u8ca1\u7b56\u5283\u7d93\u7406", "description": "The Role\nWe are looking for a creative, passionate and enthusiastic PR and Marketing Executive to join our team.\u00a0You will have a chance to work at a fast-paced mission driven company that brings material science to life and benefit the mass. We are bringing business disruption and new hygiene standard to the world with the introduction of new photocatalyst products and services. With the continuous R&D and business innovation, we are thrilled to develop the next generation technology that safeguards everyday life.\n\nResponsibilities\n\n\nAssist to plan, coordinate and implement marketing programs;\nDay-to-day management of media plans, reports and follow up on materials;\nProduce competitive analysis and reports for the relevant consumer and business sectors;\nSupport and work closely with the team on buying executions on a day-to-day basis;\nDevelop engaging, creative content for our social media & e-commerce platform (Including writing, editing and proofreading of the product description, social media feeds, advertising collaterals, SEO contents, etc.);\nAssist in marketing reports preparation and data analysis, gather insights in customer behavior and business trends to improve the performance and drive sales.\n\nRequirements\n\n\nUniversity degree holder in Marketing, Communications, Creative Media, Business or related disciplines;\n1-2 years relevant experience in FMCG/healthcare. Agency background is an advantage;\nProficiency in using Facebook, Instagram, WeChat, Weibo and others to build communities and enhance brand profile;\nStrong market sense and good creativity;\nPatient, pay attention to details and with good communication skills;\nGood command in both written and spoken English, Cantonese and Mandarin.\n\nWe offer the right candidate attractive remuneration package and outstanding prospects for career advancement and development.\u00a0 The right candidate will progress career in a forward thinking and dynamic business with exciting growth plans.\u00a0 If you are qualified and interested, please send your full resume with current & expected salary and availability by clicking \"APPLY\".\n\nAll information collected will be treated as strictly confidential and used for recruitment purposes only. (Only shortlisted candidates will be notified)", "employment_types": ["Full Time", "Internship"], "selling_points": ["\u6708\u85aa\uff08\u81f3\u5c11\uff09HK22,000.00 + \u7121\u4e0a\u9650\u4f63\u91d1 + \u5b63\u5ea6\u82b1\u7d05\u53ca\u5e74\u7d42\u82b1\u7d05", "\u5f48\u6027\u5de5\u4f5c\u6642\u9593\uff0c\u5de5\u4f5c\u8207\u751f\u6d3b\u5e73\u8861", "HUGO AGENCY \u6210\u7acb\u81f3\u4eca30\u591a\u5e74, \u591a\u5e74\u4f86\u591a\u6b21\u69ae\u7372\u570b\u969b\u734e\u9805"], "locations": ["Kwun Tong"], "categories": ["Property / Real Estate", "Property Consultancy", "Banking / Finance", "Wealth Management", "Marketing / Public Relations", "Digital Marketing"], "post_time": "2022-01-17T06:23:26Z", "salary": {"currency": "HKD", "max": 54999, "min": 20000, "period": "monthly", "term": null}, "salary_visible": true, "title_keywords": ["\u7406\u8ca1\u7b56\u5283\u7d93\u7406"], "responsibilities": ["drive sales", "social media", "advertising", "creative content", "seo", "editing", "analysis", "develop", "coordinate", "day-to-day management", "data analysis", "proofreading", "reports", "plan", "contents", "plans", "e-commerce platform"], "requirements": {"degrees": ["university degree"], "majors": ["creative media", "related disciplines", "business", "marketing", "communications"], "languages": ["cantonese", "english", "mandarin"], "language_level": ["good command"], "hard_skills": ["facebook", "wechat"], "soft_skills": ["communication skills", "attention to details", "patient", "strong market sense", "creative"], "languages_combined": [{"language": "cantonese", "language_level": ["good command"]}, {"language": "english", "language_level": ["good command"]}, {"language": "mandarin", "language_level": ["good command"]}]}, "experience_required": {"duration": ["1-2 years"], "field": ["healthcare", "fmcg", "relevant experience"]}}, {"job_id": "100003009051402", "location_code": "hk", "company": "Raze Technology Limited", "job_title": "PR and Marketing Executive", "description": "Hyper-growth tech startup. VC-backed. Competitive package. Remote work. Friendly team. : )\nPlease apply via:\u00a0https://jobs.lever.co/imbeelimited/407e77b8-1f7f-4621-a71f-e3e6710bd820\n\nAbout imBee\nimBee.io\u00a0is the #1 Customer Chat Management Platform - it provides one inbox for all communication channels with best-in-class business tools and workflow automation for brands to scale their business and communicate better externally with customers and internally with teams.\nAs one of the venture-backed, fastest-growing startups in Asia, we serve clients across industries and sizes. Some of our happy clients are insurance giants, telecom enterprises, and SMEs in the e-commerce, retail, education, and medical industry.\nOur Mission\nThe world is becoming more conversational - we\u2019re on a mission to empower businesses to scale on all communications channels effectively.\nWe\u2019re reinventing the way businesses communicate with their customers and teams, from the ground up, so businesses can sell more, accomplish more collaboratively, save more, and build better relationships with customers.\nOur Culture\nWe\u2019re ambitious, collaborative, and fun. We work smart and play hard, and pursue excellence in everything we do. It\u2019s a learning culture that we embrace.\u00a0\nAnd we care about each and everyone in our team - we want to help you achieve your personal goals and be part of this exciting and unforgettable journey.\nYou can enjoy a flexible work environment (remote work), free snacks and beers, game room, and more!\nRole\nYour duties will include promoting products and their features to an organization's target audience. Their duties include studying the company's products, locating key features that will attract customers, and creating integrated metrics-based marketing campaigns for products. In addition to being an outstanding communicator, you will also demonstrate excellent interpersonal and analytical skills.\nResponsibilities\nDevelop positioning and messaging (define and amplify our who, what, why, how)\nDevelop product marketing strategies and create marketing materials that communicate product values\nDevelop the marketing tools and campaigns to attract new prospects and customers\nCultivate user community\nCreate Integrated communication and campaigns (Email marketing, etc.)\nCollaborate with design, product, growth, and sales teams to build outbound strategies and implement them\nCase advocacy program (case studies, testimonials, campaigns, reviews)\nRequirements\nStrong experience in B2B marketing with at least 3 years of accountable, hands-on experience (previously in B2B SaaS - advantage)\nProven outstanding abilities to translate customer needs and market demand into sharp and compelling messaging, content, sales tools, and campaigns to help us meet our business goals\nProven track record of successfully launching and managing cost-effective marketing campaigns with clear ROI focused metrics\nStrong communication and collaboration skills, both verbal and written\nHighly motivated, passionate, self-starter with a can-do attitude", "employment_types": ["Full Time", "Permanent"], "selling_points": [], "locations": ["Southern Area"], "categories": ["Marketing / Public Relations", "Marketing - Brand / Product Management", "Public Relations - General / Support", "Digital Marketing"], "post_time": "2022-01-15T14:33:53Z", "salary": {"currency": null, "max": null, "min": null, "period": "monthly", "term": null}, "salary_visible": false, "title_keywords": ["marketing executive"], "responsibilities": ["collaborate with", "marketing strategies", "teams", "design", "develop", "marketing materials", "integrated communication"], "requirements": {"degrees": [], "majors": [], "languages": [], "language_level": [], "hard_skills": [], "soft_skills": ["passionate", "focused", "can-do attitude", "accountable", "clear", "communication", "hands-on", "motivated"], "languages_combined": []}, "experience_required": {"duration": ["at least 3 years"], "field": ["marketing"]}}, {"job_id": "100003009051549", "location_code": "hk", "company": "Imbee Limited", "job_title": "Product Marketing Manager (B2B Saas)", "description": "We are looking for a candidate who is experienced in the social media/ PR field. Someone who feels he/she is ready to take the next step in his/her career in running and managing a startup in-house social media company that provides PR, social media and marketing services to our company's in-house brands based in the FMCG industry (beauty/ household/ personal care/ food etc) as well as future brands and potential clients.\n\n\n\nMain responsibilities:\n\n\n\nIdeation and production for digitally engaging content (photo, video, infographic, etc)\nSocial media platform planning and management (Instagram & Facebook etc)\nDrive engagement on social media platforms\nAds and marketing management\nIdentify, outreach, and build a growing list of influencers and Brand Ambassadors\nKOL influencer management, pitching, coordination. From initial contact to follow up.\nMedia pitching\nMeasure, optimize and report on campaigns to achieve maximum awareness & engagement, and use these results to further improve the content strategy\nWork closely with sales team\nResponsible for planning and execution of PR and marketing plans\nWe are looking for:\n\nMinimum 1 year's experience in social media/ digital agency or PR company\nExperienced and passionate with various social media platforms\nSocial media savvy who can act quick with ad-hoc happenings\nStrong interest in the FMCG field\nGood commercial sense\nCANVA skills is an advantage\nStrong KOL network is an advantage\nExperience in KOL influencer management\nStrong sense of ownership and self-sufficiency \u2013 eager to own, drive, and grow our platforms\nExtremely detail oriented and comfortable in multi-tasking and priority assessment\nAn avid social media user yourself with a genuine interest in the FMCG industry\nProactive, innovative, and curious", "employment_types": ["Full Time"], "selling_points": [], "locations": ["Kowloon City Area"], "categories": ["Marketing / Public Relations", "Marketing - Brand / Product Management", "Digital Marketing"], "post_time": "2022-01-16T10:10:40Z", "salary": {"currency": "HKD", "max": 44999, "min": 35000, "period": "monthly", "term": null}, "salary_visible": true, "title_keywords": ["product marketing manager"], "responsibilities": ["ad-hoc", "social media", "management", "marketing plans", "social media platforms", "sales team", "contact", "coordination", "facebook", "report", "planning"], "requirements": {"degrees": [], "majors": [], "languages": [], "language_level": [], "hard_skills": ["facebook", "fmcg industry"], "soft_skills": ["passionate", "proactive", "responsible", "detail oriented", "innovative", "multi-tasking", "coordination", "genuine"], "languages_combined": []}, "experience_required": {"duration": ["minimum 1 year"], "field": ["social media", "pr", "management", "agency", "digital"]}}, {"job_id": "100003009046455", "location_code": "hk", "company": "TLB Hong Kong Limited", "job_title": "PR & Social Media Executive / Manager", "description": "\n\n\nTHE COMPANY :\n\nHealth supplement / FMCG brand owner target China market like Taobao, JD, Tmall....etc\nWe are looking for\u00a0 E-COMMERCE MANAGER - with details as follows :\n\nTHE JOB :\n\nJob summary : build and manage this new e-Commerce business of a US health supplement brand target China market\nAll round operate this e-Commerce business including but not limited to sales, customer service, branding, marketing, daily operation (monitor China e-Commerce agency)\nOversee e-commerce platforms to achieve sales goals, raise brand awareness and ensure high standard of customer service.\nLead and collaborate with different stakeholders, including internal teammates and external vendors for various e-commerce projects\nManage day-to-day operation and update content materials of e-commerce platforms (such as online marketing campaigns, new product launch and demonstrations, product catalogue, price change and other sales and marketing events).\nMonitor and analyze online sales performance, traffic, user behavior, conversion funnels and goals by using different analytic tools, and provide suggestion to key stakeholders.\nWork independently in the early stage, will develop a small e-commerce team in later stage\nReport to MD directly\nDegree holder\nSolid working experience in e-commerce for China market\nExperience in health supplements or FMCG brands is a plus\nExperience in China e-Commerce market like Tmall, JD, Taobao is a big plus\nAble to work independently for all round operating this e-Commerce business including both sales, digital marketing and operation management\n5 days work\nTO APPLY for this job or similar jobs :\n\n\u00a0\nFor secure and confidential job application, please click the below link to get our email address.\n\u00a0\nhttp://jpc.hk/confidential_apply.htm\n\u00a0\n\u00a0\nWe provide free job hunting services to job seekers.\n\u00a0\nTo speed up our process, please do NOT send us download links.\n\u00a0\nPersonal data provided by job applicants will be used for recruitment purpose only.\n\u00a0\nYour privacy is guaranteed. We will never give out, lease, or sell your personal information.\n\u00a0\nJPC Recruiting Services was established in 1990.\n\u00a0\nhttp://www.facebook.com/pages/JPC-Texson-Ltd/500356593325952\n\n", "employment_types": ["Full Time", "Contract"], "selling_points": ["Social media, Digital PR, Marketing", "KOL influencer management", "Company start-up ownership opportunity"], "locations": ["Kwai Hing"], "categories": ["Media & Advertising", "Creative / Design", "Marketing / Public Relations", "Marketing - Brand / Product Management", "Digital Marketing"], "post_time": "2022-01-15T03:28:23Z", "salary": {"currency": null, "max": null, "min": null, "period": "monthly", "term": null}, "salary_visible": false, "title_keywords": ["manager", "social media executive"], "responsibilities": ["collaborate with", "marketing events", "management", "raise brand awareness", "sales performance", "monitor", "daily operation", "e-commerce platforms", "develop", "customer service", "digital marketing", "marketing campaigns", "update content materials", "catalogue", "day-to-day operation", "report"], "requirements": {"degrees": ["degree holder"], "majors": [], "languages": [], "language_level": [], "hard_skills": ["small", "plus", "e-commerce"], "soft_skills": ["work independently", "customer service"], "languages_combined": []}, "experience_required": {"duration": [], "field": ["fmcg", "e-commerce"]}}, {"job_id": "100003009054868", "location_code": "hk", "company": "JPC Texson Limited", "job_title": "eCommerce Manager (30K-40K) - FMCG/health supplement brand (Kwun Tong/5 days work)", "description": "Purpose of the Job\n\nDeliver full funnel digital media strategy to optimize the performances of Club Med sales & presence online.\nManage and analyze consumer behavior to develop customer relations.\u00a0\nKey Missions\n\nMission 1 : Manage full funnel digital media strategy\n\nTasks :\n\nPlan and implement digital media strategy according to brand strategy and business needs.\nOptimize and analyze media plan and performance with media agency.\nResponsible for digital media budget.\nBrief the agency (freelancer) & ensure the digital media creative delivery\nKey KPI: # of paid sessions, BE entry, conversion rate, CPC and CPA.\nMission 2 : Ensure total fluidity and optimal consumer journey on B2C & B2B platforms to deliver growth\n\nTasks :\n\nImplement new functions and settings on official B2C site.\nManage E-commerce systems to ensure the fluidity of booking process.\nResponsible for E-commerce sales boost campaigns\nAnalyze E-commerce performance & set up actions to optimize it\nSuccessfully launch & maintain the B2B platform\nKey KPI: sales performance, conversion rate and behavior flow.\nMission 3 : Optimize consumer experience and information quality on official sites & social media\n\nTasks :\n\nResponsible for Club Med campaign launch, including branding & promotion on own digital platforms.\nOptimize onsite content and placement, based on brand strategy and travel trend.\nImplement SEO strategy to ensure organic brand visibility and positioning. \u00a0\nLead our social media calendar, manage client relationship on omnichannel tools (Chat/Facebook)\nKey KPI: # of organic sessions, bounce out rate (e-commerce) & engagement (social)\nMission 4 : Lead CRM strategy to strengthen relations with customers & Travel Agencies (TA) partners\n\nTasks :\n\nAnalyze consumer behavior to identify customer segmentations.\nDevelop customer acquisition plan to expand the database.\nLead the communication plan calendar, develop the campaign and touchpoints for members (EDM & SMS)\nSupport Indirect sales team for the elaboration of the travel agencies CRM plan\nDevelop partnerships to improve the benefit for members.\nKey KPI: Quality & quantity of data base, EDM open & reactivity rate, and repurchase rate.\nEducation: \u00a0\u00a0\n\nBachelor / Master\u2019s Degree in Marketing (preferably eBusiness)\nJob Experience: \u00a0\u00a0\n\n3 years+ experience in online marketing\nSkills: \u00a0\u00a0\u00a0\n\nGenuine passion and in-depth understanding of the digital ecosystem\nExperience in managing relationships with key partners\nCreative, attentive to detail, strong business acumen, results-orientated\nStrong written and verbal communication (CN and EN) and analytical skills\nExperience in CRM operations is a plus\nBehaviours:\u00a0\u00a0\u00a0\n\nGreat team player, positive spirit, well-organised, reliable, agile & comfortable in dealing with difficult situations, able to multi task, proactive\nEnergetic and enthusiastic person who has a strong understanding across all digital platforms and social communication channels.\nFeel in line with Club Med very strong attitude values: KINDNESS, MULTICULTURALITY, PIONNEER ATTIITUDE, FREEDOM, and RESPONSIBILITY.\nWe are looking for a creative person who will bring energy and ideas to the table.\nSoftware: \u00a0\u00a0 \u00a0\n\nAdvanced knowledge in Microsoft Office\nAdvanced knowledge in GAP and other digital analysis system\nKnowledge of a CRM management software is a plus\nLanguages :\u00a0\u00a0 \u00a0\n\nFluent in Chinese (Cantonese) and English\nWe offer competitive package to the right candidate. Qualified and interested parties please send your resume and salary expectation by clicking \"Apply Now\".\n\nPersonal data collected will be used for recruitment purpose only.\n", "employment_types": ["Full Time", "Permanent"], "selling_points": ["Solid e-commerce exp for China market", "Exp in JD, Tmall, Taobao.... is a plus", "Exp in health supplement or FMCG brands a plus"], "locations": ["Kwun Tong Area"], "categories": ["Marketing / Public Relations", "Digital Marketing", "E-commerce", "Business Development", "Marketing - Brand / Product Management"], "post_time": "2022-01-17T12:12:57Z", "salary": {"currency": null, "max": null, "min": null, "period": "monthly", "term": null}, "salary_visible": false, "title_keywords": ["manager"], "responsibilities": ["ideas", "software", "data", "operations", "budget", "quality", "communication", "maintain", "plan", "database", "facebook", "sales performance", "develop", "social media", "management", "seo", "edm", "booking", "analysis", "systems", "sales team"], "requirements": {"degrees": ["degree", "bachelor", "master"], "majors": ["marketing"], "languages": ["cantonese", "english", "chinese"], "language_level": ["fluent"], "hard_skills": ["plus", "seo", "agile", "e-commerce", "microsoft office", "analysis", "gap", "analytical skills", "cpa", "facebook", "acumen"], "soft_skills": ["proactive", "attentive to detail", "creative", "responsible", "well-organised", "agile", "advanced", "analytical skills", "communication", "energetic", "reliable", "enthusiastic", "business acumen", "team player", "genuine", "positive"], "languages_combined": [{"language": "cantonese", "language_level": ["fluent"]}, {"language": "english", "language_level": ["fluent"]}, {"language": "chinese", "language_level": ["fluent"]}]}, "experience_required": {"duration": [], "field": ["social media", "marketing"]}}, {"job_id": "100003009051165", "location_code": "hk", "company": "Club Mediterranee (Club Med) Hong Kong Ltd", "job_title": "Digital & CRM Marketing Executive", "description": "Our client is a global corporate with energy and petrochemicals companies, they are now seeking to hire an experienced Corporate Communication Manager to join their team.\nJob Responsibilities:\nDevelop and implement integrated corporate communication strategy and effective media communications programmes at corporate level\nFormulate corporate communication plans to enhance the organization reputation to sustain the business as a market leader in the industry\nDevelop corporate communications materials including but not limited to press release, newsletter, brochure, digital & social media materials, executives' speeches and presentations, ensure align with business imperatives\nDevise publicity and media plan for various business projects, establish solid media and stakeholder relationship\nAct as project leader to lead major corporate events and prepare press related and corporate materials\nJob Requirements:\n8-10 years experience in corporate communication and media management from sizable organization\nSolid experience in crisis and key stakeholder management is an advantage\nDynamic and strong ability to deal with challenges and changing priorities\nPresentable with excellent communication and interpersonal skills\nFluent spoken and written English, Cantonese & Mandarin\nInterested parties, please\u00a0CLICK HERE\u00a0to apply the position via Adecco website with your CV, or if you would like to have a further discussion about this role, please contact Cathy Yeung at 852-28996182.", "employment_types": ["Full Time", "Permanent"], "selling_points": [], "locations": ["Wan Chai"], "categories": ["Marketing / Public Relations", "Marketing - General / Support", "Marketing - Marketing Communication", "Digital Marketing"], "post_time": "2022-01-15T03:48:55Z", "salary": {"currency": null, "max": null, "min": null, "period": "monthly", "term": null}, "salary_visible": false, "title_keywords": ["marketing executive"], "responsibilities": ["social media", "business projects", "presentations", "develop", "communication", "plan", "plans"], "requirements": {"degrees": [], "majors": [], "languages": ["cantonese", "english", "mandarin"], "language_level": ["fluent"], "hard_skills": ["dynamic"], "soft_skills": ["communication", "dynamic", "communication and interpersonal skills", "presentable"], "languages_combined": [{"language": "cantonese", "language_level": ["fluent"]}, {"language": "english", "language_level": ["fluent"]}, {"language": "mandarin", "language_level": ["fluent"]}]}, "experience_required": {"duration": ["8-10 years"], "field": ["sizable organization", "corporate communication", "management", "media"]}}]