[{"job_id": "100003009055661", "location_code": "hk", "company": "Dah Chong Hong, Limited", "job_title": "Assistant Marketing Manager", "description": "The incumbent will be responsible for managing the operation of the department. He/she will also be a leading role for the following sales and marketing duties.\u00a0\n\nLead the team to achieve the preset sales target\nManage Principal and Suppliers for A&P budget and product development\nCommunicate closely with Key Account buyers for coordinating the trade marketing promotions and events\u00a0and ensure smooth trade operation execution.\nCommunicate with suppliers for product sourcing and new product development\u00a0\nExplore new sales channels for business grow\nTrack and monitor the sales performance of marketing activities\n\nThe ideal candidate should be:\u00a0\n\nUniversity graduate or above in Business Administration, Marketing or equivalent;\nAt least 3-5 years\u2019 relevant experience for product management or trade marketing in FMCG industry, food and beverage industry exposure is preferable\nProactive, creative and innovative with strong dedication to result;\nExcellent communication and presentation skills;\nExcellent planning and project management skills\nFamiliar with MS Application;\nProficient in written and spoken English and Chinese.\n\nPlease send your application with resume and expected salary to The HR Manager, Dah Chong Hong, Ltd, 8/F, DCH Building, 20 Kai Cheung Road, Kowloon Bay by post or email to click\u00a0\"Apply Now\".\u00a0\n\nWe are equal opportunities employer. Applicants who are not invited within 2 months may consider their application unsuccessful. All applicants may be considered for other suitable positions with DCH Group / CITIC Pacific Group and will be deleted from our files after 6 months from the date of application", "employment_types": ["Full Time", "Permanent"], "selling_points": [], "locations": ["Kowloon Bay"], "categories": ["Marketing / Public Relations", "Management", "Sales, CS & Business Devpt", "Account Servicing", "Sales - Sales Management"], "post_time": "2022-01-18T02:50:11Z", "salary": {"currency": null, "max": null, "min": null, "period": "monthly", "term": null}, "salary_visible": false, "title_keywords": ["assistant marketing manager"], "responsibilities": ["communicate with", "trade marketing", "management", "sales performance", "sales target", "budget", "monitor", "hr", "communication", "project management", "planning", "administration"], "requirements": {"degrees": ["university graduate or above"], "majors": ["marketing", "business administration"], "languages": ["english", "chinese"], "language_level": ["proficient"], "hard_skills": ["project management", "fmcg industry", "ms application"], "soft_skills": ["proactive", "responsible", "project management skills", "innovative", "communication", "presentation skills", "smooth", "creative", "ideal"], "languages_combined": [{"language": "english", "language_level": ["proficient"]}, {"language": "chinese", "language_level": ["proficient"]}]}, "experience_required": {"duration": ["at least 3-5 years"], "field": ["fmcg", "beverage industry", "product management", "marketing", "relevant experience", "food"]}}, {"job_id": "100003009053173", "location_code": "hk", "company": "China Mobile Hong Kong \u4e2d\u570b\u79fb\u52d5\u9999\u6e2f", "job_title": "Strategy Manager", "description": "CHINA MOBILE HONG KONG COMPANY LIMITED (\"CMHK\") is the wholly-owned subsidiary of China Mobile Limited (HKEx: 941) (NYSE: CHL), which ranks 65th on the Fortune Global 500.\n\nOur company strives to offer superior service experience and to become the preferable digital partner for customers. We are preserving an environment with trust, responsibility and caring. At CMHK, we commit to maximizing people\u2019s potential and paving the way toward success for every striver. We are now inviting high caliber professional to join us.\n\nDepartment: Entreprise Management\n\nIn this position, you will:\n\n\n\nAnalyze strategy information to drive long-term corporate strategic planning and execution\nConduct research on market competitive landscapes, benchmark digital performance and processes against industry best practice and identify digital opportunities to grow business\nCooperate with the company's business process development, improve the organizational structure and operational efficiency\nPerform gap analysis of digital asset capabilities to identify opportunities and improvements\nLead co-lead cross functional workstreams to create, implement and monitor process improvement, provide digital solution to help solve the business needs\n\nTo be successful in this position, you should meet the following requirements:\n\n\nGood technical background, Degree holder in Information Technology, Business Management or related disciplines\u00a0\nAt least 6 years' of working experience in strategy research and analytics, or digital project management field\nExpertise in digital management knowledge and strategy tactics, solution focused and service oriented Sound knowledge of innovative technologies, design patterns and keep abreast of latest technology trends\nGood command of written and spoken Chinese (must) and English (plus), strong skills in reporting, writing and communication\u00a0\nAble to work in challenging environment and under pressure to meet target lines\u00a0\nProactive, confident, innovative, organized and interactive, able to work independently\nBe able to communicate effectively with excellent presentation skills, strong written and oral skills, customer relationship skills including the ability to quickly create productive collaborations among key stakeholders\n\nWhen you work:\n\n5 days work\n8 hours/day\n\nWhat you enjoy:\n\nDouble pay\nDiscretionary Performance bonus\nLife insurance\nMedical insurance\nEducation subsidies\nBirthday gift\nMarriage leave\nBirthday leave\nStaff discount\n\n\nInterested\u00a0parties please send full resume with your availability, present and expected salary,\u00a0by clicking\u00a0Apply Now\u00a0button.\n\u00a0\u00a0\n\n\nCMHK is committed to be an equal opportunity employer. We offer exceptional benefits package and the opportunity to work in a challenging environment. Personal data provided by applicants will be treated strictly in accordance with our personal data policy and for recruitment purposes only.", "employment_types": ["Full Time", "Permanent"], "selling_points": ["14 or above AL, 5 days work week", "Staff Offer, Staff SIM", "13th mth salary, dis. performnace bonus"], "locations": ["Kwai Hing"], "categories": ["Professional Services", "Business Analysis / Data Analysis", "Management", "General Management", "Marketing / Public Relations", "Management"], "post_time": "2022-01-17T06:16:04Z", "salary": {"currency": null, "max": null, "min": null, "period": null, "term": null}, "salary_visible": false, "title_keywords": ["manager"], "responsibilities": ["reporting", "management", "strategic planning", "analysis", "monitor", "design", "communication", "project management", "business process", "insurance", "conduct research", "cooperate with"], "requirements": {"degrees": ["degree holder"], "majors": ["related disciplines", "business", "information technology"], "languages": ["english", "chinese"], "language_level": ["good command"], "hard_skills": ["business management", "plus", "analysis", "gap", "mobile", "project management"], "soft_skills": ["confident", "organized", "work independently", "proactive", "under pressure", "oral", "focused", "productive", "organizational", "communication", "project management", "presentation skills", "innovative", "superior"], "languages_combined": [{"language": "english", "language_level": ["good command"]}, {"language": "chinese", "language_level": ["good command"]}]}, "experience_required": {"duration": ["at least 6 years"], "field": ["digital", "project management", "research"]}}, {"job_id": "100003009054463", "location_code": "hk", "company": "The Wing On Department Stores (Hong Kong) Limited", "job_title": "Assistant Marketing Manager (Promotions)", "description": "Responsibilities:\n\nDevelop and implement strategic advertising and promotional plans for our department stores across all platforms\nExecute translation, copywriting and editing on marketing materials, press release and advertorials, etc.\nWorking closely with internal and external parties for retail promotion program to ensure smooth planning and timelines\nManage the A&P budget and ensure effective ROI\n\nRequirements:\n\nDegree holder in Marketing, Communications, Journalism or related disciplines\nAt least \u00a04 years or above relevant experience in retail industry, preferably in marketing promotional\u00a0events\nExperience and good knowledge of print production and graphic interpretation\u00a0\nStrong in corporate level writing skills\nSensibility to figures & designs, initiative and detail-minded\nExcellent interpersonal and communication skills in English & Chinese\nProactive and able to work efficiently under pressure with ability to meet deadlines\nProficient in using MS Office and Chinese word processing\nCandidate with more experience or qualification will be considered as Promotions Manager\nImmediately available is highly preferred\n\nCommensurate remuneration and other fringe benefits will be offered to the right candidate.\u00a0 Interested parties please send your\u00a0full\u00a0resume\u00a0including\u00a0expected salary\u00a0to Human Resources Division, 3/F, Wing On Godown Building, 1 Wang Kee Street, Kowloon Bay, Kowloon, or by click \"APPLY NOW\" button below.\n\n(Candidates not invited for interview within one month may consider their applications filed for future reference.\u00a0 All information collected will be used for recruitment purpose only and will be destroyed after 6 months.)", "employment_types": ["Full Time", "Permanent"], "selling_points": [], "locations": ["Kowloon Bay"], "categories": ["Media & Advertising", "Editorial / Journalism", "Marketing / Public Relations", "Management", "Print Media"], "post_time": "2022-01-17T09:39:33Z", "salary": {"currency": null, "max": null, "min": null, "period": "monthly", "term": null}, "salary_visible": false, "title_keywords": ["assistant marketing manager"], "responsibilities": ["advertising", "internal and external parties", "budget", "develop", "marketing materials", "editing", "promotional plans", "planning"], "requirements": {"degrees": ["degree holder"], "majors": ["journalism", "related disciplines", "marketing", "communications"], "languages": ["english", "chinese"], "language_level": ["excellent", "proficient"], "hard_skills": ["chinese word processing", "writing skills", "ms office"], "soft_skills": ["detail-minded", "communication skills", "proactive", "under pressure", "writing skills", "meet deadlines", "initiative", "interpersonal"], "languages_combined": [{"language": "english", "language_level": ["excellent"]}, {"language": "chinese", "language_level": ["excellent", "proficient"]}]}, "experience_required": {"duration": ["4 years"], "field": ["retail industry", "print", "marketing", "relevant experience", "graphic"]}}, {"job_id": "100003009054001", "location_code": "hk", "company": "T & Y Biologics Investment Limited", "job_title": "Marketing - Senior Officer/ Assistant Manager (Petmacy \u5bf5\u7269\u85e5\u599d)", "description": "Job Description\n\nThis role will work closely with Associate Director - Brand Marketing to build, strengthen and grow the Petmacy brand in HK and China region. The role will support to drive product marketing and consumer engagement initiatives to increase awareness, recruit new customer and drive conversion and transaction.\n\nPetmacy\u00a0\u5bf5\u7269\u85e5\u599d - T & Y Biologics Investment Limited\u00a0\n\nAbout Petmacy : Established by TnY Biotechnology Investment Co., Ltd. in 2018, the group is committed to sourcing worldwide high-quality pet food, pet necessities and manufacturing pet supplements for pets in HK.\n\nIn 2018, the Group cooperated with Watsons Hong Kong to launch \"Wats Petmacy\", which are now available in more than 130 locations. Of which, 2 \u201cWats Patmacy\u201d flagships store are located In Tseung Kwan O Plaza and Aberdeen Centre. In the future, the Group will actively continue to develop its pet products business and market through different channels and cooperation platforms.\n\nKey Roles & Responsibilities\n\nWork collaboratively with a range of internal and external stakeholders including social media team, Event team, Product marketing team, Sales, legal and external agencies.\nFully understand customer journey and hit the customer at right time\nLead a small team of 2 to provide project management support to set marketing calendar, initiate and execute marketing campaigns. Work closely with product marketing team to understand each of the brands under Petmacy and drive awareness and transaction.\nDevelop Promotion Calendar for chain stores, shops and ecommerce shop. Create and support marketing campaigns to drive sales and traffic.\nMeasure and report performance of all marketing campaigns\nCollaborate with different parties (Eg. IT) for e-commerce platform revamping\nSupport offline media placement with agency for various campaigns including OOH, print, Direct Mail etc. Event support may be needed occasionally.\nLead implementation and execution CRM campaign communications to retain customer\n\n\n\nWhat you must have\n\nUniversity Degree, preferably in Marketing, Communications, Business or related field. At least 4 years relevant working experience in a similar capacity, preferably in FMCG or ecommerce industry\nKnowledge of the latest growth practices including paid acquisition, technical SEO, SEM, etc.\nStrong analytical skills with the ability to interpret and utilize data to guide and shape campaigns\nStrong written and verbal communication skills with the ability to compile and present cohesive reports with clear action items and insights\nWith CRM project management experience is a plus\nWith good FMCG based media relationship is a plus\n\n\nThis is a very rewarding and exciting opportunity. We offer an attractive remuneration to the successful candidate(s). Please forward your\u00a0resume with\u00a0present and expected salary\u00a0by clicking\u00a0\u201cApply Now\u201d\u00a0for further consideration.\n\n**All information collected will be treated in strict confidence and will only be used for recruitment related purpose.**", "employment_types": ["Full Time", "Permanent"], "selling_points": ["Lead a small team to provide management support", "Develop Promotion Calendar", "Create and support marketing campaigns"], "locations": ["Kwun Tong"], "categories": ["Marketing / Public Relations", "Management", "Marketing - Direct Marketing", "Marketing - General / Support"], "post_time": "2022-01-17T08:00:53Z", "salary": {"currency": null, "max": null, "min": null, "period": "monthly", "term": null}, "salary_visible": false, "title_keywords": ["senior officer", "assistant manager"], "responsibilities": ["collaborate with", "social media", "seo", "data", "lead a small team", "quality", "implementation", "develop", "communication", "project management", "reports", "marketing campaigns", "sem", "drive sales", "e-commerce platform", "report"], "requirements": {"degrees": ["university degree"], "majors": ["business", "marketing", "communications"], "languages": [], "language_level": [], "hard_skills": ["small", "plus", "seo", "e-commerce", "analytical skills", "project management", "sem"], "soft_skills": ["communication skills", "cohesive", "analytical skills", "clear", "committed", "project management"], "languages_combined": []}, "experience_required": {"duration": ["at least 4 years"], "field": ["ecommerce", "project management", "fmcg", "relevant working experience"]}}, {"job_id": "100003009051691", "location_code": "hk", "company": "Goahead Professional Training Company Limited", "job_title": "Full Time - Event Assistant", "description": "\u5de5\u4f5c\u5167\u5bb9\uff1a\u7c4c\u5099\u65e5\u5e38\u6d3b\u52d5\u3001\u6d3b\u52d5\u69cb\u601d\u3001\u843d\u5be6\u3001\u57f7\u884c\u53ca\u62db\u52df\u3001\u88fd\u4f5cbackdrop\u3001\u6d3b\u52d5Poster\u3001\u6d3b\u52d5\u62cd\u651d\u3001\u526a\u63a5\u3001\u88fd\u4f5c\u77ed\u7247\u7b49\u7b49\n\n\u5de5\u4f5c\u6642\u9593\uff1a\u661f\u671f\u4e00\u81f3\u4e94 9:30am - 6:00pm\uff081 \u500b\u6708\u9700\u8981\u6709 1 \u5929\u661f\u671f\u516d\u5de5\u4f5c\uff09\n\n\u5de5\u4f5c\u5730\u9ede\uff1a\u9ec3\u57d4\n\n\u5de5\u8cc7\uff1a\uff5e$15000/\u6708 (\u8996\u4e4e\u5de5\u4f5c\u8868\u73fe\uff09\n\n\u5b78\u6b77\uff1a2\u5e74\u641e\u6d3b\u52d5\u7d93\u9a57\u00a0(\u6709\u53c3\u8207\u5927\u5b78\u4e0a\u838a\u3001\u5546\u6703 / \u6709\u62cd\u651d\u526a\u63a5\u7d93\u9a57\u512a\u5148)\n\n\u798f\u5229\uff1adouble pay\u3001MPF\n\nContact\uff1aWing 56639812", "employment_types": ["Full Time"], "selling_points": ["IG/FB: goahead.mdrt", "\uff5e$15000/\u6708 (\u8996\u4e4e\u5de5\u4f5c\u8868\u73fe\uff09", "wing 56639812"], "locations": ["Hung Hom"], "categories": ["Marketing / Public Relations", "Management", "Public Relations - Event Management", "Media & Advertising", "Photography / Video"], "post_time": "2022-01-16T21:50:49Z", "salary": {"currency": null, "max": null, "min": null, "period": "monthly", "term": null}, "salary_visible": false, "title_keywords": ["event assistant"], "responsibilities": [], "requirements": {"degrees": [], "majors": [], "languages": [], "language_level": [], "hard_skills": [], "soft_skills": [], "languages_combined": []}, "experience_required": {"duration": [], "field": []}}, {"job_id": "100003009054436", "location_code": "hk", "company": "Changing Young Lives Foundation", "job_title": "Development Manager", "description": "The Job:\n\nIn charge of the full spectrum of fundraising and communications duties of the Organization\nFormulate and implement a strategic fundraising and marketing plan and calendar\nDevelop and maintain sustainable relationships with donors and corporate partners\nOversee the daily operation of a small fundraising team\nReport to Executive Director and perform ad hoc duties as assigned\n\nThe Person:\n\nDegree holder in marketing or communications\nMinimum 5 to 8 years of hands-on experience in fundraising and event management\nExperience in executing large-scale charity event a plus\nKnowledge of new media and digital marketing\nFamiliar with design and editing software a definite advantage\nSolid exposure to media relations or corporate affairs\u00a0preferable\nCreative and able to convert ideas into realities\nExcellent command of spoken and written English and Chinese\nProficient in MS Office\nRemarkable presentation and inter-personal skills\nSelf-motivated, good team player, able to work independently and under pressure\nImmediately available highly preferable\n\nCompetitive remuneration will be offered to the right candidate along with a five-day work week and medical insurance. Please send full resume with current and expected salary by clicking \u201cApply Now\u201d. All personal information will only be used for recruitment purpose.", "employment_types": ["Full Time", "Permanent"], "selling_points": [], "locations": ["Sham Shui Po"], "categories": ["Marketing / Public Relations", "Management", "Marketing - Marketing Communication", "Public / Civil", "Social Services - Community / Non-profit Organization"], "post_time": "2022-01-17T09:33:16Z", "salary": {"currency": null, "max": null, "min": null, "period": "monthly", "term": null}, "salary_visible": false, "title_keywords": ["manager"], "responsibilities": ["ad hoc duties", "daily operation", "develop", "marketing plan", "maintain", "report"], "requirements": {"degrees": ["degree holder"], "majors": ["marketing", "communications"], "languages": ["english", "chinese"], "language_level": ["excellent"], "hard_skills": ["plus", "ms office", "charity"], "soft_skills": ["self-motivated", "good team player", "work independently", "under pressure", "inter-personal skills", "hands-on", "creative", "presentation"], "languages_combined": [{"language": "english", "language_level": ["excellent"]}, {"language": "chinese", "language_level": ["excellent"]}]}, "experience_required": {"duration": ["minimum 5 to 8 years"], "field": ["management"]}}, {"job_id": "100003009052821", "location_code": "hk", "company": "China Mobile Hong Kong \u4e2d\u570b\u79fb\u52d5\u9999\u6e2f", "job_title": "Senior Marketing Executive, Marketing planning (prepaid)", "description": "CHINA MOBILE HONG KONG COMPANY LIMITED (\"CMHK\") is the wholly-owned subsidiary of China Mobile Limited (HKEx: 941) (NYSE: CHL), which ranks\u00a065th on the Fortune Global 500.\n\nOur company strives to offer superior service experience and to become the preferable digital partner for customers. We are preserving an environment with trust, responsibility and caring. At CMHK, we commit to maximizing people\u2019s potential and paving the way toward success for every striver. We are now inviting high caliber professional to join us.\n\nDivision: Marketing\n\nIn this position, you will:\n\nTo explore the opportunities and provide recommendations/ insight of prepaid business.\nParticipate in the formulation of marketing strategy which is in line with company objectives\nSupport and provide report on customers\u2019 portfolio evaluation, behavior analysis, sales performance to develop appropriate marketing programs.\nWork with internal departments to formulate new products/ service/ offers roll-out campaigns.\nMonitor competitors; keep track on the market trend\nAssist in preparation of presentation materials, written reports and proposals\nOther ad hoc duties assigned by management\n\nTo be successful in this position, you should meet the following requirements:\n\nBachelor\u2019s degree in Business Administration, Marketing or equivalent disciplines\nMinimum 4 years of working experience\u00a0in consumer marketing / technology / Telecom industry\nExperience in implement end to end acquisition program, developing marketing plans and campaigns\nGood understanding in business operations\nGood coordination, project management, multitasking and presentation skills\nKnowledge in IT system is a plus\nSelf-motivated, attention to details, multi-tasking and able to work under pressure\nFluency in written and spoken English, Cantonese and Mandarin\nCandidate with less experience may consider as Marketing Executive\n\nWhen you work:\n\n5 days work\n8 hours/day\n\nWhat you enjoy:\n\nDouble pay\nDiscretionary Performance bonus\nLife insurance\nMedical insurance\nEducation subsidies\nBirthday gift\nMarriage leave\nBirthday leave\nStaff discount\n\nCMHK is committed to be an equal opportunity employer. We offer exceptional benefits package and the opportunity to work in a challenging environment. Personal data provided by applicants will be treated strictly in accordance with our personal data policy and for recruitment purposes only.\n\nPlease submit your application to us by clicking the APPLY NOW button and send your full resume with your availability, current and expected salary to us.", "employment_types": ["Full Time", "Permanent"], "selling_points": ["14 AL, 5 days work week", "double pay, dis. performance bonus", "Staff SIM, Staff Offer"], "locations": ["Kwai Hing"], "categories": ["Marketing / Public Relations", "Management", "Marketing - Brand / Product Management", "Marketing - Direct Marketing"], "post_time": "2022-01-17T16:20:50Z", "salary": {"currency": null, "max": null, "min": null, "period": null, "term": null}, "salary_visible": false, "title_keywords": ["senior marketing executive"], "responsibilities": ["marketing plans", "operations", "evaluation", "administration", "ad hoc duties", "work under pressure", "sales performance", "monitor", "developing", "develop", "reports", "report", "management", "provide recommendations", "analysis", "preparation of presentation materials", "project management", "coordination", "insurance"], "requirements": {"degrees": ["degree", "bachelor"], "majors": ["marketing", "business administration"], "languages": ["cantonese", "english", "mandarin"], "language_level": ["fluency"], "hard_skills": ["mobile", "analysis", "project management", "plus"], "soft_skills": ["self-motivated", "work under pressure", "project management", "presentation skills", "multi-tasking", "committed", "coordination", "attention to details", "presentation", "superior"], "languages_combined": [{"language": "cantonese", "language_level": ["fluency"]}, {"language": "english", "language_level": ["fluency"]}, {"language": "mandarin", "language_level": ["fluency"]}]}, "experience_required": {"duration": ["minimum 4 years"], "field": ["digital", "marketing", "developing"]}}, {"job_id": "100003009055821", "location_code": "hk", "company": "HKT Consumer Group", "job_title": "Senior Marketing Manager (Smart Charge)", "description": "Smart Charge, a new service brand run by HKT and CLP, aims to offer one-stop and hassle-free electric vehicle (EV) charging solutions for end-users and commercial entities in Hong Kong to meet the increasing market demand.\u00a0\n\nIt is a challenging and dynamic opportunity for an all rounded marketer to work for this brand which is striving for differentiation and continual growth.\u00a0\n\nYour role:\n\nExplore partnership opportunities / initiatives and manage day-to-day partnership operations and logistics;\nNurture long term relationships with key strategic partners to foster consistent support to Smart Living products via joint promotions or events, including lead generation events and external corporate events;\nBuild and manage scalable partnership programs to drive broad adoption of Smart Charge products and services;\nCollaborate with various internal and external parties for planning and executing marketing campaigns, including the planning and execution of operation logistic , advertising and communication tools from concept to implementation;\nEnsure marketing messages are synchronized across different business units and monitor\u00a0 marketing campaigns to ensure communications are streamlined and aligned;\nStay informed of news and marketing activities in\u00a0 relevant markets.\u00a0\u00a0\n\nTo succeed in this role:\n\nUniversity graduate in Marketing, Communications, Business Administration or related disciplines;\nMinimum 8 years working experience in Product or Service Marketing and/or related field;\nProven track record of driving partnership strategy, preferably in luxury product industry, prestige members clubs and automotive industries;\nStrong business acumen with exceptional logical thinking, highly motivated and presentable\nDemonstrated initiative and problem solving skills with a service focus\nExcellent communication and interpersonal skills, with ability to work effectively and cross-functionally with people at all levels\nKnowledge or interest in automobile industry\nProficiency in both spoken and written English and Cantonese\nCandidates with more experience will be considered as Assistant Vice President\n\nIf you have the desire for an exciting and rewarding career, please send us your resume immediately, quoting the reference number, your present and expected salary via email to Human Resources.", "employment_types": ["Full Time"], "selling_points": [], "locations": ["Quarry Bay"], "categories": ["Marketing / Public Relations", "Management", "Marketing - Brand / Product Management"], "post_time": "2022-01-18T02:59:03Z", "salary": {"currency": null, "max": null, "min": null, "period": "monthly", "term": null}, "salary_visible": false, "title_keywords": ["senior marketing manager"], "responsibilities": ["collaborate with", "administration", "advertising", "operations", "internal and external parties", "monitor", "implementation", "communication", "logistics", "executing", "marketing campaigns", "communication tools", "planning"], "requirements": {"degrees": ["university graduate"], "majors": ["related disciplines", "marketing", "business administration", "communications"], "languages": ["cantonese", "english"], "language_level": ["proficiency"], "hard_skills": ["focus", "problem solving skills", "dynamic", "acumen"], "soft_skills": ["work effectively", "focus", "presentable", "communication", "dynamic", "motivated", "communication and interpersonal skills", "business acumen", "problem solving skills", "initiative"], "languages_combined": [{"language": "cantonese", "language_level": ["proficiency"]}, {"language": "english", "language_level": ["proficiency"]}]}, "experience_required": {"duration": ["minimum 8 years"], "field": ["related", "marketing"]}}, {"job_id": "100003009054008", "location_code": "hk", "company": "The Marketing Store Worldwide (Asia) Ltd", "job_title": "Director, Brand Partnerships and Licensing, APMEA", "description": "The Marketing Store Worldwide (TMS), a HAVI Company, is a Global Customer Engagement Agency and Sourcing Company, with areas of expertise that include consumer promotions, toys and premiums, shopper marketing, digital platforms and innovation. TMS now ranks among the largest toy manufacturers in the world.\u00a0\n\n\n\nWHAT IS THIS ROLE ABOUT\n\nThe Senior Director, Brand Partnerships and Licensing, APMEA is a key stakeholder of the Global Brand Partnership Team. With a solid background on entertainment and licensing, the Senior Director, Brand Partnerships and Licensing, APMEA will be in charge of successfully leading market Calendar Planning Process while continuously working with the Global Brand Partnership Team to ensure markets alignment with overall McDonald\u2019s Strategy and Business Goals.\n\nAreas of responsibilities include:\n\nLead communications with market\u2019s Happy Meal Client\nLead and develop markets calendar proposals.\nLead and develop industry insights for the market - while supporting global insights reports\nSupport the Global Brand Partnership team with market program performance insights\n\nJob Relationships:\n\nReports to: Vice President, Brand Partnerships\nRelationships and Communications:\u00a0Regular and ongoing interactions with TMS colleague in various agency departments such as: Global Brand Partnership Team, Planning/Strategy, Global Havi Analytics Team, Account Team and TMS counterparts in Asia/MEA/LATAM/Europe\n\nWHAT YOU\u2019LL BRING TO TMS\n\nYouth & Family Calendar Planning (Market)\n\nResponsible for leading all communications with market\u2019s Happy Meal Client.\nResponsible for leading and developing market\u2019s calendar planning recommendations.\nEarn and keep each clients\u2019 respect and confidence as a trusted advisor bringing continuous value to their business.\nAcquire and build-upon knowledge of and be conversant in clients\u2019 business \u2013 their key issues, competitive situation, and industry trends.\nDemonstrate confidence and authority as the day-to-day voice of the agency for assigned projects.\nDevelop and/or leads client presentations for all assigned work/execution.\nAssist in establishing thought leadership/POV specific to a project or initiative.\nParticipate in client meetings to provide a project perspective and input\nLicensing and Entertainment Industry Analytics (Market)\u00a0\nResponsible for tracking market\u2019s local trends: family\u2019s trends, consumer trends.\nResponsible for keeping clients updated on markets entertainment & licensing environment. Proactively develop local insights report to ensure TMS expertise across the globe.\nResponsible for developing markets post-trade show reports\nResponsible for tracking market\u2019s competitive landscape.\u00a0\n\nProgram Performance Analytics (Market)\u00a0\n\nResponsible for tracking market\u2019s program performance.\nSupport Global Brand Partnership team on Global Program Performance report by adding market\u2019s insights and pov.\u00a0\n\nGlobal Brand Partnership Team (Market)\u00a0\n\nDevelop and nurture the relationship with the Global Brand Partnership team by:\nUpdating the team on market\u2019s calendar planning needs\nParticipate from global meetings with recommendations and opportunities to keep expanding agency\u2019s global approach.\nSupport Global Team with markets insights on entertainment & licensing industry as part of the teams\u2019 efforts to provide global insights.\n\n\u00a0SKILLS AND EXPEREINCE WE\u2019D LIKE YOU TO HAVE\u00a0\n\nExperience of working in an integrated agency environment, client side or as a Marketing Manager, Family experience would be of benefit (but not essential)\nAble to lead by example, be solutions orientated with a continuous-learning approach\nEntrepreneurial spirit \u2013 taking and creating opportunities with clients and across the agency alike\nStrong strategic and critical thinking skills with demonstrable track record\nExcellent presentation skills (writing, reviewing and delivering) and ability to express ideas with clarity, confidence and logical reasoning\nAble to work well and prioritise under pressure\nProven ability to develop solutions that address client\u2019s business issues and opportunities\nYou thrive on taking ownership of your projects and deliver best-in-class executions\nSolid experience in an agency-side partnerships role, as either a seasoned Senior Partnerships Manager or Partnership Account Director\nMeticulous attention to detail and passion for understanding & following process. Ability to review and recommend on procedural efficiencies that will help us deliver for our client and partners.\nExperience analysing, synthesizing, and utilising data to make recommendations that drive engagement. Working with a data analyst to do so\nUnderstanding of the agency\u2019s philosophy and vision\nComputer skills (Proficient in Microsoft Word, Excel and PowerPoint + key email, schedule and internet applications, etc.)\nCompetent in accessing online databases and conducting Internet research\nWorks under frequent time pressures and distractions\u00a0\n\nInterested parties please send your full resume with present and expected salary by clicking \"Apply Now\". All personal data will be used for recruitment purpose only.\n\nOnly shortlisted candidates will be contacted.\u00a0\n\nWe are the Marketing Store and we would love to meet you!\u00a0", "employment_types": ["Full Time", "Permanent"], "selling_points": ["Solid background on entertainment and licensing", "Lead calendar planning within the region", "Work & align with Global Brand Partnership Team"], "locations": ["Kowloon Bay"], "categories": ["Marketing / Public Relations", "Management", "Marketing - Brand / Product Management", "Marketing - General / Support"], "post_time": "2022-01-17T08:01:56Z", "salary": {"currency": null, "max": null, "min": null, "period": "monthly", "term": null}, "salary_visible": false, "title_keywords": ["director"], "responsibilities": ["consumer trends", "make recommendations", "business goals", "communications with", "tracking", "ideas", "data", "planning process", "teams", "developing", "presentations", "develop", "review", "reports", "schedule", "databases", "report", "planning"], "requirements": {"degrees": [], "majors": [], "languages": [], "language_level": [], "hard_skills": ["excel", "microsoft word", "presentations", "powerpoint", "make", "computer skills", "databases"], "soft_skills": ["make recommendations", "meticulous", "confidence", "under pressure", "responsible", "passion for", "competent", "prioritise", "presentation skills", "learning", "attention to detail", "leadership", "initiative"], "languages_combined": []}, "experience_required": {"duration": [], "field": ["agency", "marketing"]}}, {"job_id": "100003009052728", "location_code": "hk", "company": "Richemont Asia Pacific Limited - Cartier", "job_title": "Regional HJ Business & Talent Development Director", "description": "RESPONSIBILITIES\n\n\n\n\nDirect the development and growth of HJ Business\n\nProvide direction and high level strategies for Asia to achieve Regional HJ target\nStrategize with markets to ensure good performance and assist with achieving set business objectives, budgets and estimates\nDesign and develop regional seminars for HJ coordinators to formulate an agile platform to share synergies and expertise (including competition intelligence)\nStrategize with market HJ and retail departments in reaching HJ sales target through recurring sales and event activations with strategic direction\n\n\n\nClient Database Management\n\nLeverage regional client database with efficiency to enhance HJ business\nDirect client segmentation strategies with local market with regional focus\n\n\n\nBuilding Client relations\n\nStrategize action plan (together with market heads) to achieve business objectives\nInitiate, manage and maintain contact with regional third parties to further develop and grow HJ business in the region\n\n\n\nBuilding Business relations \u2013 Sales Expert community development\n\nProvide direction on HJ community development working together with market heads with concrete action plan\nImplement annual think tank / boot camp with market management to strategize new plans to build business\nGive direction for an encompassing and targeted booster program to raise level of competence in areas of jewelry and technical skills, client relationship building, lifestyle experiences (to include trainings on art, auction, GIA)\n\n\n\nInformation and Intelligence sharing\n\nShare and follow-up of the international HJ strategy within countries\nShare competitive intelligence (on a regional level)\n\n\n\nREQUIRED COMPETENCIES\n\nBachelor degree in Business Administration \u2013 Marketing or equivalent is preferred\n10+ years working experience in marketing and business development, either luxury field or other high-end industry\nStrong analytical skills, details oriented and positive work attitude\nStrong negotiation skills with excellent communication and interpersonal skills\nComputer skills: proficient in Microsoft office, AS400 would be a plus\nEnglish (mandatory), Cantonese (required), Mandarin (required). French (if possible)\nProactive in attaining market, customer and competitor knowledge\nAble to multi-task, reliable, positive attitude and able to work under pressure\nAbility to work well with different cultures and enjoy work/travelling", "employment_types": ["Full Time"], "selling_points": [], "locations": ["Not Specified"], "categories": ["Sales, CS & Business Devpt", "Business Development", "Management", "General Management", "Marketing / Public Relations", "Management"], "post_time": "2022-01-17T03:49:43Z", "salary": {"currency": null, "max": null, "min": null, "period": "monthly", "term": null}, "salary_visible": false, "title_keywords": ["director"], "responsibilities": ["budgets", "management", "provide direction", "work under pressure", "sales target", "design and develop", "develop", "communication", "maintain", "contact", "database", "plan", "plans", "administration"], "requirements": {"degrees": ["degree", "bachelor"], "majors": ["marketing", "business administration"], "languages": ["cantonese", "english", "french", "mandarin"], "language_level": [], "hard_skills": ["plus", "agile", "microsoft office", "analytical skills", "computer skills", "focus"], "soft_skills": ["multi-task", "agile", "analytical skills", "positive attitude", "negotiation skills", "communication and interpersonal skills", "reliable", "technical skills", "focus", "proactive", "positive work attitude", "work under pressure"], "languages_combined": [{"language": "cantonese", "language_level": []}, {"language": "english", "language_level": []}, {"language": "french", "language_level": []}, {"language": "mandarin", "language_level": []}]}, "experience_required": {"duration": ["10+ years"], "field": ["marketing", "business development"]}}, {"job_id": "100003009052964", "location_code": "hk", "company": "Telford International Co Ltd", "job_title": "Assistant Brand Manager/ Brand Manager \u2013 Alcoholic Beverage Division", "description": "Responsibilities:\n\nFormulate marketing plan and agree the marketing strategies with brand owners in a viable manner\nAble to initiate and execute marketing and promotional activities in on-& off-trade\nMonitor the brand performance and A&P spend against the target\nReview shipment and depletion forecasts regularly to ensure healthy inventory control\nAble to conduct product training and meet up trade customers when needed\nWilling to work during night and sometimes during weekend for special events\n\n\u00a0Requirements:\n\nUniversity Graduate with preferable marketing as major\nMin. 5 years in marketing, trade marketing or senior sales role in lifestyle industry or other FMCG industry,\u00a0in\u00a0alcohol\u00a0industry is highly preferred\nCommercially sensible with good negotiation skill\nHighly self-motivated, strong team player and do not resist drinking\nGood interpersonal and communication skills\nFluency in written and spoken English and Chinese\nCandidate with less experience will be considered as Assistant Brand Manager\n\n\n\nWe offer attractive remuneration package and career prospects plus 5-day week and medical insurance. Interest parties; please forward your full resume with\u00a0Expected Salary to us.\u00a0\n\nAll data collected shall be solely for recruitment purpose.\n\nWebsite\u00a0\u00a0 : \u00a0\u00a0http://www.telford.com.hk/", "employment_types": ["Full Time", "Permanent"], "selling_points": ["University Graduate with Marketing Major", "5 years in Marketing Related Exp. in Alcohol Ind.", "Attractive Package with Excellent Career Path"], "locations": ["Kwai Hing"], "categories": ["Sales, CS & Business Devpt", "Business Development", "Marketing / Public Relations", "Management", "Marketing - Brand / Product Management"], "post_time": "2022-01-17T04:43:06Z", "salary": {"currency": null, "max": null, "min": null, "period": "monthly", "term": null}, "salary_visible": false, "title_keywords": ["manager", "assistant"], "responsibilities": ["marketing strategies", "review", "monitor", "marketing plan", "inventory control", "promotional activities"], "requirements": {"degrees": ["university graduate"], "majors": ["marketing"], "languages": ["english", "chinese"], "language_level": ["fluency"], "hard_skills": ["fmcg industry"], "soft_skills": ["communication skills", "self-motivated", "negotiation skill", "team player", "interpersonal"], "languages_combined": [{"language": "english", "language_level": ["fluency"]}, {"language": "chinese", "language_level": ["fluency"]}]}, "experience_required": {"duration": [], "field": ["brand"]}}, {"job_id": "100003009055171", "location_code": "hk", "company": "NP Solution Limited", "job_title": "Digital Marketing Manager - Hong Kong Listed Company", "description": "Company Profile\nOur client is a well-established Hong Kong Listed Company with multiple businesses across the globe. They are now looking for a Digital Marketing Manager to join their team to cope with the digital advancement.\u00a0\n\n\nJob Responsibilities\n\nPlan and execute marketing content and campaigns, including social media content, copywriting, website ecommerce and app campaigns\nDevelop digital marketing strategies and on brand campaigns to drive revenue\u00a0\nFormulate\u00a0online strategy for build branding and marketing planning\nResponsible for reporting, analytics, dashboards and provide insights for improving digital key metrics\nLiaise with external agencies to optimize go-to-market strategy and sustain growth for across regions\n\nRequirements\n\nBachelor\u2019s Degree in Marketing, Business Management or related fields\nAt least 3-year of relevant experience, especially in Digital Marketing\nPractical experience Google Analytics and comfortable with data visualization tool such as PowerBI\nMotivated self-starter and good project management skill\nProficiency in both spoken and written English and Chinese\n\n\n\n\nAll information provided will be treated in strict confidence and used solely for recruitment purpose.\n\nFor more job opportunities, please visit our website:\u00a0https://npsl.com.hk/\n\n\n\n", "employment_types": ["Full Time"], "selling_points": ["Hong Kong Listed Company", "Dynamic Working Environment", "Competitive Package | Work Life Balance"], "locations": ["Not Specified"], "categories": ["Marketing / Public Relations", "Management", "Marketing - Marketing Communication", "Digital Marketing"], "post_time": "2022-01-18T01:37:11Z", "salary": {"currency": null, "max": null, "min": null, "period": "monthly", "term": null}, "salary_visible": false, "title_keywords": ["digital marketing manager"], "responsibilities": ["reporting", "provide insights", "digital marketing strategies", "website", "develop", "social media content", "plan", "liaise with", "planning"], "requirements": {"degrees": ["degree", "bachelor"], "majors": ["business", "marketing"], "languages": ["english", "chinese"], "language_level": ["proficiency"], "hard_skills": ["business management", "google analytics", "project management", "data visualization"], "soft_skills": ["motivated", "confidence", "project management skill"], "languages_combined": [{"language": "english", "language_level": ["proficiency"]}, {"language": "chinese", "language_level": ["proficiency"]}]}, "experience_required": {"duration": ["at least 3-year"], "field": ["relevant experience", "digital marketing"]}}, {"job_id": "100003009056065", "location_code": "hk", "company": "ConnectedGroup Limited", "job_title": "APAC Market Lead (Sports Brand 40K)", "description": "Our client is a global sports brand and they are now hiring a market lead across the Asia Pacific market.\n\nThe Market Lead will the main contact within APAC and will own and manage the creation of a marketing plan, calendar and execution for consumer activations with key consumer groups.\n\nJob Duties\n\nCo-ordinates the delivery of localized campaigns from briefing, planning and execution of the campaign and ensure distributors follow approval processes and brand guidelines.\n\n\nIn partnership with the distributors help build a GTM seasonal plan and deliverables to support the growth of all consumer access points.\n\n\nMonitor and track markets are using the approved assets and creative assets as per global guidelines\nShare all updated global assets for marketing campaigns and product launches, GTM calender updates with the distributors in the APAC markets\nTracks and monitors social media, retail campaigns and initiatives\nDevelop and manage the running club plans and marketing support calendar including Sports Marketing that supports brand's goals and aligns with the market place strategy in the APAC distribution markets\n\n\nPlan and ensure in-store consumer experiences and pop-up initiatives are aligned to global brand guidelines and APAC strategy\n\n\nIdentify and plan long term opportunities to engage consumers and deliver bold and impactful experiences online, in retail and through events\n\nQualifications:\n\n\nBachelor's Degree in Marketing or related field, or equivalent combination of education and experience.\n5+ years related marketing experience with a global sports or fashion brand\n\nHigh level of Proficiency in Business communication (Written and Spoken)\nSolid regional or international market experience\n\nInterested individuals please send CV (word format) to Eleanor Chan (Eleanor . Chan @connectedgroup.com) for more information", "employment_types": ["Full Time", "Permanent"], "selling_points": ["manage marketing plan", "calendar and execution", "consumer activations"], "locations": ["Not Specified"], "categories": ["Marketing / Public Relations", "Management", "Marketing - Brand / Product Management", "Marketing - General / Support"], "post_time": "2022-01-18T03:14:44Z", "salary": {"currency": null, "max": null, "min": null, "period": "monthly", "term": null}, "salary_visible": false, "title_keywords": ["lead"], "responsibilities": ["social media", "guidelines", "monitor", "develop", "communication", "marketing plan", "brand guidelines", "contact", "plan", "marketing campaigns", "plans", "planning"], "requirements": {"degrees": ["degree", "bachelor"], "majors": ["marketing"], "languages": [], "language_level": [], "hard_skills": ["access points", "word"], "soft_skills": ["communication", "creative", "bold"], "languages_combined": []}, "experience_required": {"duration": ["5+ years"], "field": ["brand", "related", "education", "marketing", "retail"]}}, {"job_id": "100003009052556", "location_code": "hk", "company": "AOSource Company Limited", "job_title": "Digital Marketing Manager / Assistant Manager (APAC)   (DM-0117-sh-JDBP)", "description": "Our client is a MNC group,\u00a0 Current they are looking for potential candidate to join their Digital Marketing team in Hong Kong.\n\n\u00a0Responsibilities;\n\nTo drive digital Campaign and program for Global Group Team\u00a0 or APAC team in Hong Kong.\nTo develop and maintain digital strategy for Website and social media.\nDevelop and create digital media strategy for the group.\nTo formulate strategic online for build branding and marketing planning.\nTo measure and report on performance of all marketing advertisement and campaigns.\nTo provide product brand information and business direction with Asia Region.\nExcellent communcation with English is must\u00a0\nIf less experience to be considered as Assistant Manager\u00a0\nRequirements:\n\nDegree or Above in Business / Marketing or related discipline;\n\nAbout 4+ years working experience in Digital Marketing,\u00a0 Asia\u00a0Regional experience is must;\u00a0\nCurrent experience in managing Digital Strategy and Campaign;\nGood experience in dealing with various country business partner;\nExperience in either CRM , Adobe Creative Suite, Google Analystics, Google Ads is a plus;\nGood experience in email marketing/ data analysis and Salesforce Marketing Cloud is plus\nExcellent spoken and written communication skill in English;\nWork independently and good team player;\nLess experience to be considered as Assistant Manager.\nOur client will offer competitive remuneration package and good career prospects to the potential candidate, interested parties please quote ref.no. DM-0117-sh-JDBP and submit your resume to Ms Fung by our email or enquiry with Tel:3428-6121.\n\n\nAll profiles are handled with strictest confidentiality. Shortlisted candidates would be notified", "employment_types": ["Full Time", "Permanent"], "selling_points": ["MNC Group", "Digital Marketing /Asia Region/ Social Media", "Exp.in Google Analytics, Google Ads, CRM etc"], "locations": ["Not Specified"], "categories": ["Marketing / Public Relations", "Management", "Marketing - Brand / Product Management", "Digital Marketing"], "post_time": "2022-01-17T03:24:42Z", "salary": {"currency": null, "max": null, "min": null, "period": "monthly", "term": null}, "salary_visible": false, "title_keywords": ["digital marketing manager", "assistant manager"], "responsibilities": ["social media", "website", "develop", "maintain", "report", "planning"], "requirements": {"degrees": ["degree or above"], "majors": ["business", "marketing"], "languages": ["english"], "language_level": ["excellent"], "hard_skills": ["plus", "analysis", "salesforce", "adobe creative suite"], "soft_skills": ["communication skill", "good team player", "work independently", "creative"], "languages_combined": [{"language": "english", "language_level": ["excellent", "excellent"]}]}, "experience_required": {"duration": ["4+ years"], "field": ["business partner", "data analysis", "marketing", "digital marketing", "digital"]}}, {"job_id": "100003009056012", "location_code": "hk", "company": "Match Talent Limited", "job_title": "\u623f\u5730\u4ea7\u8425\u9500\u603b\u76d1", "description": "Duties\nHandle service inquiries raised by clients\nMaking outbound calls regarding our services\nProvide sales and administrative support\nEnlarge and extend potential market segments in a proactive approach\nRequirements\n\nDegree holder in Business or related discipline\nMinimum 2 years\u2019 relevant experience in financial industry preferred\nExperience in customer service is an advantage\nSelf-motivated and service-oriented with good communication and interpersonal skills\nFluency in written and spoken Chinese\nBenefits\n\n\nAttractive remuneration package\u00a0will be offered to the right candidates\nHigh commission, monthly performance bonus, year-end performance bonus and pension benefits\nWell-structured training programs and comprehensive training platform\nClear career path and fast-track promotion to management level\nMedical benefits and training allowances", "employment_types": ["Full Time", "Permanent"], "selling_points": ["Strong Real Estate Company", "13 months pay", "Five-day work"], "locations": ["Others - China"], "categories": ["Marketing / Public Relations", "Management", "Marketing - Marketing Communication", "Property / Real Estate", "Others"], "post_time": "2022-01-18T03:11:30Z", "salary": {"currency": "HKD", "max": 159999, "min": 120000, "period": "monthly", "term": null}, "salary_visible": true, "title_keywords": [], "responsibilities": ["administrative support"], "requirements": {"degrees": ["degree holder"], "majors": ["business"], "languages": ["chinese"], "language_level": ["fluency"], "hard_skills": [], "soft_skills": ["self-motivated", "customer service", "communication and interpersonal skills", "service-oriented"], "languages_combined": [{"language": "chinese", "language_level": ["fluency"]}]}, "experience_required": {"duration": ["minimum 2 years"], "field": ["customer service", "financial industry", "relevant experience"]}}, {"job_id": "100003009051727", "location_code": "hk", "company": "China Mobile Hong Kong \u4e2d\u570b\u79fb\u52d5\u9999\u6e2f", "job_title": "Assistant Marketing Manager, Marketing planning (postpaid)", "description": "\u5c97\u4f4d\u804c\u8d23\uff1a\n\n1\u3001\u5236\u8ba2\u9500\u552e\u7b56\u7565\uff1a\u8fdb\u884c\u5e02\u573a\u9884\u6d4b\uff0c\u5236\u8ba2\u62d3\u5c55\u53ca\u92b7\u552e\u7b56\u7565\n\n2\u3001\u6267\u884c\u9500\u552e\u7b56\u7565\uff0c\u7ba1\u7406\u5e76\u6307\u5bfc\u9500\u552e\u56e2\u961f\uff0c\u8fbe\u6210\u5e02\u573a\u76ee\u6807\u3001\u5b8c\u6210\u56de\u6b3e\n\n3\u3001\u9500\u552e\u4f53\u7cfb\u7ba1\u7406\uff1a\u6839\u636e\u516c\u53f8\u9500\u552e\u7b56\u7565\uff0c\u5efa\u7acb\u9500\u552e\u7f51\u7edc\u53ca\u6e20\u9053\u7ba1\u7406\n\n4\u3001\u5e02\u573a\u63a8\u5e7f\uff1a\u5efa\u7acb\u7cbe\u51c6\u7684\u5e02\u573a\u63a8\u5e7f\u6d3b\u52a8\uff0c\u8425\u9020\u5e02\u573a\u73af\u5883\uff0c\u63d0\u5347\u9879\u76ee\u4e0e\u4ea7\u54c1\u54c1\u724c\uff0c\u652f\u6301\u9500\u552e\u589e\u957f\n\n5\u3001\u5ba2\u6237\u5173\u7cfb\u7ba1\u7406\uff1a\u901a\u8fc7\u5404\u79cd\u670d\u52a1\u6d3b\u52a8\u63d0\u9ad8\u5ba2\u6237\u6ee1\u610f\u5ea6\uff0c\u5de9\u56fa\u5ba2\u6237\u5173\u7cfb\u5e73\u53f0\uff0c\u638c\u63e1\u7ec8\u7aef\u5ba2\u6237\n\n\u4efb\u804c\u8981\u6c42\uff1a\n\n1\u3001\u672c\u79d1\u53ca\u4ee5\u4e0a\u5b66\u5386\uff0c5\u5e74\u4ee5\u4e0a\u5546\u4e1a\u9879\u76ee\u3001\u516c\u5bd3\u8425\u9500\u8d1f\u8d23\u4eba\u7ecf\u9a8c\n\n2\u3001\u5177\u77e5\u540d\u5f00\u53d1\u5546\u4e00\u3001\u4e8c\u7ebf\u57ce\u5e02\u5927\u578b\u7efc\u5408\u4f53\u9879\u76ee\u7d93\u9a57\n\n3\u3001\u654f\u9510\u7684\u5e02\u573a\u610f\u8bc6\u3001\u5e94\u53d8\u80fd\u529b\u3001\u72ec\u7acb\u5f00\u62d3\u5e02\u573a\u7684\u80fd\u529b\n\n4\u3001\u4f18\u79c0\u7684\u56e2\u961f\u80fd\u529b\u3001\u5b66\u4e60\u80fd\u529b\u3001\u6c9f\u901a\u80fd\u529b\u3001\u534f\u8c03\u80fd\u529b\u548c\u9886\u5bfc\u6c34\u5e73\uff0c\u5584\u4e8e\u534f\u8c03\u8425\u9500\u56e2\u961f\n\n5\u3001\u5177\u5907\u77e5\u540d\u623f\u5730\u4ea7\u9805\u76ee\u6210\u529f\u64cd\u76e4\u53ca\u9500\u552e\u4e1a\u7ee9\u80cc\u666f\u8005\u4f18\u5148", "employment_types": ["Full Time", "Permanent"], "selling_points": ["16 AL, 5 days work week", "double pay, dis. performance bonus", "Staff SIM, Staff Offer"], "locations": ["Kwai Hing"], "categories": ["Marketing / Public Relations", "Management", "Marketing - Brand / Product Management", "Marketing - Direct Marketing"], "post_time": "2022-01-16T21:51:12Z", "salary": {"currency": null, "max": null, "min": null, "period": null, "term": null}, "salary_visible": false, "title_keywords": ["assistant marketing manager"], "responsibilities": [], "requirements": {"degrees": [], "majors": [], "languages": [], "language_level": [], "hard_skills": [], "soft_skills": [], "languages_combined": []}, "experience_required": {"duration": [], "field": []}}, {"job_id": "100003009046817", "location_code": "hk", "company": "Kingstar International Trading Ltd", "job_title": "Marketing Manager", "description": "CHINA MOBILE HONG KONG COMPANY LIMITED (\"CMHK\") is the wholly-owned subsidiary of China Mobile Limited (HKEx: 941) (NYSE: CHL), which ranks\u00a065th on the Fortune Global 500.\n\nOur company strives to offer superior service experience and to become the preferable digital partner for customers. We are preserving an environment with trust, responsibility and caring. At CMHK, we commit to maximizing people\u2019s potential and paving the way toward success for every striver. We are now inviting high caliber professional to join us.\n\nDivision: Marketing\n\nIn this position, you will:\n\nTo explore the opportunities and provide recommendations/ insight of Medium to high end market segment.\nParticipate in the formulation of marketing strategy which is in line with company objectives\nAssist in develop the promotion plan for Mid to high end segment.\nSupport and provide report on customers\u2019 portfolio evaluation, behavior analysis, sales performance to develop appropriate marketing programs.\nWork with internal departments to formulate new products/ service/ offers roll-out campaigns.\nMonitor competitors; keep track on the market trend\nAssist in preparation of presentation materials, written reports and proposals\nOther ad hoc duties assigned by management\n\nTo be successful in this position, you should meet the following requirements:\n\nBachelor\u2019s degree in Business Administration, Marketing or equivalent disciplines\nMinimum\u00a06 years of working experience\u00a0in consumer marketing / technology / Telecom industry\nExperience in implement end to end acquisition program, developing marketing plans and campaigns\nGood understanding in business operations\nGood coordination, project management, multitasking and presentation skills\nKnowledge in IT system is a plus\nSelf-motivated, attention to details, multi-tasking and able to work under pressure\nFluency in written and spoken English, Cantonese and Mandarin\nCandidate with less experience may consider as Senior Marketing Executive\n\nWhen you work:\n\n5 days work\n8 hours/day\n\nWhat you enjoy:\n\nDouble pay\nDiscretionary Performance bonus\nLife insurance\nMedical insurance\nEducation subsidies\nBirthday gift\nMarriage leave\nBirthday leave\nStaff discount\n\nCMHK is committed to be an equal opportunity employer. We offer exceptional benefits package and the opportunity to work in a challenging environment. Personal data provided by applicants will be treated strictly in accordance with our personal data policy and for recruitment purposes only.\n\nPlease submit your application to us by clicking the APPLY NOW button and send your full resume with your availability, current and expected salary to us.", "employment_types": ["Full Time", "Permanent"], "selling_points": ["Plan and execute marketing objectives", "8 years experience in beauty / retail is preferred", "Able to demonstrate outstanding marketing skills"], "locations": ["Tsim Sha Tsui"], "categories": ["Sales, CS & Business Devpt", "Business Development", "Marketing / Public Relations", "Management", "Sales - Sales Management"], "post_time": "2022-01-16T21:50:19Z", "salary": {"currency": null, "max": null, "min": null, "period": "monthly", "term": null}, "salary_visible": false, "title_keywords": ["marketing manager"], "responsibilities": ["marketing plans", "operations", "plan", "evaluation", "administration", "ad hoc duties", "work under pressure", "sales performance", "monitor", "developing", "develop", "reports", "report", "management", "provide recommendations", "analysis", "preparation of presentation materials", "project management", "coordination", "insurance"], "requirements": {"degrees": ["degree", "bachelor"], "majors": ["marketing", "business administration"], "languages": ["cantonese", "english", "mandarin"], "language_level": ["fluency"], "hard_skills": ["mobile", "analysis", "project management", "plus"], "soft_skills": ["self-motivated", "work under pressure", "project management", "presentation skills", "multi-tasking", "committed", "coordination", "attention to details", "presentation", "superior"], "languages_combined": [{"language": "cantonese", "language_level": ["fluency"]}, {"language": "english", "language_level": ["fluency"]}, {"language": "mandarin", "language_level": ["fluency"]}]}, "experience_required": {"duration": ["minimum 6 years"], "field": ["digital", "marketing", "developing"]}}, {"job_id": "100003009052278", "location_code": "hk", "company": "Cathay Pacific Airways Ltd", "job_title": "Brand Manager", "description": "We are seeking a highly motivated and dynamic candidate for the position of Marketing Manager. As the head of marketing, you will build a strong marketing team and collaborate with different strategic partners to deliver brand value and drive growth.\nResponsibilities:\nLead the marketing team to develop and execute annual marketing and digital plans to drive brand development & sales growth\nDeliver business impact by managing A&P budget efficiency, prioritizing marketing campaigns to maximize ROI\nEstablish and oversee e-commerce and social media (KOL management, endorsement, video production, website enhancement)\nDevelop an in-depth understanding to anticipate market trends and understand consumer purchase behavior to be able to identify the gap in current marketing strategy and explore new marketing opportunities\nAnalyze market landscape, improve brand awareness & positioning through positive brand building strategies\nManage media relationship; coordinate with internal and external parties to explore partnership opportunities for the company\nSupport sales & marketing activities including regular reports preparation, market intelligence consolidation, data analysis etc.\nRequirements:\nDegree Holder in Marketing, Communications, Business Management or related disciplines\nMinimum 8 years of solid & relevant experience in Brand & Digital marketing, preferably in Beauty / FMCG\nDeep understanding of digital and prestige beauty industry\nStrong at leading, planning, organizing, controlling and prioritizing skill\nExcellent communication and presentation capability\nAble to work in a fast-paced and dynamic environment\nProficiency in both spoken & written English, Cantonese & Chinese\nWe Offer\n5 day work week\nDouble Pay\nMedical benefits\nStaff Free Goods & staff purchase discount\nExcellent Career development opportunities in a growing organization with a portfolio of 5 brands\n\n\nInterested parties, please send your full resume and expected salary by clicking \"Apply Now\".\nPersonal data will be used for recruitment purpose only.", "employment_types": ["Full Time", "Permanent"], "selling_points": ["8 years\u2019 experience in Brand, Design", "Development of the Cathay\u2019s brand strategy", "Travel Benefits, 5-day work, Medical Benefits"], "locations": ["Lantau Island"], "categories": ["Design", "Others", "Marketing / Public Relations", "Management", "Marketing - Brand / Product Management"], "post_time": "2022-01-17T02:38:30Z", "salary": {"currency": null, "max": null, "min": null, "period": "monthly", "term": null}, "salary_visible": false, "title_keywords": ["manager"], "responsibilities": ["social media", "management", "support sales & marketing activities", "video production", "budget", "coordinate with", "website", "internal and external parties", "develop", "regular reports preparation", "data analysis", "purchase", "marketing campaigns", "maximize roi", "plans", "market intelligence consolidation"], "requirements": {"degrees": ["degree holder"], "majors": ["business", "related disciplines", "marketing", "communications"], "languages": ["cantonese", "english", "chinese"], "language_level": ["proficiency"], "hard_skills": ["business management", "dynamic"], "soft_skills": ["dynamic environment", "deep", "communication", "presentation", "prioritizing"], "languages_combined": [{"language": "cantonese", "language_level": ["proficiency"]}, {"language": "english", "language_level": ["proficiency"]}, {"language": "chinese", "language_level": ["proficiency"]}]}, "experience_required": {"duration": ["minimum 8 years"], "field": ["fmcg", "brand", "relevant experience", "beauty", "digital marketing"]}}, {"job_id": "100003009052649", "location_code": "hk", "company": "Talent Preneur Management Consultancy Co. Limited", "job_title": "Project Manager/ Assistant Project Manager (PRC & HK business)", "description": "Reports to:\u00a0Head of Brand & Content\nDepartment:\u00a0Brand, Insights & Marketing Communications\u00a0\u00a0\n\nRole Introduction\u00a0\n\nBecoming a brand-led organisation is core to Cathay Pacific strategy, thus placing the brand team at the heart of the company. \u00a0We ensure that we remain true to our brand \u2013 lighting it up at every opportunity; amplifying, enhancing and refining it across every customer and employee touchpoint. Every interaction that our customers and employees have with our brand influences their perception of it. We therefore work on a wonderfully diverse set of projects which will stimulate, challenge and reward any candidate deeply passionate about branding.\u00a0\n\nUnder our brand platform Move Beyond, our purpose is to move people forward in life through our ability to connect them to meaningful people, places and experiences. \u00a0\n\nThe brand team helps to translate this brand promise and strategy into everything that we do. We work with the insights team to really understand our targeted customers\u2019 needs, desires and behaviours, translating the insights into our brand strategy and associated experience.\u00a0\n\nWe are looking for an exceptionally talented Brand Manager, brimming with energy to help the Cathay Group of brands to strengthen over time, build a deeper connection with our customers and a sense of pride internally. This role presents an incredible opportunity to make a significant mark on the brand\u2019s future, the full customer and employee experience, as well as your own branding career.\n\nKey Responsibilities\n\nBrand strategy & translation\n\nSupport Head of Brand & Content on the development of the Cathay\u2019s brand strategy, including brand positioning, segmentation, definition and articulation\nLead a diverse set of projects, with multiple business areas to translate our brand into different parts of the customer and employee experience\nLead Cathay\u2019s brand partnership strategy\nEstablish new processes and guidelines to help define how different areas of the business should interact with and represent the brand\n\nBrand Measurements\n\nWork closely with the insights team to measure the performance of our brand across all customer touch-points, including the items we have rolled out, to identify areas to improve and inoculate our brand\n\nMerchandise & collaterals\n\nLead a team of product designers in the design and development of branded merchandise and collaterals, working closely with marketing and commercial teams from ideation to design\nWork closely with our content team to craft compelling stories to raise awareness on our branded products\n\nBrand identity\n\nManage and preserve the Cathay Pacific Group\u2019s brand identity system, developing new sub-brands as required\nManage aircraft livery design\u00a0\nManage and lead the implementation of our trademark protection strategy\n\nRequirements\n\nWe\u2019re seeking someone who has the experience, passion and drive to bring our brand purpose to life. Someone who is thrilled with ideas and prospects to build love for our brand. We\u2019re looking for someone who is deeply passionate about branding and is brave about ideas, whilst being clear-eyed about what it takes to achieve better work. Holding oneself, and those around you, to high standards and taking pride in the quality of work are prerequisites for this role.\u00a0\n\nThe candidate will have a strong understanding of brand and design, with an ability to clearly articulate design modifications and improvements in accordance with Cathay\u2019s brand proposition.\n\nIn terms of practical experience and qualifications, the candidate should have at least 8 years\u2019 experience in Brand, Design or a Customer Experience Design and hold a bachelor\u2019s degree in marketing, design or communications related field. We are looking for someone who has worked at a branding agency, helping numerous brands bring their brand purpose to life.\u00a0\n\nBeing an exceptional communicator in written and spoken English skills is a must, Chinese would be incredible.\u00a0\n\nFinally, we\u2019re a premium travel lifestyle brand so we\u2019re naturally looking for someone who shares our absolute love for all things travel.\n\nApplication Deadline: 28 January 2022\n\nPersonal & Application Information\n\nCathay Pacific is an Equal Opportunities Employer. Personal data provided by job applicants will be used strictly in accordance with our personal data policy and for recruitment purposes only. Candidates not notified within eight weeks may consider their application unsuccessful. All related information will be kept in our file for up to 24 months. A copy of our Personal Information Collection Statement will be provided upon request by contacting our Data Protection Officer.\n\nPlease note that with effect from 1 December 2021, all employees must be vaccinated in order to access Cathay City and all other Cathay Group Company premises in Hong Kong. Consideration will be given to those who are unable to get vaccinated for valid medical reasons.\n\nApplication Deadline: 28 January 2022", "employment_types": ["Full Time", "Permanent"], "selling_points": [], "locations": ["Shatin Area"], "categories": ["Marketing / Public Relations", "Management", "Marketing - Brand / Product Management", "Digital Marketing"], "post_time": "2022-01-17T03:38:42Z", "salary": {"currency": "HKD", "max": 69999, "min": 45000, "period": "monthly", "term": null}, "salary_visible": true, "title_keywords": ["project manager", "assistant project manager"], "responsibilities": ["guidelines", "teams", "developing", "design", "implementation", "lead a team"], "requirements": {"degrees": ["degree", "bachelor"], "majors": ["marketing", "communications", "design"], "languages": ["english", "chinese"], "language_level": [], "hard_skills": [], "soft_skills": ["clear", "articulate", "communicator", "passionate about"], "languages_combined": [{"language": "english", "language_level": []}, {"language": "chinese", "language_level": []}]}, "experience_required": {"duration": ["at least 8 years"], "field": ["related", "marketing", "brand", "design"]}}, {"job_id": "100003009055894", "location_code": "hk", "company": "Links International", "job_title": "Equity Research VP (TMT ,Consumer )", "description": "Job Description\n\nResponsibilities:\n\nIdentify and create new business opportunities in both local & Mainland China\nDevelop new business/ project including but not limited to prospects researching and determining the project scope, goals, and deliverables.\nLead the planning and implementation of the project/business according to the agreed timelines and budget\nAct as the key person to coordinate with both internal and external business parties\nUnderstand clients\u2019 needs and clarify specific requirements of each project\nDevelop a detailed project plan which to fulfill client\u2019s expectations\nExecute project monitoring and cost control \u00a0\nManage large and diverse teams\n\nRequirements:\n\nBachelor degree or above\nAt least 5-year experiences under Project Management with client facing responsibilities\nFamiliar with China market will be an advantage\nExperienced in Servicing/ Medical/ Education/ Immigration industry is a plus\nExperienced in working with different business stakeholders, cross-function teams and familiar with user experience\nAble to work in a rapidly changing environment where continuous innovation is desired\nDemonstrated experience and implementation success with various project methodologies\nEnergetic, flexible and team player\nBig-picture thinking and vision\nLess experience candidate will be considered as Assistant Project Manager\nCandidate with Mainland China background is welcomed\n\n\u8077\u8cac\uff1a\n\n\u5728\u9999\u6e2f\u53ca\u4e2d\u570b\u5e02\u5834\u767c\u6398\u53ca\u5275\u9020\u71df\u5546\u6a5f\u6703\n\u767c\u5c55\u65b0\u7684\u696d\u52d9/\u9805\u76ee\uff0c\u5305\u62ec\u4f46\u4e0d\u9650\u65bc\u4e86\u89e3\u65b0\u71df\u5546\u524d\u666f\u53ca\u5236\u5b9a\u9805\u76ee\u5167\u5bb9\n\u6839\u64da\u6642\u9593\u8868\u548c\u9810\u7b97\uff0c\u8ca0\u8cac\u9818\u5c0e\u9805\u76ee\u7d71\u7c4c\u548c\u57f7\u884c\u6307\u5b9a\u5de5\u4f5c\n\u5354\u8abf\u5167\u90e8\u548c\u5916\u90e8\u696d\u52d9\u90e8\u9580\n\u6536\u96c6\u3001\u4e86\u89e3\u548c\u78ba\u8a8d\u5ba2\u4eba\u9700\u6c42\uff0c\u78ba\u4fdd\u9805\u76ee\u65b9\u6848\u6eff\u8db3\u5ba2\u6236\u9700\u8981\n\u76e3\u7ba1\u9805\u76ee\u904b\u4f5c\u8ddf\u63a7\u5236\u6210\u672c\n\u7ba1\u7406\u5718\u968a\n\n\u5165\u8077\u8981\u6c42\uff1a\n\n\u00a0\u00a0\u00a0\u00a0\u00a0\u00a0\u00a0\u00a0 \u5927\u5b78\u53ca\u4ee5\u4e0a\u5b78\u6b77\n\u00a0\u00a0\u00a0\u00a0\u00a0\u00a0\u00a0\u00a0 5-10\u5e74\u4ee5\u4e0a\u9805\u76ee\u7ba1\u7406\u5de5\u4f5c\u7d93\u9a57\uff0c\u8ca0\u8cac\u9762\u5411\u5ba2\u6236\u7684\u5de5\u4f5c\n\u00a0\u00a0\u00a0\u00a0\u00a0\u00a0\u00a0\u00a0 \u719f\u6089\u4e2d\u570b\u5e02\u5834\u512a\u5148\n\u00a0\u00a0\u00a0\u00a0\u00a0\u00a0\u00a0\u00a0 \u5177\u6709\u670d\u52d9\u6027\u3001\u91ab\u7642\u3001\u6559\u80b2\u6216\u79fb\u6c11\u7b49\u76f8\u95dc\u884c\u696d\u7684\u7d93\u9a57\u6703\u662f\u512a\u52e2\n\u00a0\u00a0\u00a0\u00a0\u00a0\u00a0\u00a0\u00a0 \u8207\u4e0d\u540c\u696d\u52d9\u76f8\u95dc\u8005\u5408\u4f5c\u3001\u8de8\u8077\u80fd\u5718\u968a\u5408\u4f5c\u7684\u7d93\u9a57\uff0c\u719f\u6089\u7528\u6236\u9ad4\u9a57\n\u00a0\u00a0\u00a0\u00a0\u00a0\u00a0\u00a0\u00a0 \u80fd\u5728\u6301\u7e8c\u5275\u65b0\u548c\u5feb\u901f\u8b8a\u5316\u7684\u74b0\u5883\u4e2d\u5de5\u4f5c\n\u00a0\u00a0\u00a0\u00a0\u00a0\u00a0\u00a0\u00a0 \u6709\u6210\u529f\u5be6\u65bd\u9805\u76ee\u7684\u7d93\u9a57\n\u00a0\u00a0\u00a0\u00a0\u00a0\u00a0\u00a0\u00a0 \u5145\u6eff\u6d3b\u529b\u3001\u9748\u6d3b\u548c\u5718\u968a\u5408\u4f5c\u7cbe\u795e\n\u00a0\u00a0\u00a0\u00a0\u00a0\u00a0\u00a0\u00a0 \u64c1\u6709\u5927\u5c40\u601d\u7dad\u548c\u9858\u666f\n\u00a0\u00a0\u00a0\u00a0\u00a0\u00a0\u00a0\u00a0 \u7d93\u9a57\u8f03\u5c11\u8005\u6703\u88ab\u8003\u616e\u70ba\u9805\u76ee\u767c\u5c55\u526f\u7d93\u7406\n\u00a0\u00a0\u00a0\u00a0\u00a0\u00a0\u00a0\u00a0 \u6b61\u8fce\u6709\u5167\u5730\u80cc\u666f\u4eba\u58eb\u7533\u8acb", "employment_types": ["Full Time", "Permanent"], "selling_points": ["Attractive Package", "TMT ,Consumer Focus", "Big 4 welcome"], "locations": ["Central & Western Area"], "categories": ["Banking / Finance", "Financial Services", "Marketing / Public Relations", "Management", "Risk Management"], "post_time": "2022-01-18T03:03:38Z", "salary": {"currency": null, "max": null, "min": null, "period": "monthly", "term": null}, "salary_visible": false, "title_keywords": [], "responsibilities": ["develop new business", "business opportunities", "budget", "coordinate with", "implementation", "project plan", "develop", "monitoring", "teams", "cost control", "planning"], "requirements": {"degrees": ["degree or above", "bachelor"], "majors": [], "languages": [], "language_level": [], "hard_skills": ["project management", "plus"], "soft_skills": ["flexible", "project management", "team player", "energetic"], "languages_combined": []}, "experience_required": {"duration": ["at least 5-year"], "field": ["project management", "business"]}}, {"job_id": "100003009055828", "location_code": "hk", "company": "Michael Page", "job_title": "Digital Marketing Manager - FMCG Global Marketing", "description": "Equity Research VP ( TMT , Consumer )\n\nAbout the client\n\nOur client is a leading PRC Securities, they are currently looking for an equity research vice president for their Greater China region.\n\nResponsibilities:\n\nPrepare various investment and market reports on different companies, mainly focusing on China/HK TMT ,Consumer Sector;\nGenerate investment ideas and contribute investment recommendations to senior management\nConduct research framework and business models assessment, develop and maintain sector-specific databases\nBuild up financial modeling and valuation\nProvide research supports to institutional clients and top management\nAssist in ad hoc projects and assignments.\n\nRequirements:\n\nBachelor degree in Accounting, Finance, Economics , or related discipline\n3 -5 years relevant experiences of research analysis, or relevant industry experience ( TMT, Consumer )\nDemonstrate interest/enthusiasm and insights in New Economy-related investing\nStrong financial modelling skills\nExcellent command of English and Chinese", "employment_types": ["Full Time", "Permanent"], "selling_points": ["Digital Marketing", "Global Exposure", "Career Growth Opportunities"], "locations": ["Not Specified"], "categories": ["Marketing / Public Relations", "Management", "Marketing - Marketing Communication", "Digital Marketing"], "post_time": "2022-01-18T02:59:27Z", "salary": {"currency": null, "max": null, "min": null, "period": "monthly", "term": null}, "salary_visible": false, "title_keywords": ["digital marketing manager"], "responsibilities": ["valuation", "management", "ideas", "financial modeling", "develop", "maintain", "reports", "ad hoc projects", "databases", "senior management", "conduct research"], "requirements": {"degrees": ["degree", "bachelor"], "majors": ["finance", "accounting", "economics"], "languages": ["english", "chinese"], "language_level": ["excellent"], "hard_skills": ["analysis"], "soft_skills": [], "languages_combined": [{"language": "english", "language_level": ["excellent"]}, {"language": "chinese", "language_level": ["excellent"]}]}, "experience_required": {"duration": ["3 -5 years"], "field": ["research"]}}, {"job_id": "100003009053735", "location_code": "hk", "company": "Hang Seng Bank Ltd", "job_title": "Manager, Marketing Planning & Governance", "description": "Our client is a well-regarded FMCG Brand. They are currently expanding their global business and seeking for a Digital Marketing Manager to join their global marketing team.\n\nClient Details\n\nOur client is a well-regarded FMCG Brand. They are currently expanding their global business and seeking for a Digital Marketing Manager to join their global marketing team. The position is the team leader to plan and implement global digital marketing campaigns and work closely with global team to develop digital marketing frameworks.\n\nDescription\n\nOur client is a well-regarded FMCG Brand. They are currently expanding their global business and seeking for a Digital Marketing Manager to join their global marketing team. The position is the team leader to plan and implement global digital marketing campaigns and work closely with global team to develop digital marketing frameworks.\n\nProfile\n\nThe successful candidate would be an experienced marketing manager for multinational company. Candidate with FMCG, Health and Beauty or pharmaceutical portfolio will be considered first. Our client is looking for a creative and brand thinking person with outstanding leadership skill to join them as a team leader. Public speaking and presentation ability are highly valued to this role. Fluency in English and Cantonese is required. Degree level qualification in marketing, business studies, or other related subjects is preferred.\n\nJob Offer\n\nWork for a global company that provides you with opportunity to expand your career. You will be provided with an attractive salary package and compensation.\n\nTo apply online please click the 'Apply' button below. For a confidential discussion about this role please contact Smania Wu on +852 3412 4858.", "employment_types": ["Full Time", "Permanent"], "selling_points": [], "locations": ["Not Specified"], "categories": ["Marketing / Public Relations", "Management", "Others"], "post_time": "2022-01-17T07:25:30Z", "salary": {"currency": null, "max": null, "min": null, "period": "monthly", "term": null}, "salary_visible": false, "title_keywords": ["manager"], "responsibilities": ["digital marketing campaigns", "develop", "digital marketing", "contact", "plan"], "requirements": {"degrees": ["degree"], "majors": ["business", "marketing"], "languages": ["cantonese", "english"], "language_level": ["fluency"], "hard_skills": [], "soft_skills": ["leadership skill", "creative", "presentation"], "languages_combined": [{"language": "cantonese", "language_level": ["fluency"]}, {"language": "english", "language_level": ["fluency"]}]}, "experience_required": {"duration": [], "field": []}}, {"job_id": "100003009054080", "location_code": "hk", "company": "Smart Charge", "job_title": "Marketing Executive/ Senior Marketing Executive (Smart Charge)", "description": "Marketing\n\nHang Seng\u2019s Marketing function is responsible for formulating marketing strategies and implementing marketing initiatives to build the brand of Hang Seng Bank, acquire new customers, strengthen customer loyalty to build long term relationships, and provide professional marketing support to different businesses to promote a comprehensive suite of products and services offered by the Bank.\n\nWe are currently seeking a high caliber professional to join our department as Manager, Marketing Planning & Governance.\n\n\n\nPrincipal responsibilities\n\nManage marketing budget and key performance indicators across the Bank and monitor business performance based on both financial and non-financial prospective\nLead the financial resource planning and cost monitoring process by liaising with different stakeholders from local, regional and global level\nDeliver accurate, quality and timely management reports to facilitate business planning\u00a0\nProvide guidance and support to Marketing teams on the Bank\u2019s governance framework, policies and procedures, risk and control management as well as relevant regulatory requirements\nAct as a change champion to lead and coordinate transformation project to improve process flow and enhance operational efficiency of Marketing\nRequirements\nUniversity degree in Business Administration, Marketing, or a related discipline\u00a0\nSolid experience in Banking/ Marketing/ Risk Management field. Past experience in cost management/ project management is a plus\nA fast learner with strong analytical and problem solving skills. Well organized and pay attention to details to handle complicated matters\u00a0\nSelf-motivated, able to work independently under pressure\u00a0\nExcellent interpersonal skills and presentation skills\nProficiency in both English and Chinese with sound knowledge on application software such as MS Excel and PowerPoint\nGreat sense of ownership and servicing mindset to ensure efficient and effective customer service processes\n\nIf you would like to explore other opportunities at Hang Seng Hong Kong, please visit\u00a0www.hangseng.com/careers/\u00a0for details.\n\nThe health and safety of our employees and candidates is very important to us. Due to the current situation related to the Novel Coronavirus (2019-nCoV), we\u2019re leveraging our digital capabilities to ensure we can continue to recruit top talent at the HSBC Group.\u00a0 As your application progresses, you may be asked to use one of our digital tools to help you through your recruitment journey.\u00a0 If so, one of our\u00a0 Resourcing colleagues will explain how our video-interviewing technology will be used throughout the recruitment process and will be on hand to answer any questions you might have.\n\nAll information provided by applicants will be used only for recruitment purposes and will be used strictly in accordance with the Bank's personal data policies, a copy of which may be obtained by the applicant upon request. Unless otherwise instructed in writing by the applicant concerned, applicants may be considered for other suitable positions within the Bank and its related companies. The personal data of unsuccessful job applicants may be retained for a maximum of two years from the date when the job application is rejected and such data may be retained for a longer period if there is a subsisting reason that obliges the Bank to do so, after which the personal data will be destroyed.\u00a0Wholesale Credit Risk Analytics Department", "employment_types": ["Full Time", "Permanent"], "selling_points": ["Degree in Marketing, Communications or Business", "3-year relevant experience", "Smart Charge - new service brand runs by HKT & CLP"], "locations": ["Quarry Bay"], "categories": ["Marketing / Public Relations", "Management", "Marketing - Brand / Product Management", "Marketing - Marketing Communication"], "post_time": "2022-01-17T08:19:54Z", "salary": {"currency": null, "max": null, "min": null, "period": null, "term": null}, "salary_visible": false, "title_keywords": ["senior marketing executive", "marketing executive"], "responsibilities": ["cost", "control", "management", "policies", "regulatory requirements", "budget", "monitor", "monitoring", "liaising with", "quality", "teams", "procedures", "management reports", "coordinate", "provide guidance", "planning"], "requirements": {"degrees": ["university degree"], "majors": ["marketing", "business administration"], "languages": ["english", "chinese"], "language_level": ["proficiency"], "hard_skills": ["plus", "powerpoint", "reason", "project management", "ms excel", "problem solving skills"], "soft_skills": ["efficient", "self-motivated", "work independently", "under pressure", "well organized", "project management", "analytical and problem solving skills", "presentation skills", "interpersonal skills", "customer service", "attention to details", "novel", "fast learner"], "languages_combined": [{"language": "english", "language_level": ["proficiency"]}, {"language": "chinese", "language_level": ["proficiency"]}]}, "experience_required": {"duration": [], "field": ["risk management", "management", "project management", "marketing", "banking"]}}, {"job_id": "100003009054612", "location_code": "hk", "company": "Sun Life Hong Kong Ltd", "job_title": "Management Trainee Program (Degree Holder in Any Disciplines)", "description": "Smart Charge, a new service brand runs by HKT and CLP, aims to offer one-stop and hassle-free electric vehicle (EV) charging solutions for end-users and commercial entities in Hong Kong to meet the increasing market demand.\n\nIt is a challenging and dynamic opportunity for an all rounded marketer to work for this brand which is striving for differentiation and continual growth.\n\nThe Job:\n\nThe incumbent will be responsible for business development and marketing of new products and services related to Smart Charge in consumer market. Major job duties include:\n\nAssist the Marketing team in planning of marketing programs to promote Smart Charge service.\nCoordinate closely with various parties and channels with on target customer identification, to ensure smoothly program execution for marketing campaigns and events / roadshows related process and logistics.\nManage communication and campaigns across digital and traditional channels, from online, social media to retail shops and location based activities.\nPreparing marketing collaterals, conduct Marketing campaign performance tracking and evaluation\nEnsure brand messages are synchronized with partners and monitor all marketing campaigns to ensure communications are streamlined and aligned.\nCollect market intelligence, conduct media evaluations and provide analyses/insights to facilitate development of marketing strategy and project assessments\n\n\u00a0The Person:\n\nUniversity graduate in Marketing, Communications, Business Administration or relevant discipline\nMinimum of 3-year experience in of Product, Digital or Service Marketing experience\nGood problem solving skills and able to work under tight timeline\nSelf-motivated and able to accomplish multiple tasks with minimal supervision\nEffective interpersonal and communication skills and able to work with people at all levels\nProficiency in both spoken and written English and Cantonese\nKnowledge or interest in automobile industry and the market trend\n\nIf you have the desire for an exciting and rewarding career, please send us your resume immediately, quoting the reference number, your present and expected salary via email to Human Resources.", "employment_types": ["Full Time"], "selling_points": ["5 day works", "$17,000-$30,000", "Competitive pay"], "locations": ["Hung Hom"], "categories": ["Banking / Finance", "Corporate Finance", "Management", "General Management", "Marketing / Public Relations", "Management"], "post_time": "2022-01-17T10:14:23Z", "salary": {"currency": "HKD", "max": 29999, "min": 17000, "period": "monthly", "term": null}, "salary_visible": true, "title_keywords": ["management trainee"], "responsibilities": ["social media", "tracking", "marketing collaterals", "monitor", "coordinate", "communication", "logistics", "marketing campaigns", "evaluation", "planning"], "requirements": {"degrees": ["university graduate"], "majors": ["marketing", "business administration", "communications"], "languages": ["cantonese", "english"], "language_level": ["proficiency"], "hard_skills": ["problem solving skills"], "soft_skills": ["communication skills", "self-motivated", "multiple tasks", "problem solving skills", "interpersonal"], "languages_combined": [{"language": "cantonese", "language_level": ["proficiency"]}, {"language": "english", "language_level": ["proficiency"]}]}, "experience_required": {"duration": ["minimum of 3-year"], "field": ["digital", "marketing"]}}, {"job_id": "100003009048848", "location_code": "hk", "company": "Sims Trading Co Ltd", "job_title": "Business Manager", "description": "Job Highlights\n\nBachelor degree holder in all disciplines\nWell-development career ladder\nFive-day work\n\nJob Description\n\nYou will enjoy working at Sun Life if you are with vision, energy and targets, join us and be part of a dynamic team and create values together.\n\nAs the leader in wealth management, offering innovative and intelligent solutions to thousands of individual and businesses in Hong Kong, China, Canada, Malaysia, Indonesia and other high growth cities around the world. We keep our clients\u2019 interests foremost in our minds at all times. This combination of intellectual capital, comprehensive training, staffed with quality leaders and professional managers set us apart as an industrial leader.\n\nWe are currently seeking young and energetic talents\u00a0to join our team as a\u00a0Management Trainee.\n\nJob Responsibilities\n\nProvide professional financial services to our clients, including risk management, health protection, retirement planning and wealth accumulation\nManaging the total wealth of clients by matching our financial and investment solutions to fulfill their financial needs\nClients relationship management, expand clients\u2019 network and review their financial need regularly\nPromoting our Premier Service to potential clients, exploring their needs and making referrals to other business units where appropriate\u00a0\n\nBenefits and Packages\n\nFive-day work\nCompetitive Pay With Quarterly Bonus and Year End Bonus\nInitial Training and On-Job Training Provided\nExcellent Career Path to Management Ladder\nLife and Medical Insurance\nClient Base Provided\u00a0\nFlexible Working Hours\u00a0\nEducation Subsidies\n\nRequirements\n\nBachelor degree or above (Fresh graduates is welcomed)\n1 year working experience or above is preferred\nExperience in\u00a0customer service or sales field\nProactive with positive mindset, excellent interpersonal &\u00a0communication skills\nAble to work independently\nFluent in Cantonese, moderate English\u00a0\n\nWorking Location\n\n\n\nWhampoa\u00a0\n\n**Personal date provided by applicants will be treated in strict confidence and used for recruitment purposes only**\n\nIf you have any further enquiries, please press\u00a0APPLY NOW\u00a0to contact us with your CV. We will get back to you shortly.", "employment_types": ["Full Time", "Permanent"], "selling_points": [], "locations": ["Kowloon Bay"], "categories": ["Marketing / Public Relations", "Management", "Sales, CS & Business Devpt", "Channel / Distribution", "Sales - Sales Management"], "post_time": "2022-01-14T07:26:45Z", "salary": {"currency": null, "max": null, "min": null, "period": "monthly", "term": null}, "salary_visible": false, "title_keywords": ["manager"], "responsibilities": ["management", "review", "quality", "planning"], "requirements": {"degrees": [], "majors": [], "languages": [], "language_level": [], "hard_skills": [], "soft_skills": [], "languages_combined": []}, "experience_required": {"duration": [], "field": []}}, {"job_id": "100003009052397", "location_code": "hk", "company": "Zebra Strategic Outsource Solution Ltd", "job_title": "Marketing Assistant (Business Management & Customer Experience)", "description": "Job Descriptions:\u00a0\n\nResponsible for the overall sales and marketing performance and strategic sales direction for the principal - Food Services channel\nWork closely with principals to develop and implement marketing plan in catering channels\nExplore and develop new sales channels and markets\nTo achieve sales target and GP level by working closely with sales team\nManage ANP budget, spending and reports\nManage budget forecast, planning and inventory control\nIdentify business opportunity through market research report and\u00a0competitive trends for future marketing plan and strategy development\n\n\u00a0The ideal candidate should be :\n\n\nUniversity graduate in Business or related disciplines\nAt least 10 years relevant experience in FMCG industry prefer with serving food service channels\nStrong connection within various sales channels and key accounts (Wholesales, Hotel, QSR and Chain Restaurant)\nExcellent planning and communication skills with internal staff and principal\nResponsible, analytical, independent, self-motivated and able to work under pressure\nGood command of spoken and written English and Chinese\nProficiency in MS Office\n\nPlease send your application with resume and expected salary to The HR Manager, Dah Chong Hong, Ltd, 8/F DCH Building, 20 Kai Cheung Road, Kowloon Bay or by email.\n\nInformation provided will be for the purpose of selection within the company and only shortlisted candidates will be contacted. All applications will be retained for a maximum period of 6 months.", "employment_types": ["Full Time", "Contract"], "selling_points": [], "locations": ["Kowloon Bay"], "categories": ["Marketing / Public Relations", "Management", "Marketing - General / Support", "Public Relations - General / Support"], "post_time": "2022-01-17T02:56:57Z", "salary": {"currency": null, "max": null, "min": null, "period": "monthly", "term": null}, "salary_visible": false, "title_keywords": ["marketing assistant"], "responsibilities": ["work under pressure", "sales target", "budget", "hr", "market research", "develop", "communication", "marketing plan", "planning", "sales team", "reports", "forecast", "inventory control", "report", "catering"], "requirements": {"degrees": ["university graduate"], "majors": ["related disciplines", "business"], "languages": ["english", "chinese"], "language_level": ["good command"], "hard_skills": ["fmcg industry", "ms office"], "soft_skills": ["communication skills", "self-motivated", "independent", "responsible", "work under pressure", "ideal"], "languages_combined": [{"language": "english", "language_level": ["good command"]}, {"language": "chinese", "language_level": ["good command"]}]}, "experience_required": {"duration": ["at least 10 years"], "field": ["food", "fmcg", "relevant experience"]}}, {"job_id": "100003009051506", "location_code": "hk", "company": "The Aurora", "job_title": "Management Trainee \uff08\u61c9\u5c46\u7562\u696d\u751f\u512a\u5148\uff0cSalary 20k-30k\uff09", "description": "Responsibilities:\n\nAssist supervisor in planning and implementing marketing projects\nLiaise with internal and external parties to ensure the smooth launch of new products/services\nWork closely with internal departments including product development, IT, CRM, fulfillment logistics and frontlines for service process / system enhancements\nResponsible for day-to-day marketing operations and clerical duties\nPerform ad-hoc duties as required\nSet up policies for frontline and provide advice to escalated issues\nRequirements:\n\nDegree holder or above in Marketing, Business Administration or related discipline\nWilling to learn and accept fast pace working environment\nGood planning skills with ability to multi-task and attention to detail\nStrong interpersonal skills, initiative and highly self-motivated\nFluent in both verbal and written English, Cantonese\nProficiency in MS Office especially in Excel & PowerPoint\nImmediate availability is preferred\nFresh graduate will also be considered", "employment_types": ["Full Time", "Part Time", "Internship"], "selling_points": [], "locations": ["Wan Chai"], "categories": ["Banking / Finance", "Financial Services", "Marketing / Public Relations", "Management", "Management", "Management Trainee"], "post_time": "2022-01-16T06:13:55Z", "salary": {"currency": null, "max": null, "min": null, "period": "monthly", "term": null}, "salary_visible": false, "title_keywords": ["management trainee"], "responsibilities": ["operations", "fulfillment", "internal and external parties", "policies", "marketing projects", "provide advice", "logistics", "ad-hoc duties", "liaise with", "planning"], "requirements": {"degrees": ["fresh graduate", "degree holder"], "majors": ["marketing", "business administration"], "languages": ["cantonese", "english"], "language_level": ["fluent"], "hard_skills": ["excel", "powerpoint", "ms office"], "soft_skills": ["planning skills", "self-motivated", "multi-task", "willing to learn", "interpersonal skills", "attention to detail", "initiative"], "languages_combined": [{"language": "cantonese", "language_level": []}, {"language": "english", "language_level": ["fluent"]}]}, "experience_required": {"duration": [], "field": []}}, {"job_id": "100003009055227", "location_code": "hk", "company": "Rue Madame Retail Limited", "job_title": "PR & Marketing Manager", "description": "Responsibilities:\n\nDefine and articulate a clear branding strategy for our brands;\nIdentify, drive and implement marketing strategic plan, PR events and marketing promotions for strengthening the brand positioning and enhancing brand images;\nAnalyze results from conducted marketing activities and ensure the marketing campaigns are hosted with satisfied business efficiency;\nDevelop strategic partnerships to increase our brands\u2019 exposures;\nBuild on existing, and establish new relationships with media in order to maximize media lineage opportunities and marketing partnership opportunities;\nManage and monitor PR and marketing strategies budget;\nLiaise with principals\n\nQualifications:\n\nIndependent, creative and result-oriented with team management skills;\nEager to try new concept and\nStrong network and connection with press, media, celebrity and agencies;\nExcellent understanding of HK branding and PR and the affordable luxury market;\nProficiency in spoken and written English;\nProven track record in designing and executing successful public relations campaigns at both a local and national (especially PRC, Macau and Singapore) level;\nGood writing and editing skills, as well as event planning experience\n\nBenefits:\n\n5-day work week\nFlex working hours\nMedical insurance & dental care\nPublic Holiday\n12-17 days paid Annual Leave\n5 days Marriage Leave\nBirthday Leave\nStaff purchase discount\n\nInterested parties, please send resume with current and expected salary to \"APPLY NOW\"\u00a0for interview arrangement. (Data collected will be used as recruitment related purpose only.)", "employment_types": ["Full Time", "Permanent"], "selling_points": ["Challenging job opportunity", "Dynamic, creative and flexible working team", "Attractive remuneration package"], "locations": ["Sheung Wan"], "categories": ["Marketing / Public Relations", "Management", "Marketing - Brand / Product Management", "Public Relations - Event Management"], "post_time": "2022-01-18T01:52:30Z", "salary": {"currency": null, "max": null, "min": null, "period": "monthly", "term": null}, "salary_visible": false, "title_keywords": ["marketing manager"], "responsibilities": ["management", "marketing strategies", "budget", "monitor", "designing", "develop", "executing", "marketing promotions", "marketing campaigns", "plan", "liaise with", "editing", "planning"], "requirements": {"degrees": [], "majors": [], "languages": ["english"], "language_level": ["proficiency"], "hard_skills": [], "soft_skills": ["independent", "clear", "articulate", "creative", "result-oriented"], "languages_combined": [{"language": "english", "language_level": ["proficiency"]}]}, "experience_required": {"duration": [], "field": ["editing", "writing", "planning"]}}, {"job_id": "100003009052094", "location_code": "hk", "company": "DKSH Hong Kong Limited", "job_title": "Manager, Business Development, FMCG", "description": "Job Responsibilities:\n\nManage the execution of Group-wide/Business Unit-wide/regional/country/channel/product expansion strategies to achieve short- and long-term business objectives\nIdentify, evaluate and manage business opportunities/leads in securing sales pipeline in line with short- and long-term financial goals\nManage research/feasibility studies/market scan, evaluate findings and prepares information for decision-making\nManage the negotiation process.\u00a0 Prepare contracts, providing inputs on proper pricing and contract terms.\u00a0 Identify up-selling opportunities and manage contract re-negotiations with existing clients\nManage the improvement of current Business Development processes and cross-functional collaboration to drive effectiveness and minimize redundancy\nCollaborate with internal stakeholders in identifying cross-selling and/or up-selling opportunities, deal negotiations and finalization of contracts\nEstablish long-term relationships with potential clients/customers with the view to enhance business opportunities\nJob Requirements:\n\nDegree in Business Studies/Marketing preferred\nMinimum 5 years' experience in FMCG industry, especially in sales, marketing and business development related work\nThrive in a fast-paced, entrepreneurial, and impact-driven environment\nCan do attitude, self-starter with a strong drive to produce results\nProvide significant industry expertise and client business acumen with strong business analysis skills\nDeal maker with target driven, results-oriented\nFluency in Chinese and English (both written and spoken)\nWorking location: Wong Chuk Hang\n\nWe offer 5-day work week, performance bonus and attractive benefits including medical insurance.\u00a0 Please apply with full particulars, contact number, current and expected salary to Human Resources Department, DKSH Hong Kong Limited, 23rd floor, Tower A, Southmark, 11 Yip Hing Street, Wong Chuk Hang, Hong Kong or fax: 2895 9711 or click the APPLY NOW button below.\n\nAll personal data collected will be used for recruitment purpose only.\u00a0 Candidates will be contacted within 2 weeks if the background and experience are closely relevant to the job requirement.\n\nDrive Growth.\u00a0 Be the Difference.\u00a0 Join DKSH\n\nDKSH's strength lies in our great diversity of services, industries, clients, products, regions and employees from various nationalities.\u00a0 We are proud of our people: they are the reason we are successful.\u00a0 Our people are the best in the industry.\u00a0 They are passionate about their career growth and about business success.\u00a0 They work as part of an energetic and committed team, positively impacting millions of lives through the products and services we provide.\n\nJoin us today if you are ready to \"Drive growth.\u00a0 Be the Difference.\"\u00a0 \u00a0With DKSH, you will experience a world of learning and development, own your career and take business responsibility and have a positive impact that touches people's lives.", "employment_types": ["Full Time", "Permanent"], "selling_points": ["Identify, evaluate and negotiate new business", "Drive sales revenue, develop new business", "Develop and execute strategic business plan"], "locations": ["Aberdeen"], "categories": ["Sales, CS & Business Devpt", "Business Development", "Marketing / Public Relations", "Management", "E-commerce", "Business Development"], "post_time": "2022-01-17T02:04:49Z", "salary": {"currency": null, "max": null, "min": null, "period": "monthly", "term": null}, "salary_visible": false, "title_keywords": ["manager"], "responsibilities": ["collaborate with", "contracts", "business opportunities", "evaluate", "negotiation process"], "requirements": {"degrees": ["degree"], "majors": ["business", "marketing"], "languages": ["english", "chinese"], "language_level": ["fluency"], "hard_skills": ["analysis", "fmcg industry", "acumen"], "soft_skills": ["business acumen", "driven"], "languages_combined": [{"language": "english", "language_level": ["fluency"]}, {"language": "chinese", "language_level": ["fluency"]}]}, "experience_required": {"duration": ["minimum 5 years"], "field": ["related", "business development", "fmcg", "marketing"]}}, {"job_id": "100003009056524", "location_code": "hk", "company": "Sun Life Hong Kong Limited", "job_title": "Customer Service Officer (MPF)", "description": "Duties\nHandle service inquiries raised by clients\nMaking outbound calls regarding our services\nProvide sales and administrative support\nEnlarge and extend potential market segments in a proactive approach\nRequirements\n\nDegree holder in Business or related discipline\nMinimum 2 years\u2019 relevant experience in financial industry preferred\nExperience in customer service is an advantage\nSelf-motivated and service-oriented with good communication and interpersonal skills\nFluency in written and spoken Chinese\nBenefits\n\n\nAttractive remuneration package\u00a0will be offered to the right candidates\nHigh commission, monthly performance bonus, year-end performance bonus and pension benefits\nWell-structured training programs and comprehensive training platform\nClear career path and fast-track promotion to management level\nMedical benefits and training allowances", "employment_types": ["Full Time"], "selling_points": ["Answer enquiries & complaints from customers", "Conduct periodic telephone calls", "Clear career path with attractive salary (20k up)"], "locations": ["Hung Hom"], "categories": ["Sales, CS & Business Devpt", "Customer Service - Supervisor / Officer", "Marketing / Public Relations", "Management", "Sales - Sales Management"], "post_time": "2022-01-18T04:39:03Z", "salary": {"currency": "HKD", "max": 29999, "min": 20000, "period": "monthly", "term": null}, "salary_visible": true, "title_keywords": ["customer service officer"], "responsibilities": ["administrative support"], "requirements": {"degrees": ["degree holder"], "majors": ["business"], "languages": ["chinese"], "language_level": ["fluency"], "hard_skills": [], "soft_skills": ["self-motivated", "customer service", "communication and interpersonal skills", "service-oriented"], "languages_combined": [{"language": "chinese", "language_level": ["fluency"]}]}, "experience_required": {"duration": ["minimum 2 years"], "field": ["customer service", "financial industry", "relevant experience"]}}, {"job_id": "100003009051191", "location_code": "hk", "company": "Mindset Asia Limited", "job_title": "Marketing Expert - Industrial/Manufacturing sector", "description": "We are young, energetic and enthusiastic team, which aim to learn new things for their personal and professional development. Here we create a working environment that enables everyone to grow.\n\nJob Responsibilities\uff1a\n\u2022Sales and marketing\n\u2022Staff Management\n\u2022Account Management\n\nEducation Level\uff1a\n\u2022HKCEE / DSE Pass\n\nEntry Requirements\uff1a\n\u2022 Good communication skills\u00a0\n\u2022 Interpersonal skills\n\u2022\u00a0Responsible\n\u2022\u00a0Punctuality\n\nCompany Benefits\uff1a\n\u2022\u00a05 days working\u00a0\n\u2022 Training\n\u2022\u00a0Travel rewards\n\u2022 Cash rewards\n\u2022\u00a0Continuing education opportunities\n\nIf you are interested, please click APPLY\n\n", "employment_types": ["Full Time"], "selling_points": [], "locations": ["Not Specified"], "categories": ["Marketing / Public Relations", "Management", "Marketing - Brand / Product Management", "Marketing - General / Support"], "post_time": "2022-01-15T04:29:50Z", "salary": {"currency": null, "max": null, "min": null, "period": "monthly", "term": null}, "salary_visible": false, "title_keywords": [], "responsibilities": ["management"], "requirements": {"degrees": [], "majors": [], "languages": [], "language_level": [], "hard_skills": [], "soft_skills": ["communication skills", "interpersonal skills", "responsible"], "languages_combined": []}, "experience_required": {"duration": [], "field": []}}, {"job_id": "100003009050218", "location_code": "hk", "company": "Saint Honore Cake Shop Ltd", "job_title": "Marketing Manager (Marketing and Category Management)", "description": "Responsibilities:\n\nLead the execution of marketing programs from start to finish, leveraging internal support and driving collaboration\nAnalyze customer insights, consumer trends, market analysis, and marketing best practices to build successful strategies\nWorking in partnership with the R&D team, develop product briefs and guide innovative direction to meet objectives for all product innovation and reinvention\nPresent ideas and final deliverables to internal and external teams, and communicate with senior leaders about marketing programs, strategies, and sales impact\nP&L responsibilities. Create, maintain, and conduct analytics sales/ profitability monitoring for assigned categories. Extract insights for future planning, complete with actionable proposals and recommendations\nWorking closely with Operation team on go-to-market plan. Leverage strong store network and well developed online platform to maximize transactions with consumers and contribute to improve CX\nManage ATL & BTL materials to promote Saint Honore brand image as well as festive and cake & bakery products. Create, maintain brand contents across multiple channels, and digital platforms\nDrive collaboration with external agencies and in-house designers to produce advertising, promotion, packaging and visual merchandising materials, as well as construct effective media plans and support PR and market research initiatives.\n\u00a0Requirements:\nUniversity graduate in Marketing, Business or related discipline;\nOver 10 years of solid experience in Retail, F&B or FMCG markets with 5 years supervisor experience gained from F&B industry is must;\nStrong analytical, organization and communication, effective time and project management skills;\nPassionate with food products development a definite asset.\n\u00a0Candidate with less experience will be considered as Assistant Marketing Manager.\n\n\nInterested parties, please forward your resume stating salary expectation and available date to us.\u00a0\nFor more information of Saint Honore Cake Shop, please visit\u00a0www.cr-asia.com\nAll applications will be treated in the strictest confidence. Personal data provided will be used for recruitment purpose only. The information collected might also be disclosed to other associated companies of the Fung Group for job matching of similar vacancies.\nThe provision of full and complete information in support of your application is necessary for selection purposes. Applicant has the right to request access to and correction of personal data collected from him/her in writing to the Human Resource Manager by post to P.O. Box 92408, Tsim Sha Tsui Post Office, Hong Kong.", "employment_types": ["Full Time"], "selling_points": ["Lead the execution of marketing programs", "5 yrs supervisor exp. gained from F&B industry", "Passionate with food products development"], "locations": ["Shatin Area"], "categories": ["Marketing / Public Relations", "Management", "Marketing - Brand / Product Management", "Marketing - Marketing Communication"], "post_time": "2022-01-14T09:57:12Z", "salary": {"currency": null, "max": null, "min": null, "period": null, "term": null}, "salary_visible": false, "title_keywords": ["marketing manager"], "responsibilities": ["ideas", "merchandising", "transactions", "maintain", "plan", "plans", "advertising", "customer insights", "teams", "p&l", "develop", "visual", "monitoring", "market analysis", "contents", "consumer trends", "communicate with", "market research", "planning"], "requirements": {"degrees": ["university graduate"], "majors": ["business", "marketing"], "languages": [], "language_level": [], "hard_skills": ["project management"], "soft_skills": ["communication", "project management skills", "passionate"], "languages_combined": []}, "experience_required": {"duration": ["5 years", "10 years"], "field": ["f&b", "retail", "marketing", "fmcg"]}}, {"job_id": "100003009056323", "location_code": "hk", "company": "AXA China Region Insurance Company Limited", "job_title": "AXA \u5b89\u76db - \u7406\u8ca1\u9867\u554f / Wealth Management Manager / Management Trainee / Financial Consultant", "description": "Job Description\nJob Highlights\n\u5c16\u6c99\u5480\u4e0a\u73ed ; \u4e2d\u4e94 / DSE / \u5927\u5c08 / \u5927\u5b78 / \u5728\u8077\u5abd\u5abd\u5747\u6b61\u8fce\u52a0\u5165\nSalary: $20,000 - $60,000/month\n4-day work week - Work Life Balance\u00a0\n\nJob Description\n\u8981\u8207\u5225\u4e0d\u540c\uff0c\u7531\u9019\u523b\u958b\u59cb\uff0c\u8aa0\u9080\u60a8\u52a0\u5165AXA\u5b89\u76db\u7684\u5e74\u8f15MDRT \u5718\u968a\u3002\u00a0\nTo be Different, Join Us! We are a young team reaching to be MDRT.\u00a0\n\u00a0\n\u9762\u8a66\u8005\u9808\u6301\u6709\u9999\u6e2f\u6c38\u4e45\u5c45\u6c11\u8eab\u4efd\u8b49\nCandidates must hold PERMANENT HONG KONG IDENTITY CARD\u00a0\n\n\u5165\u8077\u8981\u6c42\u00a0 Requirements:\n\n\u9858\u610f\u5b78\u7fd2\u53ca\u7368\u7acb\u601d\u8003 (Willing to learn and think Independently)\u00a0\n\u69ae\u83ef\u5bcc\u8cb4\u8207\u826f\u5fc3\u4e26\u5b58 (Work Sincerely and Conscientiously)\n\u5177\u5099\u540c\u7406\u5fc3 (With Empathy)\n\u6b78\u9806\u65bc\u5718\u968a\u7cbe\u795e (Team Spirit)\n\u826f\u597d\u6e9d\u901a\u6280\u5de7 (Good Communication Skill)\n\u5de5\u4f5c\u7bc4\u570d\u00a0 Job Duties:\n\n\u6559\u80b2\u5ba2\u4eba\u7406\u8ca1\u89c0\u5ff5 (Educate individual and corporate clients about investment and insurance products)\u00a0\u00a0\n\u63d0\u4f9b\u9069\u7576\u7406\u8ca1\u7522\u54c1\u7d66\u5ba2\u6236\uff0c\u5982\u53ef\u6263\u7a05\u81ea\u9858\u91ab\u4fdd\u3001\u5e74\u91d1\u7b49 (Recommend suitable products to different clients, such as Voluntary Health Insurance Scheme and Qualifying Deferred Annuity Policy)\u00a0\n\n\u70ba\u5ba2\u4eba\u63d0\u4f9b\u8ddf\u9032\u4fdd\u55ae\u670d\u52d9\u5305\u62ec\u7d22\u511f\u4fdd\u55ae\u56de\u9867\u63d0\u4f9b\u5c08\u696d\u610f\u898b (Professional opinions and services, including Claims and Policy Review)\u00a0\n\u8655\u7406MPF\u4e8b\u9805 (MPF Consulting)\n\u63d0\u4f9b\u4e00\u822c\u4fdd\u96aa\u7522\u54c1\u670d\u52d9 (General Insurance Products)\n\u5f85\u9047\u53ca\u798f\u5229\u00a0 Packages and Benefits:\n\n\u6bcf\u661f\u671f\u5de5\u4f5c\u56db\u5929 (4-day work week)\n\u5e95\u85aaHK$10,000-HK$20,000 (\u8996\u4e4e\u904e\u5f80\u5de5\u4f5c\u7d93\u9a57) (Basic Salary from HK$10,000 to HK$20,000, depends on working experience)\n\u4e00\u5e74\u81f3\u5c11\u516d\u6b21\u734e\u91d1 (At least 6 bonus every year)\n\u8868\u73fe\u51fa\u8272\u8005\u53ef\u7372\u9080\u514d\u8cbb\u51fa\u5e2d\u6d77\u5916\u696d\u52d9\u6703\u8b70 (Offering overseas conventions and travel incentives as a reward)\n\u5728\u8077\u57f9\u8a13 (Provide On-The-Job Training)\n\u5e74\u8f15\u5718\u968a (Young and Enthusiastic Team)\u00a0\u00a0\n\u8acb\u5c07\u5c65\u6b77\u548c\u5f85\u9047\u8981\u6c42\uff0cwhatsapp \u81f3 6405 9562 \u6216\u96fb\u90f5\u81f3\u00a0happyataxa @gmail.com", "employment_types": ["Full Time", "Part Time", "Permanent", "Temporary", "Contract", "Internship", "Freelance"], "selling_points": ["Tsim Sha Tsui", "\u6bcf\u661f\u671f\u5de5\u4f5c\u56db\u5929 (4-day work week)", "Salary: $20,000 - $60,000/month"], "locations": ["Tsim Sha Tsui"], "categories": ["Banking / Finance", "Financial Services", "Marketing / Public Relations", "Management", "E-commerce", "Business Development"], "post_time": "2022-01-18T03:57:13Z", "salary": {"currency": "HKD", "max": 54999, "min": 20000, "period": "monthly", "term": null}, "salary_visible": true, "title_keywords": ["management trainee", "wealth management manager", "\u7406\u8ca1\u9867\u554f", "consultant"], "responsibilities": [], "requirements": {"degrees": [], "majors": [], "languages": [], "language_level": [], "hard_skills": ["scheme"], "soft_skills": ["independently", "team spirit", "communication skill", "willing to learn", "empathy"], "languages_combined": []}, "experience_required": {"duration": [], "field": []}}, {"job_id": "100003009050774", "location_code": "hk", "company": "Upbeat Media HK Limited", "job_title": "Marketing Manager", "description": "Responsibilities\u00a0\n\nDevelop all-rounded integrated marketing and communications strategies and action plans.\nPlan and lead social media strategies across different platforms.\nImplement and optimise online marketing campaign by analysing customers' behaviour and latest marketing trends.\u00a0 Analyse and review the effectiveness of marketing programs.\nWork closely with related departments, clients and external parties to ensure effective launch of each marketing campaign.\u00a0\nPrepare marketing communications collateral.\u00a0\nIdentify, explore and liaise with strategic partners for joint promotion activities and business development.\u00a0\n\n\u00a0Requirements:\u00a0\n\nDegree or above in business administration, marketing, digital communications, or other related disciplines.\u00a0\n5+ years of solid experience in marketing and/or digital marketing, preferably within the media or agency sector.\u00a0\u00a0\nKnowledge and understanding of SEO, social media platforms, and analytic tools.\u00a0\nStrong communication skills, problem-solving skills and business sense.\nAbility to meet tight deadlines and multi-tasking.\u00a0\nExcellent command of both written and spoken English and Chinese.\n\nInterested parties, please send your full resume with current and expected salaries by clicking the \u201cAPPLY NOW\u201d button.\n", "employment_types": ["Full Time"], "selling_points": ["Marketing Manager", "Minimum of 5 years of work experience", "Marketing Experience in media/agency is preferred"], "locations": ["North Point"], "categories": ["Marketing / Public Relations", "Management"], "post_time": "2022-01-14T11:23:00Z", "salary": {"currency": null, "max": null, "min": null, "period": "monthly", "term": null}, "salary_visible": false, "title_keywords": ["marketing manager"], "responsibilities": ["review", "external parties", "develop", "plan", "liaise with", "plans", "social media strategies", "analyse"], "requirements": {"degrees": ["degree or above"], "majors": ["related disciplines", "marketing", "business administration", "communications"], "languages": ["english", "chinese"], "language_level": ["excellent"], "hard_skills": ["problem-solving skills", "seo"], "soft_skills": ["communication skills", "meet tight deadlines", "business sense", "multi-tasking", "problem-solving skills"], "languages_combined": [{"language": "english", "language_level": ["excellent"]}, {"language": "chinese", "language_level": ["excellent"]}]}, "experience_required": {"duration": ["5+ years"], "field": ["agency", "marketing", "digital marketing", "media"]}}, {"job_id": "100003009050977", "location_code": "hk", "company": "Hong Kong Science & Technology Parks Corporation", "job_title": "Assistant Manager, Intelligence Research [JDB/AMIR/220114]", "description": "Responsibilities:\n\u00a0In view of the rapid expansion and continuous growth of the Corporation, we are looking for a high-calibre to support the Business Development team bringing the top-notch global Innovation and Technology (I&T)\u00a0companies to set up research and development operation in HKSTP.\nMajor responsibilities are listed below:\nSource and identify potential start-ups & scales-ups to business development team for engagement through research in the key market intelligence platform.\nLead research to understand emerging innovations and technologies across Biotech, Property Technology AI & Robotic, Smart Mobility, Fintech, Microelectronics, Industry 4.0 sectors.\nDelivers reports and makes insights/recommendations of key findings to improve business outcomes and support growth strategy initiatives.\nSummarize and consolidate the information into actionable items.\nKeep abreast of the latest technology trend across the global.\nDevelop strong partnerships with cross-functional teams.\nPerforms other related duties as assigned.\nRequirements:\u00a0\nBachelor\u2019s degree in business, Marketing, Data Science, Statistics, or related field required.\nMinimum 5+ years experience in market research or related field, engineering background is preferred.\nExcellent organizational skills and attention to detail.\nSuperior research and analytical skills.\nAbility to translate complex concepts and methodologies into easily understood language.\nExcellent project management and business writing skills.\nExcellent interpersonal, presentation and communication skills.\nCreative, self-driven and customer-oriented.\nProficient in both written and spoken English and Chinese (including Putonghua)\nCandidates with more experience may be considered as manager.\n[This position is open for referral by Recruitment agencies. The profile should be sent to our HR email address\u00a0a g e n c y c v @ h k s t p . o r g]\nWe offer market competitive compensation, 5-day work week, and generous benefits including medical and life insurance; and voluntary contribution in addition to the legal minimum MPF.\u00a0 To apply, please send your full resume with current and expected salary to the Human Resources & Office Administration Department, Hong Kong Science and Technology Parks Corporation, 5/F, Building 5E, 5 Science Park East Avenue, Hong Kong Science Park, Hong Kong or, by email via \"Apply Now\"\u00a0on or before 27 January 2022.\u00a0 \u00a0Please quote the reference number on the email subject/envelope and the application letter.\u00a0\u00a0\nPersonal data provided will be treated in strict confidence and used for recruitment purpose only.\u00a0 All personal data collected will be used strictly in accordance with employer\u2019s personal data policies, you can access to HKSTP\u2019s Personal Information Collection Statement at https://www.hkstp.org/hkstp_web/en/hkstp/personal-information-collection-statement-recruitment\nApplicants not invited for interview within four weeks after application deadline may consider their applications unsuccessful.\u00a0 Personal data of unsuccessful applicants will be retained for a maximum of two years.\u00a0\nwww.hkstp.org", "employment_types": ["Full Time"], "selling_points": [], "locations": ["Shatin Area"], "categories": ["Marketing / Public Relations", "Management", "Marketing - Market Research", "Others"], "post_time": "2022-01-14T12:24:06Z", "salary": {"currency": null, "max": null, "min": null, "period": "monthly", "term": null}, "salary_visible": false, "title_keywords": ["assistant manager,"], "responsibilities": ["reports", "cross-functional teams", "develop"], "requirements": {"degrees": ["degree", "bachelor"], "majors": ["data science", "business", "statistics", "marketing"], "languages": ["putonghua", "english", "chinese"], "language_level": ["proficient"], "hard_skills": ["writing skills", "analytical skills", "project management", "c", "r"], "soft_skills": ["organizational skills", "communication skills", "presentation", "driven", "writing skills", "analytical skills", "project management", "customer-oriented", "attention to detail", "creative", "interpersonal", "superior"], "languages_combined": [{"language": "putonghua", "language_level": []}, {"language": "english", "language_level": ["proficient"]}, {"language": "chinese", "language_level": ["proficient"]}]}, "experience_required": {"duration": ["minimum 5+ years"], "field": ["related", "engineering", "market research"]}}, {"job_id": "100003009049863", "location_code": "hk", "company": "Vitasoy International Holdings Ltd", "job_title": "Brand Manager  / Assistant Brand Manager", "description": "Key Responsibilities:\n\nResponsible for formulating marketing objectives and strategies\nControls and implements the approved budgets and marketing plans to achieve business objectives including P&L\nLiaises with internal departments and external parties from new product development to launch implementation\nPlans, coordinates and implements advertising campaigns with advertising agencies\nPlans, coordinates and implements research with research agencies\nInitiates counteracting strategies and programs based on market trend, consumer insights and competitors\u2019 performance\nPerforms ad-hoc duties as required\n\nRequirements:\n\nUniversity graduate preferably in Business Administration or related discipline\nMinimum 8 years marketing experience gained from FMCG industry\nMature and presentable\nGood communication skills with all levels\nExcellent command of spoken and written English and Chinese\nAbility to work independently under pressure\u00a0\nCandidate with less experiences will be considered as Assistant Brand Manager\n\nInterested parties please send your detailed resume stating your available date, current & expected salary to Human Resources Manager by clicking \u201cAPPLY NOW\u201d button below.\n\nAll information provided by applicants will be treated in strict confidence and used only for recruitment purposes. If you do not provide the information mentioned in the advertisement, we may not be able to assess your job application.You have the right to request access to, and correction of, your personal data held by us and you may lodge such request with our Data Protection Officer at pdpo@ vitasoy.com, but any such data access request will only be processed after the completion of the recruitment process.", "employment_types": ["Full Time", "Permanent"], "selling_points": ["5 days work, Company shuttle", "Formulating marketing objectives and strategies", "New product development to launch implementation"], "locations": ["Tuen Mun Area"], "categories": ["Marketing / Public Relations", "Management", "Marketing - Brand / Product Management", "Others"], "post_time": "2022-01-14T09:19:43Z", "salary": {"currency": null, "max": null, "min": null, "period": "monthly", "term": null}, "salary_visible": false, "title_keywords": ["manager", "assistant"], "responsibilities": ["budgets", "advertising", "consumer insights", "marketing plans", "external parties", "implementation", "p&l", "ad-hoc duties", "plans", "advertising campaigns"], "requirements": {"degrees": ["university graduate"], "majors": ["business administration"], "languages": ["english", "chinese"], "language_level": ["excellent"], "hard_skills": ["fmcg industry"], "soft_skills": ["communication skills", "work independently", "under pressure", "mature", "presentable"], "languages_combined": [{"language": "english", "language_level": ["excellent"]}, {"language": "chinese", "language_level": ["excellent"]}]}, "experience_required": {"duration": ["minimum 8 years"], "field": ["marketing", "brand", "fmcg"]}}, {"job_id": "100003009052263", "location_code": "hk", "company": "Elite Jobs", "job_title": "(Entry Level) Management Associate [5 Days Work, Bank Holiday]", "description": "Key Roles and Responsibilities\u00a0:\n\nProviding quality services and financial solutions to customers\u00a0and satisfy their changing financial needs.\nPresent investment portfolio to our prestigious personal and corporate clients.\nManage the financial needs of a diverse range of customers from mass-market to high-net-worth segments.\nExplore business opportunities and strengthen customer relationships.\nQualifications and Skills:.\n\nUniversity fresh graduate, preferably in finance or business related discipline\nStrong client skills with ability to deliver needs based solutions\nProven organization skills and attention to details\nStrong self-motivation with good interpersonal and analytical skills.\nStrong communication with fluent Cantonese, Mandarin and English.\nCompetitive benefits package, including:\n\nFive-day work week\nPerformance bonus\n20 working days annual leave\nSuperior training and development program\nProgressive career advancement opportunities\n\nWe offer a competitive salary and benefits package and the professional advantages of a dynamic environment that supports your development and recognizes your achievements.\n\nInterested parties please click \"Apply Now\" to send\u00a0full resume with the date of availability and expected salary.\u00a0\n\nAll\u00a0information provided by applicants will be treated in strict confidence and used solely for recruitment purpose. All applicants\u2019 information will be destroyed after 12 months.", "employment_types": ["Full Time"], "selling_points": ["Five-day work week", "University degree in any discipline", "Attractive income, Sustainable career development"], "locations": ["Central & Western Area"], "categories": ["Banking / Finance", "Fund Management", "Marketing / Public Relations", "Management", "Others", "Student / Fresh Graduate / No Experience"], "post_time": "2022-01-17T02:36:21Z", "salary": {"currency": "HKD", "max": 24999, "min": 17000, "period": "monthly", "term": null}, "salary_visible": true, "title_keywords": ["management associate"], "responsibilities": ["communication", "business opportunities", "quality"], "requirements": {"degrees": ["fresh graduate"], "majors": ["finance", "business"], "languages": ["cantonese", "english", "mandarin"], "language_level": ["fluent"], "hard_skills": ["analytical skills"], "soft_skills": ["analytical skills", "communication", "diverse", "self-motivation", "attention to details", "organization skills", "interpersonal"], "languages_combined": [{"language": "cantonese", "language_level": ["fluent"]}, {"language": "english", "language_level": ["fluent"]}, {"language": "mandarin", "language_level": ["fluent"]}]}, "experience_required": {"duration": [], "field": []}}, {"job_id": "100003009050954", "location_code": "hk", "company": "ADECCO", "job_title": "Project Executive \u2013 Marketing Communication", "description": "Our client is an innovative company in organizing exhibitions, they are looking for a Project Executive to join their team to support their business expansion\n\nJob Responsibilities:\n\nInvite new associations / visitors to engage the online and offline activities\nExplore and maintain relation with major associations and visitors\nUpdate changing purchasing needs and market trends\nOrganize online and offline events, including webinar and business matching\nCoordinate with associations and other third parties\nOrganize and implement the promotion campaigns and events\nProvide onsite services to the visitors with other departments and vendors\n\nJob Requirements:\n\nDegree in Marketing / Event Management or related disciplines\nMinimum 1 year event management experience\nFluent in spoken and written English, Cantonese and Mandarin\nA good team player with excellent communication and interpersonal skills\n\n\nIf you're interested in this role, please CLICK HERE or click 'Apply Now' to apply the position via Adecco website with your CV, or if you would like to have a further discussion about this role, please contact Mr. Mok on +852 2899 6180.\nPlease note that only short-listed candidates will be notified. All information gathered will be treated in strict confidence and solely used for recruitment purposes", "employment_types": ["Full Time", "Permanent"], "selling_points": [], "locations": ["North Point"], "categories": ["Marketing / Public Relations", "Management", "Marketing - Brand / Product Management", "Public Relations - Event Management"], "post_time": "2022-01-14T12:00:48Z", "salary": {"currency": null, "max": null, "min": null, "period": "monthly", "term": null}, "salary_visible": false, "title_keywords": ["project executive"], "responsibilities": ["promotion campaigns", "maintain", "coordinate with"], "requirements": {"degrees": ["degree"], "majors": ["related disciplines", "marketing"], "languages": ["cantonese", "english", "mandarin"], "language_level": ["fluent"], "hard_skills": [], "soft_skills": ["interested in", "good team player", "communication and interpersonal skills", "confidence"], "languages_combined": [{"language": "cantonese", "language_level": ["fluent"]}, {"language": "english", "language_level": ["fluent"]}, {"language": "mandarin", "language_level": ["fluent"]}]}, "experience_required": {"duration": ["minimum 1 year"], "field": ["management"]}}, {"job_id": "100003009050958", "location_code": "hk", "company": "Links International", "job_title": "Senior Manager, Web & Mobile Marketing", "description": "Our client is a leading Financial Trading company. They are expanding the team and looking for Senior Manager, Web & Mobile Marketing to join their team.\n\nJob Description\n\nDevelop website and mobile marketing strategies for all markets including Greater China, India, Korea, etc.\nLead the team in monitoring, maintaining and optimizing the performance of digital platforms\nDrive website re-built project to deliver new websites for targeted markets\nCollaborate closely with product team and technology team for website optimization, covering structure, performance, UX, content perspectives through data analysis\nMaintain strong online presence for the brands across desktop and mobile environments\n\nJob Requirements\n\nDegree holder, with minimum 6 years of related web or mobile marketing\nIn-depth knowledge and experience in website technology, SEO & PPC\nHands-on experience in SEO optimization, preferably gained from financial industry\nKnowledgeable in search engines (google insight, metadata, WeChat integration), data analytic tools (Google Adwords), organic & paid traffics\nExperience in online community growth & maintenance is a plus\nData driven, good problem-solving and tech savvy\nExperiece Highly fluent in both English and Mandarin", "employment_types": ["Full Time", "Permanent"], "selling_points": ["Global financial trading platform", "Web marketing strategy planning", "In-depth knowledge in SEO / search engines"], "locations": ["Not Specified"], "categories": ["Information Technology (IT)", "IT - Webmaster / SEO", "Marketing / Public Relations", "Management", "Others"], "post_time": "2022-01-14T12:02:05Z", "salary": {"currency": null, "max": null, "min": null, "period": "monthly", "term": null}, "salary_visible": false, "title_keywords": ["senior manager"], "responsibilities": ["collaborate", "marketing strategies", "maintaining", "monitoring", "website", "develop", "data analysis", "maintain"], "requirements": {"degrees": ["degree holder"], "majors": ["marketing"], "languages": ["english", "mandarin"], "language_level": ["fluent"], "hard_skills": ["plus", "seo", "web", "maintenance", "adwords", "problem-solving", "wechat", "mobile", "integration"], "soft_skills": ["problem-solving", "hands-on", "driven"], "languages_combined": [{"language": "english", "language_level": ["fluent"]}, {"language": "mandarin", "language_level": ["fluent"]}]}, "experience_required": {"duration": [], "field": ["financial industry", "maintenance"]}}, {"job_id": "100003009048206", "location_code": "hk", "company": "AXA China Region Insurance Company Limited", "job_title": "AXA \u5b89\u76db \u5c08\u696d\u7406\u8ca1\u9867\u554f", "description": "Communications and Public Relations Office\nExecutive Officer I / II (carrying the job title of \u2018Communications and Public Relations Manager\u2019 / \u2018Assistant Communications and Public Relations Manager\u2019)\n(Ref. 2200001N) (Closing date: February 8, 2022)\nThe appointee will be responsible for (a) planning, managing and co-ordinating the branding and engagement events and activities related to the 60th Anniversary of The Chinese University of Hong Kong and other University\u2019s major events; (b) formulating and executing the related marketing and branding campaigns and strategies so as to increase social and digital presence on various platforms, including but not limited to Facebook, Instagram, Twitter, YouTube, WeChat, Weibo, LinkedIn, etc.; (c) co-ordinating with local community and non-local partners and stakeholders on branding and engagement events; (d) managing online and offline publicity and advertisements; (e) handling on-site social video production and photography independently; (f) monitoring performance of social media campaign and digital marketing projects and drive for higher efficiency and effectiveness; (g) liaising with various internal and external parties; and (h) performing other tasks as assigned.\n\nApplicants should have/be (i) a good Bachelor\u2019s degree, preferably in Marketing, Communications, Media, or related disciplines; (ii) fulfilled the English language requirements set out on the website: https://www.hro.cuhk.edu.hk/en-gb/languageforeo; (iii) at least 8 years\u2019 post-qualification, preferably in marketing, advertising and branding experience, must be well-versed in social content creation, copy-writing, editorial and video/ photo creation and production; (iv) an excellent command of written and spoken English and Chinese (including Putonghua); (v) creativity, self-motivation and a positive work attitude; (vi) excellent organisational, presentation and interpersonal skills; and (vii) detail-minded and able to work under tight deadlines. Agency background with in-depth knowledge of major social media platforms management with proven significant achievement will be advantageous. Those with less but at least 6 years\u2019 post-qualification marketing/corporate communications experience at large corporations may be considered for appointment as Executive Officer II. Applicants should provide 3 samples of previous work on branding/digital marketing/social media campaign, multimedia production, or video production in the online application. Shortlisted candidates will be required to sit for a written test in both Chinese and English.\n\nApplicants must submit copies of certificates showing that they have fulfilled the language requirements and academic qualifications stated above, otherwise their applications may NOT be considered.\n\nAppointment will be made on a 2-year contract with contract-end gratuity.\n\nApplication Procedure\nThe University only accepts and considers applications submitted online for the post above. For more information and to apply online, please visit http://career.cuhk.edu.hk.", "employment_types": ["Full Time", "Internship"], "selling_points": ["\u6708\u85aa\uff08\u81f3\u5c11\uff09HK22,000.00 + \u7121\u4e0a\u9650\u4f63\u91d1 + \u5b63\u5ea6\u82b1\u7d05\u53ca\u5e74\u7d42\u82b1\u7d05", "\u5f48\u6027\u5de5\u4f5c\u6642\u9593\uff0c\u5de5\u4f5c\u8207\u751f\u6d3b\u5e73\u8861", "HUGO AGENCY \u6210\u7acb\u81f3\u4eca30\u591a\u5e74, \u591a\u5e74\u4f86\u591a\u6b21\u69ae\u7372\u570b\u969b\u734e\u9805"], "locations": ["Kwun Tong"], "categories": ["Marketing / Public Relations", "Management", "Sales, CS & Business Devpt", "Sales - Sales Management", "E-commerce", "Business Development"], "post_time": "2022-01-14T05:52:43Z", "salary": {"currency": "HKD", "max": 54999, "min": 20000, "period": "monthly", "term": null}, "salary_visible": true, "title_keywords": [], "responsibilities": ["social media", "management", "advertising", "advertisements", "video production", "monitoring", "internal and external parties", "liaising with", "website", "social media platforms", "other tasks", "executing", "digital marketing", "facebook", "planning"], "requirements": {"degrees": ["degree", "bachelor"], "majors": ["related disciplines", "marketing", "communications"], "languages": ["putonghua", "english", "chinese"], "language_level": ["excellent"], "hard_skills": ["facebook", "c", "multimedia", "wechat"], "soft_skills": ["detail-minded", "independently", "responsible", "self-motivation", "interpersonal skills", "positive work attitude", "presentation"], "languages_combined": [{"language": "putonghua", "language_level": ["excellent"]}, {"language": "english", "language_level": ["excellent"]}, {"language": "chinese", "language_level": ["excellent"]}]}, "experience_required": {"duration": ["at least 8 years", "at least 6 years"], "field": ["photo", "advertising", "post-qualification", "video", "content creation", "editorial", "marketing", "writing"]}}, {"job_id": "100003009048766", "location_code": "hk", "company": "Gimmick House Ltd", "job_title": "IT Business Analyst", "description": "Want to work in a venture studio with boundless opportunities and future-crafting projects? Join Us!\n\nHere we have a cluster of passionate and goal-oriented talents who strive for the acceleration of economies in the decentralized future. With extensive business networks, profound market insights and comprehensive capabilities in Digital Assets, Blockchain, Fintech and AI, we\u00a0are inviting you to join our ambitious team to embark your bespoke venture journey and make a real impact with your expertise.\n\nWho will love this job? Someone who:\n\nIs willing to challenge themselves in a fast-paced environment\nHappy to work in a flexible and dynamic team with strong bonding\nIs not afraid of failure, and love to explore different possibilities\nHas great communication skills, knows how to cooperate with different team members and between different teams\nWants to work more on Digital Assets / FinTech / Tech-related marketing team\n\nYour responsibilities\n\nCoordinating marketing campaigns and communication tasks both online and face-to-face\nOrganising and overseeing events to support the marketing campaigns\nWriting and delivering creative copywriting content for social media and marketing campaigns\nManaging the design and production of promotional materials for websites and marketing advertisement\nAnalysing the effectiveness of marketing campaigns and reporting findings to the executive team\nConducting analytics reporting across multiple platforms to extract key insights for adjustments of our future marketing strategies\nWork internally and externally on the execution of our marketing strategies\nStudy on ways to improve customer experience on our social media platforms and websites\u00a0\nPerform ad-hoc tasks as assigned\u00a0\nJob requirements\nEnthusiasm in marketing and some knowledge in technology and finance\nProblem solving and analytical skills with the ability to communicate effectively as well as pays attention to details\nTakes initiatives, independent and task-oriented; highly motivated\nBachelor degree in relevant field and experience in marketing\nInterpersonal and presentation skills, fluency in Cantonese, good at English\nGood time management and organizational skills\nKnowledge in blockchain is an advantage\n\nIf you are interested, please apply at\u00a0https://careers.mindcluster.io\u00a0or email us~", "employment_types": ["Full Time", "Permanent"], "selling_points": ["Good project presentation and documentation skils", "Competitive package", "Immediately available is highly preferred"], "locations": ["Kwun Tong"], "categories": ["Information Technology (IT)", "IT Project Management / Team Lead", "IT Management", "Marketing / Public Relations", "Management"], "post_time": "2022-01-14T07:14:47Z", "salary": {"currency": null, "max": null, "min": null, "period": "monthly", "term": null}, "salary_visible": false, "title_keywords": ["business analyst"], "responsibilities": ["social media", "reporting", "marketing strategies", "ad-hoc tasks", "social media platforms", "design", "communication", "promotional materials", "marketing campaigns"], "requirements": {"degrees": ["degree", "bachelor"], "majors": ["marketing"], "languages": ["cantonese", "english"], "language_level": ["fluency", "good"], "hard_skills": ["problem solving", "io", "blockchain", "analytical skills"], "soft_skills": ["organizational skills", "independent", "problem solving and analytical skills", "presentation skills", "motivated", "attention to details", "time management", "interpersonal"], "languages_combined": [{"language": "cantonese", "language_level": ["fluency"]}, {"language": "english", "language_level": ["good"]}]}, "experience_required": {"duration": [], "field": ["marketing"]}}, {"job_id": "100003009050014", "location_code": "hk", "company": "Ambitious People Group", "job_title": "Data & Analytic Director,MNC, financial, 840k+", "description": "Responsibilities:\nEstablish a deep understanding of the client\u2019s business, processes, and procedures and apply that knowledge to affect the project\u2019s success\nResponsible for project definition (e.g., scope, objectives, constraints, assumptions, benefits, issues, risks, etc.), create and maintain a detailed project plan\nOversee full project life cycle, including requirement gathering, planning, system analysis, implementation, deployment, testing and training\nManage and supervise the project progress and proactively identify & solve potential risks\nProvide comprehensive supports to project documentations, plans and reports\nLiaise with internal and external teams and stakeholders in addressing and resolving issues in system development and quality assurance\nRequirements:\nBachelor's degree in Information Systems/Computer Science/Software Engineering or equivalent experience required\n3 to 5 years of project management experience, preferably within a digital agency or consulting firm with experience in managing complex, overseas and/or enterprise-level projects.\u00a0\nStrong familiarity with project management software tools, methodologies, and best practices\nQuick learner with good analytical, time management and troubleshooting skills and able to work under pressure\nGood presentation and interpersonal skills to work with all level of stakeholders\nProfessional certification in Project Management (e.g. PMP, PRINCE) would be an advantage\nExcellent communication skills with spoken and written English and Chinese\nImmediately available is highly preferred", "employment_types": ["Full Time", "Permanent"], "selling_points": ["High base salary + attractive bonus", "Regional in-depth exposure", "Dynamic work environment"], "locations": ["Not Specified"], "categories": ["Marketing / Public Relations", "Management", "Marketing - Brand / Product Management", "Digital Marketing"], "post_time": "2022-01-14T09:38:02Z", "salary": {"currency": "HKD", "max": 69999, "min": 55000, "period": "monthly", "term": null}, "salary_visible": true, "title_keywords": ["director"], "responsibilities": ["procedures"], "requirements": {"degrees": [], "majors": [], "languages": [], "language_level": [], "hard_skills": [], "soft_skills": [], "languages_combined": []}, "experience_required": {"duration": [], "field": []}}, {"job_id": "100003009045127", "location_code": "hk", "company": "Vitasoy International Holdings Ltd", "job_title": "Marketing Manager", "description": "What are you going to do as a Data & Analytics Director?\n\nYou are going to work in a high-profile, world's leading financial company. You will help your client make informed decisions by uncovering and communicating data-driven insights and analysis. You will define the vision and support the data & analytics team to build and deliver the data & analytics roadmap for the APAC region. You will need to lead a team of data experts. We are looking for a leader with a strategic mindset and solid data skills.\n\n\nWhat is offered to you as a Data & Analytics Director?\n\n* High base salary\n* In-depth regional exposure\n* International environment\n\nWhat is expected of you?\n\n* 10+ years of experience at a media agency, marketing analytics/ consulting firm, or in a data-driven field\n* Strong in statistics, and familiarity with SQL, SAS, SPSS, R, or other advanced analytics software\n* Strong in business Intelligence: SQL programming and ETL, BI platforms (particularly Google Data Studio), and cloud databases (particularly Google Big Query), digital dashboard design\n* Able to build analytical models e.g., media mix, attribution, time series forecasting, etc. for the client and leverage the same for driving business recommendations\n* Experience in people management & project planning and project management is mandatory\n\nWhere are you going to work?\n\nYou will work in a fast-growing company with all the resources you need to become successful. You will be part of a brilliant, creative and young team, which is ready to take over Asia! Send your resume to frances.hong@ambitiouspeople.com!", "employment_types": ["Full Time"], "selling_points": ["Formulate marketing objectives and strategies", "Initiate and implement strong advertising plan", "Minimum 10 years\u2019 marketing experience in FMCG"], "locations": ["Tuen Mun Area"], "categories": ["Marketing / Public Relations", "Management", "Marketing - Brand / Product Management", "Marketing - Direct Marketing"], "post_time": "2022-01-13T07:15:03Z", "salary": {"currency": null, "max": null, "min": null, "period": "monthly", "term": null}, "salary_visible": false, "title_keywords": ["marketing manager"], "responsibilities": ["management", "project planning", "software", "consulting", "data", "analysis", "design", "lead a team", "project management", "databases", "forecasting"], "requirements": {"degrees": [], "majors": [], "languages": [], "language_level": [], "hard_skills": ["bi", "sas", "analysis", "sql", "make", "project management", "programming", "databases", "r", "business intelligence"], "soft_skills": ["advanced", "project management", "creative", "driven"], "languages_combined": []}, "experience_required": {"duration": ["10+ years"], "field": ["consulting", "agency", "people management", "project management", "marketing", "media", "planning"]}}, {"job_id": "100003009050905", "location_code": "hk", "company": "Sun Cupid Technology (HK) Ltd", "job_title": "Branding and Media Manager", "description": "Key Responsibilities:\n\nFormulate marketing objectives and strategies that fits the strategic direction and tie with category growth ambition and target\nDevelop marketing plans to strengthen brand positioning, consumer preference and drive conversion\nInitiate and implement strong advertising plan and marketing activations for brands and new product launch; consistently review and renovate execution plans to strive better performance\nEvaluate brand campaign and new launches performance constantly; develop KPI measurement tracking system and recommend action plans to accelerate performance to bridge gap\nHave deep understanding of brand and business dynamics and prepare for future insights generation to capture growth opportunities and step ahead competition\nActively explores new brand opportunities through multiple analyses including consumer trend analysis & market observation; translate into actionable insights and recommend to Management\nControl and optimize the approved marketing spending to achieve business and marketing objectives including P&L and market share\nWork closely with Regional team to drive strategic brand platform and initiatives development\nLead cross-functional team cooperation including Sales, Trade Marketing, Digital, Supply Chain, Regulatory, R&D etc. to push through the launches and execution plan\nMotivates and coaches the subordinates to grow up as high performer\nAssists Marketing Director in taking up responsibilities in the assigned divisional projects\nPerform ad-hoc duties as required\n\n\u00a0Key Requirements:\n\nMinimum 10 years\u2019 marketing experience in FMCG with at least 4 years at supervisory level\nWith proven track record to drive campaigns across digital and social platforms to enrich brand experience and engage consumers. Good understanding on digital & social landscape\nWork experience in regional marketing team is a plus\nHighly agile, flexible and open-minded with can-do attitude and eager to strive for excellence\nExcellent communication skill, able to communicate with all levels\nStrong strategic and analytical thinking\nExcellent command of spoken and written English and Chinese\nPC knowledge and application\nWays to apply:\u00a0\nInterested parties please send your detailed resume stating your available date, current & expected salary to Human Resources Manager, by clicking the \u201cAPPLY NOW\u201d button below.\n\nAll information provided by applicants will be treated in strict confidence and used only for recruitment purposes. If you do not provide the information mentioned in the advertisement, we may not be able to assess your job application. You have the right to request access to, and correction of, your personal data held by us and you may lodge such request with our Data Protection Officer at pdpo@ vitasoy.com, but any such data access request will only be processed after the completion of the recruitment process.", "employment_types": ["Full Time", "Permanent"], "selling_points": [], "locations": ["Lai Chi Kok"], "categories": ["Marketing / Public Relations", "Management", "Marketing - Brand / Product Management", "Marketing - Marketing Communication"], "post_time": "2022-01-14T11:43:10Z", "salary": {"currency": null, "max": null, "min": null, "period": "monthly", "term": null}, "salary_visible": false, "title_keywords": ["manager"], "responsibilities": ["management", "control", "advertising", "trade marketing", "marketing plans", "analysis", "review", "measurement", "p&l", "develop", "evaluate", "plan", "ad-hoc duties", "plans", "tracking"], "requirements": {"degrees": [], "majors": [], "languages": ["english", "chinese"], "language_level": ["excellent"], "hard_skills": ["pc knowledge", "plus", "agile"], "soft_skills": ["flexible", "agile", "can-do attitude", "open-minded", "communication skill", "strive for excellence"], "languages_combined": [{"language": "english", "language_level": ["excellent"]}, {"language": "chinese", "language_level": ["excellent"]}]}, "experience_required": {"duration": ["at least 4 years", "minimum 10 years"], "field": ["fmcg", "brand", "digital", "marketing", "supervisory level", "team"]}}, {"job_id": "100003009044457", "location_code": "hk", "company": "Kin Yat Industrial Co Ltd", "job_title": "Sales & Marketing Manager (Small Domestics Appliances)", "description": "Responsibilities:\n\nDerive, Implement, and raise brand awareness and strengthen the brands marketing strategies campaigns to achieve business goal and marketing objectives mainly in USA.\nResponsible for market research, analysis sales data, monitor brand performance and market trends\nDevelop and grow effective digital marketing and online media strategies within social communities via livestreams, affiliate programs and assist in influencers management in USA.\nOwn and manage official Shop platforms including FB, IG, and etc.\nAnalyze online data, social media performance, audience behavior and conversion funnel to provide effective recommendations and insights\nStay up-to-date with the latest digital and social media trends. Adopt new innovations as appropriate and market best practices.\nMaintain and monitor daily operations of multimedia contents\nDevelop, identify and implement different kinds of marketing activities to obtain fans growth, viral topics and gain customers engagement\nCreate innovative and attention-grabbing content for brand website, social media platforms, including but not limited to Facebook and Instagram\nEnsure and evaluate all content and writing meets the brand communication standards\n\nRequirements:\n\nDegree holder\u00a0in business/marketing related area\nUnderstanding of Digital Media buying, including IO, DSP, social media, Search in USA and other country\nStrong analytical and Gathering data skills, highly numerate and comfortable with data processing and interpretation.\nSolid and proven digital marketing Experience with successful campaigns, brand building and positioning.\nWith 5 years\u2019 work experience in Product Marketing/Brand Management/PR/Digital Marketing/Market Research, with branding in digital marketing and social media platforms\nAnalyze and build brand equity through a consumer centric mindset\nLocalize global/international plans and strategies for local success\nTranslate brand elements into plans and go-to-market strategies with campaigns across on and off-line platforms.\nMeasure and report performance of all marketing campaigns and assess ROI and KPIs.\nMonitor and oversee new and ongoing marketing and advertising market trends, research consumer markets and competitors' activities.\nMonitor product distribution and consumer reactions.\nFollow and promote a test-and-learn culture to constantly find new opportunities for growth and optimization.\nDevelop and manage brand position,\u00a0sales, and marketing strategies\u00a0for the assigned brand\nStrong sense for lifestyle trends including cell phone and consumer electronics\nHave a good network of online media partners, influencers, KOLs, bloggers in oversea such as USA.", "employment_types": ["Full Time", "Permanent"], "selling_points": [], "locations": ["Wong Tai Sin Area"], "categories": ["Sales, CS & Business Devpt", "Business Development", "Marketing / Public Relations", "Management", "Marketing - Brand / Product Management"], "post_time": "2022-01-13T18:54:57Z", "salary": {"currency": null, "max": null, "min": null, "period": "monthly", "term": null}, "salary_visible": false, "title_keywords": ["sales & marketing manager"], "responsibilities": ["social media", "management", "marketing strategies", "raise brand awareness", "data", "analysis", "social media platforms", "monitor", "market research", "website", "develop", "evaluate", "communication", "daily operations", "maintain", "digital marketing", "contents", "facebook"], "requirements": {"degrees": ["degree holder"], "majors": ["business", "marketing"], "languages": [], "language_level": [], "hard_skills": ["go", "processing", "io"], "soft_skills": ["consumer centric"], "languages_combined": []}, "experience_required": {"duration": ["5 years"], "field": ["social media", "pr", "management", "brand", "market research", "marketing", "digital marketing"]}}, {"job_id": "100003009043300", "location_code": "hk", "company": "Bloom No.1 Limited", "job_title": "Senior Marketing Executive", "description": "What You Will Achieve\n\nDevelop & maintain long-term business relationship with new and existing customers through identifying their potential needs and conscientiously achieve customers\u2019 goal\nResponsible for full range of sales activities including meeting customers, prepare quotation, order delivery, pricing, complaints and account receivables\nLead the project group consists of various function teams to solve all issues related to the project until the end of life of product to achieve project outputs\nCoordinate activities concerned with technical developments, scheduling, and resolving engineering design and test problems\nExplore new business opportunities with regular and new customers\nAssist management on analyzing market growth\nAssist in any ad hoc duties as requested\n\nWhat You Will Need\n\nBachelor Degree or above in Business, Marketing or\u00a0Engineering\nAt least 5 years of consumer product experience in SDA, Floor Care, Baby Care, Toys\nProven technical ability and knowledge in a wide range of electronics related areas\nStrong business acumen with excellent communication, negotiation and presentation skills\nAbility to multitask, prioritize, and manage time efficiently\nOccasional travel to China is required\nImmediately available is an advantage\n\nWe are an equal opportunity employer and welcome applications from all qualified candidates. Any interest candidate, please send your resume with expected salary and availability by clicking\u00a0\u201cApply Now\u201d.\n\n(Data collected will be treated as strictly confidential and will be used for recruitment purpose only and will be destroyed after the recruitment exercise when no longer required.)", "employment_types": ["Full Time"], "selling_points": ["Experienced F&B / Consumer Marketing Talent", "Digitally Savvy, Forward Thinking, Self Driven", "Proven record in all-round marketing execution"], "locations": ["Tsim Sha Tsui"], "categories": ["Marketing / Public Relations", "Management", "Marketing - General / Support", "Digital Marketing"], "post_time": "2022-01-13T13:54:06Z", "salary": {"currency": null, "max": null, "min": null, "period": "monthly", "term": null}, "salary_visible": false, "title_keywords": ["senior marketing executive"], "responsibilities": ["ad hoc duties", "sales activities", "management", "engineering design", "explore new business opportunities", "data", "quotation", "teams", "develop", "coordinate", "scheduling", "communication", "maintain", "recruitment"], "requirements": {"degrees": ["degree or above", "bachelor"], "majors": ["business", "engineering", "marketing"], "languages": [], "language_level": [], "hard_skills": ["goal", "no", "acumen"], "soft_skills": ["negotiation", "responsible", "prioritize", "communication", "presentation skills", "business acumen", "ability to multitask"], "languages_combined": []}, "experience_required": {"duration": ["at least 5 years"], "field": ["toys", "consumer product"]}}, {"job_id": "100003009047694", "location_code": "hk", "company": "Luk Fook Holdings Company Limited", "job_title": "Assistant Marketing Officer", "description": "Responsibilities\nResponsible for developing promotional materials and supervising the design team to support marketing activities, from concept design to collateral fabrication.\nManage all digital marketing execution and optimization; drive content synergy across channels, including website, mobile app, social media, third-party platforms, etc.\nMonitor creative agencies on copy-writing, social media content development, media pitching, and events collaboration\nWork closely with the Manager and Operations team to formulate marketing initiatives, strategies, timelines and deliver projects on schedule and budget.\nCompile market intelligence, competitor analysis, and consumer insight reports for managements\nAd hoc projects as assigned by the Manager\nRequirements\nDegree holder or above in Marketing or related disciplines\n3+ years solid experience in marketing or digital marketing, preferably gained from F&B or consumer sector\nProficiency and knowledge in digital media technologies, loyalty marketing, and advertising\nForward-thinking and a strong sense of industry market trend\u00a0\nStrong interpersonal, multitasking, and project management skills\nAttentive to details, well-organized, and able to meet tight deadlines\nExcellent command of spoken and written Chinese and English\nImmediate availability is a plus\n\nBenefits: We offer attractive remuneration package including 5-day work week, medical insurance benefits, staff dining discount and competitive salary to the right candidates.\n\nTo Apply: Interested parties please send full CV with expected salary and apply via the APPLY NOW button. Only short-listed candidates will be contacted. Personal data collected will be used for recruitment purpose solely.\n", "employment_types": ["Full Time"], "selling_points": ["At least 3-year solid experience in marketing", "Excellent interpersonal and communications skills", "Candidates with PR background is highly desirable"], "locations": ["Shatin Area"], "categories": ["Marketing / Public Relations", "Management", "Marketing - Direct Marketing", "Others"], "post_time": "2022-01-14T03:46:24Z", "salary": {"currency": null, "max": null, "min": null, "period": "monthly", "term": null}, "salary_visible": false, "title_keywords": ["assistant marketing officer"], "responsibilities": ["social media", "supervising", "mobile app", "operations", "analysis", "budget", "monitor", "developing", "design", "website", "promotional materials", "digital marketing", "social media content", "schedule", "reports", "ad hoc projects"], "requirements": {"degrees": ["degree holder"], "majors": ["related disciplines", "marketing"], "languages": ["english", "chinese"], "language_level": ["excellent"], "hard_skills": ["project management", "plus"], "soft_skills": ["meet tight deadlines", "attentive to details", "project management skills", "well-organized", "interpersonal"], "languages_combined": [{"language": "english", "language_level": ["excellent"]}, {"language": "chinese", "language_level": ["excellent"]}]}, "experience_required": {"duration": ["3+ years"], "field": ["f&b", "marketing", "digital marketing"]}}, {"job_id": "100003009046663", "location_code": "hk", "company": "United Nations High Commissioner for Refugees", "job_title": "Senior PPH Associate (G7)", "description": "Responsibilities\n\n\nTo assist in planning and implementation of all marketing activities;\nTo provide marketing materials, trailers and highlights to affiliates;\nTo assist in copy writing for promotional materials and support the distribution drive for channels;\nTo contact agencies to manage and execute requests frequently.\n\nRequirements:\n\n\nDegree holders in Journalism, Communication, Marketing, Business Administration or related discipline;\nAt least 3-year solid experience in marketing, social media, copywriting, editing , translation or other related fields, preferably in retail industry;\nExperience in writing publicity materials and/or creating content for social media platforms;\nAbility to develop strong relationship, both internally and externally;\nGood communication skills, creative with strong market sense, self-motivated and attentive to details;\nAble to meet tight deadlines and work independently under pressure in fast paced environment;\nGood command of both written and spoken English and Chinese, fluency in Mandarin is added advantage;\nWell knowledge in MS Word, Excel, PowerPoint and Chinese word processing;\nImmediate available is preferable;\nCandidates with PR background is highly desirable;\nWork in Shek Mun area.\n\nInterested parties please send full resume with expected salary to\u00a0Human Resources Manager, Luk Fook Holdings Co., Ltd , Floor 25, Metropole Square, No.2 On Yiu Street, Shek Mun, Shatin, N.T., Hong Kong or\u00a0(click here)\u00a0to submit your application.\n\n\u00a0All personal data are handled in accordance with our personal data privacy policies. A copy of our statement on personal data collection is available upon request.", "employment_types": ["Full Time", "Contract"], "selling_points": [], "locations": ["Yau Ma Tei"], "categories": ["Sales, CS & Business Devpt", "Business Development", "Marketing / Public Relations", "Management", "Public / Civil", "Social Services - Community / Non-profit Organization"], "post_time": "2022-01-13T18:54:10Z", "salary": {"currency": null, "max": null, "min": null, "period": "monthly", "term": null}, "salary_visible": false, "title_keywords": ["associate"], "responsibilities": ["implementation", "promotional materials", "contact", "marketing materials", "planning"], "requirements": {"degrees": ["degree"], "majors": ["journalism", "marketing", "business administration"], "languages": ["english", "chinese", "mandarin"], "language_level": ["fluency", "advantage", "good command"], "hard_skills": ["excel", "chinese word processing", "powerpoint", "translation", "ms word"], "soft_skills": ["communication skills", "self-motivated", "meet tight deadlines", "work independently", "under pressure", "attentive to details", "communication", "strong market sense", "creative"], "languages_combined": [{"language": "english", "language_level": ["advantage", "good command"]}, {"language": "chinese", "language_level": ["advantage", "good command"]}, {"language": "mandarin", "language_level": ["fluency", "advantage", "good command"]}]}, "experience_required": {"duration": ["at least 3-year"], "field": ["retail industry", "social media", "related", "marketing", "writing", "copywriting", "editing"]}}, {"job_id": "100003009050729", "location_code": "hk", "company": "Hutchison Telecommunications (Hong Kong) Limited", "job_title": "Assistant Marketing Manager", "description": "Communications and Public Relations Office\nExecutive Officer I / II (carrying the job title of \u2018Communications and Public Relations Manager\u2019 /\u00a0\u2018Assistant Communications and Public Relations Manager\u2019)\n(Ref. 2200001M) (Closing date: February 8, 2022)\nThe appointee will be responsible for (a) planning, managing and co-ordinating the celebratory programmes of the 60th Anniversary of The Chinese University of Hong Kong and other University\u2019s major events; (b) supervising and executing the event logistics; (c) preparing event collateral materials; (d) liaising with internal and external parties; and (e) performing other tasks as assigned.\n\nApplicants should have (i) a good Bachelor\u2019s degree, preferably in Marketing or Communications; (ii) fulfilled the English language requirements set out in the website: https://www.hro.cuhk.edu.hk/en-gb/languageforeo; (iii) at least 8 years\u2019 post-qualification event management experience, preferably in organising large-scale events or projects; (iv) an excellent command of written and spoken Chinese and English; (v) excellent analytical skills with attentiveness to details; and (vi) strong organisational, presentation and interpersonal skills. Those with less but at least 6 years\u2019 post-qualification related work experience may be considered for appointment as Executive Officer II. Shortlisted candidates will be required to sit for a written test in both Chinese and English.\n\nApplicants must submit copies of certificates showing that they have fulfilled the language requirements and academic qualifications stated above, otherwise their applications may NOT be considered.\n\nAppointment will be made on a 2-year contract with contract-end gratuity.\n\nApplication Procedure\nThe University only accepts and considers applications submitted online for the post above. For more information and to apply online, please visit http://career.cuhk.edu.hk.", "employment_types": ["Full Time", "Permanent"], "selling_points": [], "locations": ["Tsing Yi"], "categories": ["Marketing / Public Relations", "Management", "Marketing - General / Support", "Marketing - Marketing Communication"], "post_time": "2022-01-14T11:14:58Z", "salary": {"currency": null, "max": null, "min": null, "period": "monthly", "term": null}, "salary_visible": false, "title_keywords": ["assistant marketing manager"], "responsibilities": ["management", "supervising", "internal and external parties", "liaising with", "website", "other tasks", "logistics", "executing", "planning"], "requirements": {"degrees": ["degree", "bachelor"], "majors": ["marketing", "communications"], "languages": ["english", "chinese"], "language_level": ["excellent"], "hard_skills": ["c", "analytical skills"], "soft_skills": ["interpersonal skills", "presentation", "responsible", "analytical skills"], "languages_combined": [{"language": "english", "language_level": ["excellent"]}, {"language": "chinese", "language_level": ["excellent"]}]}, "experience_required": {"duration": ["at least 8 years", "at least 6 years"], "field": ["related", "management", "post-qualification"]}}, {"job_id": "100003009049771", "location_code": "hk", "company": "Man Hing Hong Properties Company Limited", "job_title": "Head of Marketing and Leasing Department", "description": "Responsibilities:\n\n\nDevelop & implement acquisition, retention, upsell and loyalty programs to achieve business goal.\nClosely work with various sales channels including but not limited to telesales, retail, road show and corp sales team to ensure that they fully understand the launched program details.\nDrive different sales channels to meet sales target and achieve different KPIs.\nKnowledge in customer segmentation and profile analysis and propose suitable offers to each customer segment.\nPrepare analysis reports for result monitoring and actions.\nLiaise with different departments, suppliers and partners to ensure that marketing campaigns can be launched timely and smoothly.\nMonitor competitor activity and react to the market promptly.\n\nRequirements:\n\n\nDegree holder in Marketing / Business / Communications or relevant discipline.\n5 years of working experience or above in marketing.\nExperience In channel management and data analysis is a must.\u00a0\nWell-organized with ability to prioritize, able to multi-tasking and manage tight schedule.\nProficiency in MS office applications.\nKnowledge of the various marketing operations and on the latest social media trends is preferred.\nStrong interpersonal and presentation skill.\nPositive, eager to learn and self-motivated.\nAbility to drive execution, optimize resources, and develop innovative solutions.\nGood written and spoken English and Chinese (including\u00a0Mandarin)\u00a0is a must.\nLess experienced candidate will be considered as Senior Marketing Executive.\n\nApart from competitive remuneration package and exciting opportunity for career development within the Group, we provide attractive employee benefits such as free company shuttle, free company SIM card and preferential SIM plan offers, comprehensive medical & insurance schemes, as well as full range of other employee well-being provisions.\u00a0\n\nInterested parties, please apply with full resume, present and expected salary, by clicking \u201cAPPLY NOW\u201d. Please quote the reference number on the e-mail subject.\n\nWe are an equal opportunity employer and welcome applications from all qualified candidates. Personal data collected will be treated in the strictest confidence and handled confidentially by authorised personnel for recruitment-related purposes only within the CK Hutchison Group of companies. The personal data of unsuccessful applicants will be destroyed after the recruitment exercise pursuant to the requirements of the Personal Data (Privacy) Ordinance in Hong Kong.", "employment_types": ["Full Time", "Permanent"], "selling_points": ["+15 years Commercial Leasing for Office & Retail", "Strong marketing concept", "Track record of sales performance"], "locations": ["Central"], "categories": ["Sales, CS & Business Devpt", "Business Development", "Marketing / Public Relations", "Management", "Sales - Real Estate"], "post_time": "2022-01-14T09:12:59Z", "salary": {"currency": null, "max": null, "min": null, "period": "monthly", "term": null}, "salary_visible": false, "title_keywords": [], "responsibilities": ["analysis reports", "sales target", "analysis", "monitoring", "monitor", "develop", "sales team", "marketing campaigns", "liaise with", "kpis"], "requirements": {"degrees": ["degree holder"], "majors": ["business", "marketing", "communications"], "languages": ["english", "chinese", "mandarin"], "language_level": ["good"], "hard_skills": ["presentation skill", "analysis", "ms office"], "soft_skills": ["presentation skill", "self-motivated", "well-organized", "prioritize", "eager to learn", "multi-tasking", "comprehensive", "innovative", "interpersonal", "positive"], "languages_combined": [{"language": "english", "language_level": ["good"]}, {"language": "chinese", "language_level": ["good"]}, {"language": "mandarin", "language_level": ["good"]}]}, "experience_required": {"duration": ["5 years"], "field": ["data analysis", "marketing", "channel management"]}}, {"job_id": "100003009050090", "location_code": "hk", "company": "Ambitious People Group", "job_title": "Senior Mar Manager, B2C, 60k+", "description": "Job Responsibilities:\u00a0\nLead the Marketing and Leasing team and manage the property portfolio of the Group in line with the required KPI / Corporate targets\nDevise, implement and monitor the leasing and pricing strategies, targets, objectives, budgets and guidelines for the commercial and retail portfolio to maximize returns\nLaunch marketing plans to achieve\u00a0the leasing performance, both occupancy rate and rental rate\u00a0\nMake use of market survey and data analysis report for the betterment of managerial decisions\u00a0\nEstablish & maintain a good relationship with clients, tenants, agents and all business counterparts\nManage the team members for all tenants matters\nAdministrate the ad-hoc projects with the team\nRequirements:\u00a0\n\nDegree holder and/or any pertinent qualifications\n15+ years' Commercial Leasing Experiences, of which over 5+ years are at departmental head level with substantial marketing exposure\u00a0\nTrack record of leasing performance for both offices and retail business\nStrategic, Result-oriented, Strong presentation and negotiation skills, Client Management\u00a0\nCompetent in translating marketing strategies to leasing management\nWe offer competitive package to the right candidate.\u00a0 Interested parties, please \"APPLY\" by submitting your CV with current/last salary, expected salary and the earliest availability.\u00a0 \u00a0\n\nAll information collected is for recruitment purpose only", "employment_types": ["Full Time", "Permanent"], "selling_points": ["High base salary + attractive bonus", "Regional in-depth exposure", "Dynamic work environment"], "locations": ["Not Specified"], "categories": ["Marketing / Public Relations", "Management", "Marketing - Brand / Product Management", "Digital Marketing"], "post_time": "2022-01-14T09:46:02Z", "salary": {"currency": "HKD", "max": 69999, "min": 55000, "period": "monthly", "term": null}, "salary_visible": true, "title_keywords": ["manager"], "responsibilities": ["budgets", "guidelines", "marketing plans", "monitor", "data analysis", "good relationship", "maintain", "ad-hoc projects", "report"], "requirements": {"degrees": ["degree holder"], "majors": [], "languages": [], "language_level": [], "hard_skills": [], "soft_skills": ["negotiation skills", "presentation", "result-oriented", "competent"], "languages_combined": []}, "experience_required": {"duration": ["15+ years", "5+ years"], "field": ["commercial", "marketing"]}}, {"job_id": "100003009045128", "location_code": "hk", "company": "Store Friendly Self Storage Group Limited", "job_title": "Marketing Manager", "description": "What are you going to do as a Senior Marketing Manager?\n\nYou are going to work in the world's leading digital platform in Hong Kong. As a Senior Marketing Manager, you are responsible for business leadership and marketing plan development and for leading the agency through an understanding of clients' marketing and business context. You need to oversee from strategy to project management and take a vital role in leading the Group's marketing initiatives. You also have to track the performance and profitability of the entire team and oversee all of the agency business' client portfolio. We expect a hands-on leader to coach the team and grow the business!\n\nWhat is offered to you as a Senior Marketing Manager?\n\n* High base salary + attractive bonus\n* Global exposure\n* Dynamic work environment\n\nWhat is expected of you?\n\n* 8 years of experience in digital marketing, e-commerce, CRM\n* Experienced in Salesforce and ad agencies\n* Solid understanding of campaign tracking and reporting with a proven track record in driving brand awareness, considerations, and conversions\nthrough effective strategy.\n* Strong in communication, leadership, account servicing, and team management\n* High proficiency in both Chinese and English\n\nWhere are you going to work?\n\nYou will be working in a fast-paced environment with all brilliant, creative, and young talents from different cultural backgrounds. Apply now or directly send your resume to frances.hong@ambitiouspeople.com!", "employment_types": ["Full Time"], "selling_points": ["5-day work week, Challenging job opportunity", "Friendly and dynamic working environment", "Attractive remuneration package"], "locations": ["Tsuen Wan Area"], "categories": ["Marketing / Public Relations", "Management", "Marketing - Brand / Product Management", "Marketing - Marketing Communication"], "post_time": "2022-01-13T07:15:23Z", "salary": {"currency": null, "max": null, "min": null, "period": "monthly", "term": null}, "salary_visible": false, "title_keywords": ["marketing manager"], "responsibilities": ["reporting", "management", "digital platform", "communication", "marketing plan", "project management", "digital marketing", "tracking"], "requirements": {"degrees": [], "majors": [], "languages": ["english", "chinese"], "language_level": ["proficiency"], "hard_skills": ["project management", "dynamic", "salesforce", "e-commerce"], "soft_skills": ["responsible", "fast-paced environment", "communication", "project management", "hands-on", "dynamic", "creative", "leadership"], "languages_combined": [{"language": "english", "language_level": ["proficiency"]}, {"language": "chinese", "language_level": ["proficiency"]}]}, "experience_required": {"duration": ["8 years"], "field": ["digital marketing", "e-commerce"]}}, {"job_id": "100003009047419", "location_code": "hk", "company": "Links International", "job_title": "E-commerce specialist (APAC) - Retail brand", "description": "Key Responsibilities:\n\n\nDefine and articulate a strong, effective branding strategy\nIdentify, drive and implement marketing strategic plan, including PR events and marketing promotions to strengthen brand positioning and images\nResult analysis on marketing activities and ensure all marketing campaigns are hosted with satisfied business efficiency\nDevelop strategic partnerships to increase brand exposures and awareness\nBuild on existing and establish new relationships with media to maximize media lineage opportunities and marketing partnership opportunities\nManage and monitor PR and marketing strategies, budgets and reports\nLiaise with different stakeholders and principals\n\nRequirements:\n\n\n\nBachelor's degree in marketing, business administration or any related disciplines\nAt least 5 years' experience as a marketing manager\nExtensive knowledge of marketing strategies, channels and branding\nSuperb leadership, communication, and collaboration abilities\nExceptional analytical and problem-solving skills\nStrong time management and organizational abilities\nImmediate available is highly preferred\n\n\u00a0Benefits:\u00a0\n\n5-day work week\nMedical insurance\nPublic Holiday\nAnnual Leave\nStaff's Children Birthday Leave\nEarly Leave on Important Holidays\nStaff discount\nPerformance bonus\n\nInterested parties please apply with full resume with detailing experience, qualifications, present and expected salary via \"APPLY NOW\"\n\nFor further information, you are invited to visit our website at http://www.store-friendly.com/\n\nThe information provided will be treated in strict confidence. All personal data of unsuccessful applicants will be destroyed after the recruitment purpose.", "employment_types": ["Full Time", "Permanent"], "selling_points": ["Handle the E-commerce operation", "Support APAC region", "Detailed, Organized"], "locations": ["Not Specified"], "categories": ["Marketing / Public Relations", "Management", "E-commerce", "Marketing - Brand / Product Management", "Product Management / Business Analyst"], "post_time": "2022-01-14T03:02:01Z", "salary": {"currency": null, "max": null, "min": null, "period": "monthly", "term": null}, "salary_visible": false, "title_keywords": ["specialist"], "responsibilities": ["budgets", "marketing strategies", "analysis", "monitor", "develop", "reports", "marketing promotions", "marketing campaigns", "plan", "liaise with"], "requirements": {"degrees": ["degree", "bachelor"], "majors": ["related disciplines", "marketing", "business administration"], "languages": [], "language_level": [], "hard_skills": ["problem-solving skills"], "soft_skills": ["organizational", "communication", "leadership", "problem-solving skills", "time management", "extensive"], "languages_combined": []}, "experience_required": {"duration": ["at least 5 years"], "field": ["marketing"]}}, {"job_id": "100003009047041", "location_code": "hk", "company": "ConnectedGroup Limited", "job_title": "Hear Of Marketing, WPB (Asia) - Top Tier Bank", "description": "Our client, a US Medical Brand, is seeking an Associate Product Manager (Ethical Marketing) to lead the branding and marketing function for the brand.\n\nThis is a consumer medical brand, the strategy is to influence medical professionals and community to learn about the product and make recommendation to consumers.\n\nYou will develop drive strategy to reach potential customers through working with the medical professionals, endorsement from Key Opinion Leaders and events.\n\nThis is a No.1 player in the consumer medical sector, so you will gain solid marketing exposure in a stable business environment.\n\nResponsibilities:\n\u2022 To develop marketing and branding strategy on this medical brand. \u00a0\n\u2022 Assist to develop medical marketing strategy to reach medical professional on product\u2019s features and proven findings.\n\u2022 To organize medical events to gain product exposure and acquire new customers.\n\nRequirements:\n\u2022 University degree in business administration, science, and other discipline.\n\u2022 3 years of marketing, particularly in Consumer Marketing, Trade Marketing (FMCG), medical marketing.\n\u2022 Product experience preferences: consumer products, Over-The-Counter drugs, infant products, pharmaceutical, derma, etc.\n\u2022 Team player that enjoys collaborating with internal, external partner teams, KOL, medical professionals and event agency.\n\n***This is a No.1 player in the consumer medical sector, so you will gain solid marketing exposure in a stable business environment.\n\n420K \u2013 450K per annual", "employment_types": ["Full Time", "Permanent"], "selling_points": ["Drive marketing strategy and execution in Asia", "Solid credit cards and loans experience is a must", "Experience of leading multi channel sales program"], "locations": ["Not Specified"], "categories": ["Marketing / Public Relations", "Management", "Marketing - Brand / Product Management", "Marketing - Marketing Communication"], "post_time": "2022-01-14T02:09:07Z", "salary": {"currency": null, "max": null, "min": null, "period": "monthly", "term": null}, "salary_visible": false, "title_keywords": [], "responsibilities": ["develop"], "requirements": {"degrees": ["university degree"], "majors": ["science", "business administration"], "languages": [], "language_level": [], "hard_skills": ["no"], "soft_skills": ["business environment", "team player", "stable"], "languages_combined": []}, "experience_required": {"duration": [], "field": ["pharmaceutical"]}}, {"job_id": "100003009044032", "location_code": "hk", "company": "Our Hong Kong Foundation Limited", "job_title": "Senior Manager, Communication", "description": "Job Responsibilities:\u00a0\nResponsible for the full duties of marketing & leasing activities of office premises owned by the Group\nAssist the Head of M&L for marketing plans to achieve our required targets, objectives and budgets\u00a0\nConduct market survey and data analysis report to facilitate management decision\u00a0\nKeep close contact with property developers, agents, prospective clients, establish and maintain long-term relationship with tenants and all relevant parties\nTimely respond to tenants\u2019 inquiries and complaints and ensure all tenants\u2019 matters being handled properly\nCarry out ad-hoc projects as required by the senior management\nRequirements:\u00a0\n\nDegree holder and/or any pertinent qualifications\n10+ years' Commercial Leasing Experiences, of which over 5+ years are at managerial level with substantial marketing exposure\u00a0\nTrack record of leasing performance for office premises (Grade A preferably)\u00a0\nStrategic, Result-oriented, Strong presentation and negotiation skills, Client Management\u00a0\nCompetent in translating marketing strategies to leasing management\nWe offer competitive package to the right candidate.\u00a0 Interested parties, please \"APPLY\" by submitting your CV with current/last salary, expected salary and the earliest availability.\u00a0\n\nAll information collected is for recruitment purpose only", "employment_types": ["Full Time", "Permanent"], "selling_points": ["Provide editorial support", "Excellent language & writing skills", "Friendly and flexible culture, growing platform"], "locations": ["Central & Western Area"], "categories": ["Media & Advertising", "Editorial / Journalism", "Marketing / Public Relations", "Management", "Marketing - Marketing Communication"], "post_time": "2022-01-13T02:51:36Z", "salary": {"currency": null, "max": null, "min": null, "period": "monthly", "term": null}, "salary_visible": false, "title_keywords": ["senior manager"], "responsibilities": ["budgets", "management", "marketing plans", "data analysis", "inquiries and complaints", "senior management", "maintain", "contact", "ad-hoc projects", "report"], "requirements": {"degrees": ["degree holder"], "majors": [], "languages": [], "language_level": [], "hard_skills": [], "soft_skills": ["negotiation skills", "presentation", "result-oriented", "competent"], "languages_combined": []}, "experience_required": {"duration": ["5+ years", "10+ years"], "field": ["commercial", "marketing", "managerial"]}}, {"job_id": "100003009049231", "location_code": "hk", "company": "Arrow Asia Pac Ltd", "job_title": "Head of Digital Platform - Asia Pacific", "description": "About the Company\n\nOur Client is a leading global fintech / forex company. They are now looking for Senior Marketing Manager to join their team, specialising in Social Media.\n\nJob Description\n\n\nCovering Asian key-focused markets of Greater China, South Korean, Indian and Dubai, responsible for developing and executing regional social media marketing strategy and social content management to drive social media traffic and customer engagement\nLead the social media marketing team on campaign development and enhance WeChat ecosystem for driving higher traffic and customer engagement\nManage social media content from brainstorming, content creation, publication and performance analysis\nDevise localized content strategies in the strategic markets based on the company's objectives and customers' needs\nDevelop, execute and manage the content strategies covering all touchpoints throughout client's lifecycle, such as website, client portal, social media, client communications, trading platforms, education material, market research and more, to reinforce our brands, attract our brands' target audiences, with the objectives to drive traffic and generate leads\nWork with both internal stakeholders and external parties on content creation, manage the delivery timeline and content direction\nCollaborate with market analysis team to review the effectiveness of marketing campaigns and make adjustment in order to improve the performance\n\nJob Requirement\n\n\nBachelor Degree holder\n10 years of related marketing experience in social media and content marketing\nDemonstrated experience and knowledge in social media platforms (Chinese platforms: WeChat, Weibo, QQ, Youkou; Other platforms: Facebook, Instagram, Youtube, etc.) for the strategic markets\nExperience in budget planning and management\nHighly fluent in English and Chinese (Mandarin)", "employment_types": ["Full Time"], "selling_points": ["Regional sales position on eCommerce", "Minimum of 12 years of related exp.", "Develop customer, supplier and vendor relationship"], "locations": ["Not Specified"], "categories": ["Marketing / Public Relations", "Management", "Others"], "post_time": "2022-01-14T08:17:52Z", "salary": {"currency": null, "max": null, "min": null, "period": "monthly", "term": null}, "salary_visible": false, "title_keywords": ["head of digital platform"], "responsibilities": ["collaborate with", "social media", "management", "customers' needs", "analysis", "external parties", "review", "developing", "website", "develop", "market research", "market analysis", "executing", "social media content", "marketing campaigns", "publication"], "requirements": {"degrees": ["bachelor degree holder"], "majors": [], "languages": ["english", "chinese", "mandarin"], "language_level": ["fluent"], "hard_skills": ["facebook", "wechat"], "soft_skills": [], "languages_combined": [{"language": "english", "language_level": ["fluent"]}, {"language": "chinese", "language_level": ["fluent"]}, {"language": "mandarin", "language_level": []}]}, "experience_required": {"duration": ["10 years"], "field": ["social media", "management", "related", "marketing", "planning"]}}, {"job_id": "100003009048293", "location_code": "hk", "company": "Michael Page", "job_title": "Trade Marketing Manager  - FMCG", "description": "Responsibilities:\n\nPrepare presentations, reports and other necessary corresponding documentations for client\nInvolve in job training program\u00a0in different aspects,\u00a0such as\u00a0sales and marketing skills, communication skills, leadership and coaching skills.\nDevelop market or explore long-term business relationship with potential customers\nExplore new customers in different industries to widen the company portfolio\nOr\n\nAssist in editing online content\nSimple graphic design\nEvent planning\ndocument management\n\nRequirements:\n\nDiploma or above\u00a0in\u00a0any discipline,\u00a0Finance, Accounting,\u00a0Marketing\u00a0or related discipline\u00a0is an advantage.\nExcellent interpersonal and leadership skills. positive, proactive and meticulous;\nExcellent command of written and spoken English and Chinese\nFresh graduates and overseas graduates from mainland China is welcomed\nAble to work independently and under pressure.\nImmediately available\n\nBenefit:\n\nComprehensive on the job training and coaching\nOpportunity to explore PRC and CIES business\nExcellent advancement opportunities to be corporate trainer and leadership\nMedical benefits\nExcellent career prospect\n5-day work week, flexible working time", "employment_types": ["Full Time", "Permanent"], "selling_points": ["A world leading FMCG Group", "Trade Marketing", "Promotion Planning"], "locations": ["Not Specified"], "categories": ["Marketing / Public Relations", "Management", "Marketing - Brand / Product Management", "Marketing - General / Support"], "post_time": "2022-01-14T06:09:08Z", "salary": {"currency": null, "max": null, "min": null, "period": "monthly", "term": null}, "salary_visible": false, "title_keywords": ["marketing manager"], "responsibilities": ["management", "graphic design", "presentations", "develop", "communication", "reports", "editing", "planning"], "requirements": {"degrees": ["diploma or above"], "majors": ["finance", "accounting", "marketing"], "languages": ["english", "chinese"], "language_level": ["excellent"], "hard_skills": [], "soft_skills": ["meticulous", "work independently", "under pressure", "leadership skills", "proactive", "interpersonal", "positive"], "languages_combined": [{"language": "english", "language_level": ["excellent"]}, {"language": "chinese", "language_level": ["excellent"]}]}, "experience_required": {"duration": [], "field": []}}, {"job_id": "100003009047986", "location_code": "hk", "company": "Convoy Global Holdings Limited", "job_title": "Manager, Marketing", "description": "Introduction\n\nAt IBM, work is more than a job - it's a calling: To build. To design. To code. To consult. To think along with clients and sell. To make markets. To invent. To collaborate. Not just to do something better, but to attempt things you've never thought possible. Are you ready to lead in this new era of technology and solve some of the world's most challenging problems? If so, lets talk.\n\nYour Role and Responsibilities\n\nPrimary Responsibilities\n\n\nOptimizing performance in support of WFM KPIs and driving actions to close gaps to target.\nSupporting HK senior leadership team in all WFM activities\nBuilding effective collaboration with service line and practice leaders, solutioning, HR/TA, Procurement, and Finance/Enterprise Operation.\nEnsuring compliance with Global WFM processes and tolls\nEnsuring compliance to local labor regulations\nProactively identifying and driving capacity actions to manage shortages and excesses\nDriving quarterly demand interlock, fall plan and spring plan resource planning for HK Market\nEnsuring data integrity across supply and demand dynamics\nSupporting internal and external audits in respect of WFM scope\nSupporting special projects e.g. that enable WFM strategy\n\n\nRequirements\n\n\nStrong understanding of consulting skill portfolio\nStrong understanding of consulting business and financial metrics\nknowledgeable in WFM processes and tools\ncreative thinker who thrives in a dynamic environment\nStrong analytical skills and problem-solving abilities\nAbility to change and embrace new challenges and drive new ways of working\nEffective decision making, strong adaptability and ability to make important changes quickly\n\n\nRequired Technical and Professional Expertise\n\nSee Job Description\n\nPreferred Technical and Professional Expertise\n\nAbout Business Unit\n\nIBM Consulting is IBM\u2019s consulting and global professional services business, with market leading capabilities in business and technology transformation. With deep expertise in many industries, we offer strategy, experience, technology, and operations services to many of the most innovative and valuable companies in the world. Our people are focused on accelerating our clients\u2019 businesses through the power of collaboration. We believe in the power of technology responsibly used to help people, partners and the planet.\n\nYour Life @ IBM\n\nAre you craving to learn more? Prepared to solve some of the world's most unique challenges? And ready to shape the future for millions of people? If so, then it's time to join us, express your individuality, unleash your curiosity and discover new possibilities.\n\nEvery IBMer, and potential ones like yourself, has a voice, carves their own path, and uses their expertise to help co-create and add to our story. Together, we have the power to make meaningful change \u2013 to alter the fabric of our clients, of society and IBM itself, to create a truly positive impact and make the world work better for everyone.\n\nIt's time to define your career.\n\nAbout IBM\n\nIBM\u2019s greatest invention is the IBMer. We believe that through the application of intelligence, reason and science, we can improve business, society and the human condition, bringing the power of an open hybrid cloud and AI strategy to life for our clients and partners around the world.\n\nRestlessly reinventing since 1911, we are not only one of the largest corporate organizations in the world, we\u2019re also one of the biggest technology and consulting employers, with many of the Fortune 50 companies relying on the IBM Cloud to run their business.\n\nAt IBM, we pride ourselves on being an early adopter of artificial intelligence, quantum computing and blockchain. Now it\u2019s time for you to join us on our journey to being a responsible technology innovator and a force for good in the world.\n\nLocation Statement\n\nFor additional information about location requirements, please discuss with the recruiter following submission of your application.\n\nBeing You @ IBM\n\nIBM is committed to creating a diverse environment and is proud to be an equal opportunity employer. All qualified applicants will receive consideration for employment without regard to race, color, religion, gender, gender identity or expression, sexual orientation, national origin, genetics, pregnancy, disability, age, veteran status, or other characteristics. IBM is also committed to compliance with all fair employment practices regarding citizenship and immigration status.", "employment_types": ["Full Time", "Permanent"], "selling_points": ["brand management", "new brand development", "Marketing of of wealth & health brands"], "locations": ["Wan Chai"], "categories": ["Banking / Finance", "Others", "Marketing / Public Relations", "Management", "Marketing - Brand / Product Management"], "post_time": "2022-01-14T04:25:12Z", "salary": {"currency": null, "max": null, "min": null, "period": "monthly", "term": null}, "salary_visible": false, "title_keywords": ["manager"], "responsibilities": ["regulations", "data", "hr", "compliance", "internal and external audits", "plan", "kpis", "planning"], "requirements": {"degrees": [], "majors": [], "languages": [], "language_level": [], "hard_skills": ["blockchain", "ai", "problem-solving", "reason", "analytical skills", "make", "dynamic"], "soft_skills": ["dynamic environment", "focused", "responsible", "problem-solving", "deep", "unique", "analytical skills", "innovative", "committed", "diverse", "adaptability", "creative", "positive", "decision making"], "languages_combined": []}, "experience_required": {"duration": [], "field": []}}, {"job_id": "100003009051059", "location_code": "hk", "company": "Talent Blue Search Limited", "job_title": "Assistant Retail Marketing Manager \u2013 European Home Appliances Brand", "description": "What You'll Be Doing\n\nResponsible for managing the sales efforts of their team and providing leadership towards the achievement of maximum profitability and growth in line with the company's vision. Represents the team internally and externally; ensures their department is exceeding expectations from both a vendor ad customer perspective. Manages the workforce by making decisions on workload and setting priorities for the team. Consistently recommends operational improvements, contributes to the strategic objectives and manages team effectiveness. Accurately forecasts and drives teams to manage opportunities and sales.\u00a0\nManagement: Manage the strategic and sales objectives for the sales teams and creates tactical solutions to meet/exceed objectives. Go on field sales account calls and supplier reviews to provide leadership towards the achievement of maximum profitability and growth. Manage manager and employee development, recruiting, hiring and training, performance reviews, salary administration, daily coaching and feedback, goal setting, development planning and performance management. Progressively and proactively manage development and performance issues. Deliver a high performing team.\nSales: Direct strategy that motivates sales teams to reach sales goals and deliver results. Maintain senior level relationships at customers, suppliers and Arrow corporate. Take on assigned projects and drives corporate initiatives. Through data analysis and past experience make solid decisions on strategy and direction. Direct value added sales opportunities by implementing supply chain, engineering, supplier, or service excellence strategies. Identifies and helps obtain branch goals.\nDevelop customer, supplier and vendor relationships: Strengthens Arrow's reputation by delivering service excellence and process efficiencies. Attend reviews and meetings. Increase management presence at customer accounts in order to achieve access to all levels of decision makers. Implement effective and practiced techniques for solving problems. Effectively communicate with all levels senior level contacts at customers, suppliers and Arrow corporate.\n\nWhat We Are Looking For\n\nRequires a minimum of 12 years of related experience with a 4 year degree\nProvides leadership to managers, supervisors and/or professional staff\nIs accountable for the performance and results of multiple related units\nDevelops departmental plans, including business, production and/or organizational priorities\nControls resources and policy formation in area of responsibility\nDecisions are guided by resource availability and functional objectives\nIdentifies applications of functional knowledge and existing methodologies to complex problems\u00a0\nManages large teams of professionals and/or junior managers", "employment_types": ["Full Time", "Permanent"], "selling_points": ["Retail Marketing Strategy Visual & Display Plan", "In-store program event Retailer Partnership", "580K - 660K per annual"], "locations": ["Not Specified"], "categories": ["Design", "Visual Merchandising", "Marketing / Public Relations", "Management", "Marketing - General / Support"], "post_time": "2022-01-15T01:36:02Z", "salary": {"currency": null, "max": null, "min": null, "period": "monthly", "term": null}, "salary_visible": false, "title_keywords": ["marketing manager", "assistant"], "responsibilities": ["administration", "communicate with", "management", "teams", "develop", "data analysis", "providing leadership", "maintain", "plans", "planning"], "requirements": {"degrees": ["degree"], "majors": [], "languages": [], "language_level": [], "hard_skills": ["analysis", "vendor", "goal", "make", "go"], "soft_skills": ["organizational", "leadership", "accountable", "responsible"], "languages_combined": []}, "experience_required": {"duration": ["4 year", "minimum of 12 years"], "field": ["data analysis", "related"]}}, {"job_id": "100003009044838", "location_code": "hk", "company": "Snow Hong Kong Development Limited", "job_title": "Assistant Trade Marketing Manager", "description": "Our client is a world leading FMCG Group. They are now expanding their business and looking for a Trade Marketing Manager to join their fast growing business.\n\nClient Details\n\nOur client is a world leading FMCG. They are now expanding their business and looking for a Trade Marketing Manager to join their fast growing business.\n\nDescription\n\nYou will be responsible for trade marketing strategies.\nWork closely with the sales and brand team on trade promotion programs.\nMaintain close relationship with trade partners to increase product exposure and market share\nManage the A&P budget and evaluate promotions effectiveness and in charge of analysis and reports to draw trade strategies accordingly.\nProvide advice on distribution tactics and increase product exposure in all channels\n\nProfile\n\n* Degree holder in marketing, business or related discipline\n* At least 6 - 10 years of marketing experience from FMCG / Consumer Goods industry\n* Good command in English and Chinese\n\nJob Offer\n\nStrong career progression within company and a promising career path. Attractive salary and bonus package. This is a dynamic work environment and an excellent opportunity to work for an international company.\n\nTo apply online please click the 'Apply' button below. For a confidential discussion about this role please contact Phoebe Leung on +852 3412 4853.", "employment_types": ["Full Time", "Permanent"], "selling_points": [], "locations": ["Quarry Bay"], "categories": ["Hospitality / F & B", "Food & Beverage", "Marketing / Public Relations", "Management", "Marketing - Brand / Product Management"], "post_time": "2022-01-13T06:26:48Z", "salary": {"currency": null, "max": null, "min": null, "period": "monthly", "term": null}, "salary_visible": false, "title_keywords": ["marketing manager", "assistant"], "responsibilities": ["trade marketing", "analysis", "budget", "evaluate", "maintain", "reports", "provide advice", "contact"], "requirements": {"degrees": ["degree holder"], "majors": ["business", "marketing"], "languages": ["english", "chinese"], "language_level": ["good command"], "hard_skills": ["analysis", "dynamic"], "soft_skills": ["dynamic", "responsible"], "languages_combined": [{"language": "english", "language_level": ["good command"]}, {"language": "chinese", "language_level": ["good command"]}]}, "experience_required": {"duration": ["at least 6 - 10 years"], "field": ["marketing", "fmcg"]}}, {"job_id": "100003009044143", "location_code": "hk", "company": "Indigo Living Ltd", "job_title": "HK Marketing Manager", "description": "Our client, a European Home Appliances Brand, is seeking an Assistant Retail Marketing Manager.\n\nThis is a new position created to develop and implement comprehensive marketing and merchandising programs for strategic retailers\n\nResponsibilities:\n\nAuthor, strategize and execute the channel strategy for retailers\nDevelop retail marketing strategy based on category analysis, retailer insights and sales objectives to formulate retail marketing, merchandising and instore activation plans\nFormulate budget and monitor spending monthly\nWith the support from design and VM team to create clear and compelling instore brand presentations.\nPartner/Negotiate with retailers to execute instore activation plan to achieve brand and sales objectives\nRequirements:\n\nDegree holder in Business Administration, Design or other discipline.\n5+ years of marketing experience, particularly involving trade marketing, Visual Merchandising, display, design, etc.\nStrong commercial acumen, with in ROI and formulating budgets.\nThis is a new position, particularly welcomes Trade Marketing Professionals , with experience with VM / Display in Retail Stores from beauty, FMCG and home appliances.\n580K - 660K per annual", "employment_types": ["Full Time"], "selling_points": ["Shuttle Bus Available, Life & Medical Insurance", "5 working day, Discretionary Bonus, Staff Discount", "Immediate availability is highly preferred"], "locations": ["Pok Fu Lam"], "categories": ["Marketing / Public Relations", "Management"], "post_time": "2022-01-13T03:12:29Z", "salary": {"currency": null, "max": null, "min": null, "period": "monthly", "term": null}, "salary_visible": false, "title_keywords": ["marketing manager"], "responsibilities": ["vm team", "analysis", "budget", "merchandising", "monitor", "design", "develop", "presentations", "plan", "plans"], "requirements": {"degrees": ["degree holder"], "majors": ["business administration", "design"], "languages": [], "language_level": [], "hard_skills": ["visual merchandising", "acumen"], "soft_skills": [], "languages_combined": []}, "experience_required": {"duration": ["5+ years"], "field": ["fmcg", "merchandising", "design", "marketing", "beauty", "retail"]}}, {"job_id": "100003009042559", "location_code": "hk", "company": "Precision Enterprise Ltd", "job_title": "Assistant / Sales & Marketing Manager", "description": "We are looking for a high calibre professional to develop of our beer business in different trade channels.\n\nJob Responsibilities:\n\nChannel Strategy Formulation & Execution\n\n\nDevelop & execute channel strategies with SMART objectives, based on clear channel priorities, optimal brand/SKU mix per channel and shopper/on-trade consumer drivers.\nEnsure that channel strategies and programs deliver Company profitability objectives.\nGenerate and recommend innovation opportunities for the channel.\nChannel Activation Planning\n\nLead the channel planning process.\nBuild the annual channel plan that reflects long term channel strategy and leverage key channel value drivers.\nTransfer top-down yearly channel objectives into objective-driven activities.\nEnsure all activities are in line with portfolio/brand and channel strategies.\nManage the execution of POSM in line with brand strategy.\n\n\u00a0Activities Execution\n\nSet clear action standards and performance measures for each activity.\nCreate, collaborate and manage the project plan.\nMonitor plan and intervene effectively to keep them on track where required.\nCreate organizational alignment & commitment to effectively roll out the planned activities through other functions.\n\n\u00a0Talent\u00a0Requirements:\n\nDegree holder in related business disciplines\n4 years relevant experience, FMCG background preferred\nHands on digital experience a plus\nExcellent communication and collaboration skills\nGood command of Chinese (Putonghua) and English\nWell versed in MS Office\nPlease send in your CV with photo, current and expected packages. All information will be treated in strict confidence.", "employment_types": ["Full Time"], "selling_points": ["5 day work", "Degree holder in Business/Marketing/Engineering", "Energy storage , power electronics preferred"], "locations": ["Kwun Tong"], "categories": ["Marketing / Public Relations", "Management", "Sales, CS & Business Devpt", "Sales - Sales Management"], "post_time": "2022-01-12T08:01:45Z", "salary": {"currency": null, "max": null, "min": null, "period": "monthly", "term": null}, "salary_visible": false, "title_keywords": ["sales & marketing manager", "assistant"], "responsibilities": ["collaborate", "planning process", "monitor", "project plan", "develop", "plan", "planning"], "requirements": {"degrees": ["degree holder"], "majors": ["business"], "languages": ["putonghua", "english", "chinese"], "language_level": ["good command"], "hard_skills": ["plus", "ms office"], "soft_skills": ["communication", "hands on", "confidence"], "languages_combined": [{"language": "putonghua", "language_level": ["good command"]}, {"language": "english", "language_level": ["good command"]}, {"language": "chinese", "language_level": ["good command"]}]}, "experience_required": {"duration": ["4 years"], "field": ["digital", "fmcg", "relevant experience"]}}, {"job_id": "100003009049599", "location_code": "hk", "company": "AXA China Region Insurance Company Limited", "job_title": "AXA PRIME PROGRAM / WEALTH MANAGEMENT MANAGER", "description": "Responsibilities:\n\nReport to Deputy Marketing Director\nCoordinate with internal departments and vendors on the development and deployment of CRM program strategy and mechanics, program branding, loyalty system, digital ecosystem, app, website and other marketing communication materials\nOversee and implement customer acquisition strategy, member engagement & communication strategy via online & offline channels and work closely with internal and external parties, including various business units and external vendors/agencies\nAnalyse the effectiveness of campaigns and promotions and provide insights for enhancement, with the assistance of Data Analyst and/agency\nSupport on performance analysis on CRM program and KPIs reporting\nProvide support and evaluation on tenant partnership, CSR partnership and reward sourcing\nExplore joint promotion opportunities to drive increased engagement of the targeted community, generating insights and trends from the members\u2019 experiences\nSet and monitor annual marketing strategies in correlating with budgets for brand building, product launching and market positioning\n\n\nRequirements:\n\nDegree holder in Business Administration, Communications, Marketing, e-Commerce or related disciplines\nMinimum 10 years related experience in retail industry, focusing on development of CRM and loyalty program or related areas, experience in Jewellery industry is highly preferable\nMicrosoft Office, CRM System, CMS and analysis tools experience or similar required\nHighly motivated, detail-minded and result driven with multi-tasking skills\nWith outstanding communication and leadership skills\nWell versed in written and spoken English , Cantonese and Mandarin\u00a0\u00a0\nTravel to Mainland China is required\nImmediate availability is preferred", "employment_types": ["Full Time", "Part Time", "Permanent", "Freelance"], "selling_points": ["FLEXIBLE WORKING HOURS ; ON THE JOB TRAINING", "15K - 30K BASIC SALARY + COMMISSION + BONUS", "PENSION AND MEDICAL INSURANCE"], "locations": ["Kwun Tong"], "categories": ["Admin & HR", "Training & Development", "Insurance", "Insurance Agent / Broker", "Marketing / Public Relations", "Management"], "post_time": "2022-01-14T09:03:37Z", "salary": {"currency": "HKD", "max": 29999, "min": 14000, "period": "monthly", "term": null}, "salary_visible": true, "title_keywords": ["wealth management manager"], "responsibilities": ["provide insights", "reporting", "provide support", "evaluation", "marketing strategies", "budgets", "data", "analysis", "internal and external parties", "coordinate with", "website", "monitor", "communication", "analyse", "kpis", "report"], "requirements": {"degrees": ["degree holder"], "majors": ["business administration", "e-commerce", "related disciplines", "marketing", "communications"], "languages": ["cantonese", "english", "mandarin"], "language_level": [], "hard_skills": ["microsoft office", "analysis", "e-commerce"], "soft_skills": ["detail-minded", "leadership skills", "communication", "motivated", "multi-tasking skills", "driven"], "languages_combined": [{"language": "cantonese", "language_level": []}, {"language": "english", "language_level": []}, {"language": "mandarin", "language_level": []}]}, "experience_required": {"duration": ["minimum 10 years"], "field": ["related", "development", "retail industry"]}}, {"job_id": "100003009044354", "location_code": "hk", "company": "Hong Kong Disneyland", "job_title": "Senior Event Services Manager", "description": "We are looking for the following candidate:\u00a0\n\n- Bachelor Degree holder or above in all disciplines\n\n- Mature, self\u00ad-motivated, diligent, willing to learn and with high integrity\n\n- Excellent interpersonal and communication skills\u00a0\n\n- Experience in banking/ financial industry will be an advantage\n\n- Fresh Graduates are also welcomed\n\nJob Nature:\n\n- Professional Financial Services\n\n- Construct financial planning including Wealth Protection, Wealth Accumulation , Wealth Distribution, Company insurance , Group Medical and Mandatory Provident Fund recommendation to client\u00a0\n\n- Understand client's wealth objectives and investment requirements, by monitoring risk levels of investment portfolios\n\n- Assess client's current financial situation and develop financial plan for client by selecting suitable financial and insurance products\n\n- Prepare presentations and proposals for both internal and client usage\u00a0\n\n- Review and revise client's financial plan based on their life-changing situations\n\n- Maintain friendly and lasting client relationships\n\nTeam Development:\n\n- Acquire leadership and team management skills for future career development and progression to managerial level\n\n- Motivate and inspire team members\n\n- Plan and execute strategies for constructing team\n\n- Share market insights and strategies in team\n\nBenefits & Compensations:\n\n- High commission with expected monthly income from HK$15,000+\n\n- Performance based incentives\u00a0\n\n- Professional awards and industry-wide recognition, i.e. Million Dollar Round Table (MDRT),\u00a0\n\n- Well-developed on-job-training; qualified applicants\u00a0\n\n\nGreat Opportunities is waiting for you .\u00a0 APPLY NOW ..\u00a0", "employment_types": ["Full Time"], "selling_points": ["Lead and support the team on problem solving", "Bachelor degree or above", "7 years of event management experience"], "locations": ["Lantau Island"], "categories": ["Marketing / Public Relations", "Management", "Public Relations - Event Management", "Others"], "post_time": "2022-01-13T03:49:23Z", "salary": {"currency": null, "max": null, "min": null, "period": "monthly", "term": null}, "salary_visible": false, "title_keywords": ["manager"], "responsibilities": ["management", "monitoring", "investment portfolios", "review", "presentations", "develop", "communication", "maintain", "plan", "banking", "career development", "insurance", "planning"], "requirements": {"degrees": ["bachelor degree holder"], "majors": [], "languages": [], "language_level": [], "hard_skills": ["presentations"], "soft_skills": ["communication skills", "integrity", "willing to learn", "diligent", "mature", "friendly", "leadership", "interpersonal"], "languages_combined": []}, "experience_required": {"duration": [], "field": ["financial industry", "banking"]}}, {"job_id": "100003009049083", "location_code": "hk", "company": "Bank of China (Hong Kong) Limited", "job_title": "Senior Project Manager / Project Manager (Business System and Procedure Management)", "description": "Responsibilities:\nLead the Corporate Banking and Financial Markets Training section\nFormulate, plan and deploy training initiatives and projects in alignment with the Bank's business goals and direction\nBuild effective relationship with Division / Department Heads, and offer consultancy and advice of training solutions\nKeep abreast of the latest CPT/CPD requirement, arrange relevant training and monitor the status of all relevant individuals\nMonitor the fulfilment of the continuous professional development under the industry-wide Enhanced Competency Framework\nSource and work with external training vendors in providing training solutions based on the identified needs\nManage the staff education sponsorship scheme\nSupport ad-hoc training projects as assigned\nRequirements:\nBachelor degree with at least 10 years of Learning & Development experience preferably gained from the banking and financial service industry\nKnowledge of the banking products and services would be an advantage\nGood knowledge of the regulatory requirements on the continuous professional training and development\nStrong sense of ownership, stakeholder management, organization and execution skills\nStrong problem solving ability, communication and analytical skills\nWell-versed in written English and Chinese; Putonghua would be an advantage", "employment_types": ["Full Time"], "selling_points": ["Perform end-to-end processes review", "Develop strong project governance management", "Minimum 5 years\u2019 retail banking experience"], "locations": ["Not Specified"], "categories": ["Banking / Finance", "Others", "Marketing / Public Relations", "Management", "Risk Management"], "post_time": "2022-01-14T08:05:19Z", "salary": {"currency": null, "max": null, "min": null, "period": "monthly", "term": null}, "salary_visible": false, "title_keywords": ["project manager", "senior project manager"], "responsibilities": ["ad-hoc", "business goals", "monitor", "banking", "plan", "deploy"], "requirements": {"degrees": ["degree", "bachelor"], "majors": [], "languages": ["putonghua", "english", "chinese"], "language_level": ["advantage"], "hard_skills": ["problem solving", "analytical skills"], "soft_skills": ["problem solving", "learning", "communication", "analytical skills"], "languages_combined": [{"language": "putonghua", "language_level": ["advantage"]}, {"language": "english", "language_level": []}, {"language": "chinese", "language_level": []}]}, "experience_required": {"duration": ["at least 10 years"], "field": ["learning & development", "service industry", "financial", "banking"]}}, {"job_id": "100003009038734", "location_code": "hk", "company": "Next81 Limited", "job_title": "F&B Marketing Manager", "description": "Responsibilities:\n\nAssist to develop and implement public affairs strategy\nConduct public affairs research and analysis\nDevelop and implement engagement progammes for key stakeholders and the general public\nDevelop and implement issue management strategy\nProvide editorial support in drafting speeches, media releases, reports, and meeting records\nPlan and support key events\n\nRequirements:\n\nUniversity bachelor\u2019s degree or above\nMinimum 10 years of relevant experience in communications, journalism or public relations agency\nExcellent language skills in both Chinese and English\nKnowledge of local public policy and current affairs will be an advantage\nAbility to perform well under pressure and meet deadlines\nAttention to detail & multitasking\n\nInterested parties please send:\n\nFull resume;\nCover letter;\nCopies of academic transcripts (including\u00a0public examination results if applicable);\nPresent and expected salary;\nAvailability\n\nBy clicking 'Apply Now' or by post to: Our Hong Kong Foundation Limited, 19/F, Nan Fung Tower, 88 Connaught Road Central, Hong Kong. Applicants who are not invited to an interview within two months from the date of this advertisement should consider their applications unsuccessful.\u00a0\n\nAll information provided by applicants will be handled with strictest confidence and will be solely used for the purpose of recruitment.", "employment_types": ["Full Time", "Permanent"], "selling_points": [], "locations": ["Kwun Tong"], "categories": ["Marketing / Public Relations", "Management"], "post_time": "2022-01-11T09:10:24Z", "salary": {"currency": null, "max": null, "min": null, "period": "monthly", "term": null}, "salary_visible": false, "title_keywords": ["marketing manager"], "responsibilities": ["management", "analysis", "develop", "reports", "plan"], "requirements": {"degrees": ["degree or above", "bachelor"], "majors": [], "languages": ["english", "chinese"], "language_level": ["excellent"], "hard_skills": [], "soft_skills": ["meet deadlines", "attention to detail", "perform well under pressure"], "languages_combined": [{"language": "english", "language_level": ["excellent"]}, {"language": "chinese", "language_level": ["excellent"]}]}, "experience_required": {"duration": ["minimum 10 years"], "field": ["agency", "public relations", "relevant experience"]}}, {"job_id": "100003009048254", "location_code": "hk", "company": "Sun Life Hong Kong Limited", "job_title": "MPF Business Development Manager \u5f37\u7a4d\u91d1\u696d\u52d9\u767c\u5c55\u7d93\u7406", "description": "CHINA MOBILE HONG KONG COMPANY LIMITED (\"CMHK\") is the wholly-owned subsidiary of China Mobile Limited (HKEx: 941) (NYSE: CHL), which ranks\u00a065th on the Fortune Global 500.\n\nOur company strives to offer superior service experience and to become the preferable digital partner for customers. We are preserving an environment with trust, responsibility and caring. At CMHK, we commit to maximizing people\u2019s potential and paving the way toward success for every striver. We are now inviting high caliber professional to join us.\n\nDivision: Marketing\n\nIn this position, you will:\n\nTo explore the opportunities and provide recommendations/ insight of prepaid business.\nParticipate in the formulation of marketing strategy which is in line with company objectives\nSupport and provide report on customers\u2019 portfolio evaluation, behavior analysis, sales performance to develop appropriate marketing programs.\nWork with internal departments to formulate new products/ service/ offers roll-out campaigns.\nMonitor competitors; keep track on the market trend\nAssist in preparation of presentation materials, written reports and proposals\nOther ad hoc duties assigned by management\n\nTo be successful in this position, you should meet the following requirements:\n\nBachelor\u2019s degree in Business Administration, Marketing or equivalent disciplines\nMinimum 6 years of working experience\u00a0in consumer marketing / technology / Telecom industry\nExperience in implement end to end acquisition program, developing marketing plans and campaigns\nGood understanding in business operations\nGood coordination, project management, multitasking and presentation skills\nKnowledge in IT system is a plus\nSelf-motivated, attention to details, multi-tasking and able to work under pressure\nFluency in written and spoken English, Cantonese and Mandarin\nCandidate with less experience may consider as Senior Marketing Executive\n\nWhen you work:\n\n5 days work\n8 hours/day\n\nWhat you enjoy:\n\nDouble pay\nDiscretionary Performance bonus\nLife insurance\nMedical insurance\nEducation subsidies\nBirthday gift\nMarriage leave\nBirthday leave\nStaff discount\n\nCMHK is committed to be an equal opportunity employer. We offer exceptional benefits package and the opportunity to work in a challenging environment. Personal data provided by applicants will be treated strictly in accordance with our personal data policy and for recruitment purposes only.\n\nPlease submit your application to us by clicking the APPLY NOW button and send your full resume with your availability, current and expected salary to us.", "employment_types": ["Full Time"], "selling_points": ["Welcome allowance 17k", "5 Days work with high incentives", "Hunghom"], "locations": ["Hung Hom"], "categories": ["Banking / Finance", "Financial Services", "Marketing / Public Relations", "Management", "Sales, CS & Business Devpt", "Retail Sales"], "post_time": "2022-01-14T06:03:47Z", "salary": {"currency": null, "max": null, "min": null, "period": "monthly", "term": null}, "salary_visible": false, "title_keywords": ["business development manager"], "responsibilities": ["marketing plans", "operations", "evaluation", "administration", "ad hoc duties", "work under pressure", "sales performance", "monitor", "developing", "develop", "reports", "report", "management", "provide recommendations", "analysis", "preparation of presentation materials", "project management", "coordination", "insurance"], "requirements": {"degrees": ["degree", "bachelor"], "majors": ["marketing", "business administration"], "languages": ["cantonese", "english", "mandarin"], "language_level": ["fluency"], "hard_skills": ["mobile", "analysis", "project management", "plus"], "soft_skills": ["self-motivated", "work under pressure", "project management", "presentation skills", "multi-tasking", "committed", "coordination", "attention to details", "presentation", "superior"], "languages_combined": [{"language": "cantonese", "language_level": ["fluency"]}, {"language": "english", "language_level": ["fluency"]}, {"language": "mandarin", "language_level": ["fluency"]}]}, "experience_required": {"duration": ["minimum 6 years"], "field": ["digital", "marketing", "developing"]}}, {"job_id": "100003009040605", "location_code": "hk", "company": "Cook Medical", "job_title": "Marketing Manager, APAC (Urology)", "description": "As the leading financial advisory firm in Hong Kong, Convoy upholds its core values of Passion, Integrity and Professionalism in providing the best advices and service to help customers investing in their future.\n\nDue to our business expansion, we are looking for high calibre candidates to share our vision and venture our success.\n\n\n\nResponsibilities:\n\n\n\nReporting to the Team Head, you will be responsible for brand management, new brand development, marketing and communications of our portfolio of wealth & health brands\nDrive integrated marketing campaigns to achieve business objectives in terms of brand awareness, lead generations and customer acquisitions\nWork with sales, product, technology counterparts across different BUs and external agency partners to propose and drive marketing initiatives that support the business growth of our brands\nAct as the brand custodian to develop and manage brand and marketing communications guidelines and be accountable for brand governance across the Group\nConduct market research and customer analysis for planning and reporting purpose.\n\nRequirements:\n\nMinimum 6 years of marketing management experience from either in-house or agency side, experience in finance/insurance or healthcare industries would be an advantage\nExperience with track record driving comprehensive 360-degree integrated marketing campaigns for business growth.\nStrong understanding of effective brand management, publicity and marketing communications.\nUp to date knowledge of marketing best practice and an eye for creative marketing opportunities\nGreat communications and interpersonal skills and ability to lead and inspire the team\nGreat command of spoken and written English and Chinese, Mandarin would be an advantage\nWe offer competitive remuneration including career prospects to the right candidate. Interested parties please send detailed resume with availability, current and expected salaries to\u00a0Human Resources Department, Convoy Global Holdings Limited, Trust Tower, 68 Johnston Road, Wan Chai, Hong Kong\u00a0or by clicking the\u00a0Apply Now\u00a0button and upload your CV and cover letter.\n(All applications will be treated in strict confidence and used for recruitment purpose within Convoy Global Holdings Limited only. All applicants are kept on file 6 months from the date of the application.)", "employment_types": ["Full Time", "Permanent"], "selling_points": ["International Medical Device Company", "With 6-8 years relevant experience", "Offer attractive remuneration and benefits"], "locations": ["North Point"], "categories": ["Marketing / Public Relations", "Management", "Marketing - General / Support", "Marketing - Market Research"], "post_time": "2022-01-12T02:50:31Z", "salary": {"currency": null, "max": null, "min": null, "period": "monthly", "term": null}, "salary_visible": false, "title_keywords": ["marketing manager"], "responsibilities": ["reporting", "management", "guidelines", "conduct market research", "develop", "analysis for planning", "marketing campaigns"], "requirements": {"degrees": [], "majors": [], "languages": ["english", "chinese", "mandarin"], "language_level": ["advantage"], "hard_skills": [], "soft_skills": ["comprehensive", "interpersonal skills", "creative"], "languages_combined": [{"language": "english", "language_level": ["advantage"]}, {"language": "chinese", "language_level": ["advantage"]}, {"language": "mandarin", "language_level": []}]}, "experience_required": {"duration": ["minimum 6 years"], "field": ["healthcare", "management", "agency", "finance", "marketing", "business", "insurance"]}}, {"job_id": "100003009042420", "location_code": "hk", "company": "CITIC Telecom International CPC Limited", "job_title": "Senior Marketing Executive / Assistant Marketing Manager", "description": "The Challenge We Pose to You:\n\nSupport and develop effective marketing strategies and planning set by the company for achieving business goals\nWork closely with in-house design team and external agencies to develop marketing materials and media exposures\nWebsite content development and management\nDevelop and reinforce partnership with partners and public associations\nInitiate new marketing ideas and implement creative industry-focused marketing programs and activities\nManage budget control process for tracking expenses and payment status\nHandle ad hoc projects as assigned\nWhat You Bring to Us:\n\nBachelor Degree in Marketing or related discipline.\nMinimum 5 years experience with proven performance in telecommunications or IT related industries\nExperience in social media or digital marketing is an advantage but not a must\nInnovative, independent, self-motivating, result-oriented, able to meet tight deadlines and work under pressure\nGood interpersonal, presentation and team building skills\nGood command of English, Cantonese and Putonghua.\nCandidate with more experience will be considered as Assistant Marketing Manager\u00a0\n\nOur Offer:\n\n5-day work, 14 days annual leave, a competitive remuneration package, comprehensive medical and dental plan, local and regional training and rewarding career opportunities.\n\nPlease send your complete resume (in MS word format), inclusive of your available date, current and expected salary by clicking 'Apply Now' or by mail\u00a0 to: Human Resources and Administration Department, CITIC Telecom International CPC Limited, 20/F, Lincoln House, Taikoo Place, 979 King's Road, Quarry Bay, Hong Kong.\u00a0 \u00a0\n\nWebsite: http://www.citictel-cpc.com/\n\nAll information received will be kept strictly confidential and for employment-related purpose only.", "employment_types": ["Full Time", "Permanent"], "selling_points": ["Min. 5 years in marketing (event management)", "Telco or IT industry preferable", "Manage artwork, content development, proofreading"], "locations": ["Quarry Bay"], "categories": ["Marketing / Public Relations", "Management", "Marketing - Brand / Product Management", "Public Relations - Event Management"], "post_time": "2022-01-12T07:24:57Z", "salary": {"currency": null, "max": null, "min": null, "period": "monthly", "term": null}, "salary_visible": false, "title_keywords": ["assistant marketing manager", "senior marketing executive"], "responsibilities": ["business goals", "ideas", "website", "design", "payment", "plan", "budget control", "administration", "work under pressure", "expenses", "develop", "social media", "management", "marketing strategies", "digital marketing", "tracking", "ad hoc projects", "marketing materials", "planning"], "requirements": {"degrees": ["degree", "bachelor"], "majors": ["marketing"], "languages": ["cantonese", "putonghua", "english"], "language_level": ["good command"], "hard_skills": ["ms word"], "soft_skills": ["meet tight deadlines", "independent", "focused", "interpersonal", "presentation", "innovative", "comprehensive", "creative", "result-oriented", "work under pressure"], "languages_combined": [{"language": "cantonese", "language_level": ["good command"]}, {"language": "putonghua", "language_level": ["good command"]}, {"language": "english", "language_level": ["good command"]}]}, "experience_required": {"duration": ["minimum 5 years"], "field": ["social media", "related", "it", "digital marketing", "marketing", "telecommunications"]}}, {"job_id": "100003009040056", "location_code": "hk", "company": "China Mobile Hong Kong \u4e2d\u570b\u79fb\u52d5\u9999\u6e2f", "job_title": "Assistant Marketing Manager, Marketing planning (prepaid)", "description": "Our client is a reputable online platform with presence in Hong Kong and South East Asia. They are now seeking high\u00a0caliber\u00a0professional to join the team as Marketing Manager for the B2B side partners development.\u00a0\n\nResponsibilities:\nBuild company branding and awareness to target audience\nDrive effective usage and increase conversion rate to improve sales performance\nPlan and implement overall partnerships and affiliate strategies to boost user acquisition and drive sales\nAnalyze sales and usage data to identity opportunities for business growth\nQualifications:\n\nBachelor degree or above in business or marketing related discipline\n5 years\u2019 working experience in marketing,\u00a0preferably with B2B experience\nStrong analytical, problem solving and project management skills\u00a0\nGood written and spoken Chinese and English, with strong communication and negotiation skill\nPossess strong business networks and experience in formulating customer loyalty programme are preferred\nAn attractive remuneration package will be offered to the right candidates. Please send your updated resume with expected salary via\u00a0Apply Now\u00a0or send your application to the email address showing in the Company Description.\n\nPersonal data collected will be used for recruitment purpose only.", "employment_types": ["Full Time", "Permanent"], "selling_points": ["16 AL, 5 days work week", "double pay, dis. performance bonus", "Staff SIM, Staff Offer"], "locations": ["Kwai Hing"], "categories": ["Marketing / Public Relations", "Management", "Marketing - Brand / Product Management", "Marketing - Direct Marketing"], "post_time": "2022-01-12T01:09:47Z", "salary": {"currency": null, "max": null, "min": null, "period": null, "term": null}, "salary_visible": false, "title_keywords": ["assistant marketing manager"], "responsibilities": ["sales and usage data", "affiliate strategies", "improve sales performance", "communication", "project management", "recruitment", "plan", "drive sales", "personal data"], "requirements": {"degrees": ["degree or above", "bachelor"], "majors": ["business", "marketing"], "languages": ["english", "chinese"], "language_level": ["good"], "hard_skills": ["problem solving", "project management"], "soft_skills": ["problem solving", "project management skills", "communication", "negotiation skill"], "languages_combined": [{"language": "english", "language_level": ["good"]}, {"language": "chinese", "language_level": ["good"]}]}, "experience_required": {"duration": ["5 years"], "field": ["business", "marketing"]}}, {"job_id": "100003009041157", "location_code": "hk", "company": "Doo Technology Limited", "job_title": "Content Team Lead / Manager", "description": "This leading organization is consistently expanding their business in HK, the unique organization is now recruiting this communications position to join one of their business functions.\n\nWith over a century presence in HK, the organization continues to grow and expand their team by hiring a communications professional who helps to drive their communication strategies.\n\nResponsibilities:\n\nDevelop and manage corporate communications plans to enhance the company's image\nLead a team to drive media communications in order to achieve business goals of the company\nPartner with senior management as a corporate advisor on communications strategy\nTake charge of critical enterprise communications to assure information released on time to all stakeholders\nKeep abreast of important development related to the industry and public affairs\n\nRequirements:\n\nDegree in communications, marketing or related disciplines\nAt least 15 years of working experience in public relations & communications\nCandidates with large corporate experience within technology sector is preferred\nExtensive knowledge in media landscape\nExcellent communications skills in both conversational and written English, Mandarin and Cantonese\n\nInterested individuals can click apply now and send through updated resume in WORD format. For a more comprehensive list of current opportunities, please visit www.connectedgroup.com\n\n#StayConnected", "employment_types": ["Full Time", "Permanent"], "selling_points": [], "locations": ["Kowloon Bay"], "categories": ["Media & Advertising", "Editorial / Journalism", "Marketing / Public Relations", "Management", "Public Relations - Copy-writing"], "post_time": "2022-01-12T03:40:13Z", "salary": {"currency": null, "max": null, "min": null, "period": "monthly", "term": null}, "salary_visible": false, "title_keywords": ["manager", "lead"], "responsibilities": ["business goals", "develop", "lead a team", "plans", "senior management"], "requirements": {"degrees": ["degree"], "majors": ["related disciplines", "marketing", "communications"], "languages": ["cantonese", "english", "mandarin"], "language_level": ["conversational", "excellent"], "hard_skills": ["word"], "soft_skills": ["comprehensive", "extensive"], "languages_combined": [{"language": "cantonese", "language_level": ["conversational", "excellent"]}, {"language": "english", "language_level": ["conversational", "excellent"]}, {"language": "mandarin", "language_level": ["conversational", "excellent"]}]}, "experience_required": {"duration": ["at least 15 years"], "field": ["public relations"]}}, {"job_id": "100003009040463", "location_code": "hk", "company": "Sun Life Hong Kong Limited", "job_title": "Customer Service Officer (MPF AGENCY)", "description": "As the dealer of Bentley in Hong Kong and Macau,\u00a0we are now looking for\u00a0a talented Senior Marketing Officer / Marketing Officer to manage and run a wide range of marketing and VIP programs to strengthen relationship with Bentley customers and acquire new customers and engagement in Hong Kong and Macau markets\n\n\u00a0\nJob Responsibilities:\n\n\nAssist in developing, planning and implementing ATL & BTL marketing strategies, campaigns and promotional activities\nSupport marketing campaigns in different aspects including advertising, digital marketing, events, partnership and public relations\nWork closely with retail and CRM team to develop events / campaigns for VIPs which drive targeted sales and top of mind awareness of the brand image, and to ensure successful implementation\nConduct business analysis to monitor and evaluate the effectiveness of marketing campaign\nHandle ad-hoc projects as assigned\n\n\nTogether with creativity, integrity and passion, our ideal staff should meet the following requirements:\n\nDegree holder in Marketing, Communication, Business or relevant discipline\nMinimum 4 years of solid working experience in marketing in the similar capacity, hands-on events marketing experience is a must, preferably in luxury goods industry\nStrong interpersonal and communication skills and attentive to details\nCreative, passionate and excellent in problem solving skills with positive attitude\nIndependent, time management, ability to multi-task, work well under pressure and thrive in a fast-paced environment with the ability to respond to change in pace and priority\nExcellent command of spoken and written English & Chinese\nProficiency in MS applications and Chinese word processing\nCandidates with less experience will be considered for the post of Marketing Officer\n\n\nInterested parties, please send your application with detailed resume stating expected salary and date of availability by clicking \"APPLY NOW'.\n\nAll information will be used solely for recruitment purpose and will be destroyed when the recruitment process is finished.", "employment_types": ["Full Time"], "selling_points": ["Clear career path with attractive salary (20k up)", "Answer enquiries & complaints from customers", "Fresh graduate are welcome"], "locations": ["Hung Hom"], "categories": ["Sales, CS & Business Devpt", "Customer Service - Supervisor / Officer", "Marketing / Public Relations", "Management", "Sales - Sales Management"], "post_time": "2022-01-12T02:37:40Z", "salary": {"currency": "HKD", "max": 29999, "min": 20000, "period": "monthly", "term": null}, "salary_visible": true, "title_keywords": ["customer service officer"], "responsibilities": ["management", "marketing strategies", "advertising", "monitor", "developing", "implementation", "develop", "evaluate", "communication", "promotional activities", "digital marketing", "marketing campaigns", "business analysis", "ad-hoc projects", "planning"], "requirements": {"degrees": ["degree holder"], "majors": ["business", "marketing"], "languages": ["english", "chinese"], "language_level": ["excellent", "proficiency"], "hard_skills": ["chinese word processing", "analysis", "ms applications", "problem solving skills"], "soft_skills": ["passionate", "communication skills", "independent", "multi-task", "attentive to details", "under pressure", "fast-paced environment", "integrity", "communication", "positive attitude", "hands-on", "time management", "problem solving skills", "creative", "interpersonal", "ideal"], "languages_combined": [{"language": "english", "language_level": ["excellent"]}, {"language": "chinese", "language_level": ["excellent", "proficiency"]}]}, "experience_required": {"duration": ["minimum 4 years"], "field": ["marketing"]}}, {"job_id": "100003009042957", "location_code": "hk", "company": "ConnectedGroup Limited", "job_title": "Head of Communications - Technology", "description": "Job Summary:\nWorking closely with event sales teams in each market, the job holder will be responsible for overall management of Event Services team and deliver the highest quality service at Disney standard to various kinds of Business Solutions & Events (BS&E) events, including corporate events, wedding events, and social catering events.\nResponsibilities:\nLead a team of Event Services professionals to manage and deliver various types of BS&E events that take place in the resort hotels and in Hong Kong Disneyland Park, and ensure the team consistently offer world-class level of service to drive client and guest satisfaction for each event;\nDrive creation and capturing of upselling/ cross-selling opportunities during the course of event management and delivery with each client, and contribute to revenue generation under overall BS&E team;\nLead and support the team on problem solving and solution formulation during the event delivery process, when there are conflicts/ inconsistency among clients\u2019 requests, standards/ requirement from internal stakeholders, available resources, government regulations, etc.;\nLead the team to maintain high standard of storage and upkeep for key reusable amenities and props for BS&E event formats, and/ or to request replenishment of consumable items when necessary, in close collaboration with different vendors and internal partners;\nDrive knowledge management efforts among the team, to ensure all team members have the training and resources to carry out their current responsibilities and get ready for more, as well as continuous product, process, systems and operational knowledge refresh;\nContinuously explore ways to streamline and improve event management and delivery processes, to improve work efficiency and quality;\nAct as a primary internal point of contact for the team in terms of different operational issues, or cross-department projects/initiatives.\nBasic Qualifications:\nBachelor degree or above;\nAt least 7 years of event management experience with a luxury hotel/ resort/ venue, with extensive knowledge in hospitality management, food & beverage and banquet catering operations.\nExperience with operational teams within HKDL and/ or experience in handling sizable groups and events would be an advantage;\nDemonstrated track-record and ability to lead a team;\nBe able to work independently and under pressure, in an ever-changing business environment;\nExcellent presentation, problem solving, negotiations and coaching skills;\nExcellent written (English and Chinese) and verbal (English, Cantonese, Mandarin) communication skills.\nAdditional Information:\nSUBMITTING YOUR APPLICATION\nAfter clicking \u201cApply for this job\u201d below, the employment application will open in a new window. Please complete ALL pages of the application in ENGLISH by clicking \u201cNext\u201d on each page, then \u201cSubmit\u201d on the final page.\n#LI-GN1 HKProfessional", "employment_types": ["Full Time", "Permanent"], "selling_points": ["Team management", "Consumer & Corporate Communications", "Fast paced, dynamic"], "locations": ["Not Specified"], "categories": ["Marketing / Public Relations", "Management", "Public Relations - Copy-writing", "Public Relations - General / Support"], "post_time": "2022-01-12T09:18:40Z", "salary": {"currency": null, "max": null, "min": null, "period": "monthly", "term": null}, "salary_visible": false, "title_keywords": [], "responsibilities": ["regulations", "management", "operations", "systems", "quality", "teams", "replenishment", "communication", "lead a team", "maintain", "contact", "support the team", "catering"], "requirements": {"degrees": ["degree or above", "bachelor"], "majors": [], "languages": ["cantonese", "english", "chinese", "mandarin"], "language_level": ["excellent"], "hard_skills": ["problem solving", "basic"], "soft_skills": ["communication skills", "work independently", "under pressure", "responsible", "changing business environment", "problem solving", "extensive", "presentation", "world-class"], "languages_combined": [{"language": "cantonese", "language_level": ["excellent"]}, {"language": "english", "language_level": ["excellent"]}, {"language": "chinese", "language_level": ["excellent"]}, {"language": "mandarin", "language_level": ["excellent"]}]}, "experience_required": {"duration": ["at least 7 years"], "field": ["food", "management"]}}, {"job_id": "100003009043845", "location_code": "hk", "company": "Office Systems Ltd", "job_title": "Marketing Manager", "description": "Duties\nHandle service inquiries raised by clients\nMaking outbound calls regarding our services\nProvide sales and administrative support\nEnlarge and extend potential market segments in a proactive approach\nRequirements\n\nDegree holder in Business or related discipline\nMinimum 2 years\u2019 relevant experience in financial industry preferred\nExperience in customer service is an advantage\nSelf-motivated and service-oriented with good communication and interpersonal skills\nFluency in written and spoken Chinese\nBenefits\n\n\nAttractive remuneration package\u00a0will be offered to the right candidates\nHigh commission, monthly performance bonus, year-end performance bonus and pension benefits\nWell-structured training programs and comprehensive training platform\nClear career path and fast-track promotion to management level\nMedical benefits and training allowances", "employment_types": ["Full Time", "Permanent"], "selling_points": ["Degree in Marketing", "5 years' experience in marketing", "Experience in manage a sales team"], "locations": ["Shau Kei Wan"], "categories": ["Marketing / Public Relations", "Management", "Marketing - Brand / Product Management", "Others"], "post_time": "2022-01-13T03:46:28Z", "salary": {"currency": null, "max": null, "min": null, "period": "monthly", "term": null}, "salary_visible": false, "title_keywords": ["marketing manager"], "responsibilities": ["administrative support"], "requirements": {"degrees": ["degree holder"], "majors": ["business"], "languages": ["chinese"], "language_level": ["fluency"], "hard_skills": [], "soft_skills": ["self-motivated", "customer service", "communication and interpersonal skills", "service-oriented"], "languages_combined": [{"language": "chinese", "language_level": ["fluency"]}]}, "experience_required": {"duration": ["minimum 2 years"], "field": ["customer service", "financial industry", "relevant experience"]}}, {"job_id": "100003009041195", "location_code": "hk", "company": "KGI Hong Kong Limited", "job_title": "Head of Marketing & Public Relations (Ref: 10A46-HMPR-JDB)", "description": "Job Highlights\n\nBachelor degree holder in all disciplines\nWell-development career ladder\nFive-day work\n\nJob Description\n\nYou will enjoy working at Sun Life if you are with vision, energy and targets, join us and be part of a dynamic team and create values together.\n\nAs the leader in wealth management, offering innovative and intelligent solutions to thousands of individual and businesses in Hong Kong, China, Canada, Malaysia, Indonesia and other high growth cities around the world. We keep our clients\u2019 interests foremost in our minds at all times. This combination of intellectual capital, comprehensive training, staffed with quality leaders and professional managers set us apart as an industrial leader.\n\nWe are currently seeking young and energetic talents\u00a0to join our team as a\u00a0Management Trainee.\n\nJob Responsibilities\n\nProvide professional financial services to our clients, including risk management, health protection, retirement planning and wealth accumulation\nManaging the total wealth of clients by matching our financial and investment solutions to fulfill their financial needs\nClients relationship management, expand clients\u2019 network and review their financial need regularly\nPromoting our Premier Service to potential clients, exploring their needs and making referrals to other business units where appropriate\u00a0\n\nBenefits and Packages\n\nFive-day work\nCompetitive Pay With Quarterly Bonus and Year End Bonus\nInitial Training and On-Job Training Provided\nExcellent Career Path to Management Ladder\nLife and Medical Insurance\nClient Base Provided\u00a0\nFlexible Working Hours\u00a0\nEducation Subsidies\n\nRequirements\n\nBachelor degree or above (Fresh graduates is welcomed)\n1 year working experience or above is preferred\nExperience in\u00a0customer service or sales field\nProactive with positive mindset, excellent interpersonal &\u00a0communication skills\nAble to work independently\nFluent in Cantonese, moderate English\n\nWorking Location\n\n\nWhampoa\n\n**Personal date provided by applicants will be treated in strict confidence and used for recruitment purposes only**\n\nIf you have any further enquiries, please press\u00a0APPLY NOW\u00a0to contact us with your CV. We will get back to you shortly.", "employment_types": ["Full Time", "Permanent"], "selling_points": ["Lead full spectrum of corporate marketing & PR", "Implement marketing campaigns & communication", "Build corporate brand in public & targeted markets"], "locations": ["Wan Chai"], "categories": ["Banking / Finance", "Financial Services", "Marketing / Public Relations", "Management", "Marketing - Marketing Communication"], "post_time": "2022-01-12T03:34:54Z", "salary": {"currency": null, "max": null, "min": null, "period": "monthly", "term": null}, "salary_visible": false, "title_keywords": [], "responsibilities": ["management", "review", "quality", "planning"], "requirements": {"degrees": [], "majors": [], "languages": [], "language_level": [], "hard_skills": [], "soft_skills": [], "languages_combined": []}, "experience_required": {"duration": [], "field": []}}, {"job_id": "100003009041619", "location_code": "hk", "company": "Kam Lung Motor BM Limited", "job_title": "Senior Marketing Officer / Marketing Officer", "description": "POSITION PURPOSE\n\nAesop Visual Merchandising endeavours to develop unrivalled design and creativity that challenges and excites, through concepts that resonate with local communities and honour our environment. Visual Merchandisers at Aesop curate a full sensory and spatial experience that does not concede to the mass approach; we create distinctive retail campaigns, installations, photographic sets and events that are executed with formidable artistry. We are storytellers, delivering a unique three-dimensional approach that drives intrigue and further dialogue in store that converts pedestrian to customer.\n\nThe VM Assistant Manager will oversee the creation and implementation of each campaign across the Asia region. They will manage each step within the campaign roll-out from liaising with fabricators to forecasting stock allocation for stores to ensuring the overall visual presence of a campaign within each retail location is of exceptional standard. They will also oversee guidance and check plans for new store openings and photoshoots. The ideal candidate will come from a three-dimensional design background and will have experience in a retail environment in a similar role. The candidate must have excellent project management skills and the ability to manage multiple\n\nFollowing prescriptive guidance from the Global VM teams, the Visual Merchandising Campaign Manager will need to interpret guides and implement them in accordance with Asia, they will work closely with Marketing, Retail and Global VM to realise all aspects of campaign executions across our retail locations.\n\nMAIN RESPONSIBILITIES\n\nCampaign Assets\n\n\nWork in partnership with Marketing to select clear priorities within the VM global options that allow us to work at scale and create efficiencies.\nOversee the completion and delivery of the MMOF from local VM teams\nOversee the delivery of all campaign assets\nEnsure cohesion between all campaign components, vinyls, light boxes, props, printed assets etc.\nOversee, manage and guide the submissions of VM plans for each market\nHelp local VM Specialists to manage their campaign budget including all visual assets\nWork with Marketing and Commercial Directors to finalise the Elevated Activations list each campaign\nWork closely with the Finished Artist to provide feedback and guidance on campaign assets\nOversee post-campaign reports & review together with Regional VM Manager\n\nProp Creation\n\n\nFollow guidance from Global VM on design of all props and interpret materiality, size and quantity based off Asia's needs\nSupport local VM Specialists in understanding and sourcing of all props & materials\nQuality check and review VM teams prop samples and proposals, correcting & guiding when necessary\nConsolidate questions and seek feedback from Global VM team\nEnsure procurement and partnerships actively champion under-represented voices and minority-owned businesses\nEnsure procurement, installations, storage all adhere to environmental sustainability standards, actively propose new solutions\nExplore new solutions to providing printed assets in line with our sustainable objectives\nGuide local VM team plans for post-use of all props produced as well as storage\nSupport VM Specialists in the production and distribution of Evergreen props\n\nNew Stores\n\n\nEnsure VM needs are met and communicated to relevant teams in advance\nGuide local VM Specialists on Photoshoot planogram and Operational planogram\n\nPlanning and Logistics\n\n\nCreate campaign timeline to include all steps contributed by the Global-Regional-Local VM and Marketing teams\nGuide VM teams on product forecasting for all campaigns\nOversee the distribution and delivery of campaign assets\n\nCommunication\n\n\nMeet regularly with the VM markets to understand their needs\nMonitor the success of VM displays, collect feedback and react accordingly, analyse impact and ROI when relevant\n\nTraining and Mentoring\n\n\nProvide constant guidance and support to the Finished Artist and local VMs\n\nPREFERRED QUALIFICATIONS AND SKILLS\n\n\n5 + years experience working with three-dimensional space/displays in a commercial or creative space\nWorking knowledge of the Adobe Creative Suite (InDesign, Photoshop, Illustrator) and Microsoft Office (PPT, Excel)\nStrong attention to detail, design aesthetic and exceptional organisational skills\nExperience in project management and prop creation\nExperience leading visuals and project coordination for multilocation campaign roll-outs\nExperience building out project timelines and milestones while engaging and gaining approval from all necessary stakeholders\nUnderstanding of Aesop's visual culture and a passion for the brand\nA meticulous level of detail, in all endeavours", "employment_types": ["Full Time", "Permanent"], "selling_points": ["Leading Automotive Group", "Product marketing & branding", "Competitive remuneration package"], "locations": ["Tsuen Wan Area"], "categories": ["Marketing / Public Relations", "Management", "Marketing - Marketing Communication", "Public Relations - Event Management"], "post_time": "2022-01-12T06:15:56Z", "salary": {"currency": null, "max": null, "min": null, "period": "monthly", "term": null}, "salary_visible": false, "title_keywords": ["senior marketing officer", "marketing officer"], "responsibilities": ["vm team", "budget", "merchandising", "design", "communication", "plans", "teams", "implementation", "liaising with", "develop", "monitor", "reports", "logistics", "visual", "analyse", "forecasting", "guidance", "quality check", "stock allocation", "review", "project coordination", "project management", "planning"], "requirements": {"degrees": [], "majors": [], "languages": [], "language_level": [], "hard_skills": ["excel", "react", "microsoft office", "visual culture", "visual merchandising", "indesign", "illustrator", "project management", "adobe creative suite", "photoshop"], "soft_skills": ["meticulous", "passion for", "project management skills", "unique", "clear", "communication", "project management", "organisational skills", "attention to detail", "coordination", "creative", "ideal"], "languages_combined": []}, "experience_required": {"duration": ["5 + years"], "field": ["commercial", "project management", "retail", "design"]}}, {"job_id": "100003009037467", "location_code": "hk", "company": "Sephora Hong Kong Limited", "job_title": "Assistant CRM & Loyalty Manager", "description": "Job Highlights\n\nBachelor degree holder in all disciplines\nWell-development career ladder\nFive-day work\n\nJob Description\n\nYou will enjoy working at Sun Life if you are with vision, energy and targets, join us and be part of a dynamic team and create values together.\n\nAs the leader in wealth management, offering innovative and intelligent solutions to thousands of individual and businesses in Hong Kong, China, Canada, Malaysia, Indonesia and other high growth cities around the world. We keep our clients\u2019 interests foremost in our minds at all times. This combination of intellectual capital, comprehensive training, staffed with quality leaders and professional managers set us apart as an industrial leader.\n\nWe are currently seeking young and energetic talents\u00a0to join our team as a\u00a0Management Trainee.\n\nJob Responsibilities\n\nProvide professional financial services to our clients, including risk management, health protection, retirement planning and wealth accumulation\nManaging the total wealth of clients by matching our financial and investment solutions to fulfill their financial needs\nClients relationship management, expand clients\u2019 network and review their financial need regularly\nPromoting our Premier Service to potential clients, exploring their needs and making referrals to other business units where appropriate\u00a0\n\nBenefits and Packages\n\nFive-day work\nCompetitive Pay With Quarterly Bonus and Year End Bonus\nInitial Training and On-Job Training Provided\nExcellent Career Path to Management Ladder\nLife and Medical Insurance\nClient Base Provided\u00a0\nFlexible Working Hours\u00a0\nEducation Subsidies\n\nRequirements\n\nBachelor degree or above (Fresh graduates is welcomed)\n1 year working experience or above is preferred\nExperience in\u00a0customer service or sales field\nProactive with positive mindset, excellent interpersonal &\u00a0communication skills\nAble to work independently\nFluent in Cantonese, moderate English\u00a0\n\nWorking Location\n\n\n\nWhampoa\u00a0\n\n**Personal date provided by applicants will be treated in strict confidence and used for recruitment purposes only**\n\nIf you have any further enquiries, please press\u00a0APPLY NOW\u00a0to contact us with your CV. We will get back to you shortly.", "employment_types": ["Full Time", "Permanent"], "selling_points": ["A leading beauty retailer, backed by the LVMH", "Building and Growing the Loyalty Database", "Lead our loyalty program, Sephora Beauty Pass"], "locations": ["Quarry Bay"], "categories": ["Marketing / Public Relations", "Management", "Marketing - Brand / Product Management", "Marketing - General / Support"], "post_time": "2022-01-11T02:53:59Z", "salary": {"currency": null, "max": null, "min": null, "period": "monthly", "term": null}, "salary_visible": false, "title_keywords": ["manager", "assistant"], "responsibilities": ["management", "review", "quality", "planning"], "requirements": {"degrees": [], "majors": [], "languages": [], "language_level": [], "hard_skills": [], "soft_skills": [], "languages_combined": []}, "experience_required": {"duration": [], "field": []}}, {"job_id": "100003009043397", "location_code": "hk", "company": "Sun Life Hong Kong Limited", "job_title": "Customer Service Officer (MPF)", "description": "About KPMG\n\nThrough helping other organizations mitigate risks and grasp opportunities, we can drive positive, sustainable change for clients, our people and society at large.\n\nKPMG member firms operate in 153 countries, collectively employing more than 207,000 people, serving the needs of business, governments, public-sector agencies, not-for-profits and through member firms' audit and assurance practices, the capital markets. KPMG is committed to quality and service excellence in all that we do, bringing our best to clients and earning the public's trust through our actions and behaviours both professionally and personally.\n\nWe lead with a commitment to quality and consistency across our global network, bringing a passion for client success and a purpose to serve and improve the communities in which member firms operate. In a world where rapid change and unprecedented disruption are the new normal, we inspire confidence and empower change in all we do.\n\nWe are proud to be have won the \u201cBest Companies to Work for in Asia - China\" awarded by HR Asia Media for the past consecutive years.\n\nAbout the role\n\nThis position represents a manager role in our Markets Team, specifically the sector development for the New Economy sector and activities. The member in this role support the management and delivery of our account/channel management programme, focused on developing business relationships with targets, and converting them into business opportunities for KPMG.\n\nThe objective is to represent the full range of KPMG services, and develop and maintain profitable business relationships across key targets. In addition to strong knowledge, you will need to learn and understand our clients\u2019 needs and KPMG\u2019s opportunities across different industries.\n\nWe are looking for self-starters with a sense of personal responsibility for managing the sector as well as managing accounts. You demonstrate outstanding relationship-building skills across the firm and within the global network, as well as with important players in the sector as well as executives at relevant clients.\n\nResponsibilities\n\nWork with the Head of New Economy to drive and increase KPMG\u2019s market share in Hong Kong\u2019s New Economy ecosystem\nManage and coordinate New Economy strategic initiatives to achieve set upon targets and goals\nMake sure to know about current New Economy market developments \u2013 e.g. venture deals, events / forums\nDrive business development (develop new leads & relationship, pipeline management)) initiatives with key New Economy ecosystem players \u2013 e.g. start-ups, investors, incubators & accelerators\nSupport development of client proposals / pitches and presentation materials \u00a0\n\n1. Sector planning / Account planning and Management\n\nManage a key account/target portfolio which includes detailed relationship matrix and plans, industry and account business issues and an ongoing pipeline of opportunities\nHave an understanding of priorities on key account management goals and works with the team to implement strategic growth goals and objectives\nFacilitate in the development, strategy and execution for both internal meeting and external key client deliverables including pursuit documents, credential lists, meeting agendas, etc.\nUnderstanding of KPMG-wide services, solutions, thought leadership to determine which programs, events and initiatives would be relevant to the client\nSupport priority accounts and follow up to key activities required as part of account planning\nSupport the account plan, ensuring disciplined outcomes, with the Client Service Team (CST) around contacts, pipeline management, pursuit conversion and events\n\n\n\n2. Relationship/Pipeline Management\n\nWork with team to develop and track the client relationship strategy, and plan touch point actions to strengthen relationships\nDevelop an understanding of services and solutions to determine which initiatives would be of relevance and importance to key stakeholders/decision makers\nServe as a coach in account management and any reporting functions (i.e. dashboard, market updates)\nHelp identify business opportunities for account teams through understanding of client imperatives and marketing initiatives\nBuild an effective internal firm wide network that enables the role holder to bring the most appropriate expertise to bear, on individual clients\u2019 needs\nProvide logistic and administrative support for the execution of account management and pursuits activities\nProvide pursuit support with existing pursuits teams and/or develop/manage pursuit best practice to meet help us differentiate KPMG to our Clients\nCapturing key actions and minutes of meetings and ensuring next steps are followed up\nProducing reports and presentations to provide key updates on contacts, follow-up, pipeline, wins and revenue\nDesktop research to support the account teams and working with various groups to obtain key information for the account.\n\nRequirement\n\nUniversity graduate with a minimum 5 years\u2019 relevant experience\nExperience within the sector\nKnowledge and insights in the China Market\nBackground in a professional services/ financial services organisation would be an advantage\nStrong organizational skills, detail-conscious, pro-active, hard-working and resilient\nSelf-driven and creative with the ability to take on multiple activities and tasks\nExcellent interpersonal and communication skills, with flexibility to adapt to different working styles of senior stakeholders\nStrong Proficiency in PowerPoint, Excel and MS office suite is essential\nChinese (Mandarin) and fluent English is a must for this role\n\nWe offer successful candidates an attractive remuneration package and the opportunity to work in a dynamic and exciting environment.\n\nPersonal data collected will be used for recruitment purposes only.", "employment_types": ["Full Time"], "selling_points": ["Answer enquiries & complaints from customers", "Conduct periodic telephone calls", "Clear career path with attractive salary (20k up)"], "locations": ["Hung Hom"], "categories": ["Sales, CS & Business Devpt", "Customer Service - Supervisor / Officer", "Marketing / Public Relations", "Management", "Sales - Sales Management"], "post_time": "2022-01-12T11:29:22Z", "salary": {"currency": "HKD", "max": 29999, "min": 20000, "period": "monthly", "term": null}, "salary_visible": true, "title_keywords": ["customer service officer"], "responsibilities": ["reporting", "management", "identify business opportunities", "administrative support", "teams", "presentations", "develop", "coordinate", "reports", "plan", "plans", "client proposals", "planning"], "requirements": {"degrees": ["university graduate"], "majors": [], "languages": ["english", "chinese", "mandarin"], "language_level": ["fluent"], "hard_skills": ["excel", "powerpoint", "ms office"], "soft_skills": ["organizational skills", "communication skills", "interpersonal", "hard-working", "organisation", "pro-active", "creative", "driven"], "languages_combined": [{"language": "english", "language_level": []}, {"language": "chinese", "language_level": ["fluent"]}, {"language": "mandarin", "language_level": []}]}, "experience_required": {"duration": ["minimum 5 years"], "field": ["relevant experience"]}}, {"job_id": "100003009049678", "location_code": "hk", "company": "Sun Life Hong Kong Limited", "job_title": "Management Trainee Program (Degree Holder in Any Disciplines)", "description": "Project Executive\n\nWe are recruiting the captioned personnel to provide administrative and operational support to our fundraising projects for different NGOs.\n\nDuties\n\nVenue Application & Coordination \u2013 prepare and submit application forms to respective parties including government departments and private sectors for getting permits; to coordinate the monthly, weekly and daily location planning and updating\nDonation Form Processing \u2013 including data entry, validation and welcome phone calls to donors\nProject Result Analysis \u2013 input result data into a project analysis file\nMarketing Collateral \u2013 inventory control of NGOs material and maintenance of good condition\n\u00a0Liaise with NGO clients - prepare weekly and monthly report, training coordination and production of marketing collateral\n\nRequirements\n\nPreferrably university graduated with 1 year of solid working experience, in particular in the sales, PR or marketing field; newly university graduated candidates are welcome;\nEnglish and Chinese word processing\nWell versant in EXCEL, Powerpoint, pivot table\nAble to maintaining strong communications with all levels of staff;\nTake initiative, high accuracy and organized;\nIndependent, able to manage multi-tasks and meeting tight deadlines\nCommitted to social services\nImmediate available\nCandidate with less relevant experience can be considered for Project Assistant\n\nBenefits\n\n5 days work, working hours: 10:00-18:00 (Include: 1 hour lunch time)\nPublic Holiday\nBirthday leave\nCompassionate leave\nMarriage Leave\nMedical & dental allowance\nOverseas field trips\nGood career prospect\n\nPlease send a cover letter in English or Chinese with your full resume stating your availability, present & expected salary to \u201cAPPLY NOW\u201d.\u00a0Candidates without a covering letter will not be shortlisted for interviews.\u00a0For enquiry please contact us at 2897 9338.\n\nOffice Address: Rm B912, 9/F, International Industrial Building, 501-503 Castle Peak Road, Kowloon.\n\n(Use MTR Lai Chi Kok station exit C)\n\n(Personal data collected from applicants are for recruitment purposes only)", "employment_types": ["Full Time"], "selling_points": ["5-Day Work Week", "Flexible Working Hours", "Degree Holder in Any Disciplines"], "locations": ["Hung Hom"], "categories": ["Accounting", "Finance / Accounting Manager", "Banking / Finance", "Financial Services", "Marketing / Public Relations", "Management"], "post_time": "2022-01-14T09:04:05Z", "salary": {"currency": "HKD", "max": 29999, "min": 17000, "period": "monthly", "term": null}, "salary_visible": true, "title_keywords": ["management trainee"], "responsibilities": ["maintenance", "data entry", "data", "analysis", "coordinate", "inventory control", "coordination", "monthly report", "liaise with", "phone calls", "planning"], "requirements": {"degrees": [], "majors": [], "languages": ["english", "chinese"], "language_level": [], "hard_skills": ["excel", "pivot table", "chinese word processing", "powerpoint"], "soft_skills": ["organized", "meeting tight deadlines", "independent", "multi-tasks", "committed", "initiative"], "languages_combined": [{"language": "english", "language_level": []}, {"language": "chinese", "language_level": []}]}, "experience_required": {"duration": ["1 year"], "field": ["pr", "marketing", "relevant experience"]}}, {"job_id": "100003009026001", "location_code": "hk", "company": "Aesop", "job_title": "Regional Visual Merchandising Assistant Manager, Asia", "description": "In this role, you will be managing and leading the Aesthetics sales team to achieve a sustainable growth of the portfolio for HK & Macau market in line with company vision and values. Also, work synergistically across business units, functional teams from global, regional and local on an integrated dermatology strategy.\n\nJob Responsibilities:\n\nManage and lead the sales team to achieve the company's assigned sales, coverage expansion and engagement targets.\nFormulate and execute sales plans and go-to-market strategies for assigned Aesthetic channel.\nCall management and sales performance management for the sales team.\nPrepare sales forecast, demand planning input and analysis as well as ensure smooth operation of the sales team.\nInitiate, plan and execute customers programs and promotions within company's assigned budget and guidelines.\nFrequent visits of customers including HCPs and Customers.\nSupport Healthcare Professional engagement events including detailing, training, communication and marketing campaigns to support the company's brand & product campaign.\nBuild strong collaboration with internal key stakeholders to ensure smooth daily business operation.\nAdhere to all company policies, procedures and business ethics codes and ensure that they are communicated and implemented with the team\nProvide industry & market intelligence and ability to create and execute strategic plans to win over competition\nCreate a positive team environment through the demonstration of strong leadership behaviors, including communicating expectations clearly, installing an atmosphere of trust and respect, and leading by example\nHelp to develop each sales team member to realize their full potential\n\nJob Requirements:\n\nUniversity Graduate with a proven track record of 8+ years of experience ideally in the Aesthetic or pharmaceutical industry.\nProficient in English and Cantonese conversation & writing\nAbility to effectively present information to management, public, doctors or sales forces in oral and written form.\nAbility to read, analyze and interpret common scientific and technical information\nIdeally, the candidate should be in a senior sales position with hands-on experience in an aesthetic/ pharmaceutical company with strong connections and know-how especially within the industry.", "employment_types": ["Full Time", "Permanent"], "selling_points": ["Supportive and entrepreneurial spirit", "Cultivate a professional environment", "Visual Merchandising Asia"], "locations": ["Not Specified"], "categories": ["Marketing / Public Relations", "Management", "Merchandising & Purchasing", "Procurement / Purchasing / Sourcing"], "post_time": "2022-01-12T23:00:00Z", "salary": {"currency": null, "max": null, "min": null, "period": "monthly", "term": null}, "salary_visible": false, "title_keywords": ["assistant manager,", "merchandising"], "responsibilities": ["demand planning", "budget", "communication", "plan", "sales performance", "prepare sales", "develop", "forecast", "marketing campaigns", "management", "procedures", "installing", "business operation", "strategic plans", "guidelines", "policies", "analysis", "sales team", "sales plans"], "requirements": {"degrees": ["university graduate"], "majors": [], "languages": ["cantonese", "english"], "language_level": ["proficient"], "hard_skills": [], "soft_skills": ["oral", "hands-on"], "languages_combined": [{"language": "cantonese", "language_level": ["proficient"]}, {"language": "english", "language_level": ["proficient"]}]}, "experience_required": {"duration": ["of 8+ years"], "field": ["pharmaceutical", "aesthetic", "pharmaceutical company"]}}, {"job_id": "100003009046457", "location_code": "hk", "company": "Sun Life Hong Kong Ltd", "job_title": "Management Trainee Program (Degree Holder in Any Disciplines)", "description": "My client, a local based property developer, has great present in HK and China property market.\n\nIn order to expand their Sales & Marketing team, they are currently looking for a PR talent to join their company.\n\nMain responsibilities:\n\nResidential project focus\nSupport team leader for all aspects of public relations activities & event management, assist in press materials draft, on-site support for PR activities, and maintain contacts with mass media\nWork closely with media and PR agency to ensure the smooth implementation of PR activities with good media coverage and handle reporting\nMaintain event, customer profiles & PR materials in order to garner marketing cooperation, media support and bring in events\nNaming of new properties\n\nMain requirements:\n\nBachelor's degree holder\n3-5 years working experience in PR function\nCareer background from property developer; residential project focus preferred\nCandidate from agency side, who serves property developer clients, is also welcome\nExcellent command of English and Chinese (Cantonese and Mandarin)\nKnowledge of basic graphic design and PR social media is a huge PLUS", "employment_types": ["Full Time"], "selling_points": ["5 day works", "$17,000-$30,000", "Competitive pay"], "locations": ["Hung Hom"], "categories": ["Banking / Finance", "Corporate Finance", "Management", "General Management", "Marketing / Public Relations", "Management"], "post_time": "2022-01-13T11:23:10Z", "salary": {"currency": "HKD", "max": 29999, "min": 17000, "period": "monthly", "term": null}, "salary_visible": true, "title_keywords": ["management trainee"], "responsibilities": ["reporting", "management", "maintain", "implementation"], "requirements": {"degrees": ["bachelor", "degree holder"], "majors": [], "languages": ["cantonese", "english", "chinese", "mandarin"], "language_level": ["excellent"], "hard_skills": ["focus", "basic", "plus"], "soft_skills": ["focus"], "languages_combined": [{"language": "cantonese", "language_level": ["excellent"]}, {"language": "english", "language_level": ["excellent"]}, {"language": "chinese", "language_level": ["excellent"]}, {"language": "mandarin", "language_level": ["excellent"]}]}, "experience_required": {"duration": ["3-5 years"], "field": ["pr"]}}, {"job_id": "100003009038743", "location_code": "hk", "company": "KPMG", "job_title": "Manager / Senior Manager, Markets (New Economy Sector)", "description": "The Egg is seeking a Marketing Communications Manager to hit the ground running and be responsible for the development and supervision of all marcom activities for the company. The individual will oversee the development of goals, strategies, and implementation plans to execute comprehensive marketing campaigns.\n\nThe MarCom Manager must be passionate about all things marketing, branding, and writing\u2014a multi-tasker who is self-motivated and can apply a strong communications skillset in a dynamic organization. Leadership experience in content creation (including video, blog, website, proposals, etc.), demand generation, email marketing, social media, and other marcom functions along with strong English writing and editing skills is a must.\n\nPrimary Responsibilities\n\n\nIdeate, strategize, and lead a full spectrum of marketing activities across many formats\u2014including videos, website content, case studies, blogs, social media posts, ads, webinars, BD materials, targeted email blasts, pitch stories, press releases, PR outreach, etc.\u2014to generate demand, leads, and loyalty\nCreate a cohesive image and message, ensuring consistency and proficiency in tone, style, and English language across all content while analyzing and implementing new ways to enhance the brand of The Egg\nDevelop, manage, and execute an annual strategic marcom plan to reach target audiences at various stages of the customer journey based on specific performance goals\nEvaluate the success of the marcom strategies, prepare various marketing reports to track performance, and provide and implement recommendations for improvement\nProvide strategic leadership to the marketing team, setting the yearly agenda and actively managing a small team to accomplish marketing goals\nWork with sales and other departments to produce marketing collateral in accordance with needs\nFacilitate internal communications, maintaining a strong culture across offices/teams and coordinating internal events on occasion (e.g., staff annual party)\nOther duties as required\n\nRequired Skills\n\n\nDegree holder in marketing, communications, public relations, journalism, or relevant field\n5+ years of work experience, including the handling of corporate communications, original writing and editing, and marketing management\nFull fluency in English is a must with exceptional written and verbal communication skills and impeccable attention to detail; Chinese-language skills are a plus\nExcellent understanding and familiarity with brand building and brand management alongside demonstrated proficiency in marcom techniques, technologies, and solutions\nHands-on experience with marcom tools, like WordPress, Google Analytics, MailChimp, Google Ads, CRM, etc.\nAbility to handle multiple ongoing tasks with excellent time-management skills, including prioritizing, scheduling, and adapting to changing market and organizational dynamics\nAbility to manage and coordinate not just end-to-end marcom strategies but the people, teams, and direct reports who also contribute to the success of these strategies\nStrong creative instincts to take complex concepts and bring them to life in an easy-to-understand style\nOutgoing and creative with a sociable character and positive attitude towards new challenges\nHungry to make a difference, flexible, and willing to take on new projects\nA well-defined sense of diplomacy and people-management skills\n\nIn your application, please include:\n\nR\u00e9sum\u00e9 and cover letter\nVisa status\nCurrent and expected salary\nMarcom portfolio\n\nBenefits for full-time position include:\n\nFive-day work week\nFlexi-time\nMedical insurance\nGym subsidy\nDiscretionary performance bonus\n\nWe offer an exciting career path and growth opportunities to those who are keen to further their career. The successful candidate will have a chance to lead projects and learn many practical techniques in the field.\n\nIf you are a great problem-solver, strategic thinker, and detail-oriented person with a can-do attitude, we want to hear from you!\n\nPlease note that only short-listed candidates will be notified. All information provided will be treated in strict confidence and used solely for recruitment purposes.", "employment_types": ["Permanent"], "selling_points": ["Market Development", "Develop and maintain business relationships", "Knowledge and insights in the China Market"], "locations": ["Aberdeen"], "categories": ["Marketing / Public Relations", "Management"], "post_time": "2022-01-11T07:42:44Z", "salary": {"currency": null, "max": null, "min": null, "period": "monthly", "term": null}, "salary_visible": false, "title_keywords": ["senior manager", "manager"], "responsibilities": ["social media", "maintaining", "other duties", "teams", "website", "develop", "evaluate", "reports", "plan"], "requirements": {"degrees": ["degree holder"], "majors": ["journalism", "marketing", "communications"], "languages": ["english", "chinese"], "language_level": ["fluency"], "hard_skills": ["google analytics", "plus", "make", "wordpress"], "soft_skills": ["outgoing", "communication skills", "flexible", "organizational", "sociable", "positive attitude", "hands-on", "attention to detail", "creative", "prioritizing"], "languages_combined": [{"language": "english", "language_level": ["fluency"]}, {"language": "chinese", "language_level": []}]}, "experience_required": {"duration": ["5+ years"], "field": ["editing", "marketing", "writing", "management"]}}, {"job_id": "100003009037297", "location_code": "hk", "company": "Rise Associates Asia Limited", "job_title": "Senior Marketing Officer (Developer - Residential)", "description": "In this role, you will be leading Aesthetic BU by implementing and executing the company's integrated dermatology strategy to deliver the growth of the business.\n\nJob Responsibilities:\n\nLead the Aesthetics Business Unit commercial operation to ensure the Company achieves its mission and objectives for the business\nResponsible for the budget and P&L delivery for the Aesthetics Business Unit.\nDevelop and successfully execute end-to-end successful marketing, channel, commercial and sales plans in accordance with corporate/ company strategy\nDevelop HCP training, communication and promotional campaigns\nDevelop and successfully execute end-to-end marketing, channel, commercial and sales plans including ATL/BTL brand building, product detailing and HCP/customer engagement.\nProduces and analyzes local market data, identifies, and tracks industry market trends\nWork with internal stakeholders to ensure smooth daily business operation.\nManages the relationships with the local advertising and communication agencies\nManages relationships with opinion leaders and dermatologist's community to support the company's brand & product.\nBuild strong collaboration with Regulatory Affairs, Pharmacovigilance, Medical Affair and Compliance team.\nAdhere to all company policies, procedures and business ethics codes and ensure that they are communicated and implemented with the team\nIdentifies and analyzes local customer needs and market opportunities\nProvide market intelligence and able to create and execute strategic plans to win over competition\nCreate a positive team environment through the demonstration of strong leadership behaviors, including communicating expectations clearly, installing an atmosphere of trust and respect, and leading by example.\nUse a mix of coaching and development tools to help each team member to realize their full potential\nProvide significant input and support to accomplish management team goals which will benefit Galderma Hong Kong in the long term.\n\nJob Requirements:\n\nUniversity Graduate with proven track record of 10+ years of experience ideally in the Aesthetic or Pharmaceutical industry.\nProficient English and Cantonese writing and conversation\nAbility to effectively present information to management, public, doctors or sales forces in oral and written form.\nAbility to read, analyze and interpret common scientific and technical information\nAbility to interpret an extensive variety of technical instructions in mathematical or diagram form and deal with several abstract and concrete variables.\nIdeally, the candidate should be in a managerial position in an Aesthetic /pharmaceutical company with strong connections and know-how within the industry.", "employment_types": ["Full Time", "Permanent"], "selling_points": ["Strong project pipeline", "Great platform to further develop", "Attractive salary package"], "locations": ["Not Specified"], "categories": ["Marketing / Public Relations", "Management", "Marketing - Brand / Product Management", "Property / Real Estate", "Property Consultancy"], "post_time": "2022-01-11T02:22:25Z", "salary": {"currency": null, "max": null, "min": null, "period": "monthly", "term": null}, "salary_visible": false, "title_keywords": ["developer", "senior marketing officer"], "responsibilities": ["business operation", "management team", "advertising", "strategic plans", "policies", "budget", "compliance", "procedures", "p&l", "develop", "communication", "installing", "sales plans", "market data"], "requirements": {"degrees": ["university graduate"], "majors": [], "languages": ["cantonese", "english"], "language_level": ["proficient"], "hard_skills": [], "soft_skills": ["oral", "extensive"], "languages_combined": [{"language": "cantonese", "language_level": ["proficient"]}, {"language": "english", "language_level": ["proficient"]}]}, "experience_required": {"duration": ["of 10+ years"], "field": ["pharmaceutical", "aesthetic"]}}, {"job_id": "100003009038088", "location_code": "hk", "company": "Kindness Support Limited", "job_title": "Project Executive(5 days work)", "description": "Our client is a well-regarded Health and Wellness Brand. They are currently expanding their business and seeking for a Marketing Director to join their dynamic marketing team.\n\nClient Details\n\nOur client is a well-regarded Health and Wellness Brand. They are currently expanding their business and seeking for a Marketing Director to join their dynamic marketing team.\n\nDescription\n\nOur client is a well-regarded health and wellness brand. They are currently expanding their business and seeking for a Marketing Director to join their dynamic marketing team. The position is the team leader to develop strategic marketing framework and execution plans including digital, event management, data analysis and product training.\n\nProfile\n\nThe successful candidate would be an experienced marketing manager for multinational company. Candidate with FMCG, Health and Beauty or pharmaceutical portfolio will be considered first. Our client is looking for a creative and brand thinking person with outstanding leadership skill to join them as a team leader. Public speaking and presentation ability are highly valued to this role. Fluency in English and Cantonese is required. Degree level qualification in marketing, business studies, or other related subjects is preferred.\n\nJob Offer\n\nWork for a global company that provides you with opportunity to expand your career. You will be provided with an attractive salary package and compensation.\n\nTo apply online please click the 'Apply' button below. For a confidential discussion about this role please contact Smania Wu on +852 3412 4858.", "employment_types": ["Full Time", "Permanent"], "selling_points": [], "locations": ["Lai Chi Kok"], "categories": ["Admin & HR", "Others", "Marketing / Public Relations", "Management", "Public / Civil", "Social Services - Community / Non-profit Organization"], "post_time": "2022-01-11T04:56:48Z", "salary": {"currency": null, "max": null, "min": null, "period": "monthly", "term": null}, "salary_visible": false, "title_keywords": [], "responsibilities": ["management", "develop", "data analysis", "contact", "plans"], "requirements": {"degrees": ["degree"], "majors": ["business", "marketing"], "languages": ["cantonese", "english"], "language_level": ["fluency"], "hard_skills": ["analysis", "dynamic"], "soft_skills": ["presentation", "leadership skill", "dynamic", "creative"], "languages_combined": [{"language": "cantonese", "language_level": ["fluency"]}, {"language": "english", "language_level": ["fluency"]}]}, "experience_required": {"duration": [], "field": []}}, {"job_id": "100003009037677", "location_code": "hk", "company": "Tsit Wing Coffee Co Ltd", "job_title": "Assistant Product Marketing Manager (Frozen & Chilled food )", "description": "An international asset manager is looking for a seasoned digital content marketing manager to join their HK marketing team. Sits in a small team, the individual will be responsible for executing marketing campaign with a focus on digital content, targeting retail and pension clients.\n\nRequirements:\n\n10+ years of experience in digital marketing, preferably with financial services companies\nStrong experience managing digital campaigns\nExperience in developing client engaging content for distribution through various channels\nExperience in CRM systems\nStrong communication skill in English and Chinese (Written and Verbal) is a must", "employment_types": ["Full Time"], "selling_points": [], "locations": ["Not Specified"], "categories": ["Marketing / Public Relations", "Management", "Marketing - Brand / Product Management", "Marketing - General / Support"], "post_time": "2022-01-11T03:30:40Z", "salary": {"currency": null, "max": null, "min": null, "period": "monthly", "term": null}, "salary_visible": false, "title_keywords": ["product marketing manager", "assistant"], "responsibilities": ["systems", "developing", "communication", "executing", "digital marketing", "digital campaigns"], "requirements": {"degrees": [], "majors": [], "languages": ["english", "chinese"], "language_level": [], "hard_skills": ["small", "focus"], "soft_skills": ["focus", "communication skill", "responsible"], "languages_combined": [{"language": "english", "language_level": []}, {"language": "chinese", "language_level": []}]}, "experience_required": {"duration": ["10+ years"], "field": ["digital", "financial services", "digital marketing", "developing"]}}, {"job_id": "100003009042406", "location_code": "hk", "company": "Walters People (HK)", "job_title": "(Senior) PR Officer (Real estate - Residential; Up to 26k)", "description": "Responsibilities:\n\nTo develop and implement a marketing plan to achieve the business objectives.\u00a0\nTo plan and control the annual marketing budget.\nTo drive brand growth through different marketing programs by management, maintenance and execution.\nTo maintain effective communications with overseas business partners to implement local advertising and promotion activities.\nTo create and prepare a wide range of the marketing collaterals and work closely with design team and production agencies.\nTo develop the eCommerce and digital marketing strategies.\nTo liaise with PR and media agency.\nTo organize the overseas and local trade show.\nOccasional travelling will be required.\n\nRequirements:\n\nUniversity graduate preferably in marketing, business or related disciplines\nMinimum 5 years of marketing experience with at least 1 year at supervisory or managerial level, preferably with exposure in fashion brands or FMCG industry.\nExtensive network in PR & marketing support, sound skills in both traditional marketing and e-marketing strategies and tactics\nEffective interpersonal and communication skills and a good team player\nCreative, self-motivated with high degree of ownership and able to work under high pressure\nHands-on marketing campaign skills and experience\nGood command of written and spoken English, Chinese and Mandarin\nGood presentation and computer skills\n\nWe offer attractive remuneration and excellent career prospects to the right candidates. Interested and qualified parties please send\u00a0full resume including current salary, expected salary and availability\u00a0to The Group Human Resources Department via\u00a0JobsDB:\"Apply Now\".\n\nThe information provided will be kept confidential and used for recruitment purposes only. Applicants not contacted within three months may consider their applications unsuccessful. The company will retain all applications for a maximum of six months.", "employment_types": ["Full Time", "Permanent"], "selling_points": ["Residential Project", "PR event, Press release", "Min 3 yrs exp. up to 26k + double pay"], "locations": ["Not Specified"], "categories": ["Marketing / Public Relations", "Management", "Marketing - Brand / Product Management", "Marketing - Marketing Communication"], "post_time": "2022-01-12T07:20:40Z", "salary": {"currency": "HKD", "max": 24999, "min": 20000, "period": "monthly", "term": null}, "salary_visible": true, "title_keywords": ["officer"], "responsibilities": ["control", "management", "communications with", "advertising", "maintenance", "digital marketing strategies", "budget", "marketing collaterals", "design", "develop", "marketing plan", "maintain", "plan", "liaise with"], "requirements": {"degrees": ["university graduate", "degree"], "majors": ["business", "related disciplines", "marketing"], "languages": ["english", "chinese", "mandarin"], "language_level": ["good command"], "hard_skills": ["fmcg industry", "computer skills"], "soft_skills": ["communication skills", "good team player", "self-motivated", "presentation", "hands-on", "work under high pressure", "creative", "extensive", "interpersonal"], "languages_combined": [{"language": "english", "language_level": ["good command"]}, {"language": "chinese", "language_level": ["good command"]}, {"language": "mandarin", "language_level": ["good command"]}]}, "experience_required": {"duration": ["at least 1 year", "minimum 5 years"], "field": ["managerial", "supervisory", "marketing", "fmcg"]}}, {"job_id": "100003009036533", "location_code": "hk", "company": "The Egg Company Limited", "job_title": "Marketing Communications Manager", "description": "Assist in developing, planning and implementing Online and Offline marketing strategies, campaigns and promotional activities for the company group\nSupport marketing campaigns in different aspects including advertising, digital marketing, events, partnership and public relations\nDemonstrates creativity and hands-on experience with a strategic mindset to ensure marketing goals and business needs are met\nConsolidation of reports, monitor expenses as per budget assigned\nOther ad hoc tasks to support the team;\n\n\nRequirements\nTertiary education in\u00a0Marketing, Business Administration or related disciplines\nMinimum 3 years working experience in Marketing / Events / Advertising / Public Relations Management\nSuperior problem-solving, organizational, communication and interpersonal skills\u00a0\nFlexible attitudes and willing to accept challenges, attention to details\nIndependent, able to work under pressure and meet tight deadline\nExcellent command of spoken and written English & Chinese\nGood analytical skills and able to conduct desktop research\nExperience with Adobe / Google Ads/Analytics, Facebook Ad Manager or equivalent tools is preferred\nProficient in MS Applications and Chinese word processing\n\nAbout GigGik\n\nFounded in 2020, GigGik Technology Limited is a start-up recruitment platform under HU YI Global group.\nWe dedicate to provide an effective and reliable recruitment channels to both candidates and recruiters. A new recruitment platform \"GigGik\" is developed by our company, clients can use the brand-new gTLD 'www.brand name.\u62db\u8058' (https://www.giggik.com/tc/companies) to ensure that there will be a trusted resource and employer branding between companies and candidates.\nSecondly, we aim to solve the recruitment problems that the most HR faces. Through the 1-stop recruitment process online with the platform, companies can reduce the human resources cost and speech up the talent match.\n\nWorking Location :\n\nKowloon Bay\n\nWe offer attractive remuneration and career opportunities to the right candidate. Interested parties please send detailed\u00a0CV\u00a0and\u00a0PORTFOLIO (if you have)\u00a0with\u00a0expected and present SALARY\u00a0to our HR department.\nThere will be a\u00a0job test\u00a0before interview.\n\nPersonal data collected will be used for recruitment purpose only.\n\nWelcome to browse our website:\u00a0https://www.giggik.com/", "employment_types": ["Full Time", "Permanent"], "selling_points": ["5+ yr in marcom management & full English fluency", "Work with an international team across Asia", "Exciting career path and growth opportunities"], "locations": ["Causeway Bay"], "categories": ["Marketing / Public Relations", "Management", "Marketing - Marketing Communication", "Digital Marketing"], "post_time": "2022-01-10T10:54:54Z", "salary": {"currency": null, "max": null, "min": null, "period": "monthly", "term": null}, "salary_visible": false, "title_keywords": ["manager"], "responsibilities": ["budget", "communication", "facebook", "administration", "work under pressure", "advertising", "expenses", "monitor", "developing", "reports", "marketing campaigns", "management", "cost", "marketing strategies", "ad hoc tasks", "promotional activities", "digital marketing", "recruitment process", "support the team", "hr", "recruitment", "planning"], "requirements": {"degrees": [], "majors": [], "languages": ["english", "chinese"], "language_level": ["excellent", "proficient"], "hard_skills": ["ms applications", "chinese word processing", "problem-solving", "analytical skills", "adobe", "facebook"], "soft_skills": ["flexible", "independent", "work under pressure", "organizational", "problem-solving", "analytical skills", "hands-on", "communication and interpersonal skills", "attention to details", "meet tight deadline", "reliable", "superior"], "languages_combined": [{"language": "english", "language_level": ["excellent"]}, {"language": "chinese", "language_level": ["excellent", "proficient"]}]}, "experience_required": {"duration": ["minimum 3 years"], "field": ["management", "public relations", "advertising", "business", "marketing"]}}, {"job_id": "100003009037765", "location_code": "hk", "company": "San Miguel Brewery Hong Kong Limited", "job_title": "Brand Executive (FMCG)", "description": "Responsibilities:\nDevelop and implement Brand & Public Relations Strategy for commercial vehicle products;\nOversee the implementation of Marketing strategy \u2013 including campaigns, events, digital marketing, and PR;\nDevelop and deliver marketing and communications strategies for the organization;\nManage and develop media network and related external vendors for product/customer events.\n\u00a0Assist formulation of digital marketing strategy and plans through research, insights discovery from social media, and market understanding.\u00a0\nMonitor and maintenance\u00a0of brand\u2019s websites, brand\u2019s e-Commerce websites & brand\u2019s social media platforms in the region, such as Facebook, Twitter, Line,\u00a0Instagram, Weibo, WeChat, Tmalletc, and to manage/drive strategy of social media content calendar and implement social media activities such as paid social & social influencer activation\u2026etc.\nDrive e-commerce marketing & content deliverables to further support market to increase online business\nRequirements:\u00a0\nUniversity graduate\u00a0in\u00a0Digital Marketing, eMarketing or Strategic Marketing, Statistics or relevant discipline;\nMinimum 2\u00a0years\u2019 solid work experience in Marketing, preference will be given to those who are from high end luxury.\nProficiency in a wide range of social media apps, web analytical tools, and MS Office applications;\nExcellent track record in branding and product marketing for online and offline media\nFluent in spoken English, Cantonese and Mandarin\nInterested candidates please send your resume in MS Word by clicking \"Apply Now\"", "employment_types": ["Full Time", "Permanent"], "selling_points": ["To strengthen the exposure of assigned brand", "Work with different vendors", "Proactive, good team player"], "locations": ["Shatin Area"], "categories": ["Marketing / Public Relations", "Management", "Marketing - Brand / Product Management", "Sales, CS & Business Devpt", "Channel / Distribution"], "post_time": "2022-01-11T03:46:07Z", "salary": {"currency": null, "max": null, "min": null, "period": "monthly", "term": null}, "salary_visible": false, "title_keywords": ["executive"], "responsibilities": ["social media", "maintenance", "social media platforms", "monitor", "implementation", "develop", "digital marketing", "social media content", "plans", "facebook"], "requirements": {"degrees": ["university graduate"], "majors": ["statistics", "marketing", "digital marketing"], "languages": ["cantonese", "english", "mandarin"], "language_level": ["fluent"], "hard_skills": ["web", "ms office"], "soft_skills": [], "languages_combined": [{"language": "cantonese", "language_level": ["fluent"]}, {"language": "english", "language_level": ["fluent"]}, {"language": "mandarin", "language_level": ["fluent"]}]}, "experience_required": {"duration": ["minimum 2 years"], "field": ["marketing"]}}, {"job_id": "100003009036965", "location_code": "hk", "company": "Queenix (Asia) Limited", "job_title": "Marketing & PR Manager", "description": "Our client is a Hong Kong based start-up tech company focusing on developing communication software\u00a0that centralizes instant messaging channels like WhatsApp, WeChat, Instagram, Line, and Facebook Messenger into one inbox. With their rapid growth they are now looking for a Digital Marketing Manager to join their dynamic team.\u00a0\n\nResponsibilities:\n\nDevelop positioning and messaging (define and amplify our who, what, why, how)\nDevelop product marketing strategies and create marketing materials that communicate product values\nDevelop the marketing tools and campaigns to attract new prospects and customers\nCultivate user community\nCreate Integrated communications and campaigns (Email marketing, etc.)\nCollaborate with design, product, growth, and sales teams to build outbound strategies and implement them\u00a0\nCase advocacy program (case studies, testimonials, campaigns, reviews)\nRequirements:\n\nStrong experience in B2B marketing with at least 3 years of accountable, hands-on experience (previously in B2B SaaS - advantage)\nProven outstanding abilities to translate customer needs and market demand into sharp and compelling messaging, content, sales tools, and campaigns to help us meet our business goals\nProven track record of successfully launching and managing cost-effective marketing campaigns with clear ROI focused metrics\u00a0\nStrong communication and collaboration skills, both verbal and written\nHighly motivated, passionate, self-starter with a can-do attitude\u00a0", "employment_types": ["Full Time", "Permanent"], "selling_points": ["Develop and implement Brand & Public Relations", "Minimum 2 years\u2019 solid work experience", "University graduate in Digital Marketing"], "locations": ["Not Specified"], "categories": ["Marketing / Public Relations", "Management", "Marketing - Brand / Product Management", "Digital Marketing"], "post_time": "2022-01-11T16:01:39Z", "salary": {"currency": null, "max": null, "min": null, "period": "monthly", "term": null}, "salary_visible": false, "title_keywords": ["manager"], "responsibilities": ["collaborate with", "marketing strategies", "teams", "design", "develop", "marketing materials"], "requirements": {"degrees": [], "majors": [], "languages": [], "language_level": [], "hard_skills": [], "soft_skills": ["passionate", "focused", "can-do attitude", "accountable", "clear", "communication", "hands-on", "motivated"], "languages_combined": []}, "experience_required": {"duration": ["at least 3 years"], "field": ["marketing"]}}, {"job_id": "100003009042424", "location_code": "hk", "company": "Betterment Asia Limited", "job_title": "Digital Marketing Manager - Start-up Tech B2B SaaS", "description": "\u8981\u6c42\n\n\u6301\u6709\u5927\u5b78\u6216\u4ee5\u4e0a\u5b78\u6b77\uff0c\u6b61\u8fce\u61c9\u5c46\u9999\u6e2f\u7562\u696d\u751f\u6216\u7b26\u5408\u7559\u6e2f/\u56de\u6e2f\u5c31\u696d\u5b89\u6392\u7684\u975e\u672c\u5730\u7562\u696d\u751f(IANG)\n\u6301\u6709\u9999\u6e2f\u6c38\u4e45\u5c45\u6c11\u8eab\u4efd\u8b49\n\u597d\u5b78\u3001\u7a4d\u6975\u9032\u53d6\u3001\u5c0d\u5de5\u4f5c\u6709\u71b1\u8aa0\u53ca\u4e3b\u52d5\n\u6e34\u671b\u62d3\u5c55\u500b\u4eba\u4e8b\u696d\n\u5177\u9280\u884c\u53ca\u91d1\u878d\u670d\u52d9\u696d\u7d93\u9a57\u8005\u66f4\u4f73\n\n\u5b8c\u6210\u8a08\u5283\u5f8c, \u5408\u8cc7\u683c\u4eba\u58eb\u5c07\u6703\u7372\u5f97\u4ee5\u4e0b\u652f\u63f4:\n\n\u53ef\u8c41\u514dIIQ\u5377\u4e00\u548c\u5377\u4e09\u8003\u8a66\u8cbb\u7528\n\u6301\u7e8c\u5c08\u696d\u53ca\u5168\u9762\u7684\u8ca1\u52d9\u7b56\u5283\u57f9\u8a13\u8ab2\u7a0b\uff0c\u5168\u65b9\u4f4d\u63d0\u5347\u500b\u4eba\u6210\u9577\n\u5c08\u696d\u4eba\u58eb\u5feb\u901f\u8d77\u6b65\u6307\u5c0e\uff0c\u5718\u968a\u57f9\u8a13\u8a08\u5283\n\u53ef\u89c0\u6536\u5165\u53ca\u900f\u660e\u4e8b\u696d\u767c\u5c55\n\n\n\u6709\u610f\u8005\u8acb\u65bc1\u670831\u65e5\u6216\u4e4b\u524d\u7533\u8acb\uff0c\u984d\u6eff\u5373\u6b62", "employment_types": ["Full Time", "Permanent"], "selling_points": ["Start-up culture, friendly working environment", "Young and energetic team", "Attractive salary package, WFH policy"], "locations": ["Not Specified"], "categories": ["Marketing / Public Relations", "Management", "Marketing - Brand / Product Management", "Digital Marketing"], "post_time": "2022-01-12T07:25:45Z", "salary": {"currency": null, "max": null, "min": null, "period": "monthly", "term": null}, "salary_visible": false, "title_keywords": ["digital marketing manager"], "responsibilities": [], "requirements": {"degrees": [], "majors": [], "languages": [], "language_level": [], "hard_skills": [], "soft_skills": [], "languages_combined": []}, "experience_required": {"duration": [], "field": []}}, {"job_id": "100003009037473", "location_code": "hk", "company": "DFS Hong Kong Limited", "job_title": "Senior Manager, Global Store Operational Excellence - DFS91121244", "description": "Responsibilities:\nResponsible for reviewing of the MPF investment funds, designing of advertising campaigns, marketing plan and promotion programs including marketing materials for MPF / ORSO\nOrganize and implement the promotion campaigns and sales management programs\nDevise digital marketing campaigns\nAssist in the preparation of reports and digital service development\nAssist in monitoring of the compliance of sales in MPF regulated activities\nProvide clerical support to marketing teams\nPerform ad-hoc assignments as required\nRequirements:\nDegree holder or above in Marketing, Business, Statistics or related disciplines\nMinimum 2 years\u2019 relevant experience in marketing role of retirement industry\nStrong communication, negotiation skill and high risk awareness\nProficient in MS office application\nProficient in both spoken and written English and Chinese, Putonghua a plus\nImmediately available is highly preferred\nCandidates with less experience will be considered as Officer", "employment_types": ["Full Time", "Permanent"], "selling_points": ["World's Leading Luxury Travel Retailer", "Work Life Balance, Five-day Work Week", "International & Dynamic Working Environment"], "locations": ["Quarry Bay"], "categories": ["Sales, CS & Business Devpt", "Customer Service - Manager", "Marketing / Public Relations", "Management", "Retail Sales"], "post_time": "2022-01-11T02:55:06Z", "salary": {"currency": null, "max": null, "min": null, "period": "monthly", "term": null}, "salary_visible": false, "title_keywords": ["senior manager"], "responsibilities": ["provide clerical support", "devise digital marketing", "mpf", "ad-hoc assignments", "monitoring", "compliance", "teams", "marketing plan", "promotion campaigns", "reports", "designing", "marketing materials", "sales management", "advertising campaigns"], "requirements": {"degrees": ["degree holder"], "majors": ["business", "related disciplines", "marketing", "statistics"], "languages": ["putonghua", "english", "chinese"], "language_level": ["proficient"], "hard_skills": ["plus", "ms office"], "soft_skills": ["communication", "negotiation skill"], "languages_combined": [{"language": "putonghua", "language_level": ["proficient"]}, {"language": "english", "language_level": ["proficient"]}, {"language": "chinese", "language_level": ["proficient"]}]}, "experience_required": {"duration": ["minimum 2 years"], "field": ["marketing", "relevant experience"]}}, {"job_id": "100003009042256", "location_code": "hk", "company": "Prudential Hong Kong Limited", "job_title": "Financial Trainee \u2013 Business Internship Programme (\u5927\u5b78\u751f\u5be6\u7fd2\u8a08\u5283)", "description": "Overview\n\nThis is a regional marketing role of one of the five Specialties of the MedSurg Division. Reporting to the Global Marketing Manager of the Speciality, the APAC Marketing Manager will manage strategic marketing needs in the region, and at the same time be hands-on to maintain daily operation of marketing. The APAC manager will be the voice of global marketing team to regional field teams, and the voice of APAC to global leadership team of the Specialty.\n\nJob Duties:\n\n\nProactively collaborate with the regional urology team (Product, Training, Sales), acquire customer feedback, together with market intelligence and data to discover marketing opportunities and establish strategic marketing plans with alignment to global sales and marketing direction.\nResearch on market trends, competitors news and movements, and changes in offerings for regular market outlook updates.\nEstablish and optimizes go-to market strategies for the specialty through various marketing channels, with an emphasis on digital marketing strategies and utilization of CRM data.\nCollaborate with product management and field teams to develop marketing content \u2013 regional and local.\nLead internal support teams to implement product launches, conferences, digital marketing programs, education events, symposia and other marketing initiatives; create and maintain marketing materials and sales tools.\nWork closely with agency teams to initiate, manage, and keep track on tactical components of marketing plans.\nCollaborate with Specialty stakeholders to ensure projects meet goals, expectations, approval requirements, and deadlines, while upholding and advancing the brand equity of Cook.\nAnalyze marketing campaign performance to identify improvement opportunities.\nCollaborates with marketing managers in other regions and Specialties\u00a0based on project and Division needs, sharing intelligence, resources and best practice to achieve strategic marketing goals of the Division globally.\nCommunicate and help field-based teams understand marketing initiatives in regional business plans; work to create consistency for sales teams across initiatives. Create feedback loop from the field to inform work of marketing and communications teams.\nIdentify opportunities to improve communication with sales teams and customers.\nRequirements:\n\nDegree or above in Marketing, Business Administration, Business Management, Communications or related discipline.\nMinimum 6-8 years of relevant working experience.\nSolid experience in developing project plans and managing marketing channels.\nSolid experience in medical device industry is an advantage.\nHave marketing, advertising, PR, digital solution agency experience is preferable.\nFluent in English, both written and spoken.\nProficiency in at least one major Asian language such as Mandarin, Japanese, Korean etc. is an advantage.\nProficiency in Microsoft Office Professional, Adobe Creative Suite computer programmes.\nExcellent communication, interpersonal, project management, organization, presentation, and problem solving skills.\nStrategic and critical thinker.\nIndependent and self-motived.\nStrong team player.\n\u00a0Positive, can-do attitude, eager to strive for excellence.\nAble to meet deadlines and prioritize work.\nFlexibility to communicate with colleagues in a different time zones, occasionally out of ordinary office hours.\nRegional travel may be required.\nWe offer attractive package to the right candidate. Interested parties please click \"Apply\" to submit your application. You are also welcome to visit our website for more information: www.cookmedical.com", "employment_types": ["Full Time", "Part Time", "Permanent", "Temporary", "Contract", "Internship", "Freelance"], "selling_points": ["\u5c0d\u8c61: 2022\u5e74\u5927\u5b78\u7562\u696d\u751f\uff1b\u7533\u8acb\u65e5\u671f: 1\u670831 \u65e5\u6216\u4e4b\u524d, \u984d\u6eff\u5373\u6b62; \u4e00\u81f3\u4e8c\u6708\u4efd\u958b\u59cb", "\u5b89\u6392\u8077\u524d\u57f9\u8a13, \u5c08\u696d\u5c0e\u5e2b\u7531\u6e9d\u901a\u5354\u8abf\u5230\u6210\u529f\u4e4b\u9053, \u6bcf\u9805\u6df1\u5165\u6dfa\u51fa", "\u53ef\u89c0\u6536\u5165\u53ca\u524d\u666f\u767c\u5c55"], "locations": ["Kwai Fong"], "categories": ["Admin & HR", "Administration / Operation Manager", "Marketing / Public Relations", "Management", "Management", "Management Trainee"], "post_time": "2022-01-12T06:45:26Z", "salary": {"currency": null, "max": null, "min": null, "period": "monthly", "term": null}, "salary_visible": false, "title_keywords": ["business internship", "trainee"], "responsibilities": ["collaborate with", "management", "digital marketing strategies", "digital marketing programs", "data", "marketing plans", "teams", "business plans", "develop", "communication", "conferences", "maintain", "marketing materials"], "requirements": {"degrees": ["degree or above"], "majors": ["business", "marketing", "business administration", "communications"], "languages": ["japanese", "english", "mandarin", "korean"], "language_level": ["proficiency", "fluent"], "hard_skills": ["business management", "microsoft office", "project management", "problem solving skills", "adobe creative suite"], "soft_skills": ["independent", "interpersonal", "can-do attitude", "prioritize", "communication", "project management", "strive for excellence", "team player", "problem solving skills", "creative", "meet deadlines", "presentation", "positive"], "languages_combined": [{"language": "japanese", "language_level": ["proficiency"]}, {"language": "english", "language_level": ["fluent"]}, {"language": "mandarin", "language_level": ["proficiency"]}, {"language": "korean", "language_level": ["proficiency"]}]}, "experience_required": {"duration": ["minimum 6-8 years"], "field": ["pr", "advertising", "agency", "relevant working experience", "developing", "medical device", "marketing", "digital"]}}, {"job_id": "100003009039555", "location_code": "hk", "company": "Bank of Communications Trustee Limited", "job_title": "Contract Senior Marketing Management Officer", "description": "Company Description\n\nOur client, a well-regarded asset & wealth management group, is seeking a VP, Marketing Strategy & Planning. Reporting to the regional marketing head, the successful candidate will be responsible for managing the marketing process from research / analysis to planning & execution for various marketing initiatives (including digital).\n\nResponsibilities\n\nAct as the go-to person for all regional marketing programs (online and offline) to ensure consistency on brand and product messages across Asia (ex-Japan)\nManage conception, development and implementation of marketing plans / strategies to achieve KPIs for brand presence, campaign efficiency evaluations, , digital performance, etc\nCollaborate with local business teams to ensure regional effort is fulfilling individual market needs\nWork closely with regional data analytics team to uncover insights and to integrate such findings in marketing programs\nConstantly analyze campaign data and make data informed decisions for in-flight optimization and improving outcome\nWork alongside with global digital / marketing technology teams to contribute to the company\u2019s marketing & communications standards\nDrive sharing of best practices with local marketing teams\nManage agency providers on various regional projects and liaise closely with in-house design team\n\nRequirements\n\nUniversity graduate with degree in BBA / Marketing / related discipline\nAt least 10 years of marketing planning & execution experience from agencies or financial sector\nA proven track record in managing complex (regional) marketing projects from end to end in a multi-national firm is important\nKnowledge of wealth management /investment funds products is a bonus\nStrong project management skills, including KPI tracking, and attention to detail\nA strong team player with proven experience in managing stakeholders across the region\nExcellent communication skills in English and Chinese, and be able to pitch strategic marketing ideas using data\nInterested parties please send your updated resume in WORD format with current and expected salaries (quoting Employer Ref:)", "employment_types": ["Full Time", "Contract"], "selling_points": ["Provide clerical support to marketing teams", "Perform ad-hoc assignments as required", "Degree holder or above in Marketing, Business"], "locations": ["Not Specified"], "categories": ["Sales, CS & Business Devpt", "Business Development", "Marketing / Public Relations", "Management", "Others"], "post_time": "2022-01-11T10:04:01Z", "salary": {"currency": null, "max": null, "min": null, "period": "monthly", "term": null}, "salary_visible": false, "title_keywords": ["officer"], "responsibilities": ["collaborate with", "liaise", "data", "marketing plans", "teams", "implementation", "design", "kpis"], "requirements": {"degrees": ["university graduate", "degree"], "majors": ["bba", "marketing"], "languages": ["english", "chinese"], "language_level": ["excellent"], "hard_skills": ["project management"], "soft_skills": ["communication skills", "project management skills", "team player", "attention to detail"], "languages_combined": [{"language": "english", "language_level": ["excellent"]}, {"language": "chinese", "language_level": ["excellent"]}]}, "experience_required": {"duration": ["at least 10 years"], "field": ["team", "marketing", "financial", "planning"]}}, {"job_id": "100003009033827", "location_code": "hk", "company": "Konica Minolta Business Solutions (HK) Limited", "job_title": "Assistant Operations Support Manager", "description": "Responsibilities\n\n\nDevelop strategic marketing plans and product promotion campaigns to enhance brand awareness and drive business growth\nCreate and manage the marketing budget\nAchieve business targets set by the direct supervisor\nCreate a targeted and cost-effective multi-channel marketing strategy for generating high quality leads\nManage campaign tracking and improvement, measuring and optimizing the messaging, budget spend, and channel mix.\nBuild brand awareness; plan and implement marketing plans by using different tactics; evaluate the effectiveness of marketing strategies/activities\nOversee digital media marketing strategies, social media and content marketing\nDevelop innovative digital media marketing strategies including search engine optimisation, video and social media, and email marketing campaigns.\nMonitor education industry trends, competitor activities, demographics, pricing schedule\nPrepare online or printed marketing materials for distribution via multi-channels\nDevelop social media content and manage social media platforms for targeted parents\nMonitor and optimize company brand presence across traditional media, social media, and influencers\nManage the website ensuring content are up-to-date by coordinating with in-house and out-sourced IT vendors\nMaintain effective communications with internal and external parties to ensure marketing objectives are aligned\nImplement marketing plans, projects and tasks assigned by the Management\u00a0\n\nRequirement\n\n\nDegree or above in marketing, business or related field\n\nMin. 5-8 years\u2019 working experience in marketing, preferably in Education sector\nExcellent command of written / spoken English and Chinese\nProven understanding of marketing best practices with a track record for developing growth marketing strategies that deliver tangible business results\nStrong business acumen and up to date with the latest trends in marketing technologies\nFamiliarity with traditional and emerging marketing channels\nStrong people skills and team-oriented approach\nProactive, positive, flexible, creative and open-minded\nGood understanding of the Hong Kong education system\nWilling to meet challenges and adaptative to change\n\nWe offer competitive salaries and benefits commensurate with experiences and qualifications.\n\nInterested party please apply with your full resume and expected salary.\n\nAll information received will be kept in strict confidential and only for employment-related purposes within our Bluetop Group of Companies. You may consider your application unsuccessful if you do not hear from us within 12 weeks.", "employment_types": ["Full Time", "Permanent"], "selling_points": ["Evaluate the efficiency of manpower", "5 days work", "experience in B2B market is preferable"], "locations": ["Not Specified"], "categories": ["Management", "General Management", "Marketing / Public Relations", "Management", "Marketing - Brand / Product Management"], "post_time": "2022-01-10T01:52:00Z", "salary": {"currency": null, "max": null, "min": null, "period": "monthly", "term": null}, "salary_visible": false, "title_keywords": ["operations", "manager", "assistant"], "responsibilities": ["marketing plans", "budget", "quality", "social media platforms", "website", "internal and external parties", "promotion campaigns", "social media content", "maintain", "plan", "communications with", "monitor", "develop", "schedule", "marketing campaigns", "social media", "cost", "management", "marketing strategies", "tracking", "evaluate", "marketing materials"], "requirements": {"degrees": ["degree or above"], "majors": ["business", "marketing"], "languages": ["english", "chinese"], "language_level": ["excellent"], "hard_skills": ["acumen"], "soft_skills": ["flexible", "creative", "open-minded", "business acumen", "proactive", "positive"], "languages_combined": [{"language": "english", "language_level": ["excellent"]}, {"language": "chinese", "language_level": ["excellent"]}]}, "experience_required": {"duration": ["5-8 years"], "field": ["marketing", "education"]}}, {"job_id": "100003009038025", "location_code": "hk", "company": "Global Link Retail Management Limited", "job_title": "Marketing Manager", "description": "As the leader of the Chinese content writers team, you will need to work closely with other marketing teams to discuss about the content strategy and direction planning. You will need to ensure the quality of the content produced and matches with the brand's identity as well as the corporate image.\n\nWhat are your responsibilities?\n\nMaintaining and enhancing the quality of Mandarin content. Namely editing content produced by the CN team, including conceptualizing the projects upfront, assigning tasks and overseeing development and copy-editing prior to publishing.\u00a0\nContribute to producing high-quality articles, white papers, blogs, press releases, email marketing messages, SEO writing, and web copy\nPush the business to adopt better content creation practices through frequent testing of new content formats and distribution channels, including championing the increased use of data visualization\nManage and assign tasks to CN Content team members\nWork closely with English Content team and Brand Operation team for optimum team results\n\nWho are we looking for?\n\nEducation: Bachelor Degree and above\nAt least 3 to 5 years of content writing experience\nAble to communicate, read and write in Mandarin and English\nPrior team management experience\nExperienced in Finance or Tech industry will be an added advantage\nAble to adapt into fast-paced working environment, able to work under stress\n\nThe Doo Expectations\n\nYou don't need to know everything about our industry, because even we don't! This is an ever-changing industry that is expeditious and technology-filled - and we are learning new things every day. In this fast-paced environment, expect a lot of new challenges and changes along the way.\n\nIn a nutshell, we are looking for talent who is ready to grow and succeed together with Doo!\n\n#DooBeyondLimit #TogetherWeDooMore #SucceedYourCareerWithDoo", "employment_types": ["Full Time", "Permanent"], "selling_points": ["F&B marketing", "Good market sense", "Solid work experience in marketing and supervision"], "locations": ["Lai Chi Kok"], "categories": ["Marketing / Public Relations", "Management", "Marketing - Brand / Product Management", "Marketing - General / Support"], "post_time": "2022-01-11T04:38:34Z", "salary": {"currency": null, "max": null, "min": null, "period": "monthly", "term": null}, "salary_visible": false, "title_keywords": ["marketing manager"], "responsibilities": ["management", "seo", "visualization", "maintaining", "data", "assign tasks", "quality", "teams", "testing", "editing", "conceptualizing", "planning"], "requirements": {"degrees": ["degree", "bachelor"], "majors": [], "languages": ["english", "chinese", "mandarin"], "language_level": [], "hard_skills": ["seo", "web", "data visualization"], "soft_skills": ["fast-paced environment", "learning"], "languages_combined": [{"language": "english", "language_level": []}, {"language": "chinese", "language_level": []}, {"language": "mandarin", "language_level": []}]}, "experience_required": {"duration": ["at least 3 to 5 years"], "field": ["content writing", "management", "team"]}}, {"job_id": "100003009045809", "location_code": "hk", "company": "aimHigher Consultancy Limited", "job_title": "VP, Marketing Strategy & Planning", "description": "Duties\nHandle service inquiries raised by clients\nMaking outbound calls regarding our services\nProvide sales and administrative support\nEnlarge and extend potential market segments in a proactive approach\nRequirements\n\nDegree holder\u00a0\n2 years\u2019 relevant experience preferred, Fresh graduated also welcome\nExperience in customer service is an advantage\nSelf-motivated and service-oriented with good communication and interpersonal skills\nFluency in written and spoken Chinese\nBenefits\n\n\nAttractive remuneration package\u00a0will be offered to the right candidates\nHigh commission, monthly performance bonus, year-end performance bonus and pension benefits\nWell-structured training programs and comprehensive training platform\nClear career path and fast-track promotion to management level\nMedical benefits and training allowances", "employment_types": ["Full Time"], "selling_points": ["A well-regarded asset & wealth management group", "A strategic marketing planning & execution role", "Experience in financial industry is required"], "locations": ["Not Specified"], "categories": ["Banking / Finance", "Financial Services", "Marketing / Public Relations", "Management", "Marketing - Marketing Communication"], "post_time": "2022-01-13T08:46:18Z", "salary": {"currency": null, "max": null, "min": null, "period": "monthly", "term": null}, "salary_visible": false, "title_keywords": [], "responsibilities": ["administrative support"], "requirements": {"degrees": ["degree holder"], "majors": [], "languages": ["chinese"], "language_level": ["fluency"], "hard_skills": [], "soft_skills": ["self-motivated", "customer service", "communication and interpersonal skills", "service-oriented"], "languages_combined": [{"language": "chinese", "language_level": ["fluency"]}]}, "experience_required": {"duration": ["2 years"], "field": ["customer service", "relevant experience"]}}, {"job_id": "100003009039434", "location_code": "hk", "company": "Ambitious People Group", "job_title": "Digital Marketing Manager (Agency, MNC)", "description": "Responsibilities\nProvide oversight and management of the full spectrum of corporate marketing and public relations\nResponsible for effective implementation of marketing campaigns and communication in line with corporate direction\nDesign and develop marketing materials for brand communication through the multi-platform communication strategy\nManage communication and liaise with vendors and agencies to drive communication and marketing activities\nBuild brand awareness with public and targeted markets\nManage tracking & reporting for evaluation of marketing campaigns and its effectiveness\nLead the planning and implementation of public relations and initiatives related to corporate brand\nEstablish strong collaboration with Front Office to develop and execute marketing campaigns in achieving business goals\nRequirements\n\n\nBachelor degree in relevant disciplines\nDemonstrate a track record with at least 10 years\u2019 experience in marketing and public relations\nAbility to navigate matrix organization and strong stakeholder management skills\nAbility to think strategically and handle end-to-end execution\nPossess strong grasp of current digital marketing tools and strategies\nSolid background in a marketing role, familiar with managing agencies and internal partners\nIncumbent having a strong network of public relations and media contacts would be highly advantageous\n\nFor more details about career opportunities in KGI, please visit our website:\u00a0\nhttps://www.kgi.com.hk/Careers.aspx?sc_lang=en\n\nPlease send application with resume and expected salary quoting the job reference to the HR Department, 41/F, Central Plaza, 18 Harbour Road, Wanchai, Hong Kong.\n\n(Personal data collected will be used for recruitment purpose only.)\n\n\n", "employment_types": ["Full Time", "Permanent"], "selling_points": ["High base salary", "Dynamic working environment", "Career growth opportunities"], "locations": ["Not Specified"], "categories": ["Marketing / Public Relations", "Management", "Marketing - General / Support", "Digital Marketing"], "post_time": "2022-01-11T09:45:28Z", "salary": {"currency": null, "max": null, "min": null, "period": "monthly", "term": null}, "salary_visible": false, "title_keywords": ["digital marketing manager"], "responsibilities": ["reporting", "management", "business goals", "design and develop", "implementation", "develop", "communication", "liaise with", "planning", "marketing campaigns", "evaluation", "marketing materials", "tracking"], "requirements": {"degrees": ["degree", "bachelor"], "majors": [], "languages": [], "language_level": [], "hard_skills": ["harbour"], "soft_skills": ["think strategically"], "languages_combined": []}, "experience_required": {"duration": ["at least 10 years"], "field": ["public relations", "marketing"]}}, {"job_id": "100003009040764", "location_code": "hk", "company": "Elite Jobs", "job_title": "(Entry Level) Management Associate [5 Days Work, Bank Holiday]", "description": "At Sephora, we reimagine beauty, discover new brands, and influence positive change every day. We are seeking a dynamic and passionate Assistant CRM & Loyalty Manager to lead our loyalty program, Sephora Beauty Pass. Reporting to the Marketing Manager, he or she will be responsible for building a data-driven customer strategy to grow our active member base via retention, recruitment and reactivation as well as enhancing the engagement of the Sephora Beauty Pass loyalty. This is your opportunity to bring your passion, share your knowledge, and make your mark at a leading global beauty retailer.\nYou will shine here if you enjoy\u2026\n1.\u00a0Building and Growing the Loyalty Database.\nFull ownership of Sephora Hong Kong Beauty Pass Loyalty Program and the go-to person within the local market for understanding and engaging Hong Kong customers in a CRM perspective\nBuild lifecycle marketing journeys around key customer segments to grow, retain and activate all members as well as sustain and cultivate omni engagement\nWorking with and influencing the broader marketing team to ensure that campaign plans, content and segmentations are data-driven and aimed at achieving customer-centric results\nConduct ad-hoc analyses to shape local initiatives and enhance Hong Kong customer insights\nWork cross-functionally to ensure delivery of best-in-class loyalty experiences and rewards within Rewards Boutique for both in-store and across our online platforms\nIdentify gaps in our knowledge of the consumer, and hence drive research initiatives to ensure critical strategies can be delivered successfully\n2.\u00a0Supporting the Growth of the Brands with Recruitment.\nConduct quarterly or by campaign analyses on members\u2019 performances within brands to support brands performance\nWork closely with brand partners to create synergy on elevating brand performances within Sephora via partnered recruitment programs (i.e. cross database initiatives, paid media for new member recruiting)\n\n3. Technology and Data Driven.\u00a0\u00a0\nAdvocate within the local market team to drive adoption and evolution of automation and personalization across marketing channels from a technology aspect\nWork closely with regional teams and third parties to implement campaign communication blasts (eDM & SMS) as well as any technical updates\nWe would love to hear from you if\u2026\nYou have a Bachelor\u2019s Degree in Marketing or related studies\nYou have 7 to 8 years of working experience in managing CRM and loyalty program\nYou\u2019re proficient in SQL and relational database\nYou have working knowledge of digital marketing technologies \u2013 e.g. Salesforce Marketing Cloud is strongly favored\nYou have strong commercial acumen, preferably with retail and e-commerce experience\nYou\u2019re able to communicate complex ideas with clarity for stakeholders at all levels\nYou have strong presentation and consulting skills\n\nWhile at Sephora, you\u2019ll enjoy\u2026\n\nThe people. You will be surrounded by some of the most talented, supportive, and kind leaders and teams \u2013 people you can be proud to work with.\nThe learning. We invest heavily in training for our leaders and store associates. Not just product knowledge, but building a personalized career plan with you so you continue to evolve and build your skills.\nThe culture. As a leading beauty retailer, backed by the LVMH luxury brand, our reach is broad and our impact is global. Yet there\u2019s always room to explore. It\u2019s in our DNA to innovate and, at Sephora, all 40,000 passionate team members are united by a common goal - to reimagine the future of beauty. You can unleash your creativity, because we\u2019ve got disruptive spirit. You can learn and evolve, because we empower you to be your best. You can be yourself, because you are what sets us apart. This, is the future of beauty. Reimagine your future, at Sephora.", "employment_types": ["Full Time"], "selling_points": ["Five-day work week", "University degree in any discipline", "Attractive income, Sustainable career development"], "locations": ["Central & Western Area"], "categories": ["Banking / Finance", "Fund Management", "Marketing / Public Relations", "Management", "Others", "Student / Fresh Graduate / No Experience"], "post_time": "2022-01-12T03:02:04Z", "salary": {"currency": "HKD", "max": 24999, "min": 17000, "period": "monthly", "term": null}, "salary_visible": true, "title_keywords": ["management associate"], "responsibilities": ["ad-hoc", "reporting", "ideas", "consulting", "data", "edm", "customer insights", "teams", "communication", "recruitment", "digital marketing", "database", "plan", "plans"], "requirements": {"degrees": ["degree", "bachelor"], "majors": ["marketing"], "languages": [], "language_level": [], "hard_skills": ["salesforce", "e-commerce", "sql", "make", "goal", "dynamic", "go", "acumen"], "soft_skills": ["passionate", "supportive", "responsible", "presentation", "communication", "dynamic", "learning", "active", "driven", "positive"], "languages_combined": []}, "experience_required": {"duration": ["7 to 8 years"], "field": ["commercial", "retail", "e-commerce"]}}, {"job_id": "100003009035270", "location_code": "hk", "company": "T & Y Biologics Investment Limited", "job_title": "Marketing - Senior Officer/ Assistant Manager (Petmacy \u5bf5\u7269\u85e5\u599d)", "description": "What are you going to do as a Digital Marketing Manager?\n\nYou are going to work in a leading ad-tech MNC in Hong Kong. As a Digital Marketing Manager, you are responsible for managing Search Engine Marketing (SEM) projects including: client relations, performance analysis, campaign development, testing & reporting. You also need to analyze client websites and provide well-defined strategies to improve site performance and ROI. We expect a hands-on leader to grow the business.\n\nWhat is offered to you as a Digital Marketing Manager?\n\n* High base salary + attractive bonus\n* Career growth opportunity\n* Great job exposure\n\nWhat is expected of you?\n\n* Bachelor/ Master degree in Marketing, or related discipline;\n* 5+ years of experience in in Digital Marketing, preferably in agency background\n* In-depth knowledge of SEM, Google Ads\n* Passionate about the online marketing industry and willing to keep up with the latest Google and Social trends\n* Strong analytical skills and ability to draw conclusions and determine strategies based on data\n* China/ ecommerce exposure is a plus\n* Native English writing skills, fluent in English, Cantonese & Mandarin\n\nWhere are you going to work?\n\nYou will be working in a fast-paced environment with all brilliant, creative, and young talents from different cultural backgrounds. Apply now or directly send your resume to yuki.cheung@ambitiouspeople.com!", "employment_types": ["Full Time", "Permanent"], "selling_points": ["Lead a small team to provide management support", "Develop Promotion Calendar", "Create and support marketing campaigns"], "locations": ["Kwun Tong"], "categories": ["Marketing / Public Relations", "Management", "Marketing - General / Support", "Digital Marketing"], "post_time": "2022-01-10T06:34:54Z", "salary": {"currency": null, "max": null, "min": null, "period": "monthly", "term": null}, "salary_visible": false, "title_keywords": ["senior officer", "assistant manager"], "responsibilities": ["reporting", "data", "analysis", "testing", "digital marketing", "sem"], "requirements": {"degrees": ["bachelor", "master degree"], "majors": ["marketing"], "languages": ["cantonese", "english", "mandarin"], "language_level": ["native", "fluent"], "hard_skills": ["plus", "analysis", "writing skills", "analytical skills", "sem"], "soft_skills": ["responsible", "fast-paced environment", "writing skills", "analytical skills", "hands-on", "creative", "passionate about"], "languages_combined": [{"language": "cantonese", "language_level": ["native", "fluent"]}, {"language": "english", "language_level": ["native", "fluent"]}, {"language": "mandarin", "language_level": ["native", "fluent"]}]}, "experience_required": {"duration": ["5+ years"], "field": ["agency", "digital marketing"]}}, {"job_id": "100003009035127", "location_code": "hk", "company": "KPMG", "job_title": "Associate Director, Pursuit Leader", "description": "Our client is one of the most reputable developers who has an extensive real estate footprint in Hong Kong and China. They are now looking for a Senior Marketing Officer for their upcoming residential projects in Hong Kong.\u00a0\n\nResponsibilities:\n\nOversee the production of property sales brochure in compliance with the First-Hand Ordinance\nManage development/ production of sales and marketing materials including but not limited to sales office and show flat, advertising, promotional materials, sales materials and arrangements are in compliance with the related legislations and regulations\nCopy writing, PR writing, social media management, marketing collateral production\nConduct market research and analysis on the market trend of the residential market\nResponsible for the branding, PR, corporate communications of the company, in order to build a good corporate image of the group\u00a0\n\nRequirements:\n\nDegree in Journalism, PR, Communications, Marketing or related disciplines\nMinimum 3 years of solid experience in residential sales and marketing\nExcellent writing and editing skills in English and Chinese\nAttention to details, especially in editing and proofreading\nExperienced in brand design and development especially in corporate branding / multi brand handling\nProactive, energetic, and excellent people communications skills", "employment_types": ["Full Time"], "selling_points": ["Marketing", "Pursuit", "Competitor Analysis"], "locations": ["Aberdeen"], "categories": ["Marketing / Public Relations", "Management"], "post_time": "2022-01-10T06:06:19Z", "salary": {"currency": null, "max": null, "min": null, "period": "monthly", "term": null}, "salary_visible": false, "title_keywords": ["associate director"], "responsibilities": ["regulations", "social media", "management", "advertising", "conduct market research", "compliance", "analysis", "promotional materials", "marketing materials", "legislations"], "requirements": {"degrees": ["degree"], "majors": ["journalism", "related disciplines", "marketing", "communications"], "languages": ["english", "chinese"], "language_level": ["excellent"], "hard_skills": [], "soft_skills": ["energetic", "proactive", "attention to details"], "languages_combined": [{"language": "english", "language_level": ["excellent"]}, {"language": "chinese", "language_level": ["excellent"]}]}, "experience_required": {"duration": ["minimum 3 years"], "field": ["marketing"]}}]